Workbook
Name \: #REF!
Name \0: #REF!
Name \a: #N/A
Name \a: #N/A
Name \a: #REF!
Name \b: #REF!
Name \c: #REF!
Name \E: #REF!
Name \F: #REF!
Name \G: #REF!
Name \i: #REF!
Name \III_1: '[1]Back-up'!$A$1:$Q$37
Name \III_1: #REF!
Name \III_2: '[1]Back-up'!#REF!
Name \III_2: #REF!
Name \III_3: '[1]Back-up'!#REF!
Name \III_3: #REF!
Name \III_4: '[1]Back-up'!#REF!
Name \III_4: #REF!
Name \III_5: '[1]Back-up'!#REF!
Name \III_5: #REF!
Name \III_6: #REF!
Name \m: #REF!
Name \P: #REF!
Name \page1: #REF!
Name \page2: #REF!
Name \page3: #REF!
Name \page4: #REF!
Name \page5: #REF!
Name \page6: #REF!
Name \page7: #REF!
Name \page8: #REF!
Name \page9: #REF!
Name \pages10: #REF!
Name \pages11: #REF!
Name \S: #REF!
Name \T: #REF!
Name \W: #REF!
Name \z: #REF!
Name _: #REF!
Name __________________Act6: [2]Parameters!#REF!
Name __________________Act6: #REF!
Name __________________DAT10: '[3]Target Book'!#REF!
Name __________________DAT10: #REF!
Name __________________DAT11: '[3]Target Book'!#REF!
Name __________________DAT11: #REF!
Name __________________DAT12: '[3]Target Book'!#REF!
Name __________________DAT12: #REF!
Name __________________DAT13: '[3]Target Book'!#REF!
Name __________________DAT13: #REF!
Name __________________DAT14: '[3]Target Book'!#REF!
Name __________________DAT14: #REF!
Name __________________DAT15: '[3]Target Book'!#REF!
Name __________________DAT15: #REF!
Name __________________DAT16: '[3]Target Book'!#REF!
Name __________________DAT16: #REF!
Name __________________DAT17: '[3]Target Book'!#REF!
Name __________________DAT17: #REF!
Name __________________DAT18: '[3]Target Book'!#REF!
Name __________________DAT18: #REF!

Sheet Base Listas
A1: Resin Index | B1: Material | C1: Plant Name | D1: Plants | E1: Cost Centre
A2: Indexador de Resina | B2: Fornecedor | C2: Resina | D2: Planta | E2: Centro | G2: Incoterm | K2: 45658
A3: ICIS China mid (M-1) | B3: ALPEK | C3: Manaus | D3: MANAUS | E3: 4151 | F3: SPOT | G3: CIF | K3: 45689 | M3: SET'25
A4: ICIS China low | B4: INDORAMA | C4: Manaus - Gatorade | D4: MANAUS FORA | E4: 4151 | F4: CONTRATO | G4: FOB | K4: 45717 | M4: DEZ'25
A5: IHS no Coke | B5: CPR | C5: Manaus (ABI) | D5: SUAPE | E5: 4196 | K5: 45748 | M5: JAN'26
A6: ICIS 5 REGIONS | B6: VG | C6: Suape | D6: LOUVEIRA | E6: 4185 | K6: 45778
A7: ICIS 3 REGIONS | C7: Suape - Gatorade | D7: VESPASIANO | E7: 4188 | K7: 45809
A8: MAXIQUIM MIN | C8: Suape (ABI) | D8: LINDÓIA | E8: 418A | K8: 45839
A9: MAXIQUIM MAX | C9: Suape (Especial SUL) | K9: 45870
A10: MAXIQUIM MED | C10: Lindóia | K10: 45901
C11: Louveira | K11: 45931
C12: Vespasiano | K12: 45962
K13: 45992
K14: 46023
K15: 46054
K16: 46082
K17: 46113
K18: 46143
K19: 46174
K20: 46204
K21: 46235
K22: 46266
K23: 46296
K24: 46327
... K62: 47484

Sheet  Amcor  - Brazil  
I3: Queries
I4: Multiple categories on Column B and Column C ,
E5: File Name : | F5: 04. Amcor.xlsx | I5: what are those ?
E6: Sheet name | F6: Resina | I6: In which combinaton of Country x Supplier --- this will fall under ?
S7: Need more help understanding the below | AD7: For a specific , Supplier + Resin Type + Index , what would be the TLC ? | AL7: Actual formuale as per the Excel for Brazil and Amcor ?
AD8: Scenario 1
S9: 1. In the Resina , Core Pricing sheet we try to find for combination of Product/Supplier/ Plants / Market Index to calculate the final price | U9: Our traditional CIF formulae works , but has a lot of combinations , across supplires , plants | AA9: which Resin Index to use ?
S10: 2. Resin sheet is used to calculate the Total Landing Cost for Different Types of Resins , Suppliers and Resin Indexes
S11: 3. Formulae mismtach between , what is there in the Resina sheet and what detailed in the formulae ?
S12: 3. Pricing sheets are calculated at specific granularity in the Monthly sheets like "MAR'26 , APR'26 , at specific stages like "Preforma / Garraga"
S13: 4. How are the other sheets used in the calculation ? How is this sheet used in the calculation ? | V13: Monthly sheet calculation
S14: Indexadores | AQ14: Index | AR14: 1111.25
S15: BD Conv | AQ15: Freight | AR15: 124.22
S16: Carga | AQ16: Duties | AR16: 257
S17: Check | AQ17: Others | AR17: 167
R18: 5 | S18: 5.which Specific combination we need to consider ? | AQ18: TLC | AR18: =SUM(AR14:AR17) -> 1659.47
S19: 6. what is the link between Resina sheet and MAR'26 sheet ?

Sheet Resina
B2: AVISO! | E2: 45839 | F2: 45870 | G2: 45901 | H2: 45931 | I2: 45962 | J2: 45992 | K2: 46023 | L2: 46054 | M2: 46082 | N2: 46113 | O2: =EDATE(N2,1) -> 46143
D3: P-TAX | E3: 5.547055 | F3: 5.5284913 | G3: 5.4469238 | H3: 5.3674091 | I3: 5.3855261 | J3: 5.3408526 | K3: 5.4530909 | L3: 5.3380238 | M3: 5.2006167 | N3: 5.2315864 | O3: =_xlfn.XLOOKUP(EDATE(O2,-1),'[444]P-TAX Diária'!$1:$1,'[444]P-TAX Diária'!$35:$35,0) -> 0
C5: SUAPE | E5: 45839 | F5: 45870 | G5: 45901 | H5: 45931 | I5: 45962 | J5: 45992 | K5: 46023 | L5: 46054 | M5: 46082 | N5: 46113 | O5: =EDATE(N5,1) -> 46143
B6: ALPEK | C6: Suape | D6: ICIS China mid (M-1) | E6: 793.125 | F6: 781.875 | G6: 774 | H6: 765 | I6: 752 | J6: 748.75 | K6: 756.25 | L6: 818.125 | M6: 838.13 | N6: 1111.25 | O6: =IFERROR(INDEX([444]RESINA!$A$2:$AZ$500, MATCH(EDATE(O5,-1),[444]RESINA!$A$2:$A$500,0), MATCH($D$6,[444]RESINA!$A$2:$AZ$2,0)),"-") -> 0
D7: International freight | E7: 206.62222 | F7: =F11/22.5 -> 288.8 | G7: =G11/22.5 -> 165.15556 | H7: =H11/22.5 -> 148.35556 | I7: =I11/22.5 -> 117.95556 | J7: =J11/22.5 -> 88.844444 | K7: =K11/22.5 -> 75.511111 | L7: =L11/22.5 -> 65.466667 | M7: =M11/22.5 -> 66.044444 | ... O7: =O11/22.5 -> 0
D8: Local freight
D9: Duties | E9: 207.94742 | F9: =SUM(F6:F7)*20.8% -> 222.7004 | G9: =SUM(G6:G7)*20.8% -> 195.34436 | H9: =SUM(H6:H7)*20.8% -> 189.97796 | I9: =SUM(I6:I7)*20.8% -> 180.95076 | J9: =SUM(J6:J7)*20.8% -> 174.21964 | K9: =SUM(K6:K7)*20.8% -> 173.00631 | L9: =SUM(L6:L7)*20.8% -> 183.78707 | M9: =SUM(M6:M7)*20.8% -> 188.06828 | ... O9: =SUM(O6:O7)*20.8% -> 0
D10: Others | E10: 167 | F10: =90+77 -> 167 | G10: =90+77 -> 167 | H10: =90+77 -> 167 | I10: =90+77 -> 167 | J10: =90+77 -> 167 | K10: =90+77 -> 167 | L10: =90+77 -> 167 | M10: =90+77 -> 167 | ... O10: =90+77 -> 167
D11: Drewry | E11: 4649 | F11: 6498 | G11: 3716 | H11: 3338 | I11: 2654 | J11: 1999 | K11: 1699 | L11: 1473 | M11: 1486 | N11: 2795 | O11: =_xlfn.XLOOKUP(EDATE(O5,-1),[444]RESINA!$A:$A,[444]RESINA!$B:$B,0) -> 0
A12: =_xlfn.CONCAT(C5,B6,D12) -> SUAPEALPEKSell Side Resina USD | D12: Sell Side Resina USD | E12: 1374.6946 | F12: =SUM(F6:F10) -> 1460.3754 | G12: =SUM(G6:G10) -> 1301.4999 | H12: =SUM(H6:H10) -> 1270.3335 | I12: =SUM(I6:I10) -> 1217.9063 | J12: =SUM(J6:J10) -> 1178.8141 | K12: =SUM(K6:K10) -> 1171.7674 | L12: =SUM(L6:L10) -> 1234.3787 | M12: =SUM(M6:M10) -> 1259.2427 | ... O12: =SUM(O6:O10) -> 167
A13: =_xlfn.CONCAT(C5,B6,D13) -> SUAPEALPEKBuy Side Resina USD | C13: Suape (ABI) | D13: Buy Side Resina USD | E13: 1266.8968 | F13: 1254.2197 | G13: 1269.5954 | H13: 1232.4699 | I13: 1155.6782 | J13: 1122.0245 | K13: 1088.7028 | L13: 1129.2609 | M13: 1157.6381 | N13: 1515.5363 | O13: =IFERROR(INDEX([444]RATIONAL!$C$72:$DS$197, MATCH(EDATE(O5,-1),[444]RATIONAL!$B$72:$B$197,0), MATCH(_xlfn.CONCAT($B$6,$C$13),[444]RATIONAL!$C$1:$DS$1,0)),"-") -> -
N14: =N12/[445]Resina!$N$12-1 -> -0.081412682
C16: SUAPE | E16: 45839 | F16: 45870 | G16: 45901 | H16: 45931 | I16: 45962 | J16: 45992 | K16: 46023 | L16: 46054 | M16: 46082 | N16: 46113 | O16: =EDATE(N16,1) -> 46143
B17: VG | C17: Suape | D17: MAXIQUIM MED | E17: 4400 | F17: 4450 | G17: 4400 | H17: 4450 | I17: 4300 | J17: 4100 | K17: 3700 | L17: 3100 | M17: 3400 | N17: =IFERROR(INDEX([444]RESINA!$A$2:$AZ$500, MATCH(N16,[444]RESINA!$A$2:$A$500,0), MATCH($D$41,[444]RESINA!$A$2:$AZ$2,0)),"-") -> 0 | O17: =IFERROR(INDEX([444]RESINA!$A$2:$AZ$500, MATCH(O16,[444]RESINA!$A$2:$A$500,0), MATCH($D$41,[444]RESINA!$A$2:$AZ$2,0)),"-") -> 0
D19: Maxiquim SE Med (M-2/3/4) | I19: =AVERAGE(E17:G17)/70% -> 6309.5238 | J19: =AVERAGE(F17:H17)/70% -> 6333.3333 | K19: =AVERAGE(G17:I17)/70% -> 6261.9048 | L19: =AVERAGE(H17:J17)/70% -> 6119.0476 | M19: =AVERAGE(I17:K17)/70% -> 5761.9048 | N19: =AVERAGE(J17:L17)/70% -> 5190.4762 | O19: =AVERAGE(K17:M17)/70% -> 4857.1429
D20: Local freight | I20: 590 | J20: 590 | K20: 590 | L20: 590 | M20: 590 | N20: 590 | O20: 590
D21: Fixed cost BRL/Ton | I21: 2390 | J21: 2390 | K21: 2390 | L21: 2390 | M21: 2390 | N21: 2390 | O21: 2390
D22: Discount | I22: -538.8 | J22: -538.8 | K22: -538.8 | L22: -538.8 | M22: -538.8 | N22: -538.8 | O22: -538.8
D23: Adder | I23: 386.5 | J23: 386.5 | K23: 386.5 | L23: 386.5 | M23: 386.5 | N23: 386.5 | O23: 386.5
A25: =_xlfn.CONCAT(C16,B17,D25) -> SUAPEVGSell Side Resina USD | D25: Sell Side Resina USD | I25: =SUM(I19:I23)/I3 -> 1696.626 | J25: =SUM(J19:J23)/J3 -> 1715.2754 | K25: =SUM(K19:K23)/K3 -> 1666.872 | L25: =SUM(L19:L23)/L3 -> 1676.0412 | M25: =SUM(M19:M23)/M3 -> 1651.6512 | N25: =SUM(N19:N23)/N3 -> 1532.6472 | O25: =SUM(O19:O23)/O3 -> #DIV/0!
A26: =_xlfn.CONCAT(C16,B17,D26) -> SUAPEVGBuy Side Resina USD | C26: Suape | D26: Buy Side Resina USD | I26: 1740.412 | J26: 1768.3437 | K26: 1692.6505 | L26: 1675.6131 | M26: 1610.0071 | N26: 1436.6372 | O26: =(_xlfn.XLOOKUP(EDATE(O16,-2),'[444]RATIONAL PCR'!$B:$B,'[444]RATIONAL PCR'!$I:$I,0)+587.32)/O3 -> #DIV/0!
C29: MANAUS | E29: 45839 | F29: 45870 | G29: 45901 | H29: 45931 | I29: 45962 | J29: 45992 | K29: 46023 | L29: 46054 | M29: 46082 | N29: 46113 | O29: =EDATE(N29,1) -> 46143
B30: ALPEK | C30: Manaus | D30: ICIS China mid (M-1) | E30: 793.125 | F30: 781.875 | G30: 774 | H30: 765 | I30: 752 | J30: 748.75 | K30: 756.25 | L30: 818.125 | M30: 838.13 | N30: 1111.25 | O30: =IFERROR(INDEX([444]RESINA!$A$2:$AZ$500, MATCH(EDATE(O29,-1),[444]RESINA!$A$2:$A$500,0), MATCH($D$30,[444]RESINA!$A$2:$AZ$2,0)),"-") -> 0
D31: International freight | E31: 226.62222 | F31: =F35/22.5+20 -> 308.8 | G31: =G35/22.5+20 -> 185.15556 | H31: =H35/22.5+20 -> 168.35556 | I31: =I35/22.5+20 -> 137.95556 | J31: =J35/22.5+20 -> 108.84444 | K31: =K35/22.5+20 -> 95.511111 | L31: =L35/22.5+20 -> 85.466667 | M31: =M35/22.5+20 -> 86.044444 | ... O31: =O35/22.5+20 -> 20
D32: Local freight
D33: Duties | E33: 212.10742 | F33: =SUM(F30:F31)*20.8% -> 226.8604 | G33: =SUM(G30:G31)*20.8% -> 199.50436 | H33: =SUM(H30:H31)*20.8% -> 194.13796 | I33: =SUM(I30:I31)*20.8% -> 185.11076 | J33: =SUM(J30:J31)*20.8% -> 178.37964 | K33: =SUM(K30:K31)*20.8% -> 177.16631 | L33: =SUM(L30:L31)*20.8% -> 187.94707 | M33: =SUM(M30:M31)*20.8% -> 192.22828 | ... O33: =SUM(O30:O31)*20.8% -> 4.16
D34: Seguro | E34: 167 | F34: =90+77 -> 167 | G34: =90+77 -> 167 | H34: =90+77 -> 167 | I34: =90+77 -> 167 | J34: =90+77 -> 167 | K34: =90+77 -> 167 | L34: =90+77 -> 167 | M34: =90+77 -> 167 | ... O34: =90+77 -> 167
D35: Drewry | E35: 4649 | F35: 6498 | G35: 3716 | H35: 3338 | I35: 2654 | J35: 1999 | K35: 1699 | L35: 1473 | M35: 1486 | N35: 2795 | O35: =_xlfn.XLOOKUP(EDATE(O29,-1),[444]RESINA!$A:$A,[444]RESINA!$B:$B,0) -> 0
A36: =_xlfn.CONCAT(C29,B30,D36) -> MANAUSALPEKSell Side Resina USD | D36: Sell Side Resina USD | E36: 1398.8546 | F36: =SUM(F30:F34) -> 1484.5354 | G36: =SUM(G30:G34) -> 1325.6599 | H36: =SUM(H30:H34) -> 1294.4935 | I36: =SUM(I30:I34) -> 1242.0663 | J36: =SUM(J30:J34) -> 1202.9741 | K36: =SUM(K30:K34) -> 1195.9274 | L36: =SUM(L30:L34) -> 1258.5387 | M36: =SUM(M30:M34) -> 1283.4027 | ... O36: =SUM(O30:O34) -> 191.16
A37: =_xlfn.CONCAT(C29,B30,D37) -> MANAUSALPEKBuy Side Resina USD | C37: Manaus (ABI) | D37: Buy Side Resina USD | E37: 1325.8207 | F37: 1312.653 | G37: 1323.6237 | H37: 1290.0616 | I37: 1210.1052 | J37: 1175.1493 | K37: 1140.5383 | L37: 1182.6657 | M37: 1212.1409 | N37: 1583.8873 | O37: =IFERROR(INDEX([444]RATIONAL!$C$72:$DS$197, MATCH(EDATE(O29,-1),[444]RATIONAL!$B$72:$B$197,0), MATCH(_xlfn.CONCAT($B$30,$C$37),[444]RATIONAL!$C$1:$DS$1,0)),"-") -> -
N38: =N36/[445]Resina!$N$35-1 -> -0.080338258
C40: MANAUS | E40: 45839 | F40: 45870 | G40: 45901 | H40: 45931 | I40: 45962 | J40: 45992 | K40: 46023 | L40: 46054 | M40: 46082 | N40: 46113 | O40: =EDATE(N40,1) -> 46143
B41: VG | C41: Manaus | D41: MAXIQUIM MED | E41: 4400 | F41: 4450 | G41: 4400 | H41: 4450 | I41: 4300 | J41: 4100 | K41: 3700 | L41: 3100 | M41: 3400 | N41: =IFERROR(INDEX([444]RESINA!$A$2:$AZ$500, MATCH(N40,[444]RESINA!$A$2:$A$500,0), MATCH($D$41,[444]RESINA!$A$2:$AZ$2,0)),"-") -> 0 | O41: =IFERROR(INDEX([444]RESINA!$A$2:$AZ$500, MATCH(O40,[444]RESINA!$A$2:$A$500,0), MATCH($D$41,[444]RESINA!$A$2:$AZ$2,0)),"-") -> 0
D42: Maxiquim SE Med (M-2/3/4) | I42: =AVERAGE(E41:G41)/70% -> 6309.5238 | J42: =AVERAGE(F41:H41)/70% -> 6333.3333 | K42: =AVERAGE(G41:I41)/70% -> 6261.9048 | L42: =AVERAGE(H41:J41)/70% -> 6119.0476 | M42: =AVERAGE(I41:K41)/70% -> 5761.9048 | N42: =AVERAGE(J41:L41)/70% -> 5190.4762 | O42: =AVERAGE(K41:M41)/70% -> 4857.1429
D43: Local freight | I43: 950 | J43: 950 | K43: 950 | L43: 950 | M43: 950 | N43: 950 | O43: 950
D44: Fixed cost BRL/Ton | I44: 2390 | J44: 2390 | K44: 2390 | L44: 2390 | M44: 2390 | N44: 2390 | O44: 2390
D45: Discount | I45: -538.8 | J45: -538.8 | K45: -538.8 | L45: -538.8 | M45: -538.8 | N45: -538.8 | O45: -538.8
D46: Adder | I46: 386.5 | J46: 386.5 | K46: 386.5 | L46: 386.5 | M46: 386.5 | N46: 386.5 | O46: 386.5
D47: Drewry | I47: 2654 | J47: 1999 | K47: 1699 | L47: 1473 | M47: 1486 | N47: 2795 | O47: =_xlfn.XLOOKUP(EDATE(O40,-1),[444]RESINA!$A:$A,[444]RESINA!$B:$B,0) -> 0
A48: =_xlfn.CONCAT(C40,B41,D48) -> MANAUSVGSell Side Resina USD | D48: Sell Side Resina USD | I48: =SUM(I42:I46)/I3 -> 1763.4719 | J48: =SUM(J42:J46)/J3 -> 1782.6804 | K48: =SUM(K42:K46)/K3 -> 1732.8896 | L48: =SUM(L42:L46)/L3 -> 1743.4818 | M48: =SUM(M42:M46)/M3 -> 1720.8738 | N48: =SUM(N42:N46)/N3 -> 1601.46 | O48: =SUM(O42:O46)/O3 -> #DIV/0!
A49: =_xlfn.CONCAT(C40,B41,D49) -> MANAUSVGBuy Side Resina USD | C49: Manaus | D49: Buy Side Resina USD | I49: 1800.9457 | J49: 1820.6672 | K49: 1769.5081 | L49: 1779.6914 | M49: 1754.965 | N49: 1630.4587 | O49: =(_xlfn.XLOOKUP(EDATE(O40,-2),'[444]RATIONAL PCR'!$B:$B,'[444]RATIONAL PCR'!$E:$E,0)+717)/O3 -> #DIV/0!

Sheet MAR'26
AH1: ZBRP | AJ1: ZBSR | AK1: ZBFS | AL1: ZBCP | AN1: ZBSR | AO1: ZBUT | AP1: ZBLA | AQ1: ZBTMx | AR1: ZBTMx | AT1: ZBSR | AU1: ZBTMx | AW1: ZBOP | AX1: ZBFC | AY1: ZBPP | BA1: ZBCTx | BB1: ZBUB | BC1: ZBLL | BD1: ZBCTx | BE1: ZBCTx | BF1: ZBCTx | BH1: ZBSB | BJ1: ZBLB | BK1: ZBLB | BM1: ZBSB | BN1: ZBOB | BO1: ZBFB | BP1: ZBPB | BR1: ZBOP | DE1: CARGA | DH1: 1 | DI1: 2 | DJ1: 3 | DK1: 4 | DL1: 5 | DM1: 6 | DN1: 7 | DO1: 8 | DP1: 9 | DQ1: 10 | DR1: 11 | DS1: 12 | DT1: 13 | DU1: 14 | DV1: 15 | DW1: 16 | DX1: 17 | DY1: 18 | DZ1: 19 | EA1: 20 | EB1: 21 | EC1: 22 | ED1: 23 | EE1: 24
H3: 46082 | AK3: PREFORMA | BA3: GARRAFA | BR3: 0 | BY3: ANÁLISE | CD3: PREÇO BASE | CI3: Custo
C4: Cost Centre | D4: Plants | F4: Client | H4: Incoterm | K4: Material Description | L4: Weight | M4: Additive | W4: % Viring | Z4: Recycled Resin | AF4: Sales Unit | AG4: Fx Rate | AS4: Preform (intermediate product) | BG4: Bottle (final product) | BQ4: Bottle Price | BT4: Net Price (BRL per 1000 units) | BW4: Change vs Last Price
B5: Centro Preforma | C5: Centro | D5: Planta | E5: Cód. Cliente | F5: Descrição Cliente | G5: Grupo | H5: Incoterm | I5: Localização Cliente | J5: Cód. Produto | K5: Descrição do Material | L5: Peso (g) | M5: Aditivo 1 | N5: % Aditivo 1 | O5: Custo Aditivo 1 BRL | P5: Aditivo 2 | Q5: % Aditivo 2 | R5: Custo Aditivo 2 BRL | S5: Aditivo 3 | T5: % Aditivo 3 | U5: Custo Aditivo 3 BRL | V5: Tipo de Resina | W5: % Virgem | X5: Fornecedor | Y5: Sell Side Resina USD | Z5: % PCR | AA5: Fornecedor | AB5: Sell Side Resina USD | AC5: Início da validade | AD5: Atualização Resina | AE5: Atualização Indexadores | AF5: Unidade de Venda | AG5: P-TAX AVG m-1 | AH5: Total Resina (BRL p/ mil) | AI5: Scrap % | AJ5: Scrap (BRL) | AK5: Repasse Tributação | AL5: Aditivo (BRL) | AM5: Scrap % | AN5: Scrap (BRL) | AO5: Energia Elétrica (BRL) | AP5: Mão-de-obra (BRL) | AQ5: Manutenção USD | AR5: Manutenção (BRL) | AS5: Scrap % | AT5: Scrap (BRL) | AU5: Outros Custos (BRL) | AV5: Total Conversão (BRL p/000) | AW5: Amortização (BRL) | AX5: Freight BRL | AY5: Packaging BRL | AZ5: Preço Preforma | BA5: Conversão (BRL) | BB5: Energia Elétrica (BRL) | BC5: Mão-de-obra (BRL) | BD5: Manutenção USD | BE5: Manutenção (BRL) | BF5: Outros Custos (BRL) | BG5: Scrap % | BH5: Scrap (BRL) | BI5: Total Conversão (BRL p/000) | BJ5: Rótulo (BRL) | BK5: Colocação Rótulo (BRL) | BL5: Scrap % | BM5: Scrap (BRL) | BN5: Amortização (BRL) | BO5: Freight (BRL) | BP5: Packaging (BRL) | BQ5: Preço Frasco | BR5: Desconto | BT5: Preço Líquido BRL/000 | BU5: 9,25% PIS COFINS + 12% ICMS | BV5: Preço com Impostos BRL /000 | BW5: Variação Last Price | BY5: EBIT SEM SG&A(%) | BZ5: EBIT SEM SG&A(USD) | CA5: MARGEM DE CONTRIBUIÇÃO (USD) | CB5: MOR (USD) | CD5: 0.1 | CE5: EBIT SEM SG&A(USD) | CF5: MARGEM DE CONTRIBUIÇÃO (USD) | CG5: MOR (USD) | CI5: Buy Side Resina USD | CJ5: Buy Side Resina USD | CK5: Total Resina (BRL p/ mil) | CL5: Scrap (BRL) | CM5: Crédito ICMS | CN5: CTP | CO5: Packaging + Freight + Pigmento | CP5: Total | CQ5: Variable Costs CTP | DG5: ZBRP | DH5: ZBSR | DI5: ZBSB | DJ5: ZBCP | DK5: ZBFP | DL5: ZBFC | DM5: ZBFB | DN5: ZBTMx | DO5: ZBCTx | DP5: ZBLB | DQ5: ZBMR | DR5: ZBML | DS5: ZBPP | DT5: ZBPB | DU5: ZBOP | DV5: ZBOB | DW5: ZBSG | DX5: ZBFS | DY5: ZBUT | DZ5: ZBUB | EA5: ZBLA | EB5: ZBLL | EC5: ZBPE | ED5: ZBPL | EE5: Total | EF5: Corrigir | EG5: ZBTM | EH5: ZBCT | EI5: Total
AO6: Energy | AP6: Labor | AU6: IPCA | BB6: Energy | BC6: Labor | BF6: IPCA | BO6: IGPM | BP6: IGPM | CL6: 0.01
A7: =_xlfn.CONCAT(D7,L7) -> Louveira25.5 | B7: 4151 | C7: 4185 | D7: Louveira | F7: AMBEV | G7: CONTRATO | H7: FOB | K7: F,500ML,GATORADE,CR | L7: 25.5 | M7: CR | V7: Virgem | W7: 1 | X7: ALPEK | Y7: =IF($X7="",0,HLOOKUP($H$3,Resina!$E$2:$AK$93,MATCH("MANAUS"&$X7&$Y$5,Resina!$A$2:$A$93,0))) -> 1283.4027 | Z7: 0 | AB7: =IF($AA7="",0,HLOOKUP($H$3,Resina!$E$2:$AK$93,MATCH("MANAUS"&$AA7&$AB$5,Resina!$A$2:$A$93,0))) -> 0 | AC7: 46091 | AD7: Mensal | AE7: 45839 | AF7: MIL | AG7: =_xlfn.XLOOKUP($H$3,Resina!$2:$2,Resina!$3:$3,0) -> 5.2006167 | AH7: =(L7*((Y7*W7)+(AB7*Z7)))*AG7/1000 -> 170.19938 | AI7: 0.005 | AJ7: =AH7*AI7 -> 0.85099692 | AO7: =_xlfn.XLOOKUP($D7&$L7&$AK$3,'BD Conv'!$A:$A,'BD Conv'!$H:$H,0)*_xlfn.XLOOKUP($D7,'BD Conv'!$C$17:$C$19,'BD Conv'!$F$17:$F$19,0)*(1+(HLOOKUP($B7&AO$6,Indexadores!$C$2:$AH$32,MATCH($AE7,Indexadores!$A$2:$A$32,0)))) -> 0 | AS7: 0.005 | AT7: =(AU7+AO7)*AS7 -> 0 | AU7: =_xlfn.XLOOKUP($D7&$L7&$AK$3,'BD Conv'!$A:$A,'BD Conv'!$H:$H,0)*_xlfn.XLOOKUP($D7,'BD Conv'!$C$17:$C$19,'BD Conv'!$E$17:$E$19,0)*(1+(HLOOKUP($B7&AU$6,Indexadores!$C$2:$AH$32,MATCH($AE7,Indexadores!$A$2:$A$32,0)))) -> 0 | AV7: =SUM(AN7,AO7,AP7,(AQ7*AG7),AR7,AT7,AU7) -> 0 | AW7: =_xlfn.XLOOKUP($A7&$AK$3,'BD Conv'!$A:$A,'BD Conv'!$I:$I,0) -> 0 | AZ7: =SUM(AH7,AJ7,AK7,AL7,AV7,AW7:AY7) -> 171.05038 | BB7: =_xlfn.XLOOKUP($D7&$L7&$BA$3,'BD Conv'!$A:$A,'BD Conv'!$J:$J,0)*_xlfn.XLOOKUP($D7,'BD Conv'!$C$17:$C$19,'BD Conv'!$F$17:$F$19,0)*(1+(HLOOKUP($C7&BB$6,Indexadores!$C$2:$AH$32,MATCH($AE7,Indexadores!$A$2:$A$32,0)))) -> 0 | BF7: =_xlfn.XLOOKUP($D7&$L7&$BA$3,'BD Conv'!$A:$A,'BD Conv'!$J:$J,0)*_xlfn.XLOOKUP($D7,'BD Conv'!$C$17:$C$19,'BD Conv'!$E$17:$E$19,0)*(1+(HLOOKUP($C7&BF$6,Indexadores!$C$2:$AH$32,MATCH($AE7,Indexadores!$A$2:$A$32,0)))) -> 0 | BG7: 0.01 | BH7: =(AZ7+BB7+BF7)*BG7 -> 1.7105038 | BI7: =SUM(BA7,BB7,BC7,(BD7*AG7),BE7,BF7,BH7) -> 1.7105038 | BN7: =_xlfn.XLOOKUP($A7&$BA$3,'BD Conv'!$A:$A,'BD Conv'!$K:$K,0) -> 0 | BQ7: =SUM(BI7,BJ7,BK7,BM7,BN7,BO7,BP7) -> 1.7105038 | BR7: =-BQ7*$BR$3 -> 0 | BT7: =AZ7+BQ7+BR7+BS7 -> 172.76088 | BU7: =BV7-BT7 -> 43.568798 | BV7: =BT7/(1-(12%+1.65%+7.6%) +12%*(1.65%+7.6%)) -> 216.32968 | BY7: =BT7/CP7-1 -> 0.064083962 | BZ7: =(BT7-CP7)/AG7 -> 2.0006173 | CA7: =(BT7-CK7-CL7-AL7-AX7-AY7-BO7-BP7+CQ7)/AG7 -> 2.0006173 | CB7: =(BT7-AH7)/AG7 -> 0.49253788 | CD7: =CP7*(1+$CD$5) -> 178.59208 | CE7: =(CD7-CP7)/AG7 -> 3.121869 | CF7: =(CD7-CK7-CL7-AL7-AX7-AY7-BO7-BP7+CQ7)/AG7 -> 3.121869 | CG7: =(CD7-AH7)/AG7 -> 1.6137895 | CI7: =IF($X7="",0,HLOOKUP($H$3,Resina!$E$2:$AK$93,MATCH("MANAUS"&$X7&$CI$5,Resina!$A$2:$A$93,0))) -> 1212.1409 | CJ7: =IF($AA7="",0,HLOOKUP($H$3,Resina!$E$2:$AK$93,MATCH("MANAUS"&$AA7&$CJ$5,Resina!$A$2:$A$93,0))) -> 0 | CK7: =L7*((CI7*W7)+(CJ7*Z7))*AG7/1000 -> 160.74895 | CL7: =CK7*$CL$6 -> 1.6074895 | CM7: =IF(D7="Manaus FORA",-((CK7/0.88*0.12)*(1-9.25%))," ") | CO7: =AX7+AY7+BO7+BP7+AL7+AN7+BJ7+BK7+BM7 -> 0 | CP7: =SUM(CK7:CO7) -> 162.35644 | DE7: =_xlfn.CONCAT(D7,L7) -> Louveira25.5 | DF7: =L7 -> 25.5 | DG7: =ROUND(SUMIF($1:$1,DG$5,7:7),2) -> 170.2 | DH7: =ROUND(SUMIF($1:$1,DH$5,7:7),2) -> 0.85 | DI7: =ROUND(SUMIF($1:$1,DI$5,7:7),2) -> 1.71 | DJ7: =ROUND(SUMIF($1:$1,DJ$5,7:7),2) -> 0 | DK7: =ROUND(SUMIF($1:$1,DK$5,7:7),2) -> 0 | DL7: =ROUND(SUMIF($1:$1,DL$5,7:7),2) -> 0 | DM7: =ROUND(SUMIF($1:$1,DM$5,7:7),2) -> 0 | DN7: =ROUND(SUMIF($1:$1,DN$5,7:7),2) -> 0 | ... ED7: =ROUND(SUMIF($1:$1,ED$5,7:7),2) -> 0 | EE7: =SUM(DG7:ED7) -> 172.76 | EF7: =ROUND(SUM(EE7-BT7),2) -> 0 | EG7: =IF(DN7<>0,DN7-EF7,0) -> 0 | EH7: =IF(EG7=0,DO7-EF7,DO7) -> 0 | EI7: =SUM(DG7:DM7)+SUM(DP7:ED7)+EG7+EH7 -> 172.76
A8: =_xlfn.CONCAT(D8,L8) -> Louveira25.5 | B8: 4151 | C8: 4185 | D8: Louveira | F8: AMBEV | G8: CONTRATO | H8: FOB | K8: F,500ML,GATORADE,CR | L8: 25.5 | M8: CR | V8: Virgem | W8: 0.7 | X8: ALPEK | Y8: =IF($X8="",0,HLOOKUP($H$3,Resina!$E$2:$AK$93,MATCH("MANAUS"&$X8&$Y$5,Resina!$A$2:$A$93,0))) -> 1283.4027 | Z8: 0.3 | AA8: VG | AB8: =IF($AA8="",0,HLOOKUP($H$3,Resina!$E$2:$AK$93,MATCH("MANAUS"&$AA8&$AB$5,Resina!$A$2:$A$93,0))) -> 1720.8738 | AC8: =$AC$7 -> 46091 | AD8: Mensal | AE8: =$AE$7 -> 45839 | AF8: MIL | AG8: =_xlfn.XLOOKUP($H$3,Resina!$2:$2,Resina!$3:$3,0) -> 5.2006167 | AH8: =(L8*((Y8*W8)+(AB8*Z8)))*AG8/1000 -> 187.60404 | AI8: 0.005 | AJ8: =AH8*AI8 -> 0.93802022 | AO8: =_xlfn.XLOOKUP($D8&$L8&$AK$3,'BD Conv'!$A:$A,'BD Conv'!$H:$H,0)*_xlfn.XLOOKUP($D8,'BD Conv'!$C$17:$C$19,'BD Conv'!$F$17:$F$19,0)*(1+(HLOOKUP($B8&AO$6,Indexadores!$C$2:$AH$32,MATCH($AE8,Indexadores!$A$2:$A$32,0)))) -> 0 | AS8: 0.005 | AT8: =(AU8+AO8)*AS8 -> 0 | AU8: =_xlfn.XLOOKUP($D8&$L8&$AK$3,'BD Conv'!$A:$A,'BD Conv'!$H:$H,0)*_xlfn.XLOOKUP($D8,'BD Conv'!$C$17:$C$19,'BD Conv'!$E$17:$E$19,0)*(1+(HLOOKUP($B8&AU$6,Indexadores!$C$2:$AH$32,MATCH($AE8,Indexadores!$A$2:$A$32,0)))) -> 0 | AV8: =SUM(AN8,AO8,AP8,(AQ8*AG8),AR8,AT8,AU8) -> 0 | AW8: =_xlfn.XLOOKUP($A8&$AK$3,'BD Conv'!$A:$A,'BD Conv'!$I:$I,0) -> 0 | AZ8: =SUM(AH8,AJ8,AK8,AL8,AV8,AW8:AY8) -> 188.54207 | BB8: =_xlfn.XLOOKUP($D8&$L8&$BA$3,'BD Conv'!$A:$A,'BD Conv'!$J:$J,0)*_xlfn.XLOOKUP($D8,'BD Conv'!$C$17:$C$19,'BD Conv'!$F$17:$F$19,0)*(1+(HLOOKUP($C8&BB$6,Indexadores!$C$2:$AH$32,MATCH($AE8,Indexadores!$A$2:$A$32,0)))) -> 0 | BF8: =_xlfn.XLOOKUP($D8&$L8&$BA$3,'BD Conv'!$A:$A,'BD Conv'!$J:$J,0)*_xlfn.XLOOKUP($D8,'BD Conv'!$C$17:$C$19,'BD Conv'!$E$17:$E$19,0)*(1+(HLOOKUP($C8&BF$6,Indexadores!$C$2:$AH$32,MATCH($AE8,Indexadores!$A$2:$A$32,0)))) -> 0 | BG8: 0.01 | BH8: =(AZ8+BB8+BF8)*BG8 -> 1.8854207 | BI8: =SUM(BA8,BB8,BC8,(BD8*AG8),BE8,BF8,BH8) -> 1.8854207 | BN8: =_xlfn.XLOOKUP($A8&$BA$3,'BD Conv'!$A:$A,'BD Conv'!$K:$K,0) -> 0 | BQ8: =SUM(BI8,BJ8,BK8,BM8,BN8,BO8,BP8) -> 1.8854207 | BR8: =-BQ8*$BR$3 -> 0 | BT8: =AZ8+BQ8+BR8+BS8 -> 190.42749 | BU8: =BV8-BT8 -> 48.024162 | BV8: =BT8/(1-(12%+1.65%+7.6%) +12%*(1.65%+7.6%)) -> 238.45165 | BY8: =BT8/CP8-1 -> 0.033985099 | BZ8: =(BT8-CP8)/AG8 -> 1.2035082 | CA8: =(BT8-CK8-CL8-AL8-AX8-AY8-BO8-BP8+CQ8)/AG8 -> 1.2035082 | CB8: =(BT8-AH8)/AG8 -> 0.54290502 | CD8: =CP8*(1+$CD$5) -> 202.58535 | CE8: =(CD8-CP8)/AG8 -> 3.541282 | CF8: =(CD8-CK8-CL8-AL8-AX8-AY8-BO8-BP8+CQ8)/AG8 -> 3.541282 | CG8: =(CD8-AH8)/AG8 -> 2.8806788 | CI8: =IF($X8="",0,HLOOKUP($H$3,Resina!$E$2:$AK$93,MATCH("MANAUS"&$X8&$CI$5,Resina!$A$2:$A$93,0))) -> 1212.1409 | CJ8: =IF($AA8="",0,HLOOKUP($H$3,Resina!$E$2:$AK$93,MATCH("MANAUS"&$AA8&$CJ$5,Resina!$A$2:$A$93,0))) -> 1754.965 | CK8: =L8*((CI8*W8)+(CJ8*Z8))*AG8/1000 -> 182.34505 | CL8: =CK8*$CL$6 -> 1.8234505 | CM8: =IF(D8="Manaus FORA",-((CK8/0.88*0.12)*(1-9.25%))," ") | CO8: =AX8+AY8+BO8+BP8+AL8+AN8+BJ8+BK8+BM8 -> 0 | CP8: =SUM(CK8:CO8) -> 184.1685 | DE8: =_xlfn.CONCAT(D8,L8) -> Louveira25.5 | DF8: =L8 -> 25.5 | DG8: =ROUND(SUMIF($1:$1,DG$5,8:8),2) -> 187.6 | DH8: =ROUND(SUMIF($1:$1,DH$5,8:8),2) -> 0.94 | DI8: =ROUND(SUMIF($1:$1,DI$5,8:8),2) -> 1.89 | DJ8: =ROUND(SUMIF($1:$1,DJ$5,8:8),2) -> 0 | DK8: =ROUND(SUMIF($1:$1,DK$5,8:8),2) -> 0 | DL8: =ROUND(SUMIF($1:$1,DL$5,8:8),2) -> 0 | DM8: =ROUND(SUMIF($1:$1,DM$5,8:8),2) -> 0 | DN8: =ROUND(SUMIF($1:$1,DN$5,8:8),2) -> 0 | ... ED8: =ROUND(SUMIF($1:$1,ED$5,8:8),2) -> 0 | EE8: =SUM(DG8:ED8) -> 190.43 | EF8: =ROUND(SUM(EE8-BT8),2) -> 0 | EG8: =IF(DN8<>0,DN8-EF8,0) -> 0 | EH8: =IF(EG8=0,DO8-EF8,DO8) -> 0 | EI8: =SUM(DG8:DM8)+SUM(DP8:ED8)+EG8+EH8 -> 190.43
A9: =_xlfn.CONCAT(D9,L9) -> Manaus25.5 | B9: 4151 | C9: 4151 | D9: Manaus | F9: AMBEV | G9: CONTRATO | H9: FOB | K9: PREFORMA | L9: 25.5 | M9: CR | V9: Virgem | W9: 1 | X9: ALPEK | Y9: =IF($X9="",0,HLOOKUP($H$3,Resina!$E$2:$AK$93,MATCH($D9&$X9&$Y$5,Resina!$A$2:$A$93,0))) -> 1283.4027 | Z9: 0 | AB9: =IF($AA9="",0,HLOOKUP($H$3,Resina!$E$2:$AK$93,MATCH($D9&$AA9&$AB$5,Resina!$A$2:$A$93,0))) -> 0 | AC9: =$AC$7 -> 46091 | AD9: Mensal | AE9: =$AE$7 -> 45839 | AF9: MIL | AG9: =_xlfn.XLOOKUP($H$3,Resina!$2:$2,Resina!$3:$3,0) -> 5.2006167 | AH9: =(L9*((Y9*W9)+(AB9*Z9)))*AG9/1000 -> 170.19938 | AI9: 0.005 | AJ9: =AH9*AI9 -> 0.85099692 | AO9: =_xlfn.XLOOKUP($D9&$L9&$AK$3,'BD Conv'!$A:$A,'BD Conv'!$H:$H,0)*_xlfn.XLOOKUP($D9,'BD Conv'!$C$17:$C$19,'BD Conv'!$F$17:$F$19,0)*(1+(HLOOKUP($B9&AO$6,Indexadores!$C$2:$AH$32,MATCH($AE9,Indexadores!$A$2:$A$32,0)))) -> 0 | AS9: 0.005 | AT9: =(AU9+AO9)*AS9 -> 0 | AU9: =_xlfn.XLOOKUP($D9&$L9&$AK$3,'BD Conv'!$A:$A,'BD Conv'!$H:$H,0)*_xlfn.XLOOKUP($D9,'BD Conv'!$C$17:$C$19,'BD Conv'!$E$17:$E$19,0)*(1+(HLOOKUP($B9&AU$6,Indexadores!$C$2:$AH$32,MATCH($AE9,Indexadores!$A$2:$A$32,0)))) -> 0 | AV9: =SUM(AN9,AO9,AP9,(AQ9*AG9),AR9,AT9,AU9) -> 0 | AW9: =_xlfn.XLOOKUP($A9&$AK$3,'BD Conv'!$A:$A,'BD Conv'!$I:$I,0) -> 0 | AZ9: =SUM(AH9,AJ9,AK9,AL9,AV9,AW9:AY9) -> 171.05038 | BI9: =SUM(BA9,BB9,BC9,(BD9*AG9),BE9,BF9,BH9) -> 0 | BN9: =_xlfn.XLOOKUP($A9&$BA$3,'BD Conv'!$A:$A,'BD Conv'!$K:$K,0) -> 0 | BQ9: =SUM(BI9,BJ9,BK9,BM9,BN9,BO9,BP9) -> 0 | BR9: =-BQ9*$BR$3 -> 0 | BT9: =AZ9+BQ9+BR9+BS9 -> 171.05038 | BU9: =BV9-BT9 -> 43.137424 | BV9: =BT9/(1-(12%+1.65%+7.6%) +12%*(1.65%+7.6%)) -> 214.1878 | BY9: =BT9/CP9-1 -> 0.053548477 | BZ9: =(BT9-CP9)/AG9 -> 1.6717133 | CA9: =(BT9-CK9-CL9-AL9-AX9-AY9-BO9-BP9+CQ9)/AG9 -> 1.6717133 | CB9: =(BT9-AH9)/AG9 -> 0.16363385 | CD9: =CP9*(1+$CD$5) -> 178.59208 | CE9: =(CD9-CP9)/AG9 -> 3.121869 | CF9: =(CD9-CK9-CL9-AL9-AX9-AY9-BO9-BP9+CQ9)/AG9 -> 3.121869 | CG9: =(CD9-AH9)/AG9 -> 1.6137895 | CI9: =IF($X9="",0,HLOOKUP($H$3,Resina!$E$2:$AK$93,MATCH($D9&$X9&$CI$5,Resina!$A$2:$A$93,0))) -> 1212.1409 | CJ9: =IF($AA9="",0,HLOOKUP($H$3,Resina!$E$2:$AK$93,MATCH($D9&$AA9&$CJ$5,Resina!$A$2:$A$93,0))) -> 0 | CK9: =L9*((CI9*W9)+(CJ9*Z9))*AG9/1000 -> 160.74895 | CL9: =CK9*$CL$6 -> 1.6074895 | CM9: =IF(D9="Manaus FORA",-((CK9/0.88*0.12)*(1-9.25%))," ") | CO9: =AX9+AY9+BO9+BP9+AL9+AN9+BJ9+BK9+BM9 -> 0 | CP9: =SUM(CK9:CO9) -> 162.35644 | DE9: =_xlfn.CONCAT(D9,L9) -> Manaus25.5 | DF9: =L9 -> 25.5 | DG9: =ROUND(SUMIF($1:$1,DG$5,9:9),2) -> 170.2 | DH9: =ROUND(SUMIF($1:$1,DH$5,9:9),2) -> 0.85 | DI9: =ROUND(SUMIF($1:$1,DI$5,9:9),2) -> 0 | DJ9: =ROUND(SUMIF($1:$1,DJ$5,9:9),2) -> 0 | DK9: =ROUND(SUMIF($1:$1,DK$5,9:9),2) -> 0 | DL9: =ROUND(SUMIF($1:$1,DL$5,9:9),2) -> 0 | DM9: =ROUND(SUMIF($1:$1,DM$5,9:9),2) -> 0 | DN9: =ROUND(SUMIF($1:$1,DN$5,9:9),2) -> 0 | ... ED9: =ROUND(SUMIF($1:$1,ED$5,9:9),2) -> 0 | EE9: =SUM(DG9:ED9) -> 171.05 | EF9: =ROUND(SUM(EE9-BT9),2) -> 0 | EG9: =IF(DN9<>0,DN9-EF9,0) -> 0 | EH9: =IF(EG9=0,DO9-EF9,DO9) -> 0 | EI9: =SUM(DG9:DM9)+SUM(DP9:ED9)+EG9+EH9 -> 171.05
A10: =_xlfn.CONCAT(D10,L10) -> Manaus25.5 | B10: 4151 | C10: 4151 | D10: Manaus | F10: AMBEV | G10: CONTRATO | H10: FOB | K10: PREFORMA | L10: 25.5 | M10: CR | V10: Virgem | W10: 0.7 | X10: ALPEK | Y10: =IF($X10="",0,HLOOKUP($H$3,Resina!$E$2:$AK$93,MATCH($D10&$X10&$Y$5,Resina!$A$2:$A$93,0))) -> 1283.4027 | Z10: 0.3 | AA10: VG | AB10: =IF($AA10="",0,HLOOKUP($H$3,Resina!$E$2:$AK$93,MATCH($D10&$AA10&$AB$5,Resina!$A$2:$A$93,0))) -> 1720.8738 | AC10: =$AC$7 -> 46091 | AD10: Mensal | AE10: =$AE$7 -> 45839 | AF10: MIL | AG10: =_xlfn.XLOOKUP($H$3,Resina!$2:$2,Resina!$3:$3,0) -> 5.2006167 | AH10: =(L10*((Y10*W10)+(AB10*Z10)))*AG10/1000 -> 187.60404 | AI10: 0.005 | AJ10: =AH10*AI10 -> 0.93802022 | AO10: =_xlfn.XLOOKUP($D10&$L10&$AK$3,'BD Conv'!$A:$A,'BD Conv'!$H:$H,0)*_xlfn.XLOOKUP($D10,'BD Conv'!$C$17:$C$19,'BD Conv'!$F$17:$F$19,0)*(1+(HLOOKUP($B10&AO$6,Indexadores!$C$2:$AH$32,MATCH($AE10,Indexadores!$A$2:$A$32,0)))) -> 0 | AS10: 0.005 | AT10: =(AU10+AO10)*AS10 -> 0 | AU10: =_xlfn.XLOOKUP($D10&$L10&$AK$3,'BD Conv'!$A:$A,'BD Conv'!$H:$H,0)*_xlfn.XLOOKUP($D10,'BD Conv'!$C$17:$C$19,'BD Conv'!$E$17:$E$19,0)*(1+(HLOOKUP($B10&AU$6,Indexadores!$C$2:$AH$32,MATCH($AE10,Indexadores!$A$2:$A$32,0)))) -> 0 | AV10: =SUM(AN10,AO10,AP10,(AQ10*AG10),AR10,AT10,AU10) -> 0 | AW10: =_xlfn.XLOOKUP($A10&$AK$3,'BD Conv'!$A:$A,'BD Conv'!$I:$I,0) -> 0 | AZ10: =SUM(AH10,AJ10,AK10,AL10,AV10,AW10:AY10) -> 188.54207 | BI10: =SUM(BA10,BB10,BC10,(BD10*AG10),BE10,BF10,BH10) -> 0 | BN10: =_xlfn.XLOOKUP($A10&$BA$3,'BD Conv'!$A:$A,'BD Conv'!$K:$K,0) -> 0 | BQ10: =SUM(BI10,BJ10,BK10,BM10,BN10,BO10,BP10) -> 0 | BR10: =-BQ10*$BR$3 -> 0 | BT10: =AZ10+BQ10+BR10+BS10 -> 188.54207 | BU10: =BV10-BT10 -> 47.548675 | BV10: =BT10/(1-(12%+1.65%+7.6%) +12%*(1.65%+7.6%)) -> 236.09074 | BY10: =BT10/CP10-1 -> 0.023747623 | BZ10: =(BT10-CP10)/AG10 -> 0.84097028 | CA10: =(BT10-CK10-CL10-AL10-AX10-AY10-BO10-BP10+CQ10)/AG10 -> 0.84097028 | CB10: =(BT10-AH10)/AG10 -> 0.18036711 | CD10: =CP10*(1+$CD$5) -> 202.58535 | CE10: =(CD10-CP10)/AG10 -> 3.541282 | CF10: =(CD10-CK10-CL10-AL10-AX10-AY10-BO10-BP10+CQ10)/AG10 -> 3.541282 | CG10: =(CD10-AH10)/AG10 -> 2.8806788 | CI10: =IF($X10="",0,HLOOKUP($H$3,Resina!$E$2:$AK$93,MATCH($D10&$X10&$CI$5,Resina!$A$2:$A$93,0))) -> 1212.1409 | CJ10: =IF($AA10="",0,HLOOKUP($H$3,Resina!$E$2:$AK$93,MATCH($D10&$AA10&$CJ$5,Resina!$A$2:$A$93,0))) -> 1754.965 | CK10: =L10*((CI10*W10)+(CJ10*Z10))*AG10/1000 -> 182.34505 | CL10: =CK10*$CL$6 -> 1.8234505 | CM10: =IF(D10="Manaus FORA",-((CK10/0.88*0.12)*(1-9.25%))," ") | CO10: =AX10+AY10+BO10+BP10+AL10+AN10+BJ10+BK10+BM10 -> 0 | CP10: =SUM(CK10:CO10) -> 184.1685 | DE10: =_xlfn.CONCAT(D10,L10) -> Manaus25.5 | DF10: =L10 -> 25.5 | DG10: =ROUND(SUMIF($1:$1,DG$5,10:10),2) -> 187.6 | DH10: =ROUND(SUMIF($1:$1,DH$5,10:10),2) -> 0.94 | DI10: =ROUND(SUMIF($1:$1,DI$5,10:10),2) -> 0 | DJ10: =ROUND(SUMIF($1:$1,DJ$5,10:10),2) -> 0 | DK10: =ROUND(SUMIF($1:$1,DK$5,10:10),2) -> 0 | DL10: =ROUND(SUMIF($1:$1,DL$5,10:10),2) -> 0 | DM10: =ROUND(SUMIF($1:$1,DM$5,10:10),2) -> 0 | DN10: =ROUND(SUMIF($1:$1,DN$5,10:10),2) -> 0 | ... ED10: =ROUND(SUMIF($1:$1,ED$5,10:10),2) -> 0 | EE10: =SUM(DG10:ED10) -> 188.54 | EF10: =ROUND(SUM(EE10-BT10),2) -> 0 | EG10: =IF(DN10<>0,DN10-EF10,0) -> 0 | EH10: =IF(EG10=0,DO10-EF10,DO10) -> 0 | EI10: =SUM(DG10:DM10)+SUM(DP10:ED10)+EG10+EH10 -> 188.54
A11: =_xlfn.CONCAT(D11,L11) -> Manaus38 | B11: 4151 | C11: 4151 | D11: Manaus | F11: AMBEV | G11: CONTRATO | H11: FOB | K11: PREFORMA | L11: 38 | M11: CR | V11: Virgem | W11: 1 | X11: ALPEK | Y11: =IF($X11="",0,HLOOKUP($H$3,Resina!$E$2:$AK$93,MATCH($D11&$X11&$Y$5,Resina!$A$2:$A$93,0))) -> 1283.4027 | Z11: 0 | AA11: VG | AB11: =IF($AA11="",0,HLOOKUP($H$3,Resina!$E$2:$AK$93,MATCH($D11&$AA11&$AB$5,Resina!$A$2:$A$93,0))) -> 1720.8738 | AC11: =$AC$7 -> 46091 | AD11: Mensal | AE11: =$AE$7 -> 45839 | AF11: MIL | AG11: =_xlfn.XLOOKUP($H$3,Resina!$2:$2,Resina!$3:$3,0) -> 5.2006167 | AH11: =(L11*((Y11*W11)+(AB11*Z11)))*AG11/1000 -> 253.63045 | AI11: 0.005 | AJ11: =AH11*AI11 -> 1.2681523 | AO11: =_xlfn.XLOOKUP($D11&$L11&$AK$3,'BD Conv'!$A:$A,'BD Conv'!$H:$H,0)*_xlfn.XLOOKUP($D11,'BD Conv'!$C$17:$C$19,'BD Conv'!$F$17:$F$19,0)*(1+(HLOOKUP($B11&AO$6,Indexadores!$C$2:$AH$32,MATCH($AE11,Indexadores!$A$2:$A$32,0)))) -> 14.28 | AS11: 0.005 | AT11: =(AU11+AO11)*AS11 -> 0.357 | AU11: =_xlfn.XLOOKUP($D11&$L11&$AK$3,'BD Conv'!$A:$A,'BD Conv'!$H:$H,0)*_xlfn.XLOOKUP($D11,'BD Conv'!$C$17:$C$19,'BD Conv'!$E$17:$E$19,0)*(1+(HLOOKUP($B11&AU$6,Indexadores!$C$2:$AH$32,MATCH($AE11,Indexadores!$A$2:$A$32,0)))) -> 57.12 | AV11: =SUM(AN11,AO11,AP11,(AQ11*AG11),AR11,AT11,AU11) -> 71.757 | AW11: =_xlfn.XLOOKUP($A11&$AK$3,'BD Conv'!$A:$A,'BD Conv'!$I:$I,0) -> 0 | AZ11: =SUM(AH11,AJ11,AK11,AL11,AV11,AW11:AY11) -> 326.65561 | BI11: =SUM(BA11,BB11,BC11,(BD11*AG11),BE11,BF11,BH11) -> 0 | BN11: =_xlfn.XLOOKUP($A11&$BA$3,'BD Conv'!$A:$A,'BD Conv'!$K:$K,0) -> 0 | BQ11: =SUM(BI11,BJ11,BK11,BM11,BN11,BO11,BP11) -> 0 | BR11: =-BQ11*$BR$3 -> 0 | BT11: =AZ11+BQ11+BR11+BS11 -> 326.65561 | BU11: =BV11-BT11 -> 82.379713 | BV11: =BT11/(1-(12%+1.65%+7.6%) +12%*(1.65%+7.6%)) -> 409.03532 | BY11: =BT11/CP11-1 -> 0.35013495 | BZ11: =(BT11-CP11)/AG11 -> 16.288967 | CA11: =(BT11-CK11-CL11-AL11-AX11-AY11-BO11-BP11+CQ11)/AG11 -> 16.288967 | CB11: =(BT11-AH11)/AG11 -> 14.041633 | CD11: =CP11*(1+$CD$5) -> 266.13722 | CE11: =(CD11-CP11)/AG11 -> 4.652197 | CF11: =(CD11-CK11-CL11-AL11-AX11-AY11-BO11-BP11+CQ11)/AG11 -> 4.652197 | CG11: =(CD11-AH11)/AG11 -> 2.4048629 | CI11: =IF($X11="",0,HLOOKUP($H$3,Resina!$E$2:$AK$93,MATCH($D11&$X11&$CI$5,Resina!$A$2:$A$93,0))) -> 1212.1409 | CJ11: =IF($AA11="",0,HLOOKUP($H$3,Resina!$E$2:$AK$93,MATCH($D11&$AA11&$CJ$5,Resina!$A$2:$A$93,0))) -> 1754.965 | CK11: =L11*((CI11*W11)+(CJ11*Z11))*AG11/1000 -> 239.54746 | CL11: =CK11*$CL$6 -> 2.3954746 | CM11: =IF(D11="Manaus FORA",-((CK11/0.88*0.12)*(1-9.25%))," ") | CO11: =AX11+AY11+BO11+BP11+AL11+AN11+BJ11+BK11+BM11 -> 0 | CP11: =SUM(CK11:CO11) -> 241.94293 | DE11: =_xlfn.CONCAT(D11,L11) -> Manaus38 | DF11: =L11 -> 38 | DG11: =ROUND(SUMIF($1:$1,DG$5,11:11),2) -> 253.63 | DH11: =ROUND(SUMIF($1:$1,DH$5,11:11),2) -> 1.63 | DI11: =ROUND(SUMIF($1:$1,DI$5,11:11),2) -> 0 | DJ11: =ROUND(SUMIF($1:$1,DJ$5,11:11),2) -> 0 | DK11: =ROUND(SUMIF($1:$1,DK$5,11:11),2) -> 0 | DL11: =ROUND(SUMIF($1:$1,DL$5,11:11),2) -> 0 | DM11: =ROUND(SUMIF($1:$1,DM$5,11:11),2) -> 0 | DN11: =ROUND(SUMIF($1:$1,DN$5,11:11),2) -> 57.12 | ... ED11: =ROUND(SUMIF($1:$1,ED$5,11:11),2) -> 0 | EE11: =SUM(DG11:ED11) -> 326.66 | EF11: =ROUND(SUM(EE11-BT11),2) -> 0 | EG11: =IF(DN11<>0,DN11-EF11,0) -> 57.12 | EH11: =IF(EG11=0,DO11-EF11,DO11) -> 0 | EI11: =SUM(DG11:DM11)+SUM(DP11:ED11)+EG11+EH11 -> 326.66
A12: =_xlfn.CONCAT(D12,L12) -> Manaus38 | B12: 4151 | C12: 4151 | D12: Manaus | F12: AMBEV | G12: CONTRATO | H12: FOB | K12: PREFORMA | L12: 38 | M12: CR | V12: Virgem | W12: 0.6 | X12: ALPEK | Y12: =IF($X12="",0,HLOOKUP($H$3,Resina!$E$2:$AK$93,MATCH($D12&$X12&$Y$5,Resina!$A$2:$A$93,0))) -> 1283.4027 | Z12: 0.4 | AA12: VG | AB12: =IF($AA12="",0,HLOOKUP($H$3,Resina!$E$2:$AK$93,MATCH($D12&$AA12&$AB$5,Resina!$A$2:$A$93,0))) -> 1720.8738 | AC12: =$AC$7 -> 46091 | AD12: Mensal | AE12: =$AE$7 -> 45839 | AF12: MIL | AG12: =_xlfn.XLOOKUP($H$3,Resina!$2:$2,Resina!$3:$3,0) -> 5.2006167 | AH12: =(L12*((Y12*W12)+(AB12*Z12)))*AG12/1000 -> 288.21226 | AI12: 0.005 | AJ12: =AH12*AI12 -> 1.4410613 | AO12: =_xlfn.XLOOKUP($D12&$L12&$AK$3,'BD Conv'!$A:$A,'BD Conv'!$H:$H,0)*_xlfn.XLOOKUP($D12,'BD Conv'!$C$17:$C$19,'BD Conv'!$F$17:$F$19,0)*(1+(HLOOKUP($B12&AO$6,Indexadores!$C$2:$AH$32,MATCH($AE12,Indexadores!$A$2:$A$32,0)))) -> 14.28 | AS12: 0.005 | AT12: =(AU12+AO12)*AS12 -> 0.357 | AU12: =_xlfn.XLOOKUP($D12&$L12&$AK$3,'BD Conv'!$A:$A,'BD Conv'!$H:$H,0)*_xlfn.XLOOKUP($D12,'BD Conv'!$C$17:$C$19,'BD Conv'!$E$17:$E$19,0)*(1+(HLOOKUP($B12&AU$6,Indexadores!$C$2:$AH$32,MATCH($AE12,Indexadores!$A$2:$A$32,0)))) -> 57.12 | AV12: =SUM(AN12,AO12,AP12,(AQ12*AG12),AR12,AT12,AU12) -> 71.757 | AW12: =_xlfn.XLOOKUP($A12&$AK$3,'BD Conv'!$A:$A,'BD Conv'!$I:$I,0) -> 0 | AZ12: =SUM(AH12,AJ12,AK12,AL12,AV12,AW12:AY12) -> 361.41033 | BI12: =SUM(BA12,BB12,BC12,(BD12*AG12),BE12,BF12,BH12) -> 0 | BN12: =_xlfn.XLOOKUP($A12&$BA$3,'BD Conv'!$A:$A,'BD Conv'!$K:$K,0) -> 0 | BQ12: =SUM(BI12,BJ12,BK12,BM12,BN12,BO12,BP12) -> 0 | BR12: =-BQ12*$BR$3 -> 0 | BT12: =AZ12+BQ12+BR12+BS12 -> 361.41033 | BU12: =BV12-BT12 -> 91.144553 | BV12: =BT12/(1-(12%+1.65%+7.6%) +12%*(1.65%+7.6%)) -> 452.55488 | BY12: =BT12/CP12-1 -> 0.26685321 | BZ12: =(BT12-CP12)/AG12 -> 14.638341 | CA12: =(BT12-CK12-CL12-AL12-AX12-AY12-BO12-BP12+CQ12)/AG12 -> 14.638341 | CB12: =(BT12-AH12)/AG12 -> 14.074881 | CD12: =CP12*(1+$CD$5) -> 313.81012 | CE12: =(CD12-CP12)/AG12 -> 5.4855404 | CF12: =(CD12-CK12-CL12-AL12-AX12-AY12-BO12-BP12+CQ12)/AG12 -> 5.4855404 | CG12: =(CD12-AH12)/AG12 -> 4.9220808 | CI12: =IF($X12="",0,HLOOKUP($H$3,Resina!$E$2:$AK$93,MATCH($D12&$X12&$CI$5,Resina!$A$2:$A$93,0))) -> 1212.1409 | CJ12: =IF($AA12="",0,HLOOKUP($H$3,Resina!$E$2:$AK$93,MATCH($D12&$AA12&$CJ$5,Resina!$A$2:$A$93,0))) -> 1754.965 | CK12: =L12*((CI12*W12)+(CJ12*Z12))*AG12/1000 -> 282.45735 | CL12: =CK12*$CL$6 -> 2.8245735 | CM12: =IF(D12="Manaus FORA",-((CK12/0.88*0.12)*(1-9.25%))," ") | CO12: =AX12+AY12+BO12+BP12+AL12+AN12+BJ12+BK12+BM12 -> 0 | CP12: =SUM(CK12:CO12) -> 285.28193 | DE12: =_xlfn.CONCAT(D12,L12) -> Manaus38 | DF12: =L12 -> 38 | DG12: =ROUND(SUMIF($1:$1,DG$5,12:12),2) -> 288.21 | DH12: =ROUND(SUMIF($1:$1,DH$5,12:12),2) -> 1.8 | DI12: =ROUND(SUMIF($1:$1,DI$5,12:12),2) -> 0 | DJ12: =ROUND(SUMIF($1:$1,DJ$5,12:12),2) -> 0 | DK12: =ROUND(SUMIF($1:$1,DK$5,12:12),2) -> 0 | DL12: =ROUND(SUMIF($1:$1,DL$5,12:12),2) -> 0 | DM12: =ROUND(SUMIF($1:$1,DM$5,12:12),2) -> 0 | DN12: =ROUND(SUMIF($1:$1,DN$5,12:12),2) -> 57.12 | ... ED12: =ROUND(SUMIF($1:$1,ED$5,12:12),2) -> 0 | EE12: =SUM(DG12:ED12) -> 361.41 | EF12: =ROUND(SUM(EE12-BT12),2) -> 0 | EG12: =IF(DN12<>0,DN12-EF12,0) -> 57.12 | EH12: =IF(EG12=0,DO12-EF12,DO12) -> 0 | EI12: =SUM(DG12:DM12)+SUM(DP12:ED12)+EG12+EH12 -> 361.41
A13: =_xlfn.CONCAT(D13,L13) -> Manaus38 | B13: 4151 | C13: 4151 | D13: Manaus | F13: AMBEV | G13: CONTRATO | H13: FOB | K13: PREFORMA | L13: 38 | M13: CR | V13: Virgem | W13: 0.4 | X13: ALPEK | Y13: =IF($X13="",0,HLOOKUP($H$3,Resina!$E$2:$AK$93,MATCH($D13&$X13&$Y$5,Resina!$A$2:$A$93,0))) -> 1283.4027 | Z13: 0.6 | AA13: VG | AB13: =IF($AA13="",0,HLOOKUP($H$3,Resina!$E$2:$AK$93,MATCH($D13&$AA13&$AB$5,Resina!$A$2:$A$93,0))) -> 1720.8738 | AC13: =$AC$7 -> 46091 | AD13: Mensal | AE13: =$AE$7 -> 45839 | AF13: MIL | AG13: =_xlfn.XLOOKUP($H$3,Resina!$2:$2,Resina!$3:$3,0) -> 5.2006167 | AH13: =(L13*((Y13*W13)+(AB13*Z13)))*AG13/1000 -> 305.50317 | AI13: 0.005 | AJ13: =AH13*AI13 -> 1.5275159 | AO13: =_xlfn.XLOOKUP($D13&$L13&$AK$3,'BD Conv'!$A:$A,'BD Conv'!$H:$H,0)*_xlfn.XLOOKUP($D13,'BD Conv'!$C$17:$C$19,'BD Conv'!$F$17:$F$19,0)*(1+(HLOOKUP($B13&AO$6,Indexadores!$C$2:$AH$32,MATCH($AE13,Indexadores!$A$2:$A$32,0)))) -> 14.28 | AS13: 0.005 | AT13: =(AU13+AO13)*AS13 -> 0.357 | AU13: =_xlfn.XLOOKUP($D13&$L13&$AK$3,'BD Conv'!$A:$A,'BD Conv'!$H:$H,0)*_xlfn.XLOOKUP($D13,'BD Conv'!$C$17:$C$19,'BD Conv'!$E$17:$E$19,0)*(1+(HLOOKUP($B13&AU$6,Indexadores!$C$2:$AH$32,MATCH($AE13,Indexadores!$A$2:$A$32,0)))) -> 57.12 | AV13: =SUM(AN13,AO13,AP13,(AQ13*AG13),AR13,AT13,AU13) -> 71.757 | AW13: =_xlfn.XLOOKUP($A13&$AK$3,'BD Conv'!$A:$A,'BD Conv'!$I:$I,0) -> 0 | AZ13: =SUM(AH13,AJ13,AK13,AL13,AV13,AW13:AY13) -> 378.78769 | BI13: =SUM(BA13,BB13,BC13,(BD13*AG13),BE13,BF13,BH13) -> 0 | BN13: =_xlfn.XLOOKUP($A13&$BA$3,'BD Conv'!$A:$A,'BD Conv'!$K:$K,0) -> 0 | BQ13: =SUM(BI13,BJ13,BK13,BM13,BN13,BO13,BP13) -> 0 | BR13: =-BQ13*$BR$3 -> 0 | BT13: =AZ13+BQ13+BR13+BS13 -> 378.78769 | BU13: =BV13-BT13 -> 95.526972 | BV13: =BT13/(1-(12%+1.65%+7.6%) +12%*(1.65%+7.6%)) -> 474.31466 | BY13: =BT13/CP13-1 -> 0.23403136 | BZ13: =(BT13-CP13)/AG13 -> 13.813027 | CA13: =(BT13-CK13-CL13-AL13-AX13-AY13-BO13-BP13+CQ13)/AG13 -> 13.813027 | CB13: =(BT13-AH13)/AG13 -> 14.091505 | CD13: =CP13*(1+$CD$5) -> 337.64657 | CE13: =(CD13-CP13)/AG13 -> 5.9022121 | CF13: =(CD13-CK13-CL13-AL13-AX13-AY13-BO13-BP13+CQ13)/AG13 -> 5.9022121 | CG13: =(CD13-AH13)/AG13 -> 6.1806897 | CI13: =IF($X13="",0,HLOOKUP($H$3,Resina!$E$2:$AK$93,MATCH($D13&$X13&$CI$5,Resina!$A$2:$A$93,0))) -> 1212.1409 | CJ13: =IF($AA13="",0,HLOOKUP($H$3,Resina!$E$2:$AK$93,MATCH($D13&$AA13&$CJ$5,Resina!$A$2:$A$93,0))) -> 1754.965 | CK13: =L13*((CI13*W13)+(CJ13*Z13))*AG13/1000 -> 303.9123 | CL13: =CK13*$CL$6 -> 3.039123 | CM13: =IF(D13="Manaus FORA",-((CK13/0.88*0.12)*(1-9.25%))," ") | CO13: =AX13+AY13+BO13+BP13+AL13+AN13+BJ13+BK13+BM13 -> 0 | CP13: =SUM(CK13:CO13) -> 306.95143 | DE13: =_xlfn.CONCAT(D13,L13) -> Manaus38 | DF13: =L13 -> 38 | DG13: =ROUND(SUMIF($1:$1,DG$5,13:13),2) -> 305.5 | DH13: =ROUND(SUMIF($1:$1,DH$5,13:13),2) -> 1.88 | DI13: =ROUND(SUMIF($1:$1,DI$5,13:13),2) -> 0 | DJ13: =ROUND(SUMIF($1:$1,DJ$5,13:13),2) -> 0 | DK13: =ROUND(SUMIF($1:$1,DK$5,13:13),2) -> 0 | DL13: =ROUND(SUMIF($1:$1,DL$5,13:13),2) -> 0 | DM13: =ROUND(SUMIF($1:$1,DM$5,13:13),2) -> 0 | DN13: =ROUND(SUMIF($1:$1,DN$5,13:13),2) -> 57.12 | ... ED13: =ROUND(SUMIF($1:$1,ED$5,13:13),2) -> 0 | EE13: =SUM(DG13:ED13) -> 378.78 | EF13: =ROUND(SUM(EE13-BT13),2) -> -0.01 | EG13: =IF(DN13<>0,DN13-EF13,0) -> 57.13 | EH13: =IF(EG13=0,DO13-EF13,DO13) -> 0 | EI13: =SUM(DG13:DM13)+SUM(DP13:ED13)+EG13+EH13 -> 378.79
A14: =_xlfn.CONCAT(D14,L14) -> Manaus38 | B14: 4151 | C14: 4151 | D14: Manaus | F14: AMBEV | G14: CONTRATO | H14: FOB | K14: PREFORMA | L14: 38 | M14: CR | V14: Virgem | W14: 0 | Y14: =IF($X14="",0,HLOOKUP($H$3,Resina!$E$2:$AK$93,MATCH($D14&$X14&$Y$5,Resina!$A$2:$A$93,0))) -> 0 | Z14: 1 | AA14: VG | AB14: =IF($AA14="",0,HLOOKUP($H$3,Resina!$E$2:$AK$93,MATCH($D14&$AA14&$AB$5,Resina!$A$2:$A$93,0))) -> 1720.8738 | AC14: =$AC$7 -> 46091 | AD14: Mensal | AE14: =$AE$7 -> 45839 | AF14: MIL | AG14: =_xlfn.XLOOKUP($H$3,Resina!$2:$2,Resina!$3:$3,0) -> 5.2006167 | AH14: =(L14*((Y14*W14)+(AB14*Z14)))*AG14/1000 -> 340.08498 | AI14: 0.005 | AJ14: =AH14*AI14 -> 1.7004249 | AO14: =_xlfn.XLOOKUP($D14&$L14&$AK$3,'BD Conv'!$A:$A,'BD Conv'!$H:$H,0)*_xlfn.XLOOKUP($D14,'BD Conv'!$C$17:$C$19,'BD Conv'!$F$17:$F$19,0)*(1+(HLOOKUP($B14&AO$6,Indexadores!$C$2:$AH$32,MATCH($AE14,Indexadores!$A$2:$A$32,0)))) -> 14.28 | AS14: 0.005 | AT14: =(AU14+AO14)*AS14 -> 0.357 | AU14: =_xlfn.XLOOKUP($D14&$L14&$AK$3,'BD Conv'!$A:$A,'BD Conv'!$H:$H,0)*_xlfn.XLOOKUP($D14,'BD Conv'!$C$17:$C$19,'BD Conv'!$E$17:$E$19,0)*(1+(HLOOKUP($B14&AU$6,Indexadores!$C$2:$AH$32,MATCH($AE14,Indexadores!$A$2:$A$32,0)))) -> 57.12 | AV14: =SUM(AN14,AO14,AP14,(AQ14*AG14),AR14,AT14,AU14) -> 71.757 | AW14: =_xlfn.XLOOKUP($A14&$AK$3,'BD Conv'!$A:$A,'BD Conv'!$I:$I,0) -> 0 | AZ14: =SUM(AH14,AJ14,AK14,AL14,AV14,AW14:AY14) -> 413.54241 | BI14: =SUM(BA14,BB14,BC14,(BD14*AG14),BE14,BF14,BH14) -> 0 | BN14: =_xlfn.XLOOKUP($A14&$BA$3,'BD Conv'!$A:$A,'BD Conv'!$K:$K,0) -> 0 | BQ14: =SUM(BI14,BJ14,BK14,BM14,BN14,BO14,BP14) -> 0 | BR14: =-BQ14*$BR$3 -> 0 | BT14: =AZ14+BQ14+BR14+BS14 -> 413.54241 | BU14: =BV14-BT14 -> 104.29181 | BV14: =BT14/(1-(12%+1.65%+7.6%) +12%*(1.65%+7.6%)) -> 517.83422 | BY14: =BT14/CP14-1 -> 0.18057012 | BZ14: =(BT14-CP14)/AG14 -> 12.162401 | CA14: =(BT14-CK14-CL14-AL14-AX14-AY14-BO14-BP14+CQ14)/AG14 -> 12.162401 | CB14: =(BT14-AH14)/AG14 -> 14.124753 | CD14: =CP14*(1+$CD$5) -> 385.31946 | CE14: =(CD14-CP14)/AG14 -> 6.7355555 | CF14: =(CD14-CK14-CL14-AL14-AX14-AY14-BO14-BP14+CQ14)/AG14 -> 6.7355555 | CG14: =(CD14-AH14)/AG14 -> 8.6979076 | CI14: =IF($X14="",0,HLOOKUP($H$3,Resina!$E$2:$AK$93,MATCH($D14&$X14&$CI$5,Resina!$A$2:$A$93,0))) -> 0 | CJ14: =IF($AA14="",0,HLOOKUP($H$3,Resina!$E$2:$AK$93,MATCH($D14&$AA14&$CJ$5,Resina!$A$2:$A$93,0))) -> 1754.965 | CK14: =L14*((CI14*W14)+(CJ14*Z14))*AG14/1000 -> 346.8222 | CL14: =CK14*$CL$6 -> 3.468222 | CM14: =IF(D14="Manaus FORA",-((CK14/0.88*0.12)*(1-9.25%))," ") | CO14: =AX14+AY14+BO14+BP14+AL14+AN14+BJ14+BK14+BM14 -> 0 | CP14: =SUM(CK14:CO14) -> 350.29042 | DE14: =_xlfn.CONCAT(D14,L14) -> Manaus38 | DF14: =L14 -> 38 | DG14: =ROUND(SUMIF($1:$1,DG$5,14:14),2) -> 340.08 | DH14: =ROUND(SUMIF($1:$1,DH$5,14:14),2) -> 2.06 | DI14: =ROUND(SUMIF($1:$1,DI$5,14:14),2) -> 0 | DJ14: =ROUND(SUMIF($1:$1,DJ$5,14:14),2) -> 0 | DK14: =ROUND(SUMIF($1:$1,DK$5,14:14),2) -> 0 | DL14: =ROUND(SUMIF($1:$1,DL$5,14:14),2) -> 0 | DM14: =ROUND(SUMIF($1:$1,DM$5,14:14),2) -> 0 | DN14: =ROUND(SUMIF($1:$1,DN$5,14:14),2) -> 57.12 | ... ED14: =ROUND(SUMIF($1:$1,ED$5,14:14),2) -> 0 | EE14: =SUM(DG14:ED14) -> 413.54 | EF14: =ROUND(SUM(EE14-BT14),2) -> 0 | EG14: =IF(DN14<>0,DN14-EF14,0) -> 57.12 | EH14: =IF(EG14=0,DO14-EF14,DO14) -> 0 | EI14: =SUM(DG14:DM14)+SUM(DP14:ED14)+EG14+EH14 -> 413.54
A15: =_xlfn.CONCAT(D15,L15) -> Manaus38 | B15: 4151 | C15: 4151 | D15: Manaus | F15: AMBEV | G15: CONTRATO | H15: FOB | K15: PREFORMA | L15: 38 | M15: VD | V15: Virgem | W15: 1 | X15: ALPEK | Y15: =IF($X15="",0,HLOOKUP($H$3,Resina!$E$2:$AK$93,MATCH($D15&$X15&$Y$5,Resina!$A$2:$A$93,0))) -> 1283.4027 | Z15: 0 | AA15: VG | AB15: =IF($AA15="",0,HLOOKUP($H$3,Resina!$E$2:$AK$93,MATCH($D15&$AA15&$AB$5,Resina!$A$2:$A$93,0))) -> 1720.8738 | AC15: =$AC$7 -> 46091 | AD15: Mensal | AE15: =$AE$7 -> 45839 | AF15: MIL | AG15: =_xlfn.XLOOKUP($H$3,Resina!$2:$2,Resina!$3:$3,0) -> 5.2006167 | AH15: =(L15*((Y15*W15)+(AB15*Z15)))*AG15/1000 -> 253.63045 | AI15: 0.005 | AJ15: =AH15*AI15 -> 1.2681523 | AO15: =_xlfn.XLOOKUP($D15&$L15&$AK$3,'BD Conv'!$A:$A,'BD Conv'!$H:$H,0)*_xlfn.XLOOKUP($D15,'BD Conv'!$C$17:$C$19,'BD Conv'!$F$17:$F$19,0)*(1+(HLOOKUP($B15&AO$6,Indexadores!$C$2:$AH$32,MATCH($AE15,Indexadores!$A$2:$A$32,0)))) -> 14.28 | AS15: 0.005 | AT15: =(AU15+AO15)*AS15 -> 0.357 | AU15: =_xlfn.XLOOKUP($D15&$L15&$AK$3,'BD Conv'!$A:$A,'BD Conv'!$H:$H,0)*_xlfn.XLOOKUP($D15,'BD Conv'!$C$17:$C$19,'BD Conv'!$E$17:$E$19,0)*(1+(HLOOKUP($B15&AU$6,Indexadores!$C$2:$AH$32,MATCH($AE15,Indexadores!$A$2:$A$32,0)))) -> 57.12 | AV15: =SUM(AN15,AO15,AP15,(AQ15*AG15),AR15,AT15,AU15) -> 71.757 | AW15: =_xlfn.XLOOKUP($A15&$AK$3,'BD Conv'!$A:$A,'BD Conv'!$I:$I,0) -> 0 | AZ15: =SUM(AH15,AJ15,AK15,AL15,AV15,AW15:AY15) -> 326.65561 | BI15: =SUM(BA15,BB15,BC15,(BD15*AG15),BE15,BF15,BH15) -> 0 | BN15: =_xlfn.XLOOKUP($A15&$BA$3,'BD Conv'!$A:$A,'BD Conv'!$K:$K,0) -> 0 | BQ15: =SUM(BI15,BJ15,BK15,BM15,BN15,BO15,BP15) -> 0 | BR15: =-BQ15*$BR$3 -> 0 | BT15: =AZ15+BQ15+BR15+BS15 -> 326.65561 | BU15: =BV15-BT15 -> 82.379713 | BV15: =BT15/(1-(12%+1.65%+7.6%) +12%*(1.65%+7.6%)) -> 409.03532 | BY15: =BT15/CP15-1 -> 0.35013495 | BZ15: =(BT15-CP15)/AG15 -> 16.288967 | CA15: =(BT15-CK15-CL15-AL15-AX15-AY15-BO15-BP15+CQ15)/AG15 -> 16.288967 | CB15: =(BT15-AH15)/AG15 -> 14.041633 | CD15: =CP15*(1+$CD$5) -> 266.13722 | CE15: =(CD15-CP15)/AG15 -> 4.652197 | CF15: =(CD15-CK15-CL15-AL15-AX15-AY15-BO15-BP15+CQ15)/AG15 -> 4.652197 | CG15: =(CD15-AH15)/AG15 -> 2.4048629 | CI15: =IF($X15="",0,HLOOKUP($H$3,Resina!$E$2:$AK$93,MATCH($D15&$X15&$CI$5,Resina!$A$2:$A$93,0))) -> 1212.1409 | CJ15: =IF($AA15="",0,HLOOKUP($H$3,Resina!$E$2:$AK$93,MATCH($D15&$AA15&$CJ$5,Resina!$A$2:$A$93,0))) -> 1754.965 | CK15: =L15*((CI15*W15)+(CJ15*Z15))*AG15/1000 -> 239.54746 | CL15: =CK15*$CL$6 -> 2.3954746 | CM15: =IF(D15="Manaus FORA",-((CK15/0.88*0.12)*(1-9.25%))," ") | CO15: =AX15+AY15+BO15+BP15+AL15+AN15+BJ15+BK15+BM15 -> 0 | CP15: =SUM(CK15:CO15) -> 241.94293 | DE15: =_xlfn.CONCAT(D15,L15) -> Manaus38 | DF15: =L15 -> 38 | DG15: =ROUND(SUMIF($1:$1,DG$5,15:15),2) -> 253.63 | DH15: =ROUND(SUMIF($1:$1,DH$5,15:15),2) -> 1.63 | DI15: =ROUND(SUMIF($1:$1,DI$5,15:15),2) -> 0 | DJ15: =ROUND(SUMIF($1:$1,DJ$5,15:15),2) -> 0 | DK15: =ROUND(SUMIF($1:$1,DK$5,15:15),2) -> 0 | DL15: =ROUND(SUMIF($1:$1,DL$5,15:15),2) -> 0 | DM15: =ROUND(SUMIF($1:$1,DM$5,15:15),2) -> 0 | DN15: =ROUND(SUMIF($1:$1,DN$5,15:15),2) -> 57.12 | ... ED15: =ROUND(SUMIF($1:$1,ED$5,15:15),2) -> 0 | EE15: =SUM(DG15:ED15) -> 326.66 | EF15: =ROUND(SUM(EE15-BT15),2) -> 0 | EG15: =IF(DN15<>0,DN15-EF15,0) -> 57.12 | EH15: =IF(EG15=0,DO15-EF15,DO15) -> 0 | EI15: =SUM(DG15:DM15)+SUM(DP15:ED15)+EG15+EH15 -> 326.66
A16: =_xlfn.CONCAT(D16,L16) -> Manaus38 | B16: 4151 | C16: 4151 | D16: Manaus | F16: AMBEV | G16: CONTRATO | H16: FOB | K16: PREFORMA | L16: 38 | M16: VD | V16: Virgem | W16: 0.6 | X16: ALPEK | Y16: =IF($X16="",0,HLOOKUP($H$3,Resina!$E$2:$AK$93,MATCH($D16&$X16&$Y$5,Resina!$A$2:$A$93,0))) -> 1283.4027 | Z16: 0.4 | AA16: VG | AB16: =IF($AA16="",0,HLOOKUP($H$3,Resina!$E$2:$AK$93,MATCH($D16&$AA16&$AB$5,Resina!$A$2:$A$93,0))) -> 1720.8738 | AC16: =$AC$7 -> 46091 | AD16: Mensal | AE16: =$AE$7 -> 45839 | AF16: MIL | AG16: =_xlfn.XLOOKUP($H$3,Resina!$2:$2,Resina!$3:$3,0) -> 5.2006167 | AH16: =(L16*((Y16*W16)+(AB16*Z16)))*AG16/1000 -> 288.21226 | AI16: 0.005 | AJ16: =AH16*AI16 -> 1.4410613 | AO16: =_xlfn.XLOOKUP($D16&$L16&$AK$3,'BD Conv'!$A:$A,'BD Conv'!$H:$H,0)*_xlfn.XLOOKUP($D16,'BD Conv'!$C$17:$C$19,'BD Conv'!$F$17:$F$19,0)*(1+(HLOOKUP($B16&AO$6,Indexadores!$C$2:$AH$32,MATCH($AE16,Indexadores!$A$2:$A$32,0)))) -> 14.28 | AS16: 0.005 | AT16: =(AU16+AO16)*AS16 -> 0.357 | AU16: =_xlfn.XLOOKUP($D16&$L16&$AK$3,'BD Conv'!$A:$A,'BD Conv'!$H:$H,0)*_xlfn.XLOOKUP($D16,'BD Conv'!$C$17:$C$19,'BD Conv'!$E$17:$E$19,0)*(1+(HLOOKUP($B16&AU$6,Indexadores!$C$2:$AH$32,MATCH($AE16,Indexadores!$A$2:$A$32,0)))) -> 57.12 | AV16: =SUM(AN16,AO16,AP16,(AQ16*AG16),AR16,AT16,AU16) -> 71.757 | AW16: =_xlfn.XLOOKUP($A16&$AK$3,'BD Conv'!$A:$A,'BD Conv'!$I:$I,0) -> 0 | AZ16: =SUM(AH16,AJ16,AK16,AL16,AV16,AW16:AY16) -> 361.41033 | BI16: =SUM(BA16,BB16,BC16,(BD16*AG16),BE16,BF16,BH16) -> 0 | BN16: =_xlfn.XLOOKUP($A16&$BA$3,'BD Conv'!$A:$A,'BD Conv'!$K:$K,0) -> 0 | BQ16: =SUM(BI16,BJ16,BK16,BM16,BN16,BO16,BP16) -> 0 | BR16: =-BQ16*$BR$3 -> 0 | BT16: =AZ16+BQ16+BR16+BS16 -> 361.41033 | BU16: =BV16-BT16 -> 91.144553 | BV16: =BT16/(1-(12%+1.65%+7.6%) +12%*(1.65%+7.6%)) -> 452.55488 | BY16: =BT16/CP16-1 -> 0.26685321 | BZ16: =(BT16-CP16)/AG16 -> 14.638341 | CA16: =(BT16-CK16-CL16-AL16-AX16-AY16-BO16-BP16+CQ16)/AG16 -> 14.638341 | CB16: =(BT16-AH16)/AG16 -> 14.074881 | CD16: =CP16*(1+$CD$5) -> 313.81012 | CE16: =(CD16-CP16)/AG16 -> 5.4855404 | CF16: =(CD16-CK16-CL16-AL16-AX16-AY16-BO16-BP16+CQ16)/AG16 -> 5.4855404 | CG16: =(CD16-AH16)/AG16 -> 4.9220808 | CI16: =IF($X16="",0,HLOOKUP($H$3,Resina!$E$2:$AK$93,MATCH($D16&$X16&$CI$5,Resina!$A$2:$A$93,0))) -> 1212.1409 | CJ16: =IF($AA16="",0,HLOOKUP($H$3,Resina!$E$2:$AK$93,MATCH($D16&$AA16&$CJ$5,Resina!$A$2:$A$93,0))) -> 1754.965 | CK16: =L16*((CI16*W16)+(CJ16*Z16))*AG16/1000 -> 282.45735 | CL16: =CK16*$CL$6 -> 2.8245735 | CM16: =IF(D16="Manaus FORA",-((CK16/0.88*0.12)*(1-9.25%))," ") | CO16: =AX16+AY16+BO16+BP16+AL16+AN16+BJ16+BK16+BM16 -> 0 | CP16: =SUM(CK16:CO16) -> 285.28193 | DE16: =_xlfn.CONCAT(D16,L16) -> Manaus38 | DF16: =L16 -> 38 | DG16: =ROUND(SUMIF($1:$1,DG$5,16:16),2) -> 288.21 | DH16: =ROUND(SUMIF($1:$1,DH$5,16:16),2) -> 1.8 | DI16: =ROUND(SUMIF($1:$1,DI$5,16:16),2) -> 0 | DJ16: =ROUND(SUMIF($1:$1,DJ$5,16:16),2) -> 0 | DK16: =ROUND(SUMIF($1:$1,DK$5,16:16),2) -> 0 | DL16: =ROUND(SUMIF($1:$1,DL$5,16:16),2) -> 0 | DM16: =ROUND(SUMIF($1:$1,DM$5,16:16),2) -> 0 | DN16: =ROUND(SUMIF($1:$1,DN$5,16:16),2) -> 57.12 | ... ED16: =ROUND(SUMIF($1:$1,ED$5,16:16),2) -> 0 | EE16: =SUM(DG16:ED16) -> 361.41 | EF16: =ROUND(SUM(EE16-BT16),2) -> 0 | EG16: =IF(DN16<>0,DN16-EF16,0) -> 57.12 | EH16: =IF(EG16=0,DO16-EF16,DO16) -> 0 | EI16: =SUM(DG16:DM16)+SUM(DP16:ED16)+EG16+EH16 -> 361.41
A17: =_xlfn.CONCAT(D17,L17) -> Manaus38 | B17: 4151 | C17: 4151 | D17: Manaus | F17: AMBEV | G17: CONTRATO | H17: FOB | K17: PREFORMA | L17: 38 | M17: VD | V17: Virgem | W17: 0.4 | X17: ALPEK | Y17: =IF($X17="",0,HLOOKUP($H$3,Resina!$E$2:$AK$93,MATCH($D17&$X17&$Y$5,Resina!$A$2:$A$93,0))) -> 1283.4027 | Z17: 0.6 | AA17: VG | AB17: =IF($AA17="",0,HLOOKUP($H$3,Resina!$E$2:$AK$93,MATCH($D17&$AA17&$AB$5,Resina!$A$2:$A$93,0))) -> 1720.8738 | AC17: =$AC$7 -> 46091 | AD17: Mensal | AE17: =$AE$7 -> 45839 | AF17: MIL | AG17: =_xlfn.XLOOKUP($H$3,Resina!$2:$2,Resina!$3:$3,0) -> 5.2006167 | AH17: =(L17*((Y17*W17)+(AB17*Z17)))*AG17/1000 -> 305.50317 | AI17: 0.005 | AJ17: =AH17*AI17 -> 1.5275159 | AO17: =_xlfn.XLOOKUP($D17&$L17&$AK$3,'BD Conv'!$A:$A,'BD Conv'!$H:$H,0)*_xlfn.XLOOKUP($D17,'BD Conv'!$C$17:$C$19,'BD Conv'!$F$17:$F$19,0)*(1+(HLOOKUP($B17&AO$6,Indexadores!$C$2:$AH$32,MATCH($AE17,Indexadores!$A$2:$A$32,0)))) -> 14.28 | AS17: 0.005 | AT17: =(AU17+AO17)*AS17 -> 0.357 | AU17: =_xlfn.XLOOKUP($D17&$L17&$AK$3,'BD Conv'!$A:$A,'BD Conv'!$H:$H,0)*_xlfn.XLOOKUP($D17,'BD Conv'!$C$17:$C$19,'BD Conv'!$E$17:$E$19,0)*(1+(HLOOKUP($B17&AU$6,Indexadores!$C$2:$AH$32,MATCH($AE17,Indexadores!$A$2:$A$32,0)))) -> 57.12 | AV17: =SUM(AN17,AO17,AP17,(AQ17*AG17),AR17,AT17,AU17) -> 71.757 | AW17: =_xlfn.XLOOKUP($A17&$AK$3,'BD Conv'!$A:$A,'BD Conv'!$I:$I,0) -> 0 | AZ17: =SUM(AH17,AJ17,AK17,AL17,AV17,AW17:AY17) -> 378.78769 | BI17: =SUM(BA17,BB17,BC17,(BD17*AG17),BE17,BF17,BH17) -> 0 | BN17: =_xlfn.XLOOKUP($A17&$BA$3,'BD Conv'!$A:$A,'BD Conv'!$K:$K,0) -> 0 | BQ17: =SUM(BI17,BJ17,BK17,BM17,BN17,BO17,BP17) -> 0 | BR17: =-BQ17*$BR$3 -> 0 | BT17: =AZ17+BQ17+BR17+BS17 -> 378.78769 | BU17: =BV17-BT17 -> 95.526972 | BV17: =BT17/(1-(12%+1.65%+7.6%) +12%*(1.65%+7.6%)) -> 474.31466 | BY17: =BT17/CP17-1 -> 0.23403136 | BZ17: =(BT17-CP17)/AG17 -> 13.813027 | CA17: =(BT17-CK17-CL17-AL17-AX17-AY17-BO17-BP17+CQ17)/AG17 -> 13.813027 | CB17: =(BT17-AH17)/AG17 -> 14.091505 | CD17: =CP17*(1+$CD$5) -> 337.64657 | CE17: =(CD17-CP17)/AG17 -> 5.9022121 | CF17: =(CD17-CK17-CL17-AL17-AX17-AY17-BO17-BP17+CQ17)/AG17 -> 5.9022121 | CG17: =(CD17-AH17)/AG17 -> 6.1806897 | CI17: =IF($X17="",0,HLOOKUP($H$3,Resina!$E$2:$AK$93,MATCH($D17&$X17&$CI$5,Resina!$A$2:$A$93,0))) -> 1212.1409 | CJ17: =IF($AA17="",0,HLOOKUP($H$3,Resina!$E$2:$AK$93,MATCH($D17&$AA17&$CJ$5,Resina!$A$2:$A$93,0))) -> 1754.965 | CK17: =L17*((CI17*W17)+(CJ17*Z17))*AG17/1000 -> 303.9123 | CL17: =CK17*$CL$6 -> 3.039123 | CM17: =IF(D17="Manaus FORA",-((CK17/0.88*0.12)*(1-9.25%))," ") | CO17: =AX17+AY17+BO17+BP17+AL17+AN17+BJ17+BK17+BM17 -> 0 | CP17: =SUM(CK17:CO17) -> 306.95143 | DE17: =_xlfn.CONCAT(D17,L17) -> Manaus38 | DF17: =L17 -> 38 | DG17: =ROUND(SUMIF($1:$1,DG$5,17:17),2) -> 305.5 | DH17: =ROUND(SUMIF($1:$1,DH$5,17:17),2) -> 1.88 | DI17: =ROUND(SUMIF($1:$1,DI$5,17:17),2) -> 0 | DJ17: =ROUND(SUMIF($1:$1,DJ$5,17:17),2) -> 0 | DK17: =ROUND(SUMIF($1:$1,DK$5,17:17),2) -> 0 | DL17: =ROUND(SUMIF($1:$1,DL$5,17:17),2) -> 0 | DM17: =ROUND(SUMIF($1:$1,DM$5,17:17),2) -> 0 | DN17: =ROUND(SUMIF($1:$1,DN$5,17:17),2) -> 57.12 | ... ED17: =ROUND(SUMIF($1:$1,ED$5,17:17),2) -> 0 | EE17: =SUM(DG17:ED17) -> 378.78 | EF17: =ROUND(SUM(EE17-BT17),2) -> -0.01 | EG17: =IF(DN17<>0,DN17-EF17,0) -> 57.13 | EH17: =IF(EG17=0,DO17-EF17,DO17) -> 0 | EI17: =SUM(DG17:DM17)+SUM(DP17:ED17)+EG17+EH17 -> 378.79
A18: =_xlfn.CONCAT(D18,L18) -> Manaus38 | B18: 4151 | C18: 4151 | D18: Manaus | F18: AMBEV | G18: CONTRATO | H18: FOB | K18: PREFORMA | L18: 38 | M18: VD | V18: Virgem | W18: 0 | Y18: =IF($X18="",0,HLOOKUP($H$3,Resina!$E$2:$AK$93,MATCH($D18&$X18&$Y$5,Resina!$A$2:$A$93,0))) -> 0 | Z18: 1 | AA18: VG | AB18: =IF($AA18="",0,HLOOKUP($H$3,Resina!$E$2:$AK$93,MATCH($D18&$AA18&$AB$5,Resina!$A$2:$A$93,0))) -> 1720.8738 | AC18: =$AC$7 -> 46091 | AD18: Mensal | AE18: =$AE$7 -> 45839 | AF18: MIL | AG18: =_xlfn.XLOOKUP($H$3,Resina!$2:$2,Resina!$3:$3,0) -> 5.2006167 | AH18: =(L18*((Y18*W18)+(AB18*Z18)))*AG18/1000 -> 340.08498 | AI18: 0.005 | AJ18: =AH18*AI18 -> 1.7004249 | AO18: =_xlfn.XLOOKUP($D18&$L18&$AK$3,'BD Conv'!$A:$A,'BD Conv'!$H:$H,0)*_xlfn.XLOOKUP($D18,'BD Conv'!$C$17:$C$19,'BD Conv'!$F$17:$F$19,0)*(1+(HLOOKUP($B18&AO$6,Indexadores!$C$2:$AH$32,MATCH($AE18,Indexadores!$A$2:$A$32,0)))) -> 14.28 | AS18: 0.005 | AT18: =(AU18+AO18)*AS18 -> 0.357 | AU18: =_xlfn.XLOOKUP($D18&$L18&$AK$3,'BD Conv'!$A:$A,'BD Conv'!$H:$H,0)*_xlfn.XLOOKUP($D18,'BD Conv'!$C$17:$C$19,'BD Conv'!$E$17:$E$19,0)*(1+(HLOOKUP($B18&AU$6,Indexadores!$C$2:$AH$32,MATCH($AE18,Indexadores!$A$2:$A$32,0)))) -> 57.12 | AV18: =SUM(AN18,AO18,AP18,(AQ18*AG18),AR18,AT18,AU18) -> 71.757 | AW18: =_xlfn.XLOOKUP($A18&$AK$3,'BD Conv'!$A:$A,'BD Conv'!$I:$I,0) -> 0 | AZ18: =SUM(AH18,AJ18,AK18,AL18,AV18,AW18:AY18) -> 413.54241 | BI18: =SUM(BA18,BB18,BC18,(BD18*AG18),BE18,BF18,BH18) -> 0 | BN18: =_xlfn.XLOOKUP($A18&$BA$3,'BD Conv'!$A:$A,'BD Conv'!$K:$K,0) -> 0 | BQ18: =SUM(BI18,BJ18,BK18,BM18,BN18,BO18,BP18) -> 0 | BR18: =-BQ18*$BR$3 -> 0 | BT18: =AZ18+BQ18+BR18+BS18 -> 413.54241 | BU18: =BV18-BT18 -> 104.29181 | BV18: =BT18/(1-(12%+1.65%+7.6%) +12%*(1.65%+7.6%)) -> 517.83422 | BY18: =BT18/CP18-1 -> 0.18057012 | BZ18: =(BT18-CP18)/AG18 -> 12.162401 | CA18: =(BT18-CK18-CL18-AL18-AX18-AY18-BO18-BP18+CQ18)/AG18 -> 12.162401 | CB18: =(BT18-AH18)/AG18 -> 14.124753 | CD18: =CP18*(1+$CD$5) -> 385.31946 | CE18: =(CD18-CP18)/AG18 -> 6.7355555 | CF18: =(CD18-CK18-CL18-AL18-AX18-AY18-BO18-BP18+CQ18)/AG18 -> 6.7355555 | CG18: =(CD18-AH18)/AG18 -> 8.6979076 | CI18: =IF($X18="",0,HLOOKUP($H$3,Resina!$E$2:$AK$93,MATCH($D18&$X18&$CI$5,Resina!$A$2:$A$93,0))) -> 0 | CJ18: =IF($AA18="",0,HLOOKUP($H$3,Resina!$E$2:$AK$93,MATCH($D18&$AA18&$CJ$5,Resina!$A$2:$A$93,0))) -> 1754.965 | CK18: =L18*((CI18*W18)+(CJ18*Z18))*AG18/1000 -> 346.8222 | CL18: =CK18*$CL$6 -> 3.468222 | CM18: =IF(D18="Manaus FORA",-((CK18/0.88*0.12)*(1-9.25%))," ") | CO18: =AX18+AY18+BO18+BP18+AL18+AN18+BJ18+BK18+BM18 -> 0 | CP18: =SUM(CK18:CO18) -> 350.29042 | DE18: =_xlfn.CONCAT(D18,L18) -> Manaus38 | DF18: =L18 -> 38 | DG18: =ROUND(SUMIF($1:$1,DG$5,18:18),2) -> 340.08 | DH18: =ROUND(SUMIF($1:$1,DH$5,18:18),2) -> 2.06 | DI18: =ROUND(SUMIF($1:$1,DI$5,18:18),2) -> 0 | DJ18: =ROUND(SUMIF($1:$1,DJ$5,18:18),2) -> 0 | DK18: =ROUND(SUMIF($1:$1,DK$5,18:18),2) -> 0 | DL18: =ROUND(SUMIF($1:$1,DL$5,18:18),2) -> 0 | DM18: =ROUND(SUMIF($1:$1,DM$5,18:18),2) -> 0 | DN18: =ROUND(SUMIF($1:$1,DN$5,18:18),2) -> 57.12 | ... ED18: =ROUND(SUMIF($1:$1,ED$5,18:18),2) -> 0 | EE18: =SUM(DG18:ED18) -> 413.54 | EF18: =ROUND(SUM(EE18-BT18),2) -> 0 | EG18: =IF(DN18<>0,DN18-EF18,0) -> 57.12 | EH18: =IF(EG18=0,DO18-EF18,DO18) -> 0 | EI18: =SUM(DG18:DM18)+SUM(DP18:ED18)+EG18+EH18 -> 413.54
A19: =_xlfn.CONCAT(D19,L19) -> Manaus39.7 | B19: 4151 | C19: 4151 | D19: Manaus | F19: AMBEV | G19: CONTRATO | H19: FOB | K19: PREFORMA | L19: 39.7 | M19: CR | V19: Virgem | W19: 1 | X19: ALPEK | Y19: =IF($X19="",0,HLOOKUP($H$3,Resina!$E$2:$AK$93,MATCH($D19&$X19&$Y$5,Resina!$A$2:$A$93,0))) -> 1283.4027 | Z19: 0 | AA19: VG | AB19: =IF($AA19="",0,HLOOKUP($H$3,Resina!$E$2:$AK$93,MATCH($D19&$AA19&$AB$5,Resina!$A$2:$A$93,0))) -> 1720.8738 | AC19: =$AC$7 -> 46091 | AD19: Mensal | AE19: =$AE$7 -> 45839 | AF19: MIL | AG19: =_xlfn.XLOOKUP($H$3,Resina!$2:$2,Resina!$3:$3,0) -> 5.2006167 | AH19: =(L19*((Y19*W19)+(AB19*Z19)))*AG19/1000 -> 264.97708 | AI19: 0.005 | AJ19: =AH19*AI19 -> 1.3248854 | AO19: =_xlfn.XLOOKUP($D19&$L19&$AK$3,'BD Conv'!$A:$A,'BD Conv'!$H:$H,0)*_xlfn.XLOOKUP($D19,'BD Conv'!$C$17:$C$19,'BD Conv'!$F$17:$F$19,0)*(1+(HLOOKUP($B19&AO$6,Indexadores!$C$2:$AH$32,MATCH($AE19,Indexadores!$A$2:$A$32,0)))) -> 0 | AS19: 0.005 | AT19: =(AU19+AO19)*AS19 -> 0 | AU19: =_xlfn.XLOOKUP($D19&$L19&$AK$3,'BD Conv'!$A:$A,'BD Conv'!$H:$H,0)*_xlfn.XLOOKUP($D19,'BD Conv'!$C$17:$C$19,'BD Conv'!$E$17:$E$19,0)*(1+(HLOOKUP($B19&AU$6,Indexadores!$C$2:$AH$32,MATCH($AE19,Indexadores!$A$2:$A$32,0)))) -> 0 | AV19: =SUM(AN19,AO19,AP19,(AQ19*AG19),AR19,AT19,AU19) -> 0 | AW19: =_xlfn.XLOOKUP($A19&$AK$3,'BD Conv'!$A:$A,'BD Conv'!$I:$I,0) -> 0 | AZ19: =SUM(AH19,AJ19,AK19,AL19,AV19,AW19:AY19) -> 266.30196 | BI19: =SUM(BA19,BB19,BC19,(BD19*AG19),BE19,BF19,BH19) -> 0 | BN19: =_xlfn.XLOOKUP($A19&$BA$3,'BD Conv'!$A:$A,'BD Conv'!$K:$K,0) -> 0 | BQ19: =SUM(BI19,BJ19,BK19,BM19,BN19,BO19,BP19) -> 0 | BR19: =-BQ19*$BR$3 -> 0 | BT19: =AZ19+BQ19+BR19+BS19 -> 266.30196 | BU19: =BV19-BT19 -> 67.159048 | BV19: =BT19/(1-(12%+1.65%+7.6%) +12%*(1.65%+7.6%)) -> 333.46101 | BY19: =BT19/CP19-1 -> 0.053548477 | BZ19: =(BT19-CP19)/AG19 -> 2.6026282 | CA19: =(BT19-CK19-CL19-AL19-AX19-AY19-BO19-BP19+CQ19)/AG19 -> 2.6026282 | CB19: =(BT19-AH19)/AG19 -> 0.25475544 | CD19: =CP19*(1+$CD$5) -> 278.04336 | CE19: =(CD19-CP19)/AG19 -> 4.8603216 | CF19: =(CD19-CK19-CL19-AL19-AX19-AY19-BO19-BP19+CQ19)/AG19 -> 4.8603216 | CG19: =(CD19-AH19)/AG19 -> 2.5124488 | CI19: =IF($X19="",0,HLOOKUP($H$3,Resina!$E$2:$AK$93,MATCH($D19&$X19&$CI$5,Resina!$A$2:$A$93,0))) -> 1212.1409 | CJ19: =IF($AA19="",0,HLOOKUP($H$3,Resina!$E$2:$AK$93,MATCH($D19&$AA19&$CJ$5,Resina!$A$2:$A$93,0))) -> 1754.965 | CK19: =L19*((CI19*W19)+(CJ19*Z19))*AG19/1000 -> 250.26405 | CL19: =CK19*$CL$6 -> 2.5026405 | CM19: =IF(D19="Manaus FORA",-((CK19/0.88*0.12)*(1-9.25%))," ") | CO19: =AX19+AY19+BO19+BP19+AL19+AN19+BJ19+BK19+BM19 -> 0 | CP19: =SUM(CK19:CO19) -> 252.76669 | DE19: =_xlfn.CONCAT(D19,L19) -> Manaus39.7 | DF19: =L19 -> 39.7 | DG19: =ROUND(SUMIF($1:$1,DG$5,19:19),2) -> 264.98 | DH19: =ROUND(SUMIF($1:$1,DH$5,19:19),2) -> 1.32 | DI19: =ROUND(SUMIF($1:$1,DI$5,19:19),2) -> 0 | DJ19: =ROUND(SUMIF($1:$1,DJ$5,19:19),2) -> 0 | DK19: =ROUND(SUMIF($1:$1,DK$5,19:19),2) -> 0 | DL19: =ROUND(SUMIF($1:$1,DL$5,19:19),2) -> 0 | DM19: =ROUND(SUMIF($1:$1,DM$5,19:19),2) -> 0 | DN19: =ROUND(SUMIF($1:$1,DN$5,19:19),2) -> 0 | ... ED19: =ROUND(SUMIF($1:$1,ED$5,19:19),2) -> 0 | EE19: =SUM(DG19:ED19) -> 266.3 | EF19: =ROUND(SUM(EE19-BT19),2) -> 0 | EG19: =IF(DN19<>0,DN19-EF19,0) -> 0 | EH19: =IF(EG19=0,DO19-EF19,DO19) -> 0 | EI19: =SUM(DG19:DM19)+SUM(DP19:ED19)+EG19+EH19 -> 266.3
A20: =_xlfn.CONCAT(D20,L20) -> Manaus39.7 | B20: 4151 | C20: 4151 | D20: Manaus | F20: AMBEV | G20: CONTRATO | H20: FOB | K20: PREFORMA | L20: 39.7 | M20: CR | V20: Virgem | W20: 0.6 | X20: ALPEK | Y20: =IF($X20="",0,HLOOKUP($H$3,Resina!$E$2:$AK$93,MATCH($D20&$X20&$Y$5,Resina!$A$2:$A$93,0))) -> 1283.4027 | Z20: 0.4 | AA20: VG | AB20: =IF($AA20="",0,HLOOKUP($H$3,Resina!$E$2:$AK$93,MATCH($D20&$AA20&$AB$5,Resina!$A$2:$A$93,0))) -> 1720.8738 | AC20: =$AC$7 -> 46091 | AD20: Mensal | AE20: =$AE$7 -> 45839 | AF20: MIL | AG20: =_xlfn.XLOOKUP($H$3,Resina!$2:$2,Resina!$3:$3,0) -> 5.2006167 | AH20: =(L20*((Y20*W20)+(AB20*Z20)))*AG20/1000 -> 301.10597 | AI20: 0.005 | AJ20: =AH20*AI20 -> 1.5055299 | AO20: =_xlfn.XLOOKUP($D20&$L20&$AK$3,'BD Conv'!$A:$A,'BD Conv'!$H:$H,0)*_xlfn.XLOOKUP($D20,'BD Conv'!$C$17:$C$19,'BD Conv'!$F$17:$F$19,0)*(1+(HLOOKUP($B20&AO$6,Indexadores!$C$2:$AH$32,MATCH($AE20,Indexadores!$A$2:$A$32,0)))) -> 0 | AS20: 0.005 | AT20: =(AU20+AO20)*AS20 -> 0 | AU20: =_xlfn.XLOOKUP($D20&$L20&$AK$3,'BD Conv'!$A:$A,'BD Conv'!$H:$H,0)*_xlfn.XLOOKUP($D20,'BD Conv'!$C$17:$C$19,'BD Conv'!$E$17:$E$19,0)*(1+(HLOOKUP($B20&AU$6,Indexadores!$C$2:$AH$32,MATCH($AE20,Indexadores!$A$2:$A$32,0)))) -> 0 | AV20: =SUM(AN20,AO20,AP20,(AQ20*AG20),AR20,AT20,AU20) -> 0 | AW20: =_xlfn.XLOOKUP($A20&$AK$3,'BD Conv'!$A:$A,'BD Conv'!$I:$I,0) -> 0 | AZ20: =SUM(AH20,AJ20,AK20,AL20,AV20,AW20:AY20) -> 302.6115 | BI20: =SUM(BA20,BB20,BC20,(BD20*AG20),BE20,BF20,BH20) -> 0 | BN20: =_xlfn.XLOOKUP($A20&$BA$3,'BD Conv'!$A:$A,'BD Conv'!$K:$K,0) -> 0 | BQ20: =SUM(BI20,BJ20,BK20,BM20,BN20,BO20,BP20) -> 0 | BR20: =-BQ20*$BR$3 -> 0 | BT20: =AZ20+BQ20+BR20+BS20 -> 302.6115 | BU20: =BV20-BT20 -> 76.315998 | BV20: =BT20/(1-(12%+1.65%+7.6%) +12%*(1.65%+7.6%)) -> 378.9275 | BY20: =BT20/CP20-1 -> 0.015323084 | BZ20: =(BT20-CP20)/AG20 -> 0.87815767 | CA20: =(BT20-CK20-CL20-AL20-AX20-AY20-BO20-BP20+CQ20)/AG20 -> 0.87815767 | CB20: =(BT20-AH20)/AG20 -> 0.28949064 | CD20: =CP20*(1+$CD$5) -> 327.84899 | CE20: =(CD20-CP20)/AG20 -> 5.7309461 | CF20: =(CD20-CK20-CL20-AL20-AX20-AY20-BO20-BP20+CQ20)/AG20 -> 5.7309461 | CG20: =(CD20-AH20)/AG20 -> 5.1422791 | CI20: =IF($X20="",0,HLOOKUP($H$3,Resina!$E$2:$AK$93,MATCH($D20&$X20&$CI$5,Resina!$A$2:$A$93,0))) -> 1212.1409 | CJ20: =IF($AA20="",0,HLOOKUP($H$3,Resina!$E$2:$AK$93,MATCH($D20&$AA20&$CJ$5,Resina!$A$2:$A$93,0))) -> 1754.965 | CK20: =L20*((CI20*W20)+(CJ20*Z20))*AG20/1000 -> 295.0936 | CL20: =CK20*$CL$6 -> 2.950936 | CM20: =IF(D20="Manaus FORA",-((CK20/0.88*0.12)*(1-9.25%))," ") | CO20: =AX20+AY20+BO20+BP20+AL20+AN20+BJ20+BK20+BM20 -> 0 | CP20: =SUM(CK20:CO20) -> 298.04454 | DE20: =_xlfn.CONCAT(D20,L20) -> Manaus39.7 | DF20: =L20 -> 39.7 | DG20: =ROUND(SUMIF($1:$1,DG$5,20:20),2) -> 301.11 | DH20: =ROUND(SUMIF($1:$1,DH$5,20:20),2) -> 1.51 | DI20: =ROUND(SUMIF($1:$1,DI$5,20:20),2) -> 0 | DJ20: =ROUND(SUMIF($1:$1,DJ$5,20:20),2) -> 0 | DK20: =ROUND(SUMIF($1:$1,DK$5,20:20),2) -> 0 | DL20: =ROUND(SUMIF($1:$1,DL$5,20:20),2) -> 0 | DM20: =ROUND(SUMIF($1:$1,DM$5,20:20),2) -> 0 | DN20: =ROUND(SUMIF($1:$1,DN$5,20:20),2) -> 0 | ... ED20: =ROUND(SUMIF($1:$1,ED$5,20:20),2) -> 0 | EE20: =SUM(DG20:ED20) -> 302.62 | EF20: =ROUND(SUM(EE20-BT20),2) -> 0.01 | EG20: =IF(DN20<>0,DN20-EF20,0) -> 0 | EH20: =IF(EG20=0,DO20-EF20,DO20) -> -0.01 | EI20: =SUM(DG20:DM20)+SUM(DP20:ED20)+EG20+EH20 -> 302.61
A21: =_xlfn.CONCAT(D21,L21) -> Manaus39.7 | B21: 4151 | C21: 4151 | D21: Manaus | F21: AMBEV | G21: CONTRATO | H21: FOB | K21: PREFORMA | L21: 39.7 | M21: CR | V21: Virgem | W21: 0.4 | X21: ALPEK | Y21: =IF($X21="",0,HLOOKUP($H$3,Resina!$E$2:$AK$93,MATCH($D21&$X21&$Y$5,Resina!$A$2:$A$93,0))) -> 1283.4027 | Z21: 0.6 | AA21: VG | AB21: =IF($AA21="",0,HLOOKUP($H$3,Resina!$E$2:$AK$93,MATCH($D21&$AA21&$AB$5,Resina!$A$2:$A$93,0))) -> 1720.8738 | AC21: =$AC$7 -> 46091 | AD21: Mensal | AE21: =$AE$7 -> 45839 | AF21: MIL | AG21: =_xlfn.XLOOKUP($H$3,Resina!$2:$2,Resina!$3:$3,0) -> 5.2006167 | AH21: =(L21*((Y21*W21)+(AB21*Z21)))*AG21/1000 -> 319.17042 | AI21: 0.005 | AJ21: =AH21*AI21 -> 1.5958521 | AO21: =_xlfn.XLOOKUP($D21&$L21&$AK$3,'BD Conv'!$A:$A,'BD Conv'!$H:$H,0)*_xlfn.XLOOKUP($D21,'BD Conv'!$C$17:$C$19,'BD Conv'!$F$17:$F$19,0)*(1+(HLOOKUP($B21&AO$6,Indexadores!$C$2:$AH$32,MATCH($AE21,Indexadores!$A$2:$A$32,0)))) -> 0 | AS21: 0.005 | AT21: =(AU21+AO21)*AS21 -> 0 | AU21: =_xlfn.XLOOKUP($D21&$L21&$AK$3,'BD Conv'!$A:$A,'BD Conv'!$H:$H,0)*_xlfn.XLOOKUP($D21,'BD Conv'!$C$17:$C$19,'BD Conv'!$E$17:$E$19,0)*(1+(HLOOKUP($B21&AU$6,Indexadores!$C$2:$AH$32,MATCH($AE21,Indexadores!$A$2:$A$32,0)))) -> 0 | AV21: =SUM(AN21,AO21,AP21,(AQ21*AG21),AR21,AT21,AU21) -> 0 | AW21: =_xlfn.XLOOKUP($A21&$AK$3,'BD Conv'!$A:$A,'BD Conv'!$I:$I,0) -> 0 | AZ21: =SUM(AH21,AJ21,AK21,AL21,AV21,AW21:AY21) -> 320.76627 | BI21: =SUM(BA21,BB21,BC21,(BD21*AG21),BE21,BF21,BH21) -> 0 | BN21: =_xlfn.XLOOKUP($A21&$BA$3,'BD Conv'!$A:$A,'BD Conv'!$K:$K,0) -> 0 | BQ21: =SUM(BI21,BJ21,BK21,BM21,BN21,BO21,BP21) -> 0 | BR21: =-BQ21*$BR$3 -> 0 | BT21: =AZ21+BQ21+BR21+BS21 -> 320.76627 | BU21: =BV21-BT21 -> 80.894474 | BV21: =BT21/(1-(12%+1.65%+7.6%) +12%*(1.65%+7.6%)) -> 401.66074 | BY21: =BT21/CP21-1 -> 0.00025821841 | BZ21: =(BT21-CP21)/AG21 -> 0.015922414 | CA21: =(BT21-CK21-CL21-AL21-AX21-AY21-BO21-BP21+CQ21)/AG21 -> 0.015922414 | CB21: =(BT21-AH21)/AG21 -> 0.30685824 | CD21: =CP21*(1+$CD$5) -> 352.75181 | CE21: =(CD21-CP21)/AG21 -> 6.1662584 | CF21: =(CD21-CK21-CL21-AL21-AX21-AY21-BO21-BP21+CQ21)/AG21 -> 6.1662584 | CG21: =(CD21-AH21)/AG21 -> 6.4571942 | CI21: =IF($X21="",0,HLOOKUP($H$3,Resina!$E$2:$AK$93,MATCH($D21&$X21&$CI$5,Resina!$A$2:$A$93,0))) -> 1212.1409 | CJ21: =IF($AA21="",0,HLOOKUP($H$3,Resina!$E$2:$AK$93,MATCH($D21&$AA21&$CJ$5,Resina!$A$2:$A$93,0))) -> 1754.965 | CK21: =L21*((CI21*W21)+(CJ21*Z21))*AG21/1000 -> 317.50838 | CL21: =CK21*$CL$6 -> 3.1750838 | CM21: =IF(D21="Manaus FORA",-((CK21/0.88*0.12)*(1-9.25%))," ") | CO21: =AX21+AY21+BO21+BP21+AL21+AN21+BJ21+BK21+BM21 -> 0 | CP21: =SUM(CK21:CO21) -> 320.68346 | DE21: =_xlfn.CONCAT(D21,L21) -> Manaus39.7 | DF21: =L21 -> 39.7 | DG21: =ROUND(SUMIF($1:$1,DG$5,21:21),2) -> 319.17 | DH21: =ROUND(SUMIF($1:$1,DH$5,21:21),2) -> 1.6 | DI21: =ROUND(SUMIF($1:$1,DI$5,21:21),2) -> 0 | DJ21: =ROUND(SUMIF($1:$1,DJ$5,21:21),2) -> 0 | DK21: =ROUND(SUMIF($1:$1,DK$5,21:21),2) -> 0 | DL21: =ROUND(SUMIF($1:$1,DL$5,21:21),2) -> 0 | DM21: =ROUND(SUMIF($1:$1,DM$5,21:21),2) -> 0 | DN21: =ROUND(SUMIF($1:$1,DN$5,21:21),2) -> 0 | ... ED21: =ROUND(SUMIF($1:$1,ED$5,21:21),2) -> 0 | EE21: =SUM(DG21:ED21) -> 320.77 | EF21: =ROUND(SUM(EE21-BT21),2) -> 0 | EG21: =IF(DN21<>0,DN21-EF21,0) -> 0 | EH21: =IF(EG21=0,DO21-EF21,DO21) -> 0 | EI21: =SUM(DG21:DM21)+SUM(DP21:ED21)+EG21+EH21 -> 320.77
A22: =_xlfn.CONCAT(D22,L22) -> Manaus39.7 | B22: 4151 | C22: 4151 | D22: Manaus | F22: AMBEV | G22: CONTRATO | H22: FOB | K22: PREFORMA | L22: 39.7 | M22: CR | V22: Virgem | W22: 0 | Y22: =IF($X22="",0,HLOOKUP($H$3,Resina!$E$2:$AK$93,MATCH($D22&$X22&$Y$5,Resina!$A$2:$A$93,0))) -> 0 | Z22: 1 | AA22: VG | AB22: =IF($AA22="",0,HLOOKUP($H$3,Resina!$E$2:$AK$93,MATCH($D22&$AA22&$AB$5,Resina!$A$2:$A$93,0))) -> 1720.8738 | AC22: =$AC$7 -> 46091 | AD22: Mensal | AE22: =$AE$7 -> 45839 | AF22: MIL | AG22: =_xlfn.XLOOKUP($H$3,Resina!$2:$2,Resina!$3:$3,0) -> 5.2006167 | AH22: =(L22*((Y22*W22)+(AB22*Z22)))*AG22/1000 -> 355.29931 | AI22: 0.005 | AJ22: =AH22*AI22 -> 1.7764965 | AO22: =_xlfn.XLOOKUP($D22&$L22&$AK$3,'BD Conv'!$A:$A,'BD Conv'!$H:$H,0)*_xlfn.XLOOKUP($D22,'BD Conv'!$C$17:$C$19,'BD Conv'!$F$17:$F$19,0)*(1+(HLOOKUP($B22&AO$6,Indexadores!$C$2:$AH$32,MATCH($AE22,Indexadores!$A$2:$A$32,0)))) -> 0 | AS22: 0.005 | AT22: =(AU22+AO22)*AS22 -> 0 | AU22: =_xlfn.XLOOKUP($D22&$L22&$AK$3,'BD Conv'!$A:$A,'BD Conv'!$H:$H,0)*_xlfn.XLOOKUP($D22,'BD Conv'!$C$17:$C$19,'BD Conv'!$E$17:$E$19,0)*(1+(HLOOKUP($B22&AU$6,Indexadores!$C$2:$AH$32,MATCH($AE22,Indexadores!$A$2:$A$32,0)))) -> 0 | AV22: =SUM(AN22,AO22,AP22,(AQ22*AG22),AR22,AT22,AU22) -> 0 | AW22: =_xlfn.XLOOKUP($A22&$AK$3,'BD Conv'!$A:$A,'BD Conv'!$I:$I,0) -> 0 | AZ22: =SUM(AH22,AJ22,AK22,AL22,AV22,AW22:AY22) -> 357.07581 | BI22: =SUM(BA22,BB22,BC22,(BD22*AG22),BE22,BF22,BH22) -> 0 | BN22: =_xlfn.XLOOKUP($A22&$BA$3,'BD Conv'!$A:$A,'BD Conv'!$K:$K,0) -> 0 | BQ22: =SUM(BI22,BJ22,BK22,BM22,BN22,BO22,BP22) -> 0 | BR22: =-BQ22*$BR$3 -> 0 | BT22: =AZ22+BQ22+BR22+BS22 -> 357.07581 | BU22: =BV22-BT22 -> 90.051424 | BV22: =BT22/(1-(12%+1.65%+7.6%) +12%*(1.65%+7.6%)) -> 447.12723 | BY22: =BT22/CP22-1 -> -0.024279899 | BZ22: =(BT22-CP22)/AG22 -> -1.7085481 | CA22: =(BT22-CK22-CL22-AL22-AX22-AY22-BO22-BP22+CQ22)/AG22 -> -1.7085481 | CB22: =(BT22-AH22)/AG22 -> 0.34159344 | CD22: =CP22*(1+$CD$5) -> 402.55744 | CE22: =(CD22-CP22)/AG22 -> 7.036883 | CF22: =(CD22-CK22-CL22-AL22-AX22-AY22-BO22-BP22+CQ22)/AG22 -> 7.036883 | CG22: =(CD22-AH22)/AG22 -> 9.0870245 | CI22: =IF($X22="",0,HLOOKUP($H$3,Resina!$E$2:$AK$93,MATCH($D22&$X22&$CI$5,Resina!$A$2:$A$93,0))) -> 0 | CJ22: =IF($AA22="",0,HLOOKUP($H$3,Resina!$E$2:$AK$93,MATCH($D22&$AA22&$CJ$5,Resina!$A$2:$A$93,0))) -> 1754.965 | CK22: =L22*((CI22*W22)+(CJ22*Z22))*AG22/1000 -> 362.33793 | CL22: =CK22*$CL$6 -> 3.6233793 | CM22: =IF(D22="Manaus FORA",-((CK22/0.88*0.12)*(1-9.25%))," ") | CO22: =AX22+AY22+BO22+BP22+AL22+AN22+BJ22+BK22+BM22 -> 0 | CP22: =SUM(CK22:CO22) -> 365.96131 | DE22: =_xlfn.CONCAT(D22,L22) -> Manaus39.7 | DF22: =L22 -> 39.7 | DG22: =ROUND(SUMIF($1:$1,DG$5,22:22),2) -> 355.3 | DH22: =ROUND(SUMIF($1:$1,DH$5,22:22),2) -> 1.78 | DI22: =ROUND(SUMIF($1:$1,DI$5,22:22),2) -> 0 | DJ22: =ROUND(SUMIF($1:$1,DJ$5,22:22),2) -> 0 | DK22: =ROUND(SUMIF($1:$1,DK$5,22:22),2) -> 0 | DL22: =ROUND(SUMIF($1:$1,DL$5,22:22),2) -> 0 | DM22: =ROUND(SUMIF($1:$1,DM$5,22:22),2) -> 0 | DN22: =ROUND(SUMIF($1:$1,DN$5,22:22),2) -> 0 | ... ED22: =ROUND(SUMIF($1:$1,ED$5,22:22),2) -> 0 | EE22: =SUM(DG22:ED22) -> 357.08 | EF22: =ROUND(SUM(EE22-BT22),2) -> 0 | EG22: =IF(DN22<>0,DN22-EF22,0) -> 0 | EH22: =IF(EG22=0,DO22-EF22,DO22) -> 0 | EI22: =SUM(DG22:DM22)+SUM(DP22:ED22)+EG22+EH22 -> 357.08
A23: =_xlfn.CONCAT(D23,L23) -> Manaus39.7 | B23: 4151 | C23: 4151 | D23: Manaus | F23: AMBEV | G23: CONTRATO | H23: FOB | K23: PREFORMA | L23: 39.7 | M23: VD | V23: Virgem | W23: 1 | X23: ALPEK | Y23: =IF($X23="",0,HLOOKUP($H$3,Resina!$E$2:$AK$93,MATCH($D23&$X23&$Y$5,Resina!$A$2:$A$93,0))) -> 1283.4027 | Z23: 0 | AA23: VG | AB23: =IF($AA23="",0,HLOOKUP($H$3,Resina!$E$2:$AK$93,MATCH($D23&$AA23&$AB$5,Resina!$A$2:$A$93,0))) -> 1720.8738 | AC23: =$AC$7 -> 46091 | AD23: Mensal | AE23: =$AE$7 -> 45839 | AF23: MIL | AG23: =_xlfn.XLOOKUP($H$3,Resina!$2:$2,Resina!$3:$3,0) -> 5.2006167 | AH23: =(L23*((Y23*W23)+(AB23*Z23)))*AG23/1000 -> 264.97708 | AI23: 0.005 | AJ23: =AH23*AI23 -> 1.3248854 | AO23: =_xlfn.XLOOKUP($D23&$L23&$AK$3,'BD Conv'!$A:$A,'BD Conv'!$H:$H,0)*_xlfn.XLOOKUP($D23,'BD Conv'!$C$17:$C$19,'BD Conv'!$F$17:$F$19,0)*(1+(HLOOKUP($B23&AO$6,Indexadores!$C$2:$AH$32,MATCH($AE23,Indexadores!$A$2:$A$32,0)))) -> 0 | AS23: 0.005 | AT23: =(AU23+AO23)*AS23 -> 0 | AU23: =_xlfn.XLOOKUP($D23&$L23&$AK$3,'BD Conv'!$A:$A,'BD Conv'!$H:$H,0)*_xlfn.XLOOKUP($D23,'BD Conv'!$C$17:$C$19,'BD Conv'!$E$17:$E$19,0)*(1+(HLOOKUP($B23&AU$6,Indexadores!$C$2:$AH$32,MATCH($AE23,Indexadores!$A$2:$A$32,0)))) -> 0 | AV23: =SUM(AN23,AO23,AP23,(AQ23*AG23),AR23,AT23,AU23) -> 0 | AW23: =_xlfn.XLOOKUP($A23&$AK$3,'BD Conv'!$A:$A,'BD Conv'!$I:$I,0) -> 0 | AZ23: =SUM(AH23,AJ23,AK23,AL23,AV23,AW23:AY23) -> 266.30196 | BI23: =SUM(BA23,BB23,BC23,(BD23*AG23),BE23,BF23,BH23) -> 0 | BN23: =_xlfn.XLOOKUP($A23&$BA$3,'BD Conv'!$A:$A,'BD Conv'!$K:$K,0) -> 0 | BQ23: =SUM(BI23,BJ23,BK23,BM23,BN23,BO23,BP23) -> 0 | BR23: =-BQ23*$BR$3 -> 0 | BT23: =AZ23+BQ23+BR23+BS23 -> 266.30196 | BU23: =BV23-BT23 -> 67.159048 | BV23: =BT23/(1-(12%+1.65%+7.6%) +12%*(1.65%+7.6%)) -> 333.46101 | BY23: =BT23/CP23-1 -> 0.053548477 | BZ23: =(BT23-CP23)/AG23 -> 2.6026282 | CA23: =(BT23-CK23-CL23-AL23-AX23-AY23-BO23-BP23+CQ23)/AG23 -> 2.6026282 | CB23: =(BT23-AH23)/AG23 -> 0.25475544 | CD23: =CP23*(1+$CD$5) -> 278.04336 | CE23: =(CD23-CP23)/AG23 -> 4.8603216 | CF23: =(CD23-CK23-CL23-AL23-AX23-AY23-BO23-BP23+CQ23)/AG23 -> 4.8603216 | CG23: =(CD23-AH23)/AG23 -> 2.5124488 | CI23: =IF($X23="",0,HLOOKUP($H$3,Resina!$E$2:$AK$93,MATCH($D23&$X23&$CI$5,Resina!$A$2:$A$93,0))) -> 1212.1409 | CJ23: =IF($AA23="",0,HLOOKUP($H$3,Resina!$E$2:$AK$93,MATCH($D23&$AA23&$CJ$5,Resina!$A$2:$A$93,0))) -> 1754.965 | CK23: =L23*((CI23*W23)+(CJ23*Z23))*AG23/1000 -> 250.26405 | CL23: =CK23*$CL$6 -> 2.5026405 | CM23: =IF(D23="Manaus FORA",-((CK23/0.88*0.12)*(1-9.25%))," ") | CO23: =AX23+AY23+BO23+BP23+AL23+AN23+BJ23+BK23+BM23 -> 0 | CP23: =SUM(CK23:CO23) -> 252.76669 | DE23: =_xlfn.CONCAT(D23,L23) -> Manaus39.7 | DF23: =L23 -> 39.7 | DG23: =ROUND(SUMIF($1:$1,DG$5,23:23),2) -> 264.98 | DH23: =ROUND(SUMIF($1:$1,DH$5,23:23),2) -> 1.32 | DI23: =ROUND(SUMIF($1:$1,DI$5,23:23),2) -> 0 | DJ23: =ROUND(SUMIF($1:$1,DJ$5,23:23),2) -> 0 | DK23: =ROUND(SUMIF($1:$1,DK$5,23:23),2) -> 0 | DL23: =ROUND(SUMIF($1:$1,DL$5,23:23),2) -> 0 | DM23: =ROUND(SUMIF($1:$1,DM$5,23:23),2) -> 0 | DN23: =ROUND(SUMIF($1:$1,DN$5,23:23),2) -> 0 | ... ED23: =ROUND(SUMIF($1:$1,ED$5,23:23),2) -> 0 | EE23: =SUM(DG23:ED23) -> 266.3 | EF23: =ROUND(SUM(EE23-BT23),2) -> 0 | EG23: =IF(DN23<>0,DN23-EF23,0) -> 0 | EH23: =IF(EG23=0,DO23-EF23,DO23) -> 0 | EI23: =SUM(DG23:DM23)+SUM(DP23:ED23)+EG23+EH23 -> 266.3
A24: =_xlfn.CONCAT(D24,L24) -> Manaus39.7 | B24: 4151 | C24: 4151 | D24: Manaus | F24: AMBEV | G24: CONTRATO | H24: FOB | K24: PREFORMA | L24: 39.7 | M24: VD | V24: Virgem | W24: 0.6 | X24: ALPEK | Y24: =IF($X24="",0,HLOOKUP($H$3,Resina!$E$2:$AK$93,MATCH($D24&$X24&$Y$5,Resina!$A$2:$A$93,0))) -> 1283.4027 | Z24: 0.4 | AA24: VG | AB24: =IF($AA24="",0,HLOOKUP($H$3,Resina!$E$2:$AK$93,MATCH($D24&$AA24&$AB$5,Resina!$A$2:$A$93,0))) -> 1720.8738 | AC24: =$AC$7 -> 46091 | AD24: Mensal | AE24: =$AE$7 -> 45839 | AF24: MIL | AG24: =_xlfn.XLOOKUP($H$3,Resina!$2:$2,Resina!$3:$3,0) -> 5.2006167 | AH24: =(L24*((Y24*W24)+(AB24*Z24)))*AG24/1000 -> 301.10597 | AI24: 0.005 | AJ24: =AH24*AI24 -> 1.5055299 | AO24: =_xlfn.XLOOKUP($D24&$L24&$AK$3,'BD Conv'!$A:$A,'BD Conv'!$H:$H,0)*_xlfn.XLOOKUP($D24,'BD Conv'!$C$17:$C$19,'BD Conv'!$F$17:$F$19,0)*(1+(HLOOKUP($B24&AO$6,Indexadores!$C$2:$AH$32,MATCH($AE24,Indexadores!$A$2:$A$32,0)))) -> 0 | AS24: 0.005 | AT24: =(AU24+AO24)*AS24 -> 0 | AU24: =_xlfn.XLOOKUP($D24&$L24&$AK$3,'BD Conv'!$A:$A,'BD Conv'!$H:$H,0)*_xlfn.XLOOKUP($D24,'BD Conv'!$C$17:$C$19,'BD Conv'!$E$17:$E$19,0)*(1+(HLOOKUP($B24&AU$6,Indexadores!$C$2:$AH$32,MATCH($AE24,Indexadores!$A$2:$A$32,0)))) -> 0 | AV24: =SUM(AN24,AO24,AP24,(AQ24*AG24),AR24,AT24,AU24) -> 0 | AW24: =_xlfn.XLOOKUP($A24&$AK$3,'BD Conv'!$A:$A,'BD Conv'!$I:$I,0) -> 0 | AZ24: =SUM(AH24,AJ24,AK24,AL24,AV24,AW24:AY24) -> 302.6115 | BI24: =SUM(BA24,BB24,BC24,(BD24*AG24),BE24,BF24,BH24) -> 0 | BN24: =_xlfn.XLOOKUP($A24&$BA$3,'BD Conv'!$A:$A,'BD Conv'!$K:$K,0) -> 0 | BQ24: =SUM(BI24,BJ24,BK24,BM24,BN24,BO24,BP24) -> 0 | BR24: =-BQ24*$BR$3 -> 0 | BT24: =AZ24+BQ24+BR24+BS24 -> 302.6115 | BU24: =BV24-BT24 -> 76.315998 | BV24: =BT24/(1-(12%+1.65%+7.6%) +12%*(1.65%+7.6%)) -> 378.9275 | BY24: =BT24/CP24-1 -> 0.015323084 | BZ24: =(BT24-CP24)/AG24 -> 0.87815767 | CA24: =(BT24-CK24-CL24-AL24-AX24-AY24-BO24-BP24+CQ24)/AG24 -> 0.87815767 | CB24: =(BT24-AH24)/AG24 -> 0.28949064 | CD24: =CP24*(1+$CD$5) -> 327.84899 | CE24: =(CD24-CP24)/AG24 -> 5.7309461 | CF24: =(CD24-CK24-CL24-AL24-AX24-AY24-BO24-BP24+CQ24)/AG24 -> 5.7309461 | CG24: =(CD24-AH24)/AG24 -> 5.1422791 | CI24: =IF($X24="",0,HLOOKUP($H$3,Resina!$E$2:$AK$93,MATCH($D24&$X24&$CI$5,Resina!$A$2:$A$93,0))) -> 1212.1409 | CJ24: =IF($AA24="",0,HLOOKUP($H$3,Resina!$E$2:$AK$93,MATCH($D24&$AA24&$CJ$5,Resina!$A$2:$A$93,0))) -> 1754.965 | CK24: =L24*((CI24*W24)+(CJ24*Z24))*AG24/1000 -> 295.0936 | CL24: =CK24*$CL$6 -> 2.950936 | CM24: =IF(D24="Manaus FORA",-((CK24/0.88*0.12)*(1-9.25%))," ") | CO24: =AX24+AY24+BO24+BP24+AL24+AN24+BJ24+BK24+BM24 -> 0 | CP24: =SUM(CK24:CO24) -> 298.04454 | DE24: =_xlfn.CONCAT(D24,L24) -> Manaus39.7 | DF24: =L24 -> 39.7 | DG24: =ROUND(SUMIF($1:$1,DG$5,24:24),2) -> 301.11 | DH24: =ROUND(SUMIF($1:$1,DH$5,24:24),2) -> 1.51 | DI24: =ROUND(SUMIF($1:$1,DI$5,24:24),2) -> 0 | DJ24: =ROUND(SUMIF($1:$1,DJ$5,24:24),2) -> 0 | DK24: =ROUND(SUMIF($1:$1,DK$5,24:24),2) -> 0 | DL24: =ROUND(SUMIF($1:$1,DL$5,24:24),2) -> 0 | DM24: =ROUND(SUMIF($1:$1,DM$5,24:24),2) -> 0 | DN24: =ROUND(SUMIF($1:$1,DN$5,24:24),2) -> 0 | ... ED24: =ROUND(SUMIF($1:$1,ED$5,24:24),2) -> 0 | EE24: =SUM(DG24:ED24) -> 302.62 | EF24: =ROUND(SUM(EE24-BT24),2) -> 0.01 | EG24: =IF(DN24<>0,DN24-EF24,0) -> 0 | EH24: =IF(EG24=0,DO24-EF24,DO24) -> -0.01 | EI24: =SUM(DG24:DM24)+SUM(DP24:ED24)+EG24+EH24 -> 302.61
A25: =_xlfn.CONCAT(D25,L25) -> Manaus39.7 | B25: 4151 | C25: 4151 | D25: Manaus | F25: AMBEV | G25: CONTRATO | H25: FOB | K25: PREFORMA | L25: 39.7 | M25: VD | V25: Virgem | W25: 0.4 | X25: ALPEK | Y25: =IF($X25="",0,HLOOKUP($H$3,Resina!$E$2:$AK$93,MATCH($D25&$X25&$Y$5,Resina!$A$2:$A$93,0))) -> 1283.4027 | Z25: 0.6 | AA25: VG | AB25: =IF($AA25="",0,HLOOKUP($H$3,Resina!$E$2:$AK$93,MATCH($D25&$AA25&$AB$5,Resina!$A$2:$A$93,0))) -> 1720.8738 | AC25: =$AC$7 -> 46091 | AD25: Mensal | AE25: =$AE$7 -> 45839 | AF25: MIL | AG25: =_xlfn.XLOOKUP($H$3,Resina!$2:$2,Resina!$3:$3,0) -> 5.2006167 | AH25: =(L25*((Y25*W25)+(AB25*Z25)))*AG25/1000 -> 319.17042 | AI25: 0.005 | AJ25: =AH25*AI25 -> 1.5958521 | AO25: =_xlfn.XLOOKUP($D25&$L25&$AK$3,'BD Conv'!$A:$A,'BD Conv'!$H:$H,0)*_xlfn.XLOOKUP($D25,'BD Conv'!$C$17:$C$19,'BD Conv'!$F$17:$F$19,0)*(1+(HLOOKUP($B25&AO$6,Indexadores!$C$2:$AH$32,MATCH($AE25,Indexadores!$A$2:$A$32,0)))) -> 0 | AS25: 0.005 | AT25: =(AU25+AO25)*AS25 -> 0 | AU25: =_xlfn.XLOOKUP($D25&$L25&$AK$3,'BD Conv'!$A:$A,'BD Conv'!$H:$H,0)*_xlfn.XLOOKUP($D25,'BD Conv'!$C$17:$C$19,'BD Conv'!$E$17:$E$19,0)*(1+(HLOOKUP($B25&AU$6,Indexadores!$C$2:$AH$32,MATCH($AE25,Indexadores!$A$2:$A$32,0)))) -> 0 | AV25: =SUM(AN25,AO25,AP25,(AQ25*AG25),AR25,AT25,AU25) -> 0 | AW25: =_xlfn.XLOOKUP($A25&$AK$3,'BD Conv'!$A:$A,'BD Conv'!$I:$I,0) -> 0 | AZ25: =SUM(AH25,AJ25,AK25,AL25,AV25,AW25:AY25) -> 320.76627 | BI25: =SUM(BA25,BB25,BC25,(BD25*AG25),BE25,BF25,BH25) -> 0 | BN25: =_xlfn.XLOOKUP($A25&$BA$3,'BD Conv'!$A:$A,'BD Conv'!$K:$K,0) -> 0 | BQ25: =SUM(BI25,BJ25,BK25,BM25,BN25,BO25,BP25) -> 0 | BR25: =-BQ25*$BR$3 -> 0 | BT25: =AZ25+BQ25+BR25+BS25 -> 320.76627 | BU25: =BV25-BT25 -> 80.894474 | BV25: =BT25/(1-(12%+1.65%+7.6%) +12%*(1.65%+7.6%)) -> 401.66074 | BY25: =BT25/CP25-1 -> 0.00025821841 | BZ25: =(BT25-CP25)/AG25 -> 0.015922414 | CA25: =(BT25-CK25-CL25-AL25-AX25-AY25-BO25-BP25+CQ25)/AG25 -> 0.015922414 | CB25: =(BT25-AH25)/AG25 -> 0.30685824 | CD25: =CP25*(1+$CD$5) -> 352.75181 | CE25: =(CD25-CP25)/AG25 -> 6.1662584 | CF25: =(CD25-CK25-CL25-AL25-AX25-AY25-BO25-BP25+CQ25)/AG25 -> 6.1662584 | CG25: =(CD25-AH25)/AG25 -> 6.4571942 | CI25: =IF($X25="",0,HLOOKUP($H$3,Resina!$E$2:$AK$93,MATCH($D25&$X25&$CI$5,Resina!$A$2:$A$93,0))) -> 1212.1409 | CJ25: =IF($AA25="",0,HLOOKUP($H$3,Resina!$E$2:$AK$93,MATCH($D25&$AA25&$CJ$5,Resina!$A$2:$A$93,0))) -> 1754.965 | CK25: =L25*((CI25*W25)+(CJ25*Z25))*AG25/1000 -> 317.50838 | CL25: =CK25*$CL$6 -> 3.1750838 | CM25: =IF(D25="Manaus FORA",-((CK25/0.88*0.12)*(1-9.25%))," ") | CO25: =AX25+AY25+BO25+BP25+AL25+AN25+BJ25+BK25+BM25 -> 0 | CP25: =SUM(CK25:CO25) -> 320.68346 | DE25: =_xlfn.CONCAT(D25,L25) -> Manaus39.7 | DF25: =L25 -> 39.7 | DG25: =ROUND(SUMIF($1:$1,DG$5,25:25),2) -> 319.17 | DH25: =ROUND(SUMIF($1:$1,DH$5,25:25),2) -> 1.6 | DI25: =ROUND(SUMIF($1:$1,DI$5,25:25),2) -> 0 | DJ25: =ROUND(SUMIF($1:$1,DJ$5,25:25),2) -> 0 | DK25: =ROUND(SUMIF($1:$1,DK$5,25:25),2) -> 0 | DL25: =ROUND(SUMIF($1:$1,DL$5,25:25),2) -> 0 | DM25: =ROUND(SUMIF($1:$1,DM$5,25:25),2) -> 0 | DN25: =ROUND(SUMIF($1:$1,DN$5,25:25),2) -> 0 | ... ED25: =ROUND(SUMIF($1:$1,ED$5,25:25),2) -> 0 | EE25: =SUM(DG25:ED25) -> 320.77 | EF25: =ROUND(SUM(EE25-BT25),2) -> 0 | EG25: =IF(DN25<>0,DN25-EF25,0) -> 0 | EH25: =IF(EG25=0,DO25-EF25,DO25) -> 0 | EI25: =SUM(DG25:DM25)+SUM(DP25:ED25)+EG25+EH25 -> 320.77
A26: =_xlfn.CONCAT(D26,L26) -> Manaus39.7 | B26: 4151 | C26: 4151 | D26: Manaus | F26: AMBEV | G26: CONTRATO | H26: FOB | K26: PREFORMA | L26: 39.7 | M26: VD | V26: Virgem | W26: 0 | Y26: =IF($X26="",0,HLOOKUP($H$3,Resina!$E$2:$AK$93,MATCH($D26&$X26&$Y$5,Resina!$A$2:$A$93,0))) -> 0 | Z26: 1 | AA26: VG | AB26: =IF($AA26="",0,HLOOKUP($H$3,Resina!$E$2:$AK$93,MATCH($D26&$AA26&$AB$5,Resina!$A$2:$A$93,0))) -> 1720.8738 | AC26: =$AC$7 -> 46091 | AD26: Mensal | AE26: =$AE$7 -> 45839 | AF26: MIL | AG26: =_xlfn.XLOOKUP($H$3,Resina!$2:$2,Resina!$3:$3,0) -> 5.2006167 | AH26: =(L26*((Y26*W26)+(AB26*Z26)))*AG26/1000 -> 355.29931 | AI26: 0.005 | AJ26: =AH26*AI26 -> 1.7764965 | AO26: =_xlfn.XLOOKUP($D26&$L26&$AK$3,'BD Conv'!$A:$A,'BD Conv'!$H:$H,0)*_xlfn.XLOOKUP($D26,'BD Conv'!$C$17:$C$19,'BD Conv'!$F$17:$F$19,0)*(1+(HLOOKUP($B26&AO$6,Indexadores!$C$2:$AH$32,MATCH($AE26,Indexadores!$A$2:$A$32,0)))) -> 0 | AS26: 0.005 | AT26: =(AU26+AO26)*AS26 -> 0 | AU26: =_xlfn.XLOOKUP($D26&$L26&$AK$3,'BD Conv'!$A:$A,'BD Conv'!$H:$H,0)*_xlfn.XLOOKUP($D26,'BD Conv'!$C$17:$C$19,'BD Conv'!$E$17:$E$19,0)*(1+(HLOOKUP($B26&AU$6,Indexadores!$C$2:$AH$32,MATCH($AE26,Indexadores!$A$2:$A$32,0)))) -> 0 | AV26: =SUM(AN26,AO26,AP26,(AQ26*AG26),AR26,AT26,AU26) -> 0 | AW26: =_xlfn.XLOOKUP($A26&$AK$3,'BD Conv'!$A:$A,'BD Conv'!$I:$I,0) -> 0 | AZ26: =SUM(AH26,AJ26,AK26,AL26,AV26,AW26:AY26) -> 357.07581 | BI26: =SUM(BA26,BB26,BC26,(BD26*AG26),BE26,BF26,BH26) -> 0 | BN26: =_xlfn.XLOOKUP($A26&$BA$3,'BD Conv'!$A:$A,'BD Conv'!$K:$K,0) -> 0 | BQ26: =SUM(BI26,BJ26,BK26,BM26,BN26,BO26,BP26) -> 0 | BR26: =-BQ26*$BR$3 -> 0 | BT26: =AZ26+BQ26+BR26+BS26 -> 357.07581 | BU26: =BV26-BT26 -> 90.051424 | BV26: =BT26/(1-(12%+1.65%+7.6%) +12%*(1.65%+7.6%)) -> 447.12723 | BY26: =BT26/CP26-1 -> -0.024279899 | BZ26: =(BT26-CP26)/AG26 -> -1.7085481 | CA26: =(BT26-CK26-CL26-AL26-AX26-AY26-BO26-BP26+CQ26)/AG26 -> -1.7085481 | CB26: =(BT26-AH26)/AG26 -> 0.34159344 | CD26: =CP26*(1+$CD$5) -> 402.55744 | CE26: =(CD26-CP26)/AG26 -> 7.036883 | CF26: =(CD26-CK26-CL26-AL26-AX26-AY26-BO26-BP26+CQ26)/AG26 -> 7.036883 | CG26: =(CD26-AH26)/AG26 -> 9.0870245 | CI26: =IF($X26="",0,HLOOKUP($H$3,Resina!$E$2:$AK$93,MATCH($D26&$X26&$CI$5,Resina!$A$2:$A$93,0))) -> 0 | CJ26: =IF($AA26="",0,HLOOKUP($H$3,Resina!$E$2:$AK$93,MATCH($D26&$AA26&$CJ$5,Resina!$A$2:$A$93,0))) -> 1754.965 | CK26: =L26*((CI26*W26)+(CJ26*Z26))*AG26/1000 -> 362.33793 | CL26: =CK26*$CL$6 -> 3.6233793 | CM26: =IF(D26="Manaus FORA",-((CK26/0.88*0.12)*(1-9.25%))," ") | CO26: =AX26+AY26+BO26+BP26+AL26+AN26+BJ26+BK26+BM26 -> 0 | CP26: =SUM(CK26:CO26) -> 365.96131 | DE26: =_xlfn.CONCAT(D26,L26) -> Manaus39.7 | DF26: =L26 -> 39.7 | DG26: =ROUND(SUMIF($1:$1,DG$5,26:26),2) -> 355.3 | DH26: =ROUND(SUMIF($1:$1,DH$5,26:26),2) -> 1.78 | DI26: =ROUND(SUMIF($1:$1,DI$5,26:26),2) -> 0 | DJ26: =ROUND(SUMIF($1:$1,DJ$5,26:26),2) -> 0 | DK26: =ROUND(SUMIF($1:$1,DK$5,26:26),2) -> 0 | DL26: =ROUND(SUMIF($1:$1,DL$5,26:26),2) -> 0 | DM26: =ROUND(SUMIF($1:$1,DM$5,26:26),2) -> 0 | DN26: =ROUND(SUMIF($1:$1,DN$5,26:26),2) -> 0 | ... ED26: =ROUND(SUMIF($1:$1,ED$5,26:26),2) -> 0 | EE26: =SUM(DG26:ED26) -> 357.08 | EF26: =ROUND(SUM(EE26-BT26),2) -> 0 | EG26: =IF(DN26<>0,DN26-EF26,0) -> 0 | EH26: =IF(EG26=0,DO26-EF26,DO26) -> 0 | EI26: =SUM(DG26:DM26)+SUM(DP26:ED26)+EG26+EH26 -> 357.08
A27: =_xlfn.CONCAT(D27,L27) -> Manaus29.5 | B27: 4151 | C27: 4151 | D27: Manaus | F27: AMBEV | G27: CONTRATO | H27: FOB | K27: PREFORMA | L27: 29.5 | M27: CR | V27: Virgem | W27: 1 | X27: ALPEK | Y27: =IF($X27="",0,HLOOKUP($H$3,Resina!$E$2:$AK$93,MATCH($D27&$X27&$Y$5,Resina!$A$2:$A$93,0))) -> 1283.4027 | Z27: 0 | AA27: VG | AB27: =IF($AA27="",0,HLOOKUP($H$3,Resina!$E$2:$AK$93,MATCH($D27&$AA27&$AB$5,Resina!$A$2:$A$93,0))) -> 1720.8738 | AC27: =$AC$7 -> 46091 | AD27: Mensal | AE27: =$AE$7 -> 45839 | AF27: MIL | AG27: =_xlfn.XLOOKUP($H$3,Resina!$2:$2,Resina!$3:$3,0) -> 5.2006167 | AH27: =(L27*((Y27*W27)+(AB27*Z27)))*AG27/1000 -> 196.89733 | AI27: 0.005 | AJ27: =AH27*AI27 -> 0.98448663 | AO27: =_xlfn.XLOOKUP($D27&$L27&$AK$3,'BD Conv'!$A:$A,'BD Conv'!$H:$H,0)*_xlfn.XLOOKUP($D27,'BD Conv'!$C$17:$C$19,'BD Conv'!$F$17:$F$19,0)*(1+(HLOOKUP($B27&AO$6,Indexadores!$C$2:$AH$32,MATCH($AE27,Indexadores!$A$2:$A$32,0)))) -> 0 | AS27: 0.005 | AT27: =(AU27+AO27)*AS27 -> 0 | AU27: =_xlfn.XLOOKUP($D27&$L27&$AK$3,'BD Conv'!$A:$A,'BD Conv'!$H:$H,0)*_xlfn.XLOOKUP($D27,'BD Conv'!$C$17:$C$19,'BD Conv'!$E$17:$E$19,0)*(1+(HLOOKUP($B27&AU$6,Indexadores!$C$2:$AH$32,MATCH($AE27,Indexadores!$A$2:$A$32,0)))) -> 0 | AV27: =SUM(AN27,AO27,AP27,(AQ27*AG27),AR27,AT27,AU27) -> 0 | AW27: =_xlfn.XLOOKUP($A27&$AK$3,'BD Conv'!$A:$A,'BD Conv'!$I:$I,0) -> 0 | AZ27: =SUM(AH27,AJ27,AK27,AL27,AV27,AW27:AY27) -> 197.88181 | BI27: =SUM(BA27,BB27,BC27,(BD27*AG27),BE27,BF27,BH27) -> 0 | BN27: =_xlfn.XLOOKUP($A27&$BA$3,'BD Conv'!$A:$A,'BD Conv'!$K:$K,0) -> 0 | BQ27: =SUM(BI27,BJ27,BK27,BM27,BN27,BO27,BP27) -> 0 | BR27: =-BQ27*$BR$3 -> 0 | BT27: =AZ27+BQ27+BR27+BS27 -> 197.88181 | BU27: =BV27-BT27 -> 49.904078 | BV27: =BT27/(1-(12%+1.65%+7.6%) +12%*(1.65%+7.6%)) -> 247.78589 | BY27: =BT27/CP27-1 -> 0.053548477 | BZ27: =(BT27-CP27)/AG27 -> 1.9339429 | CA27: =(BT27-CK27-CL27-AL27-AX27-AY27-BO27-BP27+CQ27)/AG27 -> 1.9339429 | CB27: =(BT27-AH27)/AG27 -> 0.1893019 | CD27: =CP27*(1+$CD$5) -> 206.60653 | CE27: =(CD27-CP27)/AG27 -> 3.611574 | CF27: =(CD27-CK27-CL27-AL27-AX27-AY27-BO27-BP27+CQ27)/AG27 -> 3.611574 | CG27: =(CD27-AH27)/AG27 -> 1.866933 | CI27: =IF($X27="",0,HLOOKUP($H$3,Resina!$E$2:$AK$93,MATCH($D27&$X27&$CI$5,Resina!$A$2:$A$93,0))) -> 1212.1409 | CJ27: =IF($AA27="",0,HLOOKUP($H$3,Resina!$E$2:$AK$93,MATCH($D27&$AA27&$CJ$5,Resina!$A$2:$A$93,0))) -> 1754.965 | CK27: =L27*((CI27*W27)+(CJ27*Z27))*AG27/1000 -> 185.96447 | CL27: =CK27*$CL$6 -> 1.8596447 | CM27: =IF(D27="Manaus FORA",-((CK27/0.88*0.12)*(1-9.25%))," ") | CO27: =AX27+AY27+BO27+BP27+AL27+AN27+BJ27+BK27+BM27 -> 0 | CP27: =SUM(CK27:CO27) -> 187.82412 | DE27: =_xlfn.CONCAT(D27,L27) -> Manaus29.5 | DF27: =L27 -> 29.5 | DG27: =ROUND(SUMIF($1:$1,DG$5,27:27),2) -> 196.9 | DH27: =ROUND(SUMIF($1:$1,DH$5,27:27),2) -> 0.98 | DI27: =ROUND(SUMIF($1:$1,DI$5,27:27),2) -> 0 | DJ27: =ROUND(SUMIF($1:$1,DJ$5,27:27),2) -> 0 | DK27: =ROUND(SUMIF($1:$1,DK$5,27:27),2) -> 0 | DL27: =ROUND(SUMIF($1:$1,DL$5,27:27),2) -> 0 | DM27: =ROUND(SUMIF($1:$1,DM$5,27:27),2) -> 0 | DN27: =ROUND(SUMIF($1:$1,DN$5,27:27),2) -> 0 | ... ED27: =ROUND(SUMIF($1:$1,ED$5,27:27),2) -> 0 | EE27: =SUM(DG27:ED27) -> 197.88 | EF27: =ROUND(SUM(EE27-BT27),2) -> 0 | EG27: =IF(DN27<>0,DN27-EF27,0) -> 0 | EH27: =IF(EG27=0,DO27-EF27,DO27) -> 0 | EI27: =SUM(DG27:DM27)+SUM(DP27:ED27)+EG27+EH27 -> 197.88
A28: =_xlfn.CONCAT(D28,L28) -> Manaus29.5 | B28: 4151 | C28: 4151 | D28: Manaus | F28: AMBEV | G28: CONTRATO | H28: FOB | K28: PREFORMA | L28: 29.5 | M28: CR | V28: Virgem | W28: 0.6 | X28: ALPEK | Y28: =IF($X28="",0,HLOOKUP($H$3,Resina!$E$2:$AK$93,MATCH($D28&$X28&$Y$5,Resina!$A$2:$A$93,0))) -> 1283.4027 | Z28: 0.4 | AA28: VG | AB28: =IF($AA28="",0,HLOOKUP($H$3,Resina!$E$2:$AK$93,MATCH($D28&$AA28&$AB$5,Resina!$A$2:$A$93,0))) -> 1720.8738 | AC28: =$AC$7 -> 46091 | AD28: Mensal | AE28: =$AE$7 -> 45839 | AF28: MIL | AG28: =_xlfn.XLOOKUP($H$3,Resina!$2:$2,Resina!$3:$3,0) -> 5.2006167 | AH28: =(L28*((Y28*W28)+(AB28*Z28)))*AG28/1000 -> 223.74373 | AI28: 0.005 | AJ28: =AH28*AI28 -> 1.1187187 | AO28: =_xlfn.XLOOKUP($D28&$L28&$AK$3,'BD Conv'!$A:$A,'BD Conv'!$H:$H,0)*_xlfn.XLOOKUP($D28,'BD Conv'!$C$17:$C$19,'BD Conv'!$F$17:$F$19,0)*(1+(HLOOKUP($B28&AO$6,Indexadores!$C$2:$AH$32,MATCH($AE28,Indexadores!$A$2:$A$32,0)))) -> 0 | AS28: 0.005 | AT28: =(AU28+AO28)*AS28 -> 0 | AU28: =_xlfn.XLOOKUP($D28&$L28&$AK$3,'BD Conv'!$A:$A,'BD Conv'!$H:$H,0)*_xlfn.XLOOKUP($D28,'BD Conv'!$C$17:$C$19,'BD Conv'!$E$17:$E$19,0)*(1+(HLOOKUP($B28&AU$6,Indexadores!$C$2:$AH$32,MATCH($AE28,Indexadores!$A$2:$A$32,0)))) -> 0 | AV28: =SUM(AN28,AO28,AP28,(AQ28*AG28),AR28,AT28,AU28) -> 0 | AW28: =_xlfn.XLOOKUP($A28&$AK$3,'BD Conv'!$A:$A,'BD Conv'!$I:$I,0) -> 0 | AZ28: =SUM(AH28,AJ28,AK28,AL28,AV28,AW28:AY28) -> 224.86245 | BI28: =SUM(BA28,BB28,BC28,(BD28*AG28),BE28,BF28,BH28) -> 0 | BN28: =_xlfn.XLOOKUP($A28&$BA$3,'BD Conv'!$A:$A,'BD Conv'!$K:$K,0) -> 0 | BQ28: =SUM(BI28,BJ28,BK28,BM28,BN28,BO28,BP28) -> 0 | BR28: =-BQ28*$BR$3 -> 0 | BT28: =AZ28+BQ28+BR28+BS28 -> 224.86245 | BU28: =BV28-BT28 -> 56.708362 | BV28: =BT28/(1-(12%+1.65%+7.6%) +12%*(1.65%+7.6%)) -> 281.57081 | BY28: =BT28/CP28-1 -> 0.015323084 | BZ28: =(BT28-CP28)/AG28 -> 0.6525353 | CA28: =(BT28-CK28-CL28-AL28-AX28-AY28-BO28-BP28+CQ28)/AG28 -> 0.6525353 | CB28: =(BT28-AH28)/AG28 -> 0.21511269 | CD28: =CP28*(1+$CD$5) -> 243.61575 | CE28: =(CD28-CP28)/AG28 -> 4.2585116 | CF28: =(CD28-CK28-CL28-AL28-AX28-AY28-BO28-BP28+CQ28)/AG28 -> 4.2585116 | CG28: =(CD28-AH28)/AG28 -> 3.821089 | CI28: =IF($X28="",0,HLOOKUP($H$3,Resina!$E$2:$AK$93,MATCH($D28&$X28&$CI$5,Resina!$A$2:$A$93,0))) -> 1212.1409 | CJ28: =IF($AA28="",0,HLOOKUP($H$3,Resina!$E$2:$AK$93,MATCH($D28&$AA28&$CJ$5,Resina!$A$2:$A$93,0))) -> 1754.965 | CK28: =L28*((CI28*W28)+(CJ28*Z28))*AG28/1000 -> 219.2761 | CL28: =CK28*$CL$6 -> 2.192761 | CM28: =IF(D28="Manaus FORA",-((CK28/0.88*0.12)*(1-9.25%))," ") | CO28: =AX28+AY28+BO28+BP28+AL28+AN28+BJ28+BK28+BM28 -> 0 | CP28: =SUM(CK28:CO28) -> 221.46886 | DE28: =_xlfn.CONCAT(D28,L28) -> Manaus29.5 | DF28: =L28 -> 29.5 | DG28: =ROUND(SUMIF($1:$1,DG$5,28:28),2) -> 223.74 | DH28: =ROUND(SUMIF($1:$1,DH$5,28:28),2) -> 1.12 | DI28: =ROUND(SUMIF($1:$1,DI$5,28:28),2) -> 0 | DJ28: =ROUND(SUMIF($1:$1,DJ$5,28:28),2) -> 0 | DK28: =ROUND(SUMIF($1:$1,DK$5,28:28),2) -> 0 | DL28: =ROUND(SUMIF($1:$1,DL$5,28:28),2) -> 0 | DM28: =ROUND(SUMIF($1:$1,DM$5,28:28),2) -> 0 | DN28: =ROUND(SUMIF($1:$1,DN$5,28:28),2) -> 0 | ... ED28: =ROUND(SUMIF($1:$1,ED$5,28:28),2) -> 0 | EE28: =SUM(DG28:ED28) -> 224.86 | EF28: =ROUND(SUM(EE28-BT28),2) -> 0 | EG28: =IF(DN28<>0,DN28-EF28,0) -> 0 | EH28: =IF(EG28=0,DO28-EF28,DO28) -> 0 | EI28: =SUM(DG28:DM28)+SUM(DP28:ED28)+EG28+EH28 -> 224.86
A29: =_xlfn.CONCAT(D29,L29) -> Manaus29.5 | B29: 4151 | C29: 4151 | D29: Manaus | F29: AMBEV | G29: CONTRATO | H29: FOB | K29: PREFORMA | L29: 29.5 | M29: CR | V29: Virgem | W29: 0.4 | X29: ALPEK | Y29: =IF($X29="",0,HLOOKUP($H$3,Resina!$E$2:$AK$93,MATCH($D29&$X29&$Y$5,Resina!$A$2:$A$93,0))) -> 1283.4027 | Z29: 0.6 | AA29: VG | AB29: =IF($AA29="",0,HLOOKUP($H$3,Resina!$E$2:$AK$93,MATCH($D29&$AA29&$AB$5,Resina!$A$2:$A$93,0))) -> 1720.8738 | AC29: =$AC$7 -> 46091 | AD29: Mensal | AE29: =$AE$7 -> 45839 | AF29: MIL | AG29: =_xlfn.XLOOKUP($H$3,Resina!$2:$2,Resina!$3:$3,0) -> 5.2006167 | AH29: =(L29*((Y29*W29)+(AB29*Z29)))*AG29/1000 -> 237.16693 | AI29: 0.005 | AJ29: =AH29*AI29 -> 1.1858347 | AO29: =_xlfn.XLOOKUP($D29&$L29&$AK$3,'BD Conv'!$A:$A,'BD Conv'!$H:$H,0)*_xlfn.XLOOKUP($D29,'BD Conv'!$C$17:$C$19,'BD Conv'!$F$17:$F$19,0)*(1+(HLOOKUP($B29&AO$6,Indexadores!$C$2:$AH$32,MATCH($AE29,Indexadores!$A$2:$A$32,0)))) -> 0 | AS29: 0.005 | AT29: =(AU29+AO29)*AS29 -> 0 | AU29: =_xlfn.XLOOKUP($D29&$L29&$AK$3,'BD Conv'!$A:$A,'BD Conv'!$H:$H,0)*_xlfn.XLOOKUP($D29,'BD Conv'!$C$17:$C$19,'BD Conv'!$E$17:$E$19,0)*(1+(HLOOKUP($B29&AU$6,Indexadores!$C$2:$AH$32,MATCH($AE29,Indexadores!$A$2:$A$32,0)))) -> 0 | AV29: =SUM(AN29,AO29,AP29,(AQ29*AG29),AR29,AT29,AU29) -> 0 | AW29: =_xlfn.XLOOKUP($A29&$AK$3,'BD Conv'!$A:$A,'BD Conv'!$I:$I,0) -> 0 | AZ29: =SUM(AH29,AJ29,AK29,AL29,AV29,AW29:AY29) -> 238.35277 | BI29: =SUM(BA29,BB29,BC29,(BD29*AG29),BE29,BF29,BH29) -> 0 | BN29: =_xlfn.XLOOKUP($A29&$BA$3,'BD Conv'!$A:$A,'BD Conv'!$K:$K,0) -> 0 | BQ29: =SUM(BI29,BJ29,BK29,BM29,BN29,BO29,BP29) -> 0 | BR29: =-BQ29*$BR$3 -> 0 | BT29: =AZ29+BQ29+BR29+BS29 -> 238.35277 | BU29: =BV29-BT29 -> 60.110503 | BV29: =BT29/(1-(12%+1.65%+7.6%) +12%*(1.65%+7.6%)) -> 298.46327 | BY29: =BT29/CP29-1 -> 0.00025821841 | BZ29: =(BT29-CP29)/AG29 -> 0.011831517 | CA29: =(BT29-CK29-CL29-AL29-AX29-AY29-BO29-BP29+CQ29)/AG29 -> 0.011831517 | CB29: =(BT29-AH29)/AG29 -> 0.22801809 | CD29: =CP29*(1+$CD$5) -> 262.12036 | CE29: =(CD29-CP29)/AG29 -> 4.5819804 | CF29: =(CD29-CK29-CL29-AL29-AX29-AY29-BO29-BP29+CQ29)/AG29 -> 4.5819804 | CG29: =(CD29-AH29)/AG29 -> 4.798167 | CI29: =IF($X29="",0,HLOOKUP($H$3,Resina!$E$2:$AK$93,MATCH($D29&$X29&$CI$5,Resina!$A$2:$A$93,0))) -> 1212.1409 | CJ29: =IF($AA29="",0,HLOOKUP($H$3,Resina!$E$2:$AK$93,MATCH($D29&$AA29&$CJ$5,Resina!$A$2:$A$93,0))) -> 1754.965 | CK29: =L29*((CI29*W29)+(CJ29*Z29))*AG29/1000 -> 235.93192 | CL29: =CK29*$CL$6 -> 2.3593192 | CM29: =IF(D29="Manaus FORA",-((CK29/0.88*0.12)*(1-9.25%))," ") | CO29: =AX29+AY29+BO29+BP29+AL29+AN29+BJ29+BK29+BM29 -> 0 | CP29: =SUM(CK29:CO29) -> 238.29124 | DE29: =_xlfn.CONCAT(D29,L29) -> Manaus29.5 | DF29: =L29 -> 29.5 | DG29: =ROUND(SUMIF($1:$1,DG$5,29:29),2) -> 237.17 | DH29: =ROUND(SUMIF($1:$1,DH$5,29:29),2) -> 1.19 | DI29: =ROUND(SUMIF($1:$1,DI$5,29:29),2) -> 0 | DJ29: =ROUND(SUMIF($1:$1,DJ$5,29:29),2) -> 0 | DK29: =ROUND(SUMIF($1:$1,DK$5,29:29),2) -> 0 | DL29: =ROUND(SUMIF($1:$1,DL$5,29:29),2) -> 0 | DM29: =ROUND(SUMIF($1:$1,DM$5,29:29),2) -> 0 | DN29: =ROUND(SUMIF($1:$1,DN$5,29:29),2) -> 0 | ... ED29: =ROUND(SUMIF($1:$1,ED$5,29:29),2) -> 0 | EE29: =SUM(DG29:ED29) -> 238.36 | EF29: =ROUND(SUM(EE29-BT29),2) -> 0.01 | EG29: =IF(DN29<>0,DN29-EF29,0) -> 0 | EH29: =IF(EG29=0,DO29-EF29,DO29) -> -0.01 | EI29: =SUM(DG29:DM29)+SUM(DP29:ED29)+EG29+EH29 -> 238.35
A30: =_xlfn.CONCAT(D30,L30) -> Manaus29.5 | B30: 4151 | C30: 4151 | D30: Manaus | F30: AMBEV | G30: CONTRATO | H30: FOB | K30: PREFORMA | L30: 29.5 | M30: CR | V30: Virgem | W30: 0 | Y30: =IF($X30="",0,HLOOKUP($H$3,Resina!$E$2:$AK$93,MATCH($D30&$X30&$Y$5,Resina!$A$2:$A$93,0))) -> 0 | Z30: 1 | AA30: VG | AB30: =IF($AA30="",0,HLOOKUP($H$3,Resina!$E$2:$AK$93,MATCH($D30&$AA30&$AB$5,Resina!$A$2:$A$93,0))) -> 1720.8738 | AC30: =$AC$7 -> 46091 | AD30: Mensal | AE30: =$AE$7 -> 45839 | AF30: MIL | AG30: =_xlfn.XLOOKUP($H$3,Resina!$2:$2,Resina!$3:$3,0) -> 5.2006167 | AH30: =(L30*((Y30*W30)+(AB30*Z30)))*AG30/1000 -> 264.01334 | AI30: 0.005 | AJ30: =AH30*AI30 -> 1.3200667 | AO30: =_xlfn.XLOOKUP($D30&$L30&$AK$3,'BD Conv'!$A:$A,'BD Conv'!$H:$H,0)*_xlfn.XLOOKUP($D30,'BD Conv'!$C$17:$C$19,'BD Conv'!$F$17:$F$19,0)*(1+(HLOOKUP($B30&AO$6,Indexadores!$C$2:$AH$32,MATCH($AE30,Indexadores!$A$2:$A$32,0)))) -> 0 | AS30: 0.005 | AT30: =(AU30+AO30)*AS30 -> 0 | AU30: =_xlfn.XLOOKUP($D30&$L30&$AK$3,'BD Conv'!$A:$A,'BD Conv'!$H:$H,0)*_xlfn.XLOOKUP($D30,'BD Conv'!$C$17:$C$19,'BD Conv'!$E$17:$E$19,0)*(1+(HLOOKUP($B30&AU$6,Indexadores!$C$2:$AH$32,MATCH($AE30,Indexadores!$A$2:$A$32,0)))) -> 0 | AV30: =SUM(AN30,AO30,AP30,(AQ30*AG30),AR30,AT30,AU30) -> 0 | AW30: =_xlfn.XLOOKUP($A30&$AK$3,'BD Conv'!$A:$A,'BD Conv'!$I:$I,0) -> 0 | AZ30: =SUM(AH30,AJ30,AK30,AL30,AV30,AW30:AY30) -> 265.33341 | BI30: =SUM(BA30,BB30,BC30,(BD30*AG30),BE30,BF30,BH30) -> 0 | BN30: =_xlfn.XLOOKUP($A30&$BA$3,'BD Conv'!$A:$A,'BD Conv'!$K:$K,0) -> 0 | BQ30: =SUM(BI30,BJ30,BK30,BM30,BN30,BO30,BP30) -> 0 | BR30: =-BQ30*$BR$3 -> 0 | BT30: =AZ30+BQ30+BR30+BS30 -> 265.33341 | BU30: =BV30-BT30 -> 66.914786 | BV30: =BT30/(1-(12%+1.65%+7.6%) +12%*(1.65%+7.6%)) -> 332.24819 | BY30: =BT30/CP30-1 -> -0.024279899 | BZ30: =(BT30-CP30)/AG30 -> -1.269576 | CA30: =(BT30-CK30-CL30-AL30-AX30-AY30-BO30-BP30+CQ30)/AG30 -> -1.269576 | CB30: =(BT30-AH30)/AG30 -> 0.25382888 | CD30: =CP30*(1+$CD$5) -> 299.12958 | CE30: =(CD30-CP30)/AG30 -> 5.2289181 | CF30: =(CD30-CK30-CL30-AL30-AX30-AY30-BO30-BP30+CQ30)/AG30 -> 5.2289181 | CG30: =(CD30-AH30)/AG30 -> 6.752323 | CI30: =IF($X30="",0,HLOOKUP($H$3,Resina!$E$2:$AK$93,MATCH($D30&$X30&$CI$5,Resina!$A$2:$A$93,0))) -> 0 | CJ30: =IF($AA30="",0,HLOOKUP($H$3,Resina!$E$2:$AK$93,MATCH($D30&$AA30&$CJ$5,Resina!$A$2:$A$93,0))) -> 1754.965 | CK30: =L30*((CI30*W30)+(CJ30*Z30))*AG30/1000 -> 269.24355 | CL30: =CK30*$CL$6 -> 2.6924355 | CM30: =IF(D30="Manaus FORA",-((CK30/0.88*0.12)*(1-9.25%))," ") | CO30: =AX30+AY30+BO30+BP30+AL30+AN30+BJ30+BK30+BM30 -> 0 | CP30: =SUM(CK30:CO30) -> 271.93599 | DE30: =_xlfn.CONCAT(D30,L30) -> Manaus29.5 | DF30: =L30 -> 29.5 | DG30: =ROUND(SUMIF($1:$1,DG$5,30:30),2) -> 264.01 | DH30: =ROUND(SUMIF($1:$1,DH$5,30:30),2) -> 1.32 | DI30: =ROUND(SUMIF($1:$1,DI$5,30:30),2) -> 0 | DJ30: =ROUND(SUMIF($1:$1,DJ$5,30:30),2) -> 0 | DK30: =ROUND(SUMIF($1:$1,DK$5,30:30),2) -> 0 | DL30: =ROUND(SUMIF($1:$1,DL$5,30:30),2) -> 0 | DM30: =ROUND(SUMIF($1:$1,DM$5,30:30),2) -> 0 | DN30: =ROUND(SUMIF($1:$1,DN$5,30:30),2) -> 0 | ... ED30: =ROUND(SUMIF($1:$1,ED$5,30:30),2) -> 0 | EE30: =SUM(DG30:ED30) -> 265.33 | EF30: =ROUND(SUM(EE30-BT30),2) -> 0 | EG30: =IF(DN30<>0,DN30-EF30,0) -> 0 | EH30: =IF(EG30=0,DO30-EF30,DO30) -> 0 | EI30: =SUM(DG30:DM30)+SUM(DP30:ED30)+EG30+EH30 -> 265.33
A31: =_xlfn.CONCAT(D31,L31) -> Manaus29.5 | B31: 4151 | C31: 4151 | D31: Manaus | F31: AMBEV | G31: CONTRATO | H31: FOB | K31: PREFORMA | L31: 29.5 | M31: VD | V31: Virgem | W31: 1 | X31: ALPEK | Y31: =IF($X31="",0,HLOOKUP($H$3,Resina!$E$2:$AK$93,MATCH($D31&$X31&$Y$5,Resina!$A$2:$A$93,0))) -> 1283.4027 | Z31: 0 | AA31: VG | AB31: =IF($AA31="",0,HLOOKUP($H$3,Resina!$E$2:$AK$93,MATCH($D31&$AA31&$AB$5,Resina!$A$2:$A$93,0))) -> 1720.8738 | AC31: =$AC$7 -> 46091 | AD31: Mensal | AE31: =$AE$7 -> 45839 | AF31: MIL | AG31: =_xlfn.XLOOKUP($H$3,Resina!$2:$2,Resina!$3:$3,0) -> 5.2006167 | AH31: =(L31*((Y31*W31)+(AB31*Z31)))*AG31/1000 -> 196.89733 | AI31: 0.005 | AJ31: =AH31*AI31 -> 0.98448663 | AO31: =_xlfn.XLOOKUP($D31&$L31&$AK$3,'BD Conv'!$A:$A,'BD Conv'!$H:$H,0)*_xlfn.XLOOKUP($D31,'BD Conv'!$C$17:$C$19,'BD Conv'!$F$17:$F$19,0)*(1+(HLOOKUP($B31&AO$6,Indexadores!$C$2:$AH$32,MATCH($AE31,Indexadores!$A$2:$A$32,0)))) -> 0 | AS31: 0.005 | AT31: =(AU31+AO31)*AS31 -> 0 | AU31: =_xlfn.XLOOKUP($D31&$L31&$AK$3,'BD Conv'!$A:$A,'BD Conv'!$H:$H,0)*_xlfn.XLOOKUP($D31,'BD Conv'!$C$17:$C$19,'BD Conv'!$E$17:$E$19,0)*(1+(HLOOKUP($B31&AU$6,Indexadores!$C$2:$AH$32,MATCH($AE31,Indexadores!$A$2:$A$32,0)))) -> 0 | AV31: =SUM(AN31,AO31,AP31,(AQ31*AG31),AR31,AT31,AU31) -> 0 | AW31: =_xlfn.XLOOKUP($A31&$AK$3,'BD Conv'!$A:$A,'BD Conv'!$I:$I,0) -> 0 | AZ31: =SUM(AH31,AJ31,AK31,AL31,AV31,AW31:AY31) -> 197.88181 | BI31: =SUM(BA31,BB31,BC31,(BD31*AG31),BE31,BF31,BH31) -> 0 | BN31: =_xlfn.XLOOKUP($A31&$BA$3,'BD Conv'!$A:$A,'BD Conv'!$K:$K,0) -> 0 | BQ31: =SUM(BI31,BJ31,BK31,BM31,BN31,BO31,BP31) -> 0 | BR31: =-BQ31*$BR$3 -> 0 | BT31: =AZ31+BQ31+BR31+BS31 -> 197.88181 | BU31: =BV31-BT31 -> 49.904078 | BV31: =BT31/(1-(12%+1.65%+7.6%) +12%*(1.65%+7.6%)) -> 247.78589 | BY31: =BT31/CP31-1 -> 0.053548477 | BZ31: =(BT31-CP31)/AG31 -> 1.9339429 | CA31: =(BT31-CK31-CL31-AL31-AX31-AY31-BO31-BP31+CQ31)/AG31 -> 1.9339429 | CB31: =(BT31-AH31)/AG31 -> 0.1893019 | CD31: =CP31*(1+$CD$5) -> 206.60653 | CE31: =(CD31-CP31)/AG31 -> 3.611574 | CF31: =(CD31-CK31-CL31-AL31-AX31-AY31-BO31-BP31+CQ31)/AG31 -> 3.611574 | CG31: =(CD31-AH31)/AG31 -> 1.866933 | CI31: =IF($X31="",0,HLOOKUP($H$3,Resina!$E$2:$AK$93,MATCH($D31&$X31&$CI$5,Resina!$A$2:$A$93,0))) -> 1212.1409 | CJ31: =IF($AA31="",0,HLOOKUP($H$3,Resina!$E$2:$AK$93,MATCH($D31&$AA31&$CJ$5,Resina!$A$2:$A$93,0))) -> 1754.965 | CK31: =L31*((CI31*W31)+(CJ31*Z31))*AG31/1000 -> 185.96447 | CL31: =CK31*$CL$6 -> 1.8596447 | CM31: =IF(D31="Manaus FORA",-((CK31/0.88*0.12)*(1-9.25%))," ") | CO31: =AX31+AY31+BO31+BP31+AL31+AN31+BJ31+BK31+BM31 -> 0 | CP31: =SUM(CK31:CO31) -> 187.82412 | DE31: =_xlfn.CONCAT(D31,L31) -> Manaus29.5 | DF31: =L31 -> 29.5 | DG31: =ROUND(SUMIF($1:$1,DG$5,31:31),2) -> 196.9 | DH31: =ROUND(SUMIF($1:$1,DH$5,31:31),2) -> 0.98 | DI31: =ROUND(SUMIF($1:$1,DI$5,31:31),2) -> 0 | DJ31: =ROUND(SUMIF($1:$1,DJ$5,31:31),2) -> 0 | DK31: =ROUND(SUMIF($1:$1,DK$5,31:31),2) -> 0 | DL31: =ROUND(SUMIF($1:$1,DL$5,31:31),2) -> 0 | DM31: =ROUND(SUMIF($1:$1,DM$5,31:31),2) -> 0 | DN31: =ROUND(SUMIF($1:$1,DN$5,31:31),2) -> 0 | ... ED31: =ROUND(SUMIF($1:$1,ED$5,31:31),2) -> 0 | EE31: =SUM(DG31:ED31) -> 197.88 | EF31: =ROUND(SUM(EE31-BT31),2) -> 0 | EG31: =IF(DN31<>0,DN31-EF31,0) -> 0 | EH31: =IF(EG31=0,DO31-EF31,DO31) -> 0 | EI31: =SUM(DG31:DM31)+SUM(DP31:ED31)+EG31+EH31 -> 197.88
A32: =_xlfn.CONCAT(D32,L32) -> Manaus29.5 | B32: 4151 | C32: 4151 | D32: Manaus | F32: AMBEV | G32: CONTRATO | H32: FOB | K32: PREFORMA | L32: 29.5 | M32: VD | V32: Virgem | W32: 0.6 | X32: ALPEK | Y32: =IF($X32="",0,HLOOKUP($H$3,Resina!$E$2:$AK$93,MATCH($D32&$X32&$Y$5,Resina!$A$2:$A$93,0))) -> 1283.4027 | Z32: 0.4 | AA32: VG | AB32: =IF($AA32="",0,HLOOKUP($H$3,Resina!$E$2:$AK$93,MATCH($D32&$AA32&$AB$5,Resina!$A$2:$A$93,0))) -> 1720.8738 | AC32: =$AC$7 -> 46091 | AD32: Mensal | AE32: =$AE$7 -> 45839 | AF32: MIL | AG32: =_xlfn.XLOOKUP($H$3,Resina!$2:$2,Resina!$3:$3,0) -> 5.2006167 | AH32: =(L32*((Y32*W32)+(AB32*Z32)))*AG32/1000 -> 223.74373 | AI32: 0.005 | AJ32: =AH32*AI32 -> 1.1187187 | AO32: =_xlfn.XLOOKUP($D32&$L32&$AK$3,'BD Conv'!$A:$A,'BD Conv'!$H:$H,0)*_xlfn.XLOOKUP($D32,'BD Conv'!$C$17:$C$19,'BD Conv'!$F$17:$F$19,0)*(1+(HLOOKUP($B32&AO$6,Indexadores!$C$2:$AH$32,MATCH($AE32,Indexadores!$A$2:$A$32,0)))) -> 0 | AS32: 0.005 | AT32: =(AU32+AO32)*AS32 -> 0 | AU32: =_xlfn.XLOOKUP($D32&$L32&$AK$3,'BD Conv'!$A:$A,'BD Conv'!$H:$H,0)*_xlfn.XLOOKUP($D32,'BD Conv'!$C$17:$C$19,'BD Conv'!$E$17:$E$19,0)*(1+(HLOOKUP($B32&AU$6,Indexadores!$C$2:$AH$32,MATCH($AE32,Indexadores!$A$2:$A$32,0)))) -> 0 | AV32: =SUM(AN32,AO32,AP32,(AQ32*AG32),AR32,AT32,AU32) -> 0 | AW32: =_xlfn.XLOOKUP($A32&$AK$3,'BD Conv'!$A:$A,'BD Conv'!$I:$I,0) -> 0 | AZ32: =SUM(AH32,AJ32,AK32,AL32,AV32,AW32:AY32) -> 224.86245 | BI32: =SUM(BA32,BB32,BC32,(BD32*AG32),BE32,BF32,BH32) -> 0 | BN32: =_xlfn.XLOOKUP($A32&$BA$3,'BD Conv'!$A:$A,'BD Conv'!$K:$K,0) -> 0 | BQ32: =SUM(BI32,BJ32,BK32,BM32,BN32,BO32,BP32) -> 0 | BR32: =-BQ32*$BR$3 -> 0 | BT32: =AZ32+BQ32+BR32+BS32 -> 224.86245 | BU32: =BV32-BT32 -> 56.708362 | BV32: =BT32/(1-(12%+1.65%+7.6%) +12%*(1.65%+7.6%)) -> 281.57081 | BY32: =BT32/CP32-1 -> 0.015323084 | BZ32: =(BT32-CP32)/AG32 -> 0.6525353 | CA32: =(BT32-CK32-CL32-AL32-AX32-AY32-BO32-BP32+CQ32)/AG32 -> 0.6525353 | CB32: =(BT32-AH32)/AG32 -> 0.21511269 | CD32: =CP32*(1+$CD$5) -> 243.61575 | CE32: =(CD32-CP32)/AG32 -> 4.2585116 | CF32: =(CD32-CK32-CL32-AL32-AX32-AY32-BO32-BP32+CQ32)/AG32 -> 4.2585116 | CG32: =(CD32-AH32)/AG32 -> 3.821089 | CI32: =IF($X32="",0,HLOOKUP($H$3,Resina!$E$2:$AK$93,MATCH($D32&$X32&$CI$5,Resina!$A$2:$A$93,0))) -> 1212.1409 | CJ32: =IF($AA32="",0,HLOOKUP($H$3,Resina!$E$2:$AK$93,MATCH($D32&$AA32&$CJ$5,Resina!$A$2:$A$93,0))) -> 1754.965 | CK32: =L32*((CI32*W32)+(CJ32*Z32))*AG32/1000 -> 219.2761 | CL32: =CK32*$CL$6 -> 2.192761 | CM32: =IF(D32="Manaus FORA",-((CK32/0.88*0.12)*(1-9.25%))," ") | CO32: =AX32+AY32+BO32+BP32+AL32+AN32+BJ32+BK32+BM32 -> 0 | CP32: =SUM(CK32:CO32) -> 221.46886 | DE32: =_xlfn.CONCAT(D32,L32) -> Manaus29.5 | DF32: =L32 -> 29.5 | DG32: =ROUND(SUMIF($1:$1,DG$5,32:32),2) -> 223.74 | DH32: =ROUND(SUMIF($1:$1,DH$5,32:32),2) -> 1.12 | DI32: =ROUND(SUMIF($1:$1,DI$5,32:32),2) -> 0 | DJ32: =ROUND(SUMIF($1:$1,DJ$5,32:32),2) -> 0 | DK32: =ROUND(SUMIF($1:$1,DK$5,32:32),2) -> 0 | DL32: =ROUND(SUMIF($1:$1,DL$5,32:32),2) -> 0 | DM32: =ROUND(SUMIF($1:$1,DM$5,32:32),2) -> 0 | DN32: =ROUND(SUMIF($1:$1,DN$5,32:32),2) -> 0 | ... ED32: =ROUND(SUMIF($1:$1,ED$5,32:32),2) -> 0 | EE32: =SUM(DG32:ED32) -> 224.86 | EF32: =ROUND(SUM(EE32-BT32),2) -> 0 | EG32: =IF(DN32<>0,DN32-EF32,0) -> 0 | EH32: =IF(EG32=0,DO32-EF32,DO32) -> 0 | EI32: =SUM(DG32:DM32)+SUM(DP32:ED32)+EG32+EH32 -> 224.86
A33: =_xlfn.CONCAT(D33,L33) -> Manaus29.5 | B33: 4151 | C33: 4151 | D33: Manaus | F33: AMBEV | G33: CONTRATO | H33: FOB | K33: PREFORMA | L33: 29.5 | M33: VD | V33: Virgem | W33: 0.4 | X33: ALPEK | Y33: =IF($X33="",0,HLOOKUP($H$3,Resina!$E$2:$AK$93,MATCH($D33&$X33&$Y$5,Resina!$A$2:$A$93,0))) -> 1283.4027 | Z33: 0.6 | AA33: VG | AB33: =IF($AA33="",0,HLOOKUP($H$3,Resina!$E$2:$AK$93,MATCH($D33&$AA33&$AB$5,Resina!$A$2:$A$93,0))) -> 1720.8738 | AC33: =$AC$7 -> 46091 | AD33: Mensal | AE33: =$AE$7 -> 45839 | AF33: MIL | AG33: =_xlfn.XLOOKUP($H$3,Resina!$2:$2,Resina!$3:$3,0) -> 5.2006167 | AH33: =(L33*((Y33*W33)+(AB33*Z33)))*AG33/1000 -> 237.16693 | AI33: 0.005 | AJ33: =AH33*AI33 -> 1.1858347 | AO33: =_xlfn.XLOOKUP($D33&$L33&$AK$3,'BD Conv'!$A:$A,'BD Conv'!$H:$H,0)*_xlfn.XLOOKUP($D33,'BD Conv'!$C$17:$C$19,'BD Conv'!$F$17:$F$19,0)*(1+(HLOOKUP($B33&AO$6,Indexadores!$C$2:$AH$32,MATCH($AE33,Indexadores!$A$2:$A$32,0)))) -> 0 | AS33: 0.005 | AT33: =(AU33+AO33)*AS33 -> 0 | AU33: =_xlfn.XLOOKUP($D33&$L33&$AK$3,'BD Conv'!$A:$A,'BD Conv'!$H:$H,0)*_xlfn.XLOOKUP($D33,'BD Conv'!$C$17:$C$19,'BD Conv'!$E$17:$E$19,0)*(1+(HLOOKUP($B33&AU$6,Indexadores!$C$2:$AH$32,MATCH($AE33,Indexadores!$A$2:$A$32,0)))) -> 0 | AV33: =SUM(AN33,AO33,AP33,(AQ33*AG33),AR33,AT33,AU33) -> 0 | AW33: =_xlfn.XLOOKUP($A33&$AK$3,'BD Conv'!$A:$A,'BD Conv'!$I:$I,0) -> 0 | AZ33: =SUM(AH33,AJ33,AK33,AL33,AV33,AW33:AY33) -> 238.35277 | BI33: =SUM(BA33,BB33,BC33,(BD33*AG33),BE33,BF33,BH33) -> 0 | BN33: =_xlfn.XLOOKUP($A33&$BA$3,'BD Conv'!$A:$A,'BD Conv'!$K:$K,0) -> 0 | BQ33: =SUM(BI33,BJ33,BK33,BM33,BN33,BO33,BP33) -> 0 | BR33: =-BQ33*$BR$3 -> 0 | BT33: =AZ33+BQ33+BR33+BS33 -> 238.35277 | BU33: =BV33-BT33 -> 60.110503 | BV33: =BT33/(1-(12%+1.65%+7.6%) +12%*(1.65%+7.6%)) -> 298.46327 | BY33: =BT33/CP33-1 -> 0.00025821841 | BZ33: =(BT33-CP33)/AG33 -> 0.011831517 | CA33: =(BT33-CK33-CL33-AL33-AX33-AY33-BO33-BP33+CQ33)/AG33 -> 0.011831517 | CB33: =(BT33-AH33)/AG33 -> 0.22801809 | CD33: =CP33*(1+$CD$5) -> 262.12036 | CE33: =(CD33-CP33)/AG33 -> 4.5819804 | CF33: =(CD33-CK33-CL33-AL33-AX33-AY33-BO33-BP33+CQ33)/AG33 -> 4.5819804 | CG33: =(CD33-AH33)/AG33 -> 4.798167 | CI33: =IF($X33="",0,HLOOKUP($H$3,Resina!$E$2:$AK$93,MATCH($D33&$X33&$CI$5,Resina!$A$2:$A$93,0))) -> 1212.1409 | CJ33: =IF($AA33="",0,HLOOKUP($H$3,Resina!$E$2:$AK$93,MATCH($D33&$AA33&$CJ$5,Resina!$A$2:$A$93,0))) -> 1754.965 | CK33: =L33*((CI33*W33)+(CJ33*Z33))*AG33/1000 -> 235.93192 | CL33: =CK33*$CL$6 -> 2.3593192 | CM33: =IF(D33="Manaus FORA",-((CK33/0.88*0.12)*(1-9.25%))," ") | CO33: =AX33+AY33+BO33+BP33+AL33+AN33+BJ33+BK33+BM33 -> 0 | CP33: =SUM(CK33:CO33) -> 238.29124 | DE33: =_xlfn.CONCAT(D33,L33) -> Manaus29.5 | DF33: =L33 -> 29.5 | DG33: =ROUND(SUMIF($1:$1,DG$5,33:33),2) -> 237.17 | DH33: =ROUND(SUMIF($1:$1,DH$5,33:33),2) -> 1.19 | DI33: =ROUND(SUMIF($1:$1,DI$5,33:33),2) -> 0 | DJ33: =ROUND(SUMIF($1:$1,DJ$5,33:33),2) -> 0 | DK33: =ROUND(SUMIF($1:$1,DK$5,33:33),2) -> 0 | DL33: =ROUND(SUMIF($1:$1,DL$5,33:33),2) -> 0 | DM33: =ROUND(SUMIF($1:$1,DM$5,33:33),2) -> 0 | DN33: =ROUND(SUMIF($1:$1,DN$5,33:33),2) -> 0 | ... ED33: =ROUND(SUMIF($1:$1,ED$5,33:33),2) -> 0 | EE33: =SUM(DG33:ED33) -> 238.36 | EF33: =ROUND(SUM(EE33-BT33),2) -> 0.01 | EG33: =IF(DN33<>0,DN33-EF33,0) -> 0 | EH33: =IF(EG33=0,DO33-EF33,DO33) -> -0.01 | EI33: =SUM(DG33:DM33)+SUM(DP33:ED33)+EG33+EH33 -> 238.35
A34: =_xlfn.CONCAT(D34,L34) -> Manaus29.5 | B34: 4151 | C34: 4151 | D34: Manaus | F34: AMBEV | G34: CONTRATO | H34: FOB | K34: PREFORMA | L34: 29.5 | M34: VD | V34: Virgem | W34: 0 | Y34: =IF($X34="",0,HLOOKUP($H$3,Resina!$E$2:$AK$93,MATCH($D34&$X34&$Y$5,Resina!$A$2:$A$93,0))) -> 0 | Z34: 1 | AA34: VG | AB34: =IF($AA34="",0,HLOOKUP($H$3,Resina!$E$2:$AK$93,MATCH($D34&$AA34&$AB$5,Resina!$A$2:$A$93,0))) -> 1720.8738 | AC34: =$AC$7 -> 46091 | AD34: Mensal | AE34: =$AE$7 -> 45839 | AF34: MIL | AG34: =_xlfn.XLOOKUP($H$3,Resina!$2:$2,Resina!$3:$3,0) -> 5.2006167 | AH34: =(L34*((Y34*W34)+(AB34*Z34)))*AG34/1000 -> 264.01334 | AI34: 0.005 | AJ34: =AH34*AI34 -> 1.3200667 | AO34: =_xlfn.XLOOKUP($D34&$L34&$AK$3,'BD Conv'!$A:$A,'BD Conv'!$H:$H,0)*_xlfn.XLOOKUP($D34,'BD Conv'!$C$17:$C$19,'BD Conv'!$F$17:$F$19,0)*(1+(HLOOKUP($B34&AO$6,Indexadores!$C$2:$AH$32,MATCH($AE34,Indexadores!$A$2:$A$32,0)))) -> 0 | AS34: 0.005 | AT34: =(AU34+AO34)*AS34 -> 0 | AU34: =_xlfn.XLOOKUP($D34&$L34&$AK$3,'BD Conv'!$A:$A,'BD Conv'!$H:$H,0)*_xlfn.XLOOKUP($D34,'BD Conv'!$C$17:$C$19,'BD Conv'!$E$17:$E$19,0)*(1+(HLOOKUP($B34&AU$6,Indexadores!$C$2:$AH$32,MATCH($AE34,Indexadores!$A$2:$A$32,0)))) -> 0 | AV34: =SUM(AN34,AO34,AP34,(AQ34*AG34),AR34,AT34,AU34) -> 0 | AW34: =_xlfn.XLOOKUP($A34&$AK$3,'BD Conv'!$A:$A,'BD Conv'!$I:$I,0) -> 0 | AZ34: =SUM(AH34,AJ34,AK34,AL34,AV34,AW34:AY34) -> 265.33341 | BI34: =SUM(BA34,BB34,BC34,(BD34*AG34),BE34,BF34,BH34) -> 0 | BN34: =_xlfn.XLOOKUP($A34&$BA$3,'BD Conv'!$A:$A,'BD Conv'!$K:$K,0) -> 0 | BQ34: =SUM(BI34,BJ34,BK34,BM34,BN34,BO34,BP34) -> 0 | BR34: =-BQ34*$BR$3 -> 0 | BT34: =AZ34+BQ34+BR34+BS34 -> 265.33341 | BU34: =BV34-BT34 -> 66.914786 | BV34: =BT34/(1-(12%+1.65%+7.6%) +12%*(1.65%+7.6%)) -> 332.24819 | BY34: =BT34/CP34-1 -> -0.024279899 | BZ34: =(BT34-CP34)/AG34 -> -1.269576 | CA34: =(BT34-CK34-CL34-AL34-AX34-AY34-BO34-BP34+CQ34)/AG34 -> -1.269576 | CB34: =(BT34-AH34)/AG34 -> 0.25382888 | CD34: =CP34*(1+$CD$5) -> 299.12958 | CE34: =(CD34-CP34)/AG34 -> 5.2289181 | CF34: =(CD34-CK34-CL34-AL34-AX34-AY34-BO34-BP34+CQ34)/AG34 -> 5.2289181 | CG34: =(CD34-AH34)/AG34 -> 6.752323 | CI34: =IF($X34="",0,HLOOKUP($H$3,Resina!$E$2:$AK$93,MATCH($D34&$X34&$CI$5,Resina!$A$2:$A$93,0))) -> 0 | CJ34: =IF($AA34="",0,HLOOKUP($H$3,Resina!$E$2:$AK$93,MATCH($D34&$AA34&$CJ$5,Resina!$A$2:$A$93,0))) -> 1754.965 | CK34: =L34*((CI34*W34)+(CJ34*Z34))*AG34/1000 -> 269.24355 | CL34: =CK34*$CL$6 -> 2.6924355 | CM34: =IF(D34="Manaus FORA",-((CK34/0.88*0.12)*(1-9.25%))," ") | CO34: =AX34+AY34+BO34+BP34+AL34+AN34+BJ34+BK34+BM34 -> 0 | CP34: =SUM(CK34:CO34) -> 271.93599 | DE34: =_xlfn.CONCAT(D34,L34) -> Manaus29.5 | DF34: =L34 -> 29.5 | DG34: =ROUND(SUMIF($1:$1,DG$5,34:34),2) -> 264.01 | DH34: =ROUND(SUMIF($1:$1,DH$5,34:34),2) -> 1.32 | DI34: =ROUND(SUMIF($1:$1,DI$5,34:34),2) -> 0 | DJ34: =ROUND(SUMIF($1:$1,DJ$5,34:34),2) -> 0 | DK34: =ROUND(SUMIF($1:$1,DK$5,34:34),2) -> 0 | DL34: =ROUND(SUMIF($1:$1,DL$5,34:34),2) -> 0 | DM34: =ROUND(SUMIF($1:$1,DM$5,34:34),2) -> 0 | DN34: =ROUND(SUMIF($1:$1,DN$5,34:34),2) -> 0 | ... ED34: =ROUND(SUMIF($1:$1,ED$5,34:34),2) -> 0 | EE34: =SUM(DG34:ED34) -> 265.33 | EF34: =ROUND(SUM(EE34-BT34),2) -> 0 | EG34: =IF(DN34<>0,DN34-EF34,0) -> 0 | EH34: =IF(EG34=0,DO34-EF34,DO34) -> 0 | EI34: =SUM(DG34:DM34)+SUM(DP34:ED34)+EG34+EH34 -> 265.33
A35: =_xlfn.CONCAT(D35,L35) -> Suape20.6 | B35: 4196 | C35: 4196 | D35: Suape | F35: AMBEV | G35: CONTRATO | H35: FOB | K35: PREFORMA | L35: 20.6 | M35: CR | V35: Virgem | W35: 1 | X35: ALPEK | Y35: =IF($X35="",0,HLOOKUP($H$3,Resina!$E$2:$AK$93,MATCH($D35&$X35&$Y$5,Resina!$A$2:$A$93,0))) -> 1259.2427 | Z35: 0 | AA35: VG | AB35: =IF($AA35="",0,HLOOKUP($H$3,Resina!$E$2:$AK$93,MATCH($D35&$AA35&$AB$5,Resina!$A$2:$A$93,0))) -> 1651.6512 | AC35: =$AC$7 -> 46091 | AD35: Mensal | AE35: =$AE$7 -> 45839 | AF35: MIL | AG35: =_xlfn.XLOOKUP($H$3,Resina!$2:$2,Resina!$3:$3,0) -> 5.2006167 | AH35: =(L35*((Y35*W35)+(AB35*Z35)))*AG35/1000 -> 134.90608 | AI35: 0.005 | AJ35: =AH35*AI35 -> 0.67453039 | AO35: =_xlfn.XLOOKUP($D35&$L35&$AK$3,'BD Conv'!$A:$A,'BD Conv'!$H:$H,0)*_xlfn.XLOOKUP($D35,'BD Conv'!$C$17:$C$19,'BD Conv'!$F$17:$F$19,0)*(1+(HLOOKUP($B35&AO$6,Indexadores!$C$2:$AH$32,MATCH($AE35,Indexadores!$A$2:$A$32,0)))) -> 0 | AS35: 0.005 | AT35: =(AU35+AO35)*AS35 -> 0 | AU35: =_xlfn.XLOOKUP($D35&$L35&$AK$3,'BD Conv'!$A:$A,'BD Conv'!$H:$H,0)*_xlfn.XLOOKUP($D35,'BD Conv'!$C$17:$C$19,'BD Conv'!$E$17:$E$19,0)*(1+(HLOOKUP($B35&AU$6,Indexadores!$C$2:$AH$32,MATCH($AE35,Indexadores!$A$2:$A$32,0)))) -> 0 | AV35: =SUM(AN35,AO35,AP35,(AQ35*AG35),AR35,AT35,AU35) -> 0 | AW35: =_xlfn.XLOOKUP($A35&$AK$3,'BD Conv'!$A:$A,'BD Conv'!$I:$I,0) -> 0 | AZ35: =SUM(AH35,AJ35,AK35,AL35,AV35,AW35:AY35) -> 135.58061 | BI35: =SUM(BA35,BB35,BC35,(BD35*AG35),BE35,BF35,BH35) -> 0 | BN35: =_xlfn.XLOOKUP($A35&$BA$3,'BD Conv'!$A:$A,'BD Conv'!$K:$K,0) -> 0 | BQ35: =SUM(BI35,BJ35,BK35,BM35,BN35,BO35,BP35) -> 0 | BR35: =-BQ35*$BR$3 -> 0 | BT35: =AZ35+BQ35+BR35+BS35 -> 135.58061 | BU35: =BV35-BT35 -> 34.192255 | BV35: =BT35/(1-(12%+1.65%+7.6%) +12%*(1.65%+7.6%)) -> 169.77286 | BY35: =BT35/CP35-1 -> 0.082383897 | BZ35: =(BT35-CP35)/AG35 -> 1.9842836 | CA35: =(BT35-CK35-CL35-AL35-AX35-AY35-BO35-BP35+CQ35)/AG35 -> 1.9842836 | CB35: =(BT35-AH35)/AG35 -> 0.129702 | CD35: =CP35*(1+$CD$5) -> 137.78722 | CE35: =(CD35-CP35)/AG35 -> 2.4085819 | CF35: =(CD35-CK35-CL35-AL35-AX35-AY35-BO35-BP35+CQ35)/AG35 -> 2.4085819 | CG35: =(CD35-AH35)/AG35 -> 0.55400026 | CI35: =IF($X35="",0,HLOOKUP($H$3,Resina!$E$2:$AK$93,MATCH($D35&$X35&$CI$5,Resina!$A$2:$A$93,0))) -> 1157.6381 | CJ35: =IF($AA35="",0,HLOOKUP($H$3,Resina!$E$2:$AK$93,MATCH($D35&$AA35&$CJ$5,Resina!$A$2:$A$93,0))) -> 1610.0071 | CK35: =L35*((CI35*W35)+(CJ35*Z35))*AG35/1000 -> 124.0209 | CL35: =CK35*$CL$6 -> 1.240209 | CM35: =IF(D35="Manaus FORA",-((CK35/0.88*0.12)*(1-9.25%))," ") | CO35: =AX35+AY35+BO35+BP35+AL35+AN35+BJ35+BK35+BM35 -> 0 | CP35: =SUM(CK35:CO35) -> 125.26111 | DE35: =_xlfn.CONCAT(D35,L35) -> Suape20.6 | DF35: =L35 -> 20.6 | DG35: =ROUND(SUMIF($1:$1,DG$5,35:35),2) -> 134.91 | DH35: =ROUND(SUMIF($1:$1,DH$5,35:35),2) -> 0.67 | DI35: =ROUND(SUMIF($1:$1,DI$5,35:35),2) -> 0 | DJ35: =ROUND(SUMIF($1:$1,DJ$5,35:35),2) -> 0 | DK35: =ROUND(SUMIF($1:$1,DK$5,35:35),2) -> 0 | DL35: =ROUND(SUMIF($1:$1,DL$5,35:35),2) -> 0 | DM35: =ROUND(SUMIF($1:$1,DM$5,35:35),2) -> 0 | DN35: =ROUND(SUMIF($1:$1,DN$5,35:35),2) -> 0 | ... ED35: =ROUND(SUMIF($1:$1,ED$5,35:35),2) -> 0 | EE35: =SUM(DG35:ED35) -> 135.58 | EF35: =ROUND(SUM(EE35-BT35),2) -> 0 | EG35: =IF(DN35<>0,DN35-EF35,0) -> 0 | EH35: =IF(EG35=0,DO35-EF35,DO35) -> 0 | EI35: =SUM(DG35:DM35)+SUM(DP35:ED35)+EG35+EH35 -> 135.58
A36: =_xlfn.CONCAT(D36,L36) -> Suape20.6 | B36: 4196 | C36: 4196 | D36: Suape | F36: AMBEV | G36: CONTRATO | H36: FOB | K36: PREFORMA | L36: 20.6 | M36: CR | V36: Virgem | W36: 0.6 | X36: ALPEK | Y36: =IF($X36="",0,HLOOKUP($H$3,Resina!$E$2:$AK$93,MATCH($D36&$X36&$Y$5,Resina!$A$2:$A$93,0))) -> 1259.2427 | Z36: 0.4 | AA36: VG | AB36: =IF($AA36="",0,HLOOKUP($H$3,Resina!$E$2:$AK$93,MATCH($D36&$AA36&$AB$5,Resina!$A$2:$A$93,0))) -> 1651.6512 | AC36: =$AC$7 -> 46091 | AD36: Mensal | AE36: =$AE$7 -> 45839 | AF36: MIL | AG36: =_xlfn.XLOOKUP($H$3,Resina!$2:$2,Resina!$3:$3,0) -> 5.2006167 | AH36: =(L36*((Y36*W36)+(AB36*Z36)))*AG36/1000 -> 151.72199 | AI36: 0.005 | AJ36: =AH36*AI36 -> 0.75860995 | AO36: =_xlfn.XLOOKUP($D36&$L36&$AK$3,'BD Conv'!$A:$A,'BD Conv'!$H:$H,0)*_xlfn.XLOOKUP($D36,'BD Conv'!$C$17:$C$19,'BD Conv'!$F$17:$F$19,0)*(1+(HLOOKUP($B36&AO$6,Indexadores!$C$2:$AH$32,MATCH($AE36,Indexadores!$A$2:$A$32,0)))) -> 0 | AS36: 0.005 | AT36: =(AU36+AO36)*AS36 -> 0 | AU36: =_xlfn.XLOOKUP($D36&$L36&$AK$3,'BD Conv'!$A:$A,'BD Conv'!$H:$H,0)*_xlfn.XLOOKUP($D36,'BD Conv'!$C$17:$C$19,'BD Conv'!$E$17:$E$19,0)*(1+(HLOOKUP($B36&AU$6,Indexadores!$C$2:$AH$32,MATCH($AE36,Indexadores!$A$2:$A$32,0)))) -> 0 | AV36: =SUM(AN36,AO36,AP36,(AQ36*AG36),AR36,AT36,AU36) -> 0 | AW36: =_xlfn.XLOOKUP($A36&$AK$3,'BD Conv'!$A:$A,'BD Conv'!$I:$I,0) -> 0 | AZ36: =SUM(AH36,AJ36,AK36,AL36,AV36,AW36:AY36) -> 152.4806 | BI36: =SUM(BA36,BB36,BC36,(BD36*AG36),BE36,BF36,BH36) -> 0 | BN36: =_xlfn.XLOOKUP($A36&$BA$3,'BD Conv'!$A:$A,'BD Conv'!$K:$K,0) -> 0 | BQ36: =SUM(BI36,BJ36,BK36,BM36,BN36,BO36,BP36) -> 0 | BR36: =-BQ36*$BR$3 -> 0 | BT36: =AZ36+BQ36+BR36+BS36 -> 152.4806 | BU36: =BV36-BT36 -> 38.454286 | BV36: =BT36/(1-(12%+1.65%+7.6%) +12%*(1.65%+7.6%)) -> 190.93489 | BY36: =BT36/CP36-1 -> 0.052749306 | BZ36: =(BT36-CP36)/AG36 -> 1.4691006 | CA36: =(BT36-CK36-CL36-AL36-AX36-AY36-BO36-BP36+CQ36)/AG36 -> 1.4691006 | CB36: =(BT36-AH36)/AG36 -> 0.14586923 | CD36: =CP36*(1+$CD$5) -> 159.32441 | CE36: =(CD36-CP36)/AG36 -> 2.7850615 | CF36: =(CD36-CK36-CL36-AL36-AX36-AY36-BO36-BP36+CQ36)/AG36 -> 2.7850615 | CG36: =(CD36-AH36)/AG36 -> 1.4618301 | CI36: =IF($X36="",0,HLOOKUP($H$3,Resina!$E$2:$AK$93,MATCH($D36&$X36&$CI$5,Resina!$A$2:$A$93,0))) -> 1157.6381 | CJ36: =IF($AA36="",0,HLOOKUP($H$3,Resina!$E$2:$AK$93,MATCH($D36&$AA36&$CJ$5,Resina!$A$2:$A$93,0))) -> 1610.0071 | CK36: =L36*((CI36*W36)+(CJ36*Z36))*AG36/1000 -> 143.40631 | CL36: =CK36*$CL$6 -> 1.4340631 | CM36: =IF(D36="Manaus FORA",-((CK36/0.88*0.12)*(1-9.25%))," ") | CO36: =AX36+AY36+BO36+BP36+AL36+AN36+BJ36+BK36+BM36 -> 0 | CP36: =SUM(CK36:CO36) -> 144.84037 | DE36: =_xlfn.CONCAT(D36,L36) -> Suape20.6 | DF36: =L36 -> 20.6 | DG36: =ROUND(SUMIF($1:$1,DG$5,36:36),2) -> 151.72 | DH36: =ROUND(SUMIF($1:$1,DH$5,36:36),2) -> 0.76 | DI36: =ROUND(SUMIF($1:$1,DI$5,36:36),2) -> 0 | DJ36: =ROUND(SUMIF($1:$1,DJ$5,36:36),2) -> 0 | DK36: =ROUND(SUMIF($1:$1,DK$5,36:36),2) -> 0 | DL36: =ROUND(SUMIF($1:$1,DL$5,36:36),2) -> 0 | DM36: =ROUND(SUMIF($1:$1,DM$5,36:36),2) -> 0 | DN36: =ROUND(SUMIF($1:$1,DN$5,36:36),2) -> 0 | ... ED36: =ROUND(SUMIF($1:$1,ED$5,36:36),2) -> 0 | EE36: =SUM(DG36:ED36) -> 152.48 | EF36: =ROUND(SUM(EE36-BT36),2) -> 0 | EG36: =IF(DN36<>0,DN36-EF36,0) -> 0 | EH36: =IF(EG36=0,DO36-EF36,DO36) -> 0 | EI36: =SUM(DG36:DM36)+SUM(DP36:ED36)+EG36+EH36 -> 152.48
A37: =_xlfn.CONCAT(D37,L37) -> Suape20.6 | B37: 4196 | C37: 4196 | D37: Suape | F37: AMBEV | G37: CONTRATO | H37: FOB | K37: PREFORMA | L37: 20.6 | M37: CR | V37: Virgem | W37: 0.4 | X37: ALPEK | Y37: =IF($X37="",0,HLOOKUP($H$3,Resina!$E$2:$AK$93,MATCH($D37&$X37&$Y$5,Resina!$A$2:$A$93,0))) -> 1259.2427 | Z37: 0.6 | AA37: VG | AB37: =IF($AA37="",0,HLOOKUP($H$3,Resina!$E$2:$AK$93,MATCH($D37&$AA37&$AB$5,Resina!$A$2:$A$93,0))) -> 1651.6512 | AC37: =$AC$7 -> 46091 | AD37: Mensal | AE37: =$AE$7 -> 45839 | AF37: MIL | AG37: =_xlfn.XLOOKUP($H$3,Resina!$2:$2,Resina!$3:$3,0) -> 5.2006167 | AH37: =(L37*((Y37*W37)+(AB37*Z37)))*AG37/1000 -> 160.12995 | AI37: 0.005 | AJ37: =AH37*AI37 -> 0.80064973 | AO37: =_xlfn.XLOOKUP($D37&$L37&$AK$3,'BD Conv'!$A:$A,'BD Conv'!$H:$H,0)*_xlfn.XLOOKUP($D37,'BD Conv'!$C$17:$C$19,'BD Conv'!$F$17:$F$19,0)*(1+(HLOOKUP($B37&AO$6,Indexadores!$C$2:$AH$32,MATCH($AE37,Indexadores!$A$2:$A$32,0)))) -> 0 | AS37: 0.005 | AT37: =(AU37+AO37)*AS37 -> 0 | AU37: =_xlfn.XLOOKUP($D37&$L37&$AK$3,'BD Conv'!$A:$A,'BD Conv'!$H:$H,0)*_xlfn.XLOOKUP($D37,'BD Conv'!$C$17:$C$19,'BD Conv'!$E$17:$E$19,0)*(1+(HLOOKUP($B37&AU$6,Indexadores!$C$2:$AH$32,MATCH($AE37,Indexadores!$A$2:$A$32,0)))) -> 0 | AV37: =SUM(AN37,AO37,AP37,(AQ37*AG37),AR37,AT37,AU37) -> 0 | AW37: =_xlfn.XLOOKUP($A37&$AK$3,'BD Conv'!$A:$A,'BD Conv'!$I:$I,0) -> 0 | AZ37: =SUM(AH37,AJ37,AK37,AL37,AV37,AW37:AY37) -> 160.9306 | BI37: =SUM(BA37,BB37,BC37,(BD37*AG37),BE37,BF37,BH37) -> 0 | BN37: =_xlfn.XLOOKUP($A37&$BA$3,'BD Conv'!$A:$A,'BD Conv'!$K:$K,0) -> 0 | BQ37: =SUM(BI37,BJ37,BK37,BM37,BN37,BO37,BP37) -> 0 | BR37: =-BQ37*$BR$3 -> 0 | BT37: =AZ37+BQ37+BR37+BS37 -> 160.9306 | BU37: =BV37-BT37 -> 40.585302 | BV37: =BT37/(1-(12%+1.65%+7.6%) +12%*(1.65%+7.6%)) -> 201.5159 | BY37: =BT37/CP37-1 -> 0.040746262 | BZ37: =(BT37-CP37)/AG37 -> 1.2115091 | CA37: =(BT37-CK37-CL37-AL37-AX37-AY37-BO37-BP37+CQ37)/AG37 -> 1.2115091 | CB37: =(BT37-AH37)/AG37 -> 0.15395284 | CD37: =CP37*(1+$CD$5) -> 170.093 | CE37: =(CD37-CP37)/AG37 -> 2.9733013 | CF37: =(CD37-CK37-CL37-AL37-AX37-AY37-BO37-BP37+CQ37)/AG37 -> 2.9733013 | CG37: =(CD37-AH37)/AG37 -> 1.915745 | CI37: =IF($X37="",0,HLOOKUP($H$3,Resina!$E$2:$AK$93,MATCH($D37&$X37&$CI$5,Resina!$A$2:$A$93,0))) -> 1157.6381 | CJ37: =IF($AA37="",0,HLOOKUP($H$3,Resina!$E$2:$AK$93,MATCH($D37&$AA37&$CJ$5,Resina!$A$2:$A$93,0))) -> 1610.0071 | CK37: =L37*((CI37*W37)+(CJ37*Z37))*AG37/1000 -> 153.09901 | CL37: =CK37*$CL$6 -> 1.5309901 | CM37: =IF(D37="Manaus FORA",-((CK37/0.88*0.12)*(1-9.25%))," ") | CO37: =AX37+AY37+BO37+BP37+AL37+AN37+BJ37+BK37+BM37 -> 0 | CP37: =SUM(CK37:CO37) -> 154.63 | DE37: =_xlfn.CONCAT(D37,L37) -> Suape20.6 | DF37: =L37 -> 20.6 | DG37: =ROUND(SUMIF($1:$1,DG$5,37:37),2) -> 160.13 | DH37: =ROUND(SUMIF($1:$1,DH$5,37:37),2) -> 0.8 | DI37: =ROUND(SUMIF($1:$1,DI$5,37:37),2) -> 0 | DJ37: =ROUND(SUMIF($1:$1,DJ$5,37:37),2) -> 0 | DK37: =ROUND(SUMIF($1:$1,DK$5,37:37),2) -> 0 | DL37: =ROUND(SUMIF($1:$1,DL$5,37:37),2) -> 0 | DM37: =ROUND(SUMIF($1:$1,DM$5,37:37),2) -> 0 | DN37: =ROUND(SUMIF($1:$1,DN$5,37:37),2) -> 0 | ... ED37: =ROUND(SUMIF($1:$1,ED$5,37:37),2) -> 0 | EE37: =SUM(DG37:ED37) -> 160.93 | EF37: =ROUND(SUM(EE37-BT37),2) -> 0 | EG37: =IF(DN37<>0,DN37-EF37,0) -> 0 | EH37: =IF(EG37=0,DO37-EF37,DO37) -> 0 | EI37: =SUM(DG37:DM37)+SUM(DP37:ED37)+EG37+EH37 -> 160.93
A38: =_xlfn.CONCAT(D38,L38) -> Suape20.6 | B38: 4196 | C38: 4196 | D38: Suape | F38: AMBEV | G38: CONTRATO | H38: FOB | K38: PREFORMA | L38: 20.6 | M38: CR | V38: Virgem | W38: 0 | Y38: =IF($X38="",0,HLOOKUP($H$3,Resina!$E$2:$AK$93,MATCH($D38&$X38&$Y$5,Resina!$A$2:$A$93,0))) -> 0 | Z38: 1 | AA38: VG | AB38: =IF($AA38="",0,HLOOKUP($H$3,Resina!$E$2:$AK$93,MATCH($D38&$AA38&$AB$5,Resina!$A$2:$A$93,0))) -> 1651.6512 | AC38: =$AC$7 -> 46091 | AD38: Mensal | AE38: =$AE$7 -> 45839 | AF38: MIL | AG38: =_xlfn.XLOOKUP($H$3,Resina!$2:$2,Resina!$3:$3,0) -> 5.2006167 | AH38: =(L38*((Y38*W38)+(AB38*Z38)))*AG38/1000 -> 176.94586 | AI38: 0.005 | AJ38: =AH38*AI38 -> 0.88472929 | AO38: =_xlfn.XLOOKUP($D38&$L38&$AK$3,'BD Conv'!$A:$A,'BD Conv'!$H:$H,0)*_xlfn.XLOOKUP($D38,'BD Conv'!$C$17:$C$19,'BD Conv'!$F$17:$F$19,0)*(1+(HLOOKUP($B38&AO$6,Indexadores!$C$2:$AH$32,MATCH($AE38,Indexadores!$A$2:$A$32,0)))) -> 0 | AS38: 0.005 | AT38: =(AU38+AO38)*AS38 -> 0 | AU38: =_xlfn.XLOOKUP($D38&$L38&$AK$3,'BD Conv'!$A:$A,'BD Conv'!$H:$H,0)*_xlfn.XLOOKUP($D38,'BD Conv'!$C$17:$C$19,'BD Conv'!$E$17:$E$19,0)*(1+(HLOOKUP($B38&AU$6,Indexadores!$C$2:$AH$32,MATCH($AE38,Indexadores!$A$2:$A$32,0)))) -> 0 | AV38: =SUM(AN38,AO38,AP38,(AQ38*AG38),AR38,AT38,AU38) -> 0 | AW38: =_xlfn.XLOOKUP($A38&$AK$3,'BD Conv'!$A:$A,'BD Conv'!$I:$I,0) -> 0 | AZ38: =SUM(AH38,AJ38,AK38,AL38,AV38,AW38:AY38) -> 177.83059 | BI38: =SUM(BA38,BB38,BC38,(BD38*AG38),BE38,BF38,BH38) -> 0 | BN38: =_xlfn.XLOOKUP($A38&$BA$3,'BD Conv'!$A:$A,'BD Conv'!$K:$K,0) -> 0 | BQ38: =SUM(BI38,BJ38,BK38,BM38,BN38,BO38,BP38) -> 0 | BR38: =-BQ38*$BR$3 -> 0 | BT38: =AZ38+BQ38+BR38+BS38 -> 177.83059 | BU38: =BV38-BT38 -> 44.847333 | BV38: =BT38/(1-(12%+1.65%+7.6%) +12%*(1.65%+7.6%)) -> 222.67792 | BY38: =BT38/CP38-1 -> 0.020787214 | BZ38: =(BT38-CP38)/AG38 -> 0.69632612 | CA38: =(BT38-CK38-CL38-AL38-AX38-AY38-BO38-BP38+CQ38)/AG38 -> 0.69632612 | CB38: =(BT38-AH38)/AG38 -> 0.17012007 | CD38: =CP38*(1+$CD$5) -> 191.63019 | CE38: =(CD38-CP38)/AG38 -> 3.3497809 | CF38: =(CD38-CK38-CL38-AL38-AX38-AY38-BO38-BP38+CQ38)/AG38 -> 3.3497809 | CG38: =(CD38-AH38)/AG38 -> 2.8235748 | CI38: =IF($X38="",0,HLOOKUP($H$3,Resina!$E$2:$AK$93,MATCH($D38&$X38&$CI$5,Resina!$A$2:$A$93,0))) -> 0 | CJ38: =IF($AA38="",0,HLOOKUP($H$3,Resina!$E$2:$AK$93,MATCH($D38&$AA38&$CJ$5,Resina!$A$2:$A$93,0))) -> 1610.0071 | CK38: =L38*((CI38*W38)+(CJ38*Z38))*AG38/1000 -> 172.48442 | CL38: =CK38*$CL$6 -> 1.7248442 | CM38: =IF(D38="Manaus FORA",-((CK38/0.88*0.12)*(1-9.25%))," ") | CO38: =AX38+AY38+BO38+BP38+AL38+AN38+BJ38+BK38+BM38 -> 0 | CP38: =SUM(CK38:CO38) -> 174.20926 | DE38: =_xlfn.CONCAT(D38,L38) -> Suape20.6 | DF38: =L38 -> 20.6 | DG38: =ROUND(SUMIF($1:$1,DG$5,38:38),2) -> 176.95 | DH38: =ROUND(SUMIF($1:$1,DH$5,38:38),2) -> 0.88 | DI38: =ROUND(SUMIF($1:$1,DI$5,38:38),2) -> 0 | DJ38: =ROUND(SUMIF($1:$1,DJ$5,38:38),2) -> 0 | DK38: =ROUND(SUMIF($1:$1,DK$5,38:38),2) -> 0 | DL38: =ROUND(SUMIF($1:$1,DL$5,38:38),2) -> 0 | DM38: =ROUND(SUMIF($1:$1,DM$5,38:38),2) -> 0 | DN38: =ROUND(SUMIF($1:$1,DN$5,38:38),2) -> 0 | ... ED38: =ROUND(SUMIF($1:$1,ED$5,38:38),2) -> 0 | EE38: =SUM(DG38:ED38) -> 177.83 | EF38: =ROUND(SUM(EE38-BT38),2) -> 0 | EG38: =IF(DN38<>0,DN38-EF38,0) -> 0 | EH38: =IF(EG38=0,DO38-EF38,DO38) -> 0 | EI38: =SUM(DG38:DM38)+SUM(DP38:ED38)+EG38+EH38 -> 177.83
A39: =_xlfn.CONCAT(D39,L39) -> Suape20.6 | B39: 4196 | C39: 4196 | D39: Suape | F39: AMBEV | G39: CONTRATO | H39: FOB | K39: PREFORMA | L39: 20.6 | M39: VD | V39: Virgem | W39: 1 | X39: ALPEK | Y39: =IF($X39="",0,HLOOKUP($H$3,Resina!$E$2:$AK$93,MATCH($D39&$X39&$Y$5,Resina!$A$2:$A$93,0))) -> 1259.2427 | Z39: 0 | AA39: VG | AB39: =IF($AA39="",0,HLOOKUP($H$3,Resina!$E$2:$AK$93,MATCH($D39&$AA39&$AB$5,Resina!$A$2:$A$93,0))) -> 1651.6512 | AC39: =$AC$7 -> 46091 | AD39: Mensal | AE39: =$AE$7 -> 45839 | AF39: MIL | AG39: =_xlfn.XLOOKUP($H$3,Resina!$2:$2,Resina!$3:$3,0) -> 5.2006167 | AH39: =(L39*((Y39*W39)+(AB39*Z39)))*AG39/1000 -> 134.90608 | AI39: 0.005 | AJ39: =AH39*AI39 -> 0.67453039 | AO39: =_xlfn.XLOOKUP($D39&$L39&$AK$3,'BD Conv'!$A:$A,'BD Conv'!$H:$H,0)*_xlfn.XLOOKUP($D39,'BD Conv'!$C$17:$C$19,'BD Conv'!$F$17:$F$19,0)*(1+(HLOOKUP($B39&AO$6,Indexadores!$C$2:$AH$32,MATCH($AE39,Indexadores!$A$2:$A$32,0)))) -> 0 | AS39: 0.005 | AT39: =(AU39+AO39)*AS39 -> 0 | AU39: =_xlfn.XLOOKUP($D39&$L39&$AK$3,'BD Conv'!$A:$A,'BD Conv'!$H:$H,0)*_xlfn.XLOOKUP($D39,'BD Conv'!$C$17:$C$19,'BD Conv'!$E$17:$E$19,0)*(1+(HLOOKUP($B39&AU$6,Indexadores!$C$2:$AH$32,MATCH($AE39,Indexadores!$A$2:$A$32,0)))) -> 0 | AV39: =SUM(AN39,AO39,AP39,(AQ39*AG39),AR39,AT39,AU39) -> 0 | AW39: =_xlfn.XLOOKUP($A39&$AK$3,'BD Conv'!$A:$A,'BD Conv'!$I:$I,0) -> 0 | AZ39: =SUM(AH39,AJ39,AK39,AL39,AV39,AW39:AY39) -> 135.58061 | BI39: =SUM(BA39,BB39,BC39,(BD39*AG39),BE39,BF39,BH39) -> 0 | BN39: =_xlfn.XLOOKUP($A39&$BA$3,'BD Conv'!$A:$A,'BD Conv'!$K:$K,0) -> 0 | BQ39: =SUM(BI39,BJ39,BK39,BM39,BN39,BO39,BP39) -> 0 | BR39: =-BQ39*$BR$3 -> 0 | BT39: =AZ39+BQ39+BR39+BS39 -> 135.58061 | BU39: =BV39-BT39 -> 34.192255 | BV39: =BT39/(1-(12%+1.65%+7.6%) +12%*(1.65%+7.6%)) -> 169.77286 | BY39: =BT39/CP39-1 -> 0.082383897 | BZ39: =(BT39-CP39)/AG39 -> 1.9842836 | CA39: =(BT39-CK39-CL39-AL39-AX39-AY39-BO39-BP39+CQ39)/AG39 -> 1.9842836 | CB39: =(BT39-AH39)/AG39 -> 0.129702 | CD39: =CP39*(1+$CD$5) -> 137.78722 | CE39: =(CD39-CP39)/AG39 -> 2.4085819 | CF39: =(CD39-CK39-CL39-AL39-AX39-AY39-BO39-BP39+CQ39)/AG39 -> 2.4085819 | CG39: =(CD39-AH39)/AG39 -> 0.55400026 | CI39: =IF($X39="",0,HLOOKUP($H$3,Resina!$E$2:$AK$93,MATCH($D39&$X39&$CI$5,Resina!$A$2:$A$93,0))) -> 1157.6381 | CJ39: =IF($AA39="",0,HLOOKUP($H$3,Resina!$E$2:$AK$93,MATCH($D39&$AA39&$CJ$5,Resina!$A$2:$A$93,0))) -> 1610.0071 | CK39: =L39*((CI39*W39)+(CJ39*Z39))*AG39/1000 -> 124.0209 | CL39: =CK39*$CL$6 -> 1.240209 | CM39: =IF(D39="Manaus FORA",-((CK39/0.88*0.12)*(1-9.25%))," ") | CO39: =AX39+AY39+BO39+BP39+AL39+AN39+BJ39+BK39+BM39 -> 0 | CP39: =SUM(CK39:CO39) -> 125.26111 | DE39: =_xlfn.CONCAT(D39,L39) -> Suape20.6 | DF39: =L39 -> 20.6 | DG39: =ROUND(SUMIF($1:$1,DG$5,39:39),2) -> 134.91 | DH39: =ROUND(SUMIF($1:$1,DH$5,39:39),2) -> 0.67 | DI39: =ROUND(SUMIF($1:$1,DI$5,39:39),2) -> 0 | DJ39: =ROUND(SUMIF($1:$1,DJ$5,39:39),2) -> 0 | DK39: =ROUND(SUMIF($1:$1,DK$5,39:39),2) -> 0 | DL39: =ROUND(SUMIF($1:$1,DL$5,39:39),2) -> 0 | DM39: =ROUND(SUMIF($1:$1,DM$5,39:39),2) -> 0 | DN39: =ROUND(SUMIF($1:$1,DN$5,39:39),2) -> 0 | ... ED39: =ROUND(SUMIF($1:$1,ED$5,39:39),2) -> 0 | EE39: =SUM(DG39:ED39) -> 135.58 | EF39: =ROUND(SUM(EE39-BT39),2) -> 0 | EG39: =IF(DN39<>0,DN39-EF39,0) -> 0 | EH39: =IF(EG39=0,DO39-EF39,DO39) -> 0 | EI39: =SUM(DG39:DM39)+SUM(DP39:ED39)+EG39+EH39 -> 135.58
A40: =_xlfn.CONCAT(D40,L40) -> Suape20.6 | B40: 4196 | C40: 4196 | D40: Suape | F40: AMBEV | G40: CONTRATO | H40: FOB | K40: PREFORMA | L40: 20.6 | M40: VD | V40: Virgem | W40: 0.6 | X40: ALPEK | Y40: =IF($X40="",0,HLOOKUP($H$3,Resina!$E$2:$AK$93,MATCH($D40&$X40&$Y$5,Resina!$A$2:$A$93,0))) -> 1259.2427 | Z40: 0.4 | AA40: VG | AB40: =IF($AA40="",0,HLOOKUP($H$3,Resina!$E$2:$AK$93,MATCH($D40&$AA40&$AB$5,Resina!$A$2:$A$93,0))) -> 1651.6512 | AC40: =$AC$7 -> 46091 | AD40: Mensal | AE40: =$AE$7 -> 45839 | AF40: MIL | AG40: =_xlfn.XLOOKUP($H$3,Resina!$2:$2,Resina!$3:$3,0) -> 5.2006167 | AH40: =(L40*((Y40*W40)+(AB40*Z40)))*AG40/1000 -> 151.72199 | AI40: 0.005 | AJ40: =AH40*AI40 -> 0.75860995 | AO40: =_xlfn.XLOOKUP($D40&$L40&$AK$3,'BD Conv'!$A:$A,'BD Conv'!$H:$H,0)*_xlfn.XLOOKUP($D40,'BD Conv'!$C$17:$C$19,'BD Conv'!$F$17:$F$19,0)*(1+(HLOOKUP($B40&AO$6,Indexadores!$C$2:$AH$32,MATCH($AE40,Indexadores!$A$2:$A$32,0)))) -> 0 | AS40: 0.005 | AT40: =(AU40+AO40)*AS40 -> 0 | AU40: =_xlfn.XLOOKUP($D40&$L40&$AK$3,'BD Conv'!$A:$A,'BD Conv'!$H:$H,0)*_xlfn.XLOOKUP($D40,'BD Conv'!$C$17:$C$19,'BD Conv'!$E$17:$E$19,0)*(1+(HLOOKUP($B40&AU$6,Indexadores!$C$2:$AH$32,MATCH($AE40,Indexadores!$A$2:$A$32,0)))) -> 0 | AV40: =SUM(AN40,AO40,AP40,(AQ40*AG40),AR40,AT40,AU40) -> 0 | AW40: =_xlfn.XLOOKUP($A40&$AK$3,'BD Conv'!$A:$A,'BD Conv'!$I:$I,0) -> 0 | AZ40: =SUM(AH40,AJ40,AK40,AL40,AV40,AW40:AY40) -> 152.4806 | BI40: =SUM(BA40,BB40,BC40,(BD40*AG40),BE40,BF40,BH40) -> 0 | BN40: =_xlfn.XLOOKUP($A40&$BA$3,'BD Conv'!$A:$A,'BD Conv'!$K:$K,0) -> 0 | BQ40: =SUM(BI40,BJ40,BK40,BM40,BN40,BO40,BP40) -> 0 | BR40: =-BQ40*$BR$3 -> 0 | BT40: =AZ40+BQ40+BR40+BS40 -> 152.4806 | BU40: =BV40-BT40 -> 38.454286 | BV40: =BT40/(1-(12%+1.65%+7.6%) +12%*(1.65%+7.6%)) -> 190.93489 | BY40: =BT40/CP40-1 -> 0.052749306 | BZ40: =(BT40-CP40)/AG40 -> 1.4691006 | CA40: =(BT40-CK40-CL40-AL40-AX40-AY40-BO40-BP40+CQ40)/AG40 -> 1.4691006 | CB40: =(BT40-AH40)/AG40 -> 0.14586923 | CD40: =CP40*(1+$CD$5) -> 159.32441 | CE40: =(CD40-CP40)/AG40 -> 2.7850615 | CF40: =(CD40-CK40-CL40-AL40-AX40-AY40-BO40-BP40+CQ40)/AG40 -> 2.7850615 | CG40: =(CD40-AH40)/AG40 -> 1.4618301 | CI40: =IF($X40="",0,HLOOKUP($H$3,Resina!$E$2:$AK$93,MATCH($D40&$X40&$CI$5,Resina!$A$2:$A$93,0))) -> 1157.6381 | CJ40: =IF($AA40="",0,HLOOKUP($H$3,Resina!$E$2:$AK$93,MATCH($D40&$AA40&$CJ$5,Resina!$A$2:$A$93,0))) -> 1610.0071 | CK40: =L40*((CI40*W40)+(CJ40*Z40))*AG40/1000 -> 143.40631 | CL40: =CK40*$CL$6 -> 1.4340631 | CM40: =IF(D40="Manaus FORA",-((CK40/0.88*0.12)*(1-9.25%))," ") | CO40: =AX40+AY40+BO40+BP40+AL40+AN40+BJ40+BK40+BM40 -> 0 | CP40: =SUM(CK40:CO40) -> 144.84037 | DE40: =_xlfn.CONCAT(D40,L40) -> Suape20.6 | DF40: =L40 -> 20.6 | DG40: =ROUND(SUMIF($1:$1,DG$5,40:40),2) -> 151.72 | DH40: =ROUND(SUMIF($1:$1,DH$5,40:40),2) -> 0.76 | DI40: =ROUND(SUMIF($1:$1,DI$5,40:40),2) -> 0 | DJ40: =ROUND(SUMIF($1:$1,DJ$5,40:40),2) -> 0 | DK40: =ROUND(SUMIF($1:$1,DK$5,40:40),2) -> 0 | DL40: =ROUND(SUMIF($1:$1,DL$5,40:40),2) -> 0 | DM40: =ROUND(SUMIF($1:$1,DM$5,40:40),2) -> 0 | DN40: =ROUND(SUMIF($1:$1,DN$5,40:40),2) -> 0 | ... ED40: =ROUND(SUMIF($1:$1,ED$5,40:40),2) -> 0 | EE40: =SUM(DG40:ED40) -> 152.48 | EF40: =ROUND(SUM(EE40-BT40),2) -> 0 | EG40: =IF(DN40<>0,DN40-EF40,0) -> 0 | EH40: =IF(EG40=0,DO40-EF40,DO40) -> 0 | EI40: =SUM(DG40:DM40)+SUM(DP40:ED40)+EG40+EH40 -> 152.48
A41: =_xlfn.CONCAT(D41,L41) -> Suape20.6 | B41: 4196 | C41: 4196 | D41: Suape | F41: AMBEV | G41: CONTRATO | H41: FOB | K41: PREFORMA | L41: 20.6 | M41: VD | V41: Virgem | W41: 0.4 | X41: ALPEK | Y41: =IF($X41="",0,HLOOKUP($H$3,Resina!$E$2:$AK$93,MATCH($D41&$X41&$Y$5,Resina!$A$2:$A$93,0))) -> 1259.2427 | Z41: 0.6 | AA41: VG | AB41: =IF($AA41="",0,HLOOKUP($H$3,Resina!$E$2:$AK$93,MATCH($D41&$AA41&$AB$5,Resina!$A$2:$A$93,0))) -> 1651.6512 | AC41: =$AC$7 -> 46091 | AD41: Mensal | AE41: =$AE$7 -> 45839 | AF41: MIL | AG41: =_xlfn.XLOOKUP($H$3,Resina!$2:$2,Resina!$3:$3,0) -> 5.2006167 | AH41: =(L41*((Y41*W41)+(AB41*Z41)))*AG41/1000 -> 160.12995 | AI41: 0.005 | AJ41: =AH41*AI41 -> 0.80064973 | AO41: =_xlfn.XLOOKUP($D41&$L41&$AK$3,'BD Conv'!$A:$A,'BD Conv'!$H:$H,0)*_xlfn.XLOOKUP($D41,'BD Conv'!$C$17:$C$19,'BD Conv'!$F$17:$F$19,0)*(1+(HLOOKUP($B41&AO$6,Indexadores!$C$2:$AH$32,MATCH($AE41,Indexadores!$A$2:$A$32,0)))) -> 0 | AS41: 0.005 | AT41: =(AU41+AO41)*AS41 -> 0 | AU41: =_xlfn.XLOOKUP($D41&$L41&$AK$3,'BD Conv'!$A:$A,'BD Conv'!$H:$H,0)*_xlfn.XLOOKUP($D41,'BD Conv'!$C$17:$C$19,'BD Conv'!$E$17:$E$19,0)*(1+(HLOOKUP($B41&AU$6,Indexadores!$C$2:$AH$32,MATCH($AE41,Indexadores!$A$2:$A$32,0)))) -> 0 | AV41: =SUM(AN41,AO41,AP41,(AQ41*AG41),AR41,AT41,AU41) -> 0 | AW41: =_xlfn.XLOOKUP($A41&$AK$3,'BD Conv'!$A:$A,'BD Conv'!$I:$I,0) -> 0 | AZ41: =SUM(AH41,AJ41,AK41,AL41,AV41,AW41:AY41) -> 160.9306 | BI41: =SUM(BA41,BB41,BC41,(BD41*AG41),BE41,BF41,BH41) -> 0 | BN41: =_xlfn.XLOOKUP($A41&$BA$3,'BD Conv'!$A:$A,'BD Conv'!$K:$K,0) -> 0 | BQ41: =SUM(BI41,BJ41,BK41,BM41,BN41,BO41,BP41) -> 0 | BR41: =-BQ41*$BR$3 -> 0 | BT41: =AZ41+BQ41+BR41+BS41 -> 160.9306 | BU41: =BV41-BT41 -> 40.585302 | BV41: =BT41/(1-(12%+1.65%+7.6%) +12%*(1.65%+7.6%)) -> 201.5159 | BY41: =BT41/CP41-1 -> 0.040746262 | BZ41: =(BT41-CP41)/AG41 -> 1.2115091 | CA41: =(BT41-CK41-CL41-AL41-AX41-AY41-BO41-BP41+CQ41)/AG41 -> 1.2115091 | CB41: =(BT41-AH41)/AG41 -> 0.15395284 | CD41: =CP41*(1+$CD$5) -> 170.093 | CE41: =(CD41-CP41)/AG41 -> 2.9733013 | CF41: =(CD41-CK41-CL41-AL41-AX41-AY41-BO41-BP41+CQ41)/AG41 -> 2.9733013 | CG41: =(CD41-AH41)/AG41 -> 1.915745 | CI41: =IF($X41="",0,HLOOKUP($H$3,Resina!$E$2:$AK$93,MATCH($D41&$X41&$CI$5,Resina!$A$2:$A$93,0))) -> 1157.6381 | CJ41: =IF($AA41="",0,HLOOKUP($H$3,Resina!$E$2:$AK$93,MATCH($D41&$AA41&$CJ$5,Resina!$A$2:$A$93,0))) -> 1610.0071 | CK41: =L41*((CI41*W41)+(CJ41*Z41))*AG41/1000 -> 153.09901 | CL41: =CK41*$CL$6 -> 1.5309901 | CM41: =IF(D41="Manaus FORA",-((CK41/0.88*0.12)*(1-9.25%))," ") | CO41: =AX41+AY41+BO41+BP41+AL41+AN41+BJ41+BK41+BM41 -> 0 | CP41: =SUM(CK41:CO41) -> 154.63 | DE41: =_xlfn.CONCAT(D41,L41) -> Suape20.6 | DF41: =L41 -> 20.6 | DG41: =ROUND(SUMIF($1:$1,DG$5,41:41),2) -> 160.13 | DH41: =ROUND(SUMIF($1:$1,DH$5,41:41),2) -> 0.8 | DI41: =ROUND(SUMIF($1:$1,DI$5,41:41),2) -> 0 | DJ41: =ROUND(SUMIF($1:$1,DJ$5,41:41),2) -> 0 | DK41: =ROUND(SUMIF($1:$1,DK$5,41:41),2) -> 0 | DL41: =ROUND(SUMIF($1:$1,DL$5,41:41),2) -> 0 | DM41: =ROUND(SUMIF($1:$1,DM$5,41:41),2) -> 0 | DN41: =ROUND(SUMIF($1:$1,DN$5,41:41),2) -> 0 | ... ED41: =ROUND(SUMIF($1:$1,ED$5,41:41),2) -> 0 | EE41: =SUM(DG41:ED41) -> 160.93 | EF41: =ROUND(SUM(EE41-BT41),2) -> 0 | EG41: =IF(DN41<>0,DN41-EF41,0) -> 0 | EH41: =IF(EG41=0,DO41-EF41,DO41) -> 0 | EI41: =SUM(DG41:DM41)+SUM(DP41:ED41)+EG41+EH41 -> 160.93
A42: =_xlfn.CONCAT(D42,L42) -> Suape20.6 | B42: 4196 | C42: 4196 | D42: Suape | F42: AMBEV | G42: CONTRATO | H42: FOB | K42: PREFORMA | L42: 20.6 | M42: VD | V42: Virgem | W42: 0 | Y42: =IF($X42="",0,HLOOKUP($H$3,Resina!$E$2:$AK$93,MATCH($D42&$X42&$Y$5,Resina!$A$2:$A$93,0))) -> 0 | Z42: 1 | AA42: VG | AB42: =IF($AA42="",0,HLOOKUP($H$3,Resina!$E$2:$AK$93,MATCH($D42&$AA42&$AB$5,Resina!$A$2:$A$93,0))) -> 1651.6512 | AC42: =$AC$7 -> 46091 | AD42: Mensal | AE42: =$AE$7 -> 45839 | AF42: MIL | AG42: =_xlfn.XLOOKUP($H$3,Resina!$2:$2,Resina!$3:$3,0) -> 5.2006167 | AH42: =(L42*((Y42*W42)+(AB42*Z42)))*AG42/1000 -> 176.94586 | AI42: 0.005 | AJ42: =AH42*AI42 -> 0.88472929 | AO42: =_xlfn.XLOOKUP($D42&$L42&$AK$3,'BD Conv'!$A:$A,'BD Conv'!$H:$H,0)*_xlfn.XLOOKUP($D42,'BD Conv'!$C$17:$C$19,'BD Conv'!$F$17:$F$19,0)*(1+(HLOOKUP($B42&AO$6,Indexadores!$C$2:$AH$32,MATCH($AE42,Indexadores!$A$2:$A$32,0)))) -> 0 | AS42: 0.005 | AT42: =(AU42+AO42)*AS42 -> 0 | AU42: =_xlfn.XLOOKUP($D42&$L42&$AK$3,'BD Conv'!$A:$A,'BD Conv'!$H:$H,0)*_xlfn.XLOOKUP($D42,'BD Conv'!$C$17:$C$19,'BD Conv'!$E$17:$E$19,0)*(1+(HLOOKUP($B42&AU$6,Indexadores!$C$2:$AH$32,MATCH($AE42,Indexadores!$A$2:$A$32,0)))) -> 0 | AV42: =SUM(AN42,AO42,AP42,(AQ42*AG42),AR42,AT42,AU42) -> 0 | AW42: =_xlfn.XLOOKUP($A42&$AK$3,'BD Conv'!$A:$A,'BD Conv'!$I:$I,0) -> 0 | AZ42: =SUM(AH42,AJ42,AK42,AL42,AV42,AW42:AY42) -> 177.83059 | BI42: =SUM(BA42,BB42,BC42,(BD42*AG42),BE42,BF42,BH42) -> 0 | BN42: =_xlfn.XLOOKUP($A42&$BA$3,'BD Conv'!$A:$A,'BD Conv'!$K:$K,0) -> 0 | BQ42: =SUM(BI42,BJ42,BK42,BM42,BN42,BO42,BP42) -> 0 | BR42: =-BQ42*$BR$3 -> 0 | BT42: =AZ42+BQ42+BR42+BS42 -> 177.83059 | BU42: =BV42-BT42 -> 44.847333 | BV42: =BT42/(1-(12%+1.65%+7.6%) +12%*(1.65%+7.6%)) -> 222.67792 | BY42: =BT42/CP42-1 -> 0.020787214 | BZ42: =(BT42-CP42)/AG42 -> 0.69632612 | CA42: =(BT42-CK42-CL42-AL42-AX42-AY42-BO42-BP42+CQ42)/AG42 -> 0.69632612 | CB42: =(BT42-AH42)/AG42 -> 0.17012007 | CD42: =CP42*(1+$CD$5) -> 191.63019 | CE42: =(CD42-CP42)/AG42 -> 3.3497809 | CF42: =(CD42-CK42-CL42-AL42-AX42-AY42-BO42-BP42+CQ42)/AG42 -> 3.3497809 | CG42: =(CD42-AH42)/AG42 -> 2.8235748 | CI42: =IF($X42="",0,HLOOKUP($H$3,Resina!$E$2:$AK$93,MATCH($D42&$X42&$CI$5,Resina!$A$2:$A$93,0))) -> 0 | CJ42: =IF($AA42="",0,HLOOKUP($H$3,Resina!$E$2:$AK$93,MATCH($D42&$AA42&$CJ$5,Resina!$A$2:$A$93,0))) -> 1610.0071 | CK42: =L42*((CI42*W42)+(CJ42*Z42))*AG42/1000 -> 172.48442 | CL42: =CK42*$CL$6 -> 1.7248442 | CM42: =IF(D42="Manaus FORA",-((CK42/0.88*0.12)*(1-9.25%))," ") | CO42: =AX42+AY42+BO42+BP42+AL42+AN42+BJ42+BK42+BM42 -> 0 | CP42: =SUM(CK42:CO42) -> 174.20926 | DE42: =_xlfn.CONCAT(D42,L42) -> Suape20.6 | DF42: =L42 -> 20.6 | DG42: =ROUND(SUMIF($1:$1,DG$5,42:42),2) -> 176.95 | DH42: =ROUND(SUMIF($1:$1,DH$5,42:42),2) -> 0.88 | DI42: =ROUND(SUMIF($1:$1,DI$5,42:42),2) -> 0 | DJ42: =ROUND(SUMIF($1:$1,DJ$5,42:42),2) -> 0 | DK42: =ROUND(SUMIF($1:$1,DK$5,42:42),2) -> 0 | DL42: =ROUND(SUMIF($1:$1,DL$5,42:42),2) -> 0 | DM42: =ROUND(SUMIF($1:$1,DM$5,42:42),2) -> 0 | DN42: =ROUND(SUMIF($1:$1,DN$5,42:42),2) -> 0 | ... ED42: =ROUND(SUMIF($1:$1,ED$5,42:42),2) -> 0 | EE42: =SUM(DG42:ED42) -> 177.83 | EF42: =ROUND(SUM(EE42-BT42),2) -> 0 | EG42: =IF(DN42<>0,DN42-EF42,0) -> 0 | EH42: =IF(EG42=0,DO42-EF42,DO42) -> 0 | EI42: =SUM(DG42:DM42)+SUM(DP42:ED42)+EG42+EH42 -> 177.83
A43: =_xlfn.CONCAT(D43,L43) -> Suape38 | B43: 4196 | C43: 4196 | D43: Suape | F43: AMBEV | G43: CONTRATO | H43: FOB | K43: PREFORMA | L43: 38 | M43: CR | V43: Virgem | W43: 1 | X43: ALPEK | Y43: =IF($X43="",0,HLOOKUP($H$3,Resina!$E$2:$AK$93,MATCH($D43&$X43&$Y$5,Resina!$A$2:$A$93,0))) -> 1259.2427 | Z43: 0 | AA43: VG | AB43: =IF($AA43="",0,HLOOKUP($H$3,Resina!$E$2:$AK$93,MATCH($D43&$AA43&$AB$5,Resina!$A$2:$A$93,0))) -> 1651.6512 | AC43: =$AC$7 -> 46091 | AD43: Mensal | AE43: =$AE$7 -> 45839 | AF43: MIL | AG43: =_xlfn.XLOOKUP($H$3,Resina!$2:$2,Resina!$3:$3,0) -> 5.2006167 | AH43: =(L43*((Y43*W43)+(AB43*Z43)))*AG43/1000 -> 248.85587 | AI43: 0.005 | AJ43: =AH43*AI43 -> 1.2442794 | AO43: =_xlfn.XLOOKUP($D43&$L43&$AK$3,'BD Conv'!$A:$A,'BD Conv'!$H:$H,0)*_xlfn.XLOOKUP($D43,'BD Conv'!$C$17:$C$19,'BD Conv'!$F$17:$F$19,0)*(1+(HLOOKUP($B43&AO$6,Indexadores!$C$2:$AH$32,MATCH($AE43,Indexadores!$A$2:$A$32,0)))) -> 13.3 | AS43: 0.005 | AT43: =(AU43+AO43)*AS43 -> 0.3325 | AU43: =_xlfn.XLOOKUP($D43&$L43&$AK$3,'BD Conv'!$A:$A,'BD Conv'!$H:$H,0)*_xlfn.XLOOKUP($D43,'BD Conv'!$C$17:$C$19,'BD Conv'!$E$17:$E$19,0)*(1+(HLOOKUP($B43&AU$6,Indexadores!$C$2:$AH$32,MATCH($AE43,Indexadores!$A$2:$A$32,0)))) -> 53.2 | AV43: =SUM(AN43,AO43,AP43,(AQ43*AG43),AR43,AT43,AU43) -> 66.8325 | AW43: =_xlfn.XLOOKUP($A43&$AK$3,'BD Conv'!$A:$A,'BD Conv'!$I:$I,0) -> 0 | AZ43: =SUM(AH43,AJ43,AK43,AL43,AV43,AW43:AY43) -> 316.93265 | BI43: =SUM(BA43,BB43,BC43,(BD43*AG43),BE43,BF43,BH43) -> 0 | BN43: =_xlfn.XLOOKUP($A43&$BA$3,'BD Conv'!$A:$A,'BD Conv'!$K:$K,0) -> 0 | BQ43: =SUM(BI43,BJ43,BK43,BM43,BN43,BO43,BP43) -> 0 | BR43: =-BQ43*$BR$3 -> 0 | BT43: =AZ43+BQ43+BR43+BS43 -> 316.93265 | BU43: =BV43-BT43 -> 79.927668 | BV43: =BT43/(1-(12%+1.65%+7.6%) +12%*(1.65%+7.6%)) -> 396.86032 | BY43: =BT43/CP43-1 -> 0.37162171 | BZ43: =(BT43-CP43)/AG43 -> 16.511209 | CA43: =(BT43-CK43-CL43-AL43-AX43-AY43-BO43-BP43+CQ43)/AG43 -> 16.511209 | CB43: =(BT43-AH43)/AG43 -> 13.090136 | CD43: =CP43*(1+$CD$5) -> 254.1706 | CE43: =(CD43-CP43)/AG43 -> 4.4430151 | CF43: =(CD43-CK43-CL43-AL43-AX43-AY43-BO43-BP43+CQ43)/AG43 -> 4.4430151 | CG43: =(CD43-AH43)/AG43 -> 1.0219422 | CI43: =IF($X43="",0,HLOOKUP($H$3,Resina!$E$2:$AK$93,MATCH($D43&$X43&$CI$5,Resina!$A$2:$A$93,0))) -> 1157.6381 | CJ43: =IF($AA43="",0,HLOOKUP($H$3,Resina!$E$2:$AK$93,MATCH($D43&$AA43&$CJ$5,Resina!$A$2:$A$93,0))) -> 1610.0071 | CK43: =L43*((CI43*W43)+(CJ43*Z43))*AG43/1000 -> 228.77642 | CL43: =CK43*$CL$6 -> 2.2877642 | CM43: =IF(D43="Manaus FORA",-((CK43/0.88*0.12)*(1-9.25%))," ") | CO43: =AX43+AY43+BO43+BP43+AL43+AN43+BJ43+BK43+BM43 -> 0 | CP43: =SUM(CK43:CO43) -> 231.06418 | DE43: =_xlfn.CONCAT(D43,L43) -> Suape38 | DF43: =L43 -> 38 | DG43: =ROUND(SUMIF($1:$1,DG$5,43:43),2) -> 248.86 | DH43: =ROUND(SUMIF($1:$1,DH$5,43:43),2) -> 1.58 | DI43: =ROUND(SUMIF($1:$1,DI$5,43:43),2) -> 0 | DJ43: =ROUND(SUMIF($1:$1,DJ$5,43:43),2) -> 0 | DK43: =ROUND(SUMIF($1:$1,DK$5,43:43),2) -> 0 | DL43: =ROUND(SUMIF($1:$1,DL$5,43:43),2) -> 0 | DM43: =ROUND(SUMIF($1:$1,DM$5,43:43),2) -> 0 | DN43: =ROUND(SUMIF($1:$1,DN$5,43:43),2) -> 53.2 | ... ED43: =ROUND(SUMIF($1:$1,ED$5,43:43),2) -> 0 | EE43: =SUM(DG43:ED43) -> 316.94 | EF43: =ROUND(SUM(EE43-BT43),2) -> 0.01 | EG43: =IF(DN43<>0,DN43-EF43,0) -> 53.19 | EH43: =IF(EG43=0,DO43-EF43,DO43) -> 0 | EI43: =SUM(DG43:DM43)+SUM(DP43:ED43)+EG43+EH43 -> 316.93
A44: =_xlfn.CONCAT(D44,L44) -> Suape38 | B44: 4196 | C44: 4196 | D44: Suape | F44: AMBEV | G44: CONTRATO | H44: FOB | K44: PREFORMA | L44: 38 | M44: CR | V44: Virgem | W44: 0.6 | X44: ALPEK | Y44: =IF($X44="",0,HLOOKUP($H$3,Resina!$E$2:$AK$93,MATCH($D44&$X44&$Y$5,Resina!$A$2:$A$93,0))) -> 1259.2427 | Z44: 0.4 | AA44: VG | AB44: =IF($AA44="",0,HLOOKUP($H$3,Resina!$E$2:$AK$93,MATCH($D44&$AA44&$AB$5,Resina!$A$2:$A$93,0))) -> 1651.6512 | AC44: =$AC$7 -> 46091 | AD44: Mensal | AE44: =$AE$7 -> 45839 | AF44: MIL | AG44: =_xlfn.XLOOKUP($H$3,Resina!$2:$2,Resina!$3:$3,0) -> 5.2006167 | AH44: =(L44*((Y44*W44)+(AB44*Z44)))*AG44/1000 -> 279.87552 | AI44: 0.005 | AJ44: =AH44*AI44 -> 1.3993776 | AO44: =_xlfn.XLOOKUP($D44&$L44&$AK$3,'BD Conv'!$A:$A,'BD Conv'!$H:$H,0)*_xlfn.XLOOKUP($D44,'BD Conv'!$C$17:$C$19,'BD Conv'!$F$17:$F$19,0)*(1+(HLOOKUP($B44&AO$6,Indexadores!$C$2:$AH$32,MATCH($AE44,Indexadores!$A$2:$A$32,0)))) -> 13.3 | AS44: 0.005 | AT44: =(AU44+AO44)*AS44 -> 0.3325 | AU44: =_xlfn.XLOOKUP($D44&$L44&$AK$3,'BD Conv'!$A:$A,'BD Conv'!$H:$H,0)*_xlfn.XLOOKUP($D44,'BD Conv'!$C$17:$C$19,'BD Conv'!$E$17:$E$19,0)*(1+(HLOOKUP($B44&AU$6,Indexadores!$C$2:$AH$32,MATCH($AE44,Indexadores!$A$2:$A$32,0)))) -> 53.2 | AV44: =SUM(AN44,AO44,AP44,(AQ44*AG44),AR44,AT44,AU44) -> 66.8325 | AW44: =_xlfn.XLOOKUP($A44&$AK$3,'BD Conv'!$A:$A,'BD Conv'!$I:$I,0) -> 0 | AZ44: =SUM(AH44,AJ44,AK44,AL44,AV44,AW44:AY44) -> 348.10739 | BI44: =SUM(BA44,BB44,BC44,(BD44*AG44),BE44,BF44,BH44) -> 0 | BN44: =_xlfn.XLOOKUP($A44&$BA$3,'BD Conv'!$A:$A,'BD Conv'!$K:$K,0) -> 0 | BQ44: =SUM(BI44,BJ44,BK44,BM44,BN44,BO44,BP44) -> 0 | BR44: =-BQ44*$BR$3 -> 0 | BT44: =AZ44+BQ44+BR44+BS44 -> 348.10739 | BU44: =BV44-BT44 -> 87.789668 | BV44: =BT44/(1-(12%+1.65%+7.6%) +12%*(1.65%+7.6%)) -> 435.89706 | BY44: =BT44/CP44-1 -> 0.30288848 | BZ44: =(BT44-CP44)/AG44 -> 15.560871 | CA44: =(BT44-CK44-CL44-AL44-AX44-AY44-BO44-BP44+CQ44)/AG44 -> 15.560871 | CB44: =(BT44-AH44)/AG44 -> 13.119959 | CD44: =CP44*(1+$CD$5) -> 293.89939 | CE44: =(CD44-CP44)/AG44 -> 5.137492 | CF44: =(CD44-CK44-CL44-AL44-AX44-AY44-BO44-BP44+CQ44)/AG44 -> 5.137492 | CG44: =(CD44-AH44)/AG44 -> 2.6965798 | CI44: =IF($X44="",0,HLOOKUP($H$3,Resina!$E$2:$AK$93,MATCH($D44&$X44&$CI$5,Resina!$A$2:$A$93,0))) -> 1157.6381 | CJ44: =IF($AA44="",0,HLOOKUP($H$3,Resina!$E$2:$AK$93,MATCH($D44&$AA44&$CJ$5,Resina!$A$2:$A$93,0))) -> 1610.0071 | CK44: =L44*((CI44*W44)+(CJ44*Z44))*AG44/1000 -> 264.53591 | CL44: =CK44*$CL$6 -> 2.6453591 | CM44: =IF(D44="Manaus FORA",-((CK44/0.88*0.12)*(1-9.25%))," ") | CO44: =AX44+AY44+BO44+BP44+AL44+AN44+BJ44+BK44+BM44 -> 0 | CP44: =SUM(CK44:CO44) -> 267.18127 | DE44: =_xlfn.CONCAT(D44,L44) -> Suape38 | DF44: =L44 -> 38 | DG44: =ROUND(SUMIF($1:$1,DG$5,44:44),2) -> 279.88 | DH44: =ROUND(SUMIF($1:$1,DH$5,44:44),2) -> 1.73 | DI44: =ROUND(SUMIF($1:$1,DI$5,44:44),2) -> 0 | DJ44: =ROUND(SUMIF($1:$1,DJ$5,44:44),2) -> 0 | DK44: =ROUND(SUMIF($1:$1,DK$5,44:44),2) -> 0 | DL44: =ROUND(SUMIF($1:$1,DL$5,44:44),2) -> 0 | DM44: =ROUND(SUMIF($1:$1,DM$5,44:44),2) -> 0 | DN44: =ROUND(SUMIF($1:$1,DN$5,44:44),2) -> 53.2 | ... ED44: =ROUND(SUMIF($1:$1,ED$5,44:44),2) -> 0 | EE44: =SUM(DG44:ED44) -> 348.11 | EF44: =ROUND(SUM(EE44-BT44),2) -> 0 | EG44: =IF(DN44<>0,DN44-EF44,0) -> 53.2 | EH44: =IF(EG44=0,DO44-EF44,DO44) -> 0 | EI44: =SUM(DG44:DM44)+SUM(DP44:ED44)+EG44+EH44 -> 348.11
A45: =_xlfn.CONCAT(D45,L45) -> Suape38 | B45: 4196 | C45: 4196 | D45: Suape | F45: AMBEV | G45: CONTRATO | H45: FOB | K45: PREFORMA | L45: 38 | M45: CR | V45: Virgem | W45: 0.4 | X45: ALPEK | Y45: =IF($X45="",0,HLOOKUP($H$3,Resina!$E$2:$AK$93,MATCH($D45&$X45&$Y$5,Resina!$A$2:$A$93,0))) -> 1259.2427 | Z45: 0.6 | AA45: VG | AB45: =IF($AA45="",0,HLOOKUP($H$3,Resina!$E$2:$AK$93,MATCH($D45&$AA45&$AB$5,Resina!$A$2:$A$93,0))) -> 1651.6512 | AC45: =$AC$7 -> 46091 | AD45: Mensal | AE45: =$AE$7 -> 45839 | AF45: MIL | AG45: =_xlfn.XLOOKUP($H$3,Resina!$2:$2,Resina!$3:$3,0) -> 5.2006167 | AH45: =(L45*((Y45*W45)+(AB45*Z45)))*AG45/1000 -> 295.38534 | AI45: 0.005 | AJ45: =AH45*AI45 -> 1.4769267 | AO45: =_xlfn.XLOOKUP($D45&$L45&$AK$3,'BD Conv'!$A:$A,'BD Conv'!$H:$H,0)*_xlfn.XLOOKUP($D45,'BD Conv'!$C$17:$C$19,'BD Conv'!$F$17:$F$19,0)*(1+(HLOOKUP($B45&AO$6,Indexadores!$C$2:$AH$32,MATCH($AE45,Indexadores!$A$2:$A$32,0)))) -> 13.3 | AS45: 0.005 | AT45: =(AU45+AO45)*AS45 -> 0.3325 | AU45: =_xlfn.XLOOKUP($D45&$L45&$AK$3,'BD Conv'!$A:$A,'BD Conv'!$H:$H,0)*_xlfn.XLOOKUP($D45,'BD Conv'!$C$17:$C$19,'BD Conv'!$E$17:$E$19,0)*(1+(HLOOKUP($B45&AU$6,Indexadores!$C$2:$AH$32,MATCH($AE45,Indexadores!$A$2:$A$32,0)))) -> 53.2 | AV45: =SUM(AN45,AO45,AP45,(AQ45*AG45),AR45,AT45,AU45) -> 66.8325 | AW45: =_xlfn.XLOOKUP($A45&$AK$3,'BD Conv'!$A:$A,'BD Conv'!$I:$I,0) -> 0 | AZ45: =SUM(AH45,AJ45,AK45,AL45,AV45,AW45:AY45) -> 363.69476 | BI45: =SUM(BA45,BB45,BC45,(BD45*AG45),BE45,BF45,BH45) -> 0 | BN45: =_xlfn.XLOOKUP($A45&$BA$3,'BD Conv'!$A:$A,'BD Conv'!$K:$K,0) -> 0 | BQ45: =SUM(BI45,BJ45,BK45,BM45,BN45,BO45,BP45) -> 0 | BR45: =-BQ45*$BR$3 -> 0 | BT45: =AZ45+BQ45+BR45+BS45 -> 363.69476 | BU45: =BV45-BT45 -> 91.720668 | BV45: =BT45/(1-(12%+1.65%+7.6%) +12%*(1.65%+7.6%)) -> 455.41543 | BY45: =BT45/CP45-1 -> 0.27504911 | BZ45: =(BT45-CP45)/AG45 -> 15.085702 | CA45: =(BT45-CK45-CL45-AL45-AX45-AY45-BO45-BP45+CQ45)/AG45 -> 15.085702 | CB45: =(BT45-AH45)/AG45 -> 13.134871 | CD45: =CP45*(1+$CD$5) -> 313.76379 | CE45: =(CD45-CP45)/AG45 -> 5.4847305 | CF45: =(CD45-CK45-CL45-AL45-AX45-AY45-BO45-BP45+CQ45)/AG45 -> 5.4847305 | CG45: =(CD45-AH45)/AG45 -> 3.5338985 | CI45: =IF($X45="",0,HLOOKUP($H$3,Resina!$E$2:$AK$93,MATCH($D45&$X45&$CI$5,Resina!$A$2:$A$93,0))) -> 1157.6381 | CJ45: =IF($AA45="",0,HLOOKUP($H$3,Resina!$E$2:$AK$93,MATCH($D45&$AA45&$CJ$5,Resina!$A$2:$A$93,0))) -> 1610.0071 | CK45: =L45*((CI45*W45)+(CJ45*Z45))*AG45/1000 -> 282.41565 | CL45: =CK45*$CL$6 -> 2.8241565 | CM45: =IF(D45="Manaus FORA",-((CK45/0.88*0.12)*(1-9.25%))," ") | CO45: =AX45+AY45+BO45+BP45+AL45+AN45+BJ45+BK45+BM45 -> 0 | CP45: =SUM(CK45:CO45) -> 285.23981 | DE45: =_xlfn.CONCAT(D45,L45) -> Suape38 | DF45: =L45 -> 38 | DG45: =ROUND(SUMIF($1:$1,DG$5,45:45),2) -> 295.39 | DH45: =ROUND(SUMIF($1:$1,DH$5,45:45),2) -> 1.81 | DI45: =ROUND(SUMIF($1:$1,DI$5,45:45),2) -> 0 | DJ45: =ROUND(SUMIF($1:$1,DJ$5,45:45),2) -> 0 | DK45: =ROUND(SUMIF($1:$1,DK$5,45:45),2) -> 0 | DL45: =ROUND(SUMIF($1:$1,DL$5,45:45),2) -> 0 | DM45: =ROUND(SUMIF($1:$1,DM$5,45:45),2) -> 0 | DN45: =ROUND(SUMIF($1:$1,DN$5,45:45),2) -> 53.2 | ... ED45: =ROUND(SUMIF($1:$1,ED$5,45:45),2) -> 0 | EE45: =SUM(DG45:ED45) -> 363.7 | EF45: =ROUND(SUM(EE45-BT45),2) -> 0.01 | EG45: =IF(DN45<>0,DN45-EF45,0) -> 53.19 | EH45: =IF(EG45=0,DO45-EF45,DO45) -> 0 | EI45: =SUM(DG45:DM45)+SUM(DP45:ED45)+EG45+EH45 -> 363.69
A46: =_xlfn.CONCAT(D46,L46) -> Suape38 | B46: 4196 | C46: 4196 | D46: Suape | F46: AMBEV | G46: CONTRATO | H46: FOB | K46: PREFORMA | L46: 38 | M46: CR | V46: Virgem | W46: 0 | Y46: =IF($X46="",0,HLOOKUP($H$3,Resina!$E$2:$AK$93,MATCH($D46&$X46&$Y$5,Resina!$A$2:$A$93,0))) -> 0 | Z46: 1 | AA46: VG | AB46: =IF($AA46="",0,HLOOKUP($H$3,Resina!$E$2:$AK$93,MATCH($D46&$AA46&$AB$5,Resina!$A$2:$A$93,0))) -> 1651.6512 | AC46: =$AC$7 -> 46091 | AD46: Mensal | AE46: =$AE$7 -> 45839 | AF46: MIL | AG46: =_xlfn.XLOOKUP($H$3,Resina!$2:$2,Resina!$3:$3,0) -> 5.2006167 | AH46: =(L46*((Y46*W46)+(AB46*Z46)))*AG46/1000 -> 326.40498 | AI46: 0.005 | AJ46: =AH46*AI46 -> 1.6320249 | AO46: =_xlfn.XLOOKUP($D46&$L46&$AK$3,'BD Conv'!$A:$A,'BD Conv'!$H:$H,0)*_xlfn.XLOOKUP($D46,'BD Conv'!$C$17:$C$19,'BD Conv'!$F$17:$F$19,0)*(1+(HLOOKUP($B46&AO$6,Indexadores!$C$2:$AH$32,MATCH($AE46,Indexadores!$A$2:$A$32,0)))) -> 13.3 | AS46: 0.005 | AT46: =(AU46+AO46)*AS46 -> 0.3325 | AU46: =_xlfn.XLOOKUP($D46&$L46&$AK$3,'BD Conv'!$A:$A,'BD Conv'!$H:$H,0)*_xlfn.XLOOKUP($D46,'BD Conv'!$C$17:$C$19,'BD Conv'!$E$17:$E$19,0)*(1+(HLOOKUP($B46&AU$6,Indexadores!$C$2:$AH$32,MATCH($AE46,Indexadores!$A$2:$A$32,0)))) -> 53.2 | AV46: =SUM(AN46,AO46,AP46,(AQ46*AG46),AR46,AT46,AU46) -> 66.8325 | AW46: =_xlfn.XLOOKUP($A46&$AK$3,'BD Conv'!$A:$A,'BD Conv'!$I:$I,0) -> 0 | AZ46: =SUM(AH46,AJ46,AK46,AL46,AV46,AW46:AY46) -> 394.86951 | BI46: =SUM(BA46,BB46,BC46,(BD46*AG46),BE46,BF46,BH46) -> 0 | BN46: =_xlfn.XLOOKUP($A46&$BA$3,'BD Conv'!$A:$A,'BD Conv'!$K:$K,0) -> 0 | BQ46: =SUM(BI46,BJ46,BK46,BM46,BN46,BO46,BP46) -> 0 | BR46: =-BQ46*$BR$3 -> 0 | BT46: =AZ46+BQ46+BR46+BS46 -> 394.86951 | BU46: =BV46-BT46 -> 99.582668 | BV46: =BT46/(1-(12%+1.65%+7.6%) +12%*(1.65%+7.6%)) -> 494.45217 | BY46: =BT46/CP46-1 -> 0.22875693 | BZ46: =(BT46-CP46)/AG46 -> 14.135365 | CA46: =(BT46-CK46-CL46-AL46-AX46-AY46-BO46-BP46+CQ46)/AG46 -> 14.135365 | CB46: =(BT46-AH46)/AG46 -> 13.164694 | CD46: =CP46*(1+$CD$5) -> 353.49258 | CE46: =(CD46-CP46)/AG46 -> 6.1792074 | CF46: =(CD46-CK46-CL46-AL46-AX46-AY46-BO46-BP46+CQ46)/AG46 -> 6.1792074 | CG46: =(CD46-AH46)/AG46 -> 5.2085361 | CI46: =IF($X46="",0,HLOOKUP($H$3,Resina!$E$2:$AK$93,MATCH($D46&$X46&$CI$5,Resina!$A$2:$A$93,0))) -> 0 | CJ46: =IF($AA46="",0,HLOOKUP($H$3,Resina!$E$2:$AK$93,MATCH($D46&$AA46&$CJ$5,Resina!$A$2:$A$93,0))) -> 1610.0071 | CK46: =L46*((CI46*W46)+(CJ46*Z46))*AG46/1000 -> 318.17514 | CL46: =CK46*$CL$6 -> 3.1817514 | CM46: =IF(D46="Manaus FORA",-((CK46/0.88*0.12)*(1-9.25%))," ") | CO46: =AX46+AY46+BO46+BP46+AL46+AN46+BJ46+BK46+BM46 -> 0 | CP46: =SUM(CK46:CO46) -> 321.35689 | DE46: =_xlfn.CONCAT(D46,L46) -> Suape38 | DF46: =L46 -> 38 | DG46: =ROUND(SUMIF($1:$1,DG$5,46:46),2) -> 326.4 | DH46: =ROUND(SUMIF($1:$1,DH$5,46:46),2) -> 1.96 | DI46: =ROUND(SUMIF($1:$1,DI$5,46:46),2) -> 0 | DJ46: =ROUND(SUMIF($1:$1,DJ$5,46:46),2) -> 0 | DK46: =ROUND(SUMIF($1:$1,DK$5,46:46),2) -> 0 | DL46: =ROUND(SUMIF($1:$1,DL$5,46:46),2) -> 0 | DM46: =ROUND(SUMIF($1:$1,DM$5,46:46),2) -> 0 | DN46: =ROUND(SUMIF($1:$1,DN$5,46:46),2) -> 53.2 | ... ED46: =ROUND(SUMIF($1:$1,ED$5,46:46),2) -> 0 | EE46: =SUM(DG46:ED46) -> 394.86 | EF46: =ROUND(SUM(EE46-BT46),2) -> -0.01 | EG46: =IF(DN46<>0,DN46-EF46,0) -> 53.21 | EH46: =IF(EG46=0,DO46-EF46,DO46) -> 0 | EI46: =SUM(DG46:DM46)+SUM(DP46:ED46)+EG46+EH46 -> 394.87
A47: =_xlfn.CONCAT(D47,L47) -> Suape38 | B47: 4196 | C47: 4196 | D47: Suape | F47: AMBEV | G47: CONTRATO | H47: FOB | K47: PREFORMA | L47: 38 | M47: VD | V47: Virgem | W47: 1 | X47: ALPEK | Y47: =IF($X47="",0,HLOOKUP($H$3,Resina!$E$2:$AK$93,MATCH($D47&$X47&$Y$5,Resina!$A$2:$A$93,0))) -> 1259.2427 | Z47: 0 | AA47: VG | AB47: =IF($AA47="",0,HLOOKUP($H$3,Resina!$E$2:$AK$93,MATCH($D47&$AA47&$AB$5,Resina!$A$2:$A$93,0))) -> 1651.6512 | AC47: =$AC$7 -> 46091 | AD47: Mensal | AE47: =$AE$7 -> 45839 | AF47: MIL | AG47: =_xlfn.XLOOKUP($H$3,Resina!$2:$2,Resina!$3:$3,0) -> 5.2006167 | AH47: =(L47*((Y47*W47)+(AB47*Z47)))*AG47/1000 -> 248.85587 | AI47: 0.005 | AJ47: =AH47*AI47 -> 1.2442794 | AO47: =_xlfn.XLOOKUP($D47&$L47&$AK$3,'BD Conv'!$A:$A,'BD Conv'!$H:$H,0)*_xlfn.XLOOKUP($D47,'BD Conv'!$C$17:$C$19,'BD Conv'!$F$17:$F$19,0)*(1+(HLOOKUP($B47&AO$6,Indexadores!$C$2:$AH$32,MATCH($AE47,Indexadores!$A$2:$A$32,0)))) -> 13.3 | AS47: 0.005 | AT47: =(AU47+AO47)*AS47 -> 0.3325 | AU47: =_xlfn.XLOOKUP($D47&$L47&$AK$3,'BD Conv'!$A:$A,'BD Conv'!$H:$H,0)*_xlfn.XLOOKUP($D47,'BD Conv'!$C$17:$C$19,'BD Conv'!$E$17:$E$19,0)*(1+(HLOOKUP($B47&AU$6,Indexadores!$C$2:$AH$32,MATCH($AE47,Indexadores!$A$2:$A$32,0)))) -> 53.2 | AV47: =SUM(AN47,AO47,AP47,(AQ47*AG47),AR47,AT47,AU47) -> 66.8325 | AW47: =_xlfn.XLOOKUP($A47&$AK$3,'BD Conv'!$A:$A,'BD Conv'!$I:$I,0) -> 0 | AZ47: =SUM(AH47,AJ47,AK47,AL47,AV47,AW47:AY47) -> 316.93265 | BI47: =SUM(BA47,BB47,BC47,(BD47*AG47),BE47,BF47,BH47) -> 0 | BN47: =_xlfn.XLOOKUP($A47&$BA$3,'BD Conv'!$A:$A,'BD Conv'!$K:$K,0) -> 0 | BQ47: =SUM(BI47,BJ47,BK47,BM47,BN47,BO47,BP47) -> 0 | BR47: =-BQ47*$BR$3 -> 0 | BT47: =AZ47+BQ47+BR47+BS47 -> 316.93265 | BU47: =BV47-BT47 -> 79.927668 | BV47: =BT47/(1-(12%+1.65%+7.6%) +12%*(1.65%+7.6%)) -> 396.86032 | BY47: =BT47/CP47-1 -> 0.37162171 | BZ47: =(BT47-CP47)/AG47 -> 16.511209 | CA47: =(BT47-CK47-CL47-AL47-AX47-AY47-BO47-BP47+CQ47)/AG47 -> 16.511209 | CB47: =(BT47-AH47)/AG47 -> 13.090136 | CD47: =CP47*(1+$CD$5) -> 254.1706 | CE47: =(CD47-CP47)/AG47 -> 4.4430151 | CF47: =(CD47-CK47-CL47-AL47-AX47-AY47-BO47-BP47+CQ47)/AG47 -> 4.4430151 | CG47: =(CD47-AH47)/AG47 -> 1.0219422 | CI47: =IF($X47="",0,HLOOKUP($H$3,Resina!$E$2:$AK$93,MATCH($D47&$X47&$CI$5,Resina!$A$2:$A$93,0))) -> 1157.6381 | CJ47: =IF($AA47="",0,HLOOKUP($H$3,Resina!$E$2:$AK$93,MATCH($D47&$AA47&$CJ$5,Resina!$A$2:$A$93,0))) -> 1610.0071 | CK47: =L47*((CI47*W47)+(CJ47*Z47))*AG47/1000 -> 228.77642 | CL47: =CK47*$CL$6 -> 2.2877642 | CM47: =IF(D47="Manaus FORA",-((CK47/0.88*0.12)*(1-9.25%))," ") | CO47: =AX47+AY47+BO47+BP47+AL47+AN47+BJ47+BK47+BM47 -> 0 | CP47: =SUM(CK47:CO47) -> 231.06418 | DE47: =_xlfn.CONCAT(D47,L47) -> Suape38 | DF47: =L47 -> 38 | DG47: =ROUND(SUMIF($1:$1,DG$5,47:47),2) -> 248.86 | DH47: =ROUND(SUMIF($1:$1,DH$5,47:47),2) -> 1.58 | DI47: =ROUND(SUMIF($1:$1,DI$5,47:47),2) -> 0 | DJ47: =ROUND(SUMIF($1:$1,DJ$5,47:47),2) -> 0 | DK47: =ROUND(SUMIF($1:$1,DK$5,47:47),2) -> 0 | DL47: =ROUND(SUMIF($1:$1,DL$5,47:47),2) -> 0 | DM47: =ROUND(SUMIF($1:$1,DM$5,47:47),2) -> 0 | DN47: =ROUND(SUMIF($1:$1,DN$5,47:47),2) -> 53.2 | ... ED47: =ROUND(SUMIF($1:$1,ED$5,47:47),2) -> 0 | EE47: =SUM(DG47:ED47) -> 316.94 | EF47: =ROUND(SUM(EE47-BT47),2) -> 0.01 | EG47: =IF(DN47<>0,DN47-EF47,0) -> 53.19 | EH47: =IF(EG47=0,DO47-EF47,DO47) -> 0 | EI47: =SUM(DG47:DM47)+SUM(DP47:ED47)+EG47+EH47 -> 316.93
A48: =_xlfn.CONCAT(D48,L48) -> Suape38 | B48: 4196 | C48: 4196 | D48: Suape | F48: AMBEV | G48: CONTRATO | H48: FOB | K48: PREFORMA | L48: 38 | M48: VD | V48: Virgem | W48: 0.6 | X48: ALPEK | Y48: =IF($X48="",0,HLOOKUP($H$3,Resina!$E$2:$AK$93,MATCH($D48&$X48&$Y$5,Resina!$A$2:$A$93,0))) -> 1259.2427 | Z48: 0.4 | AA48: VG | AB48: =IF($AA48="",0,HLOOKUP($H$3,Resina!$E$2:$AK$93,MATCH($D48&$AA48&$AB$5,Resina!$A$2:$A$93,0))) -> 1651.6512 | AC48: =$AC$7 -> 46091 | AD48: Mensal | AE48: =$AE$7 -> 45839 | AF48: MIL | AG48: =_xlfn.XLOOKUP($H$3,Resina!$2:$2,Resina!$3:$3,0) -> 5.2006167 | AH48: =(L48*((Y48*W48)+(AB48*Z48)))*AG48/1000 -> 279.87552 | AI48: 0.005 | AJ48: =AH48*AI48 -> 1.3993776 | AO48: =_xlfn.XLOOKUP($D48&$L48&$AK$3,'BD Conv'!$A:$A,'BD Conv'!$H:$H,0)*_xlfn.XLOOKUP($D48,'BD Conv'!$C$17:$C$19,'BD Conv'!$F$17:$F$19,0)*(1+(HLOOKUP($B48&AO$6,Indexadores!$C$2:$AH$32,MATCH($AE48,Indexadores!$A$2:$A$32,0)))) -> 13.3 | AS48: 0.005 | AT48: =(AU48+AO48)*AS48 -> 0.3325 | AU48: =_xlfn.XLOOKUP($D48&$L48&$AK$3,'BD Conv'!$A:$A,'BD Conv'!$H:$H,0)*_xlfn.XLOOKUP($D48,'BD Conv'!$C$17:$C$19,'BD Conv'!$E$17:$E$19,0)*(1+(HLOOKUP($B48&AU$6,Indexadores!$C$2:$AH$32,MATCH($AE48,Indexadores!$A$2:$A$32,0)))) -> 53.2 | AV48: =SUM(AN48,AO48,AP48,(AQ48*AG48),AR48,AT48,AU48) -> 66.8325 | AW48: =_xlfn.XLOOKUP($A48&$AK$3,'BD Conv'!$A:$A,'BD Conv'!$I:$I,0) -> 0 | AZ48: =SUM(AH48,AJ48,AK48,AL48,AV48,AW48:AY48) -> 348.10739 | BI48: =SUM(BA48,BB48,BC48,(BD48*AG48),BE48,BF48,BH48) -> 0 | BN48: =_xlfn.XLOOKUP($A48&$BA$3,'BD Conv'!$A:$A,'BD Conv'!$K:$K,0) -> 0 | BQ48: =SUM(BI48,BJ48,BK48,BM48,BN48,BO48,BP48) -> 0 | BR48: =-BQ48*$BR$3 -> 0 | BT48: =AZ48+BQ48+BR48+BS48 -> 348.10739 | BU48: =BV48-BT48 -> 87.789668 | BV48: =BT48/(1-(12%+1.65%+7.6%) +12%*(1.65%+7.6%)) -> 435.89706 | BY48: =BT48/CP48-1 -> 0.30288848 | BZ48: =(BT48-CP48)/AG48 -> 15.560871 | CA48: =(BT48-CK48-CL48-AL48-AX48-AY48-BO48-BP48+CQ48)/AG48 -> 15.560871 | CB48: =(BT48-AH48)/AG48 -> 13.119959 | CD48: =CP48*(1+$CD$5) -> 293.89939 | CE48: =(CD48-CP48)/AG48 -> 5.137492 | CF48: =(CD48-CK48-CL48-AL48-AX48-AY48-BO48-BP48+CQ48)/AG48 -> 5.137492 | CG48: =(CD48-AH48)/AG48 -> 2.6965798 | CI48: =IF($X48="",0,HLOOKUP($H$3,Resina!$E$2:$AK$93,MATCH($D48&$X48&$CI$5,Resina!$A$2:$A$93,0))) -> 1157.6381 | CJ48: =IF($AA48="",0,HLOOKUP($H$3,Resina!$E$2:$AK$93,MATCH($D48&$AA48&$CJ$5,Resina!$A$2:$A$93,0))) -> 1610.0071 | CK48: =L48*((CI48*W48)+(CJ48*Z48))*AG48/1000 -> 264.53591 | CL48: =CK48*$CL$6 -> 2.6453591 | CM48: =IF(D48="Manaus FORA",-((CK48/0.88*0.12)*(1-9.25%))," ") | CO48: =AX48+AY48+BO48+BP48+AL48+AN48+BJ48+BK48+BM48 -> 0 | CP48: =SUM(CK48:CO48) -> 267.18127 | DE48: =_xlfn.CONCAT(D48,L48) -> Suape38 | DF48: =L48 -> 38 | DG48: =ROUND(SUMIF($1:$1,DG$5,48:48),2) -> 279.88 | DH48: =ROUND(SUMIF($1:$1,DH$5,48:48),2) -> 1.73 | DI48: =ROUND(SUMIF($1:$1,DI$5,48:48),2) -> 0 | DJ48: =ROUND(SUMIF($1:$1,DJ$5,48:48),2) -> 0 | DK48: =ROUND(SUMIF($1:$1,DK$5,48:48),2) -> 0 | DL48: =ROUND(SUMIF($1:$1,DL$5,48:48),2) -> 0 | DM48: =ROUND(SUMIF($1:$1,DM$5,48:48),2) -> 0 | DN48: =ROUND(SUMIF($1:$1,DN$5,48:48),2) -> 53.2 | ... ED48: =ROUND(SUMIF($1:$1,ED$5,48:48),2) -> 0 | EE48: =SUM(DG48:ED48) -> 348.11 | EF48: =ROUND(SUM(EE48-BT48),2) -> 0 | EG48: =IF(DN48<>0,DN48-EF48,0) -> 53.2 | EH48: =IF(EG48=0,DO48-EF48,DO48) -> 0 | EI48: =SUM(DG48:DM48)+SUM(DP48:ED48)+EG48+EH48 -> 348.11
A49: =_xlfn.CONCAT(D49,L49) -> Suape38 | B49: 4196 | C49: 4196 | D49: Suape | F49: AMBEV | G49: CONTRATO | H49: FOB | K49: PREFORMA | L49: 38 | M49: VD | V49: Virgem | W49: 0.4 | X49: ALPEK | Y49: =IF($X49="",0,HLOOKUP($H$3,Resina!$E$2:$AK$93,MATCH($D49&$X49&$Y$5,Resina!$A$2:$A$93,0))) -> 1259.2427 | Z49: 0.6 | AA49: VG | AB49: =IF($AA49="",0,HLOOKUP($H$3,Resina!$E$2:$AK$93,MATCH($D49&$AA49&$AB$5,Resina!$A$2:$A$93,0))) -> 1651.6512 | AC49: =$AC$7 -> 46091 | AD49: Mensal | AE49: =$AE$7 -> 45839 | AF49: MIL | AG49: =_xlfn.XLOOKUP($H$3,Resina!$2:$2,Resina!$3:$3,0) -> 5.2006167 | AH49: =(L49*((Y49*W49)+(AB49*Z49)))*AG49/1000 -> 295.38534 | AI49: 0.005 | AJ49: =AH49*AI49 -> 1.4769267 | AO49: =_xlfn.XLOOKUP($D49&$L49&$AK$3,'BD Conv'!$A:$A,'BD Conv'!$H:$H,0)*_xlfn.XLOOKUP($D49,'BD Conv'!$C$17:$C$19,'BD Conv'!$F$17:$F$19,0)*(1+(HLOOKUP($B49&AO$6,Indexadores!$C$2:$AH$32,MATCH($AE49,Indexadores!$A$2:$A$32,0)))) -> 13.3 | AS49: 0.005 | AT49: =(AU49+AO49)*AS49 -> 0.3325 | AU49: =_xlfn.XLOOKUP($D49&$L49&$AK$3,'BD Conv'!$A:$A,'BD Conv'!$H:$H,0)*_xlfn.XLOOKUP($D49,'BD Conv'!$C$17:$C$19,'BD Conv'!$E$17:$E$19,0)*(1+(HLOOKUP($B49&AU$6,Indexadores!$C$2:$AH$32,MATCH($AE49,Indexadores!$A$2:$A$32,0)))) -> 53.2 | AV49: =SUM(AN49,AO49,AP49,(AQ49*AG49),AR49,AT49,AU49) -> 66.8325 | AW49: =_xlfn.XLOOKUP($A49&$AK$3,'BD Conv'!$A:$A,'BD Conv'!$I:$I,0) -> 0 | AZ49: =SUM(AH49,AJ49,AK49,AL49,AV49,AW49:AY49) -> 363.69476 | BI49: =SUM(BA49,BB49,BC49,(BD49*AG49),BE49,BF49,BH49) -> 0 | BN49: =_xlfn.XLOOKUP($A49&$BA$3,'BD Conv'!$A:$A,'BD Conv'!$K:$K,0) -> 0 | BQ49: =SUM(BI49,BJ49,BK49,BM49,BN49,BO49,BP49) -> 0 | BR49: =-BQ49*$BR$3 -> 0 | BT49: =AZ49+BQ49+BR49+BS49 -> 363.69476 | BU49: =BV49-BT49 -> 91.720668 | BV49: =BT49/(1-(12%+1.65%+7.6%) +12%*(1.65%+7.6%)) -> 455.41543 | BY49: =BT49/CP49-1 -> 0.27504911 | BZ49: =(BT49-CP49)/AG49 -> 15.085702 | CA49: =(BT49-CK49-CL49-AL49-AX49-AY49-BO49-BP49+CQ49)/AG49 -> 15.085702 | CB49: =(BT49-AH49)/AG49 -> 13.134871 | CD49: =CP49*(1+$CD$5) -> 313.76379 | CE49: =(CD49-CP49)/AG49 -> 5.4847305 | CF49: =(CD49-CK49-CL49-AL49-AX49-AY49-BO49-BP49+CQ49)/AG49 -> 5.4847305 | CG49: =(CD49-AH49)/AG49 -> 3.5338985 | CI49: =IF($X49="",0,HLOOKUP($H$3,Resina!$E$2:$AK$93,MATCH($D49&$X49&$CI$5,Resina!$A$2:$A$93,0))) -> 1157.6381 | CJ49: =IF($AA49="",0,HLOOKUP($H$3,Resina!$E$2:$AK$93,MATCH($D49&$AA49&$CJ$5,Resina!$A$2:$A$93,0))) -> 1610.0071 | CK49: =L49*((CI49*W49)+(CJ49*Z49))*AG49/1000 -> 282.41565 | CL49: =CK49*$CL$6 -> 2.8241565 | CM49: =IF(D49="Manaus FORA",-((CK49/0.88*0.12)*(1-9.25%))," ") | CO49: =AX49+AY49+BO49+BP49+AL49+AN49+BJ49+BK49+BM49 -> 0 | CP49: =SUM(CK49:CO49) -> 285.23981 | DE49: =_xlfn.CONCAT(D49,L49) -> Suape38 | DF49: =L49 -> 38 | DG49: =ROUND(SUMIF($1:$1,DG$5,49:49),2) -> 295.39 | DH49: =ROUND(SUMIF($1:$1,DH$5,49:49),2) -> 1.81 | DI49: =ROUND(SUMIF($1:$1,DI$5,49:49),2) -> 0 | DJ49: =ROUND(SUMIF($1:$1,DJ$5,49:49),2) -> 0 | DK49: =ROUND(SUMIF($1:$1,DK$5,49:49),2) -> 0 | DL49: =ROUND(SUMIF($1:$1,DL$5,49:49),2) -> 0 | DM49: =ROUND(SUMIF($1:$1,DM$5,49:49),2) -> 0 | DN49: =ROUND(SUMIF($1:$1,DN$5,49:49),2) -> 53.2 | ... ED49: =ROUND(SUMIF($1:$1,ED$5,49:49),2) -> 0 | EE49: =SUM(DG49:ED49) -> 363.7 | EF49: =ROUND(SUM(EE49-BT49),2) -> 0.01 | EG49: =IF(DN49<>0,DN49-EF49,0) -> 53.19 | EH49: =IF(EG49=0,DO49-EF49,DO49) -> 0 | EI49: =SUM(DG49:DM49)+SUM(DP49:ED49)+EG49+EH49 -> 363.69
A50: =_xlfn.CONCAT(D50,L50) -> Suape38 | B50: 4196 | C50: 4196 | D50: Suape | F50: AMBEV | G50: CONTRATO | H50: FOB | K50: PREFORMA | L50: 38 | M50: VD | V50: Virgem | W50: 0 | Y50: =IF($X50="",0,HLOOKUP($H$3,Resina!$E$2:$AK$93,MATCH($D50&$X50&$Y$5,Resina!$A$2:$A$93,0))) -> 0 | Z50: 1 | AA50: VG | AB50: =IF($AA50="",0,HLOOKUP($H$3,Resina!$E$2:$AK$93,MATCH($D50&$AA50&$AB$5,Resina!$A$2:$A$93,0))) -> 1651.6512 | AC50: =$AC$7 -> 46091 | AD50: Mensal | AE50: =$AE$7 -> 45839 | AF50: MIL | AG50: =_xlfn.XLOOKUP($H$3,Resina!$2:$2,Resina!$3:$3,0) -> 5.2006167 | AH50: =(L50*((Y50*W50)+(AB50*Z50)))*AG50/1000 -> 326.40498 | AI50: 0.005 | AJ50: =AH50*AI50 -> 1.6320249 | AO50: =_xlfn.XLOOKUP($D50&$L50&$AK$3,'BD Conv'!$A:$A,'BD Conv'!$H:$H,0)*_xlfn.XLOOKUP($D50,'BD Conv'!$C$17:$C$19,'BD Conv'!$F$17:$F$19,0)*(1+(HLOOKUP($B50&AO$6,Indexadores!$C$2:$AH$32,MATCH($AE50,Indexadores!$A$2:$A$32,0)))) -> 13.3 | AS50: 0.005 | AT50: =(AU50+AO50)*AS50 -> 0.3325 | AU50: =_xlfn.XLOOKUP($D50&$L50&$AK$3,'BD Conv'!$A:$A,'BD Conv'!$H:$H,0)*_xlfn.XLOOKUP($D50,'BD Conv'!$C$17:$C$19,'BD Conv'!$E$17:$E$19,0)*(1+(HLOOKUP($B50&AU$6,Indexadores!$C$2:$AH$32,MATCH($AE50,Indexadores!$A$2:$A$32,0)))) -> 53.2 | AV50: =SUM(AN50,AO50,AP50,(AQ50*AG50),AR50,AT50,AU50) -> 66.8325 | AW50: =_xlfn.XLOOKUP($A50&$AK$3,'BD Conv'!$A:$A,'BD Conv'!$I:$I,0) -> 0 | AZ50: =SUM(AH50,AJ50,AK50,AL50,AV50,AW50:AY50) -> 394.86951 | BI50: =SUM(BA50,BB50,BC50,(BD50*AG50),BE50,BF50,BH50) -> 0 | BN50: =_xlfn.XLOOKUP($A50&$BA$3,'BD Conv'!$A:$A,'BD Conv'!$K:$K,0) -> 0 | BQ50: =SUM(BI50,BJ50,BK50,BM50,BN50,BO50,BP50) -> 0 | BR50: =-BQ50*$BR$3 -> 0 | BT50: =AZ50+BQ50+BR50+BS50 -> 394.86951 | BU50: =BV50-BT50 -> 99.582668 | BV50: =BT50/(1-(12%+1.65%+7.6%) +12%*(1.65%+7.6%)) -> 494.45217 | BY50: =BT50/CP50-1 -> 0.22875693 | BZ50: =(BT50-CP50)/AG50 -> 14.135365 | CA50: =(BT50-CK50-CL50-AL50-AX50-AY50-BO50-BP50+CQ50)/AG50 -> 14.135365 | CB50: =(BT50-AH50)/AG50 -> 13.164694 | CD50: =CP50*(1+$CD$5) -> 353.49258 | CE50: =(CD50-CP50)/AG50 -> 6.1792074 | CF50: =(CD50-CK50-CL50-AL50-AX50-AY50-BO50-BP50+CQ50)/AG50 -> 6.1792074 | CG50: =(CD50-AH50)/AG50 -> 5.2085361 | CI50: =IF($X50="",0,HLOOKUP($H$3,Resina!$E$2:$AK$93,MATCH($D50&$X50&$CI$5,Resina!$A$2:$A$93,0))) -> 0 | CJ50: =IF($AA50="",0,HLOOKUP($H$3,Resina!$E$2:$AK$93,MATCH($D50&$AA50&$CJ$5,Resina!$A$2:$A$93,0))) -> 1610.0071 | CK50: =L50*((CI50*W50)+(CJ50*Z50))*AG50/1000 -> 318.17514 | CL50: =CK50*$CL$6 -> 3.1817514 | CM50: =IF(D50="Manaus FORA",-((CK50/0.88*0.12)*(1-9.25%))," ") | CO50: =AX50+AY50+BO50+BP50+AL50+AN50+BJ50+BK50+BM50 -> 0 | CP50: =SUM(CK50:CO50) -> 321.35689 | DE50: =_xlfn.CONCAT(D50,L50) -> Suape38 | DF50: =L50 -> 38 | DG50: =ROUND(SUMIF($1:$1,DG$5,50:50),2) -> 326.4 | DH50: =ROUND(SUMIF($1:$1,DH$5,50:50),2) -> 1.96 | DI50: =ROUND(SUMIF($1:$1,DI$5,50:50),2) -> 0 | DJ50: =ROUND(SUMIF($1:$1,DJ$5,50:50),2) -> 0 | DK50: =ROUND(SUMIF($1:$1,DK$5,50:50),2) -> 0 | DL50: =ROUND(SUMIF($1:$1,DL$5,50:50),2) -> 0 | DM50: =ROUND(SUMIF($1:$1,DM$5,50:50),2) -> 0 | DN50: =ROUND(SUMIF($1:$1,DN$5,50:50),2) -> 53.2 | ... ED50: =ROUND(SUMIF($1:$1,ED$5,50:50),2) -> 0 | EE50: =SUM(DG50:ED50) -> 394.86 | EF50: =ROUND(SUM(EE50-BT50),2) -> -0.01 | EG50: =IF(DN50<>0,DN50-EF50,0) -> 53.21 | EH50: =IF(EG50=0,DO50-EF50,DO50) -> 0 | EI50: =SUM(DG50:DM50)+SUM(DP50:ED50)+EG50+EH50 -> 394.87
A51: =_xlfn.CONCAT(D51,L51) -> Suape39.7 | B51: 4196 | C51: 4196 | D51: Suape | F51: AMBEV | G51: CONTRATO | H51: FOB | K51: PREFORMA | L51: 39.7 | M51: CR | V51: Virgem | W51: 1 | X51: ALPEK | Y51: =IF($X51="",0,HLOOKUP($H$3,Resina!$E$2:$AK$93,MATCH($D51&$X51&$Y$5,Resina!$A$2:$A$93,0))) -> 1259.2427 | Z51: 0 | AA51: VG | AB51: =IF($AA51="",0,HLOOKUP($H$3,Resina!$E$2:$AK$93,MATCH($D51&$AA51&$AB$5,Resina!$A$2:$A$93,0))) -> 1651.6512 | AC51: =$AC$7 -> 46091 | AD51: Mensal | AE51: =$AE$7 -> 45839 | AF51: MIL | AG51: =_xlfn.XLOOKUP($H$3,Resina!$2:$2,Resina!$3:$3,0) -> 5.2006167 | AH51: =(L51*((Y51*W51)+(AB51*Z51)))*AG51/1000 -> 259.9889 | AI51: 0.005 | AJ51: =AH51*AI51 -> 1.2999445 | AO51: =_xlfn.XLOOKUP($D51&$L51&$AK$3,'BD Conv'!$A:$A,'BD Conv'!$H:$H,0)*_xlfn.XLOOKUP($D51,'BD Conv'!$C$17:$C$19,'BD Conv'!$F$17:$F$19,0)*(1+(HLOOKUP($B51&AO$6,Indexadores!$C$2:$AH$32,MATCH($AE51,Indexadores!$A$2:$A$32,0)))) -> 0 | AS51: 0.005 | AT51: =(AU51+AO51)*AS51 -> 0 | AU51: =_xlfn.XLOOKUP($D51&$L51&$AK$3,'BD Conv'!$A:$A,'BD Conv'!$H:$H,0)*_xlfn.XLOOKUP($D51,'BD Conv'!$C$17:$C$19,'BD Conv'!$E$17:$E$19,0)*(1+(HLOOKUP($B51&AU$6,Indexadores!$C$2:$AH$32,MATCH($AE51,Indexadores!$A$2:$A$32,0)))) -> 0 | AV51: =SUM(AN51,AO51,AP51,(AQ51*AG51),AR51,AT51,AU51) -> 0 | AW51: =_xlfn.XLOOKUP($A51&$AK$3,'BD Conv'!$A:$A,'BD Conv'!$I:$I,0) -> 0 | AZ51: =SUM(AH51,AJ51,AK51,AL51,AV51,AW51:AY51) -> 261.28884 | BI51: =SUM(BA51,BB51,BC51,(BD51*AG51),BE51,BF51,BH51) -> 0 | BN51: =_xlfn.XLOOKUP($A51&$BA$3,'BD Conv'!$A:$A,'BD Conv'!$K:$K,0) -> 0 | BQ51: =SUM(BI51,BJ51,BK51,BM51,BN51,BO51,BP51) -> 0 | BR51: =-BQ51*$BR$3 -> 0 | BT51: =AZ51+BQ51+BR51+BS51 -> 261.28884 | BU51: =BV51-BT51 -> 65.894782 | BV51: =BT51/(1-(12%+1.65%+7.6%) +12%*(1.65%+7.6%)) -> 327.18362 | BY51: =BT51/CP51-1 -> 0.082383897 | BZ51: =(BT51-CP51)/AG51 -> 3.8240805 | CA51: =(BT51-CK51-CL51-AL51-AX51-AY51-BO51-BP51+CQ51)/AG51 -> 3.8240805 | CB51: =(BT51-AH51)/AG51 -> 0.24995968 | CD51: =CP51*(1+$CD$5) -> 265.54139 | CE51: =(CD51-CP51)/AG51 -> 4.6417815 | CF51: =(CD51-CK51-CL51-AL51-AX51-AY51-BO51-BP51+CQ51)/AG51 -> 4.6417815 | CG51: =(CD51-AH51)/AG51 -> 1.0676607 | CI51: =IF($X51="",0,HLOOKUP($H$3,Resina!$E$2:$AK$93,MATCH($D51&$X51&$CI$5,Resina!$A$2:$A$93,0))) -> 1157.6381 | CJ51: =IF($AA51="",0,HLOOKUP($H$3,Resina!$E$2:$AK$93,MATCH($D51&$AA51&$CJ$5,Resina!$A$2:$A$93,0))) -> 1610.0071 | CK51: =L51*((CI51*W51)+(CJ51*Z51))*AG51/1000 -> 239.01115 | CL51: =CK51*$CL$6 -> 2.3901115 | CM51: =IF(D51="Manaus FORA",-((CK51/0.88*0.12)*(1-9.25%))," ") | CO51: =AX51+AY51+BO51+BP51+AL51+AN51+BJ51+BK51+BM51 -> 0 | CP51: =SUM(CK51:CO51) -> 241.40126 | DE51: =_xlfn.CONCAT(D51,L51) -> Suape39.7 | DF51: =L51 -> 39.7 | DG51: =ROUND(SUMIF($1:$1,DG$5,51:51),2) -> 259.99 | DH51: =ROUND(SUMIF($1:$1,DH$5,51:51),2) -> 1.3 | DI51: =ROUND(SUMIF($1:$1,DI$5,51:51),2) -> 0 | DJ51: =ROUND(SUMIF($1:$1,DJ$5,51:51),2) -> 0 | DK51: =ROUND(SUMIF($1:$1,DK$5,51:51),2) -> 0 | DL51: =ROUND(SUMIF($1:$1,DL$5,51:51),2) -> 0 | DM51: =ROUND(SUMIF($1:$1,DM$5,51:51),2) -> 0 | DN51: =ROUND(SUMIF($1:$1,DN$5,51:51),2) -> 0 | ... ED51: =ROUND(SUMIF($1:$1,ED$5,51:51),2) -> 0 | EE51: =SUM(DG51:ED51) -> 261.29 | EF51: =ROUND(SUM(EE51-BT51),2) -> 0 | EG51: =IF(DN51<>0,DN51-EF51,0) -> 0 | EH51: =IF(EG51=0,DO51-EF51,DO51) -> 0 | EI51: =SUM(DG51:DM51)+SUM(DP51:ED51)+EG51+EH51 -> 261.29
A52: =_xlfn.CONCAT(D52,L52) -> Suape39.7 | B52: 4196 | C52: 4196 | D52: Suape | F52: AMBEV | G52: CONTRATO | H52: FOB | K52: PREFORMA | L52: 39.7 | M52: CR | V52: Virgem | W52: 0.6 | X52: ALPEK | Y52: =IF($X52="",0,HLOOKUP($H$3,Resina!$E$2:$AK$93,MATCH($D52&$X52&$Y$5,Resina!$A$2:$A$93,0))) -> 1259.2427 | Z52: 0.4 | AA52: VG | AB52: =IF($AA52="",0,HLOOKUP($H$3,Resina!$E$2:$AK$93,MATCH($D52&$AA52&$AB$5,Resina!$A$2:$A$93,0))) -> 1651.6512 | AC52: =$AC$7 -> 46091 | AD52: Mensal | AE52: =$AE$7 -> 45839 | AF52: MIL | AG52: =_xlfn.XLOOKUP($H$3,Resina!$2:$2,Resina!$3:$3,0) -> 5.2006167 | AH52: =(L52*((Y52*W52)+(AB52*Z52)))*AG52/1000 -> 292.39626 | AI52: 0.005 | AJ52: =AH52*AI52 -> 1.4619813 | AO52: =_xlfn.XLOOKUP($D52&$L52&$AK$3,'BD Conv'!$A:$A,'BD Conv'!$H:$H,0)*_xlfn.XLOOKUP($D52,'BD Conv'!$C$17:$C$19,'BD Conv'!$F$17:$F$19,0)*(1+(HLOOKUP($B52&AO$6,Indexadores!$C$2:$AH$32,MATCH($AE52,Indexadores!$A$2:$A$32,0)))) -> 0 | AS52: 0.005 | AT52: =(AU52+AO52)*AS52 -> 0 | AU52: =_xlfn.XLOOKUP($D52&$L52&$AK$3,'BD Conv'!$A:$A,'BD Conv'!$H:$H,0)*_xlfn.XLOOKUP($D52,'BD Conv'!$C$17:$C$19,'BD Conv'!$E$17:$E$19,0)*(1+(HLOOKUP($B52&AU$6,Indexadores!$C$2:$AH$32,MATCH($AE52,Indexadores!$A$2:$A$32,0)))) -> 0 | AV52: =SUM(AN52,AO52,AP52,(AQ52*AG52),AR52,AT52,AU52) -> 0 | AW52: =_xlfn.XLOOKUP($A52&$AK$3,'BD Conv'!$A:$A,'BD Conv'!$I:$I,0) -> 0 | AZ52: =SUM(AH52,AJ52,AK52,AL52,AV52,AW52:AY52) -> 293.85824 | BI52: =SUM(BA52,BB52,BC52,(BD52*AG52),BE52,BF52,BH52) -> 0 | BN52: =_xlfn.XLOOKUP($A52&$BA$3,'BD Conv'!$A:$A,'BD Conv'!$K:$K,0) -> 0 | BQ52: =SUM(BI52,BJ52,BK52,BM52,BN52,BO52,BP52) -> 0 | BR52: =-BQ52*$BR$3 -> 0 | BT52: =AZ52+BQ52+BR52+BS52 -> 293.85824 | BU52: =BV52-BT52 -> 74.108503 | BV52: =BT52/(1-(12%+1.65%+7.6%) +12%*(1.65%+7.6%)) -> 367.96675 | BY52: =BT52/CP52-1 -> 0.052749306 | BZ52: =(BT52-CP52)/AG52 -> 2.8312279 | CA52: =(BT52-CK52-CL52-AL52-AX52-AY52-BO52-BP52+CQ52)/AG52 -> 2.8312279 | CB52: =(BT52-AH52)/AG52 -> 0.28111691 | CD52: =CP52*(1+$CD$5) -> 307.04752 | CE52: =(CD52-CP52)/AG52 -> 5.3673272 | CF52: =(CD52-CK52-CL52-AL52-AX52-AY52-BO52-BP52+CQ52)/AG52 -> 5.3673272 | CG52: =(CD52-AH52)/AG52 -> 2.8172162 | CI52: =IF($X52="",0,HLOOKUP($H$3,Resina!$E$2:$AK$93,MATCH($D52&$X52&$CI$5,Resina!$A$2:$A$93,0))) -> 1157.6381 | CJ52: =IF($AA52="",0,HLOOKUP($H$3,Resina!$E$2:$AK$93,MATCH($D52&$AA52&$CJ$5,Resina!$A$2:$A$93,0))) -> 1610.0071 | CK52: =L52*((CI52*W52)+(CJ52*Z52))*AG52/1000 -> 276.37041 | CL52: =CK52*$CL$6 -> 2.7637041 | CM52: =IF(D52="Manaus FORA",-((CK52/0.88*0.12)*(1-9.25%))," ") | CO52: =AX52+AY52+BO52+BP52+AL52+AN52+BJ52+BK52+BM52 -> 0 | CP52: =SUM(CK52:CO52) -> 279.13411 | DE52: =_xlfn.CONCAT(D52,L52) -> Suape39.7 | DF52: =L52 -> 39.7 | DG52: =ROUND(SUMIF($1:$1,DG$5,52:52),2) -> 292.4 | DH52: =ROUND(SUMIF($1:$1,DH$5,52:52),2) -> 1.46 | DI52: =ROUND(SUMIF($1:$1,DI$5,52:52),2) -> 0 | DJ52: =ROUND(SUMIF($1:$1,DJ$5,52:52),2) -> 0 | DK52: =ROUND(SUMIF($1:$1,DK$5,52:52),2) -> 0 | DL52: =ROUND(SUMIF($1:$1,DL$5,52:52),2) -> 0 | DM52: =ROUND(SUMIF($1:$1,DM$5,52:52),2) -> 0 | DN52: =ROUND(SUMIF($1:$1,DN$5,52:52),2) -> 0 | ... ED52: =ROUND(SUMIF($1:$1,ED$5,52:52),2) -> 0 | EE52: =SUM(DG52:ED52) -> 293.86 | EF52: =ROUND(SUM(EE52-BT52),2) -> 0 | EG52: =IF(DN52<>0,DN52-EF52,0) -> 0 | EH52: =IF(EG52=0,DO52-EF52,DO52) -> 0 | EI52: =SUM(DG52:DM52)+SUM(DP52:ED52)+EG52+EH52 -> 293.86
A53: =_xlfn.CONCAT(D53,L53) -> Suape39.7 | B53: 4196 | C53: 4196 | D53: Suape | F53: AMBEV | G53: CONTRATO | H53: FOB | K53: PREFORMA | L53: 39.7 | M53: CR | V53: Virgem | W53: 0.4 | X53: ALPEK | Y53: =IF($X53="",0,HLOOKUP($H$3,Resina!$E$2:$AK$93,MATCH($D53&$X53&$Y$5,Resina!$A$2:$A$93,0))) -> 1259.2427 | Z53: 0.6 | AA53: VG | AB53: =IF($AA53="",0,HLOOKUP($H$3,Resina!$E$2:$AK$93,MATCH($D53&$AA53&$AB$5,Resina!$A$2:$A$93,0))) -> 1651.6512 | AC53: =$AC$7 -> 46091 | AD53: Mensal | AE53: =$AE$7 -> 45839 | AF53: MIL | AG53: =_xlfn.XLOOKUP($H$3,Resina!$2:$2,Resina!$3:$3,0) -> 5.2006167 | AH53: =(L53*((Y53*W53)+(AB53*Z53)))*AG53/1000 -> 308.59994 | AI53: 0.005 | AJ53: =AH53*AI53 -> 1.5429997 | AO53: =_xlfn.XLOOKUP($D53&$L53&$AK$3,'BD Conv'!$A:$A,'BD Conv'!$H:$H,0)*_xlfn.XLOOKUP($D53,'BD Conv'!$C$17:$C$19,'BD Conv'!$F$17:$F$19,0)*(1+(HLOOKUP($B53&AO$6,Indexadores!$C$2:$AH$32,MATCH($AE53,Indexadores!$A$2:$A$32,0)))) -> 0 | AS53: 0.005 | AT53: =(AU53+AO53)*AS53 -> 0 | AU53: =_xlfn.XLOOKUP($D53&$L53&$AK$3,'BD Conv'!$A:$A,'BD Conv'!$H:$H,0)*_xlfn.XLOOKUP($D53,'BD Conv'!$C$17:$C$19,'BD Conv'!$E$17:$E$19,0)*(1+(HLOOKUP($B53&AU$6,Indexadores!$C$2:$AH$32,MATCH($AE53,Indexadores!$A$2:$A$32,0)))) -> 0 | AV53: =SUM(AN53,AO53,AP53,(AQ53*AG53),AR53,AT53,AU53) -> 0 | AW53: =_xlfn.XLOOKUP($A53&$AK$3,'BD Conv'!$A:$A,'BD Conv'!$I:$I,0) -> 0 | AZ53: =SUM(AH53,AJ53,AK53,AL53,AV53,AW53:AY53) -> 310.14294 | BI53: =SUM(BA53,BB53,BC53,(BD53*AG53),BE53,BF53,BH53) -> 0 | BN53: =_xlfn.XLOOKUP($A53&$BA$3,'BD Conv'!$A:$A,'BD Conv'!$K:$K,0) -> 0 | BQ53: =SUM(BI53,BJ53,BK53,BM53,BN53,BO53,BP53) -> 0 | BR53: =-BQ53*$BR$3 -> 0 | BT53: =AZ53+BQ53+BR53+BS53 -> 310.14294 | BU53: =BV53-BT53 -> 78.215363 | BV53: =BT53/(1-(12%+1.65%+7.6%) +12%*(1.65%+7.6%)) -> 388.35831 | BY53: =BT53/CP53-1 -> 0.040746262 | BZ53: =(BT53-CP53)/AG53 -> 2.3348015 | CA53: =(BT53-CK53-CL53-AL53-AX53-AY53-BO53-BP53+CQ53)/AG53 -> 2.3348015 | CB53: =(BT53-AH53)/AG53 -> 0.29669553 | CD53: =CP53*(1+$CD$5) -> 327.80059 | CE53: =(CD53-CP53)/AG53 -> 5.7301 | CF53: =(CD53-CK53-CL53-AL53-AX53-AY53-BO53-BP53+CQ53)/AG53 -> 5.7301 | CG53: =(CD53-AH53)/AG53 -> 3.691994 | CI53: =IF($X53="",0,HLOOKUP($H$3,Resina!$E$2:$AK$93,MATCH($D53&$X53&$CI$5,Resina!$A$2:$A$93,0))) -> 1157.6381 | CJ53: =IF($AA53="",0,HLOOKUP($H$3,Resina!$E$2:$AK$93,MATCH($D53&$AA53&$CJ$5,Resina!$A$2:$A$93,0))) -> 1610.0071 | CK53: =L53*((CI53*W53)+(CJ53*Z53))*AG53/1000 -> 295.05004 | CL53: =CK53*$CL$6 -> 2.9505004 | CM53: =IF(D53="Manaus FORA",-((CK53/0.88*0.12)*(1-9.25%))," ") | CO53: =AX53+AY53+BO53+BP53+AL53+AN53+BJ53+BK53+BM53 -> 0 | CP53: =SUM(CK53:CO53) -> 298.00054 | DE53: =_xlfn.CONCAT(D53,L53) -> Suape39.7 | DF53: =L53 -> 39.7 | DG53: =ROUND(SUMIF($1:$1,DG$5,53:53),2) -> 308.6 | DH53: =ROUND(SUMIF($1:$1,DH$5,53:53),2) -> 1.54 | DI53: =ROUND(SUMIF($1:$1,DI$5,53:53),2) -> 0 | DJ53: =ROUND(SUMIF($1:$1,DJ$5,53:53),2) -> 0 | DK53: =ROUND(SUMIF($1:$1,DK$5,53:53),2) -> 0 | DL53: =ROUND(SUMIF($1:$1,DL$5,53:53),2) -> 0 | DM53: =ROUND(SUMIF($1:$1,DM$5,53:53),2) -> 0 | DN53: =ROUND(SUMIF($1:$1,DN$5,53:53),2) -> 0 | ... ED53: =ROUND(SUMIF($1:$1,ED$5,53:53),2) -> 0 | EE53: =SUM(DG53:ED53) -> 310.14 | EF53: =ROUND(SUM(EE53-BT53),2) -> 0 | EG53: =IF(DN53<>0,DN53-EF53,0) -> 0 | EH53: =IF(EG53=0,DO53-EF53,DO53) -> 0 | EI53: =SUM(DG53:DM53)+SUM(DP53:ED53)+EG53+EH53 -> 310.14
A54: =_xlfn.CONCAT(D54,L54) -> Suape39.7 | B54: 4196 | C54: 4196 | D54: Suape | F54: AMBEV | G54: CONTRATO | H54: FOB | K54: PREFORMA | L54: 39.7 | M54: CR | V54: Virgem | W54: 0 | Y54: =IF($X54="",0,HLOOKUP($H$3,Resina!$E$2:$AK$93,MATCH($D54&$X54&$Y$5,Resina!$A$2:$A$93,0))) -> 0 | Z54: 1 | AA54: VG | AB54: =IF($AA54="",0,HLOOKUP($H$3,Resina!$E$2:$AK$93,MATCH($D54&$AA54&$AB$5,Resina!$A$2:$A$93,0))) -> 1651.6512 | AC54: =$AC$7 -> 46091 | AD54: Mensal | AE54: =$AE$7 -> 45839 | AF54: MIL | AG54: =_xlfn.XLOOKUP($H$3,Resina!$2:$2,Resina!$3:$3,0) -> 5.2006167 | AH54: =(L54*((Y54*W54)+(AB54*Z54)))*AG54/1000 -> 341.00731 | AI54: 0.005 | AJ54: =AH54*AI54 -> 1.7050365 | AO54: =_xlfn.XLOOKUP($D54&$L54&$AK$3,'BD Conv'!$A:$A,'BD Conv'!$H:$H,0)*_xlfn.XLOOKUP($D54,'BD Conv'!$C$17:$C$19,'BD Conv'!$F$17:$F$19,0)*(1+(HLOOKUP($B54&AO$6,Indexadores!$C$2:$AH$32,MATCH($AE54,Indexadores!$A$2:$A$32,0)))) -> 0 | AS54: 0.005 | AT54: =(AU54+AO54)*AS54 -> 0 | AU54: =_xlfn.XLOOKUP($D54&$L54&$AK$3,'BD Conv'!$A:$A,'BD Conv'!$H:$H,0)*_xlfn.XLOOKUP($D54,'BD Conv'!$C$17:$C$19,'BD Conv'!$E$17:$E$19,0)*(1+(HLOOKUP($B54&AU$6,Indexadores!$C$2:$AH$32,MATCH($AE54,Indexadores!$A$2:$A$32,0)))) -> 0 | AV54: =SUM(AN54,AO54,AP54,(AQ54*AG54),AR54,AT54,AU54) -> 0 | AW54: =_xlfn.XLOOKUP($A54&$AK$3,'BD Conv'!$A:$A,'BD Conv'!$I:$I,0) -> 0 | AZ54: =SUM(AH54,AJ54,AK54,AL54,AV54,AW54:AY54) -> 342.71235 | BI54: =SUM(BA54,BB54,BC54,(BD54*AG54),BE54,BF54,BH54) -> 0 | BN54: =_xlfn.XLOOKUP($A54&$BA$3,'BD Conv'!$A:$A,'BD Conv'!$K:$K,0) -> 0 | BQ54: =SUM(BI54,BJ54,BK54,BM54,BN54,BO54,BP54) -> 0 | BR54: =-BQ54*$BR$3 -> 0 | BT54: =AZ54+BQ54+BR54+BS54 -> 342.71235 | BU54: =BV54-BT54 -> 86.429084 | BV54: =BT54/(1-(12%+1.65%+7.6%) +12%*(1.65%+7.6%)) -> 429.14143 | BY54: =BT54/CP54-1 -> 0.020787214 | BZ54: =(BT54-CP54)/AG54 -> 1.3419489 | CA54: =(BT54-CK54-CL54-AL54-AX54-AY54-BO54-BP54+CQ54)/AG54 -> 1.3419489 | CB54: =(BT54-AH54)/AG54 -> 0.32785276 | CD54: =CP54*(1+$CD$5) -> 369.30672 | CE54: =(CD54-CP54)/AG54 -> 6.4556457 | CF54: =(CD54-CK54-CL54-AL54-AX54-AY54-BO54-BP54+CQ54)/AG54 -> 6.4556457 | CG54: =(CD54-AH54)/AG54 -> 5.4415495 | CI54: =IF($X54="",0,HLOOKUP($H$3,Resina!$E$2:$AK$93,MATCH($D54&$X54&$CI$5,Resina!$A$2:$A$93,0))) -> 0 | CJ54: =IF($AA54="",0,HLOOKUP($H$3,Resina!$E$2:$AK$93,MATCH($D54&$AA54&$CJ$5,Resina!$A$2:$A$93,0))) -> 1610.0071 | CK54: =L54*((CI54*W54)+(CJ54*Z54))*AG54/1000 -> 332.40929 | CL54: =CK54*$CL$6 -> 3.3240929 | CM54: =IF(D54="Manaus FORA",-((CK54/0.88*0.12)*(1-9.25%))," ") | CO54: =AX54+AY54+BO54+BP54+AL54+AN54+BJ54+BK54+BM54 -> 0 | CP54: =SUM(CK54:CO54) -> 335.73338 | DE54: =_xlfn.CONCAT(D54,L54) -> Suape39.7 | DF54: =L54 -> 39.7 | DG54: =ROUND(SUMIF($1:$1,DG$5,54:54),2) -> 341.01 | DH54: =ROUND(SUMIF($1:$1,DH$5,54:54),2) -> 1.71 | DI54: =ROUND(SUMIF($1:$1,DI$5,54:54),2) -> 0 | DJ54: =ROUND(SUMIF($1:$1,DJ$5,54:54),2) -> 0 | DK54: =ROUND(SUMIF($1:$1,DK$5,54:54),2) -> 0 | DL54: =ROUND(SUMIF($1:$1,DL$5,54:54),2) -> 0 | DM54: =ROUND(SUMIF($1:$1,DM$5,54:54),2) -> 0 | DN54: =ROUND(SUMIF($1:$1,DN$5,54:54),2) -> 0 | ... ED54: =ROUND(SUMIF($1:$1,ED$5,54:54),2) -> 0 | EE54: =SUM(DG54:ED54) -> 342.72 | EF54: =ROUND(SUM(EE54-BT54),2) -> 0.01 | EG54: =IF(DN54<>0,DN54-EF54,0) -> 0 | EH54: =IF(EG54=0,DO54-EF54,DO54) -> -0.01 | EI54: =SUM(DG54:DM54)+SUM(DP54:ED54)+EG54+EH54 -> 342.71
A55: =_xlfn.CONCAT(D55,L55) -> Suape39.7 | B55: 4196 | C55: 4196 | D55: Suape | F55: AMBEV | G55: CONTRATO | H55: FOB | K55: PREFORMA | L55: 39.7 | M55: VD | V55: Virgem | W55: 1 | X55: ALPEK | Y55: =IF($X55="",0,HLOOKUP($H$3,Resina!$E$2:$AK$93,MATCH($D55&$X55&$Y$5,Resina!$A$2:$A$93,0))) -> 1259.2427 | Z55: 0 | AA55: VG | AB55: =IF($AA55="",0,HLOOKUP($H$3,Resina!$E$2:$AK$93,MATCH($D55&$AA55&$AB$5,Resina!$A$2:$A$93,0))) -> 1651.6512 | AC55: =$AC$7 -> 46091 | AD55: Mensal | AE55: =$AE$7 -> 45839 | AF55: MIL | AG55: =_xlfn.XLOOKUP($H$3,Resina!$2:$2,Resina!$3:$3,0) -> 5.2006167 | AH55: =(L55*((Y55*W55)+(AB55*Z55)))*AG55/1000 -> 259.9889 | AI55: 0.005 | AJ55: =AH55*AI55 -> 1.2999445 | AO55: =_xlfn.XLOOKUP($D55&$L55&$AK$3,'BD Conv'!$A:$A,'BD Conv'!$H:$H,0)*_xlfn.XLOOKUP($D55,'BD Conv'!$C$17:$C$19,'BD Conv'!$F$17:$F$19,0)*(1+(HLOOKUP($B55&AO$6,Indexadores!$C$2:$AH$32,MATCH($AE55,Indexadores!$A$2:$A$32,0)))) -> 0 | AS55: 0.005 | AT55: =(AU55+AO55)*AS55 -> 0 | AU55: =_xlfn.XLOOKUP($D55&$L55&$AK$3,'BD Conv'!$A:$A,'BD Conv'!$H:$H,0)*_xlfn.XLOOKUP($D55,'BD Conv'!$C$17:$C$19,'BD Conv'!$E$17:$E$19,0)*(1+(HLOOKUP($B55&AU$6,Indexadores!$C$2:$AH$32,MATCH($AE55,Indexadores!$A$2:$A$32,0)))) -> 0 | AV55: =SUM(AN55,AO55,AP55,(AQ55*AG55),AR55,AT55,AU55) -> 0 | AW55: =_xlfn.XLOOKUP($A55&$AK$3,'BD Conv'!$A:$A,'BD Conv'!$I:$I,0) -> 0 | AZ55: =SUM(AH55,AJ55,AK55,AL55,AV55,AW55:AY55) -> 261.28884 | BI55: =SUM(BA55,BB55,BC55,(BD55*AG55),BE55,BF55,BH55) -> 0 | BN55: =_xlfn.XLOOKUP($A55&$BA$3,'BD Conv'!$A:$A,'BD Conv'!$K:$K,0) -> 0 | BQ55: =SUM(BI55,BJ55,BK55,BM55,BN55,BO55,BP55) -> 0 | BR55: =-BQ55*$BR$3 -> 0 | BT55: =AZ55+BQ55+BR55+BS55 -> 261.28884 | BU55: =BV55-BT55 -> 65.894782 | BV55: =BT55/(1-(12%+1.65%+7.6%) +12%*(1.65%+7.6%)) -> 327.18362 | BY55: =BT55/CP55-1 -> 0.082383897 | BZ55: =(BT55-CP55)/AG55 -> 3.8240805 | CA55: =(BT55-CK55-CL55-AL55-AX55-AY55-BO55-BP55+CQ55)/AG55 -> 3.8240805 | CB55: =(BT55-AH55)/AG55 -> 0.24995968 | CD55: =CP55*(1+$CD$5) -> 265.54139 | CE55: =(CD55-CP55)/AG55 -> 4.6417815 | CF55: =(CD55-CK55-CL55-AL55-AX55-AY55-BO55-BP55+CQ55)/AG55 -> 4.6417815 | CG55: =(CD55-AH55)/AG55 -> 1.0676607 | CI55: =IF($X55="",0,HLOOKUP($H$3,Resina!$E$2:$AK$93,MATCH($D55&$X55&$CI$5,Resina!$A$2:$A$93,0))) -> 1157.6381 | CJ55: =IF($AA55="",0,HLOOKUP($H$3,Resina!$E$2:$AK$93,MATCH($D55&$AA55&$CJ$5,Resina!$A$2:$A$93,0))) -> 1610.0071 | CK55: =L55*((CI55*W55)+(CJ55*Z55))*AG55/1000 -> 239.01115 | CL55: =CK55*$CL$6 -> 2.3901115 | CM55: =IF(D55="Manaus FORA",-((CK55/0.88*0.12)*(1-9.25%))," ") | CO55: =AX55+AY55+BO55+BP55+AL55+AN55+BJ55+BK55+BM55 -> 0 | CP55: =SUM(CK55:CO55) -> 241.40126 | DE55: =_xlfn.CONCAT(D55,L55) -> Suape39.7 | DF55: =L55 -> 39.7 | DG55: =ROUND(SUMIF($1:$1,DG$5,55:55),2) -> 259.99 | DH55: =ROUND(SUMIF($1:$1,DH$5,55:55),2) -> 1.3 | DI55: =ROUND(SUMIF($1:$1,DI$5,55:55),2) -> 0 | DJ55: =ROUND(SUMIF($1:$1,DJ$5,55:55),2) -> 0 | DK55: =ROUND(SUMIF($1:$1,DK$5,55:55),2) -> 0 | DL55: =ROUND(SUMIF($1:$1,DL$5,55:55),2) -> 0 | DM55: =ROUND(SUMIF($1:$1,DM$5,55:55),2) -> 0 | DN55: =ROUND(SUMIF($1:$1,DN$5,55:55),2) -> 0 | ... ED55: =ROUND(SUMIF($1:$1,ED$5,55:55),2) -> 0 | EE55: =SUM(DG55:ED55) -> 261.29 | EF55: =ROUND(SUM(EE55-BT55),2) -> 0 | EG55: =IF(DN55<>0,DN55-EF55,0) -> 0 | EH55: =IF(EG55=0,DO55-EF55,DO55) -> 0 | EI55: =SUM(DG55:DM55)+SUM(DP55:ED55)+EG55+EH55 -> 261.29
A56: =_xlfn.CONCAT(D56,L56) -> Suape39.7 | B56: 4196 | C56: 4196 | D56: Suape | F56: AMBEV | G56: CONTRATO | H56: FOB | K56: PREFORMA | L56: 39.7 | M56: VD | V56: Virgem | W56: 0.6 | X56: ALPEK | Y56: =IF($X56="",0,HLOOKUP($H$3,Resina!$E$2:$AK$93,MATCH($D56&$X56&$Y$5,Resina!$A$2:$A$93,0))) -> 1259.2427 | Z56: 0.4 | AA56: VG | AB56: =IF($AA56="",0,HLOOKUP($H$3,Resina!$E$2:$AK$93,MATCH($D56&$AA56&$AB$5,Resina!$A$2:$A$93,0))) -> 1651.6512 | AC56: =$AC$7 -> 46091 | AD56: Mensal | AE56: =$AE$7 -> 45839 | AF56: MIL | AG56: =_xlfn.XLOOKUP($H$3,Resina!$2:$2,Resina!$3:$3,0) -> 5.2006167 | AH56: =(L56*((Y56*W56)+(AB56*Z56)))*AG56/1000 -> 292.39626 | AI56: 0.005 | AJ56: =AH56*AI56 -> 1.4619813 | AO56: =_xlfn.XLOOKUP($D56&$L56&$AK$3,'BD Conv'!$A:$A,'BD Conv'!$H:$H,0)*_xlfn.XLOOKUP($D56,'BD Conv'!$C$17:$C$19,'BD Conv'!$F$17:$F$19,0)*(1+(HLOOKUP($B56&AO$6,Indexadores!$C$2:$AH$32,MATCH($AE56,Indexadores!$A$2:$A$32,0)))) -> 0 | AS56: 0.005 | AT56: =(AU56+AO56)*AS56 -> 0 | AU56: =_xlfn.XLOOKUP($D56&$L56&$AK$3,'BD Conv'!$A:$A,'BD Conv'!$H:$H,0)*_xlfn.XLOOKUP($D56,'BD Conv'!$C$17:$C$19,'BD Conv'!$E$17:$E$19,0)*(1+(HLOOKUP($B56&AU$6,Indexadores!$C$2:$AH$32,MATCH($AE56,Indexadores!$A$2:$A$32,0)))) -> 0 | AV56: =SUM(AN56,AO56,AP56,(AQ56*AG56),AR56,AT56,AU56) -> 0 | AW56: =_xlfn.XLOOKUP($A56&$AK$3,'BD Conv'!$A:$A,'BD Conv'!$I:$I,0) -> 0 | AZ56: =SUM(AH56,AJ56,AK56,AL56,AV56,AW56:AY56) -> 293.85824 | BI56: =SUM(BA56,BB56,BC56,(BD56*AG56),BE56,BF56,BH56) -> 0 | BN56: =_xlfn.XLOOKUP($A56&$BA$3,'BD Conv'!$A:$A,'BD Conv'!$K:$K,0) -> 0 | BQ56: =SUM(BI56,BJ56,BK56,BM56,BN56,BO56,BP56) -> 0 | BR56: =-BQ56*$BR$3 -> 0 | BT56: =AZ56+BQ56+BR56+BS56 -> 293.85824 | BU56: =BV56-BT56 -> 74.108503 | BV56: =BT56/(1-(12%+1.65%+7.6%) +12%*(1.65%+7.6%)) -> 367.96675 | BY56: =BT56/CP56-1 -> 0.052749306 | BZ56: =(BT56-CP56)/AG56 -> 2.8312279 | CA56: =(BT56-CK56-CL56-AL56-AX56-AY56-BO56-BP56+CQ56)/AG56 -> 2.8312279 | CB56: =(BT56-AH56)/AG56 -> 0.28111691 | CD56: =CP56*(1+$CD$5) -> 307.04752 | CE56: =(CD56-CP56)/AG56 -> 5.3673272 | CF56: =(CD56-CK56-CL56-AL56-AX56-AY56-BO56-BP56+CQ56)/AG56 -> 5.3673272 | CG56: =(CD56-AH56)/AG56 -> 2.8172162 | CI56: =IF($X56="",0,HLOOKUP($H$3,Resina!$E$2:$AK$93,MATCH($D56&$X56&$CI$5,Resina!$A$2:$A$93,0))) -> 1157.6381 | CJ56: =IF($AA56="",0,HLOOKUP($H$3,Resina!$E$2:$AK$93,MATCH($D56&$AA56&$CJ$5,Resina!$A$2:$A$93,0))) -> 1610.0071 | CK56: =L56*((CI56*W56)+(CJ56*Z56))*AG56/1000 -> 276.37041 | CL56: =CK56*$CL$6 -> 2.7637041 | CM56: =IF(D56="Manaus FORA",-((CK56/0.88*0.12)*(1-9.25%))," ") | CO56: =AX56+AY56+BO56+BP56+AL56+AN56+BJ56+BK56+BM56 -> 0 | CP56: =SUM(CK56:CO56) -> 279.13411 | DE56: =_xlfn.CONCAT(D56,L56) -> Suape39.7 | DF56: =L56 -> 39.7 | DG56: =ROUND(SUMIF($1:$1,DG$5,56:56),2) -> 292.4 | DH56: =ROUND(SUMIF($1:$1,DH$5,56:56),2) -> 1.46 | DI56: =ROUND(SUMIF($1:$1,DI$5,56:56),2) -> 0 | DJ56: =ROUND(SUMIF($1:$1,DJ$5,56:56),2) -> 0 | DK56: =ROUND(SUMIF($1:$1,DK$5,56:56),2) -> 0 | DL56: =ROUND(SUMIF($1:$1,DL$5,56:56),2) -> 0 | DM56: =ROUND(SUMIF($1:$1,DM$5,56:56),2) -> 0 | DN56: =ROUND(SUMIF($1:$1,DN$5,56:56),2) -> 0 | ... ED56: =ROUND(SUMIF($1:$1,ED$5,56:56),2) -> 0 | EE56: =SUM(DG56:ED56) -> 293.86 | EF56: =ROUND(SUM(EE56-BT56),2) -> 0 | EG56: =IF(DN56<>0,DN56-EF56,0) -> 0 | EH56: =IF(EG56=0,DO56-EF56,DO56) -> 0 | EI56: =SUM(DG56:DM56)+SUM(DP56:ED56)+EG56+EH56 -> 293.86
A57: =_xlfn.CONCAT(D57,L57) -> Suape39.7 | B57: 4196 | C57: 4196 | D57: Suape | F57: AMBEV | G57: CONTRATO | H57: FOB | K57: PREFORMA | L57: 39.7 | M57: VD | V57: Virgem | W57: 0.4 | X57: ALPEK | Y57: =IF($X57="",0,HLOOKUP($H$3,Resina!$E$2:$AK$93,MATCH($D57&$X57&$Y$5,Resina!$A$2:$A$93,0))) -> 1259.2427 | Z57: 0.6 | AA57: VG | AB57: =IF($AA57="",0,HLOOKUP($H$3,Resina!$E$2:$AK$93,MATCH($D57&$AA57&$AB$5,Resina!$A$2:$A$93,0))) -> 1651.6512 | AC57: =$AC$7 -> 46091 | AD57: Mensal | AE57: =$AE$7 -> 45839 | AF57: MIL | AG57: =_xlfn.XLOOKUP($H$3,Resina!$2:$2,Resina!$3:$3,0) -> 5.2006167 | AH57: =(L57*((Y57*W57)+(AB57*Z57)))*AG57/1000 -> 308.59994 | AI57: 0.005 | AJ57: =AH57*AI57 -> 1.5429997 | AO57: =_xlfn.XLOOKUP($D57&$L57&$AK$3,'BD Conv'!$A:$A,'BD Conv'!$H:$H,0)*_xlfn.XLOOKUP($D57,'BD Conv'!$C$17:$C$19,'BD Conv'!$F$17:$F$19,0)*(1+(HLOOKUP($B57&AO$6,Indexadores!$C$2:$AH$32,MATCH($AE57,Indexadores!$A$2:$A$32,0)))) -> 0 | AS57: 0.005 | AT57: =(AU57+AO57)*AS57 -> 0 | AU57: =_xlfn.XLOOKUP($D57&$L57&$AK$3,'BD Conv'!$A:$A,'BD Conv'!$H:$H,0)*_xlfn.XLOOKUP($D57,'BD Conv'!$C$17:$C$19,'BD Conv'!$E$17:$E$19,0)*(1+(HLOOKUP($B57&AU$6,Indexadores!$C$2:$AH$32,MATCH($AE57,Indexadores!$A$2:$A$32,0)))) -> 0 | AV57: =SUM(AN57,AO57,AP57,(AQ57*AG57),AR57,AT57,AU57) -> 0 | AW57: =_xlfn.XLOOKUP($A57&$AK$3,'BD Conv'!$A:$A,'BD Conv'!$I:$I,0) -> 0 | AZ57: =SUM(AH57,AJ57,AK57,AL57,AV57,AW57:AY57) -> 310.14294 | BI57: =SUM(BA57,BB57,BC57,(BD57*AG57),BE57,BF57,BH57) -> 0 | BN57: =_xlfn.XLOOKUP($A57&$BA$3,'BD Conv'!$A:$A,'BD Conv'!$K:$K,0) -> 0 | BQ57: =SUM(BI57,BJ57,BK57,BM57,BN57,BO57,BP57) -> 0 | BR57: =-BQ57*$BR$3 -> 0 | BT57: =AZ57+BQ57+BR57+BS57 -> 310.14294 | BU57: =BV57-BT57 -> 78.215363 | BV57: =BT57/(1-(12%+1.65%+7.6%) +12%*(1.65%+7.6%)) -> 388.35831 | BY57: =BT57/CP57-1 -> 0.040746262 | BZ57: =(BT57-CP57)/AG57 -> 2.3348015 | CA57: =(BT57-CK57-CL57-AL57-AX57-AY57-BO57-BP57+CQ57)/AG57 -> 2.3348015 | CB57: =(BT57-AH57)/AG57 -> 0.29669553 | CD57: =CP57*(1+$CD$5) -> 327.80059 | CE57: =(CD57-CP57)/AG57 -> 5.7301 | CF57: =(CD57-CK57-CL57-AL57-AX57-AY57-BO57-BP57+CQ57)/AG57 -> 5.7301 | CG57: =(CD57-AH57)/AG57 -> 3.691994 | CI57: =IF($X57="",0,HLOOKUP($H$3,Resina!$E$2:$AK$93,MATCH($D57&$X57&$CI$5,Resina!$A$2:$A$93,0))) -> 1157.6381 | CJ57: =IF($AA57="",0,HLOOKUP($H$3,Resina!$E$2:$AK$93,MATCH($D57&$AA57&$CJ$5,Resina!$A$2:$A$93,0))) -> 1610.0071 | CK57: =L57*((CI57*W57)+(CJ57*Z57))*AG57/1000 -> 295.05004 | CL57: =CK57*$CL$6 -> 2.9505004 | CM57: =IF(D57="Manaus FORA",-((CK57/0.88*0.12)*(1-9.25%))," ") | CO57: =AX57+AY57+BO57+BP57+AL57+AN57+BJ57+BK57+BM57 -> 0 | CP57: =SUM(CK57:CO57) -> 298.00054 | DE57: =_xlfn.CONCAT(D57,L57) -> Suape39.7 | DF57: =L57 -> 39.7 | DG57: =ROUND(SUMIF($1:$1,DG$5,57:57),2) -> 308.6 | DH57: =ROUND(SUMIF($1:$1,DH$5,57:57),2) -> 1.54 | DI57: =ROUND(SUMIF($1:$1,DI$5,57:57),2) -> 0 | DJ57: =ROUND(SUMIF($1:$1,DJ$5,57:57),2) -> 0 | DK57: =ROUND(SUMIF($1:$1,DK$5,57:57),2) -> 0 | DL57: =ROUND(SUMIF($1:$1,DL$5,57:57),2) -> 0 | DM57: =ROUND(SUMIF($1:$1,DM$5,57:57),2) -> 0 | DN57: =ROUND(SUMIF($1:$1,DN$5,57:57),2) -> 0 | ... ED57: =ROUND(SUMIF($1:$1,ED$5,57:57),2) -> 0 | EE57: =SUM(DG57:ED57) -> 310.14 | EF57: =ROUND(SUM(EE57-BT57),2) -> 0 | EG57: =IF(DN57<>0,DN57-EF57,0) -> 0 | EH57: =IF(EG57=0,DO57-EF57,DO57) -> 0 | EI57: =SUM(DG57:DM57)+SUM(DP57:ED57)+EG57+EH57 -> 310.14
A58: =_xlfn.CONCAT(D58,L58) -> Suape39.7 | B58: 4196 | C58: 4196 | D58: Suape | F58: AMBEV | G58: CONTRATO | H58: FOB | K58: PREFORMA | L58: 39.7 | M58: VD | V58: Virgem | W58: 0 | Y58: =IF($X58="",0,HLOOKUP($H$3,Resina!$E$2:$AK$93,MATCH($D58&$X58&$Y$5,Resina!$A$2:$A$93,0))) -> 0 | Z58: 1 | AA58: VG | AB58: =IF($AA58="",0,HLOOKUP($H$3,Resina!$E$2:$AK$93,MATCH($D58&$AA58&$AB$5,Resina!$A$2:$A$93,0))) -> 1651.6512 | AC58: =$AC$7 -> 46091 | AD58: Mensal | AE58: =$AE$7 -> 45839 | AF58: MIL | AG58: =_xlfn.XLOOKUP($H$3,Resina!$2:$2,Resina!$3:$3,0) -> 5.2006167 | AH58: =(L58*((Y58*W58)+(AB58*Z58)))*AG58/1000 -> 341.00731 | AI58: 0.005 | AJ58: =AH58*AI58 -> 1.7050365 | AO58: =_xlfn.XLOOKUP($D58&$L58&$AK$3,'BD Conv'!$A:$A,'BD Conv'!$H:$H,0)*_xlfn.XLOOKUP($D58,'BD Conv'!$C$17:$C$19,'BD Conv'!$F$17:$F$19,0)*(1+(HLOOKUP($B58&AO$6,Indexadores!$C$2:$AH$32,MATCH($AE58,Indexadores!$A$2:$A$32,0)))) -> 0 | AS58: 0.005 | AT58: =(AU58+AO58)*AS58 -> 0 | AU58: =_xlfn.XLOOKUP($D58&$L58&$AK$3,'BD Conv'!$A:$A,'BD Conv'!$H:$H,0)*_xlfn.XLOOKUP($D58,'BD Conv'!$C$17:$C$19,'BD Conv'!$E$17:$E$19,0)*(1+(HLOOKUP($B58&AU$6,Indexadores!$C$2:$AH$32,MATCH($AE58,Indexadores!$A$2:$A$32,0)))) -> 0 | AV58: =SUM(AN58,AO58,AP58,(AQ58*AG58),AR58,AT58,AU58) -> 0 | AW58: =_xlfn.XLOOKUP($A58&$AK$3,'BD Conv'!$A:$A,'BD Conv'!$I:$I,0) -> 0 | AZ58: =SUM(AH58,AJ58,AK58,AL58,AV58,AW58:AY58) -> 342.71235 | BI58: =SUM(BA58,BB58,BC58,(BD58*AG58),BE58,BF58,BH58) -> 0 | BN58: =_xlfn.XLOOKUP($A58&$BA$3,'BD Conv'!$A:$A,'BD Conv'!$K:$K,0) -> 0 | BQ58: =SUM(BI58,BJ58,BK58,BM58,BN58,BO58,BP58) -> 0 | BR58: =-BQ58*$BR$3 -> 0 | BT58: =AZ58+BQ58+BR58+BS58 -> 342.71235 | BU58: =BV58-BT58 -> 86.429084 | BV58: =BT58/(1-(12%+1.65%+7.6%) +12%*(1.65%+7.6%)) -> 429.14143 | BY58: =BT58/CP58-1 -> 0.020787214 | BZ58: =(BT58-CP58)/AG58 -> 1.3419489 | CA58: =(BT58-CK58-CL58-AL58-AX58-AY58-BO58-BP58+CQ58)/AG58 -> 1.3419489 | CB58: =(BT58-AH58)/AG58 -> 0.32785276 | CD58: =CP58*(1+$CD$5) -> 369.30672 | CE58: =(CD58-CP58)/AG58 -> 6.4556457 | CF58: =(CD58-CK58-CL58-AL58-AX58-AY58-BO58-BP58+CQ58)/AG58 -> 6.4556457 | CG58: =(CD58-AH58)/AG58 -> 5.4415495 | CI58: =IF($X58="",0,HLOOKUP($H$3,Resina!$E$2:$AK$93,MATCH($D58&$X58&$CI$5,Resina!$A$2:$A$93,0))) -> 0 | CJ58: =IF($AA58="",0,HLOOKUP($H$3,Resina!$E$2:$AK$93,MATCH($D58&$AA58&$CJ$5,Resina!$A$2:$A$93,0))) -> 1610.0071 | CK58: =L58*((CI58*W58)+(CJ58*Z58))*AG58/1000 -> 332.40929 | CL58: =CK58*$CL$6 -> 3.3240929 | CM58: =IF(D58="Manaus FORA",-((CK58/0.88*0.12)*(1-9.25%))," ") | CO58: =AX58+AY58+BO58+BP58+AL58+AN58+BJ58+BK58+BM58 -> 0 | CP58: =SUM(CK58:CO58) -> 335.73338 | DE58: =_xlfn.CONCAT(D58,L58) -> Suape39.7 | DF58: =L58 -> 39.7 | DG58: =ROUND(SUMIF($1:$1,DG$5,58:58),2) -> 341.01 | DH58: =ROUND(SUMIF($1:$1,DH$5,58:58),2) -> 1.71 | DI58: =ROUND(SUMIF($1:$1,DI$5,58:58),2) -> 0 | DJ58: =ROUND(SUMIF($1:$1,DJ$5,58:58),2) -> 0 | DK58: =ROUND(SUMIF($1:$1,DK$5,58:58),2) -> 0 | DL58: =ROUND(SUMIF($1:$1,DL$5,58:58),2) -> 0 | DM58: =ROUND(SUMIF($1:$1,DM$5,58:58),2) -> 0 | DN58: =ROUND(SUMIF($1:$1,DN$5,58:58),2) -> 0 | ... ED58: =ROUND(SUMIF($1:$1,ED$5,58:58),2) -> 0 | EE58: =SUM(DG58:ED58) -> 342.72 | EF58: =ROUND(SUM(EE58-BT58),2) -> 0.01 | EG58: =IF(DN58<>0,DN58-EF58,0) -> 0 | EH58: =IF(EG58=0,DO58-EF58,DO58) -> -0.01 | EI58: =SUM(DG58:DM58)+SUM(DP58:ED58)+EG58+EH58 -> 342.71
A59: =_xlfn.CONCAT(D59,L59) -> Suape55.6 | B59: 4196 | C59: 4196 | D59: Suape | F59: AMBEV | G59: CONTRATO | H59: FOB | K59: PREFORMA | L59: 55.6 | M59: CR | V59: Virgem | W59: 1 | X59: ALPEK | Y59: =IF($X59="",0,HLOOKUP($H$3,Resina!$E$2:$AK$93,MATCH($D59&$X59&$Y$5,Resina!$A$2:$A$93,0))) -> 1259.2427 | Z59: 0 | AA59: VG | AB59: =IF($AA59="",0,HLOOKUP($H$3,Resina!$E$2:$AK$93,MATCH($D59&$AA59&$AB$5,Resina!$A$2:$A$93,0))) -> 1651.6512 | AC59: =$AC$7 -> 46091 | AD59: Mensal | AE59: =$AE$7 -> 45839 | AF59: MIL | AG59: =_xlfn.XLOOKUP($H$3,Resina!$2:$2,Resina!$3:$3,0) -> 5.2006167 | AH59: =(L59*((Y59*W59)+(AB59*Z59)))*AG59/1000 -> 364.11543 | AI59: 0.005 | AJ59: =AH59*AI59 -> 1.8205772 | AO59: =_xlfn.XLOOKUP($D59&$L59&$AK$3,'BD Conv'!$A:$A,'BD Conv'!$H:$H,0)*_xlfn.XLOOKUP($D59,'BD Conv'!$C$17:$C$19,'BD Conv'!$F$17:$F$19,0)*(1+(HLOOKUP($B59&AO$6,Indexadores!$C$2:$AH$32,MATCH($AE59,Indexadores!$A$2:$A$32,0)))) -> 0 | AS59: 0.005 | AT59: =(AU59+AO59)*AS59 -> 0 | AU59: =_xlfn.XLOOKUP($D59&$L59&$AK$3,'BD Conv'!$A:$A,'BD Conv'!$H:$H,0)*_xlfn.XLOOKUP($D59,'BD Conv'!$C$17:$C$19,'BD Conv'!$E$17:$E$19,0)*(1+(HLOOKUP($B59&AU$6,Indexadores!$C$2:$AH$32,MATCH($AE59,Indexadores!$A$2:$A$32,0)))) -> 0 | AV59: =SUM(AN59,AO59,AP59,(AQ59*AG59),AR59,AT59,AU59) -> 0 | AW59: =_xlfn.XLOOKUP($A59&$AK$3,'BD Conv'!$A:$A,'BD Conv'!$I:$I,0) -> 0 | AZ59: =SUM(AH59,AJ59,AK59,AL59,AV59,AW59:AY59) -> 365.93601 | BI59: =SUM(BA59,BB59,BC59,(BD59*AG59),BE59,BF59,BH59) -> 0 | BN59: =_xlfn.XLOOKUP($A59&$BA$3,'BD Conv'!$A:$A,'BD Conv'!$K:$K,0) -> 0 | BQ59: =SUM(BI59,BJ59,BK59,BM59,BN59,BO59,BP59) -> 0 | BR59: =-BQ59*$BR$3 -> 0 | BT59: =AZ59+BQ59+BR59+BS59 -> 365.93601 | BU59: =BV59-BT59 -> 92.285891 | BV59: =BT59/(1-(12%+1.65%+7.6%) +12%*(1.65%+7.6%)) -> 458.2219 | BY59: =BT59/CP59-1 -> 0.082383897 | BZ59: =(BT59-CP59)/AG59 -> 5.3556392 | CA59: =(BT59-CK59-CL59-AL59-AX59-AY59-BO59-BP59+CQ59)/AG59 -> 5.3556392 | CB59: =(BT59-AH59)/AG59 -> 0.35006948 | CD59: =CP59*(1+$CD$5) -> 371.89172 | CE59: =(CD59-CP59)/AG59 -> 6.5008326 | CF59: =(CD59-CK59-CL59-AL59-AX59-AY59-BO59-BP59+CQ59)/AG59 -> 6.5008326 | CG59: =(CD59-AH59)/AG59 -> 1.4952628 | CI59: =IF($X59="",0,HLOOKUP($H$3,Resina!$E$2:$AK$93,MATCH($D59&$X59&$CI$5,Resina!$A$2:$A$93,0))) -> 1157.6381 | CJ59: =IF($AA59="",0,HLOOKUP($H$3,Resina!$E$2:$AK$93,MATCH($D59&$AA59&$CJ$5,Resina!$A$2:$A$93,0))) -> 1610.0071 | CK59: =L59*((CI59*W59)+(CJ59*Z59))*AG59/1000 -> 334.73602 | CL59: =CK59*$CL$6 -> 3.3473602 | CM59: =IF(D59="Manaus FORA",-((CK59/0.88*0.12)*(1-9.25%))," ") | CO59: =AX59+AY59+BO59+BP59+AL59+AN59+BJ59+BK59+BM59 -> 0 | CP59: =SUM(CK59:CO59) -> 338.08338 | DE59: =_xlfn.CONCAT(D59,L59) -> Suape55.6 | DF59: =L59 -> 55.6 | DG59: =ROUND(SUMIF($1:$1,DG$5,59:59),2) -> 364.12 | DH59: =ROUND(SUMIF($1:$1,DH$5,59:59),2) -> 1.82 | DI59: =ROUND(SUMIF($1:$1,DI$5,59:59),2) -> 0 | DJ59: =ROUND(SUMIF($1:$1,DJ$5,59:59),2) -> 0 | DK59: =ROUND(SUMIF($1:$1,DK$5,59:59),2) -> 0 | DL59: =ROUND(SUMIF($1:$1,DL$5,59:59),2) -> 0 | DM59: =ROUND(SUMIF($1:$1,DM$5,59:59),2) -> 0 | DN59: =ROUND(SUMIF($1:$1,DN$5,59:59),2) -> 0 | ... ED59: =ROUND(SUMIF($1:$1,ED$5,59:59),2) -> 0 | EE59: =SUM(DG59:ED59) -> 365.94 | EF59: =ROUND(SUM(EE59-BT59),2) -> 0 | EG59: =IF(DN59<>0,DN59-EF59,0) -> 0 | EH59: =IF(EG59=0,DO59-EF59,DO59) -> 0 | EI59: =SUM(DG59:DM59)+SUM(DP59:ED59)+EG59+EH59 -> 365.94
A60: =_xlfn.CONCAT(D60,L60) -> Suape55.6 | B60: 4196 | C60: 4196 | D60: Suape | F60: AMBEV | G60: CONTRATO | H60: FOB | K60: PREFORMA | L60: 55.6 | M60: CR | V60: Virgem | W60: 0.6 | X60: ALPEK | Y60: =IF($X60="",0,HLOOKUP($H$3,Resina!$E$2:$AK$93,MATCH($D60&$X60&$Y$5,Resina!$A$2:$A$93,0))) -> 1259.2427 | Z60: 0.4 | AA60: VG | AB60: =IF($AA60="",0,HLOOKUP($H$3,Resina!$E$2:$AK$93,MATCH($D60&$AA60&$AB$5,Resina!$A$2:$A$93,0))) -> 1651.6512 | AC60: =$AC$7 -> 46091 | AD60: Mensal | AE60: =$AE$7 -> 45839 | AF60: MIL | AG60: =_xlfn.XLOOKUP($H$3,Resina!$2:$2,Resina!$3:$3,0) -> 5.2006167 | AH60: =(L60*((Y60*W60)+(AB60*Z60)))*AG60/1000 -> 409.50207 | AI60: 0.005 | AJ60: =AH60*AI60 -> 2.0475103 | AO60: =_xlfn.XLOOKUP($D60&$L60&$AK$3,'BD Conv'!$A:$A,'BD Conv'!$H:$H,0)*_xlfn.XLOOKUP($D60,'BD Conv'!$C$17:$C$19,'BD Conv'!$F$17:$F$19,0)*(1+(HLOOKUP($B60&AO$6,Indexadores!$C$2:$AH$32,MATCH($AE60,Indexadores!$A$2:$A$32,0)))) -> 0 | AS60: 0.005 | AT60: =(AU60+AO60)*AS60 -> 0 | AU60: =_xlfn.XLOOKUP($D60&$L60&$AK$3,'BD Conv'!$A:$A,'BD Conv'!$H:$H,0)*_xlfn.XLOOKUP($D60,'BD Conv'!$C$17:$C$19,'BD Conv'!$E$17:$E$19,0)*(1+(HLOOKUP($B60&AU$6,Indexadores!$C$2:$AH$32,MATCH($AE60,Indexadores!$A$2:$A$32,0)))) -> 0 | AV60: =SUM(AN60,AO60,AP60,(AQ60*AG60),AR60,AT60,AU60) -> 0 | AW60: =_xlfn.XLOOKUP($A60&$AK$3,'BD Conv'!$A:$A,'BD Conv'!$I:$I,0) -> 0 | AZ60: =SUM(AH60,AJ60,AK60,AL60,AV60,AW60:AY60) -> 411.54958 | BI60: =SUM(BA60,BB60,BC60,(BD60*AG60),BE60,BF60,BH60) -> 0 | BN60: =_xlfn.XLOOKUP($A60&$BA$3,'BD Conv'!$A:$A,'BD Conv'!$K:$K,0) -> 0 | BQ60: =SUM(BI60,BJ60,BK60,BM60,BN60,BO60,BP60) -> 0 | BR60: =-BQ60*$BR$3 -> 0 | BT60: =AZ60+BQ60+BR60+BS60 -> 411.54958 | BU60: =BV60-BT60 -> 103.78924 | BV60: =BT60/(1-(12%+1.65%+7.6%) +12%*(1.65%+7.6%)) -> 515.33882 | BY60: =BT60/CP60-1 -> 0.052749306 | BZ60: =(BT60-CP60)/AG60 -> 3.9651453 | CA60: =(BT60-CK60-CL60-AL60-AX60-AY60-BO60-BP60+CQ60)/AG60 -> 3.9651453 | CB60: =(BT60-AH60)/AG60 -> 0.3937053 | CD60: =CP60*(1+$CD$5) -> 430.02122 | CE60: =(CD60-CP60)/AG60 -> 7.516962 | CF60: =(CD60-CK60-CL60-AL60-AX60-AY60-BO60-BP60+CQ60)/AG60 -> 7.516962 | CG60: =(CD60-AH60)/AG60 -> 3.945522 | CI60: =IF($X60="",0,HLOOKUP($H$3,Resina!$E$2:$AK$93,MATCH($D60&$X60&$CI$5,Resina!$A$2:$A$93,0))) -> 1157.6381 | CJ60: =IF($AA60="",0,HLOOKUP($H$3,Resina!$E$2:$AK$93,MATCH($D60&$AA60&$CJ$5,Resina!$A$2:$A$93,0))) -> 1610.0071 | CK60: =L60*((CI60*W60)+(CJ60*Z60))*AG60/1000 -> 387.0578 | CL60: =CK60*$CL$6 -> 3.870578 | CM60: =IF(D60="Manaus FORA",-((CK60/0.88*0.12)*(1-9.25%))," ") | CO60: =AX60+AY60+BO60+BP60+AL60+AN60+BJ60+BK60+BM60 -> 0 | CP60: =SUM(CK60:CO60) -> 390.92838 | DE60: =_xlfn.CONCAT(D60,L60) -> Suape55.6 | DF60: =L60 -> 55.6 | DG60: =ROUND(SUMIF($1:$1,DG$5,60:60),2) -> 409.5 | DH60: =ROUND(SUMIF($1:$1,DH$5,60:60),2) -> 2.05 | DI60: =ROUND(SUMIF($1:$1,DI$5,60:60),2) -> 0 | DJ60: =ROUND(SUMIF($1:$1,DJ$5,60:60),2) -> 0 | DK60: =ROUND(SUMIF($1:$1,DK$5,60:60),2) -> 0 | DL60: =ROUND(SUMIF($1:$1,DL$5,60:60),2) -> 0 | DM60: =ROUND(SUMIF($1:$1,DM$5,60:60),2) -> 0 | DN60: =ROUND(SUMIF($1:$1,DN$5,60:60),2) -> 0 | ... ED60: =ROUND(SUMIF($1:$1,ED$5,60:60),2) -> 0 | EE60: =SUM(DG60:ED60) -> 411.55 | EF60: =ROUND(SUM(EE60-BT60),2) -> 0 | EG60: =IF(DN60<>0,DN60-EF60,0) -> 0 | EH60: =IF(EG60=0,DO60-EF60,DO60) -> 0 | EI60: =SUM(DG60:DM60)+SUM(DP60:ED60)+EG60+EH60 -> 411.55
