Workbook
Name \P: #REF!
Name \P: #REF!
Name _________CTM1: #REF!
Name _________CTM1: #REF!
Name _________CTM2: #REF!
Name _________CTM3: #REF!
Name _________CTM4: #REF!
Name ________CTM1: #REF!
Name ________CTM2: #REF!
Name ________CTM3: #REF!
Name ________CTM4: #REF!
Name _______CTM1: #REF!
Name _______CTM2: #REF!
Name _______CTM3: #REF!
Name _______CTM4: #REF!
Name ______CTM1: #REF!
Name ______CTM2: #REF!
Name ______CTM3: #REF!
Name ______CTM4: #REF!
Name _____CTM1: #REF!
Name _____CTM2: #REF!
Name _____CTM3: #REF!
Name _____CTM4: #REF!
Name _____pag2: #REF!
Name _____pag3: #REF!
Name ____CTM1: #REF!
Name ____CTM2: #REF!
Name ____CTM3: #REF!
Name ____CTM4: #REF!
Name ____pag2: #REF!
Name ____pag3: #REF!
Name ___CTM1: #REF!
Name ___CTM2: #REF!
Name ___CTM3: #REF!
Name ___CTM4: #REF!
Name ___pag2: #REF!
Name ___pag3: #REF!
Name __CTM1: #REF!
Name __CTM2: #REF!
Name __CTM3: #REF!
Name __CTM4: #REF!
Name __pag2: #REF!
Name __pag3: #REF!
Name _38LINE: #REF!
Name _4LINEADJ: #REF!
Name _94BPRICE: #REF!
Name _CTM1: #REF!
Name _CTM2: #REF!
Name _CTM3: #REF!
Name _CTM4: #REF!
Name _MAG1: #REF!
Name _MAG1: '[1]Mag 1'!$E$2:$E$208
Name _MAG2: #REF!
Name _MAG2: '[1]Mag 2'!$E$82:$E$208
Name _MAG3: #REF!
Name _MAG3: '[1]Mag 3'!$E$4:$E$208
Name _MAG4: #REF!
Name _MAG4: '[1]Mag 4'!$E$4:$E$208
Name _MOR2: #REF!
Name _MOR2: #REF!

Sheet ICIS Price Forecast
B2: ICIS Dashboard Price Forecast
B4: Generated | C4: 17 Apr 2026 22:17:20
B5: Date Range 1 | C5: From 17 Apr 2025 To 01 Oct 2027
B6: Original Currency | C6: USD | D6: USD
B7: Original Unit | C7: tonne | D7: tonne
B8: Selected Currency | C8: USD
B9: Selected Unit | C9: tonne
B10: Price Forecast Range | C10: 18 Months
B11: Price History Range | C11: 1 Year
B13: Date Range 1 | C13: PET Bottle Grade FOB China Spot Forecast Apr-2026 Latest | D13: PET Bottle Grade FOB China Spot 4-12 Weeks Full Market Range
B14: 18-Apr-2025 | D14: 730.00
B15: 25-Apr-2025 | D15: 735.00
B16: 02-May-2025 | D16: 752.50
B17: 09-May-2025 | D17: 755.00
B18: 16-May-2025 | D18: 792.50
B19: 23-May-2025 | D19: 790.00
B20: 30-May-2025 | D20: 785.00
B21: 06-Jun-2025 | D21: 780.00
B22: 13-Jun-2025 | D22: 782.50
B23: 20-Jun-2025 | D23: 812.50
B24: 27-Jun-2025 | D24: 797.50
B25: 04-Jul-2025 | D25: 785.00
... B50: 26-Dec-2025 | D50: 770.00
B51: 09-Jan-2026 | D51: 800
B52: 16-Jan-2026 | D52: 802.5
B53: 23-Jan-2026 | D53: 825
B54: 30-Jan-2026 | D54: 845
B55: 06-Feb-2026 | D55: 830
B56: 13-Feb-2026 | D56: 837.5
B57: 27-Feb-2026 | D57: 847.5
B58: 06-Mar-2026 | D58: 920
B59: 13-Mar-2026 | D59: 1135
B60: 20-Mar-2026 | D60: 1215
B61: 27-Mar-2026 | D61: 1175
B62: 01-Apr-2026 | C62: 1147.00 | D62: =C62 -> 1147.00
B63: 03-Apr-2026 | D63: 1190
B64: 10-Apr-2026 | D64: 1182.5
B65: 17-Apr-2026 | D65: 1190
B66: 01-May-2026 | C66: 1173.00
B67: 01-Jun-2026 | C67: 1054.00
B68: 01-Jul-2026 | C68: 941.00
B69: 01-Aug-2026 | C69: 883.00
B70: 01-Sep-2026 | C70: 864.00
B71: 01-Oct-2026 | C71: 838.00
B72: 01-Nov-2026 | C72: 811.00
B73: 01-Dec-2026 | C73: 790.00
B74: 01-Jan-2027 | C74: 793.00
B75: 01-Feb-2027 | C75: 794.00
B76: 01-Mar-2027 | C76: 799.00
B77: 01-Apr-2027 | C77: 807.00
... B82: 01-Sep-2027 | C82: 816.00
B84: Copyright © 2026 LexisNexis Risk Solutions.
B85: ICIS is a member of the RELX.
B86: ICIS accepts no liability for commercial decisions based on the content of this report.
B87: UNAUTHORISED REPRODUCTION / TRANSMISSION PROHIBITED.
B88: Exchange rates supplied by LSEG and XE.com (http://www.XE.com).
B89: Prices that have been converted from the originally quoted unit or currency are shown to two decimal places.
B90: When exporting multiple quote series, empty cells may appear in the quote table as publishing dates may not align or may vary over holiday periods.

Sheet Drewry
BB1: =BB3-97 -> 137.45455 | BC1: =BC3-97 -> 76.363636 | BD1: =BD3-97 -> 65.136364 | BE1: =BE3-97 -> 39.954545 | BF1: =BF3-97 -> 6.5909091
B2: 44378 | C2: 44409 | D2: 44440 | E2: 44470 | F2: 44501 | G2: 44531 | H2: 44562 | I2: 44593 | J2: 44621 | K2: 44652 | L2: 44682 | M2: 44713 | N2: 44743 | O2: 44774 | P2: 44805 | Q2: 44835 | R2: 44866 | S2: 44896 | T2: 44927 | U2: 44958 | V2: 44986 | W2: 45017 | X2: 45047 | Y2: 45078 | Z2: 45108 | AA2: 45139 | AB2: 45170 | AC2: 45200 | AD2: 45231 | AE2: 45261 | AF2: 45292 | AG2: 45323 | AH2: 45352 | AI2: 45383 | AJ2: 45413 | AK2: 45444 | AL2: 45474 | AM2: 45505 | AN2: 45536 | AO2: 45566 | AP2: 45597 | AQ2: 45627 | AR2: 45658 | AS2: 45689 | AT2: 45717 | AU2: 45748 | AV2: 45778 | AW2: 45809 | AX2: 45839 | AY2: 45870 | AZ2: 45901 | BA2: 45931 | BB2: 45962 | BC2: 45992 | BD2: 46023 | BE2: 46054 | BF2: 46082 | BG2: Apr
A3: Drewry Shanghai-CTG | B3: 350 | C3: =+C4/22 -> 386.36364 | D3: =+D4/22 -> 495 | E3: =+E4/22 -> 538.63636 | F3: =+F4/22 -> 577.27273 | G3: =+G4/22 -> 577.27273 | H3: =+H4/22 -> 577.27273 | I3: =+I4/22 -> 577.27273 | J3: =+J4/22 -> 577.27273 | ... BG3: =+BG4/22 -> 134.22727
A4: Contenedor | B4: =+B3*22 -> 7700 | C4: 8500 | D4: 10890 | E4: 11850 | F4: 12700 | G4: 12700 | H4: 12700 | I4: 12700 | J4: 12700 | K4: 12700 | L4: 12090 | M4: 10570 | N4: 10580 | O4: 10920 | P4: 10920 | Q4: 10640 | R4: 8950 | S4: 6070 | T4: 4850 | U4: 4850 | V4: 2690 | W4: 2510 | X4: 1980 | Y4: 2700 | Z4: 3153 | AA4: 2873 | AB4: 2722 | AC4: 3369 | AD4: 3269 | AE4: 2848 | AF4: 3226 | AG4: 3584 | AH4: 3670 | AI4: 3649 | AJ4: 4294 | AK4: 6049 | AL4: 8585 | AM4: 9257 | AN4: 7086 | AO4: 7536 | AP4: 5849 | AQ4: 5742 | AR4: 4700 | AS4: 4700 | AT4: 4538 | AU4: 3569 | AV4: 3685 | AW4: 3215 | AX4: 3268 | AY4: 7924 | AZ4: 5721 | BA4: 5508 | BB4: 5158 | BC4: 3814 | BD4: 3567 | BE4: 3013 | BF4: 2279 | BG4: =AVERAGE(BD4:BF4) -> 2953
AI5: =+AH4/AI4-1 -> 0.0057550014 | AJ5: =+AI4/AJ4-1 -> -0.15020959 | AK5: =+AJ4/AK4-1 -> -0.2901306 | AL5: =+AK4/AL4-1 -> -0.29539895 | AM5: =+AL4/AM4-1 -> -0.072593713 | AN5: =+AM4/AN4-1 -> 0.30637878 | AO5: =+AN4/AO4-1 -> -0.059713376 | AP5: =+AO4/AP4-1 -> 0.28842537 | ... BF5: =+BE4/BF4-1 -> 0.32207108 | BG5: 3890

Sheet Amcor - Columbia 
D2: S.No | E2: Supplier Name | F2: Excel | G2: Sheet Reference | H2: Route | I2: Description | J2: Month | K2: Price
D3: 1 | E3: Bavaria | F3: 1 Bavaria - Precio Marzo | G3: Fórmula Marzo 26 | H3: China to columbia | I3: Precio Final con ajuste flete Resina | J3: March | K3: 1099.8627
N10: Country X Supplier
J11: 1 Bavaria - Precio Marzo | N11: Historical | O11: Available
I12: Formuale Sheet | J12: Supplier Sheet | K12: Formulae | L12: Source
I13: Resin cost:Quarterly Resin index average price | J13: ICIS Index - Quaret | K13: 821 | L13: ICIS
I14: Resin freight cost | J14: Freight China–Buenaventura | K14: =97 -> 97 | L14: Drewery Index
I15: Resin financing cost (Assumption based on rPET formula) | J15: Finance | K15: 32.33
I16: Sub total (con flete reg ) | J16: vPET Resin pricing | K16: =SUM(K13:K15) -> 950.33
I18: Is Sub total (con flete reg ) the Total Landing cost
I21: Doubts
I23: what is Aurora , Enkador , Enka ? | J23: Why are they not present in the supplier sheets ?
I24: What are the prices below Sub Total ? Which is used as the final price for TLC ?
I25: From where is the 97 freight referred ?
I29: Sheet Names :
I30: 1. Fórmula Marzo 26 | J30: TLC formulae considered for the calculation
I31: 2. Fórmula Ago | J31: TLC formulae sheet for different time frame
I32: 3. PCR Aurora | J32: Need more understanding of this sheet
I33: 4. PCR Enkador | J33: Need more understanding of this sheet
I34: 5. PCR Enka | J34: This sheet is used for the Legilation charges cost , but need more understanding of this sheet
I35: 6. PCR INTERCIA | J35: Need more understanding of this sheet
I36: 7. ICIS PCR | J36: Market Data Providers for Index calculation --- > Flows into ICIS - 1
I37: 8. IHS PCR | J37: Market Data Providers for Index calculation --- > Flows into ICIS - 1
I38: 9. IHS Index | J38: Has Index data -- Need why is this sheet used ?
I39: 10. ICIS -1 | J39: Used for the TLC calculation Resin Index
I40: 11. SOFR | J40: Used for the TLC calculation
I41: 12. Drewry | J41: Used for the TLC calculation
... I45: 16. Balance | J45: Need more understanding of this sheet

Sheet Fórmula Apr (2)
C1: FÓRMULA
C11: PRECIOS DE RESINA ABI MARZO 2026
CP12: 137.45455 | CQ12: 76.363636 | CR12: 65.136364 | CS12: 39.954545 | CT12: 6.5909091 | CZ12: 1. couldn’t figure out the formula here. If its colombia why is it not quarterly
AE13: Fórmula | CV13: Estimated | CZ13: what is FIFO
B14: Translation | C14: PRICE | D14: Jul-18 | E14: Ago-2018 | F14: Sep-18 | G14: Oct-18 | H14: Nov-18 | I14: Dic-18 | J14: Ene-19 | K14: Feb-19 | L14: Mar-19 | M14: Abr-19 | N14: May-19 | O14: Jun-19 | P14: Jul-19 | Q14: Ago-19 | R14: Sep-19 | S14: Oct-19 | T14: Nov-20 | U14: Dic-20 | V14: Ene-20 | W14: Feb-20 | X14: Mar-20 | Y14: Abr-20 | Z14: May-20 | AA14: Jun-20 | AB14: Jun-20 | AC14: Jul-20 | AD14: Jul-20 | AE14: Ago-20 | AF14: Ago-20 | AG14: Sep-20 | AH14: Oct-20 | AI14: Nov-20 | AJ14: Dic-20 | AK14: Ene-21 | AL14: Feb-21 | AM14: Mar-21 | AN14: Abr-21 | AO14: May-21 | AP14: Jun-21 | AQ14: Jul-21 | AR14: Ago-21 | AS14: Sep-21 | AT14: Oct-21 | AU14: Nov-21 | AV14: Dic-21 | AW14: Ene-22 | AX14: Feb-22 | AY14: Mar-22 | AZ14: Abr-22 | BA14: Mayo-22 | BB14: Junio-22 | BC14: Julio-22 | BD14: Agosto-22 | BE14: Septiembre-22 | BF14: Octubre-22 | BG14: Noviembre-22 | BH14: Diciembre-22 | BI14: Enero-23 | BJ14: Febrero-23 | BK14: Marzo-23 | BL14: Abril-23 | BM14: Mayo-23 | BN14: Junio-23 | BO14: Julio-23 | BP14: Agosto-23 | BQ14: Septiembre-23 | BR14: Octubre-23 | BS14: Noviembre-23 | BT14: Diciembre-23 | BU14: Enero-24 | BV14: Febrero-24 | BW14: Marzo-24 | BX14: Abril-24 | BY14: Mayo-24 | BZ14: Junio-24 | CA14: Julio-24 | CB14: Agosto-24 | CC14: Septiembre-24 | CD14: Octubre-24 | CE14: Noviembre-24 | CF14: Diciembre-24 | CG14: Enero-25 | CH14: Febrero-25 | CI14: Marzo-25 | CJ14: Abril-25 | CK14: Mayo-25 | CL14: Junio-25 | CM14: Julio-25 | CN14: Agosto-25 | CO14: Septie-25 | CP14: Oct-25 | CQ14: Nov-25 | CR14: Dic-25 | CS14: Ene-26 | CT14: Feb-26 | CU14: Mar-26 | CV14: Apr-26 | CW14: May-26 | CZ14: Resina Virgen | EM14: Formulae / References Needed ?
B15: Resin Price Index | C15: ICIS China MID (n-1). | D15: May-18 | E15: Jun-18 | F15: Jul-18 | G15: Ago-18 | H15: Sep-18 | I15: Oct-18 | J15: Nov-18 | K15: Dic-18 | L15: Jan-19 | M15: Feb-19 | N15: Mar-19 | O15: Abr-19 | P15: May-19 | Q15: Jun-19 | R15: Jul-19 | S15: Ago-19 | T15: Sep-19 | U15: Oct-19 | V15: Nov-19 | W15: Dic-19 | X15: Jan-20 | Y15: Feb-20 | Z15: Mar-20 | AA15: Abr-20 | AB15: Abr-20 | AC15: May-20 | AD15: May-20 | AE15: Jun-20 | AF15: Jun-20 | AG15: Jul-20 | AH15: Ago-20 | AI15: Sep-20 | AJ15: Oct-20 | AK15: Nov-20 | AL15: Dic-20 | AM15: Jan-21 | AN15: 44228 | AO15: 44256 | AP15: 44287 | AQ15: 44317 | AR15: 44348 | AS15: 44378 | AT15: 44409 | AU15: 44440 | AV15: 44440 | AW15: 44501 | AX15: 44531 | AY15: 44562 | AZ15: 44593 | BA15: 44621 | BB15: 44652 | BC15: 44682 | BD15: 44713 | BE15: 44743 | BF15: 44774 | BG15: 44805 | BH15: 44835 | BI15: 44866 | BJ15: 44896 | BK15: 44927 | BL15: 44958 | BM15: 44986 | BN15: 45017 | BO15: 45047 | BP15: 45078 | BQ15: 45108 | BR15: 45139 | BS15: 45170 | BT15: 45200 | BU15: 45231 | BV15: 45261 | BW15: 44927 | BX15: 44958 | BY15: 44986 | BZ15: 45017 | CA15: 45047 | CB15: 45078 | CC15: 45108 | CD15: 45139 | CE15: 45536 | CF15: 45566 | CG15: 45597 | CH15: 45627 | CI15: 45658 | CJ15: 45689 | CK15: 45717 | CL15: 45748 | CM15: 45778 | CN15: 45809 | CO15: 45839 | CP15: 45870 | CQ15: 45901 | CR15: 45931 | CS15: 45962 | CT15: 45992 | CU15: 46023 | CV15: 46054 | CW15: 46082 | CZ15: Descripcion. | DA15: MAYO | DB15: JUNIO | DC15: JULIO | DD15: AGOSTO | DE15: SEPTIEMBRE | DF15: OCTUBRE | DG15: NOVIEMBRE | DH15: DICIEMBRE | DI15: ENERO | DJ15: FEBRERO | DK15: MARZO | DL15: ABRIL | DM15: MAYO | DN15: JUNIO | DO15: JULIO | DP15: AGOSTO | DQ15: SEPTIEMBRE | DR15: OCTUBRE | DS15: NOVIEMBRE | DT15: DICIEMBRE | DU15: ENERO | DV15: FEBRERO | DW15: MARZO | DX15: ABRIL | DY15: MAYO | DZ15: JUNIO | EA15: JULIO | EB15: AGOSTO | EC15: SEPTIEM | ED15: OCTUBRE | EE15: NOVIEMBRE | EF15: DICIEMBRE | EG15: ENERO | EH15: FEBRERO | EI15: MARZO
D16: 1330 | E16: 1280 | F16: 1279.38 | G16: 1275.5 | H16: 1330 | I16: 1266.25 | J16: 1125 | K16: 1058.13 | L16: 1035 | M16: 1077.5 | N16: 1096.25 | O16: 1101.25 | P16: 1004.5 | Q16: 926.25 | R16: 966.88 | S16: 889 | T16: 868.75 | U16: 840 | V16: 818.75 | W16: 824.38 | X16: 840 | Y16: 840 | Z16: 736.88 | AA16: 655 | AB16: 707.17946 | AC16: 669.38 | AD16: 687.43458 | AE16: 678.13 | AF16: 682.5409 | AG16: 659 | AH16: 647.5 | AI16: 649.38 | AJ16: 641.5 | AK16: 648.13 | AL16: 713 | AM16: 789.38 | AN16: 880.63 | AO16: 1018.75 | AP16: 960 | AQ16: 932.5 | AR16: 920 | AS16: 960 | AT16: 966.25 | AU16: 953 | AV16: 1111.88 | AW16: 1124.38 | AX16: 1026.5 | AY16: 1144 | AZ16: 1138 | BA16: 1139 | BB16: 1199 | BC16: 1216.25 | BD16: 1235 | BE16: 1125 | BF16: 1096.25 | BG16: 1048 | BH16: 975.63 | BI16: 897.5 | BJ16: 890 | BK16: 941.88 | BL16: 965 | BM16: 980 | BN16: 1018.75 | BO16: 938.13 | BP16: 882 | BQ16: 878.75 | BR16: 889 | BS16: 898.75 | BT16: 880 | BU16: 865 | BV16: 863.13 | BW16: 889.38 | BX16: 906.5 | BY16: 906.5 | BZ16: 898.13 | CA16: 885 | CB16: 885.63 | CC16: 896.25 | CD16: 874 | CE16: 815 | CF16: 842 | CG16: 802.5 | CH16: 791.25 | CI16: 799.5 | CJ16: 803.125 | CK16: 786.25 | CL16: 745.625 | CM16: 775 | CN16: 793.125 | CO16: 781.875 | CP16: =+'ICIS -1'!C16 -> 774 | CQ16: =+'ICIS -1'!C17 -> 765 | CR16: =+'ICIS -1'!C18 -> 752 | CS16: =+'ICIS -1'!C19 -> 748.75 | CT16: =+'ICIS -1'!C20 -> 756.25 | CU16: =+'ICIS -1'!C21 -> 821.075 | CV16: =AVERAGE('ICIS Price Forecast'!D62:D65) -> 1187.5 | CZ16: Inv Inicial TON | DA16: 327.54748 | DB16: 455.56748 | DC16: 551.38748 | DD16: 361.38748 | DE16: 321.644 | DF16: 392.25652 | DG16: 392.25652 | DH16: =+DG19 -> 350.06179 | DI16: =+DH19 -> 316.06179 | DJ16: =+DI19 -> 350.84056 | DK16: =+DI19 -> 350.84056 | DL16: =+DK19 -> 379.54056 | DM16: =+DL19 -> 307.54056 | DN16: =+DM19 -> 307.52056 | DO16: =+DN19 -> 236.82841 | DP16: =+DO19 -> 139.47841 | DQ16: =+DP19 -> 217.93712 | DR16: =+DQ19 -> 120.58712 | DS16: =+DR19 -> 317.58712 | ... EI16: =+EH19 -> 304.9584 | EM16: ICIS Forecast / Index data
B17: Finance | C17: Finance | D17: =+D16*4.5%/365*210 -> 34.434247 | E17: =+E16*4.5%/365*210 -> 33.139726 | F17: =+F16*4.5%/365*210 -> 33.123674 | G17: =+G16*4.5%/365*210 -> 33.023219 | H17: =+H16*4.5%/365*210 -> 34.434247 | I17: =+I16*4.5%/365*210 -> 32.783733 | J17: =+J16*4.5%/365*210 -> 29.126712 | K17: =+K16*(4.5%+1.59%)/365*210 -> 37.075136 | L17: =+L16*(4.5%+1.59%)/365*210 -> 36.264699 | M17: =+M16*(4.5%+1.59%)/365*210 -> 37.753829 | N17: =+N16*(4.5%+1.59%)/365*210 -> 38.410798 | O17: =+O16*(4.5%+1.59%)/365*210 -> 38.58599 | P17: =+P16*(4.5%+1.59%)/365*210 -> 35.196029 | Q17: =+Q16*(4.5%+1.59%)/365*210 -> 32.454277 | R17: =+R16*(4.5%+1.59%)/365*210 -> 33.877886 | ... U17: =+U16*(4.5%+1.59%)/365*210 -> 29.432219 | V17: =+V16*(4.5%+1.59%+1.9%)/365*210 -> 37.637825 | W17: =+W16*(4.5%+1.59%+1.9%)/365*210 -> 37.896636 | X17: =+X16*(4.5%+1.59%+1.9%)/365*210 -> 38.614685 | Y17: =+Y16*(4.5%+1.59%+1.9%)/365*210 -> 38.614685 | Z17: =+Z16*(4.5%+1.59%+1.9%)/365*210 -> 33.874273 | AA17: =+AA16*(4.5%+1.59%+1.9%)/365*210 -> 30.11026 | AB17: =+AB16*(4.5%+1.59%+1.9%)/365*210 -> 32.508943 | AC17: =+AC16*(4.5%+1.59%+1.9%)/365*210 -> 30.771307 | ... AH17: =+AH16*(4.5%+1.59%+1.9%)/365*210 -> 29.765486 | AI17: 29.85191 | AJ17: 29.489667 | AK17: 29.794447 | AL17: 32.776512 | AM17: 36.28769 | AN17: 40.48244 | AO17: 46.831798 | AP17: 44.131068 | AQ17: 24.529984 | AR17: 24.529984 | AS17: 25.253388 | AT17: 25.253388 | AU17: 25.069249 | AV17: 18.010318 | AW17: 20.073418 | AX17: 27.002711 | AY17: 20 | AZ17: 20 | BA17: 20 | BB17: 21 | BC17: 31.994202 | BD17: 32.487432 | BE17: 29.593814 | BF17: 28.837528 | BG17: 27.568282 | BH17: 25.664545 | BI17: 41.03519 | BJ17: 40.692278 | BK17: 48.654829 | BL17: 49.337828 | BM17: 49.255313 | BN17: 52.190236 | BO17: 49.095804 | BP17: 45.969807 | BQ17: 45.510666 | BR17: 47.311118 | BS17: 47.547395 | BT17: 45.827422 | BU17: =+(BU16+BU19+BU18)*SOFR!$F$3 -> 35.374019 | BV17: =+(BV16+BV19+BV18)*SOFR!$F$3 -> 35.877641 | BW17: =+(BW16+BW19+BW18)*SOFR!$F$3 -> 36.795528 | BX17: =+(BX16+BX19+BX18)*SOFR!$F$3 -> 37.497477 | BY17: =+(BY16+BY19+BY18)*SOFR!$F$3 -> 37.497477 | BZ17: 52.325208 | CA17: 56.881264 | CB17: 58.27184 | CC17: 54.343859 | CD17: 54.263773 | CE17: 48.211712 | CF17: 49.1991 | CG17: =+(CG16+CG19+CG18)*SOFR!$F$3 -> 35.531371 | CH17: =+(CH16+CH19+CH18)*SOFR!$F$3 -> 35.137991 | CI17: =+(CI16+CI19+CI18)*SOFR!$F$3 -> 35.168984 | CJ17: =+(CJ16+CJ19+CJ18)*SOFR!$F$3 -> 33.755597 | CK17: =+(CK16+CK19+CK18)*SOFR!$F$3 -> 33.349899 | CL17: =+(CL16+CL19+CL18)*SOFR!$F$3 -> 31.182334 | CM17: =+(CM16+CM19+CM18)*SOFR!$F$3 -> 32.293733 | CN17: =+(CN16+CN19+CN18)*SOFR!$F$3 -> 40.327828 | ... CV17: =+(CV16+CV19+CV18)*SOFR!$F$3 -> 46.217008 | CZ17: Entradas TON | DA17: 467 | DB17: 396 | DC17: 113 | DD17: 260 | DE17: 370.61252 | DF17: 313 | DG17: 313 | DH17: 313 | DI17: 313 | DJ17: 313 | DK17: 313 | DL17: 200 | DM17: 300 | DN17: 300 | DO17: 300 | DP17: 500 | DQ17: 300 | DR17: 550 | DS17: 300 | DT17: 400 | DU17: 100 | DV17: =455+160 -> 615 | DW17: =330+23 -> 353 | DX17: =330+23 -> 353 | DY17: =330+23 -> 353 | DZ17: 250 | EA17: 200 | EB17: 450 | EC17: 500 | ED17: 500 | EE17: 300 | EF17: 200 | EG17: 200 | EH17: 200 | EI17: 200 | EM17: Assumed the Same Interest rate 3.5% | EP17: Interest rate charged by banks
B18: Freight China-Buenaventura (Regular) | C18: Freight China-Buenaventura (reg) | D18: 90 | E18: 90 | F18: 90 | G18: 90 | H18: 90 | I18: 90 | J18: 90 | K18: 90 | L18: 90 | M18: 90 | N18: 90 | O18: 90 | P18: 90 | Q18: 90 | R18: 90 | S18: 90 | T18: 90 | U18: 91 | V18: =+U18*(1+1.9%) -> 92.729 | W18: =+V18*(1+1.9%) -> 94.490851 | X18: =+W18*(1+1.9%) -> 96.286177 | Y18: =+X18 -> 96.286177 | Z18: =+Y18 -> 96.286177 | AA18: =+Z18 -> 96.286177 | AB18: =+AA18 -> 96.286177 | AC18: =+AB18 -> 96.286177 | AD18: =+AC18 -> 96.286177 | AE18: =+AD18 -> 96.286177 | AF18: =+AE18 -> 96.286177 | ... AP18: =+AO18 -> 96.286177 | AQ18: 96.286177 | AR18: 96.286177 | AS18: 96.286177 | AT18: 96.286177 | AU18: 96.286177 | AV18: 96.286177 | AW18: 96.286177 | AX18: 97.286177 | AY18: 97.286177 | AZ18: 97.286177 | BA18: 97.286177 | BB18: 97.286177 | BC18: 97.286177 | BD18: 97.286177 | BE18: 97.286177 | BF18: 97.286177 | BG18: 97.286177 | BH18: 97.286177 | BI18: 97.286177 | BJ18: 97.286177 | BK18: 97.286177 | BL18: 97.286177 | BM18: 97.286177 | BN18: 97.286177 | BO18: 97.286177 | BP18: 97.286177 | BQ18: 97.286177 | BR18: 97.286177 | BS18: 97.286177 | BT18: 97.286177 | BU18: 97.286177 | BV18: 97.286177 | BW18: 97.286177 | BX18: 97.286177 | BY18: 97.286177 | BZ18: 97.286177 | CA18: 97.286177 | CB18: 97.286177 | CC18: 97.286177 | CD18: 97.286177 | CE18: 97.286177 | CF18: 97.286177 | CG18: 97.286177 | CH18: 97.286177 | CI18: 97.286177 | CJ18: 97.286177 | CK18: 97.286177 | CL18: 97.286177 | CM18: 97.286177 | CN18: 97.286177 | CO18: 97.286177 | CP18: 97.286177 | CQ18: 97.286177 | CR18: 97.286177 | CS18: 97.286177 | CT18: 97.286177 | CU18: 97.286177 | CV18: 97 | CZ18: Consumo TON | DA18: 338.98 | DB18: 300.18 | DC18: 303 | DD18: 299.74348 | DE18: 300 | DF18: 313 | DG18: 355.19473 | DH18: 347 | DI18: 278.22123 | DJ18: 244 | DK18: 284.3 | DL18: 272 | DM18: 300.02 | DN18: 370.69216 | DO18: 397.35 | DP18: 421.54128 | DQ18: 397.35 | DR18: 353 | DS18: 320 | DT18: 309.39819 | DU18: 310 | DV18: 265.94053 | DW18: 328.29 | DX18: 338 | DY18: 371 | DZ18: 350 | EA18: 349 | EB18: 349 | EC18: 300 | ED18: 300 | EE18: 349 | EF18: 349 | EG18: 349 | EH18: 349 | EI18: 349 | EM18: 97 Index remains the same
B19: Freight China-Buenaventura (Incremental) | C19: Freight China-Buenaventura (Incr) | AQ19: =+Drewry!B3-'Fórmula Apr (2)'!AQ18 -> 253.71382 | AR19: =+Drewry!C3-'Fórmula Apr (2)'!AR18 -> 290.07746 | AS19: =+Drewry!D3-'Fórmula Apr (2)'!AS18 -> 398.71382 | AT19: =+Drewry!E3-'Fórmula Apr (2)'!AT18 -> 442.35019 | AU19: =+Drewry!F3-'Fórmula Apr (2)'!AU18 -> 480.98655 | AV19: 480.98655 | AW19: 480.98655 | AX19: =+Drewry!I3-'Fórmula Apr (2)'!AX18 -> 479.98655 | AY19: 480 | AZ19: 480 | BA19: 452 | BB19: 383 | BC19: =+Drewry!N3-'Fórmula Apr (2)'!BC18 -> 383.62291 | BD19: =+Drewry!O3-'Fórmula Apr (2)'!BD18 -> 399.07746 | BE19: =+Drewry!P3-'Fórmula Apr (2)'!BE18 -> 399.07746 | BF19: =+Drewry!Q3-'Fórmula Apr (2)'!BF18 -> 386.35019 | BG19: =+Drewry!R3-'Fórmula Apr (2)'!BG18 -> 309.532 | BH19: =+Drewry!S3-'Fórmula Apr (2)'!BH18 -> 178.62291 | BI19: =+Drewry!T3-'Fórmula Apr (2)'!BI18 -> 123.16837 | BJ19: =+Drewry!U3-'Fórmula Apr (2)'!BJ18 -> 123.16837 | BK19: =+IF(Drewry!V3-'Fórmula Apr (2)'!BK18<0,0,Drewry!V3-'Fórmula Apr (2)'!BK18) -> 24.98655 | BL19: =+IF(Drewry!W3-'Fórmula Apr (2)'!BL18<0,0,Drewry!W3-'Fórmula Apr (2)'!BL18) -> 16.804732 | BM19: =+IF(Drewry!X3-'Fórmula Apr (2)'!BM18<0,0,Drewry!X3-'Fórmula Apr (2)'!BM18) -> 0 | BN19: =+IF(Drewry!Y3-'Fórmula Apr (2)'!BN18<0,0,Drewry!Y3-'Fórmula Apr (2)'!BN18) -> 25.441096 | BO19: =+IF(Drewry!Z3-'Fórmula Apr (2)'!BO18<0,0,Drewry!Z3-'Fórmula Apr (2)'!BO18) -> 46.032005 | BP19: =+IF(Drewry!AA3-'Fórmula Apr (2)'!BP18<0,0,Drewry!AA3-'Fórmula Apr (2)'!BP18) -> 33.304732 | BQ19: =+IF(Drewry!AB3-'Fórmula Apr (2)'!BQ18<0,0,Drewry!AB3-'Fórmula Apr (2)'!BQ18) -> 26.441096 | BR19: =+IF(Drewry!AC3-'Fórmula Apr (2)'!BR18<0,0,Drewry!AC3-'Fórmula Apr (2)'!BR18) -> 55.850186 | ... BV19: =+IF(Drewry!AG3-'Fórmula Apr (2)'!BV18<0,0,Drewry!AG3-'Fórmula Apr (2)'!BV18) -> 65.622914 | BW19: =+IF(Drewry!AG3-'Fórmula Apr (2)'!BW18<0,0,Drewry!AG3-'Fórmula Apr (2)'!BW18) -> 65.622914 | BX19: =+IF(Drewry!AI3-'Fórmula Apr (2)'!BX18<0,0,Drewry!AI3-'Fórmula Apr (2)'!BX18) -> 68.577459 | BY19: =+IF(Drewry!AI3-'Fórmula Apr (2)'!BY18<0,0,Drewry!AI3-'Fórmula Apr (2)'!BY18) -> 68.577459 | BZ19: =+IF(Drewry!AK3-'Fórmula Apr (2)'!BZ18<0,0,Drewry!AK3-'Fórmula Apr (2)'!BZ18) -> 177.66837 | CA19: =+IF(Drewry!AL3-'Fórmula Apr (2)'!CA18<0,0,Drewry!AL3-'Fórmula Apr (2)'!CA18) -> 292.9411 | CB19: =+IF(Drewry!AM3-'Fórmula Apr (2)'!CB18<0,0,Drewry!AM3-'Fórmula Apr (2)'!CB18) -> 323.48655 | CC19: =+IF(Drewry!AN3-'Fórmula Apr (2)'!CC18<0,0,Drewry!AN3-'Fórmula Apr (2)'!CC18) -> 224.80473 | CD19: =+IF(Drewry!AO3-'Fórmula Apr (2)'!CD18<0,0,Drewry!AO3-'Fórmula Apr (2)'!CD18) -> 245.25928 | CE19: =+IF(Drewry!AP3-'Fórmula Apr (2)'!CE18<0,0,Drewry!AP3-'Fórmula Apr (2)'!CE18) -> 168.57746 | CF19: =+IF(Drewry!AQ3-'Fórmula Apr (2)'!CF18<0,0,Drewry!AQ3-'Fórmula Apr (2)'!CF18) -> 163.71382 | CG19: =+IF(Drewry!AR3-'Fórmula Apr (2)'!CG18<0,0,Drewry!AR3-'Fórmula Apr (2)'!CG18) -> 116.35019 | ... CU19: =+IF(Drewry!BF3-'Fórmula Apr (2)'!CU18<0,0,Drewry!BF3-'Fórmula Apr (2)'!CU18) -> 6.3047319 | CV19: =Drewry!BG3-'Fórmula Apr (2)'!CV18 -> 37.227273 | CZ19: Inv Final TON | DA19: 455.56748 | DB19: 551.38748 | DC19: 361.38748 | DD19: 321.644 | DE19: 392.25652 | DF19: 392.25652 | DG19: 350.06179 | DH19: =+(DH16+DH17-DH18) -> 316.06179 | DI19: =+(DI16+DI17-DI18) -> 350.84056 | DJ19: =+(DJ16+DJ17-DJ18) -> 419.84056 | DK19: =+(DK16+DK17-DK18) -> 379.54056 | DL19: =+(DL16+DL17-DL18) -> 307.54056 | DM19: =+(DM16+DM17-DM18) -> 307.52056 | DN19: =+(DN16+DN17-DN18) -> 236.82841 | DO19: =+(DO16+DO17-DO18) -> 139.47841 | ... EI19: =+(EI16+EI17-EI18) -> 155.9584 | EM19: Need Drewery Index
B20: Sub Total (with Incremental Freight) | C20: Sub total (con flete Inc) | D20: =SUM(D16:D18) -> 1454.4342 | E20: =SUM(E16:E18) -> 1403.1397 | F20: =SUM(F16:F18) -> 1402.5037 | G20: =SUM(G16:G18) -> 1398.5232 | H20: =SUM(H16:H18) -> 1454.4342 | I20: =SUM(I16:I18) -> 1389.0337 | J20: =SUM(J16:J18) -> 1244.1267 | K20: =SUM(K16:K18) -> 1185.2051 | ... AP20: =SUM(AP16:AP18) -> 1100.4172 | AQ20: =SUM(AQ16:AQ19) -> 1307.03 | AR20: =SUM(AR16:AR19) -> 1330.8936 | AS20: =SUM(AS16:AS19) -> 1480.2534 | AT20: =SUM(AT16:AT19) -> 1530.1398 | AU20: =SUM(AU16:AU19) -> 1555.342 | AV20: 1707.163 | AW20: 1721.7261 | AX20: =SUM(AX16:AX19) -> 1630.7754 | AY20: 1741 | AZ20: 1736 | BA20: 1709 | BB20: 1701 | BC20: =SUM(BC16:BC19) -> 1729.1533 | BD20: =SUM(BD16:BD19) -> 1763.8511 | BE20: =SUM(BE16:BE19) -> 1650.9575 | BF20: =SUM(BF16:BF19) -> 1608.7239 | BG20: =SUM(BG16:BG19) -> 1482.3865 | BH20: =SUM(BH16:BH19) -> 1277.2036 | BI20: =SUM(BI16:BI19) -> 1158.9897 | BJ20: =SUM(BJ16:BJ19) -> 1151.1468 | ... CV20: =SUM(CV16:CV19) -> 1367.9443 | EM20: formulae
B21: Sub Total (with Regular Freight) | C21: Sub total (con flete reg) | AQ21: =+SUM(AQ16:AQ18) -> 1053.3162 | AR21: =+SUM(AR16:AR18) -> 1040.8162 | AS21: =+SUM(AS16:AS18) -> 1081.5396 | AT21: =+SUM(AT16:AT18) -> 1087.7896 | AU21: =+SUM(AU16:AU18) -> 1074.3554 | AV21: 1226.1765 | AW21: 1240.7396 | AX21: =+SUM(AX16:AX18) -> 1150.7889 | AY21: 1261 | AZ21: 1256 | BA21: 1257 | BB21: 1317 | BC21: =+SUM(BC16:BC18) -> 1345.5304 | BD21: =+SUM(BD16:BD18) -> 1364.7736 | BE21: =+SUM(BE16:BE18) -> 1251.88 | BF21: =+SUM(BF16:BF18) -> 1222.3737 | BG21: =+SUM(BG16:BG18) -> 1172.8545 | BH21: =+SUM(BH16:BH18) -> 1098.5807 | BI21: =+SUM(BI16:BI18) -> 1035.8214 | BJ21: =+SUM(BJ16:BJ18) -> 1027.9785 | ... CV21: =+SUM(CV16:CV18) -> 1330.717 | CZ21: Precio Inv Inical | DA21: 1258.4919 | DB21: 1267.0143 | DC21: 1304.1208 | DD21: 1298.9693 | DE21: 1254.8429 | DF21: 1215.9045 | DG21: 1220.6547 | DH21: =+DG24 -> 1226.1867 | DI21: =+DH24 -> 1209.0552 | DJ21: =+DI24 -> 1194.1872 | DK21: =+DI24 -> 1194.1872 | DL21: =+DJ24 -> 1203.3754 | DM21: =+DL24 -> 1225.5446 | DN21: =+DM24 -> 1246.3188 | DO21: =+DN24 -> 1317.0024 | DP21: =+DO24 -> 1419.7187 | DQ21: =+DP24 -> 1509.9821 | DR21: =+DQ24 -> 1468.9302 | DS21: =+DR24 -> 1441.3902 | DT21: =+DS24 -> 1363.6378 | ... EI21: =+EH24 -> 1137.1396 | EM21: formulae
B22: Duty 5% (Change According to Regulation) | C22: Duty 5% (Cambio de acuerdo a la regulación) | D22: =+D20*0.1 -> 145.44342 | E22: =+E20*0.1 -> 140.31397 | F22: =+F20*0.1 -> 140.25037 | G22: =+G20*0.1 -> 139.85232 | H22: =+H20*0.1 -> 145.44342 | I22: =+I20*0.1 -> 138.90337 | J22: =+J20*0.1 -> 124.41267 | K22: =+K20*0.1 -> 118.52051 | ... AS22: =+AS20*0.1 -> 148.02534 | AT22: =+AT20*0.05 -> 76.506988 | AU22: =+AU20*0.05 -> 77.767099 | AV22: 85.358152 | AW22: 86.086307 | AX22: =+AX20*0.05 -> 81.538772 | AY22: 87.033091 | AZ22: =+AZ20*0.05 -> 86.8 | BA22: =+BA20*0.05 -> 85.45 | BB22: =+BB20*0.05 -> 85.05 | BC22: =+BC20*0.05 -> 86.457665 | BD22: =+BD20*0.05 -> 88.192553 | BE22: =+BE20*0.05 -> 82.547873 | BF22: =+BF20*0.05 -> 80.436195 | BG22: =+BG20*0.05 -> 74.119323 | ... CV22: =+CV20*0.05 -> 68.397214 | CZ22: Precio Ingreso | DA22: 1272.9919 | DB22: 1346.809 | DC22: 1273.8321 | DD22: 1193.5092 | DE22: 1182.1111 | DF22: 1226.6076 | DG22: 1233.1194 | DH22: =+BT26 -> 1189.8952 | DI22: =+BU26 -> 1179.1737 | DJ22: =+BV26 -> 1213.6744 | DK22: =+BW26 -> 1244.3742 | DL22: =+BX26 -> 1267.6152 | DM22: =+BY26 -> 1267.6152 | DN22: =+BZ26 -> 1389.4579 | DO22: =+CA26 -> 1500.8057 | ... EI22: =+CU26 -> 1099.8627 | EM22: Duty 5% is it going to vary ?
B23: Landed Factor 8% | C23: Landed factor 8% | D23: =+D20*8% -> 116.35474 | E23: =+E20*8% -> 112.25118 | F23: =+F20*8% -> 112.20029 | G23: =+G20*8% -> 111.88186 | H23: =+H20*8% -> 116.35474 | I23: =+I20*8% -> 111.1227 | J23: =+J20*8% -> 99.530137 | K23: =+K20*8% -> 94.816411 | ... AP23: =+AP20*8% -> 88.03338 | AQ23: =+AQ21*8% -> 84.265293 | AR23: =+AR21*8% -> 83.265293 | AS23: =+AS21*8% -> 86.523165 | AT23: =+AT21*8% -> 87.023165 | AU23: =+AU21*8% -> 85.948434 | AV23: 98.09412 | AW23: 99.259168 | AX23: =+AX21*8% -> 92.063111 | AY23: 100.85039 | AZ23: =+AZ21*8% -> 100.48 | BA23: =+BA21*8% -> 100.56 | BB23: =+BB21*8% -> 105.36 | BC23: =+BC21*8% -> 107.64243 | BD23: =+BD21*8% -> 109.18189 | BE23: =+BE21*8% -> 100.1504 | BF23: =+BF21*8% -> 97.789896 | BG23: =+BG21*8% -> 93.828357 | ... CV23: =+CV21*8% -> 106.45736 | CZ23: Precio Consumo | DA23: 1267.0143 | DB23: 1304.1208 | DC23: 1298.9693 | DD23: 1254.8429 | DE23: 1215.9045 | DF23: 1220.6547 | DG23: 1226.1867 | DH23: =+SUMPRODUCT(DH16:DH17,DH21:DH22)/SUM(DH16:DH17) -> 1209.0552 | DI23: =+SUMPRODUCT(DI16:DI17,DI21:DI22)/SUM(DI16:DI17) -> 1194.1872 | DJ23: =+SUMPRODUCT(DJ16:DJ17,DJ21:DJ22)/SUM(DJ16:DJ17) -> 1203.3754 | DK23: =+SUMPRODUCT(DK16:DK17,DK21:DK22)/SUM(DK16:DK17) -> 1217.8503 | DL23: =+SUMPRODUCT(DL16:DL17,DL21:DL22)/SUM(DL16:DL17) -> 1225.5446 | DM23: =+SUMPRODUCT(DM16:DM17,DM21:DM22)/SUM(DM16:DM17) -> 1246.3188 | DN23: =+SUMPRODUCT(DN16:DN17,DN21:DN22)/SUM(DN16:DN17) -> 1317.0024 | DO23: =+SUMPRODUCT(DO16:DO17,DO21:DO22)/SUM(DO16:DO17) -> 1419.7187 | ... EI23: =+SUMPRODUCT(EI16:EI17,EI21:EI22)/SUM(EI16:EI17) -> 1122.3753 | EM23: Landed Factor 8% is it going to vary ?
B24: ZF Legislation Change | C24: Cambio legislacion ZF | BV24: =+('Cambio en Condiciones ZF'!$H$23/'PCR Enka'!$CD$22)/22 -> 18.958371 | BW24: =+('Cambio en Condiciones ZF'!$H$23/'PCR Enka'!$CD$22)/22 -> 18.958371 | BX24: =+('Cambio en Condiciones ZF'!$H$23/'PCR Enka'!$CD$22)/22 -> 18.958371 | BY24: =+('Cambio en Condiciones ZF'!$H$23/'PCR Enka'!$CD$22)/22 -> 18.958371 | BZ24: =+('Cambio en Condiciones ZF'!$H$23/'PCR Enka'!$CD$22)/22 -> 18.958371 | CA24: =+('Cambio en Condiciones ZF'!$H$23/'PCR Enka'!$CD$22)/22 -> 18.958371 | CB24: =+('Cambio en Condiciones ZF'!$H$23/'PCR Enka'!$CD$22)/22 -> 18.958371 | CC24: =+('Cambio en Condiciones ZF'!$H$23/'PCR Enka'!$CD$22)/22 -> 18.958371 | ... CV24: =+('Cambio en Condiciones ZF'!$H$23/'PCR Enka'!$CD$22)/22 -> 18.958371 | CZ24: Precio Inv Final | DA24: 1267.0143 | DB24: 1304.1208 | DC24: 1298.9693 | DD24: 1254.8429 | DE24: 1215.9045 | DF24: 1220.6547 | DG24: 1226.1867 | DH24: =+(SUMPRODUCT(DH16:DH17,DH21:DH22)-(DH18*DH23))/DH19 -> 1209.0552 | DI24: =+(SUMPRODUCT(DI16:DI17,DI21:DI22)-(DI18*DI23))/DI19 -> 1194.1872 | DJ24: =+(SUMPRODUCT(DJ16:DJ17,DJ21:DJ22)-(DJ18*DJ23))/DJ19 -> 1203.3754 | DK24: =+(SUMPRODUCT(DK16:DK17,DK21:DK22)-(DK18*DK23))/DK19 -> 1217.8503 | DL24: =+(SUMPRODUCT(DL16:DL17,DL21:DL22)-(DL18*DL23))/DL19 -> 1225.5446 | DM24: =+(SUMPRODUCT(DM16:DM17,DM21:DM22)-(DM18*DM23))/DM19 -> 1246.3188 | DN24: =+(SUMPRODUCT(DN16:DN17,DN21:DN22)-(DN18*DN23))/DN19 -> 1317.0024 | DO24: =+(SUMPRODUCT(DO16:DO17,DO21:DO22)-(DO18*DO23))/DO19 -> 1419.7187 | ... EI24: =+(SUMPRODUCT(EI16:EI17,EI21:EI22)-(EI18*EI23))/EI19 -> 1122.3753 | EM24: Need more understanding on this ?
B25: Sur Charge Alpek Br | C25: Sur Charge Alpek Br | CL25: 135 | CM25: 135 | CN25: 135 | CO25: 0 | CP25: 0 | CQ25: 0 | CR25: 0 | CS25: 0 | CT25: 0 | CU25: 0 | CV25: 0
B26: Total Resin Price ABI VIRGIN Formula | C26: Total resin price ABI Fórmula VIRGEN | D26: =+D20+D22+D23 -> 1716.2324 | E26: =+E20+E22+E23 -> 1655.7049 | F26: =+F20+F22+F23 -> 1654.9543 | G26: =+G20+G22+G23 -> 1650.2574 | H26: =+H20+H22+H23 -> 1716.2324 | I26: =+I20+I22+I23 -> 1639.0598 | J26: =+J20+J22+J23 -> 1468.0695 | K26: =+K20+K22+K23 -> 1398.5421 | ... AU26: =+AU20+AU22+AU23 -> 1719.0575 | AV26: 1890.6153 | AW26: 1907.0716 | AX26: =+AX20+AX22+AX23 -> 1804.3773 | AY26: 1928.5453 | AZ26: =+AZ20+AZ22+AZ23 -> 1923.28 | BA26: =+BA20+BA22+BA23 -> 1895.01 | BB26: =+BB20+BB22+BB23 -> 1891.41 | BC26: =+BC20+BC22+BC23 -> 1923.2534 | BD26: =+BD20+BD22+BD23 -> 1961.2255 | BE26: =+BE20+BE22+BE23 -> 1833.6557 | BF26: =+BF20+BF22+BF23 -> 1786.95 | BG26: =+BG20+BG22+BG23 -> 1650.3341 | ... BU26: =+BU20+BU22+BU23 -> 1179.1737 | BV26: =+BV20+BV22+BV23+BV24 -> 1213.6744 | BW26: =+BW20+BW22+BW23+BW24 -> 1244.3742 | BX26: =+BX20+BX22+BX23+BX24 -> 1267.6152 | BY26: =+BY20+BY22+BY23+BY24 -> 1267.6152 | BZ26: =+BZ20+BZ22+BZ23+BZ24 -> 1389.4579 | CA26: =+CA20+CA22+CA23+CA24 -> 1500.8057 | CB26: =+CB20+CB22+CB23+CB24 -> 1535.1617 | CC26: =+CC20+CC22+CC23+CC24 -> 1439.1078 | ... CK26: =+CK20+CK22+CK23+CK24 -> 1128.7642 | CL26: =+CL20+CL22+CL23+CL24+CL25 -> 1192.9767 | CM26: =+CM20+CM22+CM23+CM24+CM25 -> 1229.9559 | CN26: =+CN20+CN22+CN23+CN24+CN25 -> 1481.7339 | CO26: =+CO20+CO22+CO23+CO24+CO25 -> 1224.477 | CP26: =+CP20+CP22+CP23+CP24+CP25 -> 1204.7186 | CQ26: =+CQ20+CQ22+CQ23+CQ24+CQ25 -> 1176.8598 | CR26: =+CR20+CR22+CR23+CR24+CR25 -> 1095.0968 | CS26: =+CS20+CS22+CS23+CS24+CS25 -> 1079.0637 | ... CV26: =+CV20+CV22+CV23+CV24+CV25 -> 1561.7572 | EM26: formulae
B27: Final Price with Resin Freight Adjustment | C27: Precio Final con ajuste flete Resina | AK27: =+AK26+#REF! -> #REF! | AL27: =+AL26+#REF! -> #REF! | AM27: =+AM26+#REF! -> #REF! | AN27: =+AN26+#REF! -> #REF! | AO27: =+AO26+#REF! -> #REF! | AP27: =+AP26+#REF! -> #REF! | AQ27: =+AQ26+#REF! -> #REF! | AR27: =+AR26+#REF! -> #REF! | AS27: =+AS26+#REF! -> #REF! | AT27: =+AT26 -> 1693.6699 | AU27: =+AU26 -> 1719.0575 | AV27: 1890.6153 | AW27: 1907.0716 | AX27: =+AX26 -> 1804.3773 | AY27: 1928.5453 | AZ27: =+AZ26 -> 1923.28 | BA27: =+BA26 -> 1895.01 | BB27: =+BB26 -> 1891.41 | BC27: =+BC26 -> 1923.2534 | BD27: =+BD26 -> 1961.2255 | BE27: =+BE26 -> 1833.6557 | BF27: =+BF26 -> 1786.95 | BG27: =+BG26 -> 1650.3341 | ... CV27: =+CV26 -> 1561.7572 | CZ27: 2.which pricing is used as final (do we need to calculate the consumption values as well) ? Assuming its vpet (1100) | EM27: formulae
B28: Final Price FIFO | C28: Precio final FIFO | AK28: =+#REF! -> #REF! | AL28: =+#REF! -> #REF! | AM28: =+#REF! -> #REF! | AN28: =+#REF! -> #REF! | AO28: =+#REF! -> #REF! | AP28: =+#REF! -> #REF! | AQ28: =+#REF! -> #REF! | AR28: =+#REF! -> #REF! | ... AU28: =+#REF! -> #REF! | AV28: 1780.8032 | AW28: 1844.8576 | AX28: =+#REF! -> #REF! | AY28: 1880.1282 | AZ28: =+#REF! -> #REF! | BA28: =+#REF! -> #REF! | BB28: =+#REF! -> #REF! | BC28: =+#REF! -> #REF! | BD28: =+#REF! -> #REF! | BE28: =+#REF! -> #REF! | BF28: =+#REF! -> #REF! | BG28: =+#REF! -> #REF! | ... BL28: =+#REF! -> #REF! | BM28: =+DA24 -> 1267.0143 | BN28: =+DB24 -> 1304.1208 | BO28: =+DC24 -> 1298.9693 | BP28: =+DD24 -> 1254.8429 | BQ28: =+DE24 -> 1215.9045 | BR28: =+DF24 -> 1220.6547 | BS28: =+DG24 -> 1226.1867 | BT28: =+DH24 -> 1209.0552 | ... BV28: =+DJ24 -> 1203.3754 | BW28: =+DJ24 -> 1203.3754 | BX28: =+DL24 -> 1225.5446 | BY28: =+DL24 -> 1225.5446 | BZ28: =+DN24 -> 1317.0024 | CA28: =+DO24 -> 1419.7187 | CB28: =+DP24 -> 1509.9821 | CC28: =+DQ24 -> 1468.9302 | CD28: =+DR24 -> 1441.3902 | CE28: =+DS24 -> 1363.6378 | CF28: =+DT24 -> 1331.6467 | CG28: =+DU24 -> 1304.2778 | ... CU28: =+EI24 -> 1122.3753 | CZ28: 3. do we need the wighted avarge price calculation ?
C29: Ajuste
C30: Total | BC30: =+BC28+BC29 -> #REF! | BD30: =+BD28+BD29 -> #REF! | BE30: =+BE28+BE29 -> #REF! | BF30: =+BF28+BF29 -> #REF! | BG30: =+BG28+BG29 -> #REF! | BH30: =+BH28+BH29 -> #REF! | BI30: =+BI28+BI29 -> #REF! | BJ30: =+BJ28+BJ29 -> #REF! | ... CU30: =+CU28+CU29 -> 1122.3753 | CZ30: 5. In the Freight calculation - Regulaar of 97 $ is constant and the remaining is Incremental based on the Drewery Index ? How will handle future calculation here?
CZ31: translate the cam something sheet
C32: Resin PCR % Enkador | D32: =+D26*(1-5%) -> 1630.4208 | E32: =+E26*(1-5%) -> 1572.9196 | F32: =+F26*(1-5%) -> 1572.2066 | G32: =+G26*(1-5%) -> 1567.7445 | H32: =+H26*(1-5%) -> 1630.4208 | I32: =+I26*(1-5%) -> 1557.1068 | J32: =+J26*(1-5%) -> 1394.666 | K32: =+K26*(1-5%) -> 1328.615 | ... X32: =+X26*(1-5%) -> 1092.8639 | Y32: =1.33255813953488*1000 -> 1332.5581 | Z32: =+' PCR Enkador'!H55 -> 1386.3641 | AA32: =+Z32 -> 1386.3641 | AB32: =+AA32 -> 1386.3641 | AC32: =+AB32 -> 1386.3641 | AD32: =+AC32 -> 1386.3641 | AE32: =+' PCR Enkador'!H69 -> 1412.3596 | AF32: =+' PCR Enkador'!H69 -> 1412.3596 | AG32: =+' PCR Enkador'!H69 -> 1412.3596 | AH32: =+AG32 -> 1412.3596 | AI32: =+AH32 -> 1412.3596 | AJ32: =+' PCR Enkador'!H88 -> 1394.54 | AK32: =+' PCR Enkador'!H88 -> 1394.54 | AL32: =+AK32 -> 1394.54 | AM32: =+AL32 -> 1394.54 | AN32: =+' PCR Enkador'!H104 -> 1485 | AO32: =+AN32 -> 1485 | AP32: =+AO32 -> 1485 | AQ32: =+' PCR Enkador'!H124 -> 1514.8753 | AR32: =+AQ32 -> 1514.8753 | AS32: =+AR32 -> 1514.8753 | AT32: =+' PCR Enkador'!E139 -> 1748.1782 | AU32: =+' PCR Enkador'!F139 -> 2005.359 | AV32: 1942.1299 | AW32: 1863.1434 | AX32: =+' PCR Enkador'!I139 -> 2055.0951 | AY32: 2104.5194 | AZ32: =+' PCR Enkador'!K139 -> 2174.9407 | BA32: =+' PCR Enkador'!L139 -> 2224.6328 | BB32: =+' PCR Enkador'!L139 -> 2224.6328 | BC32: =+' PCR Enkador'!N139 -> 2351.9981 | BD32: =+' PCR Enkador'!O139 -> 2084.088 | BE32: =+' PCR Enkador'!P139 -> 2039.0612 | BF32: =+' PCR Enkador'!Q139 -> 1827.4006 | BG32: =+' PCR Enkador'!R139 -> 1572.153 | BH32: =+' PCR Enkador'!S139 -> 1511.4316 | BI32: =+' PCR Enkador'!T139 -> 1571.7048 | BJ32: =+' PCR Enkador'!U139 -> 1749.1772 | ... CJ32: =+' PCR Enkador'!AU139 -> 2426.0741 | CK32: =+FIFO!BH7 -> 2350.0219 | CL32: =+' PCR Enkador'!AW139 -> 2390.1839 | CM32: =+' PCR Enkador'!AX139 -> 2381.7182 | CN32: =+' PCR Enkador'!AY139 -> 2377.8054 | CO32: =+'PCR Aurora '!W21 -> 2309.209 | CP32: =+'PCR Aurora '!X21 -> 2315.1788 | CQ32: =+'PCR Aurora '!Y21 -> 2287.8265 | CR32: =+'PCR Aurora '!Z21 -> 2304.9182 | CS32: =+' PCR Enkador'!BD139 -> 2246.5395 | CT32: =+' PCR Enkador'!BE139 -> 2284.7438 | CU32: =+' PCR Enkador'!BG139 -> 0
C33: Resin PCR % Enkador FIFO | AQ33: =+AQ32 -> 1514.8753 | AR33: =+AR32 -> 1514.8753 | AS33: =+AS32 -> 1514.8753 | AT33: =+AT32 -> 1748.1782 | AU33: =+AU32 -> 2005.359 | AV33: 1942.1299 | AW33: 1863.1434 | AX33: =+AX32 -> 2055.0951 | AY33: 2104.5194 | AZ33: =+AZ32 -> 2174.9407 | BA33: =+BA32 -> 2224.6328 | BB33: =+BB32 -> 2224.6328 | BC33: =+BC32 -> 2351.9981 | BD33: =+BD32 -> 2084.088 | BE33: =+BE32 -> 2039.0612 | BF33: =+BF32 -> 1827.4006 | BG33: =+BG32 -> 1572.153 | ... BK33: =+BK32 -> 1692.4082 | BL33: =+FIFO!J9 -> 1690.2249 | BM33: =+FIFO!L9 -> 1699.0065 | BN33: =+FIFO!N9 -> 1698.7785 | BO33: =+FIFO!P8 -> 1730.0097 | BP33: =+FIFO!R8 -> 1773.5614 | BQ33: =+FIFO!T8 -> 1784.8755 | BR33: =+FIFO!V8 -> 1784.8628 | BS33: =+FIFO!X8 -> 1813.0215 | BT33: =+FIFO!Z8 -> 1904.7514 | BU33: =+FIFO!AB9 -> 1962.2861 | BV33: =+FIFO!AD8 -> 1845.712 | BW33: =+FIFO!AF8 -> 1890.2731 | BX33: =+FIFO!AH8 -> 1917.1799 | BY33: =+FIFO!AJ7 -> 2006.62 | BZ33: =+FIFO!AL8 -> 1943.4781 | CA33: =+FIFO!AN8 -> 2034.9008 | CB33: =+FIFO!AP8 -> 2114.7268 | CC33: =+FIFO!AR8 -> 2187.7265 | CD33: =+FIFO!AT8 -> 2235.089 | CE33: =+FIFO!AV8 -> 2269.3398 | CF33: =+FIFO!AX8 -> 2218.3559 | CG33: =+FIFO!AZ8 -> 2236.8572 | CH33: =+FIFO!BB8 -> 2321.2754 | CI33: =+FIFO!BD8 -> 2410.4813 | CJ33: =+FIFO!BF8 -> 2410.8753 | CK33: =+FIFO!BH8 -> 2358.2488 | CL33: =+FIFO!#REF! -> #REF! | CM33: =+FIFO!CA8 -> 0 | CN33: =+FIFO!BN34 -> 2373.4672 | CO33: =+FIFO!BO34 -> 0 | CP33: =+FIFO!BP34 -> 2373.4672 | CQ33: =+FIFO!BR34 -> 2373.4672 | CR33: =+FIFO!CA34 -> 0 | CS33: =+FIFO!CB34 -> 0 | CT33: =+FIFO!CC34 -> 0 | CU33: =+FIFO!CD34 -> 0 | CY33: =+FIFO!BQ34 -> 0 | CZ33: 7. Enakador , Enka , Aurora what are these ? Will it always be enka in the legislation calculation?
C34: Resin PCR % Enka | Z34: =+'PCR Enka'!C26 -> 1070.2457 | AA34: =+'PCR Enka'!D26 -> 1103.3118 | AB34: =+'PCR Enka'!D26 -> 1103.3118 | AC34: =+'PCR Enka'!E26 -> 1149.9847 | AD34: =+'PCR Enka'!E26 -> 1149.9847 | AE34: =+'PCR Enka'!F26 -> 1163.7352 | AF34: =+'PCR Enka'!F26 -> 1163.7352 | AG34: 6 | AH34: =+'PCR Enka'!H26 -> 1125.2337 | AI34: =+'PCR Enka'!I26 -> 1153.6209 | AJ34: =+'PCR Enka'!J26 -> 1197.5282 | AK34: =+'PCR Enka'!K26 -> 1277.3813 | AL34: =+'PCR Enka'!L26 -> 1467.9415 | AM34: =+'PCR Enka'!M26 -> 1432.478 | AN34: =+'PCR Enka'!N26 -> 1415.0274 | AO34: =+'PCR Enka'!O26 -> 1623.5225 | ... AU34: =+'PCR Enka'!U26 -> 1905.3661 | AV34: 1842.137 | AW34: 1765.8142 | AX34: =+'PCR Enka'!X26 -> 1957.7659 | AY34: 2007.3086 | AZ34: =+'PCR Enka'!Z26 -> 2077.6143 | BA34: =+'PCR Enka'!AA26 -> 2127.3064 | BB34: =+'PCR Enka'!AA26 -> 2127.3064 | BC34: =+'PCR Enka'!AC26 -> 2251.8217 | BD34: =+'PCR Enka'!AD26 -> 1986.3646 | BE34: =+'PCR Enka'!AE26 -> 1941.3379 | BF34: =+'PCR Enka'!AF26 -> 1729.6772 | BG34: =+'PCR Enka'!AG26 -> 1474.4296 | BH34: =+'PCR Enka'!AH26 -> 1413.7082 | BI34: =+'PCR Enka'!AI26 -> 1472.9887 | BJ34: =+'PCR Enka'!AJ26 -> 1650.4611 | ... BT34: =+'PCR Enka'!AT26 -> 1819.4162 | BU34: =+' PCR Enkador'!AF134 -> 1891.8355 | BV34: =+' PCR Enkador'!AG134 -> 1664.6783 | BW34: =+' PCR Enkador'!AH134 -> 1838.384 | BX34: =+' PCR Enkador'!AI134 -> 1862.1217 | BY34: =+' PCR Enkador'!AI134 -> 1862.1217 | BZ34: =+' PCR Enkador'!AK134 -> 1939.5828 | CA34: =+' PCR Enkador'!AL134 -> 1970.9734 | CB34: =+' PCR Enkador'!AM134 -> 2046.3999 | CC34: =+' PCR Enkador'!AN134 -> 2115.9076 | CD34: =+' PCR Enkador'!AO134 -> 2145.6482 | CE34: =+' PCR Enkador'!AP134 -> 2183.3734 | CF34: =+' PCR Enkador'!AQ134 -> 2108.3299 | CG34: =+' PCR Enkador'!AR134 -> 2139.863 | ... CJ34: =+' PCR Enkador'!AU134 -> 2328.0642 | CK34: =+FIFO!BH20 -> 2252.012 | CL34: =+' PCR Enkador'!AW134 -> 2292.174 | CM34: =+'PCR Aurora '!U14 -> 2283.7083 | CN34: =+'PCR Enka'!DS26 -> 2279.7955 | CO34: =+'PCR Aurora '!W14 -> 2211.1991 | CP34: =+'PCR Aurora '!X14 -> 2217.1689 | CQ34: =+'PCR Aurora '!Y14 -> 2189.8166 | CR34: =+'PCR Aurora '!Z14 -> 2206.9083 | CS34: =+'PCR Aurora '!AA40 -> 1925.9158 | CT34: =+'PCR Enka'!EI26 -> 2187.0429 | CU34: =+'PCR Enka'!EK26 -> 0 | CZ34: 8. Are the pricing below Row # 30 are also considered for the calculation ?
C35: Resin PCR % Enka FIFO | BL35: =+FIFO!J22 -> 1541.7236 | BM35: =+FIFO!L22 -> 1572.2305 | BN35: =+FIFO!N22 -> 1582.7075 | BO35: =+FIFO!P21 -> 1624.5182 | BP35: =+FIFO!R21 -> 1640.1021 | BQ35: =+FIFO!T21 -> 1640.1021 | BR35: =+FIFO!V21 -> 1640.1021 | BS35: =+FIFO!X21 -> 1640.1021 | BT35: =+FIFO!Z21 -> 1640.1021 | BU35: =+FIFO!AB22 -> 1640.1021 | BV35: =+FIFO!AD21 -> 1640.1021 | BW35: =+FIFO!AF21 -> 1640.1021 | BX35: =+FIFO!AH21 -> 1640.1021 | BY35: =+FIFO!AJ21 -> 1640.1021 | BZ35: =+FIFO!AL21 -> 1640.1021 | CA35: =+FIFO!AN21 -> 1756.8307 | CB35: =+FIFO!AP21 -> 1848.502 | CC35: =+FIFO!AR21 -> 1924.5346 | CD35: =+FIFO!AT21 -> 1924.5346 | CE35: =+FIFO!AV21 -> 1924.5346 | CF35: =+FIFO!AX21 -> 1924.5346 | CG35: =+FIFO!AZ21 -> 1924.5346 | CH35: =+FIFO!BB21 -> 1924.5346 | CI35: =+FIFO!BD21 -> 2047.4442 | CJ35: =+FIFO!BF21 -> 2047.5847 | CK35: =+FIFO!BH21 -> 2095.2472 | CL35: =+FIFO!BJ21 -> 2103.5509 | CM35: =+FIFO!BL21 -> 2141.3654 | CN35: =+FIFO!BN21 -> 2141.3654 | CO35: =+FIFO!BP21 -> 2141.3654 | CP35: =+FIFO!BR21 -> 2141.3654 | CQ35: =+FIFO!BR21 -> 2141.3654 | CR35: =+FIFO!BV21 -> 2141.3654 | CS35: =+FIFO!BV21 -> 2141.3654 | CT35: =+FIFO!BZ21 -> 2141.3654 | CU35: =+FIFO!CA21 -> 0 | CZ35: 9. Need more undestanding on the Legilation charges calculation , it refers to 2 sheets
C36: Resin PCR % Aurora Clear. | Z36: =+'PCR Enka'!C28 -> 0 | AA36: =+'PCR Enka'!D28 -> 0 | AB36: =+'PCR Enka'!D28 -> 0 | AC36: =+'PCR Enka'!E28 -> 0 | AD36: =+'PCR Enka'!E28 -> 0 | AE36: =+'PCR Enka'!F28 -> 0 | AF36: =+'PCR Enka'!F28 -> 0 | AG36: 6 | AH36: =+'PCR Enka'!H28 -> 0 | AI36: =+'PCR Enka'!I28 -> 0 | AJ36: =+'PCR Enka'!J28 -> 0 | AK36: =+'PCR Enka'!K28 -> 0 | AL36: =+'PCR Enka'!L28 -> 0 | AM36: =+'PCR Enka'!M28 -> 0 | AN36: =+'PCR Enka'!N28 -> 0 | AO36: =+'PCR Enka'!O28 -> 0 | ... AU36: =+'PCR Enka'!U28 -> 0 | AV36: 1842.137 | AW36: 1765.8142 | AX36: =+'PCR Enka'!X28 -> 0 | AY36: 2007.3086 | AZ36: =+'PCR Enka'!Z28 -> 0 | BA36: =+'PCR Enka'!AA28 -> 0 | BB36: =+'PCR Enka'!AA28 -> 0 | BC36: =+'PCR Enka'!AC28 -> 0 | BD36: =+'PCR Enka'!AD28 -> 0 | BE36: =+'PCR Enka'!AE28 -> 0 | BF36: =+'PCR Enka'!AF28 -> 0 | BG36: =+'PCR Enka'!AG28 -> 0 | BH36: =+'PCR Enka'!AH28 -> 0 | BI36: =+'PCR Enka'!AI28 -> 0 | BJ36: =+'PCR Enka'!AJ28 -> 0 | ... BT36: =+'PCR Enka'!AT28 -> 0 | BU36: =+' PCR Enkador'!AF136 -> 94.4 | BV36: =+' PCR Enkador'!AG136 -> 94.4 | BW36: =+' PCR Enkador'!AH136 -> 94.4 | BX36: =+' PCR Enkador'!AI136 -> 94.4 | BY36: =+' PCR Enkador'!AI136 -> 94.4 | BZ36: =+' PCR Enkador'!AK136 -> 94.4 | CA36: =+' PCR Enkador'!AL136 -> 94.4 | CB36: =+' PCR Enkador'!AM136 -> 94.4 | CC36: =+' PCR Enkador'!AN136 -> 94.4 | CD36: =+' PCR Enkador'!AO136 -> 94.4 | CE36: =+' PCR Enkador'!AP136 -> 94.4 | CF36: =+' PCR Enkador'!AQ136 -> 94.4 | CG36: =+' PCR Enkador'!AR136 -> 94.4 | CK36: =+'PCR Aurora '!S40 -> 2305.7167 | CL36: =+'PCR Aurora '!T40 -> 2302.3702 | CM36: =+'PCR Aurora '!U40 -> 2271.7916 | CN36: =+'PCR Aurora '!V40 -> 2155.0837 | CO36: =+'PCR Aurora '!W40 -> 1974.3326 | CP36: =+'PCR Aurora '!X40 -> 1974.0609 | CQ36: =+'PCR Aurora '!Y40 -> 1958.5504 | CR36: =+'PCR Aurora '!Z40 -> 1951.0595 | ... CU36: =+'PCR Aurora '!AC40 -> 1982.7376 | CZ36: 12. What are the units , Price for metric ton ?
C37: Resin PCR % Aurora. FIFO | BL37: =+FIFO!J24 -> 1536.7815 | BM37: =+FIFO!L24 -> 1541.7236 | BN37: =+FIFO!N24 -> 1572.2305 | BO37: =+FIFO!P23 -> 0 | BP37: =+FIFO!R23 -> 0 | BQ37: =+FIFO!T23 -> 0 | BR37: =+FIFO!V23 -> 0 | BS37: =+FIFO!X23 -> 0 | BT37: =+FIFO!Z23 -> 0 | BU37: =+FIFO!AB24 -> 1640.1021 | BV37: =+FIFO!AD23 -> 0 | BW37: =+FIFO!AF23 -> 0 | BX37: =+FIFO!AH23 -> 0 | BY37: =+FIFO!AJ23 -> 0 | BZ37: =+FIFO!AL23 -> 0 | CA37: =+FIFO!AN23 -> 0 | CB37: =+FIFO!AP23 -> 0 | CC37: =+FIFO!AR23 -> 0 | CD37: =+FIFO!AT23 -> 0 | CE37: =+FIFO!AV23 -> 0 | CF37: =+FIFO!AX23 -> 0 | CG37: =+FIFO!AZ23 -> 0 | CK37: =+FIFO!BH23 -> 0 | CL37: =+FIFO!#REF! -> #REF! | CM37: =+FIFO!CA23 -> 0 | CN37: =+FIFO!CB23 -> 0 | CO37: =+FIFO!CC23 -> 0 | CP37: =+FIFO!CD23 -> 0 | CQ37: =+FIFO!CE23 -> 0 | CR37: =+FIFO!CF23 -> 0 | CS37: =+FIFO!CG23 -> 0 | CT37: =+FIFO!CH23 -> 0 | CU37: =+FIFO!CI23 -> 0 | CZ37: 13. What is finance here ? We are using SOFR rate % for the finance calculation
C38: Resin PCR % Aurora Ambar. | Z38: =+'PCR Enka'!C30 -> Fecha | AA38: =+'PCR Enka'!D30 -> TRM | AB38: =+'PCR Enka'!D30 -> TRM | AC38: =+'PCR Enka'!E30 -> Fecha | AD38: =+'PCR Enka'!E30 -> Fecha | AE38: =+'PCR Enka'!F30 -> TRM | AF38: =+'PCR Enka'!F30 -> TRM | AG38: 6 | AH38: =+'PCR Enka'!H30 -> TRM | AI38: =+'PCR Enka'!I30 -> Fecha | AJ38: =+'PCR Enka'!J30 -> TRM | AK38: =+'PCR Enka'!K30 -> Fecha | AL38: =+'PCR Enka'!L30 -> TRM | AM38: =+'PCR Enka'!M30 -> Fecha | AN38: =+'PCR Enka'!N30 -> TRM | AO38: =+'PCR Enka'!O30 -> Fecha | ... AU38: =+'PCR Enka'!U30 -> Fecha | AV38: 1842.137 | AW38: 1765.8142 | AX38: =+'PCR Enka'!X30 -> TRM | AY38: 2007.3086 | AZ38: =+'PCR Enka'!Z30 -> TRM | BA38: =+'PCR Enka'!AA30 -> Fecha | BB38: =+'PCR Enka'!AA30 -> Fecha | BC38: =+'PCR Enka'!AC30 -> Fecha | BD38: =+'PCR Enka'!AD30 -> TRM | BE38: =+'PCR Enka'!AE30 -> Fecha | BF38: =+'PCR Enka'!AF30 -> TRM | BG38: =+'PCR Enka'!AG30 -> Fecha | BH38: =+'PCR Enka'!AH30 -> TRM | BI38: =+'PCR Enka'!AI30 -> Fecha | BJ38: =+'PCR Enka'!AJ30 -> TRM | ... BT38: =+'PCR Enka'!AT30 -> TRM | BU38: =+' PCR Enkador'!AF138 -> 97.700897 | BV38: =+' PCR Enkador'!AG138 -> 97.700897 | BW38: =+' PCR Enkador'!AH138 -> 98.610694 | BX38: =+' PCR Enkador'!AI138 -> 98.610694 | BY38: =+' PCR Enkador'!AI138 -> 98.610694 | BZ38: =+' PCR Enkador'!AK138 -> 98.610694 | CA38: =+' PCR Enkador'!AL138 -> 98.610694 | CB38: =+' PCR Enkador'!AM138 -> 98.610694 | CC38: =+' PCR Enkador'!AN138 -> 98.610694 | CD38: =+' PCR Enkador'!AO138 -> 98.610694 | CE38: =+' PCR Enkador'!AP138 -> 98.610694 | CF38: =+' PCR Enkador'!AQ138 -> 98.610694 | CG38: =+' PCR Enkador'!AR138 -> 98.009902 | CK38: =+'PCR Aurora '!S42 -> 0 | CL38: =+'PCR Aurora '!T42 -> 0 | CM38: =+'PCR Aurora '!U42 -> 0 | CN38: =+'PCR Aurora '!V42 -> 0 | CO38: =+'PCR Aurora '!W42 -> 0 | CP38: =+'PCR Aurora '!X42 -> 0 | CQ38: =+'PCR Aurora '!Y42 -> 0 | CR38: =+'PCR Aurora '!Z42 -> 0 | ... CU38: =+'PCR Aurora '!AC42 -> 1882.7376
C39: Resin PCR % Aurora. FIFO | BL39: =+FIFO!J26 -> 1541.7236 | BM39: =+FIFO!L26 -> 1572.2305 | BN39: =+FIFO!N26 -> 1582.7075 | BO39: =+FIFO!P25 -> 1688.6913 | BP39: =+FIFO!R25 -> 1735.1046 | BQ39: =+FIFO!T25 -> 1696.6764 | BR39: =+FIFO!V25 -> 1687.1596 | BS39: =+FIFO!X25 -> 1717.7417 | BT39: =+FIFO!Z25 -> 1819.4162 | BU39: =+FIFO!AB26 -> 1640.1021 | BV39: =+FIFO!AD25 -> 0 | BW39: =+FIFO!AF25 -> 0 | BX39: =+FIFO!AH25 -> 0 | BY39: =+FIFO!AJ25 -> 0 | BZ39: =+FIFO!AL25 -> 0 | CA39: =+FIFO!AN25 -> 1970.9734 | CB39: =+FIFO!AP25 -> 2046.3999 | CC39: =+FIFO!AR25 -> 2115.9076 | CD39: =+FIFO!AT25 -> 2145.6482 | CE39: =+FIFO!AV25 -> 2183.3734 | CF39: =+FIFO!AX25 -> 2108.3299 | CG39: =+FIFO!AZ25 -> 2139.863 | CK39: =+FIFO!BH25 -> 2252.012 | CL39: =+FIFO!#REF! -> #REF! | CM39: =+FIFO!CA25 -> 0 | CN39: =+FIFO!CB25 -> 0 | CO39: =+FIFO!CC25 -> 0 | CP39: =+FIFO!CD25 -> 0 | CQ39: =+FIFO!CE25 -> 0 | CR39: =+FIFO!CF25 -> 0 | CS39: =+FIFO!CG25 -> 0 | CT39: =+FIFO!CH25 -> 0 | CU39: =+FIFO!CI25 -> 0
C41: Precio ponderado bajo formula 50 PCR Aurora /50 Virgen | V41: =+(V32*50%)+(V66*50%) -> 531.97998 | W41: =+(W26*50%)+(W32*50%) -> 1100.761 | X41: =+(X26*50%)+(X32*50%) -> 1121.6234 | Y41: =+(Y26*50%)+(Y32*50%) -> 1241.4706 | Z41: =+(Z26*50%)+(Z32*50%) -> 1204.7359 | AA41: =+(AA26*50%)+(AA32*50%) -> 1154.2059 | AB41: =+(AB26*50%)+(AB32*50%) -> 1186.407 | AC41: =+(AC26*50%)+(AC32*50%) -> 1163.0802 | AD41: =+(AD26*50%)+(AD32*50%) -> 1174.222 | ... AJ41: =+(AJ26*50%)+(AJ32*50%) -> 1149.9627 | AK41: =+(AK27*50%)+(AK32*50%) -> #REF! | AL41: =+(AL27*50%)+(AL32*50%) -> #REF! | AM41: =+(AM27*50%)+(AM32*50%) -> #REF! | AN41: =+(AN27*50%)+(AN32*50%) -> #REF! | AO41: =+(AO27*50%)+(AO32*50%) -> #REF! | AP41: =+(AP27*50%)+(AP32*50%) -> #REF! | AQ41: =+(AQ28*50%)+(AQ33*50%) -> #REF! | AR41: =+(AR28*50%)+(AR33*50%) -> #REF! | AS41: =+(AS28*50%)+(AS33*50%) -> #REF! | AT41: =+(AT28*50%)+(AT33*50%) -> #REF! | AU41: =+(AU28*50%)+(AU33*50%) -> #REF! | AV41: 1861.4665 | AW41: 1854.0005 | AX41: =+(AX28*50%)+(AX33*50%) -> #REF! | AY41: 1992.3238 | AZ41: =+(AZ28*50%)+(AZ33*50%) -> #REF! | BA41: =+(BA28*50%)+(BA33*50%) -> #REF! | BB41: =+(BB28*50%)+(BB33*50%) -> #REF! | BC41: =+(BC30*50%)+(BC33*50%) -> #REF! | BD41: =+(BD30*50%)+(BD33*50%) -> #REF! | BE41: =+(BE30*50%)+(BE33*50%) -> #REF! | BF41: =+(BF30*50%)+(BF33*50%) -> #REF! | BG41: =+(BG30*50%)+(BG33*50%) -> #REF! | BH41: =+(BH30*50%)+(BH33*50%) -> #REF! | BI41: =+(BI30*50%)+(BI33*50%) -> #REF! | BJ41: =+(BJ30*50%)+(BJ33*50%) -> #REF! | ... CJ41: =+(CJ30*50%)+(CJ33*50%) -> 1794.7595 | CK41: =+(CK30*50%)+(CK36*50%) -> 1732.6105 | CL41: =+(CL30*50%)+(CL36*50%) -> 1736.1742 | CM41: =+(CM30*50%)+(CM36*50%) -> 1730.127 | CN41: =+(CN30*50%)+(CN36*50%) -> 1759.7594 | CO41: =+(CO30*50%)+(CO36*50%) -> 1630.5479 | CP41: =+(CP30*50%)+(CP36*50%) -> 1611.7818 | CQ41: =+(CQ30*50%)+(CQ36*50%) -> 1594.1294 | CR41: =+(CR30*50%)+(CR36*50%) -> 1576.2434 | ... CU41: =+(CU30*50%)+(CU36*50%) -> 1552.5564
C42: Scrap 1% | V42: =+V41*1% -> 5.3197998 | W42: =+W41*1% -> 11.00761 | X42: =+X41*1% -> 11.216234 | Y42: =+Y41*1% -> 12.414706 | Z42: =+Z41*1% -> 12.047359 | AA42: =+AA41*1% -> 11.542059 | AB42: =+AB41*1% -> 11.86407 | AC42: =+AC41*1% -> 11.630802 | ... AU42: =+AU41*1% -> #REF! | AV42: 18.614665 | AW42: 18.540005 | AX42: =+AX41*1% -> #REF! | AY42: 19.923238 | AZ42: =+AZ41*1% -> #REF! | BA42: =+BA41*1% -> #REF! | BB42: =+BB41*1% -> #REF! | BC42: =+BC41*1% -> #REF! | BD42: =+BD41*1% -> #REF! | BE42: =+BE41*1% -> #REF! | BF42: =+BF41*1% -> #REF! | BG42: =+BG41*1% -> #REF! | ... CU42: =+CU41*1% -> 15.525564
C43: Precio ponderado con scrap | V43: =+V42+V41 -> 537.29978 | W43: =+W42+W41 -> 1111.7686 | X43: =+X42+X41 -> 1132.8397 | Y43: =+Y42+Y41 -> 1253.8853 | Z43: =+Z42+Z41 -> 1216.7833 | AA43: =+AA42+AA41 -> 1165.748 | AB43: =+AB42+AB41 -> 1198.2711 | AC43: =+AC42+AC41 -> 1174.711 | ... AU43: =+AU42+AU41 -> #REF! | AV43: 1880.0812 | AW43: 1872.5405 | AX43: =+AX42+AX41 -> #REF! | AY43: 2012.247 | AZ43: =+AZ42+AZ41 -> #REF! | BA43: =+BA42+BA41 -> #REF! | BB43: =+BB42+BB41 -> #REF! | BC43: =+BC42+BC41 -> #REF! | BD43: =+BD42+BD41 -> #REF! | BE43: =+BE42+BE41 -> #REF! | BF43: =+BF42+BF41 -> #REF! | BG43: =+BG42+BG41 -> #REF! | ... CU43: =+CU42+CU41 -> 1568.082
C45: Precio ponderado bajo formula 100% PCR Enka | Z45: =+Z34 -> 1070.2457 | AA45: =+AA34 -> 1103.3118 | AB45: =+AB34 -> 1103.3118 | AC45: =+AC34 -> 1149.9847 | AD45: =+AD34 -> 1149.9847 | AE45: =+AE34 -> 1163.7352 | AF45: =+AF34 -> 1163.7352 | AG45: =+AG34 -> 6 | ... AU45: =+AU34 -> 1905.3661 | AV45: 1842.137 | AW45: 1765.8142 | AX45: =+AX34 -> 1957.7659 | AY45: 2007.3086 | AZ45: =+AZ34 -> 2077.6143 | BA45: =+BA34 -> 2127.3064 | BB45: =+BB34 -> 2127.3064 | BC45: =+BC34 -> 2251.8217 | BD45: =+BD34 -> 1986.3646 | BE45: =+BE34 -> 1941.3379 | BF45: =+BF34 -> 1729.6772 | BG45: =+BG34 -> 1474.4296 | ... BK45: =+BK34 -> 1593.6921 | BL45: =+BL35 -> 1541.7236 | BM45: =+BM35 -> 1572.2305 | BN45: =+BN35 -> 1582.7075 | BO45: =+BO35 -> 1624.5182 | BP45: =+BP35 -> 1640.1021 | BQ45: =+BQ35 -> 1640.1021 | BR45: =+BR35 -> 1640.1021 | BS45: =+BS35 -> 1640.1021 | ... BU45: =+BU35 -> 1640.1021 | BV45: =+FIFO!AB21 -> 1640.1021 | BW45: =+BW35 -> 1640.1021 | BX45: =+BX35 -> 1640.1021 | BY45: =+BY35 -> 1640.1021 | BZ45: =+BZ35 -> 1640.1021 | CA45: =+CA35 -> 1756.8307 | CB45: =+CB35 -> 1848.502 | CC45: =+CC35 -> 1924.5346 | CD45: =+CD35 -> 1924.5346 | ... CJ45: =+CJ35 -> 2047.5847 | CK45: =+FIFO!BH21 -> 2095.2472 | CL45: =+FIFO!BJ21 -> 2103.5509 | CM45: =+CM35 -> 2141.3654 | CN45: =+CN35 -> 2141.3654 | CO45: =+FIFO!BP20 -> 2211.1991 | CP45: =+CP35 -> 2141.3654 | CQ45: =+CQ35 -> 2141.3654 | CR45: =+'PCR Aurora '!Z14 -> 2206.9083 | CS45: =+'PCR Enka'!DX26 -> 2148.8386 | CT45: =+CT35 -> 2141.3654 | CU45: =+FIFO!BZ21 -> 2141.3654
C46: Scrap 1% | Z46: =+Z45*1% -> 10.702457 | AA46: =+AA45*1% -> 11.033118 | AB46: =+AB45*1% -> 11.033118 | AC46: =+AC45*1% -> 11.499847 | AD46: =+AD45*1% -> 11.499847 | AE46: =+AE45*1% -> 11.637352 | AF46: =+AF45*1% -> 11.637352 | AG46: =+AG45*1% -> 0.06 | ... AU46: =+AU45*1% -> 19.053661 | AV46: 18.42137 | AW46: 17.658142 | AX46: =+AX45*1% -> 19.577659 | AY46: 20.073086 | AZ46: =+AZ45*1% -> 20.776143 | BA46: =+BA45*1% -> 21.273064 | BB46: =+BB45*1% -> 21.273064 | BC46: =+BC45*1% -> 22.518217 | BD46: =+BD45*1% -> 19.863646 | BE46: =+BE45*1% -> 19.413379 | BF46: =+BF45*1% -> 17.296772 | BG46: =+BG45*1% -> 14.744296 | ... CU46: =+CU45*1% -> 21.413654
C47: Precio ponderado con scrap | Z47: =+Z46+Z45 -> 1080.9482 | AA47: =+AA46+AA45 -> 1114.3449 | AB47: =+AB46+AB45 -> 1114.3449 | AC47: =+AC46+AC45 -> 1161.4845 | AD47: =+AD46+AD45 -> 1161.4845 | AE47: =+AE46+AE45 -> 1175.3725 | AF47: =+AF46+AF45 -> 1175.3725 | AG47: =+AG46+AG45 -> 6.06 | ... AU47: =+AU46+AU45 -> 1924.4198 | AV47: 1860.5584 | AW47: 1783.4723 | AX47: =+AX46+AX45 -> 1977.3435 | AY47: 2027.3817 | AZ47: =+AZ46+AZ45 -> 2098.3905 | BA47: =+BA46+BA45 -> 2148.5795 | BB47: =+BB46+BB45 -> 2148.5795 | BC47: =+BC46+BC45 -> 2274.3399 | BD47: =+BD46+BD45 -> 2006.2282 | BE47: =+BE46+BE45 -> 1960.7512 | BF47: =+BF46+BF45 -> 1746.974 | BG47: =+BG46+BG45 -> 1489.1739 | ... CU47: =+CU46+CU45 -> 2162.7791
C49: Precio ponderado bajo formula 75 PCR Aurora /25 Virgen. | AI49: =+(AI26*25%)+(AI32*75%) -> 1288.0475 | AJ49: =+(AJ26*25%)+(AJ32*75%) -> 1272.2514 | AK49: =+(AK27*25%)+(AK32*75%) -> #REF! | AL49: =+(AL27*25%)+(AL32*75%) -> #REF! | AM49: =+(AM27*25%)+(AM32*75%) -> #REF! | AN49: =+(AN27*25%)+(AN32*75%) -> #REF! | AO49: =+(AO27*25%)+(AO32*75%) -> #REF! | AP49: =+(AP27*25%)+(AP32*75%) -> #REF! | AQ49: =+(AQ28*25%)+(AQ33*75%) -> #REF! | AR49: =+(AR28*25%)+(AR33*75%) -> #REF! | AS49: =+(AS28*25%)+(AS33*75%) -> #REF! | AT49: =+(AT28*25%)+(AT33*75%) -> #REF! | AU49: =+(AU28*25%)+(AU33*75%) -> #REF! | AV49: 1901.7982 | AW49: 1858.572 | AX49: =+(AX28*25%)+(AX33*75%) -> #REF! | AY49: 2048.4216 | AZ49: =+(AZ28*25%)+(AZ33*75%) -> #REF! | BA49: =+(BA28*25%)+(BA33*75%) -> #REF! | BB49: =+(BB28*25%)+(BB33*75%) -> #REF! | BC49: =+(BC30*25%)+(BC33*75%) -> #REF! | BD49: =+(BD30*25%)+(BD33*75%) -> #REF! | BE49: =+(BE30*25%)+(BE33*75%) -> #REF! | BF49: =+(BF30*25%)+(BF33*75%) -> #REF! | BG49: =+(BG30*25%)+(BG33*75%) -> #REF! | BH49: =+(BH30*25%)+(BH33*75%) -> #REF! | BI49: =+(BI30*25%)+(BI33*75%) -> #REF! | BJ49: =+(BJ30*25%)+(BJ33*75%) -> #REF! | ... CJ49: =+(CJ30*25%)+(CJ33*75%) -> 2102.8174 | CK49: =+(CK30*25%)+(CK36*75%) -> 2019.1636 | CL49: =+(CL30*25%)+(CL36*75%) -> 2019.2722 | CM49: =+(CM30*25%)+(CM36*75%) -> 2000.9593 | CN49: =+(CN30*25%)+(CN36*75%) -> 1957.4215 | CO49: =+(CO30*25%)+(CO36*75%) -> 1802.4403 | CP49: =+(CP30*25%)+(CP36*75%) -> 1792.9214 | CQ49: =+(CQ30*25%)+(CQ36*75%) -> 1776.3399 | CR49: =+(CR30*25%)+(CR36*75%) -> 1763.6515 | ... CU49: =+(CU30*25%)+(CU36*75%) -> 1767.647
C50: Scrap 1% | AI50: =+AI49*1% -> 12.880475 | AJ50: =+AJ49*1% -> 12.722514 | AK50: =+AK49*1% -> #REF! | AL50: =+AL49*1% -> #REF! | AM50: =+AM49*1% -> #REF! | AN50: =+AN49*1% -> #REF! | AO50: =+AO49*1% -> #REF! | AP50: =+AP49*1% -> #REF! | ... AU50: =+AU49*1% -> #REF! | AV50: 19.017982 | AW50: 18.58572 | AX50: =+AX49*1% -> #REF! | AY50: 20.484216 | AZ50: =+AZ49*1% -> #REF! | BA50: =+BA49*1% -> #REF! | BB50: =+BB49*1% -> #REF! | BC50: =+BC49*1% -> #REF! | BD50: =+BD49*1% -> #REF! | BE50: =+BE49*1% -> #REF! | BF50: =+BF49*1% -> #REF! | BG50: =+BG49*1% -> #REF! | ... CU50: =+CU49*1% -> 17.67647
C51: Precio ponderado con scrap | AI51: =+AI50+AI49 -> 1300.928 | AJ51: =+AJ50+AJ49 -> 1284.9739 | AK51: =+AK50+AK49 -> #REF! | AL51: =+AL50+AL49 -> #REF! | AM51: =+AM50+AM49 -> #REF! | AN51: =+AN50+AN49 -> #REF! | AO51: =+AO50+AO49 -> #REF! | AP51: =+AP50+AP49 -> #REF! | ... AU51: =+AU50+AU49 -> #REF! | AV51: 1920.8162 | AW51: 1877.1577 | AX51: =+AX50+AX49 -> #REF! | AY51: 2068.9058 | AZ51: =+AZ50+AZ49 -> #REF! | BA51: =+BA50+BA49 -> #REF! | BB51: =+BB50+BB49 -> #REF! | BC51: =+BC50+BC49 -> #REF! | BD51: =+BD50+BD49 -> #REF! | BE51: =+BE50+BE49 -> #REF! | BF51: =+BF50+BF49 -> #REF! | BG51: =+BG50+BG49 -> #REF! | ... CU51: =+CU50+CU49 -> 1785.3235
C53: Precio ponderado bajo formula 100% PCR Enkador | V53: =+V32 -> 1063.96 | W53: =+W32 -> 1072.5364 | X53: =+X32 -> 1092.8639 | Y53: =+Y32 -> 1332.5581 | Z53: =+Z32 -> 1386.3641 | AA53: =+AA32 -> 1386.3641 | AB53: =+AB32 -> 1386.3641 | AC53: =+AC32 -> 1386.3641 | ... AP53: =+AP32 -> 1485 | AQ53: =+AQ33 -> 1514.8753 | AR53: =+AR33 -> 1514.8753 | AS53: =+AS33 -> 1514.8753 | AT53: =+AT33 -> 1748.1782 | AU53: =+AU33 -> 2005.359 | AV53: 1942.1299 | AW53: 1863.1434 | AX53: =+AX33 -> 2055.0951 | AY53: 2104.5194 | AZ53: =+AZ33 -> 2174.9407 | BA53: =+BA33 -> 2224.6328 | BB53: =+BB33 -> 2224.6328 | BC53: =+BC33 -> 2351.9981 | BD53: =+BD33 -> 2084.088 | BE53: =+BE33 -> 2039.0612 | BF53: =+BF33 -> 1827.4006 | BG53: =+BG33 -> 1572.153 | ... CU53: =+CU33 -> 0
C54: Scrap 1% | V54: =+V53*1% -> 10.6396 | W54: =+W53*1% -> 10.725364 | X54: =+X53*1% -> 10.928639 | Y54: =+Y53*1% -> 13.325581 | Z54: =+Z53*1% -> 13.863641 | AA54: =+AA53*1% -> 13.863641 | AB54: =+AB53*1% -> 13.863641 | AC54: =+AC53*1% -> 13.863641 | ... AU54: =+AU53*1% -> 20.05359 | AV54: 19.421299 | AW54: 18.631434 | AX54: =+AX53*1% -> 20.550951 | AY54: 21.045194 | AZ54: =+AZ53*1% -> 21.749407 | BA54: =+BA53*1% -> 22.246328 | BB54: =+BB53*1% -> 22.246328 | BC54: =+BC53*1% -> 23.519981 | BD54: =+BD53*1% -> 20.84088 | BE54: =+BE53*1% -> 20.390612 | BF54: =+BF53*1% -> 18.274006 | BG54: =+BG53*1% -> 15.72153 | ... CU54: =+CU53*1% -> 0
C55: Precio ponderado con scrap | V55: =+V54+V53 -> 1074.5996 | W55: =+W54+W53 -> 1083.2617 | X55: =+X54+X53 -> 1103.7925 | Y55: =+Y54+Y53 -> 1345.8837 | Z55: =+Z54+Z53 -> 1400.2277 | AA55: =+AA54+AA53 -> 1400.2277 | AB55: =+AB54+AB53 -> 1400.2277 | AC55: =+AC54+AC53 -> 1400.2277 | ... AU55: =+AU54+AU53 -> 2025.4126 | AV55: 1961.5512 | AW55: 1881.7748 | AX55: =+AX54+AX53 -> 2075.6461 | AY55: 2125.5646 | AZ55: =+AZ54+AZ53 -> 2196.6902 | BA55: =+BA54+BA53 -> 2246.8791 | BB55: =+BB54+BB53 -> 2246.8791 | BC55: =+BC54+BC53 -> 2375.518 | BD55: =+BD54+BD53 -> 2104.9288 | BE55: =+BE54+BE53 -> 2059.4518 | BF55: =+BF54+BF53 -> 1845.6746 | BG55: =+BG54+BG53 -> 1587.8745 | ... CU55: =+CU54+CU53 -> 0
C57: Precio ponderado bajo formula 100% VIRGEN | Y57: =+Y26 -> 1150.383 | Z57: =+Z26 -> 1023.1077 | AA57: =+AA26 -> 922.0478 | AB57: =+AB26 -> 986.45 | AC57: =+AC26 -> 939.79624 | AD57: =+AD26 -> 962.08 | AE57: =+AE26 -> 950.59588 | AF57: =+AF26 -> 956.04 | ... AJ57: =+AJ26 -> 905.3855 | AK57: =+AK27 -> #REF! | AL57: =+AL27 -> #REF! | AM57: =+AM27 -> #REF! | AN57: =+AN27 -> #REF! | AO57: =+AO27 -> #REF! | AP57: =+AP27 -> #REF! | AQ57: =+AQ28 -> #REF! | AR57: =+AR28 -> #REF! | AS57: =+AS28 -> #REF! | AT57: =+AT28 -> #REF! | AU57: =+AU28 -> #REF! | AV57: 1780.8032 | AW57: 1844.8576 | AX57: =+AX28 -> #REF! | AY57: 1880.1282 | AZ57: =+AZ28 -> #REF! | BA57: =+BA28 -> #REF! | BB57: =+BB28 -> #REF! | BC57: =+BC30 -> #REF! | BD57: =+BD30 -> #REF! | BE57: =+BE30 -> #REF! | BF57: =+BF30 -> #REF! | BG57: =+BG30 -> #REF! | BH57: =+BH30 -> #REF! | BI57: =+BI30 -> #REF! | BJ57: =+BJ30 -> #REF! | ... CU57: =+CU30 -> 1122.3753
C58: Scrap 1% | Y58: =+Y57*1% -> 11.50383 | Z58: =+Z57*1% -> 10.231077 | AA58: =+AA57*1% -> 9.220478 | AB58: =+AB57*1% -> 9.8645 | AC58: =+AC57*1% -> 9.3979624 | AD58: =+AD57*1% -> 9.6208 | AE58: =+AE57*1% -> 9.5059588 | AF58: =+AF57*1% -> 9.5604 | ... AU58: =+AU57*1% -> #REF! | AV58: 17.808032 | AW58: 18.448576 | AX58: =+AX57*1% -> #REF! | AY58: 18.801282 | AZ58: =+AZ57*1% -> #REF! | BA58: =+BA57*1% -> #REF! | BB58: =+BB57*1% -> #REF! | BC58: =+BC57*1% -> #REF! | BD58: =+BD57*1% -> #REF! | BE58: =+BE57*1% -> #REF! | BF58: =+BF57*1% -> #REF! | BG58: =+BG57*1% -> #REF! | ... CU58: =+CU57*1% -> 11.223753
C59: Precio ponderado con scrap | Y59: =+Y58+Y57 -> 1161.8868 | Z59: =+Z58+Z57 -> 1033.3388 | AA59: =+AA58+AA57 -> 931.26827 | AB59: =+AB58+AB57 -> 996.3145 | AC59: =+AC58+AC57 -> 949.1942 | AD59: =+AD58+AD57 -> 971.7008 | AE59: =+AE58+AE57 -> 960.10183 | AF59: =+AF58+AF57 -> 965.6004 | ... AU59: =+AU58+AU57 -> #REF! | AV59: 1798.6112 | AW59: 1863.3062 | AX59: =+AX58+AX57 -> #REF! | AY59: 1898.9295 | AZ59: =+AZ58+AZ57 -> #REF! | BA59: =+BA58+BA57 -> #REF! | BB59: =+BB58+BB57 -> #REF! | BC59: =+BC58+BC57 -> #REF! | BD59: =+BD58+BD57 -> #REF! | BE59: =+BE58+BE57 -> #REF! | BF59: =+BF58+BF57 -> #REF! | BG59: =+BG58+BG57 -> #REF! | ... CU59: =+CU58+CU57 -> 1133.599
C61: Precio ponderado bajo formula 50 PCR /50 Aurora Ambar | Z61: =+Z68 -> 0 | AA61: =+AA68 -> 0 | AB61: =+AB68 -> 0 | AC61: =+AC68 -> 0 | AD61: =+(AD26*50%)+(AD34*50%) -> 1056.0323 | AE61: =+(AE26*50%)+(AE34*50%) -> 1057.1655 | AF61: =+(AF26*50%)+(AF34*50%) -> 1059.8876 | AG61: =+(AG26*50%)+(AG34*50%) -> 466.49239 | AH61: =+(AH26*50%)+(AH34*50%) -> 1019.0123 | AI61: =+(AI26*50%)+(AI34*50%) -> 1034.3661 | AJ61: =+(AJ26*50%)+(AJ34*50%) -> 1051.4569 | AK61: =+(AK27*50%)+(AK34*50%) -> #REF! | AL61: =+(AL27*50%)+(AL34*50%) -> #REF! | AM61: =+(AM27*50%)+(AM34*50%) -> #REF! | AN61: =+(AN27*50%)+(AN34*50%) -> #REF! | AO61: =+(AO27*50%)+(AO34*50%) -> #REF! | AP61: =+(AP27*50%)+(AP34*50%) -> #REF! | AQ61: =+(AQ28*50%)+(AQ34*50%) -> #REF! | AR61: =+(AR28*50%)+(AR34*50%) -> #REF! | AS61: =+(AS28*50%)+(AS34*50%) -> #REF! | AT61: =+(AT28*50%)+(AT34*50%) -> #REF! | AU61: =+(AU28*50%)+(AU34*50%) -> #REF! | AV61: 1811.4701 | AW61: 1805.3359 | AX61: =+(AX28*50%)+(AX34*50%) -> #REF! | AY61: 1943.7184 | AZ61: =+(AZ28*50%)+(AZ34*50%) -> #REF! | BA61: =+(BA28*50%)+(BA34*50%) -> #REF! | BB61: =+(BB28*50%)+(BB34*50%) -> #REF! | BC61: =+(BC30*50%)+(BC34*50%) -> #REF! | BD61: =+(BD30*50%)+(BD34*50%) -> #REF! | BE61: =+(BE30*50%)+(BE34*50%) -> #REF! | BF61: =+(BF30*50%)+(BF34*50%) -> #REF! | BG61: =+(BG30*50%)+(BG34*50%) -> #REF! | BH61: =+(BH30*50%)+(BH34*50%) -> #REF! | BI61: =+(BI30*50%)+(BI34*50%) -> #REF! | BJ61: =+(BJ30*50%)+(BJ34*50%) -> #REF! | ... CS61: =+(CS30*50%)+(CS34*50%) -> 1548.4325 | CT61: =+(CT30*50%)+(CT38*50%) -> 1494.1051 | CU61: =+(CU30*50%)+(CU38*50%) -> 1502.5564
C62: Scrap 1% | Z62: =+Z61*1% -> 0 | AA62: =+AA61*1% -> 0 | AB62: =+AB61*1% -> 0 | AC62: =+AC61*1% -> 0 | AD62: =+AD61*1% -> 10.560323 | AE62: =+AE61*1% -> 10.571655 | AF62: =+AF61*1% -> 10.598876 | AG62: =+AG61*1% -> 4.6649239 | ... AU62: =+AU61*1% -> #REF! | AV62: 18.114701 | AW62: 18.053359 | AX62: =+AX61*1% -> #REF! | AY62: 19.437184 | AZ62: =+AZ61*1% -> #REF! | BA62: =+BA61*1% -> #REF! | BB62: =+BB61*1% -> #REF! | BC62: =+BC61*1% -> #REF! | BD62: =+BD61*1% -> #REF! | BE62: =+BE61*1% -> #REF! | BF62: =+BF61*1% -> #REF! | BG62: =+BG61*1% -> #REF! | ... CU62: =+CU61*1% -> 15.025564
C63: Precio ponderado con scrap | Z63: =+Z62+Z61 -> 0 | AA63: =+AA62+AA61 -> 0 | AB63: =+AB62+AB61 -> 0 | AC63: =+AC62+AC61 -> 0 | AD63: =+AD62+AD61 -> 1066.5926 | AE63: =+AE62+AE61 -> 1067.7372 | AF63: =+AF62+AF61 -> 1070.4865 | AG63: =+AG62+AG61 -> 471.15731 | ... AU63: =+AU62+AU61 -> #REF! | AV63: 1829.5848 | AW63: 1823.3893 | AX63: =+AX62+AX61 -> #REF! | AY63: 1963.1556 | AZ63: =+AZ62+AZ61 -> #REF! | BA63: =+BA62+BA61 -> #REF! | BB63: =+BB62+BB61 -> #REF! | BC63: =+BC62+BC61 -> #REF! | BD63: =+BD62+BD61 -> #REF! | BE63: =+BE62+BE61 -> #REF! | BF63: =+BF62+BF61 -> #REF! | BG63: =+BG62+BG61 -> #REF! | ... CU63: =+CU62+CU61 -> 1517.582
C65: Precio ponderado bajo formula 75 PCR Enka /25 Virgen | AR65: =+(AR34*75%)+(AR28*25%) -> #REF! | AS65: =+(AS34*75%)+(AS28*25%) -> #REF! | AT65: =+(AT34*75%)+(AT28*25%) -> #REF! | AU65: =+(AU34*75%)+(AU28*25%) -> #REF! | AV65: 1826.8036 | AW65: 1785.575 | AX65: =+(AX34*75%)+(AX28*25%) -> #REF! | AY65: 1975.5135 | AZ65: =+(AZ34*75%)+(AZ28*25%) -> #REF! | BA65: =+(BA34*75%)+(BA28*25%) -> #REF! | BB65: =+(BB34*75%)+(BB28*25%) -> #REF! | BC65: =+(BC34*75%)+(BC28*25%) -> #REF! | BD65: =+(BD34*75%)+(BD28*25%) -> #REF! | BE65: =+(BE34*75%)+(BE28*25%) -> #REF! | BF65: =+(BF34*75%)+(BF28*25%) -> #REF! | BG65: =+(BG34*75%)+(BG28*25%) -> #REF! | ... BK65: =+(BK34*75%)+(BK28*25%) -> #REF! | BL65: =+(BL35*75%)+(BL28*25%) -> #REF! | BM65: =+(BM35*75%)+(BM28*25%) -> 1495.9265 | BN65: =+(BN35*75%)+(BN28*25%) -> 1513.0608 | BO65: =+(BO35*75%)+(BO28*25%) -> 1543.131 | BP65: =+(BP35*75%)+(BP28*25%) -> 1543.7873 | BQ65: =+(BQ35*75%)+(BQ28*25%) -> 1534.0527 | BR65: =+(BR35*75%)+(BR28*25%) -> 1535.2403 | BS65: =+(BS35*75%)+(BS28*25%) -> 1536.6233 | ... CU65: =+(CU35*75%)+(CU28*25%) -> 280.59381
C66: Scrap 1% | AR66: =+AR65*1% -> #REF! | AS66: =+AS65*1% -> #REF! | AT66: =+AT65*1% -> #REF! | AU66: =+AU65*1% -> #REF! | AV66: 18.268036 | AW66: 17.85575 | AX66: =+AX65*1% -> #REF! | AY66: 19.755135 | AZ66: =+AZ65*1% -> #REF! | BA66: =+BA65*1% -> #REF! | BB66: =+BB65*1% -> #REF! | BC66: =+BC65*1% -> #REF! | BD66: =+BD65*1% -> #REF! | BE66: =+BE65*1% -> #REF! | BF66: =+BF65*1% -> #REF! | BG66: =+BG65*1% -> #REF! | ... CU66: =+CU65*1% -> 2.8059381
C67: Precio ponderado con scrap | AR67: =+AR66+AR65 -> #REF! | AS67: =+AS66+AS65 -> #REF! | AT67: =+AT66+AT65 -> #REF! | AU67: =+AU66+AU65 -> #REF! | AV67: 1845.0716 | AW67: 1803.4308 | AX67: =+AX66+AX65 -> #REF! | AY67: 1995.2686 | AZ67: =+AZ66+AZ65 -> #REF! | BA67: =+BA66+BA65 -> #REF! | BB67: =+BB66+BB65 -> #REF! | BC67: =+BC66+BC65 -> #REF! | BD67: =+BD66+BD65 -> #REF! | BE67: =+BE66+BE65 -> #REF! | BF67: =+BF66+BF65 -> #REF! | BG67: =+BG66+BG65 -> #REF! | ... CU67: =+CU66+CU65 -> 283.39975
C68: Precio ponderado con scrap | D68: =+D67+D66 -> 0 | E68: =+E67+E66 -> 0 | F68: =+F67+F66 -> 0 | G68: =+G67+G66 -> 0 | H68: =+H67+H66 -> 0 | I68: =+I67+I66 -> 0 | J68: =+J67+J66 -> 0 | K68: =+K67+K66 -> 0 | ... AU68: =+AU67+AU66 -> #REF! | AV68: 1863.3396 | AW68: 1821.2865 | AX68: =+AX67+AX66 -> #REF! | AY68: 2015.0238 | AZ68: =+AZ67+AZ66 -> #REF! | BA68: =+BA67+BA66 -> #REF! | BB68: =+BB67+BB66 -> #REF! | BC68: =+BC67+BC66 -> #REF! | BD68: =+BD67+BD66 -> #REF! | BE68: =+BE67+BE66 -> #REF! | BF68: =+BF67+BF66 -> #REF! | BG68: =+BG67+BG66 -> #REF! | ... CU68: =+CU67+CU66 -> 286.20569
C69: Precio ponderado bajo formula 10% PCR Enkador / 90% virgen | Y69: =+(Y26*90%)+(Y32*10%) -> 1168.6005 | Z69: =+(Z26*90%)+(Z32*10%) -> 1059.4334 | AA69: =+(AA26*90%)+(AA32*10%) -> 968.47943 | AB69: =+(AB26*90%)+(AB32*10%) -> 1026.4414 | AC69: =+(AC26*90%)+(AC32*10%) -> 984.45302 | AD69: =+(AD26*90%)+(AD32*10%) -> 1004.5084 | AE69: =+(AE26*90%)+(AE32*10%) -> 996.77225 | AF69: =+(AF26*90%)+(AF32*10%) -> 1001.672 | ... AJ69: =+(AJ26*90%)+(AJ32*10%) -> 954.30095 | AK69: =+(AK28*90%)+(AK32*10%) -> #REF! | AL69: =+(AL28*90%)+(AL32*10%) -> #REF! | AM69: =+(AM28*90%)+(AM32*10%) -> #REF! | AN69: =+(AN28*90%)+(AN32*10%) -> #REF! | AO69: =+(AO28*90%)+(AO32*10%) -> #REF! | AP69: =+(AP28*90%)+(AP32*10%) -> #REF! | AQ69: =+(AQ28*90%)+(AQ32*10%) -> #REF! | AR69: =+(AR28*90%)+(AR32*10%) -> #REF! | ... AU69: =+(AU28*90%)+(AU32*10%) -> #REF! | AV69: 1796.9358 | AW69: 1846.6862 | AX69: =+(AX28*90%)+(AX32*10%) -> #REF! | AY69: 1902.5673 | AZ69: =+(AZ28*90%)+(AZ32*10%) -> #REF! | BA69: =+(BA28*90%)+(BA32*10%) -> #REF! | BB69: =+(BB28*90%)+(BB32*10%) -> #REF! | BC69: =+(BC28*90%)+(BC32*10%) -> #REF! | BD69: =+(BD28*90%)+(BD32*10%) -> #REF! | BE69: =+(BE28*90%)+(BE32*10%) -> #REF! | BF69: =+(BF28*90%)+(BF32*10%) -> #REF! | BG69: =+(BG28*90%)+(BG32*10%) -> #REF! | ... CU69: =+(CU28*90%)+(CU32*10%) -> 1010.1377
C70: Scrap 1% | Y70: =+Y69*1% -> 11.686005 | Z70: =+Z69*1% -> 10.594334 | AA70: =+AA69*1% -> 9.6847943 | AB70: =+AB69*1% -> 10.264414 | AC70: =+AC69*1% -> 9.8445302 | AD70: =+AD69*1% -> 10.045084 | AE70: =+AE69*1% -> 9.9677225 | AF70: =+AF69*1% -> 10.01672 | ... AU70: =+AU69*1% -> #REF! | AV70: 17.969358 | AW70: 18.466862 | AX70: =+AX69*1% -> #REF! | AY70: 19.025673 | AZ70: =+AZ69*1% -> #REF! | BA70: =+BA69*1% -> #REF! | BB70: =+BB69*1% -> #REF! | BC70: =+BC69*1% -> #REF! | BD70: =+BD69*1% -> #REF! | BE70: =+BE69*1% -> #REF! | BF70: =+BF69*1% -> #REF! | BG70: =+BG69*1% -> #REF! | ... CU70: =+CU69*1% -> 10.101377
C71: Precio ponderado con scrap | Y71: =+Y70+Y69 -> 1180.2865 | Z71: =+Z70+Z69 -> 1070.0277 | AA71: =+AA70+AA69 -> 978.16422 | AB71: =+AB70+AB69 -> 1036.7058 | AC71: =+AC70+AC69 -> 994.29755 | AD71: =+AD70+AD69 -> 1014.5535 | AE71: =+AE70+AE69 -> 1006.74 | AF71: =+AF70+AF69 -> 1011.6887 | ... AU71: =+AU70+AU69 -> #REF! | AV71: 1814.9052 | AW71: 1865.1531 | AX71: =+AX70+AX69 -> #REF! | AY71: 1921.593 | AZ71: =+AZ70+AZ69 -> #REF! | BA71: =+BA70+BA69 -> #REF! | BB71: =+BB70+BB69 -> #REF! | BC71: =+BC70+BC69 -> #REF! | BD71: =+BD70+BD69 -> #REF! | BE71: =+BE70+BE69 -> #REF! | BF71: =+BF70+BF69 -> #REF! | BG71: =+BG70+BG69 -> #REF! | ... CU71: =+CU70+CU69 -> 1020.2391
C73: Precio ponderado bajo formula 25% PCR Enka / 75% Virgen | Z73: =+(Z26*75%)+(Z34*25%) -> 1034.8922 | AA73: =+(AA26*75%)+(AA34*25%) -> 967.36379 | AB73: =+(AB26*75%)+(AB34*25%) -> 1015.6654 | AC73: =+(AC26*75%)+(AC34*25%) -> 992.34334 | AD73: =+(AD26*75%)+(AD34*25%) -> 1009.0562 | AE73: =+(AE26*75%)+(AE34*25%) -> 1003.8807 | AF73: =+(AF26*75%)+(AF34*25%) -> 1007.9638 | AG73: =+(AG26*75%)+(AG34*25%) -> 696.73858 | ... AJ73: =+(AJ26*75%)+(AJ34*25%) -> 978.42118 | AK73: =+(AK28*75%)+(AK34*25%) -> #REF! | AL73: =+(AL28*75%)+(AL34*25%) -> #REF! | AM73: =+(AM28*75%)+(AM34*25%) -> #REF! | AN73: =+(AN28*75%)+(AN34*25%) -> #REF! | AO73: =+(AO28*75%)+(AO34*25%) -> #REF! | AP73: =+(AP28*75%)+(AP34*25%) -> #REF! | AQ73: =+(AQ28*75%)+(AQ34*25%) -> #REF! | AR73: =+(AR28*75%)+(AR34*25%) -> #REF! | ... AU73: =+(AU28*75%)+(AU34*25%) -> #REF! | AV73: 1796.1366 | AW73: 1825.0968 | AX73: =+(AX28*75%)+(AX34*25%) -> #REF! | AY73: 1911.9233 | AZ73: =+(AZ28*75%)+(AZ34*25%) -> #REF! | BA73: =+(BA28*75%)+(BA34*25%) -> #REF! | BB73: =+(BB28*75%)+(BB34*25%) -> #REF! | BC73: =+(BC30*75%)+(BC34*25%) -> #REF! | BD73: =+(BD30*75%)+(BD34*25%) -> #REF! | BE73: =+(BE30*75%)+(BE34*25%) -> #REF! | BF73: =+(BF30*75%)+(BF34*25%) -> #REF! | BG73: =+(BG30*75%)+(BG34*25%) -> #REF! | BH73: =+(BH30*75%)+(BH34*25%) -> #REF! | BI73: =+(BI30*75%)+(BI34*25%) -> #REF! | BJ73: =+(BJ30*75%)+(BJ34*25%) -> #REF! | ... CU73: =+(CU30*75%)+(CU34*25%) -> 841.78144
C74: Scrap 1% | Z74: =+Z73*1% -> 10.348922 | AA74: =+AA73*1% -> 9.6736379 | AB74: =+AB73*1% -> 10.156654 | AC74: =+AC73*1% -> 9.9234334 | AD74: =+AD73*1% -> 10.090562 | AE74: =+AE73*1% -> 10.038807 | AF74: =+AF73*1% -> 10.079638 | AG74: =+AG73*1% -> 6.9673858 | ... AU74: =+AU73*1% -> #REF! | AV74: 17.961366 | AW74: 18.250968 | AX74: =+AX73*1% -> #REF! | AY74: 19.119233 | AZ74: =+AZ73*1% -> #REF! | BA74: =+BA73*1% -> #REF! | BB74: =+BB73*1% -> #REF! | BC74: =+BC73*1% -> #REF! | BD74: =+BD73*1% -> #REF! | BE74: =+BE73*1% -> #REF! | BF74: =+BF73*1% -> #REF! | BG74: =+BG73*1% -> #REF! | ... CU74: =+CU73*1% -> 8.4178144
C75: Precio ponderado con scrap | Z75: =+Z74+Z73 -> 1045.2412 | AA75: =+AA74+AA73 -> 977.03742 | AB75: =+AB74+AB73 -> 1025.8221 | AC75: =+AC74+AC73 -> 1002.2668 | AD75: =+AD74+AD73 -> 1019.1467 | AE75: =+AE74+AE73 -> 1013.9195 | AF75: =+AF74+AF73 -> 1018.0434 | AG75: =+AG74+AG73 -> 703.70597 | ... AU75: =+AU74+AU73 -> #REF! | AV75: 1814.098 | AW75: 1843.3477 | AX75: =+AX74+AX73 -> #REF! | AY75: 1931.0425 | AZ75: =+AZ74+AZ73 -> #REF! | BA75: =+BA74+BA73 -> #REF! | BB75: =+BB74+BB73 -> #REF! | BC75: =+BC74+BC73 -> #REF! | BD75: =+BD74+BD73 -> #REF! | BE75: =+BE74+BE73 -> #REF! | BF75: =+BF74+BF73 -> #REF! | BG75: =+BG74+BG73 -> #REF! | ... CU75: =+CU74+CU73 -> 850.19925
C77: Precio ponderado bajo formula 75 PCR Intercia /25 Virgen | AT77: =+(AT40*75%)+(AT28*25%) -> #REF! | AU77: =+(AU40*75%)+(AU28*25%) -> #REF! | AV77: 2026.2018 | AW77: 2044.7899 | AX77: =+(AX40*75%)+(AX28*25%) -> #REF! | AY77: 2167.3695 | AZ77: =+(AZ40*75%)+(AZ28*25%) -> #REF! | BA77: =+(BA40*75%)+(BA28*25%) -> #REF! | BB77: =+(BB40*75%)+(BB28*25%) -> #REF! | BC77: =+(BC40*75%)+(BC30*25%) -> #REF! | BD77: =+(BD40*75%)+(BD30*25%) -> #REF! | BE77: =+(BE40*75%)+(BE30*25%) -> #REF! | BF77: =+(BF40*75%)+(BF30*25%) -> #REF! | BG77: =+(BG40*75%)+(BG30*25%) -> #REF! | BH77: =+(BH40*75%)+(BH30*25%) -> #REF! | BI77: =+(BI40*75%)+(BI30*25%) -> #REF! | BJ77: =+(BJ40*75%)+(BJ30*25%) -> #REF! | ... CU77: =+(CU40*75%)+(CU30*25%) -> 280.59381
C78: Scrap 1% | AT78: =+AT77*1% -> #REF! | AU78: =+AU77*1% -> #REF! | AV78: 20.262018 | AW78: 20.447899 | AX78: =+AX77*1% -> #REF! | AY78: 21.673695 | AZ78: =+AZ77*1% -> #REF! | BA78: =+BA77*1% -> #REF! | BB78: =+BB77*1% -> #REF! | BC78: =+BC77*1% -> #REF! | BD78: =+BD77*1% -> #REF! | BE78: =+BE77*1% -> #REF! | BF78: =+BF77*1% -> #REF! | BG78: =+BG77*1% -> #REF! | ... CU78: =+CU77*1% -> 2.8059381
C79: Precio ponderado con scrap | AT79: =+AT78+AT77 -> #REF! | AU79: =+AU78+AU77 -> #REF! | AV79: 2046.4638 | AW79: 2065.2378 | AX79: =+AX78+AX77 -> #REF! | AY79: 2189.0432 | AZ79: =+AZ78+AZ77 -> #REF! | BA79: =+BA78+BA77 -> #REF! | BB79: =+BB78+BB77 -> #REF! | BC79: =+BC78+BC77 -> #REF! | BD79: =+BD78+BD77 -> #REF! | BE79: =+BE78+BE77 -> #REF! | BF79: =+BF78+BF77 -> #REF! | BG79: =+BG78+BG77 -> #REF! | ... BT79: =+BT78+BT77 -> 305.28643 | BU79: =+BU49+BU50 -> 1787.964 | BV79: =+BV49+BV50 -> 1701.9791 | BW79: =+BW49+BW50 -> 1735.7341 | BX79: =+BX49+BX50 -> 1761.7138 | BY79: =+BY49+BY50 -> 1829.4647 | BZ79: =+BZ49+BZ50 -> 1804.7278 | CA79: =+CA49+CA50 -> 1899.9163 | CB79: =+CB49+CB50 -> 1983.176 | ... CU79: =+CU49+CU50 -> 1785.3235

Sheet Fórmula Marzo 26
D1: FÓRMULA
D11: PRECIOS DE RESINA ABI MARZO 2026
CQ12: 137.45455 | CR12: 76.363636 | CS12: 65.136364 | CT12: 39.954545 | CU12: 6.5909091 | CX12: 1. couldn’t figure out the formula here. If its colombia why is it not quarterly
AF13: Fórmula
B14: Translation | D14: PRICE | E14: Jul-18 | F14: Ago-2018 | G14: Sep-18 | H14: Oct-18 | I14: Nov-18 | J14: Dic-18 | K14: Ene-19 | L14: Feb-19 | M14: Mar-19 | N14: Abr-19 | O14: May-19 | P14: Jun-19 | Q14: Jul-19 | R14: Ago-19 | S14: Sep-19 | T14: Oct-19 | U14: Nov-20 | V14: Dic-20 | W14: Ene-20 | X14: Feb-20 | Y14: Mar-20 | Z14: Abr-20 | AA14: May-20 | AB14: Jun-20 | AC14: Jun-20 | AD14: Jul-20 | AE14: Jul-20 | AF14: Ago-20 | AG14: Ago-20 | AH14: Sep-20 | AI14: Oct-20 | AJ14: Nov-20 | AK14: Dic-20 | AL14: Ene-21 | AM14: Feb-21 | AN14: Mar-21 | AO14: Abr-21 | AP14: May-21 | AQ14: Jun-21 | AR14: Jul-21 | AS14: Ago-21 | AT14: Sep-21 | AU14: Oct-21 | AV14: Nov-21 | AW14: Dic-21 | AX14: Ene-22 | AY14: Feb-22 | AZ14: Mar-22 | BA14: Abr-22 | BB14: Mayo-22 | BC14: Junio-22 | BD14: Julio-22 | BE14: Agosto-22 | BF14: Septiembre-22 | BG14: Octubre-22 | BH14: Noviembre-22 | BI14: Diciembre-22 | BJ14: Enero-23 | BK14: Febrero-23 | BL14: Marzo-23 | BM14: Abril-23 | BN14: Mayo-23 | BO14: Junio-23 | BP14: Julio-23 | BQ14: Agosto-23 | BR14: Septiembre-23 | BS14: Octubre-23 | BT14: Noviembre-23 | BU14: Diciembre-23 | BV14: Enero-24 | BW14: Febrero-24 | BX14: Marzo-24 | BY14: Abril-24 | BZ14: Mayo-24 | CA14: Junio-24 | CB14: Julio-24 | CC14: Agosto-24 | CD14: Septiembre-24 | CE14: Octubre-24 | CF14: Noviembre-24 | CG14: Diciembre-24 | CH14: Enero-25 | CI14: Febrero-25 | CJ14: Marzo-25 | CK14: Abril-25 | CL14: Mayo-25 | CM14: Junio-25 | CN14: Julio-25 | CO14: Agosto-25 | CP14: Septie-25 | CQ14: Oct-25 | CR14: Nov-25 | CS14: Dic-25 | CT14: Ene-26 | CU14: Feb-26 | CV14: Mar-26 | CX14: Resina Virgen
B15: Resin Price Index | D15: ICIS China MID (n-1). | E15: May-18 | F15: Jun-18 | G15: Jul-18 | H15: Ago-18 | I15: Sep-18 | J15: Oct-18 | K15: Nov-18 | L15: Dic-18 | M15: Jan-19 | N15: Feb-19 | O15: Mar-19 | P15: Abr-19 | Q15: May-19 | R15: Jun-19 | S15: Jul-19 | T15: Ago-19 | U15: Sep-19 | V15: Oct-19 | W15: Nov-19 | X15: Dic-19 | Y15: Jan-20 | Z15: Feb-20 | AA15: Mar-20 | AB15: Abr-20 | AC15: Abr-20 | AD15: May-20 | AE15: May-20 | AF15: Jun-20 | AG15: Jun-20 | AH15: Jul-20 | AI15: Ago-20 | AJ15: Sep-20 | AK15: Oct-20 | AL15: Nov-20 | AM15: Dic-20 | AN15: Jan-21 | AO15: 44228 | AP15: 44256 | AQ15: 44287 | AR15: 44317 | AS15: 44348 | AT15: 44378 | AU15: 44409 | AV15: 44440 | AW15: 44440 | AX15: 44501 | AY15: 44531 | AZ15: 44562 | BA15: 44593 | BB15: 44621 | BC15: 44652 | BD15: 44682 | BE15: 44713 | BF15: 44743 | BG15: 44774 | BH15: 44805 | BI15: 44835 | BJ15: 44866 | BK15: 44896 | BL15: 44927 | BM15: 44958 | BN15: 44986 | BO15: 45017 | BP15: 45047 | BQ15: 45078 | BR15: 45108 | BS15: 45139 | BT15: 45170 | BU15: 45200 | BV15: 45231 | BW15: 45261 | BX15: 44927 | BY15: 44958 | BZ15: 44986 | CA15: 45017 | CB15: 45047 | CC15: 45078 | CD15: 45108 | CE15: 45139 | CF15: 45536 | CG15: 45566 | CH15: 45597 | CI15: 45627 | CJ15: 45658 | CK15: 45689 | CL15: 45717 | CM15: 45748 | CN15: 45778 | CO15: 45809 | CP15: 45839 | CQ15: 45870 | CR15: 45901 | CS15: 45931 | CT15: 45962 | CU15: 45992 | CV15: 46023 | CX15: Descripcion. | CY15: MAYO | CZ15: JUNIO | DA15: JULIO | DB15: AGOSTO | DC15: SEPTIEMBRE | DD15: OCTUBRE | DE15: NOVIEMBRE | DF15: DICIEMBRE | DG15: ENERO | DH15: FEBRERO | DI15: MARZO | DJ15: ABRIL | DK15: MAYO | DL15: JUNIO | DM15: JULIO | DN15: AGOSTO | DO15: SEPTIEMBRE | DP15: OCTUBRE | DQ15: NOVIEMBRE | DR15: DICIEMBRE | DS15: ENERO | DT15: FEBRERO | DU15: MARZO | DV15: ABRIL | DW15: MAYO | DX15: JUNIO | DY15: JULIO | DZ15: AGOSTO | EA15: SEPTIEM | EB15: OCTUBRE | EC15: NOVIEMBRE | ED15: DICIEMBRE | EE15: ENERO | EF15: FEBRERO | EG15: MARZO
E16: 1330 | F16: 1280 | G16: 1279.38 | H16: 1275.5 | I16: 1330 | J16: 1266.25 | K16: 1125 | L16: 1058.13 | M16: 1035 | N16: 1077.5 | O16: 1096.25 | P16: 1101.25 | Q16: 1004.5 | R16: 926.25 | S16: 966.88 | T16: 889 | U16: 868.75 | V16: 840 | W16: 818.75 | X16: 824.38 | Y16: 840 | Z16: 840 | AA16: 736.88 | AB16: 655 | AC16: 707.17946 | AD16: 669.38 | AE16: 687.43458 | AF16: 678.13 | AG16: 682.5409 | AH16: 659 | AI16: 647.5 | AJ16: 649.38 | AK16: 641.5 | AL16: 648.13 | AM16: 713 | AN16: 789.38 | AO16: 880.63 | AP16: 1018.75 | AQ16: 960 | AR16: 932.5 | AS16: 920 | AT16: 960 | AU16: 966.25 | AV16: 953 | AW16: 1111.88 | AX16: 1124.38 | AY16: 1026.5 | AZ16: 1144 | BA16: 1138 | BB16: 1139 | BC16: 1199 | BD16: 1216.25 | BE16: 1235 | BF16: 1125 | BG16: 1096.25 | BH16: 1048 | BI16: 975.63 | BJ16: 897.5 | BK16: 890 | BL16: 941.88 | BM16: 965 | BN16: 980 | BO16: 1018.75 | BP16: 938.13 | BQ16: 882 | BR16: 878.75 | BS16: 889 | BT16: 898.75 | BU16: 880 | BV16: 865 | BW16: 863.13 | BX16: 889.38 | BY16: 906.5 | BZ16: 906.5 | CA16: 898.13 | CB16: 885 | CC16: 885.63 | CD16: 896.25 | CE16: 874 | CF16: 815 | CG16: 842 | CH16: 802.5 | CI16: 791.25 | CJ16: 799.5 | CK16: 803.125 | CL16: 786.25 | CM16: 745.625 | CN16: 775 | CO16: 793.125 | CP16: 781.875 | CQ16: =+'ICIS -1'!C16 -> 774 | CR16: =+'ICIS -1'!C17 -> 765 | CS16: =+'ICIS -1'!C18 -> 752 | CT16: =+'ICIS -1'!C19 -> 748.75 | CU16: =+'ICIS -1'!C20 -> 756.25 | CV16: =+'ICIS -1'!C21 -> 821.075 | CX16: Inv Inicial TON | CY16: 327.54748 | CZ16: 455.56748 | DA16: 551.38748 | DB16: 361.38748 | DC16: 321.644 | DD16: 392.25652 | DE16: 392.25652 | DF16: =+DE19 -> 350.06179 | DG16: =+DF19 -> 316.06179 | DH16: =+DG19 -> 350.84056 | DI16: =+DG19 -> 350.84056 | DJ16: =+DI19 -> 379.54056 | DK16: =+DJ19 -> 307.54056 | DL16: =+DK19 -> 307.52056 | DM16: =+DL19 -> 236.82841 | DN16: =+DM19 -> 139.47841 | DO16: =+DN19 -> 217.93712 | DP16: =+DO19 -> 120.58712 | DQ16: =+DP19 -> 317.58712 | ... EG16: =+EF19 -> 304.9584
B17: Finance | D17: Finance | E17: =+E16*4.5%/365*210 -> 34.434247 | F17: =+F16*4.5%/365*210 -> 33.139726 | G17: =+G16*4.5%/365*210 -> 33.123674 | H17: =+H16*4.5%/365*210 -> 33.023219 | I17: =+I16*4.5%/365*210 -> 34.434247 | J17: =+J16*4.5%/365*210 -> 32.783733 | K17: =+K16*4.5%/365*210 -> 29.126712 | L17: =+L16*(4.5%+1.59%)/365*210 -> 37.075136 | M17: =+M16*(4.5%+1.59%)/365*210 -> 36.264699 | N17: =+N16*(4.5%+1.59%)/365*210 -> 37.753829 | O17: =+O16*(4.5%+1.59%)/365*210 -> 38.410798 | P17: =+P16*(4.5%+1.59%)/365*210 -> 38.58599 | Q17: =+Q16*(4.5%+1.59%)/365*210 -> 35.196029 | R17: =+R16*(4.5%+1.59%)/365*210 -> 32.454277 | S17: =+S16*(4.5%+1.59%)/365*210 -> 33.877886 | ... V17: =+V16*(4.5%+1.59%)/365*210 -> 29.432219 | W17: =+W16*(4.5%+1.59%+1.9%)/365*210 -> 37.637825 | X17: =+X16*(4.5%+1.59%+1.9%)/365*210 -> 37.896636 | Y17: =+Y16*(4.5%+1.59%+1.9%)/365*210 -> 38.614685 | Z17: =+Z16*(4.5%+1.59%+1.9%)/365*210 -> 38.614685 | AA17: =+AA16*(4.5%+1.59%+1.9%)/365*210 -> 33.874273 | AB17: =+AB16*(4.5%+1.59%+1.9%)/365*210 -> 30.11026 | AC17: =+AC16*(4.5%+1.59%+1.9%)/365*210 -> 32.508943 | AD17: =+AD16*(4.5%+1.59%+1.9%)/365*210 -> 30.771307 | ... AI17: =+AI16*(4.5%+1.59%+1.9%)/365*210 -> 29.765486 | AJ17: 29.85191 | AK17: 29.489667 | AL17: 29.794447 | AM17: 32.776512 | AN17: 36.28769 | AO17: 40.48244 | AP17: 46.831798 | AQ17: 44.131068 | AR17: 24.529984 | AS17: 24.529984 | AT17: 25.253388 | AU17: 25.253388 | AV17: 25.069249 | AW17: 18.010318 | AX17: 20.073418 | AY17: 27.002711 | AZ17: 20 | BA17: 20 | BB17: 20 | BC17: 21 | BD17: 31.994202 | BE17: 32.487432 | BF17: 29.593814 | BG17: 28.837528 | BH17: 27.568282 | BI17: 25.664545 | BJ17: 41.03519 | BK17: 40.692278 | BL17: 48.654829 | BM17: 49.337828 | BN17: 49.255313 | BO17: 52.190236 | BP17: 49.095804 | BQ17: 45.969807 | BR17: 45.510666 | BS17: 47.311118 | BT17: 47.547395 | BU17: 45.827422 | BV17: =+(BV16+BV19+BV18)*SOFR!$F$3 -> 35.374019 | BW17: =+(BW16+BW19+BW18)*SOFR!$F$3 -> 35.877641 | BX17: =+(BX16+BX19+BX18)*SOFR!$F$3 -> 36.795528 | BY17: =+(BY16+BY19+BY18)*SOFR!$F$3 -> 37.497477 | BZ17: =+(BZ16+BZ19+BZ18)*SOFR!$F$3 -> 37.497477 | CA17: 52.325208 | CB17: 56.881264 | CC17: 58.27184 | CD17: 54.343859 | CE17: 54.263773 | CF17: 48.211712 | CG17: 49.1991 | CH17: =+(CH16+CH19+CH18)*SOFR!$F$3 -> 35.531371 | CI17: =+(CI16+CI19+CI18)*SOFR!$F$3 -> 35.137991 | CJ17: =+(CJ16+CJ19+CJ18)*SOFR!$F$3 -> 35.168984 | CK17: =+(CK16+CK19+CK18)*SOFR!$F$3 -> 33.755597 | CL17: =+(CL16+CL19+CL18)*SOFR!$F$3 -> 33.349899 | CM17: =+(CM16+CM19+CM18)*SOFR!$F$3 -> 31.182334 | CN17: =+(CN16+CN19+CN18)*SOFR!$F$3 -> 32.293733 | CO17: =+(CO16+CO19+CO18)*SOFR!$F$3 -> 40.327828 | ... CV17: =+(CV16+CV19+CV18)*SOFR!$F$3 -> 32.332912 | CX17: Entradas TON | CY17: 467 | CZ17: 396 | DA17: 113 | DB17: 260 | DC17: 370.61252 | DD17: 313 | DE17: 313 | DF17: 313 | DG17: 313 | DH17: 313 | DI17: 313 | DJ17: 200 | DK17: 300 | DL17: 300 | DM17: 300 | DN17: 500 | DO17: 300 | DP17: 550 | DQ17: 300 | DR17: 400 | DS17: 100 | DT17: =455+160 -> 615 | DU17: =330+23 -> 353 | DV17: =330+23 -> 353 | DW17: =330+23 -> 353 | DX17: 250 | DY17: 200 | DZ17: 450 | EA17: 500 | EB17: 500 | EC17: 300 | ED17: 200 | EE17: 200 | EF17: 200 | EG17: 200
B18: Freight China-Buenaventura (Regular) | D18: Freight China-Buenaventura (reg) | E18: 90 | F18: 90 | G18: 90 | H18: 90 | I18: 90 | J18: 90 | K18: 90 | L18: 90 | M18: 90 | N18: 90 | O18: 90 | P18: 90 | Q18: 90 | R18: 90 | S18: 90 | T18: 90 | U18: 90 | V18: 91 | W18: =+V18*(1+1.9%) -> 92.729 | X18: =+W18*(1+1.9%) -> 94.490851 | Y18: =+X18*(1+1.9%) -> 96.286177 | Z18: =+Y18 -> 96.286177 | AA18: =+Z18 -> 96.286177 | AB18: =+AA18 -> 96.286177 | AC18: =+AB18 -> 96.286177 | AD18: =+AC18 -> 96.286177 | AE18: =+AD18 -> 96.286177 | AF18: =+AE18 -> 96.286177 | AG18: =+AF18 -> 96.286177 | ... AQ18: =+AP18 -> 96.286177 | AR18: 96.286177 | AS18: 96.286177 | AT18: 96.286177 | AU18: 96.286177 | AV18: 96.286177 | AW18: 96.286177 | AX18: 96.286177 | AY18: 97.286177 | AZ18: 97.286177 | BA18: 97.286177 | BB18: 97.286177 | BC18: 97.286177 | BD18: 97.286177 | BE18: 97.286177 | BF18: 97.286177 | BG18: 97.286177 | BH18: 97.286177 | BI18: 97.286177 | BJ18: 97.286177 | BK18: 97.286177 | BL18: 97.286177 | BM18: 97.286177 | BN18: 97.286177 | BO18: 97.286177 | BP18: 97.286177 | BQ18: 97.286177 | BR18: 97.286177 | BS18: 97.286177 | BT18: 97.286177 | BU18: 97.286177 | BV18: 97.286177 | BW18: 97.286177 | BX18: 97.286177 | BY18: 97.286177 | BZ18: 97.286177 | CA18: 97.286177 | CB18: 97.286177 | CC18: 97.286177 | CD18: 97.286177 | CE18: 97.286177 | CF18: 97.286177 | CG18: 97.286177 | CH18: 97.286177 | CI18: 97.286177 | CJ18: 97.286177 | CK18: 97.286177 | CL18: 97.286177 | CM18: 97.286177 | CN18: 97.286177 | CO18: 97.286177 | CP18: 97.286177 | CQ18: 97.286177 | CR18: 97.286177 | CS18: 97.286177 | CT18: 97.286177 | CU18: 97.286177 | CV18: 97.286177 | CX18: Consumo TON | CY18: 338.98 | CZ18: 300.18 | DA18: 303 | DB18: 299.74348 | DC18: 300 | DD18: 313 | DE18: 355.19473 | DF18: 347 | DG18: 278.22123 | DH18: 244 | DI18: 284.3 | DJ18: 272 | DK18: 300.02 | DL18: 370.69216 | DM18: 397.35 | DN18: 421.54128 | DO18: 397.35 | DP18: 353 | DQ18: 320 | DR18: 309.39819 | DS18: 310 | DT18: 265.94053 | DU18: 328.29 | DV18: 338 | DW18: 371 | DX18: 350 | DY18: 349 | DZ18: 349 | EA18: 300 | EB18: 300 | EC18: 349 | ED18: 349 | EE18: 349 | EF18: 349 | EG18: 349
B19: Freight China-Buenaventura (Incremental) | D19: Freight China-Buenaventura (Incr) | AR19: =+Drewry!B3-'Fórmula Marzo 26'!AR18 -> 253.71382 | AS19: =+Drewry!C3-'Fórmula Marzo 26'!AS18 -> 290.07746 | AT19: =+Drewry!D3-'Fórmula Marzo 26'!AT18 -> 398.71382 | AU19: =+Drewry!E3-'Fórmula Marzo 26'!AU18 -> 442.35019 | AV19: =+Drewry!F3-'Fórmula Marzo 26'!AV18 -> 480.98655 | AW19: 480.98655 | AX19: 480.98655 | AY19: =+Drewry!I3-'Fórmula Marzo 26'!AY18 -> 479.98655 | AZ19: 480 | BA19: 480 | BB19: 452 | BC19: 383 | BD19: =+Drewry!N3-'Fórmula Marzo 26'!BD18 -> 383.62291 | BE19: =+Drewry!O3-'Fórmula Marzo 26'!BE18 -> 399.07746 | BF19: =+Drewry!P3-'Fórmula Marzo 26'!BF18 -> 399.07746 | BG19: =+Drewry!Q3-'Fórmula Marzo 26'!BG18 -> 386.35019 | BH19: =+Drewry!R3-'Fórmula Marzo 26'!BH18 -> 309.532 | BI19: =+Drewry!S3-'Fórmula Marzo 26'!BI18 -> 178.62291 | BJ19: =+Drewry!T3-'Fórmula Marzo 26'!BJ18 -> 123.16837 | BK19: =+Drewry!U3-'Fórmula Marzo 26'!BK18 -> 123.16837 | BL19: =+IF(Drewry!V3-'Fórmula Marzo 26'!BL18<0,0,Drewry!V3-'Fórmula Marzo 26'!BL18) -> 24.98655 | BM19: =+IF(Drewry!W3-'Fórmula Marzo 26'!BM18<0,0,Drewry!W3-'Fórmula Marzo 26'!BM18) -> 16.804732 | BN19: =+IF(Drewry!X3-'Fórmula Marzo 26'!BN18<0,0,Drewry!X3-'Fórmula Marzo 26'!BN18) -> 0 | BO19: =+IF(Drewry!Y3-'Fórmula Marzo 26'!BO18<0,0,Drewry!Y3-'Fórmula Marzo 26'!BO18) -> 25.441096 | BP19: =+IF(Drewry!Z3-'Fórmula Marzo 26'!BP18<0,0,Drewry!Z3-'Fórmula Marzo 26'!BP18) -> 46.032005 | BQ19: =+IF(Drewry!AA3-'Fórmula Marzo 26'!BQ18<0,0,Drewry!AA3-'Fórmula Marzo 26'!BQ18) -> 33.304732 | BR19: =+IF(Drewry!AB3-'Fórmula Marzo 26'!BR18<0,0,Drewry!AB3-'Fórmula Marzo 26'!BR18) -> 26.441096 | BS19: =+IF(Drewry!AC3-'Fórmula Marzo 26'!BS18<0,0,Drewry!AC3-'Fórmula Marzo 26'!BS18) -> 55.850186 | ... BW19: =+IF(Drewry!AG3-'Fórmula Marzo 26'!BW18<0,0,Drewry!AG3-'Fórmula Marzo 26'!BW18) -> 65.622914 | BX19: =+IF(Drewry!AG3-'Fórmula Marzo 26'!BX18<0,0,Drewry!AG3-'Fórmula Marzo 26'!BX18) -> 65.622914 | BY19: =+IF(Drewry!AI3-'Fórmula Marzo 26'!BY18<0,0,Drewry!AI3-'Fórmula Marzo 26'!BY18) -> 68.577459 | BZ19: =+IF(Drewry!AI3-'Fórmula Marzo 26'!BZ18<0,0,Drewry!AI3-'Fórmula Marzo 26'!BZ18) -> 68.577459 | CA19: =+IF(Drewry!AK3-'Fórmula Marzo 26'!CA18<0,0,Drewry!AK3-'Fórmula Marzo 26'!CA18) -> 177.66837 | CB19: =+IF(Drewry!AL3-'Fórmula Marzo 26'!CB18<0,0,Drewry!AL3-'Fórmula Marzo 26'!CB18) -> 292.9411 | CC19: =+IF(Drewry!AM3-'Fórmula Marzo 26'!CC18<0,0,Drewry!AM3-'Fórmula Marzo 26'!CC18) -> 323.48655 | CD19: =+IF(Drewry!AN3-'Fórmula Marzo 26'!CD18<0,0,Drewry!AN3-'Fórmula Marzo 26'!CD18) -> 224.80473 | CE19: =+IF(Drewry!AO3-'Fórmula Marzo 26'!CE18<0,0,Drewry!AO3-'Fórmula Marzo 26'!CE18) -> 245.25928 | CF19: =+IF(Drewry!AP3-'Fórmula Marzo 26'!CF18<0,0,Drewry!AP3-'Fórmula Marzo 26'!CF18) -> 168.57746 | CG19: =+IF(Drewry!AQ3-'Fórmula Marzo 26'!CG18<0,0,Drewry!AQ3-'Fórmula Marzo 26'!CG18) -> 163.71382 | CH19: =+IF(Drewry!AR3-'Fórmula Marzo 26'!CH18<0,0,Drewry!AR3-'Fórmula Marzo 26'!CH18) -> 116.35019 | ... CV19: =+IF(Drewry!BF3-'Fórmula Marzo 26'!CV18<0,0,Drewry!BF3-'Fórmula Marzo 26'!CV18) -> 6.3047319 | CX19: Inv Final TON | CY19: 455.56748 | CZ19: 551.38748 | DA19: 361.38748 | DB19: 321.644 | DC19: 392.25652 | DD19: 392.25652 | DE19: 350.06179 | DF19: =+(DF16+DF17-DF18) -> 316.06179 | DG19: =+(DG16+DG17-DG18) -> 350.84056 | DH19: =+(DH16+DH17-DH18) -> 419.84056 | DI19: =+(DI16+DI17-DI18) -> 379.54056 | DJ19: =+(DJ16+DJ17-DJ18) -> 307.54056 | DK19: =+(DK16+DK17-DK18) -> 307.52056 | DL19: =+(DL16+DL17-DL18) -> 236.82841 | DM19: =+(DM16+DM17-DM18) -> 139.47841 | ... EG19: =+(EG16+EG17-EG18) -> 155.9584
B20: Sub Total (with Incremental Freight) | D20: Sub total (con flete Inc) | E20: =SUM(E16:E18) -> 1454.4342 | F20: =SUM(F16:F18) -> 1403.1397 | G20: =SUM(G16:G18) -> 1402.5037 | H20: =SUM(H16:H18) -> 1398.5232 | I20: =SUM(I16:I18) -> 1454.4342 | J20: =SUM(J16:J18) -> 1389.0337 | K20: =SUM(K16:K18) -> 1244.1267 | L20: =SUM(L16:L18) -> 1185.2051 | ... AQ20: =SUM(AQ16:AQ18) -> 1100.4172 | AR20: =SUM(AR16:AR19) -> 1307.03 | AS20: =SUM(AS16:AS19) -> 1330.8936 | AT20: =SUM(AT16:AT19) -> 1480.2534 | AU20: =SUM(AU16:AU19) -> 1530.1398 | AV20: =SUM(AV16:AV19) -> 1555.342 | AW20: 1707.163 | AX20: 1721.7261 | AY20: =SUM(AY16:AY19) -> 1630.7754 | AZ20: 1741 | BA20: 1736 | BB20: 1709 | BC20: 1701 | BD20: =SUM(BD16:BD19) -> 1729.1533 | BE20: =SUM(BE16:BE19) -> 1763.8511 | BF20: =SUM(BF16:BF19) -> 1650.9575 | BG20: =SUM(BG16:BG19) -> 1608.7239 | BH20: =SUM(BH16:BH19) -> 1482.3865 | BI20: =SUM(BI16:BI19) -> 1277.2036 | BJ20: =SUM(BJ16:BJ19) -> 1158.9897 | BK20: =SUM(BK16:BK19) -> 1151.1468 | ... CV20: =SUM(CV16:CV19) -> 956.99882
B21: Sub Total (with Regular Freight) | D21: Sub total (con flete reg) | AR21: =+SUM(AR16:AR18) -> 1053.3162 | AS21: =+SUM(AS16:AS18) -> 1040.8162 | AT21: =+SUM(AT16:AT18) -> 1081.5396 | AU21: =+SUM(AU16:AU18) -> 1087.7896 | AV21: =+SUM(AV16:AV18) -> 1074.3554 | AW21: 1226.1765 | AX21: 1240.7396 | AY21: =+SUM(AY16:AY18) -> 1150.7889 | AZ21: 1261 | BA21: 1256 | BB21: 1257 | BC21: 1317 | BD21: =+SUM(BD16:BD18) -> 1345.5304 | BE21: =+SUM(BE16:BE18) -> 1364.7736 | BF21: =+SUM(BF16:BF18) -> 1251.88 | BG21: =+SUM(BG16:BG18) -> 1222.3737 | BH21: =+SUM(BH16:BH18) -> 1172.8545 | BI21: =+SUM(BI16:BI18) -> 1098.5807 | BJ21: =+SUM(BJ16:BJ18) -> 1035.8214 | BK21: =+SUM(BK16:BK18) -> 1027.9785 | ... CV21: =+SUM(CV16:CV18) -> 950.69409 | CX21: Precio Inv Inical | CY21: 1258.4919 | CZ21: 1267.0143 | DA21: 1304.1208 | DB21: 1298.9693 | DC21: 1254.8429 | DD21: 1215.9045 | DE21: 1220.6547 | DF21: =+DE24 -> 1226.1867 | DG21: =+DF24 -> 1209.0552 | DH21: =+DG24 -> 1194.1872 | DI21: =+DG24 -> 1194.1872 | DJ21: =+DH24 -> 1203.3754 | DK21: =+DJ24 -> 1225.5446 | DL21: =+DK24 -> 1246.3188 | DM21: =+DL24 -> 1317.0024 | DN21: =+DM24 -> 1419.7187 | DO21: =+DN24 -> 1509.9821 | DP21: =+DO24 -> 1468.9302 | DQ21: =+DP24 -> 1441.3902 | DR21: =+DQ24 -> 1363.6378 | ... EG21: =+EF24 -> 1137.1396
B22: Duty 5% (Change According to Regulation) | D22: Duty 5% (Cambio de acuerdo a la regulación) | E22: =+E20*0.1 -> 145.44342 | F22: =+F20*0.1 -> 140.31397 | G22: =+G20*0.1 -> 140.25037 | H22: =+H20*0.1 -> 139.85232 | I22: =+I20*0.1 -> 145.44342 | J22: =+J20*0.1 -> 138.90337 | K22: =+K20*0.1 -> 124.41267 | L22: =+L20*0.1 -> 118.52051 | ... AT22: =+AT20*0.1 -> 148.02534 | AU22: =+AU20*0.05 -> 76.506988 | AV22: =+AV20*0.05 -> 77.767099 | AW22: 85.358152 | AX22: 86.086307 | AY22: =+AY20*0.05 -> 81.538772 | AZ22: 87.033091 | BA22: =+BA20*0.05 -> 86.8 | BB22: =+BB20*0.05 -> 85.45 | BC22: =+BC20*0.05 -> 85.05 | BD22: =+BD20*0.05 -> 86.457665 | BE22: =+BE20*0.05 -> 88.192553 | BF22: =+BF20*0.05 -> 82.547873 | BG22: =+BG20*0.05 -> 80.436195 | BH22: =+BH20*0.05 -> 74.119323 | ... CV22: =+CV20*0.05 -> 47.849941 | CX22: Precio Ingreso | CY22: 1272.9919 | CZ22: 1346.809 | DA22: 1273.8321 | DB22: 1193.5092 | DC22: 1182.1111 | DD22: 1226.6076 | DE22: 1233.1194 | DF22: =+BU26 -> 1189.8952 | DG22: =+BV26 -> 1179.1737 | DH22: =+BW26 -> 1213.6744 | DI22: =+BX26 -> 1244.3742 | DJ22: =+BY26 -> 1267.6152 | DK22: =+BZ26 -> 1267.6152 | DL22: =+CA26 -> 1389.4579 | DM22: =+CB26 -> 1500.8057 | ... EG22: =+CV26 -> 1099.8627
B23: Landed Factor 8% | D23: Landed factor 8% | E23: =+E20*8% -> 116.35474 | F23: =+F20*8% -> 112.25118 | G23: =+G20*8% -> 112.20029 | H23: =+H20*8% -> 111.88186 | I23: =+I20*8% -> 116.35474 | J23: =+J20*8% -> 111.1227 | K23: =+K20*8% -> 99.530137 | L23: =+L20*8% -> 94.816411 | ... AQ23: =+AQ20*8% -> 88.03338 | AR23: =+AR21*8% -> 84.265293 | AS23: =+AS21*8% -> 83.265293 | AT23: =+AT21*8% -> 86.523165 | AU23: =+AU21*8% -> 87.023165 | AV23: =+AV21*8% -> 85.948434 | AW23: 98.09412 | AX23: 99.259168 | AY23: =+AY21*8% -> 92.063111 | AZ23: 100.85039 | BA23: =+BA21*8% -> 100.48 | BB23: =+BB21*8% -> 100.56 | BC23: =+BC21*8% -> 105.36 | BD23: =+BD21*8% -> 107.64243 | BE23: =+BE21*8% -> 109.18189 | BF23: =+BF21*8% -> 100.1504 | BG23: =+BG21*8% -> 97.789896 | BH23: =+BH21*8% -> 93.828357 | ... CV23: =+CV21*8% -> 76.055527 | CX23: Precio Consumo | CY23: 1267.0143 | CZ23: 1304.1208 | DA23: 1298.9693 | DB23: 1254.8429 | DC23: 1215.9045 | DD23: 1220.6547 | DE23: 1226.1867 | DF23: =+SUMPRODUCT(DF16:DF17,DF21:DF22)/SUM(DF16:DF17) -> 1209.0552 | DG23: =+SUMPRODUCT(DG16:DG17,DG21:DG22)/SUM(DG16:DG17) -> 1194.1872 | DH23: =+SUMPRODUCT(DH16:DH17,DH21:DH22)/SUM(DH16:DH17) -> 1203.3754 | DI23: =+SUMPRODUCT(DI16:DI17,DI21:DI22)/SUM(DI16:DI17) -> 1217.8503 | DJ23: =+SUMPRODUCT(DJ16:DJ17,DJ21:DJ22)/SUM(DJ16:DJ17) -> 1225.5446 | DK23: =+SUMPRODUCT(DK16:DK17,DK21:DK22)/SUM(DK16:DK17) -> 1246.3188 | DL23: =+SUMPRODUCT(DL16:DL17,DL21:DL22)/SUM(DL16:DL17) -> 1317.0024 | DM23: =+SUMPRODUCT(DM16:DM17,DM21:DM22)/SUM(DM16:DM17) -> 1419.7187 | ... EG23: =+SUMPRODUCT(EG16:EG17,EG21:EG22)/SUM(EG16:EG17) -> 1122.3753
B24: ZF Legislation Change | D24: Cambio legislacion ZF | BW24: =+('Cambio en Condiciones ZF'!$H$23/'PCR Enka'!$CD$22)/22 -> 18.958371 | BX24: =+('Cambio en Condiciones ZF'!$H$23/'PCR Enka'!$CD$22)/22 -> 18.958371 | BY24: =+('Cambio en Condiciones ZF'!$H$23/'PCR Enka'!$CD$22)/22 -> 18.958371 | BZ24: =+('Cambio en Condiciones ZF'!$H$23/'PCR Enka'!$CD$22)/22 -> 18.958371 | CA24: =+('Cambio en Condiciones ZF'!$H$23/'PCR Enka'!$CD$22)/22 -> 18.958371 | CB24: =+('Cambio en Condiciones ZF'!$H$23/'PCR Enka'!$CD$22)/22 -> 18.958371 | CC24: =+('Cambio en Condiciones ZF'!$H$23/'PCR Enka'!$CD$22)/22 -> 18.958371 | CD24: =+('Cambio en Condiciones ZF'!$H$23/'PCR Enka'!$CD$22)/22 -> 18.958371 | ... CV24: =+('Cambio en Condiciones ZF'!$H$23/'PCR Enka'!$CD$22)/22 -> 18.958371 | CX24: Precio Inv Final | CY24: 1267.0143 | CZ24: 1304.1208 | DA24: 1298.9693 | DB24: 1254.8429 | DC24: 1215.9045 | DD24: 1220.6547 | DE24: 1226.1867 | DF24: =+(SUMPRODUCT(DF16:DF17,DF21:DF22)-(DF18*DF23))/DF19 -> 1209.0552 | DG24: =+(SUMPRODUCT(DG16:DG17,DG21:DG22)-(DG18*DG23))/DG19 -> 1194.1872 | DH24: =+(SUMPRODUCT(DH16:DH17,DH21:DH22)-(DH18*DH23))/DH19 -> 1203.3754 | DI24: =+(SUMPRODUCT(DI16:DI17,DI21:DI22)-(DI18*DI23))/DI19 -> 1217.8503 | DJ24: =+(SUMPRODUCT(DJ16:DJ17,DJ21:DJ22)-(DJ18*DJ23))/DJ19 -> 1225.5446 | DK24: =+(SUMPRODUCT(DK16:DK17,DK21:DK22)-(DK18*DK23))/DK19 -> 1246.3188 | DL24: =+(SUMPRODUCT(DL16:DL17,DL21:DL22)-(DL18*DL23))/DL19 -> 1317.0024 | DM24: =+(SUMPRODUCT(DM16:DM17,DM21:DM22)-(DM18*DM23))/DM19 -> 1419.7187 | ... EG24: =+(SUMPRODUCT(EG16:EG17,EG21:EG22)-(EG18*EG23))/EG19 -> 1122.3753
B25: Sur Charge Alpek Br | D25: Sur Charge Alpek Br | CM25: 135 | CN25: 135 | CO25: 135 | CP25: 0 | CQ25: 0 | CR25: 0 | CS25: 0 | CT25: 0 | CU25: 0 | CV25: 0
B26: Total Resin Price ABI VIRGIN Formula | D26: Total resin price ABI Fórmula VIRGEN | E26: =+E20+E22+E23 -> 1716.2324 | F26: =+F20+F22+F23 -> 1655.7049 | G26: =+G20+G22+G23 -> 1654.9543 | H26: =+H20+H22+H23 -> 1650.2574 | I26: =+I20+I22+I23 -> 1716.2324 | J26: =+J20+J22+J23 -> 1639.0598 | K26: =+K20+K22+K23 -> 1468.0695 | L26: =+L20+L22+L23 -> 1398.5421 | ... AV26: =+AV20+AV22+AV23 -> 1719.0575 | AW26: 1890.6153 | AX26: 1907.0716 | AY26: =+AY20+AY22+AY23 -> 1804.3773 | AZ26: 1928.5453 | BA26: =+BA20+BA22+BA23 -> 1923.28 | BB26: =+BB20+BB22+BB23 -> 1895.01 | BC26: =+BC20+BC22+BC23 -> 1891.41 | BD26: =+BD20+BD22+BD23 -> 1923.2534 | BE26: =+BE20+BE22+BE23 -> 1961.2255 | BF26: =+BF20+BF22+BF23 -> 1833.6557 | BG26: =+BG20+BG22+BG23 -> 1786.95 | BH26: =+BH20+BH22+BH23 -> 1650.3341 | ... BV26: =+BV20+BV22+BV23 -> 1179.1737 | BW26: =+BW20+BW22+BW23+BW24 -> 1213.6744 | BX26: =+BX20+BX22+BX23+BX24 -> 1244.3742 | BY26: =+BY20+BY22+BY23+BY24 -> 1267.6152 | BZ26: =+BZ20+BZ22+BZ23+BZ24 -> 1267.6152 | CA26: =+CA20+CA22+CA23+CA24 -> 1389.4579 | CB26: =+CB20+CB22+CB23+CB24 -> 1500.8057 | CC26: =+CC20+CC22+CC23+CC24 -> 1535.1617 | CD26: =+CD20+CD22+CD23+CD24 -> 1439.1078 | ... CL26: =+CL20+CL22+CL23+CL24 -> 1128.7642 | CM26: =+CM20+CM22+CM23+CM24+CM25 -> 1192.9767 | CN26: =+CN20+CN22+CN23+CN24+CN25 -> 1229.9559 | CO26: =+CO20+CO22+CO23+CO24+CO25 -> 1481.7339 | CP26: =+CP20+CP22+CP23+CP24+CP25 -> 1224.477 | CQ26: =+CQ20+CQ22+CQ23+CQ24+CQ25 -> 1204.7186 | CR26: =+CR20+CR22+CR23+CR24+CR25 -> 1176.8598 | CS26: =+CS20+CS22+CS23+CS24+CS25 -> 1095.0968 | CT26: =+CT20+CT22+CT23+CT24+CT25 -> 1079.0637 | ... CV26: =+CV20+CV22+CV23+CV24+CV25 -> 1099.8627
B27: Final Price with Resin Freight Adjustment | D27: Precio Final con ajuste flete Resina | AL27: =+AL26+#REF! -> #REF! | AM27: =+AM26+#REF! -> #REF! | AN27: =+AN26+#REF! -> #REF! | AO27: =+AO26+#REF! -> #REF! | AP27: =+AP26+#REF! -> #REF! | AQ27: =+AQ26+#REF! -> #REF! | AR27: =+AR26+#REF! -> #REF! | AS27: =+AS26+#REF! -> #REF! | AT27: =+AT26+#REF! -> #REF! | AU27: =+AU26 -> 1693.6699 | AV27: =+AV26 -> 1719.0575 | AW27: 1890.6153 | AX27: 1907.0716 | AY27: =+AY26 -> 1804.3773 | AZ27: 1928.5453 | BA27: =+BA26 -> 1923.28 | BB27: =+BB26 -> 1895.01 | BC27: =+BC26 -> 1891.41 | BD27: =+BD26 -> 1923.2534 | BE27: =+BE26 -> 1961.2255 | BF27: =+BF26 -> 1833.6557 | BG27: =+BG26 -> 1786.95 | BH27: =+BH26 -> 1650.3341 | ... CV27: =+CV26 -> 1099.8627 | CX27: 2.which pricing is used as final (do we need to calculate the consumption values as well) ? Assuming its vpet (1100)
B28: Final Price FIFO | D28: Precio final FIFO | AL28: =+#REF! -> #REF! | AM28: =+#REF! -> #REF! | AN28: =+#REF! -> #REF! | AO28: =+#REF! -> #REF! | AP28: =+#REF! -> #REF! | AQ28: =+#REF! -> #REF! | AR28: =+#REF! -> #REF! | AS28: =+#REF! -> #REF! | ... AV28: =+#REF! -> #REF! | AW28: 1780.8032 | AX28: 1844.8576 | AY28: =+#REF! -> #REF! | AZ28: 1880.1282 | BA28: =+#REF! -> #REF! | BB28: =+#REF! -> #REF! | BC28: =+#REF! -> #REF! | BD28: =+#REF! -> #REF! | BE28: =+#REF! -> #REF! | BF28: =+#REF! -> #REF! | BG28: =+#REF! -> #REF! | BH28: =+#REF! -> #REF! | ... BM28: =+#REF! -> #REF! | BN28: =+CY24 -> 1267.0143 | BO28: =+CZ24 -> 1304.1208 | BP28: =+DA24 -> 1298.9693 | BQ28: =+DB24 -> 1254.8429 | BR28: =+DC24 -> 1215.9045 | BS28: =+DD24 -> 1220.6547 | BT28: =+DE24 -> 1226.1867 | BU28: =+DF24 -> 1209.0552 | ... BW28: =+DH24 -> 1203.3754 | BX28: =+DH24 -> 1203.3754 | BY28: =+DJ24 -> 1225.5446 | BZ28: =+DJ24 -> 1225.5446 | CA28: =+DL24 -> 1317.0024 | CB28: =+DM24 -> 1419.7187 | CC28: =+DN24 -> 1509.9821 | CD28: =+DO24 -> 1468.9302 | CE28: =+DP24 -> 1441.3902 | CF28: =+DQ24 -> 1363.6378 | CG28: =+DR24 -> 1331.6467 | CH28: =+DS24 -> 1304.2778 | ... CV28: =+EG24 -> 1122.3753 | CX28: 3. do we need the wighted avarge price calculation ?
D29: Ajuste
D30: Total | BD30: =+BD28+BD29 -> #REF! | BE30: =+BE28+BE29 -> #REF! | BF30: =+BF28+BF29 -> #REF! | BG30: =+BG28+BG29 -> #REF! | BH30: =+BH28+BH29 -> #REF! | BI30: =+BI28+BI29 -> #REF! | BJ30: =+BJ28+BJ29 -> #REF! | BK30: =+BK28+BK29 -> #REF! | ... CV30: =+CV28+CV29 -> 1122.3753 | CX30: 5. In the Freight calculation - Regulaar of 97 $ is constant and the remaining is Incremental based on the Drewery Index ? How will handle future calculation here?
CX31: translate the cam something sheet
D32: Resin PCR % Enkador | E32: =+E26*(1-5%) -> 1630.4208 | F32: =+F26*(1-5%) -> 1572.9196 | G32: =+G26*(1-5%) -> 1572.2066 | H32: =+H26*(1-5%) -> 1567.7445 | I32: =+I26*(1-5%) -> 1630.4208 | J32: =+J26*(1-5%) -> 1557.1068 | K32: =+K26*(1-5%) -> 1394.666 | L32: =+L26*(1-5%) -> 1328.615 | ... Y32: =+Y26*(1-5%) -> 1092.8639 | Z32: =1.33255813953488*1000 -> 1332.5581 | AA32: =+' PCR Enkador'!H55 -> 1386.3641 | AB32: =+AA32 -> 1386.3641 | AC32: =+AB32 -> 1386.3641 | AD32: =+AC32 -> 1386.3641 | AE32: =+AD32 -> 1386.3641 | AF32: =+' PCR Enkador'!H69 -> 1412.3596 | AG32: =+' PCR Enkador'!H69 -> 1412.3596 | AH32: =+' PCR Enkador'!H69 -> 1412.3596 | AI32: =+AH32 -> 1412.3596 | AJ32: =+AI32 -> 1412.3596 | AK32: =+' PCR Enkador'!H88 -> 1394.54 | AL32: =+' PCR Enkador'!H88 -> 1394.54 | AM32: =+AL32 -> 1394.54 | AN32: =+AM32 -> 1394.54 | AO32: =+' PCR Enkador'!H104 -> 1485 | AP32: =+AO32 -> 1485 | AQ32: =+AP32 -> 1485 | AR32: =+' PCR Enkador'!H124 -> 1514.8753 | AS32: =+AR32 -> 1514.8753 | AT32: =+AS32 -> 1514.8753 | AU32: =+' PCR Enkador'!E139 -> 1748.1782 | AV32: =+' PCR Enkador'!F139 -> 2005.359 | AW32: 1942.1299 | AX32: 1863.1434 | AY32: =+' PCR Enkador'!I139 -> 2055.0951 | AZ32: 2104.5194 | BA32: =+' PCR Enkador'!K139 -> 2174.9407 | BB32: =+' PCR Enkador'!L139 -> 2224.6328 | BC32: =+' PCR Enkador'!L139 -> 2224.6328 | BD32: =+' PCR Enkador'!N139 -> 2351.9981 | BE32: =+' PCR Enkador'!O139 -> 2084.088 | BF32: =+' PCR Enkador'!P139 -> 2039.0612 | BG32: =+' PCR Enkador'!Q139 -> 1827.4006 | BH32: =+' PCR Enkador'!R139 -> 1572.153 | BI32: =+' PCR Enkador'!S139 -> 1511.4316 | BJ32: =+' PCR Enkador'!T139 -> 1571.7048 | BK32: =+' PCR Enkador'!U139 -> 1749.1772 | ... CK32: =+' PCR Enkador'!AU139 -> 2426.0741 | CL32: =+FIFO!BH7 -> 2350.0219 | CM32: =+' PCR Enkador'!AW139 -> 2390.1839 | CN32: =+' PCR Enkador'!AX139 -> 2381.7182 | CO32: =+' PCR Enkador'!AY139 -> 2377.8054 | CP32: =+'PCR Aurora '!W21 -> 2309.209 | CQ32: =+'PCR Aurora '!X21 -> 2315.1788 | CR32: =+'PCR Aurora '!Y21 -> 2287.8265 | CS32: =+'PCR Aurora '!Z21 -> 2304.9182 | CT32: =+' PCR Enkador'!BD139 -> 2246.5395 | CU32: =+' PCR Enkador'!BE139 -> 2284.7438 | CV32: =+' PCR Enkador'!BG139 -> 0
D33: Resin PCR % Enkador FIFO | AR33: =+AR32 -> 1514.8753 | AS33: =+AS32 -> 1514.8753 | AT33: =+AT32 -> 1514.8753 | AU33: =+AU32 -> 1748.1782 | AV33: =+AV32 -> 2005.359 | AW33: 1942.1299 | AX33: 1863.1434 | AY33: =+AY32 -> 2055.0951 | AZ33: 2104.5194 | BA33: =+BA32 -> 2174.9407 | BB33: =+BB32 -> 2224.6328 | BC33: =+BC32 -> 2224.6328 | BD33: =+BD32 -> 2351.9981 | BE33: =+BE32 -> 2084.088 | BF33: =+BF32 -> 2039.0612 | BG33: =+BG32 -> 1827.4006 | BH33: =+BH32 -> 1572.153 | ... BL33: =+BL32 -> 1692.4082 | BM33: =+FIFO!J9 -> 1690.2249 | BN33: =+FIFO!L9 -> 1699.0065 | BO33: =+FIFO!N9 -> 1698.7785 | BP33: =+FIFO!P8 -> 1730.0097 | BQ33: =+FIFO!R8 -> 1773.5614 | BR33: =+FIFO!T8 -> 1784.8755 | BS33: =+FIFO!V8 -> 1784.8628 | BT33: =+FIFO!X8 -> 1813.0215 | BU33: =+FIFO!Z8 -> 1904.7514 | BV33: =+FIFO!AB9 -> 1962.2861 | BW33: =+FIFO!AD8 -> 1845.712 | BX33: =+FIFO!AF8 -> 1890.2731 | BY33: =+FIFO!AH8 -> 1917.1799 | BZ33: =+FIFO!AJ7 -> 2006.62 | CA33: =+FIFO!AL8 -> 1943.4781 | CB33: =+FIFO!AN8 -> 2034.9008 | CC33: =+FIFO!AP8 -> 2114.7268 | CD33: =+FIFO!AR8 -> 2187.7265 | CE33: =+FIFO!AT8 -> 2235.089 | CF33: =+FIFO!AV8 -> 2269.3398 | CG33: =+FIFO!AX8 -> 2218.3559 | CH33: =+FIFO!AZ8 -> 2236.8572 | CI33: =+FIFO!BB8 -> 2321.2754 | CJ33: =+FIFO!BD8 -> 2410.4813 | CK33: =+FIFO!BF8 -> 2410.8753 | CL33: =+FIFO!BH8 -> 2358.2488 | CM33: =+FIFO!#REF! -> #REF! | CN33: =+FIFO!CA8 -> 0 | CO33: =+FIFO!BN34 -> 2373.4672 | CP33: =+FIFO!BO34 -> 0 | CQ33: =+FIFO!BP34 -> 2373.4672 | CR33: =+FIFO!BR34 -> 2373.4672 | CS33: =+FIFO!CA34 -> 0 | CT33: =+FIFO!CB34 -> 0 | CU33: =+FIFO!CC34 -> 0 | CV33: =+FIFO!CD34 -> 0 | CW33: =+FIFO!BQ34 -> 0 | CX33: 7. Enakador , Enka , Aurora what are these ? Will it always be enka in the legislation calculation?
D34: Resin PCR % Enka | AA34: =+'PCR Enka'!C26 -> 1070.2457 | AB34: =+'PCR Enka'!D26 -> 1103.3118 | AC34: =+'PCR Enka'!D26 -> 1103.3118 | AD34: =+'PCR Enka'!E26 -> 1149.9847 | AE34: =+'PCR Enka'!E26 -> 1149.9847 | AF34: =+'PCR Enka'!F26 -> 1163.7352 | AG34: =+'PCR Enka'!F26 -> 1163.7352 | AH34: 6 | AI34: =+'PCR Enka'!H26 -> 1125.2337 | AJ34: =+'PCR Enka'!I26 -> 1153.6209 | AK34: =+'PCR Enka'!J26 -> 1197.5282 | AL34: =+'PCR Enka'!K26 -> 1277.3813 | AM34: =+'PCR Enka'!L26 -> 1467.9415 | AN34: =+'PCR Enka'!M26 -> 1432.478 | AO34: =+'PCR Enka'!N26 -> 1415.0274 | AP34: =+'PCR Enka'!O26 -> 1623.5225 | ... AV34: =+'PCR Enka'!U26 -> 1905.3661 | AW34: 1842.137 | AX34: 1765.8142 | AY34: =+'PCR Enka'!X26 -> 1957.7659 | AZ34: 2007.3086 | BA34: =+'PCR Enka'!Z26 -> 2077.6143 | BB34: =+'PCR Enka'!AA26 -> 2127.3064 | BC34: =+'PCR Enka'!AA26 -> 2127.3064 | BD34: =+'PCR Enka'!AC26 -> 2251.8217 | BE34: =+'PCR Enka'!AD26 -> 1986.3646 | BF34: =+'PCR Enka'!AE26 -> 1941.3379 | BG34: =+'PCR Enka'!AF26 -> 1729.6772 | BH34: =+'PCR Enka'!AG26 -> 1474.4296 | BI34: =+'PCR Enka'!AH26 -> 1413.7082 | BJ34: =+'PCR Enka'!AI26 -> 1472.9887 | BK34: =+'PCR Enka'!AJ26 -> 1650.4611 | ... BU34: =+'PCR Enka'!AT26 -> 1819.4162 | BV34: =+' PCR Enkador'!AF134 -> 1891.8355 | BW34: =+' PCR Enkador'!AG134 -> 1664.6783 | BX34: =+' PCR Enkador'!AH134 -> 1838.384 | BY34: =+' PCR Enkador'!AI134 -> 1862.1217 | BZ34: =+' PCR Enkador'!AI134 -> 1862.1217 | CA34: =+' PCR Enkador'!AK134 -> 1939.5828 | CB34: =+' PCR Enkador'!AL134 -> 1970.9734 | CC34: =+' PCR Enkador'!AM134 -> 2046.3999 | CD34: =+' PCR Enkador'!AN134 -> 2115.9076 | CE34: =+' PCR Enkador'!AO134 -> 2145.6482 | CF34: =+' PCR Enkador'!AP134 -> 2183.3734 | CG34: =+' PCR Enkador'!AQ134 -> 2108.3299 | CH34: =+' PCR Enkador'!AR134 -> 2139.863 | ... CK34: =+' PCR Enkador'!AU134 -> 2328.0642 | CL34: =+FIFO!BH20 -> 2252.012 | CM34: =+' PCR Enkador'!AW134 -> 2292.174 | CN34: =+'PCR Aurora '!U14 -> 2283.7083 | CO34: =+'PCR Enka'!DS26 -> 2279.7955 | CP34: =+'PCR Aurora '!W14 -> 2211.1991 | CQ34: =+'PCR Aurora '!X14 -> 2217.1689 | CR34: =+'PCR Aurora '!Y14 -> 2189.8166 | CS34: =+'PCR Aurora '!Z14 -> 2206.9083 | CT34: =+'PCR Aurora '!AA40 -> 1925.9158 | CU34: =+'PCR Enka'!EI26 -> 2187.0429 | CV34: =+'PCR Enka'!EK26 -> 0 | CX34: 8. Are the pricing below Row # 30 are also considered for the calculation ?
D35: Resin PCR % Enka FIFO | BM35: =+FIFO!J22 -> 1541.7236 | BN35: =+FIFO!L22 -> 1572.2305 | BO35: =+FIFO!N22 -> 1582.7075 | BP35: =+FIFO!P21 -> 1624.5182 | BQ35: =+FIFO!R21 -> 1640.1021 | BR35: =+FIFO!T21 -> 1640.1021 | BS35: =+FIFO!V21 -> 1640.1021 | BT35: =+FIFO!X21 -> 1640.1021 | BU35: =+FIFO!Z21 -> 1640.1021 | BV35: =+FIFO!AB22 -> 1640.1021 | BW35: =+FIFO!AD21 -> 1640.1021 | BX35: =+FIFO!AF21 -> 1640.1021 | BY35: =+FIFO!AH21 -> 1640.1021 | BZ35: =+FIFO!AJ21 -> 1640.1021 | CA35: =+FIFO!AL21 -> 1640.1021 | CB35: =+FIFO!AN21 -> 1756.8307 | CC35: =+FIFO!AP21 -> 1848.502 | CD35: =+FIFO!AR21 -> 1924.5346 | CE35: =+FIFO!AT21 -> 1924.5346 | CF35: =+FIFO!AV21 -> 1924.5346 | CG35: =+FIFO!AX21 -> 1924.5346 | CH35: =+FIFO!AZ21 -> 1924.5346 | CI35: =+FIFO!BB21 -> 1924.5346 | CJ35: =+FIFO!BD21 -> 2047.4442 | CK35: =+FIFO!BF21 -> 2047.5847 | CL35: =+FIFO!BH21 -> 2095.2472 | CM35: =+FIFO!BJ21 -> 2103.5509 | CN35: =+FIFO!BL21 -> 2141.3654 | CO35: =+FIFO!BN21 -> 2141.3654 | CP35: =+FIFO!BP21 -> 2141.3654 | CQ35: =+FIFO!BR21 -> 2141.3654 | CR35: =+FIFO!BR21 -> 2141.3654 | CS35: =+FIFO!BV21 -> 2141.3654 | CT35: =+FIFO!BV21 -> 2141.3654 | CU35: =+FIFO!BZ21 -> 2141.3654 | CV35: =+FIFO!CA21 -> 0 | CX35: 9. Need more undestanding on the Legilation charges calculation , it refers to 2 sheets
D36: Resin PCR % Aurora Clear. | AA36: =+'PCR Enka'!C28 -> 0 | AB36: =+'PCR Enka'!D28 -> 0 | AC36: =+'PCR Enka'!D28 -> 0 | AD36: =+'PCR Enka'!E28 -> 0 | AE36: =+'PCR Enka'!E28 -> 0 | AF36: =+'PCR Enka'!F28 -> 0 | AG36: =+'PCR Enka'!F28 -> 0 | AH36: 6 | AI36: =+'PCR Enka'!H28 -> 0 | AJ36: =+'PCR Enka'!I28 -> 0 | AK36: =+'PCR Enka'!J28 -> 0 | AL36: =+'PCR Enka'!K28 -> 0 | AM36: =+'PCR Enka'!L28 -> 0 | AN36: =+'PCR Enka'!M28 -> 0 | AO36: =+'PCR Enka'!N28 -> 0 | AP36: =+'PCR Enka'!O28 -> 0 | ... AV36: =+'PCR Enka'!U28 -> 0 | AW36: 1842.137 | AX36: 1765.8142 | AY36: =+'PCR Enka'!X28 -> 0 | AZ36: 2007.3086 | BA36: =+'PCR Enka'!Z28 -> 0 | BB36: =+'PCR Enka'!AA28 -> 0 | BC36: =+'PCR Enka'!AA28 -> 0 | BD36: =+'PCR Enka'!AC28 -> 0 | BE36: =+'PCR Enka'!AD28 -> 0 | BF36: =+'PCR Enka'!AE28 -> 0 | BG36: =+'PCR Enka'!AF28 -> 0 | BH36: =+'PCR Enka'!AG28 -> 0 | BI36: =+'PCR Enka'!AH28 -> 0 | BJ36: =+'PCR Enka'!AI28 -> 0 | BK36: =+'PCR Enka'!AJ28 -> 0 | ... BU36: =+'PCR Enka'!AT28 -> 0 | BV36: =+' PCR Enkador'!AF136 -> 94.4 | BW36: =+' PCR Enkador'!AG136 -> 94.4 | BX36: =+' PCR Enkador'!AH136 -> 94.4 | BY36: =+' PCR Enkador'!AI136 -> 94.4 | BZ36: =+' PCR Enkador'!AI136 -> 94.4 | CA36: =+' PCR Enkador'!AK136 -> 94.4 | CB36: =+' PCR Enkador'!AL136 -> 94.4 | CC36: =+' PCR Enkador'!AM136 -> 94.4 | CD36: =+' PCR Enkador'!AN136 -> 94.4 | CE36: =+' PCR Enkador'!AO136 -> 94.4 | CF36: =+' PCR Enkador'!AP136 -> 94.4 | CG36: =+' PCR Enkador'!AQ136 -> 94.4 | CH36: =+' PCR Enkador'!AR136 -> 94.4 | CL36: =+'PCR Aurora '!S40 -> 2305.7167 | CM36: =+'PCR Aurora '!T40 -> 2302.3702 | CN36: =+'PCR Aurora '!U40 -> 2271.7916 | CO36: =+'PCR Aurora '!V40 -> 2155.0837 | CP36: =+'PCR Aurora '!W40 -> 1974.3326 | CQ36: =+'PCR Aurora '!X40 -> 1974.0609 | CR36: =+'PCR Aurora '!Y40 -> 1958.5504 | CS36: =+'PCR Aurora '!Z40 -> 1951.0595 | ... CV36: =+'PCR Aurora '!AC40 -> 1982.7376 | CX36: 12. What are the units , Price for metric ton ?
D37: Resin PCR % Aurora. FIFO | BM37: =+FIFO!J24 -> 1536.7815 | BN37: =+FIFO!L24 -> 1541.7236 | BO37: =+FIFO!N24 -> 1572.2305 | BP37: =+FIFO!P23 -> 0 | BQ37: =+FIFO!R23 -> 0 | BR37: =+FIFO!T23 -> 0 | BS37: =+FIFO!V23 -> 0 | BT37: =+FIFO!X23 -> 0 | BU37: =+FIFO!Z23 -> 0 | BV37: =+FIFO!AB24 -> 1640.1021 | BW37: =+FIFO!AD23 -> 0 | BX37: =+FIFO!AF23 -> 0 | BY37: =+FIFO!AH23 -> 0 | BZ37: =+FIFO!AJ23 -> 0 | CA37: =+FIFO!AL23 -> 0 | CB37: =+FIFO!AN23 -> 0 | CC37: =+FIFO!AP23 -> 0 | CD37: =+FIFO!AR23 -> 0 | CE37: =+FIFO!AT23 -> 0 | CF37: =+FIFO!AV23 -> 0 | CG37: =+FIFO!AX23 -> 0 | CH37: =+FIFO!AZ23 -> 0 | CL37: =+FIFO!BH23 -> 0 | CM37: =+FIFO!#REF! -> #REF! | CN37: =+FIFO!CA23 -> 0 | CO37: =+FIFO!CB23 -> 0 | CP37: =+FIFO!CC23 -> 0 | CQ37: =+FIFO!CD23 -> 0 | CR37: =+FIFO!CE23 -> 0 | CS37: =+FIFO!CF23 -> 0 | CT37: =+FIFO!CG23 -> 0 | CU37: =+FIFO!CH23 -> 0 | CV37: =+FIFO!CI23 -> 0 | CX37: 13. What is finance here ? We are using SOFR rate % for the finance calculation
D38: Resin PCR % Aurora Ambar. | AA38: =+'PCR Enka'!C30 -> Fecha | AB38: =+'PCR Enka'!D30 -> TRM | AC38: =+'PCR Enka'!D30 -> TRM | AD38: =+'PCR Enka'!E30 -> Fecha | AE38: =+'PCR Enka'!E30 -> Fecha | AF38: =+'PCR Enka'!F30 -> TRM | AG38: =+'PCR Enka'!F30 -> TRM | AH38: 6 | AI38: =+'PCR Enka'!H30 -> TRM | AJ38: =+'PCR Enka'!I30 -> Fecha | AK38: =+'PCR Enka'!J30 -> TRM | AL38: =+'PCR Enka'!K30 -> Fecha | AM38: =+'PCR Enka'!L30 -> TRM | AN38: =+'PCR Enka'!M30 -> Fecha | AO38: =+'PCR Enka'!N30 -> TRM | AP38: =+'PCR Enka'!O30 -> Fecha | ... AV38: =+'PCR Enka'!U30 -> Fecha | AW38: 1842.137 | AX38: 1765.8142 | AY38: =+'PCR Enka'!X30 -> TRM | AZ38: 2007.3086 | BA38: =+'PCR Enka'!Z30 -> TRM | BB38: =+'PCR Enka'!AA30 -> Fecha | BC38: =+'PCR Enka'!AA30 -> Fecha | BD38: =+'PCR Enka'!AC30 -> Fecha | BE38: =+'PCR Enka'!AD30 -> TRM | BF38: =+'PCR Enka'!AE30 -> Fecha | BG38: =+'PCR Enka'!AF30 -> TRM | BH38: =+'PCR Enka'!AG30 -> Fecha | BI38: =+'PCR Enka'!AH30 -> TRM | BJ38: =+'PCR Enka'!AI30 -> Fecha | BK38: =+'PCR Enka'!AJ30 -> TRM | ... BU38: =+'PCR Enka'!AT30 -> TRM | BV38: =+' PCR Enkador'!AF138 -> 97.700897 | BW38: =+' PCR Enkador'!AG138 -> 97.700897 | BX38: =+' PCR Enkador'!AH138 -> 98.610694 | BY38: =+' PCR Enkador'!AI138 -> 98.610694 | BZ38: =+' PCR Enkador'!AI138 -> 98.610694 | CA38: =+' PCR Enkador'!AK138 -> 98.610694 | CB38: =+' PCR Enkador'!AL138 -> 98.610694 | CC38: =+' PCR Enkador'!AM138 -> 98.610694 | CD38: =+' PCR Enkador'!AN138 -> 98.610694 | CE38: =+' PCR Enkador'!AO138 -> 98.610694 | CF38: =+' PCR Enkador'!AP138 -> 98.610694 | CG38: =+' PCR Enkador'!AQ138 -> 98.610694 | CH38: =+' PCR Enkador'!AR138 -> 98.009902 | CL38: =+'PCR Aurora '!S42 -> 0 | CM38: =+'PCR Aurora '!T42 -> 0 | CN38: =+'PCR Aurora '!U42 -> 0 | CO38: =+'PCR Aurora '!V42 -> 0 | CP38: =+'PCR Aurora '!W42 -> 0 | CQ38: =+'PCR Aurora '!X42 -> 0 | CR38: =+'PCR Aurora '!Y42 -> 0 | CS38: =+'PCR Aurora '!Z42 -> 0 | ... CV38: =+'PCR Aurora '!AC42 -> 1882.7376
D39: Resin PCR % Aurora. FIFO | BM39: =+FIFO!J26 -> 1541.7236 | BN39: =+FIFO!L26 -> 1572.2305 | BO39: =+FIFO!N26 -> 1582.7075 | BP39: =+FIFO!P25 -> 1688.6913 | BQ39: =+FIFO!R25 -> 1735.1046 | BR39: =+FIFO!T25 -> 1696.6764 | BS39: =+FIFO!V25 -> 1687.1596 | BT39: =+FIFO!X25 -> 1717.7417 | BU39: =+FIFO!Z25 -> 1819.4162 | BV39: =+FIFO!AB26 -> 1640.1021 | BW39: =+FIFO!AD25 -> 0 | BX39: =+FIFO!AF25 -> 0 | BY39: =+FIFO!AH25 -> 0 | BZ39: =+FIFO!AJ25 -> 0 | CA39: =+FIFO!AL25 -> 0 | CB39: =+FIFO!AN25 -> 1970.9734 | CC39: =+FIFO!AP25 -> 2046.3999 | CD39: =+FIFO!AR25 -> 2115.9076 | CE39: =+FIFO!AT25 -> 2145.6482 | CF39: =+FIFO!AV25 -> 2183.3734 | CG39: =+FIFO!AX25 -> 2108.3299 | CH39: =+FIFO!AZ25 -> 2139.863 | CL39: =+FIFO!BH25 -> 2252.012 | CM39: =+FIFO!#REF! -> #REF! | CN39: =+FIFO!CA25 -> 0 | CO39: =+FIFO!CB25 -> 0 | CP39: =+FIFO!CC25 -> 0 | CQ39: =+FIFO!CD25 -> 0 | CR39: =+FIFO!CE25 -> 0 | CS39: =+FIFO!CF25 -> 0 | CT39: =+FIFO!CG25 -> 0 | CU39: =+FIFO!CH25 -> 0 | CV39: =+FIFO!CI25 -> 0
D41: Precio ponderado bajo formula 50 PCR Aurora /50 Virgen | W41: =+(W32*50%)+(W66*50%) -> 531.97998 | X41: =+(X26*50%)+(X32*50%) -> 1100.761 | Y41: =+(Y26*50%)+(Y32*50%) -> 1121.6234 | Z41: =+(Z26*50%)+(Z32*50%) -> 1241.4706 | AA41: =+(AA26*50%)+(AA32*50%) -> 1204.7359 | AB41: =+(AB26*50%)+(AB32*50%) -> 1154.2059 | AC41: =+(AC26*50%)+(AC32*50%) -> 1186.407 | AD41: =+(AD26*50%)+(AD32*50%) -> 1163.0802 | AE41: =+(AE26*50%)+(AE32*50%) -> 1174.222 | ... AK41: =+(AK26*50%)+(AK32*50%) -> 1149.9627 | AL41: =+(AL27*50%)+(AL32*50%) -> #REF! | AM41: =+(AM27*50%)+(AM32*50%) -> #REF! | AN41: =+(AN27*50%)+(AN32*50%) -> #REF! | AO41: =+(AO27*50%)+(AO32*50%) -> #REF! | AP41: =+(AP27*50%)+(AP32*50%) -> #REF! | AQ41: =+(AQ27*50%)+(AQ32*50%) -> #REF! | AR41: =+(AR28*50%)+(AR33*50%) -> #REF! | AS41: =+(AS28*50%)+(AS33*50%) -> #REF! | AT41: =+(AT28*50%)+(AT33*50%) -> #REF! | AU41: =+(AU28*50%)+(AU33*50%) -> #REF! | AV41: =+(AV28*50%)+(AV33*50%) -> #REF! | AW41: 1861.4665 | AX41: 1854.0005 | AY41: =+(AY28*50%)+(AY33*50%) -> #REF! | AZ41: 1992.3238 | BA41: =+(BA28*50%)+(BA33*50%) -> #REF! | BB41: =+(BB28*50%)+(BB33*50%) -> #REF! | BC41: =+(BC28*50%)+(BC33*50%) -> #REF! | BD41: =+(BD30*50%)+(BD33*50%) -> #REF! | BE41: =+(BE30*50%)+(BE33*50%) -> #REF! | BF41: =+(BF30*50%)+(BF33*50%) -> #REF! | BG41: =+(BG30*50%)+(BG33*50%) -> #REF! | BH41: =+(BH30*50%)+(BH33*50%) -> #REF! | BI41: =+(BI30*50%)+(BI33*50%) -> #REF! | BJ41: =+(BJ30*50%)+(BJ33*50%) -> #REF! | BK41: =+(BK30*50%)+(BK33*50%) -> #REF! | ... CK41: =+(CK30*50%)+(CK33*50%) -> 1794.7595 | CL41: =+(CL30*50%)+(CL36*50%) -> 1732.6105 | CM41: =+(CM30*50%)+(CM36*50%) -> 1736.1742 | CN41: =+(CN30*50%)+(CN36*50%) -> 1730.127 | CO41: =+(CO30*50%)+(CO36*50%) -> 1759.7594 | CP41: =+(CP30*50%)+(CP36*50%) -> 1630.5479 | CQ41: =+(CQ30*50%)+(CQ36*50%) -> 1611.7818 | CR41: =+(CR30*50%)+(CR36*50%) -> 1594.1294 | CS41: =+(CS30*50%)+(CS36*50%) -> 1576.2434 | ... CV41: =+(CV30*50%)+(CV36*50%) -> 1552.5564
D42: Scrap 1% | W42: =+W41*1% -> 5.3197998 | X42: =+X41*1% -> 11.00761 | Y42: =+Y41*1% -> 11.216234 | Z42: =+Z41*1% -> 12.414706 | AA42: =+AA41*1% -> 12.047359 | AB42: =+AB41*1% -> 11.542059 | AC42: =+AC41*1% -> 11.86407 | AD42: =+AD41*1% -> 11.630802 | ... AV42: =+AV41*1% -> #REF! | AW42: 18.614665 | AX42: 18.540005 | AY42: =+AY41*1% -> #REF! | AZ42: 19.923238 | BA42: =+BA41*1% -> #REF! | BB42: =+BB41*1% -> #REF! | BC42: =+BC41*1% -> #REF! | BD42: =+BD41*1% -> #REF! | BE42: =+BE41*1% -> #REF! | BF42: =+BF41*1% -> #REF! | BG42: =+BG41*1% -> #REF! | BH42: =+BH41*1% -> #REF! | ... CV42: =+CV41*1% -> 15.525564
D43: Precio ponderado con scrap | W43: =+W42+W41 -> 537.29978 | X43: =+X42+X41 -> 1111.7686 | Y43: =+Y42+Y41 -> 1132.8397 | Z43: =+Z42+Z41 -> 1253.8853 | AA43: =+AA42+AA41 -> 1216.7833 | AB43: =+AB42+AB41 -> 1165.748 | AC43: =+AC42+AC41 -> 1198.2711 | AD43: =+AD42+AD41 -> 1174.711 | ... AV43: =+AV42+AV41 -> #REF! | AW43: 1880.0812 | AX43: 1872.5405 | AY43: =+AY42+AY41 -> #REF! | AZ43: 2012.247 | BA43: =+BA42+BA41 -> #REF! | BB43: =+BB42+BB41 -> #REF! | BC43: =+BC42+BC41 -> #REF! | BD43: =+BD42+BD41 -> #REF! | BE43: =+BE42+BE41 -> #REF! | BF43: =+BF42+BF41 -> #REF! | BG43: =+BG42+BG41 -> #REF! | BH43: =+BH42+BH41 -> #REF! | ... CV43: =+CV42+CV41 -> 1568.082
D45: Precio ponderado bajo formula 100% PCR Enka | AA45: =+AA34 -> 1070.2457 | AB45: =+AB34 -> 1103.3118 | AC45: =+AC34 -> 1103.3118 | AD45: =+AD34 -> 1149.9847 | AE45: =+AE34 -> 1149.9847 | AF45: =+AF34 -> 1163.7352 | AG45: =+AG34 -> 1163.7352 | AH45: =+AH34 -> 6 | ... AV45: =+AV34 -> 1905.3661 | AW45: 1842.137 | AX45: 1765.8142 | AY45: =+AY34 -> 1957.7659 | AZ45: 2007.3086 | BA45: =+BA34 -> 2077.6143 | BB45: =+BB34 -> 2127.3064 | BC45: =+BC34 -> 2127.3064 | BD45: =+BD34 -> 2251.8217 | BE45: =+BE34 -> 1986.3646 | BF45: =+BF34 -> 1941.3379 | BG45: =+BG34 -> 1729.6772 | BH45: =+BH34 -> 1474.4296 | ... BL45: =+BL34 -> 1593.6921 | BM45: =+BM35 -> 1541.7236 | BN45: =+BN35 -> 1572.2305 | BO45: =+BO35 -> 1582.7075 | BP45: =+BP35 -> 1624.5182 | BQ45: =+BQ35 -> 1640.1021 | BR45: =+BR35 -> 1640.1021 | BS45: =+BS35 -> 1640.1021 | BT45: =+BT35 -> 1640.1021 | ... BV45: =+BV35 -> 1640.1021 | BW45: =+FIFO!AB21 -> 1640.1021 | BX45: =+BX35 -> 1640.1021 | BY45: =+BY35 -> 1640.1021 | BZ45: =+BZ35 -> 1640.1021 | CA45: =+CA35 -> 1640.1021 | CB45: =+CB35 -> 1756.8307 | CC45: =+CC35 -> 1848.502 | CD45: =+CD35 -> 1924.5346 | CE45: =+CE35 -> 1924.5346 | ... CK45: =+CK35 -> 2047.5847 | CL45: =+FIFO!BH21 -> 2095.2472 | CM45: =+FIFO!BJ21 -> 2103.5509 | CN45: =+CN35 -> 2141.3654 | CO45: =+CO35 -> 2141.3654 | CP45: =+FIFO!BP20 -> 2211.1991 | CQ45: =+CQ35 -> 2141.3654 | CR45: =+CR35 -> 2141.3654 | CS45: =+'PCR Aurora '!Z14 -> 2206.9083 | CT45: =+'PCR Enka'!DX26 -> 2148.8386 | CU45: =+CU35 -> 2141.3654 | CV45: =+FIFO!BZ21 -> 2141.3654
D46: Scrap 1% | AA46: =+AA45*1% -> 10.702457 | AB46: =+AB45*1% -> 11.033118 | AC46: =+AC45*1% -> 11.033118 | AD46: =+AD45*1% -> 11.499847 | AE46: =+AE45*1% -> 11.499847 | AF46: =+AF45*1% -> 11.637352 | AG46: =+AG45*1% -> 11.637352 | AH46: =+AH45*1% -> 0.06 | ... AV46: =+AV45*1% -> 19.053661 | AW46: 18.42137 | AX46: 17.658142 | AY46: =+AY45*1% -> 19.577659 | AZ46: 20.073086 | BA46: =+BA45*1% -> 20.776143 | BB46: =+BB45*1% -> 21.273064 | BC46: =+BC45*1% -> 21.273064 | BD46: =+BD45*1% -> 22.518217 | BE46: =+BE45*1% -> 19.863646 | BF46: =+BF45*1% -> 19.413379 | BG46: =+BG45*1% -> 17.296772 | BH46: =+BH45*1% -> 14.744296 | ... CV46: =+CV45*1% -> 21.413654
D47: Precio ponderado con scrap | AA47: =+AA46+AA45 -> 1080.9482 | AB47: =+AB46+AB45 -> 1114.3449 | AC47: =+AC46+AC45 -> 1114.3449 | AD47: =+AD46+AD45 -> 1161.4845 | AE47: =+AE46+AE45 -> 1161.4845 | AF47: =+AF46+AF45 -> 1175.3725 | AG47: =+AG46+AG45 -> 1175.3725 | AH47: =+AH46+AH45 -> 6.06 | ... AV47: =+AV46+AV45 -> 1924.4198 | AW47: 1860.5584 | AX47: 1783.4723 | AY47: =+AY46+AY45 -> 1977.3435 | AZ47: 2027.3817 | BA47: =+BA46+BA45 -> 2098.3905 | BB47: =+BB46+BB45 -> 2148.5795 | BC47: =+BC46+BC45 -> 2148.5795 | BD47: =+BD46+BD45 -> 2274.3399 | BE47: =+BE46+BE45 -> 2006.2282 | BF47: =+BF46+BF45 -> 1960.7512 | BG47: =+BG46+BG45 -> 1746.974 | BH47: =+BH46+BH45 -> 1489.1739 | ... CV47: =+CV46+CV45 -> 2162.7791
D49: Precio ponderado bajo formula 75 PCR Aurora /25 Virgen. | AJ49: =+(AJ26*25%)+(AJ32*75%) -> 1288.0475 | AK49: =+(AK26*25%)+(AK32*75%) -> 1272.2514 | AL49: =+(AL27*25%)+(AL32*75%) -> #REF! | AM49: =+(AM27*25%)+(AM32*75%) -> #REF! | AN49: =+(AN27*25%)+(AN32*75%) -> #REF! | AO49: =+(AO27*25%)+(AO32*75%) -> #REF! | AP49: =+(AP27*25%)+(AP32*75%) -> #REF! | AQ49: =+(AQ27*25%)+(AQ32*75%) -> #REF! | AR49: =+(AR28*25%)+(AR33*75%) -> #REF! | AS49: =+(AS28*25%)+(AS33*75%) -> #REF! | AT49: =+(AT28*25%)+(AT33*75%) -> #REF! | AU49: =+(AU28*25%)+(AU33*75%) -> #REF! | AV49: =+(AV28*25%)+(AV33*75%) -> #REF! | AW49: 1901.7982 | AX49: 1858.572 | AY49: =+(AY28*25%)+(AY33*75%) -> #REF! | AZ49: 2048.4216 | BA49: =+(BA28*25%)+(BA33*75%) -> #REF! | BB49: =+(BB28*25%)+(BB33*75%) -> #REF! | BC49: =+(BC28*25%)+(BC33*75%) -> #REF! | BD49: =+(BD30*25%)+(BD33*75%) -> #REF! | BE49: =+(BE30*25%)+(BE33*75%) -> #REF! | BF49: =+(BF30*25%)+(BF33*75%) -> #REF! | BG49: =+(BG30*25%)+(BG33*75%) -> #REF! | BH49: =+(BH30*25%)+(BH33*75%) -> #REF! | BI49: =+(BI30*25%)+(BI33*75%) -> #REF! | BJ49: =+(BJ30*25%)+(BJ33*75%) -> #REF! | BK49: =+(BK30*25%)+(BK33*75%) -> #REF! | ... CK49: =+(CK30*25%)+(CK33*75%) -> 2102.8174 | CL49: =+(CL30*25%)+(CL36*75%) -> 2019.1636 | CM49: =+(CM30*25%)+(CM36*75%) -> 2019.2722 | CN49: =+(CN30*25%)+(CN36*75%) -> 2000.9593 | CO49: =+(CO30*25%)+(CO36*75%) -> 1957.4215 | CP49: =+(CP30*25%)+(CP36*75%) -> 1802.4403 | CQ49: =+(CQ30*25%)+(CQ36*75%) -> 1792.9214 | CR49: =+(CR30*25%)+(CR36*75%) -> 1776.3399 | CS49: =+(CS30*25%)+(CS36*75%) -> 1763.6515 | ... CV49: =+(CV30*25%)+(CV36*75%) -> 1767.647
D50: Scrap 1% | AJ50: =+AJ49*1% -> 12.880475 | AK50: =+AK49*1% -> 12.722514 | AL50: =+AL49*1% -> #REF! | AM50: =+AM49*1% -> #REF! | AN50: =+AN49*1% -> #REF! | AO50: =+AO49*1% -> #REF! | AP50: =+AP49*1% -> #REF! | AQ50: =+AQ49*1% -> #REF! | ... AV50: =+AV49*1% -> #REF! | AW50: 19.017982 | AX50: 18.58572 | AY50: =+AY49*1% -> #REF! | AZ50: 20.484216 | BA50: =+BA49*1% -> #REF! | BB50: =+BB49*1% -> #REF! | BC50: =+BC49*1% -> #REF! | BD50: =+BD49*1% -> #REF! | BE50: =+BE49*1% -> #REF! | BF50: =+BF49*1% -> #REF! | BG50: =+BG49*1% -> #REF! | BH50: =+BH49*1% -> #REF! | ... CV50: =+CV49*1% -> 17.67647
D51: Precio ponderado con scrap | AJ51: =+AJ50+AJ49 -> 1300.928 | AK51: =+AK50+AK49 -> 1284.9739 | AL51: =+AL50+AL49 -> #REF! | AM51: =+AM50+AM49 -> #REF! | AN51: =+AN50+AN49 -> #REF! | AO51: =+AO50+AO49 -> #REF! | AP51: =+AP50+AP49 -> #REF! | AQ51: =+AQ50+AQ49 -> #REF! | ... AV51: =+AV50+AV49 -> #REF! | AW51: 1920.8162 | AX51: 1877.1577 | AY51: =+AY50+AY49 -> #REF! | AZ51: 2068.9058 | BA51: =+BA50+BA49 -> #REF! | BB51: =+BB50+BB49 -> #REF! | BC51: =+BC50+BC49 -> #REF! | BD51: =+BD50+BD49 -> #REF! | BE51: =+BE50+BE49 -> #REF! | BF51: =+BF50+BF49 -> #REF! | BG51: =+BG50+BG49 -> #REF! | BH51: =+BH50+BH49 -> #REF! | ... CV51: =+CV50+CV49 -> 1785.3235
D53: Precio ponderado bajo formula 100% PCR Enkador | W53: =+W32 -> 1063.96 | X53: =+X32 -> 1072.5364 | Y53: =+Y32 -> 1092.8639 | Z53: =+Z32 -> 1332.5581 | AA53: =+AA32 -> 1386.3641 | AB53: =+AB32 -> 1386.3641 | AC53: =+AC32 -> 1386.3641 | AD53: =+AD32 -> 1386.3641 | ... AQ53: =+AQ32 -> 1485 | AR53: =+AR33 -> 1514.8753 | AS53: =+AS33 -> 1514.8753 | AT53: =+AT33 -> 1514.8753 | AU53: =+AU33 -> 1748.1782 | AV53: =+AV33 -> 2005.359 | AW53: 1942.1299 | AX53: 1863.1434 | AY53: =+AY33 -> 2055.0951 | AZ53: 2104.5194 | BA53: =+BA33 -> 2174.9407 | BB53: =+BB33 -> 2224.6328 | BC53: =+BC33 -> 2224.6328 | BD53: =+BD33 -> 2351.9981 | BE53: =+BE33 -> 2084.088 | BF53: =+BF33 -> 2039.0612 | BG53: =+BG33 -> 1827.4006 | BH53: =+BH33 -> 1572.153 | ... CV53: =+CV33 -> 0
D54: Scrap 1% | W54: =+W53*1% -> 10.6396 | X54: =+X53*1% -> 10.725364 | Y54: =+Y53*1% -> 10.928639 | Z54: =+Z53*1% -> 13.325581 | AA54: =+AA53*1% -> 13.863641 | AB54: =+AB53*1% -> 13.863641 | AC54: =+AC53*1% -> 13.863641 | AD54: =+AD53*1% -> 13.863641 | ... AV54: =+AV53*1% -> 20.05359 | AW54: 19.421299 | AX54: 18.631434 | AY54: =+AY53*1% -> 20.550951 | AZ54: 21.045194 | BA54: =+BA53*1% -> 21.749407 | BB54: =+BB53*1% -> 22.246328 | BC54: =+BC53*1% -> 22.246328 | BD54: =+BD53*1% -> 23.519981 | BE54: =+BE53*1% -> 20.84088 | BF54: =+BF53*1% -> 20.390612 | BG54: =+BG53*1% -> 18.274006 | BH54: =+BH53*1% -> 15.72153 | ... CV54: =+CV53*1% -> 0
D55: Precio ponderado con scrap | W55: =+W54+W53 -> 1074.5996 | X55: =+X54+X53 -> 1083.2617 | Y55: =+Y54+Y53 -> 1103.7925 | Z55: =+Z54+Z53 -> 1345.8837 | AA55: =+AA54+AA53 -> 1400.2277 | AB55: =+AB54+AB53 -> 1400.2277 | AC55: =+AC54+AC53 -> 1400.2277 | AD55: =+AD54+AD53 -> 1400.2277 | ... AV55: =+AV54+AV53 -> 2025.4126 | AW55: 1961.5512 | AX55: 1881.7748 | AY55: =+AY54+AY53 -> 2075.6461 | AZ55: 2125.5646 | BA55: =+BA54+BA53 -> 2196.6902 | BB55: =+BB54+BB53 -> 2246.8791 | BC55: =+BC54+BC53 -> 2246.8791 | BD55: =+BD54+BD53 -> 2375.518 | BE55: =+BE54+BE53 -> 2104.9288 | BF55: =+BF54+BF53 -> 2059.4518 | BG55: =+BG54+BG53 -> 1845.6746 | BH55: =+BH54+BH53 -> 1587.8745 | ... CV55: =+CV54+CV53 -> 0
D57: Precio ponderado bajo formula 100% VIRGEN | Z57: =+Z26 -> 1150.383 | AA57: =+AA26 -> 1023.1077 | AB57: =+AB26 -> 922.0478 | AC57: =+AC26 -> 986.45 | AD57: =+AD26 -> 939.79624 | AE57: =+AE26 -> 962.08 | AF57: =+AF26 -> 950.59588 | AG57: =+AG26 -> 956.04 | ... AK57: =+AK26 -> 905.3855 | AL57: =+AL27 -> #REF! | AM57: =+AM27 -> #REF! | AN57: =+AN27 -> #REF! | AO57: =+AO27 -> #REF! | AP57: =+AP27 -> #REF! | AQ57: =+AQ27 -> #REF! | AR57: =+AR28 -> #REF! | AS57: =+AS28 -> #REF! | AT57: =+AT28 -> #REF! | AU57: =+AU28 -> #REF! | AV57: =+AV28 -> #REF! | AW57: 1780.8032 | AX57: 1844.8576 | AY57: =+AY28 -> #REF! | AZ57: 1880.1282 | BA57: =+BA28 -> #REF! | BB57: =+BB28 -> #REF! | BC57: =+BC28 -> #REF! | BD57: =+BD30 -> #REF! | BE57: =+BE30 -> #REF! | BF57: =+BF30 -> #REF! | BG57: =+BG30 -> #REF! | BH57: =+BH30 -> #REF! | BI57: =+BI30 -> #REF! | BJ57: =+BJ30 -> #REF! | BK57: =+BK30 -> #REF! | ... CV57: =+CV30 -> 1122.3753
D58: Scrap 1% | Z58: =+Z57*1% -> 11.50383 | AA58: =+AA57*1% -> 10.231077 | AB58: =+AB57*1% -> 9.220478 | AC58: =+AC57*1% -> 9.8645 | AD58: =+AD57*1% -> 9.3979624 | AE58: =+AE57*1% -> 9.6208 | AF58: =+AF57*1% -> 9.5059588 | AG58: =+AG57*1% -> 9.5604 | ... AV58: =+AV57*1% -> #REF! | AW58: 17.808032 | AX58: 18.448576 | AY58: =+AY57*1% -> #REF! | AZ58: 18.801282 | BA58: =+BA57*1% -> #REF! | BB58: =+BB57*1% -> #REF! | BC58: =+BC57*1% -> #REF! | BD58: =+BD57*1% -> #REF! | BE58: =+BE57*1% -> #REF! | BF58: =+BF57*1% -> #REF! | BG58: =+BG57*1% -> #REF! | BH58: =+BH57*1% -> #REF! | ... CV58: =+CV57*1% -> 11.223753
D59: Precio ponderado con scrap | Z59: =+Z58+Z57 -> 1161.8868 | AA59: =+AA58+AA57 -> 1033.3388 | AB59: =+AB58+AB57 -> 931.26827 | AC59: =+AC58+AC57 -> 996.3145 | AD59: =+AD58+AD57 -> 949.1942 | AE59: =+AE58+AE57 -> 971.7008 | AF59: =+AF58+AF57 -> 960.10183 | AG59: =+AG58+AG57 -> 965.6004 | ... AV59: =+AV58+AV57 -> #REF! | AW59: 1798.6112 | AX59: 1863.3062 | AY59: =+AY58+AY57 -> #REF! | AZ59: 1898.9295 | BA59: =+BA58+BA57 -> #REF! | BB59: =+BB58+BB57 -> #REF! | BC59: =+BC58+BC57 -> #REF! | BD59: =+BD58+BD57 -> #REF! | BE59: =+BE58+BE57 -> #REF! | BF59: =+BF58+BF57 -> #REF! | BG59: =+BG58+BG57 -> #REF! | BH59: =+BH58+BH57 -> #REF! | ... CV59: =+CV58+CV57 -> 1133.599
D61: Precio ponderado bajo formula 50 PCR /50 Aurora Ambar | AA61: =+AA68 -> 0 | AB61: =+AB68 -> 0 | AC61: =+AC68 -> 0 | AD61: =+AD68 -> 0 | AE61: =+(AE26*50%)+(AE34*50%) -> 1056.0323 | AF61: =+(AF26*50%)+(AF34*50%) -> 1057.1655 | AG61: =+(AG26*50%)+(AG34*50%) -> 1059.8876 | AH61: =+(AH26*50%)+(AH34*50%) -> 466.49239 | AI61: =+(AI26*50%)+(AI34*50%) -> 1019.0123 | AJ61: =+(AJ26*50%)+(AJ34*50%) -> 1034.3661 | AK61: =+(AK26*50%)+(AK34*50%) -> 1051.4569 | AL61: =+(AL27*50%)+(AL34*50%) -> #REF! | AM61: =+(AM27*50%)+(AM34*50%) -> #REF! | AN61: =+(AN27*50%)+(AN34*50%) -> #REF! | AO61: =+(AO27*50%)+(AO34*50%) -> #REF! | AP61: =+(AP27*50%)+(AP34*50%) -> #REF! | AQ61: =+(AQ27*50%)+(AQ34*50%) -> #REF! | AR61: =+(AR28*50%)+(AR34*50%) -> #REF! | AS61: =+(AS28*50%)+(AS34*50%) -> #REF! | AT61: =+(AT28*50%)+(AT34*50%) -> #REF! | AU61: =+(AU28*50%)+(AU34*50%) -> #REF! | AV61: =+(AV28*50%)+(AV34*50%) -> #REF! | AW61: 1811.4701 | AX61: 1805.3359 | AY61: =+(AY28*50%)+(AY34*50%) -> #REF! | AZ61: 1943.7184 | BA61: =+(BA28*50%)+(BA34*50%) -> #REF! | BB61: =+(BB28*50%)+(BB34*50%) -> #REF! | BC61: =+(BC28*50%)+(BC34*50%) -> #REF! | BD61: =+(BD30*50%)+(BD34*50%) -> #REF! | BE61: =+(BE30*50%)+(BE34*50%) -> #REF! | BF61: =+(BF30*50%)+(BF34*50%) -> #REF! | BG61: =+(BG30*50%)+(BG34*50%) -> #REF! | BH61: =+(BH30*50%)+(BH34*50%) -> #REF! | BI61: =+(BI30*50%)+(BI34*50%) -> #REF! | BJ61: =+(BJ30*50%)+(BJ34*50%) -> #REF! | BK61: =+(BK30*50%)+(BK34*50%) -> #REF! | ... CT61: =+(CT30*50%)+(CT34*50%) -> 1548.4325 | CU61: =+(CU30*50%)+(CU38*50%) -> 1494.1051 | CV61: =+(CV30*50%)+(CV38*50%) -> 1502.5564
D62: Scrap 1% | AA62: =+AA61*1% -> 0 | AB62: =+AB61*1% -> 0 | AC62: =+AC61*1% -> 0 | AD62: =+AD61*1% -> 0 | AE62: =+AE61*1% -> 10.560323 | AF62: =+AF61*1% -> 10.571655 | AG62: =+AG61*1% -> 10.598876 | AH62: =+AH61*1% -> 4.6649239 | ... AV62: =+AV61*1% -> #REF! | AW62: 18.114701 | AX62: 18.053359 | AY62: =+AY61*1% -> #REF! | AZ62: 19.437184 | BA62: =+BA61*1% -> #REF! | BB62: =+BB61*1% -> #REF! | BC62: =+BC61*1% -> #REF! | BD62: =+BD61*1% -> #REF! | BE62: =+BE61*1% -> #REF! | BF62: =+BF61*1% -> #REF! | BG62: =+BG61*1% -> #REF! | BH62: =+BH61*1% -> #REF! | ... CV62: =+CV61*1% -> 15.025564
D63: Precio ponderado con scrap | AA63: =+AA62+AA61 -> 0 | AB63: =+AB62+AB61 -> 0 | AC63: =+AC62+AC61 -> 0 | AD63: =+AD62+AD61 -> 0 | AE63: =+AE62+AE61 -> 1066.5926 | AF63: =+AF62+AF61 -> 1067.7372 | AG63: =+AG62+AG61 -> 1070.4865 | AH63: =+AH62+AH61 -> 471.15731 | ... AV63: =+AV62+AV61 -> #REF! | AW63: 1829.5848 | AX63: 1823.3893 | AY63: =+AY62+AY61 -> #REF! | AZ63: 1963.1556 | BA63: =+BA62+BA61 -> #REF! | BB63: =+BB62+BB61 -> #REF! | BC63: =+BC62+BC61 -> #REF! | BD63: =+BD62+BD61 -> #REF! | BE63: =+BE62+BE61 -> #REF! | BF63: =+BF62+BF61 -> #REF! | BG63: =+BG62+BG61 -> #REF! | BH63: =+BH62+BH61 -> #REF! | ... CV63: =+CV62+CV61 -> 1517.582
D65: Precio ponderado bajo formula 75 PCR Enka /25 Virgen | AS65: =+(AS34*75%)+(AS28*25%) -> #REF! | AT65: =+(AT34*75%)+(AT28*25%) -> #REF! | AU65: =+(AU34*75%)+(AU28*25%) -> #REF! | AV65: =+(AV34*75%)+(AV28*25%) -> #REF! | AW65: 1826.8036 | AX65: 1785.575 | AY65: =+(AY34*75%)+(AY28*25%) -> #REF! | AZ65: 1975.5135 | BA65: =+(BA34*75%)+(BA28*25%) -> #REF! | BB65: =+(BB34*75%)+(BB28*25%) -> #REF! | BC65: =+(BC34*75%)+(BC28*25%) -> #REF! | BD65: =+(BD34*75%)+(BD28*25%) -> #REF! | BE65: =+(BE34*75%)+(BE28*25%) -> #REF! | BF65: =+(BF34*75%)+(BF28*25%) -> #REF! | BG65: =+(BG34*75%)+(BG28*25%) -> #REF! | BH65: =+(BH34*75%)+(BH28*25%) -> #REF! | ... BL65: =+(BL34*75%)+(BL28*25%) -> #REF! | BM65: =+(BM35*75%)+(BM28*25%) -> #REF! | BN65: =+(BN35*75%)+(BN28*25%) -> 1495.9265 | BO65: =+(BO35*75%)+(BO28*25%) -> 1513.0608 | BP65: =+(BP35*75%)+(BP28*25%) -> 1543.131 | BQ65: =+(BQ35*75%)+(BQ28*25%) -> 1543.7873 | BR65: =+(BR35*75%)+(BR28*25%) -> 1534.0527 | BS65: =+(BS35*75%)+(BS28*25%) -> 1535.2403 | BT65: =+(BT35*75%)+(BT28*25%) -> 1536.6233 | ... CV65: =+(CV35*75%)+(CV28*25%) -> 280.59381
D66: Scrap 1% | AS66: =+AS65*1% -> #REF! | AT66: =+AT65*1% -> #REF! | AU66: =+AU65*1% -> #REF! | AV66: =+AV65*1% -> #REF! | AW66: 18.268036 | AX66: 17.85575 | AY66: =+AY65*1% -> #REF! | AZ66: 19.755135 | BA66: =+BA65*1% -> #REF! | BB66: =+BB65*1% -> #REF! | BC66: =+BC65*1% -> #REF! | BD66: =+BD65*1% -> #REF! | BE66: =+BE65*1% -> #REF! | BF66: =+BF65*1% -> #REF! | BG66: =+BG65*1% -> #REF! | BH66: =+BH65*1% -> #REF! | ... CV66: =+CV65*1% -> 2.8059381
D67: Precio ponderado con scrap | AS67: =+AS66+AS65 -> #REF! | AT67: =+AT66+AT65 -> #REF! | AU67: =+AU66+AU65 -> #REF! | AV67: =+AV66+AV65 -> #REF! | AW67: 1845.0716 | AX67: 1803.4308 | AY67: =+AY66+AY65 -> #REF! | AZ67: 1995.2686 | BA67: =+BA66+BA65 -> #REF! | BB67: =+BB66+BB65 -> #REF! | BC67: =+BC66+BC65 -> #REF! | BD67: =+BD66+BD65 -> #REF! | BE67: =+BE66+BE65 -> #REF! | BF67: =+BF66+BF65 -> #REF! | BG67: =+BG66+BG65 -> #REF! | BH67: =+BH66+BH65 -> #REF! | ... CV67: =+CV66+CV65 -> 283.39975
D68: Precio ponderado con scrap | E68: =+E67+E66 -> 0 | F68: =+F67+F66 -> 0 | G68: =+G67+G66 -> 0 | H68: =+H67+H66 -> 0 | I68: =+I67+I66 -> 0 | J68: =+J67+J66 -> 0 | K68: =+K67+K66 -> 0 | L68: =+L67+L66 -> 0 | ... AV68: =+AV67+AV66 -> #REF! | AW68: 1863.3396 | AX68: 1821.2865 | AY68: =+AY67+AY66 -> #REF! | AZ68: 2015.0238 | BA68: =+BA67+BA66 -> #REF! | BB68: =+BB67+BB66 -> #REF! | BC68: =+BC67+BC66 -> #REF! | BD68: =+BD67+BD66 -> #REF! | BE68: =+BE67+BE66 -> #REF! | BF68: =+BF67+BF66 -> #REF! | BG68: =+BG67+BG66 -> #REF! | BH68: =+BH67+BH66 -> #REF! | ... CV68: =+CV67+CV66 -> 286.20569
D69: Precio ponderado bajo formula 10% PCR Enkador / 90% virgen | Z69: =+(Z26*90%)+(Z32*10%) -> 1168.6005 | AA69: =+(AA26*90%)+(AA32*10%) -> 1059.4334 | AB69: =+(AB26*90%)+(AB32*10%) -> 968.47943 | AC69: =+(AC26*90%)+(AC32*10%) -> 1026.4414 | AD69: =+(AD26*90%)+(AD32*10%) -> 984.45302 | AE69: =+(AE26*90%)+(AE32*10%) -> 1004.5084 | AF69: =+(AF26*90%)+(AF32*10%) -> 996.77225 | AG69: =+(AG26*90%)+(AG32*10%) -> 1001.672 | ... AK69: =+(AK26*90%)+(AK32*10%) -> 954.30095 | AL69: =+(AL28*90%)+(AL32*10%) -> #REF! | AM69: =+(AM28*90%)+(AM32*10%) -> #REF! | AN69: =+(AN28*90%)+(AN32*10%) -> #REF! | AO69: =+(AO28*90%)+(AO32*10%) -> #REF! | AP69: =+(AP28*90%)+(AP32*10%) -> #REF! | AQ69: =+(AQ28*90%)+(AQ32*10%) -> #REF! | AR69: =+(AR28*90%)+(AR32*10%) -> #REF! | AS69: =+(AS28*90%)+(AS32*10%) -> #REF! | ... AV69: =+(AV28*90%)+(AV32*10%) -> #REF! | AW69: 1796.9358 | AX69: 1846.6862 | AY69: =+(AY28*90%)+(AY32*10%) -> #REF! | AZ69: 1902.5673 | BA69: =+(BA28*90%)+(BA32*10%) -> #REF! | BB69: =+(BB28*90%)+(BB32*10%) -> #REF! | BC69: =+(BC28*90%)+(BC32*10%) -> #REF! | BD69: =+(BD28*90%)+(BD32*10%) -> #REF! | BE69: =+(BE28*90%)+(BE32*10%) -> #REF! | BF69: =+(BF28*90%)+(BF32*10%) -> #REF! | BG69: =+(BG28*90%)+(BG32*10%) -> #REF! | BH69: =+(BH28*90%)+(BH32*10%) -> #REF! | ... CV69: =+(CV28*90%)+(CV32*10%) -> 1010.1377
D70: Scrap 1% | Z70: =+Z69*1% -> 11.686005 | AA70: =+AA69*1% -> 10.594334 | AB70: =+AB69*1% -> 9.6847943 | AC70: =+AC69*1% -> 10.264414 | AD70: =+AD69*1% -> 9.8445302 | AE70: =+AE69*1% -> 10.045084 | AF70: =+AF69*1% -> 9.9677225 | AG70: =+AG69*1% -> 10.01672 | ... AV70: =+AV69*1% -> #REF! | AW70: 17.969358 | AX70: 18.466862 | AY70: =+AY69*1% -> #REF! | AZ70: 19.025673 | BA70: =+BA69*1% -> #REF! | BB70: =+BB69*1% -> #REF! | BC70: =+BC69*1% -> #REF! | BD70: =+BD69*1% -> #REF! | BE70: =+BE69*1% -> #REF! | BF70: =+BF69*1% -> #REF! | BG70: =+BG69*1% -> #REF! | BH70: =+BH69*1% -> #REF! | ... CV70: =+CV69*1% -> 10.101377
D71: Precio ponderado con scrap | Z71: =+Z70+Z69 -> 1180.2865 | AA71: =+AA70+AA69 -> 1070.0277 | AB71: =+AB70+AB69 -> 978.16422 | AC71: =+AC70+AC69 -> 1036.7058 | AD71: =+AD70+AD69 -> 994.29755 | AE71: =+AE70+AE69 -> 1014.5535 | AF71: =+AF70+AF69 -> 1006.74 | AG71: =+AG70+AG69 -> 1011.6887 | ... AV71: =+AV70+AV69 -> #REF! | AW71: 1814.9052 | AX71: 1865.1531 | AY71: =+AY70+AY69 -> #REF! | AZ71: 1921.593 | BA71: =+BA70+BA69 -> #REF! | BB71: =+BB70+BB69 -> #REF! | BC71: =+BC70+BC69 -> #REF! | BD71: =+BD70+BD69 -> #REF! | BE71: =+BE70+BE69 -> #REF! | BF71: =+BF70+BF69 -> #REF! | BG71: =+BG70+BG69 -> #REF! | BH71: =+BH70+BH69 -> #REF! | ... CV71: =+CV70+CV69 -> 1020.2391
D73: Precio ponderado bajo formula 25% PCR Enka / 75% Virgen | AA73: =+(AA26*75%)+(AA34*25%) -> 1034.8922 | AB73: =+(AB26*75%)+(AB34*25%) -> 967.36379 | AC73: =+(AC26*75%)+(AC34*25%) -> 1015.6654 | AD73: =+(AD26*75%)+(AD34*25%) -> 992.34334 | AE73: =+(AE26*75%)+(AE34*25%) -> 1009.0562 | AF73: =+(AF26*75%)+(AF34*25%) -> 1003.8807 | AG73: =+(AG26*75%)+(AG34*25%) -> 1007.9638 | AH73: =+(AH26*75%)+(AH34*25%) -> 696.73858 | ... AK73: =+(AK26*75%)+(AK34*25%) -> 978.42118 | AL73: =+(AL28*75%)+(AL34*25%) -> #REF! | AM73: =+(AM28*75%)+(AM34*25%) -> #REF! | AN73: =+(AN28*75%)+(AN34*25%) -> #REF! | AO73: =+(AO28*75%)+(AO34*25%) -> #REF! | AP73: =+(AP28*75%)+(AP34*25%) -> #REF! | AQ73: =+(AQ28*75%)+(AQ34*25%) -> #REF! | AR73: =+(AR28*75%)+(AR34*25%) -> #REF! | AS73: =+(AS28*75%)+(AS34*25%) -> #REF! | ... AV73: =+(AV28*75%)+(AV34*25%) -> #REF! | AW73: 1796.1366 | AX73: 1825.0968 | AY73: =+(AY28*75%)+(AY34*25%) -> #REF! | AZ73: 1911.9233 | BA73: =+(BA28*75%)+(BA34*25%) -> #REF! | BB73: =+(BB28*75%)+(BB34*25%) -> #REF! | BC73: =+(BC28*75%)+(BC34*25%) -> #REF! | BD73: =+(BD30*75%)+(BD34*25%) -> #REF! | BE73: =+(BE30*75%)+(BE34*25%) -> #REF! | BF73: =+(BF30*75%)+(BF34*25%) -> #REF! | BG73: =+(BG30*75%)+(BG34*25%) -> #REF! | BH73: =+(BH30*75%)+(BH34*25%) -> #REF! | BI73: =+(BI30*75%)+(BI34*25%) -> #REF! | BJ73: =+(BJ30*75%)+(BJ34*25%) -> #REF! | BK73: =+(BK30*75%)+(BK34*25%) -> #REF! | ... CV73: =+(CV30*75%)+(CV34*25%) -> 841.78144
D74: Scrap 1% | AA74: =+AA73*1% -> 10.348922 | AB74: =+AB73*1% -> 9.6736379 | AC74: =+AC73*1% -> 10.156654 | AD74: =+AD73*1% -> 9.9234334 | AE74: =+AE73*1% -> 10.090562 | AF74: =+AF73*1% -> 10.038807 | AG74: =+AG73*1% -> 10.079638 | AH74: =+AH73*1% -> 6.9673858 | ... AV74: =+AV73*1% -> #REF! | AW74: 17.961366 | AX74: 18.250968 | AY74: =+AY73*1% -> #REF! | AZ74: 19.119233 | BA74: =+BA73*1% -> #REF! | BB74: =+BB73*1% -> #REF! | BC74: =+BC73*1% -> #REF! | BD74: =+BD73*1% -> #REF! | BE74: =+BE73*1% -> #REF! | BF74: =+BF73*1% -> #REF! | BG74: =+BG73*1% -> #REF! | BH74: =+BH73*1% -> #REF! | ... CV74: =+CV73*1% -> 8.4178144
D75: Precio ponderado con scrap | AA75: =+AA74+AA73 -> 1045.2412 | AB75: =+AB74+AB73 -> 977.03742 | AC75: =+AC74+AC73 -> 1025.8221 | AD75: =+AD74+AD73 -> 1002.2668 | AE75: =+AE74+AE73 -> 1019.1467 | AF75: =+AF74+AF73 -> 1013.9195 | AG75: =+AG74+AG73 -> 1018.0434 | AH75: =+AH74+AH73 -> 703.70597 | ... AV75: =+AV74+AV73 -> #REF! | AW75: 1814.098 | AX75: 1843.3477 | AY75: =+AY74+AY73 -> #REF! | AZ75: 1931.0425 | BA75: =+BA74+BA73 -> #REF! | BB75: =+BB74+BB73 -> #REF! | BC75: =+BC74+BC73 -> #REF! | BD75: =+BD74+BD73 -> #REF! | BE75: =+BE74+BE73 -> #REF! | BF75: =+BF74+BF73 -> #REF! | BG75: =+BG74+BG73 -> #REF! | BH75: =+BH74+BH73 -> #REF! | ... CV75: =+CV74+CV73 -> 850.19925
D77: Precio ponderado bajo formula 75 PCR Intercia /25 Virgen | AU77: =+(AU40*75%)+(AU28*25%) -> #REF! | AV77: =+(AV40*75%)+(AV28*25%) -> #REF! | AW77: 2026.2018 | AX77: 2044.7899 | AY77: =+(AY40*75%)+(AY28*25%) -> #REF! | AZ77: 2167.3695 | BA77: =+(BA40*75%)+(BA28*25%) -> #REF! | BB77: =+(BB40*75%)+(BB28*25%) -> #REF! | BC77: =+(BC40*75%)+(BC28*25%) -> #REF! | BD77: =+(BD40*75%)+(BD30*25%) -> #REF! | BE77: =+(BE40*75%)+(BE30*25%) -> #REF! | BF77: =+(BF40*75%)+(BF30*25%) -> #REF! | BG77: =+(BG40*75%)+(BG30*25%) -> #REF! | BH77: =+(BH40*75%)+(BH30*25%) -> #REF! | BI77: =+(BI40*75%)+(BI30*25%) -> #REF! | BJ77: =+(BJ40*75%)+(BJ30*25%) -> #REF! | BK77: =+(BK40*75%)+(BK30*25%) -> #REF! | ... CV77: =+(CV40*75%)+(CV30*25%) -> 280.59381
D78: Scrap 1% | AU78: =+AU77*1% -> #REF! | AV78: =+AV77*1% -> #REF! | AW78: 20.262018 | AX78: 20.447899 | AY78: =+AY77*1% -> #REF! | AZ78: 21.673695 | BA78: =+BA77*1% -> #REF! | BB78: =+BB77*1% -> #REF! | BC78: =+BC77*1% -> #REF! | BD78: =+BD77*1% -> #REF! | BE78: =+BE77*1% -> #REF! | BF78: =+BF77*1% -> #REF! | BG78: =+BG77*1% -> #REF! | BH78: =+BH77*1% -> #REF! | ... CV78: =+CV77*1% -> 2.8059381
D79: Precio ponderado con scrap | AU79: =+AU78+AU77 -> #REF! | AV79: =+AV78+AV77 -> #REF! | AW79: 2046.4638 | AX79: 2065.2378 | AY79: =+AY78+AY77 -> #REF! | AZ79: 2189.0432 | BA79: =+BA78+BA77 -> #REF! | BB79: =+BB78+BB77 -> #REF! | BC79: =+BC78+BC77 -> #REF! | BD79: =+BD78+BD77 -> #REF! | BE79: =+BE78+BE77 -> #REF! | BF79: =+BF78+BF77 -> #REF! | BG79: =+BG78+BG77 -> #REF! | BH79: =+BH78+BH77 -> #REF! | ... BU79: =+BU78+BU77 -> 305.28643 | BV79: =+BV49+BV50 -> 1787.964 | BW79: =+BW49+BW50 -> 1701.9791 | BX79: =+BX49+BX50 -> 1735.7341 | BY79: =+BY49+BY50 -> 1761.7138 | BZ79: =+BZ49+BZ50 -> 1829.4647 | CA79: =+CA49+CA50 -> 1804.7278 | CB79: =+CB49+CB50 -> 1899.9163 | CC79: =+CC49+CC50 -> 1983.176 | ... CV79: =+CV49+CV50 -> 1785.3235

Sheet Fórmula Ago
B1: FÓRMULA
AD14: Fórmula | AT14: FIFO Virgen
B15: PRICE | C15: Jul-18 | D15: Ago-2018 | E15: Sep-18 | F15: Oct-18 | G15: Nov-18 | H15: Dic-18 | I15: Ene-19 | J15: Feb-19 | K15: Mar-19 | L15: Abr-19 | M15: May-19 | N15: Jun-19 | O15: Jul-19 | P15: Ago-19 | Q15: Sep-19 | R15: Oct-19 | S15: Nov-20 | T15: Dic-20 | U15: Ene-20 | V15: Feb-20 | W15: Mar-20 | X15: Abr-20 | Y15: May-20 | Z15: Jun-20 | AA15: Jun-20 | AB15: Jul-20 | AC15: Jul-20 | AD15: Ago-20 | AE15: Ago-20 | AF15: Sep-20 | AG15: Oct-20 | AH15: Nov-20 | AI15: Dic-20 | AJ15: Ene-21 | AK15: Feb-21 | AL15: Mar-21 | AM15: Abr-21 | AN15: May-21 | AO15: Jun-21 | AP15: Jul-21 | AQ15: Ago-21 | AT15: DIC | AU15: ENE | AV15: FEB | AW15: MAR | AX15: ABR | AY15: MAY | AZ15: JUN | BA15: JUL | BB15: AGO
B16: IHS Asia Non Coke approved (-2) | C16: May-18 | D16: Jun-18 | E16: Jul-18 | F16: Ago-18 | G16: Sep-18 | H16: Oct-18 | I16: Nov-18 | J16: Dic-18 | K16: Jan-19 | L16: Feb-19 | M16: Mar-19 | N16: Abr-19 | O16: May-19 | P16: Jun-19 | Q16: Jul-19 | R16: Ago-19 | S16: Sep-19 | T16: Oct-19 | U16: Nov-19 | V16: Dic-19 | W16: Jan-20 | X16: Feb-20 | Y16: Mar-20 | Z16: Abr-20 | AA16: Abr-20 | AB16: May-20 | AC16: May-20 | AD16: Jun-20 | AE16: Jun-20 | AF16: Jul-20 | AG16: Ago-20 | AH16: Sep-20 | AI16: Oct-20 | AJ16: Nov-20 | AK16: Dic-20 | AL16: Jan-21 | AM16: 44228 | AN16: Mar-21 | AO16: Apr-21 | AP16: May-21 | AQ16: May-21 | AS16: Inv inicial Tons | AT16: 402 | AU16: =+AT34 -> 908.55869 | AV16: =+AU34 -> 1484.0593 | AW16: =+AV34 -> 1983.5279 | AX16: =+AW34 -> 1948.3076 | AY16: =+AX34 -> 1958.4018 | AZ16: =+AY34 -> 2199.3719 | BA16: =+AZ34 -> 2233.7381 | BB16: =+BA34 -> 2098.1042
C17: 1330 | D17: 1280 | E17: 1279.38 | F17: 1275.5 | G17: 1330 | H17: 1266.25 | I17: 1125 | J17: 1058.13 | K17: 1035 | L17: 1077.5 | M17: 1096.25 | N17: 1101.25 | O17: 1004.5 | P17: 926.25 | Q17: 966.88 | R17: 889 | S17: 868.75 | T17: 840 | U17: 818.75 | V17: 824.38 | W17: 840 | X17: =+W17 -> 840 | Y17: 736.88 | Z17: 655 | AA17: 707.17946 | AB17: 669.38 | AC17: 687.43458 | AD17: 678.13 | AE17: 682.5409 | AF17: 659 | AG17: 647.5 | AH17: 649.38 | AI17: 641.5 | AJ17: 648.13 | AK17: 713 | AL17: 789.38 | AM17: 880.63 | AN17: 1018.75 | AO17: 960 | AP17: 932.5 | AQ17: 930 | AS17: Fórmula N-1 | AT17: =+AH25 -> 915.11135
B18: Finance | C18: =+C17*4.5%/365*210 -> 34.434247 | D18: =+D17*4.5%/365*210 -> 33.139726 | E18: =+E17*4.5%/365*210 -> 33.123674 | F18: =+F17*4.5%/365*210 -> 33.023219 | G18: =+G17*4.5%/365*210 -> 34.434247 | H18: =+H17*4.5%/365*210 -> 32.783733 | I18: =+I17*4.5%/365*210 -> 29.126712 | J18: =+J17*(4.5%+1.59%)/365*210 -> 37.075136 | K18: =+K17*(4.5%+1.59%)/365*210 -> 36.264699 | L18: =+L17*(4.5%+1.59%)/365*210 -> 37.753829 | M18: =+M17*(4.5%+1.59%)/365*210 -> 38.410798 | N18: =+N17*(4.5%+1.59%)/365*210 -> 38.58599 | O18: =+O17*(4.5%+1.59%)/365*210 -> 35.196029 | P18: =+P17*(4.5%+1.59%)/365*210 -> 32.454277 | Q18: =+Q17*(4.5%+1.59%)/365*210 -> 33.877886 | ... T18: =+T17*(4.5%+1.59%)/365*210 -> 29.432219 | U18: =+U17*(4.5%+1.59%+1.9%)/365*210 -> 37.637825 | V18: =+V17*(4.5%+1.59%+1.9%)/365*210 -> 37.896636 | W18: =+W17*(4.5%+1.59%+1.9%)/365*210 -> 38.614685 | X18: =+X17*(4.5%+1.59%+1.9%)/365*210 -> 38.614685 | Y18: =+Y17*(4.5%+1.59%+1.9%)/365*210 -> 33.874273 | Z18: =+Z17*(4.5%+1.59%+1.9%)/365*210 -> 30.11026 | AA18: =+AA17*(4.5%+1.59%+1.9%)/365*210 -> 32.508943 | AB18: =+AB17*(4.5%+1.59%+1.9%)/365*210 -> 30.771307 | ... AO18: =+AO17*(4.5%+1.59%+1.9%)/365*210 -> 44.131068 | AP18: 15.104707 | AQ18: 15.104707 | AS18: Flete Incr | AT18: 0
B19: Freight China-Buenaventura (reg) | C19: 90 | D19: 90 | E19: 90 | F19: 90 | G19: 90 | H19: 90 | I19: 90 | J19: 90 | K19: 90 | L19: 90 | M19: 90 | N19: 90 | O19: 90 | P19: 90 | Q19: 90 | R19: 90 | S19: 90 | T19: 91 | U19: =+T19*(1+1.9%) -> 92.729 | V19: =+U19*(1+1.9%) -> 94.490851 | W19: =+V19*(1+1.9%) -> 96.286177 | X19: =+W19 -> 96.286177 | Y19: =+X19 -> 96.286177 | Z19: =+Y19 -> 96.286177 | AA19: =+Z19 -> 96.286177 | AB19: =+AA19 -> 96.286177 | AC19: =+AB19 -> 96.286177 | AD19: =+AC19 -> 96.286177 | AE19: =+AD19 -> 96.286177 | ... AO19: =+AN19 -> 96.286177 | AP19: 96.286177 | AQ19: 96.286177 | AS19: Precio Total | AT19: =+AT17+AT18 -> 915.11135 | AU19: =+AT35 -> 1015.1511 | AV19: =+AU35 -> 1049.08 | AW19: =+AV35 -> 1093.0809 | AX19: =+AW35 -> 1133.4691 | AY19: =+AX35 -> 1204.9217 | AZ19: =+AY35 -> 1280.7208 | BA19: =+AZ35 -> 1336.9319 | BB19: =+BA35 -> 1364.2907
B20: Freight China-Buenaventura (Incr) | AP20: 253.71382 | AQ20: 290.07746
B21: Sub total (con flete Inc) | C21: =SUM(C17:C19) -> 1454.4342 | D21: =SUM(D17:D19) -> 1403.1397 | E21: =SUM(E17:E19) -> 1402.5037 | F21: =SUM(F17:F19) -> 1398.5232 | G21: =SUM(G17:G19) -> 1454.4342 | H21: =SUM(H17:H19) -> 1389.0337 | I21: =SUM(I17:I19) -> 1244.1267 | J21: =SUM(J17:J19) -> 1185.2051 | ... AO21: =SUM(AO17:AO19) -> 1100.4172 | AP21: =SUM(AP17:AP20) -> 1297.6047 | AQ21: =SUM(AQ17:AQ20) -> 1331.4683
B22: Sub total (con flete reg) | AP22: =+SUM(AP17:AP19) -> 1043.8909 | AQ22: =+SUM(AQ17:AQ19) -> 1041.3909
B23: Duty 10% | C23: =+C21*0.1 -> 145.44342 | D23: =+D21*0.1 -> 140.31397 | E23: =+E21*0.1 -> 140.25037 | F23: =+F21*0.1 -> 139.85232 | G23: =+G21*0.1 -> 145.44342 | H23: =+H21*0.1 -> 138.90337 | I23: =+I21*0.1 -> 124.41267 | J23: =+J21*0.1 -> 118.52051 | ... AQ23: =+AQ21*0.1 -> 133.14683 | AS23: Ingresos Tons N | AT23: 507 | AU23: =576 -> 576 | AV23: =500 -> 500 | AW23: 350 | AX23: 500 | AY23: 440 | AZ23: =200+300 -> 500 | BA23: 330 | BB23: 475
B24: Landed factor 8% | C24: =+C21*8% -> 116.35474 | D24: =+D21*8% -> 112.25118 | E24: =+E21*8% -> 112.20029 | F24: =+F21*8% -> 111.88186 | G24: =+G21*8% -> 116.35474 | H24: =+H21*8% -> 111.1227 | I24: =+I21*8% -> 99.530137 | J24: =+J21*8% -> 94.816411 | ... AO24: =+AO21*8% -> 88.03338 | AP24: =+AP22*8% -> 83.511271 | AQ24: =+AQ22*8% -> 83.311271 | AS24: Fórmula W/O flete | AT24: =+AI25 -> 905.3855 | AU24: =+AJ25 -> 913.56854 | AV24: =+AK25 -> 993.63397 | AW24: =+AL25 -> 1087.9056 | AX24: =+AM25 -> 1200.5304 | AY24: =+AN25 -> 1371.0042 | AZ24: =+AO25 -> 1298.4923 | BA24: =+AP25 -> 1510.8764 | BB24: =+AQ25 -> 1547.9264
B25: Total resin price ABI Fórmula | C25: =+C21+C23+C24 -> 1716.2324 | D25: =+D21+D23+D24 -> 1655.7049 | E25: =+E21+E23+E24 -> 1654.9543 | F25: =+F21+F23+F24 -> 1650.2574 | G25: =+G21+G23+G24 -> 1716.2324 | H25: =+H21+H23+H24 -> 1639.0598 | I25: =+I21+I23+I24 -> 1468.0695 | J25: =+J21+J23+J24 -> 1398.5421 | ... AQ25: =+AQ21+AQ23+AQ24 -> 1547.9264 | AS25: Flete Incr | AT25: 189 | AU25: 189 | AV25: 230 | AW25: =+AV25 -> 230 | AX25: =+AX46-AM19 -> 212.80473 | AY25: =+AY46-AN19 -> 212.80473 | AZ25: 233.35019 | BA25: 0 | BB25: 0
B26: Precio Final con ajuste flete Resina | AJ26: =+AJ25+AU25 -> 1102.5685 | AK26: =+AK25+AV25 -> 1223.634 | AL26: =+AL25+AW25 -> 1317.9056 | AM26: =+AM25+AX25 -> 1413.3351 | AN26: =+AN25+AY25 -> 1583.8089 | AO26: =+AO25+AZ25 -> 1531.8425 | AP26: =+AP25+BA25 -> 1510.8764 | AQ26: =+AQ25+BB25 -> 1547.9264
B27: Precio final FIFO | AJ27: =+AU35 -> 1049.08 | AK27: =+AV35 -> 1093.0809 | AL27: =+AW35 -> 1133.4691 | AM27: =+AX35 -> 1204.9217 | AN27: =+AY35 -> 1280.7208 | AO27: =+AZ35 -> 1336.9319 | AP27: =+BA35 -> 1364.2907 | AQ27: =+BB35 -> 1406.7142
AS28: Precio Total | AT28: =+AT24+AT25 -> 1094.3855 | AU28: =+AU24+AU25 -> 1102.5685 | AV28: =+AV24+AV25 -> 1223.634 | AW28: =+AW24+AW25 -> 1317.9056 | AX28: =+AX24+AX25 -> 1413.3351 | AY28: =+AY24+AY25 -> 1583.8089 | AZ28: =+AZ24+AZ25 -> 1531.8425 | BA28: =+BA24+BA25 -> 1510.8764 | BB28: =+BB24+BB25 -> 1547.9264
B29: Resin PCR % Enkador | C29: =+C25*(1-5%) -> 1630.4208 | D29: =+D25*(1-5%) -> 1572.9196 | E29: =+E25*(1-5%) -> 1572.2066 | F29: =+F25*(1-5%) -> 1567.7445 | G29: =+G25*(1-5%) -> 1630.4208 | H29: =+H25*(1-5%) -> 1557.1068 | I29: =+I25*(1-5%) -> 1394.666 | J29: =+J25*(1-5%) -> 1328.615 | ... W29: =+W25*(1-5%) -> 1092.8639 | X29: =1.33255813953488*1000 -> 1332.5581 | Y29: 1386.3641 | Z29: =+Y29 -> 1386.3641 | AA29: =+Z29 -> 1386.3641 | AB29: =+AA29 -> 1386.3641 | AC29: =+AB29 -> 1386.3641 | AD29: 1412.3596 | AE29: 1412.3596 | AF29: 1412.3596 | AG29: =+AF29 -> 1412.3596 | AH29: =+AG29 -> 1412.3596 | AI29: 1394.54 | AJ29: 1394.54 | AK29: =+AJ29 -> 1394.54 | AL29: =+AK29 -> 1394.54 | AM29: 1485 | AN29: =+AM29 -> 1485 | AO29: =+AN29 -> 1485 | AP29: 1509.0541 | AQ29: =+AP29 -> 1509.0541 | AS29: InV final N-1 | AT29: =+AT16-AT33 -> 401.55869 | AU29: =+AU16-AU33 -> 908.05933 | AV29: =+AV16-AV33 -> 1483.5279 | AW29: =+AW16-AW33 -> 1598.3076 | AX29: =+AX16-AX33 -> 1458.4018 | AY29: =+AY16-AY33 -> 1759.3719 | AZ29: =+AZ16-AZ33 -> 1733.7381 | BA29: =+BA16-BA33 -> 1768.1042 | BB29: =+BB16-BB33 -> 1581.1042
B30: Resin PCR % Enkador FIFO | AP30: =+AP29 -> 1509.0541 | AQ30: =+AQ29 -> 1509.0541
B31: Resin PCR % Enka | Y31: 1070.2457 | Z31: 1103.3118 | AA31: 1103.3118 | AB31: 1149.9847 | AC31: 1149.9847 | AD31: 1163.7352 | AE31: 1163.7352 | AF31: 6 | AG31: 1125.2337 | AH31: 1153.6209 | AI31: 1197.5282 | AJ31: 1277.3813 | AK31: 1467.9415 | AL31: 1432.478 | AM31: 1415.0274 | AN31: 1623.5225 | AO31: 1586.6292 | AP31: 1609.9822 | AQ31: 1643.8952 | AS31: Inv final N | AT31: =+AT23 -> 507 | AU31: =+AU23 -> 576 | AV31: =+AV23 -> 500 | AW31: =+AW23 -> 350 | AX31: =+AX23 -> 500 | AY31: =+AY23 -> 440 | AZ31: =+AZ23 -> 500 | BA31: =+BA23 -> 330 | BB31: =+BB23 -> 475
AS33: Venta Tons | AT33: 0.44130911 | AU33: 0.49935667 | AV33: 0.53142426 | AW33: 385.22033 | AX33: 489.90583 | AY33: 199.02983 | AZ33: 465.63387 | BA33: 465.63387 | BB33: 517
B34: Precio ponderado bajo formula 50 PCR /50 Virgen Enkador | U34: =+(U29*50%)+(U59*50%) -> 531.97998 | V34: =+(V25*50%)+(V29*50%) -> 1100.761 | W34: =+(W25*50%)+(W29*50%) -> 1121.6234 | X34: =+(X25*50%)+(X29*50%) -> 1241.4706 | Y34: =+(Y25*50%)+(Y29*50%) -> 1204.7359 | Z34: =+(Z25*50%)+(Z29*50%) -> 1154.2059 | AA34: =+(AA25*50%)+(AA29*50%) -> 1186.407 | AB34: =+(AB25*50%)+(AB29*50%) -> 1163.0802 | AC34: =+(AC25*50%)+(AC29*50%) -> 1174.222 | ... AI34: =+(AI25*50%)+(AI29*50%) -> 1149.9627 | AJ34: =+(AJ26*50%)+(AJ29*50%) -> 1248.5543 | AK34: =+(AK26*50%)+(AK29*50%) -> 1309.087 | AL34: =+(AL26*50%)+(AL29*50%) -> 1356.2228 | AM34: =+(AM26*50%)+(AM29*50%) -> 1449.1676 | AN34: =+(AN26*50%)+(AN29*50%) -> 1534.4045 | AO34: =+(AO26*50%)+(AO29*50%) -> 1508.4213 | AP34: =+(AP27*50%)+(AP30*50%) -> 1436.6724 | AQ34: =+(AQ27*50%)+(AQ30*50%) -> 1457.8842 | AS34: Inv final Tons | AT34: =+AT29+AT31 -> 908.55869 | AU34: =+AU29+AU31 -> 1484.0593 | AV34: =+AV29+AV31 -> 1983.5279 | AW34: =+AW29+AW31 -> 1948.3076 | AX34: =+AX29+AX31 -> 1958.4018 | AY34: =+AY29+AY31 -> 2199.3719 | AZ34: =+AZ29+AZ31 -> 2233.7381 | BA34: =+BA29+BA31 -> 2098.1042 | BB34: =+BB29+BB31 -> 2056.1042
B35: Scrap 1% | U35: =+U34*1% -> 5.3197998 | V35: =+V34*1% -> 11.00761 | W35: =+W34*1% -> 11.216234 | X35: =+X34*1% -> 12.414706 | Y35: =+Y34*1% -> 12.047359 | Z35: =+Z34*1% -> 11.542059 | AA35: =+AA34*1% -> 11.86407 | AB35: =+AB34*1% -> 11.630802 | ... AQ35: =+AQ34*1% -> 14.578842 | AS35: Precio ponderado | AT35: =+((AT29*AT19)+(AT31*AT28))/(AT34) -> 1015.1511 | AU35: =+((AU29*AU19)+(AU31*AU28))/(AU34) -> 1049.08 | AV35: =+((AV29*AV19)+(AV31*AV28))/(AV34) -> 1093.0809 | AW35: =+((AW29*AW19)+(AW31*AW28))/(AW34) -> 1133.4691 | AX35: =+((AX29*AX19)+(AX31*AX28))/(AX34) -> 1204.9217 | AY35: =+((AY29*AY19)+(AY31*AY28))/(AY34) -> 1280.7208 | AZ35: =+((AZ29*AZ19)+(AZ31*AZ28))/(AZ34) -> 1336.9319 | BA35: =+((BA29*BA19)+(BA31*BA28))/(BA34) -> 1364.2907 | BB35: =+((BB29*BB19)+(BB31*BB28))/(BB34) -> 1406.7142
B36: Precio ponderado con scrap | U36: =+U35+U34 -> 537.29978 | V36: =+V35+V34 -> 1111.7686 | W36: =+W35+W34 -> 1132.8397 | X36: =+X35+X34 -> 1253.8853 | Y36: =+Y35+Y34 -> 1216.7833 | Z36: =+Z35+Z34 -> 1165.748 | AA36: =+AA35+AA34 -> 1198.2711 | AB36: =+AB35+AB34 -> 1174.711 | ... AQ36: =+AQ35+AQ34 -> 1472.463
AZ37: FIFO PCR
B38: Precio ponderado bajo formula 100% PCR Enka | Y38: =+Y31 -> 1070.2457 | Z38: =+Z31 -> 1103.3118 | AA38: =+AA31 -> 1103.3118 | AB38: =+AB31 -> 1149.9847 | AC38: =+AC31 -> 1149.9847 | AD38: =+AD31 -> 1163.7352 | AE38: =+AE31 -> 1163.7352 | AF38: =+AF31 -> 6 | ... AQ38: =+AQ31 -> 1643.8952 | AZ38: JUN | BA38: JUL | BB38: AGO
B39: Scrap 1% | Y39: =+Y38*1% -> 10.702457 | Z39: =+Z38*1% -> 11.033118 | AA39: =+AA38*1% -> 11.033118 | AB39: =+AB38*1% -> 11.499847 | AC39: =+AC38*1% -> 11.499847 | AD39: =+AD38*1% -> 11.637352 | AE39: =+AE38*1% -> 11.637352 | AF39: =+AF38*1% -> 0.06 | ... AQ39: =+AQ38*1% -> 16.438952 | AS39: Inv inicial Tons N-1
B40: Precio ponderado con scrap | Y40: =+Y39+Y38 -> 1080.9482 | Z40: =+Z39+Z38 -> 1114.3449 | AA40: =+AA39+AA38 -> 1114.3449 | AB40: =+AB39+AB38 -> 1161.4845 | AC40: =+AC39+AC38 -> 1161.4845 | AD40: =+AD39+AD38 -> 1175.3725 | AE40: =+AE39+AE38 -> 1175.3725 | AF40: =+AF39+AF38 -> 6.06 | ... AQ40: =+AQ39+AQ38 -> 1660.3341 | AS40: Fórmula N-1
AS41: Ingresos Tons N
B42: Precio ponderado bajo formula 75 PCR /25 Virgen Enkador | AH42: =+(AH25*25%)+(AH29*75%) -> 1288.0475 | AI42: =+(AI25*25%)+(AI29*75%) -> 1272.2514 | AJ42: =+(AJ26*25%)+(AJ29*75%) -> 1321.5471 | AK42: =+(AK26*25%)+(AK29*75%) -> 1351.8135 | AL42: =+(AL26*25%)+(AL29*75%) -> 1375.3814 | AM42: =+(AM26*25%)+(AM29*75%) -> 1467.0838 | AN42: =+(AN26*25%)+(AN29*75%) -> 1509.7022 | AO42: =+(AO26*25%)+(AO29*75%) -> 1496.7106 | AP42: =+(AP27*25%)+(AP30*75%) -> 1472.8633 | AQ42: =+(AQ27*25%)+(AQ30*75%) -> 1483.4691 | AS42: Precio N
B43: Scrap 1% | AH43: =+AH42*1% -> 12.880475 | AI43: =+AI42*1% -> 12.722514 | AJ43: =+AJ42*1% -> 13.215471 | AK43: =+AK42*1% -> 13.518135 | AL43: =+AL42*1% -> 13.753814 | AM43: =+AM42*1% -> 14.670838 | AN43: =+AN42*1% -> 15.097022 | AO43: =+AO42*1% -> 14.967106 | ... AQ43: =+AQ42*1% -> 14.834691 | AS43: Venta
B44: Precio ponderado con scrap | AH44: =+AH43+AH42 -> 1300.928 | AI44: =+AI43+AI42 -> 1284.9739 | AJ44: =+AJ43+AJ42 -> 1334.7626 | AK44: =+AK43+AK42 -> 1365.3316 | AL44: =+AL43+AL42 -> 1389.1352 | AM44: =+AM43+AM42 -> 1481.7546 | AN44: =+AN43+AN42 -> 1524.7993 | AO44: =+AO43+AO42 -> 1511.6777 | ... AQ44: =+AQ43+AQ42 -> 1498.3038 | AS44: Precio Ponderado
AS45: Inventario final N-1
B46: Precio ponderado bajo formula 100% PCR Enkador | U46: =+U29 -> 1063.96 | V46: =+V29 -> 1072.5364 | W46: =+W29 -> 1092.8639 | X46: =+X29 -> 1332.5581 | Y46: =+Y29 -> 1386.3641 | Z46: =+Z29 -> 1386.3641 | AA46: =+AA29 -> 1386.3641 | AB46: =+AB29 -> 1386.3641 | ... AO46: =+AO29 -> 1485 | AP46: =+AP30 -> 1509.0541 | AQ46: =+AQ30 -> 1509.0541 | AS46: Inventario final N | AT46: =+(AT25+AI19) -> 285.28618 | AU46: =+(AU25+AJ19) -> 285.28618 | AV46: =+(AV25+AK19) -> 326.28618 | AW46: =+(AW25+AL19) -> 326.28618 | AX46: =+AX47/22 -> 309.09091 | AY46: =+AY47/22 -> 309.09091
B47: Scrap 1% | U47: =+U46*1% -> 10.6396 | V47: =+V46*1% -> 10.725364 | W47: =+W46*1% -> 10.928639 | X47: =+X46*1% -> 13.325581 | Y47: =+Y46*1% -> 13.863641 | Z47: =+Z46*1% -> 13.863641 | AA47: =+AA46*1% -> 13.863641 | AB47: =+AB46*1% -> 13.863641 | ... AQ47: =+AQ46*1% -> 15.090541 | AS47: Precio Ponderado | AT47: =+AT46*22 -> 6276.2959 | AU47: =+AU46*22 -> 6276.2959 | AV47: =+AV46*22 -> 7178.2959 | AW47: =+AW46*22 -> 7178.2959 | AX47: 6800 | AY47: 6800
B48: Precio ponderado con scrap | U48: =+U47+U46 -> 1074.5996 | V48: =+V47+V46 -> 1083.2617 | W48: =+W47+W46 -> 1103.7925 | X48: =+X47+X46 -> 1345.8837 | Y48: =+Y47+Y46 -> 1400.2277 | Z48: =+Z47+Z46 -> 1400.2277 | AA48: =+AA47+AA46 -> 1400.2277 | AB48: =+AB47+AB46 -> 1400.2277 | ... AQ48: =+AQ47+AQ46 -> 1524.1447
B50: Precio ponderado bajo formula 100% VIRGEN | X50: =+X25 -> 1150.383 | Y50: =+Y25 -> 1023.1077 | Z50: =+Z25 -> 922.0478 | AA50: =+AA25 -> 986.45 | AB50: =+AB25 -> 939.79624 | AC50: =+AC25 -> 962.08 | AD50: =+AD25 -> 950.59588 | AE50: =+AE25 -> 956.04 | ... AI50: =+AI25 -> 905.3855 | AJ50: =+AJ26 -> 1102.5685 | AK50: =+AK26 -> 1223.634 | AL50: =+AL26 -> 1317.9056 | AM50: =+AM26 -> 1413.3351 | AN50: =+AN26 -> 1583.8089 | AO50: =+AO26 -> 1531.8425 | AP50: =+AP27 -> 1364.2907 | AQ50: =+AQ27 -> 1406.7142
B51: Scrap 1% | X51: =+X50*1% -> 11.50383 | Y51: =+Y50*1% -> 10.231077 | Z51: =+Z50*1% -> 9.220478 | AA51: =+AA50*1% -> 9.8645 | AB51: =+AB50*1% -> 9.3979624 | AC51: =+AC50*1% -> 9.6208 | AD51: =+AD50*1% -> 9.5059588 | AE51: =+AE50*1% -> 9.5604 | ... AQ51: =+AQ50*1% -> 14.067142
B52: Precio ponderado con scrap | X52: =+X51+X50 -> 1161.8868 | Y52: =+Y51+Y50 -> 1033.3388 | Z52: =+Z51+Z50 -> 931.26827 | AA52: =+AA51+AA50 -> 996.3145 | AB52: =+AB51+AB50 -> 949.1942 | AC52: =+AC51+AC50 -> 971.7008 | AD52: =+AD51+AD50 -> 960.10183 | AE52: =+AE51+AE50 -> 965.6004 | ... AQ52: =+AQ51+AQ50 -> 1420.7813
B54: Precio ponderado bajo formula 50 PCR /50 Enka | Y54: =+Y61 -> 0 | Z54: =+Z61 -> 0 | AA54: =+AA61 -> 0 | AB54: =+AB61 -> 0 | AC54: =+(AC25*50%)+(AC31*50%) -> 1056.0323 | AD54: =+(AD25*50%)+(AD31*50%) -> 1057.1655 | AE54: =+(AE25*50%)+(AE31*50%) -> 1059.8876 | AF54: =+(AF25*50%)+(AF31*50%) -> 466.49239 | AG54: =+(AG25*50%)+(AG31*50%) -> 1019.0123 | AH54: =+(AH25*50%)+(AH31*50%) -> 1034.3661 | AI54: =+(AI25*50%)+(AI31*50%) -> 1051.4569 | AJ54: =+(AJ26*50%)+(AJ31*50%) -> 1189.9749 | AK54: =+(AK26*50%)+(AK31*50%) -> 1345.7877 | AL54: =+(AL26*50%)+(AL31*50%) -> 1375.1918 | AM54: =+(AM26*50%)+(AM31*50%) -> 1414.1813 | AN54: =+(AN26*50%)+(AN31*50%) -> 1603.6657 | AO54: =+(AO26*50%)+(AO31*50%) -> 1559.2359 | AP54: =+(AP27*50%)+(AP31*50%) -> 1487.1365 | AQ54: =+(AQ27*50%)+(AQ31*50%) -> 1525.3047
B55: Scrap 1% | Y55: =+Y54*1% -> 0 | Z55: =+Z54*1% -> 0 | AA55: =+AA54*1% -> 0 | AB55: =+AB54*1% -> 0 | AC55: =+AC54*1% -> 10.560323 | AD55: =+AD54*1% -> 10.571655 | AE55: =+AE54*1% -> 10.598876 | AF55: =+AF54*1% -> 4.6649239 | ... AQ55: =+AQ54*1% -> 15.253047
B56: Precio ponderado con scrap | Y56: =+Y55+Y54 -> 0 | Z56: =+Z55+Z54 -> 0 | AA56: =+AA55+AA54 -> 0 | AB56: =+AB55+AB54 -> 0 | AC56: =+AC55+AC54 -> 1066.5926 | AD56: =+AD55+AD54 -> 1067.7372 | AE56: =+AE55+AE54 -> 1070.4865 | AF56: =+AF55+AF54 -> 471.15731 | ... AQ56: =+AQ55+AQ54 -> 1540.5577
B58: Precio ponderado bajo formula 75 PCR /25 Enka | AQ58: =+(AQ31*75%)+(AQ27*25%) -> 1584.5999
B59: Scrap 1% | AQ59: =+AQ58*1% -> 15.845999
B60: Precio ponderado con scrap | AQ60: =+AQ59+AQ58 -> 1600.4459
B61: Precio ponderado con scrap | C61: =+C60+C59 -> 0 | D61: =+D60+D59 -> 0 | E61: =+E60+E59 -> 0 | F61: =+F60+F59 -> 0 | G61: =+G60+G59 -> 0 | H61: =+H60+H59 -> 0 | I61: =+I60+I59 -> 0 | J61: =+J60+J59 -> 0 | ... AQ61: =+AQ60+AQ59 -> 1616.2919
B62: Precio ponderado bajo formula 10% PCR Enkador / 90% virgen | X62: =+(X25*90%)+(X29*10%) -> 1168.6005 | Y62: =+(Y25*90%)+(Y29*10%) -> 1059.4334 | Z62: =+(Z25*90%)+(Z29*10%) -> 968.47943 | AA62: =+(AA25*90%)+(AA29*10%) -> 1026.4414 | AB62: =+(AB25*90%)+(AB29*10%) -> 984.45302 | AC62: =+(AC25*90%)+(AC29*10%) -> 1004.5084 | AD62: =+(AD25*90%)+(AD29*10%) -> 996.77225 | AE62: =+(AE25*90%)+(AE29*10%) -> 1001.672 | ... AI62: =+(AI25*90%)+(AI29*10%) -> 954.30095 | AJ62: =+(AJ27*90%)+(AJ29*10%) -> 1083.626 | AK62: =+(AK27*90%)+(AK29*10%) -> 1123.2268 | AL62: =+(AL27*90%)+(AL29*10%) -> 1159.5762 | AM62: =+(AM27*90%)+(AM29*10%) -> 1232.9296 | AN62: =+(AN27*90%)+(AN29*10%) -> 1301.1487 | AO62: =+(AO27*90%)+(AO29*10%) -> 1351.7387 | AP62: =+(AP27*90%)+(AP29*10%) -> 1378.7671 | AQ62: =+(AQ27*90%)+(AQ29*10%) -> 1416.9482
B63: Scrap 1% | X63: =+X62*1% -> 11.686005 | Y63: =+Y62*1% -> 10.594334 | Z63: =+Z62*1% -> 9.6847943 | AA63: =+AA62*1% -> 10.264414 | AB63: =+AB62*1% -> 9.8445302 | AC63: =+AC62*1% -> 10.045084 | AD63: =+AD62*1% -> 9.9677225 | AE63: =+AE62*1% -> 10.01672 | ... AQ63: =+AQ62*1% -> 14.169482
B64: Precio ponderado con scrap | X64: =+X63+X62 -> 1180.2865 | Y64: =+Y63+Y62 -> 1070.0277 | Z64: =+Z63+Z62 -> 978.16422 | AA64: =+AA63+AA62 -> 1036.7058 | AB64: =+AB63+AB62 -> 994.29755 | AC64: =+AC63+AC62 -> 1014.5535 | AD64: =+AD63+AD62 -> 1006.74 | AE64: =+AE63+AE62 -> 1011.6887 | ... AQ64: =+AQ63+AQ62 -> 1431.1176
B66: Precio ponderado bajo formula 25% PCR Enka / 75% Virgen | Y66: =+(Y25*75%)+(Y31*25%) -> 1034.8922 | Z66: =+(Z25*75%)+(Z31*25%) -> 967.36379 | AA66: =+(AA25*75%)+(AA31*25%) -> 1015.6654 | AB66: =+(AB25*75%)+(AB31*25%) -> 992.34334 | AC66: =+(AC25*75%)+(AC31*25%) -> 1009.0562 | AD66: =+(AD25*75%)+(AD31*25%) -> 1003.8807 | AE66: =+(AE25*75%)+(AE31*25%) -> 1007.9638 | AF66: =+(AF25*75%)+(AF31*25%) -> 696.73858 | ... AI66: =+(AI25*75%)+(AI31*25%) -> 978.42118 | AJ66: =+(AJ27*75%)+(AJ31*25%) -> 1106.1553 | AK66: =+(AK27*75%)+(AK31*25%) -> 1186.796 | AL66: =+(AL27*75%)+(AL31*25%) -> 1208.2213 | AM66: =+(AM27*75%)+(AM31*25%) -> 1257.4482 | AN66: =+(AN27*75%)+(AN31*25%) -> 1366.4212 | AO66: =+(AO27*75%)+(AO31*25%) -> 1399.3562 | AP66: =+(AP27*75%)+(AP31*25%) -> 1425.7136 | AQ66: =+(AQ27*75%)+(AQ31*25%) -> 1466.0094
B67: Scrap 1% | Y67: =+Y66*1% -> 10.348922 | Z67: =+Z66*1% -> 9.6736379 | AA67: =+AA66*1% -> 10.156654 | AB67: =+AB66*1% -> 9.9234334 | AC67: =+AC66*1% -> 10.090562 | AD67: =+AD66*1% -> 10.038807 | AE67: =+AE66*1% -> 10.079638 | AF67: =+AF66*1% -> 6.9673858 | ... AQ67: =+AQ66*1% -> 14.660094
B68: Precio ponderado con scrap | Y68: =+Y67+Y66 -> 1045.2412 | Z68: =+Z67+Z66 -> 977.03742 | AA68: =+AA67+AA66 -> 1025.8221 | AB68: =+AB67+AB66 -> 1002.2668 | AC68: =+AC67+AC66 -> 1019.1467 | AD68: =+AD67+AD66 -> 1013.9195 | AE68: =+AE67+AE66 -> 1018.0434 | AF68: =+AF67+AF66 -> 703.70597 | ... AQ68: =+AQ67+AQ66 -> 1480.6695

Sheet PCR Aurora 
F6: Actualización apertura de precios resina PCR Aurora.
D8: PRECIO ENKA | E8: 45352 | F8: 45383 | G8: 45413 | H8: 45444 | I8: 45474 | J8: 45505 | K8: 45536 | L8: 45566 | M8: 45597 | N8: 45627 | O8: 45658 | P8: 45689 | Q8: 45717 | R8: 45748 | S8: 45778 | T8: 45809 | U8: 45839 | V8: 45870 | W8: 45901 | X8: 45931 | Y8: 45962 | Z8: 45992 | AA8: 46023 | AB8: 46054 | AC8: 46082
D9: Precio Enka COP | E9: 6919000 | F9: 6951000 | G9: 7065000 | H9: 7184000 | I9: 7628000 | J9: 7905000 | K9: 8235000 | L9: 8591000 | M9: 8882000 | N9: 8898000 | O9: 9038000 | P9: 9239000 | Q9: 9255000 | R9: 9278000 | S9: 9288000 | T9: =+' PCR Enkador'!AW129 -> 9280000 | U9: =+' PCR Enkador'!AX129 -> 9048000 | V9: =+' PCR Enkador'!AY129 -> 8873000 | W9: =+' PCR Enkador'!AZ129 -> 8620000 | X9: =+' PCR Enkador'!BA129 -> 8376000 | Y9: =+' PCR Enkador'!BB129 -> 8179000 | Z9: =+' PCR Enkador'!BC129 -> 8048000 | AA9: =+' PCR Enkador'!BD129 -> 7872000 | ... AC9: =+' PCR Enkador'!BF129 -> 7782000 | AI9: =+AB9/AB10 -> 2113.1521
D10: TRM último mes | E10: 3931.5076 | F10: 3899.3413 | G10: 3867.9753 | H10: 3869.1006 | I10: 4042.797 | J10: 4035.1843 | K10: 4065.5465 | L10: 4182.5123 | M10: 4249.47 | N10: 4408.6523 | O10: 4385.1487 | P10: 4308.3929 | Q10: 4128.2444 | R10: 4137.6845 | S10: 4282.0277 | T10: =+'PCR Enka'!DQ22 -> 4203.3771 | U10: =+'PCR Enka'!DR22 -> 4113.485 | V10: =+' PCR Enkador'!AY130 -> 4040.8484 | W10: =+' PCR Enkador'!AZ130 -> 4047.4116 | X10: =+' PCR Enkador'!BA130 -> 3922.2552 | Y10: =+'PCR Enka'!EF63 -> 3877.8448 | Z10: =+'PCR Enka'!EH63 -> 3786.1833 | AA10: =+'PCR Enka'!EJ63 -> 3791.4719 | AB10: =+' PCR Enkador'!BE130 -> 3702.999 | AC10: =+'PCR Enka'!EN63 -> 3672.2837
D11: Precio Enka USD | E11: =+E9/E10 -> 1759.8847 | F11: =+F9/F10 -> 1782.6088 | G11: =+G9/G10 -> 1826.537 | H11: =+H9/H10 -> 1856.7622 | I11: =+I9/I10 -> 1886.8125 | J11: =+J9/J10 -> 1959.0183 | K11: =+K9/K10 -> 2025.558 | L11: =+L9/L10 -> 2054.0286 | ... AC11: =+AC9/AC10 -> 2119.1173
D12: Financiación % | E12: =+((5.25274%+2.5%)/365)*210 -> 0.044604805 | F12: =+((5.25274%+2.5%)/365)*210 -> 0.044604805 | G12: =+((5.25274%+2.5%)/365)*210 -> 0.044604805 | H12: =+((5.25274%+2.5%)/365)*210 -> 0.044604805 | I12: =+((5.25274%+2.5%)/365)*210 -> 0.044604805 | J12: =+((5.25274%+2.5%)/365)*210 -> 0.044604805 | K12: =+((5.25274%+2.5%)/365)*210 -> 0.044604805 | L12: 0.044604805 | M12: 0.044604805 | N12: 0.044604805 | O12: 0.038765425 | P12: 0.038765425 | Q12: 0.038765425 | R12: =+' PCR Enkador'!AU132 -> 0.038240482 | S12: =+' PCR Enkador'!AV132 -> 0.038240482 | T12: =+' PCR Enkador'!AW132 -> 0.038240482 | U12: =+' PCR Enkador'!AX132 -> 0.038240482 | V12: =+' PCR Enkador'!AY132 -> 0.038240482 | W12: =+' PCR Enkador'!AZ132 -> 0.038240482 | X12: =+' PCR Enkador'!BA132 -> 0.038240482 | Y12: =+' PCR Enkador'!BB132 -> 0.038240482 | Z12: =+' PCR Enkador'!BC132 -> 0.038240482 | AA12: =+SOFR!$F$3 -> 0.034967129 | AB12: =+SOFR!$F$3 -> 0.034967129 | AC12: =+SOFR!$F$3 -> 0.034967129
D13: Financiación USD | E13: =+E12*E11 -> 78.499314 | F13: =+F12*F11 -> 79.512918 | G13: =+G12*G11 -> 81.472327 | H13: =+H12*H11 -> 82.820519 | I13: =+I12*I11 -> 84.160905 | J13: =+J12*J11 -> 87.381631 | K13: =+K12*K11 -> 90.349619 | L13: =+L12*L11 -> 91.619547 | ... AC13: =+AC12*AC11 -> 74.099448
D14: TOTAL USD/Tn | E14: =+E11+E13 -> 1838.384 | F14: =+F11+F13 -> 1862.1217 | G14: =+G11+G13 -> 1908.0093 | H14: =+H11+H13 -> 1939.5828 | I14: =+I11+I13 -> 1970.9734 | J14: =+J11+J13 -> 2046.3999 | K14: =+K11+K13 -> 2115.9076 | L14: =+L11+L13 -> 2145.6482 | ... AC14: =+AC11+AC13 -> 2193.2168
D16: PRECIO ENKADOR | E16: 45352 | F16: 45383 | G16: 45413 | H16: 45444 | I16: 45474 | J16: 45505 | K16: 45536 | L16: 45566 | M16: 45597 | N16: 45627 | O16: 45658 | P16: 45689 | Q16: 45717 | R16: 45748 | S16: 45778 | T16: =+T8 -> 45809 | U16: =+U8 -> 45839 | V16: =+V8 -> 45870 | W16: =+W8 -> 45901 | X16: =+X8 -> 45931 | Y16: =+Y8 -> 45962 | Z16: =+Z8 -> 45992 | AA16: =+AA8 -> 46023 | ... AC16: =+AC8 -> 46082
D17: Precio Enka USD | E17: =+E14 -> 1838.384 | F17: =+F14 -> 1862.1217 | G17: =+G14 -> 1908.0093 | H17: =+H14 -> 1939.5828 | I17: =+I14 -> 1970.9734 | J17: =+J14 -> 2046.3999 | K17: =+K14 -> 2115.9076 | L17: =+L14 -> 2145.6482 | ... AC17: =+AC14 -> 2193.2168
D18: TRANSPORTE | E18: 94.4 | F18: 94.4 | G18: 94.4 | H18: 94.4 | I18: 94.4 | J18: 94.4 | K18: 94.4 | L18: 94.4 | M18: 94.4 | N18: 94.4 | O18: 94.4 | P18: 94.4 | Q18: 94.4 | R18: 94.4 | S18: 94.4 | T18: 94.4 | U18: 94.4 | V18: 94.4 | W18: 94.4 | X18: 94.4 | Y18: 94.4 | Z18: 94.4 | AA18: 94.4 | AB18: 94.4 | AC18: 94.4
D19: Finance Fee | E19: =+E18*E12 -> 4.2106936 | F19: =+F18*F12 -> 4.2106936 | G19: =+G18*G12 -> 4.2106936 | H19: =+H18*H12 -> 4.2106936 | I19: =+I18*I12 -> 4.2106936 | J19: =+J18*J12 -> 4.2106936 | K19: =+K18*K12 -> 4.2106936 | L19: =+L18*L12 -> 4.2106936 | ... AC19: =+AC18*AC12 -> 3.300897
D20: TOTAL | E20: =+E18+E19 -> 98.610694 | F20: =+F18+F19 -> 98.610694 | G20: =+G18+G19 -> 98.610694 | H20: =+H18+H19 -> 98.610694 | I20: =+I18+I19 -> 98.610694 | J20: =+J18+J19 -> 98.610694 | K20: =+K18+K19 -> 98.610694 | L20: =+L18+L19 -> 98.610694 | ... AC20: =+AC18+AC19 -> 97.700897
D21: TOTAL USD/Tn | E21: =+E20+E17 -> 1936.9947 | F21: =+F20+F17 -> 1960.7324 | G21: =+G20+G17 -> 2006.62 | H21: =+H20+H17 -> 2038.1935 | I21: =+I20+I17 -> 2069.5841 | J21: =+J20+J17 -> 2145.0106 | K21: =+K20+K17 -> 2214.5183 | L21: =+L20+L17 -> 2244.2589 | ... AC21: =+AC20+AC17 -> 2290.9177
D23: PRECIO AURORA - 100% Clear | E23: 45352 | F23: 45383 | G23: 45413 | H23: 45444 | I23: 45474 | J23: 45505 | K23: 45536 | L23: 45566 | M23: 45597 | N23: 45627 | O23: 45658 | P23: 45689 | Q23: 45717 | R23: 45748 | S23: 45778 | T23: =+T8 -> 45809 | U23: =+U8 -> 45839 | V23: =+V8 -> 45870 | W23: =+W8 -> 45901 | X23: =+X8 -> 45931 | Y23: =+Y8 -> 45962 | Z23: =+Z8 -> 45992 | AA23: =+AA8 -> 46023 | ... AC23: =+AC8 -> 46082
D24: Bale suelto (COP/kg) | E24: 1850 | F24: 1845.646 | G24: 1926.2517 | H24: 2008.0632 | I24: 2211.41 | J24: 2470 | K24: 2744 | L24: 2993 | M24: 3197 | N24: 3208 | O24: 3306 | P24: 3222 | Q24: 3220 | R24: =+R25*R26/1000 -> 3278.2874 | S24: =+S25*S26/1000 -> 3232.9144 | T24: =+T25*T26/1000 -> 3131.5159 | U24: =+U25*U26/1000 -> 3011.071 | V24: 2600 | W24: 2100 | X24: 1980 | Y24: 1896 | Z24: 1790 | AA24: 1750 | AB24: 1733 | AC24: 1784.99
D25: Precio de Bale | E25: =E24/E26*1000 -> 470.5574 | F25: =F24/F26*1000 -> 473 | G25: =G24/G26*1000 -> 498 | H25: =H24/H26*1000 -> 519 | I25: =I24/I26*1000 -> 547 | J25: =J24/J26*1000 -> 612.11578 | K25: =K24/K26*1000 -> 674.94002 | L25: =L24/L26*1000 -> 715.59861 | ... Q25: =Q24/Q26*1000 -> 779.99257 | R25: 792.3 | S25: 754.99616 | T25: 745 | U25: 732 | V25: =+V24/V26*1000 -> 643.42924 | W25: =+W24/W26*1000 -> 518.85012 | X25: =+X24/X26*1000 -> 504.81162 | Y25: =+Y24/Y26*1000 -> 488.93137 | Z25: =+Z24/Z26*1000 -> 472.77161 | AA25: =+AA24/AA26*1000 -> 461.56217 | AB25: =+AB24/AB26*1000 -> 467.99904 | AC25: =+AC24/AC26*1000 -> 486.07083
D26: TRM | E26: 3931.5076 | F26: 3902 | G26: 3867.9753 | H26: 3869.1006 | I26: 4042.797 | J26: 4035.1843 | K26: 4065.5465 | L26: 4182.5123 | M26: 4249.47 | N26: 4408.6523 | O26: 4385.1487 | P26: 4308.3929 | Q26: 4128.2444 | R26: =+R10 -> 4137.6845 | S26: =+S10 -> 4282.0277 | T26: =+'PCR Enka'!DV63 -> 4203.3771 | U26: =+'PCR Enka'!DR22 -> 4113.485 | V26: =+V10 -> 4040.8484 | W26: =+W10 -> 4047.4116 | X26: =+X10 -> 3922.2552 | Y26: =+Y10 -> 3877.8448 | Z26: =+Z10 -> 3786.1833 | AA26: =+AA10 -> 3791.4719 | AB26: =+AB10 -> 3702.999 | AC26: =+AC10 -> 3672.2837
D27: Compactación del Bale (549) | E27: =549/E26*1000 -> 139.64109 | F27: =549/F26*1000 -> 140.69708 | G27: =549/G26*1000 -> 141.93472 | H27: =549/H26*1000 -> 141.89344 | I27: =549/I26*1000 -> 135.79707 | J27: =549/J26*1000 -> 136.05326 | K27: =549/K26*1000 -> 135.0372 | L27: =549/L26*1000 -> 131.26082 | ... AC27: =549/AC26*1000 -> 149.49825
D28: Logistico | E28: =4500000/18/E26 -> 63.588838 | F28: =4500000/18/F26 -> 64.069708 | G28: =4500000/18/G26 -> 64.633297 | H28: =4500000/18/H26 -> 64.614499 | I28: =4500000/18/I26 -> 61.838376 | J28: =4500000/18/J26 -> 61.955038 | K28: =4500000/18/K26 -> 61.492349 | L28: =4500000/18/L26 -> 59.772687 | ... AC28: =4500000/18/AC26 -> 68.077529
C29: 0.7 | D29: PCR Bale Price | E29: =+E25+E27+E28 -> 673.78733 | F29: =+F25+F27+F28 -> 677.76679 | G29: =+G25+G27+G28 -> 704.56802 | H29: =+H25+H27+H28 -> 725.50794 | I29: =+I25+I27+I28 -> 744.63545 | J29: =+J25+J27+J28 -> 810.12408 | K29: =+K25+K27+K28 -> 871.46957 | L29: =+L25+L27+L28 -> 906.63211 | ... AC29: =+AC25+AC27+AC28 -> 703.64662
C30: 0.72 | D30: PCR Bale Efficiency (70% Sep - 72% Oct) | E30: =+E29/$C$29 -> 962.55333 | F30: =+F29/$C$29 -> 968.23827 | G30: =+G29/$C$29 -> 1006.5257 | H30: =+H29/$C$29 -> 1036.4399 | I30: =+I29/$C$29 -> 1063.7649 | J30: =+J29/$C$29 -> 1157.3201 | K30: =+K29/$C$29 -> 1244.9565 | L30: =+L29/$C$30 -> 1259.2113 | M30: =+M29/$C$30 -> 1306.0452 | N30: =+N29/$C$30 -> 1262.3535 | O30: =+O29/$C$30 -> 1300.1586 | P30: =+P29/$C$30 -> 1296.2426 | Q30: =+Q29/$C$30 -> 1352.1352 | R30: =+R29/$C$30 -> 1368.6155 | S30: =+S29/$C$30 -> 1307.7639 | ... AC30: =+AC29/$C$30 -> 977.28697
D31: Fixed PCR Conversion | E31: 601.25 | F31: 601.25 | G31: 601.25 | H31: 601.25 | I31: 601.25 | J31: 601.25 | K31: 601.25 | L31: 601.25 | M31: 601.25 | N31: 601.25 | O31: 601.25 | P31: 601.25 | Q31: 601.25 | R31: 601.25 | S31: 601.25 | T31: 601.25 | U31: 601.25 | V31: 601.25 | W31: 601.25 | X31: 601.25 | Y31: 601.25 | Z31: 601.25 | AA31: 601.25 | AB31: 601.25 | AC31: 601.25
D32: Adjusted PCR Conversion Cost | E32: 463.43767 | F32: 467.26064 | G32: 471.04972 | H32: 470.91272 | I32: 450.68024 | J32: 451.53048 | K32: 448.15838 | L32: 299.39892 | M32: 294.68137 | N32: 284.04137 | O32: 305.05351 | P32: 310.48817 | Q32: =1388045.05261181/Q26 -> 336.23131 | R32: =1388045.05261181/R26 -> 335.46421 | S32: =1252239/S26 -> 292.44066 | T32: =1252239/T26 -> 297.9126 | U32: =1252239/U26 -> 304.42289 | V32: =1252239/V26 -> 309.89507 | W32: =1252239/W26 -> 309.39255 | X32: =1252239/X26 -> 319.26505 | Y32: =1252239/Y26 -> 322.92138 | Z32: =1252239/Z26 -> 330.73913 | ... AC32: =1252239/AC26 -> 340.99735
D33: PCR Conversion Cost | E33: =+E32+E31 -> 1064.6877 | F33: =+F32+F31 -> 1068.5106 | G33: =+G32+G31 -> 1072.2997 | H33: =+H32+H31 -> 1072.1627 | I33: =+I32+I31 -> 1051.9302 | J33: =+J32+J31 -> 1052.7805 | K33: =+K32+K31 -> 1049.4084 | L33: =+L32+L31 -> 900.64892 | ... AC33: =+AC32+AC31 -> 942.24735
D34: PCR Conversion Efficiency (100%) | E34: =+E33/100% -> 1064.6877 | F34: =+F33/100% -> 1068.5106 | G34: =+G33/100% -> 1072.2997 | H34: =+H33/100% -> 1072.1627 | I34: =+I33/100% -> 1051.9302 | J34: =+J33/100% -> 1052.7805 | K34: =+K33/100% -> 1049.4084 | L34: =+L33/100% -> 900.64892 | ... AC34: =+AC33/100% -> 942.24735
D35: New PCR Freight Cost (Cauca - Cali) | E35: =780000/10/E26 -> 19.839718 | F35: =780000/10/F26 -> 19.989749 | G35: =780000/10/G26 -> 20.165589 | H35: =780000/10/H26 -> 20.159724 | I35: =780000/10/I26 -> 19.293573 | J35: =780000/10/J26 -> 19.329972 | K35: =780000/10/K26 -> 19.185613 | L35: =780000/10/L26 -> 18.649078 | ... AC35: =780000/10/AC26 -> 21.240189
D36: Libor Rate - SOFR Rate | E36: =+((5.25274%+2.5%)/365)*210 -> 0.044604805 | F36: =+((5.25274%+2.5%)/365)*210 -> 0.044604805 | G36: =+((5.25274%+2.5%)/365)*210 -> 0.044604805 | H36: =+((5.25274%+2.5%)/365)*210 -> 0.044604805 | I36: =+((5.25274%+2.5%)/365)*210 -> 0.044604805 | J36: =+((5.25274%+2.5%)/365)*210 -> 0.044604805 | K36: =+((5.25274%+2.5%)/365)*210 -> 0.044604805 | L36: =+((5.25274%+2.5%)/365)*210 -> 0.044604805 | ... N36: =+((5.25274%+2.5%)/365)*210 -> 0.044604805 | O36: =+((4.2378%+2.5%)/365)*210 -> 0.038765425 | P36: =+((4.2378%+2.5%)/365)*210 -> 0.038765425 | Q36: =+((4.2378%+2.5%)/365)*210 -> 0.038765425 | R36: =+((4.2378%+2.5%)/365)*210 -> 0.038765425 | S36: =+((4.2378%+2.5%)/365)*210 -> 0.038765425 | T36: =+((4.2378%+2.5%)/365)*210 -> 0.038765425 | U36: =+((4.2378%+2.5%)/365)*210 -> 0.038765425 | V36: =+((4.2378%+2.5%)/365)*210 -> 0.038765425 | ... Z36: =+((4.2378%+2.5%)/365)*210 -> 0.038765425 | AA36: =+((3.497%+2.5%)/365)*210 -> 0.034503288 | AB36: =+((3.497%+2.5%)/365)*210 -> 0.034503288 | AC36: =+((3.497%+2.5%)/365)*210 -> 0.034503288
D37: Finance Fee @210d | E37: =(E30+E34+E35)*E36 -> 91.309637 | F37: =(F30+F34+F35)*F36 -> 91.740428 | G37: =(G30+G34+G35)*G36 -> 93.625088 | H37: =(H30+H34+H35)*H36 -> 94.953031 | I37: =(I30+I34+I35)*I36 -> 95.230757 | J37: =(J30+J34+J35)*J36 -> 99.443317 | K37: =(K30+K34+K35)*K36 -> 103.19547 | L37: =(L30+L34+L35)*L36 -> 97.171982 | ... AC37: =(AC30+AC34+AC35)*AC36 -> 66.963101
D38: Valor resina | O38: =O30+O34 -> 2206.4621 | P38: =P30+P34 -> 2207.9807 | Q38: =Q30+Q34 -> 2289.6165 | R38: =R30+R34 -> 2305.3297 | S38: =S30+S34 -> 2201.4545 | T38: =T30+T34 -> 2197.8921 | U38: =U30+U34 -> 2192.1162 | V38: =V30+V34 -> 2079.4228 | ... AC38: =AC30+AC34 -> 1919.5343
D39: Discount | U39: -25 | V39: -25 | W39: -25 | X39: -25 | Y39: -25 | Z39: -25 | AA39: -25 | AB39: -25 | AC39: -25
D40: TOTAL USD/Tn | E40: =E30+E34+E35+E37 -> 2138.3904 | F40: =F30+F34+F35+F37 -> 2148.4791 | G40: =G30+G34+G35+G37 -> 2192.6161 | H40: =H30+H34+H35+H37 -> 2223.7154 | I40: =I30+I34+I35+I37 -> 2230.2195 | J40: =J30+J34+J35+J37 -> 2328.8739 | K40: =K30+K34+K35+K37 -> 2416.746 | L40: =L30+L34+L35+L37 -> 2275.6812 | ... N40: =N30+N34+N35+N37 -> 2261.9218 | O40: =+O38+O35+O37 -> 2310.4734 | P40: =+P38+P35+P37 -> 2312.38 | Q40: =+Q38+Q35+Q37 -> 2398.0011 | R40: =+R38+R35+R37 -> 2414.2787 | S40: =+S38+S35+S37 -> 2305.7167 | T40: =+T38+T35+T37 -> 2302.3702 | U40: =+U38+U35+U37+U39 -> 2271.7916 | V40: =+V38+V35+V37+V39 -> 2155.0837 | W40: =+W38+W35+W37+W39 -> 1974.3326 | X40: =+X38+X35+X37+X39 -> 1974.0609 | Y40: =+Y38+Y35+Y37+Y39 -> 1958.5504 | Z40: =+Z38+Z35+Z37+Z39 -> 1951.0595 | AA40: =+AA38+AA35+AA37+AA39 -> 1925.9158 | AB40: =+AB38+AB35+AB37+AB39 -> 1951.0705 | AC40: =+AC38+AC35+AC37+AC39 -> 1982.7376
D42: PCR Ambar | AA42: =+AA40-100 -> 1825.9158 | AB42: =+AB40-100 -> 1851.0705 | AC42: =+AC40-100 -> 1882.7376
D44: Diferencia Aurora Clear Vs Enkador | E44: =+E21-E40 -> -201.39566 | F44: =+F21-F40 -> -187.7467 | G44: =+G21-G40 -> -185.99613 | H44: =+H21-H40 -> -185.52193 | I44: =+I21-I40 -> -160.63537 | J44: =+J21-J40 -> -183.86325 | K44: =+K21-K40 -> -202.22771 | L44: =+L21-L40 -> -31.422395 | ... AC44: =+AC21-AC40 -> 308.18006
D47: PRECIO AURORA - Ambar | E47: 45352 | F47: 45383 | G47: 45413 | H47: 45444 | I47: 45474 | J47: 45505 | K47: 45536 | L47: 45566 | M47: 45597 | N47: 45627 | O47: 45658 | P47: 45689 | Q47: 45717 | R47: 45748 | S47: 45778 | T47: 45778 | U47: 45778 | V47: 45778 | W47: 45778 | X47: 45778 | Y47: 45778 | Z47: 45778 | AA47: 45778 | AB47: 45778 | AC47: 45778
D48: Bale suelto (COP/kg) | E48: 1175 | F48: 1200 | G48: 1300 | H48: 1300 | I48: 1300 | J48: 1301 | K48: 1302 | L48: 1302 | M48: 1302 | N48: 1302 | O48: 1302 | P48: 1302 | Q48: 1302
D49: Precio de Bale | E49: =E48/E50*1000 -> 298.86754 | F49: =F48/F50*1000 -> 307.5346 | G49: =G48/G50*1000 -> 336.09315 | H49: =H48/H50*1000 -> 335.9954 | I49: =I48/I50*1000 -> 321.55955 | J49: =J48/J50*1000 -> 322.41402 | K49: =K48/K50*1000 -> 320.25215 | L49: =L48/L50*1000 -> 311.29615 | ... Q49: =Q48/Q50*1000 -> 315.3883
D50: TRM | E50: =+E26 -> 3931.5076 | F50: =+F26 -> 3902 | G50: =+G26 -> 3867.9753 | H50: =+H26 -> 3869.1006 | I50: =+I26 -> 4042.797 | J50: =+J26 -> 4035.1843 | K50: =+K26 -> 4065.5465 | L50: =+L26 -> 4182.5123 | ... Q50: =+Q26 -> 4128.2444
D51: Compactación del Bale (549) | E51: =549/E50*1000 -> 139.64109 | F51: =549/F50*1000 -> 140.69708 | G51: =549/G50*1000 -> 141.93472 | H51: =549/H50*1000 -> 141.89344 | I51: =549/I50*1000 -> 135.79707 | J51: =549/J50*1000 -> 136.05326 | K51: =549/K50*1000 -> 135.0372 | L51: =549/L50*1000 -> 131.26082 | ... Q51: =549/Q50*1000 -> 132.98631
D52: Logistico | E52: =4500000/18/E50 -> 63.588838 | F52: =4500000/18/F50 -> 64.069708 | G52: =4500000/18/G50 -> 64.633297 | H52: =4500000/18/H50 -> 64.614499 | I52: =4500000/18/I50 -> 61.838376 | J52: =4500000/18/J50 -> 61.955038 | K52: =4500000/18/K50 -> 61.492349 | L52: =4500000/18/L50 -> 59.772687 | ... Q52: =4500000/18/Q50 -> 60.558429
D53: PCR Bale Price | E53: =SUM(E49+E51+E52) -> 502.09747 | F53: =SUM(F49+F51+F52) -> 512.30138 | G53: =SUM(G49+G51+G52) -> 542.66116 | H53: =SUM(H49+H51+H52) -> 542.50333 | I53: =SUM(I49+I51+I52) -> 519.195 | J53: =SUM(J49+J51+J52) -> 520.42232 | K53: =SUM(K49+K51+K52) -> 516.7817 | L53: =SUM(L49+L51+L52) -> 502.32966 | ... Q53: =SUM(Q49+Q51+Q52) -> 508.93304
C54: 0.7 | D54: PCR Bale Efficiency (70%) | E54: =E53/$C$54 -> 717.2821 | F54: =F53/$C$54 -> 731.85912 | G54: =G53/$C$54 -> 775.23024 | H54: =H53/$C$54 -> 775.00476 | I54: =I53/$C$54 -> 741.70715 | J54: =J53/$C$54 -> 743.46046 | K54: =K53/$C$54 -> 738.25957 | L54: =L53/$C$54 -> 717.6138 | ... Q54: =Q53/$C$54 -> 727.0472
D55: Fixed PCR Conversion | E55: =+E31 -> 601.25 | F55: =+F31 -> 601.25 | G55: =+G31 -> 601.25 | H55: =+H31 -> 601.25 | I55: =+I31 -> 601.25 | J55: =+J31 -> 601.25 | K55: =+K31 -> 601.25 | L55: =+L31 -> 601.25 | ... Q55: =+Q31 -> 601.25
D56: Adjusted PCR Conversion Cost | E56: =+E32 -> 463.43767 | F56: =+F32 -> 467.26064 | G56: =+G32 -> 471.04972 | H56: =+H32 -> 470.91272 | I56: =+I32 -> 450.68024 | J56: =+J32 -> 451.53048 | K56: =+K32 -> 448.15838 | L56: =+L32 -> 299.39892 | ... Q56: =+Q32 -> 336.23131
C57: 0.82 | D57: PCR Conversion Cost | E57: =+E56+E55 -> 1064.6877 | F57: =+F56+F55 -> 1068.5106 | G57: =+G56+G55 -> 1072.2997 | H57: =+H56+H55 -> 1072.1627 | I57: =+I56+I55 -> 1051.9302 | J57: =+J56+J55 -> 1052.7805 | K57: =+K56+K55 -> 1049.4084 | L57: =+L56+L55 -> 900.64892 | ... Q57: =+Q56+Q55 -> 937.48131
C58: 0.85 | D58: PCR Conversion Efficiency (82% Sep - 85% Oct) | E58: =+E57/$C$57 -> 1298.3996 | F58: =+F57/$C$57 -> 1303.0618 | G58: =+G57/$C$57 -> 1307.6826 | H58: =+H57/$C$57 -> 1307.5155 | I58: =+I57/$C$57 -> 1282.8418 | J58: =+J57/$C$57 -> 1283.8786 | K58: =+K57/$C$57 -> 1279.7663 | L58: =+L57/$C$58 -> 1059.587 | M58: =+M57/$C$58 -> 1054.0369 | N58: =+N57/$C$58 -> 1041.5193 | O58: =+O57/$C$58 -> 1066.2394 | P58: =+P57/$C$58 -> 1072.6331 | Q58: =+Q57/$C$58 -> 1102.9192
D59: New PCR Freight Cost (Cauca - Cali) | E59: =+E35 -> 19.839718 | F59: =+F35 -> 19.989749 | G59: =+G35 -> 20.165589 | H59: =+H35 -> 20.159724 | I59: =+I35 -> 19.293573 | J59: =+J35 -> 19.329972 | K59: =+K35 -> 19.185613 | L59: =+L35 -> 18.649078 | ... Q59: =+Q35 -> 18.89423
D60: Libor Rate - SOFR Rate | E60: =+E36 -> 0.044604805 | F60: =+F36 -> 0.044604805 | G60: =+G36 -> 0.044604805 | H60: =+H36 -> 0.044604805 | I60: =+I36 -> 0.044604805 | J60: =+J36 -> 0.044604805 | K60: =+K36 -> 0.044604805 | L60: =+L36 -> 0.044604805 | ... Q60: =+Q36 -> 0.038765425
D61: Finance Fee @210d | E61: =(E54+E58+E59)*E60 -> 90.794036 | F61: =(F54+F58+F59)*F60 -> 91.658889 | G61: =(G54+G58+G59)*G60 -> 93.807404 | H61: =(H54+H58+H59)*H60 -> 93.789632 | I61: =(I54+I58+I59)*I60 -> 91.165196 | J61: =(J54+J58+J59)*J60 -> 91.291275 | K61: =(K54+K58+K59)*K60 -> 90.869423 | L61: =(L54+L58+L59)*L60 -> 80.103533 | ... Q61: =(Q54+Q58+Q59)*Q60 -> 71.671867
D62: TOTAL USD/Tn | E62: =E54+E58+E59+E61 -> 2126.3154 | F62: =F54+F58+F59+F61 -> 2146.5695 | G62: =G54+G58+G59+G61 -> 2196.8858 | H62: =H54+H58+H59+H61 -> 2196.4696 | I62: =I54+I58+I59+I61 -> 2135.0077 | J62: =J54+J58+J59+J61 -> 2137.9603 | K62: =K54+K58+K59+K61 -> 2128.0809 | L62: =L54+L58+L59+L61 -> 1875.9534 | ... Q62: =Q54+Q58+Q59+Q61 -> 1920.5325
D65: Promedio 50% Clear / 50% Ambar | E65: =(+E62+E40)/2 -> 2132.3529 | F65: =(+F62+F40)/2 -> 2147.5243 | G65: =(+G62+G40)/2 -> 2194.751 | H65: =(+H62+H40)/2 -> 2210.0925 | I65: =(+I62+I40)/2 -> 2182.6136 | J65: =(+J62+J40)/2 -> 2233.4171 | K65: =(+K62+K40)/2 -> 2272.4135 | L65: =(+L62+L40)/2 -> 2075.8173 | ... Q65: =(+Q62+Q40)/2 -> 2159.2668

Sheet  PCR Enkador
B1: Fórmula ABI - ENKADOR
B20: Ejemplo precio
B22: Simulación Precio | H22: Global PET Stream - Monthly Market Report Issue 132
B23: Indice | D23: Min ($/TM) | E23: Max ($/TM) | F23: Promedio ($/TM)
B24: IHS | D24: 1293 | E24: 1337 | F24: =+(D24+E24)/2 -> 1315
B25: ICIS | D25: 1212.54 | E25: 1322.77 | F25: =+(D25+E25)/2 -> 1267.655
B26: Promedio | D26: =+(D24+D25)/2 -> 1252.77 | E26: =+(E24+E25)/2 -> 1329.885 | F26: =+IF(((F24+F25)/2)>D30,D30,((F24+F25)/2)) -> 1291.3275
B29: Piso | D29: 1275
B30: Techo | D30: 1400
B42: Precio actualizado
B44: USD/TN EXW | D44: ICIS WC PCR | F44: IHS PCR | H44: Promedio de los 2 indices
B45: Mes | D45: Base | E45: Top | F45: Average
B46: 43800 | D46: =+'ICIS PCR'!C21 -> 1212.54 | E46: =+'ICIS PCR'!D21 -> 1322.77 | F46: =+'IHS PCR'!S16 -> 1295.2025 | H46: =+AVERAGE(D46,E46,F46) -> 1276.8375
B47: 43831 | D47: =+'ICIS PCR'!C22 -> 1212.54 | E47: =+'ICIS PCR'!D22 -> 1322.77 | F47: =+'IHS PCR'!T16 -> 1324.9646 | H47: =+AVERAGE(D47,E47,F47) -> 1286.7582
B48: 43862 | D48: =+'ICIS PCR'!C23 -> 1212.54 | E48: =+'ICIS PCR'!D23 -> 1322.77 | F48: =+'IHS PCR'!U16 -> 1322.76 | H48: =+AVERAGE(D48,E48,F48) -> 1286.0233
B49: 43891 | D49: =+'ICIS PCR'!C24 -> 1295.21 | E49: =+'ICIS PCR'!D24 -> 1405.45 | F49: =+'IHS PCR'!V16 -> 1366.852 | H49: =+AVERAGE(D49,E49,F49) -> 1355.8373
D50: =+AVERAGE(D46:D49) -> 1233.2075 | E50: =+AVERAGE(E46:E49) -> 1343.44 | F50: =+AVERAGE(F46:F49) -> 1327.4448 | G50: Promedio | H50: =+AVERAGE(H46:H49) -> 1301.3641
G51: Fórmula | H51: =+IF(H50>$D$30,$D$30,IF(H50<$D$29,$D$29,H50)) -> 1301.3641
D53: Precio ABI: | H53: =+H51 -> 1301.3641
D54: Costo del inland | H54: 85
D55: Sell Side para ABI: | H55: =+H54+H53 -> 1386.3641
B58: USD/TN EXW | D58: ICIS WC PCR | F58: IHS PCR | H58: Promedio de los 2 indices
B59: Mes | D59: Base | E59: Top | F59: Average
B60: 43922 | D60: =+'ICIS PCR'!C25 -> 1322.77 | E60: =+'ICIS PCR'!D25 -> 1433 | F60: =+'IHS PCR'!W16 -> 1311.737 | H60: =+AVERAGE(D60,E60,F60) -> 1355.8357
B61: 43952 | D61: =+'ICIS PCR'!C26 -> 1322.77 | E61: =+'ICIS PCR'!D26 -> 1433 | F61: =+'IHS PCR'!X16 -> 1278.668 | H61: =+AVERAGE(D61,E61,F61) -> 1344.8127
B62: 43983 | D62: =+'ICIS PCR'!C27 -> 1322.77 | E62: =+'ICIS PCR'!D27 -> 1433 | F62: =+'IHS PCR'!Y16 -> 1267.645 | H62: =+AVERAGE(D62,E62,F62) -> 1341.1383
B63: 44013 | D63: =+'ICIS PCR'!C28 -> 1212.54 | E63: =+'ICIS PCR'!D28 -> 1322.77 | F63: =+'IHS PCR'!Z16 -> 1267.645 | H63: =+AVERAGE(D63,E63,F63) -> 1267.6517
D64: =+AVERAGE(D60:D63) -> 1295.2125 | E64: =+AVERAGE(E60:E63) -> 1405.4425 | F64: =+AVERAGE(F60:F63) -> 1281.4237 | G64: Promedio | H64: =+AVERAGE(H60:H63) -> 1327.3596
G65: Fórmula | H65: =+IF(H64>$D$30,$D$30,IF(H64<$D$29,$D$29,H64)) -> 1327.3596
D67: Precio EWX | H67: =+H65 -> 1327.3596
D68: Costo del inland | H68: 85
D69: PRECIO DDP | H69: =+H68+H67 -> 1412.3596
D71: Finance Fee | E71: % | H71: 0.059
D72: Finance Fee | E72: USD | H72: =+H69*H71 -> 83.329215
D73: Sell Side para ABI: | H73: =+H69+H72 -> 1495.6888
B77: USD/TN EXW | D77: ICIS WC PCR | F77: IHS PCR | H77: Promedio de los 2 indices
B78: Mes | D78: Base | E78: Top | F78: Average
B79: 44044 | D79: =+'ICIS PCR'!C29 -> 1212.54 | E79: =+'ICIS PCR'!D29 -> 1322.77 | F79: =+'IHS PCR'!AA16 -> 1267.645 | H79: =+AVERAGE(D79,E79,F79) -> 1267.6517
B80: 44075 | D80: =+'ICIS PCR'!C30 -> 1212.54 | E80: =+'ICIS PCR'!D30 -> 1322.77 | F80: =+'IHS PCR'!AB16 -> 1267.645 | H80: =+AVERAGE(D80,E80,F80) -> 1267.6517
B81: 44105 | D81: =+'ICIS PCR'!C31 -> 1287.5 | E81: =+'ICIS PCR'!D31 -> 1397.73 | F81: =+'IHS PCR'!AC16 -> 1267.645 | H81: =+AVERAGE(D81,E81,F81) -> 1317.625
B82: 44136 | D82: =+'ICIS PCR'!C32 -> 1388.91 | E82: =+'ICIS PCR'!D32 -> 1499.14 | F82: =+'IHS PCR'!AD16 -> 1267.645 | H82: =+AVERAGE(D82,E82,F82) -> 1385.2317
D83: =+AVERAGE(D79:D82) -> 1275.3725 | E83: =+AVERAGE(E79:E82) -> 1385.6025 | F83: =+AVERAGE(F79:F82) -> 1267.645 | G83: Promedio | H83: =+AVERAGE(H79:H82) -> 1309.54
G84: Fórmula | H84: =+IF(H83>$D$30,$D$30,IF(H83<$D$29,$D$29,H83)) -> 1309.54
D86: Precio EWX | H86: =+H84 -> 1309.54
D87: Costo del inland | H87: 85
D88: PRECIO DDP | H88: =+H87+H86 -> 1394.54
D90: Finance Fee | E90: % | H90: =(+SOFR!$F$3/365)*210 -> 0.020118074
D91: Finance Fee | E91: USD | H91: =+H88*H90 -> 28.055459
D92: Sell Side para ABI: | H92: =+H88+H91 -> 1422.5955
B93: USD/TN EXW
D94: ICIS WC PCR | F94: IHS PCR | H94: Promedio de los 2 indices
B95: Mes Precio | C95: Mes index | D95: Base | E95: Top | F95: Average
B96: 44287 | C96: 44197 | D96: =+'ICIS PCR'!C34 -> 1455.05 | E96: =+'ICIS PCR'!D34 -> 1554.26 | F96: =+'IHS PCR'!AF16 -> 1278.668 | H96: =+AVERAGE(D96,E96,F96) -> 1429.326
B97: 44317 | C97: 44228 | D97: =+'ICIS PCR'!C35 -> 1592.84 | E97: =+'ICIS PCR'!D35 -> 1664.49 | F97: =+'IHS PCR'!AG16 -> 1306.2255 | H97: =+AVERAGE(D97,E97,F97) -> 1521.1852
B98: 44348 | C98: 44256 | D98: =+'ICIS PCR'!C36 -> 1719.6 | E98: =+'ICIS PCR'!D36 -> 1785.74 | F98: =+'IHS PCR'!AH16 -> 1350.3175 | H98: =+AVERAGE(D98,E98,F98) -> 1618.5525
D99: =+AVERAGE(D96:D98) -> 1589.1633 | E99: =+AVERAGE(E96:E98) -> 1668.1633 | F99: =+AVERAGE(F96:F98) -> 1311.737 | G99: Promedio | H99: =+AVERAGE(H96:H98) -> 1523.0212
F100: Techo/Piso | H100: =+IF(H99>$D$30,$D$30,IF(H99<$D$29,$D$29,H99)) -> 1400
D102: Precio EWX | H102: =+H100 -> 1400
D103: Costo del inland | H103: 85
D104: PRECIO DDP | H104: =+H103+H102 -> 1485
D106: Finance Fee | E106: % | H106: =(+SOFR!$F$3/365)*210 -> 0.020118074
D107: Finance Fee | E107: USD | H107: =+H104*H106 -> 29.87534
D108: Sell Side para ABI: | H108: =+H104+H107 -> 1514.8753
B110: USD/TN EXW | D110: ICIS WC PCR | F110: IHS PCR | H110: Promedio de los 2 indices
C111: Mes Precio | D111: Base | E111: Top | F111: Average
B112: 44287 | C112: 44378 | D112: =+'ICIS PCR'!D37 -> 1807.79 | E112: =+'ICIS PCR'!C37 -> 1741.65 | F112: =+'IHS PCR'!AI16 -> 1427.4785 | H112: =+AVERAGE(D112,E112,F112) -> 1658.9728
B113: 44317 | C113: 44409 | D113: =+'ICIS PCR'!D38 -> 1873.93 | E113: =+'ICIS PCR'!C38 -> 1763.7 | F113: =+'IHS PCR'!AJ16 -> 1554.243 | H113: =+AVERAGE(D113,E113,F113) -> 1730.6243
B114: 44348 | C114: 44440 | D114: =+'ICIS PCR'!D39 -> 1873.93 | E114: =+'ICIS PCR'!C39 -> 1763.7 | F114: =+'IHS PCR'!AK16 -> 1686.519 | H114: =+AVERAGE(D114,E114,F114) -> 1774.7163
D115: =+AVERAGE(D112:D114) -> 1851.8833 | E115: =+AVERAGE(E112:E114) -> 1756.35 | F115: =+AVERAGE(F112:F114) -> 1556.0802 | G115: Promedio | H115: =+AVERAGE(H112:H114) -> 1721.4378
F116: Techo/Piso | H116: =+IF(H115>$D$30,$D$30,IF(H115<$D$29,$D$29,H115)) -> 1400
D118: Precio EWX | H118: =+H116 -> 1400
D119: Costo del inland | H119: 85 | I119: =100-H119 -> 15
D120: PRECIO DDP | H120: =+H119+H118 -> 1485
D122: Finance Fee | E122: % | H122: =(+SOFR!$F$3/365)*210 -> 0.020118074
D123: Finance Fee | E123: USD | H123: =+H120*H122 -> 29.87534
D124: Sell Side para ABI: | H124: =+H120+H123 -> 1514.8753
B126: Parity Enka acorde al LOI
C128: =+'Fórmula Marzo 26'!AS14 -> Ago-21 | D128: =+'Fórmula Marzo 26'!AT14 -> Sep-21 | E128: =+'Fórmula Marzo 26'!AU14 -> Oct-21 | F128: =+'Fórmula Marzo 26'!AV14 -> Nov-21 | G128: =+'Fórmula Marzo 26'!AW14 -> Dic-21 | H128: =+'Fórmula Marzo 26'!AX14 -> Ene-22 | I128: =+'Fórmula Marzo 26'!AY14 -> Feb-22 | J128: =+'Fórmula Marzo 26'!AZ14 -> Mar-22 | ... BF128: =+'Fórmula Marzo 26'!CV14 -> Mar-26
B129: Precio Enka COP | C129: =+'PCR Enka'!R21 -> 5944440 | D129: =+'PCR Enka'!S21 -> 5944440 | E129: =+'PCR Enka'!T21 -> 5944440 | F129: =+'PCR Enka'!U21 -> 6787540 | G129: =+'PCR Enka'!V21 -> 6787540 | H129: =+'PCR Enka'!W21 -> 6787540 | I129: =+'PCR Enka'!X21 -> 7594650 | J129: 7672000 | K129: =+'PCR Enka'!Z21 -> 7672001 | L129: =+'PCR Enka'!AA21 -> 7785000 | M129: =+'PCR Enka'!AB21 -> 8095000 | N129: =+'PCR Enka'!AC21 -> 8341000 | O129: =+'PCR Enka'!AD21 -> 8381000 | P129: =+'PCR Enka'!AE21 -> 8106000 | Q129: =+'PCR Enka'!AF21 -> 7391000 | R129: =+'PCR Enka'!AG21 -> 6711000 | ... X129: =+'PCR Enka'!AM21 -> 7042000 | Y129: 6945000 | Z129: 6868000 | AA129: 6822000 | AB129: 6672000 | AC129: 6528000 | AD129: 7008000 | AE129: 7100000 | AF129: 7217000 | AG129: 6297000 | AH129: 6919000 | AI129: 6951000 | AJ129: 7065000 | AK129: 7184000 | AL129: 7628000 | AM129: 7905000 | AN129: 8235000 | AO129: 8591000 | AP129: 8882000 | AQ129: 8898000 | AR129: 9038000 | AS129: 9239000 | AT129: 9255000 | AU129: 9278000 | AV129: 9288000 | AW129: 9280000 | AX129: 9048000 | AY129: 8873000 | AZ129: 8620000 | BA129: 8376000 | BB129: 8179000 | BC129: 8048000 | BD129: 7872000 | BE129: 7825000 | BF129: 7782000
B130: TRM último mes | C130: =+'PCR Enka'!R22 -> 3829.4181 | D130: =+'PCR Enka'!S22 -> 3881.1835 | E130: =+'PCR Enka'!T22 -> 3820.3396 | F130: =+'PCR Enka'!U22 -> 3773.3842 | G130: =+'PCR Enka'!V22 -> 3886.6023 | H130: =+'PCR Enka'!W22 -> 3963.1335 | I130: =+'PCR Enka'!X22 -> 3999.6161 | J130: =+'PCR Enka'!Y22 -> 3935.8357 | ... AC130: =+'PCR Enka'!AR22 -> 4004.5207 | AD130: =+'PCR Enka'!CJ63 -> 4222.4332 | AE130: =+'PCR Enka'!CL63 -> 4038.8047 | AF130: =+'PCR Enka'!CC22 -> 3948.2068 | AG130: =+'PCR Enka'!CD22 -> 3914.9835 | AH130: =+'PCR Enka'!CR63 -> 3931.5076 | AI130: =+'PCR Enka'!DC22 -> 3899.3413 | AJ130: =+'PCR Enka'!DD22 -> 3867.9753 | AK130: =+'PCR Enka'!CX63 -> 3869.1006 | AL130: =+'PCR Enka'!CZ63 -> 4042.797 | AM130: =+'PCR Enka'!DB63 -> 4035.1843 | AN130: =+'PCR Enka'!DH22 -> 4065.5465 | AO130: =+'PCR Enka'!DI22 -> 4182.5123 | AP130: =+'PCR Enka'!DJ22 -> 4249.47 | AQ130: =+'PCR Enka'!DK22 -> 4408.6523 | AR130: =+'PCR Enka'!DL22 -> 4385.1487 | AS130: =+'PCR Enka'!DM22 -> 4308.3929 | AT130: =+'PCR Enka'!DN22 -> 4128.2444 | AU130: =+'PCR Enka'!DO22 -> 4137.6845 | ... AX130: =+'PCR Enka'!DR22 -> 4113.485 | AY130: =+'PCR Enka'!DZ63 -> 4040.8484 | AZ130: =+'PCR Enka'!DT22 -> 4047.4116 | BA130: =+'PCR Enka'!ED63 -> 3922.2552 | BB130: =+'PCR Enka'!EF63 -> 3877.8448 | BC130: =+'PCR Enka'!EH63 -> 3786.1833 | BD130: =+'PCR Enka'!EJ63 -> 3791.4719 | BE130: =+'PCR Enka'!EI22 -> 3702.999 | BF130: =+'PCR Enka'!EN63 -> 3672.2837
B131: Precio Enka USD | C131: =+'PCR Enka'!R23 -> 1552.309 | D131: =+'PCR Enka'!S23 -> 1531.605 | E131: =+'PCR Enka'!T23 -> 1555.9978 | F131: =+'PCR Enka'!U23 -> 1798.7938 | G131: =+'PCR Enka'!V23 -> 1746.3943 | H131: =+'PCR Enka'!W23 -> 1712.67 | I131: =+'PCR Enka'!X23 -> 1898.8447 | J131: =+'PCR Enka'!Y23 -> 1949.2684 | ... AE131: =+'PCR Enka'!AT23 -> 1757.9459 | AF131: =+'PCR Enka'!CC23 -> 1827.9184 | AG131: =+'PCR Enka'!CD23 -> 1608.4359 | AH131: =+'PCR Enka'!DB23 -> 1759.8847 | AI131: =+'PCR Enka'!DC23 -> 1782.6088 | AJ131: =+'PCR Enka'!DD23 -> 1826.537 | AK131: =+'PCR Enka'!DE23 -> 1856.7622 | AL131: =+'PCR Enka'!DF23 -> 1886.8125 | AM131: =+'PCR Enka'!DG23 -> 1959.0183 | AN131: =+'PCR Enka'!DH23 -> 2025.558 | AO131: =+'PCR Enka'!DI23 -> 2054.0286 | ... BD131: =+'PCR Enka'!DX23 -> 2076.2385 | BE131: =+'PCR Enka'!EI23 -> 2113.1521 | BF131: =+'PCR Enka'!EJ23 -> 2119.1173
B132: Financiación % | C132: =+'PCR Enka'!R24 -> 0.059 | D132: =+'PCR Enka'!S24 -> 0.059 | E132: =+'PCR Enka'!T24 -> 0.059246575 | F132: =+'PCR Enka'!U24 -> 0.059246575 | G132: =+'PCR Enka'!V24 -> 0.059246575 | H132: =+'PCR Enka'!W24 -> 0.03103 | I132: =+'PCR Enka'!X24 -> 0.03103 | J132: =+'PCR Enka'!Y24 -> 0.03 | ... AE132: =+'PCR Enka'!AT24 -> 0.034967129 | AF132: =+'PCR Enka'!CC24 -> 0.034967129 | AG132: =+'PCR Enka'!CD24 -> 0.034967129 | AH132: =+'PCR Enka'!DB24 -> 0.044604805 | AI132: =+'PCR Enka'!DC24 -> 0.044604805 | AJ132: =+'PCR Enka'!DD24 -> 0.044604805 | AK132: =+'PCR Enka'!DE24 -> 0.044604805 | AL132: =+'PCR Enka'!DF24 -> 0.044604805 | AM132: =+'PCR Enka'!DG24 -> 0.044604805 | AN132: =+'PCR Enka'!DH24 -> 0.044604805 | AO132: =+'PCR Enka'!DI24 -> 0.044604805 | ... BD132: =+'PCR Enka'!DX24 -> 0.034967129 | BE132: =+'PCR Enka'!EI24 -> 0.034967129 | BF132: =+'PCR Enka'!EJ24 -> 0.034967129
B133: Financiación USD | C133: =+'PCR Enka'!R25 -> 91.586229 | D133: =+'PCR Enka'!S25 -> 90.364693 | E133: =+'PCR Enka'!T25 -> 92.18754 | F133: =+'PCR Enka'!U25 -> 106.57237 | G133: =+'PCR Enka'!V25 -> 103.46788 | H133: =+'PCR Enka'!W25 -> 53.144151 | I133: =+'PCR Enka'!X25 -> 58.921152 | J133: =+'PCR Enka'!Y25 -> 58.040245 | ... AE133: =+'PCR Enka'!AT25 -> 61.47032 | AF133: =+'PCR Enka'!CC25 -> 63.91706 | AG133: =+'PCR Enka'!CD25 -> 56.242384 | AH133: =+'PCR Enka'!DB25 -> 78.499314 | AI133: =+'PCR Enka'!DC25 -> 79.512918 | AJ133: =+'PCR Enka'!DD25 -> 81.472327 | AK133: =+'PCR Enka'!DE25 -> 82.820519 | AL133: =+'PCR Enka'!DF25 -> 84.160905 | AM133: =+'PCR Enka'!DG25 -> 87.381631 | AN133: =+'PCR Enka'!DH25 -> 90.349619 | AO133: =+'PCR Enka'!DI25 -> 91.619547 | ... BD133: =+'PCR Enka'!DX25 -> 72.600099 | BE133: =+'PCR Enka'!EI25 -> 73.89086 | BF133: =+'PCR Enka'!EJ25 -> 74.099448
B134: TOTAL | C134: =+'PCR Enka'!R26 -> 1643.8952 | D134: =+'PCR Enka'!S26 -> 1621.9697 | E134: =+'PCR Enka'!T26 -> 1648.1853 | F134: =+'PCR Enka'!U26 -> 1905.3661 | G134: =+'PCR Enka'!V26 -> 1849.8621 | H134: =+'PCR Enka'!W26 -> 1765.8142 | I134: =+'PCR Enka'!X26 -> 1957.7659 | J134: =+'PCR Enka'!Y26 -> 2007.3086 | ... AE134: =+'PCR Enka'!AT26 -> 1819.4162 | AF134: =+'PCR Enka'!CC26 -> 1891.8355 | AG134: =+'PCR Enka'!CD26 -> 1664.6783 | AH134: =+'PCR Enka'!DB26 -> 1838.384 | AI134: =+'PCR Enka'!DC26 -> 1862.1217 | AJ134: =+'PCR Enka'!DD26 -> 1908.0093 | AK134: =+'PCR Enka'!DE26 -> 1939.5828 | AL134: =+'PCR Enka'!DF26 -> 1970.9734 | AM134: =+'PCR Enka'!DG26 -> 2046.3999 | AN134: =+'PCR Enka'!DH26 -> 2115.9076 | AO134: =+'PCR Enka'!DI26 -> 2145.6482 | ... BD134: =+'PCR Enka'!DX26 -> 2148.8386 | BE134: =+'PCR Enka'!EI26 -> 2187.0429 | BF134: =+'PCR Enka'!EJ26 -> 2193.2168
B136: TRANSPORTE | C136: 85 | D136: 85 | E136: =+'PCR INTERCIA'!C7 -> 94.4 | F136: =+'PCR INTERCIA'!D7 -> 94.4 | G136: =+'PCR INTERCIA'!E7 -> 94.4 | H136: =+'PCR INTERCIA'!F7 -> 94.4 | I136: =+'PCR INTERCIA'!G7 -> 94.4 | J136: =+I136 -> 94.4 | K136: =+J136 -> 94.4 | L136: =+K136 -> 94.4 | M136: =+L136 -> 94.4 | N136: =+M136 -> 94.4 | O136: =+N136 -> 94.4 | P136: =+O136 -> 94.4 | Q136: =+P136 -> 94.4 | ... BF136: =+BE136 -> 94.4
B137: Finance Fee | C137: =+C136*C132 -> 5.015 | D137: =+D136*D132 -> 5.015 | E137: =+E136*E132 -> 5.5928767 | F137: =+F136*F132 -> 5.5928767 | G137: =+G136*G132 -> 5.5928767 | H137: =+H136*H132 -> 2.929232 | I137: =+I136*I132 -> 2.929232 | J137: =+J136*J132 -> 2.832 | ... BF137: =+BF136*BF132 -> 3.300897
B138: TOTAL | C138: =+C136+C137 -> 90.015 | D138: =+D136+D137 -> 90.015 | E138: =+E136+E137 -> 99.992877 | F138: =+F136+F137 -> 99.992877 | G138: =+G136+G137 -> 99.992877 | H138: =+H136+H137 -> 97.329232 | I138: =+I136+I137 -> 97.329232 | J138: =+J136+J137 -> 97.232 | ... BF138: =+BF136+BF137 -> 97.700897
B139: Precio Resina Enkador PCR Mes | C139: =+C138+C134 -> 1733.9102 | D139: =+D138+D134 -> 1711.9847 | E139: =+E138+E134 -> 1748.1782 | F139: =+F138+F134 -> 2005.359 | G139: =+G138+G134 -> 1949.855 | H139: =+H138+H134 -> 1863.1434 | I139: =+I138+I134 -> 2055.0951 | J139: =+J138+J134 -> 2104.5406 | ... BF139: =+BF138+BF134 -> 2290.9177
AG140: =+AF139/AG139-1 -> 0.12889238 | AH140: =+AG139/AH139-1 -> -0.090147658 | AI140: =+AH139/AI139-1 -> -0.012106543 | AJ140: =+AI139/AJ139-1 -> -0.022868116 | AK140: =+AJ139/AK139-1 -> -0.015490901 | AL140: =+AK139/AL139-1 -> -0.015167619 | AM140: =+AL139/AM139-1 -> -0.035163702 | AN140: =+AM139/AN139-1 -> -0.031387252 | ... BC140: =+BB139/BC139-1 -> -0.0074153255

Sheet PCR Enka
B6: =+'Fórmula Marzo 26'!D11 -> PRECIOS DE RESINA ABI MARZO 2026
B17: El precio de Amcor y ABI con ENKA es el mismo
V18: Es trimestre Vencido con un mes en el limbo, Noviembre deberia cambiar (Julio-Sept)
C19: 2020 | K19: 2021 | DN19: =+DN21/DM21-1 -> 0.0017317892 | DO19: =+DO21/DN21-1 -> 0.0024851432 | DP19: =+DP21/DO21-1 -> 0.0010778185 | DQ19: =+DQ21/DP21-1 -> -0.00086132644 | DR19: =+DR21/DQ21-1 -> -0.025 | DS19: =+DS21/DR21-1 -> -0.019341291 | DT19: =+DT21/DS21-1 -> -0.028513468 | DU19: =+DU21/DT21-1 -> -0.028306265 | ... DX19: =+DX21/DW21-1 -> -0.021868787 | EI19: =+EI21/DX21-1 -> -0.0059705285 | EJ19: =+EJ21/EI21-1 -> -0.0054952077
C20: Mayo | D20: Junio | E20: Julio | F20: Agosto | G20: Septiembre | H20: Octubre | I20: Noviembre | J20: Diciembre | K20: Enero | L20: Febrero | M20: Marzo | N20: Abril | O20: Mayo | P20: Junio | Q20: Julio | R20: Ago | S20: Sep | T20: Oct | U20: =+'Fórmula Marzo 26'!AV14 -> Nov-21 | V20: =+'Fórmula Marzo 26'!AW14 -> Dic-21 | W20: =+'Fórmula Marzo 26'!AX14 -> Ene-22 | X20: =+'Fórmula Marzo 26'!AY14 -> Feb-22 | Y20: =+'Fórmula Marzo 26'!AZ14 -> Mar-22 | Z20: =+'Fórmula Marzo 26'!BA14 -> Abr-22 | AA20: =+'Fórmula Marzo 26'!BB14 -> Mayo-22 | AB20: =+'Fórmula Marzo 26'!BC14 -> Junio-22 | ... AT20: =+'Fórmula Marzo 26'!BU14 -> Diciembre-23 | CC20: =+'Fórmula Marzo 26'!BV14 -> Enero-24 | CD20: =+'Fórmula Marzo 26'!BW14 -> Febrero-24 | DB20: =+'Fórmula Marzo 26'!BX14 -> Marzo-24 | DC20: =+'Fórmula Marzo 26'!BY14 -> Abril-24 | DD20: =+'Fórmula Marzo 26'!BZ14 -> Mayo-24 | DE20: =+'Fórmula Marzo 26'!CA14 -> Junio-24 | DF20: =+'Fórmula Marzo 26'!CB14 -> Julio-24 | DG20: =+'Fórmula Marzo 26'!CC14 -> Agosto-24 | DH20: =+'Fórmula Marzo 26'!CD14 -> Septiembre-24 | DI20: =+'Fórmula Marzo 26'!CE14 -> Octubre-24 | ... DX20: =+'Fórmula Marzo 26'!CT14 -> Ene-26 | EI20: =+'Fórmula Marzo 26'!CU14 -> Feb-26 | EJ20: =+'Fórmula Marzo 26'!CV14 -> Mar-26
A21: {=_xlfn.TRANSLATE(B21,,en)} -> #NAME? | B21: Precio Enka COP | C21: =4019.63*1000 -> 4019630 | D21: =+C21 -> 4019630 | E21: =+D21 -> 4019630 | F21: =+E21 -> 4019630 | G21: =+F21 -> 4019630 | H21: =+G21 -> 4019630 | I21: 4174460 | J21: 4174460 | K21: =+J21 -> 4174460 | L21: 4808073 | M21: 4808073 | N21: =+M21 -> 4808073 | O21: 5596900 | P21: =+O21 -> 5596900 | Q21: =+P21 -> 5596900 | R21: 5944440 | S21: =+R21 -> 5944440 | T21: =+S21 -> 5944440 | U21: 6787540 | V21: 6787540 | W21: 6787540 | X21: 7594650 | Y21: 7672000 | Z21: 7672001 | AA21: 7785000 | AB21: 8095000 | AC21: 8341000 | AD21: 8381000 | AE21: 8106000 | AF21: 7391000 | AG21: 6711000 | AH21: 6728000 | AI21: 6745000 | AJ21: 7442000 | AK21: 7320000 | AL21: 7071000 | AM21: 7042000 | AN21: =+' PCR Enkador'!Y129 -> 6945000 | AO21: =+' PCR Enkador'!Z129 -> 6868000 | AP21: =+' PCR Enkador'!AA129 -> 6822000 | AQ21: =+' PCR Enkador'!AB129 -> 6672000 | AR21: =+' PCR Enkador'!AC129 -> 6528000 | AS21: =+' PCR Enkador'!AD129 -> 7008000 | AT21: =+' PCR Enkador'!AE129 -> 7100000 | CC21: =+' PCR Enkador'!AF129 -> 7217000 | CD21: =+' PCR Enkador'!AG129 -> 6297000 | DB21: =+' PCR Enkador'!AH129 -> 6919000 | DC21: =+' PCR Enkador'!AI129 -> 6951000 | DD21: =+' PCR Enkador'!AJ129 -> 7065000 | DE21: =+' PCR Enkador'!AK129 -> 7184000 | DF21: =+' PCR Enkador'!AL129 -> 7628000 | DG21: =+' PCR Enkador'!AM129 -> 7905000 | DH21: =+' PCR Enkador'!AN129 -> 8235000 | DI21: =+' PCR Enkador'!AO129 -> 8591000 | ... DX21: =+' PCR Enkador'!BD129 -> 7872000 | EI21: =+' PCR Enkador'!BE129 -> 7825000 | EJ21: =+' PCR Enkador'!BF129 -> 7782000
