Workbook
Name \P: #REF!
Name _________CTM1: #REF!
Name _________CTM2: #REF!
Name _________CTM3: #REF!
Name _________CTM4: #REF!
Name ________CTM1: #REF!
Name ________CTM2: #REF!
Name ________CTM3: #REF!
Name ________CTM4: #REF!
Name _______CTM1: #REF!
Name _______CTM2: #REF!
Name _______CTM3: #REF!
Name _______CTM4: #REF!
Name ______CTM1: #REF!
Name ______CTM2: #REF!
Name ______CTM3: #REF!
Name ______CTM4: #REF!
Name _____CTM1: #REF!
Name _____CTM2: #REF!
Name _____CTM3: #REF!
Name _____CTM4: #REF!
Name _____pag2: #REF!
Name _____pag3: #REF!
Name ____CTM1: #REF!
Name ____CTM2: #REF!
Name ____CTM3: #REF!
Name ____CTM4: #REF!
Name ____pag2: #REF!
Name ____pag3: #REF!
Name ___CTM1: #REF!
Name ___CTM2: #REF!
Name ___CTM3: #REF!
Name ___CTM4: #REF!
Name ___pag2: #REF!
Name ___pag3: #REF!
Name __CTM1: #REF!
Name __CTM2: #REF!
Name __CTM3: #REF!
Name __CTM4: #REF!
Name __pag2: #REF!
Name __pag3: #REF!
Name _38LINE: #REF!
Name _4LINEADJ: #REF!
Name _94BPRICE: #REF!
Name _CTM1: #REF!
Name _CTM2: #REF!
Name _CTM3: #REF!
Name _CTM4: #REF!
Name _MAG1: '[1]Mag 1'!$E$2:$E$208
Name _MAG1: #REF!
Name _MAG2: '[1]Mag 2'!$E$82:$E$208
Name _MAG2: #REF!
Name _MAG3: '[1]Mag 3'!$E$4:$E$208
Name _MAG3: #REF!
Name _MAG4: '[1]Mag 4'!$E$4:$E$208
Name _MAG4: #REF!
Name _MOR2: #REF!
Name _MOR6: #REF!
Name _MOR8: #REF!
Name _pag2: #REF!

Sheet ICIS Price Forecast
B2: ICIS Dashboard Price Forecast
B4: Generated | C4: 17 Apr 2026 22:17:20
B5: Date Range 1 | C5: From 17 Apr 2025 To 01 Oct 2027
B6: Original Currency | C6: USD | D6: USD
B7: Original Unit | C7: tonne | D7: tonne
B8: Selected Currency | C8: USD
B9: Selected Unit | C9: tonne
B10: Price Forecast Range | C10: 18 Months
B11: Price History Range | C11: 1 Year
B13: Date Range 1 | C13: PET Bottle Grade FOB China Spot Forecast Apr-2026 Latest | D13: PET Bottle Grade FOB China Spot 4-12 Weeks Full Market Range
B14: 18-Apr-2025 | D14: 730.00
B15: 25-Apr-2025 | D15: 735.00
B16: 02-May-2025 | D16: 752.50
B17: 09-May-2025 | D17: 755.00
B18: 16-May-2025 | D18: 792.50
B19: 23-May-2025 | D19: 790.00
B20: 30-May-2025 | D20: 785.00
B21: 06-Jun-2025 | D21: 780.00
B22: 13-Jun-2025 | D22: 782.50
B23: 20-Jun-2025 | D23: 812.50
B24: 27-Jun-2025 | D24: 797.50
B25: 04-Jul-2025 | D25: 785.00
... B50: 26-Dec-2025 | D50: 770.00
B51: 09-Jan-2026 | D51: 800
B52: 16-Jan-2026 | D52: 802.5
B53: 23-Jan-2026 | D53: 825
B54: 30-Jan-2026 | D54: 845
B55: 06-Feb-2026 | D55: 830
B56: 13-Feb-2026 | D56: 837.5
B57: 27-Feb-2026 | D57: 847.5
B58: 06-Mar-2026 | D58: 920
B59: 13-Mar-2026 | D59: 1135
B60: 20-Mar-2026 | D60: 1215
B61: 27-Mar-2026 | D61: 1175
B62: 01-Apr-2026 | C62: 1147.00 | D62: =C62 -> 1147.00
B63: 03-Apr-2026 | D63: 1190
B64: 10-Apr-2026 | D64: 1182.5
B65: 17-Apr-2026 | D65: 1190
B66: 01-May-2026 | C66: 1173
B67: 01-Jun-2026 | C67: 1054
B68: 01-Jul-2026 | C68: 941
B69: 01-Aug-2026 | C69: 883
B70: 01-Sep-2026 | C70: 864
B71: 01-Oct-2026 | C71: 838
B72: 01-Nov-2026 | C72: 811
B73: 01-Dec-2026 | C73: 790
B74: 01-Jan-2027 | C74: 793
B75: 01-Feb-2027 | C75: 794
B76: 01-Mar-2027 | C76: 799
B77: 01-Apr-2027 | C77: 807
... B82: 01-Sep-2027 | C82: 816
B84: Copyright © 2026 LexisNexis Risk Solutions.
B85: ICIS is a member of the RELX.
B86: ICIS accepts no liability for commercial decisions based on the content of this report.
B87: UNAUTHORISED REPRODUCTION / TRANSMISSION PROHIBITED.
B88: Exchange rates supplied by LSEG and XE.com (http://www.XE.com).
B89: Prices that have been converted from the originally quoted unit or currency are shown to two decimal places.
B90: When exporting multiple quote series, empty cells may appear in the quote table as publishing dates may not align or may vary over holiday periods.

Sheet Resina
B3: precios actuales ep a Octubre
B4: Costo de Resina Virgen Actual | E4: =+D30 -> 1055 | F4: 0.05 | H4: Costo de Resina Virgen Actual | J4: =+D30 -> 1055
B5: Costo de Resina PCR Actual (Enkador) | E5: =+E4-F5 -> 1002.25 | F5: =+E4*F4 -> 52.75 | H5: Costo de Resina PCR Actual | J5: 0
C6: =+(C10+C11)/C8*1000 -> 1052.2306 | D6: =+(D10+D11)/D8*1000 -> 1052.2306 | E6: =+(E10+E11)/E8*1000 -> 1065.55 | I6: =+(I10+I11)/I8*1000 -> 1060.275 | J6: =+(J10+J11)/J8*1000 -> 1060.275 | L6: Nueva metodología / nuevas condiciones
B7: Preformas | H7: Manantial | I7: 500ml SG | J7: 500ml CG | N7: IHS Julio para precio septiembre | O7: IHS Agosto para precio Octubre | P7: IHS Septiembre para precio Noviembre | Q7: IHS Octubre para precio Diciembre
B8: Gramaje | C8: 15.6 | D8: 16.7 | E8: 30.6 | H8: Gramaje | I8: 15 | J8: 20.5 | L8: IHS Asia Non Coke approved | N8: 938.13 | O8: 959 | P8: 1006.25 | Q8: 993.75 | R8: Revisar el actualizado
B9: Finish | C9: Short | D9: Short | E9: Short | H9: Finish | I9: Short | J9: Short | L9: Finance | N9: 25.09 | O9: 25.09 | P9: 25.09 | Q9: 25
B10: Resina Virgen | C10: =+(C8*E4/1000)*1.01*75% -> 12.466935 | D10: =+(D8*$E$4/1000)*1.01*75% -> 13.346014 | E10: =+(E8*E4/1000)*1.01 -> 32.60583 | H10: Resina Virgen | I10: =+(I8*J4/1000)*1.005 -> 15.904125 | J10: =+(J8*J4/1000)*1.005 -> 21.735637 | L10: Freight China-Gye | N10: 65 | O10: 65 | P10: 65 | Q10: 65 | R10: costo x TN | S10: Análisis
B11: Resina PCR | C11: =+(C8*$E$5/1000)*1.01*25% -> 3.9478628 | D11: =+(D8*$E$5/1000)*1.01*25% -> 4.2262377 | E11: 0 | H11: Resina PCR | I11: 0 | J11: 0 | N11: =SUM(N8:N10) -> 1028.22 | O11: =SUM(O8:O10) -> 1049.09 | P11: =SUM(P8:P10) -> 1096.34 | Q11: =SUM(Q8:Q10) -> 1083.75 | R11: FOB
B12: Nueva Conversion | C12: =C39 -> 13.806909 | D12: =D39 -> 13.806909 | E12: =E39 -> 16.175542 | H12: Conversión | I12: =I39 -> 28.109813 | J12: =J39 -> 28.109813 | L12: Landed factor 4% | N12: =+N11*4% -> 41.1288 | O12: =+O11*4% -> 41.9636 | P12: =+P11*4% -> 43.8536 | Q12: =+Q11*4% -> 43.35
B13: Recargo por Penalidad y energ | C13: 0 | D13: 0 | E13: 0 | H13: Recargo por Penalidad e incr | I13: 0 | J13: 0 | L13: Total resin price | N13: =+N12+N11 -> 1069.3488 | O13: =+O12+O11 -> 1091.0536 | P13: =+P12+P11 -> 1140.1936 | Q13: =+Q12+Q11 -> 1127.1
B14: Pigmento | C14: 1.638 | D14: 1.7535 | E14: 2.97 | H14: Pigmento | I14: 1.4 | J14: 2 | L14: Resin PCR % | N14: =+N13*(1-5%) -> 1015.8814 | O14: =+O13*(1-5%) -> 1036.5009 | P14: =+P13*(1-5%) -> 1083.1839 | Q14: =+Q13*(1-5%) -> 1070.745 | R14: Validar si nos está costando el 5% por debajo
B15: Empaque | C15: 0.20356 | D15: 0.20356 | E15: 0.284984 | H15: Empaque | I15: 1.27 | J15: 1.27225 | L15: Precio ponderado bajo formuala | N15: =+N13*75%+N14*25% -> 1055.9819 | O15: =+O13*75%+O14*25% -> 1077.4154 | P15: =+P13*75%+P14*25% -> 1125.9412 | Q15: =+Q13*75%+Q14*25% -> 1113.0113
B16: Flete | C16: 0.15 | D16: 0.15 | E16: 0.213738 | H16: Flete | I16: 8.34 | J16: 8.335782 | L16: Scrap 1% | N16: =+N15*1% -> 10.559819 | O16: =+O15*1% -> 10.774154 | P16: =+P15*1% -> 11.259412 | Q16: =+Q15*1% -> 11.130113
B17: Total | C17: =SUM(C10:C16) -> 32.213266 | D17: =SUM(D10:D16) -> 33.48622 | E17: =SUM(E10:E16) -> 52.250094 | H17: Total | I17: =SUM(I10:I16) -> 55.023938 | J17: =SUM(J10:J16) -> 61.453483 | L17: Precio pnderado con scrap | N17: =+N16+N15 -> 1066.5418 | O17: =+O16+O15 -> 1088.1896 | P17: =+P16+P15 -> 1137.2006 | Q17: =+Q16+Q15 -> 1124.1414
L18: Precio facturado Sep-Oct-Nov | N18: =+D6 -> 1052.2306 | O18: =+N18 -> 1052.2306 | P18: =+O18 -> 1052.2306 | Q18: =+P18 -> 1052.2306
B20: Toneladas | C20: Precio | D20: Total | N20: =+N17-N18 -> 14.311134 | O20: =+O17-O18 -> 35.958959 | P20: =+P17-P18 -> 84.969967 | Q20: =+Q17-Q18 -> 71.910738
B21: 92 | C21: =D21/B21 -> 995 | D21: 91540
B22: 69 | C22: =D22/B22 -> 995 | D22: 68655
B23: 110 | C23: =D23/B23 -> 995 | D23: 109450
B24: 44 | C24: =D24/B24 -> 995 | D24: 43780
B25: =SUM(B21:B24) -> 315 | C25: =SUM(C21:C24) -> 3980 | D25: =SUM(D21:D24) -> 313425
B28: Promedio Ponderado | D28: =+D25/B25 -> 995
B29: Gastos + Transporte + Almacenaje | D29: 60 | E29: Fijo | F29: =+D29/D30 -> 0.056872038
B30: Total | D30: =+D29+D28 -> 1055
B33: Preformas | H33: Manantial | I33: 500ml SG | J33: 500ml CG | R33: Manantial | S33: 500ml SG | T33: 500ml CG
B34: Gramaje | C34: 15.6 | D34: 16.7 | E34: 30.6 | H34: Gramaje | I34: 15 | J34: 20.5 | R34: Gramaje | S34: 15 | T34: 20.5
B35: Conversion Base | C35: 13.64 | D35: 13.64 | E35: 15.98 | H35: Conversión | I35: 27.77 | J35: 27.77 | R35: Conversión | S35: 27.77 | T35: 27.77
B36: % de Energia en MOR | C36: 0.23 | D36: 0.23 | E36: 0.23 | I36: 0.23 | J36: 0.23 | S36: 0.23 | T36: 0.23
B37: % Incremento Energia | C37: =0.097/0.0921-1 -> 0.05320304 | D37: =0.097/0.0921-1 -> 0.05320304 | E37: =0.097/0.0921-1 -> 0.05320304 | I37: =0.097/0.0921-1 -> 0.05320304 | J37: =0.097/0.0921-1 -> 0.05320304 | S37: =0.097/0.0921-1 -> 0.05320304 | T37: =0.097/0.0921-1 -> 0.05320304
B38: Incremento de energia | C38: =C35*C36*C37 -> 0.16690858 | D38: =D35*D36*D37 -> 0.16690858 | E38: =E35*E36*E37 -> 0.19554245 | I38: =I35*I36*I37 -> 0.33981314 | J38: =J35*J36*J37 -> 0.33981314 | S38: =S35*S36*S37 -> 0.33981314 | T38: =T35*T36*T37 -> 0.33981314
B39: Nueva Conversion | C39: =C35+C38 -> 13.806909 | D39: =D35+D38 -> 13.806909 | E39: =E35+E38 -> 16.175542 | I39: =I35+I38 -> 28.109813 | J39: =J35+J38 -> 28.109813 | S39: =S35+S38 -> 28.109813 | T39: =T35+T38 -> 28.109813
B52: Fórmula | J52: Factor mundial del precio de la resina

Sheet Sep17
B3: Costo de Resina Virgen Actual | E3: 1069.3488 | I3: Costo de Resina Virgen Actual | K3: 1069.3488
B4: Costo de Resina PCR Actual (Enkador) | E4: 1015.8814 | I4: Costo de Resina PCR Actual | K4: 0
C5: =+(C9+C10)/C7*1000 -> 1066.5418 | D5: =+(D9+D10)/D7*1000 -> 1066.5418 | F5: =+(F9+F10)/F7*1000 -> 1080.0423 | J5: =+(J9+J10)/J7*1000 -> 1074.6955 | K5: =+(K9+K10)/K7*1000 -> 1074.6955 | M5: Nueva metodología / nuevas condiciones
B6: Preformas | I6: Manantial | J6: 500ml SG | K6: 500ml CG | O6: IHS Julio para precio Septiembre | P6: IHS Agosto para precio Octubre | Q6: IHS Septiembre para precio Noviembre | R6: IHS Octubre para precio Diciembre
B7: Gramaje | C7: 15.6 | D7: 16.7 | E7: 20.5 | F7: 30.6 | G7: 30.6 | I7: Gramaje | J7: 15 | K7: 20.5 | M7: IHS Asia Non Coke approved | O7: 938.13 | P7: 959 | Q7: 1006.25 | R7: 993.75 | S7: Revisar el actualizado
B8: Finish | C8: Short | D8: Short | E8: Short | F8: Short | G8: Short | I8: Finish | J8: Short | K8: Short | M8: Finance | O8: 25.09 | P8: 25.09 | Q8: 25.09 | R8: 25
B9: Resina Virgen | C9: =+(C7*E3/1000)*1.01*75% -> 12.636495 | D9: =+(D7*$E$3/1000)*1.01*75% -> 13.52753 | E9: =+(E7*$E$3/1000)*1.01*75% -> 16.60565 | F9: =+(F7*E3/1000)*1.01 -> 33.049294 | G9: =+(G7*$E$3/1000)*1.01*75% -> 24.786971 | I9: Resina Virgen | J9: =+(J7*K3/1000)*1.005 -> 16.120433 | K9: =+(K7*K3/1000)*1.005 -> 22.031259 | M9: Freight China-Gye | O9: 65 | P9: 65 | Q9: 65 | R9: 65 | S9: costo x TN | T9: Análisis
B10: Resina PCR | C10: =+(C7*$E$4/1000)*1.01*25% -> 4.0015567 | D10: =+(D7*$E$4/1000)*1.01*25% -> 4.2837177 | E10: =+(E7*$E$4/1000)*1.01*25% -> 5.2584559 | F10: 0 | G10: =+(G7*$E$4/1000)*1.01*25% -> 7.8492073 | I10: Resina PCR | J10: 0 | K10: 0 | O10: =SUM(O7:O9) -> 1028.22 | P10: =SUM(P7:P9) -> 1049.09 | Q10: =SUM(Q7:Q9) -> 1096.34 | R10: =SUM(R7:R9) -> 1083.75 | S10: FOB
B11: Nueva Conversion | C11: 8.2 | D11: 8.2 | E11: 8.2 | F11: 11.15 | G11: 11.15 | I11: Conversión | J11: 27.2 | K11: 27.2 | M11: Landed factor 4% | O11: =+O10*4% -> 41.1288 | P11: =+P10*4% -> 41.9636 | Q11: =+Q10*4% -> 43.8536 | R11: =+R10*4% -> 43.35
B12: Recargo por Penalidad y energ | C12: 0 | D12: 0 | E12: 0 | F12: 0 | G12: 0 | I12: Recargo por Penalidad e incr | J12: 0 | K12: 0 | M12: Total resin price | O12: =+O11+O10 -> 1069.3488 | P12: =+P11+P10 -> 1091.0536 | Q12: =+Q11+Q10 -> 1140.1936 | R12: =+R11+R10 -> 1127.1
B13: Pigmento | C13: 1.3 | D13: 1.3 | E13: 1.3 | F13: 2.38 | G13: 2.38 | I13: Pigmento | J13: 0.81 | K13: 1.99 | M13: Resin PCR % | O13: =+O12*(1-5%) -> 1015.8814 | P13: =+P12*(1-5%) -> 1036.5009 | Q13: =+Q12*(1-5%) -> 1083.1839 | R13: =+R12*(1-5%) -> 1070.745 | S13: Validar si nos está costando el 5% por debajo
B14: Empaque | C14: 0.19 | D14: 0.19 | E14: 0.19 | F14: 0.33 | G14: 0.33 | I14: Empaque | J14: 2.71 | K14: 2.71 | M14: Precio ponderado bajo formuala | O14: =+O12*75%+O13*25% -> 1055.9819 | P14: =+P12*75%+P13*25% -> 1077.4154 | Q14: =+Q12*75%+Q13*25% -> 1125.9412 | R14: =+R12*75%+R13*25% -> 1113.0113
B15: Flete | C15: 0.16 | D15: 0.16 | E15: 0.16 | F15: 0.28 | G15: 0.28 | I15: Flete | J15: 7.77 | K15: 7.77 | M15: Scrap 1% | O15: =+O14*1% -> 10.559819 | P15: =+P14*1% -> 10.774154 | Q15: =+Q14*1% -> 11.259412 | R15: =+R14*1% -> 11.130113
B16: Total | C16: =SUM(C9:C15) -> 26.488051 | D16: =SUM(D9:D15) -> 27.661247 | E16: =SUM(E9:E15) -> 31.714106 | F16: =SUM(F9:F15) -> 47.189294 | G16: =SUM(G9:G15) -> 46.776178 | I16: Total | J16: =SUM(J9:J15) -> 54.610433 | K16: =SUM(K9:K15) -> 61.701259 | M16: Precio pnderado con scrap | O16: =+O15+O14 -> 1066.5418 | P16: =+P15+P14 -> 1088.1896 | Q16: =+Q15+Q14 -> 1137.2006 | R16: =+R15+R14 -> 1124.1414
M17: Precio facturado Sep-Oct-Nov | O17: =+D5 -> 1066.5418 | P17: =+O17 -> 1066.5418 | Q17: =+P17 -> 1066.5418 | R17: =+Q17 -> 1066.5418
B32: Fórmula | K32: Factor mundial del precio de la resina

Sheet Oct17
B3: Costo de Resina Virgen Actual | E3: 1091.0536 | I3: Costo de Resina Virgen Actual | K3: 1091.0536
B4: Costo de Resina PCR Actual (Enkador) | E4: 1036.5009 | I4: Costo de Resina PCR Actual | K4: 0
C5: =+(C9+C10)/C7*1000 -> 1088.446 | D5: =+(D9+D10)/D7*1000 -> 1088.1896 | F5: =+(F9+F10)/F7*1000 -> 1101.9641 | J5: =+(J9+J10)/J7*1000 -> 1096.3755 | K5: =+(K9+K10)/K7*1000 -> 1096.5089 | M5: Nueva metodología / nuevas condiciones
B6: Preformas | I6: Manantial | J6: 500ml SG | K6: 500ml CG | O6: IHS Julio para precio septiembre | P6: IHS Agosto para precio Octubre | Q6: IHS Septiembre para precio Noviembre | R6: IHS Octubre para precio Diciembre
B7: Gramaje | C7: 15.6 | D7: 16.7 | E7: 20.5 | F7: 30.6 | G7: 30.6 | I7: Gramaje | J7: 15 | K7: 20.5 | M7: IHS Asia Non Coke approved | O7: 938.13 | P7: 959 | Q7: 1006.25 | R7: 993.75 | S7: Revisar el actualizado
B8: Finish | C8: Short | D8: Short | E8: Short | F8: Short | G8: Short | I8: Finish | J8: Short | K8: Short | M8: Finance | O8: 25.09 | P8: 25.09 | Q8: 25.09 | R8: 25
B9: Resina Virgen | C9: =+(C7*E3/1000)*1.01*75% -> 12.89298 | D9: =+(D7*$E$3/1000)*1.01*75% -> 13.802101 | E9: =+(E7*$E$3/1000)*1.01*75% -> 16.942699 | F9: =+(F7*E3/1000)*1.01 -> 33.720103 | G9: =+(G7*$E$3/1000)*1.01*75% -> 25.290077 | I9: Resina Virgen | J9: =+(J7*K3/1000)*1.005-0.002 -> 16.445633 | K9: =+(K7*K3/1000)*1.005 -> 22.478432 | M9: Freight China-Gye | O9: 65 | P9: 65 | Q9: 65 | R9: 65 | S9: costo x TN | T9: Análisis
B10: Resina PCR | C10: =+(C7*$E$4/1000)*1.01*25%+0.004 -> 4.0867771 | D10: =+(D7*$E$4/1000)*1.01*25% -> 4.3706653 | E10: =+(E7*$E$4/1000)*1.01*25% -> 5.3651879 | F10: 0 | G10: =+(G7*$E$4/1000)*1.01*25% -> 8.0085244 | I10: Resina PCR | J10: 0 | K10: 0 | O10: =SUM(O7:O9) -> 1028.22 | P10: =SUM(P7:P9) -> 1049.09 | Q10: =SUM(Q7:Q9) -> 1096.34 | R10: =SUM(R7:R9) -> 1083.75 | S10: FOB
B11: Nueva Conversion | C11: 8.2 | D11: 8.2 | E11: 8.2 | F11: 11.15 | G11: 11.15 | I11: Conversión | J11: 27.2 | K11: 27.2 | M11: Landed factor 4% | O11: =+O10*4% -> 41.1288 | P11: =+P10*4% -> 41.9636 | Q11: =+Q10*4% -> 43.8536 | R11: =+R10*4% -> 43.35
B12: Recargo por Penalidad y energ | C12: 0 | D12: 0 | E12: 0 | F12: 0 | G12: 0 | I12: Recargo por Penalidad e incr | J12: 0 | K12: 0 | M12: Total resin price | O12: =+O11+O10 -> 1069.3488 | P12: =+P11+P10 -> 1091.0536 | Q12: =+Q11+Q10 -> 1140.1936 | R12: =+R11+R10 -> 1127.1
B13: Pigmento | C13: 1.3 | D13: 1.3 | E13: 1.3 | F13: 2.38 | G13: 2.38 | I13: Pigmento | J13: 0.81 | K13: 1.99 | M13: Resin PCR % | O13: =+O12*(1-5%) -> 1015.8814 | P13: =+P12*(1-5%) -> 1036.5009 | Q13: =+Q12*(1-5%) -> 1083.1839 | R13: =+R12*(1-5%) -> 1070.745 | S13: Validar si nos está costando el 5% por debajo
B14: Empaque | C14: 0.19 | D14: 0.19 | E14: 0.19 | F14: 0.33 | G14: 0.33 | I14: Empaque | J14: 2.71 | K14: 2.71 | M14: Precio ponderado bajo formuala | O14: =+O12*75%+O13*25% -> 1055.9819 | P14: =+P12*75%+P13*25% -> 1077.4154 | Q14: =+Q12*75%+Q13*25% -> 1125.9412 | R14: =+R12*75%+R13*25% -> 1113.0113
B15: Flete | C15: 0.16 | D15: 0.16 | E15: 0.16 | F15: 0.28 | G15: 0.28 | I15: Flete | J15: 7.77 | K15: 7.77 | M15: Scrap 1% | O15: =+O14*1% -> 10.559819 | P15: =+P14*1% -> 10.774154 | Q15: =+Q14*1% -> 11.259412 | R15: =+R14*1% -> 11.130113
B16: Total | C16: =SUM(C9:C15) -> 26.829758 | D16: =SUM(D9:D15) -> 28.022766 | E16: =SUM(E9:E15) -> 32.157886 | F16: =SUM(F9:F15) -> 47.860103 | G16: =SUM(G9:G15) -> 47.438601 | I16: Total | J16: =SUM(J9:J15) -> 54.935633 | K16: =SUM(K9:K15) -> 62.148432 | M16: Precio pnderado con scrap | O16: =+O15+O14 -> 1066.5418 | P16: =+P15+P14 -> 1088.1896 | Q16: =+Q15+Q14 -> 1137.2006 | R16: =+R15+R14 -> 1124.1414
M17: Precio facturado Sep-Oct-Nov | O17: =+D5 -> 1088.1896 | P17: =+O17 -> 1088.1896 | Q17: =+P17 -> 1088.1896 | R17: =+Q17 -> 1088.1896
B30: Fórmula | K30: Factor mundial del precio de la resina

Sheet Nov17
B3: Costo de Resina Virgen Actual | E3: 1140.1936 | J3: Costo de Resina Virgen Actual | L3: 1140.1936
B4: Costo de Resina PCR Actual (Enkador) | E4: 1083.1839 | J4: Costo de Resina PCR Actual | L4: 0
C5: =+(C9+C10)/C7*1000 -> 1137.2006 | D5: =+(D9+D10)/D7*1000 -> 1137.2006 | F5: =+(F9+F10)/F7*1000 -> 1151.5955 | K5: =+(K9+K10)/K7*1000 -> 1145.6946 | L5: =+(L9+L10)/L7*1000 -> 1145.8946 | N5: Nueva metodología / nuevas condiciones
B6: Preformas | J6: Manantial | K6: 500ml SG | L6: 500ml CG | P6: IHS Julio para precio Septiembre | Q6: IHS Agosto para precio Octubre | R6: IHS Septiembre para precio Noviembre | S6: IHS Octubre para precio Diciembre
B7: Gramaje | C7: 15.6 | D7: 16.7 | E7: 20.5 | F7: 30.6 | G7: 30.6 | H7: 38.6 | J7: Gramaje | K7: 15 | L7: 20.5 | N7: IHS Asia Non Coke approved | P7: 938.13 | Q7: 959 | R7: 1006.25 | S7: 993.75 | T7: Revisar el actualizado
B8: Finish | C8: Short | D8: Short | E8: Short | F8: Short | G8: Short | H8: Short | J8: Finish | K8: Short | L8: Short | N8: Finance | P8: 25.09 | Q8: 25.09 | R8: 25.09 | S8: 25
B9: Resina Virgen | C9: =+(C7*E3/1000)*1.01*75% -> 13.473668 | D9: =+(D7*$E$3/1000)*1.01*75% -> 14.423734 | E9: =+(E7*$E$3/1000)*1.01*75% -> 17.705781 | F9: =+(F7*E3/1000)*1.01 -> 35.238823 | G9: =+(G7*$E$3/1000)*1.01*75% -> 26.429118 | H9: =+(H7*$E$3/1000)*1.01*75% -> 33.338691 | J9: Resina Virgen | K9: =+(K7*L3/1000)*1.005-0.003 -> 17.185419 | L9: =+(L7*L3/1000)*1.005 -> 23.490839 | N9: Freight China-Gye | P9: 65 | Q9: 65 | R9: 65 | S9: 65 | T9: costo x TN | U9: Análisis
B10: Resina PCR | C10: =+(C7*$E$4/1000)*1.01*25% -> 4.2666615 | D10: =+(D7*$E$4/1000)*1.01*25% -> 4.5675158 | E10: =+(E7*$E$4/1000)*1.01*25% -> 5.6068308 | F10: 0 | G10: =+(G7*$E$4/1000)*1.01*25% -> 8.3692206 | H10: =+(H7*$E$4/1000)*1.01*25% -> 10.557252 | J10: Resina PCR | K10: 0 | L10: 0 | P10: =SUM(P7:P9) -> 1028.22 | Q10: =SUM(Q7:Q9) -> 1049.09 | R10: =SUM(R7:R9) -> 1096.34 | S10: =SUM(S7:S9) -> 1083.75 | T10: FOB
B11: Nueva Conversion | C11: 8.2 | D11: 8.2 | E11: 8.2 | F11: 11.15 | G11: 11.15 | H11: 11.15 | J11: Conversión | K11: 27.2 | L11: 27.2 | N11: Landed factor 4% | P11: =+P10*4% -> 41.1288 | Q11: =+Q10*4% -> 41.9636 | R11: =+R10*4% -> 43.8536 | S11: =+S10*4% -> 43.35
B12: Recargo por Penalidad y energ | C12: 0 | D12: 0 | E12: 0 | F12: 0 | G12: 0 | H12: 0 | J12: Recargo por Penalidad e incr | K12: 0 | L12: 0 | N12: Total resin price | P12: =+P11+P10 -> 1069.3488 | Q12: =+Q11+Q10 -> 1091.0536 | R12: =+R11+R10 -> 1140.1936 | S12: =+S11+S10 -> 1127.1
B13: Pigmento | C13: 1.3 | D13: 1.3 | E13: 1.3 | F13: 2.38 | G13: 2.38 | H13: 2.38 | J13: Pigmento | K13: 0.81 | L13: 1.99 | N13: Resin PCR % | P13: =+P12*(1-5%) -> 1015.8814 | Q13: =+Q12*(1-5%) -> 1036.5009 | R13: =+R12*(1-5%) -> 1083.1839 | S13: =+S12*(1-5%) -> 1070.745 | T13: Validar si nos está costando el 5% por debajo
B14: Empaque | C14: 0.19 | D14: 0.19 | E14: 0.19 | F14: 0.33 | G14: 0.33 | H14: 0.33 | J14: Empaque | K14: 2.71 | L14: 2.71 | N14: Precio ponderado bajo formuala | P14: =+P12*75%+P13*25% -> 1055.9819 | Q14: =+Q12*75%+Q13*25% -> 1077.4154 | R14: =+R12*75%+R13*25% -> 1125.9412 | S14: =+S12*75%+S13*25% -> 1113.0113
B15: Flete | C15: 0.16 | D15: 0.16 | E15: 0.16 | F15: 0.28 | G15: 0.28 | H15: 0.28 | J15: Flete | K15: 7.77 | L15: 7.77 | N15: Scrap 1% | P15: =+P14*1% -> 10.559819 | Q15: =+Q14*1% -> 10.774154 | R15: =+R14*1% -> 11.259412 | S15: =+S14*1% -> 11.130113
B16: Total | C16: =SUM(C9:C15) -> 27.590329 | D16: =SUM(D9:D15) -> 28.84125 | E16: =SUM(E9:E15) -> 33.162612 | F16: =SUM(F9:F15) -> 49.378823 | G16: =SUM(G9:G15) -> 48.938338 | H16: =SUM(H9:H15) -> 58.035943 | J16: Total | K16: =SUM(K9:K15) -> 55.675419 | L16: =SUM(L9:L15) -> 63.160839 | N16: Precio pnderado con scrap | P16: =+P15+P14 -> 1066.5418 | Q16: =+Q15+Q14 -> 1088.1896 | R16: =+R15+R14 -> 1137.2006 | S16: =+S15+S14 -> 1124.1414
N17: Precio facturado Sep-Oct-Nov | P17: =+D5 -> 1137.2006 | Q17: =+P17 -> 1137.2006 | R17: =+Q17 -> 1137.2006 | S17: =+R17 -> 1137.2006
B30: Fórmula | L30: Factor mundial del precio de la resina

Sheet Dic17
B3: Costo de Resina Virgen Actual | E3: =+S12 -> 1127.1 | J3: Costo de Resina Virgen Actual | L3: =+E3 -> 1127.1
B4: Costo de Resina PCR Actual (Enkador) | E4: =+S13 -> 1070.745 | J4: Costo de Resina PCR Actual | L4: 0
C5: =+(C9+C10)/C7*1000 -> 1124.1414 | D5: =+(D9+D10)/D7*1000 -> 1124.1414 | F5: =+(F9+F10)/F7*1000 -> 1138.371 | K5: =+(K9+K10)/K7*1000 -> 1132.7355 | L5: =+(L9+L10)/L7*1000 -> 1132.7355 | N5: Nueva metodología / nuevas condiciones
B6: Preformas | J6: Manantial | K6: 500ml SG | L6: 500ml CG | P6: IHS julio para precio septiembre | Q6: IHS agosto para precio octubre | R6: IHS septiembre para precio noviembre | S6: IHS Octubre para precio Diciembre | T6: IHS Noviembre para precio Enero | U6: IHS Diciembre para precio Febrero | V6: IHS Enero para precio Marzo
B7: Gramaje | C7: 15.6 | D7: 16.7 | E7: 20.5 | F7: 30.6 | G7: 30.6 | H7: 38.6 | J7: Gramaje | K7: 15 | L7: 20.5 | N7: IHS Asia Non Coke approved | P7: 938.13 | Q7: 959 | R7: 1006.25 | S7: 993.75 | T7: 1015.5 | U7: 1045.6 | V7: 1050 | W7: Revisar el actualizado
B8: Finish | C8: Short | D8: Short | E8: Short | F8: Short | G8: Short | H8: Short | J8: Finish | K8: Short | L8: Short | N8: Finance | P8: 25.09 | Q8: 25.09 | R8: 25.09 | S8: 25 | T8: 25 | U8: 25 | V8: 25
B9: Resina Virgen | C9: =+(C7*E3/1000)*1.01*75% -> 13.318941 | D9: =+(D7*$E$3/1000)*1.01*75% -> 14.258097 | E9: =+(E7*$E$3/1000)*1.01*75% -> 17.502454 | F9: =+(F7*E3/1000)*1.01 -> 34.834153 | G9: =+(G7*$E$3/1000)*1.01*75% -> 26.125614 | H9: =+(H7*$E$3/1000)*1.01*75% -> 32.95584 | J9: Resina Virgen | K9: =+(K7*L3/1000)*1.005 -> 16.991032 | L9: =+(L7*L3/1000)*1.005 -> 23.221078 | N9: Freight China-Gye | P9: 65 | Q9: 65 | R9: 65 | S9: 65 | T9: 65 | U9: 65 | V9: 65 | W9: costo x TN | X9: Análisis
B10: Resina PCR | C10: =+(C7*$E$4/1000)*1.01*25% -> 4.2176646 | D10: =+(D7*$E$4/1000)*1.01*25% -> 4.515064 | E10: =+(E7*$E$4/1000)*1.01*25% -> 5.5424438 | F10: 0 | G10: =+(G7*$E$4/1000)*1.01*25% -> 8.2731112 | H10: =+(H7*$E$4/1000)*1.01*25% -> 10.436016 | J10: Resina PCR | K10: 0 | L10: 0 | P10: =SUM(P7:P9) -> 1028.22 | Q10: =SUM(Q7:Q9) -> 1049.09 | R10: =SUM(R7:R9) -> 1096.34 | S10: =SUM(S7:S9) -> 1083.75 | T10: =SUM(T7:T9) -> 1105.5 | U10: =SUM(U7:U9) -> 1135.6 | V10: =SUM(V7:V9) -> 1140 | W10: FOB
B11: Nueva Conversion | C11: 8.2 | D11: 8.2 | E11: 8.2 | F11: 11.15 | G11: 11.15 | H11: 11.15 | J11: Conversión | K11: 27.2 | L11: 27.2 | N11: Landed factor 4% | P11: =+P10*4% -> 41.1288 | Q11: =+Q10*4% -> 41.9636 | R11: =+R10*4% -> 43.8536 | S11: =+S10*4% -> 43.35 | T11: =+T10*4% -> 44.22 | U11: =+U10*4% -> 45.424 | V11: =+V10*4% -> 45.6
B12: Recargo por Penalidad y energ | C12: 0 | D12: 0 | E12: 0 | F12: 0 | G12: 0 | H12: 0 | J12: Recargo por Penalidad e incr | K12: 0 | L12: 0 | N12: Total resin price | P12: =+P11+P10 -> 1069.3488 | Q12: =+Q11+Q10 -> 1091.0536 | R12: =+R11+R10 -> 1140.1936 | S12: =+S11+S10 -> 1127.1 | T12: =+T11+T10 -> 1149.72 | U12: =+U11+U10 -> 1181.024 | V12: =+V11+V10 -> 1185.6
B13: Pigmento | C13: 1.3 | D13: 1.3 | E13: 1.3 | F13: 2.38 | G13: 2.38 | H13: 2.38 | J13: Pigmento | K13: 0.81 | L13: 1.99 | N13: Resin PCR % | P13: =+P12*(1-5%) -> 1015.8814 | Q13: =+Q12*(1-5%) -> 1036.5009 | R13: =+R12*(1-5%) -> 1083.1839 | S13: =+S12*(1-5%) -> 1070.745 | T13: =+T12*(1-5%) -> 1092.234 | U13: =+U12*(1-5%) -> 1121.9728 | V13: =+V12*(1-5%) -> 1126.32 | W13: Validar si nos está costando el 5% por debajo
B14: Empaque | C14: 0.19 | D14: 0.19 | E14: 0.19 | F14: 0.33 | G14: 0.33 | H14: 0.33 | J14: Empaque | K14: 2.71 | L14: 2.71 | N14: Precio ponderado bajo formuala | P14: =+P12*75%+P13*25% -> 1055.9819 | Q14: =+Q12*75%+Q13*25% -> 1077.4154 | R14: =+R12*75%+R13*25% -> 1125.9412 | S14: =+S12*75%+S13*25% -> 1113.0113 | T14: =+T12*75%+T13*25% -> 1135.3485 | U14: =+U12*75%+U13*25% -> 1166.2612 | V14: =+V12*75%+V13*25% -> 1170.78
B15: Flete | C15: 0.16 | D15: 0.16 | E15: 0.16 | F15: 0.28 | G15: 0.28 | H15: 0.28 | J15: Flete | K15: 7.77 | L15: 7.77 | N15: Scrap 1% | P15: =+P14*1% -> 10.559819 | Q15: =+Q14*1% -> 10.774154 | R15: =+R14*1% -> 11.259412 | S15: =+S14*1% -> 11.130113 | T15: =+T14*1% -> 11.353485 | U15: =+U14*1% -> 11.662612 | V15: =+V14*1% -> 11.7078
B16: Total | C16: =SUM(C9:C15) -> 27.386605 | D16: =SUM(D9:D15) -> 28.623161 | E16: =SUM(E9:E15) -> 32.894898 | F16: =SUM(F9:F15) -> 48.974153 | G16: =SUM(G9:G15) -> 48.538726 | H16: =SUM(H9:H15) -> 57.531857 | J16: Total | K16: =SUM(K9:K15) -> 55.481032 | L16: =SUM(L9:L15) -> 62.891078 | N16: Precio pnderado con scrap | P16: =+P15+P14 -> 1066.5418 | Q16: =+Q15+Q14 -> 1088.1896 | R16: =+R15+R14 -> 1137.2006 | S16: =+S15+S14 -> 1124.1414 | T16: =+T15+T14 -> 1146.702 | U16: =+U15+U14 -> 1177.9238 | V16: =+V15+V14 -> 1182.4878
N17: Precio facturado Sep-Oct-Nov | P17: =+D5 -> 1124.1414 | Q17: =+P17 -> 1124.1414 | R17: =+Q17 -> 1124.1414 | S17: =+R17 -> 1124.1414 | T17: =+S17 -> 1124.1414 | U17: =+T17 -> 1124.1414 | V17: =+U17 -> 1124.1414
B32: Fórmula | L32: Factor mundial del precio de la resina

Sheet Ene18
B3: Costo de Resina Virgen Actual | E3: =+U12 -> 1149.72 | I3: 0.05 | K3: Costo de Resina Virgen Actual | M3: =+E3 -> 1149.72
B4: Costo de Resina PCR Actual (Enkador) | E4: =+U13 -> 1092.234 | I4: =+E3*I3 -> 57.486 | K4: Costo de Resina PCR Actual | M4: 0
C5: =+(C9+C10)/C7*1000 -> 1146.702 | D5: =+(D9+D10)/D7*1000 -> 1146.702 | F5: =+(F9+F10)/F7*1000 -> 1161.2172 | L5: =+(L9+L10)/L7*1000 -> 1155.4686 | M5: =+(M9+M10)/M7*1000 -> 1155.4686 | O5: Nueva metodología / nuevas condiciones
B6: Preformas | K6: Manantial | L6: 500ml SG | M6: 500ml CG | Q6: IHS julio para precio septiembre | R6: IHS agosto para precio octubre | S6: IHS septiembre para precio noviembre | T6: IHS Octubre para precio Diciembre | U6: IHS Noviembre para precio Enero | V6: IHS Diciembre para precio Febrero | W6: IHS Enero para precio Marzo
B7: Gramaje | C7: 15.6 | D7: 16.7 | E7: 20.5 | F7: 30.6 | G7: 30.6 | H7: 38.6 | K7: Gramaje | L7: 15 | M7: 20.5 | O7: IHS Asia Non Coke approved | Q7: 938.13 | R7: 959 | S7: 1006.25 | T7: 993.75 | U7: 1015.5 | V7: 1045.6 | W7: 1050 | X7: Revisar el actualizado
B8: Finish | C8: Short | D8: Short | E8: Short | F8: Short | G8: Short | H8: Short | K8: Finish | L8: Short | M8: Short | O8: Finance | Q8: 25.09 | R8: 25.09 | S8: 25.09 | T8: 25 | U8: 25 | V8: 25 | W8: 25
B9: Resina Virgen | C9: =+(C7*E3/1000)*1.01*75% -> 13.586241 | D9: =+(D7*$E$3/1000)*1.01*75% -> 14.544245 | E9: =+(E7*$E$3/1000)*1.01*75% -> 17.853714 | F9: =+(F7*E3/1000)*1.01 -> 35.533246 | G9: =+(G7*$E$3/1000)*1.01*75% -> 26.649935 | H9: =+(H7*$E$3/1000)*1.01*75% -> 33.617238 | K9: Resina Virgen | L9: =+(L7*M3/1000)*1.005 -> 17.332029 | M9: =+(M7*M3/1000)*1.005 -> 23.687106 | O9: Freight China-Gye | Q9: 65 | R9: 65 | S9: 65 | T9: 65 | U9: 65 | V9: 65 | W9: 65 | X9: costo x TN | Y9: Análisis
B10: Resina PCR | C10: =+(C7*$E$4/1000)*1.01*25% -> 4.3023097 | D10: =+(D7*$E$4/1000)*1.01*25% -> 4.6056777 | E10: =+(E7*$E$4/1000)*1.01*25% -> 5.6536762 | F10: 0 | G10: =+(G7*$E$4/1000)*1.01*25% -> 8.439146 | H10: =+(H7*$E$4/1000)*1.01*25% -> 10.645459 | K10: Resina PCR | L10: 0 | M10: 0 | Q10: =SUM(Q7:Q9) -> 1028.22 | R10: =SUM(R7:R9) -> 1049.09 | S10: =SUM(S7:S9) -> 1096.34 | T10: =SUM(T7:T9) -> 1083.75 | U10: =SUM(U7:U9) -> 1105.5 | V10: =SUM(V7:V9) -> 1135.6 | W10: =SUM(W7:W9) -> 1140 | X10: FOB
B11: Nueva Conversion | C11: 8.2 | D11: 8.2 | E11: 8.2 | F11: 11.15 | G11: 11.15 | H11: 11.15 | K11: Conversión | L11: 27.2 | M11: 27.2 | O11: Landed factor 4% | Q11: =+Q10*4% -> 41.1288 | R11: =+R10*4% -> 41.9636 | S11: =+S10*4% -> 43.8536 | T11: =+T10*4% -> 43.35 | U11: =+U10*4% -> 44.22 | V11: =+V10*4% -> 45.424 | W11: =+W10*4% -> 45.6
B12: Recargo por Penalidad y energ | C12: 0 | D12: 0 | E12: 0 | F12: 0 | G12: 0 | H12: 0 | K12: Recargo por Penalidad e incr | L12: 0 | M12: 0 | O12: Total resin price | Q12: =+Q11+Q10 -> 1069.3488 | R12: =+R11+R10 -> 1091.0536 | S12: =+S11+S10 -> 1140.1936 | T12: =+T11+T10 -> 1127.1 | U12: =+U11+U10 -> 1149.72 | V12: =+V11+V10 -> 1181.024 | W12: =+W11+W10 -> 1185.6
B13: Pigmento | C13: 1.3 | D13: 1.3 | E13: 1.3 | F13: 2.38 | G13: 2.38 | H13: 2.38 | K13: Pigmento | L13: 0.81 | M13: 1.99 | O13: Resin PCR % | Q13: =+Q12*(1-5%) -> 1015.8814 | R13: =+R12*(1-5%) -> 1036.5009 | S13: =+S12*(1-5%) -> 1083.1839 | T13: =+T12*(1-5%) -> 1070.745 | U13: =+U12*(1-5%) -> 1092.234 | V13: =+V12*(1-5%) -> 1121.9728 | W13: =+W12*(1-5%) -> 1126.32 | X13: Validar si nos está costando el 5% por debajo
B14: Empaque | C14: 0.19 | D14: 0.19 | E14: 0.19 | F14: 0.33 | G14: 0.33 | H14: 0.33 | K14: Empaque | L14: 2.71 | M14: 2.71 | O14: Precio ponderado bajo formuala | Q14: =+Q12*75%+Q13*25% -> 1055.9819 | R14: =+R12*75%+R13*25% -> 1077.4154 | S14: =+S12*75%+S13*25% -> 1125.9412 | T14: =+T12*75%+T13*25% -> 1113.0113 | U14: =+U12*75%+U13*25% -> 1135.3485 | V14: =+V12*75%+V13*25% -> 1166.2612 | W14: =+W12*75%+W13*25% -> 1170.78
B15: Flete | C15: 0.16 | D15: 0.16 | E15: 0.16 | F15: 0.28 | G15: 0.28 | H15: 0.28 | K15: Flete | L15: 7.77 | M15: 7.77 | O15: Scrap 1% | Q15: =+Q14*1% -> 10.559819 | R15: =+R14*1% -> 10.774154 | S15: =+S14*1% -> 11.259412 | T15: =+T14*1% -> 11.130113 | U15: =+U14*1% -> 11.353485 | V15: =+V14*1% -> 11.662612 | W15: =+W14*1% -> 11.7078
B16: Total | C16: =SUM(C9:C15) -> 27.738551 | D16: =SUM(D9:D15) -> 28.999923 | E16: =SUM(E9:E15) -> 33.357391 | F16: =SUM(F9:F15) -> 49.673246 | G16: =SUM(G9:G15) -> 49.229081 | H16: =SUM(H9:H15) -> 58.402697 | K16: Total | L16: =SUM(L9:L15) -> 55.822029 | M16: =SUM(M9:M15) -> 63.357106 | O16: Precio pnderado con scrap | Q16: =+Q15+Q14 -> 1066.5418 | R16: =+R15+R14 -> 1088.1896 | S16: =+S15+S14 -> 1137.2006 | T16: =+T15+T14 -> 1124.1414 | U16: =+U15+U14 -> 1146.702 | V16: =+V15+V14 -> 1177.9238 | W16: =+W15+W14 -> 1182.4878
O17: Precio facturado Sep-Oct-Nov | Q17: =+D5 -> 1146.702 | R17: =+Q17 -> 1146.702 | S17: =+R17 -> 1146.702 | T17: =+S17 -> 1146.702 | U17: =+T17 -> 1146.702 | V17: =+U17 -> 1146.702 | W17: =+V17 -> 1146.702
B33: Fórmula | M33: Factor mundial del precio de la resina

Sheet Feb18
B3: Costo de Resina Virgen Actual | E3: =+X12 -> 1181.024 | I3: 0.05 | K3: Costo de Resina Virgen Actual | M3: =+E3 -> 1181.024
B4: Costo de Resina PCR Actual (Enkador) | E4: =+X13 -> 1121.9728 | I4: =+E3*I3 -> 59.0512 | K4: Costo de Resina PCR Actual | M4: =+E4 -> 1121.9728
C5: =+(C9+C10)/C7*1000 -> 1177.9238 | D5: =+(D9+D10)/D7*1000 -> 1177.9238 | F5: =+(F9+F10)/F7*1000 -> 1192.8342 | L5: =+(L9+L10)/L7*1000 -> 1186.9291 | M5: =+(M9+M10)/M7*1000 -> 1186.9291 | Q5: Nueva metodología / nuevas condiciones
B6: Preformas | K6: Manantial | L6: 500ml SG | M6: 500ml CG | S6: IHS julio para precio septiembre | T6: IHS agosto para precio octubre | U6: IHS septiembre para precio noviembre | V6: IHS Octubre para precio Diciembre | W6: IHS Noviembre para precio Enero | X6: IHS Diciembre para precio Febrero | Y6: IHS Enero para precio Marzo
B7: Gramaje | C7: 15.6 | D7: 16.7 | E7: 20.5 | F7: 30.6 | G7: 30.6 | H7: 38.6 | K7: Gramaje | L7: 15 | M7: 20.5 | N7: 15 | O7: 20.5 | Q7: IHS Asia Non Coke approved | S7: 938.13 | T7: 959 | U7: 1006.25 | V7: 993.75 | W7: 1015.5 | X7: 1045.6 | Y7: 1050 | Z7: Revisar el actualizado
B8: Finish | C8: Short | D8: Short | E8: Short | F8: Short | G8: Short | H8: Short | K8: Finish | L8: Short | M8: Short | N8: Short | O8: Short | Q8: Finance | S8: 25.09 | T8: 25.09 | U8: 25.09 | V8: 25 | W8: 25 | X8: 25 | Y8: 25
B9: Resina Virgen | C9: =+(C7*E3/1000)*1.01*75% -> 13.956161 | D9: =+(D7*$E$3/1000)*1.01*75% -> 14.940249 | E9: =+(E7*$E$3/1000)*1.01*75% -> 18.339826 | F9: =+(F7*E3/1000)*1.01 -> 36.500728 | G9: =+(G7*$E$3/1000)*1.01*75% -> 27.375546 | H9: =+(H7*$E$3/1000)*1.01*75% -> 34.532551 | K9: Resina Virgen | L9: =+(L7*M3/1000)*1.005 -> 17.803937 | M9: =+(M7*M3/1000)*1.005 -> 24.332047 | N9: =+(N7*M3/1000)*1.005*75% -> 13.352953 | O9: =+(O7*M3/1000)*1.005*75% -> 18.249035 | Q9: Freight China-Gye | S9: 65 | T9: 65 | U9: 65 | V9: 65 | W9: 65 | X9: 65 | Y9: 65 | Z9: costo x TN | AA9: Análisis
B10: Resina PCR | C10: =+(C7*$E$4/1000)*1.01*25% -> 4.4194509 | D10: =+(D7*$E$4/1000)*1.01*25% -> 4.7310788 | E10: =+(E7*$E$4/1000)*1.01*25% -> 5.8076117 | F10: 0 | G10: =+(G7*$E$4/1000)*1.01*25% -> 8.6689228 | H10: =+(H7*$E$4/1000)*1.01*25% -> 10.935308 | K10: Resina PCR | L10: 0 | M10: 0 | N10: =+(N7*M4/1000)*1.005*25% -> 4.228435 | O10: =+(O7*M4/1000)*1.005*25% -> 5.7788612 | S10: =SUM(S7:S9) -> 1028.22 | T10: =SUM(T7:T9) -> 1049.09 | U10: =SUM(U7:U9) -> 1096.34 | V10: =SUM(V7:V9) -> 1083.75 | W10: =SUM(W7:W9) -> 1105.5 | X10: =SUM(X7:X9) -> 1135.6 | Y10: =SUM(Y7:Y9) -> 1140 | Z10: FOB
B11: Nueva Conversion | C11: 8.2 | D11: 8.2 | E11: 8.2 | F11: 11.15 | G11: 11.15 | H11: 11.15 | K11: Conversión | L11: 27.2 | M11: 27.2 | N11: 27.2 | O11: 27.2 | Q11: Landed factor 4% | S11: =+S10*4% -> 41.1288 | T11: =+T10*4% -> 41.9636 | U11: =+U10*4% -> 43.8536 | V11: =+V10*4% -> 43.35 | W11: =+W10*4% -> 44.22 | X11: =+X10*4% -> 45.424 | Y11: =+Y10*4% -> 45.6
B12: Recargo por Penalidad y energ | C12: 0 | D12: 0 | E12: 0 | F12: 0 | G12: 0 | H12: 0 | K12: Recargo por Penalidad e incr | L12: 0 | M12: 0 | N12: 0 | O12: 0 | Q12: Total resin price | S12: =+S11+S10 -> 1069.3488 | T12: =+T11+T10 -> 1091.0536 | U12: =+U11+U10 -> 1140.1936 | V12: =+V11+V10 -> 1127.1 | W12: =+W11+W10 -> 1149.72 | X12: =+X11+X10 -> 1181.024 | Y12: =+Y11+Y10 -> 1185.6
B13: Pigmento | C13: 1.3 | D13: 1.3 | E13: 1.3 | F13: 2.38 | G13: 2.38 | H13: 2.38 | K13: Pigmento | L13: 0.81 | M13: 1.99 | N13: 0.81 | O13: 1.99 | Q13: Resin PCR % | S13: =+S12*(1-5%) -> 1015.8814 | T13: =+T12*(1-5%) -> 1036.5009 | U13: =+U12*(1-5%) -> 1083.1839 | V13: =+V12*(1-5%) -> 1070.745 | W13: =+W12*(1-5%) -> 1092.234 | X13: =+X12*(1-5%) -> 1121.9728 | Y13: =+Y12*(1-5%) -> 1126.32 | Z13: Validar si nos está costando el 5% por debajo
B14: Empaque | C14: 0.19 | D14: 0.19 | E14: 0.19 | F14: 0.33 | G14: 0.33 | H14: 0.33 | K14: Empaque | L14: 2.71 | M14: 2.71 | N14: 2.71 | O14: 2.71 | Q14: Precio ponderado bajo formuala | S14: =+S12*75%+S13*25% -> 1055.9819 | T14: =+T12*75%+T13*25% -> 1077.4154 | U14: =+U12*75%+U13*25% -> 1125.9412 | V14: =+V12*75%+V13*25% -> 1113.0113 | W14: =+W12*75%+W13*25% -> 1135.3485 | X14: =+X12*75%+X13*25% -> 1166.2612 | Y14: =+Y12*75%+Y13*25% -> 1170.78
B15: Flete | C15: 0.16 | D15: 0.16 | E15: 0.16 | F15: 0.28 | G15: 0.28 | H15: 0.28 | K15: Flete | L15: 7.77 | M15: 7.77 | N15: 7.77 | O15: 7.77 | Q15: Scrap 1% | S15: =+S14*1% -> 10.559819 | T15: =+T14*1% -> 10.774154 | U15: =+U14*1% -> 11.259412 | V15: =+V14*1% -> 11.130113 | W15: =+W14*1% -> 11.353485 | X15: =+X14*1% -> 11.662612 | Y15: =+Y14*1% -> 11.7078
B16: Total | C16: =SUM(C9:C15) -> 28.225611 | D16: =SUM(D9:D15) -> 29.521328 | E16: =SUM(E9:E15) -> 33.997438 | F16: =SUM(F9:F15) -> 50.640728 | G16: =SUM(G9:G15) -> 50.184469 | H16: =SUM(H9:H15) -> 59.607859 | K16: Total | L16: =SUM(L9:L15) -> 56.293937 | M16: =SUM(M9:M15) -> 64.002047 | N16: =SUM(N9:N15) -> 56.071388 | O16: =SUM(O9:O15) -> 63.697896 | Q16: Precio pnderado con scrap | S16: =+S15+S14 -> 1066.5418 | T16: =+T15+T14 -> 1088.1896 | U16: =+U15+U14 -> 1137.2006 | V16: =+V15+V14 -> 1124.1414 | W16: =+W15+W14 -> 1146.702 | X16: =+X15+X14 -> 1177.9238 | Y16: =+Y15+Y14 -> 1182.4878
Q17: Precio facturado Sep-Oct-Nov | S17: =+D5 -> 1177.9238 | T17: =+S17 -> 1177.9238 | U17: =+T17 -> 1177.9238 | V17: =+U17 -> 1177.9238 | W17: =+V17 -> 1177.9238 | X17: =+W17 -> 1177.9238 | Y17: =+X17 -> 1177.9238
B32: Fórmula | M32: Factor mundial del precio de la resina

Sheet Mar18
B3: Costo de Resina Virgen Actual | E3: =+Y12 -> 1241.5 | I3: 0.05 | K3: Costo de Resina Virgen Actual | M3: =+E3 -> 1241.5
B4: Costo de Resina PCR Actual (Enkador) | E4: =+Y13 -> 1179.425 | I4: =+E3*I3 -> 62.075 | K4: Costo de Resina PCR Actual | M4: =+E4 -> 1179.425
C5: =+(C9+C10)/C7*1000 -> 1238.2411 | D5: =+(D9+D10)/D7*1000 -> 1238.2411 | F5: =+(F9+F10)/F7*1000 -> 1253.915 | L5: =+(L9+L10)/L7*1000 -> 1247.7075 | M5: =+(M9+M10)/M7*1000 -> 1247.7075 | Q5: Nueva metodología / nuevas condiciones
B6: Preformas | K6: Manantial | L6: 500ml SG | M6: 500ml CG | S6: IHS julio para precio septiembre | T6: IHS agosto para precio octubre | U6: IHS septiembre para precio noviembre | V6: IHS Octubre para precio Diciembre | W6: IHS Noviembre para precio Enero | X6: IHS Diciembre para precio Febrero | Y6: IHS Enero para precio Marzo | Z6: IHS Febrero para precio Abril
B7: Gramaje | C7: 15.6 | D7: 16.7 | E7: 20.5 | F7: 30.6 | G7: 30.6 | H7: 38.6 | K7: Gramaje | L7: 15 | M7: 20.5 | N7: 15 | O7: 20.5 | Q7: IHS Asia Non Coke approved | S7: 938.13 | T7: 959 | U7: 1006.25 | V7: 993.75 | W7: 1015.5 | X7: 1045.6 | Y7: 1103.75 | Z7: 1110
B8: Finish | C8: Short | D8: Short | E8: Short | F8: Short | G8: Short | H8: Short | K8: Finish | L8: Short | M8: Short | N8: Short | O8: Short | Q8: Finance | S8: 25.09 | T8: 25.09 | U8: 25.09 | V8: 25 | W8: 25 | X8: 25 | Y8: 25 | Z8: 25
B9: Resina Virgen | C9: =+(C7*E3/1000)*1.01*75% -> 14.670805 | D9: =+(D7*$E$3/1000)*1.01*75% -> 15.705285 | E9: =+(E7*$E$3/1000)*1.01*75% -> 19.278943 | F9: =+(F7*E3/1000)*1.01 -> 38.369799 | G9: =+(G7*$E$3/1000)*1.01*75% -> 28.777349 | H9: =+(H7*$E$3/1000)*1.01*75% -> 36.300839 | K9: Resina Virgen | L9: =+(L7*M3/1000)*1.005 -> 18.715612 | M9: =+(M7*M3/1000)*1.005 -> 25.578004 | N9: =+(N7*M3/1000)*1.005*75% -> 14.036709 | O9: =+(O7*M3/1000)*1.005*75% -> 19.183503 | Q9: Freight China-Gye | S9: 65 | T9: 65 | U9: 65 | V9: 65 | W9: 65 | X9: 65 | Y9: 65 | Z9: 65 | AA9: costo x TN | AB9: Análisis
B10: Resina PCR | C10: =+(C7*$E$4/1000)*1.01*25% -> 4.6457551 | D10: =+(D7*$E$4/1000)*1.01*25% -> 4.9733404 | E10: =+(E7*$E$4/1000)*1.01*25% -> 6.1049987 | F10: 0 | G10: =+(G7*$E$4/1000)*1.01*25% -> 9.1128273 | H10: =+(H7*$E$4/1000)*1.01*25% -> 11.495266 | K10: Resina PCR | L10: 0 | M10: 0 | N10: =+(N7*M4/1000)*1.005*25% -> 4.444958 | O10: =+(O7*M4/1000)*1.005*25% -> 6.0747759 | S10: =SUM(S7:S9) -> 1028.22 | T10: =SUM(T7:T9) -> 1049.09 | U10: =SUM(U7:U9) -> 1096.34 | V10: =SUM(V7:V9) -> 1083.75 | W10: =SUM(W7:W9) -> 1105.5 | X10: =SUM(X7:X9) -> 1135.6 | Y10: =SUM(Y7:Y9) -> 1193.75 | Z10: =SUM(Z7:Z9) -> 1200 | AA10: FOB
B11: Nueva Conversion | C11: 8.2 | D11: 8.2 | E11: 8.2 | F11: 11.15 | G11: 11.15 | H11: 11.15 | K11: Conversión | L11: 27.2 | M11: 27.2 | N11: 27.2 | O11: 27.2 | Q11: Landed factor 4% | S11: =+S10*4% -> 41.1288 | T11: =+T10*4% -> 41.9636 | U11: =+U10*4% -> 43.8536 | V11: =+V10*4% -> 43.35 | W11: =+W10*4% -> 44.22 | X11: =+X10*4% -> 45.424 | Y11: =+Y10*4% -> 47.75 | Z11: =+Z10*4% -> 48
B12: Recargo por Penalidad y energ | C12: 0 | D12: 0 | E12: 0 | F12: 0 | G12: 0 | H12: 0 | K12: Recargo por Penalidad e incr | L12: 0 | M12: 0 | N12: 0 | O12: 0 | Q12: Total resin price | S12: =+S11+S10 -> 1069.3488 | T12: =+T11+T10 -> 1091.0536 | U12: =+U11+U10 -> 1140.1936 | V12: =+V11+V10 -> 1127.1 | W12: =+W11+W10 -> 1149.72 | X12: =+X11+X10 -> 1181.024 | Y12: =+Y11+Y10 -> 1241.5 | Z12: =+Z11+Z10 -> 1248
B13: Pigmento | C13: 1.3 | D13: 1.3 | E13: 1.3 | F13: 2.38 | G13: 2.38 | H13: 2.38 | K13: Pigmento | L13: 0.81 | M13: 1.99 | N13: 0.81 | O13: 1.99 | Q13: Resin PCR % | S13: =+S12*(1-5%) -> 1015.8814 | T13: =+T12*(1-5%) -> 1036.5009 | U13: =+U12*(1-5%) -> 1083.1839 | V13: =+V12*(1-5%) -> 1070.745 | W13: =+W12*(1-5%) -> 1092.234 | X13: =+X12*(1-5%) -> 1121.9728 | Y13: =+Y12*(1-5%) -> 1179.425 | Z13: =+Z12*(1-5%) -> 1185.6 | AA13: Validar si nos está costando el 5% por debajo
B14: Empaque | C14: 0.19 | D14: 0.19 | E14: 0.19 | F14: 0.33 | G14: 0.33 | H14: 0.33 | K14: Empaque | L14: 2.71 | M14: 2.71 | N14: 2.71 | O14: 2.71 | Q14: Precio ponderado bajo formuala | S14: =+S12*75%+S13*25% -> 1055.9819 | T14: =+T12*75%+T13*25% -> 1077.4154 | U14: =+U12*75%+U13*25% -> 1125.9412 | V14: =+V12*75%+V13*25% -> 1113.0113 | W14: =+W12*75%+W13*25% -> 1135.3485 | X14: =+X12*75%+X13*25% -> 1166.2612 | Y14: =+Y12*75%+Y13*25% -> 1225.9813 | Z14: =+Z12*75%+Z13*25% -> 1232.4
B15: Flete | C15: 0.16 | D15: 0.16 | E15: 0.16 | F15: 0.28 | G15: 0.28 | H15: 0.28 | K15: Flete | L15: 7.77 | M15: 7.77 | N15: 7.77 | O15: 7.77 | Q15: Scrap 1% | S15: =+S14*1% -> 10.559819 | T15: =+T14*1% -> 10.774154 | U15: =+U14*1% -> 11.259412 | V15: =+V14*1% -> 11.130113 | W15: =+W14*1% -> 11.353485 | X15: =+X14*1% -> 11.662612 | Y15: =+Y14*1% -> 12.259813 | Z15: =+Z14*1% -> 12.324
B16: Total | C16: =SUM(C9:C15) -> 29.166561 | D16: =SUM(D9:D15) -> 30.528626 | E16: =SUM(E9:E15) -> 35.233942 | F16: =SUM(F9:F15) -> 52.509799 | G16: =SUM(G9:G15) -> 52.030177 | H16: =SUM(H9:H15) -> 61.936105 | K16: Total | L16: =SUM(L9:L15) -> 57.205613 | M16: =SUM(M9:M15) -> 65.248004 | N16: =SUM(N9:N15) -> 56.971667 | O16: =SUM(O9:O15) -> 64.928279 | Q16: Precio pnderado con scrap | S16: =+S15+S14 -> 1066.5418 | T16: =+T15+T14 -> 1088.1896 | U16: =+U15+U14 -> 1137.2006 | V16: =+V15+V14 -> 1124.1414 | W16: =+W15+W14 -> 1146.702 | X16: =+X15+X14 -> 1177.9238 | Y16: =+Y15+Y14 -> 1238.2411 | Z16: =+Z15+Z14 -> 1244.724
Q17: Precio facturado Sep-Oct-Nov | S17: =+D5 -> 1238.2411 | T17: =+S17 -> 1238.2411 | U17: =+T17 -> 1238.2411 | V17: =+U17 -> 1238.2411 | W17: =+V17 -> 1238.2411 | X17: =+W17 -> 1238.2411 | Y17: =+X17 -> 1238.2411 | Z17: =+Y17 -> 1238.2411
L25: Actualización | M25: 43145
B32: Fórmula | M32: Factor mundial del precio de la resina

Sheet Abril18
B3: Costo de Resina Virgen Actual | E3: =+Z12 -> 1288.3 | I3: 0.05 | K3: Costo de Resina Virgen Actual | M3: =+E3 -> 1288.3
B4: Costo de Resina PCR Actual (Enkador) | E4: =+Z13 -> 1223.885 | I4: =+E3*I3 -> 64.415 | K4: Costo de Resina PCR Actual | M4: =+E4 -> 1223.885
C5: =+(C9+C10)/C7*1000 -> 1284.9182 | D5: =+(D9+D10)/D7*1000 -> 1284.9182 | E5: =+(E9+E10)/E7*1000 -> 1284.9182 | F5: =+(F9+F10)/F7*1000 -> 1301.183 | G5: =+(G9+G10)/G7*1000 -> 1284.9182 | H5: =+(H9+H10)/H7*1000 -> 1284.9182 | L5: =+(L9+L10)/L7*1000 -> 1294.7415 | M5: =+(M9+M10)/M7*1000 -> 1294.7415 | Q5: Nueva metodología / nuevas condiciones
B6: Preformas | K6: Manantial | L6: 500ml SG | M6: 500ml CG | N6: 500ml SG | O6: 500ml CG | S6: IHS julio para precio septiembre | T6: IHS agosto para precio octubre | U6: IHS septiembre para precio noviembre | V6: IHS Octubre para precio Diciembre | W6: IHS Noviembre para precio Enero | X6: IHS Diciembre para precio Febrero | Y6: IHS Enero para precio Marzo | Z6: IHS Febrero para precio Abril | AA6: IHS Marzo para precio Mayo
B7: Gramaje | C7: 15.6 | D7: 16.7 | E7: 20.5 | F7: 30.6 | G7: 30.6 | H7: 38.6 | K7: Gramaje | L7: 15 | M7: 20.5 | N7: 15 | O7: 20.5 | Q7: IHS Asia Non Coke approved | S7: 938.13 | T7: 959 | U7: 1006.25 | V7: 993.75 | W7: 1015.5 | X7: 1045.6 | Y7: 1103.75 | Z7: 1148.75 | AA7: 1170
B8: Finish | C8: Short | D8: Short | E8: Short | F8: Short | G8: Short | H8: Short | K8: Finish | L8: Short | M8: Short | N8: Short | O8: Short | Q8: Finance | S8: 25.09 | T8: 25.09 | U8: 25.09 | V8: 25 | W8: 25 | X8: 25 | Y8: 25 | Z8: 25 | AA8: 25
B9: Resina Virgen | C9: =+(C7*E3/1000)*1.01*75% -> 15.223841 | D9: =+(D7*$E$3/1000)*1.01*75% -> 16.297317 | E9: =+(E7*$E$3/1000)*1.01*75% -> 20.005689 | F9: =+(F7*E3/1000)*1.01 -> 39.8162 | G9: =+(G7*$E$3/1000)*1.01*75% -> 29.86215 | H9: =+(H7*$E$3/1000)*1.01*75% -> 37.669248 | K9: Resina Virgen | L9: =+(L7*M3/1000)*1.005 -> 19.421122 | M9: =+(M7*M3/1000)*1.005 -> 26.542201 | N9: =+(N7*M3/1000)*1.005*75% -> 14.565842 | O9: =+(O7*M3/1000)*1.005*75% -> 19.906651 | Q9: Freight China-Gye | S9: 65 | T9: 65 | U9: 65 | V9: 65 | W9: 65 | X9: 65 | Y9: 65 | Z9: 65 | AA9: 65 | AB9: costo x TN | AC9: Análisis
B10: Resina PCR | C10: =+(C7*$E$4/1000)*1.01*25% -> 4.820883 | D10: =+(D7*$E$4/1000)*1.01*25% -> 5.1608171 | E10: =+(E7*$E$4/1000)*1.01*25% -> 6.3351347 | F10: 0 | G10: =+(G7*$E$4/1000)*1.01*25% -> 9.4563475 | H10: =+(H7*$E$4/1000)*1.01*25% -> 11.928595 | K10: Resina PCR | L10: 0 | M10: 0 | N10: =+(N7*M4/1000)*1.005*25% -> 4.6125166 | O10: =+(O7*M4/1000)*1.005*25% -> 6.3037727 | S10: =SUM(S7:S9) -> 1028.22 | T10: =SUM(T7:T9) -> 1049.09 | U10: =SUM(U7:U9) -> 1096.34 | V10: =SUM(V7:V9) -> 1083.75 | W10: =SUM(W7:W9) -> 1105.5 | X10: =SUM(X7:X9) -> 1135.6 | Y10: =SUM(Y7:Y9) -> 1193.75 | Z10: =SUM(Z7:Z9) -> 1238.75 | AA10: =SUM(AA7:AA9) -> 1260 | AB10: FOB
B11: Nueva Conversion | C11: 8.2 | D11: 8.2 | E11: 8.2 | F11: 11.15 | G11: 11.15 | H11: 11.15 | K11: Conversión | L11: 27.2 | M11: 27.2 | N11: 27.2 | O11: 27.2 | Q11: Landed factor 4% | S11: =+S10*4% -> 41.1288 | T11: =+T10*4% -> 41.9636 | U11: =+U10*4% -> 43.8536 | V11: =+V10*4% -> 43.35 | W11: =+W10*4% -> 44.22 | X11: =+X10*4% -> 45.424 | Y11: =+Y10*4% -> 47.75 | Z11: =+Z10*4% -> 49.55 | AA11: =+AA10*4% -> 50.4
B12: Recargo por Penalidad y energ | C12: 0 | D12: 0 | E12: 0 | F12: 0 | G12: 0 | H12: 0 | K12: Recargo por Penalidad e incr | L12: 0 | M12: 0 | N12: 0 | O12: 0 | Q12: Total resin price | S12: =+S11+S10 -> 1069.3488 | T12: =+T11+T10 -> 1091.0536 | U12: =+U11+U10 -> 1140.1936 | V12: =+V11+V10 -> 1127.1 | W12: =+W11+W10 -> 1149.72 | X12: =+X11+X10 -> 1181.024 | Y12: =+Y11+Y10 -> 1241.5 | Z12: =+Z11+Z10 -> 1288.3 | AA12: =+AA11+AA10 -> 1310.4
B13: Pigmento | C13: 1.3 | D13: 1.3 | E13: 1.3 | F13: 2.38 | G13: 2.38 | H13: 2.38 | K13: Pigmento | L13: 0.81 | M13: 1.99 | N13: 0.81 | O13: 1.99 | Q13: Resin PCR % | S13: =+S12*(1-5%) -> 1015.8814 | T13: =+T12*(1-5%) -> 1036.5009 | U13: =+U12*(1-5%) -> 1083.1839 | V13: =+V12*(1-5%) -> 1070.745 | W13: =+W12*(1-5%) -> 1092.234 | X13: =+X12*(1-5%) -> 1121.9728 | Y13: =+Y12*(1-5%) -> 1179.425 | Z13: =+Z12*(1-5%) -> 1223.885 | AA13: =+AA12*(1-5%) -> 1244.88 | AB13: Validar si nos está costando el 5% por debajo
B14: Empaque | C14: 0.19 | D14: 0.19 | E14: 0.19 | F14: 0.33 | G14: 0.33 | H14: 0.33 | K14: Empaque | L14: 2.71 | M14: 2.71 | N14: 2.71 | O14: 2.71 | Q14: Precio ponderado bajo formuala | S14: =+S12*75%+S13*25% -> 1055.9819 | T14: =+T12*75%+T13*25% -> 1077.4154 | U14: =+U12*75%+U13*25% -> 1125.9412 | V14: =+V12*75%+V13*25% -> 1113.0113 | W14: =+W12*75%+W13*25% -> 1135.3485 | X14: =+X12*75%+X13*25% -> 1166.2612 | Y14: =+Y12*75%+Y13*25% -> 1225.9813 | Z14: =+Z12*75%+Z13*25% -> 1272.1962 | AA14: =+AA12*75%+AA13*25% -> 1294.02
B15: Flete | C15: 0.16 | D15: 0.16 | E15: 0.16 | F15: 0.28 | G15: 0.28 | H15: 0.28 | K15: Flete | L15: 7.77 | M15: 7.77 | N15: 7.77 | O15: 7.77 | Q15: Scrap 1% | S15: =+S14*1% -> 10.559819 | T15: =+T14*1% -> 10.774154 | U15: =+U14*1% -> 11.259412 | V15: =+V14*1% -> 11.130113 | W15: =+W14*1% -> 11.353485 | X15: =+X14*1% -> 11.662612 | Y15: =+Y14*1% -> 12.259813 | Z15: =+Z14*1% -> 12.721963 | AA15: =+AA14*1% -> 12.9402
B16: Total | C16: =SUM(C9:C15) -> 29.894724 | D16: =SUM(D9:D15) -> 31.308134 | E16: =SUM(E9:E15) -> 36.190823 | F16: =SUM(F9:F15) -> 53.9562 | G16: =SUM(G9:G15) -> 53.458497 | H16: =SUM(H9:H15) -> 63.737843 | K16: Total | L16: =SUM(L9:L15) -> 57.911123 | M16: =SUM(M9:M15) -> 66.212201 | N16: =SUM(N9:N15) -> 57.668358 | O16: =SUM(O9:O15) -> 65.880423 | Q16: Precio pnderado con scrap | S16: =+S15+S14 -> 1066.5418 | T16: =+T15+T14 -> 1088.1896 | U16: =+U15+U14 -> 1137.2006 | V16: =+V15+V14 -> 1124.1414 | W16: =+W15+W14 -> 1146.702 | X16: =+X15+X14 -> 1177.9238 | Y16: =+Y15+Y14 -> 1238.2411 | Z16: =+Z15+Z14 -> 1284.9182 | AA16: =+AA15+AA14 -> 1306.9602
Q17: Precio facturado Sep-Oct-Nov | S17: =+D5 -> 1284.9182 | T17: =+S17 -> 1284.9182 | U17: =+T17 -> 1284.9182 | V17: =+U17 -> 1284.9182 | W17: =+V17 -> 1284.9182 | X17: =+W17 -> 1284.9182 | Y17: =+X17 -> 1284.9182 | Z17: =+Y17 -> 1284.9182 | AA17: =+Z17 -> 1284.9182
L25: Actualización | M25: 43180
B32: Fórmula | M32: Factor mundial del precio de la resina

Sheet Mayo18
B3: Costo de Resina Virgen Actual | E3: =+AB12 -> 1307.28 | I3: 0.05 | K3: Costo de Resina Virgen Actual | M3: =+E3 -> 1307.28
B4: Costo de Resina PCR Actual (Enkador) | E4: =+AB13 -> 1241.916 | I4: =+E3*I3 -> 65.364 | K4: Costo de Resina PCR Actual | M4: =+E4 -> 1241.916
C5: =+(C9+C10)/C7*1000 -> 1303.8484 | D5: =+(D9+D10)/D7*1000 -> 1303.8484 | E5: =+(E9+E10)/E7*1000 -> 1303.8484 | F5: =+(F9+F10)/F7*1000 -> 1320.3528 | G5: =+(G9+G10)/G7*1000 -> 1303.8484 | H5: =+(H9+H10)/H7*1000 -> 1303.8484 | L5: =+(L9+L10)/L7*1000 -> 1313.8164 | M5: =+(M9+M10)/M7*1000 -> 1313.8164 | R5: Nueva metodología / nuevas condiciones
B6: Preformas | K6: Manantial | L6: 500ml SG | M6: 500ml CG | N6: 500ml SG | O6: 500ml CG | P6: 1000ml SG | T6: IHS julio para precio septiembre | U6: IHS agosto para precio octubre | V6: IHS septiembre para precio noviembre | W6: IHS Octubre para precio Diciembre | X6: IHS Noviembre para precio Enero | Y6: IHS Diciembre para precio Febrero | Z6: IHS Enero para precio Marzo | AA6: IHS Febrero para precio Abril | AB6: IHS Marzo para precio Mayo
B7: Gramaje | C7: 15.6 | D7: 16.7 | E7: 20.5 | F7: 30.6 | G7: 30.6 | H7: 38.6 | K7: Gramaje | L7: 15 | M7: 20.5 | N7: 15 | O7: 20.5 | P7: 30.6 | R7: IHS Asia Non Coke approved | T7: 938.13 | U7: 959 | V7: 1006.25 | W7: 993.75 | X7: 1015.5 | Y7: 1045.6 | Z7: 1103.75 | AA7: 1148.75 | AB7: 1167
B8: Finish | C8: Short | D8: Short | E8: Short | F8: Short | G8: Short | H8: Short | K8: Finish | L8: Short | M8: Short | N8: Short | O8: Short | P8: Short | R8: Finance | T8: 25.09 | U8: 25.09 | V8: 25.09 | W8: 25 | X8: 25 | Y8: 25 | Z8: 25 | AA8: 25 | AB8: 25
B9: Resina Virgen | C9: =+(C7*E3/1000)*1.01*75% -> 15.448128 | D9: =+(D7*$E$3/1000)*1.01*75% -> 16.537419 | E9: =+(E7*$E$3/1000)*1.01*75% -> 20.300424 | F9: =+(F7*E3/1000)*1.01 -> 40.402796 | G9: =+(G7*$E$3/1000)*1.01*75% -> 30.302097 | H9: =+(H7*$E$3/1000)*1.01*75% -> 38.224214 | K9: Resina Virgen | L9: =+(L7*M3/1000)*1.005 -> 19.707246 | M9: =+(M7*M3/1000)*1.005 -> 26.933236 | N9: =+(N7*M3/1000)*1.005*75% -> 14.780434 | O9: =+(O7*M3/1000)*1.005*75% -> 20.199927 | P9: =+(P7*M3/1000)*1.005*75% -> 30.152086 | R9: Freight China-Gye | T9: 65 | U9: 65 | V9: 65 | W9: 65 | X9: 65 | Y9: 65 | Z9: 65 | AA9: 65 | AB9: 65 | AC9: costo x TN | AD9: Análisis
B10: Resina PCR | C10: =+(C7*$E$4/1000)*1.01*25% -> 4.8919071 | D10: =+(D7*$E$4/1000)*1.01*25% -> 5.2368493 | E10: =+(E7*$E$4/1000)*1.01*25% -> 6.4284677 | F10: 0 | G10: =+(G7*$E$4/1000)*1.01*25% -> 9.595664 | H10: =+(H7*$E$4/1000)*1.01*25% -> 12.104334 | K10: Resina PCR | L10: 0 | M10: 0 | N10: =+(N7*M4/1000)*1.005*25% -> 4.6804709 | O10: =+(O7*M4/1000)*1.005*25% -> 6.3966436 | P10: =+(P7*M4/1000)*1.005*25% -> 9.5481607 | T10: =SUM(T7:T9) -> 1028.22 | U10: =SUM(U7:U9) -> 1049.09 | V10: =SUM(V7:V9) -> 1096.34 | W10: =SUM(W7:W9) -> 1083.75 | X10: =SUM(X7:X9) -> 1105.5 | Y10: =SUM(Y7:Y9) -> 1135.6 | Z10: =SUM(Z7:Z9) -> 1193.75 | AA10: =SUM(AA7:AA9) -> 1238.75 | AB10: =SUM(AB7:AB9) -> 1257 | AC10: FOB
B11: Nueva Conversion | C11: 8.2 | D11: 8.2 | E11: 8.2 | F11: 11.15 | G11: 11.15 | H11: 11.15 | K11: Conversión | L11: 27.2 | M11: 27.2 | N11: 27.2 | O11: 27.2 | P11: =11.15+28.25 -> 39.4 | R11: Landed factor 4% | T11: =+T10*4% -> 41.1288 | U11: =+U10*4% -> 41.9636 | V11: =+V10*4% -> 43.8536 | W11: =+W10*4% -> 43.35 | X11: =+X10*4% -> 44.22 | Y11: =+Y10*4% -> 45.424 | Z11: =+Z10*4% -> 47.75 | AA11: =+AA10*4% -> 49.55 | AB11: =+AB10*4% -> 50.28
B12: Recargo por Penalidad y energ | C12: 0 | D12: 0 | E12: 0 | F12: 0 | G12: 0 | H12: 0 | K12: Recargo por Penalidad e incr | L12: 0 | M12: 0 | N12: 0 | O12: 0 | P12: 0 | R12: Total resin price | T12: =+T11+T10 -> 1069.3488 | U12: =+U11+U10 -> 1091.0536 | V12: =+V11+V10 -> 1140.1936 | W12: =+W11+W10 -> 1127.1 | X12: =+X11+X10 -> 1149.72 | Y12: =+Y11+Y10 -> 1181.024 | Z12: =+Z11+Z10 -> 1241.5 | AA12: =+AA11+AA10 -> 1288.3 | AB12: =+AB11+AB10 -> 1307.28
B13: Pigmento | C13: 1.3 | D13: 1.3 | E13: 1.3 | F13: 2.38 | G13: 2.38 | H13: 2.38 | K13: Pigmento | L13: 0.81 | M13: 1.99 | N13: 0.81 | O13: 1.99 | P13: 2.97 | R13: Resin PCR % | T13: =+T12*(1-5%) -> 1015.8814 | U13: =+U12*(1-5%) -> 1036.5009 | V13: =+V12*(1-5%) -> 1083.1839 | W13: =+W12*(1-5%) -> 1070.745 | X13: =+X12*(1-5%) -> 1092.234 | Y13: =+Y12*(1-5%) -> 1121.9728 | Z13: =+Z12*(1-5%) -> 1179.425 | AA13: =+AA12*(1-5%) -> 1223.885 | AB13: =+AB12*(1-5%) -> 1241.916 | AC13: Validar si nos está costando el 5% por debajo
B14: Empaque | C14: 0.19 | D14: 0.19 | E14: 0.19 | F14: 0.33 | G14: 0.33 | H14: 0.33 | K14: Empaque | L14: 2.71 | M14: 2.71 | N14: 2.71 | O14: 2.71 | P14: 4.44 | R14: Precio ponderado bajo formuala | T14: =+T12*75%+T13*25% -> 1055.9819 | U14: =+U12*75%+U13*25% -> 1077.4154 | V14: =+V12*75%+V13*25% -> 1125.9412 | W14: =+W12*75%+W13*25% -> 1113.0113 | X14: =+X12*75%+X13*25% -> 1135.3485 | Y14: =+Y12*75%+Y13*25% -> 1166.2612 | Z14: =+Z12*75%+Z13*25% -> 1225.9813 | AA14: =+AA12*75%+AA13*25% -> 1272.1962 | AB14: =+AB12*75%+AB13*25% -> 1290.939
B15: Flete | C15: 0.16 | D15: 0.16 | E15: 0.16 | F15: 0.28 | G15: 0.28 | H15: 0.28 | K15: Flete | L15: 7.77 | M15: 7.77 | N15: 7.77 | O15: 7.77 | P15: 15.99 | R15: Scrap 1% | T15: =+T14*1% -> 10.559819 | U15: =+U14*1% -> 10.774154 | V15: =+V14*1% -> 11.259412 | W15: =+W14*1% -> 11.130113 | X15: =+X14*1% -> 11.353485 | Y15: =+Y14*1% -> 11.662612 | Z15: =+Z14*1% -> 12.259813 | AA15: =+AA14*1% -> 12.721963 | AB15: =+AB14*1% -> 12.90939
B16: Total | C16: =SUM(C9:C15) -> 30.190035 | D16: =SUM(D9:D15) -> 31.624268 | E16: =SUM(E9:E15) -> 36.578892 | F16: =SUM(F9:F15) -> 54.542796 | G16: =SUM(G9:G15) -> 54.037761 | H16: =SUM(H9:H15) -> 64.468548 | K16: Total | L16: =SUM(L9:L15) -> 58.197246 | M16: =SUM(M9:M15) -> 66.603236 | N16: =SUM(N9:N15) -> 57.950905 | O16: =SUM(O9:O15) -> 66.266571 | P16: =SUM(P9:P15) -> 102.50025 | R16: Precio pnderado con scrap | T16: =+T15+T14 -> 1066.5418 | U16: =+U15+U14 -> 1088.1896 | V16: =+V15+V14 -> 1137.2006 | W16: =+W15+W14 -> 1124.1414 | X16: =+X15+X14 -> 1146.702 | Y16: =+Y15+Y14 -> 1177.9238 | Z16: =+Z15+Z14 -> 1238.2411 | AA16: =+AA15+AA14 -> 1284.9182 | AB16: =+AB15+AB14 -> 1303.8484
R17: Precio facturado Sep-Oct-Nov | T17: =+D5 -> 1303.8484 | U17: =+T17 -> 1303.8484 | V17: =+U17 -> 1303.8484 | W17: =+V17 -> 1303.8484 | X17: =+W17 -> 1303.8484 | Y17: =+X17 -> 1303.8484 | Z17: =+Y17 -> 1303.8484 | AA17: =+Z17 -> 1303.8484 | AB17: =+AA17 -> 1303.8484
B32: Fórmula | M32: Factor mundial del precio de la resina

Sheet Junio18
B3: Costo de Resina Virgen Actual | E3: =+AC12 -> 1363.7 | I3: 0.05 | K3: Costo de Resina Virgen Actual | M3: =+E3 -> 1363.7
B4: Costo de Resina PCR Actual (Enkador) | E4: =+AC13 -> 1295.515 | I4: =+E3*I3 -> 68.185 | K4: Costo de Resina PCR Actual | M4: =+E4 -> 1295.515
C5: =+(C9+C10)/C7*1000 -> 1360.1203 | D5: =+(D9+D10)/D7*1000 -> 1360.1203 | E5: =+(E9+E10)/E7*1000 -> 1360.1203 | F5: =+(F9+F10)/F7*1000 -> 1377.337 | G5: =+(G9+G10)/G7*1000 -> 1360.1203 | H5: =+(H9+H10)/H7*1000 -> 1360.1203 | L5: =+(L9+L10)/L7*1000 -> 1370.5185 | M5: =+(M9+M10)/M7*1000 -> 1370.5185 | R5: Nueva metodología / nuevas condiciones
B6: Preformas | K6: Manantial | L6: 500ml SG | M6: 500ml CG | N6: 500ml SG | O6: 500ml CG | P6: 1000ml SG | T6: IHS julio para precio septiembre | U6: IHS agosto para precio octubre | V6: IHS septiembre para precio noviembre | W6: IHS Octubre para precio Diciembre | X6: IHS Noviembre para precio Enero | Y6: IHS Diciembre para precio Febrero | Z6: IHS Enero para precio Marzo | AA6: IHS Febrero para precio Abril | AB6: IHS Marzo para precio Mayo | AC6: IHS Abril para precio Junio
B7: Gramaje | C7: 15.6 | D7: 16.7 | E7: 20.5 | F7: 30.6 | G7: 30.6 | H7: 38.6 | K7: Gramaje | L7: 15 | M7: 20.5 | N7: 15 | O7: 20.5 | P7: 30.6 | R7: IHS Asia Non Coke approved | T7: 938.13 | U7: 959 | V7: 1006.25 | W7: 993.75 | X7: 1015.5 | Y7: 1045.6 | Z7: 1103.75 | AA7: 1148.75 | AB7: 1167 | AC7: 1221.25
B8: Finish | C8: Short | D8: Short | E8: Short | F8: Short | G8: Short | H8: Short | K8: Finish | L8: Short | M8: Short | N8: Short | O8: Short | P8: Short | R8: Finance | T8: 25.09 | U8: 25.09 | V8: 25.09 | W8: 25 | X8: 25 | Y8: 25 | Z8: 25 | AA8: 25 | AB8: 25 | AC8: 25
B9: Resina Virgen | C9: =+(C7*E3/1000)*1.01*75% -> 16.114843 | D9: =+(D7*$E$3/1000)*1.01*75% -> 17.251146 | E9: =+(E7*$E$3/1000)*1.01*75% -> 21.176556 | F9: =+(F7*E3/1000)*1.01 -> 42.146512 | G9: =+(G7*$E$3/1000)*1.01*75% -> 31.609884 | H9: =+(H7*$E$3/1000)*1.01*75% -> 39.873906 | K9: Resina Virgen | L9: =+(L7*M3/1000)*1.005 -> 20.557778 | M9: =+(M7*M3/1000)*1.005 -> 28.095629 | N9: =+(N7*M3/1000)*1.005*75% -> 15.418333 | O9: =+(O7*M3/1000)*1.005*75% -> 21.071722 | P9: =+(P7*M3/1000)*1.005*75% -> 31.4534 | R9: Freight China-Gye | T9: 65 | U9: 65 | V9: 65 | W9: 65 | X9: 65 | Y9: 65 | Z9: 65 | AA9: 65 | AB9: 65 | AC9: 65
B10: Resina PCR | C10: =+(C7*$E$4/1000)*1.01*25% -> 5.1030336 | D10: =+(D7*$E$4/1000)*1.01*25% -> 5.4628629 | E10: =+(E7*$E$4/1000)*1.01*25% -> 6.7059095 | F10: 0 | G10: =+(G7*$E$4/1000)*1.01*25% -> 10.009797 | H10: =+(H7*$E$4/1000)*1.01*25% -> 12.626737 | K10: Resina PCR | L10: 0 | M10: 0 | N10: =+(N7*M4/1000)*1.005*25% -> 4.8824722 | O10: =+(O7*M4/1000)*1.005*25% -> 6.6727119 | P10: =+(P7*M4/1000)*1.005*25% -> 9.9602432 | T10: =SUM(T7:T9) -> 1028.22 | U10: =SUM(U7:U9) -> 1049.09 | V10: =SUM(V7:V9) -> 1096.34 | W10: =SUM(W7:W9) -> 1083.75 | X10: =SUM(X7:X9) -> 1105.5 | Y10: =SUM(Y7:Y9) -> 1135.6 | Z10: =SUM(Z7:Z9) -> 1193.75 | AA10: =SUM(AA7:AA9) -> 1238.75 | ... AC10: =SUM(AC7:AC9) -> 1311.25
B11: Nueva Conversion | C11: 8.2 | D11: 8.2 | E11: 8.2 | F11: 11.15 | G11: 11.15 | H11: 11.15 | K11: Conversión | L11: 27.2 | M11: 27.2 | N11: 27.2 | O11: 27.2 | P11: =11.15+28.25 -> 39.4 | R11: Landed factor 4% | T11: =+T10*4% -> 41.1288 | U11: =+U10*4% -> 41.9636 | V11: =+V10*4% -> 43.8536 | W11: =+W10*4% -> 43.35 | X11: =+X10*4% -> 44.22 | Y11: =+Y10*4% -> 45.424 | Z11: =+Z10*4% -> 47.75 | AA11: =+AA10*4% -> 49.55 | ... AC11: =+AC10*4% -> 52.45
B12: Recargo por Penalidad y energ | C12: 0 | D12: 0 | E12: 0 | F12: 0 | G12: 0 | H12: 0 | K12: Recargo por Penalidad e incr | L12: 0 | M12: 0 | N12: 0 | O12: 0 | P12: 0 | R12: Total resin price | T12: =+T11+T10 -> 1069.3488 | U12: =+U11+U10 -> 1091.0536 | V12: =+V11+V10 -> 1140.1936 | W12: =+W11+W10 -> 1127.1 | X12: =+X11+X10 -> 1149.72 | Y12: =+Y11+Y10 -> 1181.024 | Z12: =+Z11+Z10 -> 1241.5 | AA12: =+AA11+AA10 -> 1288.3 | ... AC12: =+AC11+AC10 -> 1363.7
B13: Pigmento | C13: 1.3 | D13: 1.3 | E13: 1.3 | F13: 2.38 | G13: 2.38 | H13: 2.38 | K13: Pigmento | L13: 0.81 | M13: 1.99 | N13: 0.81 | O13: 1.99 | P13: 2.97 | R13: Resin PCR % | T13: =+T12*(1-5%) -> 1015.8814 | U13: =+U12*(1-5%) -> 1036.5009 | V13: =+V12*(1-5%) -> 1083.1839 | W13: =+W12*(1-5%) -> 1070.745 | X13: =+X12*(1-5%) -> 1092.234 | Y13: =+Y12*(1-5%) -> 1121.9728 | Z13: =+Z12*(1-5%) -> 1179.425 | AA13: =+AA12*(1-5%) -> 1223.885 | ... AC13: =+AC12*(1-5%) -> 1295.515
B14: Empaque | C14: 0.19 | D14: 0.19 | E14: 0.19 | F14: 0.33 | G14: 0.33 | H14: 0.33 | K14: Empaque | L14: 2.71 | M14: 2.71 | N14: 2.71 | O14: 2.71 | P14: 4.44 | R14: Precio ponderado bajo formuala | T14: =+T12*75%+T13*25% -> 1055.9819 | U14: =+U12*75%+U13*25% -> 1077.4154 | V14: =+V12*75%+V13*25% -> 1125.9412 | W14: =+W12*75%+W13*25% -> 1113.0113 | X14: =+X12*75%+X13*25% -> 1135.3485 | Y14: =+Y12*75%+Y13*25% -> 1166.2612 | Z14: =+Z12*75%+Z13*25% -> 1225.9813 | AA14: =+AA12*75%+AA13*25% -> 1272.1962 | ... AC14: =+AC12*75%+AC13*25% -> 1346.6537
B15: Flete | C15: 0.16 | D15: 0.16 | E15: 0.16 | F15: 0.28 | G15: 0.28 | H15: 0.28 | K15: Flete | L15: 7.77 | M15: 7.77 | N15: 7.77 | O15: 7.77 | P15: 15.99 | R15: Scrap 1% | T15: =+T14*1% -> 10.559819 | U15: =+U14*1% -> 10.774154 | V15: =+V14*1% -> 11.259412 | W15: =+W14*1% -> 11.130113 | X15: =+X14*1% -> 11.353485 | Y15: =+Y14*1% -> 11.662612 | Z15: =+Z14*1% -> 12.259813 | AA15: =+AA14*1% -> 12.721963 | ... AC15: =+AC14*1% -> 13.466537
B16: Total | C16: =SUM(C9:C15) -> 31.067876 | D16: =SUM(D9:D15) -> 32.564009 | E16: =SUM(E9:E15) -> 37.732466 | F16: =SUM(F9:F15) -> 56.286512 | G16: =SUM(G9:G15) -> 55.759681 | H16: =SUM(H9:H15) -> 66.640643 | K16: Total | L16: =SUM(L9:L15) -> 59.047778 | M16: =SUM(M9:M15) -> 67.765629 | N16: =SUM(N9:N15) -> 58.790805 | O16: =SUM(O9:O15) -> 67.414434 | P16: =SUM(P9:P15) -> 104.21364 | R16: Precio pnderado con scrap | T16: =+T15+T14 -> 1066.5418 | U16: =+U15+U14 -> 1088.1896 | V16: =+V15+V14 -> 1137.2006 | W16: =+W15+W14 -> 1124.1414 | X16: =+X15+X14 -> 1146.702 | Y16: =+Y15+Y14 -> 1177.9238 | Z16: =+Z15+Z14 -> 1238.2411 | AA16: =+AA15+AA14 -> 1284.9182 | ... AC16: =+AC15+AC14 -> 1360.1203
R17: Precio facturado Sep-Oct-Nov | T17: =+D5 -> 1360.1203 | U17: =+T17 -> 1360.1203 | V17: =+U17 -> 1360.1203 | W17: =+V17 -> 1360.1203 | X17: =+W17 -> 1360.1203 | Y17: =+X17 -> 1360.1203 | Z17: =+Y17 -> 1360.1203 | AA17: =+Z17 -> 1360.1203 | AB17: =+AA17 -> 1360.1203 | AC17: =+AB17 -> 1360.1203
B32: Fórmula | M32: Factor mundial del precio de la resina

Sheet Julio18
B3: Costo de Resina Virgen Actual | E3: =+AC12 -> 1476.8 | I3: 0.05 | K3: Costo de Resina Virgen Actual | L3: =+E3 -> 1476.8
B4: Costo de Resina PCR Actual (Enkador) | E4: =+AC13 -> 1402.96 | I4: =+E3*I3 -> 73.84 | K4: Costo de Resina PCR Actual | L4: =+E4 -> 1402.96
C5: =+(C9+C10)/C7*1000 -> 1472.9234 | D5: =+(D9+D10)/D7*1000 -> 1472.9234 | E5: =+(E9+E10)/E7*1000 -> 1472.9234 | F5: =+(F9+F10)/F7*1000 -> 1491.568 | G5: =+(G9+G10)/G7*1000 -> 1472.9234 | H5: =+(H9+H10)/H7*1000 -> 1472.9234 | L5: =+(L9+L10)/L7*1000 -> 1484.184 | Q5: Nueva metodología / nuevas condiciones
B6: Preformas | K6: Manantial | L6: 500ml CG | M6: 500ml SG | N6: 500ml CG | O6: 1000ml SG | S6: IHS julio para precio septiembre | T6: IHS agosto para precio octubre | U6: IHS septiembre para precio noviembre | V6: IHS Octubre para precio Diciembre | W6: IHS Noviembre para precio Enero | X6: IHS Diciembre para precio Febrero | Y6: IHS Enero para precio Marzo | Z6: IHS Febrero para precio Abril | AA6: IHS Marzo para precio Mayo | AB6: IHS Abril para precio Junio | AC6: IHS Mayo para precio Julio
B7: Gramaje | C7: 15.6 | D7: 16.7 | E7: 20.5 | F7: 30.6 | G7: 30.6 | H7: 38.6 | K7: Gramaje | L7: 20.5 | M7: 15 | N7: 20.5 | O7: 30.6 | Q7: IHS Asia Non Coke approved | S7: 938.13 | T7: 959 | U7: 1006.25 | V7: 993.75 | W7: 1015.5 | X7: 1045.6 | Y7: 1103.75 | Z7: 1148.75 | AA7: 1167 | AB7: 1221.25 | AC7: 1330
B8: Finish | C8: Short | D8: Short | E8: Short | F8: Short | G8: Short | H8: Short | K8: Finish | L8: Short | M8: Short | N8: Short | O8: Short | Q8: Finance | S8: 25.09 | T8: 25.09 | U8: 25.09 | V8: 25 | W8: 25 | X8: 25 | Y8: 25 | Z8: 25 | AA8: 25 | AB8: 25 | AC8: 25
B9: Resina Virgen | C9: =+(C7*E3/1000)*1.01*75% -> 17.451346 | D9: =+(D7*$E$3/1000)*1.01*75% -> 18.681889 | E9: =+(E7*$E$3/1000)*1.01*75% -> 22.932858 | F9: =+(F7*E3/1000)*1.01 -> 45.641981 | G9: =+(G7*$E$3/1000)*1.01*75% -> 34.231486 | H9: =+(H7*$E$3/1000)*1.01*75% -> 43.180894 | K9: Resina Virgen | L9: =+(L7*L3/1000)*1.005 -> 30.425772 | M9: =+(M7*L3/1000)*1.005*75% -> 16.69707 | N9: =+(N7*L3/1000)*1.005*75% -> 22.819329 | O9: =+(O7*L3/1000)*1.005*75% -> 34.062023 | Q9: Freight China-Gye | S9: 65 | T9: 65 | U9: 65 | V9: 65 | W9: 65 | X9: 65 | Y9: 65 | Z9: 65 | AA9: 65 | AB9: 65 | AC9: 65
B10: Resina PCR | C10: =+(C7*$E$4/1000)*1.01*25% -> 5.5262594 | D10: =+(D7*$E$4/1000)*1.01*25% -> 5.9159316 | E10: =+(E7*$E$4/1000)*1.01*25% -> 7.2620717 | F10: 0 | G10: =+(G7*$E$4/1000)*1.01*25% -> 10.83997 | H10: =+(H7*$E$4/1000)*1.01*25% -> 13.67395 | K10: Resina PCR | L10: 0 | M10: =+(M7*L4/1000)*1.005*25% -> 5.2874055 | N10: =+(N7*L4/1000)*1.005*25% -> 7.2261208 | O10: =+(O7*L4/1000)*1.005*25% -> 10.786307 | S10: =SUM(S7:S9) -> 1028.22 | T10: =SUM(T7:T9) -> 1049.09 | U10: =SUM(U7:U9) -> 1096.34 | V10: =SUM(V7:V9) -> 1083.75 | W10: =SUM(W7:W9) -> 1105.5 | X10: =SUM(X7:X9) -> 1135.6 | Y10: =SUM(Y7:Y9) -> 1193.75 | Z10: =SUM(Z7:Z9) -> 1238.75 | ... AC10: =SUM(AC7:AC9) -> 1420
B11: Nueva Conversion | C11: 8.2 | D11: 8.2 | E11: 8.2 | F11: 11.15 | G11: 11.15 | H11: 11.15 | K11: Conversión | L11: 27.2 | M11: 27.2 | N11: 27.2 | O11: =11.15+28.25 -> 39.4 | Q11: Landed factor 4% | S11: =+S10*4% -> 41.1288 | T11: =+T10*4% -> 41.9636 | U11: =+U10*4% -> 43.8536 | V11: =+V10*4% -> 43.35 | W11: =+W10*4% -> 44.22 | X11: =+X10*4% -> 45.424 | Y11: =+Y10*4% -> 47.75 | Z11: =+Z10*4% -> 49.55 | ... AC11: =+AC10*4% -> 56.8
B12: Recargo por Penalidad y energ | C12: 0 | D12: 0 | E12: 0 | F12: 0 | G12: 0 | H12: 0 | K12: Recargo por Penalidad e incr | L12: 0 | M12: 0 | N12: 0 | O12: 0 | Q12: Total resin price | S12: =+S11+S10 -> 1069.3488 | T12: =+T11+T10 -> 1091.0536 | U12: =+U11+U10 -> 1140.1936 | V12: =+V11+V10 -> 1127.1 | W12: =+W11+W10 -> 1149.72 | X12: =+X11+X10 -> 1181.024 | Y12: =+Y11+Y10 -> 1241.5 | Z12: =+Z11+Z10 -> 1288.3 | ... AC12: =+AC11+AC10 -> 1476.8
B13: Pigmento | C13: 1.3 | D13: 1.3 | E13: 1.3 | F13: 2.38 | G13: 2.38 | H13: 2.38 | K13: Pigmento | L13: 1.99 | M13: 0.81 | N13: 1.99 | O13: 2.97 | Q13: Resin PCR % | S13: =+S12*(1-5%) -> 1015.8814 | T13: =+T12*(1-5%) -> 1036.5009 | U13: =+U12*(1-5%) -> 1083.1839 | V13: =+V12*(1-5%) -> 1070.745 | W13: =+W12*(1-5%) -> 1092.234 | X13: =+X12*(1-5%) -> 1121.9728 | Y13: =+Y12*(1-5%) -> 1179.425 | Z13: =+Z12*(1-5%) -> 1223.885 | ... AC13: =+AC12*(1-5%) -> 1402.96
B14: Empaque | C14: 0.19 | D14: 0.19 | E14: 0.19 | F14: 0.33 | G14: 0.33 | H14: 0.33 | K14: Empaque | L14: 2.71 | M14: 2.71 | N14: 2.71 | O14: 4.44 | Q14: Precio ponderado bajo formuala | S14: =+S12*75%+S13*25% -> 1055.9819 | T14: =+T12*75%+T13*25% -> 1077.4154 | U14: =+U12*75%+U13*25% -> 1125.9412 | V14: =+V12*75%+V13*25% -> 1113.0113 | W14: =+W12*75%+W13*25% -> 1135.3485 | X14: =+X12*75%+X13*25% -> 1166.2612 | Y14: =+Y12*75%+Y13*25% -> 1225.9813 | Z14: =+Z12*75%+Z13*25% -> 1272.1962 | ... AC14: =+AC12*75%+AC13*25% -> 1458.34
B15: Flete | C15: 0.16 | D15: 0.16 | E15: 0.16 | F15: 0.28 | G15: 0.28 | H15: 0.28 | K15: Flete | L15: 7.77 | M15: 7.77 | N15: 7.77 | O15: 15.99 | Q15: Scrap 1% | S15: =+S14*1% -> 10.559819 | T15: =+T14*1% -> 10.774154 | U15: =+U14*1% -> 11.259412 | V15: =+V14*1% -> 11.130113 | W15: =+W14*1% -> 11.353485 | X15: =+X14*1% -> 11.662612 | Y15: =+Y14*1% -> 12.259813 | Z15: =+Z14*1% -> 12.721963 | ... AC15: =+AC14*1% -> 14.5834
B16: Total | C16: =SUM(C9:C15) -> 32.827605 | D16: =SUM(D9:D15) -> 34.447821 | E16: =SUM(E9:E15) -> 40.04493 | F16: =SUM(F9:F15) -> 59.781981 | G16: =SUM(G9:G15) -> 59.211456 | H16: =SUM(H9:H15) -> 70.994843 | K16: Total | L16: =SUM(L9:L15) -> 70.095772 | M16: =SUM(M9:M15) -> 60.474475 | N16: =SUM(N9:N15) -> 69.71545 | O16: =SUM(O9:O15) -> 107.64833 | Q16: Precio pnderado con scrap | S16: =+S15+S14 -> 1066.5418 | T16: =+T15+T14 -> 1088.1896 | U16: =+U15+U14 -> 1137.2006 | V16: =+V15+V14 -> 1124.1414 | W16: =+W15+W14 -> 1146.702 | X16: =+X15+X14 -> 1177.9238 | Y16: =+Y15+Y14 -> 1238.2411 | Z16: =+Z15+Z14 -> 1284.9182 | ... AC16: =+AC15+AC14 -> 1472.9234
Q17: Precio facturado Sep-Oct-Nov | S17: =+D5 -> 1472.9234 | T17: =+S17 -> 1472.9234 | U17: =+T17 -> 1472.9234 | V17: =+U17 -> 1472.9234 | W17: =+V17 -> 1472.9234 | X17: =+W17 -> 1472.9234 | Y17: =+X17 -> 1472.9234 | Z17: =+Y17 -> 1472.9234 | AA17: =+Z17 -> 1472.9234 | ... AC17: =+AB17 -> 1472.9234
B32: Fórmula

Sheet Agosto18
B3: Costo Resina Virgen | E3: =+AC12 -> 1438.4653 | I3: 0.05
B4: Costo Resina PCR Enkador | E4: =+AC13 -> 1366.542 | I4: =+E3*I3 -> 71.923266
C5: =+(C9+C10)/C7*1000 -> 1434.6893 | D5: =+(D9+D10)/D7*1000 -> 1434.6893 | E5: =+(E9+E10)/E7*1000 -> 1434.6893 | F5: =+(F9+F10)/F7*1000 -> 1452.85 | G5: =+(G9+G10)/G7*1000 -> 1434.6893 | H5: =+(H9+H10)/H7*1000 -> 1434.6893
B6: Preformas | C6: 200cc Pony | D6: 330cc Pony | E6: 330cc Pony | F6: 1 Litro Pony | G6: 1 Litro Pony | H6: 1 Litro Pony | K6: Envases | L6: 500ml CG | M6: 500ml SG | N6: 500ml CG | O6: 1000ml SG | Q6: Rubros | R6: IHS julio para precio septiembre | S6: IHS agosto para precio octubre | T6: IHS septiembre para precio noviembre | U6: IHS Octubre para precio Diciembre | V6: IHS Noviembre para precio Enero | W6: IHS Diciembre para precio Febrero | X6: IHS Enero para precio Marzo | Y6: IHS Febrero para precio Abril | Z6: IHS Marzo para precio Mayo | AA6: IHS Abril para precio Junio | AB6: IHS Mayo para precio Julio | AC6: IHS Junio para precio Agosto
B7: Gramaje | C7: 16.7 | D7: 16.7 | E7: 20.5 | F7: 30.6 | G7: 30.6 | H7: 38.6 | K7: Gramaje | L7: 20.5 | M7: 15 | N7: 20.5 | O7: 30.6 | Q7: IHS Asia Non Coke approved | R7: 938.13 | S7: 959 | T7: 1006.25 | U7: 993.75 | V7: 1015.5 | W7: 1045.6 | X7: 1103.75 | Y7: 1148.75 | Z7: 1167 | AA7: 1221.25 | AB7: 1330 | AC7: =+'IHS (Mod)'!I5 -> 1280
B8: Finish | C8: Short | D8: Short | E8: Short | F8: Short | G8: Short | H8: Short | K8: Finish | L8: Short | M8: Short | N8: Short | O8: Short | Q8: Finance | R8: 25.09 | S8: 25.09 | T8: 25.09 | U8: 25 | V8: 25 | W8: 25 | X8: 25 | Y8: 25 | Z8: 25 | AA8: 25 | AB8: 25 | AC8: =+AF8 -> 33.139726 | AD8: =+AC7*4.5% -> 57.6 | AE8: =+AD8/365 -> 0.15780822 | AF8: =+AE8*210 -> 33.139726
B9: Resina Virgen | C9: =+(C7*E3/1000)*1.01*75% -> 18.196946 | D9: =+(D7*$E$3/1000)*1.01*75% -> 18.196946 | E9: =+(E7*$E$3/1000)*1.01*75% -> 22.337568 | F9: =+(F7*E3/1000)*1.01 -> 44.457209 | G9: =+(G7*$E$3/1000)*1.01*75% -> 33.342907 | H9: =+(H7*$E$3/1000)*1.01*75% -> 42.060007 | K9: Resina Virgen | L9: =+(L7*E3/1000)*1.005 -> 29.635982 | M9: =+(M7*E3/1000)*1.005*75% -> 16.263648 | N9: =+(N7*E3/1000)*1.005*75% -> 22.226986 | O9: =+(O7*E3/1000)*1.005*75% -> 33.177843 | Q9: Freight China-Gye | R9: 65 | S9: 65 | T9: 65 | U9: 65 | V9: 65 | W9: 65 | X9: 65 | Y9: 65 | Z9: 65 | AA9: 65 | AB9: 65 | AC9: 70
B10: Resina PCR | C10: =+(C7*$E$4/1000)*1.01*25% -> 5.7623662 | D10: =+(D7*$E$4/1000)*1.01*25% -> 5.7623662 | E10: =+(E7*$E$4/1000)*1.01*25% -> 7.0735633 | F10: 0 | G10: =+(G7*$E$4/1000)*1.01*25% -> 10.558587 | H10: =+(H7*$E$4/1000)*1.01*25% -> 13.319002 | K10: Resina PCR | L10: 0 | M10: =+(M7*E4/1000)*1.005*25% -> 5.1501553 | N10: =+(N7*E4/1000)*1.005*25% -> 7.0385456 | O10: =+(O7*E4/1000)*1.005*25% -> 10.506317 | R10: =SUM(R7:R9) -> 1028.22 | S10: =SUM(S7:S9) -> 1049.09 | T10: =SUM(T7:T9) -> 1096.34 | U10: =SUM(U7:U9) -> 1083.75 | V10: =SUM(V7:V9) -> 1105.5 | W10: =SUM(W7:W9) -> 1135.6 | X10: =SUM(X7:X9) -> 1193.75 | Y10: =SUM(Y7:Y9) -> 1238.75 | ... AC10: =SUM(AC7:AC9) -> 1383.1397
B11: Conversión | C11: 8.2 | D11: 8.2 | E11: 8.2 | F11: 11.15 | G11: 11.15 | H11: 11.15 | K11: Conversión | L11: 27.2 | M11: 27.2 | N11: 27.2 | O11: =11.15+28.25 -> 39.4 | Q11: Landed factor 4% | R11: =+R10*4% -> 41.1288 | S11: =+S10*4% -> 41.9636 | T11: =+T10*4% -> 43.8536 | U11: =+U10*4% -> 43.35 | V11: =+V10*4% -> 44.22 | W11: =+W10*4% -> 45.424 | X11: =+X10*4% -> 47.75 | Y11: =+Y10*4% -> 49.55 | ... AC11: =+AC10*4% -> 55.325589
B12: Pigmento | C12: 1.3 | D12: 1.3 | E12: 1.3 | F12: 2.38 | G12: 2.38 | H12: 2.38 | K12: Pigmento | L12: 1.99 | M12: 0.81 | N12: 1.99 | O12: 2.97 | Q12: Total resin price | R12: =+R11+R10 -> 1069.3488 | S12: =+S11+S10 -> 1091.0536 | T12: =+T11+T10 -> 1140.1936 | U12: =+U11+U10 -> 1127.1 | V12: =+V11+V10 -> 1149.72 | W12: =+W11+W10 -> 1181.024 | X12: =+X11+X10 -> 1241.5 | Y12: =+Y11+Y10 -> 1288.3 | ... AC12: =+AC11+AC10 -> 1438.4653
B13: Empaque | C13: 0.19 | D13: 0.19 | E13: 0.19 | F13: 0.33 | G13: 0.33 | H13: 0.33 | K13: Empaque | L13: 2.71 | M13: 2.71 | N13: 2.71 | O13: 4.44 | Q13: Resin PCR % | R13: =+R12*(1-5%) -> 1015.8814 | S13: =+S12*(1-5%) -> 1036.5009 | T13: =+T12*(1-5%) -> 1083.1839 | U13: =+U12*(1-5%) -> 1070.745 | V13: =+V12*(1-5%) -> 1092.234 | W13: =+W12*(1-5%) -> 1121.9728 | X13: =+X12*(1-5%) -> 1179.425 | Y13: =+Y12*(1-5%) -> 1223.885 | ... AC13: =+AC12*(1-5%) -> 1366.542
B14: Flete | C14: 0.16 | D14: 0.16 | E14: 0.16 | F14: 0.28 | G14: 0.28 | H14: 0.28 | K14: Flete | L14: 7.77 | M14: 7.77 | N14: 7.77 | O14: 15.99 | Q14: Precio ponderado bajo formuala | R14: =+R12*75%+R13*25% -> 1055.9819 | S14: =+S12*75%+S13*25% -> 1077.4154 | T14: =+T12*75%+T13*25% -> 1125.9412 | U14: =+U12*75%+U13*25% -> 1113.0113 | V14: =+V12*75%+V13*25% -> 1135.3485 | W14: =+W12*75%+W13*25% -> 1166.2612 | X14: =+X12*75%+X13*25% -> 1225.9813 | Y14: =+Y12*75%+Y13*25% -> 1272.1962 | ... AC14: =+AC12*75%+AC13*25% -> 1420.4845
B15: Total | C15: =SUM(C9:C14) -> 33.809312 | D15: =SUM(D9:D14) -> 33.809312 | E15: =SUM(E9:E14) -> 39.261132 | F15: =SUM(F9:F14) -> 58.597209 | G15: =SUM(G9:G14) -> 58.041494 | H15: =SUM(H9:H14) -> 69.519009 | K15: Total | L15: =SUM(L9:L14) -> 69.305982 | M15: =SUM(M9:M14) -> 59.903804 | N15: =SUM(N9:N14) -> 68.935532 | O15: =SUM(O9:O14) -> 106.48416 | Q15: Scrap 1% | R15: =+R14*1% -> 10.559819 | S15: =+S14*1% -> 10.774154 | T15: =+T14*1% -> 11.259412 | U15: =+U14*1% -> 11.130113 | V15: =+V14*1% -> 11.353485 | W15: =+W14*1% -> 11.662612 | X15: =+X14*1% -> 12.259813 | Y15: =+Y14*1% -> 12.721963 | ... AC15: =+AC14*1% -> 14.204845
Q16: Precio ponderado con scrap | R16: =+R15+R14 -> 1066.5418 | S16: =+S15+S14 -> 1088.1896 | T16: =+T15+T14 -> 1137.2006 | U16: =+U15+U14 -> 1124.1414 | V16: =+V15+V14 -> 1146.702 | W16: =+W15+W14 -> 1177.9238 | X16: =+X15+X14 -> 1238.2411 | Y16: =+Y15+Y14 -> 1284.9182 | ... AC16: =+AC15+AC14 -> 1434.6893
Q17: Precio facturado Sep-Oct-Nov | R17: =+D5 -> 1434.6893 | S17: =+R17 -> 1434.6893 | T17: =+S17 -> 1434.6893 | U17: =+T17 -> 1434.6893 | V17: =+U17 -> 1434.6893 | W17: =+V17 -> 1434.6893 | X17: =+W17 -> 1434.6893 | Y17: =+X17 -> 1434.6893 | Z17: =+Y17 -> 1434.6893 | ... AC17: =+AB17 -> 1434.6893
M20: Extracto composición del precio base en el contrato
B32: Fórmula

Sheet Septiembre18
B3: Costo Resina Virgen | E3: =+AD12 -> 1437.8038 | I3: 0.05
B4: Costo Resina PCR Enkador | E4: =+AD13 -> 1365.9136 | I4: =+E3*I3 -> 71.890191
C5: =+(C9+C10)/C7*1000 -> 1434.0296 | D5: =+(D9+D10)/D7*1000 -> 1434.0296 | E5: =+(E9+E10)/E7*1000 -> 1434.0296 | F5: =+(F9+F10)/F7*1000 -> 1452.1819 | G5: =+(G9+G10)/G7*1000 -> 1434.0296 | H5: =+(H9+H10)/H7*1000 -> 1434.0296
B6: Preformas | C6: 200cc Pony | D6: 330cc Pony | E6: 330cc Pony | F6: 1 Litro Pony | G6: 1 Litro Pony | H6: 1 Litro Pony | K6: Envases | L6: 500ml CG | M6: 500ml SG | N6: 500ml CG | O6: 1000ml SG | Q6: Rubros | R6: IHS julio para precio septiembre | S6: IHS agosto para precio octubre | T6: IHS septiembre para precio noviembre | U6: IHS Octubre para precio Diciembre | V6: IHS Noviembre para precio Enero | W6: IHS Diciembre para precio Febrero | X6: IHS Enero para precio Marzo | Y6: IHS Febrero para precio Abril | Z6: IHS Marzo para precio Mayo | AA6: IHS Abril para precio Junio | AB6: IHS Mayo para precio Julio | AC6: IHS Junio para precio Agosto | AD6: IHS Julio para precio Septiembre
B7: Gramaje | C7: 16.7 | D7: 16.7 | E7: 20.5 | F7: 30.6 | G7: 30.6 | H7: 38.6 | K7: Gramaje | L7: 20.5 | M7: 15 | N7: 20.5 | O7: 30.6 | Q7: IHS Asia Non Coke approved | R7: 938.13 | S7: 959 | T7: 1006.25 | U7: 993.75 | V7: 1015.5 | W7: 1045.6 | X7: 1103.75 | Y7: 1148.75 | Z7: 1167 | AA7: 1221.25 | AB7: 1330 | AC7: =+'IHS (Mod)'!I5 -> 1280 | AD7: =+'IHS (Mod)'!J5 -> 1279.38 | AE7: Finance 4.5%
B8: Finish | C8: Short | D8: Short | E8: Short | F8: Short | G8: Short | H8: Short | K8: Finish | L8: Short | M8: Short | N8: Short | O8: Short | Q8: Finance | R8: 25.09 | S8: 25.09 | T8: 25.09 | U8: 25 | V8: 25 | W8: 25 | X8: 25 | Y8: 25 | Z8: 25 | AA8: 25 | AB8: 25 | AC8: 33.139726 | AD8: =+AG8 -> 33.123674 | AE8: =+AD7*4.5% -> 57.5721 | AF8: =+AE8/365 -> 0.15773178 | AG8: =+AF8*210 -> 33.123674
B9: Resina Virgen | C9: =+(C7*E3/1000)*1.01*75% -> 18.188578 | D9: =+(D7*$E$3/1000)*1.01*75% -> 18.188578 | E9: =+(E7*$E$3/1000)*1.01*75% -> 22.327296 | F9: =+(F7*E3/1000)*1.01 -> 44.436765 | G9: =+(G7*$E$3/1000)*1.01*75% -> 33.327574 | H9: =+(H7*$E$3/1000)*1.01*75% -> 42.040665 | K9: Resina Virgen | L9: =+(L7*E3/1000)*1.005 -> 29.622353 | M9: =+(M7*E3/1000)*1.005*75% -> 16.25617 | N9: =+(N7*E3/1000)*1.005*75% -> 22.216765 | O9: =+(O7*E3/1000)*1.005*75% -> 33.162586 | Q9: Freight China-Gye | R9: 65 | S9: 65 | T9: 65 | U9: 65 | V9: 65 | W9: 65 | X9: 65 | Y9: 65 | Z9: 65 | AA9: 65 | AB9: 65 | AC9: 70 | AD9: 70
B10: Resina PCR | C10: =+(C7*$E$4/1000)*1.01*25% -> 5.7597163 | D10: =+(D7*$E$4/1000)*1.01*25% -> 5.7597163 | E10: =+(E7*$E$4/1000)*1.01*25% -> 7.0703105 | F10: 0 | G10: =+(G7*$E$4/1000)*1.01*25% -> 10.553732 | H10: =+(H7*$E$4/1000)*1.01*25% -> 13.312877 | K10: Resina PCR | L10: 0 | M10: =+(M7*E4/1000)*1.005*25% -> 5.147787 | N10: =+(N7*E4/1000)*1.005*25% -> 7.0353089 | O10: =+(O7*E4/1000)*1.005*25% -> 10.501486 | R10: =SUM(R7:R9) -> 1028.22 | S10: =SUM(S7:S9) -> 1049.09 | T10: =SUM(T7:T9) -> 1096.34 | U10: =SUM(U7:U9) -> 1083.75 | V10: =SUM(V7:V9) -> 1105.5 | W10: =SUM(W7:W9) -> 1135.6 | X10: =SUM(X7:X9) -> 1193.75 | Y10: =SUM(Y7:Y9) -> 1238.75 | ... AD10: =SUM(AD7:AD9) -> 1382.5037
B11: Conversión | C11: 8.2 | D11: 8.2 | E11: 8.2 | F11: 11.15 | G11: 11.15 | H11: 11.15 | K11: Conversión | L11: 27.2 | M11: 27.2 | N11: 27.2 | O11: =11.15+28.25 -> 39.4 | Q11: Landed factor 4% | R11: =+R10*4% -> 41.1288 | S11: =+S10*4% -> 41.9636 | T11: =+T10*4% -> 43.8536 | U11: =+U10*4% -> 43.35 | V11: =+V10*4% -> 44.22 | W11: =+W10*4% -> 45.424 | X11: =+X10*4% -> 47.75 | Y11: =+Y10*4% -> 49.55 | ... AD11: =+AD10*4% -> 55.300147
B12: Pigmento | C12: 1.3 | D12: 1.3 | E12: 1.3 | F12: 2.38 | G12: 2.38 | H12: 2.38 | K12: Pigmento | L12: 1.99 | M12: 0.81 | N12: 1.99 | O12: 2.97 | Q12: Total resin price | R12: =+R11+R10 -> 1069.3488 | S12: =+S11+S10 -> 1091.0536 | T12: =+T11+T10 -> 1140.1936 | U12: =+U11+U10 -> 1127.1 | V12: =+V11+V10 -> 1149.72 | W12: =+W11+W10 -> 1181.024 | X12: =+X11+X10 -> 1241.5 | Y12: =+Y11+Y10 -> 1288.3 | ... AD12: =+AD11+AD10 -> 1437.8038
B13: Empaque | C13: 0.19 | D13: 0.19 | E13: 0.19 | F13: 0.33 | G13: 0.33 | H13: 0.33 | K13: Empaque | L13: 2.71 | M13: 2.71 | N13: 2.71 | O13: 4.44 | Q13: Resin PCR % | R13: =+R12*(1-5%) -> 1015.8814 | S13: =+S12*(1-5%) -> 1036.5009 | T13: =+T12*(1-5%) -> 1083.1839 | U13: =+U12*(1-5%) -> 1070.745 | V13: =+V12*(1-5%) -> 1092.234 | W13: =+W12*(1-5%) -> 1121.9728 | X13: =+X12*(1-5%) -> 1179.425 | Y13: =+Y12*(1-5%) -> 1223.885 | ... AD13: =+AD12*(1-5%) -> 1365.9136
B14: Flete | C14: 0.16 | D14: 0.16 | E14: 0.16 | F14: 0.28 | G14: 0.28 | H14: 0.28 | K14: Flete | L14: 7.77 | M14: 7.77 | N14: 7.77 | O14: 15.99 | Q14: Precio ponderado bajo formuala | R14: =+R12*75%+R13*25% -> 1055.9819 | S14: =+S12*75%+S13*25% -> 1077.4154 | T14: =+T12*75%+T13*25% -> 1125.9412 | U14: =+U12*75%+U13*25% -> 1113.0113 | V14: =+V12*75%+V13*25% -> 1135.3485 | W14: =+W12*75%+W13*25% -> 1166.2612 | X14: =+X12*75%+X13*25% -> 1225.9813 | Y14: =+Y12*75%+Y13*25% -> 1272.1962 | ... AD14: =+AD12*75%+AD13*25% -> 1419.8313
B15: Total | C15: =SUM(C9:C14) -> 33.798294 | D15: =SUM(D9:D14) -> 33.798294 | E15: =SUM(E9:E14) -> 39.247607 | F15: =SUM(F9:F14) -> 58.576765 | G15: =SUM(G9:G14) -> 58.021305 | H15: =SUM(H9:H14) -> 69.493542 | K15: Total | L15: =SUM(L9:L14) -> 69.292353 | M15: =SUM(M9:M14) -> 59.893957 | N15: =SUM(N9:N14) -> 68.922074 | O15: =SUM(O9:O14) -> 106.46407 | Q15: Scrap 1% | R15: =+R14*1% -> 10.559819 | S15: =+S14*1% -> 10.774154 | T15: =+T14*1% -> 11.259412 | U15: =+U14*1% -> 11.130113 | V15: =+V14*1% -> 11.353485 | W15: =+W14*1% -> 11.662612 | X15: =+X14*1% -> 12.259813 | Y15: =+Y14*1% -> 12.721963 | ... AD15: =+AD14*1% -> 14.198313
Q16: Precio ponderado con scrap | R16: =+R15+R14 -> 1066.5418 | S16: =+S15+S14 -> 1088.1896 | T16: =+T15+T14 -> 1137.2006 | U16: =+U15+U14 -> 1124.1414 | V16: =+V15+V14 -> 1146.702 | W16: =+W15+W14 -> 1177.9238 | X16: =+X15+X14 -> 1238.2411 | Y16: =+Y15+Y14 -> 1284.9182 | ... AD16: =+AD15+AD14 -> 1434.0296
Q17: Precio facturado Sep-Oct-Nov | R17: =+D5 -> 1434.0296 | S17: =+R17 -> 1434.0296 | T17: =+S17 -> 1434.0296 | U17: =+T17 -> 1434.0296 | V17: =+U17 -> 1434.0296 | W17: =+V17 -> 1434.0296 | X17: =+W17 -> 1434.0296 | Y17: =+X17 -> 1434.0296 | Z17: =+Y17 -> 1434.0296 | ... AD17: =+AC17 -> 1434.0296
M20: Extracto composición del precio base en el contrato
B32: Fórmula

Sheet Octubre18
B3: Costo Resina Virgen | E3: =+AE12 -> 1433.6641 | I3: 0.05
B4: Costo Resina PCR Enkador | E4: =+AE13 -> 1361.9809 | I4: =+E3*I3 -> 71.683207
C5: =+(C9+C10)/C7*1000 -> 1429.9008 | D5: =+(D9+D10)/D7*1000 -> 1429.9008 | E5: =+(E9+E10)/E7*1000 -> 1429.9008 | F5: =+(F9+F10)/F7*1000 -> 1448.0008 | G5: =+(G9+G10)/G7*1000 -> 1429.9008 | H5: =+(H9+H10)/H7*1000 -> 1429.9008
B6: Preformas | C6: 200cc Pony | D6: 330cc Pony | E6: 330cc Pony | F6: 1 Litro Pony | G6: 1 Litro Pony | H6: 1 Litro Pony | K6: Envases | L6: 500ml CG | M6: 500ml SG | N6: 500ml CG | O6: 1000ml SG | Q6: Rubros | R6: IHS julio para precio septiembre | S6: IHS agosto para precio octubre | T6: IHS septiembre para precio noviembre | U6: IHS Octubre para precio Diciembre | V6: IHS Noviembre para precio Enero | W6: IHS Diciembre para precio Febrero | X6: IHS Enero para precio Marzo | Y6: IHS Febrero para precio Abril | Z6: IHS Marzo para precio Mayo | AA6: IHS Abril para precio Junio | AB6: IHS Mayo para precio Julio | AC6: IHS Junio para precio Agosto | AD6: IHS Julio para precio Septiembre | AE6: IHS Agosto para precio Octubre
B7: Gramaje | C7: 16.7 | D7: 16.7 | E7: 20.5 | F7: 30.6 | G7: 30.6 | H7: 38.6 | K7: Gramaje | L7: 20.5 | M7: 15 | N7: 20.5 | O7: 30.6 | Q7: IHS Asia Non Coke approved | R7: 938.13 | S7: 959 | T7: 1006.25 | U7: 993.75 | V7: 1015.5 | W7: 1045.6 | X7: 1103.75 | Y7: 1148.75 | Z7: 1167 | AA7: 1221.25 | AB7: 1330 | AC7: =+'IHS (Mod)'!I5 -> 1280 | AD7: =+'IHS (Mod)'!J5 -> 1279.38 | AE7: 1275.5
B8: Finish | C8: Short | D8: Short | E8: Short | F8: Short | G8: Short | H8: Short | K8: Finish | L8: Short | M8: Short | N8: Short | O8: Short | Q8: Finance | R8: 25.09 | S8: 25.09 | T8: 25.09 | U8: 25 | V8: 25 | W8: 25 | X8: 25 | Y8: 25 | Z8: 25 | AA8: 25 | AB8: 25 | AC8: 33.139726 | AD8: =+Septiembre18!AD8 -> 33.123674 | AE8: =+AH8 -> 33.023219 | AF8: =+AE7*4.5% -> 57.3975 | AG8: =+AF8/365 -> 0.15725342 | AH8: =+AG8*210 -> 33.023219
B9: Resina Virgen | C9: =+(C7*E3/1000)*1.01*75% -> 18.13621 | D9: =+(D7*$E$3/1000)*1.01*75% -> 18.13621 | E9: =+(E7*$E$3/1000)*1.01*75% -> 22.263012 | F9: =+(F7*E3/1000)*1.01 -> 44.308824 | G9: =+(G7*$E$3/1000)*1.01*75% -> 33.231618 | H9: =+(H7*$E$3/1000)*1.01*75% -> 41.919623 | K9: Resina Virgen | L9: =+(L7*E3/1000)*1.005 -> 29.537066 | M9: =+(M7*E3/1000)*1.005*75% -> 16.209365 | N9: =+(N7*E3/1000)*1.005*75% -> 22.152799 | O9: =+(O7*E3/1000)*1.005*75% -> 33.067105 | Q9: Freight China-Gye | R9: 65 | S9: 65 | T9: 65 | U9: 65 | V9: 65 | W9: 65 | X9: 65 | Y9: 65 | Z9: 65 | AA9: 65 | AB9: 65 | AC9: 70 | AD9: 70 | AE9: 70
B10: Resina PCR | C10: =+(C7*$E$4/1000)*1.01*25% -> 5.7431331 | D10: =+(D7*$E$4/1000)*1.01*25% -> 5.7431331 | E10: =+(E7*$E$4/1000)*1.01*25% -> 7.0499538 | F10: 0 | G10: =+(G7*$E$4/1000)*1.01*25% -> 10.523346 | H10: =+(H7*$E$4/1000)*1.01*25% -> 13.274547 | K10: Resina PCR | L10: 0 | M10: =+(M7*E4/1000)*1.005*25% -> 5.1329657 | N10: =+(N7*E4/1000)*1.005*25% -> 7.0150531 | O10: =+(O7*E4/1000)*1.005*25% -> 10.47125 | R10: =SUM(R7:R9) -> 1028.22 | S10: =SUM(S7:S9) -> 1049.09 | T10: =SUM(T7:T9) -> 1096.34 | U10: =SUM(U7:U9) -> 1083.75 | V10: =SUM(V7:V9) -> 1105.5 | W10: =SUM(W7:W9) -> 1135.6 | X10: =SUM(X7:X9) -> 1193.75 | Y10: =SUM(Y7:Y9) -> 1238.75 | ... AE10: =SUM(AE7:AE9) -> 1378.5232
B11: Conversión | C11: 8.2 | D11: 8.2 | E11: 8.2 | F11: 11.15 | G11: 11.15 | H11: 11.15 | K11: Conversión | L11: 27.2 | M11: 27.2 | N11: 27.2 | O11: =11.15+28.25 -> 39.4 | Q11: Landed factor 4% | R11: =+R10*4% -> 41.1288 | S11: =+S10*4% -> 41.9636 | T11: =+T10*4% -> 43.8536 | U11: =+U10*4% -> 43.35 | V11: =+V10*4% -> 44.22 | W11: =+W10*4% -> 45.424 | X11: =+X10*4% -> 47.75 | Y11: =+Y10*4% -> 49.55 | ... AE11: =+AE10*4% -> 55.140929
B12: Pigmento | C12: 1.3 | D12: 1.3 | E12: 1.3 | F12: 2.38 | G12: 2.38 | H12: 2.38 | K12: Pigmento | L12: 1.99 | M12: 0.81 | N12: 1.99 | O12: 2.97 | Q12: Total resin price | R12: =+R11+R10 -> 1069.3488 | S12: =+S11+S10 -> 1091.0536 | T12: =+T11+T10 -> 1140.1936 | U12: =+U11+U10 -> 1127.1 | V12: =+V11+V10 -> 1149.72 | W12: =+W11+W10 -> 1181.024 | X12: =+X11+X10 -> 1241.5 | Y12: =+Y11+Y10 -> 1288.3 | ... AE12: =+AE11+AE10 -> 1433.6641
B13: Empaque | C13: 0.19 | D13: 0.19 | E13: 0.19 | F13: 0.33 | G13: 0.33 | H13: 0.33 | K13: Empaque | L13: 2.71 | M13: 2.71 | N13: 2.71 | O13: 4.44 | Q13: Resin PCR % | R13: =+R12*(1-5%) -> 1015.8814 | S13: =+S12*(1-5%) -> 1036.5009 | T13: =+T12*(1-5%) -> 1083.1839 | U13: =+U12*(1-5%) -> 1070.745 | V13: =+V12*(1-5%) -> 1092.234 | W13: =+W12*(1-5%) -> 1121.9728 | X13: =+X12*(1-5%) -> 1179.425 | Y13: =+Y12*(1-5%) -> 1223.885 | ... AE13: =+AE12*(1-5%) -> 1361.9809
B14: Flete | C14: 0.16 | D14: 0.16 | E14: 0.16 | F14: 0.28 | G14: 0.28 | H14: 0.28 | K14: Flete | L14: 7.77 | M14: 7.77 | N14: 7.77 | O14: 15.99 | Q14: Precio ponderado bajo formuala | R14: =+R12*75%+R13*25% -> 1055.9819 | S14: =+S12*75%+S13*25% -> 1077.4154 | T14: =+T12*75%+T13*25% -> 1125.9412 | U14: =+U12*75%+U13*25% -> 1113.0113 | V14: =+V12*75%+V13*25% -> 1135.3485 | W14: =+W12*75%+W13*25% -> 1166.2612 | X14: =+X12*75%+X13*25% -> 1225.9813 | Y14: =+Y12*75%+Y13*25% -> 1272.1962 | ... AE14: =+AE12*75%+AE13*25% -> 1415.7433
B15: Total | C15: =SUM(C9:C14) -> 33.729343 | D15: =SUM(D9:D14) -> 33.729343 | E15: =SUM(E9:E14) -> 39.162966 | F15: =SUM(F9:F14) -> 58.448824 | G15: =SUM(G9:G14) -> 57.894964 | H15: =SUM(H9:H14) -> 69.33417 | K15: Total | L15: =SUM(L9:L14) -> 69.207066 | M15: =SUM(M9:M14) -> 59.832331 | N15: =SUM(N9:N14) -> 68.837852 | O15: =SUM(O9:O14) -> 106.33836 | Q15: Scrap 1% | R15: =+R14*1% -> 10.559819 | S15: =+S14*1% -> 10.774154 | T15: =+T14*1% -> 11.259412 | U15: =+U14*1% -> 11.130113 | V15: =+V14*1% -> 11.353485 | W15: =+W14*1% -> 11.662612 | X15: =+X14*1% -> 12.259813 | Y15: =+Y14*1% -> 12.721963 | ... AE15: =+AE14*1% -> 14.157433
Q16: Precio ponderado con scrap | R16: =+R15+R14 -> 1066.5418 | S16: =+S15+S14 -> 1088.1896 | T16: =+T15+T14 -> 1137.2006 | U16: =+U15+U14 -> 1124.1414 | V16: =+V15+V14 -> 1146.702 | W16: =+W15+W14 -> 1177.9238 | X16: =+X15+X14 -> 1238.2411 | Y16: =+Y15+Y14 -> 1284.9182 | ... AE16: =+AE15+AE14 -> 1429.9008
Q17: Precio facturado Sep-Oct-Nov | R17: =+D5 -> 1429.9008 | S17: =+R17 -> 1429.9008 | T17: =+S17 -> 1429.9008 | U17: =+T17 -> 1429.9008 | V17: =+U17 -> 1429.9008 | W17: =+V17 -> 1429.9008 | X17: =+W17 -> 1429.9008 | Y17: =+X17 -> 1429.9008 | Z17: =+Y17 -> 1429.9008 | ... AE17: =+AD17 -> 1429.9008
M20: Extracto composición del precio base en el contrato
B32: Fórmula

Sheet Noviembre18
B3: Costo Resina Virgen | E3: =+AF12 -> #REF! | I3: 0.05
B4: Costo Resina PCR Enkador | E4: =+AF13 -> #REF! | I4: =+E3*I3 -> #REF!
C5: =+(C9+C10)/C7*1000 -> #REF! | D5: =+(D9+D10)/D7*1000 -> #REF! | E5: =+(E9+E10)/E7*1000 -> #REF! | F5: =+(F9+F10)/F7*1000 -> #REF! | G5: =+(G9+G10)/G7*1000 -> #REF! | H5: =+(H9+H10)/H7*1000 -> #REF!
B6: Preformas | C6: 200cc Pony | D6: 330cc Pony | E6: 330cc Pony | F6: 1 Litro Pony | G6: 1 Litro Pony | H6: 1 Litro Pony | K6: Envases | L6: 500ml CG | M6: 500ml SG | N6: 500ml CG | O6: 1000ml SG | Q6: Rubros | R6: IHS julio para precio septiembre | S6: IHS agosto para precio octubre | T6: IHS septiembre para precio noviembre | U6: IHS Octubre para precio Diciembre | V6: IHS Noviembre para precio Enero | W6: IHS Diciembre para precio Febrero | X6: IHS Enero para precio Marzo | Y6: IHS Febrero para precio Abril | Z6: IHS Marzo para precio Mayo | AA6: IHS Abril para precio Junio | AB6: IHS Mayo para precio Julio | AC6: IHS Junio para precio Agosto | AD6: IHS Julio para precio Septiembre | AE6: IHS Agosto para precio Octubre | AF6: IHS Septiembre para precio Nov
B7: Gramaje | C7: 16.7 | D7: 16.7 | E7: 20.5 | F7: 30.6 | G7: 30.6 | H7: 38.6 | K7: Gramaje | L7: 20.5 | M7: 15 | N7: 20.5 | O7: 30.6 | Q7: IHS Asia Non Coke approved | R7: 938.13 | S7: 959 | T7: 1006.25 | U7: 993.75 | V7: 1015.5 | W7: 1045.6 | X7: 1103.75 | Y7: 1148.75 | Z7: 1167 | AA7: 1221.25 | AB7: 1330 | AC7: =+'IHS (Mod)'!I5 -> 1280 | AD7: =+'IHS (Mod)'!J5 -> 1279.38 | AE7: 1275.5 | AF7: =+#REF! -> #REF!
B8: Finish | C8: Short | D8: Short | E8: Short | F8: Short | G8: Short | H8: Short | K8: Finish | L8: Short | M8: Short | N8: Short | O8: Short | Q8: Finance | R8: 25.09 | S8: 25.09 | T8: 25.09 | U8: 25 | V8: 25 | W8: 25 | X8: 25 | Y8: 25 | Z8: 25 | AA8: 25 | AB8: 25 | AC8: 33.139726 | AD8: =+Septiembre18!AD8 -> 33.123674 | AE8: 33.023219 | AF8: 33.023219 | AG8: =+AE7*4.5% -> 57.3975 | AH8: =+AG8/365 -> 0.15725342 | AI8: =+AH8*210 -> 33.023219
B9: Resina Virgen | C9: =+(C7*E3/1000)*1.01*75% -> #REF! | D9: =+(D7*$E$3/1000)*1.01*75% -> #REF! | E9: =+(E7*$E$3/1000)*1.01*75% -> #REF! | F9: =+(F7*E3/1000)*1.01 -> #REF! | G9: =+(G7*$E$3/1000)*1.01*75% -> #REF! | H9: =+(H7*$E$3/1000)*1.01*75% -> #REF! | K9: Resina Virgen | L9: =+(L7*E3/1000)*1.005 -> #REF! | M9: =+(M7*E3/1000)*1.005*75% -> #REF! | N9: =+(N7*E3/1000)*1.005*75% -> #REF! | O9: =+(O7*E3/1000)*1.005*75% -> #REF! | Q9: Freight China-Gye | R9: 65 | S9: 65 | T9: 65 | U9: 65 | V9: 65 | W9: 65 | X9: 65 | Y9: 65 | Z9: 65 | AA9: 65 | AB9: 65 | AC9: 70 | AD9: 70 | AE9: 70 | AF9: 70
B10: Resina PCR | C10: =+(C7*$E$4/1000)*1.01*25% -> #REF! | D10: =+(D7*$E$4/1000)*1.01*25% -> #REF! | E10: =+(E7*$E$4/1000)*1.01*25% -> #REF! | F10: 0 | G10: =+(G7*$E$4/1000)*1.01*25% -> #REF! | H10: =+(H7*$E$4/1000)*1.01*25% -> #REF! | K10: Resina PCR | L10: 0 | M10: =+(M7*E4/1000)*1.005*25% -> #REF! | N10: =+(N7*E4/1000)*1.005*25% -> #REF! | O10: =+(O7*E4/1000)*1.005*25% -> #REF! | R10: =SUM(R7:R9) -> 1028.22 | S10: =SUM(S7:S9) -> 1049.09 | T10: =SUM(T7:T9) -> 1096.34 | U10: =SUM(U7:U9) -> 1083.75 | V10: =SUM(V7:V9) -> 1105.5 | W10: =SUM(W7:W9) -> 1135.6 | X10: =SUM(X7:X9) -> 1193.75 | Y10: =SUM(Y7:Y9) -> 1238.75 | ... AF10: =SUM(AF7:AF9) -> #REF!
B11: Conversión | C11: 8.2 | D11: 8.2 | E11: 8.2 | F11: 11.15 | G11: 11.15 | H11: 11.15 | K11: Conversión | L11: 27.2 | M11: 27.2 | N11: 27.2 | O11: =11.15+28.25 -> 39.4 | Q11: Landed factor 4% | R11: =+R10*4% -> 41.1288 | S11: =+S10*4% -> 41.9636 | T11: =+T10*4% -> 43.8536 | U11: =+U10*4% -> 43.35 | V11: =+V10*4% -> 44.22 | W11: =+W10*4% -> 45.424 | X11: =+X10*4% -> 47.75 | Y11: =+Y10*4% -> 49.55 | ... AF11: =+AF10*4% -> #REF!
B12: Pigmento | C12: 1.3 | D12: 1.3 | E12: 1.3 | F12: 2.38 | G12: 2.38 | H12: 2.38 | K12: Pigmento | L12: 1.99 | M12: 0.81 | N12: 1.99 | O12: 2.97 | Q12: Total resin price | R12: =+R11+R10 -> 1069.3488 | S12: =+S11+S10 -> 1091.0536 | T12: =+T11+T10 -> 1140.1936 | U12: =+U11+U10 -> 1127.1 | V12: =+V11+V10 -> 1149.72 | W12: =+W11+W10 -> 1181.024 | X12: =+X11+X10 -> 1241.5 | Y12: =+Y11+Y10 -> 1288.3 | ... AF12: =+AF11+AF10 -> #REF!
B13: Empaque | C13: 0.19 | D13: 0.19 | E13: 0.19 | F13: 0.33 | G13: 0.33 | H13: 0.33 | K13: Empaque | L13: 2.71 | M13: 2.71 | N13: 2.71 | O13: 4.44 | Q13: Resin PCR % | R13: =+R12*(1-5%) -> 1015.8814 | S13: =+S12*(1-5%) -> 1036.5009 | T13: =+T12*(1-5%) -> 1083.1839 | U13: =+U12*(1-5%) -> 1070.745 | V13: =+V12*(1-5%) -> 1092.234 | W13: =+W12*(1-5%) -> 1121.9728 | X13: =+X12*(1-5%) -> 1179.425 | Y13: =+Y12*(1-5%) -> 1223.885 | ... AF13: =+AF12*(1-5%) -> #REF!
B14: Flete | C14: 0.16 | D14: 0.16 | E14: 0.16 | F14: 0.28 | G14: 0.28 | H14: 0.28 | K14: Flete | L14: 7.77 | M14: 7.77 | N14: 7.77 | O14: 15.99 | Q14: Precio ponderado bajo formuala | R14: =+R12*75%+R13*25% -> 1055.9819 | S14: =+S12*75%+S13*25% -> 1077.4154 | T14: =+T12*75%+T13*25% -> 1125.9412 | U14: =+U12*75%+U13*25% -> 1113.0113 | V14: =+V12*75%+V13*25% -> 1135.3485 | W14: =+W12*75%+W13*25% -> 1166.2612 | X14: =+X12*75%+X13*25% -> 1225.9813 | Y14: =+Y12*75%+Y13*25% -> 1272.1962 | ... AF14: =+AF12*75%+AF13*25% -> #REF!
B15: Total | C15: =SUM(C9:C14) -> #REF! | D15: =SUM(D9:D14) -> #REF! | E15: =SUM(E9:E14) -> #REF! | F15: =SUM(F9:F14) -> #REF! | G15: =SUM(G9:G14) -> #REF! | H15: =SUM(H9:H14) -> #REF! | K15: Total | L15: =SUM(L9:L14) -> #REF! | M15: =SUM(M9:M14) -> #REF! | N15: =SUM(N9:N14) -> #REF! | O15: =SUM(O9:O14) -> #REF! | Q15: Scrap 1% | R15: =+R14*1% -> 10.559819 | S15: =+S14*1% -> 10.774154 | T15: =+T14*1% -> 11.259412 | U15: =+U14*1% -> 11.130113 | V15: =+V14*1% -> 11.353485 | W15: =+W14*1% -> 11.662612 | X15: =+X14*1% -> 12.259813 | Y15: =+Y14*1% -> 12.721963 | ... AF15: =+AF14*1% -> #REF!
Q16: Precio ponderado con scrap | R16: =+R15+R14 -> 1066.5418 | S16: =+S15+S14 -> 1088.1896 | T16: =+T15+T14 -> 1137.2006 | U16: =+U15+U14 -> 1124.1414 | V16: =+V15+V14 -> 1146.702 | W16: =+W15+W14 -> 1177.9238 | X16: =+X15+X14 -> 1238.2411 | Y16: =+Y15+Y14 -> 1284.9182 | ... AF16: =+AF15+AF14 -> #REF!
Q17: Precio facturado Sep-Oct-Nov | R17: =+D5 -> #REF! | S17: =+R17 -> #REF! | T17: =+S17 -> #REF! | U17: =+T17 -> #REF! | V17: =+U17 -> #REF! | W17: =+V17 -> #REF! | X17: =+W17 -> #REF! | Y17: =+X17 -> #REF! | Z17: =+Y17 -> #REF! | ... AF17: =+AE17 -> #REF!
M20: Extracto composición del precio base en el contrato
B32: Fórmula

Sheet Diciembre18
B3: Costo Resina Virgen | E3: =+AG12 -> #REF! | I3: 0.05
B4: Costo Resina PCR Enkador | E4: =+AG13 -> #REF! | I4: =+E3*I3 -> #REF!
C5: =+(C9+C10)/C7*1000 -> #REF! | D5: =+(D9+D10)/D7*1000 -> #REF! | E5: =+(E9+E10)/E7*1000 -> #REF! | F5: =+(F9+F10)/F7*1000 -> #REF! | G5: =+(G9+G10)/G7*1000 -> #REF! | H5: =+(H9+H10)/H7*1000 -> #REF!
B6: Preformas | C6: 200cc Pony | D6: 330cc Pony | E6: 330cc Pony | F6: 1 Litro Pony | G6: 1 Litro Pony | H6: 1 Litro Pony | K6: Envases | L6: 500ml CG | M6: 500ml SG | N6: 500ml CG | O6: 1000ml SG | Q6: Rubros | R6: IHS julio para precio septiembre | S6: IHS agosto para precio octubre | T6: IHS septiembre para precio noviembre | U6: IHS Octubre para precio Diciembre | V6: IHS Noviembre para precio Enero | W6: IHS Diciembre para precio Febrero | X6: IHS Enero para precio Marzo | Y6: IHS Febrero para precio Abril | Z6: IHS Marzo para precio Mayo | AA6: IHS Abril para precio Junio | AB6: IHS Mayo para precio Julio | AC6: IHS Junio para precio Agosto | AD6: IHS Julio para precio Septiembre | AE6: IHS Agosto para precio Octubre | AF6: IHS Septiembre para precio Nov | AG6: IHS Octubre para precio Dic
B7: Gramaje | C7: 16.7 | D7: 16.7 | E7: 20.5 | F7: 30.6 | G7: 30.6 | H7: 38.6 | K7: Gramaje | L7: 20.5 | M7: 15 | N7: 20.5 | O7: 30.6 | Q7: IHS Asia Non Coke approved | R7: 938.13 | S7: 959 | T7: 1006.25 | U7: 993.75 | V7: 1015.5 | W7: 1045.6 | X7: 1103.75 | Y7: 1148.75 | Z7: 1167 | AA7: 1221.25 | AB7: 1330 | AC7: =+'IHS (Mod)'!I5 -> 1280 | AD7: =+'IHS (Mod)'!J5 -> 1279.38 | AE7: 1275.5 | AF7: =+#REF! -> #REF! | AG7: =+#REF! -> #REF!
B8: Finish | C8: Short | D8: Short | E8: Short | F8: Short | G8: Short | H8: Short | K8: Finish | L8: Short | M8: Short | N8: Short | O8: Short | Q8: Finance | R8: 25.09 | S8: 25.09 | T8: 25.09 | U8: 25 | V8: 25 | W8: 25 | X8: 25 | Y8: 25 | Z8: 25 | AA8: 25 | AB8: 25 | AC8: 33.139726 | AD8: =+Septiembre18!AD8 -> 33.123674 | AE8: 33.023219 | AF8: 33.023219 | AG8: =+AJ8 -> #REF! | AH8: =+AG7*4.5% -> #REF! | AI8: =+AH8/365 -> #REF! | AJ8: =+AI8*210 -> #REF!
B9: Resina Virgen | C9: =+(C7*E3/1000)*1.01*75% -> #REF! | D9: =+(D7*$E$3/1000)*1.01*75% -> #REF! | E9: =+(E7*$E$3/1000)*1.01*75% -> #REF! | F9: =+(F7*E3/1000)*1.01 -> #REF! | G9: =+(G7*$E$3/1000)*1.01*75% -> #REF! | H9: =+(H7*$E$3/1000)*1.01*75% -> #REF! | K9: Resina Virgen | L9: =+(L7*E3/1000)*1.005 -> #REF! | M9: =+(M7*E3/1000)*1.005*75% -> #REF! | N9: =+(N7*E3/1000)*1.005*75% -> #REF! | O9: =+(O7*E3/1000)*1.005*75% -> #REF! | Q9: Freight China-Gye | R9: 65 | S9: 65 | T9: 65 | U9: 65 | V9: 65 | W9: 65 | X9: 65 | Y9: 65 | Z9: 65 | AA9: 65 | AB9: 65 | AC9: 70 | AD9: 70 | AE9: 70 | AF9: 70 | AG9: 70
B10: Resina PCR | C10: =+(C7*$E$4/1000)*1.01*25% -> #REF! | D10: =+(D7*$E$4/1000)*1.01*25% -> #REF! | E10: =+(E7*$E$4/1000)*1.01*25% -> #REF! | F10: 0 | G10: =+(G7*$E$4/1000)*1.01*25% -> #REF! | H10: =+(H7*$E$4/1000)*1.01*25% -> #REF! | K10: Resina PCR | L10: 0 | M10: =+(M7*E4/1000)*1.005*25% -> #REF! | N10: =+(N7*E4/1000)*1.005*25% -> #REF! | O10: =+(O7*E4/1000)*1.005*25% -> #REF! | R10: =SUM(R7:R9) -> 1028.22 | S10: =SUM(S7:S9) -> 1049.09 | T10: =SUM(T7:T9) -> 1096.34 | U10: =SUM(U7:U9) -> 1083.75 | V10: =SUM(V7:V9) -> 1105.5 | W10: =SUM(W7:W9) -> 1135.6 | X10: =SUM(X7:X9) -> 1193.75 | Y10: =SUM(Y7:Y9) -> 1238.75 | ... AG10: =SUM(AG7:AG9) -> #REF!
B11: Conversión | C11: 8.2 | D11: 8.2 | E11: 8.2 | F11: 11.15 | G11: 11.15 | H11: 11.15 | K11: Conversión | L11: 27.2 | M11: 27.2 | N11: 27.2 | O11: =11.15+28.25 -> 39.4 | Q11: Landed factor 4% | R11: =+R10*4% -> 41.1288 | S11: =+S10*4% -> 41.9636 | T11: =+T10*4% -> 43.8536 | U11: =+U10*4% -> 43.35 | V11: =+V10*4% -> 44.22 | W11: =+W10*4% -> 45.424 | X11: =+X10*4% -> 47.75 | Y11: =+Y10*4% -> 49.55 | ... AG11: =+AG10*4% -> #REF!
B12: Pigmento | C12: 1.3 | D12: 1.3 | E12: 1.3 | F12: 2.38 | G12: 2.38 | H12: 2.38 | K12: Pigmento | L12: 1.99 | M12: 0.81 | N12: 1.99 | O12: 2.97 | Q12: Total resin price | R12: =+R11+R10 -> 1069.3488 | S12: =+S11+S10 -> 1091.0536 | T12: =+T11+T10 -> 1140.1936 | U12: =+U11+U10 -> 1127.1 | V12: =+V11+V10 -> 1149.72 | W12: =+W11+W10 -> 1181.024 | X12: =+X11+X10 -> 1241.5 | Y12: =+Y11+Y10 -> 1288.3 | ... AG12: =+AG11+AG10 -> #REF!
B13: Empaque | C13: 0.19 | D13: 0.19 | E13: 0.19 | F13: 0.33 | G13: 0.33 | H13: 0.33 | K13: Empaque | L13: 2.71 | M13: 2.71 | N13: 2.71 | O13: 4.44 | Q13: Resin PCR % | R13: =+R12*(1-5%) -> 1015.8814 | S13: =+S12*(1-5%) -> 1036.5009 | T13: =+T12*(1-5%) -> 1083.1839 | U13: =+U12*(1-5%) -> 1070.745 | V13: =+V12*(1-5%) -> 1092.234 | W13: =+W12*(1-5%) -> 1121.9728 | X13: =+X12*(1-5%) -> 1179.425 | Y13: =+Y12*(1-5%) -> 1223.885 | ... AG13: =+AG12*(1-5%) -> #REF!
B14: Flete | C14: 0.16 | D14: 0.16 | E14: 0.16 | F14: 0.28 | G14: 0.28 | H14: 0.28 | K14: Flete | L14: 7.77 | M14: 7.77 | N14: 7.77 | O14: 15.99 | Q14: Precio ponderado bajo formuala | R14: =+R12*75%+R13*25% -> 1055.9819 | S14: =+S12*75%+S13*25% -> 1077.4154 | T14: =+T12*75%+T13*25% -> 1125.9412 | U14: =+U12*75%+U13*25% -> 1113.0113 | V14: =+V12*75%+V13*25% -> 1135.3485 | W14: =+W12*75%+W13*25% -> 1166.2612 | X14: =+X12*75%+X13*25% -> 1225.9813 | Y14: =+Y12*75%+Y13*25% -> 1272.1962 | ... AG14: =+AG12*75%+AG13*25% -> #REF!
B15: Total | C15: =SUM(C9:C14) -> #REF! | D15: =SUM(D9:D14) -> #REF! | E15: =SUM(E9:E14) -> #REF! | F15: =SUM(F9:F14) -> #REF! | G15: =SUM(G9:G14) -> #REF! | H15: =SUM(H9:H14) -> #REF! | K15: Total | L15: =SUM(L9:L14) -> #REF! | M15: =SUM(M9:M14) -> #REF! | N15: =SUM(N9:N14) -> #REF! | O15: =SUM(O9:O14) -> #REF! | Q15: Scrap 1% | R15: =+R14*1% -> 10.559819 | S15: =+S14*1% -> 10.774154 | T15: =+T14*1% -> 11.259412 | U15: =+U14*1% -> 11.130113 | V15: =+V14*1% -> 11.353485 | W15: =+W14*1% -> 11.662612 | X15: =+X14*1% -> 12.259813 | Y15: =+Y14*1% -> 12.721963 | ... AG15: =+AG14*1% -> #REF!
Q16: Precio ponderado con scrap | R16: =+R15+R14 -> 1066.5418 | S16: =+S15+S14 -> 1088.1896 | T16: =+T15+T14 -> 1137.2006 | U16: =+U15+U14 -> 1124.1414 | V16: =+V15+V14 -> 1146.702 | W16: =+W15+W14 -> 1177.9238 | X16: =+X15+X14 -> 1238.2411 | Y16: =+Y15+Y14 -> 1284.9182 | ... AG16: =+AG15+AG14 -> #REF!
Q17: Precio facturado Sep-Oct-Nov | R17: =+D5 -> #REF! | S17: =+R17 -> #REF! | T17: =+S17 -> #REF! | U17: =+T17 -> #REF! | V17: =+U17 -> #REF! | W17: =+V17 -> #REF! | X17: =+W17 -> #REF! | Y17: =+X17 -> #REF! | Z17: =+Y17 -> #REF! | ... AG17: =+AF17 -> #REF!
M20: Extracto composición del precio base en el contrato
B32: Fórmula

Sheet Precios facturados
B2: Costo de Resina Virgen Actual | E2: =+D26 -> 1055 | F2: 0.05 | H2: Costo de Resina Virgen Actual | J2: =+D26 -> 1055
B3: Costo de Resina PCR Actual (Enkador) | E3: =+E2-F3 -> 1002.25 | F3: =+E2*F2 -> 52.75 | H3: Costo de Resina PCR Actual | J3: 0
B5: Preformas | H5: Manantial | I5: 500ml SG | J5: 500ml CG
B6: Gramaje | C6: 15.6 | D6: 16.7 | E6: 30.6 | H6: Gramaje | I6: 15 | J6: 20.5
B7: Finish | C7: Short | D7: Short | E7: Short | H7: Finish | I7: Short | J7: Short
B8: Resina Virgen | C8: =+(C6*E2/1000)*1.01*75% -> 12.466935 | D8: =+(D6*$E$2/1000)*1.01*75%-0.01 -> 13.336014 | E8: =+(E6*E2/1000)*1.01 -> 32.60583 | H8: Resina Virgen | I8: =+(I6*J2/1000)*1.005-0.004 -> 15.900125 | J8: =+(J6*J2/1000)*1.005+0.007 -> 21.742638
B9: Resina PCR | C9: =+(C6*$E$3/1000)*1.01*25% -> 3.9478628 | D9: =+(D6*$E$3/1000)*1.01*25% -> 4.2262377 | E9: 0 | H9: Resina PCR | I9: 0 | J9: 0
B10: Nueva Conversion | C10: =C35 -> 13.806909 | D10: =D35 -> 13.806909 | E10: =E35 -> 16.175542 | H10: Conversión | I10: =I35 -> 28.109813 | J10: =J35 -> 28.109813
B11: Recargo por Penalidad y energ | C11: 0 | D11: 0 | E11: 0 | H11: Recargo por Penalidad e incr | I11: 0 | J11: 0
B12: Pigmento | C12: 1.635 | D12: 1.7575 | E12: 2.97 | H12: Pigmento | I12: 1.4 | J12: 2
B13: Empaque | C13: 0.20356 | D13: 0.20356 | E13: 0.284984 | H13: Empaque | I13: 1.27 | J13: 1.27225
B14: Flete | C14: 0.15 | D14: 0.15 | E14: 0.213738 | H14: Flete | I14: 8.34 | J14: 8.335782
B15: Total | C15: =SUM(C8:C14) -> 32.210266 | D15: =SUM(D8:D14) -> 33.48022 | E15: =SUM(E8:E14) -> 52.250094 | H15: Total | I15: =SUM(I8:I14) -> 55.019938 | J15: =SUM(J8:J14) -> 61.460483
B18: Toneladas | C18: Precio | D18: Total
B19: 110 | C19: =D19/B19 -> 995 | D19: 109450
B20: 44 | C20: =D20/B20 -> 995 | D20: 43780
B21: =SUM(B19:B20) -> 154 | C21: =SUM(C19:C20) -> 1990 | D21: =SUM(D19:D20) -> 153230
B24: Promedio Ponderado | D24: =+D21/B21 -> 995
B25: Gastos + Transporte + Almacenaje | D25: 60
B26: Total | D26: =+D25+D24 -> 1055
B29: Preformas | H29: Manantial | I29: 500ml SG | J29: 500ml CG
B30: Gramaje | C30: 15.6 | D30: 16.7 | E30: 30.6 | H30: Gramaje | I30: 15 | J30: 20.5
B31: Conversion Base | C31: 13.64 | D31: 13.64 | E31: 15.98 | H31: Conversión | I31: 27.77 | J31: 27.77
B32: % de Energia en MOR | C32: 0.23 | D32: 0.23 | E32: 0.23 | I32: 0.23 | J32: 0.23
B33: % Incremento Energia | C33: =0.097/0.0921-1 -> 0.05320304 | D33: =0.097/0.0921-1 -> 0.05320304 | E33: =0.097/0.0921-1 -> 0.05320304 | I33: =0.097/0.0921-1 -> 0.05320304 | J33: =0.097/0.0921-1 -> 0.05320304
B34: Incremento de energia | C34: =C31*C32*C33 -> 0.16690858 | D34: =D31*D32*D33 -> 0.16690858 | E34: =E31*E32*E33 -> 0.19554245 | I34: =I31*I32*I33 -> 0.33981314 | J34: =J31*J32*J33 -> 0.33981314
B35: Nueva Conversion | C35: =C31+C34 -> 13.806909 | D35: =D31+D34 -> 13.806909 | E35: =E31+E34 -> 16.175542 | I35: =I31+I34 -> 28.109813 | J35: =J31+J34 -> 28.109813

Sheet IHS (Mod)
A1: Frequency: Monthly | G1: Fecha: | H1: 43310
A2: I H S Polyethylene Terephthalate (PET), Bottle Resin, (not Coke approved), Spot, FOB NE Asia, US$ per Metric Ton
A4: 43009 | B4: 43040 | C4: 43070 | D4: 43101 | E4: 43132 | F4: 43160 | G4: 43191 | H4: 43221 | I4: 43252 | J4: 43282 | K4: 43313
A5: 993.75 | B5: 1015.5 | C5: 1045630005 | D5: 1103.75 | E5: 1148.75 | F5: 1167 | G5: 1221.25 | H5: 1330 | I5: 1280 | J5: 1279.38 | K5: 1250
H6: Archivo DP | I6: 1339.38 | J6: Revisar

Sheet Enero19
B3: Costo Resina Virgen | E3: =+AH12 -> #REF! | I3: 0.05
B4: Costo Resina PCR Enkador | E4: =+AH13 -> #REF! | I4: =+E3*I3 -> #REF!
C5: =+(C9+C10)/C7*1000 -> #REF! | D5: =+(D9+D10)/D7*1000 -> #REF! | E5: =+(E9+E10)/E7*1000 -> #REF! | F5: =+(F9+F10)/F7*1000 -> #REF! | G5: =+(G9+G10)/G7*1000 -> #REF! | H5: =+(H9+H10)/H7*1000 -> #REF!
B6: Preformas | C6: 200cc Pony | D6: 330cc Pony | E6: 330cc Pony | F6: 1 Litro Pony | G6: 1 Litro Pony | H6: 1 Litro Pony | K6: Envases | L6: 500ml CG | M6: 500ml SG | N6: 500ml CG | O6: 1000ml SG | Q6: Rubros | R6: IHS julio para precio septiembre | S6: IHS agosto para precio octubre | T6: IHS septiembre para precio noviembre | U6: IHS Octubre para precio Diciembre | V6: IHS Noviembre para precio Enero | W6: IHS Diciembre para precio Febrero | X6: IHS Enero para precio Marzo | Y6: IHS Febrero para precio Abril | Z6: IHS Marzo para precio Mayo | AA6: IHS Abril para precio Junio | AB6: IHS Mayo para precio Julio | AC6: IHS Junio para precio Agosto | AD6: IHS Julio para precio Septiembre | AE6: IHS Agosto para precio Octubre | AF6: IHS Septiembre para precio Nov | AG6: IHS Octubre para precio Dic | AH6: IHS Noviembre para precio Enero
B7: Gramaje | C7: 16.7 | D7: 16.7 | E7: 20.5 | F7: 30.6 | G7: 30.6 | H7: 38.6 | K7: Gramaje | L7: 20.5 | M7: 15 | N7: 20.5 | O7: 30.6 | Q7: IHS Asia Non Coke approved | R7: 938.13 | S7: 959 | T7: 1006.25 | U7: 993.75 | V7: 1015.5 | W7: 1045.6 | X7: 1103.75 | Y7: 1148.75 | Z7: 1167 | AA7: 1221.25 | AB7: 1330 | AC7: =+'IHS (Mod)'!I5 -> 1280 | AD7: =+'IHS (Mod)'!J5 -> 1279.38 | AE7: 1275.5 | AF7: =+#REF! -> #REF! | AG7: =+#REF! -> #REF! | AH7: =+#REF! -> #REF!
B8: Finish | C8: Short | D8: Short | E8: Short | F8: Short | G8: Short | H8: Short | K8: Finish | L8: Short | M8: Short | N8: Short | O8: Short | Q8: Finance | R8: 25.09 | S8: 25.09 | T8: 25.09 | U8: 25 | V8: 25 | W8: 25 | X8: 25 | Y8: 25 | Z8: 25 | AA8: 25 | AB8: 25 | AC8: 33.139726 | AD8: =+Septiembre18!AD8 -> 33.123674 | AE8: 33.023219 | AF8: 33.023219 | AG8: 32.783733 | AH8: =+AK8 -> #REF! | AI8: =+AH7*4.5% -> #REF! | AJ8: =+AI8/365 -> #REF! | AK8: =+AJ8*210 -> #REF!
B9: Resina Virgen | C9: =+(C7*E3/1000)*1.01*75% -> #REF! | D9: =+(D7*$E$3/1000)*1.01*75% -> #REF! | E9: =+(E7*$E$3/1000)*1.01*50% -> #REF! | F9: =+(F7*E3/1000)*1.01 -> #REF! | G9: =+(G7*$E$3/1000)*1.01*75% -> #REF! | H9: =+(H7*$E$3/1000)*1.01*50% -> #REF! | K9: Resina Virgen | L9: =+(L7*E3/1000)*1.005 -> #REF! | M9: =+(M7*E3/1000)*1.005*75% -> #REF! | N9: =+(N7*E3/1000)*1.005*75% -> #REF! | O9: =+(O7*E3/1000)*1.005*75% -> #REF! | Q9: Freight China-Gye | R9: 65 | S9: 65 | T9: 65 | U9: 65 | V9: 65 | W9: 65 | X9: 65 | Y9: 65 | Z9: 65 | AA9: 65 | AB9: 65 | AC9: 70 | AD9: 70 | AE9: 70 | AF9: 70 | AG9: 70 | AH9: 70
B10: Resina PCR | C10: =+(C7*$E$4/1000)*1.01*25% -> #REF! | D10: =+(D7*$E$4/1000)*1.01*25% -> #REF! | E10: =+(E7*$E$4/1000)*1.01*50% -> #REF! | F10: 0 | G10: =+(G7*$E$4/1000)*1.01*25% -> #REF! | H10: =+(H7*$E$4/1000)*1.01*50% -> #REF! | K10: Resina PCR | L10: 0 | M10: =+(M7*E4/1000)*1.005*25% -> #REF! | N10: =+(N7*E4/1000)*1.005*25% -> #REF! | O10: =+(O7*E4/1000)*1.005*25% -> #REF! | R10: =SUM(R7:R9) -> 1028.22 | S10: =SUM(S7:S9) -> 1049.09 | T10: =SUM(T7:T9) -> 1096.34 | U10: =SUM(U7:U9) -> 1083.75 | V10: =SUM(V7:V9) -> 1105.5 | W10: =SUM(W7:W9) -> 1135.6 | X10: =SUM(X7:X9) -> 1193.75 | Y10: =SUM(Y7:Y9) -> 1238.75 | ... AH10: =SUM(AH7:AH9) -> #REF!
B11: Conversión | C11: 8.2 | D11: 8.2 | E11: 8.2 | F11: 11.15 | G11: 11.15 | H11: 11.15 | K11: Conversión | L11: 27.2 | M11: 27.2 | N11: 27.2 | O11: =11.15+28.25 -> 39.4 | Q11: Landed factor 4% | R11: =+R10*4% -> 41.1288 | S11: =+S10*4% -> 41.9636 | T11: =+T10*4% -> 43.8536 | U11: =+U10*4% -> 43.35 | V11: =+V10*4% -> 44.22 | W11: =+W10*4% -> 45.424 | X11: =+X10*4% -> 47.75 | Y11: =+Y10*4% -> 49.55 | ... AH11: =+AH10*4% -> #REF!
B12: Pigmento | C12: 1.3 | D12: 1.3 | E12: 1.3 | F12: 2.38 | G12: 2.38 | H12: 2.38 | K12: Pigmento | L12: 1.99 | M12: 0.81 | N12: 1.99 | O12: 2.97 | Q12: Total resin price | R12: =+R11+R10 -> 1069.3488 | S12: =+S11+S10 -> 1091.0536 | T12: =+T11+T10 -> 1140.1936 | U12: =+U11+U10 -> 1127.1 | V12: =+V11+V10 -> 1149.72 | W12: =+W11+W10 -> 1181.024 | X12: =+X11+X10 -> 1241.5 | Y12: =+Y11+Y10 -> 1288.3 | ... AH12: =+AH11+AH10 -> #REF!
B13: Empaque | C13: 0.19 | D13: 0.19 | E13: 0.19 | F13: 0.33 | G13: 0.33 | H13: 0.33 | K13: Empaque | L13: 2.71 | M13: 2.71 | N13: 2.71 | O13: 4.44 | Q13: Resin PCR % | R13: =+R12*(1-5%) -> 1015.8814 | S13: =+S12*(1-5%) -> 1036.5009 | T13: =+T12*(1-5%) -> 1083.1839 | U13: =+U12*(1-5%) -> 1070.745 | V13: =+V12*(1-5%) -> 1092.234 | W13: =+W12*(1-5%) -> 1121.9728 | X13: =+X12*(1-5%) -> 1179.425 | Y13: =+Y12*(1-5%) -> 1223.885 | ... AH13: =+AH12*(1-5%) -> #REF!
B14: Flete | C14: 0.16 | D14: 0.16 | E14: 0.16 | F14: 0.28 | G14: 0.28 | H14: 0.28 | K14: Flete | L14: 7.77 | M14: 7.77 | N14: 7.77 | O14: 15.99 | Q14: Precio ponderado bajo formuala | R14: =+R12*75%+R13*25% -> 1055.9819 | S14: =+S12*75%+S13*25% -> 1077.4154 | T14: =+T12*75%+T13*25% -> 1125.9412 | U14: =+U12*75%+U13*25% -> 1113.0113 | V14: =+V12*75%+V13*25% -> 1135.3485 | W14: =+W12*75%+W13*25% -> 1166.2612 | X14: =+X12*75%+X13*25% -> 1225.9813 | Y14: =+Y12*75%+Y13*25% -> 1272.1962 | ... AH14: =+AH12*75%+AH13*25% -> #REF!
B15: Total | C15: =SUM(C9:C14) -> #REF! | D15: =SUM(D9:D14) -> #REF! | E15: =SUM(E9:E14) -> #REF! | F15: =SUM(F9:F14) -> #REF! | G15: =SUM(G9:G14) -> #REF! | H15: =SUM(H9:H14) -> #REF! | K15: Total | L15: =SUM(L9:L14) -> #REF! | M15: =SUM(M9:M14) -> #REF! | N15: =SUM(N9:N14) -> #REF! | O15: =SUM(O9:O14) -> #REF! | Q15: Scrap 1% | R15: =+R14*1% -> 10.559819 | S15: =+S14*1% -> 10.774154 | T15: =+T14*1% -> 11.259412 | U15: =+U14*1% -> 11.130113 | V15: =+V14*1% -> 11.353485 | W15: =+W14*1% -> 11.662612 | X15: =+X14*1% -> 12.259813 | Y15: =+Y14*1% -> 12.721963 | ... AH15: =+AH14*1% -> #REF!
Q16: Precio ponderado con scrap | R16: =+R15+R14 -> 1066.5418 | S16: =+S15+S14 -> 1088.1896 | T16: =+T15+T14 -> 1137.2006 | U16: =+U15+U14 -> 1124.1414 | V16: =+V15+V14 -> 1146.702 | W16: =+W15+W14 -> 1177.9238 | X16: =+X15+X14 -> 1238.2411 | Y16: =+Y15+Y14 -> 1284.9182 | ... AH16: =+AH15+AH14 -> #REF!
Q17: Precio facturado Sep-Oct-Nov | R17: =+D5 -> #REF! | S17: =+R17 -> #REF! | T17: =+S17 -> #REF! | U17: =+T17 -> #REF! | V17: =+U17 -> #REF! | W17: =+V17 -> #REF! | X17: =+W17 -> #REF! | Y17: =+X17 -> #REF! | Z17: =+Y17 -> #REF! | ... AG17: =+AF17 -> #REF!
M20: Extracto composición del precio base en el contrato
B32: Fórmula

Sheet Feb19
B2: Costo Resina Virgen | E2: =+AH11 -> #REF! | I2: 0.05
B3: Costo Resina PCR Enkador | E3: =+AH12 -> #REF! | I3: =+E2*I2 -> #REF!
C4: =+(C9+C10)/C6*1000 -> #REF! | D4: =+(D9+D10)/D6*1000 -> #REF! | E4: =+(E9+E10)/E6*1000 -> #REF! | F4: =+(F9+F10)/F6*1000 -> #REF! | G4: =+(G9+G10)/G6*1000 -> #REF! | H4: =+(H9+H10)/H6*1000 -> #REF!
B5: Preformas | C5: 200cc Pony | D5: 330cc Pony | E5: 330cc Pony | F5: 1 Litro Pony | G5: 1 Litro Pony | H5: 1 Litro Pony | K5: Envases | L5: 500ml SG | M5: 500ml CG | N5: 500ml CG | P5: Rubros | Q5: IHS julio para precio septiembre | R5: IHS agosto para precio octubre | S5: IHS septiembre para precio noviembre | T5: IHS Octubre para precio Diciembre | U5: IHS Noviembre para precio Enero | V5: IHS Diciembre para precio Febrero | W5: IHS Enero para precio Marzo | X5: IHS Febrero para precio Abril | Y5: IHS Marzo para precio Mayo | Z5: IHS Abril para precio Junio | AA5: IHS Mayo para precio Julio | AB5: IHS Junio para precio Agosto | AC5: IHS Julio para precio Septiembre | AD5: IHS Agosto para precio Octubre | AE5: IHS Septiembre para precio Nov | AF5: IHS Octubre para precio Dic | AG5: IHS Noviembre para precio Enero | AH5: IHS Diciembre para precio Febrero
B6: Gramaje | C6: 16.7 | D6: 16.7 | E6: 20.6 | F6: 30.6 | G6: 30.6 | H6: 38.6 | K6: Gramaje | L6: 15 | M6: 20.5 | N6: 20.5 | P6: IHS Asia Non Coke approved | Q6: 938.13 | R6: 959 | S6: 1006.25 | T6: 993.75 | U6: 1015.5 | V6: 1045.6 | W6: 1103.75 | X6: 1148.75 | Y6: 1167 | Z6: 1221.25 | AA6: 1330 | AB6: =+'IHS (Mod)'!I5 -> 1280 | AC6: =+'IHS (Mod)'!J5 -> 1279.38 | AD6: 1275.5 | AE6: =+#REF! -> #REF! | AF6: =+#REF! -> #REF! | AG6: =+#REF! -> #REF! | AH6: =+#REF! -> #REF!
B7: Finish | C7: Short | D7: Short | E7: Short | F7: Short | G7: Short | H7: Short | K7: Finish | L7: Short | M7: Short | N7: Short | P7: Finance | Q7: 25.09 | R7: 25.09 | S7: 25.09 | T7: 25 | U7: 25 | V7: 25 | W7: 25 | X7: 25 | Y7: 25 | Z7: 25 | AA7: 25 | AB7: 33.139726 | AC7: =+Septiembre18!AD8 -> 33.123674 | AD7: 33.023219 | AE7: 33.023219 | AF7: 32.783733 | AG7: 29.126712 | AH7: =+AK7 -> #REF! | AI7: =+AH6*4.5% -> #REF! | AJ7: =+AI7/365 -> #REF! | AK7: =+AJ7*210 -> #REF!
B8: % Resina (Virgen/PCR) | C8: 50% - 50% | D8: 75% - 25% | E8: 50% - 50% | F8: 1 | G8: 75% - 25% | H8: 50% - 50% | K8: =+B8 -> % Resina (Virgen/PCR) | L8: 75% - 25% | M8: 1 | N8: 75% - 25% | P8: Freight China-Gye | Q8: 65 | R8: 65 | S8: 65 | T8: 65 | U8: 65 | V8: 65 | W8: 65 | X8: 65 | Y8: 65 | Z8: 65 | AA8: 65 | AB8: 70 | AC8: 70 | AD8: 70 | AE8: 70 | AF8: 70 | AG8: 70 | AH8: 70
B9: Resina Virgen | C9: =+(C6*E2/1000)*1.01*50% -> #REF! | D9: =+(D6*$E$2/1000)*1.01*75% -> #REF! | E9: =+(E6*$E$2/1000)*1.01*50% -> #REF! | F9: =+(F6*E2/1000)*1.01 -> #REF! | G9: =+(G6*$E$2/1000)*1.01*75% -> #REF! | H9: =+(H6*$E$2/1000)*1.01*50% -> #REF! | K9: Resina Virgen | L9: =+(L6*E2/1000)*1.005*75% -> #REF! | M9: =+(M6*E2/1000)*1.005 -> #REF! | N9: =+(N6*E2/1000)*1.005*75% -> #REF! | Q9: =SUM(Q6:Q8) -> 1028.22 | R9: =SUM(R6:R8) -> 1049.09 | S9: =SUM(S6:S8) -> 1096.34 | T9: =SUM(T6:T8) -> 1083.75 | U9: =SUM(U6:U8) -> 1105.5 | V9: =SUM(V6:V8) -> 1135.6 | W9: =SUM(W6:W8) -> 1193.75 | X9: =SUM(X6:X8) -> 1238.75 | ... AH9: =SUM(AH6:AH8) -> #REF!
B10: Resina PCR | C10: =+(C6*$E$3/1000)*1.01*50% -> #REF! | D10: =+(D6*$E$3/1000)*1.01*25% -> #REF! | E10: =+(E6*$E$3/1000)*1.01*50% -> #REF! | F10: 0 | G10: =+(G6*$E$3/1000)*1.01*25% -> #REF! | H10: =+(H6*$E$3/1000)*1.01*50% -> #REF! | K10: Resina PCR | L10: =+(L6*E3/1000)*1.005*25% -> #REF! | M10: 0 | N10: =+(N6*E3/1000)*1.005*25% -> #REF! | P10: Landed factor 4% | Q10: =+Q9*4% -> 41.1288 | R10: =+R9*4% -> 41.9636 | S10: =+S9*4% -> 43.8536 | T10: =+T9*4% -> 43.35 | U10: =+U9*4% -> 44.22 | V10: =+V9*4% -> 45.424 | W10: =+W9*4% -> 47.75 | X10: =+X9*4% -> 49.55 | ... AH10: =+AH9*4% -> #REF!
B11: Resina TM | C11: =SUM(C9:C10) -> #REF! | D11: =SUM(D9:D10) -> #REF! | E11: =SUM(E9:E10) -> #REF! | F11: =SUM(F9:F10) -> #REF! | G11: =SUM(G9:G10) -> #REF! | H11: =SUM(H9:H10) -> #REF! | I11: =SUM(I9:I10) -> 0 | K11: Resina TM | L11: =SUM(L9:L10) -> #REF! | M11: =SUM(M9:M10) -> #REF! | N11: =SUM(N9:N10) -> #REF! | P11: Total resin price | Q11: =+Q10+Q9 -> 1069.3488 | R11: =+R10+R9 -> 1091.0536 | S11: =+S10+S9 -> 1140.1936 | T11: =+T10+T9 -> 1127.1 | U11: =+U10+U9 -> 1149.72 | V11: =+V10+V9 -> 1181.024 | W11: =+W10+W9 -> 1241.5 | X11: =+X10+X9 -> 1288.3 | ... AH11: =+AH10+AH9 -> #REF!
B12: Conversión | C12: =8.2+0.03 -> 8.23 | D12: 8.23 | E12: =8.2+0.03 -> 8.23 | F12: 11.2 | G12: 11.2 | H12: =11.15+0.05 -> 11.2 | K12: Conversión | L12: =27.2+0.11 -> 27.31 | M12: =27.2+0.12 -> 27.32 | N12: =27.2+0.12 -> 27.32 | P12: Resin PCR % | Q12: =+Q11*(1-5%) -> 1015.8814 | R12: =+R11*(1-5%) -> 1036.5009 | S12: =+S11*(1-5%) -> 1083.1839 | T12: =+T11*(1-5%) -> 1070.745 | U12: =+U11*(1-5%) -> 1092.234 | V12: =+V11*(1-5%) -> 1121.9728 | W12: =+W11*(1-5%) -> 1179.425 | X12: =+X11*(1-5%) -> 1223.885 | ... AH12: =+AH11*(1-5%) -> #REF!
B13: Pigmento | C13: 1.5 | D13: 1.5 | E13: 1.83 | F13: 3.45 | G13: 3.45 | H13: 3.45 | K13: Pigmento | L13: 0.9 | M13: 2.18 | N13: 2.18 | P13: Precio ponderado bajo formula | Q13: =+Q11*75%+Q12*25% -> 1055.9819 | R13: =+R11*75%+R12*25% -> 1077.4154 | S13: =+S11*75%+S12*25% -> 1125.9412 | T13: =+T11*75%+T12*25% -> 1113.0113 | U13: =+U11*75%+U12*25% -> 1135.3485 | V13: =+V11*75%+V12*25% -> 1166.2612 | W13: =+W11*75%+W12*25% -> 1225.9813 | X13: =+X11*75%+X12*25% -> 1272.1962 | ... AG13: =+AG11*75%+AG12*25% -> #REF! | AH13: =+AH11*50%+AH12*50% -> #REF!
B14: Empaque | C14: 0.19 | D14: 0.19 | E14: 0.19 | F14: 0.33 | G14: 0.33 | H14: 0.33 | K14: Empaque | L14: 4.3 | M14: 4.3 | N14: 4.3 | P14: Scrap 1% | Q14: =+Q13*1% -> 10.559819 | R14: =+R13*1% -> 10.774154 | S14: =+S13*1% -> 11.259412 | T14: =+T13*1% -> 11.130113 | U14: =+U13*1% -> 11.353485 | V14: =+V13*1% -> 11.662612 | W14: =+W13*1% -> 12.259813 | X14: =+X13*1% -> 12.721963 | ... AH14: =+AH13*1% -> #REF!
B15: Flete | C15: 0.16 | D15: 0.16 | E15: 0.16 | F15: 0.28 | G15: 0.28 | H15: 0.28 | K15: Flete | L15: 7.85 | M15: 7.85 | N15: 7.85 | P15: Precio ponderado con scrap | Q15: =+Q14+Q13 -> 1066.5418 | R15: =+R14+R13 -> 1088.1896 | S15: =+S14+S13 -> 1137.2006 | T15: =+T14+T13 -> 1124.1414 | U15: =+U14+U13 -> 1146.702 | V15: =+V14+V13 -> 1177.9238 | W15: =+W14+W13 -> 1238.2411 | X15: =+X14+X13 -> 1284.9182 | ... AH15: =+AH14+AH13 -> #REF!
B16: Total | C16: =+C11+C12+C13+C14+C15 -> #REF! | D16: =+D11+D12+D13+D14+D15 -> #REF! | E16: =+E11+E12+E13+E14+E15 -> #REF! | F16: =+F11+F12+F13+F14+F15 -> #REF! | G16: =+G11+G12+G13+G14+G15 -> #REF! | H16: =+H11+H12+H13+H14+H15 -> #REF! | K16: Total | L16: =+L11+L12+L13+L14+L15 -> #REF! | M16: =+M11+M12+M13+M14+M15 -> #REF! | N16: =+N11+N12+N13+N14+N15 -> #REF! | P16: Precio facturado Sep-Oct-Nov | Q16: =+D4 -> #REF! | R16: =+Q16 -> #REF! | S16: =+R16 -> #REF! | T16: =+S16 -> #REF! | U16: =+T16 -> #REF! | V16: =+U16 -> #REF! | W16: =+V16 -> #REF! | X16: =+W16 -> #REF! | Y16: =+X16 -> #REF! | ... AF16: =+AE16 -> #REF!
B33: Fórmula

Sheet Marzo19
B2: Costo Resina Virgen | E2: =+AJ11 -> #REF! | J2: 0.05
B3: Costo Resina PCR Enkador | E3: =+AJ12 -> #REF! | J3: =+E2*J2 -> #REF!
C4: =+(C9+C10)/C6*1000 -> #REF! | D4: =+(G9+G10)/G6*1000 -> #REF! | E4: =+(E9+E10)/E6*1000 -> #REF! | F4: =+(F9+F10)/F6*1000 -> #REF! | I4: =+(I9+I10)/I6*1000 -> #REF!
B5: Preformas | C5: 200cc Pony | D5: 330cc Pony | E5: 330cc Pony | F5: 330cc Pony | G5: 1 Litro Pony | H5: 1 Litro Pony | I5: 1 Litro Pony | L5: Envases | M5: 500ml SG | N5: 500ml CG | O5: 500ml CG | Q5: Rubros | R5: IHS julio para precio septiembre | S5: IHS agosto para precio octubre | T5: IHS septiembre para precio noviembre | U5: IHS Octubre para precio Diciembre | V5: IHS Noviembre para precio Enero | W5: IHS Diciembre para precio Febrero | X5: IHS Enero para precio Marzo | Y5: IHS Febrero para precio Abril | Z5: IHS Marzo para precio Mayo | AA5: IHS Abril para precio Junio | AB5: IHS Mayo para precio Julio | AC5: IHS Junio para precio Agosto | AD5: IHS Julio para precio Septiembre | AE5: IHS Agosto para precio Octubre | AF5: IHS Septiembre para precio Nov | AG5: IHS Octubre para precio Dic | AH5: IHS Noviembre para precio Enero | AI5: IHS Diciembre para precio Febrero | AJ5: IHS Enero para precio Marzo
B6: Gramaje | C6: 16.7 | D6: 16.7 | E6: 20.6 | F6: 20.6 | G6: 30.6 | H6: 30.6 | I6: 38.6 | L6: Gramaje | M6: 15 | N6: 20.5 | O6: 20.5 | Q6: IHS Asia Non Coke approved | R6: 938.13 | S6: 959 | T6: 1006.25 | U6: 993.75 | V6: 1015.5 | W6: 1045.6 | X6: 1103.75 | Y6: 1148.75 | Z6: 1167 | AA6: 1221.25 | AB6: 1330 | AC6: =+'IHS (Mod)'!I5 -> 1280 | AD6: =+'IHS (Mod)'!J5 -> 1279.38 | AE6: 1275.5 | AF6: =+#REF! -> #REF! | AG6: =+#REF! -> #REF! | AH6: =+#REF! -> #REF! | AI6: =+#REF! -> #REF! | AJ6: =+#REF! -> #REF!
B7: Finish | C7: Short | D7: Short | E7: Short | F7: Short | G7: Short | H7: Short | I7: Short | L7: Finish | M7: Short | N7: Short | O7: Short | Q7: Finance | R7: 25.09 | S7: 25.09 | T7: 25.09 | U7: 25 | V7: 25 | W7: 25 | X7: 25 | Y7: 25 | Z7: 25 | AA7: 25 | AB7: 25 | AC7: 33.139726 | AD7: =+Septiembre18!AD8 -> 33.123674 | AE7: 33.023219 | AF7: 33.023219 | AG7: 32.783733 | AH7: 29.126712 | AI7: 27.395421 | AJ7: =+AM7 -> #REF! | AK7: =+AJ6*4.5% -> #REF! | AL7: =+AK7/365 -> #REF! | AM7: =+AL7*210 -> #REF!
B8: % Resina (Virgen/PCR) | C8: 50% - 50% | D8: 75% - 25% | E8: 1 | F8: 50% - 50% | G8: 1 | H8: 75% - 25% | I8: 50% - 50% | L8: =+B8 -> % Resina (Virgen/PCR) | M8: 75% - 25% | N8: 1 | O8: 75% - 25% | Q8: Freight China-Gye | R8: 65 | S8: 65 | T8: 65 | U8: 65 | V8: 65 | W8: 65 | X8: 65 | Y8: 65 | Z8: 65 | AA8: 65 | AB8: 65 | AC8: 70 | AD8: 70 | AE8: 70 | AF8: 70 | AG8: 70 | AH8: 70 | AI8: 70 | AJ8: 70
B9: Resina Virgen | C9: =+(C6*E2/1000)*1.01*50% -> #REF! | D9: =+(D6*$E$2/1000)*1.01*75% -> #REF! | E9: =+(E6*$E$2/1000)*1.01 -> #REF! | F9: =+(F6*$E$2/1000)*1.01*50% -> #REF! | G9: =+(G6*E2/1000)*1.01 -> #REF! | H9: =+(H6*$E$2/1000)*1.01*75% -> #REF! | I9: =+(I6*$E$2/1000)*1.01*50% -> #REF! | L9: Resina Virgen | M9: =+(M6*E2/1000)*1.005*75% -> #REF! | N9: =+(N6*E2/1000)*1.005 -> #REF! | O9: =+(O6*E2/1000)*1.005*75% -> #REF! | R9: =SUM(R6:R8) -> 1028.22 | S9: =SUM(S6:S8) -> 1049.09 | T9: =SUM(T6:T8) -> 1096.34 | U9: =SUM(U6:U8) -> 1083.75 | V9: =SUM(V6:V8) -> 1105.5 | W9: =SUM(W6:W8) -> 1135.6 | X9: =SUM(X6:X8) -> 1193.75 | Y9: =SUM(Y6:Y8) -> 1238.75 | ... AJ9: =SUM(AJ6:AJ8) -> #REF!
B10: Resina PCR | C10: =+(C6*$E$3/1000)*1.01*50% -> #REF! | D10: =+(D6*$E$3/1000)*1.01*25% -> #REF! | E10: 0 | F10: =+(F6*$E$3/1000)*1.01*50% -> #REF! | G10: 0 | H10: =+(H6*$E$3/1000)*1.01*25% -> #REF! | I10: =+(I6*$E$3/1000)*1.01*50% -> #REF! | L10: Resina PCR | M10: =+(M6*E3/1000)*1.005*25% -> #REF! | N10: 0 | O10: =+(O6*E3/1000)*1.005*25% -> #REF! | Q10: Landed factor 4% | R10: =+R9*4% -> 41.1288 | S10: =+S9*4% -> 41.9636 | T10: =+T9*4% -> 43.8536 | U10: =+U9*4% -> 43.35 | V10: =+V9*4% -> 44.22 | W10: =+W9*4% -> 45.424 | X10: =+X9*4% -> 47.75 | Y10: =+Y9*4% -> 49.55 | ... AJ10: =+AJ9*4% -> #REF!
B11: Resina TM | C11: =SUM(C9:C10) -> #REF! | D11: =SUM(D9:D10) -> #REF! | E11: =SUM(E9:E10) -> #REF! | F11: =SUM(F9:F10) -> #REF! | G11: =SUM(G9:G10) -> #REF! | H11: =SUM(H9:H10) -> #REF! | I11: =SUM(I9:I10) -> #REF! | J11: =SUM(J9:J10) -> 0 | L11: Resina TM | M11: =SUM(M9:M10) -> #REF! | N11: =SUM(N9:N10) -> #REF! | O11: =SUM(O9:O10) -> #REF! | Q11: Total resin price | R11: =+R10+R9 -> 1069.3488 | S11: =+S10+S9 -> 1091.0536 | T11: =+T10+T9 -> 1140.1936 | U11: =+U10+U9 -> 1127.1 | V11: =+V10+V9 -> 1149.72 | W11: =+W10+W9 -> 1181.024 | X11: =+X10+X9 -> 1241.5 | Y11: =+Y10+Y9 -> 1288.3 | ... AJ11: =+AJ10+AJ9 -> #REF!
B12: Conversión | C12: =8.2+0.03 -> 8.23 | D12: 8.23 | E12: =8.2+0.03 -> 8.23 | F12: =8.2+0.03 -> 8.23 | G12: 11.2 | H12: 11.2 | I12: =11.15+0.05 -> 11.2 | L12: Conversión | M12: =27.2+0.11 -> 27.31 | N12: =27.2+0.12 -> 27.32 | O12: =27.2+0.12 -> 27.32 | Q12: Resin PCR % | R12: =+R11*(1-5%) -> 1015.8814 | S12: =+S11*(1-5%) -> 1036.5009 | T12: =+T11*(1-5%) -> 1083.1839 | U12: =+U11*(1-5%) -> 1070.745 | V12: =+V11*(1-5%) -> 1092.234 | W12: =+W11*(1-5%) -> 1121.9728 | X12: =+X11*(1-5%) -> 1179.425 | Y12: =+Y11*(1-5%) -> 1223.885 | ... AJ12: =+AJ11*(1-5%) -> #REF!
B13: Pigmento | C13: 1.5 | D13: 1.5 | E13: 1.83 | F13: 1.83 | G13: 3.45 | H13: 3.45 | I13: 3.45 | L13: Pigmento | M13: 0.9 | N13: 2.18 | O13: 2.18 | Q13: Precio ponderado bajo formula | R13: =+R11*75%+R12*25% -> 1055.9819 | S13: =+S11*75%+S12*25% -> 1077.4154 | T13: =+T11*75%+T12*25% -> 1125.9412 | U13: =+U11*75%+U12*25% -> 1113.0113 | V13: =+V11*75%+V12*25% -> 1135.3485 | W13: =+W11*75%+W12*25% -> 1166.2612 | X13: =+X11*75%+X12*25% -> 1225.9813 | Y13: =+Y11*75%+Y12*25% -> 1272.1962 | ... AH13: =+AH11*75%+AH12*25% -> #REF! | AI13: =+AI11*50%+AI12*50% -> #REF! | AJ13: =+AJ11*50%+AJ12*50% -> #REF! | AK13: 1334 | AL13: =+AK13-AJ13 -> #REF!
B14: Empaque | C14: 0.19 | D14: 0.19 | E14: 0.19 | F14: 0.19 | G14: 0.33 | H14: 0.33 | I14: 0.33 | L14: Empaque | M14: 4.3 | N14: 4.3 | O14: 4.3 | Q14: Scrap 1% | R14: =+R13*1% -> 10.559819 | S14: =+S13*1% -> 10.774154 | T14: =+T13*1% -> 11.259412 | U14: =+U13*1% -> 11.130113 | V14: =+V13*1% -> 11.353485 | W14: =+W13*1% -> 11.662612 | X14: =+X13*1% -> 12.259813 | Y14: =+Y13*1% -> 12.721963 | ... AJ14: =+AJ13*1% -> #REF!
B15: Flete | C15: 0.16 | D15: 0.16 | E15: 0.16 | F15: 0.16 | G15: 0.28 | H15: 0.28 | I15: 0.28 | L15: Flete | M15: 7.85 | N15: 7.85 | O15: 7.85 | Q15: Precio ponderado con scrap | R15: =+R14+R13 -> 1066.5418 | S15: =+S14+S13 -> 1088.1896 | T15: =+T14+T13 -> 1137.2006 | U15: =+U14+U13 -> 1124.1414 | V15: =+V14+V13 -> 1146.702 | W15: =+W14+W13 -> 1177.9238 | X15: =+X14+X13 -> 1238.2411 | Y15: =+Y14+Y13 -> 1284.9182 | ... AJ15: =+AJ14+AJ13 -> #REF!
B16: Total | C16: =+C11+C12+C13+C14+C15 -> #REF! | D16: =+D11+D12+D13+D14+D15 -> #REF! | E16: =+E11+E12+E13+E14+E15 -> #REF! | F16: =+F11+F12+F13+F14+F15 -> #REF! | G16: =+G11+G12+G13+G14+G15 -> #REF! | H16: =+H11+H12+H13+H14+H15 -> #REF! | I16: =+I11+I12+I13+I14+I15 -> #REF! | L16: Total | M16: =+M11+M12+M13+M14+M15 -> #REF! | N16: =+N11+N12+N13+N14+N15 -> #REF! | O16: =+O11+O12+O13+O14+O15 -> #REF! | Q16: Precio facturado Sep-Oct-Nov | R16: =+#REF! -> #REF! | S16: =+R16 -> #REF! | T16: =+S16 -> #REF! | U16: =+T16 -> #REF! | V16: =+U16 -> #REF! | W16: =+V16 -> #REF! | X16: =+W16 -> #REF! | Y16: =+X16 -> #REF! | Z16: =+Y16 -> #REF! | ... AG16: =+AF16 -> #REF!
B33: Fórmula

Sheet Abril19
B2: Costo Resina Virgen | E2: =+AK11 -> #REF! | J2: 0.05
B3: Costo Resina PCR Enkador | E3: =+AK14 -> #REF! | J3: =+E2*J2 -> #REF!
C4: =+(C9+C10)/C6*1000 -> #REF! | D4: =+(G9+G10)/G6*1000 -> #REF! | E4: =+(E9+E10)/E6*1000 -> #REF! | F4: =+(F9+F10)/F6*1000 -> #REF! | I4: =+(I9+I10)/I6*1000 -> #REF!
B5: Preformas | C5: 200cc Pony | D5: 330cc Pony | E5: 330cc Pony | F5: 330cc Pony | G5: 1 Litro Pony | H5: 1 Litro Pony | I5: 1 Litro Pony | L5: Envases | M5: 500ml SG | N5: 500ml CG | O5: 500ml CG | Q5: Rubros | R5: IHS julio para precio septiembre | S5: IHS agosto para precio octubre | T5: IHS septiembre para precio noviembre | U5: IHS Octubre para precio Diciembre | V5: IHS Noviembre para precio Enero | W5: IHS Diciembre para precio Febrero | X5: IHS Enero para precio Marzo | Y5: IHS Febrero para precio Abril | Z5: IHS Marzo para precio Mayo | AA5: IHS Abril para precio Junio | AB5: IHS Mayo para precio Julio | AC5: IHS Junio para precio Agosto | AD5: IHS Julio para precio Septiembre | AE5: IHS Agosto para precio Octubre | AF5: IHS Septiembre para precio Nov | AG5: IHS Octubre para precio Dic | AH5: IHS Noviembre para precio Enero | AI5: IHS Diciembre para precio Febrero | AJ5: IHS Enero para precio Marzo | AK5: IHS Febrero para precio Abril
B6: Gramaje | C6: 16.7 | D6: 16.7 | E6: 20.6 | F6: 20.6 | G6: 30.6 | H6: 30.6 | I6: 38.6 | L6: Gramaje | M6: 15 | N6: 20.5 | O6: 20.5 | Q6: IHS Asia Non Coke approved | R6: 938.13 | S6: 959 | T6: 1006.25 | U6: 993.75 | V6: 1015.5 | W6: 1045.6 | X6: 1103.75 | Y6: 1148.75 | Z6: 1167 | AA6: 1221.25 | AB6: 1330 | AC6: =+'IHS (Mod)'!I5 -> 1280 | AD6: =+'IHS (Mod)'!J5 -> 1279.38 | AE6: 1275.5 | AF6: =+#REF! -> #REF! | AG6: =+#REF! -> #REF! | AH6: =+#REF! -> #REF! | AI6: =+#REF! -> #REF! | AJ6: =+#REF! -> #REF! | AK6: =+#REF! -> #REF!
B7: Finish | C7: Short | D7: Short | E7: Short | F7: Short | G7: Short | H7: Short | I7: Short | L7: Finish | M7: Short | N7: Short | O7: Short | Q7: Finance Virgen | R7: 25.09 | S7: 25.09 | T7: 25.09 | U7: 25 | V7: 25 | W7: 25 | X7: 25 | Y7: 25 | Z7: 25 | AA7: 25 | AB7: 25 | AC7: 33.139726 | AD7: =+Septiembre18!AD8 -> 33.123674 | AE7: 33.023219 | AF7: 33.023219 | AG7: 32.783733 | AH7: 29.126712 | AI7: 27.395421 | AJ7: 26.796575 | AK7: =+AN7 -> #REF! | AL7: =+AK6*4.5% -> #REF! | AM7: =+AL7/365 -> #REF! | AN7: =+(AM7*210)*50% -> #REF!
B8: % Resina (Virgen/PCR) | C8: 50% - 50% | D8: 75% - 25% | E8: 1 | F8: 50% - 50% | G8: 1 | H8: 75% - 25% | I8: 50% - 50% | L8: =+B8 -> % Resina (Virgen/PCR) | M8: 75% - 25% | N8: 1 | O8: 75% - 25% | Q8: Freight China-Gye | R8: 65 | S8: 65 | T8: 65 | U8: 65 | V8: 65 | W8: 65 | X8: 65 | Y8: 65 | Z8: 65 | AA8: 65 | AB8: 65 | AC8: 70 | AD8: 70 | AE8: 70 | AF8: 70 | AG8: 70 | AH8: 70 | AI8: 70 | AJ8: 70 | AK8: 70
B9: Resina Virgen | C9: =+(C6*E2/1000)*1.01*50% -> #REF! | D9: =+(D6*$E$2/1000)*1.01*75% -> #REF! | E9: =+(E6*$E$2/1000)*1.01 -> #REF! | F9: =+(F6*$E$2/1000)*1.01*50% -> #REF! | G9: =+(G6*E2/1000)*1.01 -> #REF! | H9: =+(H6*$E$2/1000)*1.01*75% -> #REF! | I9: =+(I6*$E$2/1000)*1.01*50% -> #REF! | L9: Resina Virgen | M9: =+(M6*E2/1000)*1.005*75% -> #REF! | N9: =+(N6*E2/1000)*1.005 -> #REF! | O9: =+(O6*E2/1000)*1.005*75% -> #REF! | R9: =SUM(R6:R8) -> 1028.22 | S9: =SUM(S6:S8) -> 1049.09 | T9: =SUM(T6:T8) -> 1096.34 | U9: =SUM(U6:U8) -> 1083.75 | V9: =SUM(V6:V8) -> 1105.5 | W9: =SUM(W6:W8) -> 1135.6 | X9: =SUM(X6:X8) -> 1193.75 | Y9: =SUM(Y6:Y8) -> 1238.75 | ... AK9: =SUM(AK6:AK8) -> #REF!
B10: Resina PCR | C10: =+(C6*$E$3/1000)*1.01*50% -> #REF! | D10: =+(D6*$E$3/1000)*1.01*25% -> #REF! | E10: 0 | F10: =+(F6*$E$3/1000)*1.01*50% -> #REF! | G10: 0 | H10: =+(H6*$E$3/1000)*1.01*25% -> #REF! | I10: =+(I6*$E$3/1000)*1.01*50% -> #REF! | L10: Resina PCR | M10: =+(M6*E3/1000)*1.005*25% -> #REF! | N10: 0 | O10: =+(O6*E3/1000)*1.005*25% -> #REF! | Q10: Landed factor 4% | R10: =+R9*4% -> 41.1288 | S10: =+S9*4% -> 41.9636 | T10: =+T9*4% -> 43.8536 | U10: =+U9*4% -> 43.35 | V10: =+V9*4% -> 44.22 | W10: =+W9*4% -> 45.424 | X10: =+X9*4% -> 47.75 | Y10: =+Y9*4% -> 49.55 | ... AK10: =+AK9*4% -> #REF!
B11: Resina TM | C11: =SUM(C9:C10) -> #REF! | D11: =SUM(D9:D10) -> #REF! | E11: =SUM(E9:E10) -> #REF! | F11: =SUM(F9:F10) -> #REF! | G11: =SUM(G9:G10) -> #REF! | H11: =SUM(H9:H10) -> #REF! | I11: =SUM(I9:I10) -> #REF! | J11: =SUM(J9:J10) -> 0 | L11: Resina TM | M11: =SUM(M9:M10) -> #REF! | N11: =SUM(N9:N10) -> #REF! | O11: =SUM(O9:O10) -> #REF! | Q11: Total resin price | R11: =+R10+R9 -> 1069.3488 | S11: =+S10+S9 -> 1091.0536 | T11: =+T10+T9 -> 1140.1936 | U11: =+U10+U9 -> 1127.1 | V11: =+V10+V9 -> 1149.72 | W11: =+W10+W9 -> 1181.024 | X11: =+X10+X9 -> 1241.5 | Y11: =+Y10+Y9 -> 1288.3 | ... AK11: =+AK10+AK9 -> #REF!
B12: Conversión | C12: =8.2+0.03 -> 8.23 | D12: 8.23 | E12: =8.2+0.03 -> 8.23 | F12: =8.2+0.03 -> 8.23 | G12: 11.2 | H12: 11.2 | I12: =11.15+0.05 -> 11.2 | L12: Conversión | M12: =27.2+0.11 -> 27.31 | N12: =27.2+0.12 -> 27.32 | O12: =27.2+0.12 -> 27.32 | Q12: Resin PCR % | R12: =+R11*(1-5%) -> 1015.8814 | S12: =+S11*(1-5%) -> 1036.5009 | T12: =+T11*(1-5%) -> 1083.1839 | U12: =+U11*(1-5%) -> 1070.745 | V12: =+V11*(1-5%) -> 1092.234 | W12: =+W11*(1-5%) -> 1121.9728 | X12: =+X11*(1-5%) -> 1179.425 | Y12: =+Y11*(1-5%) -> 1223.885 | ... AK12: =+AK11*(1-5%) -> #REF!
B13: Pigmento | C13: 1.5 | D13: 1.5 | E13: 1.83 | F13: 1.83 | G13: 3.45 | H13: 3.45 | I13: 3.45 | L13: Pigmento | M13: 0.9 | N13: 2.18 | O13: 2.18 | Q13: Finance PCR | R13: Finance | S13: Finance | T13: Finance | U13: Finance | V13: Finance | W13: Finance | X13: Finance | Y13: Finance | Z13: Finance | AA13: Finance | AB13: Finance | AC13: Finance | AD13: Finance | AE13: Finance | AF13: Finance | AG13: Finance | AH13: Finance | AI13: Finance | AJ13: 0 | AK13: =+AN13 -> #REF! | AL13: =+AK12*4.5% -> #REF! | AM13: =+AL13/365 -> #REF! | AN13: =+(AM13*210)*50% -> #REF!
B14: Empaque | C14: 0.19 | D14: 0.19 | E14: 0.19 | F14: 0.19 | G14: 0.33 | H14: 0.33 | I14: 0.33 | L14: Empaque | M14: 4.3 | N14: 4.3 | O14: 4.3 | Q14: Precio Resin PCR | AK14: =+AK12+AK13 -> #REF!
B15: Flete | C15: 0.16 | D15: 0.16 | E15: 0.16 | F15: 0.16 | G15: 0.28 | H15: 0.28 | I15: 0.28 | L15: Flete | M15: 7.85 | N15: 7.85 | O15: 7.85 | Q15: Precio ponderado bajo formula | R15: =+R11*75%+R12*25% -> 1055.9819 | S15: =+S11*75%+S12*25% -> 1077.4154 | T15: =+T11*75%+T12*25% -> 1125.9412 | U15: =+U11*75%+U12*25% -> 1113.0113 | V15: =+V11*75%+V12*25% -> 1135.3485 | W15: =+W11*75%+W12*25% -> 1166.2612 | X15: =+X11*75%+X12*25% -> 1225.9813 | Y15: =+Y11*75%+Y12*25% -> 1272.1962 | ... AH15: =+AH11*75%+AH12*25% -> #REF! | AI15: =+AI11*50%+AI12*50% -> #REF! | AJ15: =+AJ11*50%+AJ12*50% -> #REF! | AK15: =+AK11*50%+AK14*50% -> #REF!
B16: Total | C16: =+C11+C12+C13+C14+C15 -> #REF! | D16: =+D11+D12+D13+D14+D15 -> #REF! | E16: =+E11+E12+E13+E14+E15 -> #REF! | F16: =+F11+F12+F13+F14+F15 -> #REF! | G16: =+G11+G12+G13+G14+G15 -> #REF! | H16: =+H11+H12+H13+H14+H15 -> #REF! | I16: =+I11+I12+I13+I14+I15 -> #REF! | L16: Total | M16: =+M11+M12+M13+M14+M15 -> #REF! | N16: =+N11+N12+N13+N14+N15 -> #REF! | O16: =+O11+O12+O13+O14+O15 -> #REF! | Q16: Scrap 1% | R16: =+R15*1% -> 10.559819 | S16: =+S15*1% -> 10.774154 | T16: =+T15*1% -> 11.259412 | U16: =+U15*1% -> 11.130113 | V16: =+V15*1% -> 11.353485 | W16: =+W15*1% -> 11.662612 | X16: =+X15*1% -> 12.259813 | Y16: =+Y15*1% -> 12.721963 | ... AK16: =+AK15*1% -> #REF! | AN16: =+AN13+AN7 -> #REF!
Q17: Precio ponderado con scrap | R17: =+R16+R15 -> 1066.5418 | S17: =+S16+S15 -> 1088.1896 | T17: =+T16+T15 -> 1137.2006 | U17: =+U16+U15 -> 1124.1414 | V17: =+V16+V15 -> 1146.702 | W17: =+W16+W15 -> 1177.9238 | X17: =+X16+X15 -> 1238.2411 | Y17: =+Y16+Y15 -> 1284.9182 | ... AK17: =+AK16+AK15 -> #REF!
R18: =+#REF! -> #REF! | S18: =+R18 -> #REF! | T18: =+S18 -> #REF! | U18: =+T18 -> #REF! | V18: =+U18 -> #REF! | W18: =+V18 -> #REF! | X18: =+W18 -> #REF! | Y18: =+X18 -> #REF! | Z18: =+Y18 -> #REF! | ... AG18: =+AF18 -> #REF!
B33: Fórmula

Sheet May19
B2: Costo Resina Virgen | E2: =+AL11 -> #REF! | J2: 0.05
B3: Costo Resina PCR Enkador | E3: =+AL14 -> #REF! | J3: =+E2*J2 -> #REF!
C4: =+(C9+C10)/C6*1000 -> #REF! | D4: =+(G9+G10)/G6*1000 -> #REF! | E4: =+(E9+E10)/E6*1000 -> #REF! | F4: =+(F9+F10)/F6*1000 -> #REF! | I4: =+(I9+I10)/I6*1000 -> #REF!
B5: Preformas | C5: 200cc Pony | D5: 330cc Pony | E5: 330cc Pony | F5: 330cc Pony | G5: 1 Litro Pony | H5: 1 Litro Pony | I5: 1 Litro Pony | L5: Envases | M5: 500ml SG | N5: 500ml CG | O5: 500ml CG | Q5: Rubros | R5: IHS julio para precio septiembre | S5: IHS agosto para precio octubre | T5: IHS septiembre para precio noviembre | U5: IHS Octubre para precio Diciembre | V5: IHS Noviembre para precio Enero | W5: IHS Diciembre para precio Febrero | X5: IHS Enero para precio Marzo | Y5: IHS Febrero para precio Abril | Z5: IHS Marzo para precio Mayo | AA5: IHS Abril para precio Junio | AB5: IHS Mayo para precio Julio | AC5: IHS Junio para precio Agosto | AD5: IHS Julio para precio Septiembre | AE5: IHS Agosto para precio Octubre | AF5: IHS Septiembre para precio Nov | AG5: IHS Octubre para precio Dic | AH5: IHS Noviembre para precio Enero | AI5: IHS Diciembre para precio Febrero | AJ5: IHS Enero para precio Marzo | AK5: IHS Febrero para precio Abril | AL5: IHS Marzo para precio Mayo
B6: Gramaje | C6: 16.7 | D6: 16.7 | E6: 20.6 | F6: 20.6 | G6: 30.6 | H6: 30.6 | I6: 38.6 | L6: Gramaje | M6: 15 | N6: 20.5 | O6: 20.5 | Q6: IHS Asia Non Coke approved | R6: 938.13 | S6: 959 | T6: 1006.25 | U6: 993.75 | V6: 1015.5 | W6: 1045.6 | X6: 1103.75 | Y6: 1148.75 | Z6: 1167 | AA6: 1221.25 | AB6: 1330 | AC6: =+'IHS (Mod)'!I5 -> 1280 | AD6: =+'IHS (Mod)'!J5 -> 1279.38 | AE6: 1275.5 | AF6: =+#REF! -> #REF! | AG6: =+#REF! -> #REF! | AH6: =+#REF! -> #REF! | AI6: =+#REF! -> #REF! | AJ6: =+#REF! -> #REF! | AK6: =+#REF! -> #REF! | AL6: =+#REF! -> #REF!
B7: Finish | C7: Short | D7: Short | E7: Short | F7: Short | G7: Short | H7: Short | I7: Short | L7: Finish | M7: Short | N7: Short | O7: Short | Q7: Finance Virgen | R7: 25.09 | S7: 25.09 | T7: 25.09 | U7: 25 | V7: 25 | W7: 25 | X7: 25 | Y7: 25 | Z7: 25 | AA7: 25 | AB7: 25 | AC7: 33.139726 | AD7: =+Septiembre18!AD8 -> 33.123674 | AE7: 33.023219 | AF7: 33.023219 | AG7: 32.783733 | AH7: 29.126712 | AI7: 27.395421 | AJ7: 26.796575 | AK7: 13.948459 | AL7: =+AO7 -> #REF! | AM7: =+AL6*4.5% -> #REF! | AN7: =+AM7/365 -> #REF! | AO7: =+(AN7*210)*50% -> #REF!
B8: % Resina (Virgen/PCR) | C8: 50% - 50% | D8: 75% - 25% | E8: 1 | F8: 50% - 50% | G8: 1 | H8: 75% - 25% | I8: 50% - 50% | L8: =+B8 -> % Resina (Virgen/PCR) | M8: 75% - 25% | N8: 1 | O8: 75% - 25% | Q8: Freight China-Gye | R8: 65 | S8: 65 | T8: 65 | U8: 65 | V8: 65 | W8: 65 | X8: 65 | Y8: 65 | Z8: 65 | AA8: 65 | AB8: 65 | AC8: 70 | AD8: 70 | AE8: 70 | AF8: 70 | AG8: 70 | AH8: 70 | AI8: 70 | AJ8: 70 | AK8: 70 | AL8: 70
B9: Resina Virgen | C9: =+(C6*E2/1000)*1.01*50% -> #REF! | D9: =+(D6*$E$2/1000)*1.01*75% -> #REF! | E9: =+(E6*$E$2/1000)*1.01 -> #REF! | F9: =+(F6*$E$2/1000)*1.01*50% -> #REF! | G9: =+(G6*E2/1000)*1.01 -> #REF! | H9: =+(H6*$E$2/1000)*1.01*75% -> #REF! | I9: =+(I6*$E$2/1000)*1.01*50% -> #REF! | L9: Resina Virgen | M9: =+(M6*E2/1000)*1.005*75% -> #REF! | N9: =+(N6*E2/1000)*1.005 -> #REF! | O9: =+(O6*E2/1000)*1.005*75% -> #REF! | R9: =SUM(R6:R8) -> 1028.22 | S9: =SUM(S6:S8) -> 1049.09 | T9: =SUM(T6:T8) -> 1096.34 | U9: =SUM(U6:U8) -> 1083.75 | V9: =SUM(V6:V8) -> 1105.5 | W9: =SUM(W6:W8) -> 1135.6 | X9: =SUM(X6:X8) -> 1193.75 | Y9: =SUM(Y6:Y8) -> 1238.75 | ... AL9: =SUM(AL6:AL8) -> #REF!
B10: Resina PCR | C10: =+(C6*$E$3/1000)*1.01*50% -> #REF! | D10: =+(D6*$E$3/1000)*1.01*25% -> #REF! | E10: 0 | F10: =+(F6*$E$3/1000)*1.01*50% -> #REF! | G10: 0 | H10: =+(H6*$E$3/1000)*1.01*25% -> #REF! | I10: =+(I6*$E$3/1000)*1.01*50% -> #REF! | L10: Resina PCR | M10: =+(M6*E3/1000)*1.005*25% -> #REF! | N10: 0 | O10: =+(O6*E3/1000)*1.005*25% -> #REF! | Q10: Landed factor 4% | R10: =+R9*4% -> 41.1288 | S10: =+S9*4% -> 41.9636 | T10: =+T9*4% -> 43.8536 | U10: =+U9*4% -> 43.35 | V10: =+V9*4% -> 44.22 | W10: =+W9*4% -> 45.424 | X10: =+X9*4% -> 47.75 | Y10: =+Y9*4% -> 49.55 | ... AL10: =+AL9*4% -> #REF!
B11: Resina TM | C11: =SUM(C9:C10) -> #REF! | D11: =SUM(D9:D10) -> #REF! | E11: =SUM(E9:E10) -> #REF! | F11: =SUM(F9:F10) -> #REF! | G11: =SUM(G9:G10) -> #REF! | H11: =SUM(H9:H10) -> #REF! | I11: =SUM(I9:I10) -> #REF! | J11: =SUM(J9:J10) -> 0 | L11: Resina TM | M11: =SUM(M9:M10) -> #REF! | N11: =SUM(N9:N10) -> #REF! | O11: =SUM(O9:O10) -> #REF! | Q11: Total resin price | R11: =+R10+R9 -> 1069.3488 | S11: =+S10+S9 -> 1091.0536 | T11: =+T10+T9 -> 1140.1936 | U11: =+U10+U9 -> 1127.1 | V11: =+V10+V9 -> 1149.72 | W11: =+W10+W9 -> 1181.024 | X11: =+X10+X9 -> 1241.5 | Y11: =+Y10+Y9 -> 1288.3 | ... AL11: =+AL10+AL9 -> #REF!
B12: Conversión | C12: =8.2+0.03 -> 8.23 | D12: 8.23 | E12: =8.2+0.03 -> 8.23 | F12: =8.2+0.03 -> 8.23 | G12: 11.2 | H12: 11.2 | I12: =11.15+0.05 -> 11.2 | L12: Conversión | M12: =27.2+0.11 -> 27.31 | N12: =27.2+0.12 -> 27.32 | O12: =27.2+0.12 -> 27.32 | Q12: Resin PCR % | R12: =+R11*(1-5%) -> 1015.8814 | S12: =+S11*(1-5%) -> 1036.5009 | T12: =+T11*(1-5%) -> 1083.1839 | U12: =+U11*(1-5%) -> 1070.745 | V12: =+V11*(1-5%) -> 1092.234 | W12: =+W11*(1-5%) -> 1121.9728 | X12: =+X11*(1-5%) -> 1179.425 | Y12: =+Y11*(1-5%) -> 1223.885 | ... AL12: =+AL11*(1-5%) -> #REF!
B13: Pigmento | C13: 1.5 | D13: 1.5 | E13: 1.83 | F13: 1.83 | G13: 3.45 | H13: 3.45 | I13: 3.45 | L13: Pigmento | M13: 0.9 | N13: 2.18 | O13: 2.18 | Q13: Finance PCR | R13: Finance | S13: Finance | T13: Finance | U13: Finance | V13: Finance | W13: Finance | X13: Finance | Y13: Finance | Z13: Finance | AA13: Finance | AB13: Finance | AC13: Finance | AD13: Finance | AE13: Finance | AF13: Finance | AG13: Finance | AH13: Finance | AI13: Finance | AJ13: 0 | AK13: =+AO13 -> #REF! | AL13: =+AO13 -> #REF! | AM13: =+AL12*4.5% -> #REF! | AN13: =+AM13/365 -> #REF! | AO13: =+(AN13*210)*50% -> #REF!
B14: Empaque | C14: 0.19 | D14: 0.19 | E14: 0.19 | F14: 0.19 | G14: 0.33 | H14: 0.33 | I14: 0.33 | L14: Empaque | M14: 4.3 | N14: 4.3 | O14: 4.3 | Q14: Precio Resin PCR | AK14: =+AK12+AK13 -> #REF! | AL14: =+AL12+AL13 -> #REF!
B15: Flete | C15: 0.16 | D15: 0.16 | E15: 0.16 | F15: 0.16 | G15: 0.28 | H15: 0.28 | I15: 0.28 | L15: Flete | M15: 7.85 | N15: 7.85 | O15: 7.85 | Q15: Precio ponderado bajo formula | R15: =+R11*75%+R12*25% -> 1055.9819 | S15: =+S11*75%+S12*25% -> 1077.4154 | T15: =+T11*75%+T12*25% -> 1125.9412 | U15: =+U11*75%+U12*25% -> 1113.0113 | V15: =+V11*75%+V12*25% -> 1135.3485 | W15: =+W11*75%+W12*25% -> 1166.2612 | X15: =+X11*75%+X12*25% -> 1225.9813 | Y15: =+Y11*75%+Y12*25% -> 1272.1962 | ... AH15: =+AH11*75%+AH12*25% -> #REF! | AI15: =+AI11*50%+AI12*50% -> #REF! | AJ15: =+AJ11*50%+AJ12*50% -> #REF! | AK15: =+AK11*50%+AK14*50% -> #REF! | AL15: =+AL11*50%+AL14*50% -> #REF!
B16: Total | C16: =+C11+C12+C13+C14+C15 -> #REF! | D16: =+D11+D12+D13+D14+D15 -> #REF! | E16: =+E11+E12+E13+E14+E15 -> #REF! | F16: =+F11+F12+F13+F14+F15 -> #REF! | G16: =+G11+G12+G13+G14+G15 -> #REF! | H16: =+H11+H12+H13+H14+H15 -> #REF! | I16: =+I11+I12+I13+I14+I15 -> #REF! | L16: Total | M16: =+M11+M12+M13+M14+M15 -> #REF! | N16: =+N11+N12+N13+N14+N15 -> #REF! | O16: =+O11+O12+O13+O14+O15 -> #REF! | Q16: Scrap 1% | R16: =+R15*1% -> 10.559819 | S16: =+S15*1% -> 10.774154 | T16: =+T15*1% -> 11.259412 | U16: =+U15*1% -> 11.130113 | V16: =+V15*1% -> 11.353485 | W16: =+W15*1% -> 11.662612 | X16: =+X15*1% -> 12.259813 | Y16: =+Y15*1% -> 12.721963 | ... AL16: =+AL15*1% -> #REF!
Q17: Precio ponderado con scrap | R17: =+R16+R15 -> 1066.5418 | S17: =+S16+S15 -> 1088.1896 | T17: =+T16+T15 -> 1137.2006 | U17: =+U16+U15 -> 1124.1414 | V17: =+V16+V15 -> 1146.702 | W17: =+W16+W15 -> 1177.9238 | X17: =+X16+X15 -> 1238.2411 | Y17: =+Y16+Y15 -> 1284.9182 | ... AL17: =+AL16+AL15 -> #REF!
R18: =+#REF! -> #REF! | S18: =+R18 -> #REF! | T18: =+S18 -> #REF! | U18: =+T18 -> #REF! | V18: =+U18 -> #REF! | W18: =+V18 -> #REF! | X18: =+W18 -> #REF! | Y18: =+X18 -> #REF! | Z18: =+Y18 -> #REF! | ... AG18: =+AF18 -> #REF!
B32: Fórmula

Sheet Jun19
B2: Costo Resina Virgen | E2: =+AM11 -> #REF! | J2: 0.05
B3: Costo Resina PCR Enkador | E3: =+AM14 -> #REF! | J3: =+E2*J2 -> #REF!
C4: =+(C9+C10)/C6*1000 -> #REF! | D4: =+(G9+G10)/G6*1000 -> #REF! | E4: =+(E9+E10)/E6*1000 -> #REF! | F4: =+(F9+F10)/F6*1000 -> #REF! | I4: =+(I9+I10)/I6*1000 -> #REF!
B5: Preformas | C5: 200cc Pony | D5: 330cc Pony | E5: 330cc Pony | F5: 330cc Pony | G5: 1 Litro Pony | H5: 1 Litro Pony | I5: 1 Litro Pony | L5: Envases | M5: 500ml SG | N5: 500ml CG | O5: 500ml CG | Q5: Rubros | R5: IHS julio para precio septiembre | S5: IHS agosto para precio octubre | T5: IHS septiembre para precio noviembre | U5: IHS Octubre para precio Diciembre | V5: IHS Noviembre para precio Enero | W5: IHS Diciembre para precio Febrero | X5: IHS Enero para precio Marzo | Y5: IHS Febrero para precio Abril | Z5: IHS Marzo para precio Mayo | AA5: IHS Abril para precio Junio | AB5: IHS Mayo para precio Julio | AC5: IHS Junio para precio Agosto | AD5: IHS Julio para precio Septiembre | AE5: IHS Agosto para precio Octubre | AF5: IHS Septiembre para precio Nov | AG5: IHS Octubre para precio Dic | AH5: IHS Noviembre para precio Enero | AI5: IHS Diciembre para precio Febrero | AJ5: IHS Enero para precio Marzo | AK5: IHS Febrero para precio Abril | AL5: IHS Marzo para precio Mayo | AM5: IHS Abril para precio Junio
B6: Gramaje | C6: 16.7 | D6: 16.7 | E6: 20.5 | F6: 20.5 | G6: 30.6 | H6: 30.6 | I6: 38.6 | L6: Gramaje | M6: 15 | N6: 20.5 | O6: 20.5 | Q6: IHS Asia Non Coke approved | R6: 938.13 | S6: 959 | T6: 1006.25 | U6: 993.75 | V6: 1015.5 | W6: 1045.6 | X6: 1103.75 | Y6: 1148.75 | Z6: 1167 | AA6: 1221.25 | AB6: 1330 | AC6: =+'IHS (Mod)'!I5 -> 1280 | AD6: =+'IHS (Mod)'!J5 -> 1279.38 | AE6: 1275.5 | AF6: =+#REF! -> #REF! | AG6: =+#REF! -> #REF! | AH6: =+#REF! -> #REF! | AI6: =+#REF! -> #REF! | AJ6: =+#REF! -> #REF! | AK6: =+#REF! -> #REF! | AL6: =+#REF! -> #REF! | AM6: =+#REF! -> #REF!
B7: Finish | C7: Short | D7: Short | E7: Short | F7: Short | G7: Short | H7: Short | I7: Short | L7: Finish | M7: Short | N7: Short | O7: Short | Q7: Finance Virgen | R7: 25.09 | S7: 25.09 | T7: 25.09 | U7: 25 | V7: 25 | W7: 25 | X7: 25 | Y7: 25 | Z7: 25 | AA7: 25 | AB7: 25 | AC7: 33.139726 | AD7: =+Septiembre18!AD8 -> 33.123674 | AE7: 33.023219 | AF7: 33.023219 | AG7: 32.783733 | AH7: 29.126712 | AI7: 27.395421 | AJ7: 26.796575 | AK7: 13.948459 | AL7: 14.191182 | AM7: =+AP7 -> #REF! | AN7: =+AM6*4.5% -> #REF! | AO7: =+AN7/365 -> #REF! | AP7: =+(AO7*210)*50% -> #REF!
B8: % Resina (Virgen/PCR) | C8: 50% - 50% | D8: 75% - 25% | E8: 1 | F8: 50% - 50% | G8: 1 | H8: 75% - 25% | I8: 50% - 50% | L8: =+B8 -> % Resina (Virgen/PCR) | M8: 75% - 25% | N8: 1 | O8: 75% - 25% | Q8: Freight China-Gye | R8: 65 | S8: 65 | T8: 65 | U8: 65 | V8: 65 | W8: 65 | X8: 65 | Y8: 65 | Z8: 65 | AA8: 65 | AB8: 65 | AC8: 70 | AD8: 70 | AE8: 70 | AF8: 70 | AG8: 70 | AH8: 70 | AI8: 70 | AJ8: 70 | AK8: 70 | AL8: 70 | AM8: 70
B9: Resina Virgen | C9: =+(C6*E2/1000)*1.01*50% -> #REF! | D9: =+(D6*$E$2/1000)*1.01*75% -> #REF! | E9: =+(E6*$E$2/1000)*1.01 -> #REF! | F9: =+(F6*$E$2/1000)*1.01*50% -> #REF! | G9: =+(G6*E2/1000)*1.01 -> #REF! | H9: =+(H6*$E$2/1000)*1.01*75% -> #REF! | I9: =+(I6*$E$2/1000)*1.01*50% -> #REF! | L9: Resina Virgen | M9: =+(M6*E2/1000)*1.005*75% -> #REF! | N9: =+(N6*E2/1000)*1.005 -> #REF! | O9: =+(O6*E2/1000)*1.005*75% -> #REF! | R9: =SUM(R6:R8) -> 1028.22 | S9: =SUM(S6:S8) -> 1049.09 | T9: =SUM(T6:T8) -> 1096.34 | U9: =SUM(U6:U8) -> 1083.75 | V9: =SUM(V6:V8) -> 1105.5 | W9: =SUM(W6:W8) -> 1135.6 | X9: =SUM(X6:X8) -> 1193.75 | Y9: =SUM(Y6:Y8) -> 1238.75 | ... AM9: =SUM(AM6:AM8) -> #REF!
B10: Resina PCR | C10: =+(C6*$E$3/1000)*1.01*50% -> #REF! | D10: =+(D6*$E$3/1000)*1.01*25% -> #REF! | E10: 0 | F10: =+(F6*$E$3/1000)*1.01*50% -> #REF! | G10: 0 | H10: =+(H6*$E$3/1000)*1.01*25% -> #REF! | I10: =+(I6*$E$3/1000)*1.01*50% -> #REF! | L10: Resina PCR | M10: =+(M6*E3/1000)*1.005*25% -> #REF! | N10: 0 | O10: =+(O6*E3/1000)*1.005*25% -> #REF! | Q10: Landed factor 4% | R10: =+R9*4% -> 41.1288 | S10: =+S9*4% -> 41.9636 | T10: =+T9*4% -> 43.8536 | U10: =+U9*4% -> 43.35 | V10: =+V9*4% -> 44.22 | W10: =+W9*4% -> 45.424 | X10: =+X9*4% -> 47.75 | Y10: =+Y9*4% -> 49.55 | ... AM10: =+AM9*4% -> #REF!
B11: Resina TM | C11: =SUM(C9:C10) -> #REF! | D11: =SUM(D9:D10) -> #REF! | E11: =SUM(E9:E10) -> #REF! | F11: =SUM(F9:F10) -> #REF! | G11: =SUM(G9:G10) -> #REF! | H11: =SUM(H9:H10) -> #REF! | I11: =SUM(I9:I10) -> #REF! | J11: =SUM(J9:J10) -> 0 | L11: Resina TM | M11: =SUM(M9:M10) -> #REF! | N11: =SUM(N9:N10) -> #REF! | O11: =SUM(O9:O10) -> #REF! | Q11: Total resin price | R11: =+R10+R9 -> 1069.3488 | S11: =+S10+S9 -> 1091.0536 | T11: =+T10+T9 -> 1140.1936 | U11: =+U10+U9 -> 1127.1 | V11: =+V10+V9 -> 1149.72 | W11: =+W10+W9 -> 1181.024 | X11: =+X10+X9 -> 1241.5 | Y11: =+Y10+Y9 -> 1288.3 | ... AM11: =+AM10+AM9 -> #REF!
B12: Conversión | C12: =8.2+0.03 -> 8.23 | D12: 8.23 | E12: =8.2+0.03 -> 8.23 | F12: =8.2+0.03 -> 8.23 | G12: 11.2 | H12: 11.2 | I12: =11.15+0.05 -> 11.2 | L12: Conversión | M12: =27.2+0.11 -> 27.31 | N12: =27.2+0.12 -> 27.32 | O12: =27.2+0.12 -> 27.32 | Q12: Resin PCR % | R12: =+R11*(1-5%) -> 1015.8814 | S12: =+S11*(1-5%) -> 1036.5009 | T12: =+T11*(1-5%) -> 1083.1839 | U12: =+U11*(1-5%) -> 1070.745 | V12: =+V11*(1-5%) -> 1092.234 | W12: =+W11*(1-5%) -> 1121.9728 | X12: =+X11*(1-5%) -> 1179.425 | Y12: =+Y11*(1-5%) -> 1223.885 | ... AM12: =+AM11*(1-5%) -> #REF!
B13: Pigmento | C13: 1.5 | D13: 1.5 | E13: 1.83 | F13: 1.83 | G13: 3.45 | H13: 3.45 | I13: 3.45 | L13: Pigmento | M13: 0.9 | N13: 2.18 | O13: 2.18 | Q13: Finance PCR | R13: Finance | S13: Finance | T13: Finance | U13: Finance | V13: Finance | W13: Finance | X13: Finance | Y13: Finance | Z13: Finance | AA13: Finance | AB13: Finance | AC13: Finance | AD13: Finance | AE13: Finance | AF13: Finance | AG13: Finance | AH13: Finance | AI13: Finance | AJ13: 0 | AK13: =+AP13 -> #REF! | AL13: 15.097681 | AM13: =+AP13 -> #REF! | AN13: =+AM12*4.5% -> #REF! | AO13: =+AN13/365 -> #REF! | AP13: =+(AO13*210)*50% -> #REF!
B14: Empaque | C14: 0.19 | D14: 0.19 | E14: 0.19 | F14: 0.19 | G14: 0.33 | H14: 0.33 | I14: 0.33 | L14: Empaque | M14: 4.3 | N14: 4.3 | O14: 4.3 | Q14: Precio Resin PCR | AK14: =+AK12+AK13 -> #REF! | AL14: =+AL12+AL13 -> #REF! | AM14: =+AM12+AM13 -> #REF! | AQ14: 1267
B15: Flete | C15: 0.16 | D15: 0.16 | E15: 0.16 | F15: 0.16 | G15: 0.28 | H15: 0.28 | I15: 0.28 | L15: Flete | M15: 8.36 | N15: 8.36 | O15: 8.36 | Q15: Precio ponderado bajo formula | R15: =+R11*75%+R12*25% -> 1055.9819 | S15: =+S11*75%+S12*25% -> 1077.4154 | T15: =+T11*75%+T12*25% -> 1125.9412 | U15: =+U11*75%+U12*25% -> 1113.0113 | V15: =+V11*75%+V12*25% -> 1135.3485 | W15: =+W11*75%+W12*25% -> 1166.2612 | X15: =+X11*75%+X12*25% -> 1225.9813 | Y15: =+Y11*75%+Y12*25% -> 1272.1962 | ... AH15: =+AH11*75%+AH12*25% -> #REF! | AI15: =+AI11*50%+AI12*50% -> #REF! | AJ15: =+AJ11*50%+AJ12*50% -> #REF! | AK15: =+AK11*50%+AK14*50% -> #REF! | AL15: =+AL11*50%+AL14*50% -> #REF! | AM15: =+AM11*50%+AM14*50% -> #REF! | AQ15: =+AQ14-AM14 -> #REF!
B16: Total | C16: =+C11+C12+C13+C14+C15 -> #REF! | D16: =+D11+D12+D13+D14+D15 -> #REF! | E16: =+E11+E12+E13+E14+E15 -> #REF! | F16: =+F11+F12+F13+F14+F15 -> #REF! | G16: =+G11+G12+G13+G14+G15 -> #REF! | H16: =+H11+H12+H13+H14+H15 -> #REF! | I16: =+I11+I12+I13+I14+I15 -> #REF! | L16: Total | M16: =+M11+M12+M13+M14+M15 -> #REF! | N16: =+N11+N12+N13+N14+N15 -> #REF! | O16: =+O11+O12+O13+O14+O15 -> #REF! | Q16: Scrap 1% | R16: =+R15*1% -> 10.559819 | S16: =+S15*1% -> 10.774154 | T16: =+T15*1% -> 11.259412 | U16: =+U15*1% -> 11.130113 | V16: =+V15*1% -> 11.353485 | W16: =+W15*1% -> 11.662612 | X16: =+X15*1% -> 12.259813 | Y16: =+Y15*1% -> 12.721963 | ... AM16: =+AM15*1% -> #REF!
Q17: Precio ponderado con scrap | R17: =+R16+R15 -> 1066.5418 | S17: =+S16+S15 -> 1088.1896 | T17: =+T16+T15 -> 1137.2006 | U17: =+U16+U15 -> 1124.1414 | V17: =+V16+V15 -> 1146.702 | W17: =+W16+W15 -> 1177.9238 | X17: =+X16+X15 -> 1238.2411 | Y17: =+Y16+Y15 -> 1284.9182 | ... AM17: =+AM16+AM15 -> #REF!
R18: =+#REF! -> #REF! | S18: =+R18 -> #REF! | T18: =+S18 -> #REF! | U18: =+T18 -> #REF! | V18: =+U18 -> #REF! | W18: =+V18 -> #REF! | X18: =+W18 -> #REF! | Y18: =+X18 -> #REF! | Z18: =+Y18 -> #REF! | ... AG18: =+AF18 -> #REF!
B32: Fórmula

Sheet Jul19
B2: Costo Resina Virgen | F2: =+AN11 -> #REF! | J2: 0.05
B3: Costo Resina PCR Enkador | F3: =+AN14 -> 1283.4016 | J3: =+F2*J2 -> #REF!
C4: =+(C9+C10)/C6*1000 -> #REF! | D4: =+(G9+G10)/G6*1000 -> #REF! | E4: =+(E9+E10)/E6*1000 -> #REF! | F4: =+(F9+F10)/F6*1000 -> #REF! | I4: =+(I9+I10)/I6*1000 -> #REF!
B5: Preformas | C5: 200cc Pony | D5: 330cc Pony | E5: 330cc Pony | F5: 330cc Pony | G5: 1 Litro Pony | H5: 1 Litro Pony | I5: 1 Litro Pony | L5: Envases | M5: 500ml SG | N5: 500ml CG | O5: 500ml CG | Q5: Rubros | R5: IHS julio para precio septiembre | S5: IHS agosto para precio octubre | T5: IHS septiembre para precio noviembre | U5: IHS Octubre para precio Diciembre | V5: IHS Noviembre para precio Enero | W5: IHS Diciembre para precio Febrero | X5: IHS Enero para precio Marzo | Y5: IHS Febrero para precio Abril | Z5: IHS Marzo para precio Mayo | AA5: IHS Abril para precio Junio | AB5: IHS Mayo para precio Julio | AC5: IHS Junio para precio Agosto | AD5: IHS Julio para precio Septiembre | AE5: IHS Agosto para precio Octubre | AF5: IHS Septiembre para precio Nov | AG5: IHS Octubre para precio Dic | AH5: IHS Noviembre para precio Enero | AI5: IHS Diciembre para precio Febrero | AJ5: IHS Enero para precio Marzo | AK5: IHS Febrero para precio Abril | AL5: IHS Marzo para precio Mayo | AM5: IHS Abril para precio Junio | AN5: IHS Mayo para precio Julio
B6: Gramaje | C6: 16.7 | D6: 16.7 | E6: 20.5 | F6: 20.5 | G6: 30.6 | H6: 30.6 | I6: 38.6 | L6: Gramaje | M6: 15 | N6: 20.5 | O6: 20.5 | Q6: IHS Asia Non Coke approved | R6: 938.13 | S6: 959 | T6: 1006.25 | U6: 993.75 | V6: 1015.5 | W6: 1045.6 | X6: 1103.75 | Y6: 1148.75 | Z6: 1167 | AA6: 1221.25 | AB6: 1330 | AC6: =+'IHS (Mod)'!I5 -> 1280 | AD6: =+'IHS (Mod)'!J5 -> 1279.38 | AE6: 1275.5 | AF6: =+#REF! -> #REF! | AG6: =+#REF! -> #REF! | AH6: =+#REF! -> #REF! | AI6: =+#REF! -> #REF! | AJ6: =+#REF! -> #REF! | AK6: =+#REF! -> #REF! | AL6: =+#REF! -> #REF! | AM6: =+#REF! -> #REF! | AN6: =+#REF! -> #REF!
B7: Finish | C7: Short | D7: Short | E7: Short | F7: Short | G7: Short | H7: Short | I7: Short | L7: Finish | M7: Short | N7: Short | O7: Short | Q7: Finance Virgen | R7: 25.09 | S7: 25.09 | T7: 25.09 | U7: 25 | V7: 25 | W7: 25 | X7: 25 | Y7: 25 | Z7: 25 | AA7: 25 | AB7: 25 | AC7: 33.139726 | AD7: =+Septiembre18!AD8 -> 33.123674 | AE7: 33.023219 | AF7: 33.023219 | AG7: 32.783733 | AH7: 29.126712 | AI7: 27.395421 | AJ7: 26.796575 | AK7: 13.948459 | AL7: 14.191182 | AM7: 14.255908 | AN7: =+AQ7 -> #REF! | AO7: =+AN6*4.5% -> #REF! | AP7: =+AO7/365 -> #REF! | AQ7: =+(AP7*210)*50% -> #REF!
B8: % Resina (Virgen/PCR) | C8: 50% - 50% | D8: 75% - 25% | E8: 1 | F8: 50% - 50% | G8: 1 | H8: 75% - 25% | I8: 50% - 50% | L8: =+B8 -> % Resina (Virgen/PCR) | M8: 75% - 25% | N8: 1 | O8: 75% - 25% | Q8: Freight China-Gye | R8: 65 | S8: 65 | T8: 65 | U8: 65 | V8: 65 | W8: 65 | X8: 65 | Y8: 65 | Z8: 65 | AA8: 65 | AB8: 65 | AC8: 70 | AD8: 70 | AE8: 70 | AF8: 70 | AG8: 70 | AH8: 70 | AI8: 70 | AJ8: 70 | AK8: 70 | AL8: 70 | AM8: 70 | AN8: 70
B9: Resina Virgen | C9: =+(C6*F2/1000)*1.01*50% -> #REF! | D9: =+(D6*$F$2/1000)*1.01*75% -> #REF! | E9: =+(E6*$F$2/1000)*1.01 -> #REF! | F9: =+(F6*$F$2/1000)*1.01*50% -> #REF! | G9: =+(G6*F2/1000)*1.01 -> #REF! | H9: =+(H6*$F$2/1000)*1.01*75% -> #REF! | I9: =+(I6*$F$2/1000)*1.01*50% -> #REF! | L9: Resina Virgen | M9: =+(M6*F2/1000)*1.005*75% -> #REF! | N9: =+(N6*F2/1000)*1.005 -> #REF! | O9: =+(O6*F2/1000)*1.005*75% -> #REF! | R9: =SUM(R6:R8) -> 1028.22 | S9: =SUM(S6:S8) -> 1049.09 | T9: =SUM(T6:T8) -> 1096.34 | U9: =SUM(U6:U8) -> 1083.75 | V9: =SUM(V6:V8) -> 1105.5 | W9: =SUM(W6:W8) -> 1135.6 | X9: =SUM(X6:X8) -> 1193.75 | Y9: =SUM(Y6:Y8) -> 1238.75 | ... AN9: =SUM(AN6:AN8) -> #REF!
B10: Resina PCR | C10: =+(C6*$F$3/1000)*1.01*50% -> 10.823567 | D10: =+(D6*$F$3/1000)*1.01*25% -> 5.4117836 | E10: 0 | F10: =+(F6*$F$3/1000)*1.01*50% -> 13.286415 | G10: 0 | H10: =+(H6*$F$3/1000)*1.01*25% -> 9.9162023 | I10: =+(I6*$F$3/1000)*1.01*50% -> 25.017347 | L10: Resina PCR | M10: =+(M6*F3/1000)*1.005*25% -> 4.8368197 | N10: 0 | O10: =+(O6*F3/1000)*1.005*25% -> 6.6103202 | Q10: Landed factor 4% | R10: =+R9*4% -> 41.1288 | S10: =+S9*4% -> 41.9636 | T10: =+T9*4% -> 43.8536 | U10: =+U9*4% -> 43.35 | V10: =+V9*4% -> 44.22 | W10: =+W9*4% -> 45.424 | X10: =+X9*4% -> 47.75 | Y10: =+Y9*4% -> 49.55 | ... AN10: =+AN9*4% -> #REF!
B11: Resina TM | C11: =SUM(C9:C10) -> #REF! | D11: =SUM(D9:D10) -> #REF! | E11: =SUM(E9:E10) -> #REF! | F11: =SUM(F9:F10) -> #REF! | G11: =SUM(G9:G10) -> #REF! | H11: =SUM(H9:H10) -> #REF! | I11: =SUM(I9:I10) -> #REF! | J11: =SUM(J9:J10) -> 0 | L11: Resina TM | M11: =SUM(M9:M10) -> #REF! | N11: =SUM(N9:N10) -> #REF! | O11: =SUM(O9:O10) -> #REF! | Q11: Total resin price | R11: =+R10+R9 -> 1069.3488 | S11: =+S10+S9 -> 1091.0536 | T11: =+T10+T9 -> 1140.1936 | U11: =+U10+U9 -> 1127.1 | V11: =+V10+V9 -> 1149.72 | W11: =+W10+W9 -> 1181.024 | X11: =+X10+X9 -> 1241.5 | Y11: =+Y10+Y9 -> 1288.3 | ... AN11: =+AN10+AN9 -> #REF!
B12: Conversión | C12: =8.2+0.03 -> 8.23 | D12: 8.23 | E12: =8.2+0.03 -> 8.23 | F12: =8.2+0.03 -> 8.23 | G12: 11.2 | H12: 11.2 | I12: =11.15+0.05 -> 11.2 | L12: Conversión | M12: =27.2+0.11 -> 27.31 | N12: =27.2+0.12 -> 27.32 | O12: =27.2+0.12 -> 27.32 | Q12: Resin PCR % | R12: =+R11*(1-5%) -> 1015.8814 | S12: =+S11*(1-5%) -> 1036.5009 | T12: =+T11*(1-5%) -> 1083.1839 | U12: =+U11*(1-5%) -> 1070.745 | V12: =+V11*(1-5%) -> 1092.234 | W12: =+W11*(1-5%) -> 1121.9728 | X12: =+X11*(1-5%) -> 1179.425 | Y12: =+Y11*(1-5%) -> 1223.885 | ... AM12: =+AM11*(1-5%) -> #REF! | AN12: 1267 | AR12: 1267 | AS12: Costo resina PCR Enkador
B13: Pigmento | C13: 1.5 | D13: 1.5 | E13: 1.83 | F13: 1.83 | G13: 3.45 | H13: 3.45 | I13: 3.45 | L13: Pigmento | M13: 0.9 | N13: 2.18 | O13: 2.18 | Q13: Finance PCR | R13: Finance | S13: Finance | T13: Finance | U13: Finance | V13: Finance | W13: Finance | X13: Finance | Y13: Finance | Z13: Finance | AA13: Finance | AB13: Finance | AC13: Finance | AD13: Finance | AE13: Finance | AF13: Finance | AG13: Finance | AH13: Finance | AI13: Finance | AJ13: 0 | AK13: =+AQ13 -> 16.401575 | AL13: 15.097681 | AM13: 15.162458 | AN13: =+AQ13 -> 16.401575 | AO13: =+AN12*4.5% -> 57.015 | AP13: =+AO13/365 -> 0.15620548 | AQ13: =+(AP13*210)*50% -> 16.401575 | AR13: =+AM14-AR12 -> #REF! | AS13: Diferencia vs el precio anterior
B14: Empaque | C14: 0.19 | D14: 0.19 | E14: 0.19 | F14: 0.19 | G14: 0.33 | H14: 0.33 | I14: 0.33 | L14: Empaque | M14: 4.3 | N14: 4.3 | O14: 4.3 | Q14: Precio Resin PCR | AK14: =+AK12+AK13 -> #REF! | AL14: =+AL12+AL13 -> #REF! | AM14: =+AM12+AM13 -> #REF! | AN14: =+AN12+AN13 -> 1283.4016
B15: Flete | C15: 0.16 | D15: 0.16 | E15: 0.16 | F15: 0.16 | G15: 0.28 | H15: 0.28 | I15: 0.28 | L15: Flete | M15: 8.36 | N15: 8.36 | O15: 8.36 | Q15: Precio ponderado bajo formula | R15: =+R11*75%+R12*25% -> 1055.9819 | S15: =+S11*75%+S12*25% -> 1077.4154 | T15: =+T11*75%+T12*25% -> 1125.9412 | U15: =+U11*75%+U12*25% -> 1113.0113 | V15: =+V11*75%+V12*25% -> 1135.3485 | W15: =+W11*75%+W12*25% -> 1166.2612 | X15: =+X11*75%+X12*25% -> 1225.9813 | Y15: =+Y11*75%+Y12*25% -> 1272.1962 | ... AH15: =+AH11*75%+AH12*25% -> #REF! | AI15: =+AI11*50%+AI12*50% -> #REF! | AJ15: =+AJ11*50%+AJ12*50% -> #REF! | AK15: =+AK11*50%+AK14*50% -> #REF! | AL15: =+AL11*50%+AL14*50% -> #REF! | AM15: =+AM11*50%+AM14*50% -> #REF! | AN15: =+AN11*50%+AN14*50% -> #REF!
B16: Total | C16: =+C11+C12+C13+C14+C15 -> #REF! | D16: =+D11+D12+D13+D14+D15 -> #REF! | E16: =+E11+E12+E13+E14+E15 -> #REF! | F16: =+F11+F12+F13+F14+F15 -> #REF! | G16: =+G11+G12+G13+G14+G15 -> #REF! | H16: =+H11+H12+H13+H14+H15 -> #REF! | I16: =+I11+I12+I13+I14+I15 -> #REF! | L16: Total | M16: =+M11+M12+M13+M14+M15 -> #REF! | N16: =+N11+N12+N13+N14+N15 -> #REF! | O16: =+O11+O12+O13+O14+O15 -> #REF! | Q16: Scrap 1% | R16: =+R15*1% -> 10.559819 | S16: =+S15*1% -> 10.774154 | T16: =+T15*1% -> 11.259412 | U16: =+U15*1% -> 11.130113 | V16: =+V15*1% -> 11.353485 | W16: =+W15*1% -> 11.662612 | X16: =+X15*1% -> 12.259813 | Y16: =+Y15*1% -> 12.721963 | ... AN16: =+AN15*1% -> #REF!
Q17: Precio ponderado con scrap | R17: =+R16+R15 -> 1066.5418 | S17: =+S16+S15 -> 1088.1896 | T17: =+T16+T15 -> 1137.2006 | U17: =+U16+U15 -> 1124.1414 | V17: =+V16+V15 -> 1146.702 | W17: =+W16+W15 -> 1177.9238 | X17: =+X16+X15 -> 1238.2411 | Y17: =+Y16+Y15 -> 1284.9182 | ... AN17: =+AN16+AN15 -> #REF!
R18: =+#REF! -> #REF! | S18: =+R18 -> #REF! | T18: =+S18 -> #REF! | U18: =+T18 -> #REF! | V18: =+U18 -> #REF! | W18: =+V18 -> #REF! | X18: =+W18 -> #REF! | Y18: =+X18 -> #REF! | Z18: =+Y18 -> #REF! | ... AG18: =+AF18 -> #REF!
B32: Fórmula

Sheet Ago19
B2: Costo Resina Virgen | F2: =+AO11 -> #REF! | J2: 0.05
B3: Costo Resina PCR Enkador | F3: =+AO14 -> #REF! | J3: =+F2*J2 -> #REF!
C4: =+(C9+C10)/C6*1000 -> #REF! | D4: =+(G9+G10)/G6*1000 -> #REF! | E4: =+(E9+E10)/E6*1000 -> #REF! | F4: =+(F9+F10)/F6*1000 -> #REF! | I4: =+(I9+I10)/I6*1000 -> #REF!
B5: Preformas | C5: 200cc Pony | D5: 330cc Pony | E5: 330cc Pony | F5: 330cc Pony | G5: 1 Litro Pony | H5: 1 Litro Pony | I5: 1 Litro Pony | L5: Envases | M5: 500ml SG | N5: 500ml CG | O5: 500ml CG | Q5: Rubros | R5: IHS julio para precio septiembre | S5: IHS agosto para precio octubre | T5: IHS septiembre para precio noviembre | U5: IHS Octubre para precio Diciembre | V5: IHS Noviembre para precio Enero | W5: IHS Diciembre para precio Febrero | X5: IHS Enero para precio Marzo | Y5: IHS Febrero para precio Abril | Z5: IHS Marzo para precio Mayo | AA5: IHS Abril para precio Junio | AB5: IHS Mayo para precio Julio | AC5: IHS Junio para precio Agosto | AD5: IHS Julio para precio Septiembre | AE5: IHS Agosto para precio Octubre | AF5: IHS Septiembre para precio Nov | AG5: IHS Octubre para precio Dic | AH5: IHS Noviembre para precio Enero | AI5: IHS Diciembre para precio Febrero | AJ5: IHS Enero para precio Marzo | AK5: IHS Febrero para precio Abril | AL5: IHS Marzo para precio Mayo | AM5: IHS Abril para precio Junio | AN5: IHS Mayo para precio Julio | AO5: IHS Junio precio Agosto
B6: Gramaje | C6: 16.7 | D6: 16.7 | E6: 20.5 | F6: 20.5 | G6: 30.6 | H6: 30.6 | I6: 38.6 | L6: Gramaje | M6: 15 | N6: 20.5 | O6: 20.5 | Q6: IHS Asia Non Coke approved | R6: 938.13 | S6: 959 | T6: 1006.25 | U6: 993.75 | V6: 1015.5 | W6: 1045.6 | X6: 1103.75 | Y6: 1148.75 | Z6: 1167 | AA6: 1221.25 | AB6: 1330 | AC6: =+'IHS (Mod)'!I5 -> 1280 | AD6: =+'IHS (Mod)'!J5 -> 1279.38 | AE6: 1275.5 | AF6: =+#REF! -> #REF! | AG6: =+#REF! -> #REF! | AH6: =+#REF! -> #REF! | AI6: =+#REF! -> #REF! | AJ6: =+#REF! -> #REF! | AK6: =+#REF! -> #REF! | AL6: =+#REF! -> #REF! | AM6: =+#REF! -> #REF! | ... AO6: =+#REF! -> #REF!
B7: Finish | C7: Short | D7: Short | E7: Short | F7: Short | G7: Short | H7: Short | I7: Short | L7: Finish | M7: Short | N7: Short | O7: Short | Q7: Finance Virgen | R7: 25.09 | S7: 25.09 | T7: 25.09 | U7: 25 | V7: 25 | W7: 25 | X7: 25 | Y7: 25 | Z7: 25 | AA7: 25 | AB7: 25 | AC7: 33.139726 | AD7: =+Septiembre18!AD8 -> 33.123674 | AE7: 33.023219 | AF7: 33.023219 | AG7: 32.783733 | AH7: 29.126712 | AI7: 27.395421 | AJ7: 26.796575 | AK7: 13.948459 | AL7: 14.191182 | AM7: 14.255908 | AN7: =((((AN6*4.5%)/365)*210))*50% -> #REF! | AO7: =((((AO6*4.5%)/365)*210))*50% -> #REF!
B8: % Resina (Virgen/PCR) | C8: 50% - 50% | D8: 75% - 25% | E8: 1 | F8: 50% - 50% | G8: 1 | H8: 75% - 25% | I8: 50% - 50% | L8: =+B8 -> % Resina (Virgen/PCR) | M8: 75% - 25% | N8: 1 | O8: 75% - 25% | Q8: Freight China-Gye | R8: 65 | S8: 65 | T8: 65 | U8: 65 | V8: 65 | W8: 65 | X8: 65 | Y8: 65 | Z8: 65 | AA8: 65 | AB8: 65 | AC8: 70 | AD8: 70 | AE8: 70 | AF8: 70 | AG8: 70 | AH8: 70 | AI8: 70 | AJ8: 70 | AK8: 70 | AL8: 70 | AM8: 70 | AN8: 70 | AO8: 70
B9: Resina Virgen | C9: =+(C6*F2/1000)*1.01*50% -> #REF! | D9: =+(D6*$F$2/1000)*1.01*75% -> #REF! | E9: =+(E6*$F$2/1000)*1.01 -> #REF! | F9: =+(F6*$F$2/1000)*1.01*50% -> #REF! | G9: =+(G6*F2/1000)*1.01 -> #REF! | H9: =+(H6*$F$2/1000)*1.01*75% -> #REF! | I9: =+(I6*$F$2/1000)*1.01*50% -> #REF! | L9: Resina Virgen | M9: =+(M6*F2/1000)*1.005*75% -> #REF! | N9: =+(N6*F2/1000)*1.005 -> #REF! | O9: =+(O6*F2/1000)*1.005*75% -> #REF! | R9: =SUM(R6:R8) -> 1028.22 | S9: =SUM(S6:S8) -> 1049.09 | T9: =SUM(T6:T8) -> 1096.34 | U9: =SUM(U6:U8) -> 1083.75 | V9: =SUM(V6:V8) -> 1105.5 | W9: =SUM(W6:W8) -> 1135.6 | X9: =SUM(X6:X8) -> 1193.75 | Y9: =SUM(Y6:Y8) -> 1238.75 | ... AO9: =SUM(AO6:AO8) -> #REF!
B10: Resina PCR | C10: =+(C6*$F$3/1000)*1.01*50% -> #REF! | D10: =+(D6*$F$3/1000)*1.01*25% -> #REF! | E10: 0 | F10: =+(F6*$F$3/1000)*1.01*50% -> #REF! | G10: 0 | H10: =+(H6*$F$3/1000)*1.01*25% -> #REF! | I10: =+(I6*$F$3/1000)*1.01*50% -> #REF! | L10: Resina PCR | M10: =+(M6*F3/1000)*1.005*25% -> #REF! | N10: 0 | O10: =+(O6*F3/1000)*1.005*25% -> #REF! | Q10: Landed factor 4% | R10: =+R9*4% -> 41.1288 | S10: =+S9*4% -> 41.9636 | T10: =+T9*4% -> 43.8536 | U10: =+U9*4% -> 43.35 | V10: =+V9*4% -> 44.22 | W10: =+W9*4% -> 45.424 | X10: =+X9*4% -> 47.75 | Y10: =+Y9*4% -> 49.55 | ... AO10: =+AO9*4% -> #REF!
B11: Resina TM | C11: =SUM(C9:C10) -> #REF! | D11: =SUM(D9:D10) -> #REF! | E11: =SUM(E9:E10) -> #REF! | F11: =SUM(F9:F10) -> #REF! | G11: =SUM(G9:G10) -> #REF! | H11: =SUM(H9:H10) -> #REF! | I11: =SUM(I9:I10) -> #REF! | J11: =SUM(J9:J10) -> 0 | L11: Resina TM | M11: =SUM(M9:M10) -> #REF! | N11: =SUM(N9:N10) -> #REF! | O11: =SUM(O9:O10) -> #REF! | Q11: Total resin price | R11: =+R10+R9 -> 1069.3488 | S11: =+S10+S9 -> 1091.0536 | T11: =+T10+T9 -> 1140.1936 | U11: =+U10+U9 -> 1127.1 | V11: =+V10+V9 -> 1149.72 | W11: =+W10+W9 -> 1181.024 | X11: =+X10+X9 -> 1241.5 | Y11: =+Y10+Y9 -> 1288.3 | ... AO11: =+AO10+AO9 -> #REF!
B12: Conversión | C12: =8.2+0.03 -> 8.23 | D12: 8.23 | E12: =8.2+0.03 -> 8.23 | F12: =8.2+0.03 -> 8.23 | G12: 11.2 | H12: 11.2 | I12: =11.15+0.05 -> 11.2 | L12: Conversión | M12: =27.2+0.11 -> 27.31 | N12: =27.2+0.12 -> 27.32 | O12: =27.2+0.12 -> 27.32 | Q12: Resin PCR % | R12: =+R11*(1-5%) -> 1015.8814 | S12: =+S11*(1-5%) -> 1036.5009 | T12: =+T11*(1-5%) -> 1083.1839 | U12: =+U11*(1-5%) -> 1070.745 | V12: =+V11*(1-5%) -> 1092.234 | W12: =+W11*(1-5%) -> 1121.9728 | X12: =+X11*(1-5%) -> 1179.425 | Y12: =+Y11*(1-5%) -> 1223.885 | ... AM12: =+AM11*(1-5%) -> #REF! | AN12: 1267 | AO12: =+AO11*(1-5%) -> #REF! | AP12: 1267 | AQ12: Costo resina PCR Enkador
B13: Pigmento | C13: 1.5 | D13: 1.5 | E13: 1.83 | F13: 1.83 | G13: 3.45 | H13: 3.45 | I13: 3.45 | L13: Pigmento | M13: 0.9 | N13: 2.18 | O13: 2.18 | Q13: Finance PCR | R13: Finance | S13: Finance | T13: Finance | U13: Finance | V13: Finance | W13: Finance | X13: Finance | Y13: Finance | Z13: Finance | AA13: Finance | AB13: Finance | AC13: Finance | AD13: Finance | AE13: Finance | AF13: Finance | AG13: Finance | AH13: Finance | AI13: Finance | AJ13: 0 | AK13: =+AR13 -> 0 | AL13: 15.097681 | AM13: 15.162458 | AN13: =((((AN12*4.5%)/365)*210))*50% -> 16.401575 | AO13: =((((AO12*4.5%)/365)*210))*50% -> #REF! | AP13: =+AM14-AP12 -> #REF! | AQ13: Diferencia vs el precio anterior
B14: Empaque | C14: 0.19 | D14: 0.19 | E14: 0.19 | F14: 0.19 | G14: 0.33 | H14: 0.33 | I14: 0.33 | L14: Empaque | M14: 4.3 | N14: 4.3 | O14: 4.3 | Q14: Precio Resin PCR | AK14: =+AK12+AK13 -> #REF! | AL14: =+AL12+AL13 -> #REF! | AM14: =+AM12+AM13 -> #REF! | AN14: =+AN12+AN13 -> 1283.4016 | AO14: =+AO12+AO13 -> #REF!
B15: Flete | C15: 0.16 | D15: 0.16 | E15: 0.16 | F15: 0.16 | G15: 0.28 | H15: 0.28 | I15: 0.28 | L15: Flete | M15: 8.36 | N15: 8.36 | O15: 8.36 | Q15: Precio ponderado bajo formula | R15: =+R11*75%+R12*25% -> 1055.9819 | S15: =+S11*75%+S12*25% -> 1077.4154 | T15: =+T11*75%+T12*25% -> 1125.9412 | U15: =+U11*75%+U12*25% -> 1113.0113 | V15: =+V11*75%+V12*25% -> 1135.3485 | W15: =+W11*75%+W12*25% -> 1166.2612 | X15: =+X11*75%+X12*25% -> 1225.9813 | Y15: =+Y11*75%+Y12*25% -> 1272.1962 | ... AH15: =+AH11*75%+AH12*25% -> #REF! | AI15: =+AI11*50%+AI12*50% -> #REF! | AJ15: =+AJ11*50%+AJ12*50% -> #REF! | AK15: =+AK11*50%+AK14*50% -> #REF! | AL15: =+AL11*50%+AL14*50% -> #REF! | AM15: =+AM11*50%+AM14*50% -> #REF! | AN15: =+AN11*50%+AN14*50% -> #REF! | AO15: =+AO11*50%+AO14*50% -> #REF!
B16: Total | C16: =+C11+C12+C13+C14+C15 -> #REF! | D16: =+D11+D12+D13+D14+D15 -> #REF! | E16: =+E11+E12+E13+E14+E15 -> #REF! | F16: =+F11+F12+F13+F14+F15 -> #REF! | G16: =+G11+G12+G13+G14+G15 -> #REF! | H16: =+H11+H12+H13+H14+H15 -> #REF! | I16: =+I11+I12+I13+I14+I15 -> #REF! | L16: Total | M16: =+M11+M12+M13+M14+M15 -> #REF! | N16: =+N11+N12+N13+N14+N15 -> #REF! | O16: =+O11+O12+O13+O14+O15 -> #REF! | Q16: Scrap 1% | R16: =+R15*1% -> 10.559819 | S16: =+S15*1% -> 10.774154 | T16: =+T15*1% -> 11.259412 | U16: =+U15*1% -> 11.130113 | V16: =+V15*1% -> 11.353485 | W16: =+W15*1% -> 11.662612 | X16: =+X15*1% -> 12.259813 | Y16: =+Y15*1% -> 12.721963 | ... AO16: =+AO15*1% -> #REF!
Q17: Precio ponderado con scrap | R17: =+R16+R15 -> 1066.5418 | S17: =+S16+S15 -> 1088.1896 | T17: =+T16+T15 -> 1137.2006 | U17: =+U16+U15 -> 1124.1414 | V17: =+V16+V15 -> 1146.702 | W17: =+W16+W15 -> 1177.9238 | X17: =+X16+X15 -> 1238.2411 | Y17: =+Y16+Y15 -> 1284.9182 | ... AO17: =+AO16+AO15 -> #REF!
R18: =+#REF! -> #REF! | S18: =+R18 -> #REF! | T18: =+S18 -> #REF! | U18: =+T18 -> #REF! | V18: =+U18 -> #REF! | W18: =+V18 -> #REF! | X18: =+W18 -> #REF! | Y18: =+X18 -> #REF! | Z18: =+Y18 -> #REF! | ... AG18: =+AF18 -> #REF!
B32: Fórmula

Sheet Sep19 (2)
B2: Costo Resina Virgen | F2: =+AP11 -> #REF! | J2: 0.05
B3: Costo Resina PCR Enkador | F3: =+AP14 -> #REF! | J3: =+F2*J2 -> #REF!
C4: =+(C9+C10)/C6*1000 -> #REF! | D4: =+(G9+G10)/G6*1000 -> #REF! | E4: =+(E9+E10)/E6*1000 -> #REF! | F4: =+(F9+F10)/F6*1000 -> #REF! | I4: =+(I9+I10)/I6*1000 -> #REF!
B5: Preformas | C5: 200cc Pony | D5: 330cc Pony | E5: 330cc Pony | F5: 330cc Pony | G5: 1 Litro Pony | H5: 1 Litro Pony | I5: 1 Litro Pony | L5: Envases | M5: 500ml SG | N5: 500ml CG | O5: 500ml CG | Q5: Rubros | R5: IHS julio para precio septiembre | S5: IHS agosto para precio octubre | T5: IHS septiembre para precio noviembre | U5: IHS Octubre para precio Diciembre | V5: IHS Noviembre para precio Enero | W5: IHS Diciembre para precio Febrero | X5: IHS Enero para precio Marzo | Y5: IHS Febrero para precio Abril | Z5: IHS Marzo para precio Mayo | AA5: IHS Abril para precio Junio | AB5: IHS Mayo para precio Julio | AC5: IHS Junio para precio Agosto | AD5: IHS Julio para precio Septiembre | AE5: IHS Agosto para precio Octubre | AF5: IHS Septiembre para precio Nov | AG5: IHS Octubre para precio Dic | AH5: IHS Noviembre para precio Enero | AI5: IHS Diciembre para precio Febrero | AJ5: IHS Enero para precio Marzo | AK5: IHS Febrero para precio Abril | AL5: IHS Marzo para precio Mayo | AM5: IHS Abril para precio Junio | AN5: IHS Mayo para precio Julio | AO5: IHS Junio precio Agosto | AP5: IHS Julio precio Septiembre
B6: Gramaje | C6: 16.7 | D6: 16.7 | E6: 20.5 | F6: 20.5 | G6: 30.6 | H6: 30.6 | I6: 38.6 | L6: Gramaje | M6: 15 | N6: 20.5 | O6: 20.5 | Q6: IHS Asia Non Coke approved | R6: 938.13 | S6: 959 | T6: 1006.25 | U6: 993.75 | V6: 1015.5 | W6: 1045.6 | X6: 1103.75 | Y6: 1148.75 | Z6: 1167 | AA6: 1221.25 | AB6: 1330 | AC6: =+'IHS (Mod)'!I5 -> 1280 | AD6: =+'IHS (Mod)'!J5 -> 1279.38 | AE6: 1275.5 | AF6: =+#REF! -> #REF! | AG6: =+#REF! -> #REF! | AH6: =+#REF! -> #REF! | AI6: =+#REF! -> #REF! | AJ6: =+#REF! -> #REF! | AK6: =+#REF! -> #REF! | AL6: =+#REF! -> #REF! | AM6: =+#REF! -> #REF! | ... AP6: =+#REF! -> #REF!
B7: Finish | C7: Short | D7: Short | E7: Short | F7: Short | G7: Short | H7: Short | I7: Short | L7: Finish | M7: Short | N7: Short | O7: Short | Q7: Finance Virgen | R7: 25.09 | S7: 25.09 | T7: 25.09 | U7: 25 | V7: 25 | W7: 25 | X7: 25 | Y7: 25 | Z7: 25 | AA7: 25 | AB7: 25 | AC7: 33.139726 | AD7: =+Septiembre18!AD8 -> 33.123674 | AE7: 33.023219 | AF7: 33.023219 | AG7: 32.783733 | AH7: 29.126712 | AI7: 27.395421 | AJ7: 26.796575 | AK7: 13.948459 | AL7: 14.191182 | AM7: 14.255908 | AN7: =((((AN6*4.5%)/365)*210))*50% -> #REF! | AO7: =((((AO6*4.5%)/365)*210))*50% -> #REF! | AP7: =((((AP6*4.5%)/365)*210))*50% -> #REF!
B8: % Resina (Virgen/PCR) | C8: 50% - 50% | D8: 75% - 25% | E8: 1 | F8: 50% - 50% | G8: 1 | H8: 75% - 25% | I8: 50% - 50% | L8: =+B8 -> % Resina (Virgen/PCR) | M8: 75% - 25% | N8: 1 | O8: 75% - 25% | Q8: Freight China-Gye | R8: 65 | S8: 65 | T8: 65 | U8: 65 | V8: 65 | W8: 65 | X8: 65 | Y8: 65 | Z8: 65 | AA8: 65 | AB8: 65 | AC8: 70 | AD8: 70 | AE8: 70 | AF8: 70 | AG8: 70 | AH8: 70 | AI8: 70 | AJ8: 70 | AK8: 70 | AL8: 70 | AM8: 70 | AN8: 70 | AO8: 70 | AP8: 70
B9: Resina Virgen | C9: =+(C6*F2/1000)*1.01*50% -> #REF! | D9: =+(D6*$F$2/1000)*1.01*75% -> #REF! | E9: =+(E6*$F$2/1000)*1.01 -> #REF! | F9: =+(F6*$F$2/1000)*1.01*50% -> #REF! | G9: =+(G6*F2/1000)*1.01 -> #REF! | H9: =+(H6*$F$2/1000)*1.01*75% -> #REF! | I9: =+(I6*$F$2/1000)*1.01*50% -> #REF! | L9: Resina Virgen | M9: =+(M6*F2/1000)*1.005*75% -> #REF! | N9: =+(N6*F2/1000)*1.005 -> #REF! | O9: =+(O6*F2/1000)*1.005*75% -> #REF! | R9: =SUM(R6:R8) -> 1028.22 | S9: =SUM(S6:S8) -> 1049.09 | T9: =SUM(T6:T8) -> 1096.34 | U9: =SUM(U6:U8) -> 1083.75 | V9: =SUM(V6:V8) -> 1105.5 | W9: =SUM(W6:W8) -> 1135.6 | X9: =SUM(X6:X8) -> 1193.75 | Y9: =SUM(Y6:Y8) -> 1238.75 | ... AP9: =SUM(AP6:AP8) -> #REF!
B10: Resina PCR | C10: =+(C6*$F$3/1000)*1.01*50% -> #REF! | D10: =+(D6*$F$3/1000)*1.01*25% -> #REF! | E10: 0 | F10: =+(F6*$F$3/1000)*1.01*50% -> #REF! | G10: 0 | H10: =+(H6*$F$3/1000)*1.01*25% -> #REF! | I10: =+(I6*$F$3/1000)*1.01*50% -> #REF! | L10: Resina PCR | M10: =+(M6*F3/1000)*1.005*25% -> #REF! | N10: 0 | O10: =+(O6*F3/1000)*1.005*25% -> #REF! | Q10: Landed factor 4% | R10: =+R9*4% -> 41.1288 | S10: =+S9*4% -> 41.9636 | T10: =+T9*4% -> 43.8536 | U10: =+U9*4% -> 43.35 | V10: =+V9*4% -> 44.22 | W10: =+W9*4% -> 45.424 | X10: =+X9*4% -> 47.75 | Y10: =+Y9*4% -> 49.55 | ... AP10: =+AP9*4% -> #REF!
B11: Resina TM | C11: =SUM(C9:C10) -> #REF! | D11: =SUM(D9:D10) -> #REF! | E11: =SUM(E9:E10) -> #REF! | F11: =SUM(F9:F10) -> #REF! | G11: =SUM(G9:G10) -> #REF! | H11: =SUM(H9:H10) -> #REF! | I11: =SUM(I9:I10) -> #REF! | J11: =SUM(J9:J10) -> 0 | L11: Resina TM | M11: =SUM(M9:M10) -> #REF! | N11: =SUM(N9:N10) -> #REF! | O11: =SUM(O9:O10) -> #REF! | Q11: Total resin price | R11: =+R10+R9 -> 1069.3488 | S11: =+S10+S9 -> 1091.0536 | T11: =+T10+T9 -> 1140.1936 | U11: =+U10+U9 -> 1127.1 | V11: =+V10+V9 -> 1149.72 | W11: =+W10+W9 -> 1181.024 | X11: =+X10+X9 -> 1241.5 | Y11: =+Y10+Y9 -> 1288.3 | ... AP11: =+AP10+AP9 -> #REF!
B12: Conversión | C12: =8.2+0.03 -> 8.23 | D12: 8.23 | E12: =8.2+0.03 -> 8.23 | F12: =8.2+0.03 -> 8.23 | G12: 11.2 | H12: 11.2 | I12: =11.15+0.05 -> 11.2 | L12: Conversión | M12: =27.2+0.11 -> 27.31 | N12: =27.2+0.12 -> 27.32 | O12: =27.2+0.12 -> 27.32 | Q12: Resin PCR % | R12: =+R11*(1-5%) -> 1015.8814 | S12: =+S11*(1-5%) -> 1036.5009 | T12: =+T11*(1-5%) -> 1083.1839 | U12: =+U11*(1-5%) -> 1070.745 | V12: =+V11*(1-5%) -> 1092.234 | W12: =+W11*(1-5%) -> 1121.9728 | X12: =+X11*(1-5%) -> 1179.425 | Y12: =+Y11*(1-5%) -> 1223.885 | ... AM12: =+AM11*(1-5%) -> #REF! | AN12: 1267 | AO12: =+AO11*(1-5%) -> #REF! | AP12: =+AP11*(1-5%) -> #REF! | AQ12: 1267 | AR12: Costo resina PCR Enkador
B13: Pigmento | C13: 1.5 | D13: 1.5 | E13: 1.83 | F13: 1.83 | G13: 3.45 | H13: 3.45 | I13: 3.45 | L13: Pigmento | M13: 0.9 | N13: 2.18 | O13: 2.18 | Q13: Finance PCR | R13: Finance | S13: Finance | T13: Finance | U13: Finance | V13: Finance | W13: Finance | X13: Finance | Y13: Finance | Z13: Finance | AA13: Finance | AB13: Finance | AC13: Finance | AD13: Finance | AE13: Finance | AF13: Finance | AG13: Finance | AH13: Finance | AI13: Finance | AJ13: 0 | AK13: =+AS13 -> 0 | AL13: 15.097681 | AM13: 15.162458 | AN13: =((((AN12*4.5%)/365)*210))*50% -> 16.401575 | AO13: =((((AO12*4.5%)/365)*210))*50% -> #REF! | AP13: =((((AP12*4.5%)/365)*210))*50% -> #REF! | AQ13: =+AP14-AQ12 -> #REF! | AR13: Diferencia vs el precio anterior
B14: Empaque | C14: 0.19 | D14: 0.19 | E14: 0.19 | F14: 0.19 | G14: 0.33 | H14: 0.33 | I14: 0.33 | L14: Empaque | M14: 4.3 | N14: 4.3 | O14: 4.3 | Q14: Precio Resin PCR | AK14: =+AK12+AK13 -> #REF! | AL14: =+AL12+AL13 -> #REF! | AM14: =+AM12+AM13 -> #REF! | AN14: =+AN12+AN13 -> 1283.4016 | AO14: =+AO12+AO13 -> #REF! | AP14: =+AP12+AP13 -> #REF!
B15: Flete | C15: 0.16 | D15: 0.16 | E15: 0.16 | F15: 0.16 | G15: 0.28 | H15: 0.28 | I15: 0.28 | L15: Flete | M15: 8.36 | N15: 8.36 | O15: 8.36 | Q15: Precio ponderado bajo formula | R15: =+R11*75%+R12*25% -> 1055.9819 | S15: =+S11*75%+S12*25% -> 1077.4154 | T15: =+T11*75%+T12*25% -> 1125.9412 | U15: =+U11*75%+U12*25% -> 1113.0113 | V15: =+V11*75%+V12*25% -> 1135.3485 | W15: =+W11*75%+W12*25% -> 1166.2612 | X15: =+X11*75%+X12*25% -> 1225.9813 | Y15: =+Y11*75%+Y12*25% -> 1272.1962 | ... AH15: =+AH11*75%+AH12*25% -> #REF! | AI15: =+AI11*50%+AI12*50% -> #REF! | AJ15: =+AJ11*50%+AJ12*50% -> #REF! | AK15: =+AK11*50%+AK14*50% -> #REF! | AL15: =+AL11*50%+AL14*50% -> #REF! | AM15: =+AM11*50%+AM14*50% -> #REF! | AN15: =+AN11*50%+AN14*50% -> #REF! | AO15: =+AO11*50%+AO14*50% -> #REF! | AP15: =+AP11*50%+AP14*50% -> #REF!
B16: Total | C16: =+C11+C12+C13+C14+C15 -> #REF! | D16: =+D11+D12+D13+D14+D15 -> #REF! | E16: =+E11+E12+E13+E14+E15 -> #REF! | F16: =+F11+F12+F13+F14+F15 -> #REF! | G16: =+G11+G12+G13+G14+G15 -> #REF! | H16: =+H11+H12+H13+H14+H15 -> #REF! | I16: =+I11+I12+I13+I14+I15 -> #REF! | L16: Total | M16: =+M11+M12+M13+M14+M15 -> #REF! | N16: =+N11+N12+N13+N14+N15 -> #REF! | O16: =+O11+O12+O13+O14+O15 -> #REF! | Q16: Scrap 1% | R16: =+R15*1% -> 10.559819 | S16: =+S15*1% -> 10.774154 | T16: =+T15*1% -> 11.259412 | U16: =+U15*1% -> 11.130113 | V16: =+V15*1% -> 11.353485 | W16: =+W15*1% -> 11.662612 | X16: =+X15*1% -> 12.259813 | Y16: =+Y15*1% -> 12.721963 | ... AP16: =+AP15*1% -> #REF!
Q17: Precio ponderado con scrap | R17: =+R16+R15 -> 1066.5418 | S17: =+S16+S15 -> 1088.1896 | T17: =+T16+T15 -> 1137.2006 | U17: =+U16+U15 -> 1124.1414 | V17: =+V16+V15 -> 1146.702 | W17: =+W16+W15 -> 1177.9238 | X17: =+X16+X15 -> 1238.2411 | Y17: =+Y16+Y15 -> 1284.9182 | ... AP17: =+AP16+AP15 -> #REF!
R18: =+#REF! -> #REF! | S18: =+R18 -> #REF! | T18: =+S18 -> #REF! | U18: =+T18 -> #REF! | V18: =+U18 -> #REF! | W18: =+V18 -> #REF! | X18: =+W18 -> #REF! | Y18: =+X18 -> #REF! | Z18: =+Y18 -> #REF! | ... AG18: =+AF18 -> #REF!
B32: Fórmula

Sheet Sep19
B2: Costo Resina Virgen | F2: =+AP11 -> #REF! | J2: 0.05
B3: Costo Resina PCR Enkador | F3: =+AP14 -> #REF! | J3: =+F2*J2 -> #REF!
C4: =+(C9+C10)/C6*1000 -> #REF! | D4: =+(G9+G10)/G6*1000 -> #REF! | E4: =+(E9+E10)/E6*1000 -> #REF! | F4: =+(F9+F10)/F6*1000 -> #REF! | I4: =+(I9+I10)/I6*1000 -> #REF!
B5: Preformas | C5: 200cc Pony | D5: 330cc Pony | E5: 330cc Pony | F5: 330cc Pony | G5: 1 Litro Pony | H5: 1 Litro Pony | I5: 1 Litro Pony | L5: Envases | M5: 500ml SG | N5: 500ml CG | O5: 500ml CG | Q5: Rubros | R5: IHS julio para precio septiembre | S5: IHS agosto para precio octubre | T5: IHS septiembre para precio noviembre | U5: IHS Octubre para precio Diciembre | V5: IHS Noviembre para precio Enero | W5: IHS Diciembre para precio Febrero | X5: IHS Enero para precio Marzo | Y5: IHS Febrero para precio Abril | Z5: IHS Marzo para precio Mayo | AA5: IHS Abril para precio Junio | AB5: IHS Mayo para precio Julio | AC5: IHS Junio para precio Agosto | AD5: IHS Julio para precio Septiembre | AE5: IHS Agosto para precio Octubre | AF5: IHS Septiembre para precio Nov | AG5: IHS Octubre para precio Dic | AH5: IHS Noviembre para precio Enero | AI5: IHS Diciembre para precio Febrero | AJ5: IHS Enero para precio Marzo | AK5: IHS Febrero para precio Abril | AL5: IHS Marzo para precio Mayo | AM5: IHS Abril para precio Junio | AN5: IHS Mayo para precio Julio | AO5: IHS Junio precio Agosto | AP5: IHS Julio precio Septiembre
B6: Gramaje | C6: 16.7 | D6: 16.7 | E6: 20.5 | F6: 20.5 | G6: 30.6 | H6: 30.6 | I6: 38.6 | L6: Gramaje | M6: 15 | N6: 20.5 | O6: 20.5 | Q6: IHS Asia Non Coke approved | R6: 938.13 | S6: 959 | T6: 1006.25 | U6: 993.75 | V6: 1015.5 | W6: 1045.6 | X6: 1103.75 | Y6: 1148.75 | Z6: 1167 | AA6: 1221.25 | AB6: 1330 | AC6: =+'IHS (Mod)'!I5 -> 1280 | AD6: =+'IHS (Mod)'!J5 -> 1279.38 | AE6: 1275.5 | AF6: =+#REF! -> #REF! | AG6: =+#REF! -> #REF! | AH6: =+#REF! -> #REF! | AI6: =+#REF! -> #REF! | AJ6: =+#REF! -> #REF! | AK6: =+#REF! -> #REF! | AL6: =+#REF! -> #REF! | AM6: =+#REF! -> #REF! | ... AP6: =+#REF! -> #REF!
B7: Finish | C7: Short | D7: Short | E7: Short | F7: Short | G7: Short | H7: Short | I7: Short | L7: Finish | M7: Short | N7: Short | O7: Short | Q7: Finance Virgen | R7: 25.09 | S7: 25.09 | T7: 25.09 | U7: 25 | V7: 25 | W7: 25 | X7: 25 | Y7: 25 | Z7: 25 | AA7: 25 | AB7: 25 | AC7: 33.139726 | AD7: =+Septiembre18!AD8 -> 33.123674 | AE7: 33.023219 | AF7: 33.023219 | AG7: 32.783733 | AH7: 29.126712 | AI7: 27.395421 | AJ7: 26.796575 | AK7: 13.948459 | AL7: 14.191182 | AM7: 14.255908 | AN7: =((((AN6*4.5%)/365)*210))*50% -> #REF! | AO7: =((((AO6*4.5%)/365)*210))*50% -> #REF! | AP7: =((((AP6*4.5%)/365)*210))*50% -> #REF!
B8: % Resina (Virgen/PCR) | C8: 50% - 50% | D8: 75% - 25% | E8: 1 | F8: 50% - 50% | G8: 1 | H8: 75% - 25% | I8: 50% - 50% | L8: =+B8 -> % Resina (Virgen/PCR) | M8: 75% - 25% | N8: 1 | O8: 75% - 25% | Q8: Freight China-Gye | R8: 65 | S8: 65 | T8: 65 | U8: 65 | V8: 65 | W8: 65 | X8: 65 | Y8: 65 | Z8: 65 | AA8: 65 | AB8: 65 | AC8: 70 | AD8: 70 | AE8: 70 | AF8: 70 | AG8: 70 | AH8: 70 | AI8: 70 | AJ8: 70 | AK8: 70 | AL8: 70 | AM8: 70 | AN8: 70 | AO8: 70 | AP8: 70
B9: Resina Virgen | C9: =+(C6*F2/1000)*1.01*50% -> #REF! | D9: =+(D6*$F$2/1000)*1.01*75% -> #REF! | E9: =+(E6*$F$2/1000)*1.01 -> #REF! | F9: =+(F6*$F$2/1000)*1.01*50% -> #REF! | G9: =+(G6*F2/1000)*1.01 -> #REF! | H9: =+(H6*$F$2/1000)*1.01*75% -> #REF! | I9: =+(I6*$F$2/1000)*1.01*50% -> #REF! | L9: Resina Virgen | M9: =+(M6*F2/1000)*1.005*75% -> #REF! | N9: =+(N6*F2/1000)*1.005 -> #REF! | O9: =+(O6*F2/1000)*1.005*75% -> #REF! | R9: =SUM(R6:R8) -> 1028.22 | S9: =SUM(S6:S8) -> 1049.09 | T9: =SUM(T6:T8) -> 1096.34 | U9: =SUM(U6:U8) -> 1083.75 | V9: =SUM(V6:V8) -> 1105.5 | W9: =SUM(W6:W8) -> 1135.6 | X9: =SUM(X6:X8) -> 1193.75 | Y9: =SUM(Y6:Y8) -> 1238.75 | ... AP9: =SUM(AP6:AP8) -> #REF!
B10: Resina PCR | C10: =+(C6*$F$3/1000)*1.01*50% -> #REF! | D10: =+(D6*$F$3/1000)*1.01*25% -> #REF! | E10: 0 | F10: =+(F6*$F$3/1000)*1.01*50% -> #REF! | G10: 0 | H10: =+(H6*$F$3/1000)*1.01*25% -> #REF! | I10: =+(I6*$F$3/1000)*1.01*50% -> #REF! | L10: Resina PCR | M10: =+(M6*F3/1000)*1.005*25% -> #REF! | N10: 0 | O10: =+(O6*F3/1000)*1.005*25% -> #REF! | Q10: Landed factor 4% | R10: =+R9*4% -> 41.1288 | S10: =+S9*4% -> 41.9636 | T10: =+T9*4% -> 43.8536 | U10: =+U9*4% -> 43.35 | V10: =+V9*4% -> 44.22 | W10: =+W9*4% -> 45.424 | X10: =+X9*4% -> 47.75 | Y10: =+Y9*4% -> 49.55 | ... AP10: =+AP9*4% -> #REF!
B11: Resina TM | C11: =SUM(C9:C10) -> #REF! | D11: =SUM(D9:D10) -> #REF! | E11: =SUM(E9:E10) -> #REF! | F11: =SUM(F9:F10) -> #REF! | G11: =SUM(G9:G10) -> #REF! | H11: =SUM(H9:H10) -> #REF! | I11: =SUM(I9:I10) -> #REF! | J11: =SUM(J9:J10) -> 0 | L11: Resina TM | M11: =SUM(M9:M10) -> #REF! | N11: =SUM(N9:N10) -> #REF! | O11: =SUM(O9:O10) -> #REF! | Q11: Total resin price | R11: =+R10+R9 -> 1069.3488 | S11: =+S10+S9 -> 1091.0536 | T11: =+T10+T9 -> 1140.1936 | U11: =+U10+U9 -> 1127.1 | V11: =+V10+V9 -> 1149.72 | W11: =+W10+W9 -> 1181.024 | X11: =+X10+X9 -> 1241.5 | Y11: =+Y10+Y9 -> 1288.3 | ... AP11: =+AP10+AP9 -> #REF!
B12: Conversión | C12: =8.2+0.03 -> 8.23 | D12: 8.23 | E12: =8.2+0.03 -> 8.23 | F12: =8.2+0.03 -> 8.23 | G12: 11.2 | H12: 11.2 | I12: =11.15+0.05 -> 11.2 | L12: Conversión | M12: =27.2+0.11 -> 27.31 | N12: =27.2+0.12 -> 27.32 | O12: =27.2+0.12 -> 27.32 | Q12: Resin PCR % | R12: =+R11*(1-5%) -> 1015.8814 | S12: =+S11*(1-5%) -> 1036.5009 | T12: =+T11*(1-5%) -> 1083.1839 | U12: =+U11*(1-5%) -> 1070.745 | V12: =+V11*(1-5%) -> 1092.234 | W12: =+W11*(1-5%) -> 1121.9728 | X12: =+X11*(1-5%) -> 1179.425 | Y12: =+Y11*(1-5%) -> 1223.885 | ... AM12: =+AM11*(1-5%) -> #REF! | AN12: 1267 | AO12: =+AO11*(1-5%) -> #REF! | AP12: =+AP11*(1-5%) -> #REF! | AQ12: 1267 | AR12: Costo resina PCR Enkador
B13: Pigmento | C13: 1.5 | D13: 1.5 | E13: 1.83 | F13: 1.83 | G13: 3.45 | H13: 3.45 | I13: 3.45 | L13: Pigmento | M13: 0.9 | N13: 2.18 | O13: 2.18 | Q13: Finance PCR | R13: Finance | S13: Finance | T13: Finance | U13: Finance | V13: Finance | W13: Finance | X13: Finance | Y13: Finance | Z13: Finance | AA13: Finance | AB13: Finance | AC13: Finance | AD13: Finance | AE13: Finance | AF13: Finance | AG13: Finance | AH13: Finance | AI13: Finance | AJ13: 0 | AK13: =+AS13 -> 0 | AL13: 15.097681 | AM13: 15.162458 | AN13: =((((AN12*4.5%)/365)*210))*50% -> 16.401575 | AO13: =((((AO12*4.5%)/365)*210))*50% -> #REF! | AP13: =((((AP12*4.5%)/365)*210))*50% -> #REF! | AQ13: =+AP14-AQ12 -> #REF! | AR13: Diferencia vs el precio anterior
B14: Empaque | C14: 0.19 | D14: 0.19 | E14: 0.19 | F14: 0.19 | G14: 0.33 | H14: 0.33 | I14: 0.33 | L14: Empaque | M14: 4.3 | N14: 4.3 | O14: 4.3 | Q14: Precio Resin PCR | AK14: =+AK12+AK13 -> #REF! | AL14: =+AL12+AL13 -> #REF! | AM14: =+AM12+AM13 -> #REF! | AN14: =+AN12+AN13 -> 1283.4016 | AO14: =+AO12+AO13 -> #REF! | AP14: =+AP12+AP13 -> #REF!
B15: Flete | C15: 0.16 | D15: 0.16 | E15: 0.16 | F15: 0.16 | G15: 0.28 | H15: 0.28 | I15: 0.28 | L15: Flete | M15: 8.36 | N15: 8.36 | O15: 8.36 | Q15: Precio ponderado bajo formula | R15: =+R11*75%+R12*25% -> 1055.9819 | S15: =+S11*75%+S12*25% -> 1077.4154 | T15: =+T11*75%+T12*25% -> 1125.9412 | U15: =+U11*75%+U12*25% -> 1113.0113 | V15: =+V11*75%+V12*25% -> 1135.3485 | W15: =+W11*75%+W12*25% -> 1166.2612 | X15: =+X11*75%+X12*25% -> 1225.9813 | Y15: =+Y11*75%+Y12*25% -> 1272.1962 | ... AH15: =+AH11*75%+AH12*25% -> #REF! | AI15: =+AI11*50%+AI12*50% -> #REF! | AJ15: =+AJ11*50%+AJ12*50% -> #REF! | AK15: =+AK11*50%+AK14*50% -> #REF! | AL15: =+AL11*50%+AL14*50% -> #REF! | AM15: =+AM11*50%+AM14*50% -> #REF! | AN15: =+AN11*50%+AN14*50% -> #REF! | AO15: =+AO11*50%+AO14*50% -> #REF! | AP15: =+AP11*50%+AP14*50% -> #REF!
B16: Total | C16: =+C11+C12+C13+C14+C15 -> #REF! | D16: =+D11+D12+D13+D14+D15 -> #REF! | E16: =+E11+E12+E13+E14+E15 -> #REF! | F16: =+F11+F12+F13+F14+F15 -> #REF! | G16: =+G11+G12+G13+G14+G15 -> #REF! | H16: =+H11+H12+H13+H14+H15 -> #REF! | I16: =+I11+I12+I13+I14+I15 -> #REF! | L16: Total | M16: =+M11+M12+M13+M14+M15 -> #REF! | N16: =+N11+N12+N13+N14+N15 -> #REF! | O16: =+O11+O12+O13+O14+O15 -> #REF! | Q16: Scrap 1% | R16: =+R15*1% -> 10.559819 | S16: =+S15*1% -> 10.774154 | T16: =+T15*1% -> 11.259412 | U16: =+U15*1% -> 11.130113 | V16: =+V15*1% -> 11.353485 | W16: =+W15*1% -> 11.662612 | X16: =+X15*1% -> 12.259813 | Y16: =+Y15*1% -> 12.721963 | ... AP16: =+AP15*1% -> #REF!
Q17: Precio ponderado con scrap | R17: =+R16+R15 -> 1066.5418 | S17: =+S16+S15 -> 1088.1896 | T17: =+T16+T15 -> 1137.2006 | U17: =+U16+U15 -> 1124.1414 | V17: =+V16+V15 -> 1146.702 | W17: =+W16+W15 -> 1177.9238 | X17: =+X16+X15 -> 1238.2411 | Y17: =+Y16+Y15 -> 1284.9182 | ... AP17: =+AP16+AP15 -> #REF!
R18: =+#REF! -> #REF! | S18: =+R18 -> #REF! | T18: =+S18 -> #REF! | U18: =+T18 -> #REF! | V18: =+U18 -> #REF! | W18: =+V18 -> #REF! | X18: =+W18 -> #REF! | Y18: =+X18 -> #REF! | Z18: =+Y18 -> #REF! | ... AG18: =+AF18 -> #REF!
B32: Fórmula

Sheet Ejercicio costo PCR
C2: Rubros | D2: IHS Junio precio Agosto
C3: IHS Asia Non Coke approved | D3: 926.25
C4: Finance Virgen | D4: =((((D3*4.5%)/365)*210))*50% -> 11.990497
C5: Freight China-Gye | D5: 70
C6: Costo Resina Finance + Freight | D6: =SUM(D3:D5) -> 1008.2405
C7: Landed factor 4% | D7: =+D6*4% -> 40.32962
C8: Precio Resina Virgen | D8: =+D7+D6 -> 1048.5701
C9: Resin PCR % | D9: =D8*(1-5%) -> 996.14161
C10: Finance PCR | D10: =((((D9*4.5%)/365)*210))*50% -> 12.895258
C11: Precio Resina Enkador (según contrato) | D11: =+D9+D10 -> 1009.0369
C12: Costo Real Resina PCR ENKADOR | D12: 1267
C13: Diferencia precio vs costo TM | D13: =+D11-D12 -> -257.96313

Sheet Oct19
B2: Costo Resina Virgen | F2: =+AQ12 -> #REF! | J2: 0.05
B3: Costo Resina PCR Enkador | F3: =+AQ15 -> #REF! | J3: =+F2*J2 -> #REF!
C4: =+(C10+C11)/C6*1000 -> #REF! | D4: =+(G10+G11)/G6*1000 -> #REF! | E4: =+(E10+E11)/E6*1000 -> #REF! | F4: =+(F10+F11)/F6*1000 -> #REF! | I4: =+(I10+I11)/I6*1000 -> #REF!
B5: Preformas | C5: 200cc Pony | D5: 330cc Pony | E5: 330cc Pony | F5: 330cc Pony | G5: 1 Litro Pony | H5: 1 Litro Pony | I5: 1 Litro Pony | L5: Envases | M5: 500ml SG | N5: 500ml CG | O5: 500ml CG | Q5: Rubros | R5: IHS julio para precio septiembre | S5: IHS agosto para precio octubre | T5: IHS septiembre para precio noviembre | U5: IHS Octubre para precio Diciembre | V5: IHS Noviembre para precio Enero | W5: IHS Diciembre para precio Febrero | X5: IHS Enero para precio Marzo | Y5: IHS Febrero para precio Abril | Z5: IHS Marzo para precio Mayo | AA5: IHS Abril para precio Junio | AB5: IHS Mayo para precio Julio | AC5: IHS Junio para precio Agosto | AD5: IHS Julio para precio Septiembre | AE5: IHS Agosto para precio Octubre | AF5: IHS Septiembre para precio Nov | AG5: IHS Octubre para precio Dic | AH5: IHS Noviembre para precio Enero | AI5: IHS Diciembre para precio Febrero | AJ5: IHS Enero para precio Marzo | AK5: IHS Febrero para precio Abril | AL5: IHS Marzo para precio Mayo | AM5: IHS Abril para precio Junio | AN5: IHS Mayo para precio Julio | AO5: IHS Junio precio Agosto | AP5: IHS Julio precio Septiembre | AQ5: IHS Agosto precio Octubre
B6: Gramaje | C6: 16.7 | D6: 16.7 | E6: 20.5 | F6: 20.5 | G6: 30.6 | H6: 30.6 | I6: 38.6 | L6: Gramaje | M6: 15 | N6: 20.5 | O6: 20.5 | Q6: IHS Asia Non Coke approved | R6: 938.13 | S6: 959 | T6: 1006.25 | U6: 993.75 | V6: 1015.5 | W6: 1045.6 | X6: 1103.75 | Y6: 1148.75 | Z6: 1167 | AA6: 1221.25 | AB6: 1330 | AC6: =+'IHS (Mod)'!I5 -> 1280 | AD6: =+'IHS (Mod)'!J5 -> 1279.38 | AE6: 1275.5 | AF6: =+#REF! -> #REF! | AG6: =+#REF! -> #REF! | AH6: =+#REF! -> #REF! | AI6: =+#REF! -> #REF! | AJ6: =+#REF! -> #REF! | AK6: =+#REF! -> #REF! | AL6: =+#REF! -> #REF! | AM6: =+#REF! -> #REF! | ... AQ6: =+#REF! -> #REF!
B7: Finish | C7: Short | D7: Short | E7: Short | F7: Short | G7: Short | H7: Short | I7: Short | L7: Finish | M7: Short | N7: Short | O7: Short | Q7: Finance Virgen | R7: 25.09 | S7: 25.09 | T7: 25.09 | U7: 25 | V7: 25 | W7: 25 | X7: 25 | Y7: 25 | Z7: 25 | AA7: 25 | AB7: 25 | AC7: 33.139726 | AD7: =+Septiembre18!AD8 -> 33.123674 | AE7: 33.023219 | AF7: 33.023219 | AG7: 32.783733 | AH7: 29.126712 | AI7: 27.395421 | AJ7: 26.796575 | AK7: 13.948459 | AL7: 14.191182 | AM7: 14.255908 | AN7: =((((AN6*4.5%)/365)*210))*50% -> #REF! | AO7: =((((AO6*4.5%)/365)*210))*50% -> #REF! | AP7: =((((AP6*4.5%)/365)*210))*50% -> #REF! | AQ7: =((((AQ6*4.5%)/365)*210))*50% -> #REF!
B8: Codigo producto | C8: 50025364 | F8: 50028383 | I8: 50028046 | M8: 50023224 | N8: 50023395
B9: % Resina (Virgen/PCR) | C9: 50% - 50% | D9: 75% - 25% | E9: 1 | F9: 50% - 50% | G9: 1 | H9: 75% - 25% | I9: 50% - 50% | L9: =+B9 -> % Resina (Virgen/PCR) | M9: 75% - 25% | N9: 1 | O9: 75% - 25% | Q9: Freight China-Gye | R9: 65 | S9: 65 | T9: 65 | U9: 65 | V9: 65 | W9: 65 | X9: 65 | Y9: 65 | Z9: 65 | AA9: 65 | AB9: 65 | AC9: 70 | AD9: 70 | AE9: 70 | AF9: 70 | AG9: 70 | AH9: 70 | AI9: 70 | AJ9: 70 | AK9: 70 | AL9: 70 | AM9: 70 | AN9: 70 | AO9: 70 | AP9: 70 | AQ9: 70
B10: Resina Virgen | C10: =+(C6*F2/1000)*1.01*50% -> #REF! | D10: =+(D6*$F$2/1000)*1.01*75% -> #REF! | E10: =+(E6*$F$2/1000)*1.01 -> #REF! | F10: =+(F6*$F$2/1000)*1.01*50% -> #REF! | G10: =+(G6*F2/1000)*1.01 -> #REF! | H10: =+(H6*$F$2/1000)*1.01*75% -> #REF! | I10: =+(I6*$F$2/1000)*1.01*50% -> #REF! | L10: Resina Virgen | M10: =+(M6*F2/1000)*1.005*75% -> #REF! | N10: =+(N6*F2/1000)*1.005 -> #REF! | O10: =+(O6*F2/1000)*1.005*75% -> #REF! | R10: =SUM(R6:R9) -> 1028.22 | S10: =SUM(S6:S9) -> 1049.09 | T10: =SUM(T6:T9) -> 1096.34 | U10: =SUM(U6:U9) -> 1083.75 | V10: =SUM(V6:V9) -> 1105.5 | W10: =SUM(W6:W9) -> 1135.6 | X10: =SUM(X6:X9) -> 1193.75 | Y10: =SUM(Y6:Y9) -> 1238.75 | ... AQ10: =SUM(AQ6:AQ9) -> #REF!
B11: Resina PCR | C11: =+(C6*$F$3/1000)*1.01*50% -> #REF! | D11: =+(D6*$F$3/1000)*1.01*25% -> #REF! | E11: 0 | F11: =+(F6*$F$3/1000)*1.01*50% -> #REF! | G11: 0 | H11: =+(H6*$F$3/1000)*1.01*25% -> #REF! | I11: =+(I6*$F$3/1000)*1.01*50% -> #REF! | L11: Resina PCR | M11: =+(M6*F3/1000)*1.005*25% -> #REF! | N11: 0 | O11: =+(O6*F3/1000)*1.005*25% -> #REF! | Q11: Landed factor 4% | R11: =+R10*4% -> 41.1288 | S11: =+S10*4% -> 41.9636 | T11: =+T10*4% -> 43.8536 | U11: =+U10*4% -> 43.35 | V11: =+V10*4% -> 44.22 | W11: =+W10*4% -> 45.424 | X11: =+X10*4% -> 47.75 | Y11: =+Y10*4% -> 49.55 | ... AQ11: =+AQ10*4% -> #REF!
B12: Resina TM | C12: =SUM(C10:C11) -> #REF! | D12: =SUM(D10:D11) -> #REF! | E12: =SUM(E10:E11) -> #REF! | F12: =SUM(F10:F11) -> #REF! | G12: =SUM(G10:G11) -> #REF! | H12: =SUM(H10:H11) -> #REF! | I12: =SUM(I10:I11) -> #REF! | J12: =SUM(J10:J11) -> 0 | L12: Resina TM | M12: =SUM(M10:M11) -> #REF! | N12: =SUM(N10:N11) -> #REF! | O12: =SUM(O10:O11) -> #REF! | Q12: Total resin price | R12: =+R11+R10 -> 1069.3488 | S12: =+S11+S10 -> 1091.0536 | T12: =+T11+T10 -> 1140.1936 | U12: =+U11+U10 -> 1127.1 | V12: =+V11+V10 -> 1149.72 | W12: =+W11+W10 -> 1181.024 | X12: =+X11+X10 -> 1241.5 | Y12: =+Y11+Y10 -> 1288.3 | ... AQ12: =+AQ11+AQ10 -> #REF!
B13: Conversión | C13: =8.2+0.03 -> 8.23 | D13: 8.23 | E13: =8.2+0.03 -> 8.23 | F13: =8.2+0.03 -> 8.23 | G13: 11.2 | H13: 11.2 | I13: =11.15+0.05 -> 11.2 | L13: Conversión | M13: =27.2+0.11 -> 27.31 | N13: =27.2+0.12 -> 27.32 | O13: =27.2+0.12 -> 27.32 | Q13: Resin PCR % | R13: =+R12*(1-5%) -> 1015.8814 | S13: =+S12*(1-5%) -> 1036.5009 | T13: =+T12*(1-5%) -> 1083.1839 | U13: =+U12*(1-5%) -> 1070.745 | V13: =+V12*(1-5%) -> 1092.234 | W13: =+W12*(1-5%) -> 1121.9728 | X13: =+X12*(1-5%) -> 1179.425 | Y13: =+Y12*(1-5%) -> 1223.885 | ... AM13: =+AM12*(1-5%) -> #REF! | AN13: 1267 | AO13: =+AO12*(1-5%) -> #REF! | AP13: =+AP12*(1-5%) -> #REF! | AQ13: =+AQ12*(1-5%) -> #REF! | AR13: 1267 | AS13: Costo resina PCR Enkador
B14: Pigmento | C14: 1.5 | D14: 1.5 | E14: 1.83 | F14: 1.83 | G14: 3.45 | H14: 3.45 | I14: 3.45 | L14: Pigmento | M14: 0.9 | N14: 2.18 | O14: 2.18 | Q14: Finance PCR | R14: Finance | S14: Finance | T14: Finance | U14: Finance | V14: Finance | W14: Finance | X14: Finance | Y14: Finance | Z14: Finance | AA14: Finance | AB14: Finance | AC14: Finance | AD14: Finance | AE14: Finance | AF14: Finance | AG14: Finance | AH14: Finance | AI14: Finance | AJ14: 0 | AK14: =+AT14 -> 0 | AL14: 15.097681 | AM14: 15.162458 | AN14: =((((AN13*4.5%)/365)*210))*50% -> 16.401575 | AO14: =((((AO13*4.5%)/365)*210))*50% -> #REF! | AP14: =((((AP13*4.5%)/365)*210))*50% -> #REF! | AQ14: =((((AQ13*4.5%)/365)*210))*50% -> #REF! | AR14: =+AQ15-AR13 -> #REF! | AS14: Diferencia vs el precio anterior
B15: Empaque | C15: 0.19 | D15: 0.19 | E15: 0.19 | F15: 0.19 | G15: 0.33 | H15: 0.33 | I15: 0.33 | L15: Empaque | M15: 4.3 | N15: 4.3 | O15: 4.3 | Q15: Precio Resin PCR | AK15: =+AK13+AK14 -> #REF! | AL15: =+AL13+AL14 -> #REF! | AM15: =+AM13+AM14 -> #REF! | AN15: =+AN13+AN14 -> 1283.4016 | AO15: =+AO13+AO14 -> #REF! | AP15: =+AP13+AP14 -> #REF! | AQ15: =+AQ13+AQ14 -> #REF!
B16: Flete | C16: 0.16 | D16: 0.16 | E16: 0.16 | F16: 0.16 | G16: 0.28 | H16: 0.28 | I16: 0.28 | L16: Flete | M16: 8.36 | N16: 8.36 | O16: 8.36 | Q16: Precio ponderado bajo formula | R16: =+R12*75%+R13*25% -> 1055.9819 | S16: =+S12*75%+S13*25% -> 1077.4154 | T16: =+T12*75%+T13*25% -> 1125.9412 | U16: =+U12*75%+U13*25% -> 1113.0113 | V16: =+V12*75%+V13*25% -> 1135.3485 | W16: =+W12*75%+W13*25% -> 1166.2612 | X16: =+X12*75%+X13*25% -> 1225.9813 | Y16: =+Y12*75%+Y13*25% -> 1272.1962 | ... AH16: =+AH12*75%+AH13*25% -> #REF! | AI16: =+AI12*50%+AI13*50% -> #REF! | AJ16: =+AJ12*50%+AJ13*50% -> #REF! | AK16: =+AK12*50%+AK15*50% -> #REF! | AL16: =+AL12*50%+AL15*50% -> #REF! | AM16: =+AM12*50%+AM15*50% -> #REF! | AN16: =+AN12*50%+AN15*50% -> #REF! | AO16: =+AO12*50%+AO15*50% -> #REF! | AP16: =+AP12*50%+AP15*50% -> #REF! | AQ16: =+AQ12*50%+AQ15*50% -> #REF!
B17: Total | C17: =+C12+C13+C14+C15+C16 -> #REF! | D17: =+D12+D13+D14+D15+D16 -> #REF! | E17: =+E12+E13+E14+E15+E16 -> #REF! | F17: =+F12+F13+F14+F15+F16 -> #REF! | G17: =+G12+G13+G14+G15+G16 -> #REF! | H17: =+H12+H13+H14+H15+H16 -> #REF! | I17: =+I12+I13+I14+I15+I16 -> #REF! | L17: Total | M17: =+M12+M13+M14+M15+M16 -> #REF! | N17: =+N12+N13+N14+N15+N16 -> #REF! | O17: =+O12+O13+O14+O15+O16 -> #REF! | Q17: Scrap 1% | R17: =+R16*1% -> 10.559819 | S17: =+S16*1% -> 10.774154 | T17: =+T16*1% -> 11.259412 | U17: =+U16*1% -> 11.130113 | V17: =+V16*1% -> 11.353485 | W17: =+W16*1% -> 11.662612 | X17: =+X16*1% -> 12.259813 | Y17: =+Y16*1% -> 12.721963 | ... AQ17: =+AQ16*1% -> #REF!
Q18: Precio ponderado con scrap | R18: =+R17+R16 -> 1066.5418 | S18: =+S17+S16 -> 1088.1896 | T18: =+T17+T16 -> 1137.2006 | U18: =+U17+U16 -> 1124.1414 | V18: =+V17+V16 -> 1146.702 | W18: =+W17+W16 -> 1177.9238 | X18: =+X17+X16 -> 1238.2411 | Y18: =+Y17+Y16 -> 1284.9182 | ... AQ18: =+AQ17+AQ16 -> #REF!
R19: =+#REF! -> #REF! | S19: =+R19 -> #REF! | T19: =+S19 -> #REF! | U19: =+T19 -> #REF! | V19: =+U19 -> #REF! | W19: =+V19 -> #REF! | X19: =+W19 -> #REF! | Y19: =+X19 -> #REF! | Z19: =+Y19 -> #REF! | ... AG19: =+AF19 -> #REF!
F23: =+F22-F20 -> 0
B33: Fórmula

Sheet Mayo20 (2)
B2: Costo Resina Virgen | F2: =+AX12 -> #REF! | J2: 0.05
B3: Costo Resina PCR Enkador | F3: =+AX16 -> 1344.6848 | J3: =+F2*J2 -> #REF!
C4: =+(C10+C11)/C6*1000 -> #REF! | D4: =+(G10+G11)/G6*1000 -> #REF! | E4: =+(E10+E11)/E6*1000 -> #REF! | F4: =+(F10+F11)/F6*1000 -> #REF! | I4: =+(I10+I11)/I6*1000 -> #REF!
B5: Preformas | C5: 200cc Pony | D5: 330cc Pony | E5: 330cc Pony | F5: 330cc Pony | G5: 1 Litro Pony | H5: 1 Litro Pony | I5: 1 Litro Pony | L5: Envases | M5: 500ml SG | N5: 500ml CG | O5: 500ml CG | Q5: Rubros | R5: IHS julio para precio septiembre | S5: IHS agosto para precio octubre | T5: IHS septiembre para precio noviembre | U5: IHS Octubre para precio Diciembre | V5: IHS Noviembre para precio Enero | W5: IHS Diciembre para precio Febrero | X5: IHS Enero para precio Marzo | Y5: IHS Febrero para precio Abril | Z5: IHS Marzo para precio Mayo | AA5: IHS Abril para precio Junio | AB5: IHS Mayo para precio Julio | AC5: IHS Junio para precio Agosto | AD5: IHS Julio para precio Septiembre | AE5: IHS Agosto para precio Octubre | AF5: IHS Septiembre para precio Nov | AG5: IHS Octubre para precio Dic | AH5: IHS Noviembre para precio Enero | AI5: IHS Diciembre para precio Febrero | AJ5: IHS Enero para precio Marzo | AK5: IHS Febrero para precio Abril | AL5: IHS Marzo para precio Mayo | AM5: IHS Abril para precio Junio | AN5: IHS Mayo para precio Julio | AO5: IHS Junio precio Agosto | AP5: IHS Julio precio Septiembre | AQ5: IHS Agosto precio Octubre | AR5: IHS Septiembre precio Noviembre | AS5: IHS Octubre precio Diciembre | AT5: IHS Nov19 precio Enero2020 | AU5: IHS Dic19 precio Feb 2020 | AV5: IHS Ene20 precio Mar 2020 | AW5: IHS Feb20 precio Abril 2020 | AX5: IHS Mar20 precio Mayo 2020
B6: Gramaje | C6: 16.7 | D6: 16.7 | E6: 20.5 | F6: 20.5 | G6: 30.6 | H6: 30.6 | I6: 38.6 | L6: Gramaje | M6: 15 | N6: 20.5 | O6: 20.5 | Q6: IHS Asia Non Coke approved | R6: 938.13 | S6: 959 | T6: 1006.25 | U6: 993.75 | V6: 1015.5 | W6: 1045.6 | X6: 1103.75 | Y6: 1148.75 | Z6: 1167 | AA6: 1221.25 | AB6: 1330 | AC6: =+'IHS (Mod)'!I5 -> 1280 | AD6: =+'IHS (Mod)'!J5 -> 1279.38 | AE6: 1275.5 | AF6: =+#REF! -> #REF! | AG6: =+#REF! -> #REF! | AH6: =+#REF! -> #REF! | AI6: =+#REF! -> #REF! | AJ6: =+#REF! -> #REF! | AK6: =+#REF! -> #REF! | AL6: =+#REF! -> #REF! | AM6: =+#REF! -> #REF! | ... AX6: =+#REF! -> #REF!
B7: Finish | C7: Short | D7: Short | E7: Short | F7: Short | G7: Short | H7: Short | I7: Short | L7: Finish | M7: Short | N7: Short | O7: Short | Q7: Finance Virgen | R7: 25.09 | S7: 25.09 | T7: 25.09 | U7: 25 | V7: 25 | W7: 25 | X7: 25 | Y7: 25 | Z7: 25 | AA7: 25 | AB7: 25 | AC7: 33.139726 | AD7: =+Septiembre18!AD8 -> 33.123674 | AE7: 33.023219 | AF7: 33.023219 | AG7: 32.783733 | AH7: 29.126712 | AI7: 27.395421 | AJ7: 26.796575 | AK7: 13.948459 | AL7: 14.191182 | AM7: 14.255908 | AN7: =((((AN6*4.5%)/365)*210))*50% -> #REF! | AO7: =((((AO6*4.5%)/365)*210))*50% -> #REF! | AP7: =((((AP6*4.5%)/365)*210))*50% -> #REF! | AQ7: =((((AQ6*4.5%)/365)*210))*50% -> #REF! | AR7: =((((AR6*4.5%)/365)*210))*50% -> #REF! | AS7: =((((AS6*4.5%)/365)*210))*50% -> #REF! | AT7: =((((AT6*4.5%)/365)*210))*50% -> #REF! | AU7: =((((AU6*4.5%)/365)*210))*50% -> #REF! | ... AX7: =((((AX6*4.5%)/365)*210))*50% -> #REF!
B8: Codigo producto | C8: 50025364 | F8: 50028383 | I8: 50028046 | M8: 50023224 | N8: 50023395
B9: % Resina (Virgen/PCR) | C9: 50% - 50% | D9: 75% - 25% | E9: 1 | F9: 50% - 50% | G9: 1 | H9: 75% - 25% | I9: 50% - 50% | L9: =+B9 -> % Resina (Virgen/PCR) | M9: 75% - 25% | N9: 1 | O9: 75% - 25% | Q9: International Freight | R9: 65 | S9: 65 | T9: 65 | U9: 65 | V9: 65 | W9: 65 | X9: 65 | Y9: 65 | Z9: 65 | AA9: 65 | AB9: 65 | AC9: 70 | AD9: 70 | AE9: 70 | AF9: 70 | AG9: 70 | AH9: 70 | AI9: 70 | AJ9: 70 | AK9: 70 | AL9: 70 | AM9: 70 | AN9: 70 | AO9: 70 | AP9: 70 | AQ9: 70 | AR9: 70 | AS9: 70 | AT9: 70 | AU9: 90.46 | AV9: 78.56 | AW9: 78.56 | AX9: 78.56
B10: Resina Virgen | C10: =+(C6*F2/1000)*1.01*50% -> #REF! | D10: =+(D6*$F$2/1000)*1.01*75% -> #REF! | E10: =+(E6*$F$2/1000)*1.01 -> #REF! | F10: =+(F6*$F$2/1000)*1.01*50% -> #REF! | G10: =+(G6*F2/1000)*1.01 -> #REF! | H10: =+(H6*$F$2/1000)*1.01*75% -> #REF! | I10: =+(I6*$F$2/1000)*1.01*50% -> #REF! | L10: Resina Virgen | M10: =+(M6*F2/1000)*1.005*75% -> #REF! | N10: =+(N6*F2/1000)*1.005 -> #REF! | O10: =+(O6*F2/1000)*1.005*75% -> #REF! | R10: =SUM(R6:R9) -> 1028.22 | S10: =SUM(S6:S9) -> 1049.09 | T10: =SUM(T6:T9) -> 1096.34 | U10: =SUM(U6:U9) -> 1083.75 | V10: =SUM(V6:V9) -> 1105.5 | W10: =SUM(W6:W9) -> 1135.6 | X10: =SUM(X6:X9) -> 1193.75 | Y10: =SUM(Y6:Y9) -> 1238.75 | ... AX10: =SUM(AX6:AX9) -> #REF!
B11: Resina PCR | C11: =+(C6*$F$3/1000)*1.01*50% -> 11.340399 | D11: =+(D6*$F$3/1000)*1.01*25% -> 5.6701995 | E11: 0 | F11: =+(F6*$F$3/1000)*1.01*50% -> 13.920849 | G11: 0 | H11: =+(H6*$F$3/1000)*1.01*25% -> 10.389707 | I11: =+(I6*$F$3/1000)*1.01*50% -> 26.21194 | L11: Resina PCR | M11: =+(M6*F3/1000)*1.005*25% -> 5.0677807 | N11: 0 | O11: =+(O6*F3/1000)*1.005*25% -> 6.9259669 | Q11: Landed factor 4% | R11: =+R10*4% -> 41.1288 | S11: =+S10*4% -> 41.9636 | T11: =+T10*4% -> 43.8536 | U11: =+U10*4% -> 43.35 | V11: =+V10*4% -> 44.22 | W11: =+W10*4% -> 45.424 | X11: =+X10*4% -> 47.75 | Y11: =+Y10*4% -> 49.55 | ... AX11: =+AX10*4% -> #REF!
B12: Resina TM | C12: =SUM(C10:C11) -> #REF! | D12: =SUM(D10:D11) -> #REF! | E12: =SUM(E10:E11) -> #REF! | F12: =SUM(F10:F11) -> #REF! | G12: =SUM(G10:G11) -> #REF! | H12: =SUM(H10:H11) -> #REF! | I12: =SUM(I10:I11) -> #REF! | J12: =SUM(J10:J11) -> 0 | L12: Resina TM | M12: =SUM(M10:M11) -> #REF! | N12: =SUM(N10:N11) -> #REF! | O12: =SUM(O10:O11) -> #REF! | Q12: Total resin price | R12: =+R11+R10 -> 1069.3488 | S12: =+S11+S10 -> 1091.0536 | T12: =+T11+T10 -> 1140.1936 | U12: =+U11+U10 -> 1127.1 | V12: =+V11+V10 -> 1149.72 | W12: =+W11+W10 -> 1181.024 | X12: =+X11+X10 -> 1241.5 | Y12: =+Y11+Y10 -> 1288.3 | ... AX12: =+AX11+AX10 -> #REF!
B13: Conversión Inyección | C13: 8.25 | D13: 8.23 | E13: =8.2+0.03 -> 8.23 | F13: 8.25 | G13: 11.2 | H13: 11.2 | I13: 11.23 | L13: Conversión Inyección | M13: =+C13 -> 8.25 | N13: =+F13 -> 8.25 | O13: 8.23 | Q13: Resin PCR % | R13: =+R12*(1-5%) -> 1015.8814 | S13: =+S12*(1-5%) -> 1036.5009 | T13: =+T12*(1-5%) -> 1083.1839 | U13: =+U12*(1-5%) -> 1070.745 | V13: =+V12*(1-5%) -> 1092.234 | W13: =+W12*(1-5%) -> 1121.9728 | X13: =+X12*(1-5%) -> 1179.425 | Y13: =+Y12*(1-5%) -> 1223.885 | ... AM13: =+AM12*(1-5%) -> #REF! | AN13: 1267 | AO13: =+AO12*(1-5%) -> #REF! | AP13: =+AP12*(1-5%) -> #REF! | AQ13: =+AQ12*(1-5%) -> #REF! | AR13: =+AR12*(1-5%) -> #REF! | AS13: =+AS12*(1-5%) -> #REF! | AT13: =+AT12*(1-5%) -> #REF! | AU13: =+AU12*(1-5%) -> #REF! | AV13: =+AV12*(1-5%) -> #REF! | AW13: 1327.5 | AX13: 1327.5 | AY13: 1327.5 | AZ13: Costo resina PCR Enkador (Abril 2020)
B14: Conversión Soplado | C14: 0 | F14: 0 | I14: 0 | L14: Conversión Soplado | M14: =(M15-M13) -> 19.12 | N14: =(N15-N13) -> 19.14 | O14: 19.09
