Workbook

Sheet CSD List
B3: LISTA DE PRECIOS PF CSD AB INBEV
B7: 46082
B9: Type | C9: Preform Weight (gr) | D9: AR$/ 000
B10: SS 500 | C10: 19.5 | D10: =+VLOOKUP(C10,'CSD Pricing'!$D$104:$ZC$121,MATCH('CSD List'!$B$7,'CSD Pricing'!$D$2:$ZD$2,0),0) -> 48764.347
B11: SS 500 - 19.5G PCR 100% | C11: 19.5 | D11: =+VLOOKUP(C11,'CSD Pricing'!$D$104:$ZC$121,MATCH('CSD List'!$B$7,'CSD Pricing'!$D$2:$ZD$2,0),0) -> 48764.347
B12: SS 500 | C12: 22.1 | D12: =+VLOOKUP(C12,'CSD Pricing'!$D$104:$ZC$121,MATCH('CSD List'!$B$7,'CSD Pricing'!$D$2:$ZD$2,0),0) -> 53631.969
B13: SS 500 | C13: 22 | D13: =+VLOOKUP(C13,'CSD Pricing'!$D$104:$ZC$121,MATCH('CSD List'!$B$7,'CSD Pricing'!$D$2:$ZD$2,0),0) -> 0
B14: SS 500 | C14: 25 | D14: =+VLOOKUP(C14,'CSD Pricing'!$D$104:$ZC$121,MATCH('CSD List'!$B$7,'CSD Pricing'!$D$2:$ZD$2,0),0) -> 59061.239
B15: SS 500 - 25G PCR 100% | C15: 25 | D15: =+VLOOKUP(C15,'CSD Pricing'!$D$104:$ZC$121,MATCH('CSD List'!$B$7,'CSD Pricing'!$D$2:$ZD$2,0),0) -> 59061.239
B16: MS 1500 | C16: 37.2 | D16: =+VLOOKUP(C16,'CSD Pricing'!$D$104:$ZC$121,MATCH('CSD List'!$B$7,'CSD Pricing'!$D$2:$ZD$2,0),0) -> 86842.996
B17: MS 1500 | C17: 40 | D17: =+VLOOKUP(C17,'CSD Pricing'!$D$104:$ZC$121,MATCH('CSD List'!$B$7,'CSD Pricing'!$D$2:$ZD$2,0),0) -> 0
B18: MS 1500 | C18: 44 | D18: =+VLOOKUP(C18,'CSD Pricing'!$D$104:$ZC$121,MATCH('CSD List'!$B$7,'CSD Pricing'!$D$2:$ZD$2,0),0) -> 99573.699
B19: MS 2000/2250 | C19: 42.6 | D19: =+VLOOKUP(C19,'CSD Pricing'!$D$104:$ZC$121,MATCH('CSD List'!$B$7,'CSD Pricing'!$D$2:$ZD$2,0),0) -> 0
B20: MS 2000/2250 | C20: 46.6 | D20: =+VLOOKUP(C20,'CSD Pricing'!$D$104:$ZC$121,MATCH('CSD List'!$B$7,'CSD Pricing'!$D$2:$ZD$2,0),0) -> 106366.53
B21: MS 2000/2250 20% PCR | C21: 46.6 | D21: =+VLOOKUP(C21,'CSD Pricing'!$D$104:$ZC$121,MATCH('CSD List'!$B$7,'CSD Pricing'!$D$2:$ZD$2,0),0) -> 106366.53
... B27: MS 3000 | C27: 62 | D27: =+VLOOKUP(C27,'CSD Pricing'!$D$104:$ZC$121,MATCH('CSD List'!$B$7,'CSD Pricing'!$D$2:$ZD$2,0),0) -> 135711.22
B28: SS 500 | C28: 19.5 PQS (U03) | D28: =+VLOOKUP(C28,'CSD Pricing'!#REF!,MATCH('CSD List'!$B$7,'CSD Pricing'!$D$2:$ZD$2,0),0) -> #REF!
B29: MS 1500 | C29: 37.2 PQS (U03) | D29: =+VLOOKUP(C29,'CSD Pricing'!#REF!,MATCH('CSD List'!$B$7,'CSD Pricing'!$D$2:$ZD$2,0),0) -> #REF!
B30: MS 1500 | C30: 44 PQS (U03) | D30: =+VLOOKUP(C30,'CSD Pricing'!#REF!,MATCH('CSD List'!$B$7,'CSD Pricing'!$D$2:$ZD$2,0),0) -> #REF!
B31: MS 2000/2250 | C31: 46.6 PQS (U03) | D31: =+VLOOKUP(C31,'CSD Pricing'!#REF!,MATCH('CSD List'!$B$7,'CSD Pricing'!$D$2:$ZD$2,0),0) -> #REF!
B32: MS 2000/2250 | C32: 52 PQS (U03) | D32: =+VLOOKUP(C32,'CSD Pricing'!#REF!,MATCH('CSD List'!$B$7,'CSD Pricing'!$D$2:$ZD$2,0),0) -> #REF!
B33: MS 3000 | C33: 54.7 PQS (U03) | D33: =+VLOOKUP(C33,'CSD Pricing'!#REF!,MATCH('CSD List'!$B$7,'CSD Pricing'!$D$2:$ZD$2,0),0) -> #REF!
B34: MS 3000 | C34: 62 PQS (U03) | D34: =+VLOOKUP(C34,'CSD Pricing'!#REF!,MATCH('CSD List'!$B$7,'CSD Pricing'!$D$2:$ZD$2,0),0) -> #REF!
B36: Valor Resina Virgen Dak | C36: =HLOOKUP(B7,'CSD Pricing'!2:3,2,0) -> 1257.4968
B37: Valor Resina PQS | C37: =HLOOKUP(B7,'CSD Pricing'!2:5,4,0) -> #N/A
B38: Valor Resina PCR | C38: =HLOOKUP(B7,'CSD Pricing'!2:6,5,0) -> 1257.4968

Sheet HF List
B3: PRICING LIST PF HS AB INBEV
B7: 46082
B9: Type | C9: Preform Weight (gr) | D9: AR$/ 000
B10: 300 ML | C10: 24 | D10: =+VLOOKUP(C10,'HF Pricing'!$D$56:$EB$63,MATCH('HF List'!$B$7,'HF Pricing'!$D$2:$ZB$2,0),0) -> 68103.093
B11: 300 ML | C11: 30 | D11: =+VLOOKUP(C11,'HF Pricing'!$D$56:$EB$63,MATCH('HF List'!$B$7,'HF Pricing'!$D$2:$ZB$2,0),0) -> 80984.313
B12: 300 ML | C12: 30.4 Virgen | D12: =+VLOOKUP(C12,'HF Pricing'!$D$56:$EB$63,MATCH('HF List'!$B$7,'HF Pricing'!$D$2:$ZB$2,0),0) -> 80141.79
B13: 300 ML | C13: 30.4 30% PCR | D13: =+VLOOKUP(C13,'HF Pricing'!$D$56:$ZB$63,MATCH('HF List'!$B$7,'HF Pricing'!$D$2:$ZB$2,0),0) -> 80141.79
B14: 340 ML | C14: 34 Virgen | D14: =+VLOOKUP(C14,'HF Pricing'!$D$56:$ZB$63,MATCH('HF List'!$B$7,'HF Pricing'!$D$2:$ZB$2,0),0) -> 87042.014
B15: 340 ML | C15: 34 30% PCR | D15: =+VLOOKUP(C15,'HF Pricing'!$D$56:$ZB$63,MATCH('HF List'!$B$7,'HF Pricing'!$D$2:$ZB$2,0),0) -> 87042.014
B16: 750 ML | C16: 44.8 | D16: =+VLOOKUP(C16,'HF Pricing'!$D$56:$ZB$63,MATCH('HF List'!$B$7,'HF Pricing'!$D$2:$ZB$2,0),0) -> 117568.95
B17: 1250 ML | C17: 52 | D17: =+VLOOKUP(C17,'HF Pricing'!$D$56:$ZB$63,MATCH('HF List'!$B$7,'HF Pricing'!$D$2:$ZB$2,0),0) -> 130943.11
B21: Valor Resina Virgen Amcor | C21: =HLOOKUP(B7,'HF Pricing'!2:3,2,0) -> 1287.4315
B22: Valor Resina Virgen Ushuaia | C22: =HLOOKUP(B7,'HF Pricing'!2:4,3,0) -> 1293.8228
B23: Valor Resina PCR | C23: =HLOOKUP(B7,'HF Pricing'!2:5,4,0) -> 1287.4315

Sheet CSD Pricing
C2: Month | K2: 43101 | L2: 43132 | M2: 43160 | N2: 43191 | O2: 43221 | P2: 43252 | Q2: 43282 | R2: 43313 | S2: 43344 | T2: 43374 | U2: 43405 | V2: 43435 | W2: 43466 | X2: 43497 | Y2: 43525 | Z2: 43556 | AA2: 43586 | AB2: 43617 | AC2: 43647 | AD2: 43678 | AE2: 43709 | AF2: 43739 | AG2: 43770 | AH2: 43800 | AI2: 43831 | AJ2: 43862 | AK2: 43891 | AL2: 43922 | AM2: 43952 | AN2: 43983 | AO2: 44013 | AP2: 44044 | AQ2: 44075 | AR2: 44105 | AS2: 44136 | AT2: 44166 | AU2: 44197 | AV2: 44228 | AW2: 44256 | AX2: 44287 | AY2: 44317 | AZ2: 44348 | BA2: 44378 | BB2: 44409 | BC2: 44440 | BD2: 44470 | BE2: 44501 | BF2: 44531 | BG2: 44562 | BH2: 44593 | BI2: 44621 | BJ2: 44652 | BK2: 44682 | BL2: 44713 | BM2: 44743 | BN2: 44774 | BO2: 44805 | BP2: 44835 | BQ2: 44866 | BR2: 44896 | BT2: 44927 | BU2: 44958 | BV2: 44986 | BW2: 45017 | BX2: 45047 | BY2: 45078 | BZ2: 45108 | CA2: 45139 | CB2: 45170 | CC2: 45200 | CD2: 45231 | CE2: 45261 | CF2: 45292 | CG2: 45323 | CH2: 45352 | CI2: 45383 | CJ2: 45413 | CK2: 45444 | CL2: 45474 | CM2: 45505 | CO2: 45536 | CP2: 45566 | CQ2: 45597 | CR2: 45627 | CS2: 45658 | CT2: 45689 | CU2: 45717 | CV2: 45748 | CW2: 45778 | CX2: 45809 | CY2: 45839 | CZ2: 45870 | DA2: 45901 | DB2: 45931 | DC2: 45962 | DD2: 45992 | DE2: 46023 | DF2: 46054 | DG2: 46082
C3: Resin Virgen Price | K3: 1342.9442 | L3: 1374.5998 | M3: 1390.1923 | N3: 1432.5895 | O3: 1463.5562 | P3: 1494.6312 | Q3: 1574.2419 | R3: 1656.8327 | S3: 1693.0693 | T3: 1694.1975 | U3: 1694.0531 | V3: 1711.9398 | W3: 1695.6105 | X3: 1676.6117 | Y3: 1606.0031 | Z3: 1544.9132 | AA3: 1511.464 | AB3: 1491.7034 | AC3: 1491.7034 | AD3: 1223.0042 | AE3: 1272.6947 | AF3: 1178.271 | AG3: 1154.4432 | AH3: 1124.4239 | AI3: 1123.162 | AJ3: 1128.4456 | AK3: 1145.5328 | AL3: 1101.8412 | AM3: 1021.2324 | AN3: 927.68903 | AO3: 943.27499 | AP3: 952.71874 | AQ3: 930.63904 | AR3: 917.60359 | AS3: 919.73461 | AT3: 916.37867 | AU3: 923.78502 | AV3: 997.43551 | AW3: 1160.698 | AX3: #N/A | AY3: #N/A | AZ3: #N/A | BA3: #N/A | BB3: #N/A | BC3: 1494.3256 | BD3: 1501.9696 | BE3: 1486.8851 | BF3: 1664.4992 | BG3: 1678.4033 | BH3: 1570.4271 | BI3: 1733.0951 | BJ3: 1846.0531 | BK3: 1966.1218 | BL3: 2104.0935 | BM3: 2154.5856 | BN3: 2153.47 | BO3: 1937.575 | BP3: 1749.7903 | BQ3: 1695.6645 | BR3: 1622.6628 | BT3: 1532.1838 | BU3: 1517.9026 | BV3: 1494.758 | BW3: 1522.7956 | BX3: 1528.6676 | BY3: 1585.5978 | BZ3: 1494.2782 | CA3: 1429.177 | CB3: 1247.769 | CC3: 1301.1494 | CD3: 1312.7931 | CE3: 1285.056 | CF3: 1800 | CG3: 1836 | CH3: 1748 | CI3: 1703 | CJ3: 1500.0011 | CK3: 1500.0033 | CL3: 1499.9984 | CM3: 1500 | CO3: 1801 | CP3: ='Balance Resinas'!C19 -> 1166.5997 | CQ3: ='Balance Resinas'!$C28 -> 1424.3203 | CR3: ='Balance Resinas'!$C37 -> 1504.4159 | CS3: ='Balance Resinas'!$C46 -> 1524.8199 | CT3: ='Balance Resinas'!$C55 -> 1513.7984 | CU3: ='Balance Resinas'!$C64 -> 1488.7116 | CV3: ='Balance Resinas'!$C73 -> 1472.3492 | CW3: ='Balance Resinas'!$C82 -> 1425.2627 | CX3: ='Balance Resinas'!$C91 -> 1382.0971 | CY3: ='Balance Resinas'!$C100 -> 1321.4159 | CZ3: ='Balance Resinas'!$C109 -> 1283.764 | DA3: ='Balance Resinas'!$C118 -> 1317.8329 | DB3: ='Balance Resinas'!$C127 -> 1369.6513 | DC3: ='Balance Resinas'!$C136 -> 1380.2021 | DD3: ='Balance Resinas'!$C145 -> 1344.145 | DE3: ='Balance Resinas'!$C154 -> 1299.679 | DF3: ='Balance Resinas'!$C163 -> 1279.5923 | DG3: =+'Balance Resinas'!C172 -> 1257.4968
C4: Nylon price | K4: 8580 | L4: 8580 | M4: 8580 | N4: 8580 | O4: 8580 | P4: 8580 | Q4: 8580 | R4: 8580 | S4: 8580 | T4: 8580 | U4: 8580 | V4: 8580 | W4: 8580 | X4: 8580 | Y4: 8580 | Z4: 8580 | AA4: 8580 | AB4: 8580 | AC4: 8580 | AD4: 8580 | AE4: 8580 | AF4: 8580 | AG4: 8580 | AH4: 8580 | AI4: 8580 | AJ4: 8580 | AK4: 8580 | AL4: 8580 | AM4: 8580 | AN4: 8580 | AO4: 8580 | AP4: 8580 | AQ4: 8580 | AR4: 8580 | AS4: 8580 | AT4: 8580 | AU4: 8580 | AV4: 8580 | AW4: 8580 | AX4: 8580 | AY4: 8580 | AZ4: 8580 | BA4: 8580 | BB4: 8580 | BC4: 8580 | BD4: 8580 | BE4: 8580 | BF4: 8580 | BG4: 8580 | BH4: 8580 | BI4: 8580 | BJ4: 8580 | BK4: 8580 | BL4: 8580 | BM4: 8580 | BN4: 8580 | BO4: 8580 | BP4: 8580 | BQ4: 8580 | BR4: 8580 | BT4: 8580 | BU4: 8580 | BV4: 8580 | BW4: 8580 | BX4: 8580 | BY4: 8580 | BZ4: 8580 | CA4: 8580 | CB4: 8580 | CC4: 8580 | CD4: 8580 | CE4: 8580 | CF4: 8580 | CG4: 8580 | CH4: 8580 | CI4: 8580 | CJ4: 8580 | CK4: 8580 | CL4: 8580 | CM4: 8580 | CO4: 8580 | CP4: 8580 | CQ4: 8580 | CR4: 8580 | CS4: 8580 | CT4: 8580 | CU4: 8580 | CV4: 8580 | CW4: 8580 | CX4: 8580 | CY4: 8580 | CZ4: 8580 | DA4: 8580 | DB4: 8580 | DC4: 8580 | DD4: 8580 | DE4: 8580 | DF4: 8580 | DG4: 8580
C5: PQS Price | AP5: 995.71874 | AQ5: 973.63904 | AR5: 960.60359 | AS5: 962.73461 | AT5: 959.37867 | AU5: 966.78502 | AV5: 1040.4355 | AW5: 1203.698 | AX5: #N/A | AY5: #N/A | AZ5: #N/A | BA5: #N/A | BB5: #N/A | BC5: 1609.3256 | BD5: 1616.9696 | BE5: 1601.8851 | BF5: 1782.8556 | BG5: 1797.1347 | BH5: 1686.2221 | BI5: 1850.3826 | BJ5: 1923.1931 | BK5: 2015.5118 | BL5: 2183.056 | BM5: 2234.0731 | BN5: 2203.52 | BO5: 1984.325 | BP5: 1795.6778 | BQ5: 1740.1045 | BR5: 1665.6628 | BT5: 1575.1838 | BU5: 1560.9026 | BV5: 1537.758 | BW5: 1565.7956 | BX5: 1571.6676 | BY5: 1629.1603 | BZ5: 1537.2782 | CA5: 1472.177 | CB5: 1290.769 | CC5: 1344.1494 | CD5: 1355.7931 | CE5: 1328.056 | CF5: 0 | CG5: 0 | CH5: 0 | CI5: #N/A | CJ5: #N/A | CK5: #N/A | CL5: #N/A | CM5: #N/A | CO5: #N/A | CP5: #N/A | CQ5: #N/A | CR5: #N/A | CS5: #N/A | CT5: #N/A | CU5: #N/A | CV5: #N/A | CW5: #N/A | CX5: #N/A | CY5: #N/A | CZ5: #N/A | DA5: #N/A | DB5: #N/A | DC5: #N/A | DD5: #N/A | DE5: #N/A | DF5: #N/A | DG5: #N/A
C6: Resin PCR Vinisa Price | CG6: 2450 | CH6: 2450 | CI6: 2450 | CJ6: 2450 | CK6: 2450 | CL6: 2450 | CM6: 2450 | CO6: 1801 | CP6: =CP3 -> 1166.5997 | CQ6: =CQ3 -> 1424.3203 | CR6: =CR3 -> 1504.4159 | CS6: =CS3 -> 1524.8199 | CT6: =CT3 -> 1513.7984 | CU6: =CU3 -> 1488.7116 | CV6: =CV3 -> 1472.3492 | CW6: =CW3 -> 1425.2627 | ... DG6: =DG3 -> 1257.4968
C7: Scrap % | K7: 0.005 | L7: 0.005 | M7: 0.005 | N7: 0.005 | O7: 0.005 | P7: 0.005 | Q7: 0.005 | R7: 0.005 | S7: 0.005 | T7: 0.005 | U7: 0.005 | V7: 0.005 | W7: 0.005 | X7: 0.005 | Y7: 0.005 | Z7: 0.005 | AA7: 0.005 | AB7: 0.005 | AC7: =+AB7 -> 0.005 | AD7: 0.005 | AE7: 0.005 | AF7: 0.005 | AG7: 0.005 | AH7: 0.005 | AI7: 0.005 | AJ7: 0.005 | AK7: 0.005 | AL7: 0.005 | AM7: 0.005 | AN7: 0.005 | AO7: 0.005 | AP7: 0.005 | AQ7: 0.005 | AR7: 0.005 | AS7: 0.005 | AT7: 0.005 | AU7: 0.005 | AV7: 0.005 | AW7: 0.005 | AX7: 0.005 | AY7: 0.005 | AZ7: 0.005 | BA7: 0.005 | BB7: 0.005 | BC7: 0.005 | BD7: 0.005 | BE7: 0.005 | BF7: 0.005 | BG7: 0.005 | BH7: 0.005 | BI7: 0.005 | BJ7: 0.005 | BK7: 0.005 | BL7: 0.005 | BM7: 0.005 | BN7: 0.005 | BO7: 0.005 | BP7: 0.005 | BQ7: 0.005 | BR7: 0.005 | BT7: 0.005 | BU7: 0.005 | BV7: 0.005 | BW7: 0.005 | BX7: 0.005 | BY7: 0.005 | BZ7: 0.005 | CA7: 0.005 | CB7: 0.005 | CC7: 0.005 | CD7: 0.005 | CE7: 0.005 | CF7: 0.005 | CG7: 0.005 | CH7: 0.005 | CI7: 0.005 | CJ7: 0.005 | CK7: 0.005 | CL7: 0.005 | CM7: 0.005 | CO7: 0.005 | CP7: 0.005 | CQ7: 0.005 | CR7: 0.005 | CS7: 0.005 | CT7: 0.005 | CU7: 0.005 | CV7: 0.005 | CW7: 0.005 | CX7: 0.005 | CY7: 0.005 | CZ7: 0.005 | DA7: 0.005 | DB7: 0.005 | DC7: 0.005 | DD7: 0.005 | DE7: 0.005 | DF7: 0.005 | DG7: 0.005
C8: Tax | K8: 0.052705 | L8: 0.052705 | M8: 0.052705 | N8: 0.052705 | O8: 0.052705 | P8: 0.052705 | Q8: 0.052705 | R8: 0.052705 | S8: 0.052705 | T8: 0.052705 | U8: 0.052705 | V8: 0.052705 | W8: 0.052705 | X8: 0.052705 | Y8: 0.052705 | Z8: 0.052705 | AA8: 0.052705 | AB8: 0.052705 | AC8: =+AB8 -> 0.052705 | AD8: 0.052705 | AE8: 0.052705 | AF8: 0.052705 | AG8: 0.052705 | AH8: 0.052705 | AI8: 0.052705 | AJ8: 0.052705 | AK8: 0.052705 | AL8: 0.052705 | AM8: 0.052705 | AN8: 0.052705 | AO8: 0.052705 | AP8: 0.052705 | AQ8: 0.052705 | AR8: 0.052705 | AS8: 0.052705 | AT8: 0.052705 | AU8: 0.052705 | AV8: 0.052705 | AW8: 0.052705 | AX8: 0.052705 | AY8: 0.052705 | AZ8: 0.052705 | BA8: 0.052705 | BB8: 0.052705 | BC8: 0.052705 | BD8: 0.052705 | BE8: 0.052705 | BF8: 0.052705 | BG8: 0.052705 | BH8: 0.052705 | BI8: 0.052705 | BJ8: 0.052705 | BK8: 0.052705 | BL8: 0.052705 | BM8: 0.052705 | BN8: 0.052705 | BO8: 0.052705 | BP8: 0.052705 | BQ8: 0.052705 | BR8: 0.052705 | BT8: 0.052705 | BU8: 0.052705 | BV8: 0.052705 | BW8: 0.052705 | BX8: 0.052705 | BY8: 0.052705 | BZ8: 0.052705 | CA8: 0.052705 | CB8: 0.052705 | CC8: 0.052705 | CD8: 0.052705 | CE8: 0.052705 | CF8: 0.052705 | CG8: 0.052705 | CH8: 0.052705 | CI8: 0.052705 | CJ8: 0.052705 | CK8: 0.052705 | CL8: 0.052705 | CM8: 0.052705 | CO8: 0.052705 | CP8: 0.052705 | CQ8: 0.052705 | CR8: 0.0525 | CS8: 0.0525 | CT8: 0.0525 | CU8: 0.0525 | CV8: 0.0525 | CW8: 0.0525 | CX8: 0.0525 | CY8: 0.0525 | CZ8: 0.0525 | DA8: 0.0525 | DB8: 0.0525 | DC8: 0.0525 | DD8: 0.0525 | DE8: 0.0525 | DF8: 0.0525 | DG8: 0.0525
C9: IPC C.A.B.A./ Nuevo contrato IPC INDEC | E9: 0.018 | F9: 0.016 | G9: 0.016 | H9: 0.015 | I9: 0.013 | J9: 0.033 | K9: 0.016 | L9: 0.026 | M9: 0.021 | N9: 0.03 | O9: 0.023 | P9: 0.037 | Q9: 0.027 | R9: 0.037 | S9: 0.06 | T9: 0.053 | U9: 0.028 | V9: 0.024 | W9: 0.038 | X9: 0.034 | Y9: 0.04 | Z9: 0.037 | AA9: 0.031 | AB9: 0.028 | AC9: 0.028 | AD9: 0.022 | AE9: 0.034 | AF9: 0.05 | AG9: 0.028 | AH9: 0.04 | AI9: 0.035 | AJ9: 0.024 | AK9: 0.018 | AL9: 0.027 | AM9: 0.02 | AN9: 0.01 | AO9: 0.014 | AP9: 0.016 | AQ9: 0.024 | AR9: 0.022 | AS9: 0.025 | AT9: 0.031 | AU9: 0.038 | AV9: 0.038 | AW9: 0.029 | AX9: 0.039 | AY9: 0.04 | AZ9: 0.036 | BA9: 0.032 | BB9: 0.029 | BC9: 0.029 | BD9: 0.034 | BE9: 0.037 | BF9: 0.025 | BG9: 0.038 | BH9: 0.04 | BI9: 0.041 | BJ9: 0.059 | BK9: 0.053 | BL9: 0.055 | BM9: 0.051 | BN9: 0.077 | BO9: 0.062 | BP9: 0.056 | BQ9: 0.07 | BR9: 0.058 | BT9: 0.058 | BU9: 0.073 | BV9: 0.06 | BW9: 0.071 | BX9: 0.078 | BY9: 0.075 | BZ9: 0.071 | CA9: 0.073 | CB9: 0.108 | CC9: 0.12 | CD9: 0.094 | CE9: 0.119 | CF9: 0.211 | CG9: 0.217 | CH9: 0.141 | CI9: 0.132 | CJ9: 0.098 | CK9: 0.044 | CL9: 0.048 | CM9: 0.051 | CO9: 0.042 | CP9: 0.04 | CQ9: 0.032 | CR9: 0.032 | CS9: 0.033 | CT9: 0.031 | CU9: 0.021 | CV9: 0.032 | CW9: 0.023 | CX9: 0.016 | CY9: 0.021 | CZ9: 0.025 | DA9: 0.016 | DB9: 0.022 | DC9: 0.022 | DD9: 0.024 | DE9: 0.027 | DF9: 0.031
C10: IPP Caucho | E10: 0.018 | F10: 0.018 | G10: 0.014 | H10: 0.009 | I10: 0.008 | J10: 0.019 | K10: 0.025 | L10: 0.04 | M10: 0.024 | N10: 0.016 | O10: 0.097 | P10: 0.078488053 | Q10: 0.041 | R10: 0.041 | S10: 0.181 | T10: 0.028 | U10: 0.006 | V10: 0.032 | W10: 0.013 | X10: 0.027 | Y10: 0.026 | Z10: 0.052 | AA10: 0.04 | AB10: 0.011 | AC10: 0.011 | AD10: 0.006 | AE10: 0.135 | AF10: 0.067 | AG10: 0.045 | AH10: 0.043 | AI10: 0.019 | AJ10: 0.017 | AK10: 0.011 | AL10: 0.014 | AM10: 0.011 | AN10: 0.049 | AO10: 0.025 | AP10: 0.046 | AQ10: 0.03 | AR10: 0.04 | AS10: 0.049 | AT10: 0.07 | AU10: 0.034 | AV10: 0.068 | AW10: 0.065 | AX10: 0.056 | AY10: 0.067 | AZ10: 0.041 | BA10: 0.034 | BB10: 0.036 | BC10: 0.027 | BD10: 0.018 | BE10: 0.029 | BF10: 0.044 | BG10: 0.027 | BH10: 0.031 | BI10: 0.04 | BJ10: 0.051 | BK10: 0.046 | BL10: 0.054 | BM10: 0.046 | BN10: 0.094 | BO10: 0.064 | BP10: 0.061 | BQ10: 0.07 | BR10: 0.057 | BT10: 0.061 | BU10: 0.064 | BV10: 0.062 | BW10: 0.063 | BX10: 0.069 | BY10: 0.081 | BZ10: 0.071 | CA10: 0.072 | CB10: 0.17 | CC10: 0.1 | CD10: 0.086 | CE10: 0.111 | CF10: 0.683 | CG10: 0.122 | CH10: 0.177 | CI10: 0.032 | CJ10: 0.015 | CK10: 0.002 | CL10: -0.004 | CM10: 0.004 | CO10: -0.001 | CP10: 0.027 | CQ10: 0.02 | CR10: 0.01 | CS10: -0.007 | CT10: 0.008 | CU10: 0.007 | CV10: 0.005 | CW10: 0.039 | CX10: 0.004 | CY10: 0.012 | CZ10: 0.03 | DA10: 0.032 | DB10: 0.04 | DC10: 0.012 | DD10: 0.014 | DE10: 0.01 | DF10: 0.012
C11: Monthly Inflation | E11: =+(E9+E10)/2 -> 0.018 | F11: =+(F9+F10)/2 -> 0.017 | G11: =+(G9+G10)/2 -> 0.015 | H11: =+(H9+H10)/2 -> 0.012 | I11: =+(I9+I10)/2 -> 0.0105 | J11: =+(J9+J10)/2 -> 0.026 | K11: =+(K9+K10)/2 -> 0.0205 | L11: =+(L9+L10)/2 -> 0.033 | ... AB11: =+(AB9+AB10)/2 -> 0.0195 | AC11: =+AB11 -> 0.0195 | AD11: =+(AD9+AD10)/2 -> 0.014 | AE11: =+(AE9+AE10)/2 -> 0.0845 | AF11: =+(AF9+AF10)/2 -> 0.0585 | AG11: =+(AG9+AG10)/2 -> 0.0365 | AH11: =+(AH9+AH10)/2 -> 0.0415 | AI11: =+(AI9+AI10)/2 -> 0.027 | AJ11: =+(AJ9+AJ10)/2 -> 0.0205 | AK11: =+(AK9+AK10)/2 -> 0.0145 | ... BR11: =+(BR9+BR10)/2 -> 0.0575 | BT11: =+(BT9+BT10)/2 -> 0.0595 | BU11: =+(BU9+BU10)/2 -> 0.0685 | BV11: =+(BV9+BV10)/2 -> 0.061 | BW11: =+(BW9+BW10)/2 -> 0.067 | BX11: =+(BX9+BX10)/2 -> 0.0735 | BY11: =+(BY9+BY10)/2 -> 0.078 | BZ11: =+(BZ9+BZ10)/2 -> 0.071 | CA11: =+(CA9+CA10)/2 -> 0.0725 | ... CM11: =+(CM9+CM10)/2 -> 0.0275 | CO11: =+(CO9+CO10)/2 -> 0.0205 | CP11: =+(CP9+CP10)/2 -> 0.0335 | CQ11: =+(CQ9+CQ10)/2 -> 0.026 | CR11: =+(CR9+CR10)/2 -> 0.021 | CS11: =+(CS9+CS10)/2 -> 0.013 | CT11: =+(CT9+CT10)/2 -> 0.0195 | CU11: =+(CU9+CU10)/2 -> 0.014 | CV11: =+(CV9+CV10)/2 -> 0.0185 | ... DF11: =+(DF9+DF10)/2 -> 0.0215
C12: Annual Inflation | P12: =+(((1+E$9)+(1+E$10))/2*((1+F$9)+(1+F$10))/2*((1+G$9)+(1+G$10))/2*((1+H$9)+(1+H$10))/2*((1+I$9)+(1+I$10))/2*((1+J$9)+(1+J$10))/2*((1+K$9)+(1+K$10))/2*((1+L$9)+(1+L$10))/2*((1+M$9)+(1+M$10))/2*((1+N$9)+(1+N$10))/2*((1+O$9)+(1+O$10))/2*((1+P$9)+(1+P$10))/2-1) -> 0.36313131 | V12: =+(((1+K$9)+(1+K$10))/2*((1+L$9)+(1+L$10))/2*((1+M$9)+(1+M$10))/2*((1+N$9)+(1+N$10))/2*((1+O$9)+(1+O$10))/2*((1+P$9)+(1+P$10))/2*((1+Q$9)+(1+Q$10))/2*((1+R$9)+(1+R$10))/2*((1+S$9)+(1+S$10))/2*((1+T$9)+(1+T$10))/2*((1+U$9)+(1+U$10))/2*((1+V$9)+(1+V$10))/2-1) -> 0.61898501 | AB12: =+(((1+Q$9)+(1+Q$10))/2*((1+R$9)+(1+R$10))/2*((1+S$9)+(1+S$10))/2*((1+T$9)+(1+T$10))/2*((1+U$9)+(1+U$10))/2*((1+V$9)+(1+V$10))/2*((1+W$9)+(1+W$10))/2*((1+X$9)+(1+X$10))/2*((1+Y$9)+(1+Y$10))/2*((1+Z$9)+(1+Z$10))/2*((1+AA$9)+(1+AA$10))/2*((1+AB$9)+(1+AB$10))/2-1) -> 0.57628179 | AH12: =+(((1+W$9)+(1+W$10))/2*((1+X$9)+(1+X$10))/2*((1+Y$9)+(1+Y$10))/2*((1+Z$9)+(1+Z$10))/2*((1+AA$9)+(1+AA$10))/2*((1+AB$9)+(1+AB$10))/2*((1+AC$9)+(1+AC$10))/2*((1+AD$9)+(1+AD$10))/2*((1+AE$9)+(1+AE$10))/2*((1+AF$9)+(1+AF$10))/2*((1+AG$9)+(1+AG$10))/2*((1+AH$9)+(1+AH$10))/2-1) -> 0.54206949 | AN12: =(1+AC11)*(1+AD11)*(1+AE11)*(1+AF11)*(1+AG11)*(1+AH11)*(1+AI11)*(1+AJ11)*(1+AK11)*(1+AL11)*(1+AM11)*(1+AN11)-1 -> 0.453212 | AT12: =(1+AI11)*(1+AJ11)*(1+AK11)*(1+AL11)*(1+AM11)*(1+AN11)*(1+AO11)*(1+AP11)*(1+AQ11)*(1+AR11)*(1+AS11)*(1+AT11)-1 -> 0.37532269 | AZ12: =(1+AO11)*(1+AP11)*(1+AQ11)*(1+AR11)*(1+AS11)*(1+AT11)*(1+AU11)*(1+AV11)*(1+AW11)*(1+AX11)*(1+AY11)*(1+AZ11)-1 -> 0.58701013 | BF12: =(1+AU11)*(1+AV11)*(1+AW11)*(1+AX11)*(1+AY11)*(1+AZ11)*(1+BA11)*(1+BB11)*(1+BC11)*(1+BD11)*(1+BE11)*(1+BF11)-1 -> 0.57358988 | BL12: =(1+BA11)*(1+BB11)*(1+BC11)*(1+BD11)*(1+BE11)*(1+BF11)*(1+BG11)*(1+BH11)*(1+BI11)*(1+BJ11)*(1+BK11)*(1+BL11)-1 -> 0.56144039 | BR12: =(1+BG11)*(1+BH11)*(1+BI11)*(1+BJ11)*(1+BK11)*(1+BL11)*(1+BM11)*(1+BN11)*(1+BO11)*(1+BP11)*(1+BQ11)*(1+BR11)-1 -> 0.88213286 | BY12: =(1+BM11)*(1+BN11)*(1+BO11)*(1+BP11)*(1+BQ11)*(1+BR11)*(1+BT11)*(1+BU11)*(1+BV11)*(1+BW11)*(1+BX11)*(1+BY11)-1 -> 1.1491298 | CE12: =(1+BT11)*(1+BU11)*(1+BV11)*(1+BW11)*(1+BX11)*(1+BY11)*(1+BZ11)*(1+CA11)*(1+CB11)*(1+CC11)*(1+CD11)*(1+CE11)-1 -> 1.6176462 | CF12: =(1+BU11)*(1+BV11)*(1+BW11)*(1+BX11)*(1+BY11)*(1+BZ11)*(1+CA11)*(1+CB11)*(1+CC11)*(1+CD11)*(1+CE11)*(1+CF11)-1 -> 2.5750203 | CG12: =(1+BV11)*(1+BW11)*(1+BX11)*(1+BY11)*(1+BZ11)*(1+CA11)*(1+CB11)*(1+CC11)*(1+CD11)*(1+CE11)*(1+CF11)*(1+CG11)-1 -> 2.9129492 | CH12: =(1+BW11)*(1+BX11)*(1+BY11)*(1+BZ11)*(1+CA11)*(1+CB11)*(1+CC11)*(1+CD11)*(1+CE11)*(1+CF11)*(1+CG11)*(1+CH11)-1 -> 3.2743715 | CI12: =(1+BX11)*(1+BY11)*(1+BZ11)*(1+CA11)*(1+CB11)*(1+CC11)*(1+CD11)*(1+CE11)*(1+CF11)*(1+CG11)*(1+CH11)*(1+CI11)-1 -> 3.334461 | CJ12: =(1+BY11)*(1+BZ11)*(1+CA11)*(1+CB11)*(1+CC11)*(1+CD11)*(1+CE11)*(1+CF11)*(1+CG11)*(1+CH11)*(1+CI11)*(1+CJ11)-1 -> 3.2658203 | CK12: =(1+BZ11)*(1+CA11)*(1+CB11)*(1+CC11)*(1+CD11)*(1+CE11)*(1+CF11)*(1+CG11)*(1+CH11)*(1+CI11)*(1+CJ11)*(1+CK11)-1 -> 3.0481764 | CL12: =(1+CA11)*(1+CB11)*(1+CC11)*(1+CD11)*(1+CE11)*(1+CF11)*(1+CG11)*(1+CH11)*(1+CI11)*(1+CJ11)*(1+CK11)*(1+CL11)-1 -> 2.8629657 | CM12: =(1+CB11)*(1+CC11)*(1+CD11)*(1+CE11)*(1+CF11)*(1+CG11)*(1+CH11)*(1+CI11)*(1+CJ11)*(1+CK11)*(1+CL11)*(1+CM11)-1 -> 2.7008832 | CO12: =(1+CD11)*(1+CE11)*(1+CF11)*(1+CG11)*(1+CH11)*(1+CI11)*(1+CJ11)*(1+CK11)*(1+CL11)*(1+CM11)*(1+CO11)-1 -> 1.9872508 | CP12: =(1+CE11)*(1+CF11)*(1+CG11)*(1+CH11)*(1+CI11)*(1+CJ11)*(1+CK11)*(1+CL11)*(1+CM11)*(1+CO11)*(1+CP11)-1 -> 1.8324071 | CQ12: =(1+CF11)*(1+CG11)*(1+CH11)*(1+CI11)*(1+CJ11)*(1+CK11)*(1+CL11)*(1+CM11)*(1+CN11)*(1+CP11)*(1+CQ11)-1 -> 1.5539663 | CR12: =(1+CG11)*(1+CH11)*(1+CI11)*(1+CJ11)*(1+CK11)*(1+CL11)*(1+CM11)*(1+CN11)*(1+CO11)*(1+CQ11)*(1+CR11)-1 -> 0.77940537 | CS12: =(1+CH11)*(1+CI11)*(1+CJ11)*(1+CK11)*(1+CL11)*(1+CM11)*(1+CN11)*(1+CO11)*(1+CP11)*(1+CR11)*(1+CS11)-1 -> 0.55255586 | CT12: =(1+CI11)*(1+CJ11)*(1+CK11)*(1+CL11)*(1+CM11)*(1+CN11)*(1+CO11)*(1+CP11)*(1+CQ11)*(1+CS11)*(1+CT11)-1 -> 0.37237453 | CU12: =(1+CJ11)*(1+CK11)*(1+CL11)*(1+CM11)*(1+CN11)*(1+CO11)*(1+CP11)*(1+CQ11)*(1+CR11)*(1+CT11)*(1+CU11)-1 -> 0.29628244 | CV12: =(1+CK11)*(1+CL11)*(1+CM11)*(1+CN11)*(1+CO11)*(1+CP11)*(1+CQ11)*(1+CR11)*(1+CS11)*(1+CU11)*(1+CV11)-1 -> 0.24169058 | CW12: =(1+CL11)*(1+CM11)*(1+CN11)*(1+CO11)*(1+CP11)*(1+CQ11)*(1+CR11)*(1+CS11)*(1+CT11)*(1+CV11)*(1+CW11)-1 -> 0.25818845 | ... CZ12: =(1+CO11)*(1+CP11)*(1+CQ11)*(1+CR11)*(1+CS11)*(1+CT11)*(1+CU11)*(1+CV11)*(1+CW11)*(1+CY11)*(1+CZ11)-1 -> 0.26893722 | DA12: =(1+CP11)*(1+CQ11)*(1+CR11)*(1+CS11)*(1+CT11)*(1+CU11)*(1+CV11)*(1+CW11)*(1+CX11)*(1+CY11)*(1+CZ11)*(1+DA11)-1 -> 0.28602217 | DB12: =(1+CQ11)*(1+CR11)*(1+CS11)*(1+CT11)*(1+CU11)*(1+CV11)*(1+CW11)*(1+CX11)*(1+CY11)*(1+CZ11)*(1+DA11)*(1+DB11)-1 -> 0.28291133 | DC12: =(1+CR11)*(1+CS11)*(1+CT11)*(1+CU11)*(1+CV11)*(1+CW11)*(1+CX11)*(1+CY11)*(1+CZ11)*(1+DA11)*(1+DB11)*(1+DC11)-1 -> 0.27165772 | DD12: =(1+CS11)*(1+CT11)*(1+CU11)*(1+CV11)*(1+CW11)*(1+CX11)*(1+CY11)*(1+CZ11)*(1+DA11)*(1+DB11)*(1+DC11)*(1+DD11)-1 -> 0.26916672 | DE12: =(1+CT11)*(1+CU11)*(1+CV11)*(1+CW11)*(1+CX11)*(1+CY11)*(1+CZ11)*(1+DA11)*(1+DB11)*(1+DC11)*(1+DD11)*(1+DE11)-1 -> 0.27605756 | DF12: =(1+CU11)*(1+CV11)*(1+CW11)*(1+CX11)*(1+CY11)*(1+CZ11)*(1+DA11)*(1+DB11)*(1+DC11)*(1+DD11)*(1+DE11)*(1+DF11)-1 -> 0.27856086
C13: Efficiency % | P13: =+IF(P12=0,0,IF(P12<=10%,50%,IF(P12<=20%,15%,10%))) -> 0.1 | V13: =+IF(V12=0,0,IF(V12<=10%,50%,IF(V12<=20%,15%,10%))) -> 0.1 | AB13: =+IF(AB12=0,0,IF(AB12<=10%,50%,IF(AB12<=20%,15%,10%))) -> 0.1 | AH13: =+IF(AH12=0,0,IF(AH12<=10%,50%,IF(AH12<=20%,15%,10%))) -> 0.1 | AN13: =+IF(AN12=0,0,IF(AN12<=10%,50%,IF(AN12<=20%,15%,10%))) -> 0.1 | AT13: =+IF(AT12=0,0,IF(AT12<=10%,50%,IF(AT12<=20%,15%,10%))) -> 0.1 | AZ13: =+IF(AZ12=0,0,IF(AZ12<=10%,50%,IF(AZ12<=20%,15%,10%))) -> 0.1 | BF13: =+IF(BF12=0,0,IF(BF12<=10%,50%,IF(BF12<=20%,15%,10%))) -> 0.1 | BL13: =+IF(BL12=0,0,IF(BL12<=10%,50%,IF(BL12<=20%,15%,10%))) -> 0.1 | BR13: =+IF(BR12=0,0,IF(BR12<=10%,50%,IF(BR12<=20%,15%,10%))) -> 0.1 | BY13: =+IF(BY12=0,0,IF(BY12<=10%,50%,IF(BY12<=20%,15%,10%))) -> 0.1 | CE13: =+IF(CE12=0,0,IF(CE12<=10%,50%,IF(CE12<=20%,15%,10%))) -> 0.1 | CF13: =+IF(CF12=0,0,IF(CF12<=10%,50%,IF(CF12<=20%,15%,10%))) -> 0.1 | CG13: =+IF(CG12=0,0,IF(CG12<=10%,50%,IF(CG12<=20%,15%,10%))) -> 0.1 | CH13: =+IF(CH12=0,0,IF(CH12<=10%,50%,IF(CH12<=20%,15%,10%))) -> 0.1 | CI13: =+IF(CI12=0,0,IF(CI12<=10%,50%,IF(CI12<=20%,15%,10%))) -> 0.1 | CJ13: =+IF(CJ12=0,0,IF(CJ12<=10%,50%,IF(CJ12<=20%,15%,10%))) -> 0.1 | CK13: =+IF(CK12=0,0,IF(CK12<=10%,50%,IF(CK12<=20%,15%,10%))) -> 0.1 | CL13: =+IF(CL12=0,0,IF(CL12<=10%,50%,IF(CL12<=20%,15%,10%))) -> 0.1
C14: Accumulated Inflation | Q14: =+((1+$K$11)*(1+$L$11)*(1+$M$11)*(1+$N$11)*(1+$O$11)*(1+$P$11)-1)*(1-$P$13) -> 0.21270807 | R14: =+Q14 -> 0.21270807 | S14: =+R14 -> 0.21270807 | T14: =+S14 -> 0.21270807 | U14: =+T14 -> 0.21270807 | V14: =+U14 -> 0.21270807 | W14: =(1+$Q$14)*((((1+$Q$11)*(1+$R$11)*(1+$S$11)*(1+$T$11)*(1+$U$11)*(1+$V$11)-1)*(1-$V$13))+1)-1 -> 0.55050328 | X14: =(1+$Q$14)*((((1+$Q$11)*(1+$R$11)*(1+$S$11)*(1+$T$11)*(1+$U$11)*(1+$V$11)-1)*(1-$V$13))+1)-1 -> 0.55050328 | Y14: =(1+$Q$14)*((((1+$Q$11)*(1+$R$11)*(1+$S$11)*(1+$T$11)*(1+$U$11)*(1+$V$11)-1)*(1-$V$13))+1)-1 -> 0.55050328 | Z14: =(1+$Q$14)*((((1+$Q$11)*(1+$R$11)*(1+$S$11)*(1+$T$11)*(1+$U$11)*(1+$V$11)-1)*(1-$V$13))+1)-1 -> 0.55050328 | AA14: =(1+$Q$14)*((((1+$Q$11)*(1+$R$11)*(1+$S$11)*(1+$T$11)*(1+$U$11)*(1+$V$11)-1)*(1-$V$13))+1)-1 -> 0.55050328 | AB14: =(1+$Q$14)*((((1+$Q$11)*(1+$R$11)*(1+$S$11)*(1+$T$11)*(1+$U$11)*(1+$V$11)-1)*(1-$V$13))+1)-1 -> 0.55050328 | AC14: =+AB14 -> 0.55050328 | AD14: =(1+$W$14)*((((1+$W$11)*(1+$X$11)*(1+$Y$11)*(1+$Z$11)*(1+$AA$11)*(1+$AB$11)-1)*(1-$AB$13))+1)-1 -> 0.83480153 | AE14: =+AD14 -> 0.83480153 | AF14: =+AE14 -> 0.83480153 | AG14: =+AF14 -> 0.83480153 | AH14: =+AG14 -> 0.83480153 | AI14: =(1+$AH$14)*((((1+$AC$11)*(1+$AD$11)*(1+$AE$11)*(1+$AF$11)*(1+$AG$11)*(1+$AH$11)-1)*(1-$AH$13))+1)-1 -> 1.2989449 | AJ14: =(1+$AH$14)*((((1+$AC$11)*(1+$AD$11)*(1+$AE$11)*(1+$AF$11)*(1+$AG$11)*(1+$AH$11)-1)*(1-$AH$13))+1)-1 -> 1.2989449 | AK14: =(1+$AH$14)*((((1+$AC$11)*(1+$AD$11)*(1+$AE$11)*(1+$AF$11)*(1+$AG$11)*(1+$AH$11)-1)*(1-$AH$13))+1)-1 -> 1.2989449 | AL14: =(1+$AH$14)*((((1+$AC$11)*(1+$AD$11)*(1+$AE$11)*(1+$AF$11)*(1+$AG$11)*(1+$AH$11)-1)*(1-$AH$13))+1)-1 -> 1.2989449 | AM14: =(1+$AH$14)*((((1+$AC$11)*(1+$AD$11)*(1+$AE$11)*(1+$AF$11)*(1+$AG$11)*(1+$AH$11)-1)*(1-$AH$13))+1)-1 -> 1.2989449 | AN14: =(1+$AH$14)*((((1+$AC$11)*(1+$AD$11)*(1+$AE$11)*(1+$AF$11)*(1+$AG$11)*(1+$AH$11)-1)*(1-$AH$13))+1)-1 -> 1.2989449 | AO14: =(1+$AN$14)*((((1+$AI$11)*(1+$AJ$11)*(1+$AK$11)*(1+$AL$11)*(1+$AM$11)*(1+$AN$11)-1)*(1-$AN$13))+1)-1 -> 1.5769635 | AP14: =(1+$AN$14)*((((1+$AI$11)*(1+$AJ$11)*(1+$AK$11)*(1+$AL$11)*(1+$AM$11)*(1+$AN$11)-1)*(1-$AN$13))+1)-1 -> 1.5769635 | AQ14: =(1+$AN$14)*((((1+$AI$11)*(1+$AJ$11)*(1+$AK$11)*(1+$AL$11)*(1+$AM$11)*(1+$AN$11)-1)*(1-$AN$13))+1)-1 -> 1.5769635 | AR14: =(1+$AN$14)*((((1+$AI$11)*(1+$AJ$11)*(1+$AK$11)*(1+$AL$11)*(1+$AM$11)*(1+$AN$11)-1)*(1-$AN$13))+1)-1 -> 1.5769635 | AS14: =(1+$AN$14)*((((1+$AI$11)*(1+$AJ$11)*(1+$AK$11)*(1+$AL$11)*(1+$AM$11)*(1+$AN$11)-1)*(1-$AN$13))+1)-1 -> 1.5769635 | AT14: =(1+$AN$14)*((((1+$AI$11)*(1+$AJ$11)*(1+$AK$11)*(1+$AL$11)*(1+$AM$11)*(1+$AN$11)-1)*(1-$AN$13))+1)-1 -> 1.5769635 | AU14: =(1+$AT$14)*((((1+$AO$11)*(1+$AP$11)*(1+$AQ$11)*(1+$AR$11)*(1+$AS$11)*(1+$AT$11)-1)*(1-$AT$13))+1)-1 -> 2.069601 | AV14: =(1+$AT$14)*((((1+$AO$11)*(1+$AP$11)*(1+$AQ$11)*(1+$AR$11)*(1+$AS$11)*(1+$AT$11)-1)*(1-$AT$13))+1)-1 -> 2.069601 | AW14: =(1+$AT$14)*((((1+$AO$11)*(1+$AP$11)*(1+$AQ$11)*(1+$AR$11)*(1+$AS$11)*(1+$AT$11)-1)*(1-$AT$13))+1)-1 -> 2.069601 | AX14: =(1+$AT$14)*((((1+$AO$11)*(1+$AP$11)*(1+$AQ$11)*(1+$AR$11)*(1+$AS$11)*(1+$AT$11)-1)*(1-$AT$13))+1)-1 -> 2.069601 | AY14: =(1+$AT$14)*((((1+$AO$11)*(1+$AP$11)*(1+$AQ$11)*(1+$AR$11)*(1+$AS$11)*(1+$AT$11)-1)*(1-$AT$13))+1)-1 -> 2.069601 | AZ14: =(1+$AT$14)*((((1+$AO$11)*(1+$AP$11)*(1+$AQ$11)*(1+$AR$11)*(1+$AS$11)*(1+$AT$11)-1)*(1-$AT$13))+1)-1 -> 2.069601 | BA14: =(1+$AZ$14)*((((1+$AU$11)*(1+$AV$11)*(1+$AW$11)*(1+$AX$11)*(1+$AY$11)*(1+$AZ$11)-1)*(1-$AZ$13))+1)-1 -> 2.9231757 | BB14: =(1+$AZ$14)*((((1+$AU$11)*(1+$AV$11)*(1+$AW$11)*(1+$AX$11)*(1+$AY$11)*(1+$AZ$11)-1)*(1-$AZ$13))+1)-1 -> 2.9231757 | BC14: =(1+$AZ$14)*((((1+$AU$11)*(1+$AV$11)*(1+$AW$11)*(1+$AX$11)*(1+$AY$11)*(1+$AZ$11)-1)*(1-$AZ$13))+1)-1 -> 2.9231757 | BD14: =(1+$AZ$14)*((((1+$AU$11)*(1+$AV$11)*(1+$AW$11)*(1+$AX$11)*(1+$AY$11)*(1+$AZ$11)-1)*(1-$AZ$13))+1)-1 -> 2.9231757 | BE14: =(1+$AZ$14)*((((1+$AU$11)*(1+$AV$11)*(1+$AW$11)*(1+$AX$11)*(1+$AY$11)*(1+$AZ$11)-1)*(1-$AZ$13))+1)-1 -> 2.9231757 | BF14: =(1+$AZ$14)*((((1+$AU$11)*(1+$AV$11)*(1+$AW$11)*(1+$AX$11)*(1+$AY$11)*(1+$AZ$11)-1)*(1-$AZ$13))+1)-1 -> 2.9231757 | BG14: =(1+$BF$14)*((((1+$BA$11)*(1+$BB$11)*(1+$BC$11)*(1+$BD$11)*(1+$BE$11)*(1+$BF$11)-1)*(1-$BF$13))+1)-1 -> 3.6369682 | BH14: =(1+$BF$14)*((((1+$BA$11)*(1+$BB$11)*(1+$BC$11)*(1+$BD$11)*(1+$BE$11)*(1+$BF$11)-1)*(1-$BF$13))+1)-1 -> 3.6369682 | BI14: =(1+$BF$14)*((((1+$BA$11)*(1+$BB$11)*(1+$BC$11)*(1+$BD$11)*(1+$BE$11)*(1+$BF$11)-1)*(1-$BF$13))+1)-1 -> 3.6369682 | BJ14: =(1+$BF$14)*((((1+$BA$11)*(1+$BB$11)*(1+$BC$11)*(1+$BD$11)*(1+$BE$11)*(1+$BF$11)-1)*(1-$BF$13))+1)-1 -> 3.6369682 | BK14: =(1+$BF$14)*((((1+$BA$11)*(1+$BB$11)*(1+$BC$11)*(1+$BD$11)*(1+$BE$11)*(1+$BF$11)-1)*(1-$BF$13))+1)-1 -> 3.6369682 | BL14: =(1+$BF$14)*((((1+$BA$11)*(1+$BB$11)*(1+$BC$11)*(1+$BD$11)*(1+$BE$11)*(1+$BF$11)-1)*(1-$BF$13))+1)-1 -> 3.6369682 | BM14: =(1+$BL$14)*((((1+$BG$11)*(1+$BH$11)*(1+$BI$11)*(1+$BJ$11)*(1+$BK$11)*(1+$BL$11)-1)*(1-$BL$13))+1)-1 -> 4.8842094 | BN14: =(1+$BL$14)*((((1+$BG$11)*(1+$BH$11)*(1+$BI$11)*(1+$BJ$11)*(1+$BK$11)*(1+$BL$11)-1)*(1-$BL$13))+1)-1 -> 4.8842094 | BO14: =(1+$BL$14)*((((1+$BG$11)*(1+$BH$11)*(1+$BI$11)*(1+$BJ$11)*(1+$BK$11)*(1+$BL$11)-1)*(1-$BL$13))+1)-1 -> 4.8842094 | BP14: =(1+$BL$14)*((((1+$BG$11)*(1+$BH$11)*(1+$BI$11)*(1+$BJ$11)*(1+$BK$11)*(1+$BL$11)-1)*(1-$BL$13))+1)-1 -> 4.8842094 | BQ14: =(1+$BL$14)*((((1+$BG$11)*(1+$BH$11)*(1+$BI$11)*(1+$BJ$11)*(1+$BK$11)*(1+$BL$11)-1)*(1-$BL$13))+1)-1 -> 4.8842094 | BR14: =(1+$BL$14)*((((1+$BG$11)*(1+$BH$11)*(1+$BI$11)*(1+$BJ$11)*(1+$BK$11)*(1+$BL$11)-1)*(1-$BL$13))+1)-1 -> 4.8842094 | BT14: =(1+$BR$14)*((((1+$BM$11)*(1+$BN$11)*(1+$BO$11)*(1+$BP$11)*(1+$BQ$11)*(1+$BR$11)-1)*(1-$BR$13))+1)-1 -> 7.2623393 | BU14: =(1+$BR$14)*((((1+$BM$11)*(1+$BN$11)*(1+$BO$11)*(1+$BP$11)*(1+$BQ$11)*(1+$BR$11)-1)*(1-$BR$13))+1)-1 -> 7.2623393 | BV14: =(1+$BR$14)*((((1+$BM$11)*(1+$BN$11)*(1+$BO$11)*(1+$BP$11)*(1+$BQ$11)*(1+$BR$11)-1)*(1-$BR$13))+1)-1 -> 7.2623393 | BW14: =(1+$BR$14)*((((1+$BM$11)*(1+$BN$11)*(1+$BO$11)*(1+$BP$11)*(1+$BQ$11)*(1+$BR$11)-1)*(1-$BR$13))+1)-1 -> 7.2623393 | BX14: =(1+$BR$14)*((((1+$BM$11)*(1+$BN$11)*(1+$BO$11)*(1+$BP$11)*(1+$BQ$11)*(1+$BR$11)-1)*(1-$BR$13))+1)-1 -> 7.2623393 | BY14: =(1+$BR$14)*((((1+$BM$11)*(1+$BN$11)*(1+$BO$11)*(1+$BP$11)*(1+$BQ$11)*(1+$BR$11)-1)*(1-$BR$13))+1)-1 -> 7.2623393 | BZ14: =(1+$BY$14)*((((1+$BT$11)*(1+$BU$11)*(1+$BV$11)*(1+$BW$11)*(1+$BX$11)*(1+$BY$11)-1)*(1-$BY$13))+1)-1 -> 10.854866 | CA14: =(1+$BY$14)*((((1+$BT$11)*(1+$BU$11)*(1+$BV$11)*(1+$BW$11)*(1+$BX$11)*(1+$BY$11)-1)*(1-$BY$13))+1)-1 -> 10.854866 | CB14: =(1+$BY$14)*((((1+$BT$11)*(1+$BU$11)*(1+$BV$11)*(1+$BW$11)*(1+$BX$11)*(1+$BY$11)-1)*(1-$BY$13))+1)-1 -> 10.854866 | CC14: =(1+$BY$14)*((((1+$BT$11)*(1+$BU$11)*(1+$BV$11)*(1+$BW$11)*(1+$BX$11)*(1+$BY$11)-1)*(1-$BY$13))+1)-1 -> 10.854866 | CD14: =(1+$BY$14)*((((1+$BT$11)*(1+$BU$11)*(1+$BV$11)*(1+$BW$11)*(1+$BX$11)*(1+$BY$11)-1)*(1-$BY$13))+1)-1 -> 10.854866 | CE14: =(1+$BY$14)*((((1+$BT$11)*(1+$BU$11)*(1+$BV$11)*(1+$BW$11)*(1+$BX$11)*(1+$BY$11)-1)*(1-$BY$13))+1)-1 -> 10.854866 | CF14: =(1+$CE$14)*((((1+$BZ$11)*(1+$CA$11)*(1+$CB$11)*(1+$CC$11)*(1+$CD$11)*(1+$CE$11)-1)*(1-$CE$13))+1)-1 -> 19.016513 | CG14: =+CF14*(1+(CF11*(1-CF13))) -> 26.666856 | CH14: =+CG14*(1+(CG11*(1-CG13))) -> 30.734885 | CI14: =+CH14*(1+(CH11*(1-CH13))) -> 35.133047 | CJ14: =+CI14*(1+(CI11*(1-CI13))) -> 37.725865 | CK14: =+CJ14*(1+(CJ11*(1-CJ13))) -> 39.644226 | CL14: =+CK14*(1+(CK11*(1-CK13))) -> 40.464861 | CM14: =+CL14*(1+(CL11*(1-CL13))) -> 41.266065 | CO14: =1*(1+(CM11))-1 -> 0.0275 | CP14: =1*(1+(CO11))-1 -> 0.0205 | CQ14: =1*(1+(CP11))-1 -> 0.0335 | CR14: =1*(1+(CQ11))-1 -> 0.026 | CS14: =1*(1+(CR11))-1 -> 0.021 | CT14: =1*(1+(CS11))-1 -> 0.013 | CU14: =1*(1+(CT11))-1 -> 0.0195 | CV14: =1*(1+(CU11))-1 -> 0.014 | CW14: =1*(1+(CV11))-1 -> 0.0185 | ... DG14: =1*(1+(DF11))-1 -> 0.0215
BT15: =1+(((1+BT11)-1)) -> 1.0595 | BU15: =1+(((1+BU11)-1)) -> 1.0685 | BV15: =1+(((1+BV11)-1)) -> 1.061 | BW15: =1+(((1+BW11)-1)) -> 1.067 | BX15: =1+(((1+BX11)-1)) -> 1.0735 | BY15: =1+(((1+BY11)-1)) -> 1.078 | BZ15: =1+(((1+BZ11)-1)) -> 1.071 | CA15: =1+(((1+CA11)-1)) -> 1.0725 | ... CM15: =1+(((1+CM11)-1)) -> 1.0275 | CO15: =1+(((1+CO11)-1)) -> 1.0205 | CP15: =1+(((1+CP11)-1)) -> 1.0335 | CQ15: =1+(((1+CQ11)-1)) -> 1.026 | CR15: =1+(((1+CR11)-1)) -> 1.021 | CS15: =1+(((1+CS11)-1)) -> 1.013 | CT15: =1+(((1+CT11)-1)) -> 1.0195 | CU15: =1+(((1+CU11)-1)) -> 1.014 | CV15: =1+(((1+CV11)-1)) -> 1.0185 | ... DG15: =1+(((1+DG11)-1)) -> 1
A16: 17.4 | C16: FX Rate | K16: 18.6678 | L16: 19.6378 | M16: 20.2008 | N16: 20.1883 | O16: 22.3873 | P16: 25.5732 | Q16: 27.6313 | R16: 28.1558 | S16: 36.0401 | T16: 37.7419 | U16: 36.0974 | V16: 37.6768 | W16: 37.540588 | X16: 37.8426 | Y16: 40.278833 | Z16: 42.7495 | AA16: 44.6298 | AB16: 44.5014 | AC16: =+AB16 -> 44.5014 | AD16: 42.3633 | AE16: 57.9 | AF16: 56.3589 | AG16: 60 | AH16: 59.85 | AI16: 59.815 | AJ16: 60.35 | AK16: 62.21 | AL16: 64.409 | AM16: 66.84 | AN16: 68.54 | AO16: 70.46 | AP16: 72.32 | AQ16: 74.18 | AR16: 76.18 | AS16: 78.32 | AT16: 81.31 | AU16: 84.15 | AV16: 87.33 | AW16: 89.82 | AX16: 92 | AY16: 93.56 | AZ16: 94.73 | BA16: 95.72 | BB16: 96.69 | BC16: 97.74 | BD16: 98.74 | BE16: 99.72 | BF16: 100.96 | BG16: 102.72 | BH16: 105.02 | BI16: 107.45 | BJ16: 110.89 | BK16: 115.73 | BL16: 120.2 | BM16: 125.45 | BN16: 132.42 | BO16: 141.15 | BP16: 150.69 | BQ16: 157.28 | BR16: 166.96 | BT16: 176.05 | BU16: 187.57 | BV16: 197.15 | BW16: 211.22 | BX16: 225.2 | BY16: 240.25 | BZ16: 257.9 | CA16: 276.15 | CB16: 350.1 | CC16: 350 | CD16: 350 | CE16: 361.1 | CF16: 807.95 | CG16: 825.7 | CH16: 848 | CI16: 858 | CJ16: 890.5 | CK16: 907.5 | CL16: 914.5 | CM16: 931.5 | CO16: 953.5 | CP16: 975.5 | CQ16: 998 | CR16: 1013 | CS16: 1035.5 | CT16: 1054.75 | CU16: 1064.5 | CV16: 1076 | CW16: 1170 | CX16: 1188 | CY16: 1205 | CZ16: 1374 | DA16: 1342 | DB16: 1401.7 | DC16: 1434.43 | DD16: 1428.15 | DE16: 1447.5789 | DF16: 1448.9524 | DG16: 1407.5
C17: Type | D17: Wgt | K17: AR$ | L17: AR$ | M17: AR$ | N17: AR$ | O17: AR$ | P17: AR$ | Q17: AR$ | R17: AR$ | S17: AR$ | T17: AR$ | U17: AR$ | V17: AR$ | W17: AR$ | X17: AR$ | Y17: AR$ | Z17: AR$ | AA17: AR$ | AB17: AR$ | AC17: =+AB17 -> AR$ | AD17: AR$ | AE17: AR$ | AF17: AR$ | AG17: AR$ | AH17: AR$ | AI17: AR$ | AJ17: AR$ | AK17: AR$ | AL17: AR$ | AM17: AR$ | AN17: AR$ | AO17: AR$ | AP17: AR$ | AQ17: AR$ | AR17: AR$ | AS17: AR$ | AT17: AR$ | AU17: AR$ | AV17: AR$ | AW17: AR$ | AX17: AR$ | AY17: AR$ | AZ17: AR$ | BA17: AR$ | BB17: AR$ | BC17: AR$ | BD17: AR$ | BE17: AR$ | BF17: AR$ | BG17: AR$ | BH17: AR$ | BI17: AR$ | BJ17: AR$ | BK17: AR$ | BL17: AR$ | BM17: AR$ | BN17: AR$ | BO17: AR$ | BP17: AR$ | BQ17: AR$ | BR17: AR$ | BT17: AR$ | BU17: AR$ | BV17: AR$ | BW17: AR$ | BX17: AR$ | BY17: AR$ | BZ17: AR$ | CA17: AR$ | CB17: AR$ | CC17: AR$ | CD17: AR$ | CE17: AR$ | CF17: AR$ | CG17: AR$ | CH17: AR$ | CI17: AR$ | CJ17: AR$ | CK17: AR$ | CL17: AR$ | CM17: AR$ | CO17: AR$ | CP17: AR$ | CQ17: AR$ | CR17: AR$ | CS17: AR$ | CT17: AR$ | CU17: AR$ | CV17: AR$ | CW17: AR$ | CX17: AR$ | CY17: AR$ | CZ17: AR$ | DA17: AR$ | DB17: AR$ | DC17: AR$ | DD17: AR$ | DE17: AR$ | DF17: AR$ | DG17: AR$
C18: Resina
C19: SS 250 | D19: 12.5 | BT19: =((+(7*BT$3*(1+BT$7)*0/1000*(1+BT$8))+(95%*$D19*BT$3*(1+BT$7)/1000*(1+BT$8))+(5%*$D19*BT$4*(1+BT$7)/1000*(1+BT$8)))*BT$16) -> 4387.6516 | BU19: =((+(7*BU$3*(1+BU$7)*0/1000*(1+BU$8))+(95%*$D19*BU$3*(1+BU$7)/1000*(1+BU$8))+(5%*$D19*BU$4*(1+BU$7)/1000*(1+BU$8)))*BU$16) -> 4641.1079 | BV19: =((95%*$D19*BV$3*(1+BV$7)/1000*(1+BV$8))+(5%*$D19*BV$4*(1+BV$7)/1000*(1+BV$8)))*BV$16 -> 4820.8229 | BW19: =((95%*$D19*BW$3*(1+BW$7)/1000*(1+BW$8))+(5%*$D19*BW$4*(1+BW$7)/1000*(1+BW$8)))*BW$16 -> 5239.272 | BX19: =((95%*$D19*BX$3*(1+BX$7)/1000*(1+BX$8))+(5%*$D19*BX$4*(1+BX$7)/1000*(1+BX$8)))*BX$16 -> 5602.6568 | BY19: =((95%*$D19*BY$3*(1+BY$7)/1000*(1+BY$8))+(5%*$D19*BY$4*(1+BY$7)/1000*(1+BY$8)))*BY$16 -> 6148.9146 | BZ19: =((95%*$D19*BZ$3*(1+BZ$7)/1000*(1+BZ$8))+(5%*$D19*BZ$4*(1+BZ$7)/1000*(1+BZ$8)))*BZ$16 -> 6304.7614 | CA19: =((95%*$D19*CA$3*(1+CA$7)/1000*(1+CA$8))+(5%*$D19*CA$4*(1+CA$7)/1000*(1+CA$8)))*CA$16 -> 6525.0501 | CB19: =((95%*$D19*CB$3*(1+CB$7)/1000*(1+CB$8))+(5%*$D19*CB$4*(1+CB$7)/1000*(1+CB$8)))*CB$16 -> 7474.4767 | CC19: =((95%*$D19*CC$3*(1+CC$7)/1000*(1+CC$8))+(5%*$D19*CC$4*(1+CC$7)/1000*(1+CC$8)))*CC$16 -> 7707.0649 | ... CM19: =((95%*$D19*CM$3*(1+CM$7)/1000*(1+CM$8))+(5%*$D19*CM$4*(1+CM$7)/1000*(1+CM$8)))*CM$16 -> 22838.909 | CO19: =((95%*$D19*CO$3*(1+CO$7)/1000*(1+CO$8))+(5%*$D19*CO$4*(1+CO$7)/1000*(1+CO$8)))*CO$16 -> 26984.047 | CP19: =((95%*$D19*CP$3*(1+CP$7)/1000*(1+CP$8))+(5%*$D19*CP$4*(1+CP$7)/1000*(1+CP$8)))*CP$16 -> 19831.707 | CQ19: =((95%*$D19*CQ$3*(1+CQ$7)/1000*(1+CQ$8))+(5%*$D19*CQ$4*(1+CQ$7)/1000*(1+CQ$8)))*CQ$16 -> 23520.493 | CR19: =((95%*$D19*CR$3*(1+CR$7)/1000*(1+CR$8))+(5%*$D19*CR$4*(1+CR$7)/1000*(1+CR$8)))*CR$16 -> 24888.513 | CS19: =((95%*$D19*CS$3*(1+CS$7)/1000*(1+CS$8))+(5%*$D19*CS$4*(1+CS$7)/1000*(1+CS$8)))*CS$16 -> 25706.709 | CT19: =((95%*$D19*CT$3*(1+CT$7)/1000*(1+CT$8))+(5%*$D19*CT$4*(1+CT$7)/1000*(1+CT$8)))*CT$16 -> 26038.578 | CU19: =((95%*$D19*CU$3*(1+CU$7)/1000*(1+CU$8))+(5%*$D19*CU$4*(1+CU$7)/1000*(1+CU$8)))*CU$16 -> 25943.838 | CV19: =((95%*$D19*CV$3*(1+CV$7)/1000*(1+CV$8))+(5%*$D19*CV$4*(1+CV$7)/1000*(1+CV$8)))*CV$16 -> 26002.967 | ... DG19: =((95%*$D19*DG$3*(1+DG$7)/1000*(1+DG$8))+(5%*$D19*DG$4*(1+DG$7)/1000*(1+DG$8)))*DG$16 -> 30215.62
C20: SS 500 | D20: 19.5 | BT20: =((3.14*BT$3*(1+BT$7)*0/1000*(1+BT$8))+($D20*BT$3*(1+BT$7)/1000*(1+BT$8)))*BT$16 -> 5564.8603 | BU20: =((3.14*BU$3*(1+BU$7)*0/1000*(1+BU$8))+($D20*BU$3*(1+BU$7)/1000*(1+BU$8)))*BU$16 -> 5873.739 | BV20: =(($D20*BV$3*(1+BV$7)/1000*(1+BV$8)))*BV$16 -> 6079.6003 | BW20: =(($D20*BW$3*(1+BW$7)/1000*(1+BW$8)))*BW$16 -> 6635.6583 | BX20: =(($D20*BX$3*(1+BX$7)/1000*(1+BX$8)))*BX$16 -> 7102.1331 | BY20: =(($D20*BY$3*(1+BY$7)/1000*(1+BY$8)))*BY$16 -> 7858.9365 | BZ20: =(($D20*BZ$3*(1+BZ$7)/1000*(1+BZ$8)))*BZ$16 -> 7950.4214 | CA20: =(($D20*CA$3*(1+CA$7)/1000*(1+CA$8)))*CA$16 -> 8142.1372 | CB20: =(($D20*CB$3*(1+CB$7)/1000*(1+CB$8)))*CB$16 -> 9012.259 | CC20: =(($D20*CC$3*(1+CC$7)/1000*(1+CC$8)))*CC$16 -> 9395.1251 | ... CL20: =(($D20*CL$3*(1+CL$7)/1000*(1+CL$8)))*CL$16 -> 28299.701 | CM20: 28825.807 | CO20: =(($D20*CO$3*(1+CO$7)/1000*(1+CO$8)))*CO$16 -> 35427.603 | CP20: =(($D20*CP$3*(1+CP$7)/1000*(1+CP$8)))*CP$16 -> 23477.75 | CQ20: =(($D20*CQ$3*(1+CQ$7)/1000*(1+CQ$8)))*CQ$16 -> 29325.509 | CR20: =(($D20*CR$3*(1+CR$7)/1000*(1+CR$8)))*CR$16 -> 31434.036 | CS20: =(($D20*CS$3*(1+CS$7)/1000*(1+CS$8)))*CS$16 -> 32568.025 | CT20: =(($D20*CT$3*(1+CT$7)/1000*(1+CT$8)))*CT$16 -> 32933.686 | CU20: =(($D20*CU$3*(1+CU$7)/1000*(1+CU$8)))*CU$16 -> 32687.298 | CV20: =(($D20*CV$3*(1+CV$7)/1000*(1+CV$8)))*CV$16 -> 32677.279 | ... DG20: =(($D20*DG$3*(1+DG$7)/1000*(1+DG$8)))*DG$16 -> 36507.163
C21: SS 500 - 19.5G PCR 100% | D21: 19.5 | CF21: =(($D21*CF$6*(1+CF$7)/1000*(1+CF$8)))*CF$16 -> 0 | CG21: =(($D21*CG$6*(1+CG$7)/1000*(1+CG$8)))*CG$16 -> 41734.549 | CH21: =(($D21*CH$6*(1+CH$7)/1000*(1+CH$8)))*CH$16 -> 42861.69 | CI21: =(($D21*CI$6*(1+CI$7)/1000*(1+CI$8)))*CI$16 -> 43367.135 | CJ21: =(($D21*CJ$6*(1+CJ$7)/1000*(1+CJ$8)))*CJ$16 -> 45009.829 | CK21: =(($D21*CK$6*(1+CK$7)/1000*(1+CK$8)))*CK$16 -> 45869.085 | CL21: =(($D21*CL$6*(1+CL$7)/1000*(1+CL$8)))*CL$16 -> 46222.896 | CM21: 47082.152 | CO21: =(($D21*CO$6*(1+CO$7)/1000*(1+CO$8)))*CO$16 -> 35427.603 | CP21: =(($D21*CP$6*(1+CP$7)/1000*(1+CP$8)))*CP$16 -> 23477.75 | CQ21: =(($D21*CQ$6*(1+CQ$7)/1000*(1+CQ$8)))*CQ$16 -> 29325.509 | CR21: =(($D21*CR$6*(1+CR$7)/1000*(1+CR$8)))*CR$16 -> 31434.036 | CS21: =(($D21*CS$6*(1+CS$7)/1000*(1+CS$8)))*CS$16 -> 32568.025 | CT21: =(($D21*CT$6*(1+CT$7)/1000*(1+CT$8)))*CT$16 -> 32933.686 | CU21: =(($D21*CU$6*(1+CU$7)/1000*(1+CU$8)))*CU$16 -> 32687.298 | CV21: =(($D21*CV$6*(1+CV$7)/1000*(1+CV$8)))*CV$16 -> 32677.279 | ... DG21: =(($D21*DG$6*(1+DG$7)/1000*(1+DG$8)))*DG$16 -> 36507.163
C22: SS 500 | D22: 22.1 | BT22: =+($D22*BT$3*(1+BT$7)/1000*(1+BT$8))*BT$16 -> 6306.8416 | BU22: =+($D22*BU$3*(1+BU$7)/1000*(1+BU$8))*BU$16 -> 6656.9042 | BV22: =+($D22*BV$3*(1+BV$7)/1000*(1+BV$8))*BV$16 -> 6890.2137 | BW22: =+($D22*BW$3*(1+BW$7)/1000*(1+BW$8))*BW$16 -> 7520.4127 | BX22: =+($D22*BX$3*(1+BX$7)/1000*(1+BX$8))*BX$16 -> 8049.0842 | BY22: =+($D22*BY$3*(1+BY$7)/1000*(1+BY$8))*BY$16 -> 8906.7947 | BZ22: =+($D22*BZ$3*(1+BZ$7)/1000*(1+BZ$8))*BZ$16 -> 9010.4776 | CA22: =+($D22*CA$3*(1+CA$7)/1000*(1+CA$8))*CA$16 -> 9227.7555 | ... CL22: =+($D22*CL$3*(1+CL$7)/1000*(1+CL$8))*CL$16 -> 32072.995 | CM22: 32669.248 | CO22: =+($D22*CO$3*(1+CO$7)/1000*(1+CO$8))*CO$16 -> 40151.283 | CP22: =+($D22*CP$3*(1+CP$7)/1000*(1+CP$8))*CP$16 -> 26608.117 | CQ22: =+($D22*CQ$3*(1+CQ$7)/1000*(1+CQ$8))*CQ$16 -> 33235.577 | CR22: =+($D22*CR$3*(1+CR$7)/1000*(1+CR$8))*CR$16 -> 35625.241 | CS22: =+($D22*CS$3*(1+CS$7)/1000*(1+CS$8))*CS$16 -> 36910.429 | CT22: =+($D22*CT$3*(1+CT$7)/1000*(1+CT$8))*CT$16 -> 37324.845 | CU22: =+($D22*CU$3*(1+CU$7)/1000*(1+CU$8))*CU$16 -> 37045.605 | CV22: =+($D22*CV$3*(1+CV$7)/1000*(1+CV$8))*CV$16 -> 37034.249 | ... DG22: =+($D22*DG$3*(1+DG$7)/1000*(1+DG$8))*DG$16 -> 41374.785
C23: SS 500 | D23: 22 | BT23: =+($D23*BT$3*(1+BT$7)/1000*(1+BT$8))*BT$16 -> 6278.3039 | BU23: =+($D23*BU$3*(1+BU$7)/1000*(1+BU$8))*BU$16 -> 6626.7825 | BV23: =+($D23*BV$3*(1+BV$7)/1000*(1+BV$8))*BV$16*0 -> 0 | BW23: =+($D23*BW$3*(1+BW$7)/1000*(1+BW$8))*BW$16*0 -> 0 | BX23: =+($D23*BX$3*(1+BX$7)/1000*(1+BX$8))*BX$16*0 -> 0 | BY23: =+($D23*BY$3*(1+BY$7)/1000*(1+BY$8))*BY$16*0 -> 0 | BZ23: =+($D23*BZ$3*(1+BZ$7)/1000*(1+BZ$8))*BZ$16*0 -> 0 | CA23: =+($D23*CA$3*(1+CA$7)/1000*(1+CA$8))*CA$16*0 -> 0 | CB23: =+($D23*CB$3*(1+CB$7)/1000*(1+CB$8))*CB$16*0 -> 0 | CC23: =+($D23*CC$3*(1+CC$7)/1000*(1+CC$8))*CC$16*0 -> 0 | ... CL23: =+($D23*CL$3*(1+CL$7)/1000*(1+CL$8))*CL$16*0 -> 0 | CM23: 0 | CO23: =+($D23*CO$3*(1+CO$7)/1000*(1+CO$8))*CO$16*0 -> 0 | CP23: =+($D23*CP$3*(1+CP$7)/1000*(1+CP$8))*CP$16*0 -> 0 | CQ23: =+($D23*CQ$3*(1+CQ$7)/1000*(1+CQ$8))*CQ$16*0 -> 0 | CR23: =+($D23*CR$3*(1+CR$7)/1000*(1+CR$8))*CR$16*0 -> 0 | CS23: =+($D23*CS$3*(1+CS$7)/1000*(1+CS$8))*CS$16*0 -> 0 | CT23: =+($D23*CT$3*(1+CT$7)/1000*(1+CT$8))*CT$16*0 -> 0 | CU23: =+($D23*CU$3*(1+CU$7)/1000*(1+CU$8))*CU$16*0 -> 0 | CV23: =+($D23*CV$3*(1+CV$7)/1000*(1+CV$8))*CV$16*0 -> 0 | ... DG23: =+($D23*DG$3*(1+DG$7)/1000*(1+DG$8))*DG$16*0 -> 0
C24: SS 500 | D24: 25 | BT24: =+($D24*BT$3*(1+BT$7)/1000*(1+BT$8))*BT$16 -> 7134.4362 | BU24: =+($D24*BU$3*(1+BU$7)/1000*(1+BU$8))*BU$16 -> 7530.4347 | BV24: =+($D24*BV$3*(1+BV$7)/1000*(1+BV$8))*BV$16 -> 7794.3594 | BW24: =+($D24*BW$3*(1+BW$7)/1000*(1+BW$8))*BW$16 -> 8507.2542 | BX24: =+($D24*BX$3*(1+BX$7)/1000*(1+BX$8))*BX$16 -> 9105.2989 | BY24: =+($D24*BY$3*(1+BY$7)/1000*(1+BY$8))*BY$16 -> 10075.56 | BZ24: =+($D24*BZ$3*(1+BZ$7)/1000*(1+BZ$8))*BZ$16 -> 10192.848 | CA24: =+($D24*CA$3*(1+CA$7)/1000*(1+CA$8))*CA$16 -> 10438.637 | ... CL24: =+($D24*CL$3*(1+CL$7)/1000*(1+CL$8))*CL$16 -> 36281.668 | CM24: 36956.163 | CO24: =+($D24*CO$3*(1+CO$7)/1000*(1+CO$8))*CO$16 -> 45420.004 | CP24: =+($D24*CP$3*(1+CP$7)/1000*(1+CP$8))*CP$16 -> 30099.68 | CQ24: =+($D24*CQ$3*(1+CQ$7)/1000*(1+CQ$8))*CQ$16 -> 37596.806 | CR24: =+($D24*CR$3*(1+CR$7)/1000*(1+CR$8))*CR$16 -> 40300.047 | CS24: =+($D24*CS$3*(1+CS$7)/1000*(1+CS$8))*CS$16 -> 41753.879 | CT24: =+($D24*CT$3*(1+CT$7)/1000*(1+CT$8))*CT$16 -> 42222.675 | CU24: =+($D24*CU$3*(1+CU$7)/1000*(1+CU$8))*CU$16 -> 41906.793 | CV24: =+($D24*CV$3*(1+CV$7)/1000*(1+CV$8))*CV$16 -> 41893.947 | ... DG24: =+($D24*DG$3*(1+DG$7)/1000*(1+DG$8))*DG$16 -> 46804.055
C25: SS 500 - 25G PCR 100% | D25: 25 | CF25: =+($D25*CF$6*(1+CF$7)/1000*(1+CF$8))*CF$16 -> 0 | CG25: =+($D25*CG$6*(1+CG$7)/1000*(1+CG$8))*CG$16 -> 53505.832 | CH25: =+($D25*CH$6*(1+CH$7)/1000*(1+CH$8))*CH$16 -> 54950.885 | CI25: =+($D25*CI$6*(1+CI$7)/1000*(1+CI$8))*CI$16 -> 55598.891 | CJ25: =+($D25*CJ$6*(1+CJ$7)/1000*(1+CJ$8))*CJ$16 -> 57704.91 | CK25: =+($D25*CK$6*(1+CK$7)/1000*(1+CK$8))*CK$16 -> 58806.519 | CL25: =+($D25*CL$6*(1+CL$7)/1000*(1+CL$8))*CL$16 -> 59260.123 | CM25: 60361.733 | CO25: =+($D25*CO$6*(1+CO$7)/1000*(1+CO$8))*CO$16 -> 45420.004 | CP25: =+($D25*CP$6*(1+CP$7)/1000*(1+CP$8))*CP$16 -> 30099.68 | CQ25: =+($D25*CQ$6*(1+CQ$7)/1000*(1+CQ$8))*CQ$16 -> 37596.806 | CR25: =+($D25*CR$6*(1+CR$7)/1000*(1+CR$8))*CR$16 -> 40300.047 | CS25: =+($D25*CS$6*(1+CS$7)/1000*(1+CS$8))*CS$16 -> 41753.879 | CT25: =+($D25*CT$6*(1+CT$7)/1000*(1+CT$8))*CT$16 -> 42222.675 | CU25: =+($D25*CU$6*(1+CU$7)/1000*(1+CU$8))*CU$16 -> 41906.793 | CV25: =+($D25*CV$6*(1+CV$7)/1000*(1+CV$8))*CV$16 -> 41893.947 | ... DG25: =+($D25*DG$6*(1+DG$7)/1000*(1+DG$8))*DG$16 -> 46804.055
C26: MS 1500 | D26: 37.2 | BT26: =+(4.62*BT$3*(1+BT$7)*0/1000*(1+BT$8))+($D$26*BT$3*(1+BT$7)/1000*(1+BT$8))*BT$16 -> 10616.041 | BU26: =+(4.62*BU$3*(1+BU$7)*0/1000*(1+BU$8))+($D$26*BU$3*(1+BU$7)/1000*(1+BU$8))*BU$16 -> 11205.287 | BV26: =+(+(D26*BV$3*(1+BV$7)/1000*(1+BV$8))*BV$16) -> 11598.007 | BW26: =+(+($D$26*BW$3*(1+BW$7)/1000*(1+BW$8))*BW$16) -> 12658.794 | BX26: =+(+($D$26*BX$3*(1+BX$7)/1000*(1+BX$8))*BX$16) -> 13548.685 | BY26: =+(+($D$26*BY$3*(1+BY$7)/1000*(1+BY$8))*BY$16) -> 14992.433 | BZ26: =+(+($D$26*BZ$3*(1+BZ$7)/1000*(1+BZ$8))*BZ$16) -> 15166.958 | CA26: =+(+($D$26*CA$3*(1+CA$7)/1000*(1+CA$8))*CA$16) -> 15532.693 | CB26: =+(+($D$26*CB$3*(1+CB$7)/1000*(1+CB$8))*CB$16) -> 17192.617 | CC26: =+(+($D$26*CC$3*(1+CC$7)/1000*(1+CC$8))*CC$16) -> 17923.008 | CD26: =+(+($D$26*CD$3*(1+CD$7)/1000*(1+CD$8))*CD$16) -> 18083.397 | ... CL26: =+(+($D$26*CL$3*(1+CL$7)/1000*(1+CL$8))*CL$16) -> 53987.122 | CM26: 54990.771 | CO26: =+(+($D$26*CO$3*(1+CO$7)/1000*(1+CO$8))*CO$16) -> 67584.966 | CP26: =+(+($D$26*CP$3*(1+CP$7)/1000*(1+CP$8))*CP$16) -> 44788.323 | CQ26: =+(+($D$26*CQ$3*(1+CQ$7)/1000*(1+CQ$8))*CQ$16) -> 55944.048 | CR26: =+(+($D$26*CR$3*(1+CR$7)/1000*(1+CR$8))*CR$16) -> 59966.469 | CS26: =+(+($D$26*CS$3*(1+CS$7)/1000*(1+CS$8))*CS$16) -> 62129.771 | CT26: =+(+($D$26*CT$3*(1+CT$7)/1000*(1+CT$8))*CT$16) -> 62827.34 | CU26: =+(+($D$26*CU$3*(1+CU$7)/1000*(1+CU$8))*CU$16) -> 62357.308 | CV26: =+(+($D$26*CV$3*(1+CV$7)/1000*(1+CV$8))*CV$16) -> 62338.193 | ... DG26: =+(+($D$26*DG$3*(1+DG$7)/1000*(1+DG$8))*DG$16) -> 69644.434
C27: MS 1500 | D27: 40 | BT27: =+($D27*BT$3*(1+BT$7)/1000*(1+BT$8))*BT$16 -> 11415.098 | BU27: =+($D27*BU$3*(1+BU$7)/1000*(1+BU$8))*BU$16 -> 12048.695 | BV27: =+($D27*BV$3*(1+BV$7)/1000*(1+BV$8))*BV$16*0 -> 0 | BW27: =+($D27*BW$3*(1+BW$7)/1000*(1+BW$8))*BW$16*0 -> 0 | BX27: =+($D27*BX$3*(1+BX$7)/1000*(1+BX$8))*BX$16*0 -> 0 | BY27: =+($D27*BY$3*(1+BY$7)/1000*(1+BY$8))*BY$16*0 -> 0 | BZ27: =+($D27*BZ$3*(1+BZ$7)/1000*(1+BZ$8))*BZ$16*0 -> 0 | CA27: =+($D27*CA$3*(1+CA$7)/1000*(1+CA$8))*CA$16*0 -> 0 | CB27: =+($D27*CB$3*(1+CB$7)/1000*(1+CB$8))*CB$16*0 -> 0 | CC27: =+($D27*CC$3*(1+CC$7)/1000*(1+CC$8))*CC$16*0 -> 0 | ... CL27: =+($D27*CL$3*(1+CL$7)/1000*(1+CL$8))*CL$16*0 -> 0 | CM27: 0 | CO27: =+($D27*CO$3*(1+CO$7)/1000*(1+CO$8))*CO$16*0 -> 0 | CP27: =+($D27*CP$3*(1+CP$7)/1000*(1+CP$8))*CP$16*0 -> 0 | CQ27: =+($D27*CQ$3*(1+CQ$7)/1000*(1+CQ$8))*CQ$16*0 -> 0 | CR27: =+($D27*CR$3*(1+CR$7)/1000*(1+CR$8))*CR$16*0 -> 0 | CS27: =+($D27*CS$3*(1+CS$7)/1000*(1+CS$8))*CS$16*0 -> 0 | CT27: =+($D27*CT$3*(1+CT$7)/1000*(1+CT$8))*CT$16*0 -> 0 | CU27: =+($D27*CU$3*(1+CU$7)/1000*(1+CU$8))*CU$16*0 -> 0 | CV27: =+($D27*CV$3*(1+CV$7)/1000*(1+CV$8))*CV$16*0 -> 0 | ... DG27: =+($D27*DG$3*(1+DG$7)/1000*(1+DG$8))*DG$16*0 -> 0
C28: MS 1500 | D28: 44 | BT28: =+($D28*BT$3*(1+BT$7)/1000*(1+BT$8))*BT$16 -> 12556.608 | BU28: =+($D28*BU$3*(1+BU$7)/1000*(1+BU$8))*BU$16 -> 13253.565 | BV28: =+($D28*BV$3*(1+BV$7)/1000*(1+BV$8))*BV$16 -> 13718.073 | BW28: =+($D28*BW$3*(1+BW$7)/1000*(1+BW$8))*BW$16 -> 14972.767 | BX28: =+($D28*BX$3*(1+BX$7)/1000*(1+BX$8))*BX$16 -> 16025.326 | BY28: =+($D28*BY$3*(1+BY$7)/1000*(1+BY$8))*BY$16 -> 17732.985 | BZ28: =+($D28*BZ$3*(1+BZ$7)/1000*(1+BZ$8))*BZ$16 -> 17939.412 | CA28: =+($D28*CA$3*(1+CA$7)/1000*(1+CA$8))*CA$16 -> 18372.002 | ... CL28: =+($D28*CL$3*(1+CL$7)/1000*(1+CL$8))*CL$16 -> 63855.736 | CM28: 65042.847 | CO28: =+($D28*CO$3*(1+CO$7)/1000*(1+CO$8))*CO$16 -> 79939.207 | CP28: =+($D28*CP$3*(1+CP$7)/1000*(1+CP$8))*CP$16 -> 52975.436 | CQ28: =+($D28*CQ$3*(1+CQ$7)/1000*(1+CQ$8))*CQ$16 -> 66170.379 | CR28: =+($D28*CR$3*(1+CR$7)/1000*(1+CR$8))*CR$16 -> 70928.082 | CS28: =+($D28*CS$3*(1+CS$7)/1000*(1+CS$8))*CS$16 -> 73486.826 | CT28: =+($D28*CT$3*(1+CT$7)/1000*(1+CT$8))*CT$16 -> 74311.908 | CU28: =+($D28*CU$3*(1+CU$7)/1000*(1+CU$8))*CU$16 -> 73755.956 | CV28: =+($D28*CV$3*(1+CV$7)/1000*(1+CV$8))*CV$16 -> 73733.347 | ... DG28: =+($D28*DG$3*(1+DG$7)/1000*(1+DG$8))*DG$16 -> 82375.137
C29: MS 2000/2250 | D29: 42.6 | BT29: =(4*BT$3*(1+BT$7)*0/1000*(1+BT$8))+($D29*BT$3*(1+BT$7)/1000*(1+BT$8))*BT$16 -> 12157.079 | BU29: =(4*BU$3*(1+BU$7)*0/1000*(1+BU$8))+($D29*BU$3*(1+BU$7)/1000*(1+BU$8))*BU$16 -> 12831.861 | BV29: =(4*BV$3*(1+BV$7)*0/1000*(1+BV$8))+($D29*BV$3*(1+BV$7)/1000*(1+BV$8))*BV$16*0 -> 0 | BW29: =(4*BW$3*(1+BW$7)*0/1000*(1+BW$8))+($D29*BW$3*(1+BW$7)/1000*(1+BW$8))*BW$16*0 -> 0 | BX29: =(4*BX$3*(1+BX$7)*0/1000*(1+BX$8))+($D29*BX$3*(1+BX$7)/1000*(1+BX$8))*BX$16*0 -> 0 | BY29: =(4*BY$3*(1+BY$7)*0/1000*(1+BY$8))+($D29*BY$3*(1+BY$7)/1000*(1+BY$8))*BY$16*0 -> 0 | BZ29: =(4*BZ$3*(1+BZ$7)*0/1000*(1+BZ$8))+($D29*BZ$3*(1+BZ$7)/1000*(1+BZ$8))*BZ$16*0 -> 0 | CA29: =(4*CA$3*(1+CA$7)*0/1000*(1+CA$8))+($D29*CA$3*(1+CA$7)/1000*(1+CA$8))*CA$16*0 -> 0 | CB29: =(4*CB$3*(1+CB$7)*0/1000*(1+CB$8))+($D29*CB$3*(1+CB$7)/1000*(1+CB$8))*CB$16*0 -> 0 | CC29: =(4*CC$3*(1+CC$7)*0/1000*(1+CC$8))+($D29*CC$3*(1+CC$7)/1000*(1+CC$8))*CC$16*0 -> 0 | ... CL29: =(4*CL$3*(1+CL$7)*0/1000*(1+CL$8))+($D29*CL$3*(1+CL$7)/1000*(1+CL$8))*CL$16*0 -> 0 | CM29: 0 | CO29: =(4*CO$3*(1+CO$7)*0/1000*(1+CO$8))+($D29*CO$3*(1+CO$7)/1000*(1+CO$8))*CO$16*0 -> 0 | CP29: =(4*CP$3*(1+CP$7)*0/1000*(1+CP$8))+($D29*CP$3*(1+CP$7)/1000*(1+CP$8))*CP$16*0 -> 0 | CQ29: =(4*CQ$3*(1+CQ$7)*0/1000*(1+CQ$8))+($D29*CQ$3*(1+CQ$7)/1000*(1+CQ$8))*CQ$16*0 -> 0 | CR29: =(4*CR$3*(1+CR$7)*0/1000*(1+CR$8))+($D29*CR$3*(1+CR$7)/1000*(1+CR$8))*CR$16*0 -> 0 | CS29: =(4*CS$3*(1+CS$7)*0/1000*(1+CS$8))+($D29*CS$3*(1+CS$7)/1000*(1+CS$8))*CS$16*0 -> 0 | CT29: =(4*CT$3*(1+CT$7)*0/1000*(1+CT$8))+($D29*CT$3*(1+CT$7)/1000*(1+CT$8))*CT$16*0 -> 0 | CU29: =(4*CU$3*(1+CU$7)*0/1000*(1+CU$8))+($D29*CU$3*(1+CU$7)/1000*(1+CU$8))*CU$16*0 -> 0 | CV29: =(4*CV$3*(1+CV$7)*0/1000*(1+CV$8))+($D29*CV$3*(1+CV$7)/1000*(1+CV$8))*CV$16*0 -> 0 | ... DG29: =(4*DG$3*(1+DG$7)*0/1000*(1+DG$8))+($D29*DG$3*(1+DG$7)/1000*(1+DG$8))*DG$16*0 -> 0
C30: MS 2000/2250 | D30: 46.6 | BT30: =(4.833*BT$3*(1+BT$7)*0/1000*(1+BT$8))+($D30*BT$3*(1+BT$7)/1000*(1+BT$8))*BT$16 -> 13298.589 | BU30: =(4.833*BU$3*(1+BU$7)*0/1000*(1+BU$8))+($D30*BU$3*(1+BU$7)/1000*(1+BU$8))*BU$16 -> 14036.73 | BV30: =(+($D30*BV$3*(1+BV$7)/1000*(1+BV$8))*BV$16) -> 14528.686 | BW30: =(+($D30*BW$3*(1+BW$7)/1000*(1+BW$8))*BW$16) -> 15857.522 | BX30: =(+($D30*BX$3*(1+BX$7)/1000*(1+BX$8))*BX$16) -> 16972.277 | BY30: =(+($D30*BY$3*(1+BY$7)/1000*(1+BY$8))*BY$16) -> 18780.843 | BZ30: =(+($D30*BZ$3*(1+BZ$7)/1000*(1+BZ$8))*BZ$16) -> 18999.469 | CA30: =(+($D30*CA$3*(1+CA$7)/1000*(1+CA$8))*CA$16) -> 19457.62 | CB30: =(+($D30*CB$3*(1+CB$7)/1000*(1+CB$8))*CB$16) -> 21536.988 | CC30: =(+($D30*CC$3*(1+CC$7)/1000*(1+CC$8))*CC$16) -> 22451.94 | ... CL30: =(+($D30*CL$3*(1+CL$7)/1000*(1+CL$8))*CL$16) -> 67629.03 | CM30: 68886.288 | CO30: =(+($D30*CO$3*(1+CO$7)/1000*(1+CO$8))*CO$16) -> 84662.887 | CP30: =(+($D30*CP$3*(1+CP$7)/1000*(1+CP$8))*CP$16) -> 56105.803 | CQ30: =(+($D30*CQ$3*(1+CQ$7)/1000*(1+CQ$8))*CQ$16) -> 70080.447 | CR30: =(+($D30*CR$3*(1+CR$7)/1000*(1+CR$8))*CR$16) -> 75119.287 | CS30: =(+($D30*CS$3*(1+CS$7)/1000*(1+CS$8))*CS$16) -> 77829.23 | CT30: =(+($D30*CT$3*(1+CT$7)/1000*(1+CT$8))*CT$16) -> 78703.066 | CU30: =(+($D30*CU$3*(1+CU$7)/1000*(1+CU$8))*CU$16) -> 78114.262 | CV30: =(+($D30*CV$3*(1+CV$7)/1000*(1+CV$8))*CV$16) -> 78090.318 | ... DG30: =(+($D30*DG$3*(1+DG$7)/1000*(1+DG$8))*DG$16) -> 87242.759
C31: MS 2000/2250 20% PCR | D31: 46.6 | CG31: =(+((($D31*CG$3*0.8)+($D31*CG$6*0.2))*(1+CG$7)/1000*(1+CG$8))*CG$16) -> 79739.048 | CH31: =(+((($D31*CH$3*0.8)+($D31*CH$6*0.2))*(1+CH$7)/1000*(1+CH$8))*CH$16) -> 78949.341 | CI31: =(+((($D31*CI$3*0.8)+($D31*CI$6*0.2))*(1+CI$7)/1000*(1+CI$8))*CI$16) -> 78357.528 | CJ31: =(+((($D31*CJ$3*0.8)+($D31*CJ$6*0.2))*(1+CJ$7)/1000*(1+CJ$8))*CJ$16) -> 74195.833 | CK31: =(+((($D31*CK$3*0.8)+($D31*CK$6*0.2))*(1+CK$7)/1000*(1+CK$8))*CK$16) -> 75612.342 | CL31: =(+((($D31*CL$3*0.8)+($D31*CL$6*0.2))*(1+CL$7)/1000*(1+CL$8))*CL$16) -> 76195.398 | CM31: 77611.884 | CO31: =(+((($D31*CO$3*0.8)+($D31*CO$6*0.2))*(1+CO$7)/1000*(1+CO$8))*CO$16)*0 -> 0 | CP31: =(+((($D31*CP$3*0.8)+($D31*CP$6*0.2))*(1+CP$7)/1000*(1+CP$8))*CP$16)*0 -> 0 | CQ31: =(+((($D31*CQ$3*0.8)+($D31*CQ$6*0.2))*(1+CQ$7)/1000*(1+CQ$8))*CQ$16)*0 -> 0 | CR31: =(+((($D31*CR$3*0.8)+($D31*CR$6*0.2))*(1+CR$7)/1000*(1+CR$8))*CR$16)*0 -> 0 | CS31: =(+($D31*CS$3*(1+CS$7)/1000*(1+CS$8))*CS$16) -> 77829.23 | CT31: =(+($D31*CT$3*(1+CT$7)/1000*(1+CT$8))*CT$16) -> 78703.066 | CU31: =(+($D31*CU$3*(1+CU$7)/1000*(1+CU$8))*CU$16) -> 78114.262 | CV31: =(+($D31*CV$3*(1+CV$7)/1000*(1+CV$8))*CV$16) -> 78090.318 | CW31: =(+($D31*CW$3*(1+CW$7)/1000*(1+CW$8))*CW$16) -> 82196.793 | CX31: =(+($D31*CX$3*(1+CX$7)/1000*(1+CX$8))*CX$16) -> 80933.641 | CY31: =(+($D31*CY$3*(1+CY$7)/1000*(1+CY$8))*CY$16) -> 78487.531 | CZ31: =(+($D31*CZ$3*(1+CZ$7)/1000*(1+CZ$8))*CZ$16) -> 86945.279 | ... DG31: =(+($D31*DG$3*(1+DG$7)/1000*(1+DG$8))*DG$16) -> 87242.759
C32: MS 2000/2250 | D32: 48 | BT32: =+(4*BT$3*(1+BT$7)*0/1000*(1+BT$8))+($D32*BT$3*(1+BT$7)/1000*(1+BT$8))*BT$16 -> 13698.118 | BU32: =+(4*BU$3*(1+BU$7)*0/1000*(1+BU$8))+($D32*BU$3*(1+BU$7)/1000*(1+BU$8))*BU$16 -> 14458.435 | BV32: =+(+($D32*BV$3*(1+BV$7)/1000*(1+BV$8))*BV$16) -> 14965.17 | BW32: =+(+($D32*BW$3*(1+BW$7)/1000*(1+BW$8))*BW$16) -> 16333.928 | BX32: =+(+($D32*BX$3*(1+BX$7)/1000*(1+BX$8))*BX$16) -> 17482.174 | BY32: =+(+($D32*BY$3*(1+BY$7)/1000*(1+BY$8))*BY$16) -> 19345.074 | BZ32: =+(+($D32*BZ$3*(1+BZ$7)/1000*(1+BZ$8))*BZ$16) -> 19570.268 | CA32: =+(+($D32*CA$3*(1+CA$7)/1000*(1+CA$8))*CA$16) -> 20042.184 | CB32: =+(+($D32*CB$3*(1+CB$7)/1000*(1+CB$8))*CB$16) -> 22184.022 | CC32: =+(+($D32*CC$3*(1+CC$7)/1000*(1+CC$8))*CC$16) -> 23126.462 | ... CL32: =+(+($D32*CL$3*(1+CL$7)/1000*(1+CL$8))*CL$16) -> 69660.803 | CM32: 70955.833 | CO32: =+(+($D32*CO$3*(1+CO$7)/1000*(1+CO$8))*CO$16) -> 87206.407 | CP32: =+(+($D32*CP$3*(1+CP$7)/1000*(1+CP$8))*CP$16) -> 57791.385 | CQ32: =+(+($D32*CQ$3*(1+CQ$7)/1000*(1+CQ$8))*CQ$16) -> 72185.868 | CR32: =+(+($D32*CR$3*(1+CR$7)/1000*(1+CR$8))*CR$16) -> 77376.089 | CS32: =+(+($D32*CS$3*(1+CS$7)/1000*(1+CS$8))*CS$16) -> 80167.447 | CT32: =+(+($D32*CT$3*(1+CT$7)/1000*(1+CT$8))*CT$16) -> 81067.536 | CU32: =+(+($D32*CU$3*(1+CU$7)/1000*(1+CU$8))*CU$16) -> 80461.042 | CV32: =+(+($D32*CV$3*(1+CV$7)/1000*(1+CV$8))*CV$16) -> 80436.379 | ... DG32: =+(+($D32*DG$3*(1+DG$7)/1000*(1+DG$8))*DG$16) -> 89863.786
C33: MS 2000/2250 | D33: 49.6 | BT33: =+(4.833*BT$3*(1+BT$7)*0/1000*(1+BT$8))+($D33*BT$3*(1+BT$7)/1000*(1+BT$8))*BT$16 -> 14154.721 | BU33: =+(4.833*BU$3*(1+BU$7)*0/1000*(1+BU$8))+($D33*BU$3*(1+BU$7)/1000*(1+BU$8))*BU$16 -> 14940.382 | BV33: =+(($D33*BV$3*(1+BV$7)/1000*(1+BV$8))*BV$16)*0 -> 0 | BW33: =+(($D33*BW$3*(1+BW$7)/1000*(1+BW$8))*BW$16)*0 -> 0 | BX33: =+(($D33*BX$3*(1+BX$7)/1000*(1+BX$8))*BX$16)*0 -> 0 | BY33: =+(($D33*BY$3*(1+BY$7)/1000*(1+BY$8))*BY$16)*0 -> 0 | BZ33: =+(($D33*BZ$3*(1+BZ$7)/1000*(1+BZ$8))*BZ$16)*0 -> 0 | CA33: =+(($D33*CA$3*(1+CA$7)/1000*(1+CA$8))*CA$16)*0 -> 0 | CB33: =+(($D33*CB$3*(1+CB$7)/1000*(1+CB$8))*CB$16)*0 -> 0 | CC33: =+(($D33*CC$3*(1+CC$7)/1000*(1+CC$8))*CC$16)*0 -> 0 | ... CL33: =+(($D33*CL$3*(1+CL$7)/1000*(1+CL$8))*CL$16)*0 -> 0 | CM33: 0 | CO33: =+(($D33*CO$3*(1+CO$7)/1000*(1+CO$8))*CO$16)*0 -> 0 | CP33: =+(($D33*CP$3*(1+CP$7)/1000*(1+CP$8))*CP$16)*0 -> 0 | CQ33: =+(($D33*CQ$3*(1+CQ$7)/1000*(1+CQ$8))*CQ$16)*0 -> 0 | CR33: =+(($D33*CR$3*(1+CR$7)/1000*(1+CR$8))*CR$16)*0 -> 0 | CS33: =+(($D33*CS$3*(1+CS$7)/1000*(1+CS$8))*CS$16)*0 -> 0 | CT33: =+(($D33*CT$3*(1+CT$7)/1000*(1+CT$8))*CT$16)*0 -> 0 | CU33: =+(($D33*CU$3*(1+CU$7)/1000*(1+CU$8))*CU$16)*0 -> 0 | CV33: =+(($D33*CV$3*(1+CV$7)/1000*(1+CV$8))*CV$16)*0 -> 0 | ... DG33: =+(($D33*DG$3*(1+DG$7)/1000*(1+DG$8))*DG$16)*0 -> 0
C34: MS 2000/2250 | D34: 52 | BT34: =+($D34*BT$3*(1+BT$7)/1000*(1+BT$8))*BT$16 -> 14839.627 | BU34: =+($D34*BU$3*(1+BU$7)/1000*(1+BU$8))*BU$16 -> 15663.304 | BV34: =+($D34*BV$3*(1+BV$7)/1000*(1+BV$8))*BV$16 -> 16212.268 | BW34: =+($D34*BW$3*(1+BW$7)/1000*(1+BW$8))*BW$16 -> 17695.089 | BX34: =+($D34*BX$3*(1+BX$7)/1000*(1+BX$8))*BX$16 -> 18939.022 | BY34: =+($D34*BY$3*(1+BY$7)/1000*(1+BY$8))*BY$16 -> 20957.164 | BZ34: =+($D34*BZ$3*(1+BZ$7)/1000*(1+BZ$8))*BZ$16 -> 21201.124 | CA34: =+($D34*CA$3*(1+CA$7)/1000*(1+CA$8))*CA$16 -> 21712.366 | ... CL34: =+($D34*CL$3*(1+CL$7)/1000*(1+CL$8))*CL$16 -> 75465.87 | CM34: 76868.819 | CO34: =+($D34*CO$3*(1+CO$7)/1000*(1+CO$8))*CO$16 -> 94473.608 | CP34: =+($D34*CP$3*(1+CP$7)/1000*(1+CP$8))*CP$16 -> 62607.334 | CQ34: =+($D34*CQ$3*(1+CQ$7)/1000*(1+CQ$8))*CQ$16 -> 78201.357 | CR34: =+($D34*CR$3*(1+CR$7)/1000*(1+CR$8))*CR$16 -> 83824.097 | CS34: =+($D34*CS$3*(1+CS$7)/1000*(1+CS$8))*CS$16 -> 86848.067 | CT34: =+($D34*CT$3*(1+CT$7)/1000*(1+CT$8))*CT$16 -> 87823.164 | CU34: =+($D34*CU$3*(1+CU$7)/1000*(1+CU$8))*CU$16 -> 87166.129 | CV34: =+($D34*CV$3*(1+CV$7)/1000*(1+CV$8))*CV$16 -> 87139.41 | ... DG34: =+($D34*DG$3*(1+DG$7)/1000*(1+DG$8))*DG$16 -> 97352.435
C35: MS 3000 | D35: 54.7 | BT35: =+(5.18*BT$3*(1+BT$7)*0/1000*(1+BT$8))+($D35*BT$3*(1+BT$7)/1000*(1+BT$8))*BT$16 -> 15610.146 | BU35: =+(5.18*BU$3*(1+BU$7)*0/1000*(1+BU$8))+($D35*BU$3*(1+BU$7)/1000*(1+BU$8))*BU$16 -> 16476.591 | BV35: =+(+($D35*BV$3*(1+BV$7)/1000*(1+BV$8))*BV$16) -> 17054.058 | BW35: =+(+($D35*BW$3*(1+BW$7)/1000*(1+BW$8))*BW$16) -> 18613.872 | BX35: =+(+($D35*BX$3*(1+BX$7)/1000*(1+BX$8))*BX$16) -> 19922.394 | BY35: =+(+($D35*BY$3*(1+BY$7)/1000*(1+BY$8))*BY$16) -> 22045.324 | BZ35: =+(+($D35*BZ$3*(1+BZ$7)/1000*(1+BZ$8))*BZ$16) -> 22301.951 | CA35: =+(+($D35*CA$3*(1+CA$7)/1000*(1+CA$8))*CA$16) -> 22839.739 | CB35: =+(+($D35*CB$3*(1+CB$7)/1000*(1+CB$8))*CB$16) -> 25280.542 | CC35: =+(+($D35*CC$3*(1+CC$7)/1000*(1+CC$8))*CC$16) -> 26354.53 | ... CL35: =+(+($D35*CL$3*(1+CL$7)/1000*(1+CL$8))*CL$16) -> 79384.29 | CM35: 80860.085 | CO35: =+(+($D35*CO$3*(1+CO$7)/1000*(1+CO$8))*CO$16) -> 99378.968 | CP35: =+(+($D35*CP$3*(1+CP$7)/1000*(1+CP$8))*CP$16) -> 65858.099 | CQ35: =+(+($D35*CQ$3*(1+CQ$7)/1000*(1+CQ$8))*CQ$16) -> 82261.812 | CR35: =+(+($D35*CR$3*(1+CR$7)/1000*(1+CR$8))*CR$16) -> 88176.502 | CS35: =+(+($D35*CS$3*(1+CS$7)/1000*(1+CS$8))*CS$16) -> 91357.486 | CT35: =+(+($D35*CT$3*(1+CT$7)/1000*(1+CT$8))*CT$16) -> 92383.213 | CU35: =+(+($D35*CU$3*(1+CU$7)/1000*(1+CU$8))*CU$16) -> 91692.063 | CV35: =+(+($D35*CV$3*(1+CV$7)/1000*(1+CV$8))*CV$16) -> 91663.956 | ... DG35: =+(+($D35*DG$3*(1+DG$7)/1000*(1+DG$8))*DG$16) -> 102407.27
C36: MS 3000 | D36: 58 | BT36: =+(5.18*BT$3*(1+BT$7)*0/1000*(1+BT$8))+($D36*BT$3*(1+BT$7)/1000*(1+BT$8))*BT$16 -> 16551.892 | BU36: =+(5.18*BU$3*(1+BU$7)*0/1000*(1+BU$8))+($D36*BU$3*(1+BU$7)/1000*(1+BU$8))*BU$16 -> 17470.608 | BV36: =+(($D36*BV$3*(1+BV$7)/1000*(1+BV$8))*BV$16)*0 -> 0 | BW36: =+(($D36*BW$3*(1+BW$7)/1000*(1+BW$8))*BW$16)*0 -> 0 | BX36: =+(($D36*BX$3*(1+BX$7)/1000*(1+BX$8))*BX$16)*0 -> 0 | BY36: =+(($D36*BY$3*(1+BY$7)/1000*(1+BY$8))*BY$16)*0 -> 0 | BZ36: =+(($D36*BZ$3*(1+BZ$7)/1000*(1+BZ$8))*BZ$16)*0 -> 0 | CA36: =+(($D36*CA$3*(1+CA$7)/1000*(1+CA$8))*CA$16)*0 -> 0 | CB36: =+(($D36*CB$3*(1+CB$7)/1000*(1+CB$8))*CB$16)*0 -> 0 | CC36: =+(($D36*CC$3*(1+CC$7)/1000*(1+CC$8))*CC$16)*0 -> 0 | ... CL36: =+(($D36*CL$3*(1+CL$7)/1000*(1+CL$8))*CL$16)*0 -> 0 | CM36: 0 | CO36: =+(($D36*CO$3*(1+CO$7)/1000*(1+CO$8))*CO$16)*0 -> 0 | CP36: =+(($D36*CP$3*(1+CP$7)/1000*(1+CP$8))*CP$16)*0 -> 0 | CQ36: =+(($D36*CQ$3*(1+CQ$7)/1000*(1+CQ$8))*CQ$16)*0 -> 0 | CR36: =+(($D36*CR$3*(1+CR$7)/1000*(1+CR$8))*CR$16)*0 -> 0 | CS36: =+(($D36*CS$3*(1+CS$7)/1000*(1+CS$8))*CS$16)*0 -> 0 | CT36: =+(($D36*CT$3*(1+CT$7)/1000*(1+CT$8))*CT$16)*0 -> 0 | CU36: =+(($D36*CU$3*(1+CU$7)/1000*(1+CU$8))*CU$16)*0 -> 0 | CV36: =+(($D36*CV$3*(1+CV$7)/1000*(1+CV$8))*CV$16)*0 -> 0 | ... CX36: =+(($D36*CX$3*(1+CX$7)/1000*(1+CX$8))*CX$16)*0 -> 0 | CY36: =+(+($D36*CY$3*(1+CY$7)/1000*(1+CY$8))*CY$16) -> 97688.343 | CZ36: =+(+($D36*CZ$3*(1+CZ$7)/1000*(1+CZ$8))*CZ$16) -> 108215.15 | DA36: =+(+($D36*DA$3*(1+DA$7)/1000*(1+DA$8))*DA$16) -> 108499.82 | DB36: =+(+($D36*DB$3*(1+DB$7)/1000*(1+DB$8))*DB$16) -> 117782.63 | DC36: =+(+($D36*DC$3*(1+DC$7)/1000*(1+DC$8))*DC$16) -> 121461.37 | DD36: =+(+($D36*DD$3*(1+DD$7)/1000*(1+DD$8))*DD$16) -> 117770.39 | DE36: =+(+($D36*DE$3*(1+DE$7)/1000*(1+DE$8))*DE$16) -> 115423.57 | DF36: =+(+($D36*DF$3*(1+DF$7)/1000*(1+DF$8))*DF$16) -> 113747.51 | DG36: =+(+($D36*DG$3*(1+DG$7)/1000*(1+DG$8))*DG$16) -> 108585.41
C37: MS 3000 | D37: 62 | BT37: =+($D37*BT$3*(1+BT$7)/1000*(1+BT$8))*BT$16 -> 17693.402 | BU37: =+($D37*BU$3*(1+BU$7)/1000*(1+BU$8))*BU$16 -> 18675.478 | BV37: =+($D37*BV$3*(1+BV$7)/1000*(1+BV$8))*BV$16 -> 19330.011 | BW37: =+($D37*BW$3*(1+BW$7)/1000*(1+BW$8))*BW$16 -> 21097.99 | BX37: =+($D37*BX$3*(1+BX$7)/1000*(1+BX$8))*BX$16 -> 22581.141 | BY37: =+($D37*BY$3*(1+BY$7)/1000*(1+BY$8))*BY$16 -> 24987.388 | BZ37: =+($D37*BZ$3*(1+BZ$7)/1000*(1+BZ$8))*BZ$16 -> 25278.263 | CA37: =+($D37*CA$3*(1+CA$7)/1000*(1+CA$8))*CA$16 -> 25887.821 | ... CL37: =+($D37*CL$3*(1+CL$7)/1000*(1+CL$8))*CL$16 -> 89978.537 | CM37: 91651.284 | CO37: =+($D37*CO$3*(1+CO$7)/1000*(1+CO$8))*CO$16 -> 112641.61 | CP37: =+($D37*CP$3*(1+CP$7)/1000*(1+CP$8))*CP$16 -> 74647.205 | CQ37: =+($D37*CQ$3*(1+CQ$7)/1000*(1+CQ$8))*CQ$16 -> 93240.08 | CR37: =+($D37*CR$3*(1+CR$7)/1000*(1+CR$8))*CR$16 -> 99944.115 | CS37: =+($D37*CS$3*(1+CS$7)/1000*(1+CS$8))*CS$16 -> 103549.62 | CT37: =+($D37*CT$3*(1+CT$7)/1000*(1+CT$8))*CT$16 -> 104712.23 | CU37: =+($D37*CU$3*(1+CU$7)/1000*(1+CU$8))*CU$16 -> 103928.85 | CV37: =+($D37*CV$3*(1+CV$7)/1000*(1+CV$8))*CV$16 -> 103896.99 | ... DG37: =+($D37*DG$3*(1+DG$7)/1000*(1+DG$8))*DG$16 -> 116074.06
C39: MO; Energía; Packaging; Others (ARS)
C40: SS 250 | D40: 12.5 | BT40: =((+(169/$A$16)*0.3*BT$16+((169)*(1+BT$14)*0.7))*0.95)-5.05 -> 1410.8376 | BU40: =((+(169/$A$16)*0.3*BU$16+((169)*(1+BU$14)*0.7))*0.95)-5.05 -> 1442.7262 | BV40: =((+(169/$A$16)*0.3*BV$16+((169)*(1+BV$14)*0.7))*0.95)-5.05 -> 1469.2446 | BW40: =((+(169/$A$16)*0.3*BW$16+((169)*(1+BW$14)*0.7))*0.95)-5.05 -> 1508.1918 | BX40: =((+(169/$A$16)*0.3*BX$16+((169)*(1+BX$14)*0.7))*0.95)-5.05 -> 1546.8899 | BY40: =((+(169/$A$16)*0.3*BY$16+((169)*(1+BY$14)*0.7))*0.95)-5.05 -> 1588.5499 | BZ40: =((+(169/$A$16)*0.3*BZ$16+((169)*(1+BZ$14)*0.7))*0.95)-5.05 -> 2041.153 | CA40: =((+(169/$A$16)*0.3*CA$16+((169)*(1+CA$14)*0.7))*0.95)-5.05 -> 2091.6708 | ... CL40: =((+(169/$A$16)*0.3*CL$16+((169)*(1+CL$14)*0.7))*0.95)-5.05 -> 7186.409 | CM40: 7323.5101 | CO40: =((+(169/$A$16)*0.3*CO$16+((169)*(1+CO$14)*0.7))*0.95)-5.05 -> 2749.8122 | CP40: =((+(169/$A$16)*0.3*CP$16+((169)*(1+CP$14)*0.7))*0.95)-5.05 -> 2809.9238 | CQ40: =((+(169/$A$16)*0.3*CQ$16+((169)*(1+CQ$14)*0.7))*0.95)-5.05 -> 2873.6671 | CR40: =((+(169/$A$16)*0.3*CR$16+((169)*(1+CR$14)*0.7))*0.95)-5.05 -> 2914.3458 | CS40: =((+(169/$A$16)*0.3*CS$16+((169)*(1+CS$14)*0.7))*0.95)-5.05 -> 2976.0662 | CT40: =((+(169/$A$16)*0.3*CT$16+((169)*(1+CT$14)*0.7))*0.95)-5.05 -> 3028.4531 | CU40: =((+(169/$A$16)*0.3*CU$16+((169)*(1+CU$14)*0.7))*0.95)-5.05 -> 3056.1726 | CV40: =((+(169/$A$16)*0.3*CV$16+((169)*(1+CV$14)*0.7))*0.95)-5.05 -> 3087.3877 | ... DG40: =((+(169/$A$16)*0.3*DG$16+((169)*(1+DG$14)*0.7))*0.95)-5.05 -> 4005.8569
C41: SS 500 | D41: 19.5 | BT41: =BT83*0.7 -> 1116.608 | BU41: =BU83*0.7 -> 1141.8358 | BV41: =BV83*0.7 -> 1166.3502 | BW41: =BW83*0.7 -> 1197.1623 | BX41: =BX83*0.7 -> 1227.7773 | BY41: =BY83*0.7 -> 1260.7355 | BZ41: =BZ83*0.7 -> 1618.8008 | CA41: =CA83*0.7 -> 1658.7667 | ... CM41: =CM83*0.7 -> 5797.8017 | CO41: =CO83*0.7 -> 5950.4888 | CP41: =CP83*0.7 -> 6077.0668 | CQ41: =CQ83*0.7 -> 6261.6245 | CR41: =CR83*0.7 -> 6403.8198 | CS41: =CS83*0.7 -> 6540.627 | CT41: =CT83*0.7 -> 6636.6239 | CU41: =CU83*0.7 -> 6745.6183 | CV41: =CV83*0.7 -> 6833.5876 | CW41: 6833.5876 | CX41: 6833.5876 | CY41: =CV41*(1+$CW$14)*(1+$CX$14)*(1+$CY$14) -> 7247.527 | CZ41: =CY41*(1+CZ$14) -> 7367.1112 | DA41: =CZ41*(1+DA$14) -> 7569.7067 | DB41: =DA41*(1+DB$14) -> 7751.3797 | DC41: =DB41*(1+DC$14) -> 7991.6725 | DD41: =DC41*(1+DD$14) -> 8127.5309 | DE41: =DD41*(1+DE$14) -> 8281.954 | DF41: =DE41*(1+DF$14) -> 8435.1701 | DG41: =DF41*(1+DG$14) -> 8616.5263
C42: SS 500 - 19.5G PCR 100% | D42: 19.5 | BT42: =BT84*0.7 -> 0 | BU42: =BU84*0.7 -> 0 | BV42: =BV84*0.7 -> 0 | BW42: =BW84*0.7 -> 0 | BX42: =BX84*0.7 -> 0 | BY42: =BY84*0.7 -> 0 | BZ42: =BZ84*0.7 -> 0 | CA42: =CA84*0.7 -> 0 | ... CM42: =CM84*0.7 -> 5797.8017 | CO42: =CO84*0.7 -> 5950.4888 | CP42: =CP84*0.7 -> 6077.0668 | CQ42: =CQ84*0.7 -> 6261.6245 | CR42: =CR84*0.7 -> 6403.8198 | CS42: =CS84*0.7 -> 6540.627 | CT42: =CT84*0.7 -> 6636.6239 | CU42: =CU84*0.7 -> 6745.6183 | CV42: =CV84*0.7 -> 6833.5876 | CW42: 6833.5876 | CX42: 6833.5876 | CY42: =CV42*(1+$CW$14)*(1+$CX$14)*(1+$CY$14) -> 7247.527 | CZ42: =CY42*(1+CZ$14) -> 7367.1112 | DA42: =CZ42*(1+DA$14) -> 7569.7067 | DB42: =DA42*(1+DB$14) -> 7751.3797 | DC42: =DB42*(1+DC$14) -> 7991.6725 | DD42: =DC42*(1+DD$14) -> 8127.5309 | DE42: =DD42*(1+DE$14) -> 8281.954 | DF42: =DE42*(1+DF$14) -> 8435.1701 | DG42: =DF42*(1+DG$14) -> 8616.5263
C43: SS 500 | D43: 22.1 | BT43: =BT85*0.7 -> 1116.608 | BU43: =BU85*0.7 -> 1141.8358 | BV43: =BV85*0.7 -> 1166.3502 | BW43: =BW85*0.7 -> 1197.1623 | BX43: =BX85*0.7 -> 1227.7773 | BY43: =BY85*0.7 -> 1260.7355 | BZ43: =BZ85*0.7 -> 1618.8008 | CA43: =CA85*0.7 -> 1658.7667 | ... CM43: =CM85*0.7 -> 5797.8017 | CO43: =CO85*0.7 -> 5950.4888 | CP43: =CP85*0.7 -> 6077.0668 | CQ43: =CQ85*0.7 -> 6261.6245 | CR43: =CR85*0.7 -> 6403.8198 | CS43: =CS85*0.7 -> 6540.627 | CT43: =CT85*0.7 -> 6636.6239 | CU43: =CU85*0.7 -> 6745.6183 | CV43: =CV85*0.7 -> 6833.5876 | CW43: 6833.5876 | CX43: 6833.5876 | CY43: =CV43*(1+$CW$14)*(1+$CX$14)*(1+$CY$14) -> 7247.527 | CZ43: =CY43*(1+CZ$14) -> 7367.1112 | DA43: =CZ43*(1+DA$14) -> 7569.7067 | DB43: =DA43*(1+DB$14) -> 7751.3797 | DC43: =DB43*(1+DC$14) -> 7991.6725 | DD43: =DC43*(1+DD$14) -> 8127.5309 | DE43: =DD43*(1+DE$14) -> 8281.954 | DF43: =DE43*(1+DF$14) -> 8435.1701 | DG43: =DF43*(1+DG$14) -> 8616.5263
C44: SS 500 | D44: 22 | BT44: =BT86*0.7 -> 1116.608 | BU44: =BU86*0.7 -> 1141.8358 | BV44: =BV86*0.7 -> 0 | BW44: =BW86*0.7 -> 0 | BX44: =BX86*0.7 -> 0 | BY44: =BY86*0.7 -> 0 | BZ44: =BZ86*0.7 -> 0 | CA44: =CA86*0.7 -> 0 | ... CM44: =CM86*0.7 -> 0 | CO44: =CO86*0.7 -> 0 | CP44: =CP86*0.7 -> 0 | CQ44: =CQ86*0.7 -> 0 | CR44: =CR86*0.7 -> 0 | CS44: =CS86*0.7 -> 0 | CT44: =CT86*0.7 -> 0 | CU44: =CU86*0.7 -> 0 | CV44: =CV86*0.7 -> 0 | CW44: 0 | CX44: 0 | CY44: 0 | CZ44: =CY44*(1+CZ$14) -> 0 | DA44: =CZ44*(1+DA$14) -> 0 | DB44: =DA44*(1+DB$14) -> 0 | DC44: =DB44*(1+DC$14) -> 0 | DD44: =DC44*(1+DD$14) -> 0 | DE44: =DD44*(1+DE$14) -> 0 | DF44: =DE44*(1+DF$14) -> 0 | DG44: =DF44*(1+DG$14) -> 0
C45: SS 500 | D45: 25 | BT45: =BT87*0.7 -> 1116.608 | BU45: =BU87*0.7 -> 1141.8358 | BV45: =BV87*0.7 -> 1166.3502 | BW45: =BW87*0.7 -> 1197.1623 | BX45: =BX87*0.7 -> 1227.7773 | BY45: =BY87*0.7 -> 1260.7355 | BZ45: =BZ87*0.7 -> 1618.8008 | CA45: =CA87*0.7 -> 1658.7667 | ... CM45: =CM87*0.7 -> 5797.8017 | CO45: =CO87*0.7 -> 5950.4888 | CP45: =CP87*0.7 -> 6077.0668 | CQ45: =CQ87*0.7 -> 6261.6245 | CR45: =CR87*0.7 -> 6403.8198 | CS45: =CS87*0.7 -> 6540.627 | CT45: =CT87*0.7 -> 6636.6239 | CU45: =CU87*0.7 -> 6745.6183 | CV45: =CV87*0.7 -> 6833.5876 | CW45: 6833.5876 | CX45: 6833.5876 | CY45: =CV45*(1+$CW$14)*(1+$CX$14)*(1+$CY$14) -> 7247.527 | CZ45: =CY45*(1+CZ$14) -> 7367.1112 | DA45: =CZ45*(1+DA$14) -> 7569.7067 | DB45: =DA45*(1+DB$14) -> 7751.3797 | DC45: =DB45*(1+DC$14) -> 7991.6725 | DD45: =DC45*(1+DD$14) -> 8127.5309 | DE45: =DD45*(1+DE$14) -> 8281.954 | DF45: =DE45*(1+DF$14) -> 8435.1701 | DG45: =DF45*(1+DG$14) -> 8616.5263
C46: SS 500 - 25G PCR 100% | D46: 25 | BT46: =BT88*0.7 -> 0 | BU46: =BU88*0.7 -> 0 | BV46: =BV88*0.7 -> 0 | BW46: =BW88*0.7 -> 0 | BX46: =BX88*0.7 -> 0 | BY46: =BY88*0.7 -> 0 | BZ46: =BZ88*0.7 -> 0 | CA46: =CA88*0.7 -> 0 | ... CM46: =CM88*0.7 -> 5797.8017 | CO46: =CO88*0.7 -> 5950.4888 | CP46: =CP88*0.7 -> 6077.0668 | CQ46: =CQ88*0.7 -> 6261.6245 | CR46: =CR88*0.7 -> 6403.8198 | CS46: =CS88*0.7 -> 6540.627 | CT46: =CT88*0.7 -> 6636.6239 | CU46: =CU88*0.7 -> 6745.6183 | CV46: =CV88*0.7 -> 6833.5876 | CW46: 6833.5876 | CX46: 6833.5876 | CY46: =CV46*(1+$CW$14)*(1+$CX$14)*(1+$CY$14) -> 7247.527 | CZ46: =CY46*(1+CZ$14) -> 7367.1112 | DA46: =CZ46*(1+DA$14) -> 7569.7067 | DB46: =DA46*(1+DB$14) -> 7751.3797 | DC46: =DB46*(1+DC$14) -> 7991.6725 | DD46: =DC46*(1+DD$14) -> 8127.5309 | DE46: =DD46*(1+DE$14) -> 8281.954 | DF46: =DE46*(1+DF$14) -> 8435.1701 | DG46: =DF46*(1+DG$14) -> 8616.5263
C47: MS 1500 | D47: 37.2 | BT47: =BT89*0.7 -> 1568.184 | BU47: =BU89*0.7 -> 1603.5822 | BV47: =BV89*0.7 -> 1636.5542 | BW47: =BW89*0.7 -> 1679.788 | BX47: =BX89*0.7 -> 1722.7451 | BY47: =BY89*0.7 -> 1768.9901 | BZ47: =BZ89*0.7 -> 2271.4064 | CA47: =CA89*0.7 -> 2327.4842 | ... CM47: =CM89*0.7 -> 8135.1354 | CO47: =CO89*0.7 -> 8349.377 | CP47: =CP89*0.7 -> 8526.9838 | CQ47: =CQ89*0.7 -> 8785.9443 | CR47: =CR89*0.7 -> 8985.4645 | CS47: =CS89*0.7 -> 9177.4243 | CT47: =CT89*0.7 -> 9312.1215 | CU47: =CU89*0.7 -> 9465.0561 | CV47: =CV89*0.7 -> 9588.4895 | CW47: 9588.4895 | CX47: 9588.4895 | CY47: =CV47*(1+$CW$14)*(1+$CX$14)*(1+$CY$14) -> 10169.305 | CZ47: =CY47*(1+CZ$14) -> 10337.098 | DA47: =CZ47*(1+DA$14) -> 10621.369 | DB47: =DA47*(1+DB$14) -> 10876.281 | DC47: =DB47*(1+DC$14) -> 11213.446 | DD47: =DC47*(1+DD$14) -> 11404.075 | DE47: =DD47*(1+DE$14) -> 11620.752 | DF47: =DE47*(1+DF$14) -> 11835.736 | DG47: =DF47*(1+DG$14) -> 12090.204
C48: MS 1500 | D48: 40 | BT48: =BT90*0.7 -> 1568.184 | BU48: =BU90*0.7 -> 1603.5822 | BV48: =BV90*0.7 -> 0 | BW48: =BW90*0.7 -> 0 | BX48: =BX90*0.7 -> 0 | BY48: =BY90*0.7 -> 0 | BZ48: =BZ90*0.7 -> 0 | CA48: =CA90*0.7 -> 0 | ... CM48: =CM90*0.7 -> 0 | CO48: =CO90*0.7 -> 0 | CP48: =CP90*0.7 -> 0 | CQ48: =CQ90*0.7 -> 0 | CR48: =CR90*0.7 -> 0 | CS48: =CS90*0.7 -> 0 | CT48: =CT90*0.7 -> 0 | CU48: =CU90*0.7 -> 0 | CV48: =CV90*0.7 -> 0 | CW48: 0 | CX48: 0 | CY48: =CY90*0.7 -> 0 | CZ48: =CY48*(1+CZ$14) -> 0 | DA48: =CZ48*(1+DA$14) -> 0 | DB48: =DA48*(1+DB$14) -> 0 | DC48: =DB48*(1+DC$14) -> 0 | DD48: =DC48*(1+DD$14) -> 0 | DE48: =DD48*(1+DE$14) -> 0 | DF48: =DE48*(1+DF$14) -> 0 | DG48: =DF48*(1+DG$14) -> 0
C49: MS 1500 | D49: 44 | BT49: =BT91*0.7 -> 1568.184 | BU49: =BU91*0.7 -> 1603.5822 | BV49: =BV91*0.7 -> 1636.5542 | BW49: =BW91*0.7 -> 1679.788 | BX49: =BX91*0.7 -> 1722.7451 | BY49: =BY91*0.7 -> 1768.9901 | BZ49: =BZ91*0.7 -> 2271.4064 | CA49: =CA91*0.7 -> 2327.4842 | ... CM49: =CM91*0.7 -> 8135.1354 | CO49: =CO91*0.7 -> 8349.377 | CP49: =CP91*0.7 -> 8526.9838 | CQ49: =CQ91*0.7 -> 8785.9443 | CR49: =CR91*0.7 -> 8985.4645 | CS49: =CS91*0.7 -> 9177.4243 | CT49: =CT91*0.7 -> 9312.1215 | CU49: =CU91*0.7 -> 9465.0561 | CV49: =CV91*0.7 -> 9588.4895 | CW49: 9588.4895 | CX49: 9588.4895 | CY49: =CV49*(1+$CW$14)*(1+$CX$14)*(1+$CY$14) -> 10169.305 | CZ49: =CY49*(1+CZ$14) -> 10337.098 | DA49: =CZ49*(1+DA$14) -> 10621.369 | DB49: =DA49*(1+DB$14) -> 10876.281 | DC49: =DB49*(1+DC$14) -> 11213.446 | DD49: =DC49*(1+DD$14) -> 11404.075 | DE49: =DD49*(1+DE$14) -> 11620.752 | DF49: =DE49*(1+DF$14) -> 11835.736 | DG49: =DF49*(1+DG$14) -> 12090.204
C50: MS 2000/2250 | D50: 42.6 | BT50: =BT92*0.7 -> 1744.1227 | BU50: =BU92*0.7 -> 1783.4834 | BV50: =BV92*0.7 -> 0 | BW50: =BW92*0.7 -> 0 | BX50: =BX92*0.7 -> 0 | BY50: =BY92*0.7 -> 0 | BZ50: =BZ92*0.7 -> 0 | CA50: =CA92*0.7 -> 0 | ... CM50: =CM92*0.7 -> 0 | CO50: =CO92*0.7 -> 0 | CP50: =CP92*0.7 -> 0 | CQ50: =CQ92*0.7 -> 0 | CR50: =CR92*0.7 -> 0 | CS50: =CS92*0.7 -> 0 | CT50: =CT92*0.7 -> 0 | CU50: =CU92*0.7 -> 0 | CV50: =CV92*0.7 -> 0 | CW50: 0 | CX50: 0 | CY50: 0 | CZ50: =CY50*(1+CZ$14) -> 0 | DA50: =CZ50*(1+DA$14) -> 0 | DB50: =DA50*(1+DB$14) -> 0 | DC50: =DB50*(1+DC$14) -> 0 | DD50: =DC50*(1+DD$14) -> 0 | DE50: =DD50*(1+DE$14) -> 0 | DF50: =DE50*(1+DF$14) -> 0 | DG50: =DF50*(1+DG$14) -> 0
C51: MS 2000/2250 | D51: 46.6 | BT51: =BT93*0.7 -> 1744.1227 | BU51: =BU93*0.7 -> 1783.4834 | BV51: =BV93*0.7 -> 1819.7506 | BW51: =BW93*0.7 -> 1867.8239 | BX51: =BX93*0.7 -> 1915.5897 | BY51: =BY93*0.7 -> 1967.0114 | BZ51: =BZ93*0.7 -> 2525.6683 | CA51: =CA93*0.7 -> 2588.0235 | ... CM51: =CM93*0.7 -> 9045.7849 | CO51: =CO93*0.7 -> 9284.0087 | CP51: =CP93*0.7 -> 9481.4969 | CQ51: =CQ93*0.7 -> 9769.4455 | CR51: =CR93*0.7 -> 9991.3 | CS51: =CS93*0.7 -> 10204.748 | CT51: =CT93*0.7 -> 10354.523 | CU51: =CU93*0.7 -> 10524.577 | CV51: =CV93*0.7 -> 10661.828 | CW51: 10661.828 | CX51: 10661.828 | CY51: =CV51*(1+$CW$14)*(1+$CX$14)*(1+$CY$14) -> 11307.66 | CZ51: =CY51*(1+CZ$14) -> 11494.236 | DA51: =CZ51*(1+DA$14) -> 11810.328 | DB51: =DA51*(1+DB$14) -> 12093.776 | DC51: =DB51*(1+DC$14) -> 12468.683 | DD51: =DC51*(1+DD$14) -> 12680.65 | DE51: =DD51*(1+DE$14) -> 12921.583 | DF51: =DE51*(1+DF$14) -> 13160.632 | DG51: =DF51*(1+DG$14) -> 13443.586
C52: MS 2000/2250 20% PCR | D52: 46.6 | BT52: =BT94*0.7 -> 0 | BU52: =BU94*0.7 -> 0 | BV52: =BV94*0.7 -> 0 | BW52: =BW94*0.7 -> 0 | BX52: =BX94*0.7 -> 0 | BY52: =BY94*0.7 -> 0 | BZ52: =BZ94*0.7 -> 0 | CA52: =CA94*0.7 -> 0 | ... CM52: =CM94*0.7 -> 9045.7849 | CO52: =CO94*0.7 -> 9284.0087 | CP52: =CP94*0.7 -> 9481.4969 | CQ52: =CQ94*0.7 -> 9769.4455 | CR52: =CR94*0.7 -> 9991.3 | CS52: =CS94*0.7 -> 10204.748 | CT52: =CT94*0.7 -> 10354.523 | CU52: =CU94*0.7 -> 10524.577 | CV52: =CV94*0.7 -> 10661.828 | CW52: 10661.828 | CX52: 10661.828 | CY52: =CV52*(1+$CW$14)*(1+$CX$14)*(1+$CY$14) -> 11307.66 | CZ52: =CY52*(1+CZ$14) -> 11494.236 | DA52: =CZ52*(1+DA$14) -> 11810.328 | DB52: =DA52*(1+DB$14) -> 12093.776 | DC52: =DB52*(1+DC$14) -> 12468.683 | DD52: =DC52*(1+DD$14) -> 12680.65 | DE52: =DD52*(1+DE$14) -> 12921.583 | DF52: =DE52*(1+DF$14) -> 13160.632 | DG52: =DF52*(1+DG$14) -> 13443.586
C53: MS 2000/2250 | D53: 48 | BT53: =BT95*0.7 -> 1744.1227 | BU53: =BU95*0.7 -> 1783.4834 | BV53: =BV95*0.7 -> 1819.7506 | BW53: =BW95*0.7 -> 1867.8239 | BX53: =BX95*0.7 -> 1915.5897 | BY53: =BY95*0.7 -> 1967.0114 | BZ53: =BZ95*0.7 -> 2525.6683 | CA53: =CA95*0.7 -> 2588.0235 | ... CM53: =CM95*0.7 -> 9045.7849 | CO53: =CO95*0.7 -> 9284.0087 | CP53: =CP95*0.7 -> 9481.4969 | CQ53: =CQ95*0.7 -> 9769.4455 | CR53: =CR95*0.7 -> 9991.3 | CS53: =CS95*0.7 -> 10204.748 | CT53: =CT95*0.7 -> 10354.523 | CU53: =CU95*0.7 -> 10524.577 | CV53: =CV95*0.7 -> 10661.828 | CW53: 10661.828 | CX53: 10661.828 | CY53: =CV53*(1+$CW$14)*(1+$CX$14)*(1+$CY$14) -> 11307.66 | CZ53: =CY53*(1+CZ$14) -> 11494.236 | DA53: =CZ53*(1+DA$14) -> 11810.328 | DB53: =DA53*(1+DB$14) -> 12093.776 | DC53: =DB53*(1+DC$14) -> 12468.683 | DD53: =DC53*(1+DD$14) -> 12680.65 | DE53: =DD53*(1+DE$14) -> 12921.583 | DF53: =DE53*(1+DF$14) -> 13160.632 | DG53: =DF53*(1+DG$14) -> 13443.586
C54: MS 2000/2250 | D54: 49.6 | BT54: =BT96*0.7 -> 1744.1227 | BU54: =BU96*0.7 -> 1783.4834 | BV54: =BV96*0.7 -> 0 | BW54: =BW96*0.7 -> 0 | BX54: =BX96*0.7 -> 0 | BY54: =BY96*0.7 -> 0 | BZ54: =BZ96*0.7 -> 0 | CA54: =CA96*0.7 -> 0 | ... CM54: =CM96*0.7 -> 0 | CO54: =CO96*0.7 -> 0 | CP54: =CP96*0.7 -> 0 | CQ54: =CQ96*0.7 -> 0 | CR54: =CR96*0.7 -> 0 | CS54: =CS96*0.7 -> 0 | CT54: =CT96*0.7 -> 0 | CU54: =CU96*0.7 -> 0 | CV54: =CV96*0.7 -> 0 | CW54: 0 | CX54: 0 | CY54: =CY96*0.7 -> 0 | CZ54: =CY54*(1+CZ$14) -> 0 | DA54: =CZ54*(1+DA$14) -> 0 | DB54: =DA54*(1+DB$14) -> 0 | DC54: =DB54*(1+DC$14) -> 0 | DD54: =DC54*(1+DD$14) -> 0 | DE54: =DD54*(1+DE$14) -> 0 | DF54: =DE54*(1+DF$14) -> 0 | DG54: =DF54*(1+DG$14) -> 0
C55: MS 2000/2250 | D55: 52 | BT55: =BT97*0.7 -> 1744.1227 | BU55: =BU97*0.7 -> 1783.4834 | BV55: =BV97*0.7 -> 1819.7506 | BW55: =BW97*0.7 -> 1867.8239 | BX55: =BX97*0.7 -> 1915.5897 | BY55: =BY97*0.7 -> 1967.0114 | BZ55: =BZ97*0.7 -> 2525.6683 | CA55: =CA97*0.7 -> 2588.0235 | ... CM55: =CM97*0.7 -> 9045.7849 | CO55: =CO97*0.7 -> 9284.0087 | CP55: =CP97*0.7 -> 9481.4969 | CQ55: =CQ97*0.7 -> 9769.4455 | CR55: =CR97*0.7 -> 9991.3 | CS55: =CS97*0.7 -> 10204.748 | CT55: =CT97*0.7 -> 10354.523 | CU55: =CU97*0.7 -> 10524.577 | CV55: =CV97*0.7 -> 10661.828 | CW55: 10661.828 | CX55: 10661.828 | CY55: =CV55*(1+$CW$14)*(1+$CX$14)*(1+$CY$14) -> 11307.66 | CZ55: =CY55*(1+CZ$14) -> 11494.236 | DA55: =CZ55*(1+DA$14) -> 11810.328 | DB55: =DA55*(1+DB$14) -> 12093.776 | DC55: =DB55*(1+DC$14) -> 12468.683 | DD55: =DC55*(1+DD$14) -> 12680.65 | DE55: =DD55*(1+DE$14) -> 12921.583 | DF55: =DE55*(1+DF$14) -> 13160.632 | DG55: =DF55*(1+DG$14) -> 13443.586
C56: MS 3000 | D56: 54.7 | BT56: =BT98*0.7 -> 1791.0397 | BU56: =BU98*0.7 -> 1831.457 | BV56: =BV98*0.7 -> 1868.603 | BW56: =BW98*0.7 -> 1917.9668 | BX56: =BX98*0.7 -> 1967.0149 | BY56: =BY98*0.7 -> 2019.8171 | BZ56: =BZ98*0.7 -> 2593.4714 | CA56: =CA98*0.7 -> 2657.5006 | ... CM56: =CM98*0.7 -> 9288.6247 | CO56: =CO98*0.7 -> 9533.2439 | CP56: =CP98*0.7 -> 9736.0338 | CQ56: =CQ98*0.7 -> 10031.713 | CR56: =CR98*0.7 -> 10259.523 | CS56: =CS98*0.7 -> 10478.701 | CT56: =CT98*0.7 -> 10632.497 | CU56: =CU98*0.7 -> 10807.116 | CV56: =CV98*0.7 -> 10948.051 | CW56: 10948.051 | CX56: 10948.051 | CY56: =CV56*(1+$CW$14)*(1+$CX$14)*(1+$CY$14) -> 11611.221 | CZ56: =CY56*(1+CZ$14) -> 11802.806 | DA56: =CZ56*(1+DA$14) -> 12127.384 | DB56: =DA56*(1+DB$14) -> 12418.441 | DC56: =DB56*(1+DC$14) -> 12803.412 | DD56: =DC56*(1+DD$14) -> 13021.07 | DE56: =DD56*(1+DE$14) -> 13268.471 | DF56: =DE56*(1+DF$14) -> 13513.938 | DG56: =DF56*(1+DG$14) -> 13804.487
C57: MS 3000 | D57: 58 | BT57: =BT99*0.7 -> 1791.0397 | BU57: =BU99*0.7 -> 1831.457 | BV57: =BV99*0.7 -> 0 | BW57: =BW99*0.7 -> 0 | BX57: =BX99*0.7 -> 0 | BY57: =BY99*0.7 -> 0 | BZ57: =BZ99*0.7 -> 0 | CA57: =CA99*0.7 -> 0 | ... CM57: =CM99*0.7 -> 0 | CO57: =CO99*0.7 -> 0 | CP57: =CP99*0.7 -> 0 | CQ57: =CQ99*0.7 -> 0 | CR57: =CR99*0.7 -> 0 | CS57: =CS99*0.7 -> 0 | CT57: =CT99*0.7 -> 0 | CU57: =CU99*0.7 -> 0 | CV57: =CV99*0.7 -> 0 | CW57: 0 | CX57: 0 | CY57: 0 | CZ57: =CY57*(1+CZ$14) -> 0 | DA57: =CZ57*(1+DA$14) -> 0 | DB57: =DA57*(1+DB$14) -> 0 | DC57: =DB57*(1+DC$14) -> 0 | DD57: =DC57*(1+DD$14) -> 0 | DE57: =DD57*(1+DE$14) -> 0 | DF57: =DE57*(1+DF$14) -> 0 | DG57: =DF57*(1+DG$14) -> 0
C58: MS 3000 | D58: 62 | BT58: =BT100*0.7 -> 1791.0397 | BU58: =BU100*0.7 -> 1831.457 | BV58: =BV100*0.7 -> 1868.603 | BW58: =BW100*0.7 -> 1917.9668 | BX58: =BX100*0.7 -> 1967.0149 | BY58: =BY100*0.7 -> 2019.8171 | BZ58: =BZ100*0.7 -> 2593.4714 | CA58: =CA100*0.7 -> 2657.5006 | ... CM58: =CM100*0.7 -> 9288.6247 | CO58: =CO100*0.7 -> 9533.2439 | CP58: =CP100*0.7 -> 9736.0338 | CQ58: =CQ100*0.7 -> 10031.713 | CR58: =CR100*0.7 -> 10259.523 | CS58: =CS100*0.7 -> 10478.701 | CT58: =CT100*0.7 -> 10632.497 | CU58: =CU100*0.7 -> 10807.116 | CV58: =CV100*0.7 -> 10948.051 | CW58: 10948.051 | CX58: 10948.051 | CY58: =CV58*(1+$CW$14)*(1+$CX$14)*(1+$CY$14) -> 11611.221 | CZ58: =CY58*(1+CZ$14) -> 11802.806 | DA58: =CZ58*(1+DA$14) -> 12127.384 | DB58: =DA58*(1+DB$14) -> 12418.441 | DC58: =DB58*(1+DC$14) -> 12803.412 | DD58: =DC58*(1+DD$14) -> 13021.07 | DE58: =DD58*(1+DE$14) -> 13268.471 | DF58: =DE58*(1+DF$14) -> 13513.938 | DG58: =DF58*(1+DG$14) -> 13804.487
C60: Conversión (USD)
C61: SS 250 | D61: 12.5 | BT61: =((+(169/$A$16)*0.3*BT$16+((169)*(1+BT$14)*0.7))*0.95)-5.05 -> 1410.8376 | BU61: =((+(169/$A$16)*0.3*BU$16+((169)*(1+BU$14)*0.7))*0.95)-5.05 -> 1442.7262 | BV61: =((+(169/$A$16)*0.3*BV$16+((169)*(1+BV$14)*0.7))*0.95)-5.05 -> 1469.2446 | BW61: =((+(169/$A$16)*0.3*BW$16+((169)*(1+BW$14)*0.7))*0.95)-5.05 -> 1508.1918 | BX61: =((+(169/$A$16)*0.3*BX$16+((169)*(1+BX$14)*0.7))*0.95)-5.05 -> 1546.8899 | BY61: =((+(169/$A$16)*0.3*BY$16+((169)*(1+BY$14)*0.7))*0.95)-5.05 -> 1588.5499 | BZ61: =((+(169/$A$16)*0.3*BZ$16+((169)*(1+BZ$14)*0.7))*0.95)-5.05 -> 2041.153 | CA61: =((+(169/$A$16)*0.3*CA$16+((169)*(1+CA$14)*0.7))*0.95)-5.05 -> 2091.6708 | ... CL61: =((+(169/$A$16)*0.3*CL$16+((169)*(1+CL$14)*0.7))*0.95)-5.05 -> 7186.409 | CM61: 7323.5101 | CO61: =((+(169/$A$16)*0.3*CO$16+((169)*(1+CO$14)*0.7))*0.95)-5.05 -> 2749.8122 | CP61: =((+(169/$A$16)*0.3*CP$16+((169)*(1+CP$14)*0.7))*0.95)-5.05 -> 2809.9238 | CQ61: =((+(169/$A$16)*0.3*CQ$16+((169)*(1+CQ$14)*0.7))*0.95)-5.05 -> 2873.6671 | CR61: =((+(169/$A$16)*0.3*CR$16+((169)*(1+CR$14)*0.7))*0.95)-5.05 -> 2914.3458 | CS61: =((+(169/$A$16)*0.3*CS$16+((169)*(1+CS$14)*0.7))*0.95)-5.05 -> 2976.0662 | CT61: =((+(169/$A$16)*0.3*CT$16+((169)*(1+CT$14)*0.7))*0.95)-5.05 -> 3028.4531 | CU61: =((+(169/$A$16)*0.3*CU$16+((169)*(1+CU$14)*0.7))*0.95)-5.05 -> 3056.1726 | CV61: =((+(169/$A$16)*0.3*CV$16+((169)*(1+CV$14)*0.7))*0.95)-5.05 -> 3087.3877 | ... DG61: =((+(169/$A$16)*0.3*DG$16+((169)*(1+DG$14)*0.7))*0.95)-5.05 -> 4005.8569
C62: SS 500 | D62: 19.5 | BT62: =BT83*0.3 -> 478.5463 | BU62: =BU83*0.3 -> 489.35822 | BV62: =BV83*0.3 -> 499.86438 | BW62: =BW83*0.3 -> 513.06956 | BX62: =BX83*0.3 -> 526.19027 | BY62: =BY83*0.3 -> 540.31522 | BZ62: =BZ83*0.3 -> 693.77177 | CA62: =CA83*0.3 -> 710.90003 | ... CM62: =CM83*0.3 -> 2484.7722 | CO62: =CO83*0.3 -> 2550.2095 | CP62: =CP83*0.3 -> 2604.4572 | CQ62: =CQ83*0.3 -> 2683.5533 | CR62: =CR83*0.3 -> 2744.4942 | CS62: =CS83*0.3 -> 2803.1259 | CT62: =CT83*0.3 -> 2844.2674 | CU62: =CU83*0.3 -> 2890.9793 | CV62: =CV83*0.3 -> 2928.6804 | CW62: 2928.6804 | CX62: 2928.6804 | CY62: =((CV62/CV16*CW$16)/CW$16*CX$16)/CX$16*CY$16 -> 3279.7955 | CZ62: =(($CO62/$CO$16*CZ$16)) -> 3674.8693 | DA62: =(($CO62/$CO$16*DA$16)) -> 3589.2828 | DB62: =(($CO62/$CO$16*DB$16)) -> 3748.9551 | DC62: =(($CO62/$CO$16*DC$16)) -> 3836.494 | DD62: =(($CO62/$CO$16*DD$16)) -> 3819.6976 | DE62: =(($CO62/$CO$16*DE$16)) -> 3871.6619 | DF62: =(($CO62/$CO$16*DF$16)) -> 3875.3352 | DG62: =(($CO62/$CO$16*DG$16)) -> 3764.4676
C63: SS 500 - 19.5G PCR 100% | D63: 19.5 | BT63: =BT84*0.3 -> 0 | BU63: =BU84*0.3 -> 0 | BV63: =BV84*0.3 -> 0 | BW63: =BW84*0.3 -> 0 | BX63: =BX84*0.3 -> 0 | BY63: =BY84*0.3 -> 0 | BZ63: =BZ84*0.3 -> 0 | CA63: =CA84*0.3 -> 0 | ... CM63: =CM84*0.3 -> 2484.7722 | CO63: =CO84*0.3 -> 2550.2095 | CP63: =CP84*0.3 -> 2604.4572 | CQ63: =CQ84*0.3 -> 2683.5533 | CR63: =CR84*0.3 -> 2744.4942 | CS63: =CS84*0.3 -> 2803.1259 | CT63: =CT84*0.3 -> 2844.2674 | CU63: =CU84*0.3 -> 2890.9793 | CV63: =CV84*0.3 -> 2928.6804 | CW63: 2928.6804 | CX63: 2928.6804 | CY63: =((CV63/CV$16*CW$16)/CW$16*CX$16)/CX$16*CY$16 -> 3279.7955 | CZ63: =(($CO63/$CO$16*CZ$16)) -> 3674.8693 | DA63: =(($CO63/$CO$16*DA$16)) -> 3589.2828 | DB63: =(($CO63/$CO$16*DB$16)) -> 3748.9551 | DC63: =(($CO63/$CO$16*DC$16)) -> 3836.494 | DD63: =(($CO63/$CO$16*DD$16)) -> 3819.6976 | DE63: =(($CO63/$CO$16*DE$16)) -> 3871.6619 | DF63: =(($CO63/$CO$16*DF$16)) -> 3875.3352 | DG63: =(($CO63/$CO$16*DG$16)) -> 3764.4676
C64: SS 500 | D64: 22.1 | BT64: =BT85*0.3 -> 478.5463 | BU64: =BU85*0.3 -> 489.35822 | BV64: =BV85*0.3 -> 499.86438 | BW64: =BW85*0.3 -> 513.06956 | BX64: =BX85*0.3 -> 526.19027 | BY64: =BY85*0.3 -> 540.31522 | BZ64: =BZ85*0.3 -> 693.77177 | CA64: =CA85*0.3 -> 710.90003 | ... CM64: =CM85*0.3 -> 2484.7722 | CO64: =CO85*0.3 -> 2550.2095 | CP64: =CP85*0.3 -> 2604.4572 | CQ64: =CQ85*0.3 -> 2683.5533 | CR64: =CR85*0.3 -> 2744.4942 | CS64: =CS85*0.3 -> 2803.1259 | CT64: =CT85*0.3 -> 2844.2674 | CU64: =CU85*0.3 -> 2890.9793 | CV64: =CV85*0.3 -> 2928.6804 | CW64: 2928.6804 | CX64: 2928.6804 | CY64: =((CV64/CV$16*CW$16)/CW$16*CX$16)/CX$16*CY$16 -> 3279.7955 | CZ64: =(($CO64/$CO$16*CZ$16)) -> 3674.8693 | DA64: =(($CO64/$CO$16*DA$16)) -> 3589.2828 | DB64: =(($CO64/$CO$16*DB$16)) -> 3748.9551 | DC64: =(($CO64/$CO$16*DC$16)) -> 3836.494 | DD64: =(($CO64/$CO$16*DD$16)) -> 3819.6976 | DE64: =(($CO64/$CO$16*DE$16)) -> 3871.6619 | DF64: =(($CO64/$CO$16*DF$16)) -> 3875.3352 | DG64: =(($CO64/$CO$16*DG$16)) -> 3764.4676
C65: SS 500 | D65: 22 | BT65: =BT86*0.3 -> 478.5463 | BU65: =BU86*0.3 -> 489.35822 | BV65: =BV86*0.3 -> 0 | BW65: =BW86*0.3 -> 0 | BX65: =BX86*0.3 -> 0 | BY65: =BY86*0.3 -> 0 | BZ65: =BZ86*0.3 -> 0 | CA65: =CA86*0.3 -> 0 | ... CM65: =CM86*0.3 -> 0 | CO65: =CO86*0.3 -> 0 | CP65: =CP86*0.3 -> 0 | CQ65: =CQ86*0.3 -> 0 | CR65: =CR86*0.3 -> 0 | CS65: =CS86*0.3 -> 0 | CT65: =CT86*0.3 -> 0 | CU65: =CU86*0.3 -> 0 | CV65: =CV86*0.3 -> 0 | CW65: 0 | CX65: 0 | CY65: =CY86*0.3 -> 0 | CZ65: =(($CO65/$CO$16*CZ$16)) -> 0 | DA65: =(($CO65/$CO$16*DA$16)) -> 0 | DB65: =(($CO65/$CO$16*DB$16)) -> 0 | DC65: =(($CO65/$CO$16*DC$16)) -> 0 | DD65: =(($CO65/$CO$16*DD$16)) -> 0 | DE65: =(($CO65/$CO$16*DE$16)) -> 0 | DF65: =(($CO65/$CO$16*DF$16)) -> 0 | DG65: =(($CO65/$CO$16*DG$16)) -> 0
C66: SS 500 | D66: 25 | BT66: =BT87*0.3 -> 478.5463 | BU66: =BU87*0.3 -> 489.35822 | BV66: =BV87*0.3 -> 499.86438 | BW66: =BW87*0.3 -> 513.06956 | BX66: =BX87*0.3 -> 526.19027 | BY66: =BY87*0.3 -> 540.31522 | BZ66: =BZ87*0.3 -> 693.77177 | CA66: =CA87*0.3 -> 710.90003 | ... CM66: =CM87*0.3 -> 2484.7722 | CO66: =CO87*0.3 -> 2550.2095 | CP66: =CP87*0.3 -> 2604.4572 | CQ66: =CQ87*0.3 -> 2683.5533 | CR66: =CR87*0.3 -> 2744.4942 | CS66: =CS87*0.3 -> 2803.1259 | CT66: =CT87*0.3 -> 2844.2674 | CU66: =CU87*0.3 -> 2890.9793 | CV66: =CV87*0.3 -> 2928.6804 | CW66: 2928.6804 | CX66: 2928.6804 | CY66: =((CV66/CV$16*CW$16)/CW$16*CX$16)/CX$16*CY$16 -> 3279.7955 | CZ66: =(($CO66/$CO$16*CZ$16)) -> 3674.8693 | DA66: =(($CO66/$CO$16*DA$16)) -> 3589.2828 | DB66: =(($CO66/$CO$16*DB$16)) -> 3748.9551 | DC66: =(($CO66/$CO$16*DC$16)) -> 3836.494 | DD66: =(($CO66/$CO$16*DD$16)) -> 3819.6976 | DE66: =(($CO66/$CO$16*DE$16)) -> 3871.6619 | DF66: =(($CO66/$CO$16*DF$16)) -> 3875.3352 | DG66: =(($CO66/$CO$16*DG$16)) -> 3764.4676
C67: SS 500 - 25G PCR 100% | D67: 25 | BT67: =BT88*0.3 -> 0 | BU67: =BU88*0.3 -> 0 | BV67: =BV88*0.3 -> 0 | BW67: =BW88*0.3 -> 0 | BX67: =BX88*0.3 -> 0 | BY67: =BY88*0.3 -> 0 | BZ67: =BZ88*0.3 -> 0 | CA67: =CA88*0.3 -> 0 | ... CM67: =CM88*0.3 -> 2484.7722 | CO67: =CO88*0.3 -> 2550.2095 | CP67: =CP88*0.3 -> 2604.4572 | CQ67: =CQ88*0.3 -> 2683.5533 | CR67: =CR88*0.3 -> 2744.4942 | CS67: =CS88*0.3 -> 2803.1259 | CT67: =CT88*0.3 -> 2844.2674 | CU67: =CU88*0.3 -> 2890.9793 | CV67: =CV88*0.3 -> 2928.6804 | CW67: 2928.6804 | CX67: 2928.6804 | CY67: =((CV67/CV$16*CW$16)/CW$16*CX$16)/CX$16*CY$16 -> 3279.7955 | CZ67: =(($CO67/$CO$16*CZ$16)) -> 3674.8693 | DA67: =(($CO67/$CO$16*DA$16)) -> 3589.2828 | DB67: =(($CO67/$CO$16*DB$16)) -> 3748.9551 | DC67: =(($CO67/$CO$16*DC$16)) -> 3836.494 | DD67: =(($CO67/$CO$16*DD$16)) -> 3819.6976 | DE67: =(($CO67/$CO$16*DE$16)) -> 3871.6619 | DF67: =(($CO67/$CO$16*DF$16)) -> 3875.3352 | DG67: =(($CO67/$CO$16*DG$16)) -> 3764.4676
C68: MS 1500 | D68: 37.2 | BT68: =BT89*0.3 -> 672.07887 | BU68: =BU89*0.3 -> 687.24952 | BV68: =BV89*0.3 -> 701.38039 | BW68: =BW89*0.3 -> 719.90912 | BX68: =BX89*0.3 -> 738.31934 | BY68: =BY89*0.3 -> 758.13863 | BZ68: =BZ89*0.3 -> 973.45987 | CA68: =CA89*0.3 -> 997.49323 | ... CM68: =CM89*0.3 -> 3486.4866 | CO68: =CO89*0.3 -> 3578.3044 | CP68: =CP89*0.3 -> 3654.4216 | CQ68: =CQ89*0.3 -> 3765.4047 | CR68: =CR89*0.3 -> 3850.9133 | CS68: =CS89*0.3 -> 3933.1819 | CT68: =CT89*0.3 -> 3990.9092 | CU68: =CU89*0.3 -> 4056.4526 | CV68: =CV89*0.3 -> 4109.3526 | CW68: 4109.3526 | CX68: 4109.3526 | CY68: =((CV68/CV$16*CW$16)/CW$16*CX$16)/CX$16*CY$16 -> 4602.0167 | CZ68: =(($CO68/$CO$16*CZ$16)) -> 5156.3611 | DA68: =(($CO68/$CO$16*DA$16)) -> 5036.2711 | DB68: =(($CO68/$CO$16*DB$16)) -> 5260.3139 | DC68: =(($CO68/$CO$16*DC$16)) -> 5383.1434 | DD68: =(($CO68/$CO$16*DD$16)) -> 5359.5757 | DE68: =(($CO68/$CO$16*DE$16)) -> 5432.4889 | DF68: =(($CO68/$CO$16*DF$16)) -> 5437.6431 | DG68: =(($CO68/$CO$16*DG$16)) -> 5282.0802
C69: MS 1500 | D69: 40 | BT69: =BT90*0.3 -> 672.07887 | BU69: =BU90*0.3 -> 687.24952 | BV69: =BV90*0.3 -> 0 | BW69: =BW90*0.3 -> 0 | BX69: =BX90*0.3 -> 0 | BY69: =BY90*0.3 -> 0 | BZ69: =BZ90*0.3 -> 0 | CA69: =CA90*0.3 -> 0 | ... CM69: =CM90*0.3 -> 0 | CO69: =CO90*0.3 -> 0 | CP69: =CP90*0.3 -> 0 | CQ69: =CQ90*0.3 -> 0 | CR69: =CR90*0.3 -> 0 | CS69: =CS90*0.3 -> 0 | CT69: =CT90*0.3 -> 0 | CU69: =CU90*0.3 -> 0 | CV69: =CV90*0.3 -> 0 | CW69: 0 | CX69: 0 | CY69: =CY90*0.3 -> 0 | CZ69: =(($CO69/$CO$16*CZ$16)) -> 0 | DA69: =(($CO69/$CO$16*DA$16)) -> 0 | DB69: =(($CO69/$CO$16*DB$16)) -> 0 | DC69: =(($CO69/$CO$16*DC$16)) -> 0 | DD69: =(($CO69/$CO$16*DD$16)) -> 0 | DE69: =(($CO69/$CO$16*DE$16)) -> 0 | DF69: =(($CO69/$CO$16*DF$16)) -> 0 | DG69: =(($CO69/$CO$16*DG$16)) -> 0
C70: MS 1500 | D70: 44 | BT70: =BT91*0.3 -> 672.07887 | BU70: =BU91*0.3 -> 687.24952 | BV70: =BV91*0.3 -> 701.38039 | BW70: =BW91*0.3 -> 719.90912 | BX70: =BX91*0.3 -> 738.31934 | BY70: =BY91*0.3 -> 758.13863 | BZ70: =BZ91*0.3 -> 973.45987 | CA70: =CA91*0.3 -> 997.49323 | ... CM70: =CM91*0.3 -> 3486.4866 | CO70: =CO91*0.3 -> 3578.3044 | CP70: =CP91*0.3 -> 3654.4216 | CQ70: =CQ91*0.3 -> 3765.4047 | CR70: =CR91*0.3 -> 3850.9133 | CS70: =CS91*0.3 -> 3933.1819 | CT70: =CT91*0.3 -> 3990.9092 | CU70: =CU91*0.3 -> 4056.4526 | CV70: =CV91*0.3 -> 4109.3526 | CW70: 4109.3526 | CX70: 4109.3526 | CY70: =((CV70/CV$16*CW$16)/CW$16*CX$16)/CX$16*CY$16 -> 4602.0167 | CZ70: =(($CO70/$CO$16*CZ$16)) -> 5156.3611 | DA70: =(($CO70/$CO$16*DA$16)) -> 5036.2711 | DB70: =(($CO70/$CO$16*DB$16)) -> 5260.3139 | DC70: =(($CO70/$CO$16*DC$16)) -> 5383.1434 | DD70: =(($CO70/$CO$16*DD$16)) -> 5359.5757 | DE70: =(($CO70/$CO$16*DE$16)) -> 5432.4889 | DF70: =(($CO70/$CO$16*DF$16)) -> 5437.6431 | DG70: =(($CO70/$CO$16*DG$16)) -> 5282.0802
C71: MS 2000/2250 | D71: 42.6 | BT71: =BT92*0.3 -> 747.48117 | BU71: =BU92*0.3 -> 764.35002 | BV71: =BV92*0.3 -> 0 | BW71: =BW92*0.3 -> 0 | BX71: =BX92*0.3 -> 0 | BY71: =BY92*0.3 -> 0 | BZ71: =BZ92*0.3 -> 0 | CA71: =CA92*0.3 -> 0 | ... CM71: =CM92*0.3 -> 0 | CO71: =CO92*0.3 -> 0 | CP71: =CP92*0.3 -> 0 | CQ71: =CQ92*0.3 -> 0 | CR71: =CR92*0.3 -> 0 | CS71: =CS92*0.3 -> 0 | CT71: =CT92*0.3 -> 0 | CU71: =CU92*0.3 -> 0 | CV71: =CV92*0.3 -> 0 | CW71: 0 | CX71: 0 | CY71: =CY92*0.3 -> 0 | CZ71: =(($CO71/$CO$16*CZ$16)) -> 0 | DA71: =(($CO71/$CO$16*DA$16)) -> 0 | DB71: =(($CO71/$CO$16*DB$16)) -> 0 | DC71: =(($CO71/$CO$16*DC$16)) -> 0 | DD71: =(($CO71/$CO$16*DD$16)) -> 0 | DE71: =(($CO71/$CO$16*DE$16)) -> 0 | DF71: =(($CO71/$CO$16*DF$16)) -> 0 | DG71: =(($CO71/$CO$16*DG$16)) -> 0
C72: MS 2000/2250 | D72: 46.6 | BT72: =BT93*0.3 -> 747.48117 | BU72: =BU93*0.3 -> 764.35002 | BV72: =BV93*0.3 -> 779.89312 | BW72: =BW93*0.3 -> 800.49596 | BX72: =BX93*0.3 -> 820.96702 | BY72: =BY93*0.3 -> 843.00489 | BZ72: =BZ93*0.3 -> 1082.4293 | CA72: =CA93*0.3 -> 1109.1529 | ... CM72: =CM93*0.3 -> 3876.7649 | CO72: =CO93*0.3 -> 3978.8609 | CP72: =CP93*0.3 -> 4063.4987 | CQ72: =CQ93*0.3 -> 4186.9052 | CR72: =CR93*0.3 -> 4281.9857 | CS72: =CS93*0.3 -> 4373.4634 | CT72: =CT93*0.3 -> 4437.6528 | CU72: =CU93*0.3 -> 4510.5331 | CV72: =CV93*0.3 -> 4569.3548 | CW72: 4569.3548 | CX72: 4569.3548 | CY72: =((CV72/CV$16*CW$16)/CW$16*CX$16)/CX$16*CY$16 -> 5117.1678 | CZ72: =(($CO72/$CO$16*CZ$16)) -> 5733.5657 | DA72: =(($CO72/$CO$16*DA$16)) -> 5600.0328 | DB72: =(($CO72/$CO$16*DB$16)) -> 5849.155 | DC72: =(($CO72/$CO$16*DC$16)) -> 5985.7341 | DD72: =(($CO72/$CO$16*DD$16)) -> 5959.5282 | DE72: =(($CO72/$CO$16*DE$16)) -> 6040.6033 | DF72: =(($CO72/$CO$16*DF$16)) -> 6046.3345 | DG72: =(($CO72/$CO$16*DG$16)) -> 5873.3578
C73: MS 2000/2250 20% PCR | D73: 46.6 | BT73: =BT94*0.3 -> 0 | BU73: =BU94*0.3 -> 0 | BV73: =BV94*0.3 -> 0 | BW73: =BW94*0.3 -> 0 | BX73: =BX94*0.3 -> 0 | BY73: =BY94*0.3 -> 0 | BZ73: =BZ94*0.3 -> 0 | CA73: =CA94*0.3 -> 0 | ... CM73: =CM94*0.3 -> 3876.7649 | CO73: =CO94*0.3 -> 3978.8609 | CP73: =CP94*0.3 -> 4063.4987 | CQ73: =CQ94*0.3 -> 4186.9052 | CR73: =CR94*0.3 -> 4281.9857 | CS73: =CS94*0.3 -> 4373.4634 | CT73: =CT94*0.3 -> 4437.6528 | CU73: =CU94*0.3 -> 4510.5331 | CV73: =CV94*0.3 -> 4569.3548 | CW73: 4569.3548 | CX73: 4569.3548 | CY73: =((CV73/CV$16*CW$16)/CW$16*CX$16)/CX$16*CY$16 -> 5117.1678 | CZ73: =(($CO73/$CO$16*CZ$16)) -> 5733.5657 | DA73: =(($CO73/$CO$16*DA$16)) -> 5600.0328 | DB73: =(($CO73/$CO$16*DB$16)) -> 5849.155 | DC73: =(($CO73/$CO$16*DC$16)) -> 5985.7341 | DD73: =(($CO73/$CO$16*DD$16)) -> 5959.5282 | DE73: =(($CO73/$CO$16*DE$16)) -> 6040.6033 | DF73: =(($CO73/$CO$16*DF$16)) -> 6046.3345 | DG73: =(($CO73/$CO$16*DG$16)) -> 5873.3578
C74: MS 2000/2250 | D74: 48 | BT74: =BT95*0.3 -> 747.48117 | BU74: =BU95*0.3 -> 764.35002 | BV74: =BV95*0.3 -> 779.89312 | BW74: =BW95*0.3 -> 800.49596 | BX74: =BX95*0.3 -> 820.96702 | BY74: =BY95*0.3 -> 843.00489 | BZ74: =BZ95*0.3 -> 1082.4293 | CA74: =CA95*0.3 -> 1109.1529 | ... CM74: =CM95*0.3 -> 3876.7649 | CO74: =CO95*0.3 -> 3978.8609 | CP74: =CP95*0.3 -> 4063.4987 | CQ74: =CQ95*0.3 -> 4186.9052 | CR74: =CR95*0.3 -> 4281.9857 | CS74: =CS95*0.3 -> 4373.4634 | CT74: =CT95*0.3 -> 4437.6528 | CU74: =CU95*0.3 -> 4510.5331 | CV74: =CV95*0.3 -> 4569.3548 | CW74: 4569.3548 | CX74: 4569.3548 | CY74: =((CV74/CV$16*CW$16)/CW$16*CX$16)/CX$16*CY$16 -> 5117.1678 | CZ74: =(($CO74/$CO$16*CZ$16)) -> 5733.5657 | DA74: =(($CO74/$CO$16*DA$16)) -> 5600.0328 | DB74: =(($CO74/$CO$16*DB$16)) -> 5849.155 | DC74: =(($CO74/$CO$16*DC$16)) -> 5985.7341 | DD74: =(($CO74/$CO$16*DD$16)) -> 5959.5282 | DE74: =(($CO74/$CO$16*DE$16)) -> 6040.6033 | DF74: =(($CO74/$CO$16*DF$16)) -> 6046.3345 | DG74: =(($CO74/$CO$16*DG$16)) -> 5873.3578
C75: MS 2000/2250 | D75: 49.6 | BT75: =BT96*0.3 -> 747.48117 | BU75: =BU96*0.3 -> 764.35002 | BV75: =BV96*0.3 -> 0 | BW75: =BW96*0.3 -> 0 | BX75: =BX96*0.3 -> 0 | BY75: =BY96*0.3 -> 0 | BZ75: =BZ96*0.3 -> 0 | CA75: =CA96*0.3 -> 0 | ... CM75: =CM96*0.3 -> 0 | CO75: =CO96*0.3 -> 0 | CP75: =CP96*0.3 -> 0 | CQ75: =CQ96*0.3 -> 0 | CR75: =CR96*0.3 -> 0 | CS75: =CS96*0.3 -> 0 | CT75: =CT96*0.3 -> 0 | CU75: =CU96*0.3 -> 0 | CV75: =CV96*0.3 -> 0 | CW75: 0 | CX75: 0 | CY75: =CY96*0.3 -> 0 | CZ75: =(($CO75/$CO$16*CZ$16)) -> 0 | DA75: =(($CO75/$CO$16*DA$16)) -> 0 | DB75: =(($CO75/$CO$16*DB$16)) -> 0 | DC75: =(($CO75/$CO$16*DC$16)) -> 0 | DD75: =(($CO75/$CO$16*DD$16)) -> 0 | DE75: =(($CO75/$CO$16*DE$16)) -> 0 | DF75: =(($CO75/$CO$16*DF$16)) -> 0 | DG75: =(($CO75/$CO$16*DG$16)) -> 0
C76: MS 2000/2250 | D76: 52 | BT76: =BT97*0.3 -> 747.48117 | BU76: =BU97*0.3 -> 764.35002 | BV76: =BV97*0.3 -> 779.89312 | BW76: =BW97*0.3 -> 800.49596 | BX76: =BX97*0.3 -> 820.96702 | BY76: =BY97*0.3 -> 843.00489 | BZ76: =BZ97*0.3 -> 1082.4293 | CA76: =CA97*0.3 -> 1109.1529 | ... CM76: =CM97*0.3 -> 3876.7649 | CO76: =CO97*0.3 -> 3978.8609 | CP76: =CP97*0.3 -> 4063.4987 | CQ76: =CQ97*0.3 -> 4186.9052 | CR76: =CR97*0.3 -> 4281.9857 | CS76: =CS97*0.3 -> 4373.4634 | CT76: =CT97*0.3 -> 4437.6528 | CU76: =CU97*0.3 -> 4510.5331 | CV76: =CV97*0.3 -> 4569.3548 | CW76: 4569.3548 | CX76: 4569.3548 | CY76: =((CV76/CV$16*CW$16)/CW$16*CX$16)/CX$16*CY$16 -> 5117.1678 | CZ76: =(($CO76/$CO$16*CZ$16)) -> 5733.5657 | DA76: =(($CO76/$CO$16*DA$16)) -> 5600.0328 | DB76: =(($CO76/$CO$16*DB$16)) -> 5849.155 | DC76: =(($CO76/$CO$16*DC$16)) -> 5985.7341 | DD76: =(($CO76/$CO$16*DD$16)) -> 5959.5282 | DE76: =(($CO76/$CO$16*DE$16)) -> 6040.6033 | DF76: =(($CO76/$CO$16*DF$16)) -> 6046.3345 | DG76: =(($CO76/$CO$16*DG$16)) -> 5873.3578
C77: MS 3000 | D77: 54.7 | BT77: =BT98*0.3 -> 767.58845 | BU77: =BU98*0.3 -> 784.91016 | BV77: =BV98*0.3 -> 800.82985 | BW77: =BW98*0.3 -> 821.98579 | BX77: =BX98*0.3 -> 843.00641 | BY77: =BY98*0.3 -> 865.6359 | BZ77: =BZ98*0.3 -> 1111.4878 | CA77: =CA98*0.3 -> 1138.9288 | ... CM77: =CM98*0.3 -> 3980.8392 | CO77: =CO98*0.3 -> 4085.6759 | CP77: =CP98*0.3 -> 4172.5859 | CQ77: =CQ98*0.3 -> 4299.3054 | CR77: =CR98*0.3 -> 4396.9384 | CS77: =CS98*0.3 -> 4490.8718 | CT77: =CT98*0.3 -> 4556.7844 | CU77: =CU98*0.3 -> 4631.6213 | CV77: =CV98*0.3 -> 4692.022 | CW77: 4692.022 | CX77: 4692.022 | CY77: =((CV77/CV$16*CW$16)/CW$16*CX$16)/CX$16*CY$16 -> 5254.5414 | CZ77: =(($CO77/$CO$16*CZ$16)) -> 5887.4869 | DA77: =(($CO77/$CO$16*DA$16)) -> 5750.3693 | DB77: =(($CO77/$CO$16*DB$16)) -> 6006.1793 | DC77: =(($CO77/$CO$16*DC$16)) -> 6146.4249 | DD77: =(($CO77/$CO$16*DD$16)) -> 6119.5156 | DE77: =(($CO77/$CO$16*DE$16)) -> 6202.7672 | DF77: =(($CO77/$CO$16*DF$16)) -> 6208.6522 | DG77: =(($CO77/$CO$16*DG$16)) -> 6031.0319
C78: MS 3000 | D78: 58 | BT78: =BT99*0.3 -> 767.58845 | BU78: =BU99*0.3 -> 784.91016 | BV78: =BV99*0.3 -> 0 | BW78: =BW99*0.3 -> 0 | BX78: =BX99*0.3 -> 0 | BY78: =BY99*0.3 -> 0 | BZ78: =BZ99*0.3 -> 0 | CA78: =CA99*0.3 -> 0 | ... CM78: =CM99*0.3 -> 0 | CO78: =CO99*0.3 -> 0 | CP78: =CP99*0.3 -> 0 | CQ78: =CQ99*0.3 -> 0 | CR78: =CR99*0.3 -> 0 | CS78: =CS99*0.3 -> 0 | CT78: =CT99*0.3 -> 0 | CU78: =CU99*0.3 -> 0 | CV78: =CV99*0.3 -> 0 | CW78: 0 | CX78: 0 | CY78: =CY99*0.3 -> 0 | CZ78: =(($CO78/$CO$16*CZ$16)) -> 0 | DA78: =(($CO78/$CO$16*DA$16)) -> 0 | DB78: =(($CO78/$CO$16*DB$16)) -> 0 | DC78: =(($CO78/$CO$16*DC$16)) -> 0 | DD78: =(($CO78/$CO$16*DD$16)) -> 0 | DE78: =(($CO78/$CO$16*DE$16)) -> 0 | DF78: =(($CO78/$CO$16*DF$16)) -> 0 | DG78: =(($CO78/$CO$16*DG$16)) -> 0
C79: MS 3000 | D79: 62 | BT79: =BT100*0.3 -> 767.58845 | BU79: =BU100*0.3 -> 784.91016 | BV79: =BV100*0.3 -> 800.82985 | BW79: =BW100*0.3 -> 821.98579 | BX79: =BX100*0.3 -> 843.00641 | BY79: =BY100*0.3 -> 865.6359 | BZ79: =BZ100*0.3 -> 1111.4878 | CA79: =CA100*0.3 -> 1138.9288 | ... CM79: =CM100*0.3 -> 3980.8392 | CO79: =CO100*0.3 -> 4085.6759 | CP79: =CP100*0.3 -> 4172.5859 | CQ79: =CQ100*0.3 -> 4299.3054 | CR79: =CR100*0.3 -> 4396.9384 | CS79: =CS100*0.3 -> 4490.8718 | CT79: =CT100*0.3 -> 4556.7844 | CU79: =CU100*0.3 -> 4631.6213 | CV79: =CV100*0.3 -> 4692.022 | CW79: 4692.022 | CX79: 4692.022 | CY79: =((CV79/CV$16*CW$16)/CW$16*CX$16)/CX$16*CY$16 -> 5254.5414 | CZ79: =(($CO79/$CO$16*CZ$16)) -> 5887.4869 | DA79: =(($CO79/$CO$16*DA$16)) -> 5750.3693 | DB79: =(($CO79/$CO$16*DB$16)) -> 6006.1793 | DC79: =(($CO79/$CO$16*DC$16)) -> 6146.4249 | DD79: =(($CO79/$CO$16*DD$16)) -> 6119.5156 | DE79: =(($CO79/$CO$16*DE$16)) -> 6202.7672 | DF79: =(($CO79/$CO$16*DF$16)) -> 6208.6522 | DG79: =(($CO79/$CO$16*DG$16)) -> 6031.0319
C81: Total Conversión ARS
C82: SS 250 | D82: 12.5 | BT82: =((+(169/$A$16)*0.3*BT$16+((169)*(1+BT$14)*0.7))*0.95)-5.05 -> 1410.8376 | BU82: =((+(169/$A$16)*0.3*BU$16+((169)*(1+BU$14)*0.7))*0.95)-5.05 -> 1442.7262 | BV82: =((+(169/$A$16)*0.3*BV$16+((169)*(1+BV$14)*0.7))*0.95)-5.05 -> 1469.2446 | BW82: =((+(169/$A$16)*0.3*BW$16+((169)*(1+BW$14)*0.7))*0.95)-5.05 -> 1508.1918 | BX82: =((+(169/$A$16)*0.3*BX$16+((169)*(1+BX$14)*0.7))*0.95)-5.05 -> 1546.8899 | BY82: =((+(169/$A$16)*0.3*BY$16+((169)*(1+BY$14)*0.7))*0.95)-5.05 -> 1588.5499 | BZ82: =((+(169/$A$16)*0.3*BZ$16+((169)*(1+BZ$14)*0.7))*0.95)-5.05 -> 2041.153 | CA82: =((+(169/$A$16)*0.3*CA$16+((169)*(1+CA$14)*0.7))*0.95)-5.05 -> 2091.6708 | ... CL82: =((+(169/$A$16)*0.3*CL$16+((169)*(1+CL$14)*0.7))*0.95)-5.05 -> 7186.409 | CM82: 7323.5101 | CO82: =((+(169/$A$16)*0.3*CO$16+((169)*(1+CO$14)*0.7))*0.95)-5.05 -> 2749.8122 | CP82: =((+(169/$A$16)*0.3*CP$16+((169)*(1+CP$14)*0.7))*0.95)-5.05 -> 2809.9238 | CQ82: =((+(169/$A$16)*0.3*CQ$16+((169)*(1+CQ$14)*0.7))*0.95)-5.05 -> 2873.6671 | CR82: =((+(169/$A$16)*0.3*CR$16+((169)*(1+CR$14)*0.7))*0.95)-5.05 -> 2914.3458 | CS82: =((+(169/$A$16)*0.3*CS$16+((169)*(1+CS$14)*0.7))*0.95)-5.05 -> 2976.0662 | CT82: =((+(169/$A$16)*0.3*CT$16+((169)*(1+CT$14)*0.7))*0.95)-5.05 -> 3028.4531 | CU82: =((+(169/$A$16)*0.3*CU$16+((169)*(1+CU$14)*0.7))*0.95)-5.05 -> 3056.1726 | CV82: =((+(169/$A$16)*0.3*CV$16+((169)*(1+CV$14)*0.7))*0.95)-5.05 -> 3087.3877 | ... DG82: =((+(169/$A$16)*0.3*DG$16+((169)*(1+DG$14)*0.7))*0.95)-5.05 -> 4005.8569
C83: SS 500 | D83: 19.5 | BT83: =((+(191/$A$16)*0.3*BT$16+((191)*(1+BT$14)*0.7))*0.95)-5.05 -> 1595.1543 | BU83: =((+(191/$A$16)*0.3*BU$16+((191)*(1+BU$14)*0.7))*0.95)-5.05 -> 1631.1941 | BV83: =((+(191/$A$16)*0.3*BV$16+((191)*(1+BV$14)*0.7))*0.95) -> 1666.2146 | BW83: =((+(191/$A$16)*0.3*BW$16+((191)*(1+BW$14)*0.7))*0.95) -> 1710.2319 | BX83: =((+(191/$A$16)*0.3*BX$16+((191)*(1+BX$14)*0.7))*0.95) -> 1753.9676 | BY83: =((+(191/$A$16)*0.3*BY$16+((191)*(1+BY$14)*0.7))*0.95) -> 1801.0507 | BZ83: =((+(191/$A$16)*0.3*BZ$16+((191)*(1+BZ$14)*0.7))*0.95) -> 2312.5726 | CA83: =((+(191/$A$16)*0.3*CA$16+((191)*(1+CA$14)*0.7))*0.95) -> 2369.6668 | CB83: =((+(191/$A$16)*0.3*CB$16+((191)*(1+CB$14)*0.7))*0.95) -> 2601.0155 | CC83: =((+(191/$A$16)*0.3*CC$16+((191)*(1+CC$14)*0.7))*0.95) -> 2600.7027 | ... CL83: =((+(191/$A$16)*0.3*CL$16+((191)*(1+CL$14)*0.7))*0.95) -> 8127.6253 | CM83: 8282.5739 | CO83: =((+($CM83/$CM$16)*0.3*CO$16+(($CM83)*(1+CO$14)*0.7))) -> 8500.6983 | CP83: =((+($CO83/$CO$16)*0.3*CP$16+(($CO83)*(1+CP$14)*0.7))) -> 8681.524 | CQ83: =((+($CP83/$CP$16)*0.3*CQ$16+(($CP83)*(1+CQ$14)*0.7))) -> 8945.1778 | CR83: =((+($CQ83/$CQ$16)*0.3*CR$16+(($CQ83)*(1+CR$14)*0.7))) -> 9148.314 | CS83: =((+(CR83/CR$16)*0.3*CS$16+((CR83)*(1+CS$14)*0.7))) -> 9343.7529 | CT83: =((+(CS83/CS$16)*0.3*CT$16+((CS83)*(1+CT$14)*0.7))) -> 9480.8913 | CU83: =((+(CT83/CT$16)*0.3*CU$16+((CT83)*(1+CU$14)*0.7))) -> 9636.5976 | CV83: =((+(CU83/CU$16)*0.3*CV$16+((CU83)*(1+CV$14)*0.7))) -> 9762.2681 | CW83: 9762.2681 | CX83: 9762.2681 | CY83: =CY41+CY62 -> 10527.322 | CZ83: =CZ41+CZ62 -> 11041.98 | DA83: =DA41+DA62 -> 11158.99 | DB83: =(DB41+DB62)*0.99 -> 11385.331 | DC83: =(DC41+DC62)*0.99 -> 11709.885 | DD83: =(DD41+DD62)*0.99 -> 11827.756 | DE83: =(DE41+DE62)*0.99 -> 12032.08 | DF83: =(DF41+DF62)*0.99 -> 12187.4 | DG83: =(DG41+DG62)*0.99 -> 12257.184
C84: SS 500 - 19.5G PCR 100% | D84: 19.5 | CG84: =((+(191/$A$16)*0.3*CG$16+((191)*(1+CG$14)*0.7))*0.95) -> 6097.2654 | CH84: =((+(191/$A$16)*0.3*CH$16+((191)*(1+CH$14)*0.7))*0.95) -> 6683.7305 | CI84: =((+(191/$A$16)*0.3*CI$16+((191)*(1+CI$14)*0.7))*0.95) -> 7273.6475 | CJ84: =((+(191/$A$16)*0.3*CJ$16+((191)*(1+CJ$14)*0.7))*0.95) -> 7704.649 | CK84: =((+(191/$A$16)*0.3*CK$16+((191)*(1+CK$14)*0.7))*0.95) -> 8001.4931 | CL84: =((+(191/$A$16)*0.3*CL$16+((191)*(1+CL$14)*0.7))*0.95) -> 8127.6253 | CM84: 8282.5739 | CO84: =((+($CM84/$CM$16)*0.3*CO$16+(($CM84)*(1+CO$14)*0.7))) -> 8500.6983 | CP84: =((+($CO84/$CO$16)*0.3*CP$16+(($CO84)*(1+CP$14)*0.7))) -> 8681.524 | CQ84: =((+($CP84/$CP$16)*0.3*CQ$16+(($CP84)*(1+CQ$14)*0.7))) -> 8945.1778 | CR84: =((+($CQ84/$CQ$16)*0.3*CR$16+(($CQ84)*(1+CR$14)*0.7))) -> 9148.314 | CS84: =((+(CR84/CR$16)*0.3*CS$16+((CR84)*(1+CS$14)*0.7))) -> 9343.7529 | CT84: =((+(CS84/CS$16)*0.3*CT$16+((CS84)*(1+CT$14)*0.7))) -> 9480.8913 | CU84: =((+(CT84/CT$16)*0.3*CU$16+((CT84)*(1+CU$14)*0.7))) -> 9636.5976 | CV84: =((+(CU84/CU$16)*0.3*CV$16+((CU84)*(1+CV$14)*0.7))) -> 9762.2681 | CW84: 9762.2681 | CX84: 9762.2681 | CY84: =CY42+CY63 -> 10527.322 | CZ84: =CZ42+CZ63 -> 11041.98 | DA84: =DA42+DA63 -> 11158.99 | DB84: =(DB42+DB63)*0.99 -> 11385.331 | DC84: =(DC42+DC63)*0.99 -> 11709.885 | DD84: =(DD42+DD63)*0.99 -> 11827.756 | DE84: =(DE42+DE63)*0.99 -> 12032.08 | DF84: =(DF42+DF63)*0.99 -> 12187.4 | DG84: =(DG42+DG63)*0.99 -> 12257.184
C85: SS 500 | D85: 22.1 | BT85: =((+(191/$A$16)*0.3*BT$16+((191)*(1+BT$14)*0.7))*0.95)-5.05 -> 1595.1543 | BU85: =((+(191/$A$16)*0.3*BU$16+((191)*(1+BU$14)*0.7))*0.95)-5.05 -> 1631.1941 | BV85: =((+(191/$A$16)*0.3*BV$16+((191)*(1+BV$14)*0.7))*0.95) -> 1666.2146 | BW85: =((+(191/$A$16)*0.3*BW$16+((191)*(1+BW$14)*0.7))*0.95) -> 1710.2319 | BX85: =((+(191/$A$16)*0.3*BX$16+((191)*(1+BX$14)*0.7))*0.95) -> 1753.9676 | BY85: =((+(191/$A$16)*0.3*BY$16+((191)*(1+BY$14)*0.7))*0.95) -> 1801.0507 | BZ85: =((+(191/$A$16)*0.3*BZ$16+((191)*(1+BZ$14)*0.7))*0.95) -> 2312.5726 | CA85: =((+(191/$A$16)*0.3*CA$16+((191)*(1+CA$14)*0.7))*0.95) -> 2369.6668 | CB85: =((+(191/$A$16)*0.3*CB$16+((191)*(1+CB$14)*0.7))*0.95) -> 2601.0155 | CC85: =((+(191/$A$16)*0.3*CC$16+((191)*(1+CC$14)*0.7))*0.95) -> 2600.7027 | ... CL85: =((+(191/$A$16)*0.3*CL$16+((191)*(1+CL$14)*0.7))*0.95) -> 8127.6253 | CM85: 8282.5739 | CO85: =((+($CM85/$CM$16)*0.3*CO$16+(($CM85)*(1+CO$14)*0.7))) -> 8500.6983 | CP85: =((+($CO85/$CO$16)*0.3*CP$16+(($CO85)*(1+CP$14)*0.7))) -> 8681.524 | CQ85: =((+($CP85/$CP$16)*0.3*CQ$16+(($CP85)*(1+CQ$14)*0.7))) -> 8945.1778 | CR85: =((+($CQ85/$CQ$16)*0.3*CR$16+(($CQ85)*(1+CR$14)*0.7))) -> 9148.314 | CS85: =((+(CR85/CR$16)*0.3*CS$16+((CR85)*(1+CS$14)*0.7))) -> 9343.7529 | CT85: =((+(CS85/CS$16)*0.3*CT$16+((CS85)*(1+CT$14)*0.7))) -> 9480.8913 | CU85: =((+(CT85/CT$16)*0.3*CU$16+((CT85)*(1+CU$14)*0.7))) -> 9636.5976 | CV85: =((+(CU85/CU$16)*0.3*CV$16+((CU85)*(1+CV$14)*0.7))) -> 9762.2681 | CW85: 9762.2681 | CX85: 9762.2681 | CY85: =CY43+CY64 -> 10527.322 | CZ85: =CZ43+CZ64 -> 11041.98 | DA85: =DA43+DA64 -> 11158.99 | DB85: =(DB43+DB64)*0.99 -> 11385.331 | DC85: =(DC43+DC64)*0.99 -> 11709.885 | DD85: =(DD43+DD64)*0.99 -> 11827.756 | DE85: =(DE43+DE64)*0.99 -> 12032.08 | DF85: =(DF43+DF64)*0.99 -> 12187.4 | DG85: =(DG43+DG64)*0.99 -> 12257.184
C86: SS 500 | D86: 22 | BT86: =((+(191/$A$16)*0.3*BT$16+((191)*(1+BT$14)*0.7))*0.95)-5.05 -> 1595.1543 | BU86: =((+(191/$A$16)*0.3*BU$16+((191)*(1+BU$14)*0.7))*0.95)-5.05 -> 1631.1941 | BV86: =(((+(191/$A$16)*0.3*BV$16+((191)*(1+BV$14)*0.7))*0.95))*0 -> 0 | BW86: =(((+(191/$A$16)*0.3*BW$16+((191)*(1+BW$14)*0.7))*0.95))*0 -> 0 | BX86: =(((+(191/$A$16)*0.3*BX$16+((191)*(1+BX$14)*0.7))*0.95))*0 -> 0 | BY86: =(((+(191/$A$16)*0.3*BY$16+((191)*(1+BY$14)*0.7))*0.95))*0 -> 0 | BZ86: =(((+(191/$A$16)*0.3*BZ$16+((191)*(1+BZ$14)*0.7))*0.95))*0 -> 0 | CA86: =(((+(191/$A$16)*0.3*CA$16+((191)*(1+CA$14)*0.7))*0.95))*0 -> 0 | CB86: =(((+(191/$A$16)*0.3*CB$16+((191)*(1+CB$14)*0.7))*0.95))*0 -> 0 | CC86: =(((+(191/$A$16)*0.3*CC$16+((191)*(1+CC$14)*0.7))*0.95))*0 -> 0 | ... CL86: =(((+(191/$A$16)*0.3*CL$16+((191)*(1+CL$14)*0.7))*0.95))*0 -> 0 | CM86: 0 | CO86: =((+($CM86/$CM$16)*0.3*CO$16+(($CM86)*(1+CO$14)*0.7))) -> 0 | CP86: =((+($CO86/$CO$16)*0.3*CP$16+(($CO86)*(1+CP$14)*0.7))) -> 0 | CQ86: =((+($CP86/$CP$16)*0.3*CQ$16+(($CP86)*(1+CQ$14)*0.7))) -> 0 | CR86: =((+($CQ86/$CQ$16)*0.3*CR$16+(($CQ86)*(1+CR$14)*0.7))) -> 0 | CS86: =((+(CR86/CR$16)*0.3*CS$16+((CR86)*(1+CS$14)*0.7))) -> 0 | CT86: =((+(CS86/CS$16)*0.3*CT$16+((CS86)*(1+CT$14)*0.7))) -> 0 | CU86: =((+(CT86/CT$16)*0.3*CU$16+((CT86)*(1+CU$14)*0.7))) -> 0 | CV86: =((+(CU86/CU$16)*0.3*CV$16+((CU86)*(1+CV$14)*0.7))) -> 0 | CW86: 0 | CX86: 0 | CY86: =CX86 -> 0 | CZ86: =CY86 -> 0 | DA86: =CZ86 -> 0 | DB86: =(DB44+DB65)*0.99 -> 0 | DC86: =(DC44+DC65)*0.99 -> 0 | DD86: =(DD44+DD65)*0.99 -> 0 | DE86: =(DE44+DE65)*0.99 -> 0 | DF86: =(DF44+DF65)*0.99 -> 0 | DG86: =(DG44+DG65)*0.99 -> 0
C87: SS 500 | D87: 25 | BT87: =((+(191/$A$16)*0.3*BT$16+((191)*(1+BT$14)*0.7))*0.95)-5.05 -> 1595.1543 | BU87: =((+(191/$A$16)*0.3*BU$16+((191)*(1+BU$14)*0.7))*0.95)-5.05 -> 1631.1941 | BV87: =((+(191/$A$16)*0.3*BV$16+((191)*(1+BV$14)*0.7))*0.95) -> 1666.2146 | BW87: =((+(191/$A$16)*0.3*BW$16+((191)*(1+BW$14)*0.7))*0.95) -> 1710.2319 | BX87: =((+(191/$A$16)*0.3*BX$16+((191)*(1+BX$14)*0.7))*0.95) -> 1753.9676 | BY87: =((+(191/$A$16)*0.3*BY$16+((191)*(1+BY$14)*0.7))*0.95) -> 1801.0507 | BZ87: =((+(191/$A$16)*0.3*BZ$16+((191)*(1+BZ$14)*0.7))*0.95) -> 2312.5726 | CA87: =((+(191/$A$16)*0.3*CA$16+((191)*(1+CA$14)*0.7))*0.95) -> 2369.6668 | CB87: =((+(191/$A$16)*0.3*CB$16+((191)*(1+CB$14)*0.7))*0.95) -> 2601.0155 | CC87: =((+(191/$A$16)*0.3*CC$16+((191)*(1+CC$14)*0.7))*0.95) -> 2600.7027 | ... CL87: =((+(191/$A$16)*0.3*CL$16+((191)*(1+CL$14)*0.7))*0.95) -> 8127.6253 | CM87: 8282.5739 | CO87: =((+($CM87/$CM$16)*0.3*CO$16+(($CM87)*(1+CO$14)*0.7))) -> 8500.6983 | CP87: =((+($CO87/$CO$16)*0.3*CP$16+(($CO87)*(1+CP$14)*0.7))) -> 8681.524 | CQ87: =((+($CP87/$CP$16)*0.3*CQ$16+(($CP87)*(1+CQ$14)*0.7))) -> 8945.1778 | CR87: =((+($CQ87/$CQ$16)*0.3*CR$16+(($CQ87)*(1+CR$14)*0.7))) -> 9148.314 | CS87: =((+(CR87/CR$16)*0.3*CS$16+((CR87)*(1+CS$14)*0.7))) -> 9343.7529 | CT87: =((+(CS87/CS$16)*0.3*CT$16+((CS87)*(1+CT$14)*0.7))) -> 9480.8913 | CU87: =((+(CT87/CT$16)*0.3*CU$16+((CT87)*(1+CU$14)*0.7))) -> 9636.5976 | CV87: =((+(CU87/CU$16)*0.3*CV$16+((CU87)*(1+CV$14)*0.7))) -> 9762.2681 | CW87: 9762.2681 | CX87: 9762.2681 | CY87: =CY45+CY66 -> 10527.322 | CZ87: =CZ45+CZ66 -> 11041.98 | DA87: =DA45+DA66 -> 11158.99 | DB87: =(DB45+DB66)*0.99 -> 11385.331 | DC87: =(DC45+DC66)*0.99 -> 11709.885 | DD87: =(DD45+DD66)*0.99 -> 11827.756 | DE87: =(DE45+DE66)*0.99 -> 12032.08 | DF87: =(DF45+DF66)*0.99 -> 12187.4 | DG87: =(DG45+DG66)*0.99 -> 12257.184
C88: SS 500 - 25G PCR 100% | D88: 25 | CG88: =((+(191/$A$16)*0.3*CG$16+((191)*(1+CG$14)*0.7))*0.95) -> 6097.2654 | CH88: =((+(191/$A$16)*0.3*CH$16+((191)*(1+CH$14)*0.7))*0.95) -> 6683.7305 | CI88: =((+(191/$A$16)*0.3*CI$16+((191)*(1+CI$14)*0.7))*0.95) -> 7273.6475 | CJ88: =((+(191/$A$16)*0.3*CJ$16+((191)*(1+CJ$14)*0.7))*0.95) -> 7704.649 | CK88: =((+(191/$A$16)*0.3*CK$16+((191)*(1+CK$14)*0.7))*0.95) -> 8001.4931 | CL88: =((+(191/$A$16)*0.3*CL$16+((191)*(1+CL$14)*0.7))*0.95) -> 8127.6253 | CM88: 8282.5739 | CO88: =((+($CM88/$CM$16)*0.3*CO$16+(($CM88)*(1+CO$14)*0.7))) -> 8500.6983 | CP88: =((+($CO88/$CO$16)*0.3*CP$16+(($CO88)*(1+CP$14)*0.7))) -> 8681.524 | CQ88: =((+($CP88/$CP$16)*0.3*CQ$16+(($CP88)*(1+CQ$14)*0.7))) -> 8945.1778 | CR88: =((+($CQ88/$CQ$16)*0.3*CR$16+(($CQ88)*(1+CR$14)*0.7))) -> 9148.314 | CS88: =((+(CR88/CR$16)*0.3*CS$16+((CR88)*(1+CS$14)*0.7))) -> 9343.7529 | CT88: =((+(CS88/CS$16)*0.3*CT$16+((CS88)*(1+CT$14)*0.7))) -> 9480.8913 | CU88: =((+(CT88/CT$16)*0.3*CU$16+((CT88)*(1+CU$14)*0.7))) -> 9636.5976 | CV88: =((+(CU88/CU$16)*0.3*CV$16+((CU88)*(1+CV$14)*0.7))) -> 9762.2681 | CW88: 9762.2681 | CX88: 9762.2681 | CY88: =CY46+CY67 -> 10527.322 | CZ88: =CZ46+CZ67 -> 11041.98 | DA88: =DA46+DA67 -> 11158.99 | DB88: =(DB46+DB67)*0.99 -> 11385.331 | DC88: =(DC46+DC67)*0.99 -> 11709.885 | DD88: =(DD46+DD67)*0.99 -> 11827.756 | DE88: =(DE46+DE67)*0.99 -> 12032.08 | DF88: =(DF46+DF67)*0.99 -> 12187.4 | DG88: =(DG46+DG67)*0.99 -> 12257.184
C89: MS 1500 | D89: 37.2 | BT89: =((+(268/$A$16)*0.3*BT$16+((268)*(1+BT$14)*0.7))*0.95)-5.05 -> 2240.2629 | BU89: =((+(268/$A$16)*0.3*BU$16+((268)*(1+BU$14)*0.7))*0.95)-5.05 -> 2290.8317 | BV89: =((+(268/$A$16)*0.3*BV$16+((268)*(1+BV$14)*0.7))*0.95) -> 2337.9346 | BW89: =((+(268/$A$16)*0.3*BW$16+((268)*(1+BW$14)*0.7))*0.95) -> 2399.6971 | BX89: =((+(268/$A$16)*0.3*BX$16+((268)*(1+BX$14)*0.7))*0.95) -> 2461.0645 | BY89: =((+(268/$A$16)*0.3*BY$16+((268)*(1+BY$14)*0.7))*0.95) -> 2527.1288 | BZ89: =((+(268/$A$16)*0.3*BZ$16+((268)*(1+BZ$14)*0.7))*0.95) -> 3244.8662 | CA89: =((+(268/$A$16)*0.3*CA$16+((268)*(1+CA$14)*0.7))*0.95) -> 3324.9774 | CB89: =((+(268/$A$16)*0.3*CB$16+((268)*(1+CB$14)*0.7))*0.95) -> 3649.5924 | CC89: =((+(268/$A$16)*0.3*CC$16+((268)*(1+CC$14)*0.7))*0.95) -> 3649.1535 | ... CL89: =((+(268/$A$16)*0.3*CL$16+((268)*(1+CL$14)*0.7))*0.95) -> 11404.207 | CM89: 11621.622 | CO89: =((+($CM89/$CM$16)*0.3*CO$16+(($CM89)*(1+CO$14)*0.7))) -> 11927.681 | CP89: =((+($CO89/$CO$16)*0.3*CP$16+(($CO89)*(1+CP$14)*0.7))) -> 12181.405 | CQ89: =((+($CP89/$CP$16)*0.3*CQ$16+(($CP89)*(1+CQ$14)*0.7))) -> 12551.349 | CR89: =((+($CQ89/$CQ$16)*0.3*CR$16+(($CQ89)*(1+CR$14)*0.7))) -> 12836.378 | CS89: =((+(CR89/CR$16)*0.3*CS$16+((CR89)*(1+CS$14)*0.7))) -> 13110.606 | CT89: =((+(CS89/CS$16)*0.3*CT$16+((CS89)*(1+CT$14)*0.7))) -> 13303.031 | CU89: =((+(CT89/CT$16)*0.3*CU$16+((CT89)*(1+CU$14)*0.7))) -> 13521.509 | CV89: =((+(CU89/CU$16)*0.3*CV$16+((CU89)*(1+CV$14)*0.7))) -> 13697.842 | CW89: 13697.842 | CX89: 13697.842 | CY89: =CY47+CY68 -> 14771.322 | CZ89: =CZ47+CZ68 -> 15493.459 | DA89: =DA47+DA68 -> 15657.64 | DB89: =(DB47+DB68)*0.99 -> 15975.229 | DC89: =(DC47+DC68)*0.99 -> 16430.624 | DD89: =(DD47+DD68)*0.99 -> 16596.014 | DE89: =(DE47+DE68)*0.99 -> 16882.709 | DF89: =(DF47+DF68)*0.99 -> 17100.645 | DG89: =(DG47+DG68)*0.99 -> 17198.562
C90: MS 1500 | D90: 40 | BT90: =((+(268/$A$16)*0.3*BT$16+((268)*(1+BT$14)*0.7))*0.95)-5.05 -> 2240.2629 | BU90: =((+(268/$A$16)*0.3*BU$16+((268)*(1+BU$14)*0.7))*0.95)-5.05 -> 2290.8317 | BV90: =(((+(268/$A$16)*0.3*BV$16+((268)*(1+BV$14)*0.7))*0.95))*0 -> 0 | BW90: =(((+(268/$A$16)*0.3*BW$16+((268)*(1+BW$14)*0.7))*0.95))*0 -> 0 | BX90: =(((+(268/$A$16)*0.3*BX$16+((268)*(1+BX$14)*0.7))*0.95))*0 -> 0 | BY90: =(((+(268/$A$16)*0.3*BY$16+((268)*(1+BY$14)*0.7))*0.95))*0 -> 0 | BZ90: =(((+(268/$A$16)*0.3*BZ$16+((268)*(1+BZ$14)*0.7))*0.95))*0 -> 0 | CA90: =(((+(268/$A$16)*0.3*CA$16+((268)*(1+CA$14)*0.7))*0.95))*0 -> 0 | CB90: =(((+(268/$A$16)*0.3*CB$16+((268)*(1+CB$14)*0.7))*0.95))*0 -> 0 | CC90: =(((+(268/$A$16)*0.3*CC$16+((268)*(1+CC$14)*0.7))*0.95))*0 -> 0 | ... CL90: =(((+(268/$A$16)*0.3*CL$16+((268)*(1+CL$14)*0.7))*0.95))*0 -> 0 | CM90: 0 | CO90: =((+($CM90/$CM$16)*0.3*CO$16+(($CM90)*(1+CO$14)*0.7))) -> 0 | CP90: =((+($CO90/$CO$16)*0.3*CP$16+(($CO90)*(1+CP$14)*0.7))) -> 0 | CQ90: =((+($CP90/$CP$16)*0.3*CQ$16+(($CP90)*(1+CQ$14)*0.7))) -> 0 | CR90: =((+($CQ90/$CQ$16)*0.3*CR$16+(($CQ90)*(1+CR$14)*0.7))) -> 0 | CS90: =((+(CR90/CR$16)*0.3*CS$16+((CR90)*(1+CS$14)*0.7))) -> 0 | CT90: =((+(CS90/CS$16)*0.3*CT$16+((CS90)*(1+CT$14)*0.7))) -> 0 | CU90: =((+(CT90/CT$16)*0.3*CU$16+((CT90)*(1+CU$14)*0.7))) -> 0 | CV90: =((+(CU90/CU$16)*0.3*CV$16+((CU90)*(1+CV$14)*0.7))) -> 0 | CW90: 0 | CX90: 0 | CY90: =CX90 -> 0 | CZ90: =CY90 -> 0 | DA90: =CZ90 -> 0 | DB90: =(DB48+DB69)*0.99 -> 0 | DC90: =(DC48+DC69)*0.99 -> 0 | DD90: =(DD48+DD69)*0.99 -> 0 | DE90: =(DE48+DE69)*0.99 -> 0 | DF90: =(DF48+DF69)*0.99 -> 0 | DG90: =(DG48+DG69)*0.99 -> 0
C91: MS 1500 | D91: 44 | BT91: =((+(268/$A$16)*0.3*BT$16+((268)*(1+BT$14)*0.7))*0.95)-5.05 -> 2240.2629 | BU91: =((+(268/$A$16)*0.3*BU$16+((268)*(1+BU$14)*0.7))*0.95)-5.05 -> 2290.8317 | BV91: =((+(268/$A$16)*0.3*BV$16+((268)*(1+BV$14)*0.7))*0.95) -> 2337.9346 | BW91: =((+(268/$A$16)*0.3*BW$16+((268)*(1+BW$14)*0.7))*0.95) -> 2399.6971 | BX91: =((+(268/$A$16)*0.3*BX$16+((268)*(1+BX$14)*0.7))*0.95) -> 2461.0645 | BY91: =((+(268/$A$16)*0.3*BY$16+((268)*(1+BY$14)*0.7))*0.95) -> 2527.1288 | BZ91: =((+(268/$A$16)*0.3*BZ$16+((268)*(1+BZ$14)*0.7))*0.95) -> 3244.8662 | CA91: =((+(268/$A$16)*0.3*CA$16+((268)*(1+CA$14)*0.7))*0.95) -> 3324.9774 | CB91: =((+(268/$A$16)*0.3*CB$16+((268)*(1+CB$14)*0.7))*0.95) -> 3649.5924 | CC91: =((+(268/$A$16)*0.3*CC$16+((268)*(1+CC$14)*0.7))*0.95) -> 3649.1535 | ... CL91: =((+(268/$A$16)*0.3*CL$16+((268)*(1+CL$14)*0.7))*0.95) -> 11404.207 | CM91: 11621.622 | CO91: =((+($CM91/$CM$16)*0.3*CO$16+(($CM91)*(1+CO$14)*0.7))) -> 11927.681 | CP91: =((+($CO91/$CO$16)*0.3*CP$16+(($CO91)*(1+CP$14)*0.7))) -> 12181.405 | CQ91: =((+($CP91/$CP$16)*0.3*CQ$16+(($CP91)*(1+CQ$14)*0.7))) -> 12551.349 | CR91: =((+($CQ91/$CQ$16)*0.3*CR$16+(($CQ91)*(1+CR$14)*0.7))) -> 12836.378 | CS91: =((+(CR91/CR$16)*0.3*CS$16+((CR91)*(1+CS$14)*0.7))) -> 13110.606 | CT91: =((+(CS91/CS$16)*0.3*CT$16+((CS91)*(1+CT$14)*0.7))) -> 13303.031 | CU91: =((+(CT91/CT$16)*0.3*CU$16+((CT91)*(1+CU$14)*0.7))) -> 13521.509 | CV91: =((+(CU91/CU$16)*0.3*CV$16+((CU91)*(1+CV$14)*0.7))) -> 13697.842 | CW91: 13697.842 | CX91: 13697.842 | CY91: =CY49+CY70 -> 14771.322 | CZ91: =CZ49+CZ70 -> 15493.459 | DA91: =DA49+DA70 -> 15657.64 | DB91: =(DB49+DB70)*0.99 -> 15975.229 | DC91: =(DC49+DC70)*0.99 -> 16430.624 | DD91: =(DD49+DD70)*0.99 -> 16596.014 | DE91: =(DE49+DE70)*0.99 -> 16882.709 | DF91: =(DF49+DF70)*0.99 -> 17100.645 | DG91: =(DG49+DG70)*0.99 -> 17198.562
C92: MS 2000/2250 | D92: 42.6 | BT92: =((+(298/$A$16)*0.3*BT$16+((298)*(1+BT$14)*0.7))*0.95)-5.05 -> 2491.6039 | BU92: =((+(298/$A$16)*0.3*BU$16+((298)*(1+BU$14)*0.7))*0.95)-5.05 -> 2547.8334 | BV92: =(((+(298/$A$16)*0.3*BV$16+((298)*(1+BV$14)*0.7))*0.95))*0 -> 0 | BW92: =(((+(298/$A$16)*0.3*BW$16+((298)*(1+BW$14)*0.7))*0.95))*0 -> 0 | BX92: =(((+(298/$A$16)*0.3*BX$16+((298)*(1+BX$14)*0.7))*0.95))*0 -> 0 | BY92: =(((+(298/$A$16)*0.3*BY$16+((298)*(1+BY$14)*0.7))*0.95))*0 -> 0 | BZ92: =(((+(298/$A$16)*0.3*BZ$16+((298)*(1+BZ$14)*0.7))*0.95))*0 -> 0 | CA92: =(((+(298/$A$16)*0.3*CA$16+((298)*(1+CA$14)*0.7))*0.95))*0 -> 0 | CB92: =(((+(298/$A$16)*0.3*CB$16+((298)*(1+CB$14)*0.7))*0.95))*0 -> 0 | CC92: =(((+(298/$A$16)*0.3*CC$16+((298)*(1+CC$14)*0.7))*0.95))*0 -> 0 | ... CL92: =(((+(298/$A$16)*0.3*CL$16+((298)*(1+CL$14)*0.7))*0.95))*0 -> 0 | CM92: 0 | CO92: =((+($CM92/$CM$16)*0.3*CO$16+(($CM92)*(1+CO$14)*0.7))) -> 0 | CP92: =((+($CO92/$CO$16)*0.3*CP$16+(($CO92)*(1+CP$14)*0.7))) -> 0 | CQ92: =((+($CP92/$CP$16)*0.3*CQ$16+(($CP92)*(1+CQ$14)*0.7))) -> 0 | CR92: =((+($CQ92/$CQ$16)*0.3*CR$16+(($CQ92)*(1+CR$14)*0.7))) -> 0 | CS92: =((+(CR92/CR$16)*0.3*CS$16+((CR92)*(1+CS$14)*0.7))) -> 0 | CT92: =((+(CS92/CS$16)*0.3*CT$16+((CS92)*(1+CT$14)*0.7))) -> 0 | CU92: =((+(CT92/CT$16)*0.3*CU$16+((CT92)*(1+CU$14)*0.7))) -> 0 | CV92: =((+(CU92/CU$16)*0.3*CV$16+((CU92)*(1+CV$14)*0.7))) -> 0 | CW92: 0 | CX92: 0 | CY92: =CX92 -> 0 | CZ92: =CY92 -> 0 | DA92: =CZ92 -> 0 | DB92: =(DB50+DB71)*0.99 -> 0 | DC92: =(DC50+DC71)*0.99 -> 0 | DD92: =(DD50+DD71)*0.99 -> 0 | DE92: =(DE50+DE71)*0.99 -> 0 | DF92: =(DF50+DF71)*0.99 -> 0 | DG92: =(DG50+DG71)*0.99 -> 0
C93: MS 2000/2250 | D93: 46.6 | BT93: =((+(298/$A$16)*0.3*BT$16+((298)*(1+BT$14)*0.7))*0.95)-5.05 -> 2491.6039 | BU93: =((+(298/$A$16)*0.3*BU$16+((298)*(1+BU$14)*0.7))*0.95)-5.05 -> 2547.8334 | BV93: =((+(298/$A$16)*0.3*BV$16+((298)*(1+BV$14)*0.7))*0.95) -> 2599.6437 | BW93: =((+(298/$A$16)*0.3*BW$16+((298)*(1+BW$14)*0.7))*0.95) -> 2668.3199 | BX93: =((+(298/$A$16)*0.3*BX$16+((298)*(1+BX$14)*0.7))*0.95) -> 2736.5567 | BY93: =((+(298/$A$16)*0.3*BY$16+((298)*(1+BY$14)*0.7))*0.95) -> 2810.0163 | BZ93: =((+(298/$A$16)*0.3*BZ$16+((298)*(1+BZ$14)*0.7))*0.95) -> 3608.0975 | CA93: =((+(298/$A$16)*0.3*CA$16+((298)*(1+CA$14)*0.7))*0.95) -> 3697.1764 | CB93: =((+(298/$A$16)*0.3*CB$16+((298)*(1+CB$14)*0.7))*0.95) -> 4058.1289 | CC93: =((+(298/$A$16)*0.3*CC$16+((298)*(1+CC$14)*0.7))*0.95) -> 4057.6408 | ... CL93: =((+(298/$A$16)*0.3*CL$16+((298)*(1+CL$14)*0.7))*0.95) -> 12680.798 | CM93: 12922.55 | CO93: =((+($CM93/$CM$16)*0.3*CO$16+(($CM93)*(1+CO$14)*0.7))) -> 13262.87 | CP93: =((+($CO93/$CO$16)*0.3*CP$16+(($CO93)*(1+CP$14)*0.7))) -> 13544.996 | CQ93: =((+($CP93/$CP$16)*0.3*CQ$16+(($CP93)*(1+CQ$14)*0.7))) -> 13956.351 | CR93: =((+($CQ93/$CQ$16)*0.3*CR$16+(($CQ93)*(1+CR$14)*0.7))) -> 14273.286 | CS93: =((+(CR93/CR$16)*0.3*CS$16+((CR93)*(1+CS$14)*0.7))) -> 14578.211 | CT93: =((+(CS93/CS$16)*0.3*CT$16+((CS93)*(1+CT$14)*0.7))) -> 14792.176 | CU93: =((+(CT93/CT$16)*0.3*CU$16+((CT93)*(1+CU$14)*0.7))) -> 15035.11 | CV93: =((+(CU93/CU$16)*0.3*CV$16+((CU93)*(1+CV$14)*0.7))) -> 15231.183 | CW93: 15231.183 | CX93: 15231.183 | CY93: =CY51+CY72 -> 16424.828 | CZ93: =CZ51+CZ72 -> 17227.802 | DA93: =DA51+DA72 -> 17410.361 | DB93: =(DB51+DB72)*0.99 -> 17763.501 | DC93: =(DC51+DC72)*0.99 -> 18269.873 | DD93: =(DD51+DD72)*0.99 -> 18453.777 | DE93: =(DE51+DE72)*0.99 -> 18772.564 | DF93: =(DF51+DF72)*0.99 -> 19014.897 | DG93: =(DG51+DG72)*0.99 -> 19123.774
C94: MS 2000/2250 20% PCR | D94: 46.6 | CG94: =((+(298/$A$16)*0.3*CG$16+((298)*(1+CG$14)*0.7))*0.95) -> 9513.011 | CH94: =((+(298/$A$16)*0.3*CH$16+((298)*(1+CH$14)*0.7))*0.95) -> 10428.019 | CI94: =((+(298/$A$16)*0.3*CI$16+((298)*(1+CI$14)*0.7))*0.95) -> 11348.413 | CJ94: =((+(298/$A$16)*0.3*CJ$16+((298)*(1+CJ$14)*0.7))*0.95) -> 12020.866 | CK94: =((+(298/$A$16)*0.3*CK$16+((298)*(1+CK$14)*0.7))*0.95) -> 12484.005 | CL94: =((+(298/$A$16)*0.3*CL$16+((298)*(1+CL$14)*0.7))*0.95) -> 12680.798 | CM94: 12922.55 | CO94: =((+($CM94/$CM$16)*0.3*CO$16+(($CM94)*(1+CO$14)*0.7))) -> 13262.87 | CP94: =((+($CO94/$CO$16)*0.3*CP$16+(($CO94)*(1+CP$14)*0.7))) -> 13544.996 | CQ94: =((+($CP94/$CP$16)*0.3*CQ$16+(($CP94)*(1+CQ$14)*0.7))) -> 13956.351 | CR94: =((+($CQ94/$CQ$16)*0.3*CR$16+(($CQ94)*(1+CR$14)*0.7))) -> 14273.286 | CS94: =((+(CR94/CR$16)*0.3*CS$16+((CR94)*(1+CS$14)*0.7))) -> 14578.211 | CT94: =((+(CS94/CS$16)*0.3*CT$16+((CS94)*(1+CT$14)*0.7))) -> 14792.176 | CU94: =((+(CT94/CT$16)*0.3*CU$16+((CT94)*(1+CU$14)*0.7))) -> 15035.11 | CV94: =((+(CU94/CU$16)*0.3*CV$16+((CU94)*(1+CV$14)*0.7))) -> 15231.183 | CW94: 15231.183 | CX94: 15231.183 | CY94: =CY52+CY73 -> 16424.828 | CZ94: =CZ52+CZ73 -> 17227.802 | DA94: =DA52+DA73 -> 17410.361 | DB94: =(DB52+DB73)*0.99 -> 17763.501 | DC94: =(DC52+DC73)*0.99 -> 18269.873 | DD94: =(DD52+DD73)*0.99 -> 18453.777 | DE94: =(DE52+DE73)*0.99 -> 18772.564 | DF94: =(DF52+DF73)*0.99 -> 19014.897 | DG94: =(DG52+DG73)*0.99 -> 19123.774
C95: MS 2000/2250 | D95: 48 | BT95: =((+(298/$A$16)*0.3*BT$16+((298)*(1+BT$14)*0.7))*0.95)-5.05 -> 2491.6039 | BU95: =((+(298/$A$16)*0.3*BU$16+((298)*(1+BU$14)*0.7))*0.95)-5.05 -> 2547.8334 | BV95: =((+(298/$A$16)*0.3*BV$16+((298)*(1+BV$14)*0.7))*0.95) -> 2599.6437 | BW95: =((+(298/$A$16)*0.3*BW$16+((298)*(1+BW$14)*0.7))*0.95) -> 2668.3199 | BX95: =((+(298/$A$16)*0.3*BX$16+((298)*(1+BX$14)*0.7))*0.95) -> 2736.5567 | BY95: =((+(298/$A$16)*0.3*BY$16+((298)*(1+BY$14)*0.7))*0.95) -> 2810.0163 | BZ95: =((+(298/$A$16)*0.3*BZ$16+((298)*(1+BZ$14)*0.7))*0.95) -> 3608.0975 | CA95: =((+(298/$A$16)*0.3*CA$16+((298)*(1+CA$14)*0.7))*0.95) -> 3697.1764 | CB95: =((+(298/$A$16)*0.3*CB$16+((298)*(1+CB$14)*0.7))*0.95) -> 4058.1289 | CC95: =((+(298/$A$16)*0.3*CC$16+((298)*(1+CC$14)*0.7))*0.95) -> 4057.6408 | ... CL95: =((+(298/$A$16)*0.3*CL$16+((298)*(1+CL$14)*0.7))*0.95) -> 12680.798 | CM95: 12922.55 | CO95: =((+($CM95/$CM$16)*0.3*CO$16+(($CM95)*(1+CO$14)*0.7))) -> 13262.87 | CP95: =((+($CO95/$CO$16)*0.3*CP$16+(($CO95)*(1+CP$14)*0.7))) -> 13544.996 | CQ95: =((+($CP95/$CP$16)*0.3*CQ$16+(($CP95)*(1+CQ$14)*0.7))) -> 13956.351 | CR95: =((+($CQ95/$CQ$16)*0.3*CR$16+(($CQ95)*(1+CR$14)*0.7))) -> 14273.286 | CS95: =((+(CR95/CR$16)*0.3*CS$16+((CR95)*(1+CS$14)*0.7))) -> 14578.211 | CT95: =((+(CS95/CS$16)*0.3*CT$16+((CS95)*(1+CT$14)*0.7))) -> 14792.176 | CU95: =((+(CT95/CT$16)*0.3*CU$16+((CT95)*(1+CU$14)*0.7))) -> 15035.11 | CV95: =((+(CU95/CU$16)*0.3*CV$16+((CU95)*(1+CV$14)*0.7))) -> 15231.183 | CW95: 15231.183 | CX95: 15231.183 | CY95: =CY53+CY74 -> 16424.828 | CZ95: =CZ53+CZ74 -> 17227.802 | DA95: =DA53+DA74 -> 17410.361 | DB95: =(DB53+DB74)*0.99 -> 17763.501 | DC95: =(DC53+DC74)*0.99 -> 18269.873 | DD95: =(DD53+DD74)*0.99 -> 18453.777 | DE95: =(DE53+DE74)*0.99 -> 18772.564 | DF95: =(DF53+DF74)*0.99 -> 19014.897 | DG95: =(DG53+DG74)*0.99 -> 19123.774
C96: MS 2000/2250 | D96: 49.6 | BT96: =((+(298/$A$16)*0.3*BT$16+((298)*(1+BT$14)*0.7))*0.95)-5.05 -> 2491.6039 | BU96: =((+(298/$A$16)*0.3*BU$16+((298)*(1+BU$14)*0.7))*0.95)-5.05 -> 2547.8334 | BV96: =(((+(298/$A$16)*0.3*BV$16+((298)*(1+BV$14)*0.7))*0.95))*0 -> 0 | BW96: =(((+(298/$A$16)*0.3*BW$16+((298)*(1+BW$14)*0.7))*0.95))*0 -> 0 | BX96: =(((+(298/$A$16)*0.3*BX$16+((298)*(1+BX$14)*0.7))*0.95))*0 -> 0 | BY96: =(((+(298/$A$16)*0.3*BY$16+((298)*(1+BY$14)*0.7))*0.95))*0 -> 0 | BZ96: =(((+(298/$A$16)*0.3*BZ$16+((298)*(1+BZ$14)*0.7))*0.95))*0 -> 0 | CA96: =(((+(298/$A$16)*0.3*CA$16+((298)*(1+CA$14)*0.7))*0.95))*0 -> 0 | CB96: =(((+(298/$A$16)*0.3*CB$16+((298)*(1+CB$14)*0.7))*0.95))*0 -> 0 | CC96: =(((+(298/$A$16)*0.3*CC$16+((298)*(1+CC$14)*0.7))*0.95))*0 -> 0 | ... CL96: =(((+(298/$A$16)*0.3*CL$16+((298)*(1+CL$14)*0.7))*0.95))*0 -> 0 | CM96: 0 | CO96: =((+($CM96/$CM$16)*0.3*CO$16+(($CM96)*(1+CO$14)*0.7))) -> 0 | CP96: =((+($CO96/$CO$16)*0.3*CP$16+(($CO96)*(1+CP$14)*0.7))) -> 0 | CQ96: =((+($CP96/$CP$16)*0.3*CQ$16+(($CP96)*(1+CQ$14)*0.7))) -> 0 | CR96: =((+($CQ96/$CQ$16)*0.3*CR$16+(($CQ96)*(1+CR$14)*0.7))) -> 0 | CS96: =((+(CR96/CR$16)*0.3*CS$16+((CR96)*(1+CS$14)*0.7))) -> 0 | CT96: =((+(CS96/CS$16)*0.3*CT$16+((CS96)*(1+CT$14)*0.7))) -> 0 | CU96: =((+(CT96/CT$16)*0.3*CU$16+((CT96)*(1+CU$14)*0.7))) -> 0 | CV96: =((+(CU96/CU$16)*0.3*CV$16+((CU96)*(1+CV$14)*0.7))) -> 0 | CW96: 0 | CX96: 0 | CY96: =CX96 -> 0 | CZ96: =CY96 -> 0 | DA96: =CZ96 -> 0 | DB96: =(DB54+DB75)*0.99 -> 0 | DC96: =(DC54+DC75)*0.99 -> 0 | DD96: =(DD54+DD75)*0.99 -> 0 | DE96: =(DE54+DE75)*0.99 -> 0 | DF96: =(DF54+DF75)*0.99 -> 0 | DG96: =(DG54+DG75)*0.99 -> 0
C97: MS 2000/2250 | D97: 52 | BT97: =((+(298/$A$16)*0.3*BT$16+((298)*(1+BT$14)*0.7))*0.95)-5.05 -> 2491.6039 | BU97: =((+(298/$A$16)*0.3*BU$16+((298)*(1+BU$14)*0.7))*0.95)-5.05 -> 2547.8334 | BV97: =((+(298/$A$16)*0.3*BV$16+((298)*(1+BV$14)*0.7))*0.95) -> 2599.6437 | BW97: =((+(298/$A$16)*0.3*BW$16+((298)*(1+BW$14)*0.7))*0.95) -> 2668.3199 | BX97: =((+(298/$A$16)*0.3*BX$16+((298)*(1+BX$14)*0.7))*0.95) -> 2736.5567 | BY97: =((+(298/$A$16)*0.3*BY$16+((298)*(1+BY$14)*0.7))*0.95) -> 2810.0163 | BZ97: =((+(298/$A$16)*0.3*BZ$16+((298)*(1+BZ$14)*0.7))*0.95) -> 3608.0975 | CA97: =((+(298/$A$16)*0.3*CA$16+((298)*(1+CA$14)*0.7))*0.95) -> 3697.1764 | CB97: =((+(298/$A$16)*0.3*CB$16+((298)*(1+CB$14)*0.7))*0.95) -> 4058.1289 | CC97: =((+(298/$A$16)*0.3*CC$16+((298)*(1+CC$14)*0.7))*0.95) -> 4057.6408 | ... CL97: =((+(298/$A$16)*0.3*CL$16+((298)*(1+CL$14)*0.7))*0.95) -> 12680.798 | CM97: 12922.55 | CO97: =((+($CM97/$CM$16)*0.3*CO$16+(($CM97)*(1+CO$14)*0.7))) -> 13262.87 | CP97: =((+($CO97/$CO$16)*0.3*CP$16+(($CO97)*(1+CP$14)*0.7))) -> 13544.996 | CQ97: =((+($CP97/$CP$16)*0.3*CQ$16+(($CP97)*(1+CQ$14)*0.7))) -> 13956.351 | CR97: =((+($CQ97/$CQ$16)*0.3*CR$16+(($CQ97)*(1+CR$14)*0.7))) -> 14273.286 | CS97: =((+(CR97/CR$16)*0.3*CS$16+((CR97)*(1+CS$14)*0.7))) -> 14578.211 | CT97: =((+(CS97/CS$16)*0.3*CT$16+((CS97)*(1+CT$14)*0.7))) -> 14792.176 | CU97: =((+(CT97/CT$16)*0.3*CU$16+((CT97)*(1+CU$14)*0.7))) -> 15035.11 | CV97: =((+(CU97/CU$16)*0.3*CV$16+((CU97)*(1+CV$14)*0.7))) -> 15231.183 | CW97: 15231.183 | CX97: 15231.183 | CY97: =CY55+CY76 -> 16424.828 | CZ97: =CZ55+CZ76 -> 17227.802 | DA97: =DA55+DA76 -> 17410.361 | DB97: =(DB55+DB76)*0.99 -> 17763.501 | DC97: =(DC55+DC76)*0.99 -> 18269.873 | DD97: =(DD55+DD76)*0.99 -> 18453.777 | DE97: =(DE55+DE76)*0.99 -> 18772.564 | DF97: =(DF55+DF76)*0.99 -> 19014.897 | DG97: =(DG55+DG76)*0.99 -> 19123.774
C98: MS 3000 | D98: 54.7 | BT98: =((+(306/$A$16)*0.3*BT$16+((306)*(1+BT$14)*0.7))*0.95)-5.05 -> 2558.6282 | BU98: =((+(306/$A$16)*0.3*BU$16+((306)*(1+BU$14)*0.7))*0.95)-5.05 -> 2616.3672 | BV98: =((+(306/$A$16)*0.3*BV$16+((306)*(1+BV$14)*0.7))*0.95) -> 2669.4328 | BW98: =((+(306/$A$16)*0.3*BW$16+((306)*(1+BW$14)*0.7))*0.95) -> 2739.9526 | BX98: =((+(306/$A$16)*0.3*BX$16+((306)*(1+BX$14)*0.7))*0.95) -> 2810.0214 | BY98: =((+(306/$A$16)*0.3*BY$16+((306)*(1+BY$14)*0.7))*0.95) -> 2885.453 | BZ98: =((+(306/$A$16)*0.3*BZ$16+((306)*(1+BZ$14)*0.7))*0.95) -> 3704.9592 | CA98: =((+(306/$A$16)*0.3*CA$16+((306)*(1+CA$14)*0.7))*0.95) -> 3796.4295 | CB98: =((+(306/$A$16)*0.3*CB$16+((306)*(1+CB$14)*0.7))*0.95) -> 4167.072 | CC98: =((+(306/$A$16)*0.3*CC$16+((306)*(1+CC$14)*0.7))*0.95) -> 4166.5708 | ... CL98: =((+(306/$A$16)*0.3*CL$16+((306)*(1+CL$14)*0.7))*0.95) -> 13021.222 | CM98: 13269.464 | CO98: =((+($CM98/$CM$16)*0.3*CO$16+(($CM98)*(1+CO$14)*0.7))) -> 13618.92 | CP98: =((+($CO98/$CO$16)*0.3*CP$16+(($CO98)*(1+CP$14)*0.7))) -> 13908.62 | CQ98: =((+($CP98/$CP$16)*0.3*CQ$16+(($CP98)*(1+CQ$14)*0.7))) -> 14331.018 | CR98: =((+($CQ98/$CQ$16)*0.3*CR$16+(($CQ98)*(1+CR$14)*0.7))) -> 14656.461 | CS98: =((+(CR98/CR$16)*0.3*CS$16+((CR98)*(1+CS$14)*0.7))) -> 14969.573 | CT98: =((+(CS98/CS$16)*0.3*CT$16+((CS98)*(1+CT$14)*0.7))) -> 15189.281 | CU98: =((+(CT98/CT$16)*0.3*CU$16+((CT98)*(1+CU$14)*0.7))) -> 15438.738 | CV98: =((+(CU98/CU$16)*0.3*CV$16+((CU98)*(1+CV$14)*0.7))) -> 15640.073 | CW98: 15640.073 | CX98: 15640.073 | CY98: =CY56+CY77 -> 16865.763 | CZ98: =CZ56+CZ77 -> 17690.293 | DA98: =DA56+DA77 -> 17877.753 | DB98: =(DB56+DB77)*0.99 -> 18240.374 | DC98: =(DC56+DC77)*0.99 -> 18760.339 | DD98: =(DD56+DD77)*0.99 -> 18949.18 | DE98: =(DE56+DE77)*0.99 -> 19276.526 | DF98: =(DF56+DF77)*0.99 -> 19525.364 | DG98: =(DG56+DG77)*0.99 -> 19637.164
C99: MS 3000 | D99: 58 | BT99: =((+(306/$A$16)*0.3*BT$16+((306)*(1+BT$14)*0.7))*0.95)-5.05 -> 2558.6282 | BU99: =((+(306/$A$16)*0.3*BU$16+((306)*(1+BU$14)*0.7))*0.95)-5.05 -> 2616.3672 | BV99: =(((+(306/$A$16)*0.3*BV$16+((306)*(1+BV$14)*0.7))*0.95))*0 -> 0 | BW99: =(((+(306/$A$16)*0.3*BW$16+((306)*(1+BW$14)*0.7))*0.95))*0 -> 0 | BX99: =(((+(306/$A$16)*0.3*BX$16+((306)*(1+BX$14)*0.7))*0.95))*0 -> 0 | BY99: =(((+(306/$A$16)*0.3*BY$16+((306)*(1+BY$14)*0.7))*0.95))*0 -> 0 | BZ99: =(((+(306/$A$16)*0.3*BZ$16+((306)*(1+BZ$14)*0.7))*0.95))*0 -> 0 | CA99: =(((+(306/$A$16)*0.3*CA$16+((306)*(1+CA$14)*0.7))*0.95))*0 -> 0 | CB99: =(((+(306/$A$16)*0.3*CB$16+((306)*(1+CB$14)*0.7))*0.95))*0 -> 0 | CC99: =(((+(306/$A$16)*0.3*CC$16+((306)*(1+CC$14)*0.7))*0.95))*0 -> 0 | ... CL99: =(((+(306/$A$16)*0.3*CL$16+((306)*(1+CL$14)*0.7))*0.95))*0 -> 0 | CM99: 0 | CO99: =((+($CM99/$CM$16)*0.3*CO$16+(($CM99)*(1+CO$14)*0.7))) -> 0 | CP99: =((+($CO99/$CO$16)*0.3*CP$16+(($CO99)*(1+CP$14)*0.7))) -> 0 | CQ99: =((+($CP99/$CP$16)*0.3*CQ$16+(($CP99)*(1+CQ$14)*0.7))) -> 0 | CR99: =((+($CQ99/$CQ$16)*0.3*CR$16+(($CQ99)*(1+CR$14)*0.7))) -> 0 | CS99: =((+(CR99/CR$16)*0.3*CS$16+((CR99)*(1+CS$14)*0.7))) -> 0 | CT99: =((+(CS99/CS$16)*0.3*CT$16+((CS99)*(1+CT$14)*0.7))) -> 0 | CU99: =((+(CT99/CT$16)*0.3*CU$16+((CT99)*(1+CU$14)*0.7))) -> 0 | CV99: =((+(CU99/CU$16)*0.3*CV$16+((CU99)*(1+CV$14)*0.7))) -> 0 | CW99: 0 | CX99: 0 | CY99: =CX99 -> 0 | CZ99: =CY99 -> 0 | DA99: =CZ99 -> 0 | DB99: =(DB57+DB78)*0.99 -> 0 | DC99: =(DC57+DC78)*0.99 -> 0 | DD99: =(DD57+DD78)*0.99 -> 0 | DE99: =(DE57+DE78)*0.99 -> 0 | DF99: =(DF57+DF78)*0.99 -> 0 | DG99: =(DG57+DG78)*0.99 -> 0
C100: MS 3000 | D100: 62 | BT100: =((+(306/$A$16)*0.3*BT$16+((306)*(1+BT$14)*0.7))*0.95)-5.05 -> 2558.6282 | BU100: =((+(306/$A$16)*0.3*BU$16+((306)*(1+BU$14)*0.7))*0.95)-5.05 -> 2616.3672 | BV100: =((+(306/$A$16)*0.3*BV$16+((306)*(1+BV$14)*0.7))*0.95) -> 2669.4328 | BW100: =((+(306/$A$16)*0.3*BW$16+((306)*(1+BW$14)*0.7))*0.95) -> 2739.9526 | BX100: =((+(306/$A$16)*0.3*BX$16+((306)*(1+BX$14)*0.7))*0.95) -> 2810.0214 | BY100: =((+(306/$A$16)*0.3*BY$16+((306)*(1+BY$14)*0.7))*0.95) -> 2885.453 | BZ100: =((+(306/$A$16)*0.3*BZ$16+((306)*(1+BZ$14)*0.7))*0.95) -> 3704.9592 | CA100: =((+(306/$A$16)*0.3*CA$16+((306)*(1+CA$14)*0.7))*0.95) -> 3796.4295 | CB100: =((+(306/$A$16)*0.3*CB$16+((306)*(1+CB$14)*0.7))*0.95) -> 4167.072 | CC100: =((+(306/$A$16)*0.3*CC$16+((306)*(1+CC$14)*0.7))*0.95) -> 4166.5708 | ... CL100: =((+(306/$A$16)*0.3*CL$16+((306)*(1+CL$14)*0.7))*0.95) -> 13021.222 | CM100: 13269.464 | CO100: =((+($CM100/$CM$16)*0.3*CO$16+(($CM100)*(1+CO$14)*0.7))) -> 13618.92 | CP100: =((+($CO100/$CO$16)*0.3*CP$16+(($CO100)*(1+CP$14)*0.7))) -> 13908.62 | CQ100: =((+($CP100/$CP$16)*0.3*CQ$16+(($CP100)*(1+CQ$14)*0.7))) -> 14331.018 | CR100: =((+($CQ100/$CQ$16)*0.3*CR$16+(($CQ100)*(1+CR$14)*0.7))) -> 14656.461 | CS100: =((+(CR100/CR$16)*0.3*CS$16+((CR100)*(1+CS$14)*0.7))) -> 14969.573 | CT100: =((+(CS100/CS$16)*0.3*CT$16+((CS100)*(1+CT$14)*0.7))) -> 15189.281 | CU100: =((+(CT100/CT$16)*0.3*CU$16+((CT100)*(1+CU$14)*0.7))) -> 15438.738 | CV100: =((+(CU100/CU$16)*0.3*CV$16+((CU100)*(1+CV$14)*0.7))) -> 15640.073 | CW100: 15640.073 | CX100: 15640.073 | CY100: =CY58+CY79 -> 16865.763 | CZ100: =CZ58+CZ79 -> 17690.293 | DA100: =DA58+DA79 -> 17877.753 | DB100: =(DB58+DB79)*0.99 -> 18240.374 | DC100: =(DC58+DC79)*0.99 -> 18760.339 | DD100: =(DD58+DD79)*0.99 -> 18949.18 | DE100: =(DE58+DE79)*0.99 -> 19276.526 | DF100: =(DF58+DF79)*0.99 -> 19525.364 | DG100: =(DG58+DG79)*0.99 -> 19637.164
C102: Total ARS
C103: SS 250 | D103: 12.5 | BT103: =((+(169/$A$16)*0.3*BT$16+((169)*(1+BT$14)*0.7))*0.95)-5.05 -> 1410.8376 | BU103: =((+(169/$A$16)*0.3*BU$16+((169)*(1+BU$14)*0.7))*0.95)-5.05 -> 1442.7262 | BV103: =((+(169/$A$16)*0.3*BV$16+((169)*(1+BV$14)*0.7))*0.95)-5.05 -> 1469.2446 | BW103: =((+(169/$A$16)*0.3*BW$16+((169)*(1+BW$14)*0.7))*0.95)-5.05 -> 1508.1918 | BX103: =((+(169/$A$16)*0.3*BX$16+((169)*(1+BX$14)*0.7))*0.95)-5.05 -> 1546.8899 | BY103: =((+(169/$A$16)*0.3*BY$16+((169)*(1+BY$14)*0.7))*0.95)-5.05 -> 1588.5499 | BZ103: =((+(169/$A$16)*0.3*BZ$16+((169)*(1+BZ$14)*0.7))*0.95)-5.05 -> 2041.153 | CA103: =((+(169/$A$16)*0.3*CA$16+((169)*(1+CA$14)*0.7))*0.95)-5.05 -> 2091.6708 | ... CL103: =((+(169/$A$16)*0.3*CL$16+((169)*(1+CL$14)*0.7))*0.95)-5.05 -> 7186.409 | CM103: 7323.5101 | CO103: =((+(169/$A$16)*0.3*CO$16+((169)*(1+CO$14)*0.7))*0.95)-5.05 -> 2749.8122 | CP103: =((+(169/$A$16)*0.3*CP$16+((169)*(1+CP$14)*0.7))*0.95)-5.05 -> 2809.9238 | CQ103: =((+(169/$A$16)*0.3*CQ$16+((169)*(1+CQ$14)*0.7))*0.95)-5.05 -> 2873.6671 | CR103: =((+(169/$A$16)*0.3*CR$16+((169)*(1+CR$14)*0.7))*0.95)-5.05 -> 2914.3458 | CS103: =((+(169/$A$16)*0.3*CS$16+((169)*(1+CS$14)*0.7))*0.95)-5.05 -> 2976.0662 | CT103: =((+(169/$A$16)*0.3*CT$16+((169)*(1+CT$14)*0.7))*0.95)-5.05 -> 3028.4531 | CU103: =((+(169/$A$16)*0.3*CU$16+((169)*(1+CU$14)*0.7))*0.95)-5.05 -> 3056.1726 | CV103: =((+(169/$A$16)*0.3*CV$16+((169)*(1+CV$14)*0.7))*0.95)-5.05 -> 3087.3877 | ... DG103: =((+(169/$A$16)*0.3*DG$16+((169)*(1+DG$14)*0.7))*0.95)-5.05 -> 4005.8569
C104: SS 500 | D104: 19.5 | BT104: =BT83+BT20 -> 7160.0146 | BU104: =BU83+BU20 -> 7504.9331 | BV104: =BV83+BV20 -> 7745.8149 | BW104: =BW83+BW20 -> 8345.8901 | BX104: =BX83+BX20 -> 8856.1007 | BY104: =BY83+BY20 -> 9659.9872 | BZ104: =BZ83+BZ20 -> 10262.994 | CA104: =CA83+CA20 -> 10511.804 | ... CM104: =CM83+CM20 -> 37108.381 | CO104: =CO83+CO20 -> 43928.301 | CP104: =CP83+CP20 -> 32159.274 | CQ104: =CQ83+CQ20 -> 38270.687 | CR104: =CR83+CR20 -> 40582.35 | CS104: =CS83+CS20 -> 41911.778 | CT104: =CT83+CT20 -> 42414.578 | CU104: =CU83+CU20 -> 42323.896 | CV104: =CV83+CV20 -> 42439.547 | ... DG104: =DG83+DG20 -> 48764.347
C105: SS 500 - 19.5G PCR 100% | D105: 19.5 | BT105: =BT84+BT21 -> 0 | BU105: =BU84+BU21 -> 0 | BV105: =BV84+BV21 -> 0 | BW105: =BW84+BW21 -> 0 | BX105: =BX84+BX21 -> 0 | BY105: =BY84+BY21 -> 0 | BZ105: =BZ84+BZ21 -> 0 | CA105: =CA84+CA21 -> 0 | ... CM105: =CM84+CM21 -> 55364.726 | CO105: =CO84+CO21 -> 43928.301 | CP105: =CP84+CP21 -> 32159.274 | CQ105: =CQ84+CQ21 -> 38270.687 | CR105: =CR84+CR21 -> 40582.35 | CS105: =CS84+CS21 -> 41911.778 | CT105: =CT84+CT21 -> 42414.578 | CU105: =CU84+CU21 -> 42323.896 | CV105: =CV84+CV21 -> 42439.547 | ... DG105: =DG84+DG21 -> 48764.347
...

Sheet HF Pricing
C2: Month | F2: 42767 | G2: 42795 | H2: 42826 | I2: 42856 | J2: 42887 | K2: 42917 | L2: 42948 | M2: 42979 | N2: 43009 | O2: 43040 | P2: 43070 | Q2: 43101 | R2: 43132 | S2: 43160 | T2: 43191 | U2: 43221 | V2: 43252 | W2: 43282 | X2: 43313 | Y2: 43344 | Z2: 43374 | AA2: 43405 | AB2: 43435 | AC2: 43466 | AD2: 43497 | AE2: 43525 | AF2: 43556 | AG2: 43586 | AH2: 43617 | AI2: 43678 | AJ2: 43709 | AK2: 43739 | AL2: 43770 | AM2: 43800 | AN2: 43831 | AO2: 43862 | AP2: 43891 | AQ2: 43922 | AR2: 43952 | AS2: 43983 | AT2: 44013 | AU2: 44044 | AV2: 44075 | AW2: 44105 | AX2: 44136 | AY2: 44166 | AZ2: 44197 | BA2: 44228 | BB2: 44256 | BC2: 44287 | BD2: 44317 | BE2: 44348 | BF2: 44378 | BG2: 44409 | BH2: 44440 | BI2: 44470 | BJ2: 44501 | BK2: 44531 | BL2: 44562 | BM2: 44593 | BN2: 44621 | BO2: 44652 | BP2: 44682 | BQ2: 44713 | BR2: 44743 | BS2: 44774 | BT2: 44805 | BU2: 44835 | BV2: 44866 | BW2: 44896 | BX2: 44927 | BY2: =+'CSD Pricing'!BU2 -> 44958 | BZ2: =+'CSD Pricing'!BV2 -> 44986 | CA2: =+'CSD Pricing'!BW2 -> 45017 | CB2: =+'CSD Pricing'!BX2 -> 45047 | CC2: =+'CSD Pricing'!BY2 -> 45078 | CD2: =+'CSD Pricing'!BZ2 -> 45108 | CE2: =+'CSD Pricing'!CA2 -> 45139 | CF2: =+'CSD Pricing'!CB2 -> 45170 | ... CQ2: =+'CSD Pricing'!CM2 -> 45505 | CS2: =+'CSD Pricing'!CO2 -> 45536 | CT2: =+'CSD Pricing'!CP2 -> 45566 | CU2: =+'CSD Pricing'!CQ2 -> 45597 | CV2: =+'CSD Pricing'!CR2 -> 45627 | CW2: =+'CSD Pricing'!CS2 -> 45658 | CX2: =+'CSD Pricing'!CT2 -> 45689 | CY2: =+'CSD Pricing'!CU2 -> 45717 | CZ2: =+'CSD Pricing'!CV2 -> 45748 | ... DK2: =+'CSD Pricing'!DG2 -> 46082
C3: Resin Price Amcor | Q3: 1445.0614 | R3: 1487.4144 | S3: 1513.6095 | T3: 1536.8106 | U3: 1585.5181 | V3: 1637.1374 | W3: 1698.9092 | X3: 1768.6685 | Y3: 1819.1847 | Z3: 1823.8546 | AA3: 1823.8546 | AB3: 1842.4123 | AC3: 1829.8784 | AD3: 1757.3322 | AE3: 1705.8318 | AF3: 1705.8318 | AG3: 1705.8318 | AH3: 1705.8318 | AI3: 1346.1205 | AJ3: 1400.06 | AK3: 1297.6608 | AL3: 1271.7759 | AM3: 1239.2046 | AN3: 1208.1292 | AO3: 1214.1156 | AP3: 1233.5875 | AQ3: 1183.9712 | AR3: 1092.5178 | AS3: 986.23533 | AT3: 1004.0125 | AU3: 1014.7861 | AV3: 989.72232 | AW3: 974.90606 | AX3: 977.26889 | AY3: 973.65578 | AZ3: 982.08225 | BA3: 1065.781 | BB3: 1252.6158 | BC3: #N/A | BD3: #N/A | BE3: #N/A | BF3: #N/A | BG3: #N/A | BH3: 1645.1727 | BI3: 1653.8608 | BJ3: 1636.7191 | BK3: 1840.1348 | BL3: 1856.1105 | BM3: 1732.0039 | BN3: 1871.8103 | BO3: 2042.5757 | BP3: 2175.8064 | BQ3: 2311.8189 | BR3: 2365.2235 | BS3: 2367.2285 | BT3: 2118.2855 | BU3: 1926.0337 | BV3: 1863.8189 | BW3: 1779.7864 | BX3: 1676.9153 | BY3: 1660.9261 | BZ3: 1633.2382 | CA3: 1665.0544 | CB3: 1671.7262 | CC3: 1736.6669 | CD3: 1632.5163 | CE3: 1558.5062 | CF3: 1554.8878 | CG3: 1613.9385 | CH3: 1627.1221 | CI3: 1595.7007 | CJ3: 1827 | CK3: 1863 | CL3: 1863 | CM3: 1863 | CN3: 1863 | CO3: 1863 | CP3: 1863 | CQ3: 1863 | CS3: 1977 | CT3: ='Balance Resinas'!K19 -> 1617.7723 | CU3: ='Balance Resinas'!$K28 -> 1730.9967 | CV3: ='Balance Resinas'!$K37 -> 1699.1124 | CW3: ='Balance Resinas'!$K46 -> 1654.7809 | CX3: ='Balance Resinas'!$K55 -> 1615.9788 | CY3: ='Balance Resinas'!$K64 -> 1577.1935 | CZ3: ='Balance Resinas'!$K73 -> 1555.8388 | DA3: ='Balance Resinas'!$K82 -> 1484.8149 | DB3: ='Balance Resinas'!$K91 -> 1423.1806 | DC3: ='Balance Resinas'!$K100 -> 1391.4457 | DD3: ='Balance Resinas'!$K109 -> 1348.1355 | DE3: ='Balance Resinas'!$K118 -> 1373.3388 | DF3: ='Balance Resinas'!$K127 -> 1409.7608 | DG3: ='Balance Resinas'!$K136 -> 1412.0574 | DH3: ='Balance Resinas'!$K145 -> 1356.0204 | DI3: ='Balance Resinas'!$K154 -> 1325.7721 | DJ3: ='Balance Resinas'!$K163 -> 1308.6156 | DK3: ='Balance Resinas'!$K172 -> 1287.4315
C4: Resin Price Vinisa | AN4: 1163.1292 | AO4: 1169.1156 | AP4: 1188.5875 | AQ4: 1138.9712 | AR4: 1047.5178 | AS4: 941.23533 | AT4: 959.01251 | AU4: 997.71874 | AV4: 975.63904 | AW4: 962.60359 | AX4: 964.6782 | AY4: 961.37867 | AZ4: 968.78502 | BA4: 1042.4355 | BB4: 1205.698 | BC4: #N/A | BD4: #N/A | BE4: #N/A | BF4: #N/A | BG4: #N/A | BH4: 1539.3256 | BI4: 1546.9696 | BJ4: 1531.8851 | BK4: 1709.4992 | BL4: 1723.4033 | BM4: 1615.4271 | BN4: 1778.0951 | BO4: 1891.0531 | BP4: 2011.1218 | BQ4: 2149.0935 | BR4: 2199.5856 | BS4: 2198.47 | BT4: 1982.575 | BU4: 1794.7903 | BV4: 1740.6645 | BW4: 1667.6628 | BX4: 1577.1838 | BY4: 1562.9026 | BZ4: 1539.758 | CA4: 1567.7956 | CB4: 1573.6676 | CC4: 1630.5978 | CD4: 1539.2782 | CE4: 1474.177 | CF4: 1464.77 | CG4: 1518.15 | CH4: 1529.79 | CI4: 1502.06 | CJ4: 1800 | CK4: 1836 | CL4: 1836 | CM4: 1703 | CN4: 1530.0011 | CO4: 1530.0033 | CP4: 1529.9984 | CQ4: 1530 | CS4: 1835 | CT4: ='Balance Resinas'!G19 -> 1514.2571 | CU4: ='Balance Resinas'!$G28 -> 1581.679 | CV4: ='Balance Resinas'!$G37 -> 1581.679 | CW4: ='Balance Resinas'!$G46 -> 1575.1486 | CX4: ='Balance Resinas'!$G55 -> 1564.682 | CY4: ='Balance Resinas'!$G64 -> 1564.682 | CZ4: ='Balance Resinas'!$G73 -> 1506.6541 | DA4: ='Balance Resinas'!$G82 -> 1420.2929 | DB4: ='Balance Resinas'!$G91 -> 1406.076 | DC4: ='Balance Resinas'!$G100 -> 1347.8197 | DD4: ='Balance Resinas'!$G109 -> 1328.5336 | DE4: ='Balance Resinas'!$G118 -> 1334.3697 | DF4: ='Balance Resinas'!$G127 -> 1411.8683 | DG4: ='Balance Resinas'!$G136 -> 1415.0425 | DH4: ='Balance Resinas'!$G145 -> 1358.8205 | DI4: ='Balance Resinas'!$G154 -> 1324.1993 | DJ4: ='Balance Resinas'!$G163 -> 1293.8228 | DK4: ='Balance Resinas'!$G172 -> 1293.8228
C5: Resin PCR Amcor Price | CK5: 2450 | CL5: 2450 | CM5: 2450 | CN5: 2450 | CO5: 2450 | CP5: 2450 | CQ5: 2450 | CS5: =+CS3 -> 1977 | CT5: =CT3 -> 1617.7723 | CU5: =CU3 -> 1730.9967 | CV5: =CV3 -> 1699.1124 | CW5: =CW3 -> 1654.7809 | CX5: =CX3 -> 1615.9788 | CY5: =CY3 -> 1577.1935 | CZ5: =CZ3 -> 1555.8388 | DA5: =DA3 -> 1484.8149 | ... DK5: =DK3 -> 1287.4315
C6: Scrap % | Q6: 0.005 | R6: 0.005 | S6: 0.005 | T6: 0.005 | U6: 0.005 | V6: 0.005 | W6: 0.005 | X6: 0.005 | Y6: 0.005 | Z6: 0.005 | AA6: 0.005 | AB6: 0.005 | AC6: 0.005 | AD6: 0.005 | AE6: 0.005 | AF6: 0.005 | AG6: 0.005 | AH6: 0.005 | AI6: 0.005 | AJ6: 0.005 | AK6: 0.005 | AL6: 0.005 | AM6: 0.005 | AN6: 0.005 | AO6: 0.005 | AP6: 0.005 | AQ6: 0.005 | AR6: 0.005 | AS6: 0.005 | AT6: 0.005 | AU6: 0.005 | AV6: 0.005 | AW6: 0.005 | AX6: 0.005 | AY6: 0.005 | AZ6: 0.005 | BA6: 0.005 | BB6: 0.005 | BC6: 0.005 | BD6: 0.005 | BE6: 0.005 | BF6: 0.005 | BG6: 0.005 | BH6: 0.005 | BI6: 0.005 | BJ6: 0.005 | BK6: 0.005 | BL6: 0.005 | BM6: 0.005 | BN6: 0.005 | BO6: 0.005 | BP6: 0.005 | BQ6: 0.005 | BR6: 0.005 | BS6: 0.005 | BT6: 0.005 | BU6: 0.005 | BV6: 0.005 | BW6: 0.005 | BX6: 0.005 | BY6: 0.005 | BZ6: 0.005 | CA6: 0.005 | CB6: 0.005 | CC6: 0.005 | CD6: 0.005 | CE6: 0.005 | CF6: 0.005 | CG6: 0.005 | CH6: 0.005 | CI6: 0.005 | CJ6: 0.005 | CK6: 0.005 | CL6: 0.005 | CM6: 0.005 | CN6: 0.005 | CO6: 0.005 | CP6: 0.005 | CQ6: 0.005 | CS6: 0.005 | CT6: 0.005 | CU6: 0.005 | CV6: 0.005 | CW6: 0.005 | CX6: 0.005 | CY6: 0.005 | CZ6: 0.005 | DA6: 0.005 | DB6: 0.005 | DC6: 0.005 | DD6: 0.005 | DE6: 0.005 | DF6: 0.005 | DG6: 0.005 | DH6: 0.005 | DI6: 0.005 | DJ6: 0.005 | DK6: 0.005
C7: Tax | CV7: 0.0525 | CW7: 0.0525 | CX7: 0.0525 | CY7: 0.0525 | CZ7: 0.0525 | DA7: 0.0525 | DB7: 0.0525 | DC7: 0.0525 | DD7: 0.0525 | DE7: 0.0525 | DF7: 0.0525 | DG7: 0.0525 | DH7: 0.0525 | DI7: 0.0525 | DJ7: 0.0525 | DK7: 0.0525
C8: IPC C.A.B.A./ Nuevo contrato IPC INDEC | F8: 0.022 | G8: 0.029 | H8: 0.021 | I8: 0.018 | J8: 0.015 | K8: 0.018 | L8: 0.016 | M8: 0.016 | N8: 0.015 | O8: 0.013 | P8: 0.033 | Q8: 0.016 | R8: 0.026 | S8: 0.021 | T8: 0.03 | U8: 0.023 | V8: 0.037 | W8: 0.027 | X8: 0.037 | Y8: 0.06 | Z8: 0.053 | AA8: 0.028 | AB8: 0.024 | AC8: 0.038 | AD8: 0.034 | AE8: 0.04 | AF8: 0.037 | AG8: 0.031 | AH8: 0.028 | AI8: 0.022 | AJ8: 0.034 | AK8: 0.05 | AL8: 0.028 | AM8: 0.04 | AN8: 0.035 | AO8: 0.024 | AP8: 0.018 | AQ8: 0.027 | AR8: 0.02 | AS8: 0.01 | AT8: 0.014 | AU8: 0.016 | AV8: 0.024 | AW8: 0.022 | AX8: 0.025 | AY8: 0.031 | AZ8: 0.038 | BA8: 0.038 | BB8: 0.029 | BC8: 0.039 | BD8: 0.04 | BE8: 0.036 | BF8: 0.032 | BG8: 0.029 | BH8: 0.029 | BI8: 0.034 | BJ8: 0.037 | BK8: 0.025 | BL8: 0.038 | BM8: 0.04 | BN8: 0.041 | BO8: 0.059 | BP8: 0.053 | BQ8: 0.055 | BR8: 0.051 | BS8: 0.077 | BT8: 0.062 | BU8: 0.056 | BV8: 0.07 | BW8: 0.058 | BX8: 0.058 | BY8: =+'CSD Pricing'!BU9 -> 0.073 | BZ8: =+'CSD Pricing'!BV9 -> 0.06 | CA8: =+'CSD Pricing'!BW9 -> 0.071 | CB8: =+'CSD Pricing'!BX9 -> 0.078 | CC8: =+'CSD Pricing'!BY9 -> 0.075 | CD8: =+'CSD Pricing'!BZ9 -> 0.071 | CE8: =+'CSD Pricing'!CA9 -> 0.073 | CF8: =+'CSD Pricing'!CB9 -> 0.108 | ... CQ8: =+'CSD Pricing'!CM9 -> 0.051 | CS8: =+'CSD Pricing'!CO9 -> 0.042 | CT8: =+'CSD Pricing'!CP9 -> 0.04 | CU8: =+'CSD Pricing'!CQ9 -> 0.032 | CV8: =+'CSD Pricing'!CR9 -> 0.032 | CW8: =+'CSD Pricing'!CS9 -> 0.033 | CX8: =+'CSD Pricing'!CT9 -> 0.031 | CY8: =+'CSD Pricing'!CU9 -> 0.021 | CZ8: =+'CSD Pricing'!CV9 -> 0.032 | ... DJ8: =+'CSD Pricing'!DF9 -> 0.031
C9: IPP Caucho | F9: 0.021 | G9: 0.009 | H9: 0.012 | I9: 0.014 | J9: 0.002 | K9: 0.018 | L9: 0.018 | M9: 0.014 | N9: 0.009 | O9: 0.008 | P9: 0.019 | Q9: 0.025 | R9: 0.04 | S9: 0.024 | T9: 0.016 | U9: 0.097 | V9: 0.078488053 | W9: 0.041 | X9: 0.041 | Y9: 0.181 | Z9: 0.028 | AA9: 0.006 | AB9: 0.032 | AC9: 0.013 | AD9: 0.027 | AE9: 0.026 | AF9: 0.052 | AG9: 0.04 | AH9: 0.011 | AI9: 0.006 | AJ9: 0.135 | AK9: 0.067 | AL9: 0.045 | AM9: 0.043 | AN9: 0.019 | AO9: 0.017 | AP9: 0.011 | AQ9: 0.014 | AR9: 0.011 | AS9: 0.049 | AT9: 0.025 | AU9: 0.046 | AV9: 0.03 | AW9: 0.04 | AX9: 0.049 | AY9: 0.07 | AZ9: 0.034 | BA9: 0.068 | BB9: 0.065 | BC9: 0.056 | BD9: 0.067 | BE9: 0.041 | BF9: 0.034 | BG9: 0.036 | BH9: 0.027 | BI9: 0.018 | BJ9: 0.029 | BK9: 0.044 | BL9: 0.027 | BM9: 0.031 | BN9: 0.04 | BO9: 0.051 | BP9: 0.046 | BQ9: 0.054 | BR9: 0.046 | BS9: 0.094 | BT9: 0.064 | BU9: 0.061 | BV9: 0.07 | BW9: 0.057 | BX9: 0.061 | BY9: =+'CSD Pricing'!BU10 -> 0.064 | BZ9: =+'CSD Pricing'!BV10 -> 0.062 | CA9: =+'CSD Pricing'!BW10 -> 0.063 | CB9: =+'CSD Pricing'!BX10 -> 0.069 | CC9: =+'CSD Pricing'!BY10 -> 0.081 | CD9: =+'CSD Pricing'!BZ10 -> 0.071 | CE9: =+'CSD Pricing'!CA10 -> 0.072 | CF9: =+'CSD Pricing'!CB10 -> 0.17 | ... CQ9: =+'CSD Pricing'!CM10 -> 0.004 | CS9: =+'CSD Pricing'!CO10 -> -0.001 | CT9: =+'CSD Pricing'!CP10 -> 0.027 | CU9: =+'CSD Pricing'!CQ10 -> 0.02 | CV9: =+'CSD Pricing'!CR10 -> 0.01 | CW9: =+'CSD Pricing'!CS10 -> -0.007 | CX9: =+'CSD Pricing'!CT10 -> 0.008 | CY9: =+'CSD Pricing'!CU10 -> 0.007 | CZ9: =+'CSD Pricing'!CV10 -> 0.005 | ... DJ9: =+'CSD Pricing'!DF10 -> 0.012
C10: Monthly inflation | AE10: 0.033 | AF10: 0.0445 | AG10: 0.0355 | AH10: 0.0195 | AI10: 0.014 | AJ10: 0.0845 | AK10: 0.0585 | AL10: 0.0365 | AM10: 0.0415 | AN10: 0.027 | AO10: 0.0205 | AP10: 0.0145 | AQ10: 0.0205 | AR10: 0.0155 | AS10: 0.0295 | AT10: 0.0195 | AU10: 0.031 | AV10: 0.027 | AW10: 0.031 | AX10: 0.037 | AY10: 0.0505 | AZ10: 0.036 | BA10: 0.053 | BB10: 0.047 | BC10: 0.0475 | BD10: 0.0535 | BE10: 0.0385 | BF10: 0.033 | BG10: 0.0325 | BH10: 0.028 | BI10: 0.026 | BJ10: 0.033 | BK10: 0.0345 | BL10: 0.0325 | BM10: 0.0355 | BN10: 0.0405 | BO10: 0.055 | BP10: 0.0495 | BQ10: 0.0545 | BR10: 0.0485 | BS10: 0.0855 | BT10: 0.063 | BU10: 0.0585 | BV10: 0.07 | BW10: 0.0575 | BX10: 0.0595 | BY10: =+(+BY8+BY9)/2 -> 0.0685 | BZ10: =+(+BZ8+BZ9)/2 -> 0.061 | CA10: =+(+CA8+CA9)/2 -> 0.067 | CB10: =+(+CB8+CB9)/2 -> 0.0735 | CC10: =+(+CC8+CC9)/2 -> 0.078 | CD10: =+(+CD8+CD9)/2 -> 0.071 | CE10: =+(+CE8+CE9)/2 -> 0.0725 | CF10: =+(+CF8+CF9)/2 -> 0.139 | ... CQ10: =+(+CQ8+CQ9)/2 -> 0.0275 | CS10: =+(+CS8+CS9)/2 -> 0.0205 | CT10: =+(+CT8+CT9)/2 -> 0.0335 | CU10: =+(+CU8+CU9)/2 -> 0.026 | CV10: =+(+CV8+CV9)/2 -> 0.021 | CW10: =+(+CW8+CW9)/2 -> 0.013 | CX10: =+(+CX8+CX9)/2 -> 0.0195 | CY10: =+(+CY8+CY9)/2 -> 0.014 | CZ10: =+(+CZ8+CZ9)/2 -> 0.0185 | ... DJ10: =+(+DJ8+DJ9)/2 -> 0.0215
C11: Efficiency Gain Inf. % | R11: 0.23356907 | S11: 0.23356907 | T11: 0 | U11: 0 | V11: 0 | W11: 0 | X11: 0.41450683 | Y11: 0 | Z11: 0 | AA11: 0 | AB11: 0 | AC11: 0 | AD11: 0.62297996 | AE11: 0 | AF11: 0 | AG11: 0 | AH11: 0 | AI11: 0 | AJ11: 0.61348631 | AK11: 0 | AL11: 0 | AM11: 0 | AN11: 0 | AO11: 0 | AP11: 0.52183847 | AQ11: 0 | AR11: 0 | AS11: 0 | AT11: 0 | AU11: 0 | AV11: 0.39923472 | AW11: 0 | AX11: 0 | AY11: 0 | AZ11: 0 | BA11: 0 | BB11: 0.47741979 | BC11: 0 | BD11: 0 | BE11: 0 | BF11: 0 | BG11: 0 | BH11: 0 | BI11: 0 | BJ11: 0 | BK11: 0.59792767 | BL11: 0 | BM11: 0 | BN11: 0 | BO11: 0 | BP11: 0 | BQ11: 0.53774855 | BR11: 0 | BS11: 0 | BT11: 0 | BU11: 0 | BV11: 0 | BW11: 0.84119759 | BX11: 0 | BY11: 0 | BZ11: 0 | CA11: 0 | CB11: 0 | CC11: =(1+BR10)*(1+BS10)*(1+BT10)*(1+BU10)*(1+BV10)*(1+BW10)*(1+BX10)*(1+BY10)*(1+BZ10)*(1+CA10)*(1+CB10)*(1+BQ10)-1 -> 1.1022796 | CD11: 0 | CE11: 0 | CF11: 0 | CG11: 0 | CH11: 0 | CI11: =(1+BX10)*(1+BY10)*(1+BZ10)*(1+CA10)*(1+CB10)*(1+CC10)*(1+CD10)*(1+CE10)*(1+CF10)*(1+CG10)*(1+CH10)*(1+BW10)-1 -> 1.4826554 | CJ11: =+(1+CI10)*1 -> 1.115 | CK11: =+(1+CJ10)*1 -> 1.447 | CL11: =+(1+CK10)*1 -> 1.1695 | CM11: =+(1+CL10)*1 -> 1.159 | CN11: =+(1+CM10)*1 -> 1.082 | CO11: =+(1+CN10)*1 -> 1.0565 | CP11: =+(1+CO10)*1 -> 1.023 | CQ11: =+(1+CP10)*1 -> 1.022 | CS11: =+(1+CQ10)*1 -> 1.0275 | CT11: =+(1+CS10)*1 -> 1.0205 | CU11: =+(1+CT10)*1 -> 1.0335 | CV11: =+(1+CU10)*1 -> 1.026 | CW11: =+(1+CV10)*1 -> 1.021 | CX11: =+(1+CW10)*1 -> 1.013 | CY11: =+(1+CX10)*1 -> 1.0195 | CZ11: =+(1+CY10)*1 -> 1.014 | DA11: =+(1+CZ10)*1 -> 1.0185 | ... DJ11: =+(1+DI10)*1 -> 1.0185
C12: Efficiency Gain % | R12: 0.1 | S12: 0.1 | T12: 0 | U12: 0 | V12: 0 | W12: 0 | X12: 0.1 | Y12: 0 | Z12: 0 | AA12: 0 | AB12: 0 | AC12: 0 | AD12: 0.1 | AE12: 0 | AF12: 0 | AG12: 0 | AH12: 0 | AI12: 0 | AJ12: 0.1 | AK12: 0 | AL12: 0 | AM12: 0 | AN12: 0 | AO12: 0 | AP12: 0.1 | AQ12: 0 | AR12: 0 | AS12: 0 | AT12: 0 | AU12: 0 | AV12: 0.1 | AW12: 0 | AX12: 0 | AY12: 0 | AZ12: 0 | BA12: 0 | BB12: 0.1 | BC12: 0 | BD12: 0 | BE12: 0 | BF12: 0 | BG12: 0 | BH12: 0 | BI12: 0 | BJ12: 0 | BK12: 0.1 | BL12: 0 | BM12: 0 | BN12: 0 | BO12: 0 | BP12: 0 | BQ12: 0.1 | BR12: 0 | BS12: 0 | BT12: 0 | BU12: 0 | BV12: 0 | BW12: 0.1 | BX12: 0 | BY12: =+IF(BY11=0,0,IF(BY11<=10%,50%,IF(BY11<=20%,15%,10%))) -> 0 | BZ12: =+IF(BZ11=0,0,IF(BZ11<=10%,50%,IF(BZ11<=20%,15%,10%))) -> 0 | CA12: =+IF(CA11=0,0,IF(CA11<=10%,50%,IF(CA11<=20%,15%,10%))) -> 0 | CB12: =+IF(CB11=0,0,IF(CB11<=10%,50%,IF(CB11<=20%,15%,10%))) -> 0 | CC12: =+IF(CC11=0,0,IF(CC11<=10%,50%,IF(CC11<=20%,15%,10%))) -> 0.1 | CD12: =+IF(CD11=0,0,IF(CD11<=10%,50%,IF(CD11<=20%,15%,10%))) -> 0 | CE12: =+IF(CE11=0,0,IF(CE11<=10%,50%,IF(CE11<=20%,15%,10%))) -> 0 | CF12: =+IF(CF11=0,0,IF(CF11<=10%,50%,IF(CF11<=20%,15%,10%))) -> 0 | ... CP12: =+IF(CP11=0,0,IF(CP11<=10%,50%,IF(CP11<=20%,15%,10%))) -> 0.1
C13: % Ajuste Semestral | Q13: 1 | R13: 1.1103831 | S13: 1.1103831 | T13: 1 | U13: 1 | V13: 1 | W13: 1 | X13: 1.2339763 | Y13: 1 | Z13: 1 | AA13: 1 | AB13: 1 | AC13: 1 | AD13: 1.2592956 | AE13: 1 | AF13: 1 | AG13: 1 | AH13: 1 | AI13: 1 | AJ13: 1.2273431 | AK13: 1 | AL13: 1 | AM13: 1 | AN13: 1 | AO13: 1 | AP13: 1.1934463 | AQ13: 1 | AR13: 1 | AS13: 1 | AT13: 1 | AU13: 1 | AV13: 1.1365211 | AW13: 1 | AX13: 1 | AY13: 1 | AZ13: 1 | BA13: 1 | BB13: 1.2545448 | BC13: 1 | BD13: 1 | BE13: 1 | BF13: 1 | BG13: 1 | BH13: 1 | BI13: 1 | BJ13: 1 | BK13: 1.339936 | BL13: 1 | BM13: 1 | BN13: 1 | BO13: 1 | BP13: 1 | BQ13: 1.2689777 | BR13: 1 | BS13: 1 | BT13: 1 | BU13: 1 | BV13: 1 | BW13: 1.4041545 | BX13: 1 | BY13: =IF(BY12=0,1,1+(((1+BS10)*(1+BT10)*(1+BU10)*(1+BV10)*(1+BW10)*(1+BX10)-1)*(1-BY12))) -> 1 | BZ13: =IF(BZ12=0,1,1+(((1+BT10)*(1+BU10)*(1+BV10)*(1+BW10)*(1+BX10)*(1+BY10)-1)*(1-BZ12))) -> 1 | CA13: =IF(CA12=0,1,1+(((1+BU10)*(1+BV10)*(1+BW10)*(1+BX10)*(1+BY10)*(1+BZ10)-1)*(1-CA12))) -> 1 | CB13: =IF(CB12=0,1,1+(((1+BV10)*(1+BW10)*(1+BX10)*(1+BY10)*(1+BZ10)*(1+CA10)-1)*(1-CB12))) -> 1 | CC13: =IF(CC12=0,1,1+(((1+BX10)*(1+BY10)*(1+BZ10)*(1+CA10)*(1+CB10)*(1+CC10)-1)*(1-CC12))) -> 1.4348074 | CD13: =IF(CD12=0,1,1+(((1+BX10)*(1+BY10)*(1+BZ10)*(1+CA10)*(1+CB10)*(1+CC10)-1)*(1-CD12))) -> 1 | CE13: =IF(CE12=0,1,1+(((1+BY10)*(1+BZ10)*(1+CA10)*(1+CB10)*(1+CC10)*(1+CD10)-1)*(1-CE12))) -> 1 | CF13: =IF(CF12=0,1,1+(((1+BZ10)*(1+CA10)*(1+CB10)*(1+CC10)*(1+CD10)*(1+CE10)-1)*(1-CF12))) -> 1 | CG13: =IF(CG12=0,1,1+(((1+CA10)*(1+CB10)*(1+CC10)*(1+CD10)*(1+CE10)*(1+CF10)-1)*(1-CG12))) -> 1 | CH13: =IF(CH12=0,1,1+(((1+CB10)*(1+CC10)*(1+CD10)*(1+CE10)*(1+CF10)*(1+CG10)-1)*(1-CH12))) -> 1 | CI13: =IF(CI12=0,1,1+(((1+CD10)*(1+CE10)*(1+CF10)*(1+CG10)*(1+CH10)*(1+CI10)-1)*(1-CI12))) -> 1.6884639 | CJ13: =IF(CJ12=0,1,1+(((1+CJ10)-1)*(1-CJ12))) -> 1.4023 | CK13: =IF(CK12=0,1,1+(((1+CK10)-1)*(1-CK12))) -> 1.15255 | CL13: =IF(CL12=0,1,1+(((1+CL10)-1)*(1-CL12))) -> 1.1431 | CM13: =IF(CM12=0,1,1+(((1+CM10)-1)*(1-CM12))) -> 1.0738 | CN13: =IF(CN12=0,1,1+(((1+CN10)-1)*(1-CN12))) -> 1.05085 | CO13: =IF(CO12=0,1,1+(((1+CO10)-1)*(1-CO12))) -> 1.0207 | CP13: =IF(CP12=0,1,1+(((1+CP10)-1)*(1-CP12))) -> 1.0198 | CQ13: =1+(((1+CQ10)-1)) -> 1.0275 | CS13: =1+(((1+CS10)-1)) -> 1.0205 | CT13: =1+(((1+CT10)-1)) -> 1.0335 | CU13: =1+(((1+CU10)-1)) -> 1.026 | CV13: =1+(((1+CV10)-1)) -> 1.021 | CW13: =1+(((1+CW10)-1)) -> 1.013 | CX13: =1+(((1+CX10)-1)) -> 1.0195 | CY13: =1+(((1+CY10)-1)) -> 1.014 | CZ13: =1+(((1+CZ10)-1)) -> 1.0185 | ... DK13: =1+(((1+DK10)-1)) -> 1
A14: 17.4 | C14: FX Rate | Q14: 18.6678 | R14: 19.6378 | S14: 20.2008 | T14: 20.1883 | U14: 22.3873 | V14: 25.5732 | W14: 27.6313 | X14: 28.1558 | Y14: 36.0401 | Z14: 37.7419 | AA14: 36.0974 | AB14: 37.6768 | AC14: 37.540588 | AD14: 37.8426 | AE14: 40.278833 | AF14: 42.7495 | AG14: 44.6298 | AH14: 44.5014 | AI14: 42.3633 | AJ14: 57.9 | AK14: 56.3589 | AL14: 60 | AM14: 59.85 | AN14: 59.815 | AO14: 60.35 | AP14: 62.21 | AQ14: 64.409 | AR14: 66.84 | AS14: 68.54 | AT14: 70.46 | AU14: 72.32 | AV14: 74.18 | AW14: 76.18 | AX14: 78.32 | AY14: 81.31 | AZ14: 84.15 | BA14: 87.33 | BB14: 89.82 | BC14: 92 | BD14: 93.56 | BE14: 94.73 | BF14: 95.72 | BG14: 96.69 | BH14: 97.74 | BI14: 98.74 | BJ14: 99.72 | BK14: 100.96 | BL14: 102.72 | BM14: 105.02 | BN14: 107.45 | BO14: 110.89 | BP14: 115.73 | BQ14: 120.2 | BR14: 125.45 | BS14: 132.42 | BT14: 141.15 | BU14: 150.69 | BV14: 157.28 | BW14: 166.96 | BX14: 176.05 | BY14: 187.57 | BZ14: 197.15 | CA14: 211.22 | CB14: 225.2 | CC14: 240.25 | CD14: 257.9 | CE14: 276.15 | CF14: 350.1 | CG14: 350 | CH14: 350 | CI14: 361.1 | CJ14: 807.95 | CK14: 825.7 | CL14: 848 | CM14: 858 | CN14: 890.5 | CO14: 907.5 | CP14: 914.5 | CQ14: 931.5 | CS14: =+'CSD Pricing'!CO16 -> 953.5 | CT14: =+'CSD Pricing'!CP16 -> 975.5 | CU14: =+'CSD Pricing'!CQ16 -> 998 | CV14: =+'CSD Pricing'!CR16 -> 1013 | CW14: =+'CSD Pricing'!CS16 -> 1035.5 | CX14: =+'CSD Pricing'!CT16 -> 1054.75 | CY14: =+'CSD Pricing'!CU16 -> 1064.5 | CZ14: =+'CSD Pricing'!CV16 -> 1076 | ... DK14: =+'CSD Pricing'!DG16 -> 1407.5
C15: Type | D15: Wgt | Q15: AR$ | R15: AR$ | S15: AR$ | T15: AR$ | U15: AR$ | V15: AR$ | W15: AR$ | X15: AR$ | Y15: AR$ | Z15: AR$ | AA15: AR$ | AB15: AR$ | AC15: AR$ | AD15: AR$ | AE15: AR$ | AF15: AR$ | AG15: AR$ | AH15: AR$ | AI15: AR$ | AJ15: AR$ | AK15: AR$ | AL15: AR$ | AM15: AR$ | AN15: AR$ | AO15: AR$ | AP15: AR$ | AQ15: AR$ | AR15: AR$ | AS15: AR$ | AT15: AR$ | AU15: AR$ | AV15: AR$ | AW15: AR$ | AX15: AR$ | AY15: AR$ | AZ15: AR$ | BA15: AR$ | BB15: AR$ | BC15: AR$ | BD15: AR$ | BE15: AR$ | BF15: AR$ | BG15: AR$ | BH15: AR$ | BI15: AR$ | BJ15: AR$ | BK15: AR$ | BL15: AR$ | BM15: AR$ | BN15: AR$ | BO15: AR$ | BP15: AR$ | BQ15: AR$ | BR15: AR$ | BS15: AR$ | BT15: AR$ | BU15: AR$ | BV15: AR$ | BW15: AR$ | BX15: AR$ | BY15: AR$ | BZ15: AR$ | CA15: AR$ | CB15: AR$ | CC15: AR$ | CD15: AR$ | CE15: AR$ | CF15: AR$ | CG15: AR$ | CH15: AR$ | CI15: AR$ | CJ15: AR$ | CK15: AR$ | CL15: AR$ | CM15: AR$ | CN15: AR$ | CO15: AR$ | CP15: AR$ | CQ15: AR$ | CS15: AR$ | CT15: AR$ | CU15: AR$ | CV15: AR$ | CW15: AR$ | CX15: AR$ | CY15: AR$ | CZ15: AR$ | DA15: AR$ | DB15: AR$ | DC15: AR$ | DD15: AR$ | DE15: AR$ | DF15: AR$ | DG15: AR$ | DH15: AR$ | DI15: AR$ | DJ15: AR$ | DK15: AR$
C16: Estructura de Costos (.000)
C17: Resina (USD) | D17: 24 | Q17: =+$D17/1000*(1+Q$6)*Q$3 -> 34.854882 | R17: =+$D17/1000*(1+R$6)*R$3 -> 35.876435 | S17: =+$D17/1000*(1+S$6)*S$3 -> 36.50826 | T17: =+$D17/1000*(1+T$6)*T$3 -> 37.067871 | U17: =+$D17/1000*(1+U$6)*U$3 -> 38.242696 | V17: =+$D17/1000*(1+V$6)*V$3 -> 39.487753 | W17: =+$D17/1000*(1+W$6)*W$3 -> 40.977689 | X17: =+$D17/1000*(1+X$6)*X$3 -> 42.660284 | ... BI17: =+$D17/1000*(1+BI$6)*BI$3 -> 39.891123 | BJ17: =+$D17/1000*(1+BJ$6)*BJ$4 -> 36.94907 | BK17: =+$D17/1000*(1+BK$6)*BK$4 -> 41.233121 | BL17: =+$D17/1000*(1+BL$6)*BL$4 -> 41.568488 | BM17: =+$D17/1000*(1+BM$6)*BM$4 -> 38.964102 | BN17: =+$D17/1000*(1+BN$6)*BN$4 -> 42.887654 | BO17: =+$D17/1000*(1+BO$6)*BO$4 -> 45.6122 | BP17: =+$D17/1000*(1+BP$6)*BP$4 -> 48.508258 | BQ17: =+$D17/1000*(1+BQ$6)*BQ$4 -> 51.836136 | ... CQ17: =+$D17/1000*(1+CQ$6)*CQ$4 -> 36.9036 | CS17: =+$D17/1000*(1+CS$6)*CS$4 -> 44.2602 | CT17: =+$D17/1000*(1+CT$6)*CT$4 -> 36.523881 | CU17: =+$D17/1000*(1+CU$6)*CU$4 -> 38.150098 | CV17: =+$D17/1000*(1+CV$6)*CV$4*(1+CV$7) -> 40.152978 | CW17: =+$D17/1000*(1+CW$6)*CW$4*(1+CW$7) -> 39.987195 | CX17: =+$D17/1000*(1+CX$6)*CX$4*(1+CX$7) -> 39.721487 | CY17: =+$D17/1000*(1+CY$6)*CY$4*(1+CY$7) -> 39.721487 | CZ17: =+$D17/1000*(1+CZ$6)*CZ$4*(1+CZ$7) -> 38.248374 | DA17: =+$D17/1000*(1+DA$6)*DA$4*(1+DA$7) -> 36.055983 | DB17: =+$D17/1000*(1+DB$6)*DB$4*(1+DB$7) -> 35.695068 | DC17: =+$D17/1000*(1+DC$6)*DC$4*(1+DC$7) -> 34.216154 | ... DK17: =+$D17/1000*(1+DK$6)*DK$4*(1+DK$7) -> 32.845375
D18: 30 | CS18: =+$D18/1000*(1+CS$6)*CS$4*(1+CS$7) -> 55.32525 | CT18: =+$D18/1000*(1+CT$6)*CT$4*(1+CT$7) -> 45.654852 | CU18: =+$D18/1000*(1+CU$6)*CU$4*(1+CU$7) -> 47.687623 | CV18: =+$D18/1000*(1+CV$6)*CV$4*(1+CV$7) -> 50.191223 | CW18: =+$D18/1000*(1+CW$6)*CW$4*(1+CW$7) -> 49.983993 | CX18: =+$D18/1000*(1+CX$6)*CX$4*(1+CX$7) -> 49.651859 | CY18: =+$D18/1000*(1+CY$6)*CY$4*(1+CY$7) -> 49.651859 | CZ18: =+$D18/1000*(1+CZ$6)*CZ$4*(1+CZ$7) -> 47.810468 | ... DK18: =+$D18/1000*(1+DK$6)*DK$4*(1+DK$7) -> 41.056718
D19: 30.4 | Q19: =+$D19/1000*(1+Q$6)*Q$3 -> 44.149517 | R19: =+$D19/1000*(1+R$6)*R$3 -> 45.443485 | S19: =+$D19/1000*(1+S$6)*S$3 -> 46.243796 | T19: =+$D19/1000*(1+T$6)*T$3 -> 46.952637 | U19: =+$D19/1000*(1+U$6)*U$3 -> 48.440748 | V19: =+$D19/1000*(1+V$6)*V$3 -> 50.017821 | W19: =+$D19/1000*(1+W$6)*W$3 -> 51.905073 | X19: =+$D19/1000*(1+X$6)*X$3 -> 54.03636 | ... CQ19: =+$D19/1000*(1+CQ$6)*CQ$3 -> 56.918376 | CS19: =+$D19/1000*(1+CS$6)*CS$3 -> 60.401304 | CT19: =+$D19/1000*(1+CT$6)*CT$3 -> 49.426178 | CU19: =+$D19/1000*(1+CU$6)*CU$3 -> 52.885412 | CV19: =+$D19/1000*(1+CV$6)*CV$3*(1+CV$7) -> 54.636623 | CW19: =+$D19/1000*(1+CW$6)*CW$3*(1+CW$7) -> 53.2111 | CX19: =+$D19/1000*(1+CX$6)*CX$3*(1+CX$7) -> 51.963384 | CY19: =+$D19/1000*(1+CY$6)*CY$3*(1+CY$7) -> 50.716203 | CZ19: =+$D19/1000*(1+CZ$6)*CZ$3*(1+CZ$7) -> 50.029522 | DA19: =+$D19/1000*(1+DA$6)*DA$3*(1+DA$7) -> 47.745679 | DB19: =+$D19/1000*(1+DB$6)*DB$3*(1+DB$7) -> 45.763767 | DC19: =+$D19/1000*(1+DC$6)*DC$3*(1+DC$7) -> 44.7433 | ... DK19: =+$D19/1000*(1+DK$6)*DK$3*(1+DK$7) -> 41.398623
D20: 30.4 | E20: 30% PCR | CK20: =+$D20/1000*(1+CK$6)*(CK$3*0.7+CK$5*0.3) -> 62.298583 | CL20: =+$D20/1000*(1+CL$6)*(CL$3*0.7+CL$5*0.3) -> 62.298583 | CM20: =+$D20/1000*(1+CM$6)*(CM$3*0.7+CM$5*0.3) -> 62.298583 | CN20: =+$D20/1000*(1+CN$6)*(CN$3*0.7+CN$5*0.3) -> 62.298583 | CO20: =+$D20/1000*(1+CO$6)*(CO$3*0.7+CO$5*0.3) -> 62.298583 | CP20: =+$D20/1000*(1+CP$6)*(CP$3*0.7+CP$5*0.3) -> 62.298583 | CQ20: =+$D20/1000*(1+CQ$6)*(CQ$3*0.7+CQ$5*0.3) -> 62.298583 | CS20: =+$D20/1000*(1+CS$6)*(CS$3*0.7+CS$5*0.3) -> 60.401304 | CT20: =+$D20/1000*(1+CT$6)*(CT$3*0.7+CT$5*0.3) -> 49.426178 | CU20: =+$D20/1000*(1+CU$6)*(CU$3*0.7+CU$5*0.3) -> 52.885412 | CV20: =+$D20/1000*(1+CV$6)*(CV$3*0.7+CV$5*0.3)*(1+CV$7) -> 54.636623 | CW20: =+$D20/1000*(1+CW$6)*(CW$3*0.7+CW$5*0.3)*(1+CW$7) -> 53.2111 | CX20: =+$D20/1000*(1+CX$6)*(CX$3*0.7+CX$5*0.3)*(1+CX$7) -> 51.963384 | CY20: =+$D20/1000*(1+CY$6)*(CY$3*0.7+CY$5*0.3)*(1+CY$7) -> 50.716203 | CZ20: =+$D20/1000*(1+CZ$6)*(CZ$3*0.7+CZ$5*0.3)*(1+CZ$7) -> 50.029522 | DA20: =+$D20/1000*(1+DA$6)*(DA$3*0.7+DA$5*0.3)*(1+DA$7) -> 47.745679 | DB20: =+$D20/1000*(1+DB$6)*(DB$3*0.7+DB$5*0.3)*(1+DB$7) -> 45.763767 | DC20: =+$D20/1000*(1+DC$6)*(DC$3*0.7+DC$5*0.3)*(1+DC$7) -> 44.7433 | ... DK20: =+$D20/1000*(1+DK$6)*(DK$3*0.7+DK$5*0.3)*(1+DK$7) -> 41.398623
D21: 34 | CS21: =+$D21/1000*(1+CS$6)*CS$3 -> 67.55409 | CT21: =+$D21/1000*(1+CT$6)*CT$3 -> 55.279278 | CU21: =+$D21/1000*(1+CU$6)*CU$3 -> 59.148158 | CV21: =+$D21/1000*(1+CV$6)*CV$3*(1+CV$7) -> 61.10675 | CW21: =+$D21/1000*(1+CW$6)*CW$3*(1+CW$7) -> 59.512415 | CX21: =+$D21/1000*(1+CX$6)*CX$3*(1+CX$7) -> 58.116942 | CY21: =+$D21/1000*(1+CY$6)*CY$3*(1+CY$7) -> 56.722069 | CZ21: =+$D21/1000*(1+CZ$6)*CZ$3*(1+CZ$7) -> 55.954071 | DA21: =+$D21/1000*(1+DA$6)*DA$3*(1+DA$7) -> 53.399772 | DB21: =+$D21/1000*(1+DB$6)*DB$3*(1+DB$7) -> 51.183161 | DC21: =+$D21/1000*(1+DC$6)*DC$3*(1+DC$7) -> 50.041849 | ... DK21: =+$D21/1000*(1+DK$6)*DK$3*(1+DK$7) -> 46.301091
D22: 34 | E22: 30% PCR | CS22: =+$D22/1000*(1+CS$6)*(CS$3*0.7+CS$5*0.3) -> 67.55409 | CT22: =+$D22/1000*(1+CT$6)*(CT$3*0.7+CT$5*0.3) -> 55.279278 | CU22: =+$D22/1000*(1+CU$6)*(CU$3*0.7+CU$5*0.3) -> 59.148158 | CV22: =+$D22/1000*(1+CV$6)*(CV$3*0.7+CV$5*0.3)*(1+CV$7) -> 61.10675 | CW22: =+$D22/1000*(1+CW$6)*(CW$3*0.7+CW$5*0.3)*(1+CW$7) -> 59.512415 | CX22: =+$D22/1000*(1+CX$6)*(CX$3*0.7+CX$5*0.3)*(1+CX$7) -> 58.116942 | CY22: =+$D22/1000*(1+CY$6)*(CY$3*0.7+CY$5*0.3)*(1+CY$7) -> 56.722069 | CZ22: =+$D22/1000*(1+CZ$6)*(CZ$3*0.7+CZ$5*0.3)*(1+CZ$7) -> 55.954071 | DA22: =+$D22/1000*(1+DA$6)*(DA$3*0.7+DA$5*0.3)*(1+DA$7) -> 53.399772 | DB22: =+$D22/1000*(1+DB$6)*(DB$3*0.7+DB$5*0.3)*(1+DB$7) -> 51.183161 | DC22: =+$D22/1000*(1+DC$6)*(DC$3*0.7+DC$5*0.3)*(1+DC$7) -> 50.041849 | ... DK22: =+$D22/1000*(1+DK$6)*(DK$3*0.7+DK$5*0.3)*(1+DK$7) -> 46.301091
D23: 44.8 | Q23: =+$D23/1000*(1+Q$6)*Q$3 -> 65.062446 | R23: =+$D23/1000*(1+R$6)*R$3 -> 66.969346 | S23: =+$D23/1000*(1+S$6)*S$3 -> 68.148753 | T23: =+$D23/1000*(1+T$6)*T$3 -> 69.19336 | U23: =+$D23/1000*(1+U$6)*U$3 -> 71.386366 | V23: =+$D23/1000*(1+V$6)*V$3 -> 73.710473 | W23: =+$D23/1000*(1+W$6)*W$3 -> 76.491687 | X23: =+$D23/1000*(1+X$6)*X$3 -> 79.632531 | ... AM23: =+$D23/1000*(1+AM$6)*AM$3 -> 55.793949 | AN23: =+$D23/1000*(1+AN$6)*AN$4 -> 52.368727 | AO23: =+$D23/1000*(1+AO$6)*AO$4 -> 52.638262 | AP23: =+$D23/1000*(1+AP$6)*AP$4 -> 53.514965 | AQ23: =+$D23/1000*(1+AQ$6)*AQ$4 -> 51.281038 | AR23: =+$D23/1000*(1+AR$6)*AR$4 -> 47.163441 | AS23: =+$D23/1000*(1+AS$6)*AS$4 -> 42.37818 | AT23: =+$D23/1000*(1+AT$6)*AT$4 -> 43.178579 | AU23: =+$D23/1000*(1+AU$6)*AU$4 -> 44.921289 | ... CQ23: =+$D23/1000*(1+CQ$6)*CQ$4 -> 68.88672 | CS23: =+$D23/1000*(1+CS$6)*CS$4 -> 82.61904 | CT23: =+$D23/1000*(1+CT$6)*CT$4 -> 68.177912 | CU23: =+$D23/1000*(1+CU$6)*CU$4 -> 71.213516 | CV23: =+$D23/1000*(1+CV$6)*CV$4*(1+CV7) -> 74.952226 | CW23: =+$D23/1000*(1+CW$6)*CW$4*(1+CW7) -> 74.642763 | CX23: =+$D23/1000*(1+CX$6)*CX$4*(1+CX7) -> 74.146776 | CY23: =+$D23/1000*(1+CY$6)*CY$4*(1+CY7) -> 74.146776 | CZ23: =+$D23/1000*(1+CZ$6)*CZ$4*(1+CZ7) -> 71.396965 | DA23: =+$D23/1000*(1+DA$6)*DA$4*(1+DA7) -> 67.304501 | DB23: =+$D23/1000*(1+DB$6)*DB$4*(1+DB7) -> 66.630793 | DC23: =+$D23/1000*(1+DC$6)*DC$4*(1+DC7) -> 63.870155 | ... DK23: =+$D23/1000*(1+DK$6)*DK$4*(1+DK7) -> 61.311366
D24: 52 | Q24: =+$D24/1000*(1+Q$6)*Q$3 -> 75.518911 | R24: =+$D24/1000*(1+R$6)*R$3 -> 77.732276 | S24: =+$D24/1000*(1+S$6)*S$3 -> 79.101231 | T24: =+$D24/1000*(1+T$6)*T$3 -> 80.313721 | U24: =+$D24/1000*(1+U$6)*U$3 -> 82.859175 | V24: =+$D24/1000*(1+V$6)*V$3 -> 85.556799 | W24: =+$D24/1000*(1+W$6)*W$3 -> 88.784994 | X24: =+$D24/1000*(1+X$6)*X$3 -> 92.430616 | ... CQ24: =+$D24/1000*(1+CQ$6)*CQ$3 -> 97.36038 | CS24: =+$D24/1000*(1+CS$6)*CS$3 -> 103.31802 | CT24: =+$D24/1000*(1+CT$6)*CT$3 -> 84.544779 | CU24: =+$D24/1000*(1+CU$6)*CU$3 -> 90.461889 | CV24: =+$D24/1000*(1+CV$6)*CV$3*(1+CV$7) -> 93.457382 | CW24: =+$D24/1000*(1+CW$6)*CW$3*(1+CW$7) -> 91.018988 | CX24: =+$D24/1000*(1+CX$6)*CX$3*(1+CX$7) -> 88.884735 | CY24: =+$D24/1000*(1+CY$6)*CY$3*(1+CY$7) -> 86.7514 | CZ24: =+$D24/1000*(1+CZ$6)*CZ$3*(1+CZ$7) -> 85.576815 | DA24: =+$D24/1000*(1+DA$6)*DA$3*(1+DA$7) -> 81.67024 | DB24: =+$D24/1000*(1+DB$6)*DB$3*(1+DB$7) -> 78.280129 | DC24: =+$D24/1000*(1+DC$6)*DC$3*(1+DC$7) -> 76.534592 | ... DK24: =+$D24/1000*(1+DK$6)*DK$3*(1+DK$7) -> 70.813433
C26: MO; Energía; Packaging; Others (ARS) | D26: 24 | Q26: =11.55+1 -> 12.55 | R26: =+Q26*Q$13*Q$14/R$14 -> 11.930099 | S26: =+R26*1*R$14/S$14 -> 11.597605 | T26: =+S26*S$13*S$14/T$14 -> 12.885758 | U26: =+T26*T$13*T$14/U$14 -> 11.62005 | V26: =+U26*U$13*U$14/V$14 -> 10.172428 | W26: =+V26*V$13*V$14/W$14 -> 9.4147413 | X26: =+W26*W$13*W$14/X$14 -> 9.2393589 | Y26: =+X26*X$13*X$14/Y$14 -> 8.9069816 | Z26: =+Y26*Y$13*Y$14/Z$14 -> 8.5053616 | AA26: =+Z26*Z$13*Z$14/AA$14 -> 8.8928429 | ... CQ26: =+CP26*CP$13*CP$14/CQ$14 -> 11.376127 | CS26: =+CQ26*CQ$13*CQ$14/CS$14 -> 11.419272 | CT26: =+CS26*CS$13*CS$14/CT$14 -> 11.390554 | CU26: =+CT26*CT$13*CT$14/CU$14 -> 11.506734 | CV26: =+CU26*CU$13*CU$14/CV$14 -> 11.631093 | CW26: =+CV26*CV$13*CV$14/CW$14 -> 11.617311 | CX26: =+CW26*CW$13*CW$14/CX$14 -> 11.553555 | CY26: =+CX26*CX$13*CX$14/CY$14 -> 11.670964 | CZ26: =+CY26*CY$13*CY$14/CZ$14 -> 11.707875 | DA26: =+CZ26*CZ$14/DA$14 -> 10.767242 | DB26: =+DA26*DA$14/DB$14 -> 10.604102 | DC26: =+DB26*DB$13*DB$14/DC$14 -> 10.559046 | DD26: =+DC26*DC$13*DC$14/DD$14 -> 9.4130936 | DE26: =+DD26*DD$13*DD$14/DE$14 -> 9.9025815 | DF26: =+DE26*DE$13*DE$14/DF$14 -> 9.7083589 | DG26: =+DF26*DF$13*DF$14/DG$14 -> 9.7809312 | DH26: =+DG26*DG$13*DG$14/DH$14 -> 9.9909478 | DI26: =+DH26*DH$13*DH$14/DI$14 -> 10.044133 | DJ26: =+DI26*DI$13*DI$14/DJ$14 -> 10.220252 | DK26: =+DJ26*DJ$13*DJ$14/DK$14 -> 10.747457
D27: 30 | CS27: 11.670964 | CT27: 11.670964 | CU27: 11.670964 | CV27: 11.670964 | CW27: 11.670964 | CX27: 11.670964 | CY27: 11.670964 | CZ27: =+CY27*CY$13*CY$14/CZ$14 -> 11.707875 | DA27: =+CZ27*CZ$14/DA$14 -> 10.767242 | DB27: =+DA27*DA$14/DB$14 -> 10.604102 | DC27: =+DB27*DB$13*DB$14/DC$14 -> 10.559046 | DD27: =+DC27*DC$13*DC$14/DD$14 -> 9.4130936 | DE27: =+DD27*DD$13*DD$14/DE$14 -> 9.9025815 | DF27: =+DE27*DE$13*DE$14/DF$14 -> 9.7083589 | DG27: =+DF27*DF$13*DF$14/DG$14 -> 9.7809312 | DH27: =+DG27*DG$13*DG$14/DH$14 -> 9.9909478 | DI27: =+DH27*DH$13*DH$14/DI$14 -> 10.044133 | DJ27: =+DI27*DI$13*DI$14/DJ$14 -> 10.220252 | DK27: =+DJ27*DJ$13*DJ$14/DK$14 -> 10.747457
D28: 30.4 | Q28: =11.55+1 -> 12.55 | R28: =+Q28*Q$13*Q$14/R$14 -> 11.930099 | S28: =+R28*1*R$14/S$14 -> 11.597605 | T28: =+S28*S$13*S$14/T$14 -> 12.885758 | U28: =+T28*T$13*T$14/U$14 -> 11.62005 | V28: =+U28*U$13*U$14/V$14 -> 10.172428 | W28: =+V28*V$13*V$14/W$14 -> 9.4147413 | X28: =+W28*W$13*W$14/X$14 -> 9.2393589 | Y28: =+X28*X$13*X$14/Y$14 -> 8.9069816 | Z28: =+Y28*Y$13*Y$14/Z$14 -> 8.5053616 | AA28: =+Z28*Z$13*Z$14/AA$14 -> 8.8928429 | ... CQ28: =+CP28*CP$13*CP$14/CQ$14 -> 11.376127 | CS28: =+CQ28*CQ$13*CQ$14/CS$14 -> 11.419272 | CT28: =+CS28*CS$13*CS$14/CT$14 -> 11.390554 | CU28: =+CT28*CT$13*CT$14/CU$14 -> 11.506734 | CV28: =+CU28*CU$13*CU$14/CV$14 -> 11.631093 | CW28: =+CV28*CV$13*CV$14/CW$14 -> 11.617311 | CX28: =+CW28*CW$13*CW$14/CX$14 -> 11.553555 | CY28: =+CX28*CX$13*CX$14/CY$14 -> 11.670964 | CZ28: =+CY28*CY$13*CY$14/CZ$14 -> 11.707875 | DA28: =+CZ28*CZ$14/DA$14 -> 10.767242 | DB28: =+DA28*DA$14/DB$14 -> 10.604102 | DC28: =+DB28*DB$13*DB$14/DC$14 -> 10.559046 | DD28: =+DC28*DC$13*DC$14/DD$14 -> 9.4130936 | DE28: =+DD28*DD$13*DD$14/DE$14 -> 9.9025815 | DF28: =+DE28*DE$13*DE$14/DF$14 -> 9.7083589 | DG28: =+DF28*DF$13*DF$14/DG$14 -> 9.7809312 | DH28: =+DG28*DG$13*DG$14/DH$14 -> 9.9909478 | DI28: =+DH28*DH$13*DH$14/DI$14 -> 10.044133 | DJ28: =+DI28*DI$13*DI$14/DJ$14 -> 10.220252 | DK28: =+DJ28*DJ$13*DJ$14/DK$14 -> 10.747457
D29: 34 | CS29: =+CS28 -> 11.419272 | CT29: =+CS29*CS$13*CS$14/CT$14 -> 11.390554 | CU29: =+CT29*CT$13*CT$14/CU$14 -> 11.506734 | CV29: =+CU29*CU$13*CU$14/CV$14 -> 11.631093 | CW29: =+CV29*CV$13*CV$14/CW$14 -> 11.617311 | CX29: =+CW29*CW$13*CW$14/CX$14 -> 11.553555 | CY29: =+CX29*CX$13*CX$14/CY$14 -> 11.670964 | CZ29: =+CY29*CY$13*CY$14/CZ$14 -> 11.707875 | DA29: =+CZ29*CZ$14/DA$14 -> 10.767242 | DB29: =+DA29*DA$14/DB$14 -> 10.604102 | DC29: =+DB29*DB$13*DB$14/DC$14 -> 10.559046 | DD29: =+DC29*DC$13*DC$14/DD$14 -> 9.4130936 | DE29: =+DD29*DD$13*DD$14/DE$14 -> 9.9025815 | DF29: =+DE29*DE$13*DE$14/DF$14 -> 9.7083589 | DG29: =+DF29*DF$13*DF$14/DG$14 -> 9.7809312 | DH29: =+DG29*DG$13*DG$14/DH$14 -> 9.9909478 | DI29: =+DH29*DH$13*DH$14/DI$14 -> 10.044133 | DJ29: =+DI29*DI$13*DI$14/DJ$14 -> 10.220252 | DK29: =+DJ29*DJ$13*DJ$14/DK$14 -> 10.747457
D30: 44.8 | Q30: =16.8+1 -> 17.8 | R30: =+Q30*Q$13*Q$14/R$14 -> 16.920777 | S30: =+R30*1*R$14/S$14 -> 16.449192 | T30: =+S30*S$13*S$14/T$14 -> 18.276214 | U30: =+T30*T$13*T$14/U$14 -> 16.481027 | V30: =+U30*U$13*U$14/V$14 -> 14.427826 | W30: =+V30*V$13*V$14/W$14 -> 13.353179 | X30: =+W30*W$13*W$14/X$14 -> 13.104429 | Y30: =+X30*X$13*X$14/Y$14 -> 12.63301 | Z30: =+Y30*Y$13*Y$14/Z$14 -> 12.063381 | AA30: =+Z30*Z$13*Z$14/AA$14 -> 12.612956 | ... CQ30: =+CP30*CP$13*CP$14/CQ$14 -> 16.135065 | CS30: =+CQ30*CQ$13*CQ$14/CS$14 -> 16.196259 | CT30: =+CS30*CS$13*CS$14/CT$14 -> 16.155527 | CU30: =+CT30*CT$13*CT$14/CU$14 -> 16.320308 | CV30: =+CU30*CU$13*CU$14/CV$14 -> 16.49669 | CW30: =+CV30*CV$13*CV$14/CW$14 -> 16.477142 | CX30: =+CW30*CW$13*CW$14/CX$14 -> 16.386715 | CY30: =+CX30*CX$13*CX$14/CY$14 -> 16.55324 | CZ30: =+CY30*CY$13*CY$14/CZ$14 -> 16.605592 | DA30: =+CZ30*CZ$14/DA$14 -> 15.271467 | DB30: =+DA30*DA$14/DB$14 -> 15.040081 | DC30: =+DB30*DB$13*DB$14/DC$14 -> 14.976177 | DD30: =+DC30*DC$13*DC$14/DD$14 -> 13.350842 | DE30: =+DD30*DD$13*DD$14/DE$14 -> 14.045096 | DF30: =+DE30*DE$13*DE$14/DF$14 -> 13.769625 | DG30: =+DF30*DF$13*DF$14/DG$14 -> 13.872556 | DH30: =+DG30*DG$13*DG$14/DH$14 -> 14.170428 | DI30: =+DH30*DH$13*DH$14/DI$14 -> 14.245861 | DJ30: =+DI30*DI$13*DI$14/DJ$14 -> 14.495657 | DK30: =+DJ30*DJ$13*DJ$14/DK$14 -> 15.243405
D31: 52 | Q31: =16.8+1 -> 17.8 | R31: =+Q31*Q$13*Q$14/R$14 -> 16.920777 | S31: =+R31*1*R$14/S$14 -> 16.449192 | T31: =+S31*S$13*S$14/T$14 -> 18.276214 | U31: =+T31*T$13*T$14/U$14 -> 16.481027 | V31: =+U31*U$13*U$14/V$14 -> 14.427826 | W31: =+V31*V$13*V$14/W$14 -> 13.353179 | X31: =+W31*W$13*W$14/X$14 -> 13.104429 | Y31: =+X31*X$13*X$14/Y$14 -> 12.63301 | Z31: =+Y31*Y$13*Y$14/Z$14 -> 12.063381 | AA31: =+Z31*Z$13*Z$14/AA$14 -> 12.612956 | ... CQ31: =+CP31*CP$13*CP$14/CQ$14 -> 16.135065 | CS31: =+CQ31*CQ$13*CQ$14/CS$14 -> 16.196259 | CT31: =+CS31*CS$13*CS$14/CT$14 -> 16.155527 | CU31: =+CT31*CT$13*CT$14/CU$14 -> 16.320308 | CV31: =+CU31*CU$13*CU$14/CV$14 -> 16.49669 | CW31: =+CV31*CV$13*CV$14/CW$14 -> 16.477142 | CX31: =+CW31*CW$13*CW$14/CX$14 -> 16.386715 | CY31: =+CX31*CX$13*CX$14/CY$14 -> 16.55324 | CZ31: =+CY31*CY$13*CY$14/CZ$14 -> 16.605592 | DA31: =+CZ31*CZ$14/DA$14 -> 15.271467 | DB31: =+DA31*DA$14/DB$14 -> 15.040081 | DC31: =+DB31*DB$13*DB$14/DC$14 -> 14.976177 | DD31: =+DC31*DC$13*DC$14/DD$14 -> 13.350842 | DE31: =+DD31*DD$13*DD$14/DE$14 -> 14.045096 | DF31: =+DE31*DE$13*DE$14/DF$14 -> 13.769625 | DG31: =+DF31*DF$13*DF$14/DG$14 -> 13.872556 | DH31: =+DG31*DG$13*DG$14/DH$14 -> 14.170428 | DI31: =+DH31*DH$13*DH$14/DI$14 -> 14.245861 | DJ31: =+DI31*DI$13*DI$14/DJ$14 -> 14.495657 | DK31: =+DJ31*DJ$13*DJ$14/DK$14 -> 15.243405
C33: Conversion (USD) | D33: 24 | Q33: 4.95 | R33: =+Q33 -> 4.95 | S33: =+R33 -> 4.95 | T33: =+S33 -> 4.95 | U33: =+T33 -> 4.95 | V33: =+U33 -> 4.95 | W33: =+V33 -> 4.95 | X33: =+W33 -> 4.95 | Y33: =+X33 -> 4.95 | ... CQ33: =+CP33 -> 4.95 | CS33: =+CQ33 -> 4.95 | CT33: =+CS33 -> 4.95 | CU33: =+CT33 -> 4.95 | CV33: =+CU33 -> 4.95 | CW33: =+CV33 -> 4.95 | CX33: =+CW33 -> 4.95 | CY33: =+CX33 -> 4.95 | CZ33: =+CY33 -> 4.95 | DA33: =+CZ33*CZ$14/DA$14 -> 4.5523077 | DB33: =+DA33*DA$14/DB$14 -> 4.4833333 | DC33: =CZ33 -> 4.95 | DD33: =DC33 -> 4.95 | DE33: =DD33 -> 4.95 | DF33: =DE33 -> 4.95 | DG33: =DF33 -> 4.95 | DH33: =DG33 -> 4.95 | DI33: =DH33 -> 4.95 | DJ33: =DI33 -> 4.95 | DK33: =DJ33 -> 4.95
D34: 30 | CS34: 5.9 | CT34: 5.9 | CU34: 5.9 | CV34: 5.9 | CW34: 5.9 | CX34: 5.9 | CY34: 5.9 | CZ34: =+CY34 -> 5.9 | DA34: =+CZ34*CZ$14/DA$14 -> 5.4259829 | DB34: =+DA34*DA$14/DB$14 -> 5.343771 | DC34: =CZ34 -> 5.9 | DD34: =DC34 -> 5.9 | DE34: =DD34 -> 5.9 | DF34: =DE34 -> 5.9 | DG34: =DF34 -> 5.9 | DH34: =DG34 -> 5.9 | DI34: =DH34 -> 5.9 | DJ34: =DI34 -> 5.9 | DK34: =DJ34 -> 5.9
D35: 30.4 | Q35: 4.95 | R35: =+Q35 -> 4.95 | S35: =+R35 -> 4.95 | T35: =+S35 -> 4.95 | U35: =+T35 -> 4.95 | V35: =+U35 -> 4.95 | W35: =+V35 -> 4.95 | X35: =+W35 -> 4.95 | Y35: =+X35 -> 4.95 | ... CQ35: =+CP35 -> 4.95 | CS35: =+CQ35 -> 4.95 | CT35: =+CS35 -> 4.95 | CU35: =+CT35 -> 4.95 | CV35: =+CU35 -> 4.95 | CW35: =+CV35 -> 4.95 | CX35: =+CW35 -> 4.95 | CY35: =+CX35 -> 4.95 | CZ35: =+CY35 -> 4.95 | DA35: =+CZ35*CZ$14/DA$14 -> 4.5523077 | DB35: =+DA35*DA$14/DB$14 -> 4.4833333 | DC35: =CZ35 -> 4.95 | DD35: =DC35 -> 4.95 | DE35: =DD35 -> 4.95 | DF35: =DE35 -> 4.95 | DG35: =DF35 -> 4.95 | DH35: =DG35 -> 4.95 | DI35: =DH35 -> 4.95 | DJ35: =DI35 -> 4.95 | DK35: =DJ35 -> 4.95
D36: 34 | CS36: =+CS35 -> 4.95 | CT36: =+CT35 -> 4.95 | CU36: =+CU35 -> 4.95 | CV36: =+CV35 -> 4.95 | CW36: =+CW35 -> 4.95 | CX36: =+CX35 -> 4.95 | CY36: =+CY35 -> 4.95 | CZ36: =+CZ35 -> 4.95 | DA36: =+CZ36*CZ$14/DA$14 -> 4.5523077 | DB36: =+DA36*DA$14/DB$14 -> 4.4833333 | DC36: =CZ36 -> 4.95 | DD36: =DC36 -> 4.95 | DE36: =DD36 -> 4.95 | DF36: =DE36 -> 4.95 | DG36: =DF36 -> 4.95 | DH36: =DG36 -> 4.95 | DI36: =DH36 -> 4.95 | DJ36: =DI36 -> 4.95 | DK36: =DJ36 -> 4.95
D37: 44.8 | Q37: 7.2 | R37: =+Q37 -> 7.2 | S37: =+R37 -> 7.2 | T37: =+S37 -> 7.2 | U37: =+T37 -> 7.2 | V37: =+U37 -> 7.2 | W37: =+V37 -> 7.2 | X37: =+W37 -> 7.2 | Y37: =+X37 -> 7.2 | ... CQ37: =+CP37 -> 7.2 | CS37: =+CQ37 -> 7.2 | CT37: =+CS37 -> 7.2 | CU37: =+CT37 -> 7.2 | CV37: =+CU37 -> 7.2 | CW37: =+CV37 -> 7.2 | CX37: =+CW37 -> 7.2 | CY37: =+CX37 -> 7.2 | CZ37: =+CY37 -> 7.2 | DA37: =+CZ37*CZ$14/DA$14 -> 6.6215385 | DB37: =+DA37*DA$14/DB$14 -> 6.5212121 | DC37: =CZ37 -> 7.2 | DD37: =DC37 -> 7.2 | DE37: =DD37 -> 7.2 | DF37: =DE37 -> 7.2 | DG37: =DF37 -> 7.2 | DH37: =DG37 -> 7.2 | DI37: =DH37 -> 7.2 | DJ37: =DI37 -> 7.2 | DK37: =DJ37 -> 7.2
D38: 52 | Q38: 7.2 | R38: =+Q38 -> 7.2 | S38: =+R38 -> 7.2 | T38: =+S38 -> 7.2 | U38: =+T38 -> 7.2 | V38: =+U38 -> 7.2 | W38: =+V38 -> 7.2 | X38: =+W38 -> 7.2 | Y38: =+X38 -> 7.2 | ... CQ38: =+CP38 -> 7.2 | CS38: =+CQ38 -> 7.2 | CT38: =+CS38 -> 7.2 | CU38: =+CT38 -> 7.2 | CV38: =+CU38 -> 7.2 | CW38: =+CV38 -> 7.2 | CX38: =+CW38 -> 7.2 | CY38: =+CX38 -> 7.2 | CZ38: =+CY38 -> 7.2 | DA38: =+CZ38*CZ$14/DA$14 -> 6.6215385 | DB38: =+DA38*DA$14/DB$14 -> 6.5212121 | DC38: =CZ38 -> 7.2 | DD38: =DC38 -> 7.2 | DE38: =DD38 -> 7.2 | DF38: =DE38 -> 7.2 | DG38: =DF38 -> 7.2 | DH38: =DG38 -> 7.2 | DI38: =DH38 -> 7.2 | DJ38: =DI38 -> 7.2 | DK38: =DJ38 -> 7.2
C40: Total conversion (USD) | Q40: =+Q33+Q26 -> 17.5 | R40: =+R33+R26 -> 16.880099 | S40: =+S33+S26 -> 16.547605 | T40: =+T33+T26 -> 17.835758 | U40: =+U33+U26 -> 16.57005 | V40: =+V33+V26 -> 15.122428 | W40: =+W33+W26 -> 14.364741 | X40: =+X33+X26 -> 14.189359 | ... CQ40: =+CQ33+CQ26 -> 16.326127 | CS40: =+CS33+CS26 -> 16.369272 | CT40: =+CT33+CT26 -> 16.340554 | CU40: =+CU33+CU26 -> 16.456734 | CV40: =+CV33+CV26 -> 16.581093 | CW40: =+CW33+CW26 -> 16.567311 | CX40: =+CX33+CX26 -> 16.503555 | CY40: =+CY33+CY26 -> 16.620964 | CZ40: =+CZ33+CZ26 -> 16.657875 | ... DE40: =+DE33+DE26 -> 14.852581 | DF40: =+(DF33+DF26)*0.99 -> 14.511775 | DG40: =+(DG33+DG26)*0.99 -> 14.583622 | DH40: =+(DH33+DH26)*0.99 -> 14.791538 | DI40: =+(DI33+DI26)*0.99 -> 14.844191 | DJ40: =+(DJ33+DJ26)*0.99 -> 15.01855 | DK40: =+(DK33+DK26)*0.99 -> 15.540482
D41: 30 | CS41: =+CS34+CS27 -> 17.570964 | CT41: =+CT34+CT27 -> 17.570964 | CU41: =+CU34+CU27 -> 17.570964 | CV41: =+CV34+CV27 -> 17.570964 | CW41: =+CW34+CW27 -> 17.570964 | CX41: =+CX34+CX27 -> 17.570964 | CY41: =+CY34+CY27 -> 17.570964 | CZ41: =+CZ34+CZ27 -> 17.607875 | ... DE41: =+DE34+DE27 -> 15.802581 | DF41: =+(DF34+DF27)*0.99 -> 15.452275 | DG41: =+(DG34+DG27)*0.99 -> 15.524122 | DH41: =+(DH34+DH27)*0.99 -> 15.732038 | DI41: =+(DI34+DI27)*0.99 -> 15.784691 | DJ41: =+(DJ34+DJ27)*0.99 -> 15.95905 | DK41: =+(DK34+DK27)*0.99 -> 16.480982
D42: 30.4 | Q42: =+Q35+Q28 -> 17.5 | R42: =+R35+R28 -> 16.880099 | S42: =+S35+S28 -> 16.547605 | T42: =+T35+T28 -> 17.835758 | U42: =+U35+U28 -> 16.57005 | V42: =+V35+V28 -> 15.122428 | W42: =+W35+W28 -> 14.364741 | X42: =+X35+X28 -> 14.189359 | ... CQ42: =+CQ35+CQ28 -> 16.326127 | CS42: =+CS35+CS28 -> 16.369272 | CT42: =+CT35+CT28 -> 16.340554 | CU42: =+CU35+CU28 -> 16.456734 | CV42: =+CV35+CV28 -> 16.581093 | CW42: =+CW35+CW28 -> 16.567311 | CX42: =+CX35+CX28 -> 16.503555 | CY42: =+CY35+CY28 -> 16.620964 | CZ42: =+CZ35+CZ28 -> 16.657875 | ... DE42: =+DE35+DE28 -> 14.852581 | DF42: =+(DF35+DF28)*0.99 -> 14.511775 | DG42: =+(DG35+DG28)*0.99 -> 14.583622 | DH42: =+(DH35+DH28)*0.99 -> 14.791538 | DI42: =+(DI35+DI28)*0.99 -> 14.844191 | DJ42: =+(DJ35+DJ28)*0.99 -> 15.01855 | DK42: =+(DK35+DK28)*0.99 -> 15.540482
D43: 34 | CS43: =+CS29+CS36 -> 16.369272 | CT43: =+CT29+CT36 -> 16.340554 | CU43: =+CU29+CU36 -> 16.456734 | CV43: =+CV29+CV36 -> 16.581093 | CW43: =+CW29+CW36 -> 16.567311 | CX43: =+CX29+CX36 -> 16.503555 | CY43: =+CY29+CY36 -> 16.620964 | CZ43: =+CZ29+CZ36 -> 16.657875 | ... DE43: =+DE29+DE36 -> 14.852581 | DF43: =+(DF36+DF29)*0.99 -> 14.511775 | DG43: =+(DG36+DG29)*0.99 -> 14.583622 | DH43: =+(DH36+DH29)*0.99 -> 14.791538 | DI43: =+(DI36+DI29)*0.99 -> 14.844191 | DJ43: =+(DJ36+DJ29)*0.99 -> 15.01855 | DK43: =+(DK36+DK29)*0.99 -> 15.540482
D44: 44.8 | Q44: =+Q37+Q30 -> 25 | R44: =+R37+R30 -> 24.120777 | S44: =+S37+S30 -> 23.649192 | T44: =+T37+T30 -> 25.476214 | U44: =+U37+U30 -> 23.681027 | V44: =+V37+V30 -> 21.627826 | W44: =+W37+W30 -> 20.553179 | X44: =+X37+X30 -> 20.304429 | ... CQ44: =+CQ37+CQ30 -> 23.335065 | CS44: =+CS37+CS30 -> 23.396259 | CT44: =+CT37+CT30 -> 23.355527 | CU44: =+CU37+CU30 -> 23.520308 | CV44: =+CV37+CV30 -> 23.69669 | CW44: =+CW37+CW30 -> 23.677142 | CX44: =+CX37+CX30 -> 23.586715 | CY44: =+CY37+CY30 -> 23.75324 | CZ44: =+CZ37+CZ30 -> 23.805592 | ... DE44: =+DE37+DE30 -> 21.245096 | DF44: =+(DF37+DF30)*0.99 -> 20.759928 | DG44: =+(DG37+DG30)*0.99 -> 20.86183 | DH44: =+(DH37+DH30)*0.99 -> 21.156724 | DI44: =+(DI37+DI30)*0.99 -> 21.231403 | DJ44: =+(DJ37+DJ30)*0.99 -> 21.4787 | DK44: =+(DK37+DK30)*0.99 -> 22.218971
D45: 52 | Q45: =+Q38+Q31 -> 25 | R45: =+R38+R31 -> 24.120777 | S45: =+S38+S31 -> 23.649192 | T45: =+T38+T31 -> 25.476214 | U45: =+U38+U31 -> 23.681027 | V45: =+V38+V31 -> 21.627826 | W45: =+W38+W31 -> 20.553179 | X45: =+X38+X31 -> 20.304429 | ... CQ45: =+CQ38+CQ31 -> 23.335065 | CS45: =+CS38+CS31 -> 23.396259 | CT45: =+CT38+CT31 -> 23.355527 | CU45: =+CU38+CU31 -> 23.520308 | CV45: =+CV38+CV31 -> 23.69669 | CW45: =+CW38+CW31 -> 23.677142 | CX45: =+CX38+CX31 -> 23.586715 | CY45: =+CY38+CY31 -> 23.75324 | CZ45: =+CZ38+CZ31 -> 23.805592 | ... DE45: =+DE38+DE31 -> 21.245096 | DF45: =+(DF38+DF31)*0.99 -> 20.759928 | DG45: =+(DG38+DG31)*0.99 -> 20.86183 | DH45: =+(DH38+DH31)*0.99 -> 21.156724 | DI45: =+(DI38+DI31)*0.99 -> 21.231403 | DJ45: =+(DJ38+DJ31)*0.99 -> 21.4787 | DK45: =+(DK38+DK31)*0.99 -> 22.218971
C47: Total (USD) | D47: 24 | Q47: =+Q40+Q17 -> 52.354882 | R47: =+R40+R17 -> 52.756534 | S47: =+S40+S17 -> 53.055865 | T47: =+T40+T17 -> 54.903629 | U47: =+U40+U17 -> 54.812746 | V47: =+V40+V17 -> 54.610181 | W47: =+W40+W17 -> 55.342431 | X47: =+X40+X17 -> 56.849643 | ... CQ47: =+CQ40+CQ17 -> 53.229727 | CS47: =+CS40+CS17 -> 60.629472 | CT47: =+CT40+CT17 -> 52.864436 | CU47: =+CU40+CU17 -> 54.606832 | CV47: =+CV40+CV17 -> 56.734071 | CW47: =+CW40+CW17 -> 56.554506 | CX47: =+CX40+CX17 -> 56.225042 | CY47: =+CY40+CY17 -> 56.342451 | CZ47: =+CZ40+CZ17 -> 54.906249 | ... DK47: =+DK40+DK17 -> 48.385857
D48: 30 | CS48: =+CS41+CS18 -> 72.896214 | CT48: =+CT41+CT18 -> 63.225816 | CU48: =+CU41+CU18 -> 65.258587 | CV48: =+CV41+CV18 -> 67.762187 | CW48: =+CW41+CW18 -> 67.554957 | CX48: =+CX41+CX18 -> 67.222823 | CY48: =+CY41+CY18 -> 67.222823 | CZ48: =+CZ41+CZ18 -> 65.418343 | ... DK48: =+DK41+DK18 -> 57.5377
D49: 30.4 | E49: Virgen | CP49: =+CP42+CP19 -> 73.230999 | CQ49: =+CQ42+CQ19 -> 73.244503 | CS49: =+CS42+CS19 -> 76.770576 | CT49: =+CT42+CT19 -> 65.766733 | CU49: =+CU42+CU19 -> 69.342146 | CV49: =+CV42+CV19 -> 71.217716 | CW49: =+CW42+CW19 -> 69.778412 | CX49: =+CX42+CX19 -> 68.466939 | CY49: =+CY42+CY19 -> 67.337167 | CZ49: =+CZ42+CZ19 -> 66.687397 | ... DK49: =+DK42+DK19 -> 56.939105
D50: 30.4 | E50: 30% PCR | Q50: =+Q42+Q19 -> 61.649517 | R50: =+R42+R19 -> 62.323583 | S50: =+S42+S19 -> 62.791401 | T50: =+T42+T19 -> 64.788394 | U50: =+U42+U19 -> 65.010798 | V50: =+V42+V19 -> 65.140249 | W50: =+W42+W19 -> 66.269814 | X50: =+X42+X19 -> 68.225719 | ... CJ50: =+CJ42+CJ19 -> 66.81259 | CK50: =+CK42+CK20 -> 75.542005 | CL50: =+CL42+CL20 -> 76.555803 | CM50: =+CM42+CM20 -> 77.763668 | CN50: =+CN42+CN20 -> 78.127597 | CO50: =+CO42+CO20 -> 78.466638 | CP50: =+CP42+CP20 -> 78.611206 | CQ50: =+CQ42+CQ20 -> 78.62471 | CS50: =+CS42+CS20 -> 76.770576 | CT50: =+CT42+CT20 -> 65.766733 | CU50: =+CU42+CU20 -> 69.342146 | CV50: =+CV42+CV20 -> 71.217716 | CW50: =+CW42+CW20 -> 69.778412 | CX50: =+CX42+CX20 -> 68.466939 | CY50: =+CY42+CY20 -> 67.337167 | CZ50: =+CZ42+CZ20 -> 66.687397 | ... DK50: =+DK42+DK20 -> 56.939105
D51: 34 | E51: Virgen | CS51: =+CS43+CS21 -> 83.923362 | CT51: =+CT43+CT21 -> 71.619833 | CU51: =+CU43+CU21 -> 75.604892 | CV51: =+CV43+CV21 -> 77.687843 | CW51: =+CW43+CW21 -> 76.079726 | CX51: =+CX43+CX21 -> 74.620497 | CY51: =+CY43+CY21 -> 73.343033 | CZ51: =+CZ43+CZ21 -> 72.611946 | ... DK51: =+DK43+DK21 -> 61.841573
D52: 34 | E52: 30% PCR | CS52: =+CS43+CS22 -> 83.923362 | CT52: =+CT43+CT22 -> 71.619833 | CU52: =+CU43+CU22 -> 75.604892 | CV52: =+CV43+CV22 -> 77.687843 | CW52: =+CW43+CW22 -> 76.079726 | CX52: =+CX43+CX22 -> 74.620497 | CY52: =+CY43+CY22 -> 73.343033 | CZ52: =+CZ43+CZ22 -> 72.611946 | ... DK52: =+DK43+DK22 -> 61.841573
D53: 44.8 | Q53: =+Q44+Q23 -> 90.062446 | R53: =+R44+R23 -> 91.090123 | S53: =+S44+S23 -> 91.797945 | T53: =+T44+T23 -> 94.669574 | U53: =+U44+U23 -> 95.067393 | V53: =+V44+V23 -> 95.338299 | W53: =+W44+W23 -> 97.044866 | X53: =+X44+X23 -> 99.93696 | ... AB53: =+AB44+AB23 -> 102.237 | AC53: =+AC44+AC23-1 -> 100.71652 | AD53: =+AD44+AD23-1 -> 97.353405 | AE53: =+AE44+AE23-1 -> 97.237919 | AF53: =+AF44+AF23-1 -> 96.415247 | AG53: =+AG44+AG23-1 -> 95.85019 | AH53: =+AH44+AH23-1 -> 95.887257 | AI53: =+AI44+AI23-1 -> 80.341872 | AJ53: =+AJ44+AJ23-1 -> 79.138733 | ... AM53: =+AM44+AM23-1 -> 73.751648 | AN53: =+AN44+AN23-2 -> 69.333306 | AO53: =+AO44+AO23-2 -> 69.498549 | AP53: =+AP44+AP23-2 -> 70.026623 | AQ53: =+AQ44+AQ23-2 -> 69.519994 | AR53: =+AR44+AR23-2 -> 64.928164 | AS53: =+AS44+AS23-2 -> 59.83126 | AT53: =+AT44+AT23-2 -> 60.297769 | AU53: =+AU44+AU23-2 -> 61.733928 | ... AY53: =+AY44+AY23-2 -> 60.223892 | AZ53: =+AZ44+AZ23-3 -> 59.16118 | BA53: =+BA44+BA23-3 -> 62.064195 | BB53: =+BB44+BB23-3 -> 69.111934 | BC53: =+BC44+BC23-3 -> #N/A | BD53: =+BD44+BD23-3 -> #N/A | BE53: =+BE44+BE23-3 -> #N/A | BF53: =+BF44+BF23-3 -> #N/A | BG53: =+BG44+BG23-3 -> #N/A | ... BW53: =+BW44+BW23-3 -> 91.479763 | BX53: =+BX44+BX23 -> 94.450524 | BY53: =+BY44+BY23 -> 92.810151 | BZ53: =+BZ44+BZ23 -> 91.027441 | CA53: =+CA44+CA23 -> 91.323825 | CB53: =+CB44+CB23 -> 90.747954 | CC53: =+CC44+CC23 -> 92.515914 | CD53: =+CD44+CD23 -> 92.409994 | CE53: =+CE44+CE23 -> 88.427725 | ... CQ53: =+CQ44+CQ23 -> 92.221785 | CS53: =+CS44+CS23 -> 106.0153 | CT53: =+CT44+CT23 -> 91.533439 | CU53: =+CU44+CU23 -> 94.733825 | CV53: =+CV44+CV23 -> 98.648916 | CW53: =+CW44+CW23 -> 98.319906 | CX53: =+CX44+CX23 -> 97.733492 | CY53: =+CY44+CY23 -> 97.900016 | CZ53: =+CZ44+CZ23 -> 95.202557 | ... DK53: =+DK44+DK23 -> 83.530337
D54: 52 | Q54: =+Q45+Q24 -> 100.51891 | R54: =+R45+R24 -> 101.85305 | S54: =+S45+S24 -> 102.75042 | T54: =+T45+T24 -> 105.78993 | U54: =+U45+U24 -> 106.5402 | V54: =+V45+V24 -> 107.18463 | W54: =+W45+W24 -> 109.33817 | X54: =+X45+X24 -> 112.73505 | ... AB54: =+AB45+AB24 -> 115.56869 | AC54: =+AC45+AC24-1 -> 113.95752 | AD54: =+AD45+AD24-1 -> 110.06946 | AE54: =+AE45+AE24-1 -> 109.58132 | AF54: =+AF45+AF24-1 -> 108.75865 | AG54: =+AG45+AG24-1 -> 108.19359 | AH54: =+AH45+AH24-1 -> 108.23066 | AI54: =+AI45+AI24-1 -> 90.0824 | AJ54: =+AJ45+AJ24-1 -> 89.269567 | ... AM54: =+AM45+AM24-1 -> 82.718533 | AN54: =+AN45+AN24-2 -> 80.101408 | AO54: =+AO45+AO24-2 -> 80.309969 | AP54: =+AP45+AP24-2 -> 80.978943 | AQ54: =+AQ45+AQ24-2 -> 80.11329 | AR54: =+AR45+AR24-2 -> 74.859703 | AS54: =+AS45+AS24-2 -> 68.993739 | AT54: =+AT45+AT24-2 -> 69.588884 | AU54: =+AU45+AU24-2 -> 69.845361 | ... AY54: =+AY45+AY24-2 -> 67.822029 | AZ54: =+AZ45+AZ24-3 -> 66.866222 | BA54: =+BA45+BA24-3 -> 70.827295 | BB54: =+BB45+BB24-3 -> 80.288291 | BC54: =+BC45+BC24-3 -> #N/A | BD54: =+BD45+BD24-3 -> #N/A | BE54: =+BE45+BE24-3 -> #N/A | BF54: =+BF45+BF24-3 -> #N/A | BG54: =+BG45+BG24-3 -> #N/A | ... BW54: =+BW45+BW24-3 -> 109.40655 | BX54: =+BX45+BX24 -> 111.07499 | BY54: =+BY45+BY24 -> 109.24202 | BZ54: =+BZ45+BZ24 -> 107.05441 | CA54: =+CA45+CA24 -> 107.75114 | CB54: =+CB45+CB24 -> 107.25955 | CC54: =+CC45+CC24 -> 109.8581 | CD54: =+CD45+CD24 -> 108.42084 | CE54: =+CE45+CE24 -> 103.50192 | ... CQ54: =+CQ45+CQ24 -> 120.69544 | CS54: =+CS45+CS24 -> 126.71428 | CT54: =+CT45+CT24 -> 107.90031 | CU54: =+CU45+CU24 -> 113.9822 | CV54: =+CV45+CV24 -> 117.15407 | CW54: =+CW45+CW24 -> 114.69613 | CX54: =+CX45+CX24 -> 112.47145 | CY54: =+CY45+CY24 -> 110.50464 | CZ54: =+CZ45+CZ24 -> 109.38241 | ... DK54: =+DK45+DK24 -> 93.032404
C56: Total (ARS) | D56: 24 | Q56: =+Q47*Q$14 -> 977.35047 | R56: =+R47*R$14 -> 1036.0223 | S56: =+S47*S$14 -> 1071.7709 | T56: =+T47*T$14 -> 1108.4109 | U56: =+U47*U$14 -> 1227.1094 | V56: =+V47*V$14 -> 1396.5571 | W56: =+W47*W$14 -> 1529.1833 | X56: =+X47*X$14 -> 1600.6472 | ... CQ56: =+CQ47*CQ$14 -> 49583.491 | CS56: =+CS47*CS$14 -> 57810.202 | CT56: =+CT47*CT$14 -> 51569.257 | CU56: =+CU47*CU$14 -> 54497.619 | CV56: =+CV47*CV$14 -> 57471.614 | CW56: =+CW47*CW$14 -> 58562.191 | CX56: =+CX47*CX$14 -> 59303.363 | CY56: =+CY47*CY$14 -> 59976.54 | CZ56: =+CZ47*CZ$14 -> 59079.124 | ... DK56: =+DK47*DK$14 -> 68103.093
D57: 30 | CS57: =+CS48*CS$14 -> 69506.54 | CT57: =+CT48*CT$14 -> 61676.783 | CU57: =+CU48*CU$14 -> 65128.07 | CV57: =+CV48*CV$14 -> 68643.095 | CW57: =+CW48*CW$14 -> 69953.158 | CX57: =+CX48*CX$14 -> 70903.273 | CY57: =+CY48*CY$14 -> 71558.695 | CZ57: =+CZ48*CZ$14 -> 70390.137 | ... DK57: =+DK48*DK$14 -> 80984.313
D58: 30.4 Virgen | CP58: =+CP49*CP$14 -> 66969.748 | CQ58: =+CQ49*CQ$14 -> 68227.255 | CS58: =+CS49*CS$14 -> 73200.745 | CT58: =+CT49*CT$14 -> 64155.448 | CU58: =+CU49*CU$14 -> 69203.462 | CV58: =+CV49*CV$14 -> 72143.547 | CW58: =+CW49*CW$14 -> 72255.545 | CX58: =+CX49*CX$14 -> 72215.503 | CY58: =+CY49*CY$14 -> 71680.414 | CZ58: =+CZ49*CZ$14 -> 71755.64 | ... DK58: =+DK49*DK$14 -> 80141.79
D59: 30.4 30% PCR | E59: 30% PCR | Q59: =+Q50*Q$14 -> 1150.8609 | R59: =+R50*R$14 -> 1223.8981 | S59: =+S50*S$14 -> 1268.4365 | T59: =+T50*T$14 -> 1307.9675 | U59: =+U50*U$14 -> 1455.4162 | V59: =+V50*V$14 -> 1665.8446 | W59: =+W50*W$14 -> 1831.1211 | X59: =+X50*X$14 -> 1920.9497 | ... CQ59: =+CQ50*CQ$14 -> 73238.918 | CS59: =+CS50*CS$14 -> 73200.745 | CT59: =+CT50*CT$14 -> 64155.448 | CU59: =+CU50*CU$14 -> 69203.462 | CV59: =+CV50*CV$14 -> 72143.547 | CW59: =+CW50*CW$14 -> 72255.545 | CX59: =+CX50*CX$14 -> 72215.503 | CY59: =+CY50*CY$14 -> 71680.414 | CZ59: =+CZ50*CZ$14 -> 71755.64 | ... DK59: =+DK50*DK$14 -> 80141.79
D60: 34 Virgen | CS60: =+CS51*CS$14 -> 80020.926 | CT60: =+CT51*CT$14 -> 69865.147 | CU60: =+CU51*CU$14 -> 75453.683 | CV60: =+CV51*CV$14 -> 78697.785 | CW60: =+CW51*CW$14 -> 78780.556 | CX60: =+CX51*CX$14 -> 78705.969 | CY60: =+CY51*CY$14 -> 78073.659 | CZ60: =+CZ51*CZ$14 -> 78130.454 | ... DK60: =+DK51*DK$14 -> 87042.014
D61: 34 30% PCR | E61: 30% PCR | CS61: =+CS52*CS$14 -> 80020.926 | CT61: =+CT52*CT$14 -> 69865.147 | CU61: =+CU52*CU$14 -> 75453.683 | CV61: =+CV52*CV$14 -> 78697.785 | CW61: =+CW52*CW$14 -> 78780.556 | CX61: =+CX52*CX$14 -> 78705.969 | CY61: =+CY52*CY$14 -> 78073.659 | CZ61: =+CZ52*CZ$14 -> 78130.454 | ... DK61: =+DK52*DK$14 -> 87042.014
D62: 44.8 | Q62: =+Q53*Q$14 -> 1681.2677 | R62: =+R53*R$14 -> 1788.8096 | S62: =+S53*S$14 -> 1854.3919 | T62: =+T53*T$14 -> 1911.2178 | U62: =+U53*U$14 -> 2128.3022 | V62: =+V53*V$14 -> 2438.1054 | W62: =+W53*W$14 -> 2681.4758 | X62: =+X53*X$14 -> 2813.8051 | ... CQ62: =+CQ53*CQ$14 -> 85904.593 | CS62: =+CS53*CS$14 -> 101085.59 | CT62: =+CT53*CT$14 -> 89290.87 | CU62: =+CU53*CU$14 -> 94544.357 | CV62: =+CV53*CV$14 -> 99931.352 | CW62: =+CW53*CW$14 -> 101810.26 | CX62: =+CX53*CX$14 -> 103084.4 | CY62: =+CY53*CY$14 -> 104214.57 | CZ62: =+CZ53*CZ$14 -> 102437.95 | ... DK62: =+DK53*DK$14 -> 117568.95
D63: 52 | Q63: =+Q54*Q$14 -> 1876.4669 | R63: =+R54*R$14 -> 2000.1699 | S63: =+S54*S$14 -> 2075.6407 | T63: =+T54*T$14 -> 2135.7189 | U63: =+U54*U$14 -> 2385.1475 | V63: =+V54*V$14 -> 2741.0539 | W63: =+W54*W$14 -> 3021.1558 | X63: =+X54*X$14 -> 3174.1454 | ... CQ63: =+CQ54*CQ$14 -> 112427.81 | CS63: =+CS54*CS$14 -> 120822.06 | CT63: =+CT54*CT$14 -> 105256.75 | CU63: =+CU54*CU$14 -> 113754.23 | CV63: =+CV54*CV$14 -> 118677.07 | CW63: =+CW54*CW$14 -> 118767.84 | CX63: =+CX54*CX$14 -> 118629.26 | CY63: =+CY54*CY$14 -> 117632.19 | CZ63: =+CZ54*CZ$14 -> 117695.47 | ... DK63: =+DK54*DK$14 -> 130943.11

Sheet Rolling
A1: Año | B1: 2024 | C1: 2024 | D1: 2024 | E1: 2024 | F1: 2024 | G1: 2025 | H1: 2025 | I1: 2025 | J1: 2025 | K1: 2025 | L1: 2025 | M1: 2025 | N1: 2025 | O1: 2025 | P1: 2025 | Q1: 2025 | R1: 2025 | S1: 2026 | T1: 2026 | U1: 2026 | V1: 2026 | W1: 2026 | X1: 2026
A2: Mes | B2: 8 | C2: 9 | D2: 10 | E2: 11 | F2: 12 | G2: 1 | H2: 2 | I2: 3 | J2: 4 | K2: 5 | L2: 6 | M2: 7 | N2: 8 | O2: 9 | P2: 10 | Q2: 11 | R2: 12 | S2: 1 | T2: =+S2+1 -> 2 | U2: =+T2+1 -> 3 | V2: =+U2+1 -> 4 | W2: =+V2+1 -> 5 | X2: =+W2+1 -> 6
A3: CSD Vinisa Ponderado
A4: Saldo inicial | B4: ='Balance Resinas'!B$5 -> 0 | C4: ='Balance Resinas'!$B10 -> 1873 | D4: ='Balance Resinas'!$B19 -> 1534.4669 | E4: ='Balance Resinas'!$B28 -> 1458.1914 | F4: ='Balance Resinas'!$B37 -> 1449.4772 | G4: ='Balance Resinas'!$B46 -> 1799.2018 | H4: ='Balance Resinas'!$B55 -> 1649.2846 | I4: ='Balance Resinas'!$B64 -> 1362.981 | J4: ='Balance Resinas'!$B73 -> 1177.7012 | K4: ='Balance Resinas'!$B82 -> 1173.7596 | L4: ='Balance Resinas'!$B90 -> 1457.1992 | M4: ='Balance Resinas'!$B99 -> 1312.7353 | N4: ='Balance Resinas'!$B108 -> 1413.5291 | O4: ='Balance Resinas'!$B117 -> 1648.3107 | P4: ='Balance Resinas'!$B126 -> 1752.8967 | Q4: ='Balance Resinas'!$B135 -> 1703.72 | R4: ='Balance Resinas'!$B144 -> 1650.9285 | S4: ='Balance Resinas'!$B153 -> 1542.863 | T4: ='Balance Resinas'!$B162 -> 1378.5559 | U4: =+T4+T6-T7 -> 1431.443 | V4: =+U4+U6-U7 -> 1143.285 | W4: =+V4+V6-V7 -> 1053.942 | X4: =+W4+W6-W7 -> 1246.4869
A5: Stock Inicial | B5: ='Balance Resinas'!B5 -> 0 | C5: ='Balance Resinas'!B9 -> 1873 | D5: ='Balance Resinas'!$B18 -> 1534.4669 | E5: ='Balance Resinas'!$B27 -> 1458.1914 | F5: ='Balance Resinas'!$B36 -> 1449.4772 | G5: ='Balance Resinas'!$B45 -> 1799.2018 | H5: ='Balance Resinas'!$B54 -> 1649.2846 | I5: ='Balance Resinas'!$B63 -> 1362.981 | J5: ='Balance Resinas'!$B72 -> 1177.7012 | K5: ='Balance Resinas'!$B81 -> 1173.7596 | L5: ='Balance Resinas'!$B90 -> 1457.1992 | M5: ='Balance Resinas'!$B99 -> 1312.7353 | N5: ='Balance Resinas'!$B108 -> 1413.5291 | O5: ='Balance Resinas'!$B117 -> 1648.3107 | P5: ='Balance Resinas'!$B126 -> 1752.8967 | Q5: ='Balance Resinas'!$B135 -> 1703.72 | R5: ='Balance Resinas'!$B144 -> 1650.9285 | S5: ='Balance Resinas'!$B153 -> 1542.863 | T5: ='Balance Resinas'!$B162 -> 1378.5559 | U5: =T4-T7+T6 -> 1431.443 | V5: =U4-U7+U6 -> 1143.285 | W5: =V4-V7+V6 -> 1053.942 | X5: =W4-W7+W6 -> 1246.4869
A6: Pedido Resina (Sin OC) | B6: 0 | C6: 1050 | D6: 1400 | E6: 1350 | F6: 1950 | G6: 1850 | H6: 1340 | I6: 1025 | J6: 930 | K6: 1280 | L6: 1250 | M6: 1552 | N6: 1400 | O6: 1700 | P6: 1700 | Q6: 1400 | R6: 1450 | S6: 1330 | T6: 1500 | U6: =+V7 -> 1141.3455 | V6: =+W7 -> 1052.0025 | W6: =+X7 -> 1244.5474 | X6: 1503
A7: Ventas | B7: ='Balance Resinas'!B8 -> 1602 | C7: ='Balance Resinas'!$B17 -> 1388.5331 | D7: ='Balance Resinas'!$B26 -> 1476.2756 | E7: ='Balance Resinas'!$B35 -> 1358.7141 | F7: ='Balance Resinas'!$B44 -> 1600.2754 | G7: ='Balance Resinas'!$B53 -> 1999.9173 | H7: ='Balance Resinas'!$B62 -> 1626.3035 | I7: ='Balance Resinas'!$B71 -> 1210.2798 | J7: ='Balance Resinas'!$B80 -> 933.94158 | K7: ='Balance Resinas'!B89 -> 996.56041 | L7: ='Balance Resinas'!$B98 -> 1394.4639 | M7: ='Balance Resinas'!$B107 -> 1451.2062 | N7: ='Balance Resinas'!$B116 -> 1165.2184 | O7: ='Balance Resinas'!$B125 -> 1595.414 | P7: ='Balance Resinas'!$B134 -> 1749.1767 | Q7: ='Balance Resinas'!$B143 -> 1452.7915 | R7: ='Balance Resinas'!$B152 -> 1558.0655 | S7: ='Balance Resinas'!$B161 -> 1494.307 | T7: ='Balance Resinas'!$B170 -> 1447.113 | U7: =FCST!AX$3 -> 1429.5035 | V7: =FCST!AY$3 -> 1141.3455 | W7: =FCST!AZ$3 -> 1052.0025 | X7: =FCST!BA$3 -> 1244.5474
A8: DOH (Resina + Preformas) | B8: =+B4/AVERAGE(B7)*30 -> 0 | C8: =+C4/AVERAGE(C7)*30 -> 40.467168 | D8: =+D4/AVERAGE(D7)*30 -> 31.18253 | E8: =+E4/AVERAGE(E7)*30 -> 32.196427 | F8: =+F4/AVERAGE(F7)*30 -> 27.173021 | G8: =+G4/AVERAGE(G7)*30 -> 26.989144 | H8: =+H4/AVERAGE(H7)*30 -> 30.423925 | I8: =+I4/AVERAGE(I7)*30 -> 33.785105 | ... X8: =+X4/AVERAGE(X7)*30 -> 30.046751
A10: Año | B10: =B1 -> 2024 | C10: =C1 -> 2024 | D10: =D1 -> 2024 | E10: =E1 -> 2024 | F10: =F1 -> 2024 | G10: =G1 -> 2025 | H10: =H1 -> 2025 | I10: =I1 -> 2025 | ... X10: =X1 -> 2026
A11: Mes | B11: =B2 -> 8 | C11: =C2 -> 9 | D11: =D2 -> 10 | E11: =E2 -> 11 | F11: =F2 -> 12 | G11: =G2 -> 1 | H11: =H2 -> 2 | I11: =I2 -> 3 | ... X11: =X2 -> 6
A12: HF Vinisa Ponderado
A13: Saldo inicial | B13: ='Balance Resinas'!F$5 -> 0 | C13: ='Balance Resinas'!$F10 -> 34.8544 | D13: ='Balance Resinas'!$F19 -> 84.8544 | E13: ='Balance Resinas'!$F28 -> 24.895193 | F13: ='Balance Resinas'!$F37 -> 24.895193 | G13: ='Balance Resinas'!$F46 -> 71.895193 | H13: ='Balance Resinas'!$F55 -> 21.375897 | I13: ='Balance Resinas'!$F64 -> 21.375897 | J13: ='Balance Resinas'!$F73 -> 31.800882 | K13: ='Balance Resinas'!$F82 -> 54.071008 | L13: ='Balance Resinas'!$F90 -> 41.400423 | M13: ='Balance Resinas'!$F100 -> 38.551554 | N13: ='Balance Resinas'!$F108 -> 16.791907 | O13: ='Balance Resinas'!$F117 -> 18.791907 | P13: ='Balance Resinas'!$F126 -> 37.671731 | Q13: ='Balance Resinas'!$F135 -> 18.912083 | R13: ='Balance Resinas'!$F144 -> 37.604048 | S13: ='Balance Resinas'!$F153 -> 19.404488 | T13: ='Balance Resinas'!$F162 -> 43.765016 | U13: =+T13+T15-T16 -> 24.885193 | V13: =+U13+U15-U16 -> 19.099298 | W13: =+V13+V15-V16 -> 37.885193 | X13: =+W13+W15-W16 -> 19.099298
A14: Stock Inicial | B14: ='Balance Resinas'!F$5 -> 0 | C14: ='Balance Resinas'!$F10 -> 34.8544 | D14: ='Balance Resinas'!$F19 -> 84.8544 | E14: ='Balance Resinas'!$F28 -> 24.895193 | F14: ='Balance Resinas'!$F37 -> 24.895193 | G14: ='Balance Resinas'!$F46 -> 71.895193 | H14: ='Balance Resinas'!$F55 -> 21.375897 | I14: ='Balance Resinas'!$F64 -> 21.375897 | J14: ='Balance Resinas'!$F73 -> 31.800882 | K14: ='Balance Resinas'!$F82 -> 54.071008 | L14: ='Balance Resinas'!$F90 -> 41.400423 | M14: ='Balance Resinas'!$F99 -> 38.551554 | N14: ='Balance Resinas'!$F108 -> 16.791907 | O14: ='Balance Resinas'!$F117 -> 18.791907 | P14: ='Balance Resinas'!$F126 -> 37.671731 | Q14: ='Balance Resinas'!$F135 -> 18.912083 | R14: ='Balance Resinas'!$F144 -> 37.604048 | S14: ='Balance Resinas'!$F153 -> 19.404488 | T14: ='Balance Resinas'!$F162 -> 43.765016 | U14: =T13-T16+T15 -> 24.885193 | V14: =U13-U16+U15 -> 19.099298 | W14: =V13-V16+V15 -> 37.885193 | X14: =W13-W16+W15 -> 19.099298
A15: Pedido Resina (Sin OC) | B15: 0 | C15: 50 | D15: 25 | E15: 0 | F15: 47 | G15: 25 | H15: 0 | I15: 50 | J15: 112 | K15: 23 | L15: 36 | M15: 16 | N15: 2 | O15: =+P16 -> 37.759648 | P15: 19 | Q15: 37.571789 | R15: 29 | S15: 81 | T15: 0 | U15: 13 | V15: =+W16 -> 37.571789 | W15: =+X16 -> 18.785894 | X15: 30
A16: Ventas | B16: ='Balance Resinas'!$F8 -> 38 | C16: ='Balance Resinas'!$F17 -> 0 | D16: ='Balance Resinas'!$F26 -> 84.959207 | E16: ='Balance Resinas'!$F35 -> 0 | F16: ='Balance Resinas'!$F44 -> 0 | G16: ='Balance Resinas'!$F53 -> 75.519295 | H16: ='Balance Resinas'!$F62 -> 0 | I16: ='Balance Resinas'!$F71 -> 39.575015 | J16: ='Balance Resinas'!$F80 -> 89.729873 | K16: ='Balance Resinas'!F89 -> 35.670586 | L16: ='Balance Resinas'!$F98 -> 38.848868 | M16: ='Balance Resinas'!$F107 -> 37.759648 | N16: ='Balance Resinas'!$F116 -> 0 | O16: ='Balance Resinas'!$F125 -> 18.879824 | P16: ='Balance Resinas'!$F134 -> 37.759648 | Q16: ='Balance Resinas'!$F143 -> 18.879824 | R16: ='Balance Resinas'!$F152 -> 47.19956 | S16: ='Balance Resinas'!$F161 -> 56.639472 | T16: ='Balance Resinas'!$F170 -> 18.879824 | U16: =FCST!CR$3 -> 18.785894 | V16: =FCST!CS$3 -> 18.785894 | W16: =FCST!CT$3 -> 37.571789 | X16: =FCST!CU$3 -> 18.785894
A17: DOH (Resina + Preformas) | B17: =IFERROR(+B13/AVERAGE(B16)*30,"") -> 0 | C17: =IFERROR(+C13/AVERAGE(C16)*30,"") | D17: =IFERROR(+D13/AVERAGE(D16)*30,"") -> 29.962991 | E17: =IFERROR(+E13/AVERAGE(E16)*30,"") | F17: =IFERROR(+F13/AVERAGE(F16)*30,"") | G17: =IFERROR(+G13/AVERAGE(G16)*30,"") -> 28.560327 | H17: =IFERROR(+H13/AVERAGE(H16)*30,"") | I17: =IFERROR(+I13/AVERAGE(I16)*30,"") -> 16.204085 | ... X17: =IFERROR(+X13/AVERAGE(X16)*30,"") -> 30.500488
A19: Año | B19: =B10 -> 2024 | C19: =C10 -> 2024 | D19: =D10 -> 2024 | E19: =E10 -> 2024 | F19: =F10 -> 2024 | G19: =G10 -> 2025 | H19: =H10 -> 2025 | I19: =I10 -> 2025 | ... X19: =X10 -> 2026
A20: Mes | B20: =B11 -> 8 | C20: =C11 -> 9 | D20: =D11 -> 10 | E20: =E11 -> 11 | F20: =F11 -> 12 | G20: =G11 -> 1 | H20: =H11 -> 2 | I20: =I11 -> 3 | ... X20: =X11 -> 6
A21: HF Amcor Ponderado
A22: Saldo inicial | B22: ='Balance Resinas'!J$5 -> 0 | C22: ='Balance Resinas'!$J10 -> 300 | D22: ='Balance Resinas'!$J19 -> 403.54062 | E22: ='Balance Resinas'!$J28 -> 417.41983 | F22: ='Balance Resinas'!$J37 -> 399.09818 | G22: ='Balance Resinas'!$J46 -> 409.4911 | H22: ='Balance Resinas'!$J55 -> 435.30017 | I22: ='Balance Resinas'!$J64 -> 361.0199 | J22: ='Balance Resinas'!$J73 -> 296.35341 | K22: ='Balance Resinas'!$J82 -> 269.32763 | L22: ='Balance Resinas'!$J91 -> 431.87714 | M22: ='Balance Resinas'!$J100 -> 307.27644 | N22: ='Balance Resinas'!$J109 -> 290.50084 | O22: ='Balance Resinas'!$J117 -> 213.25457 | P22: ='Balance Resinas'!$J126 -> 228.42707 | Q22: ='Balance Resinas'!$J135 -> 205.25186 | R22: ='Balance Resinas'!$J144 -> 264.87329 | S22: ='Balance Resinas'!$J153 -> 264.2539 | T22: ='Balance Resinas'!$J162 -> 194.64664 | U22: =+T22+T24-T25 -> 233.37507 | V22: =+U22+U24-U25 -> 118.79868 | W22: =+V22+V24-V25 -> 116.09801 | X22: =+W22+W24-W25 -> 313.80159
A23: Stock Inicial | B23: ='Balance Resinas'!J$5 -> 0 | C23: ='Balance Resinas'!J$10 -> 300 | D23: ='Balance Resinas'!$J$19 -> 403.54062 | E23: ='Balance Resinas'!$J28 -> 417.41983 | F23: ='Balance Resinas'!$J$37 -> 399.09818 | G23: ='Balance Resinas'!$J$45 -> 409.4911 | H23: ='Balance Resinas'!$J$54 -> 435.30017 | I23: ='Balance Resinas'!$J$63 -> 361.0199 | J23: ='Balance Resinas'!$J$72 -> 296.35341 | K23: ='Balance Resinas'!$J$81 -> 269.32763 | L23: ='Balance Resinas'!$J$90 -> 431.87714 | M23: ='Balance Resinas'!$J$99 -> 307.27644 | N23: ='Balance Resinas'!$J$108 -> 290.50084 | O23: ='Balance Resinas'!$J$117 -> 213.25457 | P23: ='Balance Resinas'!$J$126 -> 228.42707 | Q23: ='Balance Resinas'!$J$135 -> 205.25186 | R23: ='Balance Resinas'!$J$144 -> 264.87329 | S23: ='Balance Resinas'!$J$153 -> 264.2539 | T23: ='Balance Resinas'!$J$162 -> 194.64664 | U23: =T22-T25+T24 -> 233.37507 | V23: =U22-U25+U24 -> 118.79868 | W23: =V22-V25+V24 -> 116.09801 | X23: =W22-W25+W24 -> 313.80159
A24: Pedido Resina (Sin OC) | B24: 0 | C24: 475 | D24: 375 | E24: 400 | F24: 400 | G24: 350 | H24: 300 | I24: 180 | J24: 320 | K24: 565 | L24: 140 | M24: 250 | N24: 220 | O24: 200 | P24: 110 | Q24: 300 | R24: 190 | S24: 265 | T24: 260 | U24: =+V25 -> 119.97773 | V24: =+W25 -> 117.27706 | W24: =+X25 -> 314.98063 | X24: 163
A25: Ventas | B25: ='Balance Resinas'!$J8 -> 300 | C25: ='Balance Resinas'!$J17 -> 371.45938 | D25: ='Balance Resinas'!$J26 -> 361.12078 | E25: ='Balance Resinas'!$J35 -> 418.32165 | F25: ='Balance Resinas'!$J44 -> 389.60708 | G25: ='Balance Resinas'!$J53 -> 324.19094 | H25: ='Balance Resinas'!$J62 -> 374.28027 | I25: ='Balance Resinas'!$J71 -> 244.66649 | J25: ='Balance Resinas'!$J80 -> 347.02578 | K25: ='Balance Resinas'!J89 -> 402.4505 | L25: ='Balance Resinas'!$J98 -> 264.6007 | M25: ='Balance Resinas'!$J107 -> 266.77559 | N25: ='Balance Resinas'!$J116 -> 297.24627 | O25: ='Balance Resinas'!$J125 -> 184.82751 | P25: ='Balance Resinas'!$J134 -> 133.1752 | Q25: ='Balance Resinas'!$J143 -> 240.37857 | R25: ='Balance Resinas'!$J152 -> 190.6194 | S25: ='Balance Resinas'!$J161 -> 334.60726 | T25: ='Balance Resinas'!$J170 -> 221.27157 | U25: =FCST!CR2 -> 234.55411 | V25: =FCST!CS2 -> 119.97773 | W25: =FCST!CT2 -> 117.27706 | X25: =FCST!CU2 -> 314.98063
A26: DOH (Resina + Preformas) | B26: =IFERROR(+B22/AVERAGE(B25)*30,"") -> 0 | C26: =IFERROR(+C22/AVERAGE(C25)*30,"") -> 24.228759 | D26: =IFERROR(+D22/AVERAGE(D25)*30,"") -> 33.524015 | E26: =IFERROR(+E22/AVERAGE(E25)*30,"") -> 29.935326 | F26: =IFERROR(+F22/AVERAGE(F25)*30,"") -> 30.730821 | G26: =IFERROR(+G22/AVERAGE(G25)*30,"") -> 37.893512 | H26: =IFERROR(+H22/AVERAGE(H25)*30,"") -> 34.890979 | I26: =IFERROR(+I22/AVERAGE(I25)*30,"") -> 44.266777 | ... X26: =IFERROR(+X22/AVERAGE(X25)*30,"") -> 29.887703
A28: Año | B28: =B19 -> 2024 | C28: =C19 -> 2024 | D28: =D19 -> 2024 | E28: =E19 -> 2024 | F28: =F19 -> 2024 | G28: =G19 -> 2025 | H28: =H19 -> 2025 | I28: =I19 -> 2025 | ... X28: =X19 -> 2026
A29: Mes | B29: =B20 -> 8 | C29: =C20 -> 9 | D29: =D20 -> 10 | E29: =E20 -> 11 | F29: =F20 -> 12 | G29: =G20 -> 1 | H29: =H20 -> 2 | I29: =I20 -> 3 | ... X29: =X20 -> 6
A30: PCR Amcor Ponderado
