Workbook

Sheet Motupe Preformas
G1: PR | H1: CC | J1: Fee
C5: CLIENTE | D5: ABI Backus
C6: PAÍS : | D6: Perú
C7: PERÍODO : | D7: Abril 26
C8: Actualización: | D8: Mensual
G10: FORMULA PRECIOS PREFORMAS MOTUPE - CON CP
C12: Precio de Resina | E12: USD/TM
C13: vPET | E13: =Inputs!H13 -> 1048.5
C14: rPET | E14: =Inputs!P10 -> 1418.108
P17: Flete USD | Q17: =Inputs!X9 -> 2076.16
S18: Base
B19: Key | C19: Formato | D19: Gramaje | E19: Color | F19: %rPET | G19: Resina (US$/Millar) | H19: Valor Fijo Preforma EXW (US$/millar) | I19: Precio Preforma EXW (US$/millar) | J19: Fee (US$/millar) | K19: Precio Preforma EXW + Fee (US$/millar) | L19: Flete (US$/millar) | M19: Precio Preforma DDP + Fee (US$/millar) | O19: Millar/caja | P19: Camión | Q19: Flete Unitario | S19: Valor Fijo Preforma EXW (US$/millar)
A20: =D20&E20 -> 17.7Clear | B20: =D20&E20&F20 -> 17.7Clear0.25 | C20: 330 | D20: 17.7 | E20: Clear | F20: 0.25 | G20: =+($E$13/1000*(1-F20)+$E$14/1000*F20)*D20*(1+0.5%) -> 20.294935 | H20: =S20*(1+(Inputs!AH$8/Inputs!AH$7-1)*50%) -> 7.2369856 | I20: =+H20+G20 -> 27.531921 | K20: =J20+I20 -> 27.531921 | L20: =Q20 -> 2.2181197 | M20: =SUM(K20:L20) -> 29.75004 | O20: 19.5 | P20: 48 | Q20: =$Q$17/(O20*P20) -> 2.2181197 | S20: 7.2369856
A21: =D21&E21 -> 17.7Clear | B21: =D21&E21&F21 -> 17.7Clear0.6 | D21: 17.7 | E21: Clear | F21: 0.6 | G21: =+($E$13/1000*(1-F21)+$E$14/1000*F21)*D21*(1+0.5%) -> 22.596105 | H21: =S21*(1+(Inputs!AH$8/Inputs!AH$7-1)*50%) -> 7.2369856 | I21: =+H21+G21 -> 29.833091 | K21: =J21+I21 -> 29.833091 | L21: =Q21 -> 2.2181197 | M21: =SUM(K21:L21) -> 32.05121 | O21: 19.5 | P21: 48 | Q21: =$Q$17/(O21*P21) -> 2.2181197 | S21: 7.2369856
A22: =D22&E22 -> 17.7Clear | B22: =D22&E22&F22 -> 17.7Clear0.15 | D22: 17.7 | E22: Clear | F22: 0.15 | G22: =+($E$13/1000*(1-F22)+$E$14/1000*F22)*D22*(1+0.5%) -> 19.637458 | H22: =S22*(1+(Inputs!AH$8/Inputs!AH$7-1)*50%) -> 7.2369856 | I22: =+H22+G22 -> 26.874444 | K22: =J22+I22 -> 26.874444 | L22: =Q22 -> 2.2181197 | M22: =SUM(K22:L22) -> 29.092563 | O22: 19.5 | P22: 48 | Q22: =$Q$17/(O22*P22) -> 2.2181197 | S22: 7.2369856
A23: =D23&E23 -> 19.7Clear | B23: =D23&E23&F23 -> 19.7Clear0.25 | C23: 450/500/600/650 | D23: 19.7 | E23: Clear | F23: 0.25 | G23: =+($E$13/1000*(1-F23)+$E$14/1000*F23)*D23*(1+0.5%) -> 22.588148 | H23: =S23*(1+(Inputs!AH$8/Inputs!AH$7-1)*50%) -> 7.2369856 | I23: =+H23+G23 -> 29.825134 | J23: 0.48862372 | K23: =J23+I23 -> 30.313757 | L23: =Q23 -> 2.2181197 | M23: =SUM(K23:L23) -> 32.531877 | O23: 19.5 | P23: 48 | Q23: =$Q$17/(O23*P23) -> 2.2181197 | S23: 7.2369856
A24: =D24&E24 -> 19.7Clear | B24: =D24&E24&F24 -> 19.7Clear0.5 | D24: 19.7 | E24: Clear | F24: 0.5 | G24: =+($E$13/1000*(1-F24)+$E$14/1000*F24)*D24*(1+0.5%) -> 24.417569 | H24: =S24*(1+(Inputs!AH$8/Inputs!AH$7-1)*50%) -> 7.2369856 | I24: =+H24+G24 -> 31.654555 | J24: 0.48862372 | K24: =J24+I24 -> 32.143178 | L24: =Q24 -> 2.2181197 | M24: =SUM(K24:L24) -> 34.361298 | O24: 19.5 | P24: 48 | Q24: =$Q$17/(O24*P24) -> 2.2181197 | S24: 7.2369856
A25: =D25&E25 -> 19.7Clear | B25: =D25&E25&F25 -> 19.7Clear0.6 | D25: 19.7 | E25: Clear | F25: 0.6 | G25: =+($E$13/1000*(1-F25)+$E$14/1000*F25)*D25*(1+0.5%) -> 25.149337 | H25: =S25*(1+(Inputs!AH$8/Inputs!AH$7-1)*50%) -> 7.2369856 | I25: =+H25+G25 -> 32.386323 | J25: 0.48862372 | K25: =J25+I25 -> 32.874947 | L25: =Q25 -> 2.2181197 | M25: =SUM(K25:L25) -> 35.093066 | O25: 19.5 | P25: 48 | Q25: =$Q$17/(O25*P25) -> 2.2181197 | S25: 7.2369856
A26: =D26&E26 -> 19.7Brown | B26: =D26&E26&F26 -> 19.7Brown0.5 | D26: 19.7 | E26: Brown | F26: 0.5 | G26: =+($E$13/1000*(1-F26)+$E$14/1000*F26)*D26*(1+0.5%) -> 24.417569 | H26: =S26*(1+(Inputs!AH$8/Inputs!AH$7-1)*50%) -> 8.8522419 | I26: =+H26+G26 -> 33.269811 | K26: =J26+I26 -> 33.269811 | L26: =Q26 -> 2.2181197 | M26: =SUM(K26:L26) -> 35.487931 | O26: 19.5 | P26: 48 | Q26: =$Q$17/(O26*P26) -> 2.2181197 | S26: 8.8522419
A27: =D27&E27 -> 19.7Brown | B27: =D27&E27&F27 -> 19.7Brown0.6 | D27: 19.7 | E27: Brown | F27: 0.6 | G27: =+($E$13/1000*(1-F27)+$E$14/1000*F27)*D27*(1+0.5%) -> 25.149337 | H27: =S27*(1+(Inputs!AH$8/Inputs!AH$7-1)*50%) -> 8.8522419 | I27: =+H27+G27 -> 34.001579 | K27: =J27+I27 -> 34.001579 | L27: =Q27 -> 2.2181197 | M27: =SUM(K27:L27) -> 36.219699 | O27: 19.5 | P27: 48 | Q27: =$Q$17/(O27*P27) -> 2.2181197 | S27: 8.8522419
A28: =D28&E28 -> 19.7Brown | B28: =D28&E28&F28 -> 19.7Brown1 | D28: 19.7 | E28: Brown | F28: 1 | G28: =+($E$13/1000*(1-F28)+$E$14/1000*F28)*D28*(1+0.5%) -> 28.076411 | H28: =S28*(1+(Inputs!AH$8/Inputs!AH$7-1)*50%) -> 8.8522419 | I28: =+H28+G28 -> 36.928653 | K28: =J28+I28 -> 36.928653 | L28: =Q28 -> 2.2181197 | M28: =SUM(K28:L28) -> 39.146772 | O28: 19.5 | P28: 48 | Q28: =$Q$17/(O28*P28) -> 2.2181197 | S28: 8.8522419
A29: =D29&E29 -> 33.7Clear | B29: =D29&E29&F29 -> 33.7Clear0.25 | C29: 1000 | D29: 33.7 | E29: Clear | F29: 0.25 | G29: =+($E$13/1000*(1-F29)+$E$14/1000*F29)*D29*(1+0.5%) -> 38.640639 | H29: =S29*(1+(Inputs!AH$8/Inputs!AH$7-1)*50%) -> 10.55124 | I29: =+H29+G29 -> 49.191879 | K29: =J29+I29 -> 49.191879 | L29: =Q29 -> 3.7611594 | M29: =SUM(K29:L29) -> 52.953039 | O29: 11.5 | P29: 48 | Q29: =$Q$17/(O29*P29) -> 3.7611594 | S29: 10.55124
A30: =D30&E30 -> 45.7Clear | B30: =D30&E30&F30 -> 45.7Clear0.25 | C30: 2000 | D30: 45.7 | E30: Clear | F30: 0.25 | G30: =+($E$13/1000*(1-F30)+$E$14/1000*F30)*D30*(1+0.5%) -> 52.399917 | H30: =S30*(1+(Inputs!AH$8/Inputs!AH$7-1)*50%) -> 14.668166 | I30: =+H30+G30 -> 67.068083 | K30: =J30+I30 -> 67.068083 | L30: =Q30 -> 5.1492063 | M30: =SUM(K30:L30) -> 72.217289 | O30: 8.4 | P30: 48 | Q30: =$Q$17/(O30*P30) -> 5.1492063 | S30: 14.668166
A31: =D31&E31 -> 45.7Clear | B31: =D31&E31&F31 -> 45.7Clear0.5 | D31: 45.7 | E31: Clear | F31: 0.5 | G31: =+($E$13/1000*(1-F31)+$E$14/1000*F31)*D31*(1+0.5%) -> 56.643802 | H31: =S31*(1+(Inputs!AH$8/Inputs!AH$7-1)*50%) -> 14.668166 | I31: =+H31+G31 -> 71.311968 | K31: =J31+I31 -> 71.311968 | L31: =Q31 -> 5.1492063 | M31: =SUM(K31:L31) -> 76.461174 | O31: 8.4 | P31: 48 | Q31: =$Q$17/(O31*P31) -> 5.1492063 | S31: 14.668166
A32: =D32&E32 -> 51.2Clear | B32: =D32&E32&F32 -> 51.2Clear0.25 | C32: 3000 | D32: 51.2 | E32: Clear | F32: 0.25 | G32: =+($E$13/1000*(1-F32)+$E$14/1000*F32)*D32*(1+0.5%) -> 58.706253 | H32: =S32*(1+(Inputs!AH$8/Inputs!AH$7-1)*50%) -> 12.25 | I32: =+H32+G32 -> 70.956253 | K32: =J32+I32 -> 70.956253 | L32: =Q32 -> 5.845045 | M32: =SUM(K32:L32) -> 76.801298 | O32: 7.4 | P32: 48 | Q32: =$Q$17/(O32*P32) -> 5.845045 | S32: 12.25
A33: =D33&E33 -> 54.7Clear | B33: =D33&E33&F33 -> 54.7Clear0.25 | D33: 54.7 | E33: Clear | F33: 0.25 | G33: =+($E$13/1000*(1-F33)+$E$14/1000*F33)*D33*(1+0.5%) -> 62.719376 | H33: =S33*(1+(Inputs!AH$8/Inputs!AH$7-1)*50%) -> 13 | I33: =+H33+G33 -> 75.719376 | K33: =J33+I33 -> 75.719376 | L33: =Q33 -> 5.845045 | M33: =SUM(K33:L33) -> 81.564421 | O33: 7.4 | P33: 48 | Q33: =$Q$17/(O33*P33) -> 5.845045 | S33: 13

Sheet Ate Preformas
G1: PR | H1: CC | J1: Fee
C5: CLIENTE | D5: ABI Backus
C6: PAÍS : | D6: Perú
C7: PERÍODO : | D7: =+'Motupe Preformas'!D7 -> Abril 26
C8: Actualización: | D8: Mensual
G10: FORMULA PRECIOS PREFORMAS ATE - CON CP
C12: Precio de Resina | E12: USD/TM
C13: vPET | E13: =Inputs!H13 -> 1048.5
C14: rPET | E14: =Inputs!P10 -> 1418.108
P17: Flete USD | Q17: =Inputs!X7 -> 133.16
V18: Base
B19: Key | C19: Formato | D19: Gramaje | E19: Color | F19: %rPET | G19: Resina (US$/Millar) | H19: Valor Fijo Preforma EXW (US$/millar) | I19: Precio Preforma EXW (US$/millar) | J19: Fee (US$/millar) | K19: Precio Preforma EXW + Fee (US$/millar) | L19: Flete (US$/millar) | M19: Precio Preforma DDP + Fee (US$/millar) | O19: Millar/caja | P19: Camión | Q19: Flete Unitario | V19: Valor Fijo Preforma EXW (US$/millar)
A20: =D20&E20 -> 17.7Clear | B20: =D20&E20&F20 -> 17.7Clear0.25 | C20: 330 | D20: 17.7 | E20: Clear | F20: 0.25 | G20: =+($E$13/1000*(1-F20)+$E$14/1000*F20)*D20*(1+0.5%) -> 20.294935 | H20: =V20*(1+(Inputs!AH$8/Inputs!AH$7-1)*50%) -> 7.2369856 | I20: =+H20+G20 -> 27.531921 | K20: =J20+I20 -> 27.531921 | L20: =Q20 -> 0.17071795 | M20: =SUM(K20:L20) -> 27.702639 | O20: 19.5 | P20: 40 | Q20: =$Q$17/(O20*P20) -> 0.17071795 | V20: 7.2369856
A21: =D21&E21 -> 17.7Clear | B21: =D21&E21&F21 -> 17.7Clear0 | D21: 17.7 | E21: Clear | F21: 0 | G21: =+($E$13/1000*(1-F21)+$E$14/1000*F21)*D21*(1+0.5%) -> 18.651242 | H21: =V21*(1+(Inputs!AH$8/Inputs!AH$7-1)*50%) -> 7.2369856 | I21: =+H21+G21 -> 25.888228 | K21: =J21+I21 -> 25.888228 | L21: =Q21 -> 0.17071795 | M21: =SUM(K21:L21) -> 26.058946 | O21: 19.5 | P21: 40 | Q21: =$Q$17/(O21*P21) -> 0.17071795 | V21: 7.2369856
A22: =D22&E22 -> 17.7Clear | B22: =D22&E22&F22 -> 17.7Clear0.6 | D22: 17.7 | E22: Clear | F22: 0.6 | G22: =+($E$13/1000*(1-F22)+$E$14/1000*F22)*D22*(1+0.5%) -> 22.596105 | H22: =V22*(1+(Inputs!AH$8/Inputs!AH$7-1)*50%) -> 7.2369856 | I22: =+H22+G22 -> 29.833091 | K22: =J22+I22 -> 29.833091 | L22: =Q22 -> 0.17071795 | M22: =SUM(K22:L22) -> 30.003809 | O22: 19.5 | P22: 40 | Q22: =$Q$17/(O22*P22) -> 0.17071795 | V22: 7.2369856
A23: =D23&E23 -> 17.7Clear | B23: =D23&E23&F23 -> 17.7Clear0.15 | D23: 17.7 | E23: Clear | F23: 0.15 | G23: =+($E$13/1000*(1-F23)+$E$14/1000*F23)*D23*(1+0.5%) -> 19.637458 | H23: =V23*(1+(Inputs!AH$8/Inputs!AH$7-1)*50%) -> 7.2369856 | I23: =+H23+G23 -> 26.874444 | K23: =J23+I23 -> 26.874444 | L23: =Q23 -> 0.17071795 | M23: =SUM(K23:L23) -> 27.045162 | O23: 19.5 | P23: 40 | Q23: =$Q$17/(O23*P23) -> 0.17071795 | V23: 7.2369856
A24: =D24&E24 -> 19.7Clear | B24: =D24&E24&F24 -> 19.7Clear0.25 | C24: 450/500/600/650 | D24: 19.7 | E24: Clear | F24: 0.25 | G24: =+($E$13/1000*(1-F24)+$E$14/1000*F24)*D24*(1+0.5%) -> 22.588148 | H24: =V24*(1+(Inputs!AH$8/Inputs!AH$7-1)*50%) -> 7.2369856 | I24: =+H24+G24 -> 29.825134 | J24: 0.48862372 | K24: =J24+I24 -> 30.313757 | L24: =Q24 -> 0.17071795 | M24: =SUM(K24:L24) -> 30.484475 | O24: 19.5 | P24: 40 | Q24: =$Q$17/(O24*P24) -> 0.17071795 | V24: 7.2369856
A25: =D25&E25 -> 19.7Clear | B25: =D25&E25&F25 -> 19.7Clear0.15 | D25: 19.7 | E25: Clear | F25: 0.15 | G25: =+($E$13/1000*(1-F25)+$E$14/1000*F25)*D25*(1+0.5%) -> 21.85638 | H25: =V25*(1+(Inputs!AH$8/Inputs!AH$7-1)*50%) -> 7.2369856 | I25: =+H25+G25 -> 29.093365 | J25: 0.48862372 | K25: =J25+I25 -> 29.581989 | L25: =Q25 -> 0.17071795 | M25: =SUM(K25:L25) -> 29.752707 | O25: 19.5 | P25: 40 | Q25: =$Q$17/(O25*P25) -> 0.17071795 | V25: 7.2369856
A26: =D26&E26 -> 19.7Clear | B26: =D26&E26&F26 -> 19.7Clear0.5 | D26: 19.7 | E26: Clear | F26: 0.5 | G26: =+($E$13/1000*(1-F26)+$E$14/1000*F26)*D26*(1+0.5%) -> 24.417569 | H26: =V26*(1+(Inputs!AH$8/Inputs!AH$7-1)*50%) -> 7.2369856 | I26: =+H26+G26 -> 31.654555 | J26: 0.48862372 | K26: =J26+I26 -> 32.143178 | L26: =Q26 -> 0.17071795 | M26: =SUM(K26:L26) -> 32.313896 | O26: 19.5 | P26: 40 | Q26: =$Q$17/(O26*P26) -> 0.17071795 | V26: 7.2369856
A27: =D27&E27 -> 19.7Clear | B27: =D27&E27&F27 -> 19.7Clear0.6 | D27: 19.7 | E27: Clear | F27: 0.6 | G27: =+($E$13/1000*(1-F27)+$E$14/1000*F27)*D27*(1+0.5%) -> 25.149337 | H27: =V27*(1+(Inputs!AH$8/Inputs!AH$7-1)*50%) -> 7.2369856 | I27: =+H27+G27 -> 32.386323 | J27: 0.48862372 | K27: =J27+I27 -> 32.874947 | L27: =Q27 -> 0.17071795 | M27: =SUM(K27:L27) -> 33.045665 | O27: 19.5 | P27: 40 | Q27: =$Q$17/(O27*P27) -> 0.17071795 | V27: 7.2369856
A28: =D28&E28 -> 19.7Brown | B28: =D28&E28&F28 -> 19.7Brown0.5 | D28: 19.7 | E28: Brown | F28: 0.5 | G28: =+($E$13/1000*(1-F28)+$E$14/1000*F28)*D28*(1+0.5%) -> 24.417569 | H28: =V28*(1+(Inputs!AH$8/Inputs!AH$7-1)*50%) -> 8.8522419 | I28: =+H28+G28 -> 33.269811 | K28: =J28+I28 -> 33.269811 | L28: =Q28 -> 0.17071795 | M28: =SUM(K28:L28) -> 33.440529 | O28: 19.5 | P28: 40 | Q28: =$Q$17/(O28*P28) -> 0.17071795 | V28: 8.8522419
A29: =D29&E29 -> 19.7Brown | B29: =D29&E29&F29 -> 19.7Brown0.6 | D29: 19.7 | E29: Brown | F29: 0.6 | G29: =+($E$13/1000*(1-F29)+$E$14/1000*F29)*D29*(1+0.5%) -> 25.149337 | H29: =V29*(1+(Inputs!AH$8/Inputs!AH$7-1)*50%) -> 8.8522419 | I29: =+H29+G29 -> 34.001579 | K29: =J29+I29 -> 34.001579 | L29: =Q29 -> 0.17071795 | M29: =SUM(K29:L29) -> 34.172297 | O29: 19.5 | P29: 40 | Q29: =$Q$17/(O29*P29) -> 0.17071795 | V29: 8.8522419
A30: =D30&E30 -> 19.7Brown | B30: =D30&E30&F30 -> 19.7Brown1 | D30: 19.7 | E30: Brown | F30: 1 | G30: =+($E$13/1000*(1-F30)+$E$14/1000*F30)*D30*(1+0.5%) -> 28.076411 | H30: =V30*(1+(Inputs!AH$8/Inputs!AH$7-1)*50%) -> 8.8522419 | I30: =+H30+G30 -> 36.928653 | K30: =J30+I30 -> 36.928653 | L30: =Q30 -> 0.17071795 | M30: =SUM(K30:L30) -> 37.099371 | O30: 19.5 | P30: 40 | Q30: =$Q$17/(O30*P30) -> 0.17071795 | V30: 8.8522419
A31: =D31&E31 -> 33.7Clear | B31: =D31&E31&F31 -> 33.7Clear0.25 | C31: 1000 | D31: 33.7 | E31: Clear | F31: 0.25 | G31: =+($E$13/1000*(1-F31)+$E$14/1000*F31)*D31*(1+0.5%) -> 38.640639 | H31: =V31*(1+(Inputs!AH$8/Inputs!AH$7-1)*50%) -> 10.55124 | I31: =+H31+G31 -> 49.191879 | K31: =J31+I31 -> 49.191879 | L31: =Q31 -> 0.28947826 | M31: =SUM(K31:L31) -> 49.481358 | O31: 11.5 | P31: 40 | Q31: =$Q$17/(O31*P31) -> 0.28947826 | V31: 10.55124
A32: =D32&E32 -> 33.7Clear | B32: =D32&E32&F32 -> 33.7Clear0.15 | C32: 1000 | D32: 33.7 | E32: Clear | F32: 0.15 | G32: =+($E$13/1000*(1-F32)+$E$14/1000*F32)*D32*(1+0.5%) -> 37.388832 | H32: =V32*(1+(Inputs!AH$8/Inputs!AH$7-1)*50%) -> 10.55124 | I32: =+H32+G32 -> 47.940073 | K32: =J32+I32 -> 47.940073 | L32: =Q32 -> 0.28947826 | M32: =SUM(K32:L32) -> 48.229551 | O32: 11.5 | P32: 40 | Q32: =$Q$17/(O32*P32) -> 0.28947826 | V32: 10.55124
A33: =D33&E33 -> 45.7Clear | B33: =D33&E33&F33 -> 45.7Clear0.15 | C33: 2000 | D33: 45.7 | E33: Clear | F33: 0.15 | G33: =+($E$13/1000*(1-F33)+$E$14/1000*F33)*D33*(1+0.5%) -> 50.702363 | H33: =V33*(1+(Inputs!AH$8/Inputs!AH$7-1)*50%) -> 14.668166 | I33: =+H33+G33 -> 65.370529 | K33: =J33+I33 -> 65.370529 | L33: =Q33 -> 0.39630952 | M33: =SUM(K33:L33) -> 65.766839 | O33: 8.4 | P33: 40 | Q33: =$Q$17/(O33*P33) -> 0.39630952 | V33: 14.668166
A34: =D34&E34 -> 45.7Clear | B34: =D34&E34&F34 -> 45.7Clear0.25 | D34: 45.7 | E34: Clear | F34: 0.25 | G34: =+($E$13/1000*(1-F34)+$E$14/1000*F34)*D34*(1+0.5%) -> 52.399917 | H34: =V34*(1+(Inputs!AH$8/Inputs!AH$7-1)*50%) -> 14.668166 | I34: =+H34+G34 -> 67.068083 | K34: =J34+I34 -> 67.068083 | L34: =Q34 -> 0.39630952 | M34: =SUM(K34:L34) -> 67.464393 | O34: 8.4 | P34: 40 | Q34: =$Q$17/(O34*P34) -> 0.39630952 | V34: 14.668166
A35: =D35&E35 -> 45.7Clear | B35: =D35&E35&F35 -> 45.7Clear0.5 | D35: 45.7 | E35: Clear | F35: 0.5 | G35: =+($E$13/1000*(1-F35)+$E$14/1000*F35)*D35*(1+0.5%) -> 56.643802 | H35: =V35*(1+(Inputs!AH$8/Inputs!AH$7-1)*50%) -> 14.668166 | I35: =+H35+G35 -> 71.311968 | K35: =J35+I35 -> 71.311968 | L35: =Q35 -> 0.39630952 | M35: =SUM(K35:L35) -> 71.708277 | O35: 8.4 | P35: 40 | Q35: =$Q$17/(O35*P35) -> 0.39630952 | V35: 14.668166
A36: =D36&E36 -> 51.2Clear | B36: =D36&E36&F36 -> 51.2Clear0.15 | C36: 3000 | D36: 51.2 | E36: Clear | F36: 0.15 | G36: =+($E$13/1000*(1-F36)+$E$14/1000*F36)*D36*(1+0.5%) -> 56.804398 | H36: =V36*(1+(Inputs!AH$8/Inputs!AH$7-1)*50%) -> 12.25 | I36: =+H36+G36 -> 69.054398 | K36: =J36+I36 -> 69.054398 | L36: =Q36 -> 0.44986486 | M36: =SUM(K36:L36) -> 69.504263 | O36: 7.4 | P36: 40 | Q36: =$Q$17/(O36*P36) -> 0.44986486 | V36: 12.25
A37: =D37&E37 -> 51.2Clear | B37: =D37&E37&F37 -> 51.2Clear0.25 | D37: 51.2 | E37: Clear | F37: 0.25 | G37: =+($E$13/1000*(1-F37)+$E$14/1000*F37)*D37*(1+0.5%) -> 58.706253 | H37: =V37*(1+(Inputs!AH$8/Inputs!AH$7-1)*50%) -> 12.25 | I37: =+H37+G37 -> 70.956253 | K37: =J37+I37 -> 70.956253 | L37: =Q37 -> 0.44986486 | M37: =SUM(K37:L37) -> 71.406118 | O37: 7.4 | P37: 40 | Q37: =$Q$17/(O37*P37) -> 0.44986486 | V37: 12.25
A38: =D38&E38 -> 54.7Clear | B38: =D38&E38&F38 -> 54.7Clear0.15 | D38: 54.7 | E38: Clear | F38: 0.15 | G38: =+($E$13/1000*(1-F38)+$E$14/1000*F38)*D38*(1+0.5%) -> 60.687511 | H38: =V38*(1+(Inputs!AH$8/Inputs!AH$7-1)*50%) -> 13 | I38: =+H38+G38 -> 73.687511 | K38: =J38+I38 -> 73.687511 | L38: =Q38 -> 0.44986486 | M38: =SUM(K38:L38) -> 74.137376 | O38: 7.4 | P38: 40 | Q38: =$Q$17/(O38*P38) -> 0.44986486 | V38: 13
A39: =D39&E39 -> 54.7Clear | B39: =D39&E39&F39 -> 54.7Clear0.25 | D39: 54.7 | E39: Clear | F39: 0.25 | G39: =+($E$13/1000*(1-F39)+$E$14/1000*F39)*D39*(1+0.5%) -> 62.719376 | H39: =V39*(1+(Inputs!AH$8/Inputs!AH$7-1)*50%) -> 13 | I39: =+H39+G39 -> 75.719376 | K39: =J39+I39 -> 75.719376 | L39: =Q39 -> 0.44986486 | M39: =SUM(K39:L39) -> 76.169241 | O39: 7.4 | P39: 40 | Q39: =$Q$17/(O39*P39) -> 0.44986486 | V39: 13

Sheet Motupe-Botellas
G1: PR | H1: CC | I1: FleteP | J1: CS | M1: Fee
C5: CLIENTE | D5: ABI Backus
C6: PAÍS : | D6: Perú
C7: PERÍODO : | D7: ='Ate Preformas'!D7 -> Abril 26
C8: Actualización: | D8: Mensual
C10: FORMULA PRECIOS MOTUPE - CON CP
C13: Precio de Resina | E13: USD/TM
C14: vPET | E14: =Inputs!H13 -> 1048.5
C15: rPET | E15: =Inputs!P10 -> 1418.108
Q17: Flete USD | R17: =+Inputs!X9 -> 2076.16
W18: Base | X18: Base
B19: Key | C19: Formato | D19: Gramaje | E19: Color | F19: %rPET | G19: Resina (US$/millar) | H19: Valor Fijo Preforma EXW (US$/millar) | I19: Flete Preforma (US$/millar) | J19: Valor Fijo Soplado Ex Energía* (US$/milllar) | K19: Energía (US$/milllar) | L19: Precio Botella (US$/millar) | M19: Fee (US$/millar) | N19: Precio Botella + Fee (US$/millar) | P19: Millar/caja | Q19: Camión | R19: Fletes Actuales | W19: Valor Fijo Preforma EXW (US$/millar) | X19: Valor Fijo Soplado (US$/millar) | Y19: Valor Fijo Soplado Ex Energía* (US$/milllar) | AA19: Costo de Energía Base* (US$/milllar)
B20: =D20&E20&F20 -> 19.7Clear0.15 | C20: 450/500/600/650 | D20: 19.7 | E20: Clear | F20: 0.15 | G20: =+($E$14/1000*(1-F20)+$E$15/1000*F20)*D20*(1+0.5%) -> 21.85638 | H20: =W20*(1+(Inputs!$AH$8/Inputs!$AH$7-1)*50%) -> 7.2369856 | I20: =+R20 -> 1.4188643 | J20: =Y20*(1+(Inputs!$AH$8/Inputs!$AH$7-1)*50%) -> 8.6815099 | K20: =VLOOKUP($C20,Inputs!$AN$14:$AQ$18,3,0) -> 2.0124962 | L20: =SUM(G20:K20) -> 41.206236 | M20: 0.48862372 | N20: =M20+L20 -> 41.694859 | P20: =VLOOKUP(D20,'Ate Preformas'!$D$20:$R$39,10,0) -> 30.484475 | Q20: 48 | R20: =$R$17/(P20*Q20) -> 1.4188643 | W20: 7.2369856 | X20: 10.466339 | Y20: =+X20-AA20 -> 8.6815099 | AA20: =VLOOKUP($C20,Inputs!$AN$14:$AQ$18,2,0) -> 1.7848293
B21: =D21&E21&F21 -> 19.7Clear0.25 | D21: 19.7 | E21: Clear | F21: 0.25 | G21: =+($E$14/1000*(1-F21)+$E$15/1000*F21)*D21*(1+0.5%) -> 22.588148 | H21: =W21*(1+(Inputs!$AH$8/Inputs!$AH$7-1)*50%) -> 7.2369856 | I21: =+R21 -> 1.4188643 | J21: =Y21*(1+(Inputs!$AH$8/Inputs!$AH$7-1)*50%) -> 8.6815099 | K21: =VLOOKUP($C20,Inputs!$AN$14:$AQ$18,3,0) -> 2.0124962 | L21: =SUM(G21:K21) -> 41.938004 | M21: 0.48862372 | N21: =M21+L21 -> 42.426628 | P21: =VLOOKUP(D21,'Ate Preformas'!$D$20:$R$39,10,0) -> 30.484475 | Q21: 48 | R21: =$R$17/(P21*Q21) -> 1.4188643 | W21: 7.2369856 | X21: 10.466339 | Y21: =+X21-AA21 -> 8.6815099 | AA21: =VLOOKUP($C20,Inputs!$AN$14:$AQ$18,2,0) -> 1.7848293
A22: NUEVO | B22: =D22&E22&F22 -> 19.7Clear0.5 | D22: 19.7 | E22: Clear | F22: 0.5 | G22: =+($E$14/1000*(1-F22)+$E$15/1000*F22)*D22*(1+0.5%) -> 24.417569 | H22: =W22*(1+(Inputs!$AH$8/Inputs!$AH$7-1)*50%) -> 7.2369856 | I22: =+R22 -> 1.4188643 | J22: =Y22*(1+(Inputs!$AH$8/Inputs!$AH$7-1)*50%) -> 8.6815099 | K22: =K21 -> 2.0124962 | L22: =SUM(G22:K22) -> 43.767425 | M22: 0.48862372 | N22: =M22+L22 -> 44.256049 | P22: =VLOOKUP(D22,'Ate Preformas'!$D$20:$R$39,10,0) -> 30.484475 | Q22: 48 | R22: =$R$17/(P22*Q22) -> 1.4188643 | W22: 7.2369856 | X22: 10.466339 | Y22: =+X22-AA22 -> 8.6815099 | AA22: =AA21 -> 1.7848293
A23: NUEVO | B23: =D23&E23&F23 -> 19.7Clear0.6 | D23: 19.7 | E23: Clear | F23: 0.6 | G23: =+($E$14/1000*(1-F23)+$E$15/1000*F23)*D23*(1+0.5%) -> 25.149337 | H23: =W23*(1+(Inputs!$AH$8/Inputs!$AH$7-1)*50%) -> 7.2369856 | I23: =+R23 -> 1.4188643 | J23: =Y23*(1+(Inputs!$AH$8/Inputs!$AH$7-1)*50%) -> 8.6815099 | K23: =K21 -> 2.0124962 | L23: =SUM(G23:K23) -> 44.499193 | M23: 0.48862372 | N23: =M23+L23 -> 44.987817 | P23: =VLOOKUP(D23,'Ate Preformas'!$D$20:$R$39,10,0) -> 30.484475 | Q23: 48 | R23: =$R$17/(P23*Q23) -> 1.4188643 | W23: 7.2369856 | X23: 10.466339 | Y23: =+X23-AA23 -> 8.6815099 | AA23: =AA21 -> 1.7848293
B24: =D24&E24&F24 -> 33.7Clear0.15 | C24: 1000 | D24: 33.7 | E24: Clear | F24: 0.15 | G24: =+($E$14/1000*(1-F24)+$E$15/1000*F24)*D24*(1+0.5%) -> 37.388832 | H24: =W24*(1+(Inputs!$AH$8/Inputs!$AH$7-1)*50%) -> 10.55124 | I24: =+R24 -> 0.87413392 | J24: =Y24*(1+(Inputs!$AH$8/Inputs!$AH$7-1)*50%) -> 8.833514 | K24: =VLOOKUP($C24,Inputs!$AN$14:$AQ$18,3,0) -> 2.9869413 | L24: =SUM(G24:K24) -> 60.634662 | N24: =M24+L24 -> 60.634662 | P24: =VLOOKUP(D24,'Ate Preformas'!$D$20:$R$39,10,0) -> 49.481358 | Q24: 48 | R24: =$R$17/(P24*Q24) -> 0.87413392 | W24: 10.55124 | X24: 11.482553 | Y24: =+X24-AA24 -> 8.833514 | AA24: =VLOOKUP($C24,Inputs!$AN$14:$AQ$18,2,0) -> 2.6490386
B25: =D25&E25&F25 -> 33.7Clear0.25 | D25: 33.7 | E25: Clear | F25: 0.25 | G25: =+($E$14/1000*(1-F25)+$E$15/1000*F25)*D25*(1+0.5%) -> 38.640639 | H25: =W25*(1+(Inputs!$AH$8/Inputs!$AH$7-1)*50%) -> 10.55124 | I25: =+R25 -> 0.87413392 | J25: =Y25*(1+(Inputs!$AH$8/Inputs!$AH$7-1)*50%) -> 8.833514 | K25: =VLOOKUP($C24,Inputs!$AN$14:$AQ$18,3,0) -> 2.9869413 | L25: =SUM(G25:K25) -> 61.886468 | N25: =M25+L25 -> 61.886468 | P25: =VLOOKUP(D25,'Ate Preformas'!$D$20:$R$39,10,0) -> 49.481358 | Q25: 48 | R25: =$R$17/(P25*Q25) -> 0.87413392 | W25: 10.55124 | X25: 11.482553 | Y25: =+X25-AA25 -> 8.833514 | AA25: =VLOOKUP($C24,Inputs!$AN$14:$AQ$18,2,0) -> 2.6490386
B26: =D26&E26&F26 -> 45.7Clear0.15 | C26: 2000 | D26: 45.7 | E26: Clear | F26: 0.15 | G26: =+($E$14/1000*(1-F26)+$E$15/1000*F26)*D26*(1+0.5%) -> 50.702363 | H26: =W26*(1+(Inputs!$AH$8/Inputs!$AH$7-1)*50%) -> 14.668166 | I26: =+R26 -> 0.65767694 | J26: =Y26*(1+(Inputs!$AH$8/Inputs!$AH$7-1)*50%) -> 7.1029446 | K26: =VLOOKUP($C26,Inputs!$AN$14:$AQ$18,3,0) -> 4.9382564 | L26: =SUM(G26:K26) -> 78.069407 | N26: =M26+L26 -> 78.069407 | P26: =VLOOKUP(D26,'Ate Preformas'!$D$20:$R$39,10,0) -> 65.766839 | Q26: 48 | R26: =$R$17/(P26*Q26) -> 0.65767694 | W26: 14.668166 | X26: 11.482553 | Y26: =+X26-AA26 -> 7.1029446 | AA26: =VLOOKUP($C26,Inputs!$AN$14:$AQ$18,2,0) -> 4.379608
B27: =D27&E27&F27 -> 45.7Clear0.25 | D27: 45.7 | E27: Clear | F27: 0.25 | G27: =+($E$14/1000*(1-F27)+$E$15/1000*F27)*D27*(1+0.5%) -> 52.399917 | H27: =W27*(1+(Inputs!$AH$8/Inputs!$AH$7-1)*50%) -> 14.668166 | I27: =+R27 -> 0.65767694 | J27: =Y27*(1+(Inputs!$AH$8/Inputs!$AH$7-1)*50%) -> 7.1029446 | K27: =VLOOKUP($C26,Inputs!$AN$14:$AQ$18,3,0) -> 4.9382564 | L27: =SUM(G27:K27) -> 79.766961 | N27: =M27+L27 -> 79.766961 | P27: =VLOOKUP(D27,'Ate Preformas'!$D$20:$R$39,10,0) -> 65.766839 | Q27: 48 | R27: =$R$17/(P27*Q27) -> 0.65767694 | W27: 14.668166 | X27: 11.482553 | Y27: =+X27-AA27 -> 7.1029446 | AA27: =VLOOKUP($C26,Inputs!$AN$14:$AQ$18,2,0) -> 4.379608
A28: NUEVO | B28: =D28&E28&F28 -> 45.7Clear0.5 | D28: 45.7 | E28: Clear | F28: 0.5 | G28: =+($E$14/1000*(1-F28)+$E$15/1000*F28)*D28*(1+0.5%) -> 56.643802 | H28: =W28*(1+(Inputs!$AH$8/Inputs!$AH$7-1)*50%) -> 14.668166 | I28: =+R28 -> 0.65767694 | J28: =Y28*(1+(Inputs!$AH$8/Inputs!$AH$7-1)*50%) -> 7.1029446 | K28: =K27 -> 4.9382564 | L28: =SUM(G28:K28) -> 84.010846 | N28: =M28+L28 -> 84.010846 | P28: =VLOOKUP(D28,'Ate Preformas'!$D$20:$R$39,10,0) -> 65.766839 | Q28: 48 | R28: =$R$17/(P28*Q28) -> 0.65767694 | W28: 14.668166 | X28: 11.482553 | Y28: =+X28-AA28 -> 7.1029446 | AA28: =AA27 -> 4.379608
B29: =D29&E29&F29 -> 54.7Clear0.25 | C29: 3000 | D29: 54.7 | E29: Clear | F29: 0.25 | G29: =+($E$14/1000*(1-F29)+$E$15/1000*F29)*D29*(1+0.5%) -> 62.719376 | H29: =W29*(1+(Inputs!$AH$8/Inputs!$AH$7-1)*50%) -> 13 | I29: =+R29 -> 0.58342142 | J29: =Y29*(1+(Inputs!$AH$8/Inputs!$AH$7-1)*50%) -> 10.812008 | K29: =VLOOKUP($C29,Inputs!$AN$14:$AQ$18,3,0) -> 5.9061334 | L29: =SUM(G29:K29) -> 93.020938 | N29: =M29+L29 -> 93.020938 | P29: =VLOOKUP(D29,'Ate Preformas'!$D$20:$R$39,10,0) -> 74.137376 | Q29: 48 | R29: =$R$17/(P29*Q29) -> 0.58342142 | W29: 13 | X29: 16.05 | Y29: =+X29-AA29 -> 10.812008 | AA29: =VLOOKUP($C29,Inputs!$AN$14:$AQ$18,2,0) -> 5.2379923
B30: =D30&E30&F30 -> 51.2Clear0.15 | C30: 3000 | D30: 51.2 | E30: Clear | F30: 0.15 | G30: =+($E$14/1000*(1-F30)+$E$15/1000*F30)*D30*(1+0.5%) -> 56.804398 | H30: =W30*(1+(Inputs!$AH$8/Inputs!$AH$7-1)*50%) -> 12.25 | I30: =+R30 -> 0.62231195 | J30: =Y30*(1+(Inputs!$AH$8/Inputs!$AH$7-1)*50%) -> 10.812008 | K30: =VLOOKUP($C30,Inputs!$AN$14:$AQ$18,3,0) -> 5.9061334 | L30: =SUM(G30:K30) -> 86.394851 | N30: =M30+L30 -> 86.394851 | P30: =VLOOKUP(D30,'Ate Preformas'!$D$20:$R$39,10,0) -> 69.504263 | Q30: 48 | R30: =$R$17/(P30*Q30) -> 0.62231195 | W30: 12.25 | X30: 16.05 | Y30: =+X30-AA30 -> 10.812008 | AA30: =VLOOKUP($C30,Inputs!$AN$14:$AQ$18,2,0) -> 5.2379923

Sheet Ate-Botellas
G1: PR | H1: CC | I1: FleteP | K1: CS | N1: Fee
C5: CLIENTE | D5: ABI Backus
C6: PAÍS : | D6: Perú
C7: PERÍODO : | D7: ='Ate Preformas'!D7 -> Abril 26
C8: Actualización: | D8: Mensual
G10: FORMULA PRECIOS BOTELLAS IN HOUSE ATE - CON CP
C12: Precio de Resina | E12: USD/TM
C13: vPET | E13: =Inputs!H13 -> 1048.5
C14: rPET | E14: =Inputs!P10 -> 1418.108
R16: Flete USD | S16: =Inputs!X7 -> 133.16
X17: Base | Y17: Base
B18: Key | C18: FORMATO | D18: Gramaje | E18: Color | F18: %rPET | G18: Resina (US$/milllar) | H18: Valor Fijo Preforma EXW (US$/milllar) | I18: Flete (US$/milllar) | J18: Valor Fijo Preforma DDP (US$/milllar) | K18: Valor Fijo Soplado Ex Energía* (US$/milllar) | L18: Energía (US$/milllar) | M18: Precio Botella (US$/milllar) | N18: Fee (US$/millar) | O18: Precio Botella + Fee (US$/millar) | Q18: Millar/caja | R18: Camión | S18: Flete Unitario | X18: Valor Fijo Preforma EXW (US$/milllar) | Y18: Valor Fijo Soplado * (US$/milllar) | Z18: Valor Fijo Soplado Ex Energía* (US$/milllar) | AB18: Costo de Energía Base* (US$/milllar)
A19: =D19&E19 -> 19.7Clear | B19: =D19&E19&F19 -> 19.7Clear0.15 | C19: 450/500/600/650 y <1 Lt | D19: 19.7 | E19: Clear | F19: 0.15 | G19: =+($E$13/1000*(1-F19)+$E$14/1000*F19)*D19*(1+0.5%) -> 21.85638 | H19: =X19*(1+(Inputs!$AH$8/Inputs!$AH$7-1)*50%) -> 7.2369856 | I19: =+S19 -> 0.10920313 | J19: =SUM(H19:I19) -> 7.3461887 | K19: =Z19*(1+(Inputs!$AH$8/Inputs!$AH$7-1)*50%) -> 2.4909756 | L19: =VLOOKUP($C19,Inputs!$AN$19:$AQ$22,3,0) -> 1.9513689 | M19: =SUM(J19:L19)+G19 -> 33.644913 | N19: 0.48862372 | O19: =N19+M19 -> 34.133537 | Q19: =VLOOKUP(D19,'Ate Preformas'!$D$20:$R$39,10,0) -> 30.484475 | R19: 40 | S19: =$S$16/(Q19*R19) -> 0.10920313 | X19: 7.2369856 | Y19: 4.2215927 | Z19: =+Y19-AB19 -> 2.4909756 | AB19: =VLOOKUP($C19,Inputs!$AN$19:$AQ$22,2,0) -> 1.7306171
A20: =D20&E20 -> 19.7Clear | B20: =D20&E20&F20 -> 19.7Clear0.25 | D20: 19.7 | E20: Clear | F20: 0.25 | G20: =+($E$13/1000*(1-F20)+$E$14/1000*F20)*D20*(1+0.5%) -> 22.588148 | H20: =X20*(1+(Inputs!$AH$8/Inputs!$AH$7-1)*50%) -> 7.2369856 | I20: =+S20 -> 0.10920313 | J20: =SUM(H20:I20) -> 7.3461887 | K20: =Z20*(1+(Inputs!$AH$8/Inputs!$AH$7-1)*50%) -> 2.4909756 | L20: =VLOOKUP($C19,Inputs!$AN$19:$AQ$22,3,0) -> 1.9513689 | M20: =SUM(J20:L20)+G20 -> 34.376681 | N20: 0.48862372 | O20: =N20+M20 -> 34.865305 | Q20: =VLOOKUP(D20,'Ate Preformas'!$D$20:$R$39,10,0) -> 30.484475 | R20: 40 | S20: =$S$16/(Q20*R20) -> 0.10920313 | X20: 7.2369856 | Y20: 4.2215927 | Z20: =+Y20-AB20 -> 2.4909756 | AB20: =VLOOKUP($C19,Inputs!$AN$19:$AQ$22,2,0) -> 1.7306171
A21: =D21&E21 -> 19.7Brown | B21: =D21&E21&F21 -> 19.7Brown0.5 | D21: 19.7 | E21: Brown | F21: 0.5 | G21: =+($E$13/1000*(1-F21)+$E$14/1000*F21)*D20*(1+0.5%) -> 24.417569 | H21: =X21*(1+(Inputs!$AH$8/Inputs!$AH$7-1)*50%) -> 8.8522419 | I21: =+S21 -> 0.10920313 | J21: =SUM(H21:I21) -> 8.961445 | K21: =Z21*(1+(Inputs!$AH$8/Inputs!$AH$7-1)*50%) -> 2.4909756 | L21: =L20 -> 1.9513689 | M21: =SUM(J21:L21)+G21 -> 37.821358 | O21: =N21+M21 -> 37.821358 | Q21: =VLOOKUP(D21,'Ate Preformas'!$D$20:$R$39,10,0) -> 30.484475 | R21: 40 | S21: =$S$16/(Q21*R21) -> 0.10920313 | X21: 8.8522419 | Y21: 4.2215927 | Z21: =+Y21-AB21 -> 2.4909756 | AB21: =AB20 -> 1.7306171
A22: =D22&E22 -> 19.7Brown | B22: =D22&E22&F22 -> 19.7Brown0.6 | D22: 19.7 | E22: Brown | F22: 0.6 | G22: =+($E$13/1000*(1-F22)+$E$14/1000*F22)*D20*(1+0.5%) -> 25.149337 | H22: =X22*(1+(Inputs!$AH$8/Inputs!$AH$7-1)*50%) -> 8.8522419 | I22: =+S22 -> 0.10920313 | J22: =SUM(H22:I22) -> 8.961445 | K22: =Z22*(1+(Inputs!$AH$8/Inputs!$AH$7-1)*50%) -> 2.4909756 | L22: =L20 -> 1.9513689 | M22: =SUM(J22:L22)+G22 -> 38.553127 | O22: =N22+M22 -> 38.553127 | Q22: =VLOOKUP(D22,'Ate Preformas'!$D$20:$R$39,10,0) -> 30.484475 | R22: 40 | S22: =$S$16/(Q22*R22) -> 0.10920313 | X22: 8.8522419 | Y22: 4.2215927 | Z22: =+Y22-AB22 -> 2.4909756 | AB22: =AB20 -> 1.7306171
A23: =D23&E23 -> 33.7Clear | B23: =D23&E23&F23 -> 33.7Clear0.15 | C23: 1000 | D23: 33.7 | E23: Clear | F23: 0.15 | G23: =+($E$13/1000*(1-F23)+$E$14/1000*F23)*D23*(1+0.5%) -> 37.388832 | H23: =X23*(1+(Inputs!$AH$8/Inputs!$AH$7-1)*50%) -> 10.55124 | I23: =+S23 -> 0.067277863 | J23: =SUM(H23:I23) -> 10.618518 | K23: =Z23*(1+(Inputs!$AH$8/Inputs!$AH$7-1)*50%) -> 6.4378383 | L23: =VLOOKUP($C23,Inputs!$AN$19:$AQ$22,3,0) -> 2.8962162 | M23: =SUM(J23:L23)+G23 -> 57.341405 | O23: =N23+M23 -> 57.341405 | Q23: =VLOOKUP(D23,'Ate Preformas'!$D$20:$R$39,10,0) -> 49.481358 | R23: 40 | S23: =$S$16/(Q23*R23) -> 0.067277863 | X23: 10.55124 | Y23: 9.0064153 | Z23: =+Y23-AB23 -> 6.4378383 | AB23: =VLOOKUP($C23,Inputs!$AN$19:$AQ$22,2,0) -> 2.568577
A24: =D24&E24 -> 33.7Clear | B24: =D24&E24&F24 -> 33.7Clear0.25 | D24: 33.7 | E24: Clear | F24: 0.25 | G24: =+($E$13/1000*(1-F24)+$E$14/1000*F24)*D24*(1+0.5%) -> 38.640639 | H24: =X24*(1+(Inputs!$AH$8/Inputs!$AH$7-1)*50%) -> 10.55124 | I24: =+S24 -> 0.067277863 | J24: =SUM(H24:I24) -> 10.618518 | K24: =Z24*(1+(Inputs!$AH$8/Inputs!$AH$7-1)*50%) -> 6.4378383 | L24: =VLOOKUP($C23,Inputs!$AN$19:$AQ$22,3,0) -> 2.8962162 | M24: =SUM(J24:L24)+G24 -> 58.593212 | O24: =N24+M24 -> 58.593212 | Q24: =VLOOKUP(D24,'Ate Preformas'!$D$20:$R$39,10,0) -> 49.481358 | R24: 40 | S24: =$S$16/(Q24*R24) -> 0.067277863 | X24: 10.55124 | Y24: 9.0064153 | Z24: =+Y24-AB24 -> 6.4378383 | AB24: =VLOOKUP($C23,Inputs!$AN$19:$AQ$22,2,0) -> 2.568577
A25: =D25&E25 -> 45.7Clear | B25: =D25&E25&F25 -> 45.7Clear0.15 | C25: 2000 | D25: 45.7 | E25: Clear | F25: 0.15 | G25: =+($E$13/1000*(1-F25)+$E$14/1000*F25)*D25*(1+0.5%) -> 50.702363 | H25: =X25*(1+(Inputs!$AH$8/Inputs!$AH$7-1)*50%) -> 14.668166 | I25: =+S25 -> 0.050618215 | J25: =SUM(H25:I25) -> 14.718784 | K25: =Z25*(1+(Inputs!$AH$8/Inputs!$AH$7-1)*50%) -> 4.7598331 | L25: =VLOOKUP($C25,Inputs!$AN$19:$AQ$22,3,0) -> 4.7882623 | M25: =SUM(J25:L25)+G25 -> 74.969243 | O25: =N25+M25 -> 74.969243 | Q25: =VLOOKUP(D25,'Ate Preformas'!$D$20:$R$39,10,0) -> 65.766839 | R25: 40 | S25: =$S$16/(Q25*R25) -> 0.050618215 | X25: 14.668166 | Y25: 9.0064153 | Z25: =+Y25-AB25 -> 4.7598331 | AB25: =VLOOKUP($C25,Inputs!$AN$19:$AQ$22,2,0) -> 4.2465822
A26: =D26&E26 -> 45.7Clear | B26: =D26&E26&F26 -> 45.7Clear0.25 | D26: 45.7 | E26: Clear | F26: 0.25 | G26: =+($E$13/1000*(1-F26)+$E$14/1000*F26)*D26*(1+0.5%) -> 52.399917 | H26: =X26*(1+(Inputs!$AH$8/Inputs!$AH$7-1)*50%) -> 14.668166 | I26: =+S26 -> 0.050618215 | J26: =SUM(H26:I26) -> 14.718784 | K26: =Z26*(1+(Inputs!$AH$8/Inputs!$AH$7-1)*50%) -> 4.7598331 | L26: =VLOOKUP($C25,Inputs!$AN$19:$AQ$22,3,0) -> 4.7882623 | M26: =SUM(J26:L26)+G26 -> 76.666797 | O26: =N26+M26 -> 76.666797 | Q26: =VLOOKUP(D26,'Ate Preformas'!$D$20:$R$39,10,0) -> 65.766839 | R26: 40 | S26: =$S$16/(Q26*R26) -> 0.050618215 | X26: 14.668166 | Y26: 9.0064153 | Z26: =+Y26-AB26 -> 4.7598331 | AB26: =VLOOKUP($C25,Inputs!$AN$19:$AQ$22,2,0) -> 4.2465822
A27: =D27&E27 -> 45.7Clear | B27: =D27&E27&F27 -> 45.7Clear0.5 | D27: 45.7 | E27: Clear | F27: 0.5 | G27: =+($E$13/1000*(1-F27)+$E$14/1000*F27)*D27*(1+0.5%) -> 56.643802 | H27: =X27*(1+(Inputs!$AH$8/Inputs!$AH$7-1)*50%) -> 14.668166 | I27: =+S27 -> 0.050618215 | J27: =SUM(H27:I27) -> 14.718784 | K27: =Z27*(1+(Inputs!$AH$8/Inputs!$AH$7-1)*50%) -> 4.7598331 | L27: =L26 -> 4.7882623 | M27: =SUM(J27:L27)+G27 -> 80.910682 | O27: =N27+M27 -> 80.910682 | Q27: =VLOOKUP(D27,'Ate Preformas'!$D$20:$R$39,10,0) -> 65.766839 | R27: 40 | S27: =$S$16/(Q27*R27) -> 0.050618215 | X27: 14.668166 | Y27: 9.0064153 | Z27: =+Y27-AB27 -> 4.7598331 | AB27: =AB26 -> 4.2465822
A28: =D28&E28 -> 51.2Clear | B28: =D28&E28&F28 -> 51.2Clear0.25 | C28: 3000 | D28: 51.2 | E28: Clear | F28: 0.25 | G28: =+($E$13/1000*(1-F28)+$E$14/1000*F28)*D28*(1+0.5%) -> 58.706253 | H28: =X28*(1+(Inputs!$AH$8/Inputs!$AH$7-1)*50%) -> 12.25 | I28: =+S28 -> 0.047896343 | J28: =SUM(H28:I28) -> 12.297896 | K28: =Z28*(1+(Inputs!$AH$8/Inputs!$AH$7-1)*50%) -> 3.9275212 | L28: =VLOOKUP($C28,Inputs!$AN$19:$AQ$22,3,0) -> 5.7267411 | M28: =SUM(J28:L28)+G28 -> 80.658412 | O28: =N28+M28 -> 80.658412 | Q28: =VLOOKUP(D28,'Ate Preformas'!$D$20:$R$39,10,0) -> 69.504263 | R28: 40 | S28: =$S$16/(Q28*R28) -> 0.047896343 | X28: 12.25 | Y28: 9.0064153 | Z28: =+Y28-AB28 -> 3.9275212 | AB28: =VLOOKUP($C28,Inputs!$AN$19:$AQ$22,2,0) -> 5.0788941
A29: =D29&E29 -> 51.2Clear | B29: =D29&E29&F29 -> 51.2Clear0.15 | D29: 51.2 | E29: Clear | F29: 0.15 | G29: =+($E$13/1000*(1-F29)+$E$14/1000*F29)*D29*(1+0.5%) -> 56.804398 | H29: =X29*(1+(Inputs!$AH$8/Inputs!$AH$7-1)*50%) -> 12.25 | I29: =+S29 -> 0.047896343 | J29: =SUM(H29:I29) -> 12.297896 | K29: =Z29*(1+(Inputs!$AH$8/Inputs!$AH$7-1)*50%) -> 3.9275212 | L29: =VLOOKUP($C28,Inputs!$AN$19:$AQ$22,3,0) -> 5.7267411 | M29: =SUM(J29:L29)+G29 -> 78.756557 | O29: =N29+M29 -> 78.756557 | Q29: =VLOOKUP(D29,'Ate Preformas'!$D$20:$R$39,10,0) -> 69.504263 | R29: 40 | S29: =$S$16/(Q29*R29) -> 0.047896343 | X29: 12.25 | Y29: 9.0064153 | Z29: =+Y29-AB29 -> 3.9275212 | AB29: =VLOOKUP($C28,Inputs!$AN$19:$AQ$22,2,0) -> 5.0788941

Sheet Inputs
B2: HOJA DE INPUTS | G2: 1. vPET | K2: 1.2 Fletes Marítimos Internacionales: | O2: 2. rPET | U2: 3. Costos Logisticos de Preforma | AB2: 4. Tipo de Cambio | AG2: 5. IPC | AL2: 6. Tarifa de Energía
G3: 1.1 Indice de precios de resina | K3: Indices Fletes Maritimos Drewry | AB3: Fuente: | AC3: SBS | AG3: Fuente: | AH3: U.S. BLS | AL3: Tarifa de Planeamiento Financiero
G4: Índice: | K4: Índice: | O4: Inventario Final | P4: Perú | U4: Origen | V4: Planta SMI - Cercado de Lima | AB4: Oficial Venta SBS (PEN) PERU | AG4: CPI for All Urban Consumers (CPI-U) | AL4: Mes | AM4: 2026-2 | AN4: In House
C5: AÑO | D5: MES | G5: ICIS - ASIA SE - Low | K5: Central China (Shanghai) to Peru (Callao) | O5: Mes | P5: Precio Paca | AB5: Mes | AC5: Promedio | AG5: IPC USA | AL5: Pais | AM5: Centro | AN5: Planta | AO5: Soles/KWH | AP5: USD/KWH | AQ5: TC
B6: *ACTUALIZAR A LP: | C6: 2026 | D6: 4 | G6: Mes | H6: USD/TM | K6: Mes | L6: Flete (USD/TM) | O6: 2026-2 | P6: 485.17558 | Q6: USD / TM | W6: S/ Viaje | X6: USD/Viaje | AB6: 2026-2 | AC6: 3.36125 | AG6: Mes | AH6: IPC | AI6: Inflación acum | AL6: Perú | AM6: 1020 | AN6: Backus Ate | AO6: 0.322 | AP6: =+AO6/AQ6 -> 0.095797694 | AQ6: =+$AC$6 -> 3.36125
G7: 2026-2 | H7: 852.5 | K7: 2026-2 | L7: 55.272727 | U7: Destino | V7: Ate | W7: 447.6 | X7: =ROUND(W7/$AC$6,2) -> 133.16 | AB7: Fecha | AC7: TC | AF7: Base | AG7: 2024-6 | AH7: 314.175 | AL7: Perú | AM7: 1070 | AN7: Backus Motupe | AO7: 0.322 | AP7: =+AO7/AQ7 -> 0.095797694 | AQ7: =+$AC$6 -> 3.36125
C8: PERIODO | D8: MES INICIAL | O8: Scrap | P8: 0.3 | V8: Huarochirí | W8: =1265*5/4 -> 1581.25 | X8: =ROUND(W8/$AC$6,2) -> 470.44 | AB8: 46054 | AF8: Actual | AG8: 2025-11 | AH8: 314.175 | AI8: =+AH8/AH7-1 -> 0 | AJ8: Actualizar en Jul-27, con CPI Nov-26
C9: =UPPER(C6&"-"&D6) -> 2026-4 | D9: =D6 -> 4 | G9: Precio FOB | H9: =AVERAGE(H7:H7) -> 852.5 | O9: Conversión | P9: 725 | Q9: USD / TM | V9: Motupe | W9: =+(5961*4+4070)/4 -> 6978.5 | X9: =ROUND(W9/$AC$6,2) -> 2076.16 | AB9: 46055 | AC9: 3.369 | AL9: Perú | AM9: Base | AN9: Backus Motupe/ Ate | AO9: 0.084960422 | AS9: USD/KWH
G10: Flete marítimo | H10: =IF(L7>180,L7+25,161) -> 161 | O10: Precio rPET | P10: =+P6/(1-P8)+P9 -> 1418.108 | Q10: USD / TM | AB10: 46056 | AC10: 3.365 | AN10: %Var | AO10: 0.12755671 | AR10: Tarifa Energia | AS10: 0.084960422
B11: Validez Inicial | C11: =DATE($C$6,$D$6,1) -> 46113 | G11: Precio CIF | H11: =SUM(H9:H10) -> 1013.5 | AB11: 46057 | AC11: 3.364 | AR11: Tipo de Cambio | AS11: 3.79
B12: Validez Final | C12: =IF(ISNUMBER($D$6),EOMONTH(C11,0),0) + IF(LEFT($D$6,1)="B",EOMONTH(C11,1),0) + IF(LEFT($D$6,1)="Q",EOMONTH(C11,2),0) + IF(LEFT($D$6,1)="S",EOMONTH(C11,5),0) -> 46142 | G12: Nacionalización | H12: 35 | O12: Merma sobre precio DDP | P12: 0.005 | AB12: 46058 | AC12: 3.368
G13: Valor vPET | H13: =+H12+H11 -> 1048.5 | AB13: 46059 | AC13: 3.363 | AL13: Planta | AM13: Gramaje | AN13: Formato | AO13: Energía Base | AP13: Energía Ajustado
AB14: 46060 | AL14: Motupe | AM14: 19.7 | AN14: 450/500/600/650 | AO14: 1.7848293 | AP14: =AO14*(1+$AO$10) -> 2.0124962
AB15: 46061 | AL15: Motupe | AM15: 33.7 | AN15: 1000 | AO15: 2.6490386 | AP15: =AO15*(1+$AO$10) -> 2.9869413
G16: Merma sobre precio DDP | H16: 0.005 | AB16: 46062 | AC16: 3.363 | AL16: Motupe | AM16: 45.7 | AN16: 2000 | AO16: 4.379608 | AP16: =AO16*(1+$AO$10) -> 4.9382564
AB17: 46063 | AC17: 3.362 | AL17: Motupe | AM17: 54.7 | AN17: 3000 | AO17: 5.2379923 | AP17: =AO17*(1+$AO$10) -> 5.9061334
AB18: 46064 | AC18: 3.363 | AL18: Motupe | AM18: 51.2 | AN18: 3000 | AO18: 5.2379923 | AP18: =AO18*(1+$AO$10) -> 5.9061334
AB19: 46065 | AC19: 3.358 | AL19: Ate | AM19: 19.7 | AN19: 450/500/600/650 y <1 Lt | AO19: 1.7306171 | AP19: =AO19*(1+$AO$10) -> 1.9513689
AB20: 46066 | AC20: 3.358 | AL20: Ate | AM20: 33.7 | AN20: 1000 | AO20: 2.568577 | AP20: =AO20*(1+$AO$10) -> 2.8962162
AB21: 46067 | AL21: Ate | AM21: 45.7 | AN21: 2000 | AO21: 4.2465822 | AP21: =AO21*(1+$AO$10) -> 4.7882623
AB22: 46068 | AL22: Ate | AM22: 51.2 | AN22: 3000 | AO22: 5.0788941 | AP22: =AO22*(1+$AO$10) -> 5.7267411
AB23: 46069 | AC23: 3.356
AB24: 46070 | AC24: 3.348
AB25: 46071 | AC25: 3.353
AB26: 46072 | AC26: 3.366
AB27: 46073 | AC27: 3.36
AB28: 46074
AB29: 46075
AB30: 46076 | AC30: 3.362
AB31: 46077 | AC31: 3.363
AB32: 46078 | AC32: 3.363
AB33: 46079 | AC33: 3.36
AB34: 46080 | AC34: 3.361
AB35: 46081
AC36: =IFERROR(IF(VLOOKUP(AB36,#REF!,2,0)=0,"",VLOOKUP(AB36,#REF!,2,0)),"")
AC37: =IFERROR(IF(VLOOKUP(AB37,#REF!,2,0)=0,"",VLOOKUP(AB37,#REF!,2,0)),"")
AC38: =IFERROR(IF(VLOOKUP(AB38,#REF!,2,0)=0,"",VLOOKUP(AB38,#REF!,2,0)),"")

Sheet Sheet1
G4: Current Month | I4: Forward
F6: ICIS | G6: Precio FOB | H6: 852.5 | I6: ICIS Asia Low Index
F7: OF | G7: Flete marítimo | H7: 161 | I7: Constant as per formulae
F8: IT | G8: Tax | H8: 0
G9: Precio CIF | H9: =(H7+H6)*(1+H8) -> 1013.5 | I9: Formulae
F10: Customs Clearance | G10: Nacionalización | H10: 35 | I10: Constant as per formulae
G11: Valor vPET | H11: =H10+H9 -> 1048.5 | I11: Formuale

Sheet Hoja2
C2: Destinatario | D2: Codigo Material | E2: Material | F2: Descripción | G2: Centro | H2: % Rpet | I2: Gramaje
C3: 401737 | D3: 000500019700040407 | E3: =VLOOKUP(D3,#REF!,1,0) -> #REF! | F3: ENV.500 GUARANA BACKUS S/ETIQ. CP | G3: 1020 | H3: 25 | I3: 19.7
C4: 401737 | D4: 003000054700020408 | E4: =VLOOKUP(D4,#REF!,1,0) -> #REF! | F4: ENV. 3LT. BACKUS GENERICA S/ETIQ.PENT CP | G4: 1020 | H4: 25 | I4: 54.7
C5: 401737 | D5: 002000045700040407 | E5: =VLOOKUP(D5,#REF!,1,0) -> #REF! | F5: ENV. 2LT.GUARANA S/ETIQ. COUNTUR CP | G5: 1020 | H5: 25 | I5: 45.7
C6: 401737 | D6: 001000033700040047 | E6: =VLOOKUP(D6,#REF!,1,0) -> #REF! | F6: ENV. 1.0 LT. GUARANA S/E COUNTOUR PETAL | G6: 1020 | H6: 25 | I6: 33.7
C7: 401737 | D7: 003000051200020408 | E7: =VLOOKUP(D7,#REF!,1,0) -> #REF! | F7: ENV. 3LT. BACKUS GENERICA S/ETIQ.PENT CP | G7: 1020 | H7: 25 | I7: 51.2
C8: 401737 | D8: 002000042700040407 | E8: =VLOOKUP(D8,#REF!,1,0) -> #REF! | F8: ENV. 2LT.GUARANA S/ETIQ. COUNTUR CP | G8: 1020 | H8: 25 | I8: 42.7
C9: 401737 | D9: 002000045700040406 | E9: =VLOOKUP(D9,#REF!,1,0) -> #REF! | F9: ENV.2LT. BACKUS VIVA CP S/E COUNT PEN | G9: 1020 | H9: 25 | I9: 45.7
C10: 400009 | D10: 002000045700040407 | E10: =VLOOKUP(D10,#REF!,1,0) -> #REF! | F10: ENV. 2LT.GUARANA S/ETIQ. COUNTUR CP | G10: 1070 | H10: 25 | I10: 45.7
C11: 400009 | D11: 000450019700040407 | E11: =VLOOKUP(D11,#REF!,1,0) -> #REF! | F11: ENV.450 GUARANA BACKUS S/ETIQ. CP | G11: 1070 | H11: 25 | I11: 19.7
C12: 400009 | D12: 003000054700020408 | E12: =VLOOKUP(D12,#REF!,1,0) -> #REF! | F12: ENV. 3LT. BACKUS GENERICA S/ETIQ.PENT CP | G12: 1070 | H12: 25 | I12: 54.7
C13: 400009 | D13: 001000033700040407 | E13: =VLOOKUP(D13,#REF!,1,0) -> #REF! | F13: ENV. 1.0 LT. GUARANA S/E COUNTOUR PE CP | G13: 1070 | H13: 25 | I13: 33.7
C14: 400009 | D14: 003000051200020408 | E14: =VLOOKUP(D14,#REF!,1,0) -> #REF! | F14: ENV. 3LT. BACKUS GENERICA S/ETIQ.PENT CP | G14: 1070 | H14: 25 | I14: 51.2
... C24: 400008 | D24: 00145A140U5 | E24: =VLOOKUP(D24,#REF!,1,0) -> #REF! | F24: PREFORMAS 14.5 GR.CELESTE RP.1881 | G24: 1000 | H24: 100 | I24: 14.5

Sheet Resumen Inputs (2)
B1: RESUMEN INPUTS
B4: Pais | C4: Linea | D4: Cliente | E4: Periodo | F4: Año | G4: Mes | H4: Tipo Producto | I4: Input | J4: Tipo Resina | K4: BD | L4: Fuente | M4: Esquema | N4: Precio FOB | O4: Precio CIF | P4: Precio DDP | Q4: Precio Paca | R4: Precio Conversion | S4: Precio RPET | T4: Precio | U4: Moneda | V4: Origen | W4: Destino | X4: UM | Y4: TC | Z4: OBS
B5: ="Perú" -> Perú | C5: ="SMI" -> SMI | D5: ="ABINVEV" -> ABINVEV | E5: =Inputs!$D$6 -> 4 | F5: =Inputs!$C$6 -> 2026 | G5: =Inputs!$D$9 -> 4 | H5: Containers | I5: RESINA | J5: CSD | K5: Indices Resina | L5: =Inputs!$G$5 -> ICIS - ASIA SE - Low | M5: Promedio trimestral anterior menos 1 mes | N5: =Inputs!H9 -> 852.5 | O5: =Inputs!H11 -> 1013.5 | P5: =Inputs!H13 -> 1048.5 | X5: ="US$ / TM" -> US$ / TM | Y5: =1 -> 1
B6: ="Perú" -> Perú | C6: ="SMI" -> SMI | D6: ="ABINVEV" -> ABINVEV | E6: =Inputs!$D$6 -> 4 | F6: =Inputs!$C$6 -> 2026 | G6: =Inputs!$D$9 -> 4 | H6: Containers | I6: FLETE EXTERNO | J6: Perú | K6: Fletes Mercado | L6: Planeamiento Financiero SMI | M6: Promedio trimestral anterior | T6: =Inputs!$L$10 -> 0 | W6: =Inputs!$L$5 -> 0 | X6: ="US$ / TM" -> US$ / TM | Y6: =1 -> 1
B7: ="Perú" -> Perú | C7: ="SMI" -> SMI | D7: ="ABINVEV" -> ABINVEV | E7: =Inputs!$D$6 -> 4 | F7: =Inputs!$C$6 -> 2026 | G7: =Inputs!$D$9 -> 4 | H7: Containers | I7: FLETE INTERNO | J7: Ate | K7: Fletes Terrestres PER | L7: Distribucion SMI Perú | M7: Fijo | T7: =Inputs!$X$7 -> 133.16 | V7: SMI | W7: Ate | X7: ="US$ / TM" -> US$ / TM | Y7: =1 -> 1
B8: ="Perú" -> Perú | C8: ="SMI" -> SMI | D8: ="ABINVEV" -> ABINVEV | E8: =Inputs!$D$6 -> 4 | F8: =Inputs!$C$6 -> 2026 | G8: =Inputs!$D$9 -> 4 | H8: Containers | I8: FLETE INTERNO | J8: Huarochirí | K8: Fletes Terrestres PER | L8: Distribucion SMI Perú | M8: Fijo | T8: =Inputs!$X$8 -> 470.44 | V8: SMI | W8: Huarochirí | X8: ="US$ / TM" -> US$ / TM | Y8: =1 -> 1
B9: ="Perú" -> Perú | C9: ="SMI" -> SMI | D9: ="ABINVEV" -> ABINVEV | E9: =Inputs!$D$6 -> 4 | F9: =Inputs!$C$6 -> 2026 | G9: =Inputs!$D$9 -> 4 | H9: Containers | I9: FLETE INTERNO | J9: Motupe | K9: Fletes Terrestres PER | L9: Distribucion SMI Perú | M9: Fijo | T9: =Inputs!$X$9 -> 2076.16 | V9: SMI | W9: Motupe | X9: ="US$ / TM" -> US$ / TM | Y9: =1 -> 1
B10: ="Perú" -> Perú | C10: ="SMI" -> SMI | D10: ="ABINVEV" -> ABINVEV | E10: =Inputs!$D$6 -> 4 | F10: =Inputs!$C$6 -> 2026 | G10: =Inputs!$D$9 -> 4 | H10: Containers | I10: TIPO CAMBIO | J10: PEN | K10: Tipo Cambio | L10: SBS Oficial Venta | M10: Promedio mes anterior menos 1 mes | T10: =Inputs!$AC$6 -> 3.36125 | U10: PEN | X10: ="US$ / TM" -> US$ / TM | Y10: =1 -> 1
B11: ="Perú" -> Perú | C11: ="SMI" -> SMI | D11: ="ABINVEV" -> ABINVEV | E11: =Inputs!$D$6 -> 4 | F11: =Inputs!$C$6 -> 2026 | G11: =Inputs!$D$9 -> 4 | H11: Containers | I11: RESINA | J11: RPET | K11: Precios Resina RPET | M11: Precio mes anterior menos 1 mes | Q11: =Inputs!$P$6 -> 485.17558 | R11: =Inputs!$P$9 -> 725 | S11: =Inputs!$P$10 -> 1418.108 | X11: ="US$ / TM" -> US$ / TM | Y11: =1 -> 1
B13: Resina Virgen
B14: Pais | C14: Linea | D14: Cliente | E14: Periodo | F14: Año | G14: Mes | H14: Tipo Producto | I14: Input | J14: Tipo Resina | K14: BD | L14: Fuente | M14: Esquema | N14: Precio FOB | O14: Precio CIF | P14: Precio DDP | Q14: UM | R14: OBS
B15: ="Perú" -> Perú | C15: ="SMI" -> SMI | D15: ="ABINVEV" -> ABINVEV | E15: =Inputs!$D$6 -> 4 | F15: =Inputs!$C$6 -> 2026 | G15: =Inputs!$D$9 -> 4 | H15: ="Containers" -> Containers | I15: ="RESINA" -> RESINA | J15: CSD | K15: Indices Resina | L15: =Inputs!$G$5 -> ICIS - ASIA SE - Low | M15: Promedio trimestral anterior menos 1 mes | N15: =Inputs!$H$9 -> 852.5 | O15: =Inputs!$H$11 -> 1013.5 | P15: =Inputs!$H$13 -> 1048.5 | Q15: ="USD / TM" -> USD / TM
B17: Resina RPET
B18: Pais | C18: Linea | D18: Cliente | E18: Periodo | F18: Año | G18: Mes | H18: Tipo Producto | I18: Input | J18: Tipo Resina | K18: BD | L18: Fuente | M18: Esquema | N18: Precio Paca | O18: Precio Conversion | P18: Precio RPET | Q18: UM | R18: OBS
B19: ="Perú" -> Perú | C19: ="SMI" -> SMI | D19: ="ABINVEV" -> ABINVEV | E19: =Inputs!$D$6 -> 4 | F19: =Inputs!$C$6 -> 2026 | G19: =Inputs!$D$9 -> 4 | H19: ="Containers" -> Containers | I19: ="RESINA" -> RESINA | J19: RPET | K19: RPET | M19: Precio mes anterior menos 1 mes | N19: =Inputs!$P$6 -> 485.17558 | O19: =Inputs!$P$9 -> 725 | P19: =Inputs!$P$10 -> 1418.108 | Q19: ="USD / TM" -> USD / TM
B21: Tipo Cambio
B22: Pais | C22: Linea | D22: Cliente | E22: Periodo | F22: Año | G22: Mes | H22: Tipo Producto | I22: Input | J22: Moneda | K22: BD | L22: Fuente | M22: Esquema | N22: Precio | O22: OBS
B23: ="Perú" -> Perú | C23: ="SMI" -> SMI | D23: ="ABINVEV" -> ABINVEV | E23: =Inputs!$D$6 -> 4 | F23: =Inputs!$C$6 -> 2026 | G23: =Inputs!$D$9 -> 4 | H23: ="Containers" -> Containers | I23: ="TIPO CAMBIO" -> TIPO CAMBIO | J23: PEN | K23: Tipo Cambio | L23: SBS - Oficial Venta | M23: Promedio mes anterior menos 1 mes | N23: =Inputs!$AC$6 -> 3.36125
B25: Flete Interno
B26: Pais | C26: Linea | D26: Cliente | E26: Periodo | F26: Año | G26: Mes | H26: Tipo Producto | I26: Input | J26: Origen | K26: Destino | L26: BD | M26: Fuente | N26: Esquema | O26: Precio | P26: OBS
B27: ="Perú" -> Perú | C27: ="SMI" -> SMI | D27: ="ABINVEV" -> ABINVEV | E27: =Inputs!$D$6 -> 4 | F27: =Inputs!$C$6 -> 2026 | G27: =Inputs!$D$9 -> 4 | H27: ="Containers" -> Containers | I27: ="FLETE INTERNO" -> FLETE INTERNO | J27: SMI | K27: Ate | L27: Fletes Terrestres PER | M27: Distribucion SMI Perú | N27: Fijo | O27: =Inputs!$X$7 -> 133.16
B28: ="Perú" -> Perú | C28: ="SMI" -> SMI | D28: ="ABINVEV" -> ABINVEV | E28: =Inputs!$D$6 -> 4 | F28: =Inputs!$C$6 -> 2026 | G28: =Inputs!$D$9 -> 4 | H28: ="Containers" -> Containers | I28: ="FLETE INTERNO" -> FLETE INTERNO | J28: SMI | K28: Huarochirí | L28: Fletes Terrestres PER | M28: Distribucion SMI Perú | N28: Fijo | O28: =Inputs!$X$8 -> 470.44
B29: ="Perú" -> Perú | C29: ="SMI" -> SMI | D29: ="ABINVEV" -> ABINVEV | E29: =Inputs!$D$6 -> 4 | F29: =Inputs!$C$6 -> 2026 | G29: =Inputs!$D$9 -> 4 | H29: ="Containers" -> Containers | I29: ="FLETE INTERNO" -> FLETE INTERNO | J29: SMI | K29: Motupe | L29: Fletes Terrestres PER | M29: Distribucion SMI Perú | N29: Fijo | O29: =Inputs!$X$9 -> 2076.16
B31: Flete Externo
B32: Pais | C32: Linea | D32: Cliente | E32: Periodo | F32: Año | G32: Mes | H32: Tipo Producto | I32: Input | J32: Origen | K32: Destino | L32: BD | M32: Fuente | N32: Esquema | O32: Precio | P32: OBS
B33: ="Perú" -> Perú | C33: ="SMI" -> SMI | D33: ="ABINVEV" -> ABINVEV | E33: =Inputs!$D$6 -> 4 | F33: =Inputs!$C$6 -> 2026 | G33: =Inputs!$D$9 -> 4 | H33: ="Containers" -> Containers | I33: ="FLETE EXTERNO" -> FLETE EXTERNO | K33: Perú | L33: Fletes Mercado | M33: Planeamiento Financiero SMI | N33: Promedio trimestral anterior | O33: =Inputs!$L$10 -> 0

Sheet Plantas
D3: Destino | E3: Planta
D4: 100002 | E4: Ate
D5: 400007 | E5: Ate
D6: 400009 | E6: Motupe
D7: 400008 | E7: Huarochirí
