Workbook

Sheet Pricing
H1: PR | I1: CC | J1: Flete | R1: DDP
B6: CLIENTE | C6: ABI
B7: PAÍS : | C7: República Dominicana
B8: PERÍODO : | C8: =TEXT(DATE(2024,Inputs!$D$6,1),"mmmm")&" "&Inputs!$C$6 -> Abril 2026
B9: Actualización: | C9: Mensual
B11: Costos de Resina USD/TM
B12: Virgin Resin Price DDP | C12: El Salvador | D12: =+Inputs!H12 -> 1111.5
B13: Virgin Resin Price DDP | C13: Perú | D13: =+Inputs!I12 -> 1048.5
B15: RPET Price DDP (Perú) | D15: =+Inputs!Q10 -> 1429.585
B16: RPET Price DDP (El Salvador) | D16: =+Inputs!Q12 -> 1629.585
B18: Merma | D18: 0.005
B20: Costos Logisticos de Preforma
B21: Perú | D21: =+Inputs!W4 -> 3538.2447
B22: El Salvador | D22: =+Inputs!W5 -> 4340
B24: Seguro Maritimo (%) | D24: 0.00253
B25: Gastos de Internación (USD/Contenedor) | D25: =+Inputs!W8 -> 855
B26: Flete al Almacén (USD/Camión) | D26: =+Inputs!W9 -> 360
B27: Gastos de Almacenaje (USD/caja) | D27: =+Inputs!W10 -> 14.9
B28: Recepción y despacho (USD/Caja) | D28: =+Inputs!W11 -> 13.88
B29: Gastos Financieros (Tasa Anual) | D29: 0.08 | E29: =+(1+D29)^(30/365)-1 -> 0.0063456137
B30: Flete al Planta Cliente (USD/Caja) | D30: =+Inputs!W13 -> 11
B31: Seguro Terreste (%) | D31: 0.00418
T34: x | AB34: Base
B35: Preform Weight SMI (g) | C35: Colors | D35: Neck Finish SMI | E35: %rPET | F35: Preform Origin | G35: Incoterm | H35: Resin Price USD/Thousand | I35: Non Resin Price (ExW) USD/Thousand | J35: Maritime Freight USD/Thousand | K35: Total CFR - Caucedo (USD/Thousand) | M35: Maritime Insurance, expenses of internalization, internal freight to SMI warehouse (USD/Thousand) | N35: Storage costs (USD/Thousand) | O35: Financial expenses for 30 days of stock in stock (USD/Thousand) | P35: Freight to the ABI plant - Hato Nuevo (USD/Thousand) | Q35: Terrestrial insurance (USD/Thousand) | R35: Total expenses to DDP - Hato Nuevo (USD/Thousand) | T35: Total Price (DDP) USD/Thousand | V35: Millares/ Caja | W35: Cajas/ Contenedor | AB35: Non Resin Price (ExW) USD/Thousand
A36: =B36&C36&D36&E36&F36 -> 19.5PLATA18810El Salvador | B36: 19.5 | C36: PLATA | D36: 1881 | E36: 0 | F36: El Salvador | G36: CFR | H36: =+(VLOOKUP(F36,$C$12:$D$13,2,0)*B36/1000*(1-E36)+IF(F36="Perú",$D$15,$D$16)*B36/1000*E36)*(1+$D$18) -> 21.782621 | I36: =AB36*(1+(Inputs!AD$8/Inputs!AD$7-1)*50%) -> 11.482162 | J36: =+IF(F36="Perú",$D$21,$D$22)/V36/W36 -> 5.4778061 | K36: =+SUM(H36:J36) -> 38.74259 | M36: =+SUM(H36:J36)*$D$24+$D$25/V36/W36+$D$26/V36/48 -> 1.5747545 | N36: =+($D$27+$D$28)/V36 -> 1.5256573 | O36: =+SUM(H36:N36)*$E$29 -> 0.51136503 | P36: =+$D$30/V36 -> 0.58312129 | Q36: =+SUM(H36:P36)*$D$31 -> 0.34142272 | R36: =+SUM(M36:Q36) -> 4.5363209 | T36: =+H36+I36+R36+J36 -> 43.278911 | V36: 18.864 | W36: 42 | AB36: 11.303228
A37: =B37&C37&D37&E37&F37 -> 17.7CRISTAL18810El Salvador | B37: 17.7 | C37: CRISTAL | D37: 1881 | E37: 0 | F37: El Salvador | G37: CFR | H37: =+(VLOOKUP(F37,$C$12:$D$13,2,0)*B37/1000*(1-E37)+IF(F37="Perú",$D$15,$D$16)*B37/1000*E37)*(1+$D$18) -> 19.771918 | I37: =AB37*(1+(Inputs!AD$8/Inputs!AD$7-1)*50%) -> 9.0168893 | J37: =+IF(F37="Perú",$D$21,$D$22)/V37/W37 -> 5.4778061 | K37: =+SUM(H37:J37) -> 34.266613 | M37: =+SUM(H37:J37)*$D$24+$D$25/V37/W37+$D$26/V37/48 -> 1.5634303 | N37: =+($D$27+$D$28)/V37 -> 1.5256573 | O37: =+SUM(H37:N37)*$E$29 -> 0.45448753 | P37: =+$D$30/V37 -> 0.58312129 | Q37: =+SUM(H37:P37)*$D$31 -> 0.30371848 | R37: =+SUM(M37:Q37) -> 4.4304149 | T37: =+H37+I37+R37+J37 -> 38.697028 | V37: 18.864 | W37: 42 | AB37: 8.8763732
A38: =B38&C38&D38&E38&F38 -> 17.7AMBAR18810.75El Salvador | B38: 17.7 | C38: AMBAR | D38: 1881 | E38: 0.75 | F38: El Salvador | G38: CFR | H38: =+(VLOOKUP(F38,$C$12:$D$13,2,0)*B38/1000*(1-E38)+IF(F38="Perú",$D$15,$D$16)*B38/1000*E38)*(1+$D$18) -> 26.683884 | I38: =AB38*(1+(Inputs!AD$8/Inputs!AD$7-1)*50%) -> 11.495911 | J38: =+IF(F38="Perú",$D$21,$D$22)/V38/W38 -> 5.4778061 | K38: =+SUM(H38:J38) -> 43.657601 | M38: =+SUM(H38:J38)*$D$24+$D$25/V38/W38+$D$26/V38/48 -> 1.5871895 | N38: =+($D$27+$D$28)/V38 -> 1.5256573 | O38: =+SUM(H38:N38)*$E$29 -> 0.57382146 | P38: =+$D$30/V38 -> 0.58312129 | Q38: =+SUM(H38:P38)*$D$31 -> 0.38282527 | R38: =+SUM(M38:Q38) -> 4.6526148 | T38: =+H38+I38+R38+J38 -> 48.310216 | V38: 18.864 | W38: 42 | AB38: 11.316763
A39: =B39&C39&D39&E39&F39 -> 17.7VERDE18810El Salvador | B39: 17.7 | C39: VERDE | D39: 1881 | E39: 0 | F39: El Salvador | G39: CFR | H39: =+(VLOOKUP(F39,$C$12:$D$13,2,0)*B39/1000*(1-E39)+IF(F39="Perú",$D$15,$D$16)*B39/1000*E39)*(1+$D$18) -> 19.771918 | I39: =AB39*(1+(Inputs!AD$8/Inputs!AD$7-1)*50%) -> 12.564906 | J39: =+IF(F39="Perú",$D$21,$D$22)/V39/W39 -> 5.4778061 | K39: =+SUM(H39:J39) -> 37.81463 | M39: =+SUM(H39:J39)*$D$24+$D$25/V39/W39+$D$26/V39/48 -> 1.5724067 | N39: =+($D$27+$D$28)/V39 -> 1.5256573 | O39: =+SUM(H39:N39)*$E$29 -> 0.49957318 | P39: =+$D$30/V39 -> 0.58312129 | Q39: =+SUM(H39:P39)*$D$31 -> 0.33360588 | R39: =+SUM(M39:Q39) -> 4.5143644 | T39: =+H39+I39+R39+J39 -> 42.328994 | V39: 18.864 | W39: 42 | AB39: 12.369099
A40: =B40&C40&D40&E40&F40 -> 19.5CRISTAL18810El Salvador | B40: 19.5 | C40: CRISTAL | D40: 1881 | E40: 0 | F40: El Salvador | G40: CFR | H40: =+(VLOOKUP(F40,$C$12:$D$13,2,0)*B40/1000*(1-E40)+IF(F40="Perú",$D$15,$D$16)*B40/1000*E40)*(1+$D$18) -> 21.782621 | I40: =AB40*(1+(Inputs!AD$8/Inputs!AD$7-1)*50%) -> 9.016074 | J40: =+IF(F40="Perú",$D$21,$D$22)/V40/W40 -> 5.4778061 | K40: =+SUM(H40:J40) -> 36.276501 | M40: =+SUM(H40:J40)*$D$24+$D$25/V40/W40+$D$26/V40/48 -> 1.5685153 | N40: =+($D$27+$D$28)/V40 -> 1.5256573 | O40: =+SUM(H40:N40)*$E$29 -> 0.48002775 | P40: =+$D$30/V40 -> 0.58312129 | Q40: =+SUM(H40:P40)*$D$31 -> 0.32064916 | R40: =+SUM(M40:Q40) -> 4.4779708 | T40: =+H40+I40+R40+J40 -> 40.754472 | V40: 18.864 | W40: 42 | AB40: 8.8755706
A41: =B41&C41&D41&E41&F41 -> 19.5VERDE18810El Salvador | B41: 19.5 | C41: VERDE | D41: 1881 | E41: 0 | F41: El Salvador | G41: CFR | H41: =+(VLOOKUP(F41,$C$12:$D$13,2,0)*B41/1000*(1-E41)+IF(F41="Perú",$D$15,$D$16)*B41/1000*E41)*(1+$D$18) -> 21.782621 | I41: =AB41*(1+(Inputs!AD$8/Inputs!AD$7-1)*50%) -> 9.0288006 | J41: =+IF(F41="Perú",$D$21,$D$22)/V41/W41 -> 5.4778061 | K41: =+SUM(H41:J41) -> 36.289228 | M41: =+SUM(H41:J41)*$D$24+$D$25/V41/W41+$D$26/V41/48 -> 1.5685475 | N41: =+($D$27+$D$28)/V41 -> 1.5256573 | O41: =+SUM(H41:N41)*$E$29 -> 0.48018947 | P41: =+$D$30/V41 -> 0.58312129 | Q41: =+SUM(H41:P41)*$D$31 -> 0.32075636 | R41: =+SUM(M41:Q41) -> 4.4782719 | T41: =+H41+I41+R41+J41 -> 40.7675 | V41: 18.864 | W41: 42 | AB41: 8.8880989
A42: =B42&C42&D42&E42&F42 -> 17.7CRISTAL18810Perú | B42: 17.7 | C42: CRISTAL | D42: 1881 | E42: 0 | F42: Perú | G42: DDP | H42: =+(VLOOKUP(F42,$C$12:$D$13,2,0)*B42/1000*(1-E42)+IF(F42="Perú",$D$15,$D$16)*B42/1000*E42)*(1+$D$18) -> 18.651242 | I42: =AB42*(1+(Inputs!AD$8/Inputs!AD$7-1)*50%) -> 9.016074 | J42: =+IF(F42="Perú",$D$21,$D$22)/V42/W42 -> 5.0402346 | K42: =+SUM(H42:J42) -> 32.707551 | M42: =+SUM(H42:J42)*$D$24+$D$25/V42/W42+$D$26/V42/48 -> 1.6853142 | N42: =+($D$27+$D$28)/V42 -> 1.4758974 | O42: =+SUM(H42:N42)*$E$29 -> 0.43515879 | P42: =+$D$30/V42 -> 0.56410256 | Q42: =+SUM(H42:P42)*$D$31 -> 0.2908259 | R42: =+SUM(M42:Q42) -> 4.4512989 | T42: =+H42+I42+R42+J42 -> 37.15885 | V42: 19.5 | W42: 36 | AB42: 8.8755706
A43: =B43&C43&D43&E43&F43 -> 17.7VERDE18810Perú | B43: 17.7 | C43: VERDE | D43: 1881 | E43: 0 | F43: Perú | G43: DDP | H43: =+(VLOOKUP(F43,$C$12:$D$13,2,0)*B43/1000*(1-E43)+IF(F43="Perú",$D$15,$D$16)*B43/1000*E43)*(1+$D$18) -> 18.651242 | I43: =AB43*(1+(Inputs!AD$8/Inputs!AD$7-1)*50%) -> 10.420967 | J43: =+IF(F43="Perú",$D$21,$D$22)/V43/W43 -> 5.0402346 | K43: =+SUM(H43:J43) -> 34.112444 | M43: =+SUM(H43:J43)*$D$24+$D$25/V43/W43+$D$26/V43/48 -> 1.6888686 | N43: =+($D$27+$D$28)/V43 -> 1.4758974 | O43: =+SUM(H43:N43)*$E$29 -> 0.45301117 | P43: =+$D$30/V43 -> 0.56410256 | Q43: =+SUM(H43:P43)*$D$31 -> 0.30266029 | R43: =+SUM(M43:Q43) -> 4.48454 | T43: =+H43+I43+R43+J43 -> 38.596984 | V43: 19.5 | W43: 36 | AB43: 10.258571
A44: =B44&C44&D44&E44&F44 -> 19.7CRISTAL18810Perú | B44: 19.7 | C44: CRISTAL | D44: 1881 | E44: 0 | F44: Perú | G44: DDP | H44: =+(VLOOKUP(F44,$C$12:$D$13,2,0)*B44/1000*(1-E44)+IF(F44="Perú",$D$15,$D$16)*B44/1000*E44)*(1+$D$18) -> 20.758727 | I44: =AB44*(1+(Inputs!AD$8/Inputs!AD$7-1)*50%) -> 9.016074 | J44: =+IF(F44="Perú",$D$21,$D$22)/V44/W44 -> 5.0402346 | K44: =+SUM(H44:J44) -> 34.815036 | M44: =+SUM(H44:J44)*$D$24+$D$25/V44/W44+$D$26/V44/48 -> 1.6906461 | N44: =+($D$27+$D$28)/V44 -> 1.4758974 | O44: =+SUM(H44:N44)*$E$29 -> 0.4619392 | P44: =+$D$30/V44 -> 0.56410256 | Q44: =+SUM(H44:P44)*$D$31 -> 0.30857871 | R44: =+SUM(M44:Q44) -> 4.501164 | T44: =+H44+I44+R44+J44 -> 39.3162 | V44: 19.5 | W44: 36 | AB44: 8.8755706
A45: =B45&C45&D45&E45&F45 -> 19.7VERDE18810Perú | B45: 19.7 | C45: VERDE | D45: 1881 | E45: 0 | F45: Perú | G45: DDP | H45: =+(VLOOKUP(F45,$C$12:$D$13,2,0)*B45/1000*(1-E45)+IF(F45="Perú",$D$15,$D$16)*B45/1000*E45)*(1+$D$18) -> 20.758727 | I45: =AB45*(1+(Inputs!AD$8/Inputs!AD$7-1)*50%) -> 10.420967 | J45: =+IF(F45="Perú",$D$21,$D$22)/V45/W45 -> 5.0402346 | K45: =+SUM(H45:J45) -> 36.219929 | M45: =+SUM(H45:J45)*$D$24+$D$25/V45/W45+$D$26/V45/48 -> 1.6942005 | N45: =+($D$27+$D$28)/V45 -> 1.4758974 | O45: =+SUM(H45:N45)*$E$29 -> 0.47979157 | P45: =+$D$30/V45 -> 0.56410256 | Q45: =+SUM(H45:P45)*$D$31 -> 0.3204131 | R45: =+SUM(M45:Q45) -> 4.5344052 | T45: =+H45+I45+R45+J45 -> 40.754334 | V45: 19.5 | W45: 36 | AB45: 10.258571
A46: =B46&C46&D46&E46&F46 -> 29CRISTAL18160El Salvador | B46: 29 | C46: CRISTAL | D46: 1816 | E46: 0 | F46: El Salvador | G46: CFR | H46: =+(VLOOKUP(F46,$C$12:$D$13,2,0)*B46/1000*(1-E46)+IF(F46="Perú",$D$15,$D$16)*B46/1000*E46)*(1+$D$18) -> 32.394667 | I46: =AB46*(1+(Inputs!AD$8/Inputs!AD$7-1)*50%) -> 17.69134 | J46: =+IF(F46="Perú",$D$21,$D$22)/V46/W46 -> 10.251323 | K46: =+SUM(H46:J46) -> 60.33733 | M46: =+SUM(H46:J46)*$D$24+$D$25/V46/W46+$D$26/V46/48 -> 2.9162589 | N46: =+($D$27+$D$28)/V46 -> 2.8551587 | O46: =+SUM(H46:N46)*$E$29 -> 0.80237795 | P46: =+$D$30/V46 -> 1.0912698 | Q46: =+SUM(H46:P46)*$D$31 -> 0.53646005 | R46: =+SUM(M46:Q46) -> 8.2015255 | T46: =+H46+I46+R46+J46 -> 68.538855 | V46: 10.08 | W46: 42 | AB46: 17.415644
A47: =B47&C47&D47&E47&F47 -> 29VERDE18160El Salvador | B47: 29 | C47: VERDE | D47: 1816 | E47: 0 | F47: El Salvador | G47: CFR | H47: =+(VLOOKUP(F47,$C$12:$D$13,2,0)*B47/1000*(1-E47)+IF(F47="Perú",$D$15,$D$16)*B47/1000*E47)*(1+$D$18) -> 32.394667 | I47: =AB47*(1+(Inputs!AD$8/Inputs!AD$7-1)*50%) -> 18.247342 | J47: =+IF(F47="Perú",$D$21,$D$22)/V47/W47 -> 10.251323 | K47: =+SUM(H47:J47) -> 60.893332 | M47: =+SUM(H47:J47)*$D$24+$D$25/V47/W47+$D$26/V47/48 -> 2.9176656 | N47: =+($D$27+$D$28)/V47 -> 2.8551587 | O47: =+SUM(H47:N47)*$E$29 -> 0.80944323 | P47: =+$D$30/V47 -> 1.0912698 | Q47: =+SUM(H47:P47)*$D$31 -> 0.54114364 | R47: =+SUM(M47:Q47) -> 8.214681 | T47: =+H47+I47+R47+J47 -> 69.108013 | V47: 10.08 | W47: 42 | AB47: 17.962981
... A49: =B49&C49&D49&E49&F49 -> 42.5VERDE18160.5El Salvador | B49: 42.5 | C49: VERDE | D49: 1816 | E49: 0.5 | F49: El Salvador | G49: CFR | H49: =+(VLOOKUP(F49,$C$12:$D$13,2,0)*B49/1000*(1-E49)+IF(F49="Perú",$D$15,$D$16)*B49/1000*E49)*(1+$D$18) -> 58.539296 | I49: =AB49*(1+(Inputs!AD$8/Inputs!AD$7-1)*50%) -> 18.504004 | J49: =+IF(F49="Perú",$D$21,$D$22)/V49/W49 -> 10.790866 | K49: =+SUM(H49:J49) -> 87.834166 | M49: =+SUM(H49:J49)*$D$24+$D$25/V49/W49+$D$26/V49/48 -> 3.1312788 | N49: =+($D$27+$D$28)/V49 -> 3.0054302 | O49: =+SUM(H49:N49)*$E$29 -> 1.1536646 | P49: =+$D$30/V49 -> 1.1487051 | Q49: =+SUM(H49:P49)*$D$31 -> 0.76956898 | R49: =+SUM(M49:Q49) -> 9.2086477 | T49: =+H49+I49+R49+J49 -> 97.042813 | V49: 9.576 | W49: 42 | AB49: 18.215644
B50: 2 | C50: =+B50+1 -> 3 | D50: =+C50+1 -> 4 | E50: =+D50+1 -> 5 | F50: =+E50+1 -> 6 | G50: =+F50+1 -> 7 | H50: =+G50+1 -> 8 | I50: =+H50+1 -> 9 | J50: =+I50+1 -> 10 | ... AB50: =+AA50+1 -> 28

Sheet Inputs
B2: HOJA DE INPUTS | G2: 1. vPET | L2: 1.2 Fletes Marítimos Internacionales: | P2: 2. Resina Reciclada | U2: 3. Costos Logisticos de Preforma | AC2: 4. IPC
G3: 1.1 Indice de precios de resina | L3: Indices Fletes Maritimos Drewry | AC3: Fuente: | AD3: U.S. BLS
G4: Índice: | L4: Índice: | P4: Inventario Final | Q4: Perú | U4: Perú | W4: 3538.2447 | AC4: CPI for All Urban Consumers (CPI-U)
C5: AÑO | D5: MES | G5: ICIS - ASIA SE - Low | L5: Central China (Shanghai) to El Salvador (Acajutla) | P5: Mes | Q5: Precio Paca | U5: El Salvador | W5: 4340 | AC5: IPC USA
B6: *ACTUALIZAR A LP: | C6: 2026 | D6: 4 | G6: Mes | H6: USD/TM | L6: Mes | M6: Flete (USD/TM) | P6: 2026-2 | Q6: 485.17558 | R6: USD / TM | AC6: Mes | AD6: IPC | AE6: Inflación acum
G7: 2026-2 | H7: 852.5 | L7: 2026-2 | M7: 122.22727 | U7: Seguro Maritimo (%) | W7: 0.00253 | AB7: Base | AC7: 2024-6 | AD7: 314.175
C8: PERIODO | D8: MES INICIAL | H8: El Salvador | I8: Perú | P8: Scrap | Q8: 0.3 | U8: Gastos de Internación (USD/Contenedor) | W8: 855 | AB8: Actual | AC8: 2025-11 | AD8: 324.122 | AE8: =AD8/AD7-1 -> 0.031660699 | AF8: Actualizar en Ene-26, con CPI Nov-25
C9: =UPPER(C6&"-"&D6) -> 2026-4 | D9: =D6 -> 4 | G9: Precio FOB | H9: =AVERAGE(H7:H7) -> 852.5 | I9: =+H7 -> 852.5 | L9: Central China (Shanghai) to Peru (Callao) | P9: Conversión | Q9: =725*(1+(Inputs!AD$8/Inputs!AD$7-1)*50%) -> 736.477 | R9: USD / TM | U9: Flete al Almacén (USD/Camión) | W9: 360
G10: Flete marítimo | H10: =IF(M7>180,M7+25,195) -> 195 | I10: =IF(M11>180,M11+25,161) -> 161 | L10: Mes | M10: Flete (USD/TM) | P10: Precio rPET | Q10: =+Q6/(1-Q8)+Q9 -> 1429.585 | R10: USD / TM | U10: Gastos de Almacenaje (USD/caja) | W10: 14.9
B11: Validez Inicial | C11: =DATE($C$6,$D$6,1) -> 46113 | G11: Nacionalización (%) | H11: 64 | I11: 35 | L11: 2026-2 | M11: 55.272727 | P11: Flete | Q11: 200 | U11: Recepción y despacho (USD/Caja) | W11: 13.88
B12: Validez Final | C12: =IF(ISNUMBER($D$6),EOMONTH(C11,0),0) + IF(LEFT($D$6,1)="B",EOMONTH(C11,1),0) + IF(LEFT($D$6,1)="Q",EOMONTH(C11,2),0) + IF(LEFT($D$6,1)="S",EOMONTH(C11,5),0) -> 46142 | G12: Precio DDP | H12: =+SUM(Inputs!H9:H11) -> 1111.5 | I12: =+SUM(Inputs!I9:I11) -> 1048.5 | P12: Precio rPET ES | Q12: =+Q10+Q11 -> 1629.585 | U12: Gastos Financieros (Tasa Anual) | W12: 0.08 | X12: =+(1+W12)^(30/365)-1 -> 0.0063456137
U13: Flete al Planta Cliente (USD/Caja) | W13: 11
G14: Merma sobre precio DDP | H14: 0.005 | I14: 0.005 | P14: Merma sobre precio DDP | Q14: 0.005 | U14: Seguro Terreste (%) | W14: 0.00418

Sheet Hoja1
B2: Preform Weight SMI (g) | C2: Colors | D2: Neck Finish SMI | E2: %rPET | F2: Preform Origin | G2: Incoterm | H2: Resin Price USD/Thousand | I2: Non Resin Price (ExW) USD/Thousand | J2: Maritime Freight USD/Thousand | L2: Maritime Insurance, expenses of internalization, internal freight to SMI warehouse (USD/Thousand) | M2: Storage costs (USD/Thousand) | N2: Financial expenses for 30 days of stock in stock (USD/Thousand) | O2: Freight to the ABI plant - Hato Nuevo (USD/Thousand) | P2: Terrestrial insurance (USD/Thousand) | Q2: Total expenses to DDP - Hato Nuevo (USD/Thousand) | S2: Total Price (DDP) USD/Thousand
B3: 29 | C3: CRISTAL | D3: 1881 | E3: 0 | F3: El Salvador | G3: CFR | H3: 31.933481 | I3: 18.072406 | J3: 9.731335 | L3: 2.9336992 | M3: 1.3053467 | N3: 0.40596868 | O3: 1.2531328 | P3: 0.27435585 | Q3: 6.1725033 | S3: 65.909726
