Workbook

Sheet ICIS Price History
B2: ICIS Dashboard Price History
B3: Generated | C3: 03 May 2021 23:34:05
B4: Data | C4: Price History
B5: Date Range | C5: From 03 May 2020 to 03 May 2021
B6: Original Currency | C6: USD | D6: USD | E6: USD
B7: Original Unit | C7: tonne | D7: tonne | E7: tonne
B8: Original Frequency | C8: Weekly | D8: Weekly | E8: Weekly
B9: Selected Currency | C9: USD | D9: USD | E9: USD
B10: Selected Unit | C10: tonne | D10: tonne | E10: tonne | I10: Referencia índice resina para ABI
B11: Selected Frequency | C11: Weekly | D11: Weekly | E11: Weekly
B13: Date | C13: PET Bottle Grade FOB China Assessment Spot Full Market Range Weekly (Low) : USD/tonne | D13: PET Bottle Grade FOB China Assessment Spot Full Market Range Weekly (High) : USD/tonne | E13: PET Bottle Grade FOB China Assessment Spot Full Market Range Weekly (Mid) : USD/tonne | G13: PET Bottle Grade FOB China Assessment Spot Full Market Range Weekly (Low) : USD/tonne | H13: PET Bottle Grade FOB China Assessment Spot Full Market Range Weekly (High) : USD/tonne | I13: PET Bottle Grade FOB China Assessment Spot Full Market Range Weekly (Mid) : USD/tonne (N-4 a partir de julio 2023) | J13: i | K13: Logistics | L13: LANDED | M13: Finance fee V (SOFR +3,8%@185) | N13: CME TERM SOFR (%) 180 | O13: Surcharge | Q13: Total precio ABI
B14: 08-May-2020 | C14: 660 | D14: 680 | E14: 670 | F14: 43952 | G14: 662.5 | H14: 687.5 | I14: 675 | J14: 34.84 | K14: 125 | O14: 0 | Q14: =I14+J14+K14+O14 -> 834.84
B15: 15-May-2020 | C15: 655 | D15: 680 | E15: 667.5
B16: 22-May-2020 | C16: 670 | D16: 700 | E16: 685
B17: 29-May-2020 | C17: 665 | D17: 690 | E17: 677.5
B18: 05-Jun-2020 | C18: 670 | D18: 700 | E18: 685 | F18: 43983 | G18: =AVERAGE(C18:C21) -> 666.25 | H18: 691.25 | I18: =+AVERAGE(E18:E21) -> 678.75 | J18: 34.84 | K18: 125 | O18: 0 | Q18: =I18+J18+K18+O18 -> 838.59
B19: 12-Jun-2020 | C19: 670 | D19: 695 | E19: 682.5
B20: 19-Jun-2020 | C20: 660 | D20: 680 | E20: 670
B21: 26-Jun-2020 | C21: 665 | D21: 690 | E21: 677.5
B22: 03-Jul-2020 | C22: 665 | D22: 685 | E22: 675 | F22: 44013 | G22: 657 | H22: 674 | I22: 665.5 | J22: 34.84 | K22: 125 | O22: 0 | Q22: =I22+J22+K22+O22 -> 825.34
B23: 10-Jul-2020 | C23: 665 | D23: 680 | E23: 672.5
B24: 17-Jul-2020 | C24: 655 | D24: 675 | E24: 665
B25: 24-Jul-2020 | C25: 650 | D25: 665 | E25: 657.5
B26: 31-Jul-2020 | C26: 650 | D26: 665 | E26: 657.5
B27: 07-Aug-2020 | C27: 645 | D27: 665 | E27: 655 | F27: 44044 | G27: 645 | H27: 661.25 | I27: 653.125 | J27: 34.84 | K27: 125 | O27: 0 | Q27: =I27+J27+K27+O27 -> 812.965
B28: 14-Aug-2020 | C28: 645 | D28: 660 | E28: 652.5
B29: 21-Aug-2020 | C29: 645 | D29: 660 | E29: 652.5
B30: 28-Aug-2020 | C30: 645 | D30: 660 | E30: 652.5
B31: 04-Sep-2020 | C31: 645 | D31: 670 | E31: 657.5 | F31: 44075 | G31: 645 | H31: 665 | I31: 655 | J31: 34.84 | K31: 125 | O31: 0 | Q31: =I31+J31+K31+O31 -> 814.84
B32: 11-Sep-2020 | C32: 645 | D32: 670 | E32: 657.5
B33: 18-Sep-2020 | C33: 645 | D33: 665 | E33: 655
B34: 25-Sep-2020 | C34: 645 | D34: 655 | E34: 650
B35: 02-Oct-2020 | C35: 630 | D35: 650 | E35: 640 | F35: 44105 | G35: 635 | H35: 657 | I35: 646 | J35: 34.84 | K35: 125 | O35: 0 | Q35: =I35+J35+K35+O35 -> 805.84
B36: 09-Oct-2020 | C36: 630 | D36: 650 | E36: 640
B37: 16-Oct-2020 | C37: 630 | D37: 660 | E37: 645
B38: 23-Oct-2020 | C38: 645 | D38: 665 | E38: 655
B39: 30-Oct-2020 | C39: 640 | D39: 660 | E39: 650
B40: 06-Nov-2020 | C40: 635 | D40: 650 | E40: 642.5 | F40: 44136 | G40: 642.5 | H40: 665 | I40: 653.75 | J40: 34.84 | K40: 125 | O40: 0 | Q40: =I40+J40+K40+O40 -> 813.59
B41: 13-Nov-2020 | C41: 640 | D41: 660 | E41: 650
B42: 20-Nov-2020 | C42: 645 | D42: 670 | E42: 657.5
B43: 27-Nov-2020 | C43: 650 | D43: 680 | E43: 665
B44: 04-Dec-2020 | C44: 665 | D44: 695 | E44: 680 | F44: 44166 | G44: 701.25 | H44: 727.5 | I44: 714.375 | J44: 34.84 | K44: 131 | O44: 0 | Q44: =I44+J44+K44+O44 -> 880.215
B45: 11-Dec-2020 | C45: 700 | D45: 720 | E45: 710
B46: 18-Dec-2020 | C46: 720 | D46: 750 | E46: 735
B47: 25-Dec-2020 | C47: 720 | D47: 745 | E47: 732.5
B48: 08-Jan-2021 | C48: 755 | D48: 790 | E48: 772.5 | F48: 44197 | G48: 778.75 | H48: 812.5 | I48: 795.625 | J48: 34.84 | K48: 131 | O48: 0 | Q48: =I48+J48+K48+O48 -> 961.465
B49: 15-Jan-2021 | C49: 780 | D49: 820 | E49: 800
B50: 22-Jan-2021 | C50: 790 | D50: 820 | E50: 805
B51: 29-Jan-2021 | C51: 790 | D51: 820 | E51: 805
B52: 05-Feb-2021 | C52: 820 | D52: 860 | E52: 840 | F52: 44228 | G52: 868.75 | H52: 920 | I52: 894.375 | J52: 34.84 | K52: =131+78 -> 209 | O52: 55 | Q52: =I52+J52+K52+O52 -> 1193.215
B53: 12-Feb-2021 | C53: 845 | D53: 870 | E53: 857.5
B54: 19-Feb-2021 | C54: 870 | D54: 920 | E54: 895
B55: 26-Feb-2021 | C55: 940 | D55: 1030 | E55: 985
B56: 05-Mar-2021 | C56: 1020 | D56: 1060 | E56: 1040 | F56: 44256 | G56: 1008.75 | H56: 1046.25 | I56: 1027.5 | J56: 34.84 | K56: =131+78 -> 209 | O56: 55 | Q56: =I56+J56+K56+O56 -> 1326.34
B57: 12-Mar-2021 | C57: 1020 | D57: 1060 | E57: 1040
B58: 19-Mar-2021 | C58: 1005 | D58: 1045 | E58: 1025
B59: 26-Mar-2021 | C59: 990 | D59: 1020 | E59: 1005
B60: 02-Apr-2021 | C60: 980 | D60: 1015 | E60: 997.5 | F60: 44287 | G60: 948 | H60: 990 | I60: 969 | J60: 34.84 | K60: =131+78 -> 209 | O60: 55 | Q60: =I60+J60+K60+O60 -> 1267.84
B61: 09-Apr-2021 | C61: 960 | D61: 1005 | E61: 982.5
B62: 16-Apr-2021 | C62: 940 | D62: 990 | E62: 965
B63: 23-Apr-2021 | C63: 940 | D63: 980 | E63: 960
B64: 30-Apr-2021 | C64: 920 | D64: 960 | E64: 940
B65: 07-May-2021 | C65: 920 | D65: 970 | E65: 945 | F65: 44317 | G65: =AVERAGE(C65:C68) -> 918.75 | H65: =AVERAGE(D65:D68) -> 962.5 | I65: =AVERAGE(E65:E68) -> 940.625 | J65: =34.84 -> 34.84 | K65: =131+78+18 -> 227 | O65: 55 | Q65: =I65+J65+K65+O65 -> 1257.465
B66: 14-May-2021 | C66: 910 | D66: 965 | E66: 937.5
B67: 21-May-2021 | C67: 930 | D67: 970 | E67: 950
B68: 28-May-2021 | C68: 915 | D68: 945 | E68: 930
B69: 04-Jun-2021 | C69: 915 | D69: 950 | E69: 932.5 | F69: 44348 | G69: =AVERAGE(C69:C72) -> 906.25 | H69: =AVERAGE(D69:D72) -> 947.5 | I69: =AVERAGE(E69:E72) -> 926.875 | J69: =34.84 -> 34.84 | K69: =131+78+18 -> 227 | O69: 55 | Q69: =I69+J69+K69+O69 -> 1243.715
B70: 11-Jun-2021 | C70: 900 | D70: 940 | E70: 920
B71: 18-Jun-2021 | C71: 900 | D71: 940 | E71: 920
B72: 25-Jun-2021 | C72: 910 | D72: 960 | E72: 935
B73: 02-Jul-2021 | C73: 930 | D73: 960 | E73: 945 | F73: 44378 | G73: =AVERAGE(C73:C76) -> 940 | H73: =AVERAGE(D73:D76) -> 978.75 | I73: =AVERAGE(E73:E76) -> 959.375 | J73: 34.84 | K73: =227+70 -> 297 | O73: 55 | Q73: =I73+J73+K73+O73 -> 1346.215
B74: 09-Jul-2021 | C74: 945 | D74: 990 | E74: 967.5
B75: 16-Jul-2021 | C75: 945 | D75: 975 | E75: 960
B76: 23-Jul-2021 | C76: 940 | D76: 990 | E76: 965
B77: 30-Jul-2021 | C77: 975 | D77: 1010 | E77: 992.5
B78: 06-Aug-2021 | C78: 980 | D78: 1000 | E78: 990 | F78: 44409 | G78: =AVERAGE(C78:C81) -> 962.5 | H78: =AVERAGE(D78:D81) -> 990 | I78: =AVERAGE(E78:E81) -> 976.25 | J78: =34.84 -> 34.84 | K78: =227+70 -> 297 | O78: 55 | Q78: =I78+J78+K78+O78 -> 1363.09
B79: 13-Aug-2021 | C79: 970 | D79: 1000 | E79: 985
B80: 20-Aug-2021 | C80: 950 | D80: 980 | E80: 965
B81: 27-Aug-2021 | C81: 950 | D81: 980 | E81: 965
B82: 03-Sep-2021 | C82: 940 | D82: 970 | E82: 955 | F82: 44440 | G82: =AVERAGE(C82:C85) -> 938.75 | H82: =AVERAGE(D82:D85) -> 968.75 | I82: =AVERAGE(E82:E85) -> 953.75 | J82: 34.84 | K82: =227+70 -> 297 | O82: 55 | Q82: =I82+J82+K82+O82 -> 1340.59
B83: 10-Sep-2021 | C83: 930 | D83: 955 | E83: 942.5
B84: 17-Sep-2021 | C84: 940 | D84: 960 | E84: 950
B85: 24-Sep-2021 | C85: 945 | D85: 990 | E85: 967.5
B86: 01-Oct-2021 | C86: 995 | D86: 1040 | E86: 1017.5 | F86: 44470 | G86: =AVERAGE(C86:C89) -> 1076.25 | H86: =AVERAGE(D86:D89) -> 1120 | I86: =AVERAGE(E86:E90) -> 1111.5 | J86: 34.84 | K86: 297 | O86: 55 | Q86: =I86+J86+K86+O86 -> 1498.34
B87: 08-Oct-2021 | C87: 1020 | D87: 1100 | E87: 1060
B88: 15-Oct-2021 | C88: 1120 | D88: 1150 | E88: 1135
B89: 22-Oct-2021 | C89: 1170 | D89: 1190 | E89: 1180
B90: 29-Oct-2021 | C90: 1150 | D90: 1180 | E90: 1165
B91: 44505 | C91: 1130 | D91: 1170 | E91: 1150 | F91: 44501 | G91: =AVERAGE(C91:C94) -> 1091.25 | H91: =AVERAGE(D91:D94) -> 1142.5 | I91: =AVERAGE(E91:E94) -> 1116.875 | J91: 34.84 | K91: =227+70+72.16 -> 369.16 | O91: 55 | Q91: =I91+J91+K91+O91 -> 1575.875
B92: 44512 | C92: 1100 | D92: 1155 | E92: 1127.5
B93: 44519 | C93: 1085 | D93: 1135 | E93: 1110
B94: 44526 | C94: 1050 | D94: 1110 | E94: 1080
B95: 03-Dec-2021 | C95: 1000 | D95: 1050 | E95: 1025 | F95: 44531 | G95: =AVERAGE(C95:C98) -> 1000 | H95: =AVERAGE(D95:D98) -> 1050 | I95: =AVERAGE(E95:E98) -> 1025 | J95: 34.84 | K95: =227+70+72.16 -> 369.16 | O95: 55 | Q95: =I95+J95+K95+O95 -> 1484
B96: 10-Dec-2021 | C96: 1000 | D96: 1050 | E96: 1025
B97: 17-Dec-2021 | C97: 1000 | D97: 1050 | E97: 1025
B98: 24-Dec-2022 | C98: 1000 | D98: 1050 | E98: 1025
B99: 7 jan 2022 | C99: 1040 | D99: 1085 | E99: 1062.5 | G99: =AVERAGE(C99:C101) -> 1060 | H99: =AVERAGE(D99:D101) -> 1100 | I99: =AVERAGE(E99:E101) -> 1080 | J99: 34.84 | K99: 441.82 | Q99: =I99+J99+K99+O99 -> 1556.66
B100: 14 jan 2022 | C100: 1060 | D100: 1105 | E100: 1082.5
B101: 21 jan 2022 | C101: 1080 | D101: 1110 | E101: 1095
B102: 28 jan 2022 | C102: 1090 | D102: 1130 | E102: 1110 | G102: =AVERAGE(C102:C104) -> 1116.6667 | H102: =AVERAGE(D102:D104) -> 1153.3333 | I102: =AVERAGE(E102:E104) -> 1135 | J102: 34.84 | K102: 441.82 | Q102: =I102+J102+K102+O102 -> 1611.66
...

Sheet Sheet1
H8: Formulae is different than how is it calucated
H9: scrap is not used
E11: Index | F11: 748.75
E12: Adder | F12: 34.84 | G12: Is it constant ? | H12: Not available I nthe formulae
E13: Freight | F13: 185.8 | G13: constant
E14: Landed | F14: 30 | G14: constant
E15: CIF | F15: =SUM(F11:F14) -> 999.39
E16: Tax | F16: 0.038 | G16: constant ?
E17: SOFR | F17: 0.04 | G17: Constant
F18: =F17+F16 -> 0.078
E19: Finance Fee | F19: =((F15*F18)/365)*185 -> 39.510131 | H19: Can I consider the whole 40 as part of Tax ?
E20: TLC | F20: =F19+F11+F12+F13+F14 -> 1038.9001

Sheet Precios - MAR 26 
B3: SELL SIDE PreMix (100% Virgen) | D3: SELL SIDE para aplicar en Mar 2026
B4: Precio aplicable Mar 2026
B5: Rpet Formula | F5: Kardex | G5: Handling Fee | H5: Scrap Fee | I5: Sell Side Invema
C6: cpp | F6: =+F7/22.0462262 -> 0 | G6: 0 | H6: =+SUM(F6:G6)*0.5% -> 0 | I6: =+SUM(D6:H6) -> 0
C7: $/MT | G7: =+G6*22.0462 -> 0 | H7: =+H6*22.0462 -> 0 | I7: =+I6*22.0462 -> 0
B9: Vpet Formula | F9: Kardex | G9: Handling Fee | H9: Scrap Fee | I9: Sell Side FENC
C10: cpp | F10: =+F11/22.0462262 -> 47.509979 | G10: 0 | H10: =+SUM(F10:G10)*0.5% -> 0.23754989 | I10: =SUM(D10:H10) -> 47.747529
C11: $/MT | F11: =+Kardex!CX8 -> 1047.4157 | G11: =+G10*22.0462 -> 0 | H11: =+H10*22.0462 -> 5.2370725 | I11: =+I10*22.0462 -> 1052.6516
B13: Pre-Mix Price | D13: 0% PCR | E13: 100% virgen | F13: Mixing Fee | G13: Handling Fee | H13: Scrap Fee | I13: Sell Side Pre-Mix
C14: cpp | D14: =I6*0.25 -> 0 | E14: =I10*1 -> 47.747529 | G14: 1.3655 | H14: 0 | I14: =+SUM(D14:H14) -> 49.113029
C15: $/MT | D15: =+D14*22.0462 -> 0 | E15: =+E14*22.0462 -> 1052.6516 | F15: =+F14*22.0462 -> 0 | G15: =+G14*22.0462 -> 30.104086 | H15: =+H14*22.0462 -> 0 | I15: =+I14*22.0462 -> 1082.7557
F16: =F15/2 -> 0 | G16: =G15/1 -> 30.104086 | H16: =+H15*22.0462 -> 0
B21: TERCERA PARTE 75/25
B22: SELL SIDE PreMix (FENC @ 75% + Invema @ 25%) | D22: =+D3 -> SELL SIDE para aplicar en Mar 2026
B23: =+B4 -> Precio aplicable Mar 2026
B24: Rpet Formula | F24: Kardex | G24: Handling Fee | H24: Scrap Fee | I24: Sell Side Invema
C25: cpp | F25: =+F26/22.0462262 -> 70.202412 | G25: 0 | H25: =+SUM(F25:G25)*0.5% -> 0.35101206 | I25: =+SUM(D25:H25) -> 70.553424
C26: $/MT | F26: =+Kardex!CX23 -> 1547.6983 | G26: =+G25*22.0462 -> 0 | H26: =+H25*22.0462 -> 7.7384821 | I26: =+I25*22.0462 -> 1555.4349
B28: Vpet Formula | F28: Kardex | G28: Handling Fee | H28: Scrap Fee | I28: Sell Side FENC
C29: cpp | F29: =+F30/22.0462262 -> 47.509979 | G29: 0 | H29: =+SUM(F29:G29)*0.5% -> 0.23754989 | I29: =SUM(D29:H29) -> 47.747529
C30: $/MT | F30: =+F11 -> 1047.4157 | G30: =+G29*22.0462 -> 0 | H30: =+H29*22.0462 -> 5.2370725 | I30: =+I29*22.0462 -> 1052.6516
B32: Pre-Mix Price | D32: 25% PCR | E32: 75% virgen | F32: Mixing Fee | G32: Handling Fee | H32: Scrap Fee | I32: Sell Side Pre-Mix
C33: cpp | D33: =I25*0.25 -> 17.638356 | E33: =I29*0.75 -> 35.810647 | F33: 0.4763 | G33: 1.3655 | H33: 0 | I33: =+SUM(D33:H33) -> 55.290803
C34: $/MT | D34: =+D33*22.0462 -> 388.85873 | E34: =+E33*22.0462 -> 789.48868 | F34: =+F33*22.0462 -> 10.500605 | G34: =+G33*22.0462 -> 30.104086 | H34: =+H33*22.0462 -> 0 | I34: =+I33*22.0462 -> 1218.9521
F35: =F34/2 -> 5.2503025 | G35: =G34/2 -> 15.052043 | H35: =G35+F35 -> 20.302346
B36: TERCERA PARTE 50/50
B37: SELL SIDE PreMix (FENC @ 50% + Invema @ 50%) | D37: =+D22 -> SELL SIDE para aplicar en Mar 2026
B38: =+B23 -> Precio aplicable Mar 2026
B39: Rpet Formula | F39: Kardex | G39: Handling Fee | H39: Scrap Fee | I39: Sell Side Invema
C40: cpp | F40: =+F41/22.0462262 -> 70.202412 | G40: 0 | H40: =+SUM(F40:G40)*0.5% -> 0.35101206 | I40: =+SUM(D40:H40) -> 70.553424
C41: $/MT | F41: =+F26 -> 1547.6983 | G41: =+G40*22.0462 -> 0 | H41: =+H40*22.0462 -> 7.7384821 | I41: =+I40*22.0462 -> 1555.4349
B43: Vpet Formula | F43: Kardex | G43: Handling Fee | H43: Scrap Fee | I43: Sell Side FENC
C44: cpp | F44: =+F45/22.0462262 -> 47.509979 | G44: 0 | H44: =+SUM(F44:G44)*0.5% -> 0.23754989 | I44: =SUM(D44:H44) -> 47.747529
C45: $/MT | F45: =+F30 -> 1047.4157 | G45: =+G44*22.0462 -> 0 | H45: =+H44*22.0462 -> 5.2370725 | I45: =+I44*22.0462 -> 1052.6516
B47: Pre-Mix Price | D47: 50% PCR | E47: 50% virgen | F47: Mixing Fee | G47: Handling Fee | H47: Scrap Fee | I47: Sell Side Pre-Mix
C48: cpp | D48: =I40*0.5 -> 35.276712 | E48: =I44*0.5 -> 23.873764 | F48: 0.4763 | G48: 1.3655 | H48: 0 | I48: =+SUM(D48:H48) -> 60.992277
C49: $/MT | D49: =+D48*22.0462 -> 777.71745 | E49: =+E48*22.0462 -> 526.32579 | F49: =+F48*22.0462 -> 10.500605 | G49: =+G48*22.0462 -> 30.104086 | H49: =+H48*22.0462 -> 0 | I49: =+I48*22.0462 -> 1344.6479
B54: TERCERA PARTE 100%PCR
B55: SELL SIDE PreMix (FENC @ 0 + Invema @ 100%) | D55: =+D37 -> SELL SIDE para aplicar en Mar 2026
B56: =+B38 -> Precio aplicable Mar 2026
B57: Rpet Formula | F57: Kardex | G57: Handling Fee | H57: Scrap Fee | I57: Sell Side Invema
C58: cpp | F58: =+F59/22.0462262 -> 70.202412 | G58: 0 | H58: =+SUM(F58:G58)*0.5% -> 0.35101206 | I58: =+SUM(D58:H58) -> 70.553424
C59: $/MT | F59: =+F41 -> 1547.6983 | G59: =+G58*22.0462 -> 0 | H59: =+H58*22.0462 -> 7.7384821 | I59: =+I58*22.0462 -> 1555.4349
B61: Vpet Formula | F61: Kardex | G61: Handling Fee | H61: Scrap Fee | I61: Sell Side FENC
C62: cpp | F62: =+F63/22.0462262 -> 0 | G62: 0 | H62: =+SUM(F62:G62)*0.5% -> 0 | I62: =SUM(D62:H62) -> 0
C63: $/MT | G63: =+G62*22.0462 -> 0 | H63: =+H62*22.0462 -> 0 | I63: =+I62*22.0462 -> 0
B65: Pre-Mix Price | D65: 100% PCR | E65: Virgen | F65: Mixing Fee | G65: Handling Fee | H65: Scrap Fee | I65: Sell Side Pre-Mix
C66: cpp | D66: =I58*1 -> 70.553424 | E66: =I62*0 -> 0 | F66: 0 | G66: 1.3655 | H66: 0 | I66: =+SUM(D66:H66) -> 71.918924
C67: $/MT | D67: =+D66*22.0462 -> 1555.4349 | E67: =+E66*22.0462 -> 0 | F67: =+F66*22.0462 -> 0 | G67: =+G66*22.0462 -> 30.104086 | H67: =+H66*22.0462 -> 0 | I67: =+I66*22.0462 -> 1585.539

Sheet Kardex
A1: Vírgen
BG2: Precio Ene | BJ2: Precio Feb | BM2: Precio Marzo | BP2: Precio Abril | BS2: Precio Mayo | BV2: Precio Junio | BY2: Precio Julio | CB2: Precio Agosto | CE2: Precio Sep | CH2: Precio Oct | CK2: Precio Nov | CN2: Precio Dic | CQ2: Precio Ene | CT2: Precio Feb | CW2: Precio Mar
A3: Sell Side | B3: 45047 | E3: 45078 | H3: 45108 | K3: 45139 | N3: 45170 | Q3: 45200 | T3: 45231 | W3: 45261 | Z3: 45292 | AC3: 45323 | AF3: 45352 | AI3: 45383 | AL3: 45413 | AO3: 45444 | AR3: 45474 | AU3: 45505 | AX3: 45536 | BA3: 45566 | BD3: 45597 | BG3: 45627 | BJ3: 45658 | BM3: 45689 | BP3: 45717 | BS3: 45748 | BV3: 45778 | BY3: 45809 | CB3: 45839 | CE3: 45870 | CH3: 45901 | CI3: 45901 | CJ3: 45901 | CK3: 45931 | CL3: 45931 | CM3: 45931 | CN3: 45962 | CQ3: 45992 | CT3: 46023 | CW3: 46054
B4: Cantidad (kg) | C4: Precio/TM (USD$) | D4: Precio Total (USD$) | E4: Cantidad (kg) | F4: Precio/TM (USD$) | G4: Precio Total (USD$) | H4: Cantidad (kg) | I4: Precio/TM (USD$) | J4: Precio Total (USD$) | K4: Cantidad (kg) | L4: Precio/TM (USD$) | M4: Precio Total (USD$) | N4: Cantidad (kg) | O4: Precio/TM (USD$) | P4: Precio Total (USD$) | Q4: Cantidad (kg) | R4: Precio/TM (USD$) | S4: Precio Total (USD$) | T4: Cantidad (kg) | U4: Precio/TM (USD$) | V4: Precio Total (USD$) | W4: Cantidad (kg) | X4: Precio/TM (USD$) | Y4: Precio Total (USD$) | Z4: Cantidad (kg) | AA4: Precio/TM (USD$) | AB4: Precio Total (USD$) | AC4: Cantidad (kg) | AD4: Precio/TM (USD$) | AE4: Precio Total (USD$) | AF4: Cantidad (kg) | AG4: Precio/TM (USD$) | AH4: Precio Total (USD$) | AI4: Cantidad (kg) | AJ4: Precio/TM (USD$) | AK4: Precio Total (USD$) | AL4: Cantidad (kg) | AM4: Precio/TM (USD$) | AN4: Precio Total (USD$) | AO4: Cantidad (kg) | AP4: Precio/TM (USD$) | AQ4: Precio Total (USD$) | AR4: Cantidad (kg) | AS4: Precio/TM (USD$) | AT4: Precio Total (USD$) | AU4: Cantidad (kg) | AV4: Precio/TM (USD$) | AW4: Precio Total (USD$) | AX4: Cantidad (kg) | AY4: Precio/TM (USD$) | AZ4: Precio Total (USD$) | BA4: Cantidad (kg) | BB4: Precio/TM (USD$) | BC4: Precio Total (USD$) | BD4: Cantidad (kg) | BE4: Precio/TM (USD$) | BF4: Precio Total (USD$) | BG4: Cantidad (kg) | BH4: Precio/TM (USD$) | BI4: Precio Total (USD$) | BJ4: Cantidad (kg) | BK4: Precio/TM (USD$) | BL4: Precio Total (USD$) | BM4: Cantidad (kg) | BN4: Precio/TM (USD$) | BO4: Precio Total (USD$) | BP4: Cantidad (kg) | BQ4: Precio/TM (USD$) | BR4: Precio Total (USD$) | BS4: Cantidad (kg) | BT4: Precio/TM (USD$) | BU4: Precio Total (USD$) | BV4: Cantidad (kg) | BW4: Precio/TM (USD$) | BX4: Precio Total (USD$) | BY4: Cantidad (kg) | BZ4: Precio/TM (USD$) | CA4: Precio Total (USD$) | CB4: Cantidad (kg) | CC4: Precio/TM (USD$) | CD4: Precio Total (USD$) | CE4: Cantidad (kg) | CF4: Precio/TM (USD$) | CG4: Precio Total (USD$) | CH4: Cantidad (kg) | CI4: Precio/TM (USD$) | CJ4: Precio Total (USD$) | CK4: Cantidad (kg) | CL4: Precio/TM (USD$) | CM4: Precio Total (USD$) | CN4: Cantidad (kg) | CO4: Precio/TM (USD$) | CP4: Precio Total (USD$) | CQ4: Cantidad (kg) | CR4: Precio/TM (USD$) | CS4: Precio Total (USD$) | CT4: Cantidad (kg) | CU4: Precio/TM (USD$) | CV4: Precio Total (USD$) | CW4: Cantidad (kg) | CX4: Precio/TM (USD$) | CY4: Precio Total (USD$)
A5: Inventario inicial | B5: 2323510.8 | C5: 1222.5882 | D5: =B5*C5/1000 -> 2840696.9 | E5: =B8 -> 2996145.8 | F5: =C8 -> 1170.5706 | G5: =E5*F5/1000 -> 3507200.3 | H5: =E8 -> 2577958.9 | I5: =F8 -> 1199.5922 | J5: =H5*I5/1000 -> 3092499.3 | K5: =H8 -> 2028118.9 | L5: =I8 -> 1233.5404 | M5: =K5*L5/1000 -> 2501766.6 | N5: =K8 -> 2349353.7 | O5: =L8 -> 1224.0835 | P5: =N5*O5/1000 -> 2875805.1 | Q5: =N8 -> 1689238.7 | R5: =O8 -> 1205.413 | S5: =Q5*R5/1000 -> 2036230.3 | T5: =Q8 -> 1396350.2 | U5: =R8 -> 1256.3334 | V5: =T5*U5/1000 -> 1754281.4 | W5: =T8 -> 1663252.9 | X5: =U8 -> 1259.2537 | Y5: =W5*X5/1000 -> 2094457.5 | Z5: =W8 -> 2607570.7 | AA5: =X8 -> 1255.9788 | AB5: =Z5*AA5/1000 -> 3275053.5 | AC5: =Z8 -> 2486070.7 | AD5: =AA8 -> 1242.0869 | AE5: =AC5*AD5/1000 -> 3087915.7 | AF5: =AC8 -> 1994320.7 | AG5: =AD8 -> 1233.2268 | AH5: =AF5*AG5/1000 -> 2459449.7 | AI5: =AF8 -> 1919755.9 | AJ5: =AG8 -> 1233.5212 | AK5: =AI5*AJ5/1000 -> 2368059.5 | AL5: =AI8 -> 2646630.5 | AM5: =AJ8 -> 1256.1605 | AN5: =AL5*AM5/1000 -> 3324592.6 | AO5: =AL8 -> 1476755.2 | AP5: =AM8 -> 1271.5642 | AQ5: =AO5*AP5/1000 -> 1877789 | AR5: =AO8 -> 1615226.7 | AS5: =AP8 -> 1451.7041 | AT5: =AR5*AS5/1000 -> 2344831.1 | AU5: =AR8 -> 1652127.1 | AV5: =AS8 -> 1592.354 | AW5: =AU5*AV5/1000 -> 2630771.1 | AX5: =AU8 -> 2208127.1 | AY5: =AV8 -> 1532.797 | AZ5: =AX5*AY5/1000 -> 3384610.7 | BA5: =AX8 -> 2965281.1 | BB5: =AY8 -> 1480.2515 | BC5: =BA5*BB5/1000 -> 4389361.8 | BD5: =BA8 -> 3247521.1 | BE5: =BB8 -> 1444.3574 | BF5: =BD5*BE5/1000 -> 4690581.1 | BG5: =BD8 -> 2997987.1 | BH5: =BE8 -> 1429.8201 | BI5: =BG5*BH5/1000 -> 4286582.3 | BJ5: =BG8 -> 2456987.1 | BK5: =BH8 -> 1420.518 | BL5: =BJ5*BK5/1000 -> 3490194.4 | BM5: =BJ8 -> 2189191.1 | BN5: =BK8 -> 1382.1423 | BO5: =BM5*BN5/1000 -> 3025773.6 | BP5: =BM8 -> 2160752.6 | BQ5: =BN8 -> 1341.8994 | BR5: =BP5*BQ5/1000 -> 2899512.6 | BS5: =BP8 -> 1844752.6 | BT5: =BQ8 -> 1309.7996 | BU5: =BS5*BT5/1000 -> 2416256.3 | BV5: =BS8 -> 1410752.6 | BW5: =BT8 -> 1291.8021 | BX5: =BV5*BW5/1000 -> 1822413.1 | BY5: =BV8 -> 2001752.6 | BZ5: =BW8 -> 1241.2471 | CA5: =BY5*BZ5/1000 -> 2484669.6 | CB5: =BY8 -> 1910752.6 | CC5: =BZ8 -> 1180.2337 | CD5: =CB5*CC5/1000 -> 2255134.6 | CE5: =CB8 -> 1939252.6 | CF5: =CC8 -> 1116.43 | CG5: =CE5*CF5/1000 -> 2165039.9 | CH5: =CE8 -> 2343252.6 | CI5: =CF8 -> 1082.4997 | CJ5: =CH5*CI5/1000 -> 2536570.2 | CK5: =CH8 -> 2333752.6 | CL5: =CI8 -> 1113.9948 | CM5: =CK5*CL5/1000 -> 2599788.3 | CN5: =CK8 -> 2017752.6 | CO5: =CL8 -> 1105.1978 | CP5: =CN5*CO5/1000 -> 2230015.7 | CQ5: =CN8 -> 1628752.6 | CR5: =CO8 -> 1087.3004 | CS5: =CQ5*CR5/1000 -> 1770943.3 | CT5: =CQ8 -> 2190502.6 | CU5: =CR8 -> 1067.0272 | CV5: =CT5*CU5/1000 -> 2337325.8 | CW5: =CT8 -> 2527002.6 | CX5: =CU8 -> 1059.4431 | CY5: =CW5*CX5/1000 -> 2677215.5 | DD5: Virgen | DE5: PCR
A6: Total Ingresos | B6: 2336400 | C6: ='ICIS Price History'!Q163 -> 1118.84 | D6: =B6*C6/1000 -> 2614057.8 | E6: 1227600 | F6: ='ICIS Price History'!Q168 -> 1270.4237 | G6: =E6*F6/1000 -> 1559572.1 | H6: 1247400 | I6: =+'ICIS Price History'!Q173 -> 1303.7 | J6: =H6*I6/1000 -> 1626235.4 | K6: 2402400 | L6: ='ICIS Price History'!Q177 -> 1216.1 | M6: =K6*L6/1000 -> 2921558.6 | N6: 935000 | O6: ='ICIS Price History'!Q181 -> 1158.5 | P6: =N6*O6/1000 -> 1083197.5 | Q6: 1300000 | R6: ='ICIS Price History'!Q185 -> 1322.5 | S6: =Q6*R6/1000 -> 1719250 | T6: 1900000 | U6: ='ICIS Price History'!Q186 -> 1261.4 | V6: =T6*U6/1000 -> 2396660 | W6: 2500000 | X6: ='ICIS Price History'!Q187 -> 1253.8 | Y6: =W6*X6/1000 -> 3134500 | Z6: 1200000 | AA6: ='ICIS Price History'!Q188 -> 1211.9 | AB6: =Z6*AA6/1000 -> 1454280 | AC6: 1000000 | AD6: ='ICIS Price History'!Q189 -> 1211.2 | AE6: =AC6*AD6/1000 -> 1211200 | AF6: 1550000 | AG6: ='ICIS Price History'!Q190 -> 1233.9 | AH6: =AF6*AG6/1000 -> 1912545 | AI6: 2450000 | AJ6: ='ICIS Price History'!Q191 -> 1273.9 | AK6: =AI6*AJ6/1000 -> 3121055 | AL6: 500000 | AM6: ='ICIS Price History'!Q192 -> 1353.1 | AN6: =AL6*AM6/1000 -> 676550 | AO6: 1850000 | AP6: ='ICIS Price History'!Q193 -> 1595.5 | AQ6: =AO6*AP6/1000 -> 2951675 | AR6: 1500000 | AS6: ='ICIS Price History'!Q196 -> 1743.8083 | AT6: =AR6*AS6/1000 -> 2615712.4 | AU6: 1500000 | AV6: ='ICIS Price History'!Q197 -> 1467.2 | AW6: =AU6*AV6/1000 -> 2200800 | AX6: 1500000 | AY6: ='ICIS Price History'!Q198 -> 1402.9 | AZ6: =AX6*AY6/1000 -> 2104350 | BA6: 1500000 | BB6: ='ICIS Price History'!Q199 -> 1373.4 | BC6: =BA6*BB6/1000 -> 2060100 | BD6: 500000 | BE6: ='ICIS Price History'!Q200 -> 1335.4 | BF6: =BD6*BE6/1000 -> 667700 | BG6: 150000 | BH6: ='ICIS Price History'!Q201 -> 1234.6 | BI6: =BG6*BH6/1000 -> 185190 | BJ6: 890000 | BK6: ='ICIS Price History'!Q202 -> 1276.2 | BL6: =BJ6*BK6/1000 -> 1135818 | BM6: 1000000 | BN6: ='ICIS Price History'!Q203 -> 1253.8 | BO6: =BM6*BN6/1000 -> 1253800 | BP6: 800000 | BQ6: ='ICIS Price History'!Q204 -> 1223.1 | BR6: =BP6*BQ6/1000 -> 978480 | BS6: 500000 | BT6: ='ICIS Price History'!Q205 -> 1225.4 | BU6: =BS6*BT6/1000 -> 612700 | BV6: 1500000 | BW6: ='ICIS Price History'!Q206 -> 1193.7 | BX6: =BV6*BW6/1000 -> 1790550 | BY6: 1000000 | BZ6: ='ICIS Price History'!Q207 -> 1058.1 | CA6: =BY6*BZ6/1000 -> 1058100 | CB6: 1100000 | CC6: ='ICIS Price History'!Q208 -> 1005.6 | CD6: =CB6*CC6/1000 -> 1106160 | CE6: 1400000 | CF6: ='ICIS Price History'!Q209 -> 1035.5 | CG6: =CE6*CF6/1000 -> 1449700 | CH6: ='ICIS Price History'!T212*1000 -> 1415000 | CI6: ='ICIS Price History'!Q212 -> 1166.1511 | CJ6: =CH6*CI6/1000 -> 1650103.7 | CK6: 1098000 | CL6: ='ICIS Price History'!Q213 -> 1086.5 | CM6: =CK6*CL6/1000 -> 1192977 | CN6: 1480000 | CO6: ='ICIS Price History'!Q214 -> 1062.9 | CP6: =CN6*CO6/1000 -> 1573092 | CQ6: 2354000 | CR6: =+'ICIS Price History'!Q215 -> 1053 | CS6: =CQ6*CR6/1000 -> 2478762 | CT6: 2232000 | CU6: =+'ICIS Price History'!Q216 -> 1052 | CV6: =CT6*CU6/1000 -> 2348064 | CW6: 2918000 | CX6: =+'ICIS Price History'!Q217 -> 1037 | CY6: =CW6*CX6/1000 -> 3025966 | DB6: 0.25 | DC6: 1850 | DD6: =+DC6*0.75 -> 1387.5 | DE6: =+DC6-DD6 -> 462.5
A7: Consumo (Facturación) | B7: 1663765 | C7: 1222.5882 | D7: =B7*C7/1000 -> 2034099.5 | E7: 1645786.9 | F7: =F5 -> 1170.5706 | G7: =E7*F7/1000 -> 1926509.8 | H7: 1797240 | I7: =I5 -> 1199.5922 | J7: =H7*I7/1000 -> 2155955 | K7: 2081165.2 | L7: =L5 -> 1233.5404 | M7: =K7*L7/1000 -> 2567201.3 | N7: 1595115 | O7: =O5 -> 1224.0835 | P7: =N7*O7/1000 -> 1952554 | Q7: 1592888.4 | R7: =R5 -> 1205.413 | S7: =Q7*R7/1000 -> 1920088.4 | T7: 1633097.3 | U7: =U5 -> 1256.3334 | V7: =T7*U7/1000 -> 2051714.6 | W7: 1555682.3 | X7: =X5 -> 1259.2537 | Y7: =W7*X7/1000 -> 1958998.7 | Z7: 1321500 | AA7: =AA5 -> 1255.9788 | AB7: =Z7*AA7/1000 -> 1659776 | AC7: 1491750 | AD7: =AD5 -> 1242.0869 | AE7: =AC7*AD7/1000 -> 1852883.1 | AF7: 1624564.8 | AG7: =AG5 -> 1233.2268 | AH7: =AF7*AG7/1000 -> 2003456.8 | AI7: 1723125.3 | AJ7: =AJ5 -> 1233.5212 | AK7: =AI7*AJ7/1000 -> 2125511.6 | AL7: 1669875.3 | AM7: =AM5 -> 1256.1605 | AN7: =AL7*AM7/1000 -> 2097631.4 | AO7: 1711528.5 | AP7: =AP5 -> 1271.5642 | AQ7: =AO7*AP7/1000 -> 2176318.3 | AR7: 1463099.6 | AS7: =AS5 -> 1451.7041 | AT7: =AR7*AS7/1000 -> 2123987.6 | AU7: 944000 | AV7: =AV5 -> 1592.354 | AW7: =AU7*AV7/1000 -> 1503182.1 | AX7: 742846 | AY7: =AY5 -> 1532.797 | AZ7: =AX7*AY7/1000 -> 1138632.2 | BA7: =2064000*59% -> 1217760 | BB7: =BB5 -> 1480.2515 | BC7: =BA7*BB7/1000 -> 1802591.1 | BD7: 749534 | BE7: =BE5 -> 1444.3574 | BF7: =BD7*BE7/1000 -> 1082595 | BG7: 691000 | BH7: =BH5 -> 1429.8201 | BI7: =BG7*BH7/1000 -> 988005.71 | BJ7: 1157795.9 | BK7: =BK5 -> 1420.518 | BL7: =BJ7*BK7/1000 -> 1644670 | BM7: 1028438.5 | BN7: =BN5 -> 1382.1423 | BO7: =BM7*BN7/1000 -> 1421448.4 | BP7: 1116000 | BQ7: =BQ5 -> 1341.8994 | BR7: =BP7*BQ7/1000 -> 1497559.7 | BS7: 934000 | BT7: =BT5 -> 1309.7996 | BU7: =BS7*BT7/1000 -> 1223352.8 | BV7: 909000 | BW7: =BW5 -> 1291.8021 | BX7: =BV7*BW7/1000 -> 1174248.1 | BY7: 1091000 | BZ7: =BZ5 -> 1241.2471 | CA7: =BY7*BZ7/1000 -> 1354200.5 | CB7: =2143000/2 -> 1071500 | CC7: =CC5 -> 1180.2337 | CD7: =CB7*CC7/1000 -> 1264620.4 | CE7: =1992000/2 -> 996000 | CF7: =CF5 -> 1116.43 | CG7: =CE7*CF7/1000 -> 1111964.3 | CH7: 1424500 | CI7: =CI5 -> 1082.4997 | CJ7: =CH7*CI7/1000 -> 1542020.8 | CK7: 1414000 | CL7: =CL5 -> 1113.9948 | CM7: =CK7*CL7/1000 -> 1575188.7 | CN7: 1869000 | CO7: =CO5 -> 1105.1978 | CP7: =CN7*CO7/1000 -> 2065614.6 | CQ7: 1792250 | CR7: =CR5 -> 1087.3004 | CS7: =CQ7*CR7/1000 -> 1948714.1 | CT7: 1895500 | CU7: =CU5 -> 1067.0272 | CV7: =CT7*CU7/1000 -> 2022550 | CW7: 1472500 | CX7: =CX5 -> 1059.4431 | CY7: =CW7*CX7/1000 -> 1560029.9 | DB7: 0.5 | DC7: 0
A8: Inventario Final | B8: 2996145.8 | C8: =+(B5*C5+B6*C6)/(B5+B6) -> 1170.5706 | D8: =B8*C8/1000 -> 3507200.3 | E8: =E5+E6-E7 -> 2577958.9 | F8: =+(E5*F5+E6*F6)/(E5+E6) -> 1199.5922 | G8: =E8*F8/1000 -> 3092499.3 | H8: =H5+H6-H7 -> 2028118.9 | I8: =+(H5*I5+H6*I6)/(H5+H6) -> 1233.5404 | J8: =H8*I8/1000 -> 2501766.6 | K8: =K5+K6-K7 -> 2349353.7 | L8: =+(K5*L5+K6*L6)/(K5+K6) -> 1224.0835 | M8: =K8*L8/1000 -> 2875805.1 | N8: =N5+N6-N7 -> 1689238.7 | O8: =+(N5*O5+N6*O6)/(N5+N6) -> 1205.413 | P8: =N8*O8/1000 -> 2036230.3 | Q8: =Q5+Q6-Q7 -> 1396350.2 | R8: =+(Q5*R5+Q6*R6)/(Q5+Q6) -> 1256.3334 | S8: =Q8*R8/1000 -> 1754281.4 | T8: =T5+T6-T7 -> 1663252.9 | U8: =+(T5*U5+T6*U6)/(T5+T6) -> 1259.2537 | V8: =T8*U8/1000 -> 2094457.5 | W8: =W5+W6-W7 -> 2607570.7 | X8: =+(W5*X5+W6*X6)/(W5+W6) -> 1255.9788 | Y8: =W8*X8/1000 -> 3275053.5 | Z8: =Z5+Z6-Z7 -> 2486070.7 | AA8: =+(Z5*AA5+Z6*AA6)/(Z5+Z6) -> 1242.0869 | AB8: =Z8*AA8/1000 -> 3087915.7 | AC8: =AC5+AC6-AC7 -> 1994320.7 | AD8: =+(AC5*AD5+AC6*AD6)/(AC5+AC6) -> 1233.2268 | AE8: =AC8*AD8/1000 -> 2459449.7 | AF8: =AF5+AF6-AF7 -> 1919755.9 | AG8: =+(AF5*AG5+AF6*AG6)/(AF5+AF6) -> 1233.5212 | AH8: =AF8*AG8/1000 -> 2368059.5 | AI8: =AI5+AI6-AI7 -> 2646630.5 | AJ8: =+(AI5*AJ5+AI6*AJ6)/(AI5+AI6) -> 1256.1605 | AK8: =AI8*AJ8/1000 -> 3324592.6 | AL8: =AL5+AL6-AL7 -> 1476755.2 | AM8: =+(AL5*AM5+AL6*AM6)/(AL5+AL6) -> 1271.5642 | AN8: =AL8*AM8/1000 -> 1877789 | AO8: =AO5+AO6-AO7 -> 1615226.7 | AP8: =+(AO5*AP5+AO6*AP6)/(AO5+AO6) -> 1451.7041 | AQ8: =AO8*AP8/1000 -> 2344831.1 | AR8: =AR5+AR6-AR7 -> 1652127.1 | AS8: =+(AR5*AS5+AR6*AS6)/(AR5+AR6) -> 1592.354 | AT8: =AR8*AS8/1000 -> 2630771.1 | AU8: =AU5+AU6-AU7 -> 2208127.1 | AV8: =+(AU5*AV5+AU6*AV6)/(AU5+AU6) -> 1532.797 | AW8: =AU8*AV8/1000 -> 3384610.7 | AX8: =AX5+AX6-AX7 -> 2965281.1 | AY8: =+(AX5*AY5+AX6*AY6)/(AX5+AX6) -> 1480.2515 | AZ8: =AX8*AY8/1000 -> 4389361.8 | BA8: =BA5+BA6-BA7 -> 3247521.1 | BB8: =+(BA5*BB5+BA6*BB6)/(BA5+BA6) -> 1444.3574 | BC8: =BA8*BB8/1000 -> 4690581.1 | BD8: =BD5+BD6-BD7 -> 2997987.1 | BE8: =+(BD5*BE5+BD6*BE6)/(BD5+BD6) -> 1429.8201 | BF8: =BD8*BE8/1000 -> 4286582.3 | BG8: =BG5+BG6-BG7 -> 2456987.1 | BH8: =+(BG5*BH5+BG6*BH6)/(BG5+BG6) -> 1420.518 | BI8: =BG8*BH8/1000 -> 3490194.4 | BJ8: =BJ5+BJ6-BJ7 -> 2189191.1 | BK8: =+(BJ5*BK5+BJ6*BK6)/(BJ5+BJ6) -> 1382.1423 | BL8: =BJ8*BK8/1000 -> 3025773.6 | BM8: =BM5+BM6-BM7 -> 2160752.6 | BN8: =+(BM5*BN5+BM6*BN6)/(BM5+BM6) -> 1341.8994 | BO8: =BM8*BN8/1000 -> 2899512.6 | BP8: =BP5+BP6-BP7 -> 1844752.6 | BQ8: =+(BP5*BQ5+BP6*BQ6)/(BP5+BP6) -> 1309.7996 | BR8: =BP8*BQ8/1000 -> 2416256.3 | BS8: =BS5+BS6-BS7 -> 1410752.6 | BT8: =+(BS5*BT5+BS6*BT6)/(BS5+BS6) -> 1291.8021 | BU8: =BS8*BT8/1000 -> 1822413.1 | BV8: =BV5+BV6-BV7 -> 2001752.6 | BW8: =+(BV5*BW5+BV6*BW6)/(BV5+BV6) -> 1241.2471 | BX8: =BV8*BW8/1000 -> 2484669.6 | BY8: =BY5+BY6-BY7 -> 1910752.6 | BZ8: =+(BY5*BZ5+BY6*BZ6)/(BY5+BY6) -> 1180.2337 | CA8: =BY8*BZ8/1000 -> 2255134.6 | CB8: =CB5+CB6-CB7 -> 1939252.6 | CC8: =+(CB5*CC5+CB6*CC6)/(CB5+CB6) -> 1116.43 | CD8: =CB8*CC8/1000 -> 2165039.9 | CE8: =CE5+CE6-CE7 -> 2343252.6 | CF8: =+(CE5*CF5+CE6*CF6)/(CE5+CE6) -> 1082.4997 | CG8: =CE8*CF8/1000 -> 2536570.2 | CH8: =CH5+CH6-CH7 -> 2333752.6 | CI8: =+(CH5*CI5+CH6*CI6)/(CH5+CH6) -> 1113.9948 | CJ8: =CH8*CI8/1000 -> 2599788.3 | CK8: =CK5+CK6-CK7 -> 2017752.6 | CL8: =+(CK5*CL5+CK6*CL6)/(CK5+CK6) -> 1105.1978 | CM8: =CK8*CL8/1000 -> 2230015.7 | CN8: =CN5+CN6-CN7 -> 1628752.6 | CO8: =+(CN5*CO5+CN6*CO6)/(CN5+CN6) -> 1087.3004 | CP8: =CN8*CO8/1000 -> 1770943.3 | CQ8: =CQ5+CQ6-CQ7 -> 2190502.6 | CR8: =+(CQ5*CR5+CQ6*CR6)/(CQ5+CQ6) -> 1067.0272 | CS8: =CQ8*CR8/1000 -> 2337325.8 | CT8: =CT5+CT6-CT7 -> 2527002.6 | CU8: =+(CT5*CU5+CT6*CU6)/(CT5+CT6) -> 1059.4431 | CV8: =CT8*CU8/1000 -> 2677215.5 | CW8: =CW5+CW6-CW7 -> 3972502.6 | CX8: =+(CW5*CX5+CW6*CX6)/(CW5+CW6) -> 1047.4157 | CY8: =CW8*CX8/1000 -> 4160861.8 | DB8: 1 | DC8: =1935-DC6 -> 85 | DD8: =+DC8 -> 85
DD9: =SUM(DD6:DD8) -> 1472.5 | DE9: =SUM(DE6:DE8) -> 462.5
AR10: Desc 50% | AS10: =150*'ICIS Price History'!T195/'ICIS Price History'!T197 -> 49.917426
AR11: Precio Agosto | AS11: =AS8-AS10 -> 1542.4365
A12: PCR | BA12: Precio Nov | BD12: Precio Dic | BG12: Precio Ene | BJ12: Precio Feb | BM12: Precio Marzo | BP12: Precio Abril | BS12: Precio Mayo | BV12: Precio Junio | BY12: Precio Julio | CB12: Precio Agosto | CE12: Precio Sep | CH12: Precio Oct | CK12: Precio Nov | CN12: Precio Dic | CQ12: =+CQ2 -> Precio Ene | CT12: =+CT2 -> Precio Feb | CW12: =+CW2 -> Precio Mar
A13: Sell Side | B13: 45047 | E13: 45078 | H13: 45108 | K13: 45139 | N13: 45170 | Q13: 45200 | T13: 45231 | W13: 45261 | Z13: 45292 | AC13: 45323 | AF13: 45352 | AI13: 45383 | AL13: 45413 | AO13: 45444 | AR13: 45444 | AU13: 45505 | AX13: 45536 | BA13: 45566 | BD13: 45597 | BG13: 45627 | BJ13: 45658 | BM13: 45689 | BP13: 45717 | BS13: 45748 | BV13: 45778 | BY13: 45809 | CB13: 45839 | CE13: 45870 | CH13: 45901 | CK13: 45931 | CN13: 45962 | CQ13: =+CQ3 -> 45992 | CT13: =+CT3 -> 46023 | CW13: =+CW3 -> 46054
B14: Cantidad (kg) | C14: Precio/TM (USD$) | D14: Precio Total (USD$) | E14: Cantidad (kg) | F14: Precio/TM (USD$) | G14: Precio Total (USD$) | H14: Cantidad (kg) | I14: Precio/TM (USD$) | J14: Precio Total (USD$) | K14: Cantidad (kg) | L14: Precio/TM (USD$) | M14: Precio Total (USD$) | N14: Cantidad (kg) | O14: Precio/TM (USD$) | P14: Precio Total (USD$) | Q14: Cantidad (kg) | R14: Precio/TM (USD$) | S14: Precio Total (USD$) | T14: Cantidad (kg) | U14: Precio/TM (USD$) | V14: Precio Total (USD$) | W14: Cantidad (kg) | X14: Precio/TM (USD$) | Y14: Precio Total (USD$) | Z14: Cantidad (kg) | AA14: Precio/TM (USD$) | AB14: Precio Total (USD$) | AC14: Cantidad (kg) | AD14: Precio/TM (USD$) | AE14: Precio Total (USD$) | AF14: Cantidad (kg) | AG14: Precio/TM (USD$) | AH14: Precio Total (USD$) | AI14: Cantidad (kg) | AJ14: Precio/TM (USD$) | AK14: Precio Total (USD$) | AL14: Cantidad (kg) | AM14: Precio/TM (USD$) | AN14: Precio Total (USD$) | AO14: Cantidad (kg) | AP14: Precio/TM (USD$) | AQ14: Precio Total (USD$) | AR14: Cantidad (kg) | AS14: Precio/TM (USD$) | AT14: Precio Total (USD$) | AU14: Cantidad (kg) | AV14: Precio/TM (USD$) | AW14: Precio Total (USD$) | AX14: Cantidad (kg) | AY14: Precio/TM (USD$) | AZ14: Precio Total (USD$) | BA14: Cantidad (kg) | BB14: Precio/TM (USD$) | BC14: Precio Total (USD$) | BD14: Cantidad (kg) | BE14: Precio/TM (USD$) | BF14: Precio Total (USD$) | BG14: Cantidad (kg) | BH14: Precio/TM (USD$) | BI14: Precio Total (USD$) | BJ14: Cantidad (kg) | BK14: Precio/TM (USD$) | BL14: Precio Total (USD$) | BM14: Cantidad (kg) | BN14: Precio/TM (USD$) | BO14: Precio Total (USD$) | BP14: Cantidad (kg) | BQ14: Precio/TM (USD$) | BR14: Precio Total (USD$) | BS14: Cantidad (kg) | BT14: Precio/TM (USD$) | BU14: Precio Total (USD$) | BV14: Cantidad (kg) | BW14: Precio/TM (USD$) | BX14: Precio Total (USD$) | BY14: Cantidad (kg) | BZ14: Precio/TM (USD$) | CA14: Precio Total (USD$) | CB14: Cantidad (kg) | CC14: Precio/TM (USD$) | CD14: Precio Total (USD$) | CE14: Cantidad (kg) | CF14: Precio/TM (USD$) | CG14: Precio Total (USD$) | CH14: Cantidad (kg) | CI14: Precio/TM (USD$) | CJ14: Precio Total (USD$) | CK14: Cantidad (kg) | CL14: Precio/TM (USD$) | CM14: Precio Total (USD$) | CN14: Cantidad (kg) | CO14: Precio/TM (USD$) | CP14: Precio Total (USD$) | CQ14: Cantidad (kg) | CR14: Precio/TM (USD$) | CS14: Precio Total (USD$) | CT14: Cantidad (kg) | CU14: Precio/TM (USD$) | CV14: Precio Total (USD$) | CW14: Cantidad (kg) | CX14: Precio/TM (USD$) | CY14: Precio Total (USD$)
A15: Inventario inicial | B15: 1261711.8 | C15: 1721.1985 | D15: 2171655.8 | E15: =B18 -> 1291123.5 | F15: =C18 -> 1723.3 | G15: =D18 -> 2224993.1 | H15: =E18 -> 1296527.8 | I15: =F18 -> 1722.7728 | J15: =G18 -> 2233622.9 | K15: =H18 -> 1304447.8 | L15: =I18 -> 1642.5538 | ... CY15: =CV18 -> 3722207.7
A16: Total Ingresos | B16: 540000 | C16: =PCR!AR15 -> 1728.2101 | D16: =B16*C16/1000 -> 933233.45 | E16: 554000 | F16: =PCR!AT15 -> 1721.5442 | G16: =E16*F16/1000 -> 953735.51 | H16: 607000 | I16: =+PCR!AV15 -> 1471.2091 | J16: =H16*I16/1000 -> 893023.94 | K16: 500000 | L16: =PCR!AX15 -> 1422.9115 | M16: =K16*L16/1000 -> 711455.75 | N16: 156000 | O16: =PCR!AZ15 -> 1428.453 | P16: =N16*O16/1000 -> 222838.67 | Q16: 190000 | R16: =PCR!BB15 -> 1499.2141 | S16: =Q16*R16/1000 -> 284850.68 | T16: 510000 | U16: =PCR!BD15 -> 1542.4526 | V16: =T16*U16/1000 -> 786650.82 | W16: 540000 | X16: =PCR!BF15 -> 1592.2443 | Y16: =W16*X16/1000 -> 859811.93 | Z16: 500000 | AA16: =PCR!BH15 -> 1610.0833 | AB16: =Z16*AA16/1000 -> 805041.66 | AC16: 670000 | AD16: =PCR!BJ15 -> 1638.7966 | AE16: =AC16*AD16/1000 -> 1097993.7 | AF16: 510000 | AG16: =PCR!BL15 -> 1661.5198 | AH16: =AF16*AG16/1000 -> 847375.1 | AI16: 550000 | AJ16: =PCR!BN15 -> 1705.5892 | AK16: =AI16*AJ16/1000 -> 938074.07 | AL16: 520000 | AM16: =PCR!BP15 -> 1752.0296 | AN16: =AL16*AM16/1000 -> 911055.38 | AO16: 500000 | AP16: =PCR!BR15 -> 1779.5086 | AQ16: =AO16*AP16/1000 -> 889754.28 | AR16: 540000 | AS16: =PCR!BT15 -> 1837.3601 | AT16: =AR16*AS16/1000 -> 992174.48 | AU16: 698000 | AV16: =PCR!BV15 -> 1887.0923 | AW16: =AU16*AV16/1000 -> 1317190.4 | AX16: =PCR!BW28 -> 1640000 | AY16: =PCR!BV28 -> 1913.6674 | AZ16: =AX16*AY16/1000 -> 3138414.5 | BA16: =PCR!BY28 -> 1776000 | BB16: =PCR!BX28 -> 1911.2016 | BC16: =BA16*BB16/1000 -> 3394294 | BD16: =PCR!CB28 -> 888430 | BE16: =PCR!CA28 -> 1909.0338 | BF16: =BD16*BE16/1000 -> 1696042.9 | BG16: =PCR!CD28 -> 789000 | BH16: =PCR!CC28 -> 1797.1435 | BI16: =BG16*BH16/1000 -> 1417946.2 | BJ16: =PCR!CF28 -> 990000 | BK16: =PCR!CE28 -> 1839.327 | BL16: =BJ16*BK16/1000 -> 1820933.7 | BM16: =PCR!CH51 -> 749000 | BN16: =PCR!CI51 -> 1847.4226 | BO16: =BM16*BN16/1000 -> 1383719.5 | BP16: =PCR!CL51 -> 996000 | BQ16: =PCR!CM51 -> 1855.3319 | BR16: =BP16*BQ16/1000 -> 1847910.6 | BS16: =PCR!CP51 -> 1000000 | BT16: =PCR!CQ51 -> 1855.4656 | BU16: =BS16*BT16/1000 -> 1855465.6 | BV16: =PCR!CT51 -> 807000 | BW16: =PCR!CU51 -> 1809.9237 | BX16: =BV16*BW16/1000 -> 1460608.4 | BY16: =PCR!CX51 -> 1081000 | BZ16: =PCR!CY51 -> 1810.8221 | CA16: =BY16*BZ16/1000 -> 1957498.7 | CB16: =PCR!DB51 -> 1209000 | CC16: =PCR!DC51 -> 1653.7461 | CD16: =CB16*CC16/1000 -> 1999379 | CE16: =PCR!DF51 -> 1137000 | CF16: =PCR!DG51 -> 1515.1675 | CG16: =CE16*CF16/1000 -> 1722745.4 | CH16: =PCR!DJ51 -> 677000 | CI16: =PCR!DK51 -> 1383.8091 | CJ16: =CH16*CI16/1000 -> 936838.77 | CK16: =PCR!DN51 -> 580000 | CL16: =PCR!$DO$51 -> 1376.1702 | CM16: =CK16*CL16/1000 -> 798178.73 | CN16: =PCR!DR51 -> 580000 | CO16: =PCR!DS51 -> 1418.4658 | CP16: =CN16*CO16/1000 -> 822710.15 | CQ16: 580000 | CR16: =+PCR!DW51 -> 1430.2246 | CS16: =CQ16*CR16/1000 -> 829530.29 | CT16: 562600 | CU16: =+PCR!EA51 -> 1427.614 | CV16: =CT16*CU16/1000 -> 803175.66 | CW16: 504000 | CX16: =+PCR!EE50 -> 1406.054 | CY16: =CW16*CX16/1000 -> 708651.19
A17: Consumo (Facturación) | B17: 510588.33 | C17: 1721.1985 | D17: =B17*C17/1000 -> 878823.88 | E17: 548595.64 | F17: =F15 -> 1723.3 | G17: =E17*F17/1000 -> 945394.86 | H17: 599080 | I17: 1722.7728 | J17: =H17*I17/1000 -> 1032078.7 | K17: 693721.74 | L17: 1722.7728 | M17: =K17*L17/1000 -> 1195125 | N17: 531705 | O17: 1722.7728 | P17: =N17*O17/1000 -> 916006.92 | Q17: 530962.81 | R17: =R15 -> 1562.8207 | S17: =Q17*R17/1000 -> 829799.66 | T17: 544365.77 | U17: =U15 -> 1549.7558 | V17: =T17*U17/1000 -> 843634.03 | W17: 518560.76 | X17: =X15 -> 1545.6359 | Y17: =W17*X17/1000 -> 801506.12 | Z17: 440500 | AA17: =AA15 -> 1573.6105 | AB17: =Z17*AA17/1000 -> 693175.43 | AC17: 497250 | AD17: =AD15 -> 1594.3071 | AE17: =AC17*AD17/1000 -> 792769.19 | AF17: 541521.6 | AG17: =AG15 -> 1621.1458 | AH17: =AF17*AG17/1000 -> 877885.47 | AI17: 574375.12 | AJ17: =AJ15 -> 1639.4751 | AK17: =AI17*AJ17/1000 -> 941673.68 | AL17: 556625.12 | AM17: =AM15 -> 1671.6016 | AN17: =AL17*AM17/1000 -> 930455.45 | AO17: 556625.12 | AP17: =AP15 -> 1710.4166 | AQ17: =AO17*AP17/1000 -> 952060.83 | AR17: 576133.15 | AS17: =AS15 -> 1744.2567 | AT17: =AR17*AS17/1000 -> 1004924.1 | AU17: 782000 | AV17: =AV15 -> 1794.3205 | AW17: =AU17*AV17/1000 -> 1403158.7 | AX17: 1333000 | AY17: =AY15 -> 1851.8239 | AZ17: =AX17*AY17/1000 -> 2468481.3 | BA17: 846240 | BB17: =BB15 -> 1902.9419 | BC17: =BA17*BB17/1000 -> 1610345.6 | BD17: 749534 | BE17: =BE15 -> 1908.9858 | BF17: =BD17*BE17/1000 -> 1430849.8 | BG17: 691000 | BH17: =BH15 -> 1909.0031 | BI17: =BG17*BH17/1000 -> 1319121.1 | BJ17: 1157795.9 | BK17: =BK15 -> 1873.8234 | BL17: =BJ17*BK17/1000 -> 2169505.2 | BM17: 1028438.5 | BN17: =BN15 -> 1861.6602 | BO17: =BM17*BN17/1000 -> 1914603 | BP17: 1116000 | BQ17: =BQ15 -> 1857.2149 | BR17: =BP17*BQ17/1000 -> 2072651.9 | BS17: 934000 | BT17: =BT15 -> 1856.4224 | BU17: =BS17*BT17/1000 -> 1733898.6 | BV17: 1073000 | BW17: =BW15 -> 1855.9973 | BX17: =BV17*BW17/1000 -> 1991485.1 | BY17: =BY7 -> 1091000 | BZ17: =BZ15 -> 1838.488 | CA17: =BY17*BZ17/1000 -> 2005790.4 | CB17: =CB7 -> 1071500 | CC17: =CC15 -> 1824.4573 | CD17: =CB17*CC17/1000 -> 1954906 | CE17: =CE7 -> 996000 | CF17: =CF15 -> 1732.709 | CG17: =CE17*CF17/1000 -> 1725778.2 | CH17: 589500 | CI17: =CI15 -> 1625.8657 | CJ17: =CH17*CI17/1000 -> 958447.83 | CK17: 538000 | CL17: =CL15 -> 1543.7663 | CM17: =CK17*CL17/1000 -> 830546.27 | CN17: 222000 | CO17: =CO15 -> 1494.8337 | CP17: =CN17*CO17/1000 -> 331853.08 | CQ17: 9000 | CR17: =CR15 -> 1472.9984 | CS17: =CQ17*CR17/1000 -> 13256.986 | CT17: 383500 | CU17: =CU15 -> 1462.603 | CV17: =CT17*CU17/1000 -> 560908.27 | CW17: 462500 | CX17: =CX15 -> 1455.9078 | CY17: =CW17*CX17/1000 -> 673357.36
A18: Inventario Final | B18: 1291123.5 | C18: =+(B15*C15+B16*C16)/(B15+B16) -> 1723.3 | D18: =B18*C18/1000 -> 2224993.1 | E18: =E15+E16-E17 -> 1296527.8 | F18: =+(E15*F15+E16*F16)/(E15+E16) -> 1722.7728 | G18: =E18*F18/1000 -> 2233622.9 | H18: =H15+H16-H17 -> 1304447.8 | I18: =+(H15*I15+H16*I16)/(H15+H16) -> 1642.5538 | J18: =H18*I18/1000 -> 2142625.7 | K18: =K15+K16-K17 -> 1110726.1 | L18: =+(K15*L15+K16*L16)/(K15+K16) -> 1581.6924 | M18: =K18*L18/1000 -> 1756827.1 | N18: =N15+N16-N17 -> 735021.09 | O18: =+(N15*O15+N16*O16)/(N15+N16) -> 1562.8207 | P18: =N18*O18/1000 -> 1148706.2 | Q18: =Q15+Q16-Q17 -> 394058.27 | R18: =+(Q15*R15+Q16*R16)/(Q15+Q16) -> 1549.7558 | S18: =Q18*R18/1000 -> 610694.11 | T18: =T15+T16-T17 -> 359692.5 | U18: =+(T15*U15+T16*U16)/(T15+T16) -> 1545.6359 | V18: =T18*U18/1000 -> 555953.65 | W18: =W15+W16-W17 -> 381131.75 | X18: =+(W15*X15+W16*X16)/(W15+W16) -> 1573.6105 | Y18: =W18*X18/1000 -> 599752.92 | Z18: =Z15+Z16-Z17 -> 440631.75 | AA18: =+(Z15*AA15+Z16*AA16)/(Z15+Z16) -> 1594.3071 | AB18: =Z18*AA18/1000 -> 702502.31 | AC18: =AC15+AC16-AC17 -> 613381.75 | AD18: =+(AC15*AD15+AC16*AD16)/(AC15+AC16) -> 1621.1458 | AE18: =AC18*AD18/1000 -> 994381.25 | AF18: =AF15+AF16-AF17 -> 581860.15 | AG18: =+(AF15*AG15+AF16*AG16)/(AF15+AF16) -> 1639.4751 | AH18: =AF18*AG18/1000 -> 953945.2 | AI18: =AI15+AI16-AI17 -> 557485.03 | AJ18: =+(AI15*AJ15+AI16*AJ16)/(AI15+AI16) -> 1671.6016 | AK18: =AI18*AJ18/1000 -> 931892.89 | AL18: =AL15+AL16-AL17 -> 520859.92 | AM18: =+(AL15*AM15+AL16*AM16)/(AL15+AL16) -> 1710.4166 | AN18: =AL18*AM18/1000 -> 890887.44 | AO18: =AO15+AO16-AO17 -> 464234.8 | AP18: =+(AO15*AP15+AO16*AP16)/(AO15+AO16) -> 1744.2567 | AQ18: =AO18*AP18/1000 -> 809744.65 | AR18: =AR15+AR16-AR17 -> 428101.65 | AS18: =+(AR15*AS15+AR16*AS16)/(AR15+AR16) -> 1794.3205 | AT18: =AR18*AS18/1000 -> 768151.59 | AU18: =AU15+AU16-AU17 -> 344101.65 | AV18: =+(AU15*AV15+AU16*AV16)/(AU15+AU16) -> 1851.8239 | AW18: =AU18*AV18/1000 -> 637215.68 | AX18: =AX15+AX16-AX17 -> 651101.65 | AY18: =+(AX15*AY15+AX16*AY16)/(AX15+AX16) -> 1902.9419 | AZ18: =AX18*AY18/1000 -> 1239008.6 | BA18: =BA15+BA16-BA17 -> 1580861.7 | BB18: =+(BA15*BB15+BA16*BB16)/(BA15+BA16) -> 1908.9858 | BC18: =BA18*BB18/1000 -> 3017842.5 | BD18: =BD15+BD16-BD17 -> 1719757.7 | BE18: =+(BD15*BE15+BD16*BE16)/(BD15+BD16) -> 1909.0031 | BF18: =BD18*BE18/1000 -> 3283022.7 | BG18: =BG15+BG16-BG17 -> 1817757.7 | BH18: =+(BG15*BH15+BG16*BH16)/(BG15+BG16) -> 1873.8234 | BI18: =BG18*BH18/1000 -> 3406156.9 | BJ18: =BJ15+BJ16-BJ17 -> 1649961.7 | BK18: =+(BJ15*BK15+BJ16*BK16)/(BJ15+BJ16) -> 1861.6602 | BL18: =BJ18*BK18/1000 -> 3071668 | BM18: =BM15+BM16-BM17 -> 1370523.2 | BN18: =+(BM15*BN15+BM16*BN16)/(BM15+BM16) -> 1857.2149 | BO18: =BM18*BN18/1000 -> 2545356.1 | BP18: =BP15+BP16-BP17 -> 1250523.2 | BQ18: =+(BP15*BQ15+BP16*BQ16)/(BP15+BP16) -> 1856.4224 | BR18: =BP18*BQ18/1000 -> 2321499.3 | BS18: =BS15+BS16-BS17 -> 1316523.2 | BT18: =+(BS15*BT15+BS16*BT16)/(BS15+BS16) -> 1855.9973 | BU18: =BS18*BT18/1000 -> 2443463.5 | BV18: =BV15+BV16-BV17 -> 1050523.2 | BW18: =+(BV15*BW15+BV16*BW16)/(BV15+BV16) -> 1838.488 | BX18: =BV18*BW18/1000 -> 1931374.3 | BY18: =BY15+BY16-BY17 -> 1040523.2 | BZ18: =+(BY15*BZ15+BY16*BZ16)/(BY15+BY16) -> 1824.4573 | CA18: =BY18*BZ18/1000 -> 1898390.1 | CB18: =CB15+CB16-CB17 -> 1178023.2 | CC18: =+(CB15*CC15+CB16*CC16)/(CB15+CB16) -> 1732.709 | CD18: =CB18*CC18/1000 -> 2041171.4 | CE18: =CE15+CE16-CE17 -> 1319023.2 | CF18: =+(CE15*CF15+CE16*CF16)/(CE15+CE16) -> 1625.8657 | CG18: =CE18*CF18/1000 -> 2144554.6 | CH18: =CH15+CH16-CH17 -> 1406523.2 | CI18: =+(CH15*CI15+CH16*CI16)/(CH15+CH16) -> 1543.7663 | CJ18: =CH18*CI18/1000 -> 2171343.1 | CK18: =CK15+CK16-CK17 -> 1448523.2 | CL18: =+(CK15*CL15+CK16*CL16)/(CK15+CK16) -> 1494.8337 | CM18: =CK18*CL18/1000 -> 2165301.3 | CN18: =CN15+CN16-CN17 -> 1806523.2 | CO18: =+(CN15*CO15+CN16*CO16)/(CN15+CN16) -> 1472.9984 | CP18: =CN18*CO18/1000 -> 2661005.8 | CQ18: =CQ15+CQ16-CQ17 -> 2377523.2 | CR18: =+(CQ15*CR15+CQ16*CR16)/(CQ15+CQ16) -> 1462.603 | CS18: =CQ18*CR18/1000 -> 3477372.7 | CT18: =CT15+CT16-CT17 -> 2556623.2 | CU18: =+(CT15*CU15+CT16*CU16)/(CT15+CT16) -> 1455.9078 | CV18: =CT18*CU18/1000 -> 3722207.7 | CW18: =CW15+CW16-CW17 -> 2598123.2 | CX18: =+(CW15*CX15+CW16*CX16)/(CW15+CW16) -> 1447.6983 | CY18: =CW18*CX18/1000 -> 3761298.4
AZ20: PCR NOV INVEMA | BB20: 1896.8798
AZ21: dif | BB21: =BB20-BB18 -> -12.106027
CD22: Sobre costo reducción PCR | CF22: 100 | CI22: 100 | CR22: 100 | CU22: 100 | CX22: 100
CE23: Precio $ TM | CF23: =CF18+CF22 -> 1725.8657 | CH23: Precio $ TM | CI23: =CI18+CI22 -> 1643.7663 | CQ23: Precio $ TM | CR23: =CR18+CR22 -> 1562.603 | CT23: Precio $ TM | CU23: =+CU18+CU22 -> 1555.9078 | CW23: Precio $ TM | CX23: =+CX18+CX22 -> 1547.6983

Sheet PCR
B2: =22.0462*100 -> 2204.62 | CG2: FEB | CK2: MAR | CO2: ABRIL | CS2: MAYO | CW2: JUNIO | DA2: JULIO | DE2: Agosto (cpp) | DI2: Sep (cpp) | DM2: Oct (cpp) | DQ2: Nov (cpp) | DU2: Dic (cpp) | DY2: Ene (cpp) | EC2: Feb (cpp)
B3: PRECIO INVEMA | H3: DIC | I3: ENE (ccp) | J3: ENE | K3: FEB (ccp) | L3: FEB | M3: MAR (ccp) | N3: MAR | O3: ABR (ccp) | P3: ABR | Q3: MAY (ccp) | R3: MAY | S3: JUN (ccp) | T3: JUN | U3: JUL (ccp) | V3: JUL | W3: AGO (ccp) | X3: AGO | Y3: SEP (ccp) | Z3: SEP | AA3: OCT (ccp) | AB3: OCT | AC3: NOV (ccp) | AD3: NOV | AE3: DIC (ccp) | AF3: DIC | AG3: ENE (ccp) | AH3: ENE | AI3: ENE (ccp) | AJ3: ENE | AK3: FEB (ccp) | AL3: FEB | AM3: MAR (ccp) | AN3: MAR | AO3: ABR (ccp) | AP3: ABR | AQ3: MAY (ccp) | AR3: MAY | AS3: JUN (ccp) | AT3: JUN | AU3: JUL (cpp) | AV3: JUL | AW3: AGO (cpp) | AX3: AGO | AY3: SEP (cpp) | AZ3: SEP | BA3: NOV (cpp) | BB3: NOV | BC3: DIC (cpp) | BD3: DIC | BE3: ENE (cpp) | BF3: ENE | BG3: FEB (cpp) | BH3: FEB | BI3: MAR (cpp) | BJ3: MAR | BK3: ABR (cpp) | BL3: ABR | BM3: MAY (cpp) | BN3: MAY | BO3: JUN (cpp) | BP3: JUN | BQ3: JUL (cpp) | BR3: JUL | BS3: AGO (cpp) | BT3: AGO | BU3: SEP (cpp) | BV3: SEP | BW3: oct (cpp) | BX3: oct | BY3: Nov (cpp) | BZ3: Nov | CA3: Dic (cpp) | CB3: Dic | CC3: Ene (cpp) | CD3: Ene | CE3: Feb (cpp) | CF3: Feb | CG3: Mar (cpp) | CH3: Mar | CI3: % | CJ3: POND. | CK3: Abr (cpp) | CL3: Abr | CM3: % | CN3: POND. | CO3: Mayo (cpp) | CP3: Mayo | CQ3: % | CR3: POND. | CS3: Junio (cpp) | CT3: Junio | CU3: % | CV3: POND. | CW3: Julio (cpp) | CX3: Julio | CY3: % | CZ3: POND. | DA3: Agosto (cpp) | DB3: Agosto | DC3: % | DD3: POND. | DE3: Sep (cpp) | DF3: Sep | DG3: % | DH3: POND. | DI3: Oct (cpp) | DJ3: Oct | DK3: % | DL3: POND. | DM3: Nov (cpp) | DN3: Nov | DO3: % | DP3: POND. | DQ3: Dic (cpp) | DR3: Dic | DS3: % | DT3: POND. | DU3: Ene (cpp) | DV3: Ene | DW3: % | DX3: POND. | DY3: Feb (cpp) | DZ3: Feb | EA3: % | EB3: POND. | EC3: Mar (cpp) | ED3: Mar | EE3: % | EF3: POND.
B4: IHS Curbside x Deposit AVG (CPP) | C4: 0.36 | D4: =+C4*$B$2 -> 793.6632 | E4: 0.375 | F4: =+E4*$B$2 -> 826.7325 | G4: 0.375 | H4: =+G4*$B$2 -> 826.7325 | I4: 0.375 | J4: =+I4*$B$2 -> 826.7325 | K4: 0.39 | L4: =+K4*$B$2 -> 859.8018 | M4: 0.435 | N4: =M4*$B$2 -> 959.0097 | O4: 0.5 | P4: =O4*$B$2 -> 1102.31 | Q4: 0.54 | R4: =Q4*$B$2 -> 1190.4948 | S4: 0.54 | T4: =S4*$B$2 -> 1190.4948 | U4: 0.54 | V4: =U4*$B$2 -> 1190.4948 | W4: 0.5 | X4: =W4*$B$2 -> 1102.31 | Y4: 0.4 | Z4: =Y4*$B$2 -> 881.848 | AA4: 0.3 | AB4: =AA4*$B$2 -> 661.386 | AC4: 0.27 | AD4: =AC4*$B$2 -> 595.2474 | AE4: 0.27 | AF4: =AE4*$B$2 -> 595.2474 | AG4: 0.1731 | AH4: =AG4*$B$2 -> 381.61972 | AI4: 0.1894 | AJ4: =AI4*$B$2 -> 417.55503 | AK4: 0.2069 | AL4: =AK4*$B$2 -> 456.13588 | AM4: 0.2206 | AN4: =AM4*$B$2 -> 486.33917 | AO4: 0.2225 | AP4: =AO4*$B$2 -> 490.52795 | AQ4: 0.2225 | AR4: =AQ4*$B$2 -> 490.52795 | AS4: 0.2135 | AT4: =AS4*$B$2 -> 470.68637 | AU4: 0.1456 | AV4: 320.99267 | AW4: 0.1325 | AX4: =AW4*$B$2 -> 292.11215 | AY4: 0.134 | AZ4: =AY4*$B$2 -> 295.41908 | BA4: 0.1532 | BB4: =BA4*$B$2 -> 337.74778 | BC4: 0.165 | BD4: =BC4*$B$2 -> 363.7623 | BE4: 0.1788 | BF4: =BE4*$B$2 -> 394.18606 | BG4: 0.1838 | BH4: =BG4*$B$2 -> 405.20916 | BI4: 0.1913 | BJ4: =BI4*$B$2 -> 421.74381 | BK4: 0.1975 | BL4: =BK4*$B$2 -> 435.41245 | BM4: 0.2094 | BN4: =BM4*$B$2 -> 461.64743 | BO4: 0.2219 | BP4: =BO4*$B$2 -> 489.20518 | BQ4: 0.23 | BR4: =BQ4*$B$2 -> 507.0626 | BS4: 0.2456 | BT4: =BS4*$B$2 -> 541.45467 | BU4: 0.26 | BV4: =BU4*$B$2 -> 573.2012 | BW4: 0.265 | BX4: =BW4*$B$2 -> 584.2243 | BY4: 0.2625 | BZ4: =BY4*$B$2 -> 578.71275 | CA4: 0.2575 | CB4: =CA4*$B$2 -> 567.68965 | CC4: 0.23 | CD4: =CC4*$B$2 -> 507.0626 | CE4: 0.237 | CF4: =CE4*$B$2 -> 522.49494 | CG4: 0.245 | CH4: =CG4*$B$2 -> 540.1319 | CK4: 0.2475 | CL4: =CK4*$B$2 -> 545.64345 | CO4: 0.2463 | CP4: =CO4*$B$2 -> 542.99791 | CS4: 0.24 | CT4: =CS4*$B$2 -> 529.1088 | CW4: 0.2267 | CX4: =CW4*$B$2 -> 499.78735 | DA4: 0.1831 | DB4: =DA4*$B$2 -> 403.66592 | DE4: 0.1313 | DF4: =DE4*$B$2 -> 289.46661 | DI4: 0.12437387 | DJ4: =DI4*$B$2 -> 274.19712 | DM4: 0.12261889 | DN4: =DM4*$B$2 -> 270.32805 | DQ4: 0.13407378 | DR4: =DQ4*$B$2 -> 295.58174 | DU4: 0.13749875 | DV4: =DU4*$B$2 -> 303.1325 | DY4: 0.13675876 | DZ4: =DY4*$B$2 -> 301.5011 | EC4: 0.13090381 | ED4: =EC4*$B$2 -> 288.59316
B5: Bale to Flake (% Yield Loss) | C5: 0.77 | D5: 0.77 | E5: 0.77 | F5: 0.77 | G5: 0.77 | H5: 0.77 | I5: 0.77 | J5: 0.77 | K5: 0.77 | L5: 0.77 | M5: 0.77 | N5: 0.77 | O5: 0.77 | P5: 0.77 | Q5: 0.77 | R5: 0.77 | S5: 0.77 | T5: 0.77 | U5: 0.77 | V5: 0.77 | W5: 0.77 | X5: 0.77 | Y5: 0.77 | Z5: 0.77 | AA5: 0.77 | AB5: 0.77 | AC5: 0.77 | AD5: 0.77 | AE5: 0.77 | AF5: 0.77 | AG5: 0.65 | AH5: 0.65 | AI5: 0.65 | AJ5: 0.65 | AK5: 0.65 | AL5: 0.65 | AM5: 0.65 | AN5: 0.65 | AO5: 0.65 | AP5: 0.65 | AQ5: 0.65 | AR5: 0.65 | AS5: 0.65 | AT5: 0.65 | AU5: 0.65 | AV5: 0.65 | AW5: 0.65 | AX5: 0.65 | AY5: 0.65 | AZ5: 0.65 | BA5: 0.65 | BB5: 0.65 | BC5: 0.65 | BD5: 0.65 | BE5: 0.65 | BF5: 0.65 | BG5: 0.65 | BH5: 0.65 | BI5: 0.65 | BJ5: 0.65 | BK5: 0.65 | BL5: 0.65 | BM5: 0.65 | BN5: 0.65 | BO5: 0.65 | BP5: 0.65 | BQ5: 0.65 | BR5: 0.65 | BS5: 0.65 | BT5: 0.65 | BU5: 0.65 | BV5: 0.65 | BW5: 0.65 | BX5: 0.65 | BY5: 0.65 | BZ5: 0.65 | CA5: 0.65 | CB5: 0.65 | CC5: 0.65 | CD5: 0.65 | CE5: 0.65 | CF5: 0.65 | CG5: 0.65 | CH5: 0.65 | CK5: 0.65 | CL5: 0.65 | CO5: 0.65 | CP5: 0.65 | CS5: 0.65 | CT5: 0.65 | CW5: 0.65 | CX5: 0.65 | DA5: 0.65 | DB5: 0.65 | DE5: 0.65 | DF5: 0.65 | DI5: 0.65 | DJ5: 0.65 | DM5: 0.65 | DN5: 0.65 | DQ5: 0.65 | DR5: 0.65 | DU5: 0.65 | DV5: 0.65 | DY5: 0.65 | DZ5: 0.65 | EC5: 0.65 | ED5: 0.65
B6: Net Price After Yield | C6: =+C4/C5 -> 0.46753247 | D6: =+D4/D5 -> 1030.7314 | E6: =+E4/E5 -> 0.48701299 | F6: =+F4/F5 -> 1073.6786 | G6: =+G4/G5 -> 0.48701299 | H6: =+H4/H5 -> 1073.6786 | I6: =+I4/I5 -> 0.48701299 | J6: =+J4/J5 -> 1073.6786 | ... L6: =+L4/L5 -> 1116.6257 | M6: =M4/M5 -> 0.56493506 | N6: =N4/N5 -> 1245.4671 | O6: =O4/O5 -> 0.64935065 | P6: =P4/P5 -> 1431.5714 | Q6: =Q4/Q5 -> 0.7012987 | R6: =R4/R5 -> 1546.0971 | S6: =S4/S5 -> 0.7012987 | T6: =T4/T5 -> 1546.0971 | ... AT6: =AT4/AT5 -> 724.13288 | AU6: 0.224 | AV6: 493.83488 | AW6: =AW4/AW5 -> 0.20384615 | AX6: =AX4/AX5 -> 449.40331 | AY6: =AY4/AY5 -> 0.20615385 | AZ6: =AZ4/AZ5 -> 454.49089 | BA6: =BA4/BA5 -> 0.23569231 | BB6: =BB4/BB5 -> 519.61198 | BC6: =BC4/BC5 -> 0.25384615 | BD6: =BD4/BD5 -> 559.63431 | ... CH6: =CH4/CH5 -> 830.97215 | CK6: =CK4/CK5 -> 0.38076923 | CL6: =CL4/CL5 -> 839.45146 | CO6: =CO4/CO5 -> 0.37892308 | CP6: =CP4/CP5 -> 835.38139 | CS6: =CS4/CS5 -> 0.36923077 | CT6: =CT4/CT5 -> 814.01354 | CW6: =CW4/CW5 -> 0.34876923 | CX6: =CX4/CX5 -> 768.90362 | DA6: =DA4/DA5 -> 0.28169231 | DB6: =DB4/DB5 -> 621.0245 | DE6: =DE4/DE5 -> 0.202 | DF6: =DF4/DF5 -> 445.33324 | DI6: =DI4/DI5 -> 0.19134442 | DJ6: =DJ4/DJ5 -> 421.84173 | DM6: =DM4/DM5 -> 0.18864444 | DN6: =DN4/DN5 -> 415.88931 | DQ6: =DQ4/DQ5 -> 0.20626736 | DR6: =DR4/DR5 -> 454.74115 | DU6: =DU4/DU5 -> 0.21153654 | DV6: =DV4/DV5 -> 466.35769 | DY6: =DY4/DY5 -> 0.21039809 | DZ6: =DZ4/DZ5 -> 463.84784 | EC6: =EC4/EC5 -> 0.20139048 | ED6: =ED4/ED5 -> 443.98948
B7: Bale to Flake (Conversion Cost) | C7: 0.2 | D7: =+C7*$B$2 -> 440.924 | E7: 0.2 | F7: =+E7*$B$2 -> 440.924 | G7: 0.2 | H7: =+G7*$B$2 -> 440.924 | I7: 0.2 | J7: =+I7*$B$2 -> 440.924 | K7: 0.2 | L7: =+K7*$B$2 -> 440.924 | M7: =K7 -> 0.2 | N7: =M7*$B$2 -> 440.924 | O7: =M7 -> 0.2 | P7: =O7*$B$2 -> 440.924 | Q7: =O7 -> 0.2 | R7: =Q7*$B$2 -> 440.924 | S7: =Q7 -> 0.2 | T7: =S7*$B$2 -> 440.924 | U7: =S7 -> 0.2 | V7: =U7*$B$2 -> 440.924 | W7: 0.2 | X7: =W7*$B$2 -> 440.924 | Y7: 0.2 | Z7: =Y7*$B$2 -> 440.924 | AA7: 0.2 | AB7: =AA7*$B$2 -> 440.924 | AC7: 0.2 | AD7: =AC7*$B$2 -> 440.924 | AE7: 0.2 | AF7: =AE7*$B$2 -> 440.924 | AG7: 0.2 | AH7: =AG7*$B$2 -> 440.924 | AI7: 0.2 | AJ7: =AI7*$B$2 -> 440.924 | AK7: 0.2 | AL7: =AK7*$B$2 -> 440.924 | AM7: 0.2 | AN7: =AM7*$B$2 -> 440.924 | AO7: 0.2 | AP7: =AO7*$B$2 -> 440.924 | AQ7: 0.2 | AR7: =AQ7*$B$2 -> 440.924 | AS7: 0.189 | AT7: =AS7*$B$2 -> 416.67318 | AU7: 0.189 | AV7: 416.67318 | AW7: 0.189 | AX7: =AW7*$B$2 -> 416.67318 | AY7: 0.189 | AZ7: =AY7*$B$2 -> 416.67318 | BA7: 0.189 | BB7: =BA7*$B$2 -> 416.67318 | BC7: 0.189 | BD7: =BC7*$B$2 -> 416.67318 | BE7: 0.189 | BF7: =BE7*$B$2 -> 416.67318 | BG7: 0.189 | BH7: =BG7*$B$2 -> 416.67318 | BI7: 0.189 | BJ7: =BI7*$B$2 -> 416.67318 | BK7: 0.189 | BL7: =BK7*$B$2 -> 416.67318 | BM7: 0.189 | BN7: =BM7*$B$2 -> 416.67318 | BO7: 0.189 | BP7: =BO7*$B$2 -> 416.67318 | BQ7: 0.189 | BR7: =BQ7*$B$2 -> 416.67318 | BS7: 0.189 | BT7: =BS7*$B$2 -> 416.67318 | BU7: 0.189 | BV7: =BU7*$B$2 -> 416.67318 | BW7: 0.189 | BX7: =BW7*$B$2 -> 416.67318 | BY7: 0.189 | BZ7: =BY7*$B$2 -> 416.67318 | CA7: 0.189 | CB7: =CA7*$B$2 -> 416.67318 | CC7: 0.189 | CD7: =CC7*$B$2 -> 416.67318 | CE7: 0.189 | CF7: =CE7*$B$2 -> 416.67318 | CG7: 0.189 | CH7: =CG7*$B$2 -> 416.67318 | CK7: 0.189 | CL7: =CK7*$B$2 -> 416.67318 | CO7: 0.189 | CP7: =CO7*$B$2 -> 416.67318 | CS7: 0.189 | CT7: =CS7*$B$2 -> 416.67318 | CW7: 0.189 | CX7: =CW7*$B$2 -> 416.67318 | DA7: 0.189 | DB7: =DA7*$B$2 -> 416.67318 | DE7: 0.189 | DF7: =DE7*$B$2 -> 416.67318 | DI7: 0.189 | DJ7: =DI7*$B$2 -> 416.67318 | DM7: 0.189 | DN7: =DM7*$B$2 -> 416.67318 | DQ7: 0.189 | DR7: =DQ7*$B$2 -> 416.67318 | DU7: 0.189 | DV7: =DU7*$B$2 -> 416.67318 | DY7: 0.189 | DZ7: =DY7*$B$2 -> 416.67318 | EC7: 0.189 | ED7: =EC7*$B$2 -> 416.67318
B8: Flake to Pellet (% Yield Loss) | C8: 0.96 | D8: 0.96 | E8: 0.96 | F8: 0.96 | G8: 0.96 | H8: 0.96 | I8: 0.96 | J8: 0.96 | K8: 0.96 | L8: 0.96 | M8: 0.96 | N8: 0.96 | O8: 0.96 | P8: 0.96 | Q8: 0.96 | R8: 0.96 | S8: 0.96 | T8: 0.96 | U8: 0.96 | V8: 0.96 | W8: 0.96 | X8: 0.96 | Y8: 0.96 | Z8: 0.96 | AA8: 0.96 | AB8: 0.96 | AC8: 0.96 | AD8: 0.96 | AE8: 0.96 | AF8: 0.96 | AG8: 0.96 | AH8: 0.96 | AI8: 0.96 | AJ8: 0.96 | AK8: 0.96 | AL8: 0.96 | AM8: 0.96 | AN8: 0.96 | AO8: 0.96 | AP8: 0.96 | AQ8: 0.96 | AR8: 0.96 | AS8: 0.96 | AT8: 0.96 | AU8: 0.96 | AV8: 0.96 | AW8: 0.96 | AX8: 0.96 | AY8: 0.96 | AZ8: 0.96 | BA8: 0.96 | BB8: 0.96 | BC8: 0.96 | BD8: 0.96 | BE8: 0.96 | BF8: 0.96 | BG8: 0.96 | BH8: 0.96 | BI8: 0.96 | BJ8: 0.96 | BK8: 0.96 | BL8: 0.96 | BM8: 0.96 | BN8: 0.96 | BO8: 0.96 | BP8: 0.96 | BQ8: 0.96 | BR8: 0.96 | BS8: 0.96 | BT8: 0.96 | BU8: 0.96 | BV8: 0.96 | BW8: 0.96 | BX8: 0.96 | BY8: 0.96 | BZ8: 0.96 | CA8: 0.96 | CB8: 0.96 | CC8: 0.96 | CD8: 0.96 | CE8: 0.96 | CF8: 0.96 | CG8: 0.96 | CH8: 0.96 | CK8: 0.96 | CL8: 0.96 | CO8: 0.96 | CP8: 0.96 | CS8: 0.96 | CT8: 0.96 | CW8: 0.96 | CX8: 0.96 | DA8: 0.96 | DB8: 0.96 | DE8: 0.96 | DF8: 0.96 | DI8: 0.96 | DJ8: 0.96 | DM8: 0.96 | DN8: 0.96 | DQ8: 0.96 | DR8: 0.96 | DU8: 0.96 | DV8: 0.96 | DY8: 0.96 | DZ8: 0.96 | EC8: 0.96 | ED8: 0.96
B9: Flake to Pellet (Converson Cost) | C9: 0.19 | D9: =+C9*$B$2 -> 418.8778 | E9: 0.19 | F9: =+E9*$B$2 -> 418.8778 | G9: 0.19 | H9: =+G9*$B$2 -> 418.8778 | I9: 0.19 | J9: =+I9*$B$2 -> 418.8778 | K9: 0.19 | L9: =+K9*$B$2 -> 418.8778 | M9: =K9 -> 0.19 | N9: =M9*$B$2 -> 418.8778 | O9: =M9 -> 0.19 | P9: =O9*$B$2 -> 418.8778 | Q9: =O9 -> 0.19 | R9: =Q9*$B$2 -> 418.8778 | S9: =Q9 -> 0.19 | T9: =S9*$B$2 -> 418.8778 | U9: =S9 -> 0.19 | V9: =U9*$B$2 -> 418.8778 | W9: 0.19 | X9: =W9*$B$2 -> 418.8778 | Y9: 0.19 | Z9: =Y9*$B$2 -> 418.8778 | AA9: 0.19 | AB9: =AA9*$B$2 -> 418.8778 | AC9: 0.19 | AD9: =AC9*$B$2 -> 418.8778 | AE9: 0.19 | AF9: =AE9*$B$2 -> 418.8778 | AG9: 0.19 | AH9: =AG9*$B$2 -> 418.8778 | AI9: 0.19 | AJ9: =AI9*$B$2 -> 418.8778 | AK9: 0.19 | AL9: =AK9*$B$2 -> 418.8778 | AM9: 0.19 | AN9: =AM9*$B$2 -> 418.8778 | AO9: 0.19 | AP9: =AO9*$B$2 -> 418.8778 | AQ9: 0.19 | AR9: =AQ9*$B$2 -> 418.8778 | AS9: 0.179 | AT9: =AS9*$B$2 -> 394.62698 | AU9: 0.179 | AV9: 394.62698 | AW9: 0.179 | AX9: =AW9*$B$2 -> 394.62698 | AY9: 0.179 | AZ9: =AY9*$B$2 -> 394.62698 | BA9: 0.179 | BB9: =BA9*$B$2 -> 394.62698 | BC9: 0.179 | BD9: =BC9*$B$2 -> 394.62698 | BE9: 0.179 | BF9: =BE9*$B$2 -> 394.62698 | BG9: 0.179 | BH9: =BG9*$B$2 -> 394.62698 | BI9: 0.179 | BJ9: =BI9*$B$2 -> 394.62698 | BK9: 0.179 | BL9: =BK9*$B$2 -> 394.62698 | BM9: 0.179 | BN9: =BM9*$B$2 -> 394.62698 | BO9: 0.179 | BP9: =BO9*$B$2 -> 394.62698 | BQ9: 0.179 | BR9: =BQ9*$B$2 -> 394.62698 | BS9: 0.179 | BT9: =BS9*$B$2 -> 394.62698 | BU9: 0.179 | BV9: =BU9*$B$2 -> 394.62698 | BW9: 0.179 | BX9: =BW9*$B$2 -> 394.62698 | BY9: 0.179 | BZ9: =BY9*$B$2 -> 394.62698 | CA9: 0.179 | CB9: =CA9*$B$2 -> 394.62698 | CC9: 0.179 | CD9: =CC9*$B$2 -> 394.62698 | CE9: 0.179 | CF9: =CE9*$B$2 -> 394.62698 | CG9: 0.179 | CH9: =CG9*$B$2 -> 394.62698 | CK9: 0.179 | CL9: =CK9*$B$2 -> 394.62698 | CO9: 0.179 | CP9: =CO9*$B$2 -> 394.62698 | CS9: 0.179 | CT9: =CS9*$B$2 -> 394.62698 | CW9: 0.179 | CX9: =CW9*$B$2 -> 394.62698 | DA9: 0.179 | DB9: =DA9*$B$2 -> 394.62698 | DE9: 0.179 | DF9: =DE9*$B$2 -> 394.62698 | DI9: 0.179 | DJ9: =DI9*$B$2 -> 394.62698 | DM9: 0.179 | DN9: =DM9*$B$2 -> 394.62698 | DQ9: 0.179 | DR9: =DQ9*$B$2 -> 394.62698 | DU9: 0.179 | DV9: =DU9*$B$2 -> 394.62698 | DY9: 0.179 | DZ9: =DY9*$B$2 -> 394.62698 | EC9: 0.179 | ED9: =EC9*$B$2 -> 394.62698
B10: EXWORKS | C10: =+((C6+C7)/C8)+C9 -> 0.88534632 | D10: =+((D6+D7)/D8)+D9 -> 1951.8522 | E10: =+((E6+E7)/E8)+E9 -> 0.90563853 | F10: =+((F6+F7)/F8)+F9 -> 1996.5888 | G10: =+((G6+G7)/G8)+G9 -> 0.90563853 | H10: =+((H6+H7)/H8)+H9 -> 1996.5888 | I10: =+((I6+I7)/I8)+I9 -> 0.90563853 | J10: =+((J6+J7)/J8)+J9 -> 1996.5888 | ... AT10: =+((AT6+AT7)/AT8)+AT9 -> 1582.9666 | AU10: 0.60920833 | AV10: 1343.0729 | AW10: =+((AW6+AW7)/AW8)+AW9 -> 0.58821474 | AX10: =+((AX6+AX7)/AX8)+AX9 -> 1296.79 | AY10: =+((AY6+AY7)/AY8)+AY9 -> 0.59061859 | AZ10: =+((AZ6+AZ7)/AZ8)+AZ9 -> 1302.0896 | BA10: =+((BA6+BA7)/BA8)+BA9 -> 0.62138782 | BB10: =+((BB6+BB7)/BB8)+BB9 -> 1369.924 | BC10: =+((BC6+BC7)/BC8)+BC9 -> 0.64029808 | BD10: =+((BD6+BD7)/BD8)+BD9 -> 1411.6139 | ... CH10: =+((CH6+CH7)/CH8)+CH9 -> 1694.2575 | CI10: =CH10/$CH$15 -> 0.92681247 | CJ10: =CI10*$CI$50 -> 1196.6118 | CK10: =+((CK6+CK7)/CK8)+CK9 -> 0.77250962 | CL10: =+((CL6+CL7)/CL8)+CL9 -> 1703.0901 | CM10: =CL10/CL15 -> 0.92713316 | CN10: =CM10*CM50 -> 1326.9056 | CO10: =+((CO6+CO7)/CO8)+CO9 -> 0.77058654 | CP10: =+((CP6+CP7)/CP8)+CP9 -> 1698.8505 | CQ10: =CP10/CP15 -> 0.92751333 | CR10: =CQ10*CQ50 -> 1212.9793 | CS10: =+((CS6+CS7)/CS8)+CS9 -> 0.76049038 | CT10: =+((CT6+CT7)/CT8)+CT9 -> 1676.5923 | CU10: =CT10/CT15 -> 0.92633317 | CV10: =CU10*CU50 -> 1676.5923 | CW10: =+((CW6+CW7)/CW8)+CW9 -> 0.73917628 | CX10: =+((CX6+CX7)/CX8)+CX9 -> 1629.6028 | CY10: =CX10/CX15 -> 0.9259612 | CZ10: =CY10*CY50 -> 667.82058 | DA10: =+((DA6+DA7)/DA8)+DA9 -> 0.66930449 | DB10: =+((DB6+DB7)/DB8)+DB9 -> 1475.5621 | DC10: =DB10/DB15 -> 0.92115994 | DD10: =DC10*DC50 -> 1207.0561 | DE10: =+((DE6+DE7)/DE8)+DE9 -> 0.58629167 | DF10: =+((DF6+DF7)/DF8)+DF9 -> 1292.5503 | DG10: =DF10/DF15 -> 0.91638937 | DH10: =DG10*DG50 -> 892.39403 | DI10: =+((DI6+DI7)/DI8)+DI9 -> 0.5751921 | DJ10: =+((DJ6+DJ7)/DJ8)+DJ9 -> 1268.08 | DK10: =DJ10/DJ15 -> 0.91636917 | DL10: =DK10*DK50 -> 1268.08 | DM10: =+((DM6+DM7)/DM8)+DM9 -> 0.57237963 | DN10: =+((DN6+DN7)/DN8)+DN9 -> 1261.8796 | DO10: =DN10/DN15 -> 0.91695021 | DP10: =DO10*DO50 -> 1261.8796 | DQ10: =+((DQ6+DQ7)/DQ8)+DQ9 -> 0.59073683 | DR10: =+((DR6+DR7)/DR8)+DR9 -> 1302.3502 | DS10: =DR10/DR15 -> 0.91814005 | DT10: =DS10*DS50 -> 1302.3502 | DU10: =+((DU6+DU7)/DU8)+DU9 -> 0.59622557 | DV10: =+((DV6+DV7)/DV8)+DV9 -> 1314.4508 | DW10: =DV10/DV15 -> 0.91905199 | DX10: =DW10*DW50 -> 1314.4508 | DY10: =+((DY6+DY7)/DY8)+DY9 -> 0.59503968 | DZ10: =+((DZ6+DZ7)/DZ8)+DZ9 -> 1311.8364 | EA10: =DZ10/DZ15 -> 0.91890129 | EB10: =EA10*EA50 -> 1311.8364 | EC10: =+((EC6+EC7)/EC8)+EC9 -> 0.58565675 | ED10: =+((ED6+ED7)/ED8)+ED9 -> 1291.1506 | EE10: =ED10/ED15 -> 0.91827954 | EF10: =EE10*EE50 -> 1291.1506
B11: Logistics (63.93 USD) | C11: 0.029 | D11: =+C11*$B$2 -> 63.93398 | E11: 0.029 | F11: =+E11*$B$2 -> 63.93398 | G11: 0.029 | H11: =+G11*$B$2 -> 63.93398 | I11: 0.029 | J11: =+I11*$B$2 -> 63.93398 | K11: 0.029 | L11: =+K11*$B$2 -> 63.93398 | M11: =K11 -> 0.029 | N11: =M11*$B$2 -> 63.93398 | O11: =M11 -> 0.029 | P11: =O11*$B$2 -> 63.93398 | Q11: =O11 -> 0.029 | R11: =Q11*$B$2 -> 63.93398 | S11: =Q11 -> 0.029 | T11: =S11*$B$2 -> 63.93398 | U11: =S11 -> 0.029 | V11: =U11*$B$2 -> 63.93398 | W11: =U11 -> 0.029 | X11: =W11*$B$2 -> 63.93398 | Y11: =W11 -> 0.029 | Z11: =Y11*$B$2 -> 63.93398 | AA11: =Y11 -> 0.029 | AB11: =AA11*$B$2 -> 63.93398 | AC11: =AA11 -> 0.029 | AD11: =AC11*$B$2 -> 63.93398 | AE11: =AC11 -> 0.029 | AF11: =AE11*$B$2 -> 63.93398 | AG11: =AE11 -> 0.029 | AH11: =AG11*$B$2 -> 63.93398 | AI11: =AG11 -> 0.029 | AJ11: =AI11*$B$2 -> 63.93398 | AK11: =AI11 -> 0.029 | AL11: =AK11*$B$2 -> 63.93398 | AM11: =AK11 -> 0.029 | AN11: =AM11*$B$2 -> 63.93398 | AO11: =AM11 -> 0.029 | AP11: =AO11*$B$2 -> 63.93398 | AQ11: =AO11 -> 0.029 | AR11: =AQ11*$B$2 -> 63.93398 | AS11: =AQ11 -> 0.029 | AT11: =AS11*$B$2 -> 63.93398 | AU11: 0.029 | AV11: 63.93398 | AW11: =AU11 -> 0.029 | AX11: =AW11*$B$2 -> 63.93398 | AY11: =AW11 -> 0.029 | AZ11: =AY11*$B$2 -> 63.93398 | BA11: =AY11 -> 0.029 | BB11: =BA11*$B$2 -> 63.93398 | BC11: =BA11 -> 0.029 | BD11: =BC11*$B$2 -> 63.93398 | BE11: =BC11 -> 0.029 | BF11: =BE11*$B$2 -> 63.93398 | BG11: =BE11 -> 0.029 | BH11: =BG11*$B$2 -> 63.93398 | BI11: =BG11 -> 0.029 | BJ11: =BI11*$B$2 -> 63.93398 | BK11: =BI11 -> 0.029 | BL11: =BK11*$B$2 -> 63.93398 | BM11: =BK11 -> 0.029 | BN11: =BM11*$B$2 -> 63.93398 | BO11: =BM11 -> 0.029 | BP11: =BO11*$B$2 -> 63.93398 | BQ11: =BO11 -> 0.029 | BR11: =BQ11*$B$2 -> 63.93398 | BS11: =BQ11 -> 0.029 | BT11: =BS11*$B$2 -> 63.93398 | BU11: =BS11 -> 0.029 | BV11: =BU11*$B$2 -> 63.93398 | BW11: =BU11 -> 0.029 | BX11: =BW11*$B$2 -> 63.93398 | BY11: =BW11 -> 0.029 | BZ11: =BY11*$B$2 -> 63.93398 | CA11: =BY11 -> 0.029 | CB11: =CA11*$B$2 -> 63.93398 | CC11: =CA11 -> 0.029 | CD11: =CC11*$B$2 -> 63.93398 | CE11: =CC11 -> 0.029 | CF11: =CE11*$B$2 -> 63.93398 | CG11: =CE11 -> 0.029 | CH11: =CG11*$B$2 -> 63.93398 | CI11: =CH11/$CH$15 -> 0.03497391 | CJ11: =CI11*$CI$50 -> 45.154974 | CK11: =CG11 -> 0.029 | CL11: =CK11*$B$2 -> 63.93398 | CM11: =CL11/CL$15 -> 0.034804566 | CN11: =CM11*CM50 -> 49.812017 | CO11: =CK11 -> 0.029 | CP11: =CO11*$B$2 -> 63.93398 | CQ11: =CP11/CP$15 -> 0.034905731 | CR11: =CQ11*CQ50 -> 45.648862 | CS11: =CO11 -> 0.029 | CT11: =CS11*$B$2 -> 63.93398 | CU11: =CT11/CT$15 -> 0.035324131 | CV11: =CU11*CU50 -> 63.93398 | CW11: =CS11 -> 0.029 | CX11: =CW11*$B$2 -> 63.93398 | CY11: =CX11/CX$15 -> 0.036328107 | CZ11: =CY11*CY50 -> 26.200512 | DA11: =CW11 -> 0.029 | DB11: =DA11*$B$2 -> 63.93398 | DC11: =DB11/DB$15 -> 0.039912534 | DD11: =DC11*DC50 -> 52.300005 | DE11: =DA11 -> 0.029 | DF11: =DE11*$B$2 -> 63.93398 | DG11: =DF11/DF$15 -> 0.045327767 | DH11: =DG11*DG50 -> 44.140874 | DI11: =DE11 -> 0.029 | DJ11: =DI11*$B$2 -> 63.93398 | DK11: =DJ11/DJ$15 -> 0.046201444 | DL11: =DK11*DK50 -> 63.93398 | DM11: =DI11 -> 0.029 | DN11: =DM11*$B$2 -> 63.93398 | DO11: =DN11/DN$15 -> 0.046457901 | DP11: =DO11*DO50 -> 63.93398 | DQ11: =DM11 -> 0.029 | DR11: =DQ11*$B$2 -> 63.93398 | DS11: =DR11/DR$15 -> 0.045072628 | DT11: =DS11*DS50 -> 63.93398 | DU11: =DQ11 -> 0.029 | DV11: =DU11*$B$2 -> 63.93398 | DW11: =DV11/DV$15 -> 0.044702055 | DX11: =DW11*DW50 -> 63.93398 | DY11: =DU11 -> 0.029 | DZ11: =DY11*$B$2 -> 63.93398 | EA11: =DZ11/DZ$15 -> 0.044783799 | EB11: =EA11*EA50 -> 63.93398 | EC11: =DY11 -> 0.029 | ED11: =EC11*$B$2 -> 63.93398 | EE11: =ED11/ED$15 -> 0.045470503 | EF11: =EE11*EE50 -> 63.93398
B12: CME TERM SOFR (%) 180 | AT12: 0.0539064 | AV12: 0.0545283 | AX12: 0.0546731 | AZ12: ='ICIS Price History'!N181 -> 0.0546727 | BB12: ='ICIS Price History'!N185 -> 0.0544273 | BD12: ='ICIS Price History'!N186 -> 0.053944 | BF12: ='ICIS Price History'!N187 -> 0.0523809 | BH12: ='ICIS Price History'!N188 -> 0.051574 | BJ12: ='ICIS Price History'!N189 -> 0.0529249 | BL12: ='ICIS Price History'!N190 -> 0.052716 | BN12: ='ICIS Price History'!N191 -> 0.0528965 | BP12: ='ICIS Price History'!N192 -> 0.0532565 | BR12: ='ICIS Price History'!N193 -> 0.0503709 | BT12: ='ICIS Price History'!N194 -> 0.0507558 | BV12: ='ICIS Price History'!N197 -> 0.0469822 | BX12: ='ICIS Price History'!N198 -> 0.0433369 | BZ12: ='ICIS Price History'!N199 -> 0.0443072 | CB12: ='ICIS Price History'!N200 -> 0.0443287 | CD12: ='ICIS Price History'!N201 -> 0.04175 | CF12: ='ICIS Price History'!N202 -> 0.0423682 | CH12: ='ICIS Price History'!N203 -> 0.0425675 | CL12: ='ICIS Price History'!N204 -> 0.0422358 | CP12: ='ICIS Price History'!N205 -> 0.0411815 | CT12: ='ICIS Price History'!N206 -> 0.0428505 | CX12: ='ICIS Price History'!N207 -> 0.0414656 | DB12: ='ICIS Price History'!N208 -> 0.0419138 | DF12: ='ICIS Price History'!N209 -> 0.0405377 | DJ12: ='ICIS Price History'!N210 -> 0.0387187 | DN12: ='ICIS Price History'!N213 -> 0.0369369 | DR12: ='ICIS Price History'!N214 -> 0.0373524 | DV12: =+'ICIS Price History'!N215 -> 0.0362018 | DZ12: =+'ICIS Price History'!N216 -> 0.0363483 | ED12: =+'ICIS Price History'!N217 -> 0.0362103
B13: Finance fee PCR (SOFR +3,8%@180) | AT13: =SUM(AT10:AT11)*(3.8%+AT12)/365*180 -> 74.643636 | AV13: 64.202278 | AX13: =SUM(AX10:AX11)*(3.8%+AX12)/365*180 -> 62.187538 | AZ13: =SUM(AZ10:AZ11)*(3.8%+AZ12)/365*180 -> 62.429469 | BB13: =SUM(BB10:BB11)*(3.8%+BB12)/365*180 -> 65.356088 | BD13: =SUM(BD10:BD11)*(3.8%+BD12)/365*180 -> 66.904658 | BF13: =SUM(BF10:BF11)*(3.8%+BF12)/365*180 -> 67.940365 | BH13: =SUM(BH10:BH11)*(3.8%+BH12)/365*180 -> 68.114143 | BJ13: =SUM(BJ10:BJ11)*(3.8%+BJ12)/365*180 -> 70.329554 | BL13: =SUM(BL10:BL11)*(3.8%+BL12)/365*180 -> 71.147922 | BN13: =SUM(BN10:BN11)*(3.8%+BN12)/365*180 -> 73.174103 | BP13: =SUM(BP10:BP11)*(3.8%+BP12)/365*180 -> 75.451392 | BR13: =SUM(BR10:BR11)*(3.8%+BR12)/365*180 -> 74.312724 | BT13: =SUM(BT10:BT11)*(3.8%+BT12)/365*180 -> 77.048799 | BV13: =SUM(BV10:BV11)*(3.8%+BV12)/365*180 -> 75.905098 | BX13: =SUM(BX10:BX11)*(3.8%+BX12)/365*180 -> 73.357735 | BZ13: =SUM(BZ10:BZ11)*(3.8%+BZ12)/365*180 -> 73.874334 | CB13: =SUM(CB10:CB11)*(3.8%+CB12)/365*180 -> 73.176416 | CD13: =SUM(CD10:CD11)*(3.8%+CD12)/365*180 -> 67.06325 | CF13: =SUM(CF10:CF11)*(3.8%+CF12)/365*180 -> 68.563298 | CH13: =SUM(CH10:CH11)*(3.8%+CH12)/365*180 -> 69.856321 | CI13: =CH13/$CH$15 -> 0.038213617 | CJ13: =CI13*$CI$50 -> 49.337775 | CL13: =SUM(CL10:CL11)*(3.8%+CL12)/365*180 -> 69.918211 | CM13: =CL13/CL$15 -> 0.038062279 | CN13: =CM13*CM50 -> 54.474429 | CP13: =SUM(CP10:CP11)*(3.8%+CP12)/365*180 -> 68.833933 | CQ13: =CP13/CP$15 -> 0.037580935 | CR13: =CQ13*CQ50 -> 49.147428 | CT13: =SUM(CT10:CT11)*(3.8%+CT12)/365*180 -> 69.397358 | CU13: =CT13/CT$15 -> 0.038342699 | CV13: =CU13*CU50 -> 69.397358 | CX13: =SUM(CX10:CX11)*(3.8%+CX12)/365*180 -> 66.367192 | CY13: =CX13/CX$15 -> 0.037710689 | CZ13: =CY13*CY50 -> 27.197656 | DB13: =SUM(DB10:DB11)*(3.8%+DB12)/365*185 -> 62.35614 | DC13: =DB13/DB$15 -> 0.038927524 | DD13: =DC13*DC50 -> 51.009282 | DF13: =SUM(DF10:DF11)*(3.8%+DF12)/365*185 -> 53.997272 | DG13: =DF13/DF$15 -> 0.038282862 | DH13: =DG13*DG50 -> 37.280438 | DJ13: =SUM(DJ10:DJ11)*(3.8%+DJ12)/365*185 -> 51.795125 | DK13: =DJ13/DJ$15 -> 0.037429386 | DL13: =DK13*DK50 -> 51.795125 | DN13: =SUM(DN10:DN11)*(3.8%+DN12)/365*185 -> 50.356674 | DO13: =DN13/DN$15 -> 0.036591894 | DP13: =DO13*DO50 -> 50.356674 | DR13: =SUM(DR10:DR11)*(3.8%+DR12)/365*185 -> 52.181554 | DS13: =DR13/DR$15 -> 0.03678732 | DT13: =DS13*DS50 -> 52.181554 | DV13: =SUM(DV10:DV11)*(3.8%+DV12)/365*185 -> 51.839855 | DW13: =DV13/DV$15 -> 0.036245953 | DX13: =DW13*DW50 -> 51.839855 | DZ13: =SUM(DZ10:DZ11)*(3.8%+DZ12)/365*185 -> 51.843684 | EA13: =DZ13/DZ$15 -> 0.036314916 | EB13: =EA13*EA50 -> 51.843684 | ED13: =SUM(ED10:ED11)*(3.8%+ED12)/365*185 -> 50.969392 | EE13: =ED13/ED$15 -> 0.036249954 | EF13: =EE13*EE50 -> 50.969392
B14: Descuento $35USD | CH14: 0 | CL14: 0 | CP14: 0 | CT14: 0 | CX14: 0 | DB14: 0 | DF14: 0 | DJ14: 0 | DN14: 0 | DR14: 0 | DV14: 0 | DZ14: 0 | ED14: 0
C15: =SUM(C10:C11) -> 0.91434632 | D15: =+C15*$B$2 -> 2015.7862 | E15: =SUM(E10:E11) -> 0.93463853 | F15: =+E15*$B$2 -> 2060.5228 | G15: =SUM(G10:G11) -> 0.93463853 | H15: =+G15*$B$2 -> 2060.5228 | I15: =SUM(I10:I11) -> 0.93463853 | J15: =+I15*$B$2 -> 2060.5228 | K15: =SUM(K10:K11) -> 0.95493074 | L15: =+K15*$B$2 -> 2105.2594 | M15: =SUM(M10:M11) -> 1.0158074 | N15: =+M15*$B$2 -> 2239.4692 | O15: =SUM(O10:O11) -> 1.1037403 | P15: =+O15*$B$2 -> 2433.3279 | Q15: =SUM(Q10:Q11) -> 1.1578528 | R15: =+Q15*$B$2 -> 2552.6255 | S15: =SUM(S10:S11) -> 1.1578528 | T15: =+S15*$B$2 -> 2552.6255 | U15: =SUM(U10:U11) -> 1.1578528 | V15: =+U15*$B$2 -> 2552.6255 | W15: =SUM(W10:W11) -> 1.1037403 | X15: =+W15*$B$2 -> 2433.3279 | Y15: =SUM(Y10:Y11) -> 0.96845887 | Z15: =+Y15*$B$2 -> 2135.0838 | AA15: =SUM(AA10:AA11) -> 0.83317749 | AB15: =+AA15*$B$2 -> 1836.8398 | AC15: =SUM(AC10:AC11) -> 0.79259307 | AD15: =+AC15*$B$2 -> 1747.3665 | AE15: =SUM(AE10:AE11) -> 0.79259307 | AF15: =+AE15*$B$2 -> 1747.3665 | AG15: =SUM(AG10:AG11) -> 0.70473718 | AH15: =+AG15*$B$2 -> 1553.6777 | AI15: =SUM(AI10:AI11) -> 0.73085897 | AJ15: =+AI15*$B$2 -> 1611.2663 | AK15: =SUM(AK10:AK11) -> 0.75890385 | AL15: =+AK15*$B$2 -> 1673.0946 | AM15: =SUM(AM10:AM11) -> 0.78085897 | AN15: =+AM15*$B$2 -> 1721.4973 | AO15: =SUM(AO10:AO11) -> 0.78390385 | AP15: =+AO15*$B$2 -> 1728.2101 | AQ15: =SUM(AQ10:AQ11) -> 0.78390385 | AR15: =+AQ15*$B$2 -> 1728.2101 | AS15: =SUM(AS10:AS11) -> 0.74702244 | AT15: =+(AS15*$B$2)+AT13 -> 1721.5442 | AV15: 1471.2091 | AW15: =SUM(AW10:AW11) -> 0.61721474 | AX15: =+(AW15*$B$2)+AX13 -> 1422.9115 | AY15: =SUM(AY10:AY11) -> 0.61961859 | AZ15: =+(AY15*$B$2)+AZ13 -> 1428.453 | BA15: =SUM(BA10:BA11) -> 0.65038782 | BB15: =+(BA15*$B$2)+BB13 -> 1499.2141 | BC15: =SUM(BC10:BC11) -> 0.66929808 | BD15: =+(BC15*$B$2)+BD13 -> 1542.4526 | BE15: =SUM(BE10:BE11) -> 0.69141346 | BF15: =+(BE15*$B$2)+BF13 -> 1592.2443 | BG15: =SUM(BG10:BG11) -> 0.69942628 | BH15: =+(BG15*$B$2)+BH13 -> 1610.0833 | BI15: =SUM(BI10:BI11) -> 0.71144551 | BJ15: =+(BI15*$B$2)+BJ13 -> 1638.7966 | BK15: =SUM(BK10:BK11) -> 0.72138141 | BL15: =+(BK15*$B$2)+BL13 -> 1661.5198 | BM15: =SUM(BM10:BM11) -> 0.74045192 | BN15: =+(BM15*$B$2)+BN13 -> 1705.5892 | BO15: =SUM(BO10:BO11) -> 0.76048397 | BP15: =+(BO15*$B$2)+BP13 -> 1752.0296 | BQ15: =SUM(BQ10:BQ11) -> 0.77346474 | BR15: =+(BQ15*$B$2)+BR13 -> 1779.5086 | BS15: =SUM(BS10:BS11) -> 0.79846474 | BT15: =+(BS15*$B$2)+BT13 -> 1837.3601 | BU15: =SUM(BU10:BU11) -> 0.82154167 | BV15: =+(BU15*$B$2)+BV13 -> 1887.0923 | BW15: =SUM(BW10:BW11) -> 0.82955449 | BX15: =+(BW15*$B$2)+BX13 -> 1902.2101 | BY15: =SUM(BY10:BY11) -> 0.82554808 | BZ15: =+(BY15*$B$2)+BZ13 -> 1893.8941 | CA15: =SUM(CA10:CA11) -> 0.81753526 | CB15: =+(CA15*$B$2)+CB13 -> 1875.531 | CC15: =SUM(CC10:CC11) -> 0.77346474 | CD15: =+(CC15*$B$2)+CD13 -> 1772.2591 | CE15: =SUM(CE10:CE11) -> 0.78468269 | CF15: =+(CE15*$B$2)+CF13 -> 1798.4905 | CG15: =SUM(CG10:CG11) -> 0.79750321 | CH15: =+(CG15*$B$2)+CH13+CH14 -> 1828.0478 | CI15: =SUM(CI4:CI14) -> 1 | CJ15: =SUM(CJ5:CJ13) -> 1291.1045 | CK15: =SUM(CK10:CK11) -> 0.80150962 | CL15: =+(CK15*$B$2)+CL13+CL14 -> 1836.9423 | CM15: =SUM(CM4:CM14) -> 1 | CN15: =SUM(CN5:CN13) -> 1431.192 | CO15: =SUM(CO10:CO11) -> 0.79958654 | CP15: =+(CO15*$B$2)+CP13+CP14 -> 1831.6184 | CQ15: =SUM(CQ4:CQ14) -> 1 | CR15: =SUM(CR5:CR13) -> 1307.7755 | CS15: =SUM(CS10:CS11) -> 0.78949038 | CT15: =+(CS15*$B$2)+CT13+CT14 -> 1809.9237 | CU15: =SUM(CU4:CU14) -> 1 | CV15: =SUM(CV5:CV13) -> 1809.9237 | CW15: =SUM(CW10:CW11) -> 0.76817628 | CX15: =+(CW15*$B$2)+CX13+CX14 -> 1759.904 | CY15: =SUM(CY4:CY14) -> 1 | CZ15: =SUM(CZ5:CZ13) -> 721.21875 | DA15: =SUM(DA10:DA11) -> 0.69830449 | DB15: =+(DA15*$B$2)+DB13+DB14 -> 1601.8522 | DC15: =SUM(DC4:DC14) -> 1 | DD15: =SUM(DD5:DD13) -> 1310.3654 | DE15: =SUM(DE10:DE11) -> 0.61529167 | DF15: =+(DE15*$B$2)+DF13+DF14 -> 1410.4816 | DG15: =SUM(DG4:DG14) -> 1 | DH15: =SUM(DH5:DH13) -> 973.81534 | DI15: =SUM(DI10:DI11) -> 0.6041921 | DJ15: =+(DI15*$B$2)+DJ13+DJ14 -> 1383.8091 | DK15: =SUM(DK4:DK14) -> 1 | DL15: =SUM(DL5:DL13) -> 1383.8091 | DM15: =SUM(DM10:DM11) -> 0.60137963 | DN15: =+(DM15*$B$2)+DN13+DN14 -> 1376.1702 | DO15: =SUM(DO4:DO14) -> 1 | DP15: =SUM(DP5:DP13) -> 1376.1702 | DQ15: =SUM(DQ10:DQ11) -> 0.61973683 | DR15: =+(DQ15*$B$2)+DR13+DR14 -> 1418.4658 | DS15: =SUM(DS4:DS14) -> 1 | DT15: =SUM(DT5:DT13) -> 1418.4658 | DU15: =SUM(DU10:DU11) -> 0.62522557 | DV15: =+(DU15*$B$2)+DV13+DV14 -> 1430.2246 | DW15: =SUM(DW4:DW14) -> 1 | DX15: =SUM(DX5:DX13) -> 1430.2246 | DY15: =SUM(DY10:DY11) -> 0.62403968 | DZ15: =+(DY15*$B$2)+DZ13+DZ14 -> 1427.614 | EA15: =SUM(EA4:EA14) -> 1 | EB15: =SUM(EB5:EB13) -> 1427.614 | EC15: =SUM(EC10:EC11) -> 0.61465675 | ED15: =+(EC15*$B$2)+ED13+ED14 -> 1406.054 | EE15: =SUM(EE4:EE14) -> 1 | EF15: =SUM(EF5:EF13) -> 1406.054
CJ16: =CJ15+CJ42 -> 1847.4226 | CN16: =CN15+CN42 -> 1855.3319 | CR16: =CR15+CR42 -> 1855.4656 | CV16: =CV15+CV42 -> 1809.9237 | CZ16: =CZ15+CZ42 -> 1810.8221 | DD16: =DD15+DD42 -> 1653.7461 | DH16: =DH15+DH42 -> 1515.1675 | DL16: =DL15+DL42 -> 1383.8091 | DP16: =DP15+DP42 -> 1376.1702 | DT16: =DT15+DT42 -> 1418.4658 | DX16: =DX15+DX42 -> 1430.2246 | EB16: =EB15+EB42 -> 1427.614 | EF16: =EF15+EF42 -> 1406.054
BR17: =BR15*1.05 -> 1868.484
BV18: Precio Octubre | BX18: Precio Nov | CA18: Precio Dic | CC18: Precio Enero | CE18: Precio Feb
B19: ENKA | BR19: =BR17*1.05 -> 1961.9082 | BV19: Ingreso Agosto | BX19: Ingreso Sep - Oct | CA19: Ingreso Nov | CC19: Ingreso Dic | CE19: Ingreso Ene
B20: ENKA PARITY EC-CO (EXW) | BR20: 18 | BV20: 2046 | BW20: 2046 | BX20: 2046 | BY20: 2046 | CA20: 2046 | CB20: 2046 | CC20: 2046 | CD20: 2046 | CE20: 2046 | CF20: 2046
B21: Flete | BV21: 130 | BW21: 130 | BX21: 130 | BY21: 130 | CA21: 130 | CB21: 130 | CC21: 130 | CD21: 130 | CE21: 130 | CF21: 130
B22: Precio CIF | BV22: =SUM(BV20:BV21) -> 2176 | BW22: =SUM(BW20:BW21) -> 2176 | BX22: =SUM(BX20:BX21) -> 2176 | BY22: =SUM(BY20:BY21) -> 2176 | CA22: =SUM(CA20:CA21) -> 2176 | CB22: =SUM(CB20:CB21) -> 2176 | CC22: =SUM(CC20:CC21) -> 2176 | CD22: =SUM(CD20:CD21) -> 2176 | CE22: =SUM(CE20:CE21) -> 2176 | CF22: =SUM(CF20:CF21) -> 2176
B24: ARP | BV24: -190 | BX24: -190 | CA24: -190 | CC24: -190 | CE24: -190
B25: Flete 50% | C25: ARP | BV25: =-BV21*0.5 -> -65 | BX25: =-BX21*0.5 -> -65 | CA25: =-CA21*0.5 -> -65 | CC25: =-CC21*0.5 -> -65 | CE25: =-CE21*0.5 -> -65
B26: $$ ENKA | BV26: =BV22+BV24+BV25 -> 1921 | BW26: 1000000 | BX26: =BX22+BX24+BX25 -> 1921 | BY26: =451000+264000+417000+2000 -> 1134000 | CA26: =CA22+CA24+CA25 -> 1921 | CB26: 418000 | CC26: =CC22+CC24+CC25 -> 1921 | CD26: 132000 | CE26: =CE22+CE24+CE25 -> 1921 | CF26: 330000
B27: $$ INVEMA | BV27: =BX15 -> 1902.2101 | BW27: 640000 | BX27: =BZ15 -> 1893.8941 | BY27: 642000 | CA27: =CB15 -> 1875.531 | CB27: 470430 | CC27: =CD15 -> 1772.2591 | CD27: 657000 | CE27: =CF15 -> 1798.4905 | CF27: 660000
B28: Precio Pond | BV28: =+SUMPRODUCT(BV26:BV27,BW26:BW27)/(BW26+BW27) -> 1913.6674 | BW28: =SUM(BW26:BW27) -> 1640000 | BX28: =+SUMPRODUCT(BX26:BX27,BY26:BY27)/(BY26+BY27) -> 1911.2016 | BY28: =SUM(BY26:BY27) -> 1776000 | CA28: =+SUMPRODUCT(CA26:CA27,CB26:CB27)/(CB26+CB27)+12.11 -> 1909.0338 | CB28: =SUM(CB26:CB27) -> 888430 | CC28: =+SUMPRODUCT(CC26:CC27,CD26:CD27)/(CD26+CD27) -> 1797.1435 | CD28: =SUM(CD26:CD27) -> 789000 | CE28: =+SUMPRODUCT(CE26:CE27,CF26:CF27)/(CF26+CF27) -> 1839.327 | CF28: =SUM(CF26:CF27) -> 990000
A30: 2204.62 | B30: PRECIO ENKA - NUEVO 2025 | CG30: 45717 | CI30: % | CJ30: POND. | CK30: 45748 | CM30: % | CN30: POND. | CO30: 45778 | CQ30: % | CR30: POND. | CS30: 45809 | CU30: % | CV30: POND. | CW30: 45839 | CY30: % | CZ30: POND. | DA30: 45870 | DC30: % | DD30: POND. | DE30: 45901 | DG30: % | DH30: POND. | DI30: 45931 | DK30: % | DL30: POND. | DM30: 45962 | DO30: % | DP30: POND. | DQ30: 45992 | DS30: % | DT30: POND. | DU30: 46023 | DW30: % | DX30: POND. | DY30: 46054 | EA30: % | EB30: POND. | EC30: 46082 | EE30: % | EF30: POND.
B31: IHS Curbside x Deposit AVG (CPP) | CG31: 0.245 | CK31: 0.2475 | CO31: 0.2463 | CS31: 0.24 | CW31: 0.2267 | DA31: 0.2267 | DE31: 0.1831 | DI31: 0 | DM31: 0 | DQ31: 0 | DU31: 0 | DY31: 0 | EC31: 0
B32: Average Bale USD | CG32: =+CG31*$A$30 -> 540.1319 | CK32: =+CK31*$A$30 -> 545.64345 | CO32: =+CO31*$A$30 -> 542.99791 | CS32: =+CS31*$A$30 -> 529.1088 | CW32: =+CW31*$A$30 -> 499.78735 | DA32: =+DA31*$A$30 -> 499.78735 | DE32: =+DE31*$A$30 -> 403.66592 | DI32: =+DI31*$A$30 -> 0 | DM32: =+DM31*$A$30 -> 0 | DQ32: =+DQ31*$A$30 -> 0 | DU32: =+DU31*$A$30 -> 0 | DY32: =+DY31*$A$30 -> 0 | EC32: =+EC31*$A$30 -> 0
A33: 0.65 | B33: Net Bale Price After Yield (% Yield Loss) | CG33: =+CG32/$A$33 -> 830.97215 | CJ33: =CI33*$CI$49 -> 0 | CK33: =+CK32/$A$33 -> 839.45146 | CN33: =CM33*$CI$49 -> 0 | CO33: =+CO32/$A$33 -> 835.38139 | CR33: =CQ33*$CI$49 -> 0 | CS33: =+CS32/$A$33 -> 814.01354 | CV33: =CU33*$CI$49 -> 0 | CW33: =+CW32/$A$33 -> 768.90362 | CZ33: =CY33*$CI$49 -> 0 | DA33: =+DA32/$A$33 -> 768.90362 | DD33: =DC33*$CI$49 -> 0 | DE33: =+DE32/$A$33 -> 621.0245 | DH33: =DG33*$CI$49 -> 0 | DI33: =+DI32/$A$33 -> 0 | DL33: =DK33*$CI$49 -> 0 | DM33: =+DM32/$A$33 -> 0 | DP33: =DO33*$CI$49 -> 0 | DQ33: =+DQ32/$A$33 -> 0 | DT33: =DS33*$CI$49 -> 0 | DU33: =+DU32/$A$33 -> 0 | DX33: =DW33*$CI$49 -> 0 | DY33: =+DY32/$A$33 -> 0 | EB33: =EA33*$CI$49 -> 0 | EC33: =+EC32/$A$33 -> 0 | EF33: =EE33*$CI$49 -> 0
B34: Fixed PCR Conversion | CG34: 517.075 | CK34: 517.075 | CO34: 517.075 | CS34: 517.075 | CW34: 517.075 | DA34: 517.075 | DE34: 517.075 | DI34: 517.075 | DM34: 517.075 | DQ34: 517.075 | DU34: 517.075 | DY34: 517.075 | EC34: 517.075
B35: Adjusted PCR Conversion Cost | CG35: 308.01263 | CK35: 308.01263 | CO35: 308.01263 | CS35: 308.01263 | CW35: 308.01263 | DA35: 308.01263 | DE35: 308.01263 | DI35: 308.01263 | DM35: 308.01263 | DQ35: 308.01263 | DU35: 308.01263 | DY35: 308.01263 | EC35: 308.01263
B36: Total Conversion Cost | CG36: =CG34+CG35 -> 825.08763 | CH36: =+SUM(CH34:CH35)/$A$21 -> #DIV/0! | CJ36: =CI36*$CI$49 -> 0 | CK36: =CK34+CK35 -> 825.08763 | CL36: =+SUM(CL34:CL35)/$A$21 -> #DIV/0! | CN36: =CM36*$CI$49 -> 0 | CO36: =CO34+CO35 -> 825.08763 | CP36: =+SUM(CP34:CP35)/$A$21 -> #DIV/0! | CR36: =CQ36*$CI$49 -> 0 | CS36: =CS34+CS35 -> 825.08763 | CT36: =+SUM(CT34:CT35)/$A$21 -> #DIV/0! | CV36: =CU36*$CI$49 -> 0 | CW36: =CW34+CW35 -> 825.08763 | CX36: =+SUM(CX34:CX35)/$A$21 -> #DIV/0! | CZ36: =CY36*$CI$49 -> 0 | DA36: =DA34+DA35 -> 825.08763 | DB36: =+SUM(DB34:DB35)/$A$21 -> #DIV/0! | DD36: =DC36*$CI$49 -> 0 | DE36: =DE34+DE35 -> 825.08763 | DF36: =+SUM(DF34:DF35)/$A$21 -> #DIV/0! | DH36: =DG36*$CI$49 -> 0 | DI36: =DI34+DI35 -> 825.08763 | DJ36: =+SUM(DJ34:DJ35)/$A$21 -> #DIV/0! | DL36: =DK36*$CI$49 -> 0 | DM36: =DM34+DM35 -> 825.08763 | DN36: =+SUM(DN34:DN35)/$A$21 -> #DIV/0! | DP36: =DO36*$CI$49 -> 0 | DQ36: =DQ34+DQ35 -> 825.08763 | DR36: =+SUM(DR34:DR35)/$A$21 -> #DIV/0! | DT36: =DS36*$CI$49 -> 0 | DU36: =DU34+DU35 -> 825.08763 | DV36: =+SUM(DV34:DV35)/$A$21 -> #DIV/0! | DX36: =DW36*$CI$49 -> 0 | DY36: =DY34+DY35 -> 825.08763 | DZ36: =+SUM(DZ34:DZ35)/$A$21 -> #DIV/0! | EB36: =EA36*$CI$49 -> 0 | EC36: =EC34+EC35 -> 825.08763 | ED36: =+SUM(ED34:ED35)/$A$21 -> #DIV/0! | EF36: =EE36*$CI$49 -> 0
B37: EX WORKS | CG37: =CG36+CG33 -> 1656.0598 | CH37: =+((CH33+CH34)/CH35)+CH36 -> #DIV/0! | CI37: =CG37/$CG$42 -> 0.87436699 | CJ37: =CI37*$CI$49 -> 486.42611 | CK37: =CK36+CK33 -> 1664.5391 | CL37: =+((CL33+CL34)/CL35)+CL36 -> #DIV/0! | CM37: =CK37/CK42 -> 0.86685845 | CN37: =CM37*CM49 -> 367.66928 | CO37: =CO36+CO33 -> 1660.469 | CP37: =+((CP33+CP34)/CP35)+CP36 -> #DIV/0! | CQ37: =CO37/CO42 -> 0.86708554 | CR37: =CQ37*CQ49 -> 474.89414 | CS37: =CS36+CS33 -> 1639.1012 | CT37: =+((CT33+CT34)/CT35)+CT36 -> #DIV/0! | CU37: =CS37/CS42 -> 0.86527645 | CV37: =CU37*CU49 -> 0 | CW37: =CW36+CW33 -> 1593.9913 | CX37: =+((CX33+CX34)/CX35)+CX36 -> #DIV/0! | CY37: =CW37/CW42 -> 0.86340085 | CZ37: =CY37*CY49 -> 940.7645 | DA37: =DA36+DA33 -> 1593.9913 | DB37: =+((DB33+DB34)/DB35)+DB36 -> #DIV/0! | DC37: =DA37/DA42 -> 0.84470782 | DD37: =DC37*DC49 -> 290.05631 | DE37: =DE36+DE33 -> 1446.1121 | DF37: =+((DF33+DF34)/DF35)+DF36 -> #DIV/0! | DG37: =DE37/DE42 -> 0.82699773 | DH37: =DG37*DG49 -> 447.69698 | DI37: =DI36+DI33 -> 825.08763 | DJ37: =+((DJ33+DJ34)/DJ35)+DJ36 -> #DIV/0! | DK37: =DI37/DI42 -> 0.74879159 | DL37: =DK37*DK49 -> 0 | DM37: =DM36+DM33 -> 825.08763 | DN37: =+((DN33+DN34)/DN35)+DN36 -> #DIV/0! | DO37: =DM37/DM42 -> 0.74945196 | DP37: =DO37*DO49 -> 0 | DQ37: =DQ36+DQ33 -> 825.08763 | DR37: =+((DR33+DR34)/DR35)+DR36 -> #DIV/0! | DS37: =DQ37/DQ42 -> 0.74929787 | DT37: =DS37*DS49 -> 0 | DU37: =DU36+DU33 -> 825.08763 | DV37: =+((DV33+DV34)/DV35)+DV36 -> #DIV/0! | DW37: =DU37/DU42 -> 0.74972474 | DX37: =DW37*DW49 -> 0 | DY37: =DY36+DY33 -> 825.08763 | DZ37: =+((DZ33+DZ34)/DZ35)+DZ36 -> #DIV/0! | EA37: =DY37/DY42 -> 0.74967036 | EB37: =EA37*EA49 -> 0 | EC37: =EC36+EC33 -> 825.08763 | ED37: =+((ED33+ED34)/ED35)+ED36 -> #DIV/0! | EE37: =EC37/EC42 -> 0.74972159 | EF37: =EE37*EE49 -> 0
B38: Flete Colombia - El Salvador (Variable) | CG38: 180 | CI38: =CG38/$CG$42 -> 0.095036459 | CJ38: =CI38*$CI$49 -> 52.870494 | CK38: 197 | CM38: =CK38/CK42 -> 0.10259363 | CN38: =CM38*CM49 -> 43.514056 | CO38: 197 | CQ38: =CO38/CO42 -> 0.10287205 | CR38: =CQ38*CQ49 -> 56.342 | CS38: 197 | CU38: =CS38/CS42 -> 0.10399569 | CV38: =CU38*CU49 -> 0 | CW38: 197 | CY38: =CW38/CW42 -> 0.10670696 | CZ38: =CY38*CY49 -> 116.26827 | DA38: 234 | DC38: =DA38/DA42 -> 0.12400421 | DD38: =DC38*DC49 -> 42.580645 | DE38: 250 | DG38: =DE38/DE42 -> 0.14296916 | DH38: =DG38*DG49 -> 77.396658 | DI38: 250 | DK38: =DI38/DI42 -> 0.22688244 | DL38: =DK38*DK49 -> 0 | DM38: 250 | DO38: =DM38/DM42 -> 0.22708253 | DP38: =DO38*DO49 -> 0 | DQ38: 250 | DS38: =DQ38/DQ42 -> 0.22703584 | DT38: =DS38*DS49 -> 0 | DU38: 250 | DW38: =DU38/DU42 -> 0.22716519 | DX38: =DW38*DW49 -> 0 | DY38: 250 | EA38: =DY38/DY42 -> 0.22714871 | EB38: =EA38*EA49 -> 0 | EC38: 250 | EE38: =EC38/EC42 -> 0.22716423 | EF38: =EE38*EE49 -> 0
B39: Libor Rate - SOFR Rate | CG39: =CH12 -> 0.0425675 | CK39: =CL12 -> 0.0422358 | CO39: =CP12 -> 0.0411815 | CS39: =CT12 -> 0.0428505 | CW39: =CX12 -> 0.0414656 | DA39: =DB12 -> 0.0419138 | DE39: =DF12 -> 0.0405377 | DI39: =DJ12 -> 0.0387187 | DM39: =DN12 -> 0.0369369 | DQ39: =DR12 -> 0.0373524 | DU39: =DV12 -> 0.0362018 | DY39: =DZ12 -> 0.0363483 | EC39: =ED12 -> 0.0362103
B40: Finance fee PCR (SOFR +3,8%@180) | CG40: =(CG37+CG38)*(3.8%+CG39)/365*180 -> 72.950176 | CH40: =SUM(CH36:CH38)*(3.8%+CH39)/365*180 -> #DIV/0! | CI40: =CG40/$CG$42 -> 0.038516258 | CJ40: =CI40*$CI$49 -> 21.427288 | CK40: =(CK37+CK38)*(3.8%+CK39)/365*180 -> 73.658011 | CL40: =SUM(CL36:CL38)*(3.8%+CL39)/365*180 -> #DIV/0! | CM40: =CK40/CK42 -> 0.03835961 | CN40: =CM40*CM49 -> 16.269842 | CO40: =(CO37+CO38)*(3.8%+CO39)/365*180 -> 72.531214 | CP40: =SUM(CP36:CP38)*(3.8%+CP39)/365*180 -> #DIV/0! | CQ40: =CO40/CO42 -> 0.037875303 | CR40: =CQ40*CQ49 -> 20.743927 | CS40: =(CS37+CS38)*(3.8%+CS39)/365*180 -> 73.20807 | CT40: =SUM(CT36:CT38)*(3.8%+CT39)/365*180 -> #DIV/0! | CU40: =CS40/CS42 -> 0.038646314 | CV40: =CU40*CU49 -> 0 | CW40: =(CW37+CW38)*(3.8%+CW39)/365*180 -> 70.186288 | CX40: =SUM(CX36:CX38)*(3.8%+CX39)/365*180 -> #DIV/0! | CY40: =CW40/CW42 -> 0.038017085 | CZ40: =CY40*CY49 -> 41.423544 | DA40: =(DA37+DA38)*(3.8%+DA39)/365*185 -> 74.041423 | DB40: =SUM(DB36:DB38)*(3.8%+DB39)/365*180 -> #DIV/0! | DC40: =DA40/DA42 -> 0.039236959 | DD40: =DC40*DC49 -> 13.473212 | DE40: =(DE37+DE38)*(3.8%+DE39)/365*185 -> 67.516761 | DF40: =SUM(DF36:DF38)*(3.8%+DF39)/365*180 -> #DIV/0! | DG40: =DE40/DE42 -> 0.038611258 | DH40: =DG40*DG49 -> 20.902287 | DI40: =(DI37+DI38)*(3.8%+DI39)/365*185 -> 41.80459 | DJ40: =SUM(DJ36:DJ38)*(3.8%+DJ39)/365*180 -> #DIV/0! | DK40: =DI40/DI42 -> 0.03793891 | DL40: =DK40*DK49 -> 0 | DM40: =(DM37+DM38)*(3.8%+DM39)/365*185 -> 40.833674 | DN40: =SUM(DN36:DN38)*(3.8%+DN39)/365*180 -> #DIV/0! | DO40: =DM40/DM42 -> 0.037090456 | DP40: =DO40*DO49 -> 0 | DQ40: =(DQ37+DQ38)*(3.8%+DQ39)/365*185 -> 41.060083 | DR40: =SUM(DR36:DR38)*(3.8%+DR39)/365*180 -> #DIV/0! | DS40: =DQ40/DQ42 -> 0.037288442 | DT40: =DS40*DS49 -> 0 | DU40: =(DU37+DU38)*(3.8%+DU39)/365*185 -> 40.433112 | DV40: =SUM(DV36:DV38)*(3.8%+DV39)/365*180 -> #DIV/0! | DW40: =DU40/DU42 -> 0.036739982 | DX40: =DW40*DW49 -> 0 | DY40: =(DY37+DY38)*(3.8%+DY39)/365*185 -> 40.512941 | DZ40: =SUM(DZ36:DZ38)*(3.8%+DZ39)/365*180 -> #DIV/0! | EA40: =DY40/DY42 -> 0.036809849 | EB40: =EA40*EA49 -> 0 | EC40: =(EC37+EC38)*(3.8%+EC39)/365*185 -> 40.437744 | ED40: =SUM(ED36:ED38)*(3.8%+ED39)/365*180 -> #DIV/0! | EE40: =EC40/EC42 -> 0.036744036 | EF40: =EE40*EE49 -> 0
A41: 15 | B41: NEW Discount | CG41: =-$A$41 -> -15 | CI41: =CG41/$CG$42 -> -0.0079197049 | CJ41: =CI41*$CI$49 -> -4.4058745 | CK41: =-$A$41 -> -15 | CM41: =CK41/CK42 -> -0.0078116981 | CN41: =CM41*CM49 -> -3.313253 | CO41: =-$A$41 -> -15 | CQ41: =CO41/CO42 -> -0.0078328972 | CR41: =CQ41*CQ49 -> -4.29 | CS41: =-$A$41 -> -15 | CU41: =CS41/CS42 -> -0.0079184537 | CV41: =CU41*CU49 -> 0 | CW41: =-$A$41 -> -15 | CY41: =CW41/CW42 -> -0.0081248957 | CZ41: =CY41*CY49 -> -8.852914 | DA41: =-$A$41 -> -15 | DC41: =DA41/DA42 -> -0.0079489879 | DD41: =DC41*DC49 -> -2.7295285 | DE41: =-$A$41 -> -15 | DG41: =DE41/DE42 -> -0.0085781495 | DH41: =DG41*DG49 -> -4.6437995 | DI41: =-$A$41 -> -15 | DK41: =DI41/DI42 -> -0.013612947 | DL41: =DK41*DK49 -> 0 | DM41: =-$A$41 -> -15 | DO41: =DM41/DM42 -> -0.013624952 | DP41: =DO41*DO49 -> 0 | DQ41: =-$A$41 -> -15 | DS41: =DQ41/DQ42 -> -0.013622151 | DT41: =DS41*DS49 -> 0 | DU41: =-$A$41 -> -15 | DW41: =DU41/DU42 -> -0.013629911 | DX41: =DW41*DW49 -> 0 | DY41: =-$A$41 -> -15 | EA41: =DY41/DY42 -> -0.013628923 | EB41: =EA41*EA49 -> 0 | EC41: =-$A$41 -> -15 | EE41: =EC41/EC42 -> -0.013629854 | EF41: =EE41*EE49 -> 0
B42: TOTAL USD/Tn | CG42: =CG37+CG38+CG40+CG41 -> 1894.01 | CI42: =SUM(CI31:CI41) -> 1 | CJ42: =SUM(CJ33:CJ41) -> 556.31801 | CK42: =CK37+CK38+CK40+CK41 -> 1920.1971 | CM42: =SUM(CM31:CM41) -> 1 | CN42: =SUM(CN33:CN41) -> 424.13992 | CO42: =CO37+CO38+CO40+CO41 -> 1915.0002 | CQ42: =SUM(CQ31:CQ41) -> 1 | CR42: =SUM(CR33:CR41) -> 547.69007 | CS42: =CS37+CS38+CS40+CS41 -> 1894.3092 | CU42: =SUM(CU31:CU41) -> 1 | CV42: =SUM(CV33:CV41) -> 0 | CW42: =CW37+CW38+CW40+CW41 -> 1846.1775 | CY42: =SUM(CY31:CY41) -> 1 | CZ42: =SUM(CZ33:CZ41) -> 1089.6034 | DA42: =DA37+DA38+DA40+DA41 -> 1887.0327 | DC42: =SUM(DC31:DC41) -> 1 | DD42: =SUM(DD33:DD41) -> 343.38064 | DE42: =DE37+DE38+DE40+DE41 -> 1748.6289 | DG42: =SUM(DG31:DG41) -> 1 | DH42: =SUM(DH33:DH41) -> 541.35213 | DI42: =DI37+DI38+DI40+DI41 -> 1101.8922 | DK42: =SUM(DK31:DK41) -> 1 | DL42: =SUM(DL33:DL41) -> 0 | DM42: =DM37+DM38+DM40+DM41 -> 1100.9213 | DO42: =SUM(DO31:DO41) -> 1 | DP42: =SUM(DP33:DP41) -> 0 | DQ42: =DQ37+DQ38+DQ40+DQ41 -> 1101.1477 | DS42: =SUM(DS31:DS41) -> 1 | DT42: =SUM(DT33:DT41) -> 0 | DU42: =DU37+DU38+DU40+DU41 -> 1100.5207 | DW42: =SUM(DW31:DW41) -> 1 | DX42: =SUM(DX33:DX41) -> 0 | DY42: =DY37+DY38+DY40+DY41 -> 1100.6006 | EA42: =SUM(EA31:EA41) -> 1 | EB42: =SUM(EB33:EB41) -> 0 | EC42: =EC37+EC38+EC40+EC41 -> 1100.5254 | EE42: =SUM(EE31:EE41) -> 1 | EF42: =SUM(EF33:EF41) -> 0
B48: RESINAS PCR | CG48: $ x TM | CH48: CANTIDAD KGS | CI48: $ POND | CJ48: % | CK48: $ x TM | CL48: CANTIDAD KGS | CM48: $ POND | CN48: % | CO48: $ x TM | CP48: CANTIDAD KGS | CQ48: $ POND | CR48: % | CS48: $ x TM | CT48: CANTIDAD KGS | CU48: $ POND | CV48: % | CW48: $ x TM | CX48: CANTIDAD KGS | CY48: $ POND | CZ48: % | DA48: $ x TM | DB48: CANTIDAD KGS | DC48: $ POND | DD48: % | DE48: $ x TM | DF48: CANTIDAD KGS | DG48: $ POND | DH48: % | DI48: $ x TM | DJ48: CANTIDAD KGS | DK48: $ POND | DL48: % | DM48: $ x TM | DN48: CANTIDAD KGS | DO48: $ POND | DP48: % | DQ48: $ x TM | DR48: CANTIDAD KGS | DS48: $ POND | DT48: % | DU48: $ x TM | DV48: CANTIDAD KGS | DW48: $ POND | DX48: % | DY48: $ x TM | DZ48: CANTIDAD KGS | EA48: $ POND | EB48: % | EC48: $ x TM | ED48: CANTIDAD KGS | EE48: $ POND | EF48: %
B49: $$ ENKA | CG49: =CG42 -> 1894.01 | CH49: 220000 | CI49: =CG49*CJ49 -> 556.31801 | CJ49: =CH49/$CH$51 -> 0.29372497 | CK49: =CK42 -> 1920.1971 | CL49: 220000 | CM49: =CK49*CN49 -> 424.13992 | CN49: =CL49/$CL$51 -> 0.22088353 | CO49: =CO42 -> 1915.0002 | CP49: 286000 | CQ49: =CO49*CR49 -> 547.69007 | CR49: =CP49/$CP$51 -> 0.286 | CS49: =CS42 -> 1894.3092 | CT49: 0 | CU49: =CS49*CV49 -> 0 | CV49: =CT49/$CT$51 -> 0 | CW49: =CW42 -> 1846.1775 | CX49: 638000 | CY49: =CW49*CZ49 -> 1089.6034 | CZ49: =CX49/$CX$51 -> 0.59019426 | DA49: =DA42 -> 1887.0327 | DB49: 220000 | DC49: =DA49*DD49 -> 343.38064 | DD49: =DB49/DB51 -> 0.18196857 | DE49: =DE42 -> 1748.6289 | DF49: 352000 | DG49: =DE49*DH49 -> 541.35213 | DH49: =DF49/DF51 -> 0.30958663 | DI49: =DI42 -> 1101.8922 | DJ49: 0 | DK49: =DI49*DL49 -> 0 | DL49: =DJ49/DJ51 -> 0 | DM49: =DM42 -> 1100.9213 | DN49: 0 | DO49: =DM49*DP49 -> 0 | DP49: =DN49/DN51 -> 0 | DQ49: =DQ42 -> 1101.1477 | DR49: 0 | DS49: =DQ49*DT49 -> 0 | DT49: =DR49/DR51 -> 0 | DU49: =DU42 -> 1100.5207 | DV49: 0 | DW49: =DU49*DX49 -> 0 | DX49: =DV49/DV51 -> 0 | DY49: =DY42 -> 1100.6006 | DZ49: 0 | EA49: =DY49*EB49 -> 0 | EB49: =DZ49/DZ51 -> 0 | EC49: =EC42 -> 1100.5254 | ED49: 0 | EE49: =EC49*EF49 -> 0 | EF49: =ED49/ED51 -> 0
B50: $$ INVEMA | CG50: =CH15 -> 1828.0478 | CH50: 529000 | CI50: =CG50*CJ50 -> 1291.1045 | CJ50: =CH50/$CH$51 -> 0.70627503 | CK50: =CL15 -> 1836.9423 | CL50: 776000 | CM50: =CK50*CN50 -> 1431.192 | CN50: =CL50/$CL$51 -> 0.77911647 | CO50: =CP15 -> 1831.6184 | CP50: 714000 | CQ50: =CO50*CR50 -> 1307.7755 | CR50: =CP50/$CP$51 -> 0.714 | CS50: =CT15 -> 1809.9237 | CT50: 807000 | CU50: =CS50*CV50 -> 1809.9237 | CV50: =CT50/$CT$51 -> 1 | CW50: =CX15 -> 1759.904 | CX50: 443000 | CY50: =CW50*CZ50 -> 721.21875 | CZ50: =CX50/$CX$51 -> 0.40980574 | DA50: =DB15 -> 1601.8522 | DB50: 989000 | DC50: =DA50*DD50 -> 1310.3654 | DD50: =DB50/DB51 -> 0.81803143 | DE50: =DF15 -> 1410.4816 | DF50: 785000 | DG50: =DE50*DH50 -> 973.81534 | DH50: =DF50/DF51 -> 0.69041337 | DI50: =DJ15 -> 1383.8091 | DJ50: 677000 | DK50: =DI50*DL50 -> 1383.8091 | DL50: =DJ50/DJ51 -> 1 | DM50: =DN15 -> 1376.1702 | DN50: 580000 | DO50: =DM50*DP50 -> 1376.1702 | DP50: =DN50/DN51 -> 1 | DQ50: =DR15 -> 1418.4658 | DR50: 580000 | DS50: =DQ50*DT50 -> 1418.4658 | DT50: =DR50/DR51 -> 1 | DU50: =DV15 -> 1430.2246 | DV50: 580000 | DW50: =DU50*DX50 -> 1430.2246 | DX50: =DV50/DV51 -> 1 | DY50: =DZ15 -> 1427.614 | DZ50: 580000 | EA50: =DY50*EB50 -> 1427.614 | EB50: =DZ50/DZ51 -> 1 | EC50: =ED15 -> 1406.054 | ED50: =+Kardex!CW16 -> 504000 | EE50: =EC50*EF50 -> 1406.054 | EF50: =ED50/ED51 -> 1
CH51: =SUM(CH49:CH50) -> 749000 | CI51: =SUMPRODUCT(CG49:CG50,CH49:CH50)/SUM(CH49:CH50) -> 1847.4226 | CJ51: =SUM(CJ49:CJ50) -> 1 | CL51: =SUM(CL49:CL50) -> 996000 | CM51: =SUMPRODUCT(CK49:CK50,CL49:CL50)/SUM(CL49:CL50) -> 1855.3319 | CN51: =SUM(CN49:CN50) -> 1 | CP51: =SUM(CP49:CP50) -> 1000000 | CQ51: =SUMPRODUCT(CO49:CO50,CP49:CP50)/SUM(CP49:CP50) -> 1855.4656 | CR51: =SUM(CR49:CR50) -> 1 | CT51: =SUM(CT49:CT50) -> 807000 | CU51: =SUMPRODUCT(CS49:CS50,CT49:CT50)/SUM(CT49:CT50) -> 1809.9237 | CV51: =SUM(CV49:CV50) -> 1 | CX51: =SUM(CX49:CX50) -> 1081000 | CY51: =SUMPRODUCT(CW49:CW50,CX49:CX50)/SUM(CX49:CX50) -> 1810.8221 | CZ51: =SUM(CZ49:CZ50) -> 1 | DB51: =SUM(DB49:DB50) -> 1209000 | DC51: =SUMPRODUCT(DA49:DA50,DB49:DB50)/SUM(DB49:DB50) -> 1653.7461 | DD51: =SUM(DD49:DD50) -> 1 | DF51: =SUM(DF49:DF50) -> 1137000 | DG51: =SUMPRODUCT(DE49:DE50,DF49:DF50)/SUM(DF49:DF50) -> 1515.1675 | DH51: =SUM(DH49:DH50) -> 1 | DJ51: =SUM(DJ49:DJ50) -> 677000 | DK51: =SUMPRODUCT(DI49:DI50,DJ49:DJ50)/SUM(DJ49:DJ50) -> 1383.8091 | DL51: =SUM(DL49:DL50) -> 1 | DN51: =SUM(DN49:DN50) -> 580000 | DO51: =SUMPRODUCT(DM49:DM50,DN49:DN50)/SUM(DN49:DN50) -> 1376.1702 | DP51: =SUM(DP49:DP50) -> 1 | DR51: =SUM(DR49:DR50) -> 580000 | DS51: =SUMPRODUCT(DQ49:DQ50,DR49:DR50)/SUM(DR49:DR50) -> 1418.4658 | DT51: =SUM(DT49:DT50) -> 1 | DV51: =SUM(DV49:DV50) -> 580000 | DW51: =SUMPRODUCT(DU49:DU50,DV49:DV50)/SUM(DV49:DV50) -> 1430.2246 | DX51: =SUM(DX49:DX50) -> 1 | DZ51: =SUM(DZ49:DZ50) -> 580000 | EA51: =SUMPRODUCT(DY49:DY50,DZ49:DZ50)/SUM(DZ49:DZ50) -> 1427.614 | EB51: =SUM(EB49:EB50) -> 1 | ED51: =SUM(ED49:ED50) -> 504000 | EE51: =SUMPRODUCT(EC49:EC50,ED49:ED50)/SUM(ED49:ED50) -> 1406.054 | EF51: =SUM(EF49:EF50) -> 1
CG53: =CG51*CJ49 -> 0
CG54: =CG51*CJ50 -> 0

Sheet Fletes
A3: Ano/mês | B3: Colombia | C3: ELS
A4: jan/26 | B4: $ 162,14 | C4: $ 185,00
A5: fev/26 | B5: $ 136,95 | C5: $ 197,00
A6: 46082 | B6: Drewry | C6: $ 185,80
A7: 46113 | B7: Drewry | C7: $ 175,80
A8: mai/26 | B8: Drewry | C8: $ 161,18
A9: 46174 | B9: $ 105,23 | C9: $ 149,67
A10: 46204 | B10: $ 105,23 | C10: $ 168,00
A11: 46235 | B11: $ 105,23 | C11: $ 168,00
A12: set/26 | B12: $ 105,23 | C12: $ 168,00
A13: out/26 | B13: $ 105,23 | C13: $ 168,00
A14: 46327 | B14: $ 105,23 | C14: $ 168,00
A15: dez/26 | C15: $ 168,00

Sheet Proyección Resina Virgen 
B6: Mes Recepcion | D6: Cantidad Kg | E6: ICIS | F6: Adder | G6: Flete | H6: Landed | I6: Finance Fee | J6: CME TERM SOFR (%) 180 | K6: Precio Total
B9: Mayo | D9: 500 | E9: 799.5 | F9: 34.84 | G9: 315 | H9: 30 | I9: =SUM(E9:H9)*(3.8%+J9)/365*180 -> 46.051353 | J9: 0.0411815 | K9: =SUM(E9:I9) -> 1225.3914
B10: Junio | D10: 1250 | E10: 803.125 | F10: 34.84 | G10: 280 | H10: 30 | I10: =SUM(E10:H10)*(3.8%+J10)/365*180 -> 45.771063 | J10: 0.0428505 | K10: =SUM(E10:I10) -> 1193.7361
B11: Julio | D11: 1250 | E11: =AVERAGE('ICIS Price History'!E257:E260) -> 786.25 | F11: 34.84 | G11: 166 | H11: 30 | I11: =SUM(E11:H11)*(3.8%+J11)/365*180 -> 39.123133 | J11: 0.04 | K11: =SUM(E11:I11) -> 1056.2131
B12: Agosto | D12: 1100 | E12: =AVERAGE('ICIS Price History'!E261:E264) -> 745.625 | F12: 34.84 | G12: 156 | H12: 30 | I12: =SUM(E12:H12)*(3.8%+J12)/365*180 -> 37.175804 | J12: 0.04 | K12: =SUM(E12:I12) -> 1003.6408
B13: Septiembre | F13: 34.84 | G13: 156
B14: Octubre | F14: 34.84 | G14: 176
B15: Noviembre | F15: 34.84 | G15: 191
B16: Diciembre | F16: 34.84 | G16: 185
B17: Enero | F17: 34.84 | G17: 185
B18: Febrero
